{
  "geometry": {
    "type": "Point",
    "coordinates": [
      -112.4333,
      34.3667
    ]
  },
  "type": "Feature",
  "properties": {
    "hierarchy": [
      "tgn:2303072",
      "tgn:1000001",
      "tgn:7006451",
      "tgn:7012149",
      "tgn:2000103",
      "tgn:7029392"
    ],
    "placetype": [
      "aat:300008697"
    ],
    "id": 2303072,
    "name:xx": "E Cross L Spring"
  }
}
