{
  "geometry": {
    "type": "Point",
    "coordinates": [
      -116.1333,
      45.5333
    ]
  },
  "type": "Feature",
  "properties": {
    "hierarchy": [
      "tgn:2733654",
      "tgn:1000001",
      "tgn:7012149",
      "tgn:2000476",
      "tgn:7007250",
      "tgn:7029392"
    ],
    "placetype": [
      "aat:300008706"
    ],
    "id": 2733654,
    "name:xx": "Turnbull Creek"
  }
}
