{
  "type": "FeatureCollection",
  "features": [
    {
      "geometry": {
        "type": "Point",
        "coordinates": [
          -92.641667,
          17.729167
        ]
      },
      "type": "Feature",
      "properties": {
        "hierarchy": [
          "tgn:7413630",
          "tgn:1000001",
          "tgn:7005596",
          "tgn:7005560",
          "tgn:7029392"
        ],
        "placetype": [
          "aat:300008347"
        ],
        "id": 7413630,
        "name:es": "Alvaro Obregón"
      }
    },
    {
      "geometry": {
        "type": "Point",
        "coordinates": [
          -92.7,
          17.733333
        ]
      },
      "type": "Feature",
      "properties": {
        "hierarchy": [
          "tgn:7413631",
          "tgn:1000001",
          "tgn:7005596",
          "tgn:7005560",
          "tgn:7029392"
        ],
        "placetype": [
          "aat:300008347"
        ],
        "id": 7413631,
        "name:es": "El Bojón"
      }
    },
    {
      "geometry": {
        "type": "Point",
        "coordinates": [
          -92.55,
          17.741667
        ]
      },
      "type": "Feature",
      "properties": {
        "hierarchy": [
          "tgn:7413634",
          "tgn:1000001",
          "tgn:7005596",
          "tgn:7005560",
          "tgn:7029392"
        ],
        "placetype": [
          "aat:300008347"
        ],
        "id": 7413634,
        "name:es": "El Alto"
      }
    },
    {
      "geometry": {
        "type": "Point",
        "coordinates": [
          -92.6625,
          17.741667
        ]
      },
      "type": "Feature",
      "properties": {
        "hierarchy": [
          "tgn:7413635",
          "tgn:1000001",
          "tgn:7005596",
          "tgn:7005560",
          "tgn:7029392"
        ],
        "placetype": [
          "aat:300008347"
        ],
        "id": 7413635,
        "name:es": "Narciso Mendoza"
      }
    },
    {
      "geometry": {
        "type": "Point",
        "coordinates": [
          -92.8,
          17.5625
        ]
      },
      "type": "Feature",
      "properties": {
        "hierarchy": [
          "tgn:7413637",
          "tgn:1000001",
          "tgn:7005596",
          "tgn:7005560",
          "tgn:7029392"
        ],
        "placetype": [
          "aat:300008347"
        ],
        "id": 7413637,
        "name:es": "Madrigal"
      }
    },
    {
      "geometry": {
        "type": "Point",
        "coordinates": [
          -92.975,
          17.508333
        ]
      },
      "type": "Feature",
      "properties": {
        "hierarchy": [
          "tgn:7413638",
          "tgn:1000001",
          "tgn:7005596",
          "tgn:7005560",
          "tgn:7029392"
        ],
        "placetype": [
          "aat:300008347"
        ],
        "id": 7413638,
        "name:es": "El Azufrito"
      }
    }
  ]
}
