{
  "geometry": {
    "type": "Point",
    "coordinates": [
      -118.7833,
      40.45
    ]
  },
  "type": "Feature",
  "properties": {
    "hierarchy": [
      "tgn:2437539",
      "tgn:1000001",
      "tgn:2001419",
      "tgn:7012149",
      "tgn:7007526",
      "tgn:7029392"
    ],
    "placetype": [
      "aat:300000390"
    ],
    "id": 2437539,
    "name:xx": "Kindergarten-Therian Group Mine"
  }
}
