{
  "geometry": {
    "type": "Point",
    "coordinates": [
      -104.7167,
      31.65
    ]
  },
  "type": "Feature",
  "properties": {
    "hierarchy": [
      "tgn:2608880",
      "tgn:1000001",
      "tgn:7012149",
      "tgn:2001969",
      "tgn:7007826",
      "tgn:7029392"
    ],
    "placetype": [
      "aat:300006191"
    ],
    "id": 2608880,
    "name:xx": "Rattlesnake Tank"
  }
}
