{
  "geometry": {
    "type": "Point",
    "coordinates": [
      -78.2167,
      41.55
    ]
  },
  "type": "Feature",
  "properties": {
    "hierarchy": [
      "tgn:2442319",
      "tgn:1000001",
      "tgn:1002229",
      "tgn:7012149",
      "tgn:7007710",
      "tgn:7029392"
    ],
    "placetype": [
      "aat:300008761"
    ],
    "id": 2442319,
    "name:xx": "Krebs Hollow"
  }
}
