{
  "geometry": {
    "type": "Point",
    "coordinates": [
      -94.95,
      39.0833
    ]
  },
  "type": "Feature",
  "properties": {
    "hierarchy": [
      "tgn:2456919",
      "tgn:1000001",
      "tgn:7012149",
      "tgn:7007254",
      "tgn:7029392"
    ],
    "placetype": [
      "aat:300008706"
    ],
    "id": 2456919,
    "name:xx": "Little Kaw Creek"
  }
}
