{
  "geometry": {
    "type": "Point",
    "coordinates": [
      -77.7667,
      35.9167
    ]
  },
  "type": "Feature",
  "properties": {
    "hierarchy": [
      "tgn:2263064",
      "tgn:1000001",
      "tgn:7012149",
      "tgn:2001493",
      "tgn:7007709",
      "tgn:7029392"
    ],
    "placetype": [
      "aat:300008699"
    ],
    "id": 2263064,
    "name:xx": "Cowlick Branch"
  }
}
