{
  "geometry": {
    "type": "Point",
    "coordinates": [
      8.5833,
      46.2167
    ]
  },
  "type": "Feature",
  "properties": {
    "hierarchy": [
      "tgn:7007338",
      "tgn:1000003",
      "tgn:7004723",
      "tgn:7011731",
      "tgn:7029392"
    ],
    "placetype": [
      "aat:300008347"
    ],
    "id": 7007338,
    "name:xx": "Comologno"
  }
}
