{
  "geometry": {
    "type": "Point",
    "coordinates": [
      -122.25,
      44.35
    ]
  },
  "type": "Feature",
  "properties": {
    "hierarchy": [
      "tgn:2356535",
      "tgn:1000001",
      "tgn:7012149",
      "tgn:2001717",
      "tgn:7007708",
      "tgn:7029392"
    ],
    "placetype": [
      "aat:300008680"
    ],
    "id": 2356535,
    "name:xx": "Gordon Lakes"
  }
}
