{
  "geometry": {
    "type": "Point",
    "coordinates": [
      6.15,
      52.85
    ]
  },
  "type": "Feature",
  "properties": {
    "hierarchy": [
      "tgn:7267922",
      "tgn:7003614",
      "tgn:1000003",
      "tgn:7016845",
      "tgn:7029392"
    ],
    "placetype": [
      "aat:300387200"
    ],
    "name:nl": "Nijensleekerveld",
    "id": 7267922
  }
}
