{
  "geometry": {
    "type": "Point",
    "coordinates": [
      -112.45,
      38.1333
    ]
  },
  "type": "Feature",
  "properties": {
    "hierarchy": [
      "tgn:2263831",
      "tgn:1000001",
      "tgn:7012149",
      "tgn:7007827",
      "tgn:7029392"
    ],
    "placetype": [
      "aat:300008706"
    ],
    "id": 2263831,
    "name:xx": "Coyote Creek"
  }
}
