{
  "type": "FeatureCollection",
  "features": [
    {
      "geometry": {
        "type": "Point",
        "coordinates": [
          -88.0833,
          34.5833
        ]
      },
      "type": "Feature",
      "properties": {
        "hierarchy": [
          "tgn:2568660",
          "tgn:7002659",
          "tgn:1000001",
          "tgn:2000016",
          "tgn:7012149",
          "tgn:7029392"
        ],
        "placetype": [
          "aat:300008699"
        ],
        "id": 2568660,
        "name:xx": "Parker Branch"
      }
    },
    {
      "geometry": {
        "type": "Point",
        "coordinates": [
          -87.4167,
          34.6
        ]
      },
      "type": "Feature",
      "properties": {
        "hierarchy": [
          "tgn:2568661",
          "tgn:7002659",
          "tgn:1000001",
          "tgn:7012149",
          "tgn:2000039",
          "tgn:7029392"
        ],
        "placetype": [
          "aat:300008699"
        ],
        "id": 2568661,
        "name:xx": "Parker Branch"
      }
    },
    {
      "geometry": {
        "type": "Point",
        "coordinates": [
          -93.7833,
          34.9333
        ]
      },
      "type": "Feature",
      "properties": {
        "hierarchy": [
          "tgn:2568662",
          "tgn:1000001",
          "tgn:7016172",
          "tgn:7012149",
          "tgn:2000168",
          "tgn:7029392"
        ],
        "placetype": [
          "aat:300008699"
        ],
        "id": 2568662,
        "name:xx": "Parker Branch"
      }
    },
    {
      "geometry": {
        "type": "Point",
        "coordinates": [
          -94.0833,
          35.8833
        ]
      },
      "type": "Feature",
      "properties": {
        "hierarchy": [
          "tgn:2568663",
          "tgn:1000001",
          "tgn:7016172",
          "tgn:7012149",
          "tgn:2000176",
          "tgn:7029392"
        ],
        "placetype": [
          "aat:300008699"
        ],
        "id": 2568663,
        "name:xx": "Parker Branch"
      }
    },
    {
      "geometry": {
        "type": "Point",
        "coordinates": [
          -75.4833,
          38.8
        ]
      },
      "type": "Feature",
      "properties": {
        "hierarchy": [
          "tgn:2568664",
          "tgn:1002933",
          "tgn:1000001",
          "tgn:7012149",
          "tgn:7007239",
          "tgn:7029392"
        ],
        "placetype": [
          "aat:300008699"
        ],
        "id": 2568664,
        "name:xx": "Parker Branch"
      }
    },
    {
      "geometry": {
        "type": "Point",
        "coordinates": [
          -81.7333,
          27.65
        ]
      },
      "type": "Feature",
      "properties": {
        "hierarchy": [
          "tgn:2568665",
          "tgn:1000001",
          "tgn:7012149",
          "tgn:7007240",
          "tgn:7029392"
        ],
        "placetype": [
          "aat:300008699"
        ],
        "id": 2568665,
        "name:xx": "Parker Branch"
      }
    },
    {
      "geometry": {
        "type": "Point",
        "coordinates": [
          -85.5167,
          30.15
        ]
      },
      "type": "Feature",
      "properties": {
        "hierarchy": [
          "tgn:2568666",
          "tgn:2000258",
          "tgn:1000001",
          "tgn:7012149",
          "tgn:7007240",
          "tgn:7029392"
        ],
        "placetype": [
          "aat:300008699"
        ],
        "id": 2568666,
        "name:xx": "Parker Branch"
      }
    },
    {
      "geometry": {
        "type": "Point",
        "coordinates": [
          -80.6167,
          27.2
        ]
      },
      "type": "Feature",
      "properties": {
        "hierarchy": [
          "tgn:2568667",
          "tgn:1000001",
          "tgn:7012149",
          "tgn:7016124",
          "tgn:7007240",
          "tgn:7029392"
        ],
        "placetype": [
          "aat:300008699"
        ],
        "id": 2568667,
        "name:xx": "Parker Branch"
      }
    },
    {
      "geometry": {
        "type": "Point",
        "coordinates": [
          -82.7333,
          33.1333
        ]
      },
      "type": "Feature",
      "properties": {
        "hierarchy": [
          "tgn:2568668",
          "tgn:1000001",
          "tgn:7012149",
          "tgn:2000441",
          "tgn:7007248",
          "tgn:7029392"
        ],
        "placetype": [
          "aat:300008699"
        ],
        "id": 2568668,
        "name:xx": "Parker Branch"
      }
    },
    {
      "geometry": {
        "type": "Point",
        "coordinates": [
          -84.1,
          33.15
        ]
      },
      "type": "Feature",
      "properties": {
        "hierarchy": [
          "tgn:2568669",
          "tgn:1000001",
          "tgn:7012149",
          "tgn:2000376",
          "tgn:7007248",
          "tgn:7029392"
        ],
        "placetype": [
          "aat:300008699"
        ],
        "id": 2568669,
        "name:xx": "Parker Branch"
      }
    }
  ]
}
