{
  "geometry": {
    "type": "Point",
    "coordinates": [
      -102.333333,
      21.85
    ]
  },
  "type": "Feature",
  "properties": {
    "hierarchy": [
      "tgn:7393680",
      "tgn:7005579",
      "tgn:1000001",
      "tgn:7005560",
      "tgn:7029392"
    ],
    "placetype": [
      "aat:300008699"
    ],
    "id": 7393680,
    "name:xx": "San Francisco, Río de"
  }
}
