{
  "type": "FeatureCollection",
  "features": [
    {
      "geometry": {
        "type": "Point",
        "coordinates": [
          6.35,
          45.4
        ]
      },
      "type": "Feature",
      "properties": {
        "hierarchy": [
          "tgn:1035323",
          "tgn:1000003",
          "tgn:1000070",
          "tgn:7002897",
          "tgn:7029392"
        ],
        "placetype": [
          "aat:300008347"
        ],
        "id": 1035323,
        "name:xx": "Saint-François-sur-Bugeon"
      }
    },
    {
      "geometry": {
        "type": "Point",
        "coordinates": [
          4.15,
          44.9833
        ]
      },
      "type": "Feature",
      "properties": {
        "hierarchy": [
          "tgn:1035324",
          "tgn:7002871",
          "tgn:1000003",
          "tgn:1000070",
          "tgn:7029392"
        ],
        "placetype": [
          "aat:300008347"
        ],
        "id": 1035324,
        "name:xx": "Saint-Front"
      }
    },
    {
      "geometry": {
        "type": "Point",
        "coordinates": [
          3.8,
          43.6833
        ]
      },
      "type": "Feature",
      "properties": {
        "hierarchy": [
          "tgn:1035325",
          "tgn:1000003",
          "tgn:7002885",
          "tgn:1000070",
          "tgn:7029392"
        ],
        "placetype": [
          "aat:300008347"
        ],
        "id": 1035325,
        "name:xx": "Saint-Gély-du-Fesc"
      }
    },
    {
      "geometry": {
        "type": "Point",
        "coordinates": [
          1.5667,
          44.4667
        ]
      },
      "type": "Feature",
      "properties": {
        "hierarchy": [
          "tgn:1035326",
          "tgn:1000003",
          "tgn:7002889",
          "tgn:1000070",
          "tgn:7029392"
        ],
        "placetype": [
          "aat:300008347"
        ],
        "id": 1035326,
        "name:xx": "Saint-Géry"
      }
    }
  ]
}
