{
  "geometry": {
    "type": "Point",
    "coordinates": [
      -90.8833,
      36.8833
    ]
  },
  "type": "Feature",
  "properties": {
    "hierarchy": [
      "tgn:2471604",
      "tgn:1000001",
      "tgn:2001181",
      "tgn:7012149",
      "tgn:7007523",
      "tgn:7029392"
    ],
    "placetype": [
      "aat:300008746"
    ],
    "id": 2471604,
    "name:xx": "Lost Man Cave"
  }
}
