{
  "geometry": {
    "type": "Point",
    "coordinates": [
      -82.4833,
      36.5667
    ]
  },
  "type": "Feature",
  "properties": {
    "hierarchy": [
      "tgn:2438613",
      "tgn:1000001",
      "tgn:7012149",
      "tgn:2001918",
      "tgn:7007825",
      "tgn:7029392"
    ],
    "placetype": [
      "aat:300008347"
    ],
    "id": 2438613,
    "name:xx": "Kingsley Hills"
  }
}
