{
  "geometry": {
    "type": "Point",
    "coordinates": [
      11.95,
      51.433333
    ]
  },
  "type": "Feature",
  "properties": {
    "hierarchy": [
      "tgn:7077529",
      "tgn:1000003",
      "tgn:7003687",
      "tgn:7000084",
      "tgn:7029392"
    ],
    "placetype": [
      "aat:300008699"
    ],
    "id": 7077529,
    "name:xx": "Bílý Halštrov"
  }
}
