{
  "geometry": {
    "type": "Point",
    "coordinates": [
      -106.15,
      44.8833
    ]
  },
  "type": "Feature",
  "properties": {
    "hierarchy": [
      "tgn:2623058",
      "tgn:1000001",
      "tgn:7012149",
      "tgn:2002381",
      "tgn:7007923",
      "tgn:7029392"
    ],
    "placetype": [
      "aat:300008761"
    ],
    "id": 2623058,
    "name:xx": "Robling Draw"
  }
}
