{
  "geometry": {
    "type": "Point",
    "coordinates": [
      -91.05,
      39.15
    ]
  },
  "type": "Feature",
  "properties": {
    "hierarchy": [
      "tgn:2772369",
      "tgn:1000001",
      "tgn:7012149",
      "tgn:1002598",
      "tgn:7007523",
      "tgn:7029392"
    ],
    "placetype": [
      "aat:300006191"
    ],
    "id": 2772369,
    "name:xx": "William Logan State Wildlife Area Lake"
  }
}
