{
  "geometry": {
    "type": "Point",
    "coordinates": [
      -86.4833,
      30.5167
    ]
  },
  "type": "Feature",
  "properties": {
    "hierarchy": [
      "tgn:2730085",
      "tgn:1000001",
      "tgn:7012149",
      "tgn:2000281",
      "tgn:7007240",
      "tgn:7029392"
    ],
    "placetype": [
      "aat:300006191"
    ],
    "id": 2730085,
    "name:xx": "Trout Lake"
  }
}
