{
  "geometry": {
    "type": "Point",
    "coordinates": [
      9.1667,
      9.2333
    ]
  },
  "type": "Feature",
  "properties": {
    "hierarchy": [
      "tgn:1092254",
      "tgn:7001242",
      "tgn:1001931",
      "tgn:1000182",
      "tgn:7029392"
    ],
    "placetype": [
      "aat:300008347"
    ],
    "id": 1092254,
    "name:xx": "Panyam"
  }
}
