{
  "type": "FeatureCollection",
  "features": [
    {
      "geometry": {
        "type": "Point",
        "coordinates": [
          -1.559722,
          54.991389
        ]
      },
      "type": "Feature",
      "properties": {
        "hierarchy": [
          "tgn:1030980",
          "tgn:7019072",
          "tgn:7002445",
          "tgn:1000003",
          "tgn:7012033",
          "tgn:7008591",
          "tgn:7029392"
        ],
        "placetype": [
          "aat:300008347",
          "aat:300008389",
          "aat:300387308",
          "aat:300387305",
          "aat:300006888",
          "aat:300387220",
          "aat:300387302",
          "aat:300387288"
        ],
        "name:en": "Wallsend",
        "id": 1030980
      }
    },
    {
      "geometry": {
        "type": "Point",
        "coordinates": [
          -2.3,
          53.616667
        ]
      },
      "type": "Feature",
      "properties": {
        "hierarchy": [
          "tgn:1030982",
          "tgn:1003572",
          "tgn:7002445",
          "tgn:1000003",
          "tgn:7026570",
          "tgn:7008591",
          "tgn:7029392"
        ],
        "placetype": [
          "aat:300008347"
        ],
        "name:en": "Walmersley",
        "id": 1030982
      }
    },
    {
      "geometry": {
        "type": "Point",
        "coordinates": [
          -2.1,
          53.7
        ]
      },
      "type": "Feature",
      "properties": {
        "hierarchy": [
          "tgn:1030985",
          "tgn:1003573",
          "tgn:7002445",
          "tgn:1000003",
          "tgn:7029507",
          "tgn:7008591",
          "tgn:7029392"
        ],
        "placetype": [
          "aat:300008347"
        ],
        "name:en": "Walsden",
        "id": 1030985
      }
    },
    {
      "geometry": {
        "type": "Point",
        "coordinates": [
          -0.1,
          53.516667
        ]
      },
      "type": "Feature",
      "properties": {
        "hierarchy": [
          "tgn:1030986",
          "tgn:7002445",
          "tgn:1000003",
          "tgn:7019055",
          "tgn:7008591",
          "tgn:7029392"
        ],
        "placetype": [
          "aat:300008347",
          "aat:300008375"
        ],
        "name:en": "Waltham",
        "id": 1030986
      }
    },
    {
      "geometry": {
        "type": "Point",
        "coordinates": [
          -0.8,
          52.8
        ]
      },
      "type": "Feature",
      "properties": {
        "hierarchy": [
          "tgn:1030988",
          "tgn:7002445",
          "tgn:1000003",
          "tgn:7008155",
          "tgn:7008591",
          "tgn:7029392"
        ],
        "placetype": [
          "aat:300008347",
          "aat:300008372"
        ],
        "name:en": "Waltham on the Wolds",
        "id": 1030988
      }
    }
  ]
}
