{
  "geometry": {
    "type": "Point",
    "coordinates": [
      32.016692,
      30.534486
    ]
  },
  "type": "Feature",
  "properties": {
    "hierarchy": [
      "tgn:7539267",
      "tgn:7001242",
      "tgn:7016833",
      "tgn:1001080",
      "tgn:7029392"
    ],
    "placetype": [
      "aat:300008680"
    ],
    "name:en": "Matrūk, Birkat al",
    "id": 7539267
  }
}
