{
  "geometry": {
    "type": "Point",
    "coordinates": [
      -97.6333,
      38.9333
    ]
  },
  "type": "Feature",
  "properties": {
    "hierarchy": [
      "tgn:2752069",
      "tgn:1000001",
      "tgn:7012149",
      "tgn:2000744",
      "tgn:7007254",
      "tgn:7029392"
    ],
    "placetype": [
      "aat:300006191"
    ],
    "id": 2752069,
    "name:xx": "Wary Lake"
  }
}
