{
  "geometry": {
    "type": "Point",
    "coordinates": [
      -105.3167,
      33.2333
    ]
  },
  "type": "Feature",
  "properties": {
    "hierarchy": [
      "tgn:2279527",
      "tgn:1000001",
      "tgn:7012149",
      "tgn:2001447",
      "tgn:7007566",
      "tgn:7029392"
    ],
    "placetype": [
      "aat:300008680"
    ],
    "id": 2279527,
    "name:xx": "Deadman Lake"
  }
}
