{
  "geometry": {
    "type": "Point",
    "coordinates": [
      77.866667,
      18.816667
    ]
  },
  "type": "Feature",
  "properties": {
    "hierarchy": [
      "tgn:7552427",
      "tgn:1001828",
      "tgn:1000004",
      "tgn:7000198",
      "tgn:7029392"
    ],
    "placetype": [
      "aat:300008699"
    ],
    "name:en": "Mānjra River",
    "id": 7552427
  }
}
