{
  "geometry": {
    "type": "Point",
    "coordinates": [
      -78.5333,
      36.2167
    ]
  },
  "type": "Feature",
  "properties": {
    "hierarchy": [
      "tgn:2422928",
      "tgn:1000001",
      "tgn:7012149",
      "tgn:7014128",
      "tgn:7007709",
      "tgn:7029392"
    ],
    "placetype": [
      "aat:300006191"
    ],
    "id": 2422928,
    "name:xx": "Joe Hamme Jr Lake"
  }
}
