{
  "type": "FeatureCollection",
  "features": [
    {
      "geometry": {
        "type": "Point",
        "coordinates": [
          -98.516667,
          24.25
        ]
      },
      "type": "Feature",
      "properties": {
        "hierarchy": [
          "tgn:7383390",
          "tgn:1000001",
          "tgn:7005597",
          "tgn:7005560",
          "tgn:7029392"
        ],
        "placetype": [
          "aat:300000241"
        ],
        "id": 7383390,
        "name:xx": "Rancho Nuevo"
      }
    },
    {
      "geometry": {
        "type": "Point",
        "coordinates": [
          -99.45,
          23.85
        ]
      },
      "type": "Feature",
      "properties": {
        "hierarchy": [
          "tgn:7383391",
          "tgn:1000001",
          "tgn:7005597",
          "tgn:7005560",
          "tgn:7029392"
        ],
        "placetype": [
          "aat:300000241"
        ],
        "id": 7383391,
        "name:xx": "Rancho Nuevo"
      }
    },
    {
      "geometry": {
        "type": "Point",
        "coordinates": [
          -98.6,
          23.783333
        ]
      },
      "type": "Feature",
      "properties": {
        "hierarchy": [
          "tgn:7383392",
          "tgn:1000001",
          "tgn:7005597",
          "tgn:7005560",
          "tgn:7029392"
        ],
        "placetype": [
          "aat:300000241"
        ],
        "id": 7383392,
        "name:xx": "Rancho Nuevo"
      }
    },
    {
      "geometry": {
        "type": "Point",
        "coordinates": [
          -102.866667,
          20.8
        ]
      },
      "type": "Feature",
      "properties": {
        "hierarchy": [
          "tgn:7383393",
          "tgn:7005586",
          "tgn:1000001",
          "tgn:7005560",
          "tgn:7029392"
        ],
        "placetype": [
          "aat:300000241"
        ],
        "id": 7383393,
        "name:xx": "Rancho Nuevo"
      }
    },
    {
      "geometry": {
        "type": "Point",
        "coordinates": [
          -102.75,
          20.65
        ]
      },
      "type": "Feature",
      "properties": {
        "hierarchy": [
          "tgn:7383394",
          "tgn:7005586",
          "tgn:1000001",
          "tgn:7005560",
          "tgn:7029392"
        ],
        "placetype": [
          "aat:300000241"
        ],
        "id": 7383394,
        "name:xx": "Rancho Nuevo"
      }
    },
    {
      "geometry": {
        "type": "Point",
        "coordinates": [
          -103.366667,
          20.116667
        ]
      },
      "type": "Feature",
      "properties": {
        "hierarchy": [
          "tgn:7383395",
          "tgn:7005586",
          "tgn:1000001",
          "tgn:7005560",
          "tgn:7029392"
        ],
        "placetype": [
          "aat:300000241"
        ],
        "id": 7383395,
        "name:xx": "Rancho Nuevo"
      }
    },
    {
      "geometry": {
        "type": "Point",
        "coordinates": [
          -104.683333,
          19.65
        ]
      },
      "type": "Feature",
      "properties": {
        "hierarchy": [
          "tgn:7383396",
          "tgn:7005586",
          "tgn:1000001",
          "tgn:7005560",
          "tgn:7029392"
        ],
        "placetype": [
          "aat:300000241"
        ],
        "id": 7383396,
        "name:xx": "Rancho Nuevo"
      }
    },
    {
      "geometry": {
        "type": "Point",
        "coordinates": [
          -91.216667,
          17.5
        ]
      },
      "type": "Feature",
      "properties": {
        "hierarchy": [
          "tgn:7383397",
          "tgn:1000001",
          "tgn:7005596",
          "tgn:7005560",
          "tgn:7029392"
        ],
        "placetype": [
          "aat:300008347"
        ],
        "id": 7383397,
        "name:xx": "Rancho Nuevo"
      }
    },
    {
      "geometry": {
        "type": "Point",
        "coordinates": [
          -109.7,
          30.65
        ]
      },
      "type": "Feature",
      "properties": {
        "hierarchy": [
          "tgn:7383398",
          "tgn:1000001",
          "tgn:1001960",
          "tgn:7005560",
          "tgn:7029392"
        ],
        "placetype": [
          "aat:300000241"
        ],
        "id": 7383398,
        "name:xx": "El Rancho Nuevo"
      }
    },
    {
      "geometry": {
        "type": "Point",
        "coordinates": [
          -110.583333,
          30.616667
        ]
      },
      "type": "Feature",
      "properties": {
        "hierarchy": [
          "tgn:7383399",
          "tgn:1000001",
          "tgn:1001960",
          "tgn:7005560",
          "tgn:7029392"
        ],
        "placetype": [
          "aat:300000241"
        ],
        "id": 7383399,
        "name:xx": "El Rancho Nuevo"
      }
    }
  ]
}
