{
  "geometry": {
    "type": "Point",
    "coordinates": [
      117.65,
      40.0667
    ]
  },
  "type": "Feature",
  "properties": {
    "hierarchy": [
      "tgn:1069881",
      "tgn:1000004",
      "tgn:1000960",
      "tgn:1000111",
      "tgn:7029392"
    ],
    "placetype": [
      "aat:300008347"
    ],
    "id": 1069881,
    "name:xx": "Linhezhuang"
  }
}
