{
  "geometry": {
    "type": "Point",
    "coordinates": [
      -109.3667,
      31.6333
    ]
  },
  "type": "Feature",
  "properties": {
    "hierarchy": [
      "tgn:2389813",
      "tgn:1000001",
      "tgn:7006451",
      "tgn:2000091",
      "tgn:7012149",
      "tgn:7029392"
    ],
    "placetype": [
      "aat:300008697"
    ],
    "id": 2389813,
    "name:xx": "High Lonesome Spring"
  }
}
