{
  "geometry": {
    "type": "Point",
    "coordinates": [
      -80.5167,
      37.2833
    ]
  },
  "type": "Feature",
  "properties": {
    "hierarchy": [
      "tgn:2688644",
      "tgn:1000001",
      "tgn:7012149",
      "tgn:2002162",
      "tgn:7007919",
      "tgn:7029392"
    ],
    "placetype": [
      "aat:300008699"
    ],
    "id": 2688644,
    "name:xx": "Spruce Run"
  }
}
