{
  "geometry": {
    "type": "Point",
    "coordinates": [
      9.65,
      39.55
    ]
  },
  "type": "Feature",
  "properties": {
    "hierarchy": [
      "tgn:7054391",
      "tgn:1001724",
      "tgn:1000003",
      "tgn:7003121",
      "tgn:1000080",
      "tgn:7029392"
    ],
    "placetype": [
      "aat:300008678"
    ],
    "id": 7054391,
    "name:xx": "Paglia, Porto de sa"
  }
}
