{
  "geometry": {
    "type": "Point",
    "coordinates": [
      -154.95,
      19.4833
    ]
  },
  "type": "Feature",
  "properties": {
    "hierarchy": [
      "tgn:2025190",
      "tgn:7023902",
      "tgn:1000001",
      "tgn:7012149",
      "tgn:7007249",
      "tgn:7029392"
    ],
    "placetype": [
      "aat:300008347"
    ],
    "id": 2025190,
    "name:xx": "Pahoa"
  }
}
