{
  "geometry": {
    "type": "Point",
    "coordinates": [
      -84.1667,
      45.2333
    ]
  },
  "type": "Feature",
  "properties": {
    "hierarchy": [
      "tgn:2660476",
      "tgn:1000001",
      "tgn:7012149",
      "tgn:2000990",
      "tgn:7007520",
      "tgn:7029392"
    ],
    "placetype": [
      "aat:300008680"
    ],
    "id": 2660476,
    "name:xx": "Shoepac Lake"
  }
}
