{
  "geometry": {
    "type": "Point",
    "coordinates": [
      -156.2667,
      20.9167
    ]
  },
  "type": "Feature",
  "properties": {
    "hierarchy": [
      "tgn:2572628",
      "tgn:1002648",
      "tgn:1000001",
      "tgn:7019158",
      "tgn:7012149",
      "tgn:7007249",
      "tgn:7029392"
    ],
    "placetype": [
      "aat:300006191"
    ],
    "id": 2572628,
    "name:xx": "Peahi Reservoir"
  }
}
