{
  "type": "FeatureCollection",
  "features": [
    {
      "geometry": {
        "type": "Point",
        "coordinates": [
          -72.6,
          -36.283333
        ]
      },
      "type": "Feature",
      "properties": {
        "hierarchy": [
          "tgn:7314600",
          "tgn:1001637",
          "tgn:1000049",
          "tgn:1000002",
          "tgn:7029392"
        ],
        "placetype": [
          "aat:300387200"
        ],
        "id": 7314600,
        "name:xx": "Los Lirios"
      }
    },
    {
      "geometry": {
        "type": "Point",
        "coordinates": [
          -70.65,
          -32.833333
        ]
      },
      "type": "Feature",
      "properties": {
        "hierarchy": [
          "tgn:7314601",
          "tgn:1001768",
          "tgn:1000049",
          "tgn:1000002",
          "tgn:7029392"
        ],
        "placetype": [
          "aat:300005433"
        ],
        "id": 7314601,
        "name:xx": "Los Lirios"
      }
    },
    {
      "geometry": {
        "type": "Point",
        "coordinates": [
          -71.3,
          -34.166667
        ]
      },
      "type": "Feature",
      "properties": {
        "hierarchy": [
          "tgn:7314602",
          "tgn:1001708",
          "tgn:1000049",
          "tgn:1000002",
          "tgn:7029392"
        ],
        "placetype": [
          "aat:300008699"
        ],
        "id": 7314602,
        "name:xx": "Los Lingues, Quebrada de"
      }
    },
    {
      "geometry": {
        "type": "Point",
        "coordinates": [
          -71.083333,
          -35.016667
        ]
      },
      "type": "Feature",
      "properties": {
        "hierarchy": [
          "tgn:7314603",
          "tgn:1001705",
          "tgn:1000049",
          "tgn:1000002",
          "tgn:7029392"
        ],
        "placetype": [
          "aat:300008699"
        ],
        "id": 7314603,
        "name:xx": "Los Lingues, Quebrada"
      }
    },
    {
      "geometry": {
        "type": "Point",
        "coordinates": [
          -71.733333,
          -34.116667
        ]
      },
      "type": "Feature",
      "properties": {
        "hierarchy": [
          "tgn:7314604",
          "tgn:1001695",
          "tgn:1000049",
          "tgn:1000002",
          "tgn:7029392"
        ],
        "placetype": [
          "aat:300008699"
        ],
        "id": 7314604,
        "name:xx": "Los Lingues, Estero"
      }
    },
    {
      "geometry": {
        "type": "Point",
        "coordinates": [
          -70.9,
          -34.516667
        ]
      },
      "type": "Feature",
      "properties": {
        "hierarchy": [
          "tgn:7314605",
          "tgn:1001695",
          "tgn:1000049",
          "tgn:1000002",
          "tgn:7029392"
        ],
        "placetype": [
          "aat:300008347"
        ],
        "id": 7314605,
        "name:xx": "Los Lingues"
      }
    },
    {
      "geometry": {
        "type": "Point",
        "coordinates": [
          -71.766667,
          -34.116667
        ]
      },
      "type": "Feature",
      "properties": {
        "hierarchy": [
          "tgn:7314606",
          "tgn:1001695",
          "tgn:1000049",
          "tgn:1000002",
          "tgn:7029392"
        ],
        "placetype": [
          "aat:300387200"
        ],
        "id": 7314606,
        "name:xx": "Los Lingues"
      }
    },
    {
      "geometry": {
        "type": "Point",
        "coordinates": [
          -71.083333,
          -33.983333
        ]
      },
      "type": "Feature",
      "properties": {
        "hierarchy": [
          "tgn:7314607",
          "tgn:1001708",
          "tgn:1000049",
          "tgn:1000002",
          "tgn:7029392"
        ],
        "placetype": [
          "aat:300387002"
        ],
        "id": 7314607,
        "name:xx": "Los Linderos, Loma"
      }
    },
    {
      "geometry": {
        "type": "Point",
        "coordinates": [
          -71.4,
          -30.4
        ]
      },
      "type": "Feature",
      "properties": {
        "hierarchy": [
          "tgn:7314608",
          "tgn:1001657",
          "tgn:1000049",
          "tgn:1000002",
          "tgn:7029392"
        ],
        "placetype": [
          "aat:300008795"
        ],
        "id": 7314608,
        "name:xx": "Los Linderos, Cordón"
      }
    },
    {
      "geometry": {
        "type": "Point",
        "coordinates": [
          -71.5,
          -34.766667
        ]
      },
      "type": "Feature",
      "properties": {
        "hierarchy": [
          "tgn:7314609",
          "tgn:1001695",
          "tgn:1000049",
          "tgn:1000002",
          "tgn:7029392"
        ],
        "placetype": [
          "aat:300008795"
        ],
        "id": 7314609,
        "name:xx": "Los Linderos, Cerro"
      }
    }
  ]
}
