{
  "geometry": {
    "type": "Point",
    "coordinates": [
      -76.5167,
      0.5167
    ]
  },
  "type": "Feature",
  "properties": {
    "hierarchy": [
      "tgn:1023931",
      "tgn:1000050",
      "tgn:1002106",
      "tgn:1000002",
      "tgn:7029392"
    ],
    "placetype": [
      "aat:300008347"
    ],
    "id": 1023931,
    "name:xx": "Puerto Asís"
  }
}
