{
  "geometry": {
    "type": "Point",
    "coordinates": [
      -83.6833,
      40.55
    ]
  },
  "type": "Feature",
  "properties": {
    "hierarchy": [
      "tgn:2663307",
      "tgn:1000001",
      "tgn:7012149",
      "tgn:1002453",
      "tgn:7007706",
      "tgn:7029392"
    ],
    "placetype": [
      "aat:300008706"
    ],
    "id": 2663307,
    "name:xx": "Silver Creek"
  }
}
