{
  "type": "FeatureCollection",
  "features": [
    {
      "geometry": {
        "type": "Point",
        "coordinates": [
          14.866667,
          40.95
        ]
      },
      "type": "Feature",
      "properties": {
        "hierarchy": [
          "tgn:7044880",
          "tgn:7003002",
          "tgn:7003005",
          "tgn:1000003",
          "tgn:1000080",
          "tgn:7029392"
        ],
        "placetype": [
          "aat:300008347"
        ],
        "id": 7044880,
        "name:xx": "Candida"
      }
    },
    {
      "geometry": {
        "type": "Point",
        "coordinates": [
          7.9,
          45.316667
        ]
      },
      "type": "Feature",
      "properties": {
        "hierarchy": [
          "tgn:7044884",
          "tgn:7003154",
          "tgn:1000003",
          "tgn:7003120",
          "tgn:1000080",
          "tgn:7029392"
        ],
        "placetype": [
          "aat:300008680"
        ],
        "id": 7044884,
        "name:xx": "Candia, Lago di"
      }
    },
    {
      "geometry": {
        "type": "Point",
        "coordinates": [
          13.483333,
          43.566667
        ]
      },
      "type": "Feature",
      "properties": {
        "hierarchy": [
          "tgn:7044885",
          "tgn:1003429",
          "tgn:1000003",
          "tgn:7003240",
          "tgn:1000080",
          "tgn:7029392"
        ],
        "placetype": [
          "aat:300008347"
        ],
        "id": 7044885,
        "name:xx": "Candia"
      }
    }
  ]
}
