{
  "geometry": {
    "type": "Point",
    "coordinates": [
      74.85,
      32.748611
    ]
  },
  "type": "Feature",
  "properties": {
    "hierarchy": [
      "tgn:7592315",
      "tgn:1000004",
      "tgn:7000198",
      "tgn:7000799",
      "tgn:7029392"
    ],
    "placetype": [
      "aat:300008347"
    ],
    "name:en": "Sarwāl",
    "id": 7592315
  }
}
