{
  "geometry": {
    "type": "Point",
    "coordinates": [
      31.971111,
      31.45747
    ]
  },
  "type": "Feature",
  "properties": {
    "hierarchy": [
      "tgn:7525343",
      "tgn:7001242",
      "tgn:7016833",
      "tgn:1001225",
      "tgn:7029392"
    ],
    "placetype": [
      "aat:300386885"
    ],
    "name:en": "Ḑahrah, Barr aḑ",
    "id": 7525343
  }
}
