{
  "geometry": {
    "type": "Point",
    "coordinates": [
      -74.3167,
      43.05
    ]
  },
  "type": "Feature",
  "properties": {
    "hierarchy": [
      "tgn:2135154",
      "tgn:1000001",
      "tgn:7012149",
      "tgn:1002397",
      "tgn:7007568",
      "tgn:7029392"
    ],
    "placetype": [
      "aat:300008706"
    ],
    "id": 2135154,
    "name:xx": "Anthony Creek"
  }
}
