{
  "geometry": {
    "type": "Point",
    "coordinates": [
      31.1833,
      29.9333
    ]
  },
  "type": "Feature",
  "properties": {
    "hierarchy": [
      "tgn:1135982",
      "tgn:7001242",
      "tgn:7016833",
      "tgn:1001083",
      "tgn:7029392"
    ],
    "placetype": [
      "aat:300006075",
      "aat:300387086"
    ],
    "id": 1135982,
    "name:xx": "Lubaynī, Baḥr al"
  }
}
