{
  "geometry": {
    "type": "Point",
    "coordinates": [
      -102.8667,
      30.9167
    ]
  },
  "type": "Feature",
  "properties": {
    "hierarchy": [
      "tgn:2653424",
      "tgn:1000001",
      "tgn:7012149",
      "tgn:2002055",
      "tgn:7007826",
      "tgn:7029392"
    ],
    "placetype": [
      "aat:300008798"
    ],
    "id": 2653424,
    "name:xx": "Sevenmile Mesa"
  }
}
