{
  "geometry": {
    "type": "Point",
    "coordinates": [
      105.3667,
      9.75
    ]
  },
  "type": "Feature",
  "properties": {
    "hierarchy": [
      "tgn:1087154",
      "tgn:1000004",
      "tgn:7001047",
      "tgn:1000145",
      "tgn:7029392"
    ],
    "placetype": [
      "aat:300008347"
    ],
    "id": 1087154,
    "name:xx": "Kiên Hủng"
  }
}
