{
  "geometry": {
    "type": "Point",
    "coordinates": [
      -96.95,
      48.5333
    ]
  },
  "type": "Feature",
  "properties": {
    "hierarchy": [
      "tgn:2428360",
      "tgn:1000001",
      "tgn:7012149",
      "tgn:7007521",
      "tgn:7029392"
    ],
    "placetype": [
      "aat:300006075"
    ],
    "id": 2428360,
    "name:xx": "Judicial Ditch Number Three"
  }
}
