{
  "geometry": {
    "type": "Point",
    "coordinates": [
      -98.0167,
      50.6833
    ]
  },
  "type": "Feature",
  "properties": {
    "hierarchy": [
      "tgn:1013938",
      "tgn:7005685",
      "tgn:1000001",
      "tgn:7005734",
      "tgn:7029392"
    ],
    "placetype": [
      "aat:300008347"
    ],
    "id": 1013938,
    "name:xx": "Lundar"
  }
}
