{
  "geometry": {
    "type": "Point",
    "coordinates": [
      32.356914,
      26.169625
    ]
  },
  "type": "Feature",
  "properties": {
    "hierarchy": [
      "tgn:7520952",
      "tgn:7001242",
      "tgn:7001311",
      "tgn:7016833",
      "tgn:7029392"
    ],
    "placetype": [
      "aat:300379998"
    ],
    "name:en": "Ab큰 'Azz큰z, W훮d카",
    "id": 7520952
  }
}
