{
  "geometry": {
    "type": "Point",
    "coordinates": [
      -92.3167,
      29.5333
    ]
  },
  "type": "Feature",
  "properties": {
    "hierarchy": [
      "tgn:2642165",
      "tgn:1000001",
      "tgn:7012149",
      "tgn:2000910",
      "tgn:7007256",
      "tgn:7029392"
    ],
    "placetype": [
      "aat:300266640"
    ],
    "id": 2642165,
    "name:xx": "Sand Ridge"
  }
}
