{
  "type": "FeatureCollection",
  "features": [
    {
      "geometry": {
        "type": "Point",
        "coordinates": [
          9.7,
          50.383333
        ]
      },
      "type": "Feature",
      "properties": {
        "hierarchy": [
          "tgn:7095080",
          "tgn:1000003",
          "tgn:7003678",
          "tgn:7000084",
          "tgn:7029392"
        ],
        "placetype": [
          "aat:300008777"
        ],
        "id": 7095080,
        "name:xx": "Schwarzen-Berg"
      }
    },
    {
      "geometry": {
        "type": "Point",
        "coordinates": [
          9.95,
          50.333333
        ]
      },
      "type": "Feature",
      "properties": {
        "hierarchy": [
          "tgn:7095081",
          "tgn:7003669",
          "tgn:1000003",
          "tgn:7000084",
          "tgn:7029392"
        ],
        "placetype": [
          "aat:300008777"
        ],
        "id": 7095081,
        "name:xx": "Schwarzen Berg"
      }
    },
    {
      "geometry": {
        "type": "Point",
        "coordinates": [
          6.933333,
          50.3
        ]
      },
      "type": "Feature",
      "properties": {
        "hierarchy": [
          "tgn:7095082",
          "tgn:1000003",
          "tgn:7003682",
          "tgn:7000084",
          "tgn:7029392"
        ],
        "placetype": [
          "aat:300008777"
        ],
        "id": 7095082,
        "name:xx": "Schwarzen-Berg"
      }
    },
    {
      "geometry": {
        "type": "Point",
        "coordinates": [
          8.033333,
          49.816667
        ]
      },
      "type": "Feature",
      "properties": {
        "hierarchy": [
          "tgn:7095083",
          "tgn:1000003",
          "tgn:7003682",
          "tgn:7000084",
          "tgn:7029392"
        ],
        "placetype": [
          "aat:300008777"
        ],
        "id": 7095083,
        "name:xx": "Schwarzen Berg"
      }
    },
    {
      "geometry": {
        "type": "Point",
        "coordinates": [
          7.566667,
          49.733333
        ]
      },
      "type": "Feature",
      "properties": {
        "hierarchy": [
          "tgn:7095084",
          "tgn:1000003",
          "tgn:7003682",
          "tgn:7000084",
          "tgn:7029392"
        ],
        "placetype": [
          "aat:300008777"
        ],
        "id": 7095084,
        "name:xx": "Schwarzen-Berg"
      }
    },
    {
      "geometry": {
        "type": "Point",
        "coordinates": [
          11.833333,
          49.666667
        ]
      },
      "type": "Feature",
      "properties": {
        "hierarchy": [
          "tgn:7095085",
          "tgn:7003669",
          "tgn:1000003",
          "tgn:7000084",
          "tgn:7029392"
        ],
        "placetype": [
          "aat:300008777"
        ],
        "id": 7095085,
        "name:xx": "Schwarzenberg"
      }
    },
    {
      "geometry": {
        "type": "Point",
        "coordinates": [
          12.469167,
          49.254722
        ]
      },
      "type": "Feature",
      "properties": {
        "hierarchy": [
          "tgn:7095086",
          "tgn:7003669",
          "tgn:1000003",
          "tgn:7000084",
          "tgn:7029392"
        ],
        "placetype": [
          "aat:300008777"
        ],
        "id": 7095086,
        "name:xx": "Schwarzenberg"
      }
    },
    {
      "geometry": {
        "type": "Point",
        "coordinates": [
          7.033333,
          49.25
        ]
      },
      "type": "Feature",
      "properties": {
        "hierarchy": [
          "tgn:7095087",
          "tgn:1000003",
          "tgn:7003684",
          "tgn:7000084",
          "tgn:7029392"
        ],
        "placetype": [
          "aat:300008777"
        ],
        "id": 7095087,
        "name:xx": "Schwarzenberg"
      }
    },
    {
      "geometry": {
        "type": "Point",
        "coordinates": [
          8.116667,
          53.35
        ]
      },
      "type": "Feature",
      "properties": {
        "hierarchy": [
          "tgn:7095088",
          "tgn:1000003",
          "tgn:7003676",
          "tgn:7000084",
          "tgn:7029392"
        ],
        "placetype": [
          "aat:300000206"
        ],
        "id": 7095088,
        "name:xx": "Schwarzenberg"
      }
    },
    {
      "geometry": {
        "type": "Point",
        "coordinates": [
          7.9,
          51.216667
        ]
      },
      "type": "Feature",
      "properties": {
        "hierarchy": [
          "tgn:7095089",
          "tgn:1000003",
          "tgn:7003677",
          "tgn:7000084",
          "tgn:7029392"
        ],
        "placetype": [
          "aat:300000206"
        ],
        "id": 7095089,
        "name:xx": "Schwarzenberg"
      }
    }
  ]
}
