{
  "geometry": {
    "type": "Point",
    "coordinates": [
      -81.3167,
      29.8167
    ]
  },
  "type": "Feature",
  "properties": {
    "hierarchy": [
      "tgn:2020441",
      "tgn:1000001",
      "tgn:7012149",
      "tgn:2000283",
      "tgn:7007240",
      "tgn:7029392"
    ],
    "placetype": [
      "aat:300008347",
      "aat:300387210"
    ],
    "id": 2020441,
    "name:xx": "Moultrie"
  }
}
