{
  "type": "FeatureCollection",
  "features": [
    {
      "geometry": {
        "type": "Point",
        "coordinates": [
          -1.3,
          51.6833
        ]
      },
      "type": "Feature",
      "properties": {
        "hierarchy": [
          "tgn:7026460",
          "tgn:7002445",
          "tgn:1000003",
          "tgn:7008168",
          "tgn:7008591",
          "tgn:7029392"
        ],
        "placetype": [
          "aat:300008347",
          "aat:300000874"
        ],
        "id": 7026460,
        "name:xx": "Shippon"
      }
    },
    {
      "geometry": {
        "type": "Point",
        "coordinates": [
          -1.433333,
          51.5
        ]
      },
      "type": "Feature",
      "properties": {
        "hierarchy": [
          "tgn:7026462",
          "tgn:7002445",
          "tgn:1000003",
          "tgn:7026382",
          "tgn:7008591",
          "tgn:7029392"
        ],
        "placetype": [
          "aat:300008347",
          "aat:300008372"
        ],
        "name:en": "South Fawley",
        "id": 7026462
      }
    },
    {
      "geometry": {
        "type": "Point",
        "coordinates": [
          -1.183333,
          51.583333
        ]
      },
      "type": "Feature",
      "properties": {
        "hierarchy": [
          "tgn:7026463",
          "tgn:7002445",
          "tgn:1000003",
          "tgn:7008168",
          "tgn:7008591",
          "tgn:7029392"
        ],
        "placetype": [
          "aat:300008347",
          "aat:300008372"
        ],
        "name:en": "South Moreton",
        "id": 7026463
      }
    },
    {
      "geometry": {
        "type": "Point",
        "coordinates": [
          -1.5,
          51.5833
        ]
      },
      "type": "Feature",
      "properties": {
        "hierarchy": [
          "tgn:7026464",
          "tgn:7002445",
          "tgn:1000003",
          "tgn:7008168",
          "tgn:7008591",
          "tgn:7029392"
        ],
        "placetype": [
          "aat:300008347",
          "aat:300008372"
        ],
        "id": 7026464,
        "name:xx": "Sparsholt"
      }
    },
    {
      "geometry": {
        "type": "Point",
        "coordinates": [
          -1.35,
          51.4
        ]
      },
      "type": "Feature",
      "properties": {
        "hierarchy": [
          "tgn:7026465",
          "tgn:7002445",
          "tgn:1000003",
          "tgn:7026382",
          "tgn:7008591",
          "tgn:7029392"
        ],
        "placetype": [
          "aat:300008347",
          "aat:300008372"
        ],
        "name:en": "Speen",
        "id": 7026465
      }
    },
    {
      "geometry": {
        "type": "Point",
        "coordinates": [
          -1.1667,
          51.4333
        ]
      },
      "type": "Feature",
      "properties": {
        "hierarchy": [
          "tgn:7026466",
          "tgn:7002445",
          "tgn:1000003",
          "tgn:7026382",
          "tgn:7008591",
          "tgn:7029392"
        ],
        "placetype": [
          "aat:300008347",
          "aat:300008372"
        ],
        "id": 7026466,
        "name:xx": "Stanford Dingley"
      }
    },
    {
      "geometry": {
        "type": "Point",
        "coordinates": [
          -1.5,
          51.633333
        ]
      },
      "type": "Feature",
      "properties": {
        "hierarchy": [
          "tgn:7026467",
          "tgn:7002445",
          "tgn:1000003",
          "tgn:7008168",
          "tgn:7008591",
          "tgn:7029392"
        ],
        "placetype": [
          "aat:300008347",
          "aat:300008372"
        ],
        "name:en": "Stanford in the Vale",
        "id": 7026467
      }
    },
    {
      "geometry": {
        "type": "Point",
        "coordinates": [
          -1.05,
          51.3833
        ]
      },
      "type": "Feature",
      "properties": {
        "hierarchy": [
          "tgn:7026468",
          "tgn:7002445",
          "tgn:1000003",
          "tgn:7026382",
          "tgn:7008591",
          "tgn:7029392"
        ],
        "placetype": [
          "aat:300008347",
          "aat:300008372"
        ],
        "id": 7026468,
        "name:xx": "Stratfield Mortimer"
      }
    },
    {
      "geometry": {
        "type": "Point",
        "coordinates": [
          -1.0667,
          51.4667
        ]
      },
      "type": "Feature",
      "properties": {
        "hierarchy": [
          "tgn:7026469",
          "tgn:7002445",
          "tgn:1000003",
          "tgn:7026382",
          "tgn:7008591",
          "tgn:7029392"
        ],
        "placetype": [
          "aat:300008347",
          "aat:300008372"
        ],
        "id": 7026469,
        "name:xx": "Sulham"
      }
    }
  ]
}
