{
  "geometry": {
    "type": "Point",
    "coordinates": [
      -93.1833,
      39.6667
    ]
  },
  "type": "Feature",
  "properties": {
    "hierarchy": [
      "tgn:2726077",
      "tgn:1000001",
      "tgn:2001184",
      "tgn:7012149",
      "tgn:7007523",
      "tgn:7029392"
    ],
    "placetype": [
      "aat:300008699"
    ],
    "id": 2726077,
    "name:xx": "Tough Branch"
  }
}
