{
  "geometry": {
    "type": "Point",
    "coordinates": [
      -112.45,
      41.3667
    ]
  },
  "type": "Feature",
  "properties": {
    "hierarchy": [
      "tgn:2514965",
      "tgn:1000001",
      "tgn:2002102",
      "tgn:7012149",
      "tgn:7007827",
      "tgn:7029392"
    ],
    "placetype": [
      "aat:300008697"
    ],
    "id": 2514965,
    "name:xx": "Miller Spring"
  }
}
