{
  "geometry": {
    "type": "Point",
    "coordinates": [
      -82.2333,
      36.4667
    ]
  },
  "type": "Feature",
  "properties": {
    "hierarchy": [
      "tgn:2099724",
      "tgn:1000001",
      "tgn:7012149",
      "tgn:2001918",
      "tgn:7007825",
      "tgn:7029392"
    ],
    "placetype": [
      "aat:300008347"
    ],
    "id": 2099724,
    "name:xx": "Island Park"
  }
}
