{
  "geometry": {
    "type": "Point",
    "coordinates": [
      -82.4833,
      35.3167
    ]
  },
  "type": "Feature",
  "properties": {
    "hierarchy": [
      "tgn:2752139",
      "tgn:1000001",
      "tgn:7012149",
      "tgn:2001504",
      "tgn:7007709",
      "tgn:7029392"
    ],
    "placetype": [
      "aat:300008706"
    ],
    "id": 2752139,
    "name:xx": "Wash Creek"
  }
}
