{
  "geometry": {
    "type": "Point",
    "coordinates": [
      -122.8833,
      43.4833
    ]
  },
  "type": "Feature",
  "properties": {
    "hierarchy": [
      "tgn:2243545",
      "tgn:1000001",
      "tgn:7012149",
      "tgn:2001706",
      "tgn:7007708",
      "tgn:7029392"
    ],
    "placetype": [
      "aat:300008706"
    ],
    "id": 2243545,
    "name:xx": "Cleft Creek"
  }
}
