{
  "geometry": {
    "type": "Point",
    "coordinates": [
      5.65,
      52.95
    ]
  },
  "type": "Feature",
  "properties": {
    "hierarchy": [
      "tgn:7264376",
      "tgn:7003616",
      "tgn:1000003",
      "tgn:7016845",
      "tgn:7029392"
    ],
    "placetype": [
      "aat:300008347"
    ],
    "name:nl": "Koufurderrige",
    "id": 7264376
  }
}
