{
  "geometry": {
    "type": "Point",
    "coordinates": [
      -95.1333,
      38.7667
    ]
  },
  "type": "Feature",
  "properties": {
    "hierarchy": [
      "tgn:2245722",
      "tgn:1000001",
      "tgn:2000682",
      "tgn:7012149",
      "tgn:7007254",
      "tgn:7029392"
    ],
    "placetype": [
      "aat:300008706"
    ],
    "id": 2245722,
    "name:xx": "Coal Creek"
  }
}
