{
  "type": "FeatureCollection",
  "features": [
    {
      "geometry": {
        "type": "Point",
        "coordinates": [
          -81.8667,
          31.1667
        ]
      },
      "type": "Feature",
      "properties": {
        "hierarchy": [
          "tgn:2290510",
          "tgn:1000001",
          "tgn:2000304",
          "tgn:7012149",
          "tgn:7007248",
          "tgn:7029392"
        ],
        "placetype": [
          "aat:300008680"
        ],
        "id": 2290510,
        "name:xx": "Doe Lake"
      }
    },
    {
      "geometry": {
        "type": "Point",
        "coordinates": [
          -114.5833,
          45.0833
        ]
      },
      "type": "Feature",
      "properties": {
        "hierarchy": [
          "tgn:2290511",
          "tgn:1000001",
          "tgn:7012149",
          "tgn:2000481",
          "tgn:7007250",
          "tgn:7029392"
        ],
        "placetype": [
          "aat:300008680"
        ],
        "id": 2290511,
        "name:xx": "Doe Lake"
      }
    },
    {
      "geometry": {
        "type": "Point",
        "coordinates": [
          -115.0833,
          46
        ]
      },
      "type": "Feature",
      "properties": {
        "hierarchy": [
          "tgn:2290512",
          "tgn:1000001",
          "tgn:7012149",
          "tgn:2000476",
          "tgn:7007250",
          "tgn:7029392"
        ],
        "placetype": [
          "aat:300008680"
        ],
        "id": 2290512,
        "name:xx": "Doe Lake"
      }
    },
    {
      "geometry": {
        "type": "Point",
        "coordinates": [
          -91.2,
          32.9833
        ]
      },
      "type": "Feature",
      "properties": {
        "hierarchy": [
          "tgn:2290513",
          "tgn:1000001",
          "tgn:2000871",
          "tgn:7012149",
          "tgn:7007256",
          "tgn:7029392"
        ],
        "placetype": [
          "aat:300008680"
        ],
        "id": 2290513,
        "name:xx": "Doe Lake"
      }
    },
    {
      "geometry": {
        "type": "Point",
        "coordinates": [
          -84.4833,
          45.2
        ]
      },
      "type": "Feature",
      "properties": {
        "hierarchy": [
          "tgn:2290514",
          "tgn:1000001",
          "tgn:2000951",
          "tgn:7012149",
          "tgn:7007520",
          "tgn:7029392"
        ],
        "placetype": [
          "aat:300008680"
        ],
        "id": 2290514,
        "name:xx": "Doe Lake"
      }
    },
    {
      "geometry": {
        "type": "Point",
        "coordinates": [
          -86.6667,
          46.25
        ]
      },
      "type": "Feature",
      "properties": {
        "hierarchy": [
          "tgn:2290515",
          "tgn:2000943",
          "tgn:1000001",
          "tgn:7012149",
          "tgn:7007520",
          "tgn:7029392"
        ],
        "placetype": [
          "aat:300008680"
        ],
        "id": 2290515,
        "name:xx": "Doe Lake"
      }
    },
    {
      "geometry": {
        "type": "Point",
        "coordinates": [
          -88.9833,
          46.4
        ]
      },
      "type": "Feature",
      "properties": {
        "hierarchy": [
          "tgn:2290516",
          "tgn:1000001",
          "tgn:7012149",
          "tgn:2000966",
          "tgn:7007520",
          "tgn:7029392"
        ],
        "placetype": [
          "aat:300008680"
        ],
        "id": 2290516,
        "name:xx": "Doe Lake"
      }
    },
    {
      "geometry": {
        "type": "Point",
        "coordinates": [
          -94.6,
          46.35
        ]
      },
      "type": "Feature",
      "properties": {
        "hierarchy": [
          "tgn:2290517",
          "tgn:1000001",
          "tgn:2001009",
          "tgn:7012149",
          "tgn:7007521",
          "tgn:7029392"
        ],
        "placetype": [
          "aat:300008680"
        ],
        "id": 2290517,
        "name:xx": "Doe Lake"
      }
    },
    {
      "geometry": {
        "type": "Point",
        "coordinates": [
          -94.6667,
          46.95
        ]
      },
      "type": "Feature",
      "properties": {
        "hierarchy": [
          "tgn:2290518",
          "tgn:1000001",
          "tgn:7012149",
          "tgn:2001027",
          "tgn:7007521",
          "tgn:7029392"
        ],
        "placetype": [
          "aat:300008680"
        ],
        "id": 2290518,
        "name:xx": "Doe Lake"
      }
    },
    {
      "geometry": {
        "type": "Point",
        "coordinates": [
          -93.6333,
          47.5167
        ]
      },
      "type": "Feature",
      "properties": {
        "hierarchy": [
          "tgn:2290519",
          "tgn:1000001",
          "tgn:7012149",
          "tgn:2001029",
          "tgn:7007521",
          "tgn:7029392"
        ],
        "placetype": [
          "aat:300008680"
        ],
        "id": 2290519,
        "name:xx": "Doe Lake"
      }
    }
  ]
}
