{
  "type": "FeatureCollection",
  "features": [
    {
      "geometry": {
        "type": "Point",
        "coordinates": [
          -104.266667,
          25.616667
        ]
      },
      "type": "Feature",
      "properties": {
        "hierarchy": [
          "tgn:7380450",
          "tgn:7005583",
          "tgn:1000001",
          "tgn:7005560",
          "tgn:7029392"
        ],
        "placetype": [
          "aat:300000241"
        ],
        "id": 7380450,
        "name:xx": "Rancho Loma Larga"
      }
    },
    {
      "geometry": {
        "type": "Point",
        "coordinates": [
          -107.95,
          25.133333
        ]
      },
      "type": "Feature",
      "properties": {
        "hierarchy": [
          "tgn:7380451",
          "tgn:1000001",
          "tgn:7005595",
          "tgn:7005560",
          "tgn:7029392"
        ],
        "placetype": [
          "aat:300000241"
        ],
        "id": 7380451,
        "name:xx": "Rancho Loma Larga"
      }
    },
    {
      "geometry": {
        "type": "Point",
        "coordinates": [
          -100.55,
          26.05
        ]
      },
      "type": "Feature",
      "properties": {
        "hierarchy": [
          "tgn:7380452",
          "tgn:1000001",
          "tgn:7005589",
          "tgn:7005560",
          "tgn:7029392"
        ],
        "placetype": [
          "aat:300008811"
        ],
        "id": 7380452,
        "name:xx": "Loma Larga, Mesa"
      }
    },
    {
      "geometry": {
        "type": "Point",
        "coordinates": [
          -99.1,
          26.283333
        ]
      },
      "type": "Feature",
      "properties": {
        "hierarchy": [
          "tgn:7380453",
          "tgn:1000001",
          "tgn:7005597",
          "tgn:7005560",
          "tgn:7029392"
        ],
        "placetype": [
          "aat:300008347"
        ],
        "id": 7380453,
        "name:xx": "Loma Larga"
      }
    },
    {
      "geometry": {
        "type": "Point",
        "coordinates": [
          -106.898333,
          24.056389
        ]
      },
      "type": "Feature",
      "properties": {
        "hierarchy": [
          "tgn:7380454",
          "tgn:1000001",
          "tgn:7005595",
          "tgn:7005560",
          "tgn:7029392"
        ],
        "placetype": [
          "aat:300008347"
        ],
        "id": 7380454,
        "name:xx": "Loma Larga"
      }
    },
    {
      "geometry": {
        "type": "Point",
        "coordinates": [
          -99.566667,
          23.216667
        ]
      },
      "type": "Feature",
      "properties": {
        "hierarchy": [
          "tgn:7380455",
          "tgn:1000001",
          "tgn:7005597",
          "tgn:7005560",
          "tgn:7029392"
        ],
        "placetype": [
          "aat:300008347"
        ],
        "id": 7380455,
        "name:xx": "Loma Larga"
      }
    },
    {
      "geometry": {
        "type": "Point",
        "coordinates": [
          -104.333333,
          19.6
        ]
      },
      "type": "Feature",
      "properties": {
        "hierarchy": [
          "tgn:7380456",
          "tgn:7005586",
          "tgn:1000001",
          "tgn:7005560",
          "tgn:7029392"
        ],
        "placetype": [
          "aat:300008347"
        ],
        "id": 7380456,
        "name:xx": "Loma Larga"
      }
    },
    {
      "geometry": {
        "type": "Point",
        "coordinates": [
          -97.733333,
          17.133333
        ]
      },
      "type": "Feature",
      "properties": {
        "hierarchy": [
          "tgn:7380457",
          "tgn:1000001",
          "tgn:7005591",
          "tgn:7005560",
          "tgn:7029392"
        ],
        "placetype": [
          "aat:300008347"
        ],
        "id": 7380457,
        "name:xx": "Loma Larga"
      }
    },
    {
      "geometry": {
        "type": "Point",
        "coordinates": [
          -95.016667,
          16.766667
        ]
      },
      "type": "Feature",
      "properties": {
        "hierarchy": [
          "tgn:7380458",
          "tgn:1000001",
          "tgn:7005591",
          "tgn:7005560",
          "tgn:7029392"
        ],
        "placetype": [
          "aat:300008347"
        ],
        "id": 7380458,
        "name:xx": "Loma Larga"
      }
    },
    {
      "geometry": {
        "type": "Point",
        "coordinates": [
          -97.233333,
          16.516667
        ]
      },
      "type": "Feature",
      "properties": {
        "hierarchy": [
          "tgn:7380459",
          "tgn:1000001",
          "tgn:7005591",
          "tgn:7005560",
          "tgn:7029392"
        ],
        "placetype": [
          "aat:300008347"
        ],
        "id": 7380459,
        "name:xx": "Loma Larga"
      }
    }
  ]
}
