{
  "geometry": {
    "type": "Point",
    "coordinates": [
      29.766667,
      30.983333
    ]
  },
  "type": "Feature",
  "properties": {
    "hierarchy": [
      "tgn:7537014",
      "tgn:7001242",
      "tgn:7016833",
      "tgn:1001079",
      "tgn:7029392"
    ],
    "placetype": [
      "aat:300006207"
    ],
    "name:en": "Sāniyat al Ḩājj Khalīl",
    "id": 7537014
  }
}
