{
  "geometry": {
    "type": "Point",
    "coordinates": [
      -7.4833,
      11.2333
    ]
  },
  "type": "Feature",
  "properties": {
    "hierarchy": [
      "tgn:1091123",
      "tgn:7001242",
      "tgn:1001750",
      "tgn:1000175",
      "tgn:7029392"
    ],
    "placetype": [
      "aat:300008347"
    ],
    "id": 1091123,
    "name:xx": "Dénié"
  }
}
