{
  "type": "FeatureCollection",
  "features": [
    {
      "geometry": {
        "type": "Point",
        "coordinates": [
          -105.416667,
          25.566667
        ]
      },
      "type": "Feature",
      "properties": {
        "hierarchy": [
          "tgn:7355650",
          "tgn:7005583",
          "tgn:1000001",
          "tgn:7005560",
          "tgn:7029392"
        ],
        "placetype": [
          "aat:300266554",
          "aat:300008699"
        ],
        "id": 7355650,
        "name:xx": "Capulín, Arroyo de"
      }
    },
    {
      "geometry": {
        "type": "Point",
        "coordinates": [
          -109.3,
          29.3
        ]
      },
      "type": "Feature",
      "properties": {
        "hierarchy": [
          "tgn:7355651",
          "tgn:1000001",
          "tgn:1001960",
          "tgn:7005560",
          "tgn:7029392"
        ],
        "placetype": [
          "aat:300008347"
        ],
        "id": 7355651,
        "name:xx": "Capulín"
      }
    },
    {
      "geometry": {
        "type": "Point",
        "coordinates": [
          -106.966667,
          29.116667
        ]
      },
      "type": "Feature",
      "properties": {
        "hierarchy": [
          "tgn:7355652",
          "tgn:7005581",
          "tgn:1000001",
          "tgn:7005560",
          "tgn:7029392"
        ],
        "placetype": [
          "aat:300008347"
        ],
        "id": 7355652,
        "name:xx": "Capulín"
      }
    },
    {
      "geometry": {
        "type": "Point",
        "coordinates": [
          -108.6,
          28.116667
        ]
      },
      "type": "Feature",
      "properties": {
        "hierarchy": [
          "tgn:7355653",
          "tgn:7005581",
          "tgn:1000001",
          "tgn:7005560",
          "tgn:7029392"
        ],
        "placetype": [
          "aat:300008347"
        ],
        "id": 7355653,
        "name:xx": "Capulín"
      }
    },
    {
      "geometry": {
        "type": "Point",
        "coordinates": [
          -107.516667,
          27.833333
        ]
      },
      "type": "Feature",
      "properties": {
        "hierarchy": [
          "tgn:7355654",
          "tgn:7005581",
          "tgn:1000001",
          "tgn:7005560",
          "tgn:7029392"
        ],
        "placetype": [
          "aat:300008347"
        ],
        "id": 7355654,
        "name:xx": "Capulín"
      }
    },
    {
      "geometry": {
        "type": "Point",
        "coordinates": [
          -105.766667,
          25.916667
        ]
      },
      "type": "Feature",
      "properties": {
        "hierarchy": [
          "tgn:7355655",
          "tgn:7005583",
          "tgn:1000001",
          "tgn:7005560",
          "tgn:7029392"
        ],
        "placetype": [
          "aat:300008347"
        ],
        "id": 7355655,
        "name:xx": "Capulín"
      }
    },
    {
      "geometry": {
        "type": "Point",
        "coordinates": [
          -99.65,
          22.583333
        ]
      },
      "type": "Feature",
      "properties": {
        "hierarchy": [
          "tgn:7355656",
          "tgn:1000001",
          "tgn:7005594",
          "tgn:7005560",
          "tgn:7029392"
        ],
        "placetype": [
          "aat:300008347"
        ],
        "id": 7355656,
        "name:xx": "Capulín"
      }
    },
    {
      "geometry": {
        "type": "Point",
        "coordinates": [
          -103.383333,
          22.3
        ]
      },
      "type": "Feature",
      "properties": {
        "hierarchy": [
          "tgn:7355657",
          "tgn:1000001",
          "tgn:7005601",
          "tgn:7005560",
          "tgn:7029392"
        ],
        "placetype": [
          "aat:300008347"
        ],
        "id": 7355657,
        "name:xx": "Capulín"
      }
    },
    {
      "geometry": {
        "type": "Point",
        "coordinates": [
          -102.8,
          22.25
        ]
      },
      "type": "Feature",
      "properties": {
        "hierarchy": [
          "tgn:7355658",
          "tgn:1000001",
          "tgn:7005601",
          "tgn:7005560",
          "tgn:7029392"
        ],
        "placetype": [
          "aat:300008347"
        ],
        "id": 7355658,
        "name:xx": "Capulín"
      }
    },
    {
      "geometry": {
        "type": "Point",
        "coordinates": [
          -99.866667,
          21.566667
        ]
      },
      "type": "Feature",
      "properties": {
        "hierarchy": [
          "tgn:7355659",
          "tgn:1000001",
          "tgn:7005594",
          "tgn:7005560",
          "tgn:7029392"
        ],
        "placetype": [
          "aat:300008347"
        ],
        "id": 7355659,
        "name:xx": "Capulín"
      }
    }
  ]
}
