{
  "geometry": {
    "type": "Point",
    "coordinates": [
      -114.65,
      42.5833
    ]
  },
  "type": "Feature",
  "properties": {
    "hierarchy": [
      "tgn:2025994",
      "tgn:1000001",
      "tgn:7012149",
      "tgn:2000493",
      "tgn:7007250",
      "tgn:7029392"
    ],
    "placetype": [
      "aat:300387016"
    ],
    "id": 2025994,
    "name:xx": "Peavey"
  }
}
