{
  "geometry": {
    "type": "Point",
    "coordinates": [
      -76.4667,
      38.9667
    ]
  },
  "type": "Feature",
  "properties": {
    "hierarchy": [
      "tgn:2708540",
      "tgn:7014651",
      "tgn:1000001",
      "tgn:7012149",
      "tgn:7007516",
      "tgn:7029392"
    ],
    "placetype": [
      "aat:300008850"
    ],
    "id": 2708540,
    "name:xx": "Sycamore Point"
  }
}
