{
  "geometry": {
    "type": "Point",
    "coordinates": [
      -118.0167,
      35.4833
    ]
  },
  "type": "Feature",
  "properties": {
    "hierarchy": [
      "tgn:2454653",
      "tgn:1000001",
      "tgn:7012149",
      "tgn:1002545",
      "tgn:7007157",
      "tgn:7029392"
    ],
    "placetype": [
      "aat:300008699"
    ],
    "id": 2454653,
    "name:xx": "Little Dixie Wash"
  }
}
