{
  "type": "FeatureCollection",
  "features": [
    {
      "geometry": {
        "type": "Point",
        "coordinates": [
          -94.75,
          32.95
        ]
      },
      "type": "Feature",
      "properties": {
        "hierarchy": [
          "tgn:2243150",
          "tgn:1000001",
          "tgn:7012149",
          "tgn:1002696",
          "tgn:7007826",
          "tgn:7029392"
        ],
        "placetype": [
          "aat:300008680"
        ],
        "id": 2243150,
        "name:xx": "Clear Lake"
      }
    },
    {
      "geometry": {
        "type": "Point",
        "coordinates": [
          -95.4833,
          29.5
        ]
      },
      "type": "Feature",
      "properties": {
        "hierarchy": [
          "tgn:2243151",
          "tgn:1000001",
          "tgn:7012149",
          "tgn:1002379",
          "tgn:7007826",
          "tgn:7029392"
        ],
        "placetype": [
          "aat:300008680"
        ],
        "id": 2243151,
        "name:xx": "Clear Lake"
      }
    },
    {
      "geometry": {
        "type": "Point",
        "coordinates": [
          -96.4833,
          33.0667
        ]
      },
      "type": "Feature",
      "properties": {
        "hierarchy": [
          "tgn:2243152",
          "tgn:1000001",
          "tgn:7012149",
          "tgn:1002290",
          "tgn:7007826",
          "tgn:7029392"
        ],
        "placetype": [
          "aat:300008347"
        ],
        "id": 2243152,
        "name:xx": "Clear Lake"
      }
    },
    {
      "geometry": {
        "type": "Point",
        "coordinates": [
          -94.2,
          32.7167
        ]
      },
      "type": "Feature",
      "properties": {
        "hierarchy": [
          "tgn:2243153",
          "tgn:1000001",
          "tgn:7012149",
          "tgn:1002637",
          "tgn:7007826",
          "tgn:7029392"
        ],
        "placetype": [
          "aat:300006191"
        ],
        "id": 2243153,
        "name:xx": "Clear Lake"
      }
    },
    {
      "geometry": {
        "type": "Point",
        "coordinates": [
          -94.0833,
          30.4
        ]
      },
      "type": "Feature",
      "properties": {
        "hierarchy": [
          "tgn:2243154",
          "tgn:1000001",
          "tgn:7012149",
          "tgn:2002009",
          "tgn:7007826",
          "tgn:7029392"
        ],
        "placetype": [
          "aat:300008680"
        ],
        "id": 2243154,
        "name:xx": "Clear Lake"
      }
    },
    {
      "geometry": {
        "type": "Point",
        "coordinates": [
          -96.1833,
          30.7667
        ]
      },
      "type": "Feature",
      "properties": {
        "hierarchy": [
          "tgn:2243155",
          "tgn:1000001",
          "tgn:1002199",
          "tgn:7012149",
          "tgn:7007826",
          "tgn:7029392"
        ],
        "placetype": [
          "aat:300008680"
        ],
        "id": 2243155,
        "name:xx": "Clear Lake"
      }
    },
    {
      "geometry": {
        "type": "Point",
        "coordinates": [
          -94.8167,
          31.15
        ]
      },
      "type": "Feature",
      "properties": {
        "hierarchy": [
          "tgn:2243156",
          "tgn:1002149",
          "tgn:1000001",
          "tgn:7012149",
          "tgn:7007826",
          "tgn:7029392"
        ],
        "placetype": [
          "aat:300008680"
        ],
        "id": 2243156,
        "name:xx": "Clear Lake"
      }
    },
    {
      "geometry": {
        "type": "Point",
        "coordinates": [
          -95.7,
          31.3833
        ]
      },
      "type": "Feature",
      "properties": {
        "hierarchy": [
          "tgn:2243157",
          "tgn:1000001",
          "tgn:7012149",
          "tgn:1002590",
          "tgn:7007826",
          "tgn:7029392"
        ],
        "placetype": [
          "aat:300008680"
        ],
        "id": 2243157,
        "name:xx": "Clear Lake"
      }
    },
    {
      "geometry": {
        "type": "Point",
        "coordinates": [
          -96.4,
          31.45
        ]
      },
      "type": "Feature",
      "properties": {
        "hierarchy": [
          "tgn:2243158",
          "tgn:1000001",
          "tgn:7012149",
          "tgn:1002597",
          "tgn:7007826",
          "tgn:7029392"
        ],
        "placetype": [
          "aat:300008680"
        ],
        "id": 2243158,
        "name:xx": "Clear Lake"
      }
    },
    {
      "geometry": {
        "type": "Point",
        "coordinates": [
          -94.0833,
          32.0167
        ]
      },
      "type": "Feature",
      "properties": {
        "hierarchy": [
          "tgn:2243159",
          "tgn:1000001",
          "tgn:7012149",
          "tgn:1002769",
          "tgn:7007826",
          "tgn:7029392"
        ],
        "placetype": [
          "aat:300008680"
        ],
        "id": 2243159,
        "name:xx": "Clear Lake"
      }
    }
  ]
}
