{
  "geometry": {
    "type": "Point",
    "coordinates": [
      -75.4167,
      41.9167
    ]
  },
  "type": "Feature",
  "properties": {
    "hierarchy": [
      "tgn:2088333",
      "tgn:1000001",
      "tgn:7012149",
      "tgn:1003008",
      "tgn:7007710",
      "tgn:7029392"
    ],
    "placetype": [
      "aat:300008347",
      "aat:300387210"
    ],
    "id": 2088333,
    "name:xx": "Fairmount"
  }
}
