{
  "geometry": {
    "type": "Point",
    "coordinates": [
      30.738254,
      28.70441
    ]
  },
  "type": "Feature",
  "properties": {
    "hierarchy": [
      "tgn:1095244",
      "tgn:7001242",
      "tgn:7016833",
      "tgn:1001088",
      "tgn:7029392"
    ],
    "placetype": [
      "aat:300008347"
    ],
    "name:en": "Al Basqalūn",
    "id": 1095244
  }
}
