{
  "geometry": {
    "type": "Point",
    "coordinates": [
      -68.3667,
      44.3333
    ]
  },
  "type": "Feature",
  "properties": {
    "hierarchy": [
      "tgn:2633276",
      "tgn:1000001",
      "tgn:2000922",
      "tgn:7012149",
      "tgn:7007515",
      "tgn:7029392"
    ],
    "placetype": [
      "aat:300008791"
    ],
    "id": 2633276,
    "name:xx": "Rum Island"
  }
}
