{
  "type": "FeatureCollection",
  "features": [
    {
      "geometry": {
        "type": "Point",
        "coordinates": [
          -1.45,
          52.5
        ]
      },
      "type": "Feature",
      "properties": {
        "hierarchy": [
          "tgn:7464991",
          "tgn:7002445",
          "tgn:1000003",
          "tgn:7008178",
          "tgn:7008591",
          "tgn:7029392"
        ],
        "placetype": [
          "aat:300008347"
        ],
        "name:en": "Attleborough",
        "id": 7464991
      }
    },
    {
      "geometry": {
        "type": "Point",
        "coordinates": [
          -2.666667,
          52.683333
        ]
      },
      "type": "Feature",
      "properties": {
        "hierarchy": [
          "tgn:7464992",
          "tgn:7002445",
          "tgn:1000003",
          "tgn:7012034",
          "tgn:7008591",
          "tgn:7029392"
        ],
        "placetype": [
          "aat:300387502"
        ],
        "name:en": "Attingham",
        "id": 7464992
      }
    },
    {
      "geometry": {
        "type": "Point",
        "coordinates": [
          -1.233333,
          52.883333
        ]
      },
      "type": "Feature",
      "properties": {
        "hierarchy": [
          "tgn:7464994",
          "tgn:7002445",
          "tgn:1000003",
          "tgn:7008167",
          "tgn:7008591",
          "tgn:7029392"
        ],
        "placetype": [
          "aat:300008347"
        ],
        "name:en": "Attenborough",
        "id": 7464994
      }
    },
    {
      "geometry": {
        "type": "Point",
        "coordinates": [
          -5.466667,
          57.383333
        ]
      },
      "type": "Feature",
      "properties": {
        "hierarchy": [
          "tgn:7464995",
          "tgn:7002444",
          "tgn:1000003",
          "tgn:7008082",
          "tgn:7008591",
          "tgn:7029392"
        ],
        "placetype": [
          "aat:300387502"
        ],
        "name:en": "Attadale House",
        "id": 7464995
      }
    },
    {
      "geometry": {
        "type": "Point",
        "coordinates": [
          -5.466667,
          57.4
        ]
      },
      "type": "Feature",
      "properties": {
        "hierarchy": [
          "tgn:7464996",
          "tgn:7002444",
          "tgn:1000003",
          "tgn:7008082",
          "tgn:7008591",
          "tgn:7029392"
        ],
        "placetype": [
          "aat:300008699"
        ],
        "name:en": "Attadale, River",
        "id": 7464996
      }
    },
    {
      "geometry": {
        "type": "Point",
        "coordinates": [
          -1.65,
          53.033333
        ]
      },
      "type": "Feature",
      "properties": {
        "hierarchy": [
          "tgn:7464997",
          "tgn:7002445",
          "tgn:1000003",
          "tgn:7008118",
          "tgn:7008591",
          "tgn:7029392"
        ],
        "placetype": [
          "aat:300008347"
        ],
        "name:en": "Atlow",
        "id": 7464997
      }
    }
  ]
}
