{
  "geometry": {
    "type": "Point",
    "coordinates": [
      35.23271,
      24.395771
    ]
  },
  "type": "Feature",
  "properties": {
    "hierarchy": [
      "tgn:7537780",
      "tgn:7001242",
      "tgn:7001311",
      "tgn:7016833",
      "tgn:7029392"
    ],
    "placetype": [
      "aat:300379998"
    ],
    "name:en": "Ranga, Wâdi",
    "id": 7537780
  }
}
