{
  "geometry": {
    "type": "Point",
    "coordinates": [
      31.246121,
      30.064325
    ]
  },
  "type": "Feature",
  "properties": {
    "hierarchy": [
      "tgn:7531907",
      "tgn:7001242",
      "tgn:7016833",
      "tgn:1001091",
      "tgn:7029392"
    ],
    "placetype": [
      "aat:300007466"
    ],
    "id": 7531907,
    "name:xx": "Kanīsat Mārmīnā al 'Ajāybī"
  }
}
