{
  "geometry": {
    "type": "Point",
    "coordinates": [
      -91.8833,
      34.45
    ]
  },
  "type": "Feature",
  "properties": {
    "hierarchy": [
      "tgn:2299819",
      "tgn:1000001",
      "tgn:7016172",
      "tgn:7012149",
      "tgn:2000139",
      "tgn:7029392"
    ],
    "placetype": [
      "aat:300008680"
    ],
    "id": 2299819,
    "name:xx": "Dudley Lake"
  }
}
