{
  "geometry": {
    "type": "Point",
    "coordinates": [
      -86.2333,
      37.2833
    ]
  },
  "type": "Feature",
  "properties": {
    "hierarchy": [
      "tgn:2040568",
      "tgn:1000001",
      "tgn:7012149",
      "tgn:2000787",
      "tgn:7007255",
      "tgn:7029392"
    ],
    "placetype": [
      "aat:300008347",
      "aat:300387210"
    ],
    "id": 2040568,
    "name:xx": "Oak Ridge"
  }
}
