{
  "type": "FeatureCollection",
  "features": [
    {
      "geometry": {
        "type": "Point",
        "coordinates": [
          -75.2833,
          40.2333
        ]
      },
      "type": "Feature",
      "properties": {
        "hierarchy": [
          "tgn:2089960",
          "tgn:1000001",
          "tgn:7012149",
          "tgn:1002690",
          "tgn:7007710",
          "tgn:7029392"
        ],
        "placetype": [
          "aat:300008347"
        ],
        "id": 2089960,
        "name:xx": "Lansdale"
      }
    },
    {
      "geometry": {
        "type": "Point",
        "coordinates": [
          -75.2667,
          39.9333
        ]
      },
      "type": "Feature",
      "properties": {
        "hierarchy": [
          "tgn:2089963",
          "tgn:1000001",
          "tgn:1002330",
          "tgn:7012149",
          "tgn:7007710",
          "tgn:7029392"
        ],
        "placetype": [
          "aat:300008347"
        ],
        "id": 2089963,
        "name:xx": "Lansdowne"
      }
    },
    {
      "geometry": {
        "type": "Point",
        "coordinates": [
          -78.1167,
          40.9667
        ]
      },
      "type": "Feature",
      "properties": {
        "hierarchy": [
          "tgn:2089966",
          "tgn:1000001",
          "tgn:1002278",
          "tgn:7012149",
          "tgn:7007710",
          "tgn:7029392"
        ],
        "placetype": [
          "aat:300008347"
        ],
        "id": 2089966,
        "name:xx": "Lanse"
      }
    },
    {
      "geometry": {
        "type": "Point",
        "coordinates": [
          -75.8667,
          40.8167
        ]
      },
      "type": "Feature",
      "properties": {
        "hierarchy": [
          "tgn:2089969",
          "tgn:1000001",
          "tgn:1002233",
          "tgn:7012149",
          "tgn:7007710",
          "tgn:7029392"
        ],
        "placetype": [
          "aat:300008347"
        ],
        "id": 2089969,
        "name:xx": "Lansford"
      }
    }
  ]
}
