{
  "geometry": {
    "type": "Point",
    "coordinates": [
      34.072857,
      22.498143
    ]
  },
  "type": "Feature",
  "properties": {
    "hierarchy": [
      "tgn:7521452",
      "tgn:7001242",
      "tgn:7001311",
      "tgn:7016833",
      "tgn:7029392"
    ],
    "placetype": [
      "aat:300379998"
    ],
    "name:en": "Abū Ḩād, Wādī",
    "id": 7521452
  }
}
