{
  "geometry": {
    "type": "Point",
    "coordinates": [
      -106.4167,
      32.0167
    ]
  },
  "type": "Feature",
  "properties": {
    "hierarchy": [
      "tgn:2604125",
      "tgn:1000001",
      "tgn:2001435",
      "tgn:7012149",
      "tgn:7007566",
      "tgn:7029392"
    ],
    "placetype": [
      "aat:300008680"
    ],
    "id": 2604125,
    "name:xx": "Quirke Lake"
  }
}
