{
  "geometry": {
    "type": "Point",
    "coordinates": [
      -103.75,
      44.3833
    ]
  },
  "type": "Feature",
  "properties": {
    "hierarchy": [
      "tgn:2591387",
      "tgn:1000001",
      "tgn:2001810",
      "tgn:7012149",
      "tgn:7007713",
      "tgn:7029392"
    ],
    "placetype": [
      "aat:300008706"
    ],
    "id": 2591387,
    "name:xx": "Polo Creek"
  }
}
