{
  "geometry": {
    "type": "Point",
    "coordinates": [
      -119.3333,
      44.1333
    ]
  },
  "type": "Feature",
  "properties": {
    "hierarchy": [
      "tgn:2696899",
      "tgn:1000001",
      "tgn:7012149",
      "tgn:2001708",
      "tgn:7007708",
      "tgn:7029392"
    ],
    "placetype": [
      "aat:300008706"
    ],
    "id": 2696899,
    "name:xx": "Stonewall Creek"
  }
}
