{
  "geometry": {
    "type": "Point",
    "coordinates": [
      -103.3333,
      43.8667
    ]
  },
  "type": "Feature",
  "properties": {
    "hierarchy": [
      "tgn:2382608",
      "tgn:1000001",
      "tgn:7012149",
      "tgn:2001821",
      "tgn:7007713",
      "tgn:7029392"
    ],
    "placetype": [
      "aat:300008347"
    ],
    "id": 2382608,
    "name:xx": "Hayward"
  }
}
