{
  "type": "FeatureCollection",
  "features": [
    {
      "geometry": {
        "type": "Point",
        "coordinates": [
          -81.3,
          41.4
        ]
      },
      "type": "Feature",
      "properties": {
        "hierarchy": [
          "tgn:2500930",
          "tgn:1000001",
          "tgn:7012149",
          "tgn:7021516",
          "tgn:7007706",
          "tgn:7029392"
        ],
        "placetype": [
          "aat:300008706"
        ],
        "id": 2500930,
        "name:xx": "McFarland Creek"
      }
    },
    {
      "geometry": {
        "type": "Point",
        "coordinates": [
          -96.4833,
          29.0833
        ]
      },
      "type": "Feature",
      "properties": {
        "hierarchy": [
          "tgn:2500931",
          "tgn:1000001",
          "tgn:7012149",
          "tgn:1002510",
          "tgn:7007826",
          "tgn:7029392"
        ],
        "placetype": [
          "aat:300008706"
        ],
        "id": 2500931,
        "name:xx": "McFarland Creek"
      }
    },
    {
      "geometry": {
        "type": "Point",
        "coordinates": [
          -101.55,
          34.9
        ]
      },
      "type": "Feature",
      "properties": {
        "hierarchy": [
          "tgn:2500932",
          "tgn:2001935",
          "tgn:1000001",
          "tgn:7012149",
          "tgn:7007826",
          "tgn:7029392"
        ],
        "placetype": [
          "aat:300008706"
        ],
        "id": 2500932,
        "name:xx": "McFarland Creek"
      }
    },
    {
      "geometry": {
        "type": "Point",
        "coordinates": [
          -120.15,
          48.0667
        ]
      },
      "type": "Feature",
      "properties": {
        "hierarchy": [
          "tgn:2500933",
          "tgn:1000001",
          "tgn:7012149",
          "tgn:7007920",
          "tgn:7029392"
        ],
        "placetype": [
          "aat:300008706"
        ],
        "id": 2500933,
        "name:xx": "McFarland Creek"
      }
    },
    {
      "geometry": {
        "type": "Point",
        "coordinates": [
          -87.05,
          40.4833
        ]
      },
      "type": "Feature",
      "properties": {
        "hierarchy": [
          "tgn:2500934",
          "tgn:1000001",
          "tgn:7012149",
          "tgn:1002946",
          "tgn:7007252",
          "tgn:7029392"
        ],
        "placetype": [
          "aat:300006075"
        ],
        "id": 2500934,
        "name:xx": "McFarland Ditch"
      }
    },
    {
      "geometry": {
        "type": "Point",
        "coordinates": [
          -87.4667,
          39.3333
        ]
      },
      "type": "Feature",
      "properties": {
        "hierarchy": [
          "tgn:2500935",
          "tgn:1000001",
          "tgn:7012149",
          "tgn:2000559",
          "tgn:7007252",
          "tgn:7029392"
        ],
        "placetype": [
          "aat:300006075"
        ],
        "id": 2500935,
        "name:xx": "McFarland Ditch"
      }
    },
    {
      "geometry": {
        "type": "Point",
        "coordinates": [
          -87.05,
          40.0167
        ]
      },
      "type": "Feature",
      "properties": {
        "hierarchy": [
          "tgn:2500936",
          "tgn:1000001",
          "tgn:7012149",
          "tgn:2000547",
          "tgn:7007252",
          "tgn:7029392"
        ],
        "placetype": [
          "aat:300006075"
        ],
        "id": 2500936,
        "name:xx": "McFarland Ditch"
      }
    },
    {
      "geometry": {
        "type": "Point",
        "coordinates": [
          -111,
          41.8667
        ]
      },
      "type": "Feature",
      "properties": {
        "hierarchy": [
          "tgn:2500937",
          "tgn:1000001",
          "tgn:7012149",
          "tgn:2002376",
          "tgn:7007923",
          "tgn:7029392"
        ],
        "placetype": [
          "aat:300006075"
        ],
        "id": 2500937,
        "name:xx": "McFarland Ditch"
      }
    },
    {
      "geometry": {
        "type": "Point",
        "coordinates": [
          -104.5667,
          44.4667
        ]
      },
      "type": "Feature",
      "properties": {
        "hierarchy": [
          "tgn:2500938",
          "tgn:1000001",
          "tgn:2002370",
          "tgn:7012149",
          "tgn:7007923",
          "tgn:7029392"
        ],
        "placetype": [
          "aat:300266640"
        ],
        "id": 2500938,
        "name:xx": "McFarland Divide"
      }
    },
    {
      "geometry": {
        "type": "Point",
        "coordinates": [
          -123.6667,
          41.2167
        ]
      },
      "type": "Feature",
      "properties": {
        "hierarchy": [
          "tgn:2500939",
          "tgn:1000001",
          "tgn:7012149",
          "tgn:2000181",
          "tgn:7007157",
          "tgn:7029392"
        ],
        "placetype": [
          "aat:300008761"
        ],
        "id": 2500939,
        "name:xx": "McFarland Gulch"
      }
    }
  ]
}
