{
  "type": "FeatureCollection",
  "features": [
    {
      "geometry": {
        "type": "Point",
        "coordinates": [
          -100.4,
          17.933333
        ]
      },
      "type": "Feature",
      "properties": {
        "hierarchy": [
          "tgn:7394370",
          "tgn:7005585",
          "tgn:1000001",
          "tgn:7005560",
          "tgn:7029392"
        ],
        "placetype": [
          "aat:300008347"
        ],
        "id": 7394370,
        "name:xx": "San Gregorio"
      }
    },
    {
      "geometry": {
        "type": "Point",
        "coordinates": [
          -101.683333,
          27.3
        ]
      },
      "type": "Feature",
      "properties": {
        "hierarchy": [
          "tgn:7394371",
          "tgn:1001853",
          "tgn:1000001",
          "tgn:7005560",
          "tgn:7029392"
        ],
        "placetype": [
          "aat:300008347"
        ],
        "id": 7394371,
        "name:xx": "San Lorenzo"
      }
    },
    {
      "geometry": {
        "type": "Point",
        "coordinates": [
          -113.75,
          27.1
        ]
      },
      "type": "Feature",
      "properties": {
        "hierarchy": [
          "tgn:7394372",
          "tgn:1001836",
          "tgn:1000001",
          "tgn:7005560",
          "tgn:7029392"
        ],
        "placetype": [
          "aat:300008347"
        ],
        "id": 7394372,
        "name:xx": "San Lorenzo"
      }
    },
    {
      "geometry": {
        "type": "Point",
        "coordinates": [
          -105.333333,
          26.983333
        ]
      },
      "type": "Feature",
      "properties": {
        "hierarchy": [
          "tgn:7394373",
          "tgn:7005581",
          "tgn:1000001",
          "tgn:7005560",
          "tgn:7029392"
        ],
        "placetype": [
          "aat:300008347"
        ],
        "id": 7394373,
        "name:xx": "San Lorenzo"
      }
    },
    {
      "geometry": {
        "type": "Point",
        "coordinates": [
          -99.066667,
          26.4
        ]
      },
      "type": "Feature",
      "properties": {
        "hierarchy": [
          "tgn:7394374",
          "tgn:1000001",
          "tgn:7005597",
          "tgn:7005560",
          "tgn:7029392"
        ],
        "placetype": [
          "aat:300008347"
        ],
        "id": 7394374,
        "name:xx": "San Lorenzo"
      }
    },
    {
      "geometry": {
        "type": "Point",
        "coordinates": [
          -103.183333,
          25.716667
        ]
      },
      "type": "Feature",
      "properties": {
        "hierarchy": [
          "tgn:7394375",
          "tgn:1001853",
          "tgn:1000001",
          "tgn:7005560",
          "tgn:7029392"
        ],
        "placetype": [
          "aat:300008347"
        ],
        "id": 7394375,
        "name:xx": "San Lorenzo"
      }
    },
    {
      "geometry": {
        "type": "Point",
        "coordinates": [
          -108.066667,
          25.683333
        ]
      },
      "type": "Feature",
      "properties": {
        "hierarchy": [
          "tgn:7394376",
          "tgn:7005583",
          "tgn:1000001",
          "tgn:7005560",
          "tgn:7029392"
        ],
        "placetype": [
          "aat:300008347"
        ],
        "id": 7394376,
        "name:xx": "San Lorenzo"
      }
    },
    {
      "geometry": {
        "type": "Point",
        "coordinates": [
          -102.3,
          25.5
        ]
      },
      "type": "Feature",
      "properties": {
        "hierarchy": [
          "tgn:7394379",
          "tgn:1001853",
          "tgn:1000001",
          "tgn:7005560",
          "tgn:7029392"
        ],
        "placetype": [
          "aat:300008347"
        ],
        "id": 7394379,
        "name:xx": "San Lorenzo"
      }
    }
  ]
}
