{
  "geometry": {
    "type": "Point",
    "coordinates": [
      -78.0333,
      38.3333
    ]
  },
  "type": "Feature",
  "properties": {
    "hierarchy": [
      "tgn:2110854",
      "tgn:1000001",
      "tgn:7012149",
      "tgn:2002155",
      "tgn:7007919",
      "tgn:7029392"
    ],
    "placetype": [
      "aat:300008347",
      "aat:300387210"
    ],
    "id": 2110854,
    "name:xx": "Buena"
  }
}
