{
  "type": "FeatureCollection",
  "features": [
    {
      "geometry": {
        "type": "Point",
        "coordinates": [
          -90.5,
          37.8333
        ]
      },
      "type": "Feature",
      "properties": {
        "hierarchy": [
          "tgn:2058750",
          "tgn:1000001",
          "tgn:7012149",
          "tgn:2001241",
          "tgn:7007523",
          "tgn:7029392"
        ],
        "placetype": [
          "aat:300008347",
          "aat:300387210"
        ],
        "id": 2058750,
        "name:xx": "Federal"
      }
    },
    {
      "geometry": {
        "type": "Point",
        "coordinates": [
          -90.9333,
          38.6333
        ]
      },
      "type": "Feature",
      "properties": {
        "hierarchy": [
          "tgn:2058752",
          "tgn:1000001",
          "tgn:7012149",
          "tgn:7016166",
          "tgn:7007523",
          "tgn:7029392"
        ],
        "placetype": [
          "aat:300008347",
          "aat:300387210"
        ],
        "id": 2058752,
        "name:xx": "Femme Osage"
      }
    },
    {
      "geometry": {
        "type": "Point",
        "coordinates": [
          -90.4333,
          38.5
        ]
      },
      "type": "Feature",
      "properties": {
        "hierarchy": [
          "tgn:2058753",
          "tgn:1000001",
          "tgn:7012149",
          "tgn:7016167",
          "tgn:7007523",
          "tgn:7029392"
        ],
        "placetype": [
          "aat:300008347"
        ],
        "id": 2058753,
        "name:xx": "Fenton"
      }
    },
    {
      "geometry": {
        "type": "Point",
        "coordinates": [
          -90.3,
          38.7333
        ]
      },
      "type": "Feature",
      "properties": {
        "hierarchy": [
          "tgn:2058755",
          "tgn:1000001",
          "tgn:7012149",
          "tgn:7016167",
          "tgn:7007523",
          "tgn:7029392"
        ],
        "placetype": [
          "aat:300008347"
        ],
        "id": 2058755,
        "name:xx": "Ferguson"
      }
    }
  ]
}
