{
  "geometry": {
    "type": "Point",
    "coordinates": [
      -104.9833,
      31.35
    ]
  },
  "type": "Feature",
  "properties": {
    "hierarchy": [
      "tgn:2229892",
      "tgn:1000001",
      "tgn:7012149",
      "tgn:2002005",
      "tgn:7007826",
      "tgn:7029392"
    ],
    "placetype": [
      "aat:300006191"
    ],
    "id": 2229892,
    "name:xx": "Cedar Tank"
  }
}
