{
  "geometry": {
    "type": "Point",
    "coordinates": [
      121.8057,
      24.7358
    ]
  },
  "type": "Feature",
  "properties": {
    "hierarchy": [
      "tgn:7478386",
      "tgn:1000004",
      "tgn:7489179",
      "tgn:1000141",
      "tgn:7029392"
    ],
    "placetype": [
      "aat:300007836"
    ],
    "id": 7478386,
    "name:xx": "Zhuangwei Daqiao"
  }
}
