{
  "geometry": {
    "type": "Point",
    "coordinates": [
      -82.6667,
      33.05
    ]
  },
  "type": "Feature",
  "properties": {
    "hierarchy": [
      "tgn:2294453",
      "tgn:1000001",
      "tgn:7012149",
      "tgn:2000441",
      "tgn:7007248",
      "tgn:7029392"
    ],
    "placetype": [
      "aat:300008347"
    ],
    "id": 2294453,
    "name:xx": "Downs"
  }
}
