{
  "geometry": {
    "type": "Point",
    "coordinates": [
      -71.65,
      42.5333
    ]
  },
  "type": "Feature",
  "properties": {
    "hierarchy": [
      "tgn:2189487",
      "tgn:1000001",
      "tgn:1002665",
      "tgn:7012149",
      "tgn:7007517",
      "tgn:7029392"
    ],
    "placetype": [
      "aat:300006191"
    ],
    "id": 2189487,
    "name:xx": "Bow Brook Reservoir"
  }
}
