{
  "geometry": {
    "type": "Point",
    "coordinates": [
      64.7833,
      54.3833
    ]
  },
  "type": "Feature",
  "properties": {
    "hierarchy": [
      "tgn:1061678",
      "tgn:1000004",
      "tgn:6003227",
      "tgn:7018214",
      "tgn:7002435",
      "tgn:7029392"
    ],
    "placetype": [
      "aat:300008347"
    ],
    "id": 1061678,
    "name:xx": "Zverinogolovskoye"
  }
}
