{
  "geometry": {
    "type": "Point",
    "coordinates": [
      74.441216,
      25.53885
    ]
  },
  "type": "Feature",
  "properties": {
    "hierarchy": [
      "tgn:7547824",
      "tgn:1000004",
      "tgn:7000198",
      "tgn:7016788",
      "tgn:7029392"
    ],
    "placetype": [
      "aat:300008347"
    ],
    "name:en": "Bhagwānpur",
    "id": 7547824
  }
}
