{
  "type": "FeatureCollection",
  "features": [
    {
      "geometry": {
        "type": "Point",
        "coordinates": [
          19.75,
          52.5
        ]
      },
      "type": "Feature",
      "properties": {
        "hierarchy": [
          "tgn:1002030",
          "tgn:1000003",
          "tgn:7006366",
          "tgn:7029392"
        ],
        "placetype": [
          "aat:300387179",
          "aat:300235112"
        ],
        "id": 1002030,
        "name:xx": "Płock"
      }
    },
    {
      "geometry": {
        "type": "Point",
        "coordinates": [
          16.75,
          53.25
        ]
      },
      "type": "Feature",
      "properties": {
        "hierarchy": [
          "tgn:1002031",
          "tgn:1000003",
          "tgn:7006366",
          "tgn:7029392"
        ],
        "placetype": [
          "aat:300387179",
          "aat:300235112"
        ],
        "id": 1002031,
        "name:xx": "Piła"
      }
    },
    {
      "geometry": {
        "type": "Point",
        "coordinates": [
          19.75,
          51.5
        ]
      },
      "type": "Feature",
      "properties": {
        "hierarchy": [
          "tgn:1002032",
          "tgn:1000003",
          "tgn:7006366",
          "tgn:7029392"
        ],
        "placetype": [
          "aat:300387179",
          "aat:300235112"
        ],
        "id": 1002032,
        "name:xx": "Piotrków"
      }
    },
    {
      "geometry": {
        "type": "Point",
        "coordinates": [
          17,
          52.5
        ]
      },
      "type": "Feature",
      "properties": {
        "hierarchy": [
          "tgn:1002033",
          "tgn:1000003",
          "tgn:7006366",
          "tgn:7029392"
        ],
        "placetype": [
          "aat:300387179",
          "aat:300235112"
        ],
        "id": 1002033,
        "name:xx": "Poznań"
      }
    },
    {
      "geometry": {
        "type": "Point",
        "coordinates": [
          21,
          51.5
        ]
      },
      "type": "Feature",
      "properties": {
        "hierarchy": [
          "tgn:1002035",
          "tgn:1000003",
          "tgn:7006366",
          "tgn:7029392"
        ],
        "placetype": [
          "aat:300387179",
          "aat:300235112"
        ],
        "id": 1002035,
        "name:xx": "Radom"
      }
    }
  ]
}
