{
  "geometry": {
    "type": "Point",
    "coordinates": [
      -110.0167,
      35.8833
    ]
  },
  "type": "Feature",
  "properties": {
    "hierarchy": [
      "tgn:2730725",
      "tgn:1000001",
      "tgn:7006451",
      "tgn:7012149",
      "tgn:2000099",
      "tgn:7029392"
    ],
    "placetype": [
      "aat:300008699"
    ],
    "id": 2730725,
    "name:xx": "Tse Chizzi Wash"
  }
}
