{
  "geometry": {
    "type": "Point",
    "coordinates": [
      -133.8833,
      56.9333
    ]
  },
  "type": "Feature",
  "properties": {
    "hierarchy": [
      "tgn:2593992",
      "tgn:7006450",
      "tgn:1000001",
      "tgn:7012149",
      "tgn:2000088",
      "tgn:7029392"
    ],
    "placetype": [
      "aat:300132316"
    ],
    "id": 2593992,
    "name:xx": "Portage Bay"
  }
}
