{
  "geometry": {
    "type": "Point",
    "coordinates": [
      30.888568,
      29.512419
    ]
  },
  "type": "Feature",
  "properties": {
    "hierarchy": [
      "tgn:7541113",
      "tgn:7001242",
      "tgn:7001105",
      "tgn:7016833",
      "tgn:7029392"
    ],
    "placetype": [
      "aat:300008347"
    ],
    "name:en": "Kafr al Masallāt",
    "id": 7541113
  }
}
