{
  "geometry": {
    "type": "Point",
    "coordinates": [
      -111.0667,
      33.9167
    ]
  },
  "type": "Feature",
  "properties": {
    "hierarchy": [
      "tgn:2202706",
      "tgn:1000001",
      "tgn:7006451",
      "tgn:2000093",
      "tgn:7012149",
      "tgn:7029392"
    ],
    "placetype": [
      "aat:300006191"
    ],
    "id": 2202706,
    "name:xx": "Buckaroo Tank"
  }
}
