{
  "type": "FeatureCollection",
  "features": [
    {
      "geometry": {
        "type": "Point",
        "coordinates": [
          6.616667,
          52.7
        ]
      },
      "type": "Feature",
      "properties": {
        "hierarchy": [
          "tgn:7267670",
          "tgn:7003614",
          "tgn:1000003",
          "tgn:7016845",
          "tgn:7029392"
        ],
        "placetype": [
          "aat:300008347"
        ],
        "name:nl": "Nieuwlande",
        "id": 7267670
      }
    },
    {
      "geometry": {
        "type": "Point",
        "coordinates": [
          4.1,
          51.45
        ]
      },
      "type": "Feature",
      "properties": {
        "hierarchy": [
          "tgn:7267671",
          "tgn:1000003",
          "tgn:7003635",
          "tgn:7016845",
          "tgn:7029392"
        ],
        "placetype": [
          "aat:300132350"
        ],
        "name:nl": "Nieuwlande",
        "id": 7267671
      }
    },
    {
      "geometry": {
        "type": "Point",
        "coordinates": [
          4.516667,
          51.633333
        ]
      },
      "type": "Feature",
      "properties": {
        "hierarchy": [
          "tgn:7267672",
          "tgn:1000003",
          "tgn:7003624",
          "tgn:7016845",
          "tgn:7029392"
        ],
        "placetype": [
          "aat:300006163"
        ],
        "name:nl": "Nieuwland, Polder het",
        "id": 7267672
      }
    },
    {
      "geometry": {
        "type": "Point",
        "coordinates": [
          6.15,
          53.333333
        ]
      },
      "type": "Feature",
      "properties": {
        "hierarchy": [
          "tgn:7267674",
          "tgn:7003616",
          "tgn:1000003",
          "tgn:7016845",
          "tgn:7029392"
        ],
        "placetype": [
          "aat:300008347"
        ],
        "name:nl": "Nieuwland",
        "id": 7267674
      }
    },
    {
      "geometry": {
        "type": "Point",
        "coordinates": [
          5.383333,
          52.2
        ]
      },
      "type": "Feature",
      "properties": {
        "hierarchy": [
          "tgn:7267675",
          "tgn:1000003",
          "tgn:7003627",
          "tgn:7016845",
          "tgn:7029392"
        ],
        "placetype": [
          "aat:300008347"
        ],
        "name:nl": "Nieuwland",
        "id": 7267675
      }
    },
    {
      "geometry": {
        "type": "Point",
        "coordinates": [
          5.016667,
          51.9
        ]
      },
      "type": "Feature",
      "properties": {
        "hierarchy": [
          "tgn:7267676",
          "tgn:1000003",
          "tgn:7003632",
          "tgn:7016845",
          "tgn:7029392"
        ],
        "placetype": [
          "aat:300008347"
        ],
        "name:nl": "Nieuwland",
        "id": 7267676
      }
    },
    {
      "geometry": {
        "type": "Point",
        "coordinates": [
          3.65,
          51.483333
        ]
      },
      "type": "Feature",
      "properties": {
        "hierarchy": [
          "tgn:7267677",
          "tgn:1000003",
          "tgn:7003635",
          "tgn:7016845",
          "tgn:7029392"
        ],
        "placetype": [
          "aat:300008347"
        ],
        "name:nl": "Nieuwland",
        "id": 7267677
      }
    },
    {
      "geometry": {
        "type": "Point",
        "coordinates": [
          3.65,
          51.333333
        ]
      },
      "type": "Feature",
      "properties": {
        "hierarchy": [
          "tgn:7267678",
          "tgn:1000003",
          "tgn:7003635",
          "tgn:7016845",
          "tgn:7029392"
        ],
        "placetype": [
          "aat:300008347"
        ],
        "name:nl": "Nieuwland",
        "id": 7267678
      }
    },
    {
      "geometry": {
        "type": "Point",
        "coordinates": [
          6.266667,
          52.883333
        ]
      },
      "type": "Feature",
      "properties": {
        "hierarchy": [
          "tgn:7267679",
          "tgn:7003614",
          "tgn:1000003",
          "tgn:7016845",
          "tgn:7029392"
        ],
        "placetype": [
          "aat:300000206"
        ],
        "name:nl": "Rijkmanshoeve",
        "id": 7267679
      }
    }
  ]
}
