{
  "geometry": {
    "type": "Point",
    "coordinates": [
      -80.15,
      33.05
    ]
  },
  "type": "Feature",
  "properties": {
    "hierarchy": [
      "tgn:2690966",
      "tgn:1000001",
      "tgn:7012149",
      "tgn:7007712",
      "tgn:7029392"
    ],
    "placetype": [
      "aat:300008699"
    ],
    "id": 2690966,
    "name:xx": "Stanley Branch"
  }
}
