{
  "geometry": {
    "type": "Point",
    "coordinates": [
      109.7333,
      18.7667
    ]
  },
  "type": "Feature",
  "properties": {
    "hierarchy": [
      "tgn:1066785",
      "tgn:1000004",
      "tgn:7001800",
      "tgn:1000111",
      "tgn:7029392"
    ],
    "placetype": [
      "aat:300008347"
    ],
    "id": 1066785,
    "name:xx": "Baoting"
  }
}
