{
  "geometry": {
    "type": "Point",
    "coordinates": [
      -99.1667,
      26.9667
    ]
  },
  "type": "Feature",
  "properties": {
    "hierarchy": [
      "tgn:2397233",
      "tgn:1000001",
      "tgn:7012149",
      "tgn:2002099",
      "tgn:7007826",
      "tgn:7029392"
    ],
    "placetype": [
      "aat:300006191"
    ],
    "id": 2397233,
    "name:xx": "Hondo Tank"
  }
}
