{
  "geometry": {
    "type": "Point",
    "coordinates": [
      -91.3667,
      38.0167
    ]
  },
  "type": "Feature",
  "properties": {
    "hierarchy": [
      "tgn:2313353",
      "tgn:1000001",
      "tgn:7012149",
      "tgn:2001190",
      "tgn:7007523",
      "tgn:7029392"
    ],
    "placetype": [
      "aat:300006191"
    ],
    "id": 2313353,
    "name:xx": "Elders Lake"
  }
}
