{
  "geometry": {
    "type": "Point",
    "coordinates": [
      77.15,
      9.816667
    ]
  },
  "type": "Feature",
  "properties": {
    "hierarchy": [
      "tgn:7571061",
      "tgn:1000004",
      "tgn:7000198",
      "tgn:1001886",
      "tgn:7029392"
    ],
    "placetype": [
      "aat:300008347"
    ],
    "name:en": "Kallār",
    "id": 7571061
  }
}
