{
  "geometry": {
    "type": "Point",
    "coordinates": [
      -94.6333,
      37.4833
    ]
  },
  "type": "Feature",
  "properties": {
    "hierarchy": [
      "tgn:2037409",
      "tgn:1000001",
      "tgn:2000678",
      "tgn:7012149",
      "tgn:7007254",
      "tgn:7029392"
    ],
    "placetype": [
      "aat:300008347"
    ],
    "id": 2037409,
    "name:xx": "Yale"
  }
}
