{
  "type": "FeatureCollection",
  "features": [
    {
      "geometry": {
        "type": "Point",
        "coordinates": [
          -94.5667,
          37.4167
        ]
      },
      "type": "Feature",
      "properties": {
        "hierarchy": [
          "tgn:2526380",
          "tgn:2001171",
          "tgn:1000001",
          "tgn:7012149",
          "tgn:7007523",
          "tgn:7029392"
        ],
        "placetype": [
          "aat:300006191"
        ],
        "id": 2526380,
        "name:xx": "Moss Lake"
      }
    },
    {
      "geometry": {
        "type": "Point",
        "coordinates": [
          -91.2667,
          36.5833
        ]
      },
      "type": "Feature",
      "properties": {
        "hierarchy": [
          "tgn:2526381",
          "tgn:1000001",
          "tgn:7012149",
          "tgn:2001225",
          "tgn:7007523",
          "tgn:7029392"
        ],
        "placetype": [
          "aat:300006191"
        ],
        "id": 2526381,
        "name:xx": "Moss Lake"
      }
    },
    {
      "geometry": {
        "type": "Point",
        "coordinates": [
          -96.45,
          41.55
        ]
      },
      "type": "Feature",
      "properties": {
        "hierarchy": [
          "tgn:2526382",
          "tgn:1000001",
          "tgn:7012149",
          "tgn:7007525",
          "tgn:7029392"
        ],
        "placetype": [
          "aat:300008680"
        ],
        "id": 2526382,
        "name:xx": "Moss Lake"
      }
    },
    {
      "geometry": {
        "type": "Point",
        "coordinates": [
          -78.1833,
          42.3833
        ]
      },
      "type": "Feature",
      "properties": {
        "hierarchy": [
          "tgn:2526383",
          "tgn:1002141",
          "tgn:1000001",
          "tgn:7012149",
          "tgn:7007568",
          "tgn:7029392"
        ],
        "placetype": [
          "aat:300008680"
        ],
        "id": 2526383,
        "name:xx": "Moss Lake"
      }
    },
    {
      "geometry": {
        "type": "Point",
        "coordinates": [
          -74.85,
          43.7833
        ]
      },
      "type": "Feature",
      "properties": {
        "hierarchy": [
          "tgn:2526384",
          "tgn:1000001",
          "tgn:7012149",
          "tgn:1002472",
          "tgn:7007568",
          "tgn:7029392"
        ],
        "placetype": [
          "aat:300008680"
        ],
        "id": 2526384,
        "name:xx": "Moss Lake"
      }
    },
    {
      "geometry": {
        "type": "Point",
        "coordinates": [
          -81.45,
          35.2667
        ]
      },
      "type": "Feature",
      "properties": {
        "hierarchy": [
          "tgn:2526385",
          "tgn:1000001",
          "tgn:2001484",
          "tgn:7012149",
          "tgn:7007709",
          "tgn:7029392"
        ],
        "placetype": [
          "aat:300006191"
        ],
        "id": 2526385,
        "name:xx": "Moss Lake"
      }
    },
    {
      "geometry": {
        "type": "Point",
        "coordinates": [
          -77.8,
          36.1833
        ]
      },
      "type": "Feature",
      "properties": {
        "hierarchy": [
          "tgn:2526386",
          "tgn:1000001",
          "tgn:7012149",
          "tgn:2001501",
          "tgn:7007709",
          "tgn:7029392"
        ],
        "placetype": [
          "aat:300006191"
        ],
        "id": 2526386,
        "name:xx": "Moss Lake"
      }
    },
    {
      "geometry": {
        "type": "Point",
        "coordinates": [
          -122.5667,
          44.9667
        ]
      },
      "type": "Feature",
      "properties": {
        "hierarchy": [
          "tgn:2526387",
          "tgn:1000001",
          "tgn:7012149",
          "tgn:1002636",
          "tgn:7007708",
          "tgn:7029392"
        ],
        "placetype": [
          "aat:300008680"
        ],
        "id": 2526387,
        "name:xx": "Moss Lake"
      }
    },
    {
      "geometry": {
        "type": "Point",
        "coordinates": [
          -80.6667,
          33.5833
        ]
      },
      "type": "Feature",
      "properties": {
        "hierarchy": [
          "tgn:2526388",
          "tgn:1000001",
          "tgn:2001733",
          "tgn:7012149",
          "tgn:7007712",
          "tgn:7029392"
        ],
        "placetype": [
          "aat:300006191"
        ],
        "id": 2526388,
        "name:xx": "Moss Lake"
      }
    },
    {
      "geometry": {
        "type": "Point",
        "coordinates": [
          -94.8167,
          32.45
        ]
      },
      "type": "Feature",
      "properties": {
        "hierarchy": [
          "tgn:2526389",
          "tgn:1000001",
          "tgn:7012149",
          "tgn:1002427",
          "tgn:7007826",
          "tgn:7029392"
        ],
        "placetype": [
          "aat:300008680"
        ],
        "id": 2526389,
        "name:xx": "Moss Lake"
      }
    }
  ]
}
