{
  "geometry": {
    "type": "Point",
    "coordinates": [
      -58.3667,
      -34.6833
    ]
  },
  "type": "Feature",
  "properties": {
    "hierarchy": [
      "tgn:1004525",
      "tgn:1001160",
      "tgn:7006477",
      "tgn:1136422",
      "tgn:1000002",
      "tgn:7029392"
    ],
    "placetype": [
      "aat:300000745"
    ],
    "id": 1004525,
    "name:xx": "Gerli"
  }
}
