{
  "type": "FeatureCollection",
  "features": [
    {
      "geometry": {
        "type": "Point",
        "coordinates": [
          29.206548,
          30.748009
        ]
      },
      "type": "Feature",
      "properties": {
        "hierarchy": [
          "tgn:7520101",
          "tgn:7001242",
          "tgn:7016833",
          "tgn:1001418",
          "tgn:7029392"
        ],
        "placetype": [
          "aat:300006207"
        ],
        "name:en": "Bi'r Ab큰 Shunaynah",
        "id": 7520101
      }
    },
    {
      "geometry": {
        "type": "Point",
        "coordinates": [
          29.166667,
          30.816667
        ]
      },
      "type": "Feature",
      "properties": {
        "hierarchy": [
          "tgn:7520103",
          "tgn:7001242",
          "tgn:7016833",
          "tgn:1001418",
          "tgn:7029392"
        ],
        "placetype": [
          "aat:300008347"
        ],
        "name:en": "Ab큰 Shunaynah",
        "id": 7520103
      }
    },
    {
      "geometry": {
        "type": "Point",
        "coordinates": [
          29.2,
          30.8
        ]
      },
      "type": "Feature",
      "properties": {
        "hierarchy": [
          "tgn:7520104",
          "tgn:7001242",
          "tgn:7016833",
          "tgn:1001418",
          "tgn:7029392"
        ],
        "placetype": [
          "aat:300006207"
        ],
        "name:en": "Bi'r Ab큰 Shunayf",
        "id": 7520104
      }
    },
    {
      "geometry": {
        "type": "Point",
        "coordinates": [
          34.052732,
          26.502496
        ]
      },
      "type": "Feature",
      "properties": {
        "hierarchy": [
          "tgn:7520105",
          "tgn:7001242",
          "tgn:7001311",
          "tgn:7016833",
          "tgn:7029392"
        ],
        "placetype": [
          "aat:300379998"
        ],
        "name:en": "Abu Shiqeili, W창di",
        "id": 7520105
      }
    },
    {
      "geometry": {
        "type": "Point",
        "coordinates": [
          34.2,
          26.216667
        ]
      },
      "type": "Feature",
      "properties": {
        "hierarchy": [
          "tgn:7520107",
          "tgn:7001242",
          "tgn:7001311",
          "tgn:7016833",
          "tgn:7029392"
        ],
        "placetype": [
          "aat:300379998"
        ],
        "name:en": "Abu Shiqeili, Wadi",
        "id": 7520107
      }
    },
    {
      "geometry": {
        "type": "Point",
        "coordinates": [
          34,
          26.516667
        ]
      },
      "type": "Feature",
      "properties": {
        "hierarchy": [
          "tgn:7520108",
          "tgn:7001242",
          "tgn:7001311",
          "tgn:7016833",
          "tgn:7029392"
        ],
        "placetype": [
          "aat:300008795"
        ],
        "name:en": "Abu Shiqeili, Gebel",
        "id": 7520108
      }
    },
    {
      "geometry": {
        "type": "Point",
        "coordinates": [
          25.716952,
          31.318307
        ]
      },
      "type": "Feature",
      "properties": {
        "hierarchy": [
          "tgn:7520109",
          "tgn:7001242",
          "tgn:7016833",
          "tgn:1001418",
          "tgn:7029392"
        ],
        "placetype": [
          "aat:300005926"
        ],
        "name:en": "Qabr Abu Shinat",
        "id": 7520109
      }
    }
  ]
}
