{
  "geometry": {
    "type": "Point",
    "coordinates": [
      102.15,
      1.3333
    ]
  },
  "type": "Feature",
  "properties": {
    "hierarchy": [
      "tgn:1078651",
      "tgn:1000004",
      "tgn:1001502",
      "tgn:1000116",
      "tgn:7029392"
    ],
    "placetype": [
      "aat:300008347"
    ],
    "id": 1078651,
    "name:xx": "Sungaipakning"
  }
}
