{
  "geometry": {
    "type": "Point",
    "coordinates": [
      79.423352,
      22.168008
    ]
  },
  "type": "Feature",
  "properties": {
    "hierarchy": [
      "tgn:7553453",
      "tgn:1000004",
      "tgn:7000198",
      "tgn:1001894",
      "tgn:7029392"
    ],
    "placetype": [
      "aat:300008347"
    ],
    "name:en": "Mungwāni Kalān",
    "id": 7553453
  }
}
