{
  "geometry": {
    "type": "Point",
    "coordinates": [
      -118.1333,
      44.8667
    ]
  },
  "type": "Feature",
  "properties": {
    "hierarchy": [
      "tgn:2436948",
      "tgn:7013349",
      "tgn:1000001",
      "tgn:7012149",
      "tgn:7007708",
      "tgn:7029392"
    ],
    "placetype": [
      "aat:300008680"
    ],
    "id": 2436948,
    "name:xx": "Killamacue Lake"
  }
}
