{
  "type": "FeatureCollection",
  "features": [
    {
      "geometry": {
        "type": "Point",
        "coordinates": [
          -116.8,
          42.6833
        ]
      },
      "type": "Feature",
      "properties": {
        "hierarchy": [
          "tgn:2543090",
          "tgn:1000001",
          "tgn:7012149",
          "tgn:2000488",
          "tgn:7007250",
          "tgn:7029392"
        ],
        "placetype": [
          "aat:300008706"
        ],
        "id": 2543090,
        "name:xx": "Noon Creek"
      }
    },
    {
      "geometry": {
        "type": "Point",
        "coordinates": [
          -111.85,
          43.35
        ]
      },
      "type": "Feature",
      "properties": {
        "hierarchy": [
          "tgn:2543091",
          "tgn:1000001",
          "tgn:7012149",
          "tgn:7007250",
          "tgn:7029392"
        ],
        "placetype": [
          "aat:300008706"
        ],
        "id": 2543091,
        "name:xx": "Noon Creek"
      }
    },
    {
      "geometry": {
        "type": "Point",
        "coordinates": [
          -122.4,
          43.5833
        ]
      },
      "type": "Feature",
      "properties": {
        "hierarchy": [
          "tgn:2543092",
          "tgn:1000001",
          "tgn:7012149",
          "tgn:2001716",
          "tgn:7007708",
          "tgn:7029392"
        ],
        "placetype": [
          "aat:300008706"
        ],
        "id": 2543092,
        "name:xx": "Noon Creek"
      }
    },
    {
      "geometry": {
        "type": "Point",
        "coordinates": [
          -109.8167,
          32.65
        ]
      },
      "type": "Feature",
      "properties": {
        "hierarchy": [
          "tgn:2543093",
          "tgn:1000001",
          "tgn:7006451",
          "tgn:2000094",
          "tgn:7012149",
          "tgn:7029392"
        ],
        "placetype": [
          "aat:300266640"
        ],
        "id": 2543093,
        "name:xx": "Noon Creek Ridge"
      }
    },
    {
      "geometry": {
        "type": "Point",
        "coordinates": [
          -116.8,
          42.6833
        ]
      },
      "type": "Feature",
      "properties": {
        "hierarchy": [
          "tgn:2543094",
          "tgn:1000001",
          "tgn:7012149",
          "tgn:2000488",
          "tgn:7007250",
          "tgn:7029392"
        ],
        "placetype": [
          "aat:300008697"
        ],
        "id": 2543094,
        "name:xx": "Noon Creek Spring"
      }
    },
    {
      "geometry": {
        "type": "Point",
        "coordinates": [
          -111.4167,
          38.0833
        ]
      },
      "type": "Feature",
      "properties": {
        "hierarchy": [
          "tgn:2543095",
          "tgn:1000001",
          "tgn:2002109",
          "tgn:7012149",
          "tgn:7007827",
          "tgn:7029392"
        ],
        "placetype": [
          "aat:300008680"
        ],
        "id": 2543095,
        "name:xx": "Noon Lake"
      }
    },
    {
      "geometry": {
        "type": "Point",
        "coordinates": [
          -111.2,
          45.5
        ]
      },
      "type": "Feature",
      "properties": {
        "hierarchy": [
          "tgn:2543096",
          "tgn:1000001",
          "tgn:7012149",
          "tgn:2001275",
          "tgn:7007524",
          "tgn:7029392"
        ],
        "placetype": [
          "aat:300008798"
        ],
        "id": 2543096,
        "name:xx": "Noon Mark"
      }
    },
    {
      "geometry": {
        "type": "Point",
        "coordinates": [
          -70.5167,
          44.8
        ]
      },
      "type": "Feature",
      "properties": {
        "hierarchy": [
          "tgn:2543097",
          "tgn:1000001",
          "tgn:2000921",
          "tgn:7012149",
          "tgn:7007515",
          "tgn:7029392"
        ],
        "placetype": [
          "aat:300008798"
        ],
        "id": 2543097,
        "name:xx": "Noon Mountain"
      }
    },
    {
      "geometry": {
        "type": "Point",
        "coordinates": [
          -119.4667,
          34.4667
        ]
      },
      "type": "Feature",
      "properties": {
        "hierarchy": [
          "tgn:2543098",
          "tgn:1000001",
          "tgn:7012149",
          "tgn:7007157",
          "tgn:1002867",
          "tgn:7029392"
        ],
        "placetype": [
          "aat:300008798"
        ],
        "id": 2543098,
        "name:xx": "Noon Peak"
      }
    },
    {
      "geometry": {
        "type": "Point",
        "coordinates": [
          -71.5,
          43.9167
        ]
      },
      "type": "Feature",
      "properties": {
        "hierarchy": [
          "tgn:2543099",
          "tgn:1000001",
          "tgn:2001424",
          "tgn:7012149",
          "tgn:7007564",
          "tgn:7029392"
        ],
        "placetype": [
          "aat:300008798"
        ],
        "id": 2543099,
        "name:xx": "Noon Peak"
      }
    }
  ]
}
