{
  "geometry": {
    "type": "Point",
    "coordinates": [
      -98.9833,
      29.5833
    ]
  },
  "type": "Feature",
  "properties": {
    "hierarchy": [
      "tgn:2273269",
      "tgn:1000001",
      "tgn:7012149",
      "tgn:2002039",
      "tgn:7007826",
      "tgn:7029392"
    ],
    "placetype": [
      "aat:300132316"
    ],
    "id": 2273269,
    "name:xx": "Cypress Cove"
  }
}
