{
  "geometry": {
    "type": "Point",
    "coordinates": [
      89.9833,
      22.9833
    ]
  },
  "type": "Feature",
  "properties": {
    "hierarchy": [
      "tgn:1065782",
      "tgn:1000004",
      "tgn:7000190",
      "tgn:1000105",
      "tgn:7029392"
    ],
    "placetype": [
      "aat:300008347"
    ],
    "id": 1065782,
    "name:xx": "Kotwālīpāra"
  }
}
