{
  "geometry": {
    "type": "Point",
    "coordinates": [
      31.636831,
      26.730774
    ]
  },
  "type": "Feature",
  "properties": {
    "hierarchy": [
      "tgn:7522628",
      "tgn:7001242",
      "tgn:7001311",
      "tgn:7016833",
      "tgn:7029392"
    ],
    "placetype": [
      "aat:300008347"
    ],
    "name:en": "Ar Rayāyinah bi al Ḩājir",
    "id": 7522628
  }
}
