{
  "geometry": {
    "type": "Point",
    "coordinates": [
      18.284,
      49.77
    ]
  },
  "type": "Feature",
  "properties": {
    "hierarchy": [
      "tgn:4005164",
      "tgn:7593916",
      "tgn:1000003",
      "tgn:1001780",
      "tgn:7029392"
    ],
    "placetype": [
      "aat:300008347"
    ],
    "id": 4005164,
    "name:xx": "Hrabová"
  }
}
