{
  "geometry": {
    "type": "Point",
    "coordinates": [
      -70.985,
      19.584
    ]
  },
  "type": "Feature",
  "properties": {
    "hierarchy": [
      "tgn:7593542",
      "tgn:7005424",
      "tgn:1000001",
      "tgn:7005388",
      "tgn:7029392"
    ],
    "placetype": [
      "aat:300008347"
    ],
    "id": 7593542,
    "name:xx": "Esperanza"
  }
}
