{
  "geometry": {
    "type": "Point",
    "coordinates": [
      -102.283333,
      21.75
    ]
  },
  "type": "Feature",
  "properties": {
    "hierarchy": [
      "tgn:7354793",
      "tgn:7005579",
      "tgn:1000001",
      "tgn:7005560",
      "tgn:7029392"
    ],
    "placetype": [
      "aat:300008347"
    ],
    "id": 7354793,
    "name:xx": "Churubusco"
  }
}
