{
  "geometry": {
    "type": "Point",
    "coordinates": [
      -93.1167,
      45.2333
    ]
  },
  "type": "Feature",
  "properties": {
    "hierarchy": [
      "tgn:2778078",
      "tgn:2001000",
      "tgn:1000001",
      "tgn:7012149",
      "tgn:7007521",
      "tgn:7029392"
    ],
    "placetype": [
      "aat:300008905"
    ],
    "id": 2778078,
    "name:xx": "Wiregrass Marsh"
  }
}
