{
  "geometry": {
    "type": "Point",
    "coordinates": [
      -116.5833,
      33.5167
    ]
  },
  "type": "Feature",
  "properties": {
    "hierarchy": [
      "tgn:2709252",
      "tgn:1000001",
      "tgn:7012149",
      "tgn:7007157",
      "tgn:1002828",
      "tgn:7029392"
    ],
    "placetype": [
      "aat:300008798"
    ],
    "id": 2709252,
    "name:xx": "Table Mountain"
  }
}
