{
  "geometry": {
    "type": "Point",
    "coordinates": [
      96.4667,
      18.4833
    ]
  },
  "type": "Feature",
  "properties": {
    "hierarchy": [
      "tgn:7002158",
      "tgn:7002161",
      "tgn:1000004",
      "tgn:1000108",
      "tgn:7029392"
    ],
    "placetype": [
      "aat:300008347"
    ],
    "id": 7002158,
    "name:xx": "Pyu"
  }
}
