{
  "geometry": {
    "type": "Point",
    "coordinates": [
      -133.6667,
      58.5333
    ]
  },
  "type": "Feature",
  "properties": {
    "hierarchy": [
      "tgn:2220105",
      "tgn:7006450",
      "tgn:1000001",
      "tgn:2124089",
      "tgn:7012149",
      "tgn:7029392"
    ],
    "placetype": [
      "aat:300008791"
    ],
    "id": 2220105,
    "name:xx": "Canyon Island"
  }
}
