{
  "geometry": {
    "type": "Point",
    "coordinates": [
      -112.0333,
      41.1833
    ]
  },
  "type": "Feature",
  "properties": {
    "hierarchy": [
      "tgn:2762927",
      "tgn:1000001",
      "tgn:7012149",
      "tgn:2002129",
      "tgn:7007827",
      "tgn:7029392"
    ],
    "placetype": [
      "aat:300008347"
    ],
    "id": 2762927,
    "name:xx": "Westlake Village"
  }
}
