{
  "geometry": {
    "type": "Point",
    "coordinates": [
      -2.3667,
      50.9333
    ]
  },
  "type": "Feature",
  "properties": {
    "hierarchy": [
      "tgn:1111701",
      "tgn:7002445",
      "tgn:1000003",
      "tgn:7011961",
      "tgn:7008591",
      "tgn:7029392"
    ],
    "placetype": [
      "aat:300008707"
    ],
    "id": 1111701,
    "name:xx": "Lydden"
  }
}
