{
  "geometry": {
    "type": "Point",
    "coordinates": [
      -79.75,
      39.4833
    ]
  },
  "type": "Feature",
  "properties": {
    "hierarchy": [
      "tgn:2579052",
      "tgn:1000001",
      "tgn:7012149",
      "tgn:2002288",
      "tgn:7013961",
      "tgn:7029392"
    ],
    "placetype": [
      "aat:300008798"
    ],
    "id": 2579052,
    "name:xx": "Phoebe, Mount"
  }
}
