{
  "geometry": {
    "type": "Point",
    "coordinates": [
      -83.5833,
      44.1167
    ]
  },
  "type": "Feature",
  "properties": {
    "hierarchy": [
      "tgn:2265081",
      "tgn:2000946",
      "tgn:1000001",
      "tgn:7012149",
      "tgn:7007520",
      "tgn:7029392"
    ],
    "placetype": [
      "aat:300008680"
    ],
    "id": 2265081,
    "name:xx": "Cranberry Lake"
  }
}
