{
  "geometry": {
    "type": "Point",
    "coordinates": [
      -107.8167,
      35.3167
    ]
  },
  "type": "Feature",
  "properties": {
    "hierarchy": [
      "tgn:2331194",
      "tgn:1000001",
      "tgn:7012149",
      "tgn:7019676",
      "tgn:7007566",
      "tgn:7029392"
    ],
    "placetype": [
      "aat:300000390"
    ],
    "id": 2331194,
    "name:xx": "Flat Top Mine"
  }
}
