{
  "type": "FeatureCollection",
  "features": [
    {
      "geometry": {
        "type": "Point",
        "coordinates": [
          -97.516667,
          21.033333
        ]
      },
      "type": "Feature",
      "properties": {
        "hierarchy": [
          "tgn:7384060",
          "tgn:1000001",
          "tgn:7005599",
          "tgn:7005560",
          "tgn:7029392"
        ],
        "placetype": [
          "aat:300008347"
        ],
        "id": 7384060,
        "name:xx": "Nalúa"
      }
    },
    {
      "geometry": {
        "type": "Point",
        "coordinates": [
          -104,
          21.65
        ]
      },
      "type": "Feature",
      "properties": {
        "hierarchy": [
          "tgn:7384061",
          "tgn:7005586",
          "tgn:1000001",
          "tgn:7005560",
          "tgn:7029392"
        ],
        "placetype": [
          "aat:300008347"
        ],
        "id": 7384061,
        "name:xx": "Nájares"
      }
    },
    {
      "geometry": {
        "type": "Point",
        "coordinates": [
          -96.9,
          19.466667
        ]
      },
      "type": "Feature",
      "properties": {
        "hierarchy": [
          "tgn:7384062",
          "tgn:1000001",
          "tgn:7005599",
          "tgn:7005560",
          "tgn:7029392"
        ],
        "placetype": [
          "aat:300008795"
        ],
        "id": 7384062,
        "name:xx": "Pacho"
      }
    },
    {
      "geometry": {
        "type": "Point",
        "coordinates": [
          -88.166667,
          19.3
        ]
      },
      "type": "Feature",
      "properties": {
        "hierarchy": [
          "tgn:7384063",
          "tgn:1000001",
          "tgn:1001937",
          "tgn:7005560",
          "tgn:7029392"
        ],
        "placetype": [
          "aat:300008347"
        ],
        "id": 7384063,
        "name:xx": "Pachmul"
      }
    },
    {
      "geometry": {
        "type": "Point",
        "coordinates": [
          -99.766667,
          18.4
        ]
      },
      "type": "Feature",
      "properties": {
        "hierarchy": [
          "tgn:7384064",
          "tgn:7005585",
          "tgn:1000001",
          "tgn:7005560",
          "tgn:7029392"
        ],
        "placetype": [
          "aat:300008347"
        ],
        "id": 7384064,
        "name:xx": "Pachivia"
      }
    },
    {
      "geometry": {
        "type": "Point",
        "coordinates": [
          -98.316667,
          20.85
        ]
      },
      "type": "Feature",
      "properties": {
        "hierarchy": [
          "tgn:7384065",
          "tgn:7005587",
          "tgn:1000001",
          "tgn:7005560",
          "tgn:7029392"
        ],
        "placetype": [
          "aat:300008347"
        ],
        "id": 7384065,
        "name:xx": "Pachiquitla"
      }
    },
    {
      "geometry": {
        "type": "Point",
        "coordinates": [
          -107.4,
          28.283333
        ]
      },
      "type": "Feature",
      "properties": {
        "hierarchy": [
          "tgn:7384066",
          "tgn:7005581",
          "tgn:1000001",
          "tgn:7005560",
          "tgn:7029392"
        ],
        "placetype": [
          "aat:300008347"
        ],
        "id": 7384066,
        "name:xx": "Pachera"
      }
    },
    {
      "geometry": {
        "type": "Point",
        "coordinates": [
          -108.35,
          30.1
        ]
      },
      "type": "Feature",
      "properties": {
        "hierarchy": [
          "tgn:7384067",
          "tgn:7005581",
          "tgn:1000001",
          "tgn:7005560",
          "tgn:7029392"
        ],
        "placetype": [
          "aat:300008347"
        ],
        "id": 7384067,
        "name:xx": "Pacheco"
      }
    },
    {
      "geometry": {
        "type": "Point",
        "coordinates": [
          -104.816667,
          29.25
        ]
      },
      "type": "Feature",
      "properties": {
        "hierarchy": [
          "tgn:7384068",
          "tgn:7005581",
          "tgn:1000001",
          "tgn:7005560",
          "tgn:7029392"
        ],
        "placetype": [
          "aat:300008347"
        ],
        "id": 7384068,
        "name:xx": "Pacheco"
      }
    },
    {
      "geometry": {
        "type": "Point",
        "coordinates": [
          -102.416667,
          23.966667
        ]
      },
      "type": "Feature",
      "properties": {
        "hierarchy": [
          "tgn:7384069",
          "tgn:1000001",
          "tgn:7005601",
          "tgn:7005560",
          "tgn:7029392"
        ],
        "placetype": [
          "aat:300008347"
        ],
        "id": 7384069,
        "name:xx": "Pacheco"
      }
    }
  ]
}
