{
  "geometry": {
    "type": "Point",
    "coordinates": [
      30.55,
      59.1667
    ]
  },
  "type": "Feature",
  "properties": {
    "hierarchy": [
      "tgn:1057399",
      "tgn:1000004",
      "tgn:7011572",
      "tgn:7018214",
      "tgn:7002435",
      "tgn:7029392"
    ],
    "placetype": [
      "aat:300008347"
    ],
    "id": 1057399,
    "name:xx": "Nesterkovo"
  }
}
