{
  "type": "FeatureCollection",
  "features": [
    {
      "geometry": {
        "type": "Point",
        "coordinates": [
          12.056944,
          46.450278
        ]
      },
      "type": "Feature",
      "properties": {
        "hierarchy": [
          "tgn:1046840",
          "tgn:7002991",
          "tgn:1000003",
          "tgn:7002997",
          "tgn:1000080",
          "tgn:7029392"
        ],
        "placetype": [
          "aat:300008347"
        ],
        "id": 1046840,
        "name:xx": "Selva di Cadore"
      }
    },
    {
      "geometry": {
        "type": "Point",
        "coordinates": [
          9.75,
          45.8
        ]
      },
      "type": "Feature",
      "properties": {
        "hierarchy": [
          "tgn:1046841",
          "tgn:7005023",
          "tgn:1000003",
          "tgn:7003237",
          "tgn:1000080",
          "tgn:7029392"
        ],
        "placetype": [
          "aat:300008347"
        ],
        "id": 1046841,
        "name:xx": "Selvino"
      }
    },
    {
      "geometry": {
        "type": "Point",
        "coordinates": [
          9.116667,
          45.583333
        ]
      },
      "type": "Feature",
      "properties": {
        "hierarchy": [
          "tgn:1046843",
          "tgn:7003150",
          "tgn:1000003",
          "tgn:7003237",
          "tgn:1000080",
          "tgn:7029392"
        ],
        "placetype": [
          "aat:300008347"
        ],
        "id": 1046843,
        "name:xx": "Senago"
      }
    },
    {
      "geometry": {
        "type": "Point",
        "coordinates": [
          11.1,
          46.516667
        ]
      },
      "type": "Feature",
      "properties": {
        "hierarchy": [
          "tgn:1046844",
          "tgn:1003440",
          "tgn:1000003",
          "tgn:7003124",
          "tgn:1000080",
          "tgn:7029392"
        ],
        "placetype": [
          "aat:300008347"
        ],
        "id": 1046844,
        "name:xx": "Senale"
      }
    },
    {
      "geometry": {
        "type": "Point",
        "coordinates": [
          8.6,
          40.083333
        ]
      },
      "type": "Feature",
      "properties": {
        "hierarchy": [
          "tgn:1046845",
          "tgn:1001730",
          "tgn:1000003",
          "tgn:7003121",
          "tgn:1000080",
          "tgn:7029392"
        ],
        "placetype": [
          "aat:300008347"
        ],
        "id": 1046845,
        "name:xx": "Seneghe"
      }
    },
    {
      "geometry": {
        "type": "Point",
        "coordinates": [
          15.2,
          40.733333
        ]
      },
      "type": "Feature",
      "properties": {
        "hierarchy": [
          "tgn:1046846",
          "tgn:7003002",
          "tgn:7003005",
          "tgn:1000003",
          "tgn:1000080",
          "tgn:7029392"
        ],
        "placetype": [
          "aat:300008347"
        ],
        "id": 1046846,
        "name:xx": "Senerchia"
      }
    },
    {
      "geometry": {
        "type": "Point",
        "coordinates": [
          8.595,
          40.791389
        ]
      },
      "type": "Feature",
      "properties": {
        "hierarchy": [
          "tgn:1046849",
          "tgn:7015163",
          "tgn:1000003",
          "tgn:7003121",
          "tgn:1000080",
          "tgn:7029392"
        ],
        "placetype": [
          "aat:300008347"
        ],
        "id": 1046849,
        "name:xx": "Sennori"
      }
    }
  ]
}
