{
  "geometry": {
    "type": "Point",
    "coordinates": [
      -124.0167,
      41.9167
    ]
  },
  "type": "Feature",
  "properties": {
    "hierarchy": [
      "tgn:2255905",
      "tgn:1000001",
      "tgn:7012149",
      "tgn:2000180",
      "tgn:7007157",
      "tgn:7029392"
    ],
    "placetype": [
      "aat:300000390"
    ],
    "id": 2255905,
    "name:xx": "Copper Creek Mine"
  }
}
