{
  "type": "FeatureCollection",
  "features": [
    {
      "geometry": {
        "type": "Point",
        "coordinates": [
          -83.6667,
          36.1
        ]
      },
      "type": "Feature",
      "properties": {
        "hierarchy": [
          "tgn:2212420",
          "tgn:1000001",
          "tgn:7012149",
          "tgn:2001865",
          "tgn:7007825",
          "tgn:7029392"
        ],
        "placetype": [
          "aat:300008791"
        ],
        "id": 2212420,
        "name:xx": "Byerley Island"
      }
    },
    {
      "geometry": {
        "type": "Point",
        "coordinates": [
          -84.0167,
          35.8
        ]
      },
      "type": "Feature",
      "properties": {
        "hierarchy": [
          "tgn:2212421",
          "tgn:1000001",
          "tgn:2001841",
          "tgn:7012149",
          "tgn:7007825",
          "tgn:7029392"
        ],
        "placetype": [
          "aat:300008680"
        ],
        "id": 2212421,
        "name:xx": "Byerley Lake"
      }
    },
    {
      "geometry": {
        "type": "Point",
        "coordinates": [
          -79.75,
          40.3333
        ]
      },
      "type": "Feature",
      "properties": {
        "hierarchy": [
          "tgn:2212422",
          "tgn:1000001",
          "tgn:7012149",
          "tgn:1003017",
          "tgn:7007710",
          "tgn:7029392"
        ],
        "placetype": [
          "aat:300008347"
        ],
        "id": 2212422,
        "name:xx": "Byerly"
      }
    },
    {
      "geometry": {
        "type": "Point",
        "coordinates": [
          -90.3667,
          38.3833
        ]
      },
      "type": "Feature",
      "properties": {
        "hierarchy": [
          "tgn:2212423",
          "tgn:1000001",
          "tgn:7012149",
          "tgn:1002517",
          "tgn:7007523",
          "tgn:7029392"
        ],
        "placetype": [
          "aat:300008347"
        ],
        "id": 2212423,
        "name:xx": "Byers"
      }
    },
    {
      "geometry": {
        "type": "Point",
        "coordinates": [
          -123.5,
          42.9167
        ]
      },
      "type": "Feature",
      "properties": {
        "hierarchy": [
          "tgn:2212424",
          "tgn:1000001",
          "tgn:7012149",
          "tgn:2001706",
          "tgn:7007708",
          "tgn:7029392"
        ],
        "placetype": [
          "aat:300008347"
        ],
        "id": 2212424,
        "name:xx": "Byers"
      }
    },
    {
      "geometry": {
        "type": "Point",
        "coordinates": [
          -93.3667,
          41.8
        ]
      },
      "type": "Feature",
      "properties": {
        "hierarchy": [
          "tgn:2212425",
          "tgn:1000001",
          "tgn:7012149",
          "tgn:7007253",
          "tgn:7029392"
        ],
        "placetype": [
          "aat:300008699"
        ],
        "id": 2212425,
        "name:xx": "Byers Branch"
      }
    },
    {
      "geometry": {
        "type": "Point",
        "coordinates": [
          -83.7667,
          35.0333
        ]
      },
      "type": "Feature",
      "properties": {
        "hierarchy": [
          "tgn:2212426",
          "tgn:1000001",
          "tgn:2001483",
          "tgn:7012149",
          "tgn:7007709",
          "tgn:7029392"
        ],
        "placetype": [
          "aat:300008699"
        ],
        "id": 2212426,
        "name:xx": "Byers Branch"
      }
    },
    {
      "geometry": {
        "type": "Point",
        "coordinates": [
          -79,
          38.25
        ]
      },
      "type": "Feature",
      "properties": {
        "hierarchy": [
          "tgn:2212427",
          "tgn:2002142",
          "tgn:1000001",
          "tgn:7012149",
          "tgn:7007919",
          "tgn:7029392"
        ],
        "placetype": [
          "aat:300008699"
        ],
        "id": 2212427,
        "name:xx": "Byers Branch"
      }
    },
    {
      "geometry": {
        "type": "Point",
        "coordinates": [
          -106.1,
          40.0667
        ]
      },
      "type": "Feature",
      "properties": {
        "hierarchy": [
          "tgn:2212428",
          "tgn:1000001",
          "tgn:7012149",
          "tgn:2000216",
          "tgn:7007158",
          "tgn:7029392"
        ],
        "placetype": [
          "aat:300008761"
        ],
        "id": 2212428,
        "name:xx": "Byers Canyon"
      }
    },
    {
      "geometry": {
        "type": "Point",
        "coordinates": [
          -117.8,
          39.6667
        ]
      },
      "type": "Feature",
      "properties": {
        "hierarchy": [
          "tgn:2212429",
          "tgn:1000001",
          "tgn:2001409",
          "tgn:7012149",
          "tgn:7007526",
          "tgn:7029392"
        ],
        "placetype": [
          "aat:300008761"
        ],
        "id": 2212429,
        "name:xx": "Byers Canyon"
      }
    }
  ]
}
