{
  "geometry": {
    "type": "Point",
    "coordinates": [
      -149.6667,
      67.6333
    ]
  },
  "type": "Feature",
  "properties": {
    "hierarchy": [
      "tgn:2287798",
      "tgn:7006450",
      "tgn:1000001",
      "tgn:7019674",
      "tgn:7012149",
      "tgn:7029392"
    ],
    "placetype": [
      "aat:300008798"
    ],
    "id": 2287798,
    "name:xx": "Dillon Mountain"
  }
}
