{
  "geometry": {
    "type": "Point",
    "coordinates": [
      -85.2167,
      43.6667
    ]
  },
  "type": "Feature",
  "properties": {
    "hierarchy": [
      "tgn:2405637",
      "tgn:1000001",
      "tgn:7012149",
      "tgn:2000977",
      "tgn:7007520",
      "tgn:7029392"
    ],
    "placetype": [
      "aat:300008905"
    ],
    "id": 2405637,
    "name:xx": "Hughes Swamp"
  }
}
