{
  "geometry": {
    "type": "Point",
    "coordinates": [
      -69.55,
      -18.45
    ]
  },
  "type": "Feature",
  "properties": {
    "hierarchy": [
      "tgn:7281844",
      "tgn:7002464",
      "tgn:1000049",
      "tgn:1000002",
      "tgn:7029392"
    ],
    "placetype": [
      "aat:300266554",
      "aat:300008699"
    ],
    "id": 7281844,
    "name:xx": "San Andrés, Quebrada"
  }
}
