{
  "geometry": {
    "type": "Point",
    "coordinates": [
      -93.25,
      43.1333
    ]
  },
  "type": "Feature",
  "properties": {
    "hierarchy": [
      "tgn:2588273",
      "tgn:1000001",
      "tgn:2000579",
      "tgn:7012149",
      "tgn:7007253",
      "tgn:7029392"
    ],
    "placetype": [
      "aat:300008706"
    ],
    "id": 2588273,
    "name:xx": "Plum Creek"
  }
}
