{
  "type": "FeatureCollection",
  "features": [
    {
      "geometry": {
        "type": "Point",
        "coordinates": [
          -71.566667,
          -34
        ]
      },
      "type": "Feature",
      "properties": {
        "hierarchy": [
          "tgn:7287250",
          "tgn:1001708",
          "tgn:1000049",
          "tgn:1000002",
          "tgn:7029392"
        ],
        "placetype": [
          "aat:300008777"
        ],
        "id": 7287250,
        "name:xx": "Grande, Piedra"
      }
    },
    {
      "geometry": {
        "type": "Point",
        "coordinates": [
          -71.366667,
          -31.683333
        ]
      },
      "type": "Feature",
      "properties": {
        "hierarchy": [
          "tgn:7287251",
          "tgn:1001657",
          "tgn:1000049",
          "tgn:1000002",
          "tgn:7029392"
        ],
        "placetype": [
          "aat:300008795"
        ],
        "id": 7287251,
        "name:xx": "Grande, Morro"
      }
    },
    {
      "geometry": {
        "type": "Point",
        "coordinates": [
          -73.1,
          -36.85
        ]
      },
      "type": "Feature",
      "properties": {
        "hierarchy": [
          "tgn:7287252",
          "tgn:1001637",
          "tgn:1000049",
          "tgn:1000002",
          "tgn:7029392"
        ],
        "placetype": [
          "aat:300008680"
        ],
        "id": 7287252,
        "name:xx": "Grande, Laguna"
      }
    },
    {
      "geometry": {
        "type": "Point",
        "coordinates": [
          -69.916667,
          -28.733333
        ]
      },
      "type": "Feature",
      "properties": {
        "hierarchy": [
          "tgn:7287253",
          "tgn:1001630",
          "tgn:1000049",
          "tgn:1000002",
          "tgn:7029392"
        ],
        "placetype": [
          "aat:300008680"
        ],
        "id": 7287253,
        "name:xx": "Grande, Laguna"
      }
    },
    {
      "geometry": {
        "type": "Point",
        "coordinates": [
          -68.683333,
          -20.666667
        ]
      },
      "type": "Feature",
      "properties": {
        "hierarchy": [
          "tgn:7287254",
          "tgn:7002464",
          "tgn:1000049",
          "tgn:1000002",
          "tgn:7029392"
        ],
        "placetype": [
          "aat:300008680"
        ],
        "id": 7287254,
        "name:xx": "Grande, Laguna"
      }
    },
    {
      "geometry": {
        "type": "Point",
        "coordinates": [
          -68.766667,
          -55.15
        ]
      },
      "type": "Feature",
      "properties": {
        "hierarchy": [
          "tgn:7287255",
          "tgn:1001702",
          "tgn:1000049",
          "tgn:1000002",
          "tgn:7029392"
        ],
        "placetype": [
          "aat:300008791"
        ],
        "id": 7287255,
        "name:xx": "Grande, Isla"
      }
    },
    {
      "geometry": {
        "type": "Point",
        "coordinates": [
          -69.9,
          -55.05
        ]
      },
      "type": "Feature",
      "properties": {
        "hierarchy": [
          "tgn:7287256",
          "tgn:1001702",
          "tgn:1000049",
          "tgn:1000002",
          "tgn:7029392"
        ],
        "placetype": [
          "aat:300008791"
        ],
        "id": 7287256,
        "name:xx": "Grande, Isla"
      }
    },
    {
      "geometry": {
        "type": "Point",
        "coordinates": [
          -70.916667,
          -54.833333
        ]
      },
      "type": "Feature",
      "properties": {
        "hierarchy": [
          "tgn:7287257",
          "tgn:1001702",
          "tgn:1000049",
          "tgn:1000002",
          "tgn:7029392"
        ],
        "placetype": [
          "aat:300008791"
        ],
        "id": 7287257,
        "name:xx": "Grande, Isla"
      }
    },
    {
      "geometry": {
        "type": "Point",
        "coordinates": [
          -72.733333,
          -53.15
        ]
      },
      "type": "Feature",
      "properties": {
        "hierarchy": [
          "tgn:7287258",
          "tgn:1001702",
          "tgn:1000049",
          "tgn:1000002",
          "tgn:7029392"
        ],
        "placetype": [
          "aat:300008791"
        ],
        "id": 7287258,
        "name:xx": "Grande, Isla"
      }
    },
    {
      "geometry": {
        "type": "Point",
        "coordinates": [
          -72.433333,
          -52.75
        ]
      },
      "type": "Feature",
      "properties": {
        "hierarchy": [
          "tgn:7287259",
          "tgn:1001702",
          "tgn:1000049",
          "tgn:1000002",
          "tgn:7029392"
        ],
        "placetype": [
          "aat:300008791"
        ],
        "id": 7287259,
        "name:xx": "Grande, Isla"
      }
    }
  ]
}
