{
  "geometry": {
    "type": "Point",
    "coordinates": [
      -79.2667,
      41.5833
    ]
  },
  "type": "Feature",
  "properties": {
    "hierarchy": [
      "tgn:2509011",
      "tgn:1000001",
      "tgn:7012149",
      "tgn:1002378",
      "tgn:7007710",
      "tgn:7029392"
    ],
    "placetype": [
      "aat:300008699"
    ],
    "id": 2509011,
    "name:xx": "Middle Fork Run"
  }
}
