{
  "geometry": {
    "type": "Point",
    "coordinates": [
      89.9167,
      22.5833
    ]
  },
  "type": "Feature",
  "properties": {
    "hierarchy": [
      "tgn:1065605",
      "tgn:1000004",
      "tgn:7000190",
      "tgn:1000105",
      "tgn:7029392"
    ],
    "placetype": [
      "aat:300008347"
    ],
    "id": 1065605,
    "name:xx": "Banagrām"
  }
}
