{
  "geometry": {
    "type": "Point",
    "coordinates": [
      151.9167,
      7.4167
    ]
  },
  "type": "Feature",
  "properties": {
    "hierarchy": [
      "tgn:1006985",
      "tgn:7018508",
      "tgn:1010363",
      "tgn:1000220",
      "tgn:1000006",
      "tgn:7029392"
    ],
    "placetype": [
      "aat:300008791"
    ],
    "id": 1006985,
    "name:xx": "Dublon"
  }
}
