{
  "geometry": {
    "type": "Point",
    "coordinates": [
      -81.0333,
      39.95
    ]
  },
  "type": "Feature",
  "properties": {
    "hierarchy": [
      "tgn:2511299",
      "tgn:1002175",
      "tgn:1000001",
      "tgn:7012149",
      "tgn:7007706",
      "tgn:7029392"
    ],
    "placetype": [
      "aat:300008699"
    ],
    "id": 2511299,
    "name:xx": "Mikes Run"
  }
}
