{
  "geometry": {
    "type": "Point",
    "coordinates": [
      133.5333,
      -17.55
    ]
  },
  "type": "Feature",
  "properties": {
    "hierarchy": [
      "tgn:1096834",
      "tgn:7000490",
      "tgn:1000006",
      "tgn:7001829",
      "tgn:7029392"
    ],
    "placetype": [
      "aat:300008347"
    ],
    "id": 1096834,
    "name:xx": "Elliott"
  }
}
