{
  "geometry": {
    "type": "Point",
    "coordinates": [
      -94.2667,
      30.7667
    ]
  },
  "type": "Feature",
  "properties": {
    "hierarchy": [
      "tgn:2752147",
      "tgn:1000001",
      "tgn:7012149",
      "tgn:1002959",
      "tgn:7007826",
      "tgn:7029392"
    ],
    "placetype": [
      "aat:300008699"
    ],
    "id": 2752147,
    "name:xx": "Wash Hole Branch"
  }
}
