{
  "type": "FeatureCollection",
  "features": [
    {
      "geometry": {
        "type": "Point",
        "coordinates": [
          -86.4167,
          33.6667
        ]
      },
      "type": "Feature",
      "properties": {
        "hierarchy": [
          "tgn:2583450",
          "tgn:7002659",
          "tgn:1000001",
          "tgn:7012149",
          "tgn:7029392"
        ],
        "placetype": [
          "aat:300266640"
        ],
        "id": 2583450,
        "name:xx": "Pine Ridge"
      }
    },
    {
      "geometry": {
        "type": "Point",
        "coordinates": [
          -85.7833,
          34.4333
        ]
      },
      "type": "Feature",
      "properties": {
        "hierarchy": [
          "tgn:2583451",
          "tgn:7002659",
          "tgn:1000001",
          "tgn:7012149",
          "tgn:7021514",
          "tgn:7029392"
        ],
        "placetype": [
          "aat:300008347"
        ],
        "id": 2583451,
        "name:xx": "Pine Ridge"
      }
    },
    {
      "geometry": {
        "type": "Point",
        "coordinates": [
          -110.15,
          32.3833
        ]
      },
      "type": "Feature",
      "properties": {
        "hierarchy": [
          "tgn:2583452",
          "tgn:1000001",
          "tgn:7006451",
          "tgn:2000091",
          "tgn:7012149",
          "tgn:7029392"
        ],
        "placetype": [
          "aat:300266640"
        ],
        "id": 2583452,
        "name:xx": "Pine Ridge"
      }
    },
    {
      "geometry": {
        "type": "Point",
        "coordinates": [
          -111.4667,
          34.3333
        ]
      },
      "type": "Feature",
      "properties": {
        "hierarchy": [
          "tgn:2583453",
          "tgn:1000001",
          "tgn:7006451",
          "tgn:2000093",
          "tgn:7012149",
          "tgn:7029392"
        ],
        "placetype": [
          "aat:300266640"
        ],
        "id": 2583453,
        "name:xx": "Pine Ridge"
      }
    },
    {
      "geometry": {
        "type": "Point",
        "coordinates": [
          -112.15,
          35.0333
        ]
      },
      "type": "Feature",
      "properties": {
        "hierarchy": [
          "tgn:2583454",
          "tgn:1000001",
          "tgn:7006451",
          "tgn:2000092",
          "tgn:7012149",
          "tgn:7029392"
        ],
        "placetype": [
          "aat:300266640"
        ],
        "id": 2583454,
        "name:xx": "Pine Ridge"
      }
    },
    {
      "geometry": {
        "type": "Point",
        "coordinates": [
          -92.2667,
          34.9
        ]
      },
      "type": "Feature",
      "properties": {
        "hierarchy": [
          "tgn:2583455",
          "tgn:1000001",
          "tgn:7016172",
          "tgn:7012149",
          "tgn:2000164",
          "tgn:7029392"
        ],
        "placetype": [
          "aat:300266640"
        ],
        "id": 2583455,
        "name:xx": "Pine Ridge"
      }
    },
    {
      "geometry": {
        "type": "Point",
        "coordinates": [
          -93.9667,
          35.2
        ]
      },
      "type": "Feature",
      "properties": {
        "hierarchy": [
          "tgn:2583456",
          "tgn:1000001",
          "tgn:7016172",
          "tgn:7012149",
          "tgn:2000146",
          "tgn:7029392"
        ],
        "placetype": [
          "aat:300266640"
        ],
        "id": 2583456,
        "name:xx": "Pine Ridge"
      }
    },
    {
      "geometry": {
        "type": "Point",
        "coordinates": [
          -93.2833,
          35.7167
        ]
      },
      "type": "Feature",
      "properties": {
        "hierarchy": [
          "tgn:2583457",
          "tgn:1000001",
          "tgn:7016172",
          "tgn:7012149",
          "tgn:2000140",
          "tgn:7029392"
        ],
        "placetype": [
          "aat:300266640"
        ],
        "id": 2583457,
        "name:xx": "Pine Ridge"
      }
    },
    {
      "geometry": {
        "type": "Point",
        "coordinates": [
          -121.9333,
          36.5
        ]
      },
      "type": "Feature",
      "properties": {
        "hierarchy": [
          "tgn:2583458",
          "tgn:1000001",
          "tgn:7012149",
          "tgn:7007157",
          "tgn:1002684",
          "tgn:7029392"
        ],
        "placetype": [
          "aat:300266640"
        ],
        "id": 2583458,
        "name:xx": "Pine Ridge"
      }
    },
    {
      "geometry": {
        "type": "Point",
        "coordinates": [
          -121.0333,
          36.5333
        ]
      },
      "type": "Feature",
      "properties": {
        "hierarchy": [
          "tgn:2583459",
          "tgn:1000001",
          "tgn:7012149",
          "tgn:7007157",
          "tgn:1002856",
          "tgn:7029392"
        ],
        "placetype": [
          "aat:300266640"
        ],
        "id": 2583459,
        "name:xx": "Pine Ridge"
      }
    }
  ]
}
