{
  "geometry": {
    "type": "Point",
    "coordinates": [
      -94.9833,
      47.7833
    ]
  },
  "type": "Feature",
  "properties": {
    "hierarchy": [
      "tgn:2459953",
      "tgn:2001002",
      "tgn:1000001",
      "tgn:7012149",
      "tgn:7007521",
      "tgn:7029392"
    ],
    "placetype": [
      "aat:300008706"
    ],
    "id": 2459953,
    "name:xx": "Little Rock Creek"
  }
}
