{
  "geometry": {
    "type": "Point",
    "coordinates": [
      -86.6167,
      39.1833
    ]
  },
  "type": "Feature",
  "properties": {
    "hierarchy": [
      "tgn:2617312",
      "tgn:1000001",
      "tgn:7012149",
      "tgn:7007252",
      "tgn:7029392"
    ],
    "placetype": [
      "aat:300008706"
    ],
    "id": 2617312,
    "name:xx": "Richland Creek"
  }
}
