{
  "geometry": {
    "type": "Point",
    "coordinates": [
      -84.35,
      32.2167
    ]
  },
  "type": "Feature",
  "properties": {
    "hierarchy": [
      "tgn:2729284",
      "tgn:1000001",
      "tgn:7012149",
      "tgn:2000414",
      "tgn:7007248",
      "tgn:7029392"
    ],
    "placetype": [
      "aat:300008699"
    ],
    "id": 2729284,
    "name:xx": "Trip Up Branch"
  }
}
