{
  "geometry": {
    "type": "Point",
    "coordinates": [
      39.8167,
      -16.15
    ]
  },
  "type": "Feature",
  "properties": {
    "hierarchy": [
      "tgn:1091479",
      "tgn:7001242",
      "tgn:1000902",
      "tgn:1000180",
      "tgn:7029392"
    ],
    "placetype": [
      "aat:300008347"
    ],
    "id": 1091479,
    "name:xx": "Boila"
  }
}
