{
  "geometry": {
    "type": "Point",
    "coordinates": [
      -83.7667,
      43.5667
    ]
  },
  "type": "Feature",
  "properties": {
    "hierarchy": [
      "tgn:2373273",
      "tgn:2000948",
      "tgn:1000001",
      "tgn:7012149",
      "tgn:7007520",
      "tgn:7029392"
    ],
    "placetype": [
      "aat:300006075"
    ],
    "id": 2373273,
    "name:xx": "Halstead Drain"
  }
}
