{
  "geometry": {
    "type": "Point",
    "coordinates": [
      -86.6833,
      41.3667
    ]
  },
  "type": "Feature",
  "properties": {
    "hierarchy": [
      "tgn:2656335",
      "tgn:1000001",
      "tgn:7012149",
      "tgn:1002918",
      "tgn:7007252",
      "tgn:7029392"
    ],
    "placetype": [
      "aat:300006075"
    ],
    "id": 2656335,
    "name:xx": "Shearin Ditch"
  }
}
