{
  "geometry": {
    "type": "Point",
    "coordinates": [
      -74.0667,
      43.8667
    ]
  },
  "type": "Feature",
  "properties": {
    "hierarchy": [
      "tgn:2779059",
      "tgn:1000001",
      "tgn:7012149",
      "tgn:2001461",
      "tgn:7007568",
      "tgn:7029392"
    ],
    "placetype": [
      "aat:300008706"
    ],
    "id": 2779059,
    "name:xx": "Wolf Creek"
  }
}
