{
  "type": "FeatureCollection",
  "features": [
    {
      "geometry": {
        "type": "Point",
        "coordinates": [
          -6.216667,
          56.85
        ]
      },
      "type": "Feature",
      "properties": {
        "hierarchy": [
          "tgn:1114960",
          "tgn:7002444",
          "tgn:1000003",
          "tgn:7008082",
          "tgn:7008591",
          "tgn:7029392"
        ],
        "placetype": [
          "aat:300266558"
        ],
        "name:en": "Eigg, Sound of",
        "id": 1114960
      }
    },
    {
      "geometry": {
        "type": "Point",
        "coordinates": [
          -62,
          66.1667
        ]
      },
      "type": "Feature",
      "properties": {
        "hierarchy": [
          "tgn:1114962",
          "tgn:7013003",
          "tgn:7005685",
          "tgn:1000001",
          "tgn:7024197",
          "tgn:7029392"
        ],
        "placetype": [
          "aat:300266558"
        ],
        "id": 1114962,
        "name:xx": "Exeter Sound"
      }
    },
    {
      "geometry": {
        "type": "Point",
        "coordinates": [
          -76,
          24.25
        ]
      },
      "type": "Feature",
      "properties": {
        "hierarchy": [
          "tgn:1114963",
          "tgn:7593484",
          "tgn:7005332",
          "tgn:1000001",
          "tgn:7029392"
        ],
        "placetype": [
          "aat:300266558"
        ],
        "id": 1114963,
        "name:xx": "Exuma Sound"
      }
    },
    {
      "geometry": {
        "type": "Point",
        "coordinates": [
          -3.1,
          59.133333
        ]
      },
      "type": "Feature",
      "properties": {
        "hierarchy": [
          "tgn:1114964",
          "tgn:7002444",
          "tgn:1000003",
          "tgn:7009907",
          "tgn:7008591",
          "tgn:7029392"
        ],
        "placetype": [
          "aat:300266558"
        ],
        "name:en": "Eynhallow Sound",
        "id": 1114964
      }
    },
    {
      "geometry": {
        "type": "Point",
        "coordinates": [
          -127.9167,
          51.6667
        ]
      },
      "type": "Feature",
      "properties": {
        "hierarchy": [
          "tgn:1114967",
          "tgn:7005735",
          "tgn:7005685",
          "tgn:1000001",
          "tgn:7029392"
        ],
        "placetype": [
          "aat:300266558"
        ],
        "id": 1114967,
        "name:xx": "Fitz Hugh Sound"
      }
    }
  ]
}
