{
  "geometry": {
    "type": "Point",
    "coordinates": [
      -106.9833,
      48.2333
    ]
  },
  "type": "Feature",
  "properties": {
    "hierarchy": [
      "tgn:2615323",
      "tgn:1000001",
      "tgn:7012149",
      "tgn:2001312",
      "tgn:7007524",
      "tgn:7029392"
    ],
    "placetype": [
      "aat:300006191"
    ],
    "id": 2615323,
    "name:xx": "Reservoir Number 14"
  }
}
