{
  "geometry": {
    "type": "Point",
    "coordinates": [
      -113.1333,
      45.7333
    ]
  },
  "type": "Feature",
  "properties": {
    "hierarchy": [
      "tgn:2561342",
      "tgn:1000001",
      "tgn:2001260",
      "tgn:7012149",
      "tgn:7007524",
      "tgn:7029392"
    ],
    "placetype": [
      "aat:300008706"
    ],
    "id": 2561342,
    "name:xx": "Osborne Creek"
  }
}
