{
  "type": "FeatureCollection",
  "features": [
    {
      "geometry": {
        "type": "Point",
        "coordinates": [
          173.166667,
          -41.35
        ]
      },
      "type": "Feature",
      "properties": {
        "hierarchy": [
          "tgn:7519100",
          "tgn:1009227",
          "tgn:1000226",
          "tgn:7520095",
          "tgn:1000006",
          "tgn:7029392"
        ],
        "placetype": [
          "aat:300007783"
        ],
        "name:en": "Appleby",
        "id": 7519100
      }
    },
    {
      "geometry": {
        "type": "Point",
        "coordinates": [
          173.116667,
          -41.3
        ]
      },
      "type": "Feature",
      "properties": {
        "hierarchy": [
          "tgn:7519101",
          "tgn:1009227",
          "tgn:1000226",
          "tgn:7520095",
          "tgn:1000006",
          "tgn:7029392"
        ],
        "placetype": [
          "aat:300008347"
        ],
        "name:en": "Appleby",
        "id": 7519101
      }
    },
    {
      "geometry": {
        "type": "Point",
        "coordinates": [
          174.916667,
          -37.583333
        ]
      },
      "type": "Feature",
      "properties": {
        "hierarchy": [
          "tgn:7519102",
          "tgn:1008380",
          "tgn:1000226",
          "tgn:7018426",
          "tgn:1000006",
          "tgn:7029392"
        ],
        "placetype": [
          "aat:300008777"
        ],
        "name:en": "Apotu",
        "id": 7519102
      }
    },
    {
      "geometry": {
        "type": "Point",
        "coordinates": [
          174.033333,
          -35.7
        ]
      },
      "type": "Feature",
      "properties": {
        "hierarchy": [
          "tgn:7519103",
          "tgn:1008380",
          "tgn:7000507",
          "tgn:1000226",
          "tgn:1000006",
          "tgn:7508910",
          "tgn:7029392"
        ],
        "placetype": [
          "aat:300008699"
        ],
        "name:en": "Aponga Stream",
        "id": 7519103
      }
    },
    {
      "geometry": {
        "type": "Point",
        "coordinates": [
          176.733333,
          -39.466667
        ]
      },
      "type": "Feature",
      "properties": {
        "hierarchy": [
          "tgn:7519104",
          "tgn:7016670",
          "tgn:1008380",
          "tgn:1000226",
          "tgn:1000006",
          "tgn:7029392"
        ],
        "placetype": [
          "aat:300000206"
        ],
        "name:en": "Apley",
        "id": 7519104
      }
    },
    {
      "geometry": {
        "type": "Point",
        "coordinates": [
          176.133333,
          -40.05
        ]
      },
      "type": "Feature",
      "properties": {
        "hierarchy": [
          "tgn:7519105",
          "tgn:7016670",
          "tgn:1008380",
          "tgn:1000226",
          "tgn:1000006",
          "tgn:7029392"
        ],
        "placetype": [
          "aat:300259572"
        ],
        "name:en": "Apiti Saddle",
        "id": 7519105
      }
    },
    {
      "geometry": {
        "type": "Point",
        "coordinates": [
          169.383333,
          -45
        ]
      },
      "type": "Feature",
      "properties": {
        "hierarchy": [
          "tgn:7519106",
          "tgn:1009227",
          "tgn:1000226",
          "tgn:7018437",
          "tgn:1000006",
          "tgn:7029392"
        ],
        "placetype": [
          "aat:300008795"
        ],
        "name:en": "Apiti, Mount",
        "id": 7519106
      }
    },
    {
      "geometry": {
        "type": "Point",
        "coordinates": [
          176,
          -37.65
        ]
      },
      "type": "Feature",
      "properties": {
        "hierarchy": [
          "tgn:7519108",
          "tgn:7000509",
          "tgn:1008380",
          "tgn:1000226",
          "tgn:1000006",
          "tgn:7029392"
        ],
        "placetype": [
          "aat:300008347"
        ],
        "name:en": "Apata",
        "id": 7519108
      }
    }
  ]
}
