{
  "type": "FeatureCollection",
  "features": [
    {
      "geometry": {
        "type": "Point",
        "coordinates": [
          -100.783333,
          22.2
        ]
      },
      "type": "Feature",
      "properties": {
        "hierarchy": [
          "tgn:7365571",
          "tgn:1000001",
          "tgn:7005594",
          "tgn:7005560",
          "tgn:7029392"
        ],
        "placetype": [
          "aat:300008347"
        ],
        "id": 7365571,
        "name:xx": "Encino"
      }
    },
    {
      "geometry": {
        "type": "Point",
        "coordinates": [
          -116.65,
          32.333333
        ]
      },
      "type": "Feature",
      "properties": {
        "hierarchy": [
          "tgn:7365572",
          "tgn:1001835",
          "tgn:1000001",
          "tgn:7005560",
          "tgn:7029392"
        ],
        "placetype": [
          "aat:300008795"
        ],
        "id": 7365572,
        "name:xx": "Encino"
      }
    },
    {
      "geometry": {
        "type": "Point",
        "coordinates": [
          -104.116667,
          28.216667
        ]
      },
      "type": "Feature",
      "properties": {
        "hierarchy": [
          "tgn:7365573",
          "tgn:7005581",
          "tgn:1000001",
          "tgn:7005560",
          "tgn:7029392"
        ],
        "placetype": [
          "aat:300008795"
        ],
        "id": 7365573,
        "name:xx": "Encinillas, Sierra de"
      }
    },
    {
      "geometry": {
        "type": "Point",
        "coordinates": [
          -104.183333,
          28.233333
        ]
      },
      "type": "Feature",
      "properties": {
        "hierarchy": [
          "tgn:7365574",
          "tgn:7005581",
          "tgn:1000001",
          "tgn:7005560",
          "tgn:7029392"
        ],
        "placetype": [
          "aat:300000241"
        ],
        "id": 7365574,
        "name:xx": "Rancho Encinillas"
      }
    },
    {
      "geometry": {
        "type": "Point",
        "coordinates": [
          -106.35,
          29.466667
        ]
      },
      "type": "Feature",
      "properties": {
        "hierarchy": [
          "tgn:7365575",
          "tgn:7005581",
          "tgn:1000001",
          "tgn:7005560",
          "tgn:7029392"
        ],
        "placetype": [
          "aat:300008680"
        ],
        "id": 7365575,
        "name:xx": "Encinillas, Laguna de"
      }
    },
    {
      "geometry": {
        "type": "Point",
        "coordinates": [
          -106.283333,
          29.233333
        ]
      },
      "type": "Feature",
      "properties": {
        "hierarchy": [
          "tgn:7365576",
          "tgn:7005581",
          "tgn:1000001",
          "tgn:7005560",
          "tgn:7029392"
        ],
        "placetype": [
          "aat:300007783"
        ],
        "id": 7365576,
        "name:xx": "Apeadero Encinillas"
      }
    },
    {
      "geometry": {
        "type": "Point",
        "coordinates": [
          -107.65,
          30.083333
        ]
      },
      "type": "Feature",
      "properties": {
        "hierarchy": [
          "tgn:7365578",
          "tgn:7005581",
          "tgn:1000001",
          "tgn:7005560",
          "tgn:7029392"
        ],
        "placetype": [
          "aat:300008347"
        ],
        "id": 7365578,
        "name:xx": "Encinillas"
      }
    },
    {
      "geometry": {
        "type": "Point",
        "coordinates": [
          -106.35,
          29.25
        ]
      },
      "type": "Feature",
      "properties": {
        "hierarchy": [
          "tgn:7365579",
          "tgn:7005581",
          "tgn:1000001",
          "tgn:7005560",
          "tgn:7029392"
        ],
        "placetype": [
          "aat:300008347"
        ],
        "id": 7365579,
        "name:xx": "Encinillas"
      }
    }
  ]
}
