{
  "geometry": {
    "type": "Point",
    "coordinates": [
      -115.7167,
      48.2833
    ]
  },
  "type": "Feature",
  "properties": {
    "hierarchy": [
      "tgn:2440091",
      "tgn:1000001",
      "tgn:7012149",
      "tgn:2001286",
      "tgn:7007524",
      "tgn:7029392"
    ],
    "placetype": [
      "aat:300008680"
    ],
    "id": 2440091,
    "name:xx": "Klatawa Lake"
  }
}
