{
  "geometry": {
    "type": "Point",
    "coordinates": [
      -96.1667,
      32.0333
    ]
  },
  "type": "Feature",
  "properties": {
    "hierarchy": [
      "tgn:2107270",
      "tgn:1000001",
      "tgn:7012149",
      "tgn:1002709",
      "tgn:7007826",
      "tgn:7029392"
    ],
    "placetype": [
      "aat:300008347",
      "aat:300387210"
    ],
    "id": 2107270,
    "name:xx": "Round Prairie"
  }
}
