{
  "geometry": {
    "type": "Point",
    "coordinates": [
      -86.95,
      38.1667
    ]
  },
  "type": "Feature",
  "properties": {
    "hierarchy": [
      "tgn:2274412",
      "tgn:1000001",
      "tgn:7012149",
      "tgn:2000555",
      "tgn:7007252",
      "tgn:7029392"
    ],
    "placetype": [
      "aat:300006191"
    ],
    "id": 2274412,
    "name:xx": "Dale Reservoir"
  }
}
