{
  "geometry": {
    "type": "Point",
    "coordinates": [
      42.5333,
      40.5833
    ]
  },
  "type": "Feature",
  "properties": {
    "hierarchy": [
      "tgn:1108693",
      "tgn:1000004",
      "tgn:1000144",
      "tgn:7029392"
    ],
    "placetype": [
      "aat:300386831"
    ],
    "id": 1108693,
    "name:xx": "Allahuekber Daglari"
  }
}
