{
  "geometry": {
    "type": "Point",
    "coordinates": [
      -6.35,
      53.7167
    ]
  },
  "type": "Feature",
  "properties": {
    "hierarchy": [
      "tgn:7006967",
      "tgn:7001199",
      "tgn:7003484",
      "tgn:1000003",
      "tgn:1000078",
      "tgn:7029392"
    ],
    "placetype": [
      "aat:300008347",
      "aat:300008389",
      "aat:300120599"
    ],
    "name:en": "Drogheda",
    "id": 7006967
  }
}
