{
  "geometry": {
    "type": "Point",
    "coordinates": [
      46.2833,
      49.7667
    ]
  },
  "type": "Feature",
  "properties": {
    "hierarchy": [
      "tgn:1061647",
      "tgn:1000004",
      "tgn:7013207",
      "tgn:7018214",
      "tgn:7002435",
      "tgn:7029392"
    ],
    "placetype": [
      "aat:300008347"
    ],
    "id": 1061647,
    "name:xx": "Zolotari"
  }
}
