{
  "geometry": {
    "type": "Point",
    "coordinates": [
      -87.4167,
      36.6333
    ]
  },
  "type": "Feature",
  "properties": {
    "hierarchy": [
      "tgn:2311311",
      "tgn:1000001",
      "tgn:2000780",
      "tgn:7012149",
      "tgn:7007255",
      "tgn:7029392"
    ],
    "placetype": [
      "aat:300008347"
    ],
    "id": 2311311,
    "name:xx": "Edgoten"
  }
}
