{
  "geometry": {
    "type": "Point",
    "coordinates": [
      -116.0333,
      47.25
    ]
  },
  "type": "Feature",
  "properties": {
    "hierarchy": [
      "tgn:2318599",
      "tgn:1000001",
      "tgn:7012149",
      "tgn:2000491",
      "tgn:7007250",
      "tgn:7029392"
    ],
    "placetype": [
      "aat:300008347"
    ],
    "id": 2318599,
    "name:xx": "Erlmo"
  }
}
