{
  "geometry": {
    "type": "Point",
    "coordinates": [
      -121.35,
      37.55
    ]
  },
  "type": "Feature",
  "properties": {
    "hierarchy": [
      "tgn:2137018",
      "tgn:1000001",
      "tgn:7012149",
      "tgn:7007157",
      "tgn:1002915",
      "tgn:7029392"
    ],
    "placetype": [
      "aat:300008706"
    ],
    "id": 2137018,
    "name:xx": "Arkansas Creek"
  }
}
