{
  "geometry": {
    "type": "Point",
    "coordinates": [
      -88.8167,
      43.8333
    ]
  },
  "type": "Feature",
  "properties": {
    "hierarchy": [
      "tgn:2357064",
      "tgn:1000001",
      "tgn:7020939",
      "tgn:7012149",
      "tgn:7007922",
      "tgn:7029392"
    ],
    "placetype": [
      "aat:300006191"
    ],
    "id": 2357064,
    "name:xx": "Gothic Mill Pond"
  }
}
