{
  "geometry": {
    "type": "Point",
    "coordinates": [
      112.0167,
      -7.75
    ]
  },
  "type": "Feature",
  "properties": {
    "hierarchy": [
      "tgn:7016704",
      "tgn:1000004",
      "tgn:1001323",
      "tgn:1000116",
      "tgn:7029392"
    ],
    "placetype": [
      "aat:300008347"
    ],
    "id": 7016704,
    "name:xx": "Kediri"
  }
}
