{
  "geometry": {
    "type": "Point",
    "coordinates": [
      -95.15,
      33.65
    ]
  },
  "type": "Feature",
  "properties": {
    "hierarchy": [
      "tgn:2196853",
      "tgn:1000001",
      "tgn:7012149",
      "tgn:2002061",
      "tgn:7007826",
      "tgn:7029392"
    ],
    "placetype": [
      "aat:300006191"
    ],
    "id": 2196853,
    "name:xx": "Brooks Lake"
  }
}
