{
  "geometry": {
    "type": "Point",
    "coordinates": [
      -96.7833,
      33.1333
    ]
  },
  "type": "Feature",
  "properties": {
    "hierarchy": [
      "tgn:1135049",
      "tgn:1000001",
      "tgn:7012149",
      "tgn:7007826",
      "tgn:7029392"
    ],
    "placetype": [
      "aat:300008706"
    ],
    "id": 1135049,
    "name:xx": "White Rock Creek"
  }
}
