{
  "type": "FeatureCollection",
  "features": [
    {
      "geometry": {
        "type": "Point",
        "coordinates": [
          36.1333,
          11.4167
        ]
      },
      "type": "Feature",
      "properties": {
        "hierarchy": [
          "tgn:1103910",
          "tgn:7001242",
          "tgn:1001266",
          "tgn:7000489",
          "tgn:7029392"
        ],
        "placetype": [
          "aat:300008795"
        ],
        "id": 1103910,
        "name:xx": "Belaya"
      }
    },
    {
      "geometry": {
        "type": "Point",
        "coordinates": [
          7.833333,
          47.816667
        ]
      },
      "type": "Feature",
      "properties": {
        "hierarchy": [
          "tgn:1103911",
          "tgn:7003692",
          "tgn:1000003",
          "tgn:7000084",
          "tgn:7029392"
        ],
        "placetype": [
          "aat:300008795"
        ],
        "id": 1103911,
        "name:xx": "Belchen"
      }
    },
    {
      "geometry": {
        "type": "Point",
        "coordinates": [
          -74.4833,
          42.1
        ]
      },
      "type": "Feature",
      "properties": {
        "hierarchy": [
          "tgn:1103914",
          "tgn:1000001",
          "tgn:7012149",
          "tgn:1002961",
          "tgn:7007568",
          "tgn:7029392"
        ],
        "placetype": [
          "aat:300008795"
        ],
        "id": 1103914,
        "name:xx": "Belle Ayr Mountain"
      }
    },
    {
      "geometry": {
        "type": "Point",
        "coordinates": [
          -61.7667,
          16.2667
        ]
      },
      "type": "Feature",
      "properties": {
        "hierarchy": [
          "tgn:1103915",
          "tgn:7018312",
          "tgn:1006440",
          "tgn:1000001",
          "tgn:7004545",
          "tgn:7029392"
        ],
        "placetype": [
          "aat:300008795"
        ],
        "id": 1103915,
        "name:xx": "Belle Hôtesse"
      }
    },
    {
      "geometry": {
        "type": "Point",
        "coordinates": [
          86.6667,
          49.8
        ]
      },
      "type": "Feature",
      "properties": {
        "hierarchy": [
          "tgn:1103916",
          "tgn:1000004",
          "tgn:7029392"
        ],
        "placetype": [
          "aat:300008795"
        ],
        "id": 1103916,
        "name:xx": "Belucha, gora"
      }
    }
  ]
}
