{
  "type": "FeatureCollection",
  "features": [
    {
      "geometry": {
        "type": "Point",
        "coordinates": [
          -101.5,
          41.5833
        ]
      },
      "type": "Feature",
      "properties": {
        "hierarchy": [
          "tgn:2299360",
          "tgn:2001318",
          "tgn:1000001",
          "tgn:7012149",
          "tgn:7007525",
          "tgn:7029392"
        ],
        "placetype": [
          "aat:300008680"
        ],
        "id": 2299360,
        "name:xx": "Duck Lake"
      }
    },
    {
      "geometry": {
        "type": "Point",
        "coordinates": [
          -118.6167,
          39.6833
        ]
      },
      "type": "Feature",
      "properties": {
        "hierarchy": [
          "tgn:2299361",
          "tgn:1000001",
          "tgn:2001409",
          "tgn:7012149",
          "tgn:7007526",
          "tgn:7029392"
        ],
        "placetype": [
          "aat:300008680"
        ],
        "id": 2299361,
        "name:xx": "Duck Lake"
      }
    },
    {
      "geometry": {
        "type": "Point",
        "coordinates": [
          -105.9667,
          33.8
        ]
      },
      "type": "Feature",
      "properties": {
        "hierarchy": [
          "tgn:2299362",
          "tgn:1000001",
          "tgn:7012149",
          "tgn:2001442",
          "tgn:7007566",
          "tgn:7029392"
        ],
        "placetype": [
          "aat:300008680"
        ],
        "id": 2299362,
        "name:xx": "Duck Lake"
      }
    },
    {
      "geometry": {
        "type": "Point",
        "coordinates": [
          -76.6833,
          43.1333
        ]
      },
      "type": "Feature",
      "properties": {
        "hierarchy": [
          "tgn:2299363",
          "tgn:1000001",
          "tgn:1002246",
          "tgn:7012149",
          "tgn:7007568",
          "tgn:7029392"
        ],
        "placetype": [
          "aat:300008680"
        ],
        "id": 2299363,
        "name:xx": "Duck Lake"
      }
    },
    {
      "geometry": {
        "type": "Point",
        "coordinates": [
          -74.45,
          43.2333
        ]
      },
      "type": "Feature",
      "properties": {
        "hierarchy": [
          "tgn:2299364",
          "tgn:1000001",
          "tgn:7012149",
          "tgn:7007568",
          "tgn:7029392"
        ],
        "placetype": [
          "aat:300008680"
        ],
        "id": 2299364,
        "name:xx": "Duck Lake"
      }
    },
    {
      "geometry": {
        "type": "Point",
        "coordinates": [
          -74.4333,
          44.1
        ]
      },
      "type": "Feature",
      "properties": {
        "hierarchy": [
          "tgn:2299365",
          "tgn:1000001",
          "tgn:7012149",
          "tgn:7013941",
          "tgn:7007568",
          "tgn:7029392"
        ],
        "placetype": [
          "aat:300008680"
        ],
        "id": 2299365,
        "name:xx": "Duck Lake"
      }
    },
    {
      "geometry": {
        "type": "Point",
        "coordinates": [
          -79.9,
          35.3167
        ]
      },
      "type": "Feature",
      "properties": {
        "hierarchy": [
          "tgn:2299366",
          "tgn:1000001",
          "tgn:7012149",
          "tgn:2001520",
          "tgn:7007709",
          "tgn:7029392"
        ],
        "placetype": [
          "aat:300006191"
        ],
        "id": 2299366,
        "name:xx": "Duck Lake"
      }
    },
    {
      "geometry": {
        "type": "Point",
        "coordinates": [
          -99.65,
          47.5167
        ]
      },
      "type": "Feature",
      "properties": {
        "hierarchy": [
          "tgn:2299367",
          "tgn:1000001",
          "tgn:7012149",
          "tgn:2001608",
          "tgn:7007705",
          "tgn:7029392"
        ],
        "placetype": [
          "aat:300008680"
        ],
        "id": 2299367,
        "name:xx": "Duck Lake"
      }
    },
    {
      "geometry": {
        "type": "Point",
        "coordinates": [
          -100.3833,
          48.9167
        ]
      },
      "type": "Feature",
      "properties": {
        "hierarchy": [
          "tgn:2299368",
          "tgn:7020393",
          "tgn:1000001",
          "tgn:7012149",
          "tgn:7007705",
          "tgn:7029392"
        ],
        "placetype": [
          "aat:300008680"
        ],
        "id": 2299368,
        "name:xx": "Duck Lake"
      }
    },
    {
      "geometry": {
        "type": "Point",
        "coordinates": [
          -117,
          45.0833
        ]
      },
      "type": "Feature",
      "properties": {
        "hierarchy": [
          "tgn:2299369",
          "tgn:1000001",
          "tgn:7012149",
          "tgn:2001722",
          "tgn:7007708",
          "tgn:7029392"
        ],
        "placetype": [
          "aat:300008680"
        ],
        "id": 2299369,
        "name:xx": "Duck Lake"
      }
    }
  ]
}
