{
  "geometry": {
    "type": "Point",
    "coordinates": [
      -89.5167,
      46.3833
    ]
  },
  "type": "Feature",
  "properties": {
    "hierarchy": [
      "tgn:2715218",
      "tgn:1000001",
      "tgn:7012149",
      "tgn:2000966",
      "tgn:7007520",
      "tgn:7029392"
    ],
    "placetype": [
      "aat:300008680"
    ],
    "id": 2715218,
    "name:xx": "Tepee Lake"
  }
}
