{
  "geometry": {
    "type": "Point",
    "coordinates": [
      -120.8667,
      37.8333
    ]
  },
  "type": "Feature",
  "properties": {
    "hierarchy": [
      "tgn:2708980",
      "tgn:1000001",
      "tgn:7012149",
      "tgn:7007157",
      "tgn:1002915",
      "tgn:7029392"
    ],
    "placetype": [
      "aat:300008791"
    ],
    "id": 2708980,
    "name:xx": "T Island"
  }
}
