{
  "geometry": {
    "type": "Point",
    "coordinates": [
      -108.7833,
      37.2333
    ]
  },
  "type": "Feature",
  "properties": {
    "hierarchy": [
      "tgn:2703886",
      "tgn:1000001",
      "tgn:7012149",
      "tgn:2000233",
      "tgn:7007158",
      "tgn:7029392"
    ],
    "placetype": [
      "aat:300055621"
    ],
    "id": 2703886,
    "name:xx": "Sundance Ground"
  }
}
