{
  "geometry": {
    "type": "Point",
    "coordinates": [
      30.776315,
      30.690232
    ]
  },
  "type": "Feature",
  "properties": {
    "hierarchy": [
      "tgn:7523684",
      "tgn:7001242",
      "tgn:1001075",
      "tgn:7016833",
      "tgn:7029392"
    ],
    "placetype": [
      "aat:300008347"
    ],
    "name:en": "Aş Şawwāf",
    "id": 7523684
  }
}
