{
  "geometry": {
    "type": "Point",
    "coordinates": [
      -95.05,
      41.85
    ]
  },
  "type": "Feature",
  "properties": {
    "hierarchy": [
      "tgn:2466485",
      "tgn:1000001",
      "tgn:7012149",
      "tgn:7007253",
      "tgn:7029392"
    ],
    "placetype": [
      "aat:300008699"
    ],
    "id": 2466485,
    "name:xx": "Long Branch"
  }
}
