{
  "geometry": {
    "type": "Point",
    "coordinates": [
      10.116667,
      52.35
    ]
  },
  "type": "Feature",
  "properties": {
    "hierarchy": [
      "tgn:1039384",
      "tgn:1000003",
      "tgn:7003676",
      "tgn:7000084",
      "tgn:7029392"
    ],
    "placetype": [
      "aat:300008347"
    ],
    "id": 1039384,
    "name:xx": "Hämelerwald"
  }
}
