{
  "type": "FeatureCollection",
  "features": [
    {
      "geometry": {
        "type": "Point",
        "coordinates": [
          24,
          40.05
        ]
      },
      "type": "Feature",
      "properties": {
        "hierarchy": [
          "tgn:7221100",
          "tgn:7011170",
          "tgn:7002715",
          "tgn:1000003",
          "tgn:1000074",
          "tgn:7029392"
        ],
        "placetype": [
          "aat:300008347"
        ],
        "id": 7221100,
        "name:xx": "Valtí"
      }
    },
    {
      "geometry": {
        "type": "Point",
        "coordinates": [
          22.283333,
          37.483333
        ]
      },
      "type": "Feature",
      "properties": {
        "hierarchy": [
          "tgn:7221101",
          "tgn:7002739",
          "tgn:7017076",
          "tgn:1000003",
          "tgn:1000074",
          "tgn:7029392"
        ],
        "placetype": [
          "aat:300008347"
        ],
        "id": 7221101,
        "name:xx": "Valtétsion"
      }
    },
    {
      "geometry": {
        "type": "Point",
        "coordinates": [
          22.1,
          37.716667
        ]
      },
      "type": "Feature",
      "properties": {
        "hierarchy": [
          "tgn:7221102",
          "tgn:7002739",
          "tgn:7017076",
          "tgn:1000003",
          "tgn:1000074",
          "tgn:7029392"
        ],
        "placetype": [
          "aat:300008347"
        ],
        "id": 7221102,
        "name:xx": "Valtesiníkon"
      }
    },
    {
      "geometry": {
        "type": "Point",
        "coordinates": [
          23.316667,
          41.183333
        ]
      },
      "type": "Feature",
      "properties": {
        "hierarchy": [
          "tgn:7221103",
          "tgn:7002725",
          "tgn:7002715",
          "tgn:1000003",
          "tgn:1000074",
          "tgn:7029392"
        ],
        "placetype": [
          "aat:300008347"
        ],
        "id": 7221103,
        "name:xx": "Valterón"
      }
    },
    {
      "geometry": {
        "type": "Point",
        "coordinates": [
          22.066667,
          38.116667
        ]
      },
      "type": "Feature",
      "properties": {
        "hierarchy": [
          "tgn:7221104",
          "tgn:7002741",
          "tgn:7017076",
          "tgn:1000003",
          "tgn:1000074",
          "tgn:7029392"
        ],
        "placetype": [
          "aat:300008347"
        ],
        "id": 7221104,
        "name:xx": "Válta"
      }
    },
    {
      "geometry": {
        "type": "Point",
        "coordinates": [
          21.633333,
          37.1
        ]
      },
      "type": "Feature",
      "properties": {
        "hierarchy": [
          "tgn:7221105",
          "tgn:7011369",
          "tgn:7017076",
          "tgn:1000003",
          "tgn:1000074",
          "tgn:7029392"
        ],
        "placetype": [
          "aat:300008347"
        ],
        "id": 7221105,
        "name:xx": "Válta"
      }
    },
    {
      "geometry": {
        "type": "Point",
        "coordinates": [
          20.6,
          38.166667
        ]
      },
      "type": "Feature",
      "properties": {
        "hierarchy": [
          "tgn:7221106",
          "tgn:7011167",
          "tgn:7001338",
          "tgn:1000003",
          "tgn:1000074",
          "tgn:7029392"
        ],
        "placetype": [
          "aat:300008347"
        ],
        "id": 7221106,
        "name:xx": "Valsamáta"
      }
    },
    {
      "geometry": {
        "type": "Point",
        "coordinates": [
          21.55,
          37.9
        ]
      },
      "type": "Feature",
      "properties": {
        "hierarchy": [
          "tgn:7221107",
          "tgn:7002743",
          "tgn:7017076",
          "tgn:1000003",
          "tgn:1000074",
          "tgn:7029392"
        ],
        "placetype": [
          "aat:300008347"
        ],
        "id": 7221107,
        "name:xx": "Válmi"
      }
    },
    {
      "geometry": {
        "type": "Point",
        "coordinates": [
          21.210278,
          39.067222
        ]
      },
      "type": "Feature",
      "properties": {
        "hierarchy": [
          "tgn:7221108",
          "tgn:7002680",
          "tgn:7001395",
          "tgn:1000003",
          "tgn:1000074",
          "tgn:7029392"
        ],
        "placetype": [
          "aat:300008347"
        ],
        "id": 7221108,
        "name:xx": "Valmáda"
      }
    },
    {
      "geometry": {
        "type": "Point",
        "coordinates": [
          20.566667,
          38.3
        ]
      },
      "type": "Feature",
      "properties": {
        "hierarchy": [
          "tgn:7221109",
          "tgn:7011167",
          "tgn:7001338",
          "tgn:1000003",
          "tgn:1000074",
          "tgn:7029392"
        ],
        "placetype": [
          "aat:300008347"
        ],
        "id": 7221109,
        "name:xx": "Vallianáta"
      }
    }
  ]
}
