{
  "geometry": {
    "type": "Point",
    "coordinates": [
      -121.1333,
      48.2833
    ]
  },
  "type": "Feature",
  "properties": {
    "hierarchy": [
      "tgn:2581516",
      "tgn:1000001",
      "tgn:7012149",
      "tgn:1002899",
      "tgn:7007920",
      "tgn:7029392"
    ],
    "placetype": [
      "aat:300008680"
    ],
    "id": 2581516,
    "name:xx": "Pilot Lake"
  }
}
