{
  "geometry": {
    "type": "Point",
    "coordinates": [
      -136.1833,
      57.9833
    ]
  },
  "type": "Feature",
  "properties": {
    "hierarchy": [
      "tgn:2755635",
      "tgn:7006450",
      "tgn:1000001",
      "tgn:7012149",
      "tgn:7019760",
      "tgn:7029392"
    ],
    "placetype": [
      "aat:300008798"
    ],
    "id": 2755635,
    "name:xx": "Wedge Mountain"
  }
}
