{
  "geometry": {
    "type": "Point",
    "coordinates": [
      -90.8167,
      32.05
    ]
  },
  "type": "Feature",
  "properties": {
    "hierarchy": [
      "tgn:2605411",
      "tgn:1000001",
      "tgn:2001096",
      "tgn:7012149",
      "tgn:7007522",
      "tgn:7029392"
    ],
    "placetype": [
      "aat:300008706"
    ],
    "id": 2605411,
    "name:xx": "Ragsdall Creek"
  }
}
