{
  "geometry": {
    "type": "Point",
    "coordinates": [
      -77.1167,
      7.45
    ]
  },
  "type": "Feature",
  "properties": {
    "hierarchy": [
      "tgn:1129439",
      "tgn:7016640",
      "tgn:1000050",
      "tgn:1000002",
      "tgn:7029392"
    ],
    "placetype": [
      "aat:300008707"
    ],
    "id": 1129439,
    "name:xx": "Salaquí"
  }
}
