{
  "geometry": {
    "type": "Point",
    "coordinates": [
      121.7093,
      25.1303
    ]
  },
  "type": "Feature",
  "properties": {
    "hierarchy": [
      "tgn:7497902",
      "tgn:1000957",
      "tgn:1000004",
      "tgn:1000141",
      "tgn:7029392"
    ],
    "placetype": [
      "aat:300006191"
    ],
    "id": 7497902,
    "name:xx": "Xinshan Shuiku"
  }
}
