{
  "geometry": {
    "type": "Point",
    "coordinates": [
      -81.0833,
      35.3667
    ]
  },
  "type": "Feature",
  "properties": {
    "hierarchy": [
      "tgn:2264787",
      "tgn:1000001",
      "tgn:7012149",
      "tgn:2001496",
      "tgn:7007709",
      "tgn:7029392"
    ],
    "placetype": [
      "aat:300008347"
    ],
    "id": 2264787,
    "name:xx": "Craig Heights"
  }
}
