{
  "geometry": {
    "type": "Point",
    "coordinates": [
      -112.4333,
      33.5333
    ]
  },
  "type": "Feature",
  "properties": {
    "hierarchy": [
      "tgn:2006666",
      "tgn:1000001",
      "tgn:7006451",
      "tgn:7012149",
      "tgn:2000097",
      "tgn:7029392"
    ],
    "placetype": [
      "aat:300387016"
    ],
    "id": 2006666,
    "name:xx": "Citrus Park"
  }
}
