{
  "geometry": {
    "type": "Point",
    "coordinates": [
      -104.45,
      44.4833
    ]
  },
  "type": "Feature",
  "properties": {
    "hierarchy": [
      "tgn:2477543",
      "tgn:1000001",
      "tgn:2002370",
      "tgn:7012149",
      "tgn:7007923",
      "tgn:7029392"
    ],
    "placetype": [
      "aat:300008706"
    ],
    "id": 2477543,
    "name:xx": "Lytle Creek"
  }
}
