{
  "geometry": {
    "type": "Point",
    "coordinates": [
      -78.75,
      38.1333
    ]
  },
  "type": "Feature",
  "properties": {
    "hierarchy": [
      "tgn:2645605",
      "tgn:2002137",
      "tgn:1000001",
      "tgn:7012149",
      "tgn:7007919",
      "tgn:7029392"
    ],
    "placetype": [
      "aat:300266640"
    ],
    "id": 2645605,
    "name:xx": "Sawlog Ridge"
  }
}
