{
  "geometry": {
    "type": "Point",
    "coordinates": [
      66.9833,
      54.3667
    ]
  },
  "type": "Feature",
  "properties": {
    "hierarchy": [
      "tgn:1137296",
      "tgn:1000004",
      "tgn:7012930",
      "tgn:7014786",
      "tgn:7029392"
    ],
    "placetype": [
      "aat:300008347"
    ],
    "id": 1137296,
    "name:xx": "Blagoveshchenka"
  }
}
