{
  "geometry": {
    "type": "Point",
    "coordinates": [
      -78.2667,
      34.0167
    ]
  },
  "type": "Feature",
  "properties": {
    "hierarchy": [
      "tgn:2076850",
      "tgn:1000001",
      "tgn:2001472",
      "tgn:7012149",
      "tgn:7007709",
      "tgn:7029392"
    ],
    "placetype": [
      "aat:300008347"
    ],
    "id": 2076850,
    "name:xx": "Supply"
  }
}
