{
  "type": "FeatureCollection",
  "features": [
    {
      "geometry": {
        "type": "Point",
        "coordinates": [
          -70.233333,
          -34.116667
        ]
      },
      "type": "Feature",
      "properties": {
        "hierarchy": [
          "tgn:7313620",
          "tgn:1001695",
          "tgn:1000049",
          "tgn:1000002",
          "tgn:7029392"
        ],
        "placetype": [
          "aat:300008699"
        ],
        "id": 7313620,
        "name:xx": "La Vuelta, Quebrada"
      }
    },
    {
      "geometry": {
        "type": "Point",
        "coordinates": [
          -72.116667,
          -35
        ]
      },
      "type": "Feature",
      "properties": {
        "hierarchy": [
          "tgn:7313621",
          "tgn:1001705",
          "tgn:1000049",
          "tgn:1000002",
          "tgn:7029392"
        ],
        "placetype": [
          "aat:300387200"
        ],
        "id": 7313621,
        "name:xx": "La Vuelta"
      }
    },
    {
      "geometry": {
        "type": "Point",
        "coordinates": [
          -73.116667,
          -36.7
        ]
      },
      "type": "Feature",
      "properties": {
        "hierarchy": [
          "tgn:7313622",
          "tgn:1001637",
          "tgn:1000049",
          "tgn:1000002",
          "tgn:7029392"
        ],
        "placetype": [
          "aat:300011692"
        ],
        "id": 7313622,
        "name:xx": "La Viuda, Roca"
      }
    },
    {
      "geometry": {
        "type": "Point",
        "coordinates": [
          -70.433333,
          -27.766667
        ]
      },
      "type": "Feature",
      "properties": {
        "hierarchy": [
          "tgn:7313623",
          "tgn:1001630",
          "tgn:1000049",
          "tgn:1000002",
          "tgn:7029392"
        ],
        "placetype": [
          "aat:300259572"
        ],
        "id": 7313623,
        "name:xx": "La Viuda, Portezuelo"
      }
    },
    {
      "geometry": {
        "type": "Point",
        "coordinates": [
          -72.816667,
          -52.6
        ]
      },
      "type": "Feature",
      "properties": {
        "hierarchy": [
          "tgn:7313624",
          "tgn:1001702",
          "tgn:1000049",
          "tgn:1000002",
          "tgn:7029392"
        ],
        "placetype": [
          "aat:300008791"
        ],
        "id": 7313624,
        "name:xx": "La Viuda, Islote"
      }
    },
    {
      "geometry": {
        "type": "Point",
        "coordinates": [
          -70.433333,
          -27.783333
        ]
      },
      "type": "Feature",
      "properties": {
        "hierarchy": [
          "tgn:7313625",
          "tgn:1001630",
          "tgn:1000049",
          "tgn:1000002",
          "tgn:7029392"
        ],
        "placetype": [
          "aat:300008795"
        ],
        "id": 7313625,
        "name:xx": "La Viuda, Cerro"
      }
    },
    {
      "geometry": {
        "type": "Point",
        "coordinates": [
          -72,
          -40.45
        ]
      },
      "type": "Feature",
      "properties": {
        "hierarchy": [
          "tgn:7313626",
          "tgn:1001699",
          "tgn:1000049",
          "tgn:1000002",
          "tgn:7029392"
        ],
        "placetype": [
          "aat:300008699"
        ],
        "id": 7313626,
        "name:xx": "La Virgen, Estero"
      }
    },
    {
      "geometry": {
        "type": "Point",
        "coordinates": [
          -71.2,
          -34.7
        ]
      },
      "type": "Feature",
      "properties": {
        "hierarchy": [
          "tgn:7313627",
          "tgn:1001695",
          "tgn:1000049",
          "tgn:1000002",
          "tgn:7029392"
        ],
        "placetype": [
          "aat:300387002"
        ],
        "id": 7313627,
        "name:xx": "La Virgen, Cerro"
      }
    },
    {
      "geometry": {
        "type": "Point",
        "coordinates": [
          -71.95,
          -45.766667
        ]
      },
      "type": "Feature",
      "properties": {
        "hierarchy": [
          "tgn:7313628",
          "tgn:1001623",
          "tgn:1000049",
          "tgn:1000002",
          "tgn:7029392"
        ],
        "placetype": [
          "aat:300008795"
        ],
        "id": 7313628,
        "name:xx": "La Virgen, Cerro"
      }
    },
    {
      "geometry": {
        "type": "Point",
        "coordinates": [
          -71.983333,
          -34.533333
        ]
      },
      "type": "Feature",
      "properties": {
        "hierarchy": [
          "tgn:7313629",
          "tgn:1001695",
          "tgn:1000049",
          "tgn:1000002",
          "tgn:7029392"
        ],
        "placetype": [
          "aat:300008347"
        ],
        "id": 7313629,
        "name:xx": "La Viñuela"
      }
    }
  ]
}
