{
  "geometry": {
    "type": "Point",
    "coordinates": [
      2.65,
      42.5833
    ]
  },
  "type": "Feature",
  "properties": {
    "hierarchy": [
      "tgn:1108734",
      "tgn:7002878",
      "tgn:1000003",
      "tgn:1000070",
      "tgn:7029392"
    ],
    "placetype": [
      "aat:300008795"
    ],
    "id": 1108734,
    "name:xx": "Les Aspres"
  }
}
