{
  "geometry": {
    "type": "Point",
    "coordinates": [
      -84.5167,
      40.1167
    ]
  },
  "type": "Feature",
  "properties": {
    "hierarchy": [
      "tgn:2275968",
      "tgn:1000001",
      "tgn:1002317",
      "tgn:7012149",
      "tgn:7007706",
      "tgn:7029392"
    ],
    "placetype": [
      "aat:300006191"
    ],
    "id": 2275968,
    "name:xx": "Darke Company Lake Wildlife Area Pond"
  }
}
