{
  "geometry": {
    "type": "Point",
    "coordinates": [
      -71.5833,
      42.6167
    ]
  },
  "type": "Feature",
  "properties": {
    "hierarchy": [
      "tgn:2567482",
      "tgn:1000001",
      "tgn:1002665",
      "tgn:7012149",
      "tgn:7007517",
      "tgn:7029392"
    ],
    "placetype": [
      "aat:300008347"
    ],
    "id": 2567482,
    "name:xx": "Paper Mill Village"
  }
}
