{
  "geometry": {
    "type": "Point",
    "coordinates": [
      120.7204,
      23.9585
    ]
  },
  "type": "Feature",
  "properties": {
    "hierarchy": [
      "tgn:7494391",
      "tgn:7488858",
      "tgn:1000004",
      "tgn:1000141",
      "tgn:7029392"
    ],
    "placetype": [
      "aat:300008347"
    ],
    "id": 7494391,
    "name:xx": "Fengshuiping"
  }
}
