{
  "type": "FeatureCollection",
  "features": [
    {
      "geometry": {
        "type": "Point",
        "coordinates": [
          8.283333,
          47.983333
        ]
      },
      "type": "Feature",
      "properties": {
        "hierarchy": [
          "tgn:7065260",
          "tgn:7003692",
          "tgn:1000003",
          "tgn:7000084",
          "tgn:7029392"
        ],
        "placetype": [
          "aat:300000206"
        ],
        "id": 7065260,
        "name:xx": "Steingremmen"
      }
    },
    {
      "geometry": {
        "type": "Point",
        "coordinates": [
          11.766667,
          47.816667
        ]
      },
      "type": "Feature",
      "properties": {
        "hierarchy": [
          "tgn:7065261",
          "tgn:7003669",
          "tgn:1000003",
          "tgn:7000084",
          "tgn:7029392"
        ],
        "placetype": [
          "aat:300000206"
        ],
        "id": 7065261,
        "name:xx": "Steingraber"
      }
    },
    {
      "geometry": {
        "type": "Point",
        "coordinates": [
          11,
          51.216667
        ]
      },
      "type": "Feature",
      "properties": {
        "hierarchy": [
          "tgn:7065262",
          "tgn:1000003",
          "tgn:7003689",
          "tgn:7000084",
          "tgn:7029392"
        ],
        "placetype": [
          "aat:300008699"
        ],
        "id": 7065262,
        "name:xx": "Stein-Graben"
      }
    },
    {
      "geometry": {
        "type": "Point",
        "coordinates": [
          9.833333,
          49.883333
        ]
      },
      "type": "Feature",
      "properties": {
        "hierarchy": [
          "tgn:7065263",
          "tgn:7003669",
          "tgn:1000003",
          "tgn:7000084",
          "tgn:7029392"
        ],
        "placetype": [
          "aat:300008699"
        ],
        "id": 7065263,
        "name:xx": "Stein-Graben"
      }
    },
    {
      "geometry": {
        "type": "Point",
        "coordinates": [
          11.15,
          49.683333
        ]
      },
      "type": "Feature",
      "properties": {
        "hierarchy": [
          "tgn:7065264",
          "tgn:7003669",
          "tgn:1000003",
          "tgn:7000084",
          "tgn:7029392"
        ],
        "placetype": [
          "aat:300008699"
        ],
        "id": 7065264,
        "name:xx": "Stein-Graben"
      }
    },
    {
      "geometry": {
        "type": "Point",
        "coordinates": [
          12.65,
          47.866667
        ]
      },
      "type": "Feature",
      "properties": {
        "hierarchy": [
          "tgn:7065265",
          "tgn:7003669",
          "tgn:1000003",
          "tgn:7000084",
          "tgn:7029392"
        ],
        "placetype": [
          "aat:300008699"
        ],
        "id": 7065265,
        "name:xx": "Stein-Graben"
      }
    },
    {
      "geometry": {
        "type": "Point",
        "coordinates": [
          11.716667,
          47.733333
        ]
      },
      "type": "Feature",
      "properties": {
        "hierarchy": [
          "tgn:7065266",
          "tgn:7003669",
          "tgn:1000003",
          "tgn:7000084",
          "tgn:7029392"
        ],
        "placetype": [
          "aat:300008699"
        ],
        "id": 7065266,
        "name:xx": "Stein Graben"
      }
    },
    {
      "geometry": {
        "type": "Point",
        "coordinates": [
          11.466667,
          47.7
        ]
      },
      "type": "Feature",
      "properties": {
        "hierarchy": [
          "tgn:7065267",
          "tgn:7003669",
          "tgn:1000003",
          "tgn:7000084",
          "tgn:7029392"
        ],
        "placetype": [
          "aat:300008699"
        ],
        "id": 7065267,
        "name:xx": "Stein Graben"
      }
    },
    {
      "geometry": {
        "type": "Point",
        "coordinates": [
          11.383333,
          47.666667
        ]
      },
      "type": "Feature",
      "properties": {
        "hierarchy": [
          "tgn:7065268",
          "tgn:7003669",
          "tgn:1000003",
          "tgn:7000084",
          "tgn:7029392"
        ],
        "placetype": [
          "aat:300008699"
        ],
        "id": 7065268,
        "name:xx": "Stein Graben"
      }
    },
    {
      "geometry": {
        "type": "Point",
        "coordinates": [
          11.7,
          51.183333
        ]
      },
      "type": "Feature",
      "properties": {
        "hierarchy": [
          "tgn:7065269",
          "tgn:1000003",
          "tgn:7003687",
          "tgn:7000084",
          "tgn:7029392"
        ],
        "placetype": [
          "aat:300008773"
        ],
        "id": 7065269,
        "name:xx": "Stein-Graben"
      }
    }
  ]
}
