{
  "geometry": {
    "type": "Point",
    "coordinates": [
      -81.4333,
      41.4833
    ]
  },
  "type": "Feature",
  "properties": {
    "hierarchy": [
      "tgn:2560151",
      "tgn:1000001",
      "tgn:1002313",
      "tgn:7012149",
      "tgn:7007706",
      "tgn:7029392"
    ],
    "placetype": [
      "aat:300008798"
    ],
    "id": 2560151,
    "name:xx": "Orange Hill"
  }
}
