{
  "geometry": {
    "type": "Point",
    "coordinates": [
      -83.4667,
      35.2333
    ]
  },
  "type": "Feature",
  "properties": {
    "hierarchy": [
      "tgn:2280063",
      "tgn:1000001",
      "tgn:7012149",
      "tgn:2001515",
      "tgn:7007709",
      "tgn:7029392"
    ],
    "placetype": [
      "aat:300008347"
    ],
    "id": 2280063,
    "name:xx": "Deans Mill"
  }
}
