{
  "geometry": {
    "type": "Point",
    "coordinates": [
      -89.3333,
      34.7667
    ]
  },
  "type": "Feature",
  "properties": {
    "hierarchy": [
      "tgn:2235998",
      "tgn:1000001",
      "tgn:7012149",
      "tgn:2001132",
      "tgn:7007522",
      "tgn:7029392"
    ],
    "placetype": [
      "aat:300006191"
    ],
    "id": 2235998,
    "name:xx": "Chewalla Lake"
  }
}
