{
  "geometry": {
    "type": "Point",
    "coordinates": [
      -87.5833,
      39.5833
    ]
  },
  "type": "Feature",
  "properties": {
    "hierarchy": [
      "tgn:2410716",
      "tgn:1000001",
      "tgn:2000504",
      "tgn:7012149",
      "tgn:7007251",
      "tgn:7029392"
    ],
    "placetype": [
      "aat:300008706"
    ],
    "id": 2410716,
    "name:xx": "Indian Creek"
  }
}
