{
  "geometry": {
    "type": "Point",
    "coordinates": [
      -112.8667,
      37.7667
    ]
  },
  "type": "Feature",
  "properties": {
    "hierarchy": [
      "tgn:2274544",
      "tgn:1000001",
      "tgn:7012149",
      "tgn:2002111",
      "tgn:7007827",
      "tgn:7029392"
    ],
    "placetype": [
      "aat:300008761"
    ],
    "id": 2274544,
    "name:xx": "Dalley Canyon"
  }
}
