{
  "geometry": {
    "type": "Point",
    "coordinates": [
      -108.7667,
      36.3833
    ]
  },
  "type": "Feature",
  "properties": {
    "hierarchy": [
      "tgn:2067616",
      "tgn:1000001",
      "tgn:7012149",
      "tgn:2001452",
      "tgn:7007566",
      "tgn:7029392"
    ],
    "placetype": [
      "aat:300008347",
      "aat:300387210"
    ],
    "id": 2067616,
    "name:xx": "Tocito"
  }
}
