{
  "geometry": {
    "type": "Point",
    "coordinates": [
      -81.7333,
      36.6167
    ]
  },
  "type": "Feature",
  "properties": {
    "hierarchy": [
      "tgn:2315301",
      "tgn:1000001",
      "tgn:7012149",
      "tgn:7029392"
    ],
    "placetype": [
      "aat:300008699"
    ],
    "id": 2315301,
    "name:xx": "Elliot Branch"
  }
}
