{
  "geometry": {
    "type": "Point",
    "coordinates": [
      78.906472,
      24.61277
    ]
  },
  "type": "Feature",
  "properties": {
    "hierarchy": [
      "tgn:7585257",
      "tgn:1000004",
      "tgn:7000198",
      "tgn:1001894",
      "tgn:7029392"
    ],
    "placetype": [
      "aat:300008347"
    ],
    "name:en": "Kenwār",
    "id": 7585257
  }
}
