{
  "type": "FeatureCollection",
  "features": [
    {
      "geometry": {
        "type": "Point",
        "coordinates": [
          -83.0333,
          35.8333
        ]
      },
      "type": "Feature",
      "properties": {
        "hierarchy": [
          "tgn:2617870",
          "tgn:1000001",
          "tgn:7012149",
          "tgn:2001851",
          "tgn:7007825",
          "tgn:7029392"
        ],
        "placetype": [
          "aat:300008761"
        ],
        "id": 2617870,
        "name:xx": "Ridge Hollow"
      }
    },
    {
      "geometry": {
        "type": "Point",
        "coordinates": [
          -78.6667,
          38.85
        ]
      },
      "type": "Feature",
      "properties": {
        "hierarchy": [
          "tgn:2617871",
          "tgn:1000001",
          "tgn:7012149",
          "tgn:2002190",
          "tgn:7007919",
          "tgn:7029392"
        ],
        "placetype": [
          "aat:300008761"
        ],
        "id": 2617871,
        "name:xx": "Ridge Hollow"
      }
    },
    {
      "geometry": {
        "type": "Point",
        "coordinates": [
          -133.2,
          55.2667
        ]
      },
      "type": "Feature",
      "properties": {
        "hierarchy": [
          "tgn:2617872",
          "tgn:7006450",
          "tgn:1000001",
          "tgn:7012149",
          "tgn:2000082",
          "tgn:7029392"
        ],
        "placetype": [
          "aat:300008791"
        ],
        "id": 2617872,
        "name:xx": "Ridge Island"
      }
    },
    {
      "geometry": {
        "type": "Point",
        "coordinates": [
          -72.9,
          40.7167
        ]
      },
      "type": "Feature",
      "properties": {
        "hierarchy": [
          "tgn:2617873",
          "tgn:1000001",
          "tgn:7012149",
          "tgn:1002924",
          "tgn:7007568",
          "tgn:7029392"
        ],
        "placetype": [
          "aat:300008791"
        ],
        "id": 2617873,
        "name:xx": "Ridge Island"
      }
    },
    {
      "geometry": {
        "type": "Point",
        "coordinates": [
          -124.3667,
          42.2167
        ]
      },
      "type": "Feature",
      "properties": {
        "hierarchy": [
          "tgn:2617874",
          "tgn:1000001",
          "tgn:2001704",
          "tgn:7012149",
          "tgn:7007708",
          "tgn:7029392"
        ],
        "placetype": [
          "aat:300008798"
        ],
        "id": 2617874,
        "name:xx": "Ridge Knob"
      }
    },
    {
      "geometry": {
        "type": "Point",
        "coordinates": [
          -119.7333,
          38.2167
        ]
      },
      "type": "Feature",
      "properties": {
        "hierarchy": [
          "tgn:2617875",
          "tgn:1000001",
          "tgn:7012149",
          "tgn:7007157",
          "tgn:1002957",
          "tgn:7029392"
        ],
        "placetype": [
          "aat:300008680"
        ],
        "id": 2617875,
        "name:xx": "Ridge Lake"
      }
    },
    {
      "geometry": {
        "type": "Point",
        "coordinates": [
          -121.45,
          40.4
        ]
      },
      "type": "Feature",
      "properties": {
        "hierarchy": [
          "tgn:2617876",
          "tgn:1000001",
          "tgn:7012149",
          "tgn:7007157",
          "tgn:2000187",
          "tgn:7029392"
        ],
        "placetype": [
          "aat:300008680"
        ],
        "id": 2617876,
        "name:xx": "Ridge Lake"
      }
    },
    {
      "geometry": {
        "type": "Point",
        "coordinates": [
          -91.35,
          32.2
        ]
      },
      "type": "Feature",
      "properties": {
        "hierarchy": [
          "tgn:2617877",
          "tgn:1000001",
          "tgn:7012149",
          "tgn:2000886",
          "tgn:7007256",
          "tgn:7029392"
        ],
        "placetype": [
          "aat:300008680"
        ],
        "id": 2617877,
        "name:xx": "Ridge Lake"
      }
    },
    {
      "geometry": {
        "type": "Point",
        "coordinates": [
          -89.7667,
          46.2833
        ]
      },
      "type": "Feature",
      "properties": {
        "hierarchy": [
          "tgn:2617878",
          "tgn:1000001",
          "tgn:7012149",
          "tgn:2000960",
          "tgn:7007520",
          "tgn:7029392"
        ],
        "placetype": [
          "aat:300008680"
        ],
        "id": 2617878,
        "name:xx": "Ridge Lake"
      }
    },
    {
      "geometry": {
        "type": "Point",
        "coordinates": [
          -113.65,
          45.2833
        ]
      },
      "type": "Feature",
      "properties": {
        "hierarchy": [
          "tgn:2617879",
          "tgn:1000001",
          "tgn:2001260",
          "tgn:7012149",
          "tgn:7007524",
          "tgn:7029392"
        ],
        "placetype": [
          "aat:300008680"
        ],
        "id": 2617879,
        "name:xx": "Ridge Lake"
      }
    }
  ]
}
