{
  "geometry": {
    "type": "Point",
    "coordinates": [
      8.4167,
      49.1167
    ]
  },
  "type": "Feature",
  "properties": {
    "hierarchy": [
      "tgn:1040135",
      "tgn:7003692",
      "tgn:1000003",
      "tgn:7000084",
      "tgn:7029392"
    ],
    "placetype": [
      "aat:300008347"
    ],
    "id": 1040135,
    "name:xx": "Linkenheim"
  }
}
