{
  "geometry": {
    "type": "Point",
    "coordinates": [
      31.133333,
      29.333333
    ]
  },
  "type": "Feature",
  "properties": {
    "hierarchy": [
      "tgn:7535692",
      "tgn:7001242",
      "tgn:7016833",
      "tgn:1001142",
      "tgn:7029392"
    ],
    "placetype": [
      "aat:300008347"
    ],
    "name:en": "Ibwīţ al Qadīmah",
    "id": 7535692
  }
}
