{
  "geometry": {
    "type": "Point",
    "coordinates": [
      98.5167,
      8.4833
    ]
  },
  "type": "Feature",
  "properties": {
    "hierarchy": [
      "tgn:1085625",
      "tgn:7000939",
      "tgn:7005195",
      "tgn:1000004",
      "tgn:1000142",
      "tgn:7029392"
    ],
    "placetype": [
      "aat:300008347",
      "aat:300387223"
    ],
    "id": 1085625,
    "name:xx": "Phangnga"
  }
}
