{
  "geometry": {
    "type": "Point",
    "coordinates": [
      -74.6167,
      40.75
    ]
  },
  "type": "Feature",
  "properties": {
    "hierarchy": [
      "tgn:2587894",
      "tgn:1000001",
      "tgn:1002695",
      "tgn:7012149",
      "tgn:7007565",
      "tgn:7029392"
    ],
    "placetype": [
      "aat:300008680"
    ],
    "id": 2587894,
    "name:xx": "Pleasant Valley Lake"
  }
}
