{
  "type": "FeatureCollection",
  "features": [
    {
      "geometry": {
        "type": "Point",
        "coordinates": [
          -114.7833,
          47.1167
        ]
      },
      "type": "Feature",
      "properties": {
        "hierarchy": [
          "tgn:2061831",
          "tgn:1000001",
          "tgn:7012149",
          "tgn:2001290",
          "tgn:7007524",
          "tgn:7029392"
        ],
        "placetype": [
          "aat:300387016"
        ],
        "id": 2061831,
        "name:xx": "Westfall"
      }
    },
    {
      "geometry": {
        "type": "Point",
        "coordinates": [
          -113.9667,
          48.5
        ]
      },
      "type": "Feature",
      "properties": {
        "hierarchy": [
          "tgn:2061832",
          "tgn:1000001",
          "tgn:7012149",
          "tgn:2001274",
          "tgn:7007524",
          "tgn:7029392"
        ],
        "placetype": [
          "aat:300008347"
        ],
        "id": 2061832,
        "name:xx": "West Glacier"
      }
    },
    {
      "geometry": {
        "type": "Point",
        "coordinates": [
          -109.45,
          47.0833
        ]
      },
      "type": "Feature",
      "properties": {
        "hierarchy": [
          "tgn:2061833",
          "tgn:1000001",
          "tgn:7012149",
          "tgn:2001273",
          "tgn:7007524",
          "tgn:7029392"
        ],
        "placetype": [
          "aat:300008347"
        ],
        "id": 2061833,
        "name:xx": "West Lewistown"
      }
    },
    {
      "geometry": {
        "type": "Point",
        "coordinates": [
          -113.8833,
          46.8667
        ]
      },
      "type": "Feature",
      "properties": {
        "hierarchy": [
          "tgn:2061834",
          "tgn:1000001",
          "tgn:7012149",
          "tgn:2001291",
          "tgn:7007524",
          "tgn:7029392"
        ],
        "placetype": [
          "aat:300008347"
        ],
        "id": 2061834,
        "name:xx": "West Riverside"
      }
    },
    {
      "geometry": {
        "type": "Point",
        "coordinates": [
          -111.1,
          44.65
        ]
      },
      "type": "Feature",
      "properties": {
        "hierarchy": [
          "tgn:2061835",
          "tgn:1000001",
          "tgn:7012149",
          "tgn:2001275",
          "tgn:7007524",
          "tgn:7029392"
        ],
        "placetype": [
          "aat:300008347"
        ],
        "id": 2061835,
        "name:xx": "West Yellowstone"
      }
    },
    {
      "geometry": {
        "type": "Point",
        "coordinates": [
          -106.5,
          48
        ]
      },
      "type": "Feature",
      "properties": {
        "hierarchy": [
          "tgn:2061836",
          "tgn:1000001",
          "tgn:7012149",
          "tgn:2001312",
          "tgn:7007524",
          "tgn:7029392"
        ],
        "placetype": [
          "aat:300008347",
          "aat:300387210"
        ],
        "id": 2061836,
        "name:xx": "Wheeler"
      }
    },
    {
      "geometry": {
        "type": "Point",
        "coordinates": [
          -114.3333,
          48.4
        ]
      },
      "type": "Feature",
      "properties": {
        "hierarchy": [
          "tgn:2061837",
          "tgn:1000001",
          "tgn:7012149",
          "tgn:2001274",
          "tgn:7007524",
          "tgn:7029392"
        ],
        "placetype": [
          "aat:300008347"
        ],
        "id": 2061837,
        "name:xx": "Whitefish"
      }
    },
    {
      "geometry": {
        "type": "Point",
        "coordinates": [
          -112.0833,
          45.8667
        ]
      },
      "type": "Feature",
      "properties": {
        "hierarchy": [
          "tgn:2061838",
          "tgn:1000001",
          "tgn:7012149",
          "tgn:2001281",
          "tgn:7007524",
          "tgn:7029392"
        ],
        "placetype": [
          "aat:300008347"
        ],
        "id": 2061838,
        "name:xx": "Whitehall"
      }
    }
  ]
}
