{
  "geometry": {
    "type": "Point",
    "coordinates": [
      32.0075,
      31.023611
    ]
  },
  "type": "Feature",
  "properties": {
    "hierarchy": [
      "tgn:7534204",
      "tgn:7001242",
      "tgn:7016833",
      "tgn:1001123",
      "tgn:7029392"
    ],
    "placetype": [
      "aat:300008791"
    ],
    "name:en": "Maḥash, Gezîret el-",
    "id": 7534204
  }
}
