{
  "geometry": {
    "type": "Point",
    "coordinates": [
      -99.7833,
      32.75
    ]
  },
  "type": "Feature",
  "properties": {
    "hierarchy": [
      "tgn:2104383",
      "tgn:1000001",
      "tgn:7012149",
      "tgn:2002014",
      "tgn:7007826",
      "tgn:7029392"
    ],
    "placetype": [
      "aat:300008347",
      "aat:300387210"
    ],
    "id": 2104383,
    "name:xx": "Funston"
  }
}
