{
  "geometry": {
    "type": "Point",
    "coordinates": [
      -94.35,
      36.5333
    ]
  },
  "type": "Feature",
  "properties": {
    "hierarchy": [
      "tgn:2779612",
      "tgn:1000001",
      "tgn:7012149",
      "tgn:2001216",
      "tgn:7007523",
      "tgn:7029392"
    ],
    "placetype": [
      "aat:300008761"
    ],
    "id": 2779612,
    "name:xx": "Wolf Pen Hollow"
  }
}
