{
  "geometry": {
    "type": "Point",
    "coordinates": [
      -112.8667,
      38.2333
    ]
  },
  "type": "Feature",
  "properties": {
    "hierarchy": [
      "tgn:2588679",
      "tgn:2002101",
      "tgn:1000001",
      "tgn:7012149",
      "tgn:7007827",
      "tgn:7029392"
    ],
    "placetype": [
      "aat:300008697"
    ],
    "id": 2588679,
    "name:xx": "Plunge Spring"
  }
}
