{
  "geometry": {
    "type": "Point",
    "coordinates": [
      52.7833,
      54.8167
    ]
  },
  "type": "Feature",
  "properties": {
    "hierarchy": [
      "tgn:1052034",
      "tgn:1000004",
      "tgn:7002435",
      "tgn:7011524",
      "tgn:7029392"
    ],
    "placetype": [
      "aat:300008347"
    ],
    "id": 1052034,
    "name:xx": "Aktyubinskiy"
  }
}
