{
  "geometry": {
    "type": "Point",
    "coordinates": [
      30.560556,
      31.1475
    ]
  },
  "type": "Feature",
  "properties": {
    "hierarchy": [
      "tgn:7523009",
      "tgn:7001242",
      "tgn:1001075",
      "tgn:7016833",
      "tgn:7029392"
    ],
    "placetype": [
      "aat:300008347"
    ],
    "name:en": "Disyā al Kanā'is",
    "id": 7523009
  }
}
