{
  "geometry": {
    "type": "Point",
    "coordinates": [
      -83.0333,
      35.1167
    ]
  },
  "type": "Feature",
  "properties": {
    "hierarchy": [
      "tgn:2451269",
      "tgn:1000001",
      "tgn:7012149",
      "tgn:2001508",
      "tgn:7007709",
      "tgn:7029392"
    ],
    "placetype": [
      "aat:300008798"
    ],
    "id": 2451269,
    "name:xx": "Little Bald Rock Mountain"
  }
}
