{
  "type": "FeatureCollection",
  "features": [
    {
      "geometry": {
        "type": "Point",
        "coordinates": [
          -5.283333,
          40.833333
        ]
      },
      "type": "Feature",
      "properties": {
        "hierarchy": [
          "tgn:4006760",
          "tgn:7002835",
          "tgn:7001158",
          "tgn:1000003",
          "tgn:1000095",
          "tgn:7029392"
        ],
        "placetype": [
          "aat:300008347"
        ],
        "id": 4006760,
        "name:xx": "Macotera"
      }
    },
    {
      "geometry": {
        "type": "Point",
        "coordinates": [
          -3.516667,
          41.483333
        ]
      },
      "type": "Feature",
      "properties": {
        "hierarchy": [
          "tgn:4006765",
          "tgn:7002839",
          "tgn:7001158",
          "tgn:1000003",
          "tgn:1000095",
          "tgn:7029392"
        ],
        "placetype": [
          "aat:300008347"
        ],
        "id": 4006765,
        "name:xx": "Maderuelo"
      }
    },
    {
      "geometry": {
        "type": "Point",
        "coordinates": [
          14.383333,
          40.866667
        ]
      },
      "type": "Feature",
      "properties": {
        "hierarchy": [
          "tgn:4006769",
          "tgn:7003013",
          "tgn:7003005",
          "tgn:1000003",
          "tgn:1000080",
          "tgn:7029392"
        ],
        "placetype": [
          "aat:300008347"
        ],
        "id": 4006769,
        "name:xx": "Madonna dell'Arco"
      }
    }
  ]
}
