{
  "geometry": {
    "type": "Point",
    "coordinates": [
      -77.6833,
      40.3333
    ]
  },
  "type": "Feature",
  "properties": {
    "hierarchy": [
      "tgn:2217603",
      "tgn:1000001",
      "tgn:7012149",
      "tgn:1002528",
      "tgn:7007710",
      "tgn:7029392"
    ],
    "placetype": [
      "aat:300008761"
    ],
    "id": 2217603,
    "name:xx": "Campbell Hollow"
  }
}
