{
  "type": "FeatureCollection",
  "features": [
    {
      "geometry": {
        "type": "Point",
        "coordinates": [
          -84.2333,
          39.65
        ]
      },
      "type": "Feature",
      "properties": {
        "hierarchy": [
          "tgn:2656160",
          "tgn:1000001",
          "tgn:7012149",
          "tgn:1002689",
          "tgn:7007706",
          "tgn:7029392"
        ],
        "placetype": [
          "aat:300008798"
        ],
        "id": 2656160,
        "name:xx": "Shawnee Indian Mound"
      }
    },
    {
      "geometry": {
        "type": "Point",
        "coordinates": [
          -83.85,
          40.4833
        ]
      },
      "type": "Feature",
      "properties": {
        "hierarchy": [
          "tgn:2656161",
          "tgn:1000001",
          "tgn:7012149",
          "tgn:1002606",
          "tgn:7007706",
          "tgn:7029392"
        ],
        "placetype": [
          "aat:300008791"
        ],
        "id": 2656161,
        "name:xx": "Shawnee Island"
      }
    },
    {
      "geometry": {
        "type": "Point",
        "coordinates": [
          -75.1167,
          41
        ]
      },
      "type": "Feature",
      "properties": {
        "hierarchy": [
          "tgn:2656162",
          "tgn:1000001",
          "tgn:7012149",
          "tgn:1002682",
          "tgn:7007710",
          "tgn:7029392"
        ],
        "placetype": [
          "aat:300008791"
        ],
        "id": 2656162,
        "name:xx": "Shawnee Island"
      }
    },
    {
      "geometry": {
        "type": "Point",
        "coordinates": [
          -84.7,
          33.7333
        ]
      },
      "type": "Feature",
      "properties": {
        "hierarchy": [
          "tgn:2656163",
          "tgn:1000001",
          "tgn:7012149",
          "tgn:2000339",
          "tgn:7007248",
          "tgn:7029392"
        ],
        "placetype": [
          "aat:300006191"
        ],
        "id": 2656163,
        "name:xx": "Shawnee Lake"
      }
    },
    {
      "geometry": {
        "type": "Point",
        "coordinates": [
          -87.25,
          40.25
        ]
      },
      "type": "Feature",
      "properties": {
        "hierarchy": [
          "tgn:2656164",
          "tgn:1000001",
          "tgn:7012149",
          "tgn:1002380",
          "tgn:7007252",
          "tgn:7029392"
        ],
        "placetype": [
          "aat:300006191"
        ],
        "id": 2656164,
        "name:xx": "Shawnee Lake"
      }
    },
    {
      "geometry": {
        "type": "Point",
        "coordinates": [
          -84.2667,
          46.4667
        ]
      },
      "type": "Feature",
      "properties": {
        "hierarchy": [
          "tgn:2656165",
          "tgn:1000001",
          "tgn:2000952",
          "tgn:7012149",
          "tgn:7007520",
          "tgn:7029392"
        ],
        "placetype": [
          "aat:300008680"
        ],
        "id": 2656165,
        "name:xx": "Shawnee Lake"
      }
    },
    {
      "geometry": {
        "type": "Point",
        "coordinates": [
          -83.7833,
          39.6333
        ]
      },
      "type": "Feature",
      "properties": {
        "hierarchy": [
          "tgn:2656166",
          "tgn:1000001",
          "tgn:7012149",
          "tgn:1002424",
          "tgn:7007706",
          "tgn:7029392"
        ],
        "placetype": [
          "aat:300006191"
        ],
        "id": 2656166,
        "name:xx": "Shawnee Lake"
      }
    },
    {
      "geometry": {
        "type": "Point",
        "coordinates": [
          -75.1,
          41.0167
        ]
      },
      "type": "Feature",
      "properties": {
        "hierarchy": [
          "tgn:2656167",
          "tgn:1000001",
          "tgn:7012149",
          "tgn:1002682",
          "tgn:7007710",
          "tgn:7029392"
        ],
        "placetype": [
          "aat:300006191"
        ],
        "id": 2656167,
        "name:xx": "Shawnee Lake"
      }
    },
    {
      "geometry": {
        "type": "Point",
        "coordinates": [
          -78.6167,
          40.0167
        ]
      },
      "type": "Feature",
      "properties": {
        "hierarchy": [
          "tgn:2656168",
          "tgn:1002172",
          "tgn:1000001",
          "tgn:7012149",
          "tgn:7007710",
          "tgn:7029392"
        ],
        "placetype": [
          "aat:300006191"
        ],
        "id": 2656168,
        "name:xx": "Shawnee Lake"
      }
    },
    {
      "geometry": {
        "type": "Point",
        "coordinates": [
          -94.65,
          31.45
        ]
      },
      "type": "Feature",
      "properties": {
        "hierarchy": [
          "tgn:2656169",
          "tgn:1000001",
          "tgn:7012149",
          "tgn:1002703",
          "tgn:7007826",
          "tgn:7029392"
        ],
        "placetype": [
          "aat:300008680"
        ],
        "id": 2656169,
        "name:xx": "Shawnee Lake"
      }
    }
  ]
}
