{
  "geometry": {
    "type": "Point",
    "coordinates": [
      -113.0167,
      44.8167
    ]
  },
  "type": "Feature",
  "properties": {
    "hierarchy": [
      "tgn:2436243",
      "tgn:1000001",
      "tgn:2001260",
      "tgn:7012149",
      "tgn:7007524",
      "tgn:7029392"
    ],
    "placetype": [
      "aat:300006191"
    ],
    "id": 2436243,
    "name:xx": "Keystone Reservoir"
  }
}
