{
  "geometry": {
    "type": "Point",
    "coordinates": [
      -108.4833,
      45.7667
    ]
  },
  "type": "Feature",
  "properties": {
    "hierarchy": [
      "tgn:2784697",
      "tgn:1000001",
      "tgn:7012149",
      "tgn:2001315",
      "tgn:7007524",
      "tgn:7029392"
    ],
    "placetype": [
      "aat:300006075"
    ],
    "id": 2784697,
    "name:xx": "Yegen Drain"
  }
}
