{
  "geometry": {
    "type": "Point",
    "coordinates": [
      -108.7333,
      43.7667
    ]
  },
  "type": "Feature",
  "properties": {
    "hierarchy": [
      "tgn:2265873",
      "tgn:1000001",
      "tgn:7012149",
      "tgn:2002373",
      "tgn:7007923",
      "tgn:7029392"
    ],
    "placetype": [
      "aat:300386845"
    ],
    "id": 2265873,
    "name:xx": "Crater Sink"
  }
}
