{
  "geometry": {
    "type": "Point",
    "coordinates": [
      -91.2333,
      35.1833
    ]
  },
  "type": "Feature",
  "properties": {
    "hierarchy": [
      "tgn:2250384",
      "tgn:1000001",
      "tgn:7016172",
      "tgn:7012149",
      "tgn:2000178",
      "tgn:7029392"
    ],
    "placetype": [
      "aat:300008347"
    ],
    "id": 2250384,
    "name:xx": "Colona"
  }
}
