{
  "geometry": {
    "type": "Point",
    "coordinates": [
      76.83033,
      30.20767
    ]
  },
  "type": "Feature",
  "properties": {
    "hierarchy": [
      "tgn:7582729",
      "tgn:1000004",
      "tgn:1001871",
      "tgn:7000198",
      "tgn:7029392"
    ],
    "placetype": [
      "aat:300008347"
    ],
    "name:en": "Mohīuddīnpur",
    "id": 7582729
  }
}
