{
  "type": "FeatureCollection",
  "features": [
    {
      "geometry": {
        "type": "Point",
        "coordinates": [
          -86.7333,
          33.5833
        ]
      },
      "type": "Feature",
      "properties": {
        "hierarchy": [
          "tgn:2548280",
          "tgn:7002659",
          "tgn:1000001",
          "tgn:7012149",
          "tgn:2000036",
          "tgn:7029392"
        ],
        "placetype": [
          "aat:300006191"
        ],
        "id": 2548280,
        "name:xx": "North Lake"
      }
    },
    {
      "geometry": {
        "type": "Point",
        "coordinates": [
          -132.55,
          55.6333
        ]
      },
      "type": "Feature",
      "properties": {
        "hierarchy": [
          "tgn:2548281",
          "tgn:7006450",
          "tgn:1000001",
          "tgn:7012149",
          "tgn:2000082",
          "tgn:7029392"
        ],
        "placetype": [
          "aat:300008680"
        ],
        "id": 2548281,
        "name:xx": "North Lake"
      }
    },
    {
      "geometry": {
        "type": "Point",
        "coordinates": [
          -90.1,
          35.4
        ]
      },
      "type": "Feature",
      "properties": {
        "hierarchy": [
          "tgn:2548282",
          "tgn:1000001",
          "tgn:7016172",
          "tgn:2000122",
          "tgn:7012149",
          "tgn:7029392"
        ],
        "placetype": [
          "aat:300008680"
        ],
        "id": 2548282,
        "name:xx": "North Lake"
      }
    },
    {
      "geometry": {
        "type": "Point",
        "coordinates": [
          -91.7333,
          36.25
        ]
      },
      "type": "Feature",
      "properties": {
        "hierarchy": [
          "tgn:2548283",
          "tgn:1000001",
          "tgn:7016172",
          "tgn:7012149",
          "tgn:2000129",
          "tgn:7029392"
        ],
        "placetype": [
          "aat:300006191"
        ],
        "id": 2548283,
        "name:xx": "North Lake"
      }
    },
    {
      "geometry": {
        "type": "Point",
        "coordinates": [
          -118.6,
          37.2167
        ]
      },
      "type": "Feature",
      "properties": {
        "hierarchy": [
          "tgn:2548284",
          "tgn:1000001",
          "tgn:7012149",
          "tgn:2000183",
          "tgn:7007157",
          "tgn:7029392"
        ],
        "placetype": [
          "aat:300008680"
        ],
        "id": 2548284,
        "name:xx": "North Lake"
      }
    },
    {
      "geometry": {
        "type": "Point",
        "coordinates": [
          -122.5,
          37.7667
        ]
      },
      "type": "Feature",
      "properties": {
        "hierarchy": [
          "tgn:2548285",
          "tgn:1000001",
          "tgn:7012149",
          "tgn:7007157",
          "tgn:1002859",
          "tgn:7029392"
        ],
        "placetype": [
          "aat:300008680"
        ],
        "id": 2548285,
        "name:xx": "North Lake"
      }
    },
    {
      "geometry": {
        "type": "Point",
        "coordinates": [
          -117.3333,
          34.75
        ]
      },
      "type": "Feature",
      "properties": {
        "hierarchy": [
          "tgn:2548286",
          "tgn:1000001",
          "tgn:7012149",
          "tgn:7007157",
          "tgn:1002857",
          "tgn:7029392"
        ],
        "placetype": [
          "aat:300006191"
        ],
        "id": 2548286,
        "name:xx": "North Lake"
      }
    },
    {
      "geometry": {
        "type": "Point",
        "coordinates": [
          -106.6833,
          40.7167
        ]
      },
      "type": "Feature",
      "properties": {
        "hierarchy": [
          "tgn:2548287",
          "tgn:1000001",
          "tgn:7012149",
          "tgn:7007158",
          "tgn:2000245",
          "tgn:7029392"
        ],
        "placetype": [
          "aat:300008680"
        ],
        "id": 2548287,
        "name:xx": "North Lake"
      }
    },
    {
      "geometry": {
        "type": "Point",
        "coordinates": [
          -105.0333,
          37.2333
        ]
      },
      "type": "Feature",
      "properties": {
        "hierarchy": [
          "tgn:2548288",
          "tgn:1000001",
          "tgn:7012149",
          "tgn:2000227",
          "tgn:7007158",
          "tgn:7029392"
        ],
        "placetype": [
          "aat:300006191"
        ],
        "id": 2548288,
        "name:xx": "North Lake"
      }
    },
    {
      "geometry": {
        "type": "Point",
        "coordinates": [
          -80.15,
          26.1667
        ]
      },
      "type": "Feature",
      "properties": {
        "hierarchy": [
          "tgn:2548289",
          "tgn:1000001",
          "tgn:1002207",
          "tgn:7012149",
          "tgn:7007240",
          "tgn:7029392"
        ],
        "placetype": [
          "aat:300008680"
        ],
        "id": 2548289,
        "name:xx": "North Lake"
      }
    }
  ]
}
