{
  "geometry": {
    "type": "Point",
    "coordinates": [
      -103.7333,
      47.0167
    ]
  },
  "type": "Feature",
  "properties": {
    "hierarchy": [
      "tgn:2309472",
      "tgn:1000001",
      "tgn:2001573",
      "tgn:7012149",
      "tgn:7007705",
      "tgn:7029392"
    ],
    "placetype": [
      "aat:300008798"
    ],
    "id": 2309472,
    "name:xx": "East Twin Butte"
  }
}
