{
  "geometry": {
    "type": "Point",
    "coordinates": [
      -121.8167,
      46.6333
    ]
  },
  "type": "Feature",
  "properties": {
    "hierarchy": [
      "tgn:1134618",
      "tgn:1000001",
      "tgn:7012149",
      "tgn:1002594",
      "tgn:7007920",
      "tgn:7029392"
    ],
    "placetype": [
      "aat:300008706"
    ],
    "id": 1134618,
    "name:xx": "Skate Creek"
  }
}
