{
  "geometry": {
    "type": "Point",
    "coordinates": [
      79.9285,
      27.2317
    ]
  },
  "type": "Feature",
  "properties": {
    "hierarchy": [
      "tgn:7561873",
      "tgn:1000004",
      "tgn:7000198",
      "tgn:7016722",
      "tgn:7029392"
    ],
    "placetype": [
      "aat:300008347"
    ],
    "name:en": "Daīchaur",
    "id": 7561873
  }
}
