{
  "type": "FeatureCollection",
  "features": [
    {
      "geometry": {
        "type": "Point",
        "coordinates": [
          -121.1,
          38.95
        ]
      },
      "type": "Feature",
      "properties": {
        "hierarchy": [
          "tgn:2011190",
          "tgn:1000001",
          "tgn:7012149",
          "tgn:7007157",
          "tgn:1002791",
          "tgn:7029392"
        ],
        "placetype": [
          "aat:300008347"
        ],
        "id": 2011190,
        "name:xx": "Elders Corner"
      }
    },
    {
      "geometry": {
        "type": "Point",
        "coordinates": [
          -119.1167,
          36.4667
        ]
      },
      "type": "Feature",
      "properties": {
        "hierarchy": [
          "tgn:2011191",
          "tgn:1000001",
          "tgn:7012149",
          "tgn:7007157",
          "tgn:1002956",
          "tgn:7029392"
        ],
        "placetype": [
          "aat:300008347",
          "aat:300387210"
        ],
        "id": 2011191,
        "name:xx": "Elderwood"
      }
    },
    {
      "geometry": {
        "type": "Point",
        "coordinates": [
          -120.8333,
          38.6667
        ]
      },
      "type": "Feature",
      "properties": {
        "hierarchy": [
          "tgn:2011192",
          "tgn:1000001",
          "tgn:7012149",
          "tgn:1002350",
          "tgn:7007157",
          "tgn:7029392"
        ],
        "placetype": [
          "aat:300008347"
        ],
        "id": 2011192,
        "name:xx": "El Dorado"
      }
    },
    {
      "geometry": {
        "type": "Point",
        "coordinates": [
          -119.85,
          34.4167
        ]
      },
      "type": "Feature",
      "properties": {
        "hierarchy": [
          "tgn:2011195",
          "tgn:1000001",
          "tgn:7012149",
          "tgn:7007157",
          "tgn:1002867",
          "tgn:7029392"
        ],
        "placetype": [
          "aat:300008347"
        ],
        "id": 2011195,
        "name:xx": "El Encanto Heights"
      }
    },
    {
      "geometry": {
        "type": "Point",
        "coordinates": [
          -118.2167,
          33.8333
        ]
      },
      "type": "Feature",
      "properties": {
        "hierarchy": [
          "tgn:2011198",
          "tgn:1000001",
          "tgn:7012149",
          "tgn:7007157",
          "tgn:1002608",
          "tgn:7029392"
        ],
        "placetype": [
          "aat:300387016"
        ],
        "id": 2011198,
        "name:xx": "Elftman"
      }
    },
    {
      "geometry": {
        "type": "Point",
        "coordinates": [
          -122.4667,
          37.5
        ]
      },
      "type": "Feature",
      "properties": {
        "hierarchy": [
          "tgn:2011199",
          "tgn:1000001",
          "tgn:7012149",
          "tgn:7007157",
          "tgn:1002864",
          "tgn:7029392"
        ],
        "placetype": [
          "aat:300008347"
        ],
        "id": 2011199,
        "name:xx": "El Granada"
      }
    }
  ]
}
