{
  "geometry": {
    "type": "Point",
    "coordinates": [
      -97.5167,
      31.3667
    ]
  },
  "type": "Feature",
  "properties": {
    "hierarchy": [
      "tgn:2227650",
      "tgn:1000001",
      "tgn:7012149",
      "tgn:1002303",
      "tgn:7007826",
      "tgn:7029392"
    ],
    "placetype": [
      "aat:300008347"
    ],
    "id": 2227650,
    "name:xx": "Cavitt"
  }
}
