{
  "geometry": {
    "type": "Point",
    "coordinates": [
      -133.4667,
      56.15
    ]
  },
  "type": "Feature",
  "properties": {
    "hierarchy": [
      "tgn:2333598",
      "tgn:7006450",
      "tgn:1000001",
      "tgn:7012149",
      "tgn:2000082",
      "tgn:7029392"
    ],
    "placetype": [
      "aat:300008791"
    ],
    "id": 2333598,
    "name:xx": "Fontaine Island"
  }
}
