{
  "type": "FeatureCollection",
  "features": [
    {
      "geometry": {
        "type": "Point",
        "coordinates": [
          -83.0333,
          37.9333
        ]
      },
      "type": "Feature",
      "properties": {
        "hierarchy": [
          "tgn:2368950",
          "tgn:1000001",
          "tgn:7012149",
          "tgn:2000831",
          "tgn:7007255",
          "tgn:7029392"
        ],
        "placetype": [
          "aat:300008699"
        ],
        "id": 2368950,
        "name:xx": "Gum Bottom Branch"
      }
    },
    {
      "geometry": {
        "type": "Point",
        "coordinates": [
          -91.5167,
          35.0833
        ]
      },
      "type": "Feature",
      "properties": {
        "hierarchy": [
          "tgn:2368951",
          "tgn:1000001",
          "tgn:7016172",
          "tgn:7012149",
          "tgn:2000177",
          "tgn:7029392"
        ],
        "placetype": [
          "aat:300008905"
        ],
        "id": 2368951,
        "name:xx": "Gum Brake"
      }
    },
    {
      "geometry": {
        "type": "Point",
        "coordinates": [
          -88.3833,
          31.2167
        ]
      },
      "type": "Feature",
      "properties": {
        "hierarchy": [
          "tgn:2368952",
          "tgn:7002659",
          "tgn:1000001",
          "tgn:7012149",
          "tgn:2000064",
          "tgn:7029392"
        ],
        "placetype": [
          "aat:300008699"
        ],
        "id": 2368952,
        "name:xx": "Gum Branch"
      }
    },
    {
      "geometry": {
        "type": "Point",
        "coordinates": [
          -86.45,
          33.4
        ]
      },
      "type": "Feature",
      "properties": {
        "hierarchy": [
          "tgn:2368953",
          "tgn:7002659",
          "tgn:1000001",
          "tgn:7012149",
          "tgn:2000058",
          "tgn:7029392"
        ],
        "placetype": [
          "aat:300008699"
        ],
        "id": 2368953,
        "name:xx": "Gum Branch"
      }
    },
    {
      "geometry": {
        "type": "Point",
        "coordinates": [
          -87.5667,
          30.4
        ]
      },
      "type": "Feature",
      "properties": {
        "hierarchy": [
          "tgn:2368954",
          "tgn:2000001",
          "tgn:7002659",
          "tgn:1000001",
          "tgn:7012149",
          "tgn:7029392"
        ],
        "placetype": [
          "aat:300008699"
        ],
        "id": 2368954,
        "name:xx": "Gum Branch"
      }
    },
    {
      "geometry": {
        "type": "Point",
        "coordinates": [
          -88.2833,
          30.8667
        ]
      },
      "type": "Feature",
      "properties": {
        "hierarchy": [
          "tgn:2368955",
          "tgn:7002659",
          "tgn:1000001",
          "tgn:7012149",
          "tgn:2000048",
          "tgn:7029392"
        ],
        "placetype": [
          "aat:300008699"
        ],
        "id": 2368955,
        "name:xx": "Gum Branch"
      }
    },
    {
      "geometry": {
        "type": "Point",
        "coordinates": [
          -94.3,
          34.8667
        ]
      },
      "type": "Feature",
      "properties": {
        "hierarchy": [
          "tgn:2368956",
          "tgn:1000001",
          "tgn:7016172",
          "tgn:7012149",
          "tgn:2000168",
          "tgn:7029392"
        ],
        "placetype": [
          "aat:300008699"
        ],
        "id": 2368956,
        "name:xx": "Gum Branch"
      }
    },
    {
      "geometry": {
        "type": "Point",
        "coordinates": [
          -93.3167,
          35.8667
        ]
      },
      "type": "Feature",
      "properties": {
        "hierarchy": [
          "tgn:2368957",
          "tgn:1000001",
          "tgn:7016172",
          "tgn:7012149",
          "tgn:2000155",
          "tgn:7029392"
        ],
        "placetype": [
          "aat:300008699"
        ],
        "id": 2368957,
        "name:xx": "Gum Branch"
      }
    },
    {
      "geometry": {
        "type": "Point",
        "coordinates": [
          -75.4,
          38.5
        ]
      },
      "type": "Feature",
      "properties": {
        "hierarchy": [
          "tgn:2368958",
          "tgn:1002933",
          "tgn:1000001",
          "tgn:7012149",
          "tgn:7007239",
          "tgn:7029392"
        ],
        "placetype": [
          "aat:300008699"
        ],
        "id": 2368958,
        "name:xx": "Gum Branch"
      }
    },
    {
      "geometry": {
        "type": "Point",
        "coordinates": [
          -81.1833,
          27.6333
        ]
      },
      "type": "Feature",
      "properties": {
        "hierarchy": [
          "tgn:2368959",
          "tgn:1000001",
          "tgn:7012149",
          "tgn:7007240",
          "tgn:7029392"
        ],
        "placetype": [
          "aat:300008699"
        ],
        "id": 2368959,
        "name:xx": "Gum Branch"
      }
    }
  ]
}
