{
  "geometry": {
    "type": "Point",
    "coordinates": [
      -123.95,
      44.3333
    ]
  },
  "type": "Feature",
  "properties": {
    "hierarchy": [
      "tgn:2327701",
      "tgn:1000001",
      "tgn:7012149",
      "tgn:1002599",
      "tgn:7007708",
      "tgn:7029392"
    ],
    "placetype": [
      "aat:300008706"
    ],
    "id": 2327701,
    "name:xx": "Fish Creek"
  }
}
