{
  "geometry": {
    "type": "Point",
    "coordinates": [
      -72.7167,
      41.4833
    ]
  },
  "type": "Feature",
  "properties": {
    "hierarchy": [
      "tgn:2476920",
      "tgn:1000001",
      "tgn:1002664",
      "tgn:7012149",
      "tgn:7007159",
      "tgn:7029392"
    ],
    "placetype": [
      "aat:300008699"
    ],
    "id": 2476920,
    "name:xx": "Lyman Meadow Brook"
  }
}
