{
  "type": "FeatureCollection",
  "features": [
    {
      "geometry": {
        "type": "Point",
        "coordinates": [
          -74.7333,
          71.5
        ]
      },
      "type": "Feature",
      "properties": {
        "hierarchy": [
          "tgn:1114361",
          "tgn:7013003",
          "tgn:7005685",
          "tgn:1000001",
          "tgn:7024197",
          "tgn:7029392"
        ],
        "placetype": [
          "aat:300008676"
        ],
        "id": 1114361,
        "name:xx": "Cambridge Fiord"
      }
    },
    {
      "geometry": {
        "type": "Point",
        "coordinates": [
          -73.05,
          71.1833
        ]
      },
      "type": "Feature",
      "properties": {
        "hierarchy": [
          "tgn:1114362",
          "tgn:7013003",
          "tgn:7005685",
          "tgn:1000001",
          "tgn:7024197",
          "tgn:7029392"
        ],
        "placetype": [
          "aat:300008676"
        ],
        "id": 1114362,
        "name:xx": "Dexterity Fiord"
      }
    },
    {
      "geometry": {
        "type": "Point",
        "coordinates": [
          -73.683333,
          -46.166667
        ]
      },
      "type": "Feature",
      "properties": {
        "hierarchy": [
          "tgn:1114364",
          "tgn:1001623",
          "tgn:1000049",
          "tgn:1000002",
          "tgn:7029392"
        ],
        "placetype": [
          "aat:300008676"
        ],
        "id": 1114364,
        "name:xx": "Elefantes, Estero"
      }
    },
    {
      "geometry": {
        "type": "Point",
        "coordinates": [
          -18.25,
          65.9167
        ]
      },
      "type": "Feature",
      "properties": {
        "hierarchy": [
          "tgn:1114365",
          "tgn:7594017",
          "tgn:1000003",
          "tgn:1000077",
          "tgn:7029392"
        ],
        "placetype": [
          "aat:300008676"
        ],
        "id": 1114365,
        "name:xx": "Eyjafjörður"
      }
    }
  ]
}
