{
  "geometry": {
    "type": "Point",
    "coordinates": [
      86.261884,
      20.36098
    ]
  },
  "type": "Feature",
  "properties": {
    "hierarchy": [
      "tgn:7572810",
      "tgn:1000004",
      "tgn:7000198",
      "tgn:7016694",
      "tgn:7029392"
    ],
    "placetype": [
      "aat:300008347"
    ],
    "name:en": "Gājipur",
    "id": 7572810
  }
}
