{
  "geometry": {
    "type": "Point",
    "coordinates": [
      -96.5167,
      37.3833
    ]
  },
  "type": "Feature",
  "properties": {
    "hierarchy": [
      "tgn:2648240",
      "tgn:1000001",
      "tgn:7012149",
      "tgn:7007254",
      "tgn:7029392"
    ],
    "placetype": [
      "aat:300008699"
    ],
    "id": 2648240,
    "name:xx": "Schrader Branch"
  }
}
