{
  "geometry": {
    "type": "Point",
    "coordinates": [
      -116.9667,
      43.6833
    ]
  },
  "type": "Feature",
  "properties": {
    "hierarchy": [
      "tgn:2588164",
      "tgn:1000001",
      "tgn:2000465",
      "tgn:7012149",
      "tgn:7007250",
      "tgn:7029392"
    ],
    "placetype": [
      "aat:300006075"
    ],
    "id": 2588164,
    "name:xx": "Plowhead Lateral"
  }
}
