{
  "geometry": {
    "type": "Point",
    "coordinates": [
      -84.5667,
      37.3333
    ]
  },
  "type": "Feature",
  "properties": {
    "hierarchy": [
      "tgn:2532048",
      "tgn:1000001",
      "tgn:7012149",
      "tgn:2000813",
      "tgn:7007255",
      "tgn:7029392"
    ],
    "placetype": [
      "aat:300008798"
    ],
    "id": 2532048,
    "name:xx": "Muncie Knob"
  }
}
