{
  "geometry": {
    "type": "Point",
    "coordinates": [
      31.862197,
      31.408265
    ]
  },
  "type": "Feature",
  "properties": {
    "hierarchy": [
      "tgn:7527364",
      "tgn:7001242",
      "tgn:1001059",
      "tgn:7016833",
      "tgn:7029392"
    ],
    "placetype": [
      "aat:300008688"
    ],
    "name:en": "Sīdī Shaţā, Mallāḩāt",
    "id": 7527364
  }
}
