{
  "geometry": {
    "type": "Point",
    "coordinates": [
      -108.15,
      46.8667
    ]
  },
  "type": "Feature",
  "properties": {
    "hierarchy": [
      "tgn:2488023",
      "tgn:1000001",
      "tgn:7012149",
      "tgn:2001294",
      "tgn:7007524",
      "tgn:7029392"
    ],
    "placetype": [
      "aat:300008706"
    ],
    "id": 2488023,
    "name:xx": "Maginnis Creek"
  }
}
