{
  "type": "FeatureCollection",
  "features": [
    {
      "geometry": {
        "type": "Point",
        "coordinates": [
          -99.661667,
          24.235278
        ]
      },
      "type": "Feature",
      "properties": {
        "hierarchy": [
          "tgn:7391471",
          "tgn:1000001",
          "tgn:7005589",
          "tgn:7005560",
          "tgn:7029392"
        ],
        "placetype": [
          "aat:300008347"
        ],
        "id": 7391471,
        "name:xx": "Rodeo"
      }
    },
    {
      "geometry": {
        "type": "Point",
        "coordinates": [
          -109.883333,
          23.7
        ]
      },
      "type": "Feature",
      "properties": {
        "hierarchy": [
          "tgn:7391472",
          "tgn:1001836",
          "tgn:1000001",
          "tgn:7005560",
          "tgn:7029392"
        ],
        "placetype": [
          "aat:300008347"
        ],
        "id": 7391472,
        "name:xx": "Rodeo"
      }
    },
    {
      "geometry": {
        "type": "Point",
        "coordinates": [
          -105.616667,
          22.616667
        ]
      },
      "type": "Feature",
      "properties": {
        "hierarchy": [
          "tgn:7391473",
          "tgn:1000001",
          "tgn:7005595",
          "tgn:7005560",
          "tgn:7029392"
        ],
        "placetype": [
          "aat:300008347"
        ],
        "id": 7391473,
        "name:xx": "Rodeo"
      }
    },
    {
      "geometry": {
        "type": "Point",
        "coordinates": [
          -99.8,
          21.7
        ]
      },
      "type": "Feature",
      "properties": {
        "hierarchy": [
          "tgn:7391474",
          "tgn:1000001",
          "tgn:7005594",
          "tgn:7005560",
          "tgn:7029392"
        ],
        "placetype": [
          "aat:300008347"
        ],
        "id": 7391474,
        "name:xx": "Rodeo"
      }
    },
    {
      "geometry": {
        "type": "Point",
        "coordinates": [
          -95.766667,
          18.2
        ]
      },
      "type": "Feature",
      "properties": {
        "hierarchy": [
          "tgn:7391475",
          "tgn:1000001",
          "tgn:7005599",
          "tgn:7005560",
          "tgn:7029392"
        ],
        "placetype": [
          "aat:300008347"
        ],
        "id": 7391475,
        "name:xx": "Rodeo"
      }
    },
    {
      "geometry": {
        "type": "Point",
        "coordinates": [
          -100.1,
          17.916667
        ]
      },
      "type": "Feature",
      "properties": {
        "hierarchy": [
          "tgn:7391476",
          "tgn:7005585",
          "tgn:1000001",
          "tgn:7005560",
          "tgn:7029392"
        ],
        "placetype": [
          "aat:300008347"
        ],
        "id": 7391476,
        "name:xx": "Rodeo"
      }
    },
    {
      "geometry": {
        "type": "Point",
        "coordinates": [
          -107.333333,
          30.1
        ]
      },
      "type": "Feature",
      "properties": {
        "hierarchy": [
          "tgn:7391477",
          "tgn:7005581",
          "tgn:1000001",
          "tgn:7005560",
          "tgn:7029392"
        ],
        "placetype": [
          "aat:300000241"
        ],
        "id": 7391477,
        "name:xx": "Rancho de Rodelas"
      }
    },
    {
      "geometry": {
        "type": "Point",
        "coordinates": [
          -110.933333,
          18.85
        ]
      },
      "type": "Feature",
      "properties": {
        "hierarchy": [
          "tgn:7391478",
          "tgn:7016644",
          "tgn:1000001",
          "tgn:7005560",
          "tgn:7029392"
        ],
        "placetype": [
          "aat:300011692"
        ],
        "id": 7391478,
        "name:xx": "Rocosos, Islotes"
      }
    },
    {
      "geometry": {
        "type": "Point",
        "coordinates": [
          -113.2,
          29.3
        ]
      },
      "type": "Feature",
      "properties": {
        "hierarchy": [
          "tgn:7391479",
          "tgn:1001835",
          "tgn:1000001",
          "tgn:7005560",
          "tgn:7029392"
        ],
        "placetype": [
          "aat:300386846"
        ],
        "id": 7391479,
        "name:xx": "Rocosa, Punta"
      }
    }
  ]
}
