{
  "geometry": {
    "type": "Point",
    "coordinates": [
      -123.65,
      47.6833
    ]
  },
  "type": "Feature",
  "properties": {
    "hierarchy": [
      "tgn:2383973",
      "tgn:1000001",
      "tgn:7012149",
      "tgn:1002521",
      "tgn:7007920",
      "tgn:7029392"
    ],
    "placetype": [
      "aat:300008706"
    ],
    "id": 2383973,
    "name:xx": "Hee Haw Creek"
  }
}
