{
  "geometry": {
    "type": "Point",
    "coordinates": [
      -85.8333,
      34.4167
    ]
  },
  "type": "Feature",
  "properties": {
    "hierarchy": [
      "tgn:2212502",
      "tgn:7002659",
      "tgn:1000001",
      "tgn:7012149",
      "tgn:7021514",
      "tgn:7029392"
    ],
    "placetype": [
      "aat:300008699"
    ],
    "id": 2212502,
    "name:xx": "Bynum Mill Branch"
  }
}
