{
  "geometry": {
    "type": "Point",
    "coordinates": [
      -98.8667,
      29.2667
    ]
  },
  "type": "Feature",
  "properties": {
    "hierarchy": [
      "tgn:2573066",
      "tgn:1000001",
      "tgn:7012149",
      "tgn:2002039",
      "tgn:7007826",
      "tgn:7029392"
    ],
    "placetype": [
      "aat:300008347"
    ],
    "id": 2573066,
    "name:xx": "Pearson"
  }
}
