{
  "geometry": {
    "type": "Point",
    "coordinates": [
      -151.6333,
      67.0667
    ]
  },
  "type": "Feature",
  "properties": {
    "hierarchy": [
      "tgn:2541700",
      "tgn:7006450",
      "tgn:1000001",
      "tgn:7012149",
      "tgn:2000089",
      "tgn:7029392"
    ],
    "placetype": [
      "aat:300008706"
    ],
    "id": 2541700,
    "name:xx": "Ninemile Creek"
  }
}
