{
  "geometry": {
    "type": "Point",
    "coordinates": [
      -75.6167,
      40.3167
    ]
  },
  "type": "Feature",
  "properties": {
    "hierarchy": [
      "tgn:2516954",
      "tgn:1000001",
      "tgn:7012149",
      "tgn:7007710",
      "tgn:7029392"
    ],
    "placetype": [
      "aat:300008706"
    ],
    "id": 2516954,
    "name:xx": "Minister Creek"
  }
}
