{
  "geometry": {
    "type": "Point",
    "coordinates": [
      -114.3667,
      35.0667
    ]
  },
  "type": "Feature",
  "properties": {
    "hierarchy": [
      "tgn:2151866",
      "tgn:1000001",
      "tgn:7006451",
      "tgn:7012149",
      "tgn:2000098",
      "tgn:7029392"
    ],
    "placetype": [
      "aat:300008798"
    ],
    "id": 2151866,
    "name:xx": "Battleship Mountain"
  }
}
