{
  "geometry": {
    "type": "Point",
    "coordinates": [
      -92.6667,
      42.15
    ]
  },
  "type": "Feature",
  "properties": {
    "hierarchy": [
      "tgn:2270233",
      "tgn:1000001",
      "tgn:7012149",
      "tgn:2000646",
      "tgn:7007253",
      "tgn:7029392"
    ],
    "placetype": [
      "aat:300008706"
    ],
    "id": 2270233,
    "name:xx": "Crystal Creek"
  }
}
