{
  "geometry": {
    "type": "Point",
    "coordinates": [
      -104.85,
      45.0833
    ]
  },
  "type": "Feature",
  "properties": {
    "hierarchy": [
      "tgn:2279355",
      "tgn:1000001",
      "tgn:2001265",
      "tgn:7012149",
      "tgn:7007524",
      "tgn:7029392"
    ],
    "placetype": [
      "aat:300008706"
    ],
    "id": 2279355,
    "name:xx": "Deadman Creek"
  }
}
