{
  "geometry": {
    "type": "Point",
    "coordinates": [
      -108.35,
      39.0833
    ]
  },
  "type": "Feature",
  "properties": {
    "hierarchy": [
      "tgn:2308626",
      "tgn:1000001",
      "tgn:7012149",
      "tgn:2000230",
      "tgn:7007158",
      "tgn:7029392"
    ],
    "placetype": [
      "aat:300008798"
    ],
    "id": 2308626,
    "name:xx": "East Orchard Mesa"
  }
}
