{
  "type": "FeatureCollection",
  "features": [
    {
      "geometry": {
        "type": "Point",
        "coordinates": [
          6.85,
          49.866667
        ]
      },
      "type": "Feature",
      "properties": {
        "hierarchy": [
          "tgn:7166110",
          "tgn:1000003",
          "tgn:7003682",
          "tgn:7000084",
          "tgn:7029392"
        ],
        "placetype": [
          "aat:300008777"
        ],
        "id": 7166110,
        "name:xx": "Helde Berg"
      }
    },
    {
      "geometry": {
        "type": "Point",
        "coordinates": [
          10.716667,
          50.316667
        ]
      },
      "type": "Feature",
      "properties": {
        "hierarchy": [
          "tgn:7166111",
          "tgn:1000003",
          "tgn:7003689",
          "tgn:7000084",
          "tgn:7029392"
        ],
        "placetype": [
          "aat:300008863"
        ],
        "id": 7166111,
        "name:xx": "Heldburg, Forst"
      }
    },
    {
      "geometry": {
        "type": "Point",
        "coordinates": [
          10.733333,
          50.3
        ]
      },
      "type": "Feature",
      "properties": {
        "hierarchy": [
          "tgn:7166112",
          "tgn:1000003",
          "tgn:7003689",
          "tgn:7000084",
          "tgn:7029392"
        ],
        "placetype": [
          "aat:300006891"
        ],
        "id": 7166112,
        "name:xx": "Feste Heldburg"
      }
    },
    {
      "geometry": {
        "type": "Point",
        "coordinates": [
          7,
          49.583333
        ]
      },
      "type": "Feature",
      "properties": {
        "hierarchy": [
          "tgn:7166114",
          "tgn:1000003",
          "tgn:7003684",
          "tgn:7000084",
          "tgn:7029392"
        ],
        "placetype": [
          "aat:300008777"
        ],
        "id": 7166114,
        "name:xx": "Held-Berg"
      }
    },
    {
      "geometry": {
        "type": "Point",
        "coordinates": [
          6.6,
          49.833333
        ]
      },
      "type": "Feature",
      "properties": {
        "hierarchy": [
          "tgn:7166115",
          "tgn:1000003",
          "tgn:7003682",
          "tgn:7000084",
          "tgn:7029392"
        ],
        "placetype": [
          "aat:300000206"
        ],
        "id": 7166115,
        "name:xx": "Held"
      }
    },
    {
      "geometry": {
        "type": "Point",
        "coordinates": [
          10.516667,
          48
        ]
      },
      "type": "Feature",
      "properties": {
        "hierarchy": [
          "tgn:7166116",
          "tgn:7003669",
          "tgn:1000003",
          "tgn:7000084",
          "tgn:7029392"
        ],
        "placetype": [
          "aat:300008347"
        ],
        "id": 7166116,
        "name:xx": "Helchenried"
      }
    },
    {
      "geometry": {
        "type": "Point",
        "coordinates": [
          9.083333,
          47.85
        ]
      },
      "type": "Feature",
      "properties": {
        "hierarchy": [
          "tgn:7166117",
          "tgn:7003692",
          "tgn:1000003",
          "tgn:7000084",
          "tgn:7029392"
        ],
        "placetype": [
          "aat:300000206"
        ],
        "id": 7166117,
        "name:xx": "Helchenhof"
      }
    },
    {
      "geometry": {
        "type": "Point",
        "coordinates": [
          11.983333,
          48.8
        ]
      },
      "type": "Feature",
      "properties": {
        "hierarchy": [
          "tgn:7166118",
          "tgn:7003669",
          "tgn:1000003",
          "tgn:7000084",
          "tgn:7029392"
        ],
        "placetype": [
          "aat:300008347"
        ],
        "id": 7166118,
        "name:xx": "Helchenbach"
      }
    }
  ]
}
