{
  "geometry": {
    "type": "Point",
    "coordinates": [
      121.5217,
      24.0391
    ]
  },
  "type": "Feature",
  "properties": {
    "hierarchy": [
      "tgn:7471965",
      "tgn:7001010",
      "tgn:1000004",
      "tgn:1000141",
      "tgn:7029392"
    ],
    "placetype": [
      "aat:300008798"
    ],
    "id": 7471965,
    "name:xx": "Lan Shan Nanfeng"
  }
}
