{
  "type": "FeatureCollection",
  "features": [
    {
      "geometry": {
        "type": "Point",
        "coordinates": [
          -72.7833,
          43.75
        ]
      },
      "type": "Feature",
      "properties": {
        "hierarchy": [
          "tgn:2197330",
          "tgn:1000001",
          "tgn:2002136",
          "tgn:7012149",
          "tgn:7007828",
          "tgn:7029392"
        ],
        "placetype": [
          "aat:300008699"
        ],
        "id": 2197330,
        "name:xx": "Brown Brook"
      }
    },
    {
      "geometry": {
        "type": "Point",
        "coordinates": [
          -72.1833,
          44.4167
        ]
      },
      "type": "Feature",
      "properties": {
        "hierarchy": [
          "tgn:2197331",
          "tgn:2002131",
          "tgn:1000001",
          "tgn:7012149",
          "tgn:7007828",
          "tgn:7029392"
        ],
        "placetype": [
          "aat:300008699"
        ],
        "id": 2197331,
        "name:xx": "Brown Brook"
      }
    },
    {
      "geometry": {
        "type": "Point",
        "coordinates": [
          -72.85,
          42.75
        ]
      },
      "type": "Feature",
      "properties": {
        "hierarchy": [
          "tgn:2197332",
          "tgn:1000001",
          "tgn:1003029",
          "tgn:7012149",
          "tgn:7007828",
          "tgn:7029392"
        ],
        "placetype": [
          "aat:300008699"
        ],
        "id": 2197332,
        "name:xx": "Brown Brook"
      }
    },
    {
      "geometry": {
        "type": "Point",
        "coordinates": [
          -68.9,
          46.4167
        ]
      },
      "type": "Feature",
      "properties": {
        "hierarchy": [
          "tgn:2197333",
          "tgn:1000001",
          "tgn:7012149",
          "tgn:2000928",
          "tgn:7007515",
          "tgn:7029392"
        ],
        "placetype": [
          "aat:300008680"
        ],
        "id": 2197333,
        "name:xx": "Brown Brook Pond"
      }
    },
    {
      "geometry": {
        "type": "Point",
        "coordinates": [
          -113.3167,
          44.4667
        ]
      },
      "type": "Feature",
      "properties": {
        "hierarchy": [
          "tgn:2197334",
          "tgn:1000001",
          "tgn:7012149",
          "tgn:2000481",
          "tgn:7007250",
          "tgn:7029392"
        ],
        "placetype": [
          "aat:300000390"
        ],
        "id": 2197334,
        "name:xx": "Brown Bull Mine"
      }
    },
    {
      "geometry": {
        "type": "Point",
        "coordinates": [
          -109.6333,
          34.0833
        ]
      },
      "type": "Feature",
      "properties": {
        "hierarchy": [
          "tgn:2197335",
          "tgn:2000090",
          "tgn:1000001",
          "tgn:7006451",
          "tgn:7012149",
          "tgn:7029392"
        ],
        "placetype": [
          "aat:300008798"
        ],
        "id": 2197335,
        "name:xx": "Brown Butte"
      }
    },
    {
      "geometry": {
        "type": "Point",
        "coordinates": [
          -121.5167,
          40.8333
        ]
      },
      "type": "Feature",
      "properties": {
        "hierarchy": [
          "tgn:2197336",
          "tgn:1000001",
          "tgn:7012149",
          "tgn:7007157",
          "tgn:2000188",
          "tgn:7029392"
        ],
        "placetype": [
          "aat:300008798"
        ],
        "id": 2197336,
        "name:xx": "Brown Butte"
      }
    },
    {
      "geometry": {
        "type": "Point",
        "coordinates": [
          -118.0167,
          34.9833
        ]
      },
      "type": "Feature",
      "properties": {
        "hierarchy": [
          "tgn:2197337",
          "tgn:1000001",
          "tgn:7012149",
          "tgn:1002545",
          "tgn:7007157",
          "tgn:7029392"
        ],
        "placetype": [
          "aat:300008798"
        ],
        "id": 2197337,
        "name:xx": "Brown Butte"
      }
    },
    {
      "geometry": {
        "type": "Point",
        "coordinates": [
          -114.2167,
          42.9833
        ]
      },
      "type": "Feature",
      "properties": {
        "hierarchy": [
          "tgn:2197338",
          "tgn:1000001",
          "tgn:7012149",
          "tgn:2000483",
          "tgn:7007250",
          "tgn:7029392"
        ],
        "placetype": [
          "aat:300008798"
        ],
        "id": 2197338,
        "name:xx": "Brown Butte"
      }
    },
    {
      "geometry": {
        "type": "Point",
        "coordinates": [
          -117.0833,
          43.7333
        ]
      },
      "type": "Feature",
      "properties": {
        "hierarchy": [
          "tgn:2197339",
          "tgn:1000001",
          "tgn:7012149",
          "tgn:2001718",
          "tgn:7007708",
          "tgn:7029392"
        ],
        "placetype": [
          "aat:300008798"
        ],
        "id": 2197339,
        "name:xx": "Brown Butte"
      }
    }
  ]
}
