{
  "geometry": {
    "type": "Point",
    "coordinates": [
      31.830691,
      31.483808
    ]
  },
  "type": "Feature",
  "properties": {
    "hierarchy": [
      "tgn:7523175",
      "tgn:7001242",
      "tgn:1001059",
      "tgn:7016833",
      "tgn:7029392"
    ],
    "placetype": [
      "aat:300008347"
    ],
    "name:en": "Ash Shaykh Ḑirghām",
    "id": 7523175
  }
}
