{
  "type": "FeatureCollection",
  "features": [
    {
      "geometry": {
        "type": "Point",
        "coordinates": [
          -3.283333,
          55.9
        ]
      },
      "type": "Feature",
      "properties": {
        "hierarchy": [
          "tgn:7461511",
          "tgn:7002444",
          "tgn:1000003",
          "tgn:7019109",
          "tgn:7008591",
          "tgn:7029392"
        ],
        "placetype": [
          "aat:300008347"
        ],
        "name:en": "Juniper Green",
        "id": 7461511
      }
    },
    {
      "geometry": {
        "type": "Point",
        "coordinates": [
          -2.466667,
          56.633333
        ]
      },
      "type": "Feature",
      "properties": {
        "hierarchy": [
          "tgn:7461512",
          "tgn:7019140",
          "tgn:7002444",
          "tgn:1000003",
          "tgn:7008591",
          "tgn:7029392"
        ],
        "placetype": [
          "aat:300011692"
        ],
        "name:en": "Joss Rock",
        "id": 7461512
      }
    },
    {
      "geometry": {
        "type": "Point",
        "coordinates": [
          -5.9,
          54.683333
        ]
      },
      "type": "Feature",
      "properties": {
        "hierarchy": [
          "tgn:7461513",
          "tgn:7002448",
          "tgn:1000003",
          "tgn:7019166",
          "tgn:7008591",
          "tgn:7029392"
        ],
        "placetype": [
          "aat:300008347"
        ],
        "name:en": "Jordanstown",
        "id": 7461513
      }
    },
    {
      "geometry": {
        "type": "Point",
        "coordinates": [
          -3.183333,
          56.6
        ]
      },
      "type": "Feature",
      "properties": {
        "hierarchy": [
          "tgn:7461514",
          "tgn:7002444",
          "tgn:1000003",
          "tgn:7019152",
          "tgn:7008591",
          "tgn:7029392"
        ],
        "placetype": [
          "aat:300007783"
        ],
        "name:en": "Jordanstone Station",
        "id": 7461514
      }
    },
    {
      "geometry": {
        "type": "Point",
        "coordinates": [
          -5.029722,
          51.953333
        ]
      },
      "type": "Feature",
      "properties": {
        "hierarchy": [
          "tgn:7461515",
          "tgn:7002443",
          "tgn:1000003",
          "tgn:7018993",
          "tgn:7008591",
          "tgn:7029392"
        ],
        "placetype": [
          "aat:300008347"
        ],
        "name:en": "Jordanston",
        "id": 7461515
      }
    },
    {
      "geometry": {
        "type": "Point",
        "coordinates": [
          -3.083333,
          55.95
        ]
      },
      "type": "Feature",
      "properties": {
        "hierarchy": [
          "tgn:7461517",
          "tgn:7002444",
          "tgn:1000003",
          "tgn:7019109",
          "tgn:7008591",
          "tgn:7029392"
        ],
        "placetype": [
          "aat:300000745"
        ],
        "name:en": "Joppa",
        "id": 7461517
      }
    },
    {
      "geometry": {
        "type": "Point",
        "coordinates": [
          -6.366667,
          54.1
        ]
      },
      "type": "Feature",
      "properties": {
        "hierarchy": [
          "tgn:7461518",
          "tgn:7002448",
          "tgn:1000003",
          "tgn:7019199",
          "tgn:7008591",
          "tgn:7029392"
        ],
        "placetype": [
          "aat:300008347"
        ],
        "name:en": "Jonesborough",
        "id": 7461518
      }
    },
    {
      "geometry": {
        "type": "Point",
        "coordinates": [
          -5.533333,
          55.366667
        ]
      },
      "type": "Feature",
      "properties": {
        "hierarchy": [
          "tgn:7461519",
          "tgn:7019094",
          "tgn:7002444",
          "tgn:1000003",
          "tgn:7008591",
          "tgn:7029392"
        ],
        "placetype": [
          "aat:300386846"
        ],
        "name:en": "Johnstons Point",
        "id": 7461519
      }
    }
  ]
}
