{
  "geometry": {
    "type": "Point",
    "coordinates": [
      -37.4833,
      -11.5167
    ]
  },
  "type": "Feature",
  "properties": {
    "hierarchy": [
      "tgn:1021638",
      "tgn:1001955",
      "tgn:1000047",
      "tgn:7002455",
      "tgn:1000002",
      "tgn:7029392"
    ],
    "placetype": [
      "aat:300008347"
    ],
    "id": 1021638,
    "name:xx": "Indiaroba"
  }
}
