{
  "geometry": {
    "type": "Point",
    "coordinates": [
      -116.7167,
      40.5333
    ]
  },
  "type": "Feature",
  "properties": {
    "hierarchy": [
      "tgn:2514739",
      "tgn:1000001",
      "tgn:2001415",
      "tgn:7012149",
      "tgn:7007526",
      "tgn:7029392"
    ],
    "placetype": [
      "aat:300000390"
    ],
    "id": 2514739,
    "name:xx": "Miller Mine"
  }
}
