{
  "geometry": {
    "type": "Point",
    "coordinates": [
      160.6333,
      -9.9333
    ]
  },
  "type": "Feature",
  "properties": {
    "hierarchy": [
      "tgn:1010774",
      "tgn:7002068",
      "tgn:1001273",
      "tgn:1000233",
      "tgn:1000006",
      "tgn:7029392"
    ],
    "placetype": [
      "aat:300008850"
    ],
    "id": 1010774,
    "name:xx": "Henslow, Cape"
  }
}
