{
  "geometry": {
    "type": "Point",
    "coordinates": [
      144.7833,
      -5.05
    ]
  },
  "type": "Feature",
  "properties": {
    "hierarchy": [
      "tgn:1099422",
      "tgn:1000886",
      "tgn:7006160",
      "tgn:1000006",
      "tgn:7029392"
    ],
    "placetype": [
      "aat:300008347"
    ],
    "id": 1099422,
    "name:xx": "Atemble"
  }
}
