{
  "geometry": {
    "type": "Point",
    "coordinates": [
      -104.6333,
      33.9667
    ]
  },
  "type": "Feature",
  "properties": {
    "hierarchy": [
      "tgn:2506693",
      "tgn:1000001",
      "tgn:2001430",
      "tgn:7012149",
      "tgn:7007566",
      "tgn:7029392"
    ],
    "placetype": [
      "aat:300006191"
    ],
    "id": 2506693,
    "name:xx": "Mesa Tank"
  }
}
