{
  "geometry": {
    "type": "Point",
    "coordinates": [
      -83.2667,
      33.3833
    ]
  },
  "type": "Feature",
  "properties": {
    "hierarchy": [
      "tgn:2684803",
      "tgn:1000001",
      "tgn:7012149",
      "tgn:2000408",
      "tgn:7007248",
      "tgn:7029392"
    ],
    "placetype": [
      "aat:300008347"
    ],
    "id": 2684803,
    "name:xx": "Spivey"
  }
}
