{
  "geometry": {
    "type": "Point",
    "coordinates": [
      34.7667,
      31.9333
    ]
  },
  "type": "Feature",
  "properties": {
    "hierarchy": [
      "tgn:1079578",
      "tgn:1000862",
      "tgn:1000004",
      "tgn:1000119",
      "tgn:7029392"
    ],
    "placetype": [
      "aat:300008347"
    ],
    "id": 1079578,
    "name:xx": "Nes Ẕiyyona"
  }
}
