{
  "geometry": {
    "type": "Point",
    "coordinates": [
      113.5333,
      30.8667
    ]
  },
  "type": "Feature",
  "properties": {
    "hierarchy": [
      "tgn:1123271",
      "tgn:1000004",
      "tgn:7002078",
      "tgn:1000111",
      "tgn:7029392"
    ],
    "placetype": [
      "aat:300008707"
    ],
    "id": 1123271,
    "name:xx": "Dafu"
  }
}
