{
  "geometry": {
    "type": "Point",
    "coordinates": [
      -90.1667,
      38.5667
    ]
  },
  "type": "Feature",
  "properties": {
    "hierarchy": [
      "tgn:2491753",
      "tgn:1000001",
      "tgn:7012149",
      "tgn:7016022",
      "tgn:7007251",
      "tgn:7029392"
    ],
    "placetype": [
      "aat:300008347"
    ],
    "id": 2491753,
    "name:xx": "Maplewood Park"
  }
}
