{
  "geometry": {
    "type": "Point",
    "coordinates": [
      -95.15,
      31.85
    ]
  },
  "type": "Feature",
  "properties": {
    "hierarchy": [
      "tgn:2132849",
      "tgn:1000001",
      "tgn:7012149",
      "tgn:1002263",
      "tgn:7007826",
      "tgn:7029392"
    ],
    "placetype": [
      "aat:300008699"
    ],
    "id": 2132849,
    "name:xx": "Anderson Branch"
  }
}
