{
  "type": "FeatureCollection",
  "features": [
    {
      "geometry": {
        "type": "Point",
        "coordinates": [
          -2.733333,
          52.366667
        ]
      },
      "type": "Feature",
      "properties": {
        "hierarchy": [
          "tgn:7012100",
          "tgn:7002445",
          "tgn:1000003",
          "tgn:7012034",
          "tgn:7008591",
          "tgn:7029392"
        ],
        "placetype": [
          "aat:300008347"
        ],
        "name:en": "Ludlow",
        "id": 7012100
      }
    },
    {
      "geometry": {
        "type": "Point",
        "coordinates": [
          -2.2333,
          53.7333
        ]
      },
      "type": "Feature",
      "properties": {
        "hierarchy": [
          "tgn:7012102",
          "tgn:7002445",
          "tgn:1000003",
          "tgn:7008154",
          "tgn:7008591",
          "tgn:7029392"
        ],
        "placetype": [
          "aat:300008347"
        ],
        "id": 7012102,
        "name:xx": "Water"
      }
    },
    {
      "geometry": {
        "type": "Point",
        "coordinates": [
          2.8333,
          45.5333
        ]
      },
      "type": "Feature",
      "properties": {
        "hierarchy": [
          "tgn:7012106",
          "tgn:7002871",
          "tgn:1000003",
          "tgn:1000070",
          "tgn:7029392"
        ],
        "placetype": [
          "aat:300008795"
        ],
        "id": 7012106,
        "name:xx": "Sancy, Puy de"
      }
    },
    {
      "geometry": {
        "type": "Point",
        "coordinates": [
          -6.75,
          54.516667
        ]
      },
      "type": "Feature",
      "properties": {
        "hierarchy": [
          "tgn:7012107",
          "tgn:7002448",
          "tgn:7019203",
          "tgn:1000003",
          "tgn:7008591",
          "tgn:7029392"
        ],
        "placetype": [
          "aat:300008347",
          "aat:300387220"
        ],
        "name:en": "Dungannon",
        "id": 7012107
      }
    },
    {
      "geometry": {
        "type": "Point",
        "coordinates": [
          -7.1333,
          55.1
        ]
      },
      "type": "Feature",
      "properties": {
        "hierarchy": [
          "tgn:7012108",
          "tgn:7001181",
          "tgn:1000003",
          "tgn:1009896",
          "tgn:7029392"
        ],
        "placetype": [
          "aat:300266571"
        ],
        "id": 7012108,
        "name:xx": "Foyle, Lough"
      }
    },
    {
      "geometry": {
        "type": "Point",
        "coordinates": [
          -6.766667,
          54.8
        ]
      },
      "type": "Feature",
      "properties": {
        "hierarchy": [
          "tgn:7012109",
          "tgn:7002448",
          "tgn:7019217",
          "tgn:1000003",
          "tgn:7008591",
          "tgn:7029392"
        ],
        "placetype": [
          "aat:300008347"
        ],
        "name:en": "Draperstown",
        "id": 7012109
      }
    }
  ]
}
