{
  "geometry": {
    "type": "Point",
    "coordinates": [
      -112.35,
      47.0167
    ]
  },
  "type": "Feature",
  "properties": {
    "hierarchy": [
      "tgn:2132578",
      "tgn:1000001",
      "tgn:7012149",
      "tgn:2001284",
      "tgn:7007524",
      "tgn:7029392"
    ],
    "placetype": [
      "aat:300000390"
    ],
    "id": 2132578,
    "name:xx": "Anaconda Mine"
  }
}
