{
  "geometry": {
    "type": "Point",
    "coordinates": [
      -82.0333,
      34.9833
    ]
  },
  "type": "Feature",
  "properties": {
    "hierarchy": [
      "tgn:2362212",
      "tgn:1000001",
      "tgn:7012149",
      "tgn:2001766",
      "tgn:7007712",
      "tgn:7029392"
    ],
    "placetype": [
      "aat:300008706"
    ],
    "id": 2362212,
    "name:xx": "Grays Creek"
  }
}
