{
  "geometry": {
    "type": "Point",
    "coordinates": [
      -114.0833,
      36.2667
    ]
  },
  "type": "Feature",
  "properties": {
    "hierarchy": [
      "tgn:2141461",
      "tgn:1000001",
      "tgn:7012149",
      "tgn:7029392"
    ],
    "placetype": [
      "aat:300008761"
    ],
    "id": 2141461,
    "name:xx": "Azure Ridge Draw"
  }
}
