{
  "geometry": {
    "type": "Point",
    "coordinates": [
      -114.6833,
      47.1833
    ]
  },
  "type": "Feature",
  "properties": {
    "hierarchy": [
      "tgn:2547312",
      "tgn:1000001",
      "tgn:7012149",
      "tgn:7007524",
      "tgn:7029392"
    ],
    "placetype": [
      "aat:300008706"
    ],
    "id": 2547312,
    "name:xx": "North Fork Second Creek"
  }
}
