{
  "geometry": {
    "type": "Point",
    "coordinates": [
      -74.8333,
      44.7833
    ]
  },
  "type": "Feature",
  "properties": {
    "hierarchy": [
      "tgn:2161019",
      "tgn:1000001",
      "tgn:7012149",
      "tgn:7016021",
      "tgn:7007568",
      "tgn:7029392"
    ],
    "placetype": [
      "aat:300008699"
    ],
    "id": 2161019,
    "name:xx": "Bell Brook"
  }
}
