{
  "geometry": {
    "type": "Point",
    "coordinates": [
      -111.9833,
      33.4667
    ]
  },
  "type": "Feature",
  "properties": {
    "hierarchy": [
      "tgn:2482790",
      "tgn:1000001",
      "tgn:7006451",
      "tgn:7012149",
      "tgn:2000097",
      "tgn:7029392"
    ],
    "placetype": [
      "aat:300008347"
    ],
    "id": 2482790,
    "name:xx": "Lariat Tra-Tel Trailer Court"
  }
}
