{
  "geometry": {
    "type": "Point",
    "coordinates": [
      -83.6833,
      39.9167
    ]
  },
  "type": "Feature",
  "properties": {
    "hierarchy": [
      "tgn:2079895",
      "tgn:1000001",
      "tgn:1002274",
      "tgn:7012149",
      "tgn:7007706",
      "tgn:7029392"
    ],
    "placetype": [
      "aat:300008347"
    ],
    "id": 2079895,
    "name:xx": "Harmony"
  }
}
