{
  "geometry": {
    "type": "Point",
    "coordinates": [
      -123.3833,
      46.0833
    ]
  },
  "type": "Feature",
  "properties": {
    "hierarchy": [
      "tgn:2758664",
      "tgn:1000001",
      "tgn:7012149",
      "tgn:7007708",
      "tgn:7029392"
    ],
    "placetype": [
      "aat:300008706"
    ],
    "id": 2758664,
    "name:xx": "West Creek"
  }
}
