{
  "geometry": {
    "type": "Point",
    "coordinates": [
      -157.3333,
      58.8167
    ]
  },
  "type": "Feature",
  "properties": {
    "hierarchy": [
      "tgn:2372121",
      "tgn:7006450",
      "tgn:1000001",
      "tgn:2124105",
      "tgn:7012149",
      "tgn:7029392"
    ],
    "placetype": [
      "aat:300132316"
    ],
    "id": 2372121,
    "name:xx": "Halfmoon Bay"
  }
}
