{
  "geometry": {
    "type": "Point",
    "coordinates": [
      -80.1833,
      37.4833
    ]
  },
  "type": "Feature",
  "properties": {
    "hierarchy": [
      "tgn:2002154",
      "tgn:1000001",
      "tgn:7012149",
      "tgn:7007919",
      "tgn:7029392"
    ],
    "placetype": [
      "aat:300387145",
      "aat:300000771"
    ],
    "id": 2002154,
    "name:xx": "Craig"
  }
}
