{
  "geometry": {
    "type": "Point",
    "coordinates": [
      -122.05,
      47.5833
    ]
  },
  "type": "Feature",
  "properties": {
    "hierarchy": [
      "tgn:2431095",
      "tgn:1000001",
      "tgn:7012149",
      "tgn:7018871",
      "tgn:7007920",
      "tgn:7029392"
    ],
    "placetype": [
      "aat:300008706"
    ],
    "id": 2431095,
    "name:xx": "Kanim Creek"
  }
}
