{
  "type": "FeatureCollection",
  "features": [
    {
      "geometry": {
        "type": "Point",
        "coordinates": [
          34.2667,
          38.3
        ]
      },
      "type": "Feature",
      "properties": {
        "hierarchy": [
          "tgn:4012410",
          "tgn:1001442",
          "tgn:1000004",
          "tgn:7018453",
          "tgn:1000144",
          "tgn:7029392"
        ],
        "placetype": [
          "aat:300008347",
          "aat:300008375"
        ],
        "id": 4012410,
        "name:xx": "Yaprakhisar"
      }
    },
    {
      "geometry": {
        "type": "Point",
        "coordinates": [
          -2.483333,
          51.05
        ]
      },
      "type": "Feature",
      "properties": {
        "hierarchy": [
          "tgn:4012411",
          "tgn:7002445",
          "tgn:1000003",
          "tgn:7012032",
          "tgn:7008591",
          "tgn:7029392"
        ],
        "placetype": [
          "aat:300008347"
        ],
        "name:en": "Yarlington",
        "id": 4012411
      }
    },
    {
      "geometry": {
        "type": "Point",
        "coordinates": [
          -1.35,
          54.5
        ]
      },
      "type": "Feature",
      "properties": {
        "hierarchy": [
          "tgn:4012412",
          "tgn:7002445",
          "tgn:1000003",
          "tgn:7019067",
          "tgn:7008591",
          "tgn:7029392"
        ],
        "placetype": [
          "aat:300008347"
        ],
        "name:en": "Yarm",
        "id": 4012412
      }
    },
    {
      "geometry": {
        "type": "Point",
        "coordinates": [
          -2.866667,
          52.116667
        ]
      },
      "type": "Feature",
      "properties": {
        "hierarchy": [
          "tgn:4012416",
          "tgn:7002445",
          "tgn:1000003",
          "tgn:7008143",
          "tgn:7008591",
          "tgn:7029392"
        ],
        "placetype": [
          "aat:300008347",
          "aat:300008372"
        ],
        "name:en": "Yazor",
        "id": 4012416
      }
    }
  ]
}
