{
  "geometry": {
    "type": "Point",
    "coordinates": [
      -117.0667,
      48.5833
    ]
  },
  "type": "Feature",
  "properties": {
    "hierarchy": [
      "tgn:2607634",
      "tgn:1000001",
      "tgn:7012149",
      "tgn:2002248",
      "tgn:7007920",
      "tgn:7029392"
    ],
    "placetype": [
      "aat:300008706"
    ],
    "id": 2607634,
    "name:xx": "Rapids Creek"
  }
}
