{
  "geometry": {
    "type": "Point",
    "coordinates": [
      -122.9667,
      38.8833
    ]
  },
  "type": "Feature",
  "properties": {
    "hierarchy": [
      "tgn:2290568",
      "tgn:1000001",
      "tgn:7012149",
      "tgn:7007157",
      "tgn:2000185",
      "tgn:7029392"
    ],
    "placetype": [
      "aat:300008798"
    ],
    "id": 2290568,
    "name:xx": "Doe Rock"
  }
}
