{
  "geometry": {
    "type": "Point",
    "coordinates": [
      16.825,
      -9.675
    ]
  },
  "type": "Feature",
  "properties": {
    "hierarchy": [
      "tgn:1000888",
      "tgn:7001242",
      "tgn:1000149",
      "tgn:7029392"
    ],
    "placetype": [
      "aat:300387064",
      "aat:300000774"
    ],
    "id": 1000888,
    "name:xx": "Malanje"
  }
}
