{
  "geometry": {
    "type": "Point",
    "coordinates": [
      -91.783333,
      16.85
    ]
  },
  "type": "Feature",
  "properties": {
    "hierarchy": [
      "tgn:1131180",
      "tgn:7005580",
      "tgn:1000001",
      "tgn:7005560",
      "tgn:7029392"
    ],
    "placetype": [
      "aat:300008707",
      "aat:300008699"
    ],
    "id": 1131180,
    "name:xx": "Tzanconeja, Río"
  }
}
