{
  "geometry": {
    "type": "Point",
    "coordinates": [
      -90.2667,
      37.6167
    ]
  },
  "type": "Feature",
  "properties": {
    "hierarchy": [
      "tgn:2707604",
      "tgn:1000001",
      "tgn:7012149",
      "tgn:2001217",
      "tgn:7007523",
      "tgn:7029392"
    ],
    "placetype": [
      "aat:300008699"
    ],
    "id": 2707604,
    "name:xx": "Sweetwater Branch"
  }
}
