{
  "geometry": {
    "type": "Point",
    "coordinates": [
      -81.75,
      35.45
    ]
  },
  "type": "Feature",
  "properties": {
    "hierarchy": [
      "tgn:2712549",
      "tgn:1000001",
      "tgn:7012149",
      "tgn:2001537",
      "tgn:7007709",
      "tgn:7029392"
    ],
    "placetype": [
      "aat:300008699"
    ],
    "id": 2712549,
    "name:xx": "Taylor Branch"
  }
}
