{
  "geometry": {
    "type": "Point",
    "coordinates": [
      -82.8833,
      40.05
    ]
  },
  "type": "Feature",
  "properties": {
    "hierarchy": [
      "tgn:2240522",
      "tgn:1000001",
      "tgn:7012149",
      "tgn:1002386",
      "tgn:7007706",
      "tgn:7029392"
    ],
    "placetype": [
      "aat:300006191"
    ],
    "id": 2240522,
    "name:xx": "City of Columbus Sludge Pond"
  }
}
