{
  "type": "FeatureCollection",
  "features": [
    {
      "geometry": {
        "type": "Point",
        "coordinates": [
          -71.7667,
          43.6833
        ]
      },
      "type": "Feature",
      "properties": {
        "hierarchy": [
          "tgn:2469920",
          "tgn:1000001",
          "tgn:2001424",
          "tgn:7012149",
          "tgn:7007564",
          "tgn:7029392"
        ],
        "placetype": [
          "aat:300008791"
        ],
        "id": 2469920,
        "name:xx": "Loon Island"
      }
    },
    {
      "geometry": {
        "type": "Point",
        "coordinates": [
          -73.5,
          43.65
        ]
      },
      "type": "Feature",
      "properties": {
        "hierarchy": [
          "tgn:2469921",
          "tgn:1000001",
          "tgn:7012149",
          "tgn:1002986",
          "tgn:7007568",
          "tgn:7029392"
        ],
        "placetype": [
          "aat:300008791"
        ],
        "id": 2469921,
        "name:xx": "Loon Island"
      }
    },
    {
      "geometry": {
        "type": "Point",
        "coordinates": [
          -91.1,
          46.0667
        ]
      },
      "type": "Feature",
      "properties": {
        "hierarchy": [
          "tgn:2469922",
          "tgn:1000001",
          "tgn:7012149",
          "tgn:2002353",
          "tgn:7007922",
          "tgn:7029392"
        ],
        "placetype": [
          "aat:300008791"
        ],
        "id": 2469922,
        "name:xx": "Loon Island"
      }
    },
    {
      "geometry": {
        "type": "Point",
        "coordinates": [
          -71.5167,
          43.75
        ]
      },
      "type": "Feature",
      "properties": {
        "hierarchy": [
          "tgn:2469923",
          "tgn:2001423",
          "tgn:1000001",
          "tgn:7012149",
          "tgn:7007564",
          "tgn:7029392"
        ],
        "placetype": [
          "aat:300386853"
        ],
        "id": 2469923,
        "name:xx": "Loon Islands"
      }
    },
    {
      "geometry": {
        "type": "Point",
        "coordinates": [
          -132.5,
          55.6167
        ]
      },
      "type": "Feature",
      "properties": {
        "hierarchy": [
          "tgn:2469924",
          "tgn:7006450",
          "tgn:1000001",
          "tgn:7012149",
          "tgn:2000082",
          "tgn:7029392"
        ],
        "placetype": [
          "aat:300008680"
        ],
        "id": 2469924,
        "name:xx": "Loon Lake"
      }
    },
    {
      "geometry": {
        "type": "Point",
        "coordinates": [
          -151,
          59.7
        ]
      },
      "type": "Feature",
      "properties": {
        "hierarchy": [
          "tgn:2469925",
          "tgn:7006450",
          "tgn:1000001",
          "tgn:7019698",
          "tgn:7012149",
          "tgn:7029392"
        ],
        "placetype": [
          "aat:300008680"
        ],
        "id": 2469925,
        "name:xx": "Loon Lake"
      }
    },
    {
      "geometry": {
        "type": "Point",
        "coordinates": [
          -146.5833,
          62.1833
        ]
      },
      "type": "Feature",
      "properties": {
        "hierarchy": [
          "tgn:2469926",
          "tgn:7006450",
          "tgn:1000001",
          "tgn:7012149",
          "tgn:2000086",
          "tgn:7029392"
        ],
        "placetype": [
          "aat:300008680"
        ],
        "id": 2469926,
        "name:xx": "Loon Lake"
      }
    },
    {
      "geometry": {
        "type": "Point",
        "coordinates": [
          -143.75,
          66.8167
        ]
      },
      "type": "Feature",
      "properties": {
        "hierarchy": [
          "tgn:2469927",
          "tgn:7006450",
          "tgn:1000001",
          "tgn:7012149",
          "tgn:2000089",
          "tgn:7029392"
        ],
        "placetype": [
          "aat:300008680"
        ],
        "id": 2469927,
        "name:xx": "Loon Lake"
      }
    },
    {
      "geometry": {
        "type": "Point",
        "coordinates": [
          -149.75,
          61.6
        ]
      },
      "type": "Feature",
      "properties": {
        "hierarchy": [
          "tgn:2469928",
          "tgn:7006450",
          "tgn:1000001",
          "tgn:2124053",
          "tgn:7012149",
          "tgn:7029392"
        ],
        "placetype": [
          "aat:300008680"
        ],
        "id": 2469928,
        "name:xx": "Loon Lake"
      }
    },
    {
      "geometry": {
        "type": "Point",
        "coordinates": [
          -115.8333,
          45.15
        ]
      },
      "type": "Feature",
      "properties": {
        "hierarchy": [
          "tgn:2469929",
          "tgn:1000001",
          "tgn:7012149",
          "tgn:2000494",
          "tgn:7007250",
          "tgn:7029392"
        ],
        "placetype": [
          "aat:300008680"
        ],
        "id": 2469929,
        "name:xx": "Loon Lake"
      }
    }
  ]
}
