{
  "geometry": {
    "type": "Point",
    "coordinates": [
      -76.5167,
      35.3167
    ]
  },
  "type": "Feature",
  "properties": {
    "hierarchy": [
      "tgn:2156119",
      "tgn:1000001",
      "tgn:7012149",
      "tgn:2001526",
      "tgn:7007709",
      "tgn:7029392"
    ],
    "placetype": [
      "aat:300008850"
    ],
    "id": 2156119,
    "name:xx": "Beard Island Point"
  }
}
