{
  "geometry": {
    "type": "Point",
    "coordinates": [
      -82.7167,
      40.65
    ]
  },
  "type": "Feature",
  "properties": {
    "hierarchy": [
      "tgn:2764375",
      "tgn:1000001",
      "tgn:7012149",
      "tgn:7007706",
      "tgn:7029392"
    ],
    "placetype": [
      "aat:300008706"
    ],
    "id": 2764375,
    "name:xx": "Whetstone Creek"
  }
}
