{
  "geometry": {
    "type": "Point",
    "coordinates": [
      -114.9667,
      41.3167
    ]
  },
  "type": "Feature",
  "properties": {
    "hierarchy": [
      "tgn:1107103",
      "tgn:1000001",
      "tgn:2001411",
      "tgn:7012149",
      "tgn:7007526",
      "tgn:7029392"
    ],
    "placetype": [
      "aat:300008798"
    ],
    "id": 1107103,
    "name:xx": "Antelope Peak"
  }
}
