{
  "geometry": {
    "type": "Point",
    "coordinates": [
      -87.8167,
      40.1833
    ]
  },
  "type": "Feature",
  "properties": {
    "hierarchy": [
      "tgn:2250319",
      "tgn:1000001",
      "tgn:7012149",
      "tgn:1002974",
      "tgn:7007251",
      "tgn:7029392"
    ],
    "placetype": [
      "aat:300008699"
    ],
    "id": 2250319,
    "name:xx": "Collison Branch"
  }
}
