{
  "geometry": {
    "type": "Point",
    "coordinates": [
      -92.95,
      39.3667
    ]
  },
  "type": "Feature",
  "properties": {
    "hierarchy": [
      "tgn:2768348",
      "tgn:1000001",
      "tgn:2001184",
      "tgn:7012149",
      "tgn:7007523",
      "tgn:7029392"
    ],
    "placetype": [
      "aat:300008680"
    ],
    "id": 2768348,
    "name:xx": "Whiteside Lake"
  }
}
