{
  "geometry": {
    "type": "Point",
    "coordinates": [
      -83.2167,
      31.6333
    ]
  },
  "type": "Feature",
  "properties": {
    "hierarchy": [
      "tgn:2703686",
      "tgn:1000001",
      "tgn:7012149",
      "tgn:2000368",
      "tgn:7007248",
      "tgn:7029392"
    ],
    "placetype": [
      "aat:300006191"
    ],
    "id": 2703686,
    "name:xx": "Sumner Lake"
  }
}
