{
  "geometry": {
    "type": "Point",
    "coordinates": [
      121.45,
      31.35
    ]
  },
  "type": "Feature",
  "properties": {
    "hierarchy": [
      "tgn:1070648",
      "tgn:1000004",
      "tgn:1000958",
      "tgn:1000111",
      "tgn:7029392"
    ],
    "placetype": [
      "aat:300008347"
    ],
    "id": 1070648,
    "name:xx": "Nansunzhai"
  }
}
