{
  "geometry": {
    "type": "Point",
    "coordinates": [
      -105.9833,
      43.15
    ]
  },
  "type": "Feature",
  "properties": {
    "hierarchy": [
      "tgn:2678691",
      "tgn:1000001",
      "tgn:2002369",
      "tgn:7012149",
      "tgn:7007923",
      "tgn:7029392"
    ],
    "placetype": [
      "aat:300008707"
    ],
    "id": 2678691,
    "name:xx": "South Fork Dry Fork Cheyenne River"
  }
}
