{
  "geometry": {
    "type": "Point",
    "coordinates": [
      -85.6333,
      36.5667
    ]
  },
  "type": "Feature",
  "properties": {
    "hierarchy": [
      "tgn:2100999",
      "tgn:1000001",
      "tgn:7012149",
      "tgn:2001850",
      "tgn:7007825",
      "tgn:7029392"
    ],
    "placetype": [
      "aat:300008347",
      "aat:300387210"
    ],
    "id": 2100999,
    "name:xx": "Pine Hill"
  }
}
