{
  "geometry": {
    "type": "Point",
    "coordinates": [
      16.8833,
      59.9333
    ]
  },
  "type": "Feature",
  "properties": {
    "hierarchy": [
      "tgn:1063117",
      "tgn:1000003",
      "tgn:7003780",
      "tgn:1000097",
      "tgn:7029392"
    ],
    "placetype": [
      "aat:300008347"
    ],
    "id": 1063117,
    "name:xx": "Heby"
  }
}
