{
  "type": "FeatureCollection",
  "features": [
    {
      "geometry": {
        "type": "Point",
        "coordinates": [
          -80.3333,
          43.9
        ]
      },
      "type": "Feature",
      "properties": {
        "hierarchy": [
          "tgn:1014800",
          "tgn:7005685",
          "tgn:1000001",
          "tgn:7013154",
          "tgn:7029392"
        ],
        "placetype": [
          "aat:300008347"
        ],
        "id": 1014800,
        "name:xx": "Grand Valley"
      }
    },
    {
      "geometry": {
        "type": "Point",
        "coordinates": [
          -79.3667,
          44.9167
        ]
      },
      "type": "Feature",
      "properties": {
        "hierarchy": [
          "tgn:1014801",
          "tgn:7005685",
          "tgn:1000001",
          "tgn:7013154",
          "tgn:7029392"
        ],
        "placetype": [
          "aat:300008347"
        ],
        "id": 1014801,
        "name:xx": "Gravenhurst"
      }
    },
    {
      "geometry": {
        "type": "Point",
        "coordinates": [
          -74.6,
          45.2667
        ]
      },
      "type": "Feature",
      "properties": {
        "hierarchy": [
          "tgn:1014802",
          "tgn:7005685",
          "tgn:1000001",
          "tgn:7013154",
          "tgn:7029392"
        ],
        "placetype": [
          "aat:300008347"
        ],
        "id": 1014802,
        "name:xx": "Green Valley"
      }
    },
    {
      "geometry": {
        "type": "Point",
        "coordinates": [
          -79.3,
          43.8333
        ]
      },
      "type": "Feature",
      "properties": {
        "hierarchy": [
          "tgn:1014805",
          "tgn:7005685",
          "tgn:1000001",
          "tgn:7013154",
          "tgn:7029392"
        ],
        "placetype": [
          "aat:300008347"
        ],
        "id": 1014805,
        "name:xx": "Hagerman Corners"
      }
    },
    {
      "geometry": {
        "type": "Point",
        "coordinates": [
          -80.0667,
          42.9667
        ]
      },
      "type": "Feature",
      "properties": {
        "hierarchy": [
          "tgn:1014806",
          "tgn:7005685",
          "tgn:1000001",
          "tgn:7013154",
          "tgn:7029392"
        ],
        "placetype": [
          "aat:300008347"
        ],
        "id": 1014806,
        "name:xx": "Hagersville"
      }
    },
    {
      "geometry": {
        "type": "Point",
        "coordinates": [
          -79.65,
          47.45
        ]
      },
      "type": "Feature",
      "properties": {
        "hierarchy": [
          "tgn:1014807",
          "tgn:7005685",
          "tgn:1000001",
          "tgn:7013154",
          "tgn:7029392"
        ],
        "placetype": [
          "aat:300008347"
        ],
        "id": 1014807,
        "name:xx": "Haileybury"
      }
    },
    {
      "geometry": {
        "type": "Point",
        "coordinates": [
          -78.5,
          45.05
        ]
      },
      "type": "Feature",
      "properties": {
        "hierarchy": [
          "tgn:1014808",
          "tgn:7005685",
          "tgn:1000001",
          "tgn:7013154",
          "tgn:7029392"
        ],
        "placetype": [
          "aat:300008347"
        ],
        "id": 1014808,
        "name:xx": "Haliburton"
      }
    },
    {
      "geometry": {
        "type": "Point",
        "coordinates": [
          -79.85,
          42.9333
        ]
      },
      "type": "Feature",
      "properties": {
        "hierarchy": [
          "tgn:1014809",
          "tgn:7005685",
          "tgn:1000001",
          "tgn:7013154",
          "tgn:7029392"
        ],
        "placetype": [
          "aat:300008347"
        ],
        "id": 1014809,
        "name:xx": "Halidmand"
      }
    }
  ]
}
