{
  "geometry": {
    "type": "Point",
    "coordinates": [
      -114.1833,
      35.35
    ]
  },
  "type": "Feature",
  "properties": {
    "hierarchy": [
      "tgn:2316750",
      "tgn:1000001",
      "tgn:7006451",
      "tgn:7012149",
      "tgn:2000098",
      "tgn:7029392"
    ],
    "placetype": [
      "aat:300000390"
    ],
    "id": 2316750,
    "name:xx": "Emerald Isle Mine"
  }
}
