{
  "geometry": {
    "type": "Point",
    "coordinates": [
      -94.25,
      32.1667
    ]
  },
  "type": "Feature",
  "properties": {
    "hierarchy": [
      "tgn:2329980",
      "tgn:1000001",
      "tgn:7012149",
      "tgn:1002769",
      "tgn:7007826",
      "tgn:7029392"
    ],
    "placetype": [
      "aat:300008905"
    ],
    "id": 2329980,
    "name:xx": "Flag Pond"
  }
}
