{
  "geometry": {
    "type": "Point",
    "coordinates": [
      22.75,
      -25.8333
    ]
  },
  "type": "Feature",
  "properties": {
    "hierarchy": [
      "tgn:1128585",
      "tgn:7001242",
      "tgn:7029392"
    ],
    "placetype": [
      "aat:300008707"
    ],
    "id": 1128585,
    "name:xx": "Phepane"
  }
}
