{
  "geometry": {
    "type": "Point",
    "coordinates": [
      -111.85,
      41.1833
    ]
  },
  "type": "Feature",
  "properties": {
    "hierarchy": [
      "tgn:2297116",
      "tgn:1000001",
      "tgn:7012149",
      "tgn:2002115",
      "tgn:7007827",
      "tgn:7029392"
    ],
    "placetype": [
      "aat:300008706"
    ],
    "id": 2297116,
    "name:xx": "Dry Creek"
  }
}
