{
  "geometry": {
    "type": "Point",
    "coordinates": [
      -109.2667,
      31.8333
    ]
  },
  "type": "Feature",
  "properties": {
    "hierarchy": [
      "tgn:2304029",
      "tgn:1000001",
      "tgn:7006451",
      "tgn:2000091",
      "tgn:7012149",
      "tgn:7029392"
    ],
    "placetype": [
      "aat:300008697"
    ],
    "id": 2304029,
    "name:xx": "Eagle Spring"
  }
}
