{
  "geometry": {
    "type": "Point",
    "coordinates": [
      -97.55,
      33.0667
    ]
  },
  "type": "Feature",
  "properties": {
    "hierarchy": [
      "tgn:2102857",
      "tgn:1000001",
      "tgn:7012149",
      "tgn:1003031",
      "tgn:7007826",
      "tgn:7029392"
    ],
    "placetype": [
      "aat:300008347"
    ],
    "id": 2102857,
    "name:xx": "Boyd"
  }
}
