{
  "geometry": {
    "type": "Point",
    "coordinates": [
      -91.9833,
      45.5833
    ]
  },
  "type": "Feature",
  "properties": {
    "hierarchy": [
      "tgn:2363084",
      "tgn:2002307",
      "tgn:1000001",
      "tgn:7012149",
      "tgn:7007922",
      "tgn:7029392"
    ],
    "placetype": [
      "aat:300008680"
    ],
    "id": 2363084,
    "name:xx": "Greeley Lake"
  }
}
