{
  "geometry": {
    "type": "Point",
    "coordinates": [
      -92.9667,
      35.5333
    ]
  },
  "type": "Feature",
  "properties": {
    "hierarchy": [
      "tgn:2496484",
      "tgn:1000001",
      "tgn:7016172",
      "tgn:7012149",
      "tgn:2000162",
      "tgn:7029392"
    ],
    "placetype": [
      "aat:300008761"
    ],
    "id": 2496484,
    "name:xx": "Mathis Hollow"
  }
}
