{
  "geometry": {
    "type": "Point",
    "coordinates": [
      -94.8833,
      39.8833
    ]
  },
  "type": "Feature",
  "properties": {
    "hierarchy": [
      "tgn:2567852",
      "tgn:2001168",
      "tgn:1000001",
      "tgn:7012149",
      "tgn:7007523",
      "tgn:7029392"
    ],
    "placetype": [
      "aat:300006191"
    ],
    "id": 2567852,
    "name:xx": "Paradise Lake"
  }
}
