{
  "geometry": {
    "type": "Point",
    "coordinates": [
      -80.9167,
      36.65
    ]
  },
  "type": "Feature",
  "properties": {
    "hierarchy": [
      "tgn:2111883",
      "tgn:1000001",
      "tgn:7012149",
      "tgn:2002212",
      "tgn:7007919",
      "tgn:7029392"
    ],
    "placetype": [
      "aat:300008347"
    ],
    "id": 2111883,
    "name:xx": "Galax"
  }
}
