{
  "geometry": {
    "type": "Point",
    "coordinates": [
      78.566667,
      9.116667
    ]
  },
  "type": "Feature",
  "properties": {
    "hierarchy": [
      "tgn:7555104",
      "tgn:1000004",
      "tgn:7000198",
      "tgn:7001797",
      "tgn:7029392"
    ],
    "placetype": [
      "aat:300008791"
    ],
    "name:en": "Nallatanni Tīvu",
    "id": 7555104
  }
}
