{
  "geometry": {
    "type": "Point",
    "coordinates": [
      26.5333,
      55.8833
    ]
  },
  "type": "Feature",
  "properties": {
    "hierarchy": [
      "tgn:7006491",
      "tgn:1000003",
      "tgn:7006541",
      "tgn:7029392"
    ],
    "placetype": [
      "aat:300387064",
      "aat:300387081"
    ],
    "id": 7006491,
    "name:xx": "Daugavpils"
  }
}
