{
  "geometry": {
    "type": "Point",
    "coordinates": [
      -73.6167,
      41.7667
    ]
  },
  "type": "Feature",
  "properties": {
    "hierarchy": [
      "tgn:2533772",
      "tgn:1000001",
      "tgn:1002347",
      "tgn:7012149",
      "tgn:7007568",
      "tgn:7029392"
    ],
    "placetype": [
      "aat:300008761"
    ],
    "id": 2533772,
    "name:xx": "Mutton Hollow"
  }
}
