{
  "geometry": {
    "type": "Point",
    "coordinates": [
      -92.5833,
      40.7833
    ]
  },
  "type": "Feature",
  "properties": {
    "hierarchy": [
      "tgn:2035431",
      "tgn:1000001",
      "tgn:2000586",
      "tgn:7012149",
      "tgn:7007253",
      "tgn:7029392"
    ],
    "placetype": [
      "aat:300008347"
    ],
    "id": 2035431,
    "name:xx": "Paris"
  }
}
