{
  "geometry": {
    "type": "Point",
    "coordinates": [
      -72.2667,
      44.1667
    ]
  },
  "type": "Feature",
  "properties": {
    "hierarchy": [
      "tgn:2709481",
      "tgn:1000001",
      "tgn:2002134",
      "tgn:7012149",
      "tgn:7007828",
      "tgn:7029392"
    ],
    "placetype": [
      "aat:300008699"
    ],
    "id": 2709481,
    "name:xx": "Tabor Branch"
  }
}
