{
  "geometry": {
    "type": "Point",
    "coordinates": [
      -82.2667,
      27.0167
    ]
  },
  "type": "Feature",
  "properties": {
    "hierarchy": [
      "tgn:2711934",
      "tgn:1000001",
      "tgn:7012149",
      "tgn:1002870",
      "tgn:7007240",
      "tgn:7029392"
    ],
    "placetype": [
      "aat:300008347"
    ],
    "id": 2711934,
    "name:xx": "Tarpon Point"
  }
}
