{
  "geometry": {
    "type": "Point",
    "coordinates": [
      -91.1667,
      43.3667
    ]
  },
  "type": "Feature",
  "properties": {
    "hierarchy": [
      "tgn:2231333",
      "tgn:1000001",
      "tgn:7012149",
      "tgn:7007922",
      "tgn:7029392"
    ],
    "placetype": [
      "aat:300008680"
    ],
    "id": 2231333,
    "name:xx": "Chain of Lakes"
  }
}
