{
  "type": "FeatureCollection",
  "features": [
    {
      "geometry": {
        "type": "Point",
        "coordinates": [
          83.4167,
          49.6
        ]
      },
      "type": "Feature",
      "properties": {
        "hierarchy": [
          "tgn:1057920",
          "tgn:1000004",
          "tgn:7012943",
          "tgn:7014786",
          "tgn:7029392"
        ],
        "placetype": [
          "aat:300008347"
        ],
        "id": 1057920,
        "name:xx": "Ogn'ovka"
      }
    },
    {
      "geometry": {
        "type": "Point",
        "coordinates": [
          83.5,
          51.8667
        ]
      },
      "type": "Feature",
      "properties": {
        "hierarchy": [
          "tgn:1057921",
          "tgn:7013670",
          "tgn:1000004",
          "tgn:7018214",
          "tgn:7002435",
          "tgn:7029392"
        ],
        "placetype": [
          "aat:300008347"
        ],
        "id": 1057921,
        "name:xx": "Ogni"
      }
    },
    {
      "geometry": {
        "type": "Point",
        "coordinates": [
          132.55,
          52.75
        ]
      },
      "type": "Feature",
      "properties": {
        "hierarchy": [
          "tgn:1057922",
          "tgn:1003354",
          "tgn:1000004",
          "tgn:7018214",
          "tgn:7002435",
          "tgn:7029392"
        ],
        "placetype": [
          "aat:300008347"
        ],
        "id": 1057922,
        "name:xx": "Ogodzha"
      }
    },
    {
      "geometry": {
        "type": "Point",
        "coordinates": [
          28.8333,
          45.8833
        ]
      },
      "type": "Feature",
      "properties": {
        "hierarchy": [
          "tgn:1057923",
          "tgn:1000003",
          "tgn:1003396",
          "tgn:7006660",
          "tgn:7029392"
        ],
        "placetype": [
          "aat:300008347"
        ],
        "id": 1057923,
        "name:xx": "Horodne"
      }
    },
    {
      "geometry": {
        "type": "Point",
        "coordinates": [
          24.5167,
          56.8333
        ]
      },
      "type": "Feature",
      "properties": {
        "hierarchy": [
          "tgn:1057924",
          "tgn:7006503",
          "tgn:1000003",
          "tgn:7006541",
          "tgn:7029392"
        ],
        "placetype": [
          "aat:300008347",
          "aat:300008389",
          "aat:300387222"
        ],
        "id": 1057924,
        "name:xx": "Ogre"
      }
    },
    {
      "geometry": {
        "type": "Point",
        "coordinates": [
          142.7333,
          63.5
        ]
      },
      "type": "Feature",
      "properties": {
        "hierarchy": [
          "tgn:1057925",
          "tgn:1000004",
          "tgn:7011528",
          "tgn:7002435",
          "tgn:7029392"
        ],
        "placetype": [
          "aat:300008347"
        ],
        "id": 1057925,
        "name:xx": "Oymyakon"
      }
    },
    {
      "geometry": {
        "type": "Point",
        "coordinates": [
          104.45,
          52.5833
        ]
      },
      "type": "Feature",
      "properties": {
        "hierarchy": [
          "tgn:1057926",
          "tgn:1003373",
          "tgn:1000004",
          "tgn:7018214",
          "tgn:7002435",
          "tgn:7029392"
        ],
        "placetype": [
          "aat:300008347"
        ],
        "id": 1057926,
        "name:xx": "Ojok"
      }
    },
    {
      "geometry": {
        "type": "Point",
        "coordinates": [
          74.1,
          40.4
        ]
      },
      "type": "Feature",
      "properties": {
        "hierarchy": [
          "tgn:1057927",
          "tgn:1000004",
          "tgn:7012212",
          "tgn:7006655",
          "tgn:7029392"
        ],
        "placetype": [
          "aat:300008347"
        ],
        "id": 1057927,
        "name:xx": "Ojtal"
      }
    },
    {
      "geometry": {
        "type": "Point",
        "coordinates": [
          107.1,
          50.6
        ]
      },
      "type": "Feature",
      "properties": {
        "hierarchy": [
          "tgn:1057928",
          "tgn:1000004",
          "tgn:7011500",
          "tgn:7002435",
          "tgn:7029392"
        ],
        "placetype": [
          "aat:300008347"
        ],
        "id": 1057928,
        "name:xx": "Okino-Klyuchi"
      }
    },
    {
      "geometry": {
        "type": "Point",
        "coordinates": [
          33.65,
          58.6
        ]
      },
      "type": "Feature",
      "properties": {
        "hierarchy": [
          "tgn:1057929",
          "tgn:1000004",
          "tgn:4008031",
          "tgn:7018214",
          "tgn:7002435",
          "tgn:7029392"
        ],
        "placetype": [
          "aat:300008347"
        ],
        "id": 1057929,
        "name:xx": "Okladnevo"
      }
    }
  ]
}
