{
  "geometry": {
    "type": "Point",
    "coordinates": [
      -76.1167,
      43.9333
    ]
  },
  "type": "Feature",
  "properties": {
    "hierarchy": [
      "tgn:2635874",
      "tgn:1000001",
      "tgn:7012149",
      "tgn:1002518",
      "tgn:7007568",
      "tgn:7029392"
    ],
    "placetype": [
      "aat:300132316"
    ],
    "id": 2635874,
    "name:xx": "Sackets Harbor"
  }
}
