{
  "geometry": {
    "type": "Point",
    "coordinates": [
      -97.1333,
      41.85
    ]
  },
  "type": "Feature",
  "properties": {
    "hierarchy": [
      "tgn:2307049",
      "tgn:1000001",
      "tgn:7012149",
      "tgn:7007525",
      "tgn:7029392"
    ],
    "placetype": [
      "aat:300008706"
    ],
    "id": 2307049,
    "name:xx": "East Fork Maple Creek"
  }
}
