{
  "geometry": {
    "type": "Point",
    "coordinates": [
      -71.777,
      18.431
    ]
  },
  "type": "Feature",
  "properties": {
    "hierarchy": [
      "tgn:7593415",
      "tgn:7005401",
      "tgn:1000001",
      "tgn:7005388",
      "tgn:7029392"
    ],
    "placetype": [
      "aat:300008347"
    ],
    "id": 7593415,
    "name:xx": "El Limón"
  }
}
