{
  "geometry": {
    "type": "Point",
    "coordinates": [
      -89.3833,
      33.7333
    ]
  },
  "type": "Feature",
  "properties": {
    "hierarchy": [
      "tgn:2643505",
      "tgn:1000001",
      "tgn:2001092",
      "tgn:7012149",
      "tgn:7007522",
      "tgn:7029392"
    ],
    "placetype": [
      "aat:300008798"
    ],
    "id": 2643505,
    "name:xx": "Sandy Mountain"
  }
}
