{
  "geometry": {
    "type": "Point",
    "coordinates": [
      16.6167,
      49.0333
    ]
  },
  "type": "Feature",
  "properties": {
    "hierarchy": [
      "tgn:1027059",
      "tgn:1003523",
      "tgn:1000003",
      "tgn:1001780",
      "tgn:7029392"
    ],
    "placetype": [
      "aat:300008347"
    ],
    "id": 1027059,
    "name:xx": "Židlochovice"
  }
}
