{
  "geometry": {
    "type": "Point",
    "coordinates": [
      43.4167,
      -11.8333
    ]
  },
  "type": "Feature",
  "properties": {
    "hierarchy": [
      "tgn:1088587",
      "tgn:1008355",
      "tgn:7001242",
      "tgn:1000157",
      "tgn:7029392"
    ],
    "placetype": [
      "aat:300008347"
    ],
    "id": 1088587,
    "name:xx": "Dembéni"
  }
}
