{
  "type": "FeatureCollection",
  "features": [
    {
      "geometry": {
        "type": "Point",
        "coordinates": [
          -106.116667,
          23
        ]
      },
      "type": "Feature",
      "properties": {
        "hierarchy": [
          "tgn:1114720",
          "tgn:1000001",
          "tgn:7005595",
          "tgn:7005560",
          "tgn:7029392"
        ],
        "placetype": [
          "aat:300008679"
        ],
        "id": 1114720,
        "name:xx": "Camaronero, Laguna del"
      }
    },
    {
      "geometry": {
        "type": "Point",
        "coordinates": [
          -83.9167,
          15.3833
        ]
      },
      "type": "Feature",
      "properties": {
        "hierarchy": [
          "tgn:1114722",
          "tgn:1000617",
          "tgn:1000001",
          "tgn:7005554",
          "tgn:7029392"
        ],
        "placetype": [
          "aat:300008679"
        ],
        "id": 1114722,
        "name:xx": "Caratasca, Laguna de"
      }
    },
    {
      "geometry": {
        "type": "Point",
        "coordinates": [
          -93.8,
          18.283333
        ]
      },
      "type": "Feature",
      "properties": {
        "hierarchy": [
          "tgn:1114725",
          "tgn:1000001",
          "tgn:7005596",
          "tgn:7005560",
          "tgn:7029392"
        ],
        "placetype": [
          "aat:300008679"
        ],
        "id": 1114725,
        "name:xx": "Carmen, Laguna del"
      }
    },
    {
      "geometry": {
        "type": "Point",
        "coordinates": [
          -97.95,
          22.283333
        ]
      },
      "type": "Feature",
      "properties": {
        "hierarchy": [
          "tgn:1114728",
          "tgn:1000001",
          "tgn:7005599",
          "tgn:7005560",
          "tgn:7029392"
        ],
        "placetype": [
          "aat:300008679"
        ],
        "id": 1114728,
        "name:xx": "Chairel, Laguna de"
      }
    },
    {
      "geometry": {
        "type": "Point",
        "coordinates": [
          -99.116667,
          16.616667
        ]
      },
      "type": "Feature",
      "properties": {
        "hierarchy": [
          "tgn:1114729",
          "tgn:7005585",
          "tgn:1000001",
          "tgn:7005560",
          "tgn:7029392"
        ],
        "placetype": [
          "aat:300008679"
        ],
        "id": 1114729,
        "name:xx": "Chantengo, Laguna"
      }
    }
  ]
}
