{
  "geometry": {
    "type": "Point",
    "coordinates": [
      -117.4333,
      33.6667
    ]
  },
  "type": "Feature",
  "properties": {
    "hierarchy": [
      "tgn:2485929",
      "tgn:1000001",
      "tgn:7012149",
      "tgn:7007157",
      "tgn:7029392"
    ],
    "placetype": [
      "aat:300008761"
    ],
    "id": 2485929,
    "name:xx": "Leach Canyon"
  }
}
