{
  "geometry": {
    "type": "Point",
    "coordinates": [
      -99.8333,
      54.75
    ]
  },
  "type": "Feature",
  "properties": {
    "hierarchy": [
      "tgn:1118681",
      "tgn:7005685",
      "tgn:1000001",
      "tgn:7005734",
      "tgn:7029392"
    ],
    "placetype": [
      "aat:300008680"
    ],
    "id": 1118681,
    "name:xx": "Wekusko Lake"
  }
}
