{
  "geometry": {
    "type": "Point",
    "coordinates": [
      -81.0833,
      38.8667
    ]
  },
  "type": "Feature",
  "properties": {
    "hierarchy": [
      "tgn:2525165",
      "tgn:1000001",
      "tgn:2002258",
      "tgn:7012149",
      "tgn:7013961",
      "tgn:7029392"
    ],
    "placetype": [
      "aat:300008699"
    ],
    "id": 2525165,
    "name:xx": "Morris Run"
  }
}
