{
  "geometry": {
    "type": "Point",
    "coordinates": [
      -60.9667,
      14.0833
    ]
  },
  "type": "Feature",
  "properties": {
    "hierarchy": [
      "tgn:1113074",
      "tgn:7015075",
      "tgn:1000001",
      "tgn:7004772",
      "tgn:7029392"
    ],
    "placetype": [
      "aat:300132316"
    ],
    "id": 1113074,
    "name:xx": "Rodney Bay"
  }
}
