{
  "type": "FeatureCollection",
  "features": [
    {
      "geometry": {
        "type": "Point",
        "coordinates": [
          -96.7333,
          34.1333
        ]
      },
      "type": "Feature",
      "properties": {
        "hierarchy": [
          "tgn:2555940",
          "tgn:1000001",
          "tgn:7012149",
          "tgn:7007707",
          "tgn:7029392"
        ],
        "placetype": [
          "aat:300008706"
        ],
        "id": 2555940,
        "name:xx": "Oil Creek"
      }
    },
    {
      "geometry": {
        "type": "Point",
        "coordinates": [
          -95,
          34.8167
        ]
      },
      "type": "Feature",
      "properties": {
        "hierarchy": [
          "tgn:2555941",
          "tgn:1000001",
          "tgn:7012149",
          "tgn:2001662",
          "tgn:7007707",
          "tgn:7029392"
        ],
        "placetype": [
          "aat:300008706"
        ],
        "id": 2555941,
        "name:xx": "Oil Creek"
      }
    },
    {
      "geometry": {
        "type": "Point",
        "coordinates": [
          -76.95,
          39.7667
        ]
      },
      "type": "Feature",
      "properties": {
        "hierarchy": [
          "tgn:2555942",
          "tgn:1000001",
          "tgn:7012149",
          "tgn:1003047",
          "tgn:7007710",
          "tgn:7029392"
        ],
        "placetype": [
          "aat:300008706"
        ],
        "id": 2555942,
        "name:xx": "Oil Creek"
      }
    },
    {
      "geometry": {
        "type": "Point",
        "coordinates": [
          -76.4333,
          40.45
        ]
      },
      "type": "Feature",
      "properties": {
        "hierarchy": [
          "tgn:2555943",
          "tgn:1000001",
          "tgn:7012149",
          "tgn:1002581",
          "tgn:7007710",
          "tgn:7029392"
        ],
        "placetype": [
          "aat:300008706"
        ],
        "id": 2555943,
        "name:xx": "Oil Creek"
      }
    },
    {
      "geometry": {
        "type": "Point",
        "coordinates": [
          -78.6333,
          41.5833
        ]
      },
      "type": "Feature",
      "properties": {
        "hierarchy": [
          "tgn:2555944",
          "tgn:1000001",
          "tgn:7012149",
          "tgn:1002352",
          "tgn:7007710",
          "tgn:7029392"
        ],
        "placetype": [
          "aat:300008706"
        ],
        "id": 2555944,
        "name:xx": "Oil Creek"
      }
    },
    {
      "geometry": {
        "type": "Point",
        "coordinates": [
          -95.2,
          30.4833
        ]
      },
      "type": "Feature",
      "properties": {
        "hierarchy": [
          "tgn:2555945",
          "tgn:1000001",
          "tgn:7012149",
          "tgn:1002860",
          "tgn:7007826",
          "tgn:7029392"
        ],
        "placetype": [
          "aat:300008706"
        ],
        "id": 2555945,
        "name:xx": "Oil Creek"
      }
    },
    {
      "geometry": {
        "type": "Point",
        "coordinates": [
          -78.4,
          38.2333
        ]
      },
      "type": "Feature",
      "properties": {
        "hierarchy": [
          "tgn:2555946",
          "tgn:1000001",
          "tgn:7012149",
          "tgn:2002165",
          "tgn:7007919",
          "tgn:7029392"
        ],
        "placetype": [
          "aat:300008706"
        ],
        "id": 2555946,
        "name:xx": "Oil Creek"
      }
    },
    {
      "geometry": {
        "type": "Point",
        "coordinates": [
          -80.5,
          38.9
        ]
      },
      "type": "Feature",
      "properties": {
        "hierarchy": [
          "tgn:2555947",
          "tgn:1000001",
          "tgn:7012149",
          "tgn:7013961",
          "tgn:7029392"
        ],
        "placetype": [
          "aat:300008706"
        ],
        "id": 2555947,
        "name:xx": "Oil Creek"
      }
    },
    {
      "geometry": {
        "type": "Point",
        "coordinates": [
          -104.2167,
          44.1167
        ]
      },
      "type": "Feature",
      "properties": {
        "hierarchy": [
          "tgn:2555948",
          "tgn:1000001",
          "tgn:7012149",
          "tgn:2002387",
          "tgn:7007923",
          "tgn:7029392"
        ],
        "placetype": [
          "aat:300008706"
        ],
        "id": 2555948,
        "name:xx": "Oil Creek"
      }
    },
    {
      "geometry": {
        "type": "Point",
        "coordinates": [
          -105.2,
          38.4333
        ]
      },
      "type": "Feature",
      "properties": {
        "hierarchy": [
          "tgn:2555949",
          "tgn:1000001",
          "tgn:7012149",
          "tgn:2000213",
          "tgn:7007158",
          "tgn:7029392"
        ],
        "placetype": [
          "aat:300006075"
        ],
        "id": 2555949,
        "name:xx": "Oil Creek Ditch"
      }
    }
  ]
}
