{
  "geometry": {
    "type": "Point",
    "coordinates": [
      -82.3333,
      38.05
    ]
  },
  "type": "Feature",
  "properties": {
    "hierarchy": [
      "tgn:2183187",
      "tgn:1000001",
      "tgn:7012149",
      "tgn:2002299",
      "tgn:7013961",
      "tgn:7029392"
    ],
    "placetype": [
      "aat:300008699"
    ],
    "id": 2183187,
    "name:xx": "Bluelick Branch"
  }
}
