{
  "geometry": {
    "type": "Point",
    "coordinates": [
      31.904167,
      26.254167
    ]
  },
  "type": "Feature",
  "properties": {
    "hierarchy": [
      "tgn:7523165",
      "tgn:7001242",
      "tgn:7016833",
      "tgn:7000124",
      "tgn:7029392"
    ],
    "placetype": [
      "aat:300008347"
    ],
    "name:en": "Ash Shaykh Marzūq",
    "id": 7523165
  }
}
