{
  "geometry": {
    "type": "Point",
    "coordinates": [
      -98.65,
      20.116667
    ]
  },
  "type": "Feature",
  "properties": {
    "hierarchy": [
      "tgn:7386310",
      "tgn:7005587",
      "tgn:1000001",
      "tgn:7005560",
      "tgn:7029392"
    ],
    "placetype": [
      "aat:300008795"
    ],
    "id": 7386310,
    "name:xx": "Peña del Águila, Cerro"
  }
}
