{
  "geometry": {
    "type": "Point",
    "coordinates": [
      -94.5167,
      46.8167
    ]
  },
  "type": "Feature",
  "properties": {
    "hierarchy": [
      "tgn:2583346",
      "tgn:1000001",
      "tgn:2001009",
      "tgn:7012149",
      "tgn:7007521",
      "tgn:7029392"
    ],
    "placetype": [
      "aat:300008680"
    ],
    "id": 2583346,
    "name:xx": "Pine Mountain Lake"
  }
}
