{
  "geometry": {
    "type": "Point",
    "coordinates": [
      -91.25,
      35.8667
    ]
  },
  "type": "Feature",
  "properties": {
    "hierarchy": [
      "tgn:2271974",
      "tgn:1000001",
      "tgn:7016172",
      "tgn:7012149",
      "tgn:2000136",
      "tgn:7029392"
    ],
    "placetype": [
      "aat:300006075"
    ],
    "id": 2271974,
    "name:xx": "Curia Creek Ditch"
  }
}
