{
  "type": "FeatureCollection",
  "features": [
    {
      "geometry": {
        "type": "Point",
        "coordinates": [
          -105.583333,
          27.05
        ]
      },
      "type": "Feature",
      "properties": {
        "hierarchy": [
          "tgn:7352040",
          "tgn:7005581",
          "tgn:1000001",
          "tgn:7005560",
          "tgn:7029392"
        ],
        "placetype": [
          "aat:300008347"
        ],
        "id": 7352040,
        "name:xx": "Arroyo Seco"
      }
    },
    {
      "geometry": {
        "type": "Point",
        "coordinates": [
          -106.266667,
          26.633333
        ]
      },
      "type": "Feature",
      "properties": {
        "hierarchy": [
          "tgn:7352041",
          "tgn:7005581",
          "tgn:1000001",
          "tgn:7005560",
          "tgn:7029392"
        ],
        "placetype": [
          "aat:300008347"
        ],
        "id": 7352041,
        "name:xx": "Arroyo Seco"
      }
    },
    {
      "geometry": {
        "type": "Point",
        "coordinates": [
          -97.283333,
          25.916667
        ]
      },
      "type": "Feature",
      "properties": {
        "hierarchy": [
          "tgn:7352042",
          "tgn:1000001",
          "tgn:7005597",
          "tgn:7005560",
          "tgn:7029392"
        ],
        "placetype": [
          "aat:300008347"
        ],
        "id": 7352042,
        "name:xx": "Arroyo Seco"
      }
    },
    {
      "geometry": {
        "type": "Point",
        "coordinates": [
          -100.766667,
          23.383333
        ]
      },
      "type": "Feature",
      "properties": {
        "hierarchy": [
          "tgn:7352043",
          "tgn:1000001",
          "tgn:7005594",
          "tgn:7005560",
          "tgn:7029392"
        ],
        "placetype": [
          "aat:300008347"
        ],
        "id": 7352043,
        "name:xx": "Arroyo Seco"
      }
    },
    {
      "geometry": {
        "type": "Point",
        "coordinates": [
          -99.7,
          21.55
        ]
      },
      "type": "Feature",
      "properties": {
        "hierarchy": [
          "tgn:7352044",
          "tgn:1000001",
          "tgn:7005593",
          "tgn:7005560",
          "tgn:7029392"
        ],
        "placetype": [
          "aat:300008347"
        ],
        "id": 7352044,
        "name:xx": "Arroyo Seco"
      }
    },
    {
      "geometry": {
        "type": "Point",
        "coordinates": [
          -98.95,
          21.3
        ]
      },
      "type": "Feature",
      "properties": {
        "hierarchy": [
          "tgn:7352045",
          "tgn:7005587",
          "tgn:1000001",
          "tgn:7005560",
          "tgn:7029392"
        ],
        "placetype": [
          "aat:300008347"
        ],
        "id": 7352045,
        "name:xx": "Arroyo Seco"
      }
    },
    {
      "geometry": {
        "type": "Point",
        "coordinates": [
          -101.566667,
          17.816667
        ]
      },
      "type": "Feature",
      "properties": {
        "hierarchy": [
          "tgn:7352046",
          "tgn:7005585",
          "tgn:1000001",
          "tgn:7005560",
          "tgn:7029392"
        ],
        "placetype": [
          "aat:300008347"
        ],
        "id": 7352046,
        "name:xx": "Arroyo Seco"
      }
    },
    {
      "geometry": {
        "type": "Point",
        "coordinates": [
          -116.6,
          32.383333
        ]
      },
      "type": "Feature",
      "properties": {
        "hierarchy": [
          "tgn:7352047",
          "tgn:1001835",
          "tgn:1000001",
          "tgn:7005560",
          "tgn:7029392"
        ],
        "placetype": [
          "aat:300008777"
        ],
        "id": 7352047,
        "name:xx": "Arroyo Seco"
      }
    },
    {
      "geometry": {
        "type": "Point",
        "coordinates": [
          -100.9,
          22.066667
        ]
      },
      "type": "Feature",
      "properties": {
        "hierarchy": [
          "tgn:7352048",
          "tgn:1000001",
          "tgn:7005594",
          "tgn:7005560",
          "tgn:7029392"
        ],
        "placetype": [
          "aat:300007783"
        ],
        "id": 7352048,
        "name:xx": "Arroyos"
      }
    },
    {
      "geometry": {
        "type": "Point",
        "coordinates": [
          -100.9,
          22.05
        ]
      },
      "type": "Feature",
      "properties": {
        "hierarchy": [
          "tgn:7352049",
          "tgn:1000001",
          "tgn:7005594",
          "tgn:7005560",
          "tgn:7029392"
        ],
        "placetype": [
          "aat:300008347"
        ],
        "id": 7352049,
        "name:xx": "Arroyos"
      }
    }
  ]
}
