{
  "geometry": {
    "type": "Point",
    "coordinates": [
      -81.95,
      36.4667
    ]
  },
  "type": "Feature",
  "properties": {
    "hierarchy": [
      "tgn:2450080",
      "tgn:1000001",
      "tgn:7012149",
      "tgn:2001846",
      "tgn:7007825",
      "tgn:7029392"
    ],
    "placetype": [
      "aat:300008699"
    ],
    "id": 2450080,
    "name:xx": "Lindy Camp Branch"
  }
}
