{
  "geometry": {
    "type": "Point",
    "coordinates": [
      -110.2833,
      34.5667
    ]
  },
  "type": "Feature",
  "properties": {
    "hierarchy": [
      "tgn:2412087",
      "tgn:1000001",
      "tgn:7006451",
      "tgn:7012149",
      "tgn:2000099",
      "tgn:7029392"
    ],
    "placetype": [
      "aat:300006191"
    ],
    "id": 2412087,
    "name:xx": "Indian Rock Tank"
  }
}
