{
  "geometry": {
    "type": "Point",
    "coordinates": [
      -120.65,
      43.1667
    ]
  },
  "type": "Feature",
  "properties": {
    "hierarchy": [
      "tgn:2778446",
      "tgn:1000001",
      "tgn:7012149",
      "tgn:2001715",
      "tgn:7007708",
      "tgn:7029392"
    ],
    "placetype": [
      "aat:300006191"
    ],
    "id": 2778446,
    "name:xx": "Withers Reservoir"
  }
}
