{
  "geometry": {
    "type": "Point",
    "coordinates": [
      17.2833,
      12.7167
    ]
  },
  "type": "Feature",
  "properties": {
    "hierarchy": [
      "tgn:1116294",
      "tgn:1000966",
      "tgn:7001242",
      "tgn:1000156",
      "tgn:7029392"
    ],
    "placetype": [
      "aat:300008680"
    ],
    "id": 1116294,
    "name:xx": "Fittri, Lac"
  }
}
