{
  "type": "FeatureCollection",
  "features": [
    {
      "geometry": {
        "type": "Point",
        "coordinates": [
          -81.7167,
          33.8667
        ]
      },
      "type": "Feature",
      "properties": {
        "hierarchy": [
          "tgn:2410950",
          "tgn:1000001",
          "tgn:7012149",
          "tgn:2001765",
          "tgn:7007712",
          "tgn:7029392"
        ],
        "placetype": [
          "aat:300008706"
        ],
        "id": 2410950,
        "name:xx": "Indian Creek"
      }
    },
    {
      "geometry": {
        "type": "Point",
        "coordinates": [
          -80.0167,
          34.3
        ]
      },
      "type": "Feature",
      "properties": {
        "hierarchy": [
          "tgn:2410951",
          "tgn:1000001",
          "tgn:2001740",
          "tgn:7012149",
          "tgn:7007712",
          "tgn:7029392"
        ],
        "placetype": [
          "aat:300008706"
        ],
        "id": 2410951,
        "name:xx": "Indian Creek"
      }
    },
    {
      "geometry": {
        "type": "Point",
        "coordinates": [
          -81.8,
          34.45
        ]
      },
      "type": "Feature",
      "properties": {
        "hierarchy": [
          "tgn:2410952",
          "tgn:1000001",
          "tgn:7012149",
          "tgn:7007712",
          "tgn:7029392"
        ],
        "placetype": [
          "aat:300008706"
        ],
        "id": 2410952,
        "name:xx": "Indian Creek"
      }
    },
    {
      "geometry": {
        "type": "Point",
        "coordinates": [
          -80.15,
          34.7
        ]
      },
      "type": "Feature",
      "properties": {
        "hierarchy": [
          "tgn:2410953",
          "tgn:1000001",
          "tgn:2001737",
          "tgn:7012149",
          "tgn:7007712",
          "tgn:7029392"
        ],
        "placetype": [
          "aat:300008706"
        ],
        "id": 2410953,
        "name:xx": "Indian Creek"
      }
    },
    {
      "geometry": {
        "type": "Point",
        "coordinates": [
          -102.6333,
          44.65
        ]
      },
      "type": "Feature",
      "properties": {
        "hierarchy": [
          "tgn:2410954",
          "tgn:1000001",
          "tgn:2001816",
          "tgn:7012149",
          "tgn:7007713",
          "tgn:7029392"
        ],
        "placetype": [
          "aat:300008706"
        ],
        "id": 2410954,
        "name:xx": "Indian Creek"
      }
    },
    {
      "geometry": {
        "type": "Point",
        "coordinates": [
          -103.8,
          44.9
        ]
      },
      "type": "Feature",
      "properties": {
        "hierarchy": [
          "tgn:2410955",
          "tgn:1000001",
          "tgn:2001779",
          "tgn:7012149",
          "tgn:7007713",
          "tgn:7029392"
        ],
        "placetype": [
          "aat:300008706"
        ],
        "id": 2410955,
        "name:xx": "Indian Creek"
      }
    },
    {
      "geometry": {
        "type": "Point",
        "coordinates": [
          -102.3667,
          45.35
        ]
      },
      "type": "Feature",
      "properties": {
        "hierarchy": [
          "tgn:2410956",
          "tgn:1000001",
          "tgn:7012149",
          "tgn:2001822",
          "tgn:7007713",
          "tgn:7029392"
        ],
        "placetype": [
          "aat:300008706"
        ],
        "id": 2410956,
        "name:xx": "Indian Creek"
      }
    },
    {
      "geometry": {
        "type": "Point",
        "coordinates": [
          -85.75,
          36.4167
        ]
      },
      "type": "Feature",
      "properties": {
        "hierarchy": [
          "tgn:2410957",
          "tgn:1000001",
          "tgn:7012149",
          "tgn:2001880",
          "tgn:7007825",
          "tgn:7029392"
        ],
        "placetype": [
          "aat:300008706"
        ],
        "id": 2410957,
        "name:xx": "Indian Creek"
      }
    },
    {
      "geometry": {
        "type": "Point",
        "coordinates": [
          -86.3,
          35.0833
        ]
      },
      "type": "Feature",
      "properties": {
        "hierarchy": [
          "tgn:2410958",
          "tgn:1000001",
          "tgn:7012149",
          "tgn:2001862",
          "tgn:7007825",
          "tgn:7029392"
        ],
        "placetype": [
          "aat:300008706"
        ],
        "id": 2410958,
        "name:xx": "Indian Creek"
      }
    },
    {
      "geometry": {
        "type": "Point",
        "coordinates": [
          -89.85,
          35.55
        ]
      },
      "type": "Feature",
      "properties": {
        "hierarchy": [
          "tgn:2410959",
          "tgn:1000001",
          "tgn:7012149",
          "tgn:2001920",
          "tgn:7007825",
          "tgn:7029392"
        ],
        "placetype": [
          "aat:300008706"
        ],
        "id": 2410959,
        "name:xx": "Indian Creek"
      }
    }
  ]
}
