{
  "geometry": {
    "type": "Point",
    "coordinates": [
      -111.9667,
      47.2833
    ]
  },
  "type": "Feature",
  "properties": {
    "hierarchy": [
      "tgn:2702421",
      "tgn:1000001",
      "tgn:2001266",
      "tgn:7012149",
      "tgn:7007524",
      "tgn:7029392"
    ],
    "placetype": [
      "aat:300008761"
    ],
    "id": 2702421,
    "name:xx": "Sullivan Valley"
  }
}
