{
  "geometry": {
    "type": "Point",
    "coordinates": [
      -142.2333,
      60.05
    ]
  },
  "type": "Feature",
  "properties": {
    "hierarchy": [
      "tgn:2342560",
      "tgn:7006450",
      "tgn:1000001",
      "tgn:7012149",
      "tgn:2000086",
      "tgn:7029392"
    ],
    "placetype": [
      "aat:300008706"
    ],
    "id": 2342560,
    "name:xx": "Fulton Creek"
  }
}
