{
  "geometry": {
    "type": "Point",
    "coordinates": [
      -106.15,
      34.9833
    ]
  },
  "type": "Feature",
  "properties": {
    "hierarchy": [
      "tgn:2301425",
      "tgn:1000001",
      "tgn:7012149",
      "tgn:2001458",
      "tgn:7007566",
      "tgn:7029392"
    ],
    "placetype": [
      "aat:300008347"
    ],
    "id": 2301425,
    "name:xx": "Dunn Place"
  }
}
