{
  "geometry": {
    "type": "Point",
    "coordinates": [
      -74.3167,
      42.05
    ]
  },
  "type": "Feature",
  "properties": {
    "hierarchy": [
      "tgn:2073303",
      "tgn:1000001",
      "tgn:7012149",
      "tgn:1002961",
      "tgn:7007568",
      "tgn:7029392"
    ],
    "placetype": [
      "aat:300008347"
    ],
    "id": 2073303,
    "name:xx": "Woodland"
  }
}
