{
  "geometry": {
    "type": "Point",
    "coordinates": [
      -110.5333,
      42.7167
    ]
  },
  "type": "Feature",
  "properties": {
    "hierarchy": [
      "tgn:2135830",
      "tgn:1000001",
      "tgn:7012149",
      "tgn:7007923",
      "tgn:7029392"
    ],
    "placetype": [
      "aat:300008706"
    ],
    "id": 2135830,
    "name:xx": "Apperson Creek"
  }
}
