{
  "type": "FeatureCollection",
  "features": [
    {
      "geometry": {
        "type": "Point",
        "coordinates": [
          12.3,
          51.1
        ]
      },
      "type": "Feature",
      "properties": {
        "hierarchy": [
          "tgn:7140830",
          "tgn:1000003",
          "tgn:7003685",
          "tgn:7000084",
          "tgn:7029392"
        ],
        "placetype": [
          "aat:300008347"
        ],
        "id": 7140830,
        "name:xx": "Maltitz"
      }
    },
    {
      "geometry": {
        "type": "Point",
        "coordinates": [
          12.416667,
          50.916667
        ]
      },
      "type": "Feature",
      "properties": {
        "hierarchy": [
          "tgn:7140831",
          "tgn:1000003",
          "tgn:7003689",
          "tgn:7000084",
          "tgn:7029392"
        ],
        "placetype": [
          "aat:300008347"
        ],
        "id": 7140831,
        "name:xx": "Maltis"
      }
    },
    {
      "geometry": {
        "type": "Point",
        "coordinates": [
          12.933333,
          52
        ]
      },
      "type": "Feature",
      "properties": {
        "hierarchy": [
          "tgn:7140832",
          "tgn:7000096",
          "tgn:1000003",
          "tgn:7000084",
          "tgn:7029392"
        ],
        "placetype": [
          "aat:300008347"
        ],
        "id": 7140832,
        "name:xx": "Malterhausen"
      }
    },
    {
      "geometry": {
        "type": "Point",
        "coordinates": [
          7.8,
          48.166667
        ]
      },
      "type": "Feature",
      "properties": {
        "hierarchy": [
          "tgn:7140833",
          "tgn:7003692",
          "tgn:1000003",
          "tgn:7000084",
          "tgn:7029392"
        ],
        "placetype": [
          "aat:300008347"
        ],
        "id": 7140833,
        "name:xx": "Malterdingen"
      }
    },
    {
      "geometry": {
        "type": "Point",
        "coordinates": [
          13.666667,
          50.916667
        ]
      },
      "type": "Feature",
      "properties": {
        "hierarchy": [
          "tgn:7140834",
          "tgn:1000003",
          "tgn:7003685",
          "tgn:7000084",
          "tgn:7029392"
        ],
        "placetype": [
          "aat:300006191"
        ],
        "id": 7140834,
        "name:xx": "Talsperre Malter"
      }
    },
    {
      "geometry": {
        "type": "Point",
        "coordinates": [
          13.666667,
          50.916667
        ]
      },
      "type": "Feature",
      "properties": {
        "hierarchy": [
          "tgn:7140835",
          "tgn:1000003",
          "tgn:7003685",
          "tgn:7000084",
          "tgn:7029392"
        ],
        "placetype": [
          "aat:300008347"
        ],
        "id": 7140835,
        "name:xx": "Malter"
      }
    },
    {
      "geometry": {
        "type": "Point",
        "coordinates": [
          6.716667,
          51.6
        ]
      },
      "type": "Feature",
      "properties": {
        "hierarchy": [
          "tgn:7140836",
          "tgn:1000003",
          "tgn:7003677",
          "tgn:7000084",
          "tgn:7029392"
        ],
        "placetype": [
          "aat:300000206"
        ],
        "id": 7140836,
        "name:xx": "Malta"
      }
    },
    {
      "geometry": {
        "type": "Point",
        "coordinates": [
          9.133333,
          51.083333
        ]
      },
      "type": "Feature",
      "properties": {
        "hierarchy": [
          "tgn:7140837",
          "tgn:1000003",
          "tgn:7003678",
          "tgn:7000084",
          "tgn:7029392"
        ],
        "placetype": [
          "aat:300008777"
        ],
        "id": 7140837,
        "name:xx": "Malstein"
      }
    },
    {
      "geometry": {
        "type": "Point",
        "coordinates": [
          9.266667,
          53.433333
        ]
      },
      "type": "Feature",
      "properties": {
        "hierarchy": [
          "tgn:7140839",
          "tgn:1000003",
          "tgn:7003676",
          "tgn:7000084",
          "tgn:7029392"
        ],
        "placetype": [
          "aat:300008347"
        ],
        "id": 7140839,
        "name:xx": "Malstedt"
      }
    }
  ]
}
