{
  "geometry": {
    "type": "Point",
    "coordinates": [
      -76.9667,
      38.4333
    ]
  },
  "type": "Feature",
  "properties": {
    "hierarchy": [
      "tgn:2646748",
      "tgn:7016100",
      "tgn:1000001",
      "tgn:7012149",
      "tgn:7007516",
      "tgn:7029392"
    ],
    "placetype": [
      "aat:300008699"
    ],
    "id": 2646748,
    "name:xx": "Scar Branch"
  }
}
