{
  "geometry": {
    "type": "Point",
    "coordinates": [
      -107.5833,
      38.2167
    ]
  },
  "type": "Feature",
  "properties": {
    "hierarchy": [
      "tgn:2151357",
      "tgn:1000001",
      "tgn:7012149",
      "tgn:2000237",
      "tgn:7007158",
      "tgn:7029392"
    ],
    "placetype": [
      "aat:300008680"
    ],
    "id": 2151357,
    "name:xx": "Bates Lakes"
  }
}
