{
  "geometry": {
    "type": "Point",
    "coordinates": [
      -148.65,
      60.8333
    ]
  },
  "type": "Feature",
  "properties": {
    "hierarchy": [
      "tgn:2680300",
      "tgn:7006450",
      "tgn:1000001",
      "tgn:7012149",
      "tgn:7029392"
    ],
    "placetype": [
      "aat:300008707"
    ],
    "id": 2680300,
    "name:xx": "South Fork Upper Carmen River"
  }
}
