{
  "geometry": {
    "type": "Point",
    "coordinates": [
      30.735803,
      28.61583
    ]
  },
  "type": "Feature",
  "properties": {
    "hierarchy": [
      "tgn:7538295",
      "tgn:7001242",
      "tgn:7016833",
      "tgn:1001088",
      "tgn:7029392"
    ],
    "placetype": [
      "aat:300008347"
    ],
    "name:en": "Shimm al Başal al Qiblīyah",
    "id": 7538295
  }
}
