{
  "geometry": {
    "type": "Point",
    "coordinates": [
      -86.85,
      34.9667
    ]
  },
  "type": "Feature",
  "properties": {
    "hierarchy": [
      "tgn:2488199",
      "tgn:1000001",
      "tgn:7012149",
      "tgn:7029392"
    ],
    "placetype": [
      "aat:300008761"
    ],
    "id": 2488199,
    "name:xx": "Magnusson Hollow"
  }
}
