{
  "geometry": {
    "type": "Point",
    "coordinates": [
      31.5833,
      49.4833
    ]
  },
  "type": "Feature",
  "properties": {
    "hierarchy": [
      "tgn:1137260",
      "tgn:6001332",
      "tgn:1000003",
      "tgn:7006660",
      "tgn:7029392"
    ],
    "placetype": [
      "aat:300008347",
      "aat:300008375"
    ],
    "id": 1137260,
    "name:xx": "Bilozir'ya"
  }
}
