{
  "geometry": {
    "type": "Point",
    "coordinates": [
      -112.0333,
      46.0167
    ]
  },
  "type": "Feature",
  "properties": {
    "hierarchy": [
      "tgn:2280092",
      "tgn:1000001",
      "tgn:7012149",
      "tgn:2001281",
      "tgn:7007524",
      "tgn:7029392"
    ],
    "placetype": [
      "aat:300008706"
    ],
    "id": 2280092,
    "name:xx": "Dearborn Creek"
  }
}
