{
  "geometry": {
    "type": "Point",
    "coordinates": [
      -120.4833,
      41.4833
    ]
  },
  "type": "Feature",
  "properties": {
    "hierarchy": [
      "tgn:2292841",
      "tgn:1000001",
      "tgn:7012149",
      "tgn:7007157",
      "tgn:2000186",
      "tgn:7029392"
    ],
    "placetype": [
      "aat:300006191"
    ],
    "id": 2292841,
    "name:xx": "Dorris Reservoir"
  }
}
