{
  "geometry": {
    "type": "Point",
    "coordinates": [
      -77.0833,
      42.8167
    ]
  },
  "type": "Feature",
  "properties": {
    "hierarchy": [
      "tgn:2072525",
      "tgn:1000001",
      "tgn:7012149",
      "tgn:1002747",
      "tgn:7007568",
      "tgn:7029392"
    ],
    "placetype": [
      "aat:300008347"
    ],
    "id": 2072525,
    "name:xx": "Stanley"
  }
}
