{
  "geometry": {
    "type": "Point",
    "coordinates": [
      -121.2667,
      45.9333
    ]
  },
  "type": "Feature",
  "properties": {
    "hierarchy": [
      "tgn:2420024",
      "tgn:1000001",
      "tgn:7012149",
      "tgn:1002554",
      "tgn:7007920",
      "tgn:7029392"
    ],
    "placetype": [
      "aat:300008699"
    ],
    "id": 2420024,
    "name:xx": "Jebe Swale"
  }
}
