{
  "geometry": {
    "type": "Point",
    "coordinates": [
      98.05,
      16.5833
    ]
  },
  "type": "Feature",
  "properties": {
    "hierarchy": [
      "tgn:1066104",
      "tgn:1000004",
      "tgn:7002188",
      "tgn:1000108",
      "tgn:7029392"
    ],
    "placetype": [
      "aat:300008347"
    ],
    "id": 1066104,
    "name:xx": "Kyondo"
  }
}
