{
  "type": "FeatureCollection",
  "features": [
    {
      "geometry": {
        "type": "Point",
        "coordinates": [
          -90.9833,
          34.8667
        ]
      },
      "type": "Feature",
      "properties": {
        "hierarchy": [
          "tgn:2539640",
          "tgn:1000001",
          "tgn:7016172",
          "tgn:7012149",
          "tgn:2000143",
          "tgn:7029392"
        ],
        "placetype": [
          "aat:300008347"
        ],
        "id": 2539640,
        "name:xx": "New Salem"
      }
    },
    {
      "geometry": {
        "type": "Point",
        "coordinates": [
          -89.9667,
          35.75
        ]
      },
      "type": "Feature",
      "properties": {
        "hierarchy": [
          "tgn:2539641",
          "tgn:1000001",
          "tgn:7016172",
          "tgn:7012149",
          "tgn:2000151",
          "tgn:7029392"
        ],
        "placetype": [
          "aat:300008347"
        ],
        "id": 2539641,
        "name:xx": "New Salem"
      }
    },
    {
      "geometry": {
        "type": "Point",
        "coordinates": [
          -91.2833,
          35.2833
        ]
      },
      "type": "Feature",
      "properties": {
        "hierarchy": [
          "tgn:2539642",
          "tgn:1000001",
          "tgn:7016172",
          "tgn:7012149",
          "tgn:2000178",
          "tgn:7029392"
        ],
        "placetype": [
          "aat:300008347"
        ],
        "id": 2539642,
        "name:xx": "New Salem"
      }
    },
    {
      "geometry": {
        "type": "Point",
        "coordinates": [
          -85.9,
          38.6167
        ]
      },
      "type": "Feature",
      "properties": {
        "hierarchy": [
          "tgn:2539643",
          "tgn:1000001",
          "tgn:7012149",
          "tgn:1002992",
          "tgn:7007252",
          "tgn:7029392"
        ],
        "placetype": [
          "aat:300008347"
        ],
        "id": 2539643,
        "name:xx": "New Salem"
      }
    },
    {
      "geometry": {
        "type": "Point",
        "coordinates": [
          -83.35,
          39.3167
        ]
      },
      "type": "Feature",
      "properties": {
        "hierarchy": [
          "tgn:2539644",
          "tgn:1000001",
          "tgn:7012149",
          "tgn:1002835",
          "tgn:7007706",
          "tgn:7029392"
        ],
        "placetype": [
          "aat:300008347"
        ],
        "id": 2539644,
        "name:xx": "New Salem"
      }
    },
    {
      "geometry": {
        "type": "Point",
        "coordinates": [
          -82.7167,
          34.55
        ]
      },
      "type": "Feature",
      "properties": {
        "hierarchy": [
          "tgn:2539646",
          "tgn:2001728",
          "tgn:1000001",
          "tgn:7012149",
          "tgn:7007712",
          "tgn:7029392"
        ],
        "placetype": [
          "aat:300008347"
        ],
        "id": 2539646,
        "name:xx": "New Salem"
      }
    },
    {
      "geometry": {
        "type": "Point",
        "coordinates": [
          -85.8667,
          36.2
        ]
      },
      "type": "Feature",
      "properties": {
        "hierarchy": [
          "tgn:2539647",
          "tgn:1000001",
          "tgn:7012149",
          "tgn:2001916",
          "tgn:7007825",
          "tgn:7029392"
        ],
        "placetype": [
          "aat:300008746"
        ],
        "id": 2539647,
        "name:xx": "New Salem Cave"
      }
    },
    {
      "geometry": {
        "type": "Point",
        "coordinates": [
          -88.1833,
          37.3
        ]
      },
      "type": "Feature",
      "properties": {
        "hierarchy": [
          "tgn:2539648",
          "tgn:1000001",
          "tgn:7012149",
          "tgn:2000784",
          "tgn:7007255",
          "tgn:7029392"
        ],
        "placetype": [
          "aat:300008706"
        ],
        "id": 2539648,
        "name:xx": "New Salem Creek"
      }
    },
    {
      "geometry": {
        "type": "Point",
        "coordinates": [
          -72.35,
          42.5
        ]
      },
      "type": "Feature",
      "properties": {
        "hierarchy": [
          "tgn:2539649",
          "tgn:1000001",
          "tgn:7013942",
          "tgn:7012149",
          "tgn:7007517",
          "tgn:7029392"
        ],
        "placetype": [
          "aat:300008863"
        ],
        "id": 2539649,
        "name:xx": "New Salem State Forest"
      }
    }
  ]
}
