{
  "geometry": {
    "type": "Point",
    "coordinates": [
      171.85,
      -42.15
    ]
  },
  "type": "Feature",
  "properties": {
    "hierarchy": [
      "tgn:7514984",
      "tgn:1009227",
      "tgn:1000226",
      "tgn:1000006",
      "tgn:7016850",
      "tgn:7029392"
    ],
    "placetype": [
      "aat:300008699"
    ],
    "name:en": "Carton Creek",
    "id": 7514984
  }
}
