{
  "geometry": {
    "type": "Point",
    "coordinates": [
      17.1667,
      47.9167
    ]
  },
  "type": "Feature",
  "properties": {
    "hierarchy": [
      "tgn:1042351",
      "tgn:7006350",
      "tgn:1000003",
      "tgn:7006278",
      "tgn:7029392"
    ],
    "placetype": [
      "aat:300008347"
    ],
    "id": 1042351,
    "name:xx": "Hegyeshalom"
  }
}
