{
  "geometry": {
    "type": "Point",
    "coordinates": [
      -113.6667,
      38.1333
    ]
  },
  "type": "Feature",
  "properties": {
    "hierarchy": [
      "tgn:1111733",
      "tgn:1000001",
      "tgn:7012149",
      "tgn:7007827",
      "tgn:7029392"
    ],
    "placetype": [
      "aat:300008761"
    ],
    "id": 1111733,
    "name:xx": "Pine Valley"
  }
}
