{
  "geometry": {
    "type": "Point",
    "coordinates": [
      -119.75,
      34.8167
    ]
  },
  "type": "Feature",
  "properties": {
    "hierarchy": [
      "tgn:2521462",
      "tgn:1000001",
      "tgn:7012149",
      "tgn:7007157",
      "tgn:1002867",
      "tgn:7029392"
    ],
    "placetype": [
      "aat:300008697"
    ],
    "id": 2521462,
    "name:xx": "Montgomery Number Three Spring"
  }
}
