{
  "geometry": {
    "type": "Point",
    "coordinates": [
      -104.8167,
      41.9667
    ]
  },
  "type": "Feature",
  "properties": {
    "hierarchy": [
      "tgn:2600790",
      "tgn:1000001",
      "tgn:7012149",
      "tgn:2002380",
      "tgn:7007923",
      "tgn:7029392"
    ],
    "placetype": [
      "aat:300006191"
    ],
    "id": 2600790,
    "name:xx": "Pump Reservoir"
  }
}
