{
  "geometry": {
    "type": "Point",
    "coordinates": [
      -1.6833,
      54.3833
    ]
  },
  "type": "Feature",
  "properties": {
    "hierarchy": [
      "tgn:1028902",
      "tgn:7002445",
      "tgn:1000003",
      "tgn:7008166",
      "tgn:7008591",
      "tgn:7029392"
    ],
    "placetype": [
      "aat:300008347"
    ],
    "id": 1028902,
    "name:xx": "Colburn"
  }
}
