{
  "type": "FeatureCollection",
  "features": [
    {
      "geometry": {
        "type": "Point",
        "coordinates": [
          -76.9,
          37.1167
        ]
      },
      "type": "Feature",
      "properties": {
        "hierarchy": [
          "tgn:1002931",
          "tgn:1000001",
          "tgn:7012149",
          "tgn:7007919",
          "tgn:7029392"
        ],
        "placetype": [
          "aat:300387145",
          "aat:300000771"
        ],
        "id": 1002931,
        "name:xx": "Surry"
      }
    },
    {
      "geometry": {
        "type": "Point",
        "coordinates": [
          -76.1167,
          41.8667
        ]
      },
      "type": "Feature",
      "properties": {
        "hierarchy": [
          "tgn:1002932",
          "tgn:1000001",
          "tgn:7012149",
          "tgn:7007710",
          "tgn:7029392"
        ],
        "placetype": [
          "aat:300387145",
          "aat:300000771"
        ],
        "id": 1002932,
        "name:xx": "Susquehanna"
      }
    },
    {
      "geometry": {
        "type": "Point",
        "coordinates": [
          -75.4167,
          38.7
        ]
      },
      "type": "Feature",
      "properties": {
        "hierarchy": [
          "tgn:1002933",
          "tgn:1000001",
          "tgn:7012149",
          "tgn:7007239",
          "tgn:7029392"
        ],
        "placetype": [
          "aat:300387145",
          "aat:300000771"
        ],
        "id": 1002933,
        "name:xx": "Sussex"
      }
    },
    {
      "geometry": {
        "type": "Point",
        "coordinates": [
          -74.6667,
          41.1833
        ]
      },
      "type": "Feature",
      "properties": {
        "hierarchy": [
          "tgn:1002934",
          "tgn:1000001",
          "tgn:7012149",
          "tgn:7007565",
          "tgn:7029392"
        ],
        "placetype": [
          "aat:300387145",
          "aat:300000771"
        ],
        "id": 1002934,
        "name:xx": "Sussex"
      }
    },
    {
      "geometry": {
        "type": "Point",
        "coordinates": [
          -77.25,
          36.9333
        ]
      },
      "type": "Feature",
      "properties": {
        "hierarchy": [
          "tgn:1002935",
          "tgn:1000001",
          "tgn:7012149",
          "tgn:7007919",
          "tgn:7029392"
        ],
        "placetype": [
          "aat:300387145",
          "aat:300000771"
        ],
        "id": 1002935,
        "name:xx": "Sussex"
      }
    },
    {
      "geometry": {
        "type": "Point",
        "coordinates": [
          -121.7,
          39.0167
        ]
      },
      "type": "Feature",
      "properties": {
        "hierarchy": [
          "tgn:1002937",
          "tgn:1000001",
          "tgn:7012149",
          "tgn:7007157",
          "tgn:7029392"
        ],
        "placetype": [
          "aat:300387145",
          "aat:300000771"
        ],
        "id": 1002937,
        "name:xx": "Sutter"
      }
    },
    {
      "geometry": {
        "type": "Point",
        "coordinates": [
          -85.0167,
          38.8333
        ]
      },
      "type": "Feature",
      "properties": {
        "hierarchy": [
          "tgn:1002938",
          "tgn:1000001",
          "tgn:7012149",
          "tgn:7007252",
          "tgn:7029392"
        ],
        "placetype": [
          "aat:300387145",
          "aat:300000771"
        ],
        "id": 1002938,
        "name:xx": "Switzerland"
      }
    },
    {
      "geometry": {
        "type": "Point",
        "coordinates": [
          -97.3,
          32.7667
        ]
      },
      "type": "Feature",
      "properties": {
        "hierarchy": [
          "tgn:1002939",
          "tgn:1000001",
          "tgn:7012149",
          "tgn:7007826",
          "tgn:7029392"
        ],
        "placetype": [
          "aat:300387145",
          "aat:300000771"
        ],
        "id": 1002939,
        "name:xx": "Tarrant"
      }
    }
  ]
}
