{
  "geometry": {
    "type": "Point",
    "coordinates": [
      14.4167,
      -2.45
    ]
  },
  "type": "Feature",
  "properties": {
    "hierarchy": [
      "tgn:1088645",
      "tgn:7001242",
      "tgn:1001022",
      "tgn:1000158",
      "tgn:7029392"
    ],
    "placetype": [
      "aat:300008347"
    ],
    "id": 1088645,
    "name:xx": "Kébara"
  }
}
