{
  "geometry": {
    "type": "Point",
    "coordinates": [
      -109.4333,
      44.4667
    ]
  },
  "type": "Feature",
  "properties": {
    "hierarchy": [
      "tgn:2123223",
      "tgn:1000001",
      "tgn:7012149",
      "tgn:2002379",
      "tgn:7007923",
      "tgn:7029392"
    ],
    "placetype": [
      "aat:300008347"
    ],
    "id": 2123223,
    "name:xx": "Wapiti"
  }
}
