{
  "geometry": {
    "type": "Point",
    "coordinates": [
      -111.7167,
      34.25
    ]
  },
  "type": "Feature",
  "properties": {
    "hierarchy": [
      "tgn:2689239",
      "tgn:1000001",
      "tgn:7006451",
      "tgn:7012149",
      "tgn:2000103",
      "tgn:7029392"
    ],
    "placetype": [
      "aat:300008706"
    ],
    "id": 2689239,
    "name:xx": "Squaw Creek"
  }
}
