{
  "geometry": {
    "type": "Point",
    "coordinates": [
      41.4667,
      39.1667
    ]
  },
  "type": "Feature",
  "properties": {
    "hierarchy": [
      "tgn:1086978",
      "tgn:1001437",
      "tgn:1000004",
      "tgn:7018455",
      "tgn:1000144",
      "tgn:7029392"
    ],
    "placetype": [
      "aat:300008347"
    ],
    "id": 1086978,
    "name:xx": "Varto"
  }
}
