{
  "geometry": {
    "type": "Point",
    "coordinates": [
      -114.2167,
      44.6333
    ]
  },
  "type": "Feature",
  "properties": {
    "hierarchy": [
      "tgn:2186690",
      "tgn:1000001",
      "tgn:2000470",
      "tgn:7012149",
      "tgn:7007250",
      "tgn:7029392"
    ],
    "placetype": [
      "aat:300008761"
    ],
    "id": 2186690,
    "name:xx": "Boneyard Gulch"
  }
}
