{
  "geometry": {
    "type": "Point",
    "coordinates": [
      86.499692,
      23.664495
    ]
  },
  "type": "Feature",
  "properties": {
    "hierarchy": [
      "tgn:7559265",
      "tgn:1000004",
      "tgn:7000198",
      "tgn:7031783",
      "tgn:7029392"
    ],
    "placetype": [
      "aat:300008347"
    ],
    "name:en": "Rohrābāndh",
    "id": 7559265
  }
}
