{
  "geometry": {
    "type": "Point",
    "coordinates": [
      -69.1667,
      45.2167
    ]
  },
  "type": "Feature",
  "properties": {
    "hierarchy": [
      "tgn:2345342",
      "tgn:1000001",
      "tgn:7012149",
      "tgn:2000928",
      "tgn:7007515",
      "tgn:7029392"
    ],
    "placetype": [
      "aat:300008680"
    ],
    "id": 2345342,
    "name:xx": "Garland Pond"
  }
}
