{
  "geometry": {
    "type": "Point",
    "coordinates": [
      -86.2333,
      35.2833
    ]
  },
  "type": "Feature",
  "properties": {
    "hierarchy": [
      "tgn:2539311",
      "tgn:1000001",
      "tgn:7012149",
      "tgn:2001862",
      "tgn:7007825",
      "tgn:7029392"
    ],
    "placetype": [
      "aat:300008697"
    ],
    "id": 2539311,
    "name:xx": "New Hope Spring"
  }
}
