{
  "geometry": {
    "type": "Point",
    "coordinates": [
      87.3333,
      23.0833
    ]
  },
  "type": "Feature",
  "properties": {
    "hierarchy": [
      "tgn:1123593",
      "tgn:1000004",
      "tgn:7000198",
      "tgn:1001977",
      "tgn:7029392"
    ],
    "placetype": [
      "aat:300008707"
    ],
    "id": 1123593,
    "name:xx": "Dwārkeswar"
  }
}
