{
  "type": "FeatureCollection",
  "features": [
    {
      "geometry": {
        "type": "Point",
        "coordinates": [
          11.2,
          47.566667
        ]
      },
      "type": "Feature",
      "properties": {
        "hierarchy": [
          "tgn:7062950",
          "tgn:7003669",
          "tgn:1000003",
          "tgn:7000084",
          "tgn:7029392"
        ],
        "placetype": [
          "aat:300008795"
        ],
        "id": 7062950,
        "name:xx": "Archtal-Kopf"
      }
    },
    {
      "geometry": {
        "type": "Point",
        "coordinates": [
          8.366667,
          54.9
        ]
      },
      "type": "Feature",
      "properties": {
        "hierarchy": [
          "tgn:7062951",
          "tgn:1000003",
          "tgn:7003688",
          "tgn:7000084",
          "tgn:7029392"
        ],
        "placetype": [
          "aat:300008699"
        ],
        "id": 7062951,
        "name:xx": "Archs-Wehle"
      }
    },
    {
      "geometry": {
        "type": "Point",
        "coordinates": [
          8.4,
          54.866667
        ]
      },
      "type": "Feature",
      "properties": {
        "hierarchy": [
          "tgn:7062952",
          "tgn:1000003",
          "tgn:7003688",
          "tgn:7000084",
          "tgn:7029392"
        ],
        "placetype": [
          "aat:300008347"
        ],
        "id": 7062952,
        "name:xx": "Archsum"
      }
    },
    {
      "geometry": {
        "type": "Point",
        "coordinates": [
          10.3,
          49.216667
        ]
      },
      "type": "Feature",
      "properties": {
        "hierarchy": [
          "tgn:7062954",
          "tgn:7003669",
          "tgn:1000003",
          "tgn:7000084",
          "tgn:7029392"
        ],
        "placetype": [
          "aat:300008347"
        ],
        "id": 7062954,
        "name:xx": "Archshofen"
      }
    },
    {
      "geometry": {
        "type": "Point",
        "coordinates": [
          10.15,
          51.033333
        ]
      },
      "type": "Feature",
      "properties": {
        "hierarchy": [
          "tgn:7062955",
          "tgn:1000003",
          "tgn:7003678",
          "tgn:7000084",
          "tgn:7029392"
        ],
        "placetype": [
          "aat:300008347"
        ],
        "id": 7062955,
        "name:xx": "Archfeld"
      }
    },
    {
      "geometry": {
        "type": "Point",
        "coordinates": [
          12.966667,
          47.566667
        ]
      },
      "type": "Feature",
      "properties": {
        "hierarchy": [
          "tgn:7062956",
          "tgn:7003669",
          "tgn:1000003",
          "tgn:7000084",
          "tgn:7029392"
        ],
        "placetype": [
          "aat:300008749"
        ],
        "id": 7062956,
        "name:xx": "Archen Wand"
      }
    },
    {
      "geometry": {
        "type": "Point",
        "coordinates": [
          11.933333,
          49.25
        ]
      },
      "type": "Feature",
      "properties": {
        "hierarchy": [
          "tgn:7062957",
          "tgn:7003669",
          "tgn:1000003",
          "tgn:7000084",
          "tgn:7029392"
        ],
        "placetype": [
          "aat:300000206"
        ],
        "id": 7062957,
        "name:xx": "Archenleiten"
      }
    },
    {
      "geometry": {
        "type": "Point",
        "coordinates": [
          12.966667,
          47.566667
        ]
      },
      "type": "Feature",
      "properties": {
        "hierarchy": [
          "tgn:7062958",
          "tgn:7003669",
          "tgn:1000003",
          "tgn:7000084",
          "tgn:7029392"
        ],
        "placetype": [
          "aat:300008795"
        ],
        "id": 7062958,
        "name:xx": "Archenkopf"
      }
    },
    {
      "geometry": {
        "type": "Point",
        "coordinates": [
          7.3,
          53.3
        ]
      },
      "type": "Feature",
      "properties": {
        "hierarchy": [
          "tgn:7062959",
          "tgn:1000003",
          "tgn:7003676",
          "tgn:7000084",
          "tgn:7029392"
        ],
        "placetype": [
          "aat:300000206"
        ],
        "id": 7062959,
        "name:xx": "Arche"
      }
    }
  ]
}
