{
  "type": "FeatureCollection",
  "features": [
    {
      "geometry": {
        "type": "Point",
        "coordinates": [
          -85.7,
          30.8167
        ]
      },
      "type": "Feature",
      "properties": {
        "hierarchy": [
          "tgn:2468880",
          "tgn:1000001",
          "tgn:2000272",
          "tgn:7012149",
          "tgn:7007240",
          "tgn:7029392"
        ],
        "placetype": [
          "aat:300008905"
        ],
        "id": 2468880,
        "name:xx": "Long Round Bay"
      }
    },
    {
      "geometry": {
        "type": "Point",
        "coordinates": [
          -85.1167,
          38.75
        ]
      },
      "type": "Feature",
      "properties": {
        "hierarchy": [
          "tgn:2468881",
          "tgn:1000001",
          "tgn:7012149",
          "tgn:1002938",
          "tgn:7007252",
          "tgn:7029392"
        ],
        "placetype": [
          "aat:300008347"
        ],
        "id": 2468881,
        "name:xx": "Long Run"
      }
    },
    {
      "geometry": {
        "type": "Point",
        "coordinates": [
          -87.9167,
          38.1
        ]
      },
      "type": "Feature",
      "properties": {
        "hierarchy": [
          "tgn:2468882",
          "tgn:1000001",
          "tgn:7012149",
          "tgn:2000552",
          "tgn:7007252",
          "tgn:7029392"
        ],
        "placetype": [
          "aat:300008699"
        ],
        "id": 2468882,
        "name:xx": "Long Run"
      }
    },
    {
      "geometry": {
        "type": "Point",
        "coordinates": [
          -86.6,
          38.0667
        ]
      },
      "type": "Feature",
      "properties": {
        "hierarchy": [
          "tgn:2468883",
          "tgn:1000001",
          "tgn:7012149",
          "tgn:2000550",
          "tgn:7007252",
          "tgn:7029392"
        ],
        "placetype": [
          "aat:300008699"
        ],
        "id": 2468883,
        "name:xx": "Long Run"
      }
    },
    {
      "geometry": {
        "type": "Point",
        "coordinates": [
          -86.2333,
          39.3833
        ]
      },
      "type": "Feature",
      "properties": {
        "hierarchy": [
          "tgn:2468884",
          "tgn:1000001",
          "tgn:7012149",
          "tgn:7007252",
          "tgn:7029392"
        ],
        "placetype": [
          "aat:300008699"
        ],
        "id": 2468884,
        "name:xx": "Long Run"
      }
    },
    {
      "geometry": {
        "type": "Point",
        "coordinates": [
          -85.15,
          38.7833
        ]
      },
      "type": "Feature",
      "properties": {
        "hierarchy": [
          "tgn:2468885",
          "tgn:1000001",
          "tgn:7012149",
          "tgn:1002938",
          "tgn:7007252",
          "tgn:7029392"
        ],
        "placetype": [
          "aat:300008699"
        ],
        "id": 2468885,
        "name:xx": "Long Run"
      }
    },
    {
      "geometry": {
        "type": "Point",
        "coordinates": [
          -85.05,
          37.65
        ]
      },
      "type": "Feature",
      "properties": {
        "hierarchy": [
          "tgn:2468886",
          "tgn:1000001",
          "tgn:7012149",
          "tgn:2000849",
          "tgn:7007255",
          "tgn:7029392"
        ],
        "placetype": [
          "aat:300008699"
        ],
        "id": 2468886,
        "name:xx": "Long Run"
      }
    },
    {
      "geometry": {
        "type": "Point",
        "coordinates": [
          -85.2167,
          37.95
        ]
      },
      "type": "Feature",
      "properties": {
        "hierarchy": [
          "tgn:2468887",
          "tgn:1000001",
          "tgn:7012149",
          "tgn:2000833",
          "tgn:7007255",
          "tgn:7029392"
        ],
        "placetype": [
          "aat:300008699"
        ],
        "id": 2468887,
        "name:xx": "Long Run"
      }
    },
    {
      "geometry": {
        "type": "Point",
        "coordinates": [
          -85.4,
          38.25
        ]
      },
      "type": "Feature",
      "properties": {
        "hierarchy": [
          "tgn:2468888",
          "tgn:1000001",
          "tgn:7012149",
          "tgn:1002516",
          "tgn:7007255",
          "tgn:7029392"
        ],
        "placetype": [
          "aat:300008699"
        ],
        "id": 2468888,
        "name:xx": "Long Run"
      }
    },
    {
      "geometry": {
        "type": "Point",
        "coordinates": [
          -92.7333,
          36.65
        ]
      },
      "type": "Feature",
      "properties": {
        "hierarchy": [
          "tgn:2468889",
          "tgn:1000001",
          "tgn:7012149",
          "tgn:2001226",
          "tgn:7007523",
          "tgn:7029392"
        ],
        "placetype": [
          "aat:300008699"
        ],
        "id": 2468889,
        "name:xx": "Long Run"
      }
    }
  ]
}
