{
  "geometry": {
    "type": "Point",
    "coordinates": [
      -69.4167,
      -1.0833
    ]
  },
  "type": "Feature",
  "properties": {
    "hierarchy": [
      "tgn:7017937",
      "tgn:1000002",
      "tgn:7029392"
    ],
    "placetype": [
      "aat:300008707"
    ],
    "id": 7017937,
    "name:xx": "Traīra"
  }
}
