{
  "geometry": {
    "type": "Point",
    "coordinates": [
      -104.7167,
      33.8667
    ]
  },
  "type": "Feature",
  "properties": {
    "hierarchy": [
      "tgn:2452857",
      "tgn:1000001",
      "tgn:2001430",
      "tgn:7012149",
      "tgn:7007566",
      "tgn:7029392"
    ],
    "placetype": [
      "aat:300006191"
    ],
    "id": 2452857,
    "name:xx": "Little Burts Tank"
  }
}
