{
  "geometry": {
    "type": "Point",
    "coordinates": [
      -111.5167,
      40.0333
    ]
  },
  "type": "Feature",
  "properties": {
    "hierarchy": [
      "tgn:2225057",
      "tgn:1000001",
      "tgn:7012149",
      "tgn:2002125",
      "tgn:7007827",
      "tgn:7029392"
    ],
    "placetype": [
      "aat:300008347"
    ],
    "id": 2225057,
    "name:xx": "Castilla"
  }
}
