{
  "geometry": {
    "type": "Point",
    "coordinates": [
      33.9833,
      57.7333
    ]
  },
  "type": "Feature",
  "properties": {
    "hierarchy": [
      "tgn:1055990",
      "tgn:1000004",
      "tgn:7012941",
      "tgn:7018214",
      "tgn:7002435",
      "tgn:7029392"
    ],
    "placetype": [
      "aat:300008347"
    ],
    "id": 1055990,
    "name:xx": "Kuzhenkino"
  }
}
