{
  "geometry": {
    "type": "Point",
    "coordinates": [
      173.9333,
      52.7333
    ]
  },
  "type": "Feature",
  "properties": {
    "hierarchy": [
      "tgn:2542261",
      "tgn:7030516",
      "tgn:7006450",
      "tgn:1000001",
      "tgn:7012149",
      "tgn:7029392"
    ],
    "placetype": [
      "aat:300132316"
    ],
    "id": 2542261,
    "name:xx": "Nizki Cove"
  }
}
