{
  "geometry": {
    "type": "Point",
    "coordinates": [
      -84.4333,
      44.55
    ]
  },
  "type": "Feature",
  "properties": {
    "hierarchy": [
      "tgn:2293873",
      "tgn:1000001",
      "tgn:2000954",
      "tgn:7012149",
      "tgn:7007520",
      "tgn:7029392"
    ],
    "placetype": [
      "aat:300008706"
    ],
    "id": 2293873,
    "name:xx": "Douglas Creek"
  }
}
