{
  "type": "FeatureCollection",
  "features": [
    {
      "geometry": {
        "type": "Point",
        "coordinates": [
          -103.65,
          39.7
        ]
      },
      "type": "Feature",
      "properties": {
        "hierarchy": [
          "tgn:2184320",
          "tgn:1000001",
          "tgn:7012149",
          "tgn:7007158",
          "tgn:2000252",
          "tgn:7029392"
        ],
        "placetype": [
          "aat:300008761"
        ],
        "id": 2184320,
        "name:xx": "Bobcat Canyon"
      }
    },
    {
      "geometry": {
        "type": "Point",
        "coordinates": [
          -103.9,
          41.75
        ]
      },
      "type": "Feature",
      "properties": {
        "hierarchy": [
          "tgn:2184321",
          "tgn:1000001",
          "tgn:7012149",
          "tgn:2001394",
          "tgn:7007525",
          "tgn:7029392"
        ],
        "placetype": [
          "aat:300008761"
        ],
        "id": 2184321,
        "name:xx": "Bobcat Canyon"
      }
    },
    {
      "geometry": {
        "type": "Point",
        "coordinates": [
          -118.7167,
          41.9167
        ]
      },
      "type": "Feature",
      "properties": {
        "hierarchy": [
          "tgn:2184322",
          "tgn:1000001",
          "tgn:2001414",
          "tgn:7012149",
          "tgn:7007526",
          "tgn:7029392"
        ],
        "placetype": [
          "aat:300008761"
        ],
        "id": 2184322,
        "name:xx": "Bobcat Canyon"
      }
    },
    {
      "geometry": {
        "type": "Point",
        "coordinates": [
          -107.6,
          32.1833
        ]
      },
      "type": "Feature",
      "properties": {
        "hierarchy": [
          "tgn:2184323",
          "tgn:1000001",
          "tgn:7012149",
          "tgn:2001444",
          "tgn:7007566",
          "tgn:7029392"
        ],
        "placetype": [
          "aat:300008761"
        ],
        "id": 2184323,
        "name:xx": "Bobcat Canyon"
      }
    },
    {
      "geometry": {
        "type": "Point",
        "coordinates": [
          -105.6667,
          35.3667
        ]
      },
      "type": "Feature",
      "properties": {
        "hierarchy": [
          "tgn:2184324",
          "tgn:1000001",
          "tgn:7012149",
          "tgn:7007566",
          "tgn:7029392"
        ],
        "placetype": [
          "aat:300008761"
        ],
        "id": 2184324,
        "name:xx": "Bobcat Canyon"
      }
    },
    {
      "geometry": {
        "type": "Point",
        "coordinates": [
          -103.3333,
          43.6833
        ]
      },
      "type": "Feature",
      "properties": {
        "hierarchy": [
          "tgn:2184325",
          "tgn:1000001",
          "tgn:2001786",
          "tgn:7012149",
          "tgn:7007713",
          "tgn:7029392"
        ],
        "placetype": [
          "aat:300008761"
        ],
        "id": 2184325,
        "name:xx": "Bobcat Canyon"
      }
    },
    {
      "geometry": {
        "type": "Point",
        "coordinates": [
          -103.1667,
          45.4833
        ]
      },
      "type": "Feature",
      "properties": {
        "hierarchy": [
          "tgn:2184326",
          "tgn:1000001",
          "tgn:2001801",
          "tgn:7012149",
          "tgn:7007713",
          "tgn:7029392"
        ],
        "placetype": [
          "aat:300008761"
        ],
        "id": 2184326,
        "name:xx": "Bobcat Canyon"
      }
    },
    {
      "geometry": {
        "type": "Point",
        "coordinates": [
          -104.7,
          30.5667
        ]
      },
      "type": "Feature",
      "properties": {
        "hierarchy": [
          "tgn:2184327",
          "tgn:1000001",
          "tgn:7012149",
          "tgn:2002010",
          "tgn:7007826",
          "tgn:7029392"
        ],
        "placetype": [
          "aat:300008761"
        ],
        "id": 2184327,
        "name:xx": "Bobcat Canyon"
      }
    },
    {
      "geometry": {
        "type": "Point",
        "coordinates": [
          -105.0667,
          42.4167
        ]
      },
      "type": "Feature",
      "properties": {
        "hierarchy": [
          "tgn:2184328",
          "tgn:1000001",
          "tgn:7012149",
          "tgn:2002380",
          "tgn:7007923",
          "tgn:7029392"
        ],
        "placetype": [
          "aat:300008761"
        ],
        "id": 2184328,
        "name:xx": "Bobcat Canyon"
      }
    },
    {
      "geometry": {
        "type": "Point",
        "coordinates": [
          -107.4333,
          47.2167
        ]
      },
      "type": "Feature",
      "properties": {
        "hierarchy": [
          "tgn:2184329",
          "tgn:1000001",
          "tgn:7012149",
          "tgn:2001276",
          "tgn:7007524",
          "tgn:7029392"
        ],
        "placetype": [
          "aat:300008761"
        ],
        "id": 2184329,
        "name:xx": "Bobcat Coulee"
      }
    }
  ]
}
