{
  "geometry": {
    "type": "Point",
    "coordinates": [
      -75.3333,
      43.35
    ]
  },
  "type": "Feature",
  "properties": {
    "hierarchy": [
      "tgn:2711231",
      "tgn:1000001",
      "tgn:7012149",
      "tgn:7014287",
      "tgn:7007568",
      "tgn:7029392"
    ],
    "placetype": [
      "aat:300008699"
    ],
    "id": 2711231,
    "name:xx": "Tannery Brook"
  }
}
