{
  "geometry": {
    "type": "Point",
    "coordinates": [
      -83.1667,
      33.0833
    ]
  },
  "type": "Feature",
  "properties": {
    "hierarchy": [
      "tgn:2344389",
      "tgn:2000296",
      "tgn:1000001",
      "tgn:7012149",
      "tgn:7007248",
      "tgn:7029392"
    ],
    "placetype": [
      "aat:300008706"
    ],
    "id": 2344389,
    "name:xx": "Gantry Creek"
  }
}
