{
  "geometry": {
    "type": "Point",
    "coordinates": [
      -86.9333,
      13.1833
    ]
  },
  "type": "Feature",
  "properties": {
    "hierarchy": [
      "tgn:1018789",
      "tgn:1000566",
      "tgn:1000001",
      "tgn:7005562",
      "tgn:7029392"
    ],
    "placetype": [
      "aat:300008347"
    ],
    "id": 1018789,
    "name:xx": "Santo Tomás del Norte"
  }
}
