{
  "geometry": {
    "type": "Point",
    "coordinates": [
      -123.4833,
      40.95
    ]
  },
  "type": "Feature",
  "properties": {
    "hierarchy": [
      "tgn:2367911",
      "tgn:1000001",
      "tgn:7012149",
      "tgn:2000181",
      "tgn:7007157",
      "tgn:7029392"
    ],
    "placetype": [
      "aat:300055621"
    ],
    "id": 2367911,
    "name:xx": "Groves Prairie"
  }
}
