{
  "type": "FeatureCollection",
  "features": [
    {
      "geometry": {
        "type": "Point",
        "coordinates": [
          9.066667,
          50
        ]
      },
      "type": "Feature",
      "properties": {
        "hierarchy": [
          "tgn:7070330",
          "tgn:7003669",
          "tgn:1000003",
          "tgn:7000084",
          "tgn:7029392"
        ],
        "placetype": [
          "aat:300008699"
        ],
        "id": 7070330,
        "name:xx": "Stein-Bach"
      }
    },
    {
      "geometry": {
        "type": "Point",
        "coordinates": [
          6.8,
          50
        ]
      },
      "type": "Feature",
      "properties": {
        "hierarchy": [
          "tgn:7070331",
          "tgn:1000003",
          "tgn:7003682",
          "tgn:7000084",
          "tgn:7029392"
        ],
        "placetype": [
          "aat:300008699"
        ],
        "id": 7070331,
        "name:xx": "Stein Bach"
      }
    },
    {
      "geometry": {
        "type": "Point",
        "coordinates": [
          12.05,
          49.966667
        ]
      },
      "type": "Feature",
      "properties": {
        "hierarchy": [
          "tgn:7070332",
          "tgn:7003669",
          "tgn:1000003",
          "tgn:7000084",
          "tgn:7029392"
        ],
        "placetype": [
          "aat:300008699"
        ],
        "id": 7070332,
        "name:xx": "Stein Bach"
      }
    },
    {
      "geometry": {
        "type": "Point",
        "coordinates": [
          10.55,
          49.883333
        ]
      },
      "type": "Feature",
      "properties": {
        "hierarchy": [
          "tgn:7070333",
          "tgn:7003669",
          "tgn:1000003",
          "tgn:7000084",
          "tgn:7029392"
        ],
        "placetype": [
          "aat:300008699"
        ],
        "id": 7070333,
        "name:xx": "Steinbach"
      }
    },
    {
      "geometry": {
        "type": "Point",
        "coordinates": [
          10.933333,
          49.85
        ]
      },
      "type": "Feature",
      "properties": {
        "hierarchy": [
          "tgn:7070334",
          "tgn:7003669",
          "tgn:1000003",
          "tgn:7000084",
          "tgn:7029392"
        ],
        "placetype": [
          "aat:300008699"
        ],
        "id": 7070334,
        "name:xx": "Stein-Bach"
      }
    },
    {
      "geometry": {
        "type": "Point",
        "coordinates": [
          12.433333,
          49.816667
        ]
      },
      "type": "Feature",
      "properties": {
        "hierarchy": [
          "tgn:7070335",
          "tgn:7003669",
          "tgn:1000003",
          "tgn:7000084",
          "tgn:7029392"
        ],
        "placetype": [
          "aat:300008699"
        ],
        "id": 7070335,
        "name:xx": "Stein Bach"
      }
    },
    {
      "geometry": {
        "type": "Point",
        "coordinates": [
          12.1,
          49.833333
        ]
      },
      "type": "Feature",
      "properties": {
        "hierarchy": [
          "tgn:7070336",
          "tgn:7003669",
          "tgn:1000003",
          "tgn:7000084",
          "tgn:7029392"
        ],
        "placetype": [
          "aat:300008699"
        ],
        "id": 7070336,
        "name:xx": "Stein Bach"
      }
    },
    {
      "geometry": {
        "type": "Point",
        "coordinates": [
          7.716667,
          49.566667
        ]
      },
      "type": "Feature",
      "properties": {
        "hierarchy": [
          "tgn:7070338",
          "tgn:1000003",
          "tgn:7003682",
          "tgn:7000084",
          "tgn:7029392"
        ],
        "placetype": [
          "aat:300008699"
        ],
        "id": 7070338,
        "name:xx": "Stein Bach"
      }
    },
    {
      "geometry": {
        "type": "Point",
        "coordinates": [
          7.4,
          49.466667
        ]
      },
      "type": "Feature",
      "properties": {
        "hierarchy": [
          "tgn:7070339",
          "tgn:1000003",
          "tgn:7003682",
          "tgn:7000084",
          "tgn:7029392"
        ],
        "placetype": [
          "aat:300008699"
        ],
        "id": 7070339,
        "name:xx": "Stein Bach"
      }
    }
  ]
}
