{
  "geometry": {
    "type": "Point",
    "coordinates": [
      -93.65,
      45.6833
    ]
  },
  "type": "Feature",
  "properties": {
    "hierarchy": [
      "tgn:2260645",
      "tgn:1000001",
      "tgn:7012149",
      "tgn:2001046",
      "tgn:7007521",
      "tgn:7029392"
    ],
    "placetype": [
      "aat:300006075"
    ],
    "id": 2260645,
    "name:xx": "County Ditch Number Nine"
  }
}
