{
  "geometry": {
    "type": "Point",
    "coordinates": [
      -112.1333,
      46.35
    ]
  },
  "type": "Feature",
  "properties": {
    "hierarchy": [
      "tgn:7020498",
      "tgn:1000001",
      "tgn:7012149",
      "tgn:2001281",
      "tgn:7007524",
      "tgn:7029392"
    ],
    "placetype": [
      "aat:300000390"
    ],
    "id": 7020498,
    "name:xx": "Washington Mines"
  }
}
