{
  "type": "FeatureCollection",
  "features": [
    {
      "geometry": {
        "type": "Point",
        "coordinates": [
          -81.2833,
          28.5667
        ]
      },
      "type": "Feature",
      "properties": {
        "hierarchy": [
          "tgn:2021620",
          "tgn:1000001",
          "tgn:7012149",
          "tgn:1002749",
          "tgn:7007240",
          "tgn:7029392"
        ],
        "placetype": [
          "aat:300008347"
        ],
        "id": 2021620,
        "name:xx": "Union Park"
      }
    },
    {
      "geometry": {
        "type": "Point",
        "coordinates": [
          -80.3,
          26.9
        ]
      },
      "type": "Feature",
      "properties": {
        "hierarchy": [
          "tgn:2021623",
          "tgn:1000001",
          "tgn:7012149",
          "tgn:1002768",
          "tgn:7007240",
          "tgn:7029392"
        ],
        "placetype": [
          "aat:300387016"
        ],
        "id": 2021623,
        "name:xx": "United"
      }
    },
    {
      "geometry": {
        "type": "Point",
        "coordinates": [
          -82.4,
          28.05
        ]
      },
      "type": "Feature",
      "properties": {
        "hierarchy": [
          "tgn:2021627",
          "tgn:1000001",
          "tgn:1002479",
          "tgn:7012149",
          "tgn:7007240",
          "tgn:7029392"
        ],
        "placetype": [
          "aat:300006617"
        ],
        "id": 2021627,
        "name:xx": "University of South Florida"
      }
    },
    {
      "geometry": {
        "type": "Point",
        "coordinates": [
          -87.2167,
          30.55
        ]
      },
      "type": "Feature",
      "properties": {
        "hierarchy": [
          "tgn:2021628",
          "tgn:1000001",
          "tgn:2000265",
          "tgn:7012149",
          "tgn:7007240",
          "tgn:7029392"
        ],
        "placetype": [
          "aat:300006617"
        ],
        "id": 2021628,
        "name:xx": "University of West Florida"
      }
    }
  ]
}
