{
  "geometry": {
    "type": "Point",
    "coordinates": [
      79.63985,
      26.764188
    ]
  },
  "type": "Feature",
  "properties": {
    "hierarchy": [
      "tgn:7566032",
      "tgn:1000004",
      "tgn:7000198",
      "tgn:7016722",
      "tgn:7029392"
    ],
    "placetype": [
      "aat:300008347"
    ],
    "name:en": "Gopālpur",
    "id": 7566032
  }
}
