{
  "geometry": {
    "type": "Point",
    "coordinates": [
      -57.3333,
      -23.5667
    ]
  },
  "type": "Feature",
  "properties": {
    "hierarchy": [
      "tgn:1130007",
      "tgn:7002636",
      "tgn:1000730",
      "tgn:1000002",
      "tgn:1000055",
      "tgn:7029392"
    ],
    "placetype": [
      "aat:300008707"
    ],
    "id": 1130007,
    "name:xx": "Siete Puntas, Río"
  }
}
