{
  "geometry": {
    "type": "Point",
    "coordinates": [
      79.4504,
      24.8541
    ]
  },
  "type": "Feature",
  "properties": {
    "hierarchy": [
      "tgn:7564094",
      "tgn:1000004",
      "tgn:7000198",
      "tgn:1001894",
      "tgn:7029392"
    ],
    "placetype": [
      "aat:300008865"
    ],
    "name:en": "Gairwār Protected Forest",
    "id": 7564094
  }
}
