{
  "geometry": {
    "type": "Point",
    "coordinates": [
      -119.15,
      35.4833
    ]
  },
  "type": "Feature",
  "properties": {
    "hierarchy": [
      "tgn:2012202",
      "tgn:1000001",
      "tgn:7012149",
      "tgn:1002545",
      "tgn:7007157",
      "tgn:7029392"
    ],
    "placetype": [
      "aat:300387016"
    ],
    "id": 2012202,
    "name:xx": "Lerdo"
  }
}
