{
  "geometry": {
    "type": "Point",
    "coordinates": [
      -98.5833,
      46.0833
    ]
  },
  "type": "Feature",
  "properties": {
    "hierarchy": [
      "tgn:2653770",
      "tgn:1000001",
      "tgn:7012149",
      "tgn:7029392"
    ],
    "placetype": [
      "aat:300008699"
    ],
    "id": 2653770,
    "name:xx": "Sewer Branch"
  }
}
