{
  "geometry": {
    "type": "Point",
    "coordinates": [
      -101.7167,
      39.0667
    ]
  },
  "type": "Feature",
  "properties": {
    "hierarchy": [
      "tgn:2479740",
      "tgn:1000001",
      "tgn:7012149",
      "tgn:2000714",
      "tgn:7007254",
      "tgn:7029392"
    ],
    "placetype": [
      "aat:300008706"
    ],
    "id": 2479740,
    "name:xx": "Lake Creek"
  }
}
