{
  "geometry": {
    "type": "Point",
    "coordinates": [
      34.487344,
      28.802996
    ]
  },
  "type": "Feature",
  "properties": {
    "hierarchy": [
      "tgn:7521330",
      "tgn:7001242",
      "tgn:7016833",
      "tgn:7001336",
      "tgn:7029392"
    ],
    "placetype": [
      "aat:300379998"
    ],
    "name:en": "Ab큰 Jard훮n, W훮d카",
    "id": 7521330
  }
}
