{
  "geometry": {
    "type": "Point",
    "coordinates": [
      -85.7167,
      36.0833
    ]
  },
  "type": "Feature",
  "properties": {
    "hierarchy": [
      "tgn:2650834",
      "tgn:1000001",
      "tgn:7012149",
      "tgn:7007825",
      "tgn:7029392"
    ],
    "placetype": [
      "aat:300008706"
    ],
    "id": 2650834,
    "name:xx": "Second Creek"
  }
}
