{
  "geometry": {
    "type": "Point",
    "coordinates": [
      -105.2667,
      44.1833
    ]
  },
  "type": "Feature",
  "properties": {
    "hierarchy": [
      "tgn:2245983",
      "tgn:1000001",
      "tgn:2002367",
      "tgn:7012149",
      "tgn:7007923",
      "tgn:7029392"
    ],
    "placetype": [
      "aat:300008761"
    ],
    "id": 2245983,
    "name:xx": "Coal Mine Draw"
  }
}
