{
  "geometry": {
    "type": "Point",
    "coordinates": [
      -122.4333,
      39.6833
    ]
  },
  "type": "Feature",
  "properties": {
    "hierarchy": [
      "tgn:2377150",
      "tgn:1000001",
      "tgn:7012149",
      "tgn:1002409",
      "tgn:7007157",
      "tgn:7029392"
    ],
    "placetype": [
      "aat:300008697"
    ],
    "id": 2377150,
    "name:xx": "Harmes Spring"
  }
}
