{
  "geometry": {
    "type": "Point",
    "coordinates": [
      16.3333,
      48.1167
    ]
  },
  "type": "Feature",
  "properties": {
    "hierarchy": [
      "tgn:1026178",
      "tgn:7003025",
      "tgn:1000003",
      "tgn:1000062",
      "tgn:7029392"
    ],
    "placetype": [
      "aat:300008347"
    ],
    "id": 1026178,
    "name:xx": "Vösendorf"
  }
}
