{
  "type": "FeatureCollection",
  "features": [
    {
      "geometry": {
        "type": "Point",
        "coordinates": [
          115,
          38.5
        ]
      },
      "type": "Feature",
      "properties": {
        "hierarchy": [
          "tgn:1067730",
          "tgn:1000004",
          "tgn:7002077",
          "tgn:1000111",
          "tgn:7029392"
        ],
        "placetype": [
          "aat:300008347"
        ],
        "id": 1067730,
        "name:xx": "Dingxian"
      }
    },
    {
      "geometry": {
        "type": "Point",
        "coordinates": [
          112.9333,
          38.5167
        ]
      },
      "type": "Feature",
      "properties": {
        "hierarchy": [
          "tgn:1067731",
          "tgn:1000004",
          "tgn:7002086",
          "tgn:1000111",
          "tgn:7029392"
        ],
        "placetype": [
          "aat:300008347"
        ],
        "id": 1067731,
        "name:xx": "Dingxiang"
      }
    },
    {
      "geometry": {
        "type": "Point",
        "coordinates": [
          105.0167,
          25.2
        ]
      },
      "type": "Feature",
      "properties": {
        "hierarchy": [
          "tgn:1067732",
          "tgn:1000004",
          "tgn:7002080",
          "tgn:1000111",
          "tgn:7029392"
        ],
        "placetype": [
          "aat:300008347"
        ],
        "id": 1067732,
        "name:xx": "Dingxiao"
      }
    },
    {
      "geometry": {
        "type": "Point",
        "coordinates": [
          115.7667,
          39.2667
        ]
      },
      "type": "Feature",
      "properties": {
        "hierarchy": [
          "tgn:1067733",
          "tgn:1000004",
          "tgn:7002077",
          "tgn:1000111",
          "tgn:7029392"
        ],
        "placetype": [
          "aat:300008347"
        ],
        "id": 1067733,
        "name:xx": "Dingxing"
      }
    },
    {
      "geometry": {
        "type": "Point",
        "coordinates": [
          120.7,
          32.35
        ]
      },
      "type": "Feature",
      "properties": {
        "hierarchy": [
          "tgn:1067734",
          "tgn:1000004",
          "tgn:7002081",
          "tgn:1000111",
          "tgn:7029392"
        ],
        "placetype": [
          "aat:300008347"
        ],
        "id": 1067734,
        "name:xx": "Dingyan"
      }
    },
    {
      "geometry": {
        "type": "Point",
        "coordinates": [
          117.6667,
          32.5
        ]
      },
      "type": "Feature",
      "properties": {
        "hierarchy": [
          "tgn:1067735",
          "tgn:7002075",
          "tgn:1000004",
          "tgn:1000111",
          "tgn:7029392"
        ],
        "placetype": [
          "aat:300008347"
        ],
        "id": 1067735,
        "name:xx": "Dingyuan"
      }
    },
    {
      "geometry": {
        "type": "Point",
        "coordinates": [
          115.7167,
          40.3333
        ]
      },
      "type": "Feature",
      "properties": {
        "hierarchy": [
          "tgn:1067736",
          "tgn:1000004",
          "tgn:7002077",
          "tgn:1000111",
          "tgn:7029392"
        ],
        "placetype": [
          "aat:300008347"
        ],
        "id": 1067736,
        "name:xx": "Dingzhouying"
      }
    },
    {
      "geometry": {
        "type": "Point",
        "coordinates": [
          106.1333,
          28.9
        ]
      },
      "type": "Feature",
      "properties": {
        "hierarchy": [
          "tgn:1067737",
          "tgn:1000004",
          "tgn:7002087",
          "tgn:1000111",
          "tgn:7029392"
        ],
        "placetype": [
          "aat:300008347"
        ],
        "id": 1067737,
        "name:xx": "Dingzichang"
      }
    },
    {
      "geometry": {
        "type": "Point",
        "coordinates": [
          114.05,
          23.85
        ]
      },
      "type": "Feature",
      "properties": {
        "hierarchy": [
          "tgn:1067738",
          "tgn:1000004",
          "tgn:7005232",
          "tgn:1000111",
          "tgn:7029392"
        ],
        "placetype": [
          "aat:300008347"
        ],
        "id": 1067738,
        "name:xx": "Dipai"
      }
    }
  ]
}
