{
  "geometry": {
    "type": "Point",
    "coordinates": [
      -101.762778,
      20.6475
    ]
  },
  "type": "Feature",
  "properties": {
    "hierarchy": [
      "tgn:7416720",
      "tgn:7005584",
      "tgn:1000001",
      "tgn:7005560",
      "tgn:7029392"
    ],
    "placetype": [
      "aat:300008347"
    ],
    "id": 7416720,
    "name:xx": "Capulín Grande"
  }
}
