{
  "geometry": {
    "type": "Point",
    "coordinates": [
      -85.9333,
      41.1667
    ]
  },
  "type": "Feature",
  "properties": {
    "hierarchy": [
      "tgn:2565777",
      "tgn:1000001",
      "tgn:7012149",
      "tgn:1002557",
      "tgn:7007252",
      "tgn:7029392"
    ],
    "placetype": [
      "aat:300006191"
    ],
    "id": 2565777,
    "name:xx": "Palestine Lake"
  }
}
