{
  "type": "FeatureCollection",
  "features": [
    {
      "geometry": {
        "type": "Point",
        "coordinates": [
          -82.6333,
          35.7833
        ]
      },
      "type": "Feature",
      "properties": {
        "hierarchy": [
          "tgn:2721530",
          "tgn:1000001",
          "tgn:7012149",
          "tgn:2001516",
          "tgn:7007709",
          "tgn:7029392"
        ],
        "placetype": [
          "aat:300008699"
        ],
        "id": 2721530,
        "name:xx": "Tillery Branch"
      }
    },
    {
      "geometry": {
        "type": "Point",
        "coordinates": [
          -85.7667,
          34.15
        ]
      },
      "type": "Feature",
      "properties": {
        "hierarchy": [
          "tgn:2721531",
          "tgn:7002659",
          "tgn:1000001",
          "tgn:2000009",
          "tgn:7012149",
          "tgn:7029392"
        ],
        "placetype": [
          "aat:300132316"
        ],
        "id": 2721531,
        "name:xx": "Tillery Cove"
      }
    },
    {
      "geometry": {
        "type": "Point",
        "coordinates": [
          -85.1833,
          32.6833
        ]
      },
      "type": "Feature",
      "properties": {
        "hierarchy": [
          "tgn:2721532",
          "tgn:7002659",
          "tgn:1000001",
          "tgn:7012149",
          "tgn:2000040",
          "tgn:7029392"
        ],
        "placetype": [
          "aat:300008347"
        ],
        "id": 2721532,
        "name:xx": "Tillery Crossroad"
      }
    },
    {
      "geometry": {
        "type": "Point",
        "coordinates": [
          -86.6,
          38.4167
        ]
      },
      "type": "Feature",
      "properties": {
        "hierarchy": [
          "tgn:2721533",
          "tgn:1000001",
          "tgn:7012149",
          "tgn:1002750",
          "tgn:7007252",
          "tgn:7029392"
        ],
        "placetype": [
          "aat:300008798"
        ],
        "id": 2721533,
        "name:xx": "Tillery Hill"
      }
    },
    {
      "geometry": {
        "type": "Point",
        "coordinates": [
          -110.8333,
          44.1167
        ]
      },
      "type": "Feature",
      "properties": {
        "hierarchy": [
          "tgn:2721534",
          "tgn:1000001",
          "tgn:7012149",
          "tgn:2002384",
          "tgn:7007923",
          "tgn:7029392"
        ],
        "placetype": [
          "aat:300008680"
        ],
        "id": 2721534,
        "name:xx": "Tillery Lake"
      }
    },
    {
      "geometry": {
        "type": "Point",
        "coordinates": [
          -80.05,
          35.2
        ]
      },
      "type": "Feature",
      "properties": {
        "hierarchy": [
          "tgn:2721537",
          "tgn:1000001",
          "tgn:7012149",
          "tgn:2001540",
          "tgn:7007709",
          "tgn:7029392"
        ],
        "placetype": [
          "aat:300006191"
        ],
        "id": 2721537,
        "name:xx": "Tillery, Lake"
      }
    },
    {
      "geometry": {
        "type": "Point",
        "coordinates": [
          -82.3167,
          35.1
        ]
      },
      "type": "Feature",
      "properties": {
        "hierarchy": [
          "tgn:2721538",
          "tgn:1000001",
          "tgn:2001747",
          "tgn:7012149",
          "tgn:7007712",
          "tgn:7029392"
        ],
        "placetype": [
          "aat:300008798"
        ],
        "id": 2721538,
        "name:xx": "Tillet Mountain"
      }
    },
    {
      "geometry": {
        "type": "Point",
        "coordinates": [
          -75.7,
          36.05
        ]
      },
      "type": "Feature",
      "properties": {
        "hierarchy": [
          "tgn:2721539",
          "tgn:1000001",
          "tgn:7012149",
          "tgn:2001488",
          "tgn:7007709",
          "tgn:7029392"
        ],
        "placetype": [
          "aat:300132316"
        ],
        "id": 2721539,
        "name:xx": "Tillets Cove"
      }
    }
  ]
}
