{
  "geometry": {
    "type": "Point",
    "coordinates": [
      -96.0167,
      29.4167
    ]
  },
  "type": "Feature",
  "properties": {
    "hierarchy": [
      "tgn:2187368",
      "tgn:1000001",
      "tgn:7012149",
      "tgn:1003019",
      "tgn:7007826",
      "tgn:7029392"
    ],
    "placetype": [
      "aat:300008699"
    ],
    "id": 2187368,
    "name:xx": "Boone Branch"
  }
}
