{
  "geometry": {
    "type": "Point",
    "coordinates": [
      32.75,
      25.85
    ]
  },
  "type": "Feature",
  "properties": {
    "hierarchy": [
      "tgn:7529599",
      "tgn:7001242",
      "tgn:7016833",
      "tgn:7000123",
      "tgn:7029392"
    ],
    "placetype": [
      "aat:300005926"
    ],
    "name:en": "Sīdī Dahmash",
    "id": 7529599
  }
}
