{
  "geometry": {
    "type": "Point",
    "coordinates": [
      -63.4167,
      -29.0833
    ]
  },
  "type": "Feature",
  "properties": {
    "hierarchy": [
      "tgn:1129429",
      "tgn:7006477",
      "tgn:1000002",
      "tgn:7029392"
    ],
    "placetype": [
      "aat:300008707"
    ],
    "id": 1129429,
    "name:xx": "Saladillo, Río"
  }
}
