{
  "geometry": {
    "type": "Point",
    "coordinates": [
      -90.7333,
      46.5833
    ]
  },
  "type": "Feature",
  "properties": {
    "hierarchy": [
      "tgn:2430426",
      "tgn:2002306",
      "tgn:1000001",
      "tgn:7012149",
      "tgn:7007922",
      "tgn:7029392"
    ],
    "placetype": [
      "aat:300008707"
    ],
    "id": 2430426,
    "name:xx": "Kakagon River"
  }
}
