{
  "geometry": {
    "type": "Point",
    "coordinates": [
      143.8667,
      -37.1167
    ]
  },
  "type": "Feature",
  "properties": {
    "hierarchy": [
      "tgn:1120596",
      "tgn:7000490",
      "tgn:1000006",
      "tgn:7006238",
      "tgn:7029392"
    ],
    "placetype": [
      "aat:300006191"
    ],
    "id": 1120596,
    "name:xx": "Tullaroop Reservoir"
  }
}
