{
  "geometry": {
    "type": "Point",
    "coordinates": [
      -16.6667,
      15.0333
    ]
  },
  "type": "Feature",
  "properties": {
    "hierarchy": [
      "tgn:1092532",
      "tgn:7001242",
      "tgn:1001757",
      "tgn:1000189",
      "tgn:7029392"
    ],
    "placetype": [
      "aat:300008347"
    ],
    "id": 1092532,
    "name:xx": "Mekhé"
  }
}
