{
  "geometry": {
    "type": "Point",
    "coordinates": [
      -176.4333,
      51.8333
    ]
  },
  "type": "Feature",
  "properties": {
    "hierarchy": [
      "tgn:2180081",
      "tgn:7030516",
      "tgn:7006450",
      "tgn:1000001",
      "tgn:7012149",
      "tgn:7029392"
    ],
    "placetype": [
      "aat:300008850"
    ],
    "id": 2180081,
    "name:xx": "Blind Point"
  }
}
