{
  "type": "FeatureCollection",
  "features": [
    {
      "geometry": {
        "type": "Point",
        "coordinates": [
          -102.4667,
          43.9
        ]
      },
      "type": "Feature",
      "properties": {
        "hierarchy": [
          "tgn:2604051",
          "tgn:1000001",
          "tgn:7012149",
          "tgn:2001821",
          "tgn:7007713",
          "tgn:7029392"
        ],
        "placetype": [
          "aat:300008798"
        ],
        "id": 2604051,
        "name:xx": "Quinn Table"
      }
    },
    {
      "geometry": {
        "type": "Point",
        "coordinates": [
          -99.6833,
          28.85
        ]
      },
      "type": "Feature",
      "properties": {
        "hierarchy": [
          "tgn:2604052",
          "tgn:1000001",
          "tgn:7012149",
          "tgn:2002100",
          "tgn:7007826",
          "tgn:7029392"
        ],
        "placetype": [
          "aat:300006191"
        ],
        "id": 2604052,
        "name:xx": "Quinn Tank"
      }
    },
    {
      "geometry": {
        "type": "Point",
        "coordinates": [
          -92.6667,
          39.4
        ]
      },
      "type": "Feature",
      "properties": {
        "hierarchy": [
          "tgn:2604053",
          "tgn:1000001",
          "tgn:7012149",
          "tgn:1002819",
          "tgn:7007523",
          "tgn:7029392"
        ],
        "placetype": [
          "aat:300006191"
        ],
        "id": 2604053,
        "name:xx": "Quinn and Fitzgerald Lake"
      }
    },
    {
      "geometry": {
        "type": "Point",
        "coordinates": [
          -75.4167,
          41.5
        ]
      },
      "type": "Feature",
      "properties": {
        "hierarchy": [
          "tgn:2604054",
          "tgn:1000001",
          "tgn:7012149",
          "tgn:1003008",
          "tgn:7007710",
          "tgn:7029392"
        ],
        "placetype": [
          "aat:300008680"
        ],
        "id": 2604054,
        "name:xx": "Quinn, Lake"
      }
    },
    {
      "geometry": {
        "type": "Point",
        "coordinates": [
          -117.0667,
          47.5667
        ]
      },
      "type": "Feature",
      "properties": {
        "hierarchy": [
          "tgn:2604055",
          "tgn:1000001",
          "tgn:7012149",
          "tgn:2002249",
          "tgn:7007920",
          "tgn:7029392"
        ],
        "placetype": [
          "aat:300008706"
        ],
        "id": 2604055,
        "name:xx": "Quinnamose Creek"
      }
    },
    {
      "geometry": {
        "type": "Point",
        "coordinates": [
          -71.85,
          41.95
        ]
      },
      "type": "Feature",
      "properties": {
        "hierarchy": [
          "tgn:2604056",
          "tgn:1000001",
          "tgn:1003028",
          "tgn:7012149",
          "tgn:7007159",
          "tgn:7029392"
        ],
        "placetype": [
          "aat:300008699"
        ],
        "id": 2604056,
        "name:xx": "Quinnatisset Brook"
      }
    },
    {
      "geometry": {
        "type": "Point",
        "coordinates": [
          -96.1667,
          41.9333
        ]
      },
      "type": "Feature",
      "properties": {
        "hierarchy": [
          "tgn:2604057",
          "tgn:1000001",
          "tgn:2001326",
          "tgn:7012149",
          "tgn:7007525",
          "tgn:7029392"
        ],
        "placetype": [
          "aat:300008680"
        ],
        "id": 2604057,
        "name:xx": "Quinnebaugh, Lake"
      }
    },
    {
      "geometry": {
        "type": "Point",
        "coordinates": [
          -89.7,
          44.4
        ]
      },
      "type": "Feature",
      "properties": {
        "hierarchy": [
          "tgn:2604058",
          "tgn:1000001",
          "tgn:7012149",
          "tgn:7007922",
          "tgn:7029392"
        ],
        "placetype": [
          "aat:300008706"
        ],
        "id": 2604058,
        "name:xx": "Quinnell Creek"
      }
    },
    {
      "geometry": {
        "type": "Point",
        "coordinates": [
          -87.9833,
          45.8
        ]
      },
      "type": "Feature",
      "properties": {
        "hierarchy": [
          "tgn:2604059",
          "tgn:1000001",
          "tgn:2000956",
          "tgn:7012149",
          "tgn:7007520",
          "tgn:7029392"
        ],
        "placetype": [
          "aat:300000390"
        ],
        "id": 2604059,
        "name:xx": "Quinnesec Mine"
      }
    }
  ]
}
