{
  "geometry": {
    "type": "Point",
    "coordinates": [
      -88.9833,
      36.45
    ]
  },
  "type": "Feature",
  "properties": {
    "hierarchy": [
      "tgn:2766218",
      "tgn:1000001",
      "tgn:7012149",
      "tgn:2001902",
      "tgn:7007825",
      "tgn:7029392"
    ],
    "placetype": [
      "aat:300006191"
    ],
    "id": 2766218,
    "name:xx": "White Lake"
  }
}
