{
  "geometry": {
    "type": "Point",
    "coordinates": [
      -85.25,
      33.7333
    ]
  },
  "type": "Feature",
  "properties": {
    "hierarchy": [
      "tgn:2353045",
      "tgn:1000001",
      "tgn:7012149",
      "tgn:2000362",
      "tgn:7007248",
      "tgn:7029392"
    ],
    "placetype": [
      "aat:300006191"
    ],
    "id": 2353045,
    "name:xx": "Godwin Lake"
  }
}
