{
  "geometry": {
    "type": "Point",
    "coordinates": [
      -116.1833,
      35.9333
    ]
  },
  "type": "Feature",
  "properties": {
    "hierarchy": [
      "tgn:2232936",
      "tgn:1000001",
      "tgn:7012149",
      "tgn:2000183",
      "tgn:7007157",
      "tgn:7029392"
    ],
    "placetype": [
      "aat:300008697"
    ],
    "id": 2232936,
    "name:xx": "Chappo Spring"
  }
}
