{
  "type": "FeatureCollection",
  "features": [
    {
      "geometry": {
        "type": "Point",
        "coordinates": [
          -4.15,
          51.1
        ]
      },
      "type": "Feature",
      "properties": {
        "hierarchy": [
          "tgn:7444520",
          "tgn:7002445",
          "tgn:1000003",
          "tgn:7012077",
          "tgn:7008591",
          "tgn:7029392"
        ],
        "placetype": [
          "aat:300008347"
        ],
        "name:en": "Wrafton",
        "id": 7444520
      }
    },
    {
      "geometry": {
        "type": "Point",
        "coordinates": [
          1.166667,
          51.95
        ]
      },
      "type": "Feature",
      "properties": {
        "hierarchy": [
          "tgn:7444521",
          "tgn:7002445",
          "tgn:1000003",
          "tgn:7008131",
          "tgn:7008591",
          "tgn:7029392"
        ],
        "placetype": [
          "aat:300008347"
        ],
        "name:en": "Wrabness",
        "id": 7444521
      }
    },
    {
      "geometry": {
        "type": "Point",
        "coordinates": [
          -5.666667,
          50.166667
        ]
      },
      "type": "Feature",
      "properties": {
        "hierarchy": [
          "tgn:7444522",
          "tgn:7002445",
          "tgn:7008116",
          "tgn:1000003",
          "tgn:7008591",
          "tgn:7029392"
        ],
        "placetype": [
          "aat:300011692"
        ],
        "name:en": "Wra, The",
        "id": 7444522
      }
    },
    {
      "geometry": {
        "type": "Point",
        "coordinates": [
          1.633333,
          52.9
        ]
      },
      "type": "Feature",
      "properties": {
        "hierarchy": [
          "tgn:7444524",
          "tgn:7002445",
          "tgn:1000003",
          "tgn:7008160",
          "tgn:7008591",
          "tgn:7029392"
        ],
        "placetype": [
          "aat:300008713"
        ],
        "name:en": "Would, The",
        "id": 7444524
      }
    },
    {
      "geometry": {
        "type": "Point",
        "coordinates": [
          -2.041111,
          51.316111
        ]
      },
      "type": "Feature",
      "properties": {
        "hierarchy": [
          "tgn:7444528",
          "tgn:7002445",
          "tgn:1000003",
          "tgn:7008180",
          "tgn:7008591",
          "tgn:7029392"
        ],
        "placetype": [
          "aat:300008347"
        ],
        "name:en": "Worton",
        "id": 7444528
      }
    }
  ]
}
