{
  "geometry": {
    "type": "Point",
    "coordinates": [
      -74.8333,
      41.1667
    ]
  },
  "type": "Feature",
  "properties": {
    "hierarchy": [
      "tgn:2656105",
      "tgn:1000001",
      "tgn:1002934",
      "tgn:7012149",
      "tgn:7007565",
      "tgn:7029392"
    ],
    "placetype": [
      "aat:300006191"
    ],
    "id": 2656105,
    "name:xx": "Shawanni, Lake"
  }
}
