{
  "geometry": {
    "type": "Point",
    "coordinates": [
      -83.2667,
      30.0667
    ]
  },
  "type": "Feature",
  "properties": {
    "hierarchy": [
      "tgn:2641859",
      "tgn:1000001",
      "tgn:2000275",
      "tgn:7012149",
      "tgn:7007240",
      "tgn:7029392"
    ],
    "placetype": [
      "aat:300008680"
    ],
    "id": 2641859,
    "name:xx": "Sand Lake"
  }
}
