{
  "geometry": {
    "type": "Point",
    "coordinates": [
      -93.2833,
      38.8333
    ]
  },
  "type": "Feature",
  "properties": {
    "hierarchy": [
      "tgn:2059143",
      "tgn:1000001",
      "tgn:7012149",
      "tgn:2001229",
      "tgn:7007523",
      "tgn:7029392"
    ],
    "placetype": [
      "aat:300008347"
    ],
    "id": 2059143,
    "name:xx": "Hughesville"
  }
}
