{
  "geometry": {
    "type": "Point",
    "coordinates": [
      116.3833,
      39.9333
    ]
  },
  "type": "Feature",
  "properties": {
    "hierarchy": [
      "tgn:1102757",
      "tgn:1000956",
      "tgn:1000004",
      "tgn:1000111",
      "tgn:7029392"
    ],
    "placetype": [
      "aat:300008187"
    ],
    "id": 1102757,
    "name:xx": "Coal Hill Park"
  }
}
