{
  "geometry": {
    "type": "Point",
    "coordinates": [
      -110.5333,
      32.1833
    ]
  },
  "type": "Feature",
  "properties": {
    "hierarchy": [
      "tgn:2281982",
      "tgn:1000001",
      "tgn:7006451",
      "tgn:7012149",
      "tgn:2000100",
      "tgn:7029392"
    ],
    "placetype": [
      "aat:300008697"
    ],
    "id": 2281982,
    "name:xx": "Deer Head Spring"
  }
}
