{
  "geometry": {
    "type": "Point",
    "coordinates": [
      -119.1833,
      43.55
    ]
  },
  "type": "Feature",
  "properties": {
    "hierarchy": [
      "tgn:2324780",
      "tgn:1000001",
      "tgn:7012149",
      "tgn:2001709",
      "tgn:7007708",
      "tgn:7029392"
    ],
    "placetype": [
      "aat:300008761"
    ],
    "id": 2324780,
    "name:xx": "Fenwick Canyon"
  }
}
