{
  "geometry": {
    "type": "Point",
    "coordinates": [
      8.95,
      51.616667
    ]
  },
  "type": "Feature",
  "properties": {
    "hierarchy": [
      "tgn:7067840",
      "tgn:1000003",
      "tgn:7003677",
      "tgn:7000084",
      "tgn:7029392"
    ],
    "placetype": [
      "aat:300004792"
    ],
    "id": 7067840,
    "name:xx": "Försterei Torfbruch"
  }
}
