{
  "geometry": {
    "type": "Point",
    "coordinates": [
      -95.2667,
      39.3167
    ]
  },
  "type": "Feature",
  "properties": {
    "hierarchy": [
      "tgn:2037389",
      "tgn:1000001",
      "tgn:2000703",
      "tgn:7012149",
      "tgn:7007254",
      "tgn:7029392"
    ],
    "placetype": [
      "aat:300008347"
    ],
    "id": 2037389,
    "name:xx": "Winchester"
  }
}
