{
  "geometry": {
    "type": "Point",
    "coordinates": [
      -71.7333,
      44.65
    ]
  },
  "type": "Feature",
  "properties": {
    "hierarchy": [
      "tgn:2329055",
      "tgn:1000001",
      "tgn:1002361",
      "tgn:7012149",
      "tgn:7007828",
      "tgn:7029392"
    ],
    "placetype": [
      "aat:300008699"
    ],
    "id": 2329055,
    "name:xx": "Fitch Brook"
  }
}
