{
  "geometry": {
    "type": "Point",
    "coordinates": [
      -120.7333,
      51.0333
    ]
  },
  "type": "Feature",
  "properties": {
    "hierarchy": [
      "tgn:1013464",
      "tgn:7005735",
      "tgn:7005685",
      "tgn:1000001",
      "tgn:7029392"
    ],
    "placetype": [
      "aat:300008347"
    ],
    "id": 1013464,
    "name:xx": "Criss Creek"
  }
}
