{
  "geometry": {
    "type": "Point",
    "coordinates": [
      -84.3833,
      34.85
    ]
  },
  "type": "Feature",
  "properties": {
    "hierarchy": [
      "tgn:2183901",
      "tgn:1000001",
      "tgn:7012149",
      "tgn:7007248",
      "tgn:7029392"
    ],
    "placetype": [
      "aat:300008706"
    ],
    "id": 2183901,
    "name:xx": "Boardtown Creek"
  }
}
