{
  "geometry": {
    "type": "Point",
    "coordinates": [
      -87.3333,
      37.6167
    ]
  },
  "type": "Feature",
  "properties": {
    "hierarchy": [
      "tgn:2759798",
      "tgn:1000001",
      "tgn:7012149",
      "tgn:2000786",
      "tgn:7007255",
      "tgn:7029392"
    ],
    "placetype": [
      "aat:300008706"
    ],
    "id": 2759798,
    "name:xx": "West Fork Knoblick Creek"
  }
}
