{
  "geometry": {
    "type": "Point",
    "coordinates": [
      -95.3833,
      33.95
    ]
  },
  "type": "Feature",
  "properties": {
    "hierarchy": [
      "tgn:2549334",
      "tgn:1000001",
      "tgn:2001634",
      "tgn:7012149",
      "tgn:7007707",
      "tgn:7029392"
    ],
    "placetype": [
      "aat:300008699"
    ],
    "id": 2549334,
    "name:xx": "North Sandy Branch"
  }
}
