{
  "geometry": {
    "type": "Point",
    "coordinates": [
      -94.6667,
      46.1833
    ]
  },
  "type": "Feature",
  "properties": {
    "hierarchy": [
      "tgn:2453863",
      "tgn:1000001",
      "tgn:7012149",
      "tgn:2001075",
      "tgn:7007521",
      "tgn:7029392"
    ],
    "placetype": [
      "aat:300008680"
    ],
    "id": 2453863,
    "name:xx": "Little Cranberry Lake"
  }
}
