{
  "geometry": {
    "type": "Point",
    "coordinates": [
      -52.4167,
      -22.5833
    ]
  },
  "type": "Feature",
  "properties": {
    "hierarchy": [
      "tgn:1128391",
      "tgn:1000002",
      "tgn:7029392"
    ],
    "placetype": [
      "aat:300008707"
    ],
    "id": 1128391,
    "name:xx": "Paraná"
  }
}
