{
  "geometry": {
    "type": "Point",
    "coordinates": [
      -88.1167,
      37.8333
    ]
  },
  "type": "Feature",
  "properties": {
    "hierarchy": [
      "tgn:2785294",
      "tgn:1000001",
      "tgn:2000507",
      "tgn:7012149",
      "tgn:7007251",
      "tgn:7029392"
    ],
    "placetype": [
      "aat:300008905"
    ],
    "id": 2785294,
    "name:xx": "Yellowbank Slough"
  }
}
