{
  "geometry": {
    "type": "Point",
    "coordinates": [
      -116.0667,
      37.45
    ]
  },
  "type": "Feature",
  "properties": {
    "hierarchy": [
      "tgn:1107630",
      "tgn:1000001",
      "tgn:2001418",
      "tgn:7012149",
      "tgn:7007526",
      "tgn:7029392"
    ],
    "placetype": [
      "aat:300008798"
    ],
    "id": 1107630,
    "name:xx": "Wheelbarrow Peak"
  }
}
