{
  "geometry": {
    "type": "Point",
    "coordinates": [
      99.9167,
      19.1667
    ]
  },
  "type": "Feature",
  "properties": {
    "hierarchy": [
      "tgn:1085630",
      "tgn:7000916",
      "tgn:7005194",
      "tgn:1000004",
      "tgn:1000142",
      "tgn:7029392"
    ],
    "placetype": [
      "aat:300008347"
    ],
    "id": 1085630,
    "name:xx": "Phayao"
  }
}
