{
  "geometry": {
    "type": "Point",
    "coordinates": [
      -93.2667,
      30.8167
    ]
  },
  "type": "Feature",
  "properties": {
    "hierarchy": [
      "tgn:2239345",
      "tgn:1000001",
      "tgn:2000859",
      "tgn:7012149",
      "tgn:7007256",
      "tgn:7029392"
    ],
    "placetype": [
      "aat:300008699"
    ],
    "id": 2239345,
    "name:xx": "Church Branch"
  }
}
