{
  "type": "FeatureCollection",
  "features": [
    {
      "geometry": {
        "type": "Point",
        "coordinates": [
          -117.7833,
          33.7333
        ]
      },
      "type": "Feature",
      "properties": {
        "hierarchy": [
          "tgn:2013543",
          "tgn:1000001",
          "tgn:7012149",
          "tgn:7007157",
          "tgn:1002748",
          "tgn:7029392"
        ],
        "placetype": [
          "aat:300008798"
        ],
        "id": 2013543,
        "name:xx": "Red Hill"
      }
    },
    {
      "geometry": {
        "type": "Point",
        "coordinates": [
          -117.2,
          34.0167
        ]
      },
      "type": "Feature",
      "properties": {
        "hierarchy": [
          "tgn:2013544",
          "tgn:1000001",
          "tgn:7012149",
          "tgn:7007157",
          "tgn:1002857",
          "tgn:7029392"
        ],
        "placetype": [
          "aat:300008347"
        ],
        "id": 2013544,
        "name:xx": "Redlands"
      }
    },
    {
      "geometry": {
        "type": "Point",
        "coordinates": [
          -117.6,
          35.35
        ]
      },
      "type": "Feature",
      "properties": {
        "hierarchy": [
          "tgn:2013549",
          "tgn:1000001",
          "tgn:7012149",
          "tgn:7007157",
          "tgn:1002857",
          "tgn:7029392"
        ],
        "placetype": [
          "aat:300008347"
        ],
        "id": 2013549,
        "name:xx": "Red Mountain"
      }
    }
  ]
}
