{
  "geometry": {
    "type": "Point",
    "coordinates": [
      -85.75,
      39.7833
    ]
  },
  "type": "Feature",
  "properties": {
    "hierarchy": [
      "tgn:2622138",
      "tgn:1000001",
      "tgn:7012149",
      "tgn:1002447",
      "tgn:7007252",
      "tgn:7029392"
    ],
    "placetype": [
      "aat:300008680"
    ],
    "id": 2622138,
    "name:xx": "Roberts Lake"
  }
}
