{
  "geometry": {
    "type": "Point",
    "coordinates": [
      -84.7833,
      32.55
    ]
  },
  "type": "Feature",
  "properties": {
    "hierarchy": [
      "tgn:2346245",
      "tgn:1000001",
      "tgn:2156155",
      "tgn:7012149",
      "tgn:7007248",
      "tgn:7029392"
    ],
    "placetype": [
      "aat:300006191"
    ],
    "id": 2346245,
    "name:xx": "Gates Lake"
  }
}
