{
  "geometry": {
    "type": "Point",
    "coordinates": [
      -86.4333,
      39.1167
    ]
  },
  "type": "Feature",
  "properties": {
    "hierarchy": [
      "tgn:2152091",
      "tgn:1000001",
      "tgn:7012149",
      "tgn:1002678",
      "tgn:7007252",
      "tgn:7029392"
    ],
    "placetype": [
      "aat:300008699"
    ],
    "id": 2152091,
    "name:xx": "Baxter Branch"
  }
}
