{
  "geometry": {
    "type": "Point",
    "coordinates": [
      39.1167,
      47.3833
    ]
  },
  "type": "Feature",
  "properties": {
    "hierarchy": [
      "tgn:1121933",
      "tgn:1000004",
      "tgn:1003405",
      "tgn:7018214",
      "tgn:7002435",
      "tgn:7029392"
    ],
    "placetype": [
      "aat:300008707"
    ],
    "id": 1121933,
    "name:xx": "Bir'učja"
  }
}
