{
  "geometry": {
    "type": "Point",
    "coordinates": [
      -87.6833,
      32.6167
    ]
  },
  "type": "Feature",
  "properties": {
    "hierarchy": [
      "tgn:2691936",
      "tgn:7002659",
      "tgn:1000001",
      "tgn:7012149",
      "tgn:2000032",
      "tgn:7029392"
    ],
    "placetype": [
      "aat:300006191"
    ],
    "id": 2691936,
    "name:xx": "State Cattle Ranch Lakes"
  }
}
