{
  "geometry": {
    "type": "Point",
    "coordinates": [
      30.75,
      29.283333
    ]
  },
  "type": "Feature",
  "properties": {
    "hierarchy": [
      "tgn:7529261",
      "tgn:7001242",
      "tgn:7001105",
      "tgn:7016833",
      "tgn:7029392"
    ],
    "placetype": [
      "aat:300005926"
    ],
    "name:en": "Manāmat Sīdī al Murābiţ",
    "id": 7529261
  }
}
