{
  "type": "FeatureCollection",
  "features": [
    {
      "geometry": {
        "type": "Point",
        "coordinates": [
          21.5,
          38.5
        ]
      },
      "type": "Feature",
      "properties": {
        "hierarchy": [
          "tgn:7002680",
          "tgn:7001395",
          "tgn:1000003",
          "tgn:1000074",
          "tgn:7029392"
        ],
        "placetype": [
          "aat:300387145",
          "aat:300000772",
          "aat:300387131"
        ],
        "name:en": "Aetolia and Acarnania regional division",
        "id": 7002680
      }
    },
    {
      "geometry": {
        "type": "Point",
        "coordinates": [
          23.5,
          38.0833
        ]
      },
      "type": "Feature",
      "properties": {
        "hierarchy": [
          "tgn:7002681",
          "tgn:7001395",
          "tgn:1000003",
          "tgn:1000074",
          "tgn:7029392"
        ],
        "placetype": [
          "aat:300387145",
          "aat:300000772",
          "aat:300387131"
        ],
        "name:en": "Attica",
        "id": 7002681
      }
    },
    {
      "geometry": {
        "type": "Point",
        "coordinates": [
          23,
          38.333333
        ]
      },
      "type": "Feature",
      "properties": {
        "hierarchy": [
          "tgn:7002683",
          "tgn:7001395",
          "tgn:1000003",
          "tgn:1000074",
          "tgn:7029392"
        ],
        "placetype": [
          "aat:300387145",
          "aat:300000772",
          "aat:300387131"
        ],
        "name:en": "Boeotia",
        "id": 7002683
      }
    },
    {
      "geometry": {
        "type": "Point",
        "coordinates": [
          22.416667,
          38.833333
        ]
      },
      "type": "Feature",
      "properties": {
        "hierarchy": [
          "tgn:7002684",
          "tgn:7001395",
          "tgn:1000003",
          "tgn:1000074",
          "tgn:7029392"
        ],
        "placetype": [
          "aat:300387145",
          "aat:300000772",
          "aat:300387131"
        ],
        "name:en": "Phthiotis",
        "id": 7002684
      }
    },
    {
      "geometry": {
        "type": "Point",
        "coordinates": [
          24,
          35.3333
        ]
      },
      "type": "Feature",
      "properties": {
        "hierarchy": [
          "tgn:7002689",
          "tgn:7012056",
          "tgn:1000003",
          "tgn:1000074",
          "tgn:7029392"
        ],
        "placetype": [
          "aat:300387145",
          "aat:300000772",
          "aat:300387131"
        ],
        "name:en": "Canea",
        "id": 7002689
      }
    }
  ]
}
