{
  "geometry": {
    "type": "Point",
    "coordinates": [
      -89.1167,
      43.6833
    ]
  },
  "type": "Feature",
  "properties": {
    "hierarchy": [
      "tgn:2121524",
      "tgn:1000001",
      "tgn:2002325",
      "tgn:7012149",
      "tgn:7007922",
      "tgn:7029392"
    ],
    "placetype": [
      "aat:300008347"
    ],
    "id": 2121524,
    "name:xx": "Kingston"
  }
}
