{
  "type": "FeatureCollection",
  "features": [
    {
      "geometry": {
        "type": "Point",
        "coordinates": [
          -3.183333,
          53.35
        ]
      },
      "type": "Feature",
      "properties": {
        "hierarchy": [
          "tgn:7454310",
          "tgn:7002445",
          "tgn:1003666",
          "tgn:1000003",
          "tgn:7029504",
          "tgn:7008591",
          "tgn:7029392"
        ],
        "placetype": [
          "aat:300008699"
        ],
        "name:en": "Dee, River",
        "id": 7454310
      }
    },
    {
      "geometry": {
        "type": "Point",
        "coordinates": [
          -3.55,
          56.983333
        ]
      },
      "type": "Feature",
      "properties": {
        "hierarchy": [
          "tgn:7454312",
          "tgn:5000432",
          "tgn:7002444",
          "tgn:1000003",
          "tgn:7008591",
          "tgn:7029392"
        ],
        "placetype": [
          "aat:300008736"
        ],
        "name:en": "Dee, Linn of",
        "id": 7454312
      }
    },
    {
      "geometry": {
        "type": "Point",
        "coordinates": [
          -3.666667,
          57.033333
        ]
      },
      "type": "Feature",
      "properties": {
        "hierarchy": [
          "tgn:7454313",
          "tgn:5000432",
          "tgn:7002444",
          "tgn:1000003",
          "tgn:7008591",
          "tgn:7029392"
        ],
        "placetype": [
          "aat:300008761"
        ],
        "name:en": "Dee, Glen",
        "id": 7454313
      }
    },
    {
      "geometry": {
        "type": "Point",
        "coordinates": [
          1.283333,
          52.133333
        ]
      },
      "type": "Feature",
      "properties": {
        "hierarchy": [
          "tgn:7454319",
          "tgn:7002445",
          "tgn:1000003",
          "tgn:7008185",
          "tgn:7008591",
          "tgn:7029392"
        ],
        "placetype": [
          "aat:300008347"
        ],
        "name:en": "Debach",
        "id": 7454319
      }
    }
  ]
}
