{
  "geometry": {
    "type": "Point",
    "coordinates": [
      -135.3667,
      56.9667
    ]
  },
  "type": "Feature",
  "properties": {
    "hierarchy": [
      "tgn:2719468",
      "tgn:7006450",
      "tgn:1000001",
      "tgn:7012149",
      "tgn:2124002",
      "tgn:7029392"
    ],
    "placetype": [
      "aat:300132316"
    ],
    "id": 2719468,
    "name:xx": "Three Entrance Bay"
  }
}
