{
  "geometry": {
    "type": "Point",
    "coordinates": [
      -73.95,
      42.55
    ]
  },
  "type": "Feature",
  "properties": {
    "hierarchy": [
      "tgn:2071460",
      "tgn:1002139",
      "tgn:1000001",
      "tgn:7012149",
      "tgn:7007568",
      "tgn:7029392"
    ],
    "placetype": [
      "aat:300008347",
      "aat:300387210"
    ],
    "id": 2071460,
    "name:xx": "Tarrytown"
  }
}
