{
  "type": "FeatureCollection",
  "features": [
    {
      "geometry": {
        "type": "Point",
        "coordinates": [
          -81.4833,
          36.6167
        ]
      },
      "type": "Feature",
      "properties": {
        "hierarchy": [
          "tgn:2171332",
          "tgn:1000001",
          "tgn:7012149",
          "tgn:2002164",
          "tgn:7007919",
          "tgn:7029392"
        ],
        "placetype": [
          "aat:300266640"
        ],
        "id": 2171332,
        "name:xx": "Big Spring Ridge"
      }
    },
    {
      "geometry": {
        "type": "Point",
        "coordinates": [
          -77.65,
          40.25
        ]
      },
      "type": "Feature",
      "properties": {
        "hierarchy": [
          "tgn:2171333",
          "tgn:1000001",
          "tgn:7012149",
          "tgn:1002779",
          "tgn:7007710",
          "tgn:7029392"
        ],
        "placetype": [
          "aat:300008699"
        ],
        "id": 2171333,
        "name:xx": "Big Spring Run"
      }
    },
    {
      "geometry": {
        "type": "Point",
        "coordinates": [
          -76.25,
          39.9667
        ]
      },
      "type": "Feature",
      "properties": {
        "hierarchy": [
          "tgn:2171334",
          "tgn:1000001",
          "tgn:7012149",
          "tgn:7013867",
          "tgn:7007710",
          "tgn:7029392"
        ],
        "placetype": [
          "aat:300008699"
        ],
        "id": 2171334,
        "name:xx": "Big Spring Run"
      }
    },
    {
      "geometry": {
        "type": "Point",
        "coordinates": [
          -76.8,
          40.1667
        ]
      },
      "type": "Feature",
      "properties": {
        "hierarchy": [
          "tgn:2171335",
          "tgn:1000001",
          "tgn:7012149",
          "tgn:1003047",
          "tgn:7007710",
          "tgn:7029392"
        ],
        "placetype": [
          "aat:300008699"
        ],
        "id": 2171335,
        "name:xx": "Big Spring Run"
      }
    },
    {
      "geometry": {
        "type": "Point",
        "coordinates": [
          -78.9667,
          40.3667
        ]
      },
      "type": "Feature",
      "properties": {
        "hierarchy": [
          "tgn:2171336",
          "tgn:1000001",
          "tgn:7012149",
          "tgn:7007710",
          "tgn:7029392"
        ],
        "placetype": [
          "aat:300008699"
        ],
        "id": 2171336,
        "name:xx": "Big Spring Run"
      }
    },
    {
      "geometry": {
        "type": "Point",
        "coordinates": [
          -79.55,
          38.9
        ]
      },
      "type": "Feature",
      "properties": {
        "hierarchy": [
          "tgn:2171337",
          "tgn:1000001",
          "tgn:7012149",
          "tgn:2002291",
          "tgn:7013961",
          "tgn:7029392"
        ],
        "placetype": [
          "aat:300008699"
        ],
        "id": 2171337,
        "name:xx": "Big Spring Run"
      }
    },
    {
      "geometry": {
        "type": "Point",
        "coordinates": [
          -119,
          41.9
        ]
      },
      "type": "Feature",
      "properties": {
        "hierarchy": [
          "tgn:2171339",
          "tgn:1000001",
          "tgn:7012149",
          "tgn:7029392"
        ],
        "placetype": [
          "aat:300008798"
        ],
        "id": 2171339,
        "name:xx": "Big Spring Table"
      }
    }
  ]
}
