{
  "geometry": {
    "type": "Point",
    "coordinates": [
      79.786,
      27.2361
    ]
  },
  "type": "Feature",
  "properties": {
    "hierarchy": [
      "tgn:7561313",
      "tgn:1000004",
      "tgn:7000198",
      "tgn:7016722",
      "tgn:7029392"
    ],
    "placetype": [
      "aat:300008347"
    ],
    "name:en": "Behta Lākhi",
    "id": 7561313
  }
}
