{
  "geometry": {
    "type": "Point",
    "coordinates": [
      -121.8667,
      37.2333
    ]
  },
  "type": "Feature",
  "properties": {
    "hierarchy": [
      "tgn:1124417",
      "tgn:1000001",
      "tgn:7012149",
      "tgn:7007157",
      "tgn:7014475",
      "tgn:7029392"
    ],
    "placetype": [
      "aat:300008707"
    ],
    "id": 1124417,
    "name:xx": "Guadalupe"
  }
}
