{
  "geometry": {
    "type": "Point",
    "coordinates": [
      -82.5333,
      28.0833
    ]
  },
  "type": "Feature",
  "properties": {
    "hierarchy": [
      "tgn:2372151",
      "tgn:1000001",
      "tgn:1002479",
      "tgn:7012149",
      "tgn:7007240",
      "tgn:7029392"
    ],
    "placetype": [
      "aat:300008680"
    ],
    "id": 2372151,
    "name:xx": "Halfmoon Lake"
  }
}
