{
  "type": "FeatureCollection",
  "features": [
    {
      "geometry": {
        "type": "Point",
        "coordinates": [
          -124.5833,
          42.7833
        ]
      },
      "type": "Feature",
      "properties": {
        "hierarchy": [
          "tgn:2650230",
          "tgn:1000001",
          "tgn:2001704",
          "tgn:7012149",
          "tgn:7007708",
          "tgn:7029392"
        ],
        "placetype": [
          "aat:300008791"
        ],
        "id": 2650230,
        "name:xx": "Seal Rock"
      }
    },
    {
      "geometry": {
        "type": "Point",
        "coordinates": [
          -123.9833,
          45.45
        ]
      },
      "type": "Feature",
      "properties": {
        "hierarchy": [
          "tgn:2650231",
          "tgn:1000001",
          "tgn:7012149",
          "tgn:1002943",
          "tgn:7007708",
          "tgn:7029392"
        ],
        "placetype": [
          "aat:300008791"
        ],
        "id": 2650231,
        "name:xx": "Seal Rock"
      }
    },
    {
      "geometry": {
        "type": "Point",
        "coordinates": [
          -122.8833,
          47.7
        ]
      },
      "type": "Feature",
      "properties": {
        "hierarchy": [
          "tgn:2650232",
          "tgn:1000001",
          "tgn:7012149",
          "tgn:1002521",
          "tgn:7007920",
          "tgn:7029392"
        ],
        "placetype": [
          "aat:300008347"
        ],
        "id": 2650232,
        "name:xx": "Seal Rock"
      }
    },
    {
      "geometry": {
        "type": "Point",
        "coordinates": [
          -121.9167,
          36.5667
        ]
      },
      "type": "Feature",
      "properties": {
        "hierarchy": [
          "tgn:2650233",
          "tgn:1000001",
          "tgn:7012149",
          "tgn:7007157",
          "tgn:1002684",
          "tgn:7029392"
        ],
        "placetype": [
          "aat:300008706"
        ],
        "id": 2650233,
        "name:xx": "Seal Rock Creek"
      }
    },
    {
      "geometry": {
        "type": "Point",
        "coordinates": [
          -130.0833,
          55.8167
        ]
      },
      "type": "Feature",
      "properties": {
        "hierarchy": [
          "tgn:2650234",
          "tgn:7006450",
          "tgn:1000001",
          "tgn:7012149",
          "tgn:2000082",
          "tgn:7029392"
        ],
        "placetype": [
          "aat:300055621"
        ],
        "id": 2650234,
        "name:xx": "Seal Rocks"
      }
    },
    {
      "geometry": {
        "type": "Point",
        "coordinates": [
          -146.8167,
          60.15
        ]
      },
      "type": "Feature",
      "properties": {
        "hierarchy": [
          "tgn:2650235",
          "tgn:7006450",
          "tgn:1000001",
          "tgn:7012149",
          "tgn:2000086",
          "tgn:7029392"
        ],
        "placetype": [
          "aat:300132348"
        ],
        "id": 2650235,
        "name:xx": "Seal Rocks"
      }
    },
    {
      "geometry": {
        "type": "Point",
        "coordinates": [
          -149.6167,
          59.5167
        ]
      },
      "type": "Feature",
      "properties": {
        "hierarchy": [
          "tgn:2650236",
          "tgn:7006450",
          "tgn:1000001",
          "tgn:7019698",
          "tgn:7012149",
          "tgn:7029392"
        ],
        "placetype": [
          "aat:300008791"
        ],
        "id": 2650236,
        "name:xx": "Seal Rocks"
      }
    },
    {
      "geometry": {
        "type": "Point",
        "coordinates": [
          -146.8333,
          60.15
        ]
      },
      "type": "Feature",
      "properties": {
        "hierarchy": [
          "tgn:2650237",
          "tgn:7006450",
          "tgn:1000001",
          "tgn:7012149",
          "tgn:2000086",
          "tgn:7029392"
        ],
        "placetype": [
          "aat:300008791"
        ],
        "id": 2650237,
        "name:xx": "Seal Rocks"
      }
    },
    {
      "geometry": {
        "type": "Point",
        "coordinates": [
          -123.9167,
          39.9
        ]
      },
      "type": "Feature",
      "properties": {
        "hierarchy": [
          "tgn:2650238",
          "tgn:1000001",
          "tgn:7012149",
          "tgn:7007157",
          "tgn:2000185",
          "tgn:7029392"
        ],
        "placetype": [
          "aat:300008791"
        ],
        "id": 2650238,
        "name:xx": "Seal Rocks"
      }
    },
    {
      "geometry": {
        "type": "Point",
        "coordinates": [
          -122.5,
          37.7667
        ]
      },
      "type": "Feature",
      "properties": {
        "hierarchy": [
          "tgn:2650239",
          "tgn:1000001",
          "tgn:7012149",
          "tgn:7007157",
          "tgn:1002859",
          "tgn:7029392"
        ],
        "placetype": [
          "aat:300008791"
        ],
        "id": 2650239,
        "name:xx": "Seal Rocks"
      }
    }
  ]
}
