{
  "geometry": {
    "type": "Point",
    "coordinates": [
      3.7833,
      49.75
    ]
  },
  "type": "Feature",
  "properties": {
    "hierarchy": [
      "tgn:1122251",
      "tgn:1000003",
      "tgn:7002890",
      "tgn:1000070",
      "tgn:7029392"
    ],
    "placetype": [
      "aat:300008707"
    ],
    "id": 1122251,
    "name:xx": "Brune"
  }
}
