{
  "geometry": {
    "type": "Point",
    "coordinates": [
      -83.2833,
      39.95
    ]
  },
  "type": "Feature",
  "properties": {
    "hierarchy": [
      "tgn:2334560",
      "tgn:1000001",
      "tgn:7012149",
      "tgn:1002625",
      "tgn:7007706",
      "tgn:7029392"
    ],
    "placetype": [
      "aat:300008680"
    ],
    "id": 2334560,
    "name:xx": "Forest, Lake"
  }
}
