{
  "geometry": {
    "type": "Point",
    "coordinates": [
      -145.2167,
      68.1667
    ]
  },
  "type": "Feature",
  "properties": {
    "hierarchy": [
      "tgn:2612735",
      "tgn:7006450",
      "tgn:1000001",
      "tgn:7012149",
      "tgn:2000089",
      "tgn:7029392"
    ],
    "placetype": [
      "aat:300008680"
    ],
    "id": 2612735,
    "name:xx": "Redfish Lake"
  }
}
