{
  "geometry": {
    "type": "Point",
    "coordinates": [
      -76.5167,
      34.75
    ]
  },
  "type": "Feature",
  "properties": {
    "hierarchy": [
      "tgn:2076678",
      "tgn:1000001",
      "tgn:2001477",
      "tgn:7012149",
      "tgn:7007709",
      "tgn:7029392"
    ],
    "placetype": [
      "aat:300008347"
    ],
    "id": 2076678,
    "name:xx": "Smyrna"
  }
}
