{
  "geometry": {
    "type": "Point",
    "coordinates": [
      -58.15,
      -32.15
    ]
  },
  "type": "Feature",
  "properties": {
    "hierarchy": [
      "tgn:1128920",
      "tgn:7002641",
      "tgn:1000002",
      "tgn:1000058",
      "tgn:7029392"
    ],
    "placetype": [
      "aat:300008707"
    ],
    "id": 1128920,
    "name:xx": "Río Queguay Grande"
  }
}
