{
  "geometry": {
    "type": "Point",
    "coordinates": [
      -111.9333,
      41.0833
    ]
  },
  "type": "Feature",
  "properties": {
    "hierarchy": [
      "tgn:2232612",
      "tgn:1000001",
      "tgn:2002106",
      "tgn:7012149",
      "tgn:7007827",
      "tgn:7029392"
    ],
    "placetype": [
      "aat:300008347"
    ],
    "id": 2232612,
    "name:xx": "Chapel Hill"
  }
}
