{
  "geometry": {
    "type": "Point",
    "coordinates": [
      75.319693,
      31.85135
    ]
  },
  "type": "Feature",
  "properties": {
    "hierarchy": [
      "tgn:7556600",
      "tgn:1000004",
      "tgn:7000198",
      "tgn:7016883",
      "tgn:7029392"
    ],
    "placetype": [
      "aat:300008347"
    ],
    "name:en": "Sekhwān",
    "id": 7556600
  }
}
