{
  "geometry": {
    "type": "Point",
    "coordinates": [
      -92.9333,
      32.1833
    ]
  },
  "type": "Feature",
  "properties": {
    "hierarchy": [
      "tgn:2222242",
      "tgn:1000001",
      "tgn:2000860",
      "tgn:7012149",
      "tgn:7007256",
      "tgn:7029392"
    ],
    "placetype": [
      "aat:300008347"
    ],
    "id": 2222242,
    "name:xx": "Carolina"
  }
}
