{
  "geometry": {
    "type": "Point",
    "coordinates": [
      30.991944,
      29.3925
    ]
  },
  "type": "Feature",
  "properties": {
    "hierarchy": [
      "tgn:7538049",
      "tgn:7001242",
      "tgn:7001105",
      "tgn:7016833",
      "tgn:7029392"
    ],
    "placetype": [
      "aat:300387086"
    ],
    "name:en": "Rawḑah, Baḩr ar",
    "id": 7538049
  }
}
