{
  "geometry": {
    "type": "Point",
    "coordinates": [
      61.4333,
      32.1333
    ]
  },
  "type": "Feature",
  "properties": {
    "hierarchy": [
      "tgn:1065497",
      "tgn:7016612",
      "tgn:1000004",
      "tgn:1001249",
      "tgn:7029392"
    ],
    "placetype": [
      "aat:300008347"
    ],
    "id": 1065497,
    "name:xx": "Do Qaleh"
  }
}
