{
  "geometry": {
    "type": "Point",
    "coordinates": [
      -113.0333,
      46.0333
    ]
  },
  "type": "Feature",
  "properties": {
    "hierarchy": [
      "tgn:2666407",
      "tgn:1000001",
      "tgn:7012149",
      "tgn:7020792",
      "tgn:7007524",
      "tgn:7029392"
    ],
    "placetype": [
      "aat:300008706"
    ],
    "id": 2666407,
    "name:xx": "Sixmile Creek"
  }
}
