{
  "geometry": {
    "type": "Point",
    "coordinates": [
      -85.4167,
      32.9833
    ]
  },
  "type": "Feature",
  "properties": {
    "hierarchy": [
      "tgn:2003060",
      "tgn:7002659",
      "tgn:1000001",
      "tgn:2000008",
      "tgn:7012149",
      "tgn:7029392"
    ],
    "placetype": [
      "aat:300008347",
      "aat:300387210"
    ],
    "id": 2003060,
    "name:xx": "Chapel Hill"
  }
}
