{
  "geometry": {
    "type": "Point",
    "coordinates": [
      -83.1833,
      34.4333
    ]
  },
  "type": "Feature",
  "properties": {
    "hierarchy": [
      "tgn:2615176",
      "tgn:1000001",
      "tgn:7012149",
      "tgn:2000350",
      "tgn:7007248",
      "tgn:7029392"
    ],
    "placetype": [
      "aat:300006191"
    ],
    "id": 2615176,
    "name:xx": "Reservoir 33"
  }
}
