{
  "geometry": {
    "type": "Point",
    "coordinates": [
      -109.7167,
      46.3167
    ]
  },
  "type": "Feature",
  "properties": {
    "hierarchy": [
      "tgn:2721784",
      "tgn:1000001",
      "tgn:7012149",
      "tgn:2001313",
      "tgn:7007524",
      "tgn:7029392"
    ],
    "placetype": [
      "aat:300008706"
    ],
    "id": 2721784,
    "name:xx": "Timber Creek"
  }
}
