{
  "geometry": {
    "type": "Point",
    "coordinates": [
      17.95,
      -3.7833
    ]
  },
  "type": "Feature",
  "properties": {
    "hierarchy": [
      "tgn:1088771",
      "tgn:1001143",
      "tgn:7001242",
      "tgn:1000159",
      "tgn:7029392"
    ],
    "placetype": [
      "aat:300008347"
    ],
    "id": 1088771,
    "name:xx": "Bagata"
  }
}
