{
  "geometry": {
    "type": "Point",
    "coordinates": [
      7.1667,
      4.3333
    ]
  },
  "type": "Feature",
  "properties": {
    "hierarchy": [
      "tgn:1135757",
      "tgn:7001242",
      "tgn:1001943",
      "tgn:1000182",
      "tgn:7029392"
    ],
    "placetype": [
      "aat:300387055"
    ],
    "id": 1135757,
    "name:xx": "Bonny"
  }
}
