{
  "geometry": {
    "type": "Point",
    "coordinates": [
      -87.1333,
      31.9333
    ]
  },
  "type": "Feature",
  "properties": {
    "hierarchy": [
      "tgn:2005149",
      "tgn:7002659",
      "tgn:1000001",
      "tgn:7012149",
      "tgn:2000065",
      "tgn:7029392"
    ],
    "placetype": [
      "aat:300008347"
    ],
    "id": 2005149,
    "name:xx": "Rosebud"
  }
}
