{
  "type": "FeatureCollection",
  "features": [
    {
      "geometry": {
        "type": "Point",
        "coordinates": [
          -2.633333,
          41.066667
        ]
      },
      "type": "Feature",
      "properties": {
        "hierarchy": [
          "tgn:7008680",
          "tgn:7002822",
          "tgn:1001647",
          "tgn:1000003",
          "tgn:1000095",
          "tgn:7029392"
        ],
        "placetype": [
          "aat:300008347"
        ],
        "id": 7008680,
        "name:xx": "Sigüenza"
      }
    },
    {
      "geometry": {
        "type": "Point",
        "coordinates": [
          -4.688611,
          51.635833
        ]
      },
      "type": "Feature",
      "properties": {
        "hierarchy": [
          "tgn:7008683",
          "tgn:7002443",
          "tgn:1000003",
          "tgn:7018993",
          "tgn:7008591",
          "tgn:7029392"
        ],
        "placetype": [
          "aat:300008791"
        ],
        "name:en": "Caldey Island",
        "id": 7008683
      }
    },
    {
      "geometry": {
        "type": "Point",
        "coordinates": [
          -0.1,
          41.666667
        ]
      },
      "type": "Feature",
      "properties": {
        "hierarchy": [
          "tgn:7008685",
          "tgn:7002759",
          "tgn:7008909",
          "tgn:1000003",
          "tgn:1000095",
          "tgn:7029392"
        ],
        "placetype": [
          "aat:300266640"
        ],
        "id": 7008685,
        "name:xx": "Sigena, Sierra de"
      }
    }
  ]
}
