{
  "geometry": {
    "type": "Point",
    "coordinates": [
      -79.3667,
      39.5167
    ]
  },
  "type": "Feature",
  "properties": {
    "hierarchy": [
      "tgn:2200340",
      "tgn:1000001",
      "tgn:2000935",
      "tgn:7012149",
      "tgn:7007516",
      "tgn:7029392"
    ],
    "placetype": [
      "aat:300008761"
    ],
    "id": 2200340,
    "name:xx": "Brushy Hollow"
  }
}
