{
  "type": "FeatureCollection",
  "features": [
    {
      "geometry": {
        "type": "Point",
        "coordinates": [
          -97.05,
          39.8333
        ]
      },
      "type": "Feature",
      "properties": {
        "hierarchy": [
          "tgn:2588280",
          "tgn:1000001",
          "tgn:7012149",
          "tgn:2000760",
          "tgn:7007254",
          "tgn:7029392"
        ],
        "placetype": [
          "aat:300008706"
        ],
        "id": 2588280,
        "name:xx": "Plum Creek"
      }
    },
    {
      "geometry": {
        "type": "Point",
        "coordinates": [
          -95.7667,
          39.8
        ]
      },
      "type": "Feature",
      "properties": {
        "hierarchy": [
          "tgn:2588281",
          "tgn:1000001",
          "tgn:2000666",
          "tgn:7012149",
          "tgn:7007254",
          "tgn:7029392"
        ],
        "placetype": [
          "aat:300008706"
        ],
        "id": 2588281,
        "name:xx": "Plum Creek"
      }
    },
    {
      "geometry": {
        "type": "Point",
        "coordinates": [
          -97.5833,
          39.5
        ]
      },
      "type": "Feature",
      "properties": {
        "hierarchy": [
          "tgn:2588282",
          "tgn:1000001",
          "tgn:2000674",
          "tgn:7012149",
          "tgn:7007254",
          "tgn:7029392"
        ],
        "placetype": [
          "aat:300008706"
        ],
        "id": 2588282,
        "name:xx": "Plum Creek"
      }
    },
    {
      "geometry": {
        "type": "Point",
        "coordinates": [
          -95.5833,
          37.9333
        ]
      },
      "type": "Feature",
      "properties": {
        "hierarchy": [
          "tgn:2588283",
          "tgn:1000001",
          "tgn:7012149",
          "tgn:2000763",
          "tgn:7007254",
          "tgn:7029392"
        ],
        "placetype": [
          "aat:300008706"
        ],
        "id": 2588283,
        "name:xx": "Plum Creek"
      }
    },
    {
      "geometry": {
        "type": "Point",
        "coordinates": [
          -96.2667,
          37.65
        ]
      },
      "type": "Feature",
      "properties": {
        "hierarchy": [
          "tgn:2588284",
          "tgn:1000001",
          "tgn:2000696",
          "tgn:7012149",
          "tgn:7007254",
          "tgn:7029392"
        ],
        "placetype": [
          "aat:300008706"
        ],
        "id": 2588284,
        "name:xx": "Plum Creek"
      }
    },
    {
      "geometry": {
        "type": "Point",
        "coordinates": [
          -96.6333,
          37.5833
        ]
      },
      "type": "Feature",
      "properties": {
        "hierarchy": [
          "tgn:2588285",
          "tgn:1000001",
          "tgn:2000667",
          "tgn:7012149",
          "tgn:7007254",
          "tgn:7029392"
        ],
        "placetype": [
          "aat:300008706"
        ],
        "id": 2588285,
        "name:xx": "Plum Creek"
      }
    },
    {
      "geometry": {
        "type": "Point",
        "coordinates": [
          -96.4333,
          39.2167
        ]
      },
      "type": "Feature",
      "properties": {
        "hierarchy": [
          "tgn:2588286",
          "tgn:1000001",
          "tgn:7012149",
          "tgn:2000734",
          "tgn:7007254",
          "tgn:7029392"
        ],
        "placetype": [
          "aat:300008706"
        ],
        "id": 2588286,
        "name:xx": "Plum Creek"
      }
    },
    {
      "geometry": {
        "type": "Point",
        "coordinates": [
          -95.95,
          38.4167
        ]
      },
      "type": "Feature",
      "properties": {
        "hierarchy": [
          "tgn:2588287",
          "tgn:1000001",
          "tgn:7012149",
          "tgn:2000715",
          "tgn:7007254",
          "tgn:7029392"
        ],
        "placetype": [
          "aat:300008706"
        ],
        "id": 2588287,
        "name:xx": "Plum Creek"
      }
    },
    {
      "geometry": {
        "type": "Point",
        "coordinates": [
          -95.05,
          39.4
        ]
      },
      "type": "Feature",
      "properties": {
        "hierarchy": [
          "tgn:2588288",
          "tgn:1000001",
          "tgn:7012149",
          "tgn:2000711",
          "tgn:7007254",
          "tgn:7029392"
        ],
        "placetype": [
          "aat:300008706"
        ],
        "id": 2588288,
        "name:xx": "Plum Creek"
      }
    },
    {
      "geometry": {
        "type": "Point",
        "coordinates": [
          -95.25,
          39.15
        ]
      },
      "type": "Feature",
      "properties": {
        "hierarchy": [
          "tgn:2588289",
          "tgn:1000001",
          "tgn:2000703",
          "tgn:7012149",
          "tgn:7007254",
          "tgn:7029392"
        ],
        "placetype": [
          "aat:300008706"
        ],
        "id": 2588289,
        "name:xx": "Plum Creek"
      }
    }
  ]
}
