{
  "geometry": {
    "type": "Point",
    "coordinates": [
      -121.5333,
      39.8167
    ]
  },
  "type": "Feature",
  "properties": {
    "hierarchy": [
      "tgn:2608287",
      "tgn:1000001",
      "tgn:1002218",
      "tgn:7012149",
      "tgn:7007157",
      "tgn:7029392"
    ],
    "placetype": [
      "aat:300008706"
    ],
    "id": 2608287,
    "name:xx": "Rattlesnake Creek"
  }
}
