{
  "type": "FeatureCollection",
  "features": [
    {
      "geometry": {
        "type": "Point",
        "coordinates": [
          -69.05,
          -22.8
        ]
      },
      "type": "Feature",
      "properties": {
        "hierarchy": [
          "tgn:7289570",
          "tgn:7016598",
          "tgn:1000049",
          "tgn:1000002",
          "tgn:7029392"
        ],
        "placetype": [
          "aat:300387033"
        ],
        "id": 7289570,
        "name:xx": "Esperanza"
      }
    },
    {
      "geometry": {
        "type": "Point",
        "coordinates": [
          -71.5,
          -35.6
        ]
      },
      "type": "Feature",
      "properties": {
        "hierarchy": [
          "tgn:7289571",
          "tgn:1001705",
          "tgn:1000049",
          "tgn:1000002",
          "tgn:7029392"
        ],
        "placetype": [
          "aat:300008347"
        ],
        "id": 7289571,
        "name:xx": "Esperanza"
      }
    },
    {
      "geometry": {
        "type": "Point",
        "coordinates": [
          -70.783333,
          -34.2
        ]
      },
      "type": "Feature",
      "properties": {
        "hierarchy": [
          "tgn:7289572",
          "tgn:1001695",
          "tgn:1000049",
          "tgn:1000002",
          "tgn:7029392"
        ],
        "placetype": [
          "aat:300387200"
        ],
        "id": 7289572,
        "name:xx": "Esperanza"
      }
    },
    {
      "geometry": {
        "type": "Point",
        "coordinates": [
          -73.766667,
          -41.133333
        ]
      },
      "type": "Feature",
      "properties": {
        "hierarchy": [
          "tgn:7289573",
          "tgn:1001699",
          "tgn:1000049",
          "tgn:1000002",
          "tgn:7029392"
        ],
        "placetype": [
          "aat:300000206"
        ],
        "id": 7289573,
        "name:xx": "Esperanza"
      }
    },
    {
      "geometry": {
        "type": "Point",
        "coordinates": [
          -72.133333,
          -38.75
        ]
      },
      "type": "Feature",
      "properties": {
        "hierarchy": [
          "tgn:7289574",
          "tgn:1001692",
          "tgn:1000049",
          "tgn:1000002",
          "tgn:7029392"
        ],
        "placetype": [
          "aat:300000206"
        ],
        "id": 7289574,
        "name:xx": "Esperanza"
      }
    },
    {
      "geometry": {
        "type": "Point",
        "coordinates": [
          -73.666667,
          -37.616667
        ]
      },
      "type": "Feature",
      "properties": {
        "hierarchy": [
          "tgn:7289575",
          "tgn:1001637",
          "tgn:1000049",
          "tgn:1000002",
          "tgn:7029392"
        ],
        "placetype": [
          "aat:300000206"
        ],
        "id": 7289575,
        "name:xx": "Esperanza"
      }
    },
    {
      "geometry": {
        "type": "Point",
        "coordinates": [
          -71.766667,
          -36.766667
        ]
      },
      "type": "Feature",
      "properties": {
        "hierarchy": [
          "tgn:7289576",
          "tgn:1001637",
          "tgn:1000049",
          "tgn:1000002",
          "tgn:7029392"
        ],
        "placetype": [
          "aat:300000206"
        ],
        "id": 7289576,
        "name:xx": "Esperanza"
      }
    },
    {
      "geometry": {
        "type": "Point",
        "coordinates": [
          -71.666667,
          -34.45
        ]
      },
      "type": "Feature",
      "properties": {
        "hierarchy": [
          "tgn:7289577",
          "tgn:1001695",
          "tgn:1000049",
          "tgn:1000002",
          "tgn:7029392"
        ],
        "placetype": [
          "aat:300004792"
        ],
        "id": 7289577,
        "name:xx": "Esperanza"
      }
    },
    {
      "geometry": {
        "type": "Point",
        "coordinates": [
          -73.283333,
          -47.95
        ]
      },
      "type": "Feature",
      "properties": {
        "hierarchy": [
          "tgn:7289578",
          "tgn:1001623",
          "tgn:1000049",
          "tgn:1000002",
          "tgn:7029392"
        ],
        "placetype": [
          "aat:300386846"
        ],
        "id": 7289578,
        "name:xx": "Espejo, Punta"
      }
    },
    {
      "geometry": {
        "type": "Point",
        "coordinates": [
          -74.983333,
          -49.55
        ]
      },
      "type": "Feature",
      "properties": {
        "hierarchy": [
          "tgn:7289579",
          "tgn:1001702",
          "tgn:1000049",
          "tgn:1000002",
          "tgn:7029392"
        ],
        "placetype": [
          "aat:300008676"
        ],
        "id": 7289579,
        "name:xx": "Espejo, Fiordo"
      }
    }
  ]
}
