{
  "geometry": {
    "type": "Point",
    "coordinates": [
      -116.5833,
      38.8333
    ]
  },
  "type": "Feature",
  "properties": {
    "hierarchy": [
      "tgn:2524171",
      "tgn:1000001",
      "tgn:2001418",
      "tgn:7012149",
      "tgn:7007526",
      "tgn:7029392"
    ],
    "placetype": [
      "aat:300008706"
    ],
    "id": 2524171,
    "name:xx": "Morgan Creek"
  }
}
