{
  "geometry": {
    "type": "Point",
    "coordinates": [
      -102.7667,
      33.9333
    ]
  },
  "type": "Feature",
  "properties": {
    "hierarchy": [
      "tgn:2474983",
      "tgn:1000001",
      "tgn:2001937",
      "tgn:7012149",
      "tgn:7007826",
      "tgn:7029392"
    ],
    "placetype": [
      "aat:300006191"
    ],
    "id": 2474983,
    "name:xx": "Lower White Lake"
  }
}
