{
  "geometry": {
    "type": "Point",
    "coordinates": [
      -108.55,
      40.3167
    ]
  },
  "type": "Feature",
  "properties": {
    "hierarchy": [
      "tgn:2490236",
      "tgn:1000001",
      "tgn:7012149",
      "tgn:2000232",
      "tgn:7007158",
      "tgn:7029392"
    ],
    "placetype": [
      "aat:300006191"
    ],
    "id": 2490236,
    "name:xx": "Mancos Reservoir Number 3"
  }
}
