{
  "geometry": {
    "type": "Point",
    "coordinates": [
      -94.7833,
      40.5167
    ]
  },
  "type": "Feature",
  "properties": {
    "hierarchy": [
      "tgn:2668811",
      "tgn:1000001",
      "tgn:7012149",
      "tgn:2001224",
      "tgn:7007523",
      "tgn:7029392"
    ],
    "placetype": [
      "aat:300008699"
    ],
    "id": 2668811,
    "name:xx": "Slaughter Branch"
  }
}
