{
  "geometry": {
    "type": "Point",
    "coordinates": [
      -117.0667,
      46.95
    ]
  },
  "type": "Feature",
  "properties": {
    "hierarchy": [
      "tgn:2366787",
      "tgn:1000001",
      "tgn:7012149",
      "tgn:2002252",
      "tgn:7007920",
      "tgn:7029392"
    ],
    "placetype": [
      "aat:300008347"
    ],
    "id": 2366787,
    "name:xx": "Grinnell"
  }
}
