{
  "geometry": {
    "type": "Point",
    "coordinates": [
      -149.8833,
      62.6167
    ]
  },
  "type": "Feature",
  "properties": {
    "hierarchy": [
      "tgn:2279170",
      "tgn:7006450",
      "tgn:1000001",
      "tgn:2124053",
      "tgn:7012149",
      "tgn:7029392"
    ],
    "placetype": [
      "aat:300008706"
    ],
    "id": 2279170,
    "name:xx": "Deadhorse Creek"
  }
}
