{
  "geometry": {
    "type": "Point",
    "coordinates": [
      -90.55,
      16.4667
    ]
  },
  "type": "Feature",
  "properties": {
    "hierarchy": [
      "tgn:1129447",
      "tgn:1000001",
      "tgn:7029392"
    ],
    "placetype": [
      "aat:300008707"
    ],
    "id": 1129447,
    "name:xx": "Salinas"
  }
}
