{
  "geometry": {
    "type": "Point",
    "coordinates": [
      -73.65,
      -52.35
    ]
  },
  "type": "Feature",
  "properties": {
    "hierarchy": [
      "tgn:7318826",
      "tgn:1001702",
      "tgn:1000049",
      "tgn:1000002",
      "tgn:7029392"
    ],
    "placetype": [
      "aat:300011692"
    ],
    "id": 7318826,
    "name:xx": "Barrie, Roca"
  }
}
