{
  "geometry": {
    "type": "Point",
    "coordinates": [
      79.646875,
      26.891285
    ]
  },
  "type": "Feature",
  "properties": {
    "hierarchy": [
      "tgn:7565136",
      "tgn:1000004",
      "tgn:7000198",
      "tgn:7016722",
      "tgn:7029392"
    ],
    "placetype": [
      "aat:300008347"
    ],
    "name:en": "Kaliānpur",
    "id": 7565136
  }
}
