{
  "type": "FeatureCollection",
  "features": [
    {
      "geometry": {
        "type": "Point",
        "coordinates": [
          -105.3167,
          36.2667
        ]
      },
      "type": "Feature",
      "properties": {
        "hierarchy": [
          "tgn:2205330",
          "tgn:1000001",
          "tgn:7012149",
          "tgn:7007566",
          "tgn:7029392"
        ],
        "placetype": [
          "aat:300008761"
        ],
        "id": 2205330,
        "name:xx": "Bull Canyon"
      }
    },
    {
      "geometry": {
        "type": "Point",
        "coordinates": [
          -119.7,
          44.6333
        ]
      },
      "type": "Feature",
      "properties": {
        "hierarchy": [
          "tgn:2205331",
          "tgn:1000001",
          "tgn:7012149",
          "tgn:7007708",
          "tgn:7029392"
        ],
        "placetype": [
          "aat:300008761"
        ],
        "id": 2205331,
        "name:xx": "Bull Canyon"
      }
    },
    {
      "geometry": {
        "type": "Point",
        "coordinates": [
          -120.15,
          44.8167
        ]
      },
      "type": "Feature",
      "properties": {
        "hierarchy": [
          "tgn:2205332",
          "tgn:1000001",
          "tgn:7012149",
          "tgn:2001723",
          "tgn:7007708",
          "tgn:7029392"
        ],
        "placetype": [
          "aat:300008761"
        ],
        "id": 2205332,
        "name:xx": "Bull Canyon"
      }
    },
    {
      "geometry": {
        "type": "Point",
        "coordinates": [
          -120.95,
          44.8333
        ]
      },
      "type": "Feature",
      "properties": {
        "hierarchy": [
          "tgn:2205333",
          "tgn:1000001",
          "tgn:7012149",
          "tgn:1002990",
          "tgn:7007708",
          "tgn:7029392"
        ],
        "placetype": [
          "aat:300008761"
        ],
        "id": 2205333,
        "name:xx": "Bull Canyon"
      }
    },
    {
      "geometry": {
        "type": "Point",
        "coordinates": [
          -120.55,
          45.4167
        ]
      },
      "type": "Feature",
      "properties": {
        "hierarchy": [
          "tgn:2205334",
          "tgn:1000001",
          "tgn:7012149",
          "tgn:1002891",
          "tgn:7007708",
          "tgn:7029392"
        ],
        "placetype": [
          "aat:300008761"
        ],
        "id": 2205334,
        "name:xx": "Bull Canyon"
      }
    },
    {
      "geometry": {
        "type": "Point",
        "coordinates": [
          -118.0833,
          45.45
        ]
      },
      "type": "Feature",
      "properties": {
        "hierarchy": [
          "tgn:2205335",
          "tgn:1000001",
          "tgn:7012149",
          "tgn:2001721",
          "tgn:7007708",
          "tgn:7029392"
        ],
        "placetype": [
          "aat:300008761"
        ],
        "id": 2205335,
        "name:xx": "Bull Canyon"
      }
    },
    {
      "geometry": {
        "type": "Point",
        "coordinates": [
          -117.9667,
          43.6667
        ]
      },
      "type": "Feature",
      "properties": {
        "hierarchy": [
          "tgn:2205336",
          "tgn:1000001",
          "tgn:7012149",
          "tgn:2001718",
          "tgn:7007708",
          "tgn:7029392"
        ],
        "placetype": [
          "aat:300008761"
        ],
        "id": 2205336,
        "name:xx": "Bull Canyon"
      }
    },
    {
      "geometry": {
        "type": "Point",
        "coordinates": [
          -123.9833,
          43.85
        ]
      },
      "type": "Feature",
      "properties": {
        "hierarchy": [
          "tgn:2205337",
          "tgn:1000001",
          "tgn:7012149",
          "tgn:2001716",
          "tgn:7007708",
          "tgn:7029392"
        ],
        "placetype": [
          "aat:300008761"
        ],
        "id": 2205337,
        "name:xx": "Bull Canyon"
      }
    },
    {
      "geometry": {
        "type": "Point",
        "coordinates": [
          -103.7167,
          30.6667
        ]
      },
      "type": "Feature",
      "properties": {
        "hierarchy": [
          "tgn:2205338",
          "tgn:1000001",
          "tgn:7012149",
          "tgn:2002010",
          "tgn:7007826",
          "tgn:7029392"
        ],
        "placetype": [
          "aat:300008761"
        ],
        "id": 2205338,
        "name:xx": "Bull Canyon"
      }
    },
    {
      "geometry": {
        "type": "Point",
        "coordinates": [
          -100.0833,
          33.75
        ]
      },
      "type": "Feature",
      "properties": {
        "hierarchy": [
          "tgn:2205339",
          "tgn:1000001",
          "tgn:7012149",
          "tgn:2002020",
          "tgn:7007826",
          "tgn:7029392"
        ],
        "placetype": [
          "aat:300008761"
        ],
        "id": 2205339,
        "name:xx": "Bull Canyon"
      }
    }
  ]
}
