{
  "type": "FeatureCollection",
  "features": [
    {
      "geometry": {
        "type": "Point",
        "coordinates": [
          -106.533333,
          28.6
        ]
      },
      "type": "Feature",
      "properties": {
        "hierarchy": [
          "tgn:7380370",
          "tgn:7005581",
          "tgn:1000001",
          "tgn:7005560",
          "tgn:7029392"
        ],
        "placetype": [
          "aat:300008347"
        ],
        "id": 7380370,
        "name:xx": "Los Hornitos"
      }
    },
    {
      "geometry": {
        "type": "Point",
        "coordinates": [
          -108.783333,
          27.85
        ]
      },
      "type": "Feature",
      "properties": {
        "hierarchy": [
          "tgn:7380371",
          "tgn:7005581",
          "tgn:1000001",
          "tgn:7005560",
          "tgn:7029392"
        ],
        "placetype": [
          "aat:300008347"
        ],
        "id": 7380371,
        "name:xx": "Los Hornitos"
      }
    },
    {
      "geometry": {
        "type": "Point",
        "coordinates": [
          -108.483333,
          27.566667
        ]
      },
      "type": "Feature",
      "properties": {
        "hierarchy": [
          "tgn:7380372",
          "tgn:7005581",
          "tgn:1000001",
          "tgn:7005560",
          "tgn:7029392"
        ],
        "placetype": [
          "aat:300008347"
        ],
        "id": 7380372,
        "name:xx": "Los Hornitos"
      }
    },
    {
      "geometry": {
        "type": "Point",
        "coordinates": [
          -104.183333,
          20.733333
        ]
      },
      "type": "Feature",
      "properties": {
        "hierarchy": [
          "tgn:7380373",
          "tgn:7005586",
          "tgn:1000001",
          "tgn:7005560",
          "tgn:7029392"
        ],
        "placetype": [
          "aat:300008347"
        ],
        "id": 7380373,
        "name:xx": "Los Hornitos"
      }
    },
    {
      "geometry": {
        "type": "Point",
        "coordinates": [
          -108.508611,
          26.474444
        ]
      },
      "type": "Feature",
      "properties": {
        "hierarchy": [
          "tgn:7380374",
          "tgn:1000001",
          "tgn:7005595",
          "tgn:7005560",
          "tgn:7029392"
        ],
        "placetype": [
          "aat:300008347"
        ],
        "id": 7380374,
        "name:xx": "Los Hornillos"
      }
    },
    {
      "geometry": {
        "type": "Point",
        "coordinates": [
          -109.283333,
          28.116667
        ]
      },
      "type": "Feature",
      "properties": {
        "hierarchy": [
          "tgn:7380375",
          "tgn:1000001",
          "tgn:1001960",
          "tgn:7005560",
          "tgn:7029392"
        ],
        "placetype": [
          "aat:300000241"
        ],
        "id": 7380375,
        "name:xx": "Rancho Los Horcores"
      }
    },
    {
      "geometry": {
        "type": "Point",
        "coordinates": [
          -102.416667,
          19.216667
        ]
      },
      "type": "Feature",
      "properties": {
        "hierarchy": [
          "tgn:7380376",
          "tgn:1000001",
          "tgn:7005590",
          "tgn:7005560",
          "tgn:7029392"
        ],
        "placetype": [
          "aat:300008777"
        ],
        "id": 7380376,
        "name:xx": "Los Horcones, Cerro"
      }
    },
    {
      "geometry": {
        "type": "Point",
        "coordinates": [
          -109.633333,
          28.233333
        ]
      },
      "type": "Feature",
      "properties": {
        "hierarchy": [
          "tgn:7380377",
          "tgn:1000001",
          "tgn:1001960",
          "tgn:7005560",
          "tgn:7029392"
        ],
        "placetype": [
          "aat:300008347"
        ],
        "id": 7380377,
        "name:xx": "Los Horcones"
      }
    },
    {
      "geometry": {
        "type": "Point",
        "coordinates": [
          -103.616667,
          19.433333
        ]
      },
      "type": "Feature",
      "properties": {
        "hierarchy": [
          "tgn:7380378",
          "tgn:7016644",
          "tgn:1000001",
          "tgn:7005560",
          "tgn:7029392"
        ],
        "placetype": [
          "aat:300008347"
        ],
        "id": 7380378,
        "name:xx": "Los Horcones"
      }
    },
    {
      "geometry": {
        "type": "Point",
        "coordinates": [
          -102.816667,
          19
        ]
      },
      "type": "Feature",
      "properties": {
        "hierarchy": [
          "tgn:7380379",
          "tgn:1000001",
          "tgn:7005590",
          "tgn:7005560",
          "tgn:7029392"
        ],
        "placetype": [
          "aat:300008347"
        ],
        "id": 7380379,
        "name:xx": "Los Horcones"
      }
    }
  ]
}
