{
  "type": "FeatureCollection",
  "features": [
    {
      "geometry": {
        "type": "Point",
        "coordinates": [
          -76.1333,
          38.7333
        ]
      },
      "type": "Feature",
      "properties": {
        "hierarchy": [
          "tgn:2468420",
          "tgn:1000001",
          "tgn:2000939",
          "tgn:7012149",
          "tgn:7007516",
          "tgn:7029392"
        ],
        "placetype": [
          "aat:300008850"
        ],
        "id": 2468420,
        "name:xx": "Long Point"
      }
    },
    {
      "geometry": {
        "type": "Point",
        "coordinates": [
          -76.5,
          38.9
        ]
      },
      "type": "Feature",
      "properties": {
        "hierarchy": [
          "tgn:2468422",
          "tgn:7014651",
          "tgn:1000001",
          "tgn:7012149",
          "tgn:7007516",
          "tgn:7029392"
        ],
        "placetype": [
          "aat:300008850"
        ],
        "id": 2468422,
        "name:xx": "Long Point"
      }
    },
    {
      "geometry": {
        "type": "Point",
        "coordinates": [
          -76.1667,
          39.1
        ]
      },
      "type": "Feature",
      "properties": {
        "hierarchy": [
          "tgn:2468423",
          "tgn:1000001",
          "tgn:1002539",
          "tgn:7012149",
          "tgn:7007516",
          "tgn:7029392"
        ],
        "placetype": [
          "aat:300008850"
        ],
        "id": 2468423,
        "name:xx": "Long Point"
      }
    },
    {
      "geometry": {
        "type": "Point",
        "coordinates": [
          -76.4833,
          39.2333
        ]
      },
      "type": "Feature",
      "properties": {
        "hierarchy": [
          "tgn:2468424",
          "tgn:7016099",
          "tgn:1000001",
          "tgn:7012149",
          "tgn:7007516",
          "tgn:7029392"
        ],
        "placetype": [
          "aat:300008850"
        ],
        "id": 2468424,
        "name:xx": "Long Point"
      }
    },
    {
      "geometry": {
        "type": "Point",
        "coordinates": [
          -75.8833,
          39.4667
        ]
      },
      "type": "Feature",
      "properties": {
        "hierarchy": [
          "tgn:2468425",
          "tgn:1002247",
          "tgn:1000001",
          "tgn:7012149",
          "tgn:7007516",
          "tgn:7029392"
        ],
        "placetype": [
          "aat:300008850"
        ],
        "id": 2468425,
        "name:xx": "Long Point"
      }
    },
    {
      "geometry": {
        "type": "Point",
        "coordinates": [
          -75.8833,
          39.4667
        ]
      },
      "type": "Feature",
      "properties": {
        "hierarchy": [
          "tgn:2468426",
          "tgn:1002247",
          "tgn:1000001",
          "tgn:7012149",
          "tgn:7007516",
          "tgn:7029392"
        ],
        "placetype": [
          "aat:300008347"
        ],
        "id": 2468426,
        "name:xx": "Long Point"
      }
    },
    {
      "geometry": {
        "type": "Point",
        "coordinates": [
          -70.8833,
          42.5
        ]
      },
      "type": "Feature",
      "properties": {
        "hierarchy": [
          "tgn:2468427",
          "tgn:1000001",
          "tgn:1002359",
          "tgn:7012149",
          "tgn:7007517",
          "tgn:7029392"
        ],
        "placetype": [
          "aat:300008850"
        ],
        "id": 2468427,
        "name:xx": "Long Point"
      }
    },
    {
      "geometry": {
        "type": "Point",
        "coordinates": [
          -70.7667,
          41.3333
        ]
      },
      "type": "Feature",
      "properties": {
        "hierarchy": [
          "tgn:2468428",
          "tgn:7014010",
          "tgn:1000001",
          "tgn:1002344",
          "tgn:7012149",
          "tgn:7007517",
          "tgn:7029392"
        ],
        "placetype": [
          "aat:300008850"
        ],
        "id": 2468428,
        "name:xx": "Long Point"
      }
    },
    {
      "geometry": {
        "type": "Point",
        "coordinates": [
          -70.6667,
          42.0333
        ]
      },
      "type": "Feature",
      "properties": {
        "hierarchy": [
          "tgn:2468429",
          "tgn:1000001",
          "tgn:7014423",
          "tgn:7012149",
          "tgn:7007517",
          "tgn:7029392"
        ],
        "placetype": [
          "aat:300008791"
        ],
        "id": 2468429,
        "name:xx": "Long Point"
      }
    }
  ]
}
