{
  "geometry": {
    "type": "Point",
    "coordinates": [
      -76.5667,
      35.3167
    ]
  },
  "type": "Feature",
  "properties": {
    "hierarchy": [
      "tgn:2281360",
      "tgn:1000001",
      "tgn:7012149",
      "tgn:2001526",
      "tgn:7007709",
      "tgn:7029392"
    ],
    "placetype": [
      "aat:300008850"
    ],
    "id": 2281360,
    "name:xx": "Deep Water Point"
  }
}
