{
  "geometry": {
    "type": "Point",
    "coordinates": [
      -90.3833,
      39.1833
    ]
  },
  "type": "Feature",
  "properties": {
    "hierarchy": [
      "tgn:2289876",
      "tgn:1000001",
      "tgn:7012149",
      "tgn:1002422",
      "tgn:7007251",
      "tgn:7029392"
    ],
    "placetype": [
      "aat:300008761"
    ],
    "id": 2289876,
    "name:xx": "Dobson Hollow"
  }
}
