{
  "geometry": {
    "type": "Point",
    "coordinates": [
      -73.45,
      42.3333
    ]
  },
  "type": "Feature",
  "properties": {
    "hierarchy": [
      "tgn:2333288",
      "tgn:1000001",
      "tgn:7013638",
      "tgn:7012149",
      "tgn:7007568",
      "tgn:7029392"
    ],
    "placetype": [
      "aat:300008798"
    ],
    "id": 2333288,
    "name:xx": "Fog Hill"
  }
}
