{
  "geometry": {
    "type": "Point",
    "coordinates": [
      -110.7667,
      32.9833
    ]
  },
  "type": "Feature",
  "properties": {
    "hierarchy": [
      "tgn:2640773",
      "tgn:1000001",
      "tgn:7006451",
      "tgn:7012149",
      "tgn:7029392"
    ],
    "placetype": [
      "aat:300008707"
    ],
    "id": 2640773,
    "name:xx": "San Pedro River"
  }
}
