{
  "geometry": {
    "type": "Point",
    "coordinates": [
      -77.1167,
      39.3333
    ]
  },
  "type": "Feature",
  "properties": {
    "hierarchy": [
      "tgn:2381656",
      "tgn:1000001",
      "tgn:7012149",
      "tgn:7007516",
      "tgn:7029392"
    ],
    "placetype": [
      "aat:300008699"
    ],
    "id": 2381656,
    "name:xx": "Hay Meadow Branch"
  }
}
