{
  "geometry": {
    "type": "Point",
    "coordinates": [
      103.1833,
      -0.35
    ]
  },
  "type": "Feature",
  "properties": {
    "hierarchy": [
      "tgn:1078766",
      "tgn:1000004",
      "tgn:1001502",
      "tgn:1000116",
      "tgn:7029392"
    ],
    "placetype": [
      "aat:300008347"
    ],
    "id": 1078766,
    "name:xx": "Tembilahan"
  }
}
