{
  "geometry": {
    "type": "Point",
    "coordinates": [
      -64.75,
      32.3333
    ]
  },
  "type": "Feature",
  "properties": {
    "hierarchy": [
      "tgn:7032026",
      "tgn:1000001",
      "tgn:7029392"
    ],
    "placetype": [
      "aat:300387054",
      "aat:300235115",
      "aat:300386853",
      "aat:300387176"
    ],
    "name:fr": "Bermudes",
    "name:en": "Bermuda",
    "id": 7032026
  }
}
