{
  "geometry": {
    "type": "Point",
    "coordinates": [
      30.855679,
      28.953552
    ]
  },
  "type": "Feature",
  "properties": {
    "hierarchy": [
      "tgn:7523131",
      "tgn:7001242",
      "tgn:7016833",
      "tgn:1001142",
      "tgn:7029392"
    ],
    "placetype": [
      "aat:300008347"
    ],
    "name:en": "Ash Shunţūr",
    "id": 7523131
  }
}
