{
  "geometry": {
    "type": "Point",
    "coordinates": [
      70.8333,
      42.6833
    ]
  },
  "type": "Feature",
  "properties": {
    "hierarchy": [
      "tgn:1053180",
      "tgn:1000004",
      "tgn:1003362",
      "tgn:7014786",
      "tgn:7029392"
    ],
    "placetype": [
      "aat:300008347"
    ],
    "id": 1053180,
    "name:xx": "Burnooktybr'skoye"
  }
}
