{
  "type": "FeatureCollection",
  "features": [
    {
      "geometry": {
        "type": "Point",
        "coordinates": [
          -90.0833,
          45.5667
        ]
      },
      "type": "Feature",
      "properties": {
        "hierarchy": [
          "tgn:1130167",
          "tgn:1000001",
          "tgn:7012149",
          "tgn:7007922",
          "tgn:7029392"
        ],
        "placetype": [
          "aat:300008707"
        ],
        "id": 1130167,
        "name:xx": "Somo"
      }
    },
    {
      "geometry": {
        "type": "Point",
        "coordinates": [
          84.8667,
          25.7
        ]
      },
      "type": "Feature",
      "properties": {
        "hierarchy": [
          "tgn:1130168",
          "tgn:1000004",
          "tgn:7000198",
          "tgn:7029392"
        ],
        "placetype": [
          "aat:300008707"
        ],
        "id": 1130168,
        "name:xx": "Son"
      }
    },
    {
      "geometry": {
        "type": "Point",
        "coordinates": [
          79.929755,
          24.389164
        ]
      },
      "type": "Feature",
      "properties": {
        "hierarchy": [
          "tgn:1130169",
          "tgn:1000004",
          "tgn:7000198",
          "tgn:1001894",
          "tgn:7029392"
        ],
        "placetype": [
          "aat:300008707",
          "aat:300008699"
        ],
        "id": 1130169,
        "name:xx": "Sonār"
      }
    }
  ]
}
