{
  "geometry": {
    "type": "Point",
    "coordinates": [
      -79.1333,
      35.6667
    ]
  },
  "type": "Feature",
  "properties": {
    "hierarchy": [
      "tgn:2695572",
      "tgn:1000001",
      "tgn:2001480",
      "tgn:7012149",
      "tgn:7007709",
      "tgn:7029392"
    ],
    "placetype": [
      "aat:300008706"
    ],
    "id": 2695572,
    "name:xx": "Stinking Creek"
  }
}
