{
  "type": "FeatureCollection",
  "features": [
    {
      "geometry": {
        "type": "Point",
        "coordinates": [
          13.6,
          52.2
        ]
      },
      "type": "Feature",
      "properties": {
        "hierarchy": [
          "tgn:7151670",
          "tgn:7000096",
          "tgn:1000003",
          "tgn:7000084",
          "tgn:7029392"
        ],
        "placetype": [
          "aat:300008777"
        ],
        "id": 7151670,
        "name:xx": "Kahler-Berg"
      }
    },
    {
      "geometry": {
        "type": "Point",
        "coordinates": [
          8.633333,
          52.183333
        ]
      },
      "type": "Feature",
      "properties": {
        "hierarchy": [
          "tgn:7151671",
          "tgn:1000003",
          "tgn:7003677",
          "tgn:7000084",
          "tgn:7029392"
        ],
        "placetype": [
          "aat:300008777"
        ],
        "id": 7151671,
        "name:xx": "Kahler-Berg"
      }
    },
    {
      "geometry": {
        "type": "Point",
        "coordinates": [
          8.016667,
          52.15
        ]
      },
      "type": "Feature",
      "properties": {
        "hierarchy": [
          "tgn:7151672",
          "tgn:1000003",
          "tgn:7003676",
          "tgn:7000084",
          "tgn:7029392"
        ],
        "placetype": [
          "aat:300008777"
        ],
        "id": 7151672,
        "name:xx": "Kahler Berg"
      }
    },
    {
      "geometry": {
        "type": "Point",
        "coordinates": [
          9.183333,
          52.116667
        ]
      },
      "type": "Feature",
      "properties": {
        "hierarchy": [
          "tgn:7151673",
          "tgn:1000003",
          "tgn:7003676",
          "tgn:7000084",
          "tgn:7029392"
        ],
        "placetype": [
          "aat:300008777"
        ],
        "id": 7151673,
        "name:xx": "Kahler-Berg"
      }
    },
    {
      "geometry": {
        "type": "Point",
        "coordinates": [
          13.433333,
          51.916667
        ]
      },
      "type": "Feature",
      "properties": {
        "hierarchy": [
          "tgn:7151674",
          "tgn:7000096",
          "tgn:1000003",
          "tgn:7000084",
          "tgn:7029392"
        ],
        "placetype": [
          "aat:300008777"
        ],
        "id": 7151674,
        "name:xx": "Kahler Berg"
      }
    },
    {
      "geometry": {
        "type": "Point",
        "coordinates": [
          10.916667,
          50.766667
        ]
      },
      "type": "Feature",
      "properties": {
        "hierarchy": [
          "tgn:7151675",
          "tgn:1000003",
          "tgn:7003689",
          "tgn:7000084",
          "tgn:7029392"
        ],
        "placetype": [
          "aat:300008777"
        ],
        "id": 7151675,
        "name:xx": "Kahler-Berg"
      }
    },
    {
      "geometry": {
        "type": "Point",
        "coordinates": [
          7.866667,
          50.416667
        ]
      },
      "type": "Feature",
      "properties": {
        "hierarchy": [
          "tgn:7151676",
          "tgn:1000003",
          "tgn:7003682",
          "tgn:7000084",
          "tgn:7029392"
        ],
        "placetype": [
          "aat:300008777"
        ],
        "id": 7151676,
        "name:xx": "Kahler Berg"
      }
    },
    {
      "geometry": {
        "type": "Point",
        "coordinates": [
          9.533333,
          50.283333
        ]
      },
      "type": "Feature",
      "properties": {
        "hierarchy": [
          "tgn:7151677",
          "tgn:1000003",
          "tgn:7003678",
          "tgn:7000084",
          "tgn:7029392"
        ],
        "placetype": [
          "aat:300008777"
        ],
        "id": 7151677,
        "name:xx": "Kahler-Berg"
      }
    },
    {
      "geometry": {
        "type": "Point",
        "coordinates": [
          7.266667,
          49.2
        ]
      },
      "type": "Feature",
      "properties": {
        "hierarchy": [
          "tgn:7151678",
          "tgn:1000003",
          "tgn:7003684",
          "tgn:7000084",
          "tgn:7029392"
        ],
        "placetype": [
          "aat:300008777"
        ],
        "id": 7151678,
        "name:xx": "Kleiner Kahlen Berg"
      }
    },
    {
      "geometry": {
        "type": "Point",
        "coordinates": [
          7.983333,
          48.483333
        ]
      },
      "type": "Feature",
      "properties": {
        "hierarchy": [
          "tgn:7151679",
          "tgn:7003692",
          "tgn:1000003",
          "tgn:7000084",
          "tgn:7029392"
        ],
        "placetype": [
          "aat:300008699"
        ],
        "id": 7151679,
        "name:xx": "Kahler Bach"
      }
    }
  ]
}
