{
  "type": "FeatureCollection",
  "features": [
    {
      "geometry": {
        "type": "Point",
        "coordinates": [
          7.233333,
          50.15
        ]
      },
      "type": "Feature",
      "properties": {
        "hierarchy": [
          "tgn:5001893",
          "tgn:1000003",
          "tgn:7003682",
          "tgn:7000084",
          "tgn:7029392"
        ],
        "placetype": [
          "aat:300008347",
          "aat:300008375"
        ],
        "id": 5001893,
        "name:xx": "Ernst an der Mosel"
      }
    },
    {
      "geometry": {
        "type": "Point",
        "coordinates": [
          6.6,
          49.733333
        ]
      },
      "type": "Feature",
      "properties": {
        "hierarchy": [
          "tgn:5001894",
          "tgn:1000003",
          "tgn:7003682",
          "tgn:7000084",
          "tgn:7004447",
          "tgn:7029392"
        ],
        "placetype": [
          "aat:300000745",
          "aat:300000874"
        ],
        "id": 5001894,
        "name:xx": "Euren"
      }
    },
    {
      "geometry": {
        "type": "Point",
        "coordinates": [
          7.9,
          49.95
        ]
      },
      "type": "Feature",
      "properties": {
        "hierarchy": [
          "tgn:5001899",
          "tgn:1000003",
          "tgn:7003682",
          "tgn:7000084",
          "tgn:7029392"
        ],
        "placetype": [
          "aat:300008347",
          "aat:300008375"
        ],
        "id": 5001899,
        "name:xx": "Münster-Sarmsheim"
      }
    }
  ]
}
