{
  "type": "FeatureCollection",
  "features": [
    {
      "geometry": {
        "type": "Point",
        "coordinates": [
          -96.9167,
          44.0167
        ]
      },
      "type": "Feature",
      "properties": {
        "hierarchy": [
          "tgn:2141960",
          "tgn:1000001",
          "tgn:7012149",
          "tgn:7007713",
          "tgn:7029392"
        ],
        "placetype": [
          "aat:300008706"
        ],
        "id": 2141960,
        "name:xx": "Bachelor Creek"
      }
    },
    {
      "geometry": {
        "type": "Point",
        "coordinates": [
          -96.2667,
          32.8167
        ]
      },
      "type": "Feature",
      "properties": {
        "hierarchy": [
          "tgn:2141961",
          "tgn:1000001",
          "tgn:7012149",
          "tgn:1002535",
          "tgn:7007826",
          "tgn:7029392"
        ],
        "placetype": [
          "aat:300008706"
        ],
        "id": 2141961,
        "name:xx": "Bachelor Creek"
      }
    },
    {
      "geometry": {
        "type": "Point",
        "coordinates": [
          -120.7667,
          46.5167
        ]
      },
      "type": "Feature",
      "properties": {
        "hierarchy": [
          "tgn:2141962",
          "tgn:1000001",
          "tgn:7012149",
          "tgn:1003042",
          "tgn:7007920",
          "tgn:7029392"
        ],
        "placetype": [
          "aat:300008706"
        ],
        "id": 2141962,
        "name:xx": "Bachelor Creek"
      }
    },
    {
      "geometry": {
        "type": "Point",
        "coordinates": [
          -121.0833,
          48.3
        ]
      },
      "type": "Feature",
      "properties": {
        "hierarchy": [
          "tgn:2141963",
          "tgn:1000001",
          "tgn:7012149",
          "tgn:7014510",
          "tgn:7007920",
          "tgn:7029392"
        ],
        "placetype": [
          "aat:300008706"
        ],
        "id": 2141963,
        "name:xx": "Bachelor Creek"
      }
    },
    {
      "geometry": {
        "type": "Point",
        "coordinates": [
          -107.1,
          41.1667
        ]
      },
      "type": "Feature",
      "properties": {
        "hierarchy": [
          "tgn:2141964",
          "tgn:1000001",
          "tgn:2002368",
          "tgn:7012149",
          "tgn:7007923",
          "tgn:7029392"
        ],
        "placetype": [
          "aat:300008706"
        ],
        "id": 2141964,
        "name:xx": "Bachelor Creek"
      }
    },
    {
      "geometry": {
        "type": "Point",
        "coordinates": [
          -109.7333,
          43.4833
        ]
      },
      "type": "Feature",
      "properties": {
        "hierarchy": [
          "tgn:2141965",
          "tgn:1000001",
          "tgn:7012149",
          "tgn:2002371",
          "tgn:7007923",
          "tgn:7029392"
        ],
        "placetype": [
          "aat:300008706"
        ],
        "id": 2141965,
        "name:xx": "Bachelor Creek"
      }
    },
    {
      "geometry": {
        "type": "Point",
        "coordinates": [
          -108.8333,
          38.1333
        ]
      },
      "type": "Feature",
      "properties": {
        "hierarchy": [
          "tgn:2141966",
          "tgn:1000001",
          "tgn:7012149",
          "tgn:7007158",
          "tgn:7029392"
        ],
        "placetype": [
          "aat:300008761"
        ],
        "id": 2141966,
        "name:xx": "Bachelor Draw"
      }
    },
    {
      "geometry": {
        "type": "Point",
        "coordinates": [
          -106.2667,
          35.1
        ]
      },
      "type": "Feature",
      "properties": {
        "hierarchy": [
          "tgn:2141967",
          "tgn:1000001",
          "tgn:7012149",
          "tgn:7007566",
          "tgn:7029392"
        ],
        "placetype": [
          "aat:300008761"
        ],
        "id": 2141967,
        "name:xx": "Bachelor Draw"
      }
    },
    {
      "geometry": {
        "type": "Point",
        "coordinates": [
          -122.8667,
          45.8333
        ]
      },
      "type": "Feature",
      "properties": {
        "hierarchy": [
          "tgn:2141968",
          "tgn:1000001",
          "tgn:1002293",
          "tgn:7012149",
          "tgn:7007708",
          "tgn:7029392"
        ],
        "placetype": [
          "aat:300008347"
        ],
        "id": 2141968,
        "name:xx": "Bachelor Flat"
      }
    },
    {
      "geometry": {
        "type": "Point",
        "coordinates": [
          -87.7833,
          41.6167
        ]
      },
      "type": "Feature",
      "properties": {
        "hierarchy": [
          "tgn:2141969",
          "tgn:1000001",
          "tgn:7013649",
          "tgn:7012149",
          "tgn:7007251",
          "tgn:7029392"
        ],
        "placetype": [
          "aat:300132451"
        ],
        "id": 2141969,
        "name:xx": "Bachelor Grove"
      }
    }
  ]
}
