{
  "geometry": {
    "type": "Point",
    "coordinates": [
      -81.6167,
      34.9167
    ]
  },
  "type": "Feature",
  "properties": {
    "hierarchy": [
      "tgn:2267474",
      "tgn:1000001",
      "tgn:2001735",
      "tgn:7012149",
      "tgn:7007712",
      "tgn:7029392"
    ],
    "placetype": [
      "aat:300008699"
    ],
    "id": 2267474,
    "name:xx": "Crocker Branch"
  }
}
