{
  "geometry": {
    "type": "Point",
    "coordinates": [
      33.795499,
      27.676067
    ]
  },
  "type": "Feature",
  "properties": {
    "hierarchy": [
      "tgn:7534364",
      "tgn:7001242",
      "tgn:7001311",
      "tgn:7016833",
      "tgn:7029392"
    ],
    "placetype": [
      "aat:300008791"
    ],
    "name:en": "Jūbāl aş Şaghīrah, Jazīrat",
    "id": 7534364
  }
}
