{
  "geometry": {
    "type": "Point",
    "coordinates": [
      -7.5833,
      53.9167
    ]
  },
  "type": "Feature",
  "properties": {
    "hierarchy": [
      "tgn:1042579",
      "tgn:7003501",
      "tgn:7003478",
      "tgn:1000003",
      "tgn:1000078",
      "tgn:7029392"
    ],
    "placetype": [
      "aat:300008347"
    ],
    "id": 1042579,
    "name:xx": "Arvagh"
  }
}
