{
  "geometry": {
    "type": "Point",
    "coordinates": [
      -86.0667,
      36.5167
    ]
  },
  "type": "Feature",
  "properties": {
    "hierarchy": [
      "tgn:2286976",
      "tgn:1000001",
      "tgn:7012149",
      "tgn:2001892",
      "tgn:7007825",
      "tgn:7029392"
    ],
    "placetype": [
      "aat:300008761"
    ],
    "id": 2286976,
    "name:xx": "Dick Hollow"
  }
}
