{
  "geometry": {
    "type": "Point",
    "coordinates": [
      79.183333,
      11.716667
    ]
  },
  "type": "Feature",
  "properties": {
    "hierarchy": [
      "tgn:7549523",
      "tgn:1000004",
      "tgn:7000198",
      "tgn:7001797",
      "tgn:7029392"
    ],
    "placetype": [
      "aat:300008347"
    ],
    "name:en": "Elavanasūr",
    "id": 7549523
  }
}
