{
  "geometry": {
    "type": "Point",
    "coordinates": [
      -83.1833,
      35.7333
    ]
  },
  "type": "Feature",
  "properties": {
    "hierarchy": [
      "tgn:2626285",
      "tgn:1000001",
      "tgn:7012149",
      "tgn:7029392"
    ],
    "placetype": [
      "aat:300008798"
    ],
    "id": 2626285,
    "name:xx": "Rocky Face Mountain"
  }
}
