{
  "geometry": {
    "type": "Point",
    "coordinates": [
      -111.4667,
      39.8667
    ]
  },
  "type": "Feature",
  "properties": {
    "hierarchy": [
      "tgn:2229107",
      "tgn:1000001",
      "tgn:7012149",
      "tgn:2002125",
      "tgn:7007827",
      "tgn:7029392"
    ],
    "placetype": [
      "aat:300008798"
    ],
    "id": 2229107,
    "name:xx": "Cedar Knoll"
  }
}
