{
  "type": "FeatureCollection",
  "features": [
    {
      "geometry": {
        "type": "Point",
        "coordinates": [
          -116.2,
          44.9
        ]
      },
      "type": "Feature",
      "properties": {
        "hierarchy": [
          "tgn:2327910",
          "tgn:2000453",
          "tgn:1000001",
          "tgn:7012149",
          "tgn:7007250",
          "tgn:7029392"
        ],
        "placetype": [
          "aat:300006191"
        ],
        "id": 2327910,
        "name:xx": "Fish Lake"
      }
    },
    {
      "geometry": {
        "type": "Point",
        "coordinates": [
          -115.4167,
          45.0167
        ]
      },
      "type": "Feature",
      "properties": {
        "hierarchy": [
          "tgn:2327911",
          "tgn:1000001",
          "tgn:7012149",
          "tgn:2000494",
          "tgn:7007250",
          "tgn:7029392"
        ],
        "placetype": [
          "aat:300008680"
        ],
        "id": 2327911,
        "name:xx": "Fish Lake"
      }
    },
    {
      "geometry": {
        "type": "Point",
        "coordinates": [
          -115.3167,
          45.3833
        ]
      },
      "type": "Feature",
      "properties": {
        "hierarchy": [
          "tgn:2327912",
          "tgn:1000001",
          "tgn:7012149",
          "tgn:2000476",
          "tgn:7007250",
          "tgn:7029392"
        ],
        "placetype": [
          "aat:300008680"
        ],
        "id": 2327912,
        "name:xx": "Fish Lake"
      }
    },
    {
      "geometry": {
        "type": "Point",
        "coordinates": [
          -114.9,
          46.8167
        ]
      },
      "type": "Feature",
      "properties": {
        "hierarchy": [
          "tgn:2327913",
          "tgn:1000001",
          "tgn:2000469",
          "tgn:7012149",
          "tgn:7007250",
          "tgn:7029392"
        ],
        "placetype": [
          "aat:300008680"
        ],
        "id": 2327913,
        "name:xx": "Fish Lake"
      }
    },
    {
      "geometry": {
        "type": "Point",
        "coordinates": [
          -115.95,
          47.1
        ]
      },
      "type": "Feature",
      "properties": {
        "hierarchy": [
          "tgn:2327914",
          "tgn:1000001",
          "tgn:7012149",
          "tgn:2000491",
          "tgn:7007250",
          "tgn:7029392"
        ],
        "placetype": [
          "aat:300008680"
        ],
        "id": 2327914,
        "name:xx": "Fish Lake"
      }
    },
    {
      "geometry": {
        "type": "Point",
        "coordinates": [
          -88.0833,
          37.7167
        ]
      },
      "type": "Feature",
      "properties": {
        "hierarchy": [
          "tgn:2327915",
          "tgn:1000001",
          "tgn:2000507",
          "tgn:7012149",
          "tgn:7007251",
          "tgn:7029392"
        ],
        "placetype": [
          "aat:300008680"
        ],
        "id": 2327915,
        "name:xx": "Fish Lake"
      }
    },
    {
      "geometry": {
        "type": "Point",
        "coordinates": [
          -89.1333,
          38.8833
        ]
      },
      "type": "Feature",
      "properties": {
        "hierarchy": [
          "tgn:2327916",
          "tgn:1000001",
          "tgn:1002369",
          "tgn:7012149",
          "tgn:7007251",
          "tgn:7029392"
        ],
        "placetype": [
          "aat:300008680"
        ],
        "id": 2327916,
        "name:xx": "Fish Lake"
      }
    },
    {
      "geometry": {
        "type": "Point",
        "coordinates": [
          -90.0667,
          40.1
        ]
      },
      "type": "Feature",
      "properties": {
        "hierarchy": [
          "tgn:2327917",
          "tgn:1000001",
          "tgn:7012149",
          "tgn:1002643",
          "tgn:7007251",
          "tgn:7029392"
        ],
        "placetype": [
          "aat:300008680"
        ],
        "id": 2327917,
        "name:xx": "Fish Lake"
      }
    },
    {
      "geometry": {
        "type": "Point",
        "coordinates": [
          -91.1,
          40.7333
        ]
      },
      "type": "Feature",
      "properties": {
        "hierarchy": [
          "tgn:2327918",
          "tgn:1000001",
          "tgn:7012149",
          "tgn:2000510",
          "tgn:7007251",
          "tgn:7029392"
        ],
        "placetype": [
          "aat:300008680"
        ],
        "id": 2327918,
        "name:xx": "Fish Lake"
      }
    },
    {
      "geometry": {
        "type": "Point",
        "coordinates": [
          -88.15,
          42.3333
        ]
      },
      "type": "Feature",
      "properties": {
        "hierarchy": [
          "tgn:2327919",
          "tgn:1000001",
          "tgn:7012149",
          "tgn:7013855",
          "tgn:7007251",
          "tgn:7029392"
        ],
        "placetype": [
          "aat:300008680"
        ],
        "id": 2327919,
        "name:xx": "Fish Lake"
      }
    }
  ]
}
