{
  "geometry": {
    "type": "Point",
    "coordinates": [
      3.28576,
      42.332762
    ]
  },
  "type": "Feature",
  "properties": {
    "hierarchy": [
      "tgn:7328987",
      "tgn:7002820",
      "tgn:7030216",
      "tgn:1000003",
      "tgn:1000095",
      "tgn:7029392"
    ],
    "placetype": [
      "aat:300008791"
    ],
    "id": 7328987,
    "name:xx": "Purtaló, Isla"
  }
}
