{
  "geometry": {
    "type": "Point",
    "coordinates": [
      -107.7667,
      37.8167
    ]
  },
  "type": "Feature",
  "properties": {
    "hierarchy": [
      "tgn:2242585",
      "tgn:1000001",
      "tgn:7012149",
      "tgn:7007158",
      "tgn:2000247",
      "tgn:7029392"
    ],
    "placetype": [
      "aat:300008706"
    ],
    "id": 2242585,
    "name:xx": "Clear Creek"
  }
}
