{
  "geometry": {
    "type": "Point",
    "coordinates": [
      -139.75,
      59.5833
    ]
  },
  "type": "Feature",
  "properties": {
    "hierarchy": [
      "tgn:2436290",
      "tgn:7006450",
      "tgn:1000001",
      "tgn:7012149",
      "tgn:7030574",
      "tgn:7029392"
    ],
    "placetype": [
      "aat:300008791"
    ],
    "id": 2436290,
    "name:xx": "Khantaak Island"
  }
}
