{
  "type": "FeatureCollection",
  "features": [
    {
      "geometry": {
        "type": "Point",
        "coordinates": [
          10,
          54.333333
        ]
      },
      "type": "Feature",
      "properties": {
        "hierarchy": [
          "tgn:7077850",
          "tgn:1000003",
          "tgn:7003688",
          "tgn:7000084",
          "tgn:7029392"
        ],
        "placetype": [
          "aat:300000206"
        ],
        "id": 7077850,
        "name:xx": "Ziegelhof"
      }
    },
    {
      "geometry": {
        "type": "Point",
        "coordinates": [
          8.933333,
          54.316667
        ]
      },
      "type": "Feature",
      "properties": {
        "hierarchy": [
          "tgn:7077851",
          "tgn:1000003",
          "tgn:7003688",
          "tgn:7000084",
          "tgn:7029392"
        ],
        "placetype": [
          "aat:300000206"
        ],
        "id": 7077851,
        "name:xx": "Ziegelhof"
      }
    },
    {
      "geometry": {
        "type": "Point",
        "coordinates": [
          9.983333,
          54.183333
        ]
      },
      "type": "Feature",
      "properties": {
        "hierarchy": [
          "tgn:7077852",
          "tgn:1000003",
          "tgn:7003688",
          "tgn:7000084",
          "tgn:7029392"
        ],
        "placetype": [
          "aat:300000206"
        ],
        "id": 7077852,
        "name:xx": "Ziegelhof"
      }
    },
    {
      "geometry": {
        "type": "Point",
        "coordinates": [
          10.15,
          54.116667
        ]
      },
      "type": "Feature",
      "properties": {
        "hierarchy": [
          "tgn:7077853",
          "tgn:1000003",
          "tgn:7003688",
          "tgn:7000084",
          "tgn:7029392"
        ],
        "placetype": [
          "aat:300000206"
        ],
        "id": 7077853,
        "name:xx": "Ziegelhof"
      }
    },
    {
      "geometry": {
        "type": "Point",
        "coordinates": [
          10.683333,
          54.033333
        ]
      },
      "type": "Feature",
      "properties": {
        "hierarchy": [
          "tgn:7077854",
          "tgn:1000003",
          "tgn:7003688",
          "tgn:7000084",
          "tgn:7029392"
        ],
        "placetype": [
          "aat:300000206"
        ],
        "id": 7077854,
        "name:xx": "Ziegelhof"
      }
    },
    {
      "geometry": {
        "type": "Point",
        "coordinates": [
          7.883333,
          53.583333
        ]
      },
      "type": "Feature",
      "properties": {
        "hierarchy": [
          "tgn:7077855",
          "tgn:1000003",
          "tgn:7003676",
          "tgn:7000084",
          "tgn:7029392"
        ],
        "placetype": [
          "aat:300000206"
        ],
        "id": 7077855,
        "name:xx": "Ziegelhof"
      }
    },
    {
      "geometry": {
        "type": "Point",
        "coordinates": [
          9.966667,
          50.566667
        ]
      },
      "type": "Feature",
      "properties": {
        "hierarchy": [
          "tgn:7077856",
          "tgn:1000003",
          "tgn:7003678",
          "tgn:7000084",
          "tgn:7029392"
        ],
        "placetype": [
          "aat:300000206"
        ],
        "id": 7077856,
        "name:xx": "Ziegelhof"
      }
    },
    {
      "geometry": {
        "type": "Point",
        "coordinates": [
          9.866667,
          50.516667
        ]
      },
      "type": "Feature",
      "properties": {
        "hierarchy": [
          "tgn:7077857",
          "tgn:1000003",
          "tgn:7003678",
          "tgn:7000084",
          "tgn:7029392"
        ],
        "placetype": [
          "aat:300000206"
        ],
        "id": 7077857,
        "name:xx": "Ziegelhof"
      }
    },
    {
      "geometry": {
        "type": "Point",
        "coordinates": [
          12.366667,
          49.383333
        ]
      },
      "type": "Feature",
      "properties": {
        "hierarchy": [
          "tgn:7077858",
          "tgn:7003669",
          "tgn:1000003",
          "tgn:7000084",
          "tgn:7029392"
        ],
        "placetype": [
          "aat:300000206"
        ],
        "id": 7077858,
        "name:xx": "Ziegelhof"
      }
    },
    {
      "geometry": {
        "type": "Point",
        "coordinates": [
          11.2,
          48.9
        ]
      },
      "type": "Feature",
      "properties": {
        "hierarchy": [
          "tgn:7077859",
          "tgn:7003669",
          "tgn:1000003",
          "tgn:7000084",
          "tgn:7029392"
        ],
        "placetype": [
          "aat:300000206"
        ],
        "id": 7077859,
        "name:xx": "Mittelwimpasing"
      }
    }
  ]
}
