{
  "geometry": {
    "type": "Point",
    "coordinates": [
      -106.4667,
      38.5667
    ]
  },
  "type": "Feature",
  "properties": {
    "hierarchy": [
      "tgn:2451278",
      "tgn:1000001",
      "tgn:7012149",
      "tgn:2000217",
      "tgn:7007158",
      "tgn:7029392"
    ],
    "placetype": [
      "aat:300008798"
    ],
    "id": 2451278,
    "name:xx": "Little Baldy"
  }
}
