{
  "geometry": {
    "type": "Point",
    "coordinates": [
      -76.5833,
      35.3167
    ]
  },
  "type": "Feature",
  "properties": {
    "hierarchy": [
      "tgn:2169547",
      "tgn:1000001",
      "tgn:7012149",
      "tgn:2001526",
      "tgn:7007709",
      "tgn:7029392"
    ],
    "placetype": [
      "aat:300008699"
    ],
    "id": 2169547,
    "name:xx": "Big Marsh Gut"
  }
}
