{
  "type": "FeatureCollection",
  "features": [
    {
      "geometry": {
        "type": "Point",
        "coordinates": [
          -82.4333,
          33.2667
        ]
      },
      "type": "Feature",
      "properties": {
        "hierarchy": [
          "tgn:2540490",
          "tgn:1000001",
          "tgn:7012149",
          "tgn:2000353",
          "tgn:7007248",
          "tgn:7029392"
        ],
        "placetype": [
          "aat:300006191"
        ],
        "id": 2540490,
        "name:xx": "Newsomes Pond"
      }
    },
    {
      "geometry": {
        "type": "Point",
        "coordinates": [
          -85.1,
          32.15
        ]
      },
      "type": "Feature",
      "properties": {
        "hierarchy": [
          "tgn:2540491",
          "tgn:7002659",
          "tgn:1000001",
          "tgn:7012149",
          "tgn:2000056",
          "tgn:7029392"
        ],
        "placetype": [
          "aat:300006191"
        ],
        "id": 2540491,
        "name:xx": "Newsoms Pond"
      }
    },
    {
      "geometry": {
        "type": "Point",
        "coordinates": [
          -81.6167,
          37.4
        ]
      },
      "type": "Feature",
      "properties": {
        "hierarchy": [
          "tgn:2540492",
          "tgn:1000001",
          "tgn:7012149",
          "tgn:2002274",
          "tgn:7013961",
          "tgn:7029392"
        ],
        "placetype": [
          "aat:300008699"
        ],
        "id": 2540492,
        "name:xx": "Newson Branch"
      }
    },
    {
      "geometry": {
        "type": "Point",
        "coordinates": [
          -78.0333,
          35.6167
        ]
      },
      "type": "Feature",
      "properties": {
        "hierarchy": [
          "tgn:2540493",
          "tgn:1000001",
          "tgn:7012149",
          "tgn:2001554",
          "tgn:7007709",
          "tgn:7029392"
        ],
        "placetype": [
          "aat:300006191"
        ],
        "id": 2540493,
        "name:xx": "Newson Millpond"
      }
    },
    {
      "geometry": {
        "type": "Point",
        "coordinates": [
          -80.25,
          34.3
        ]
      },
      "type": "Feature",
      "properties": {
        "hierarchy": [
          "tgn:2540494",
          "tgn:1000001",
          "tgn:7012149",
          "tgn:2001755",
          "tgn:7007712",
          "tgn:7029392"
        ],
        "placetype": [
          "aat:300006191"
        ],
        "id": 2540494,
        "name:xx": "Newson Pond"
      }
    },
    {
      "geometry": {
        "type": "Point",
        "coordinates": [
          -94.1,
          36.7833
        ]
      },
      "type": "Feature",
      "properties": {
        "hierarchy": [
          "tgn:2540495",
          "tgn:1000001",
          "tgn:7012149",
          "tgn:2001223",
          "tgn:7007523",
          "tgn:7029392"
        ],
        "placetype": [
          "aat:300008347"
        ],
        "id": 2540495,
        "name:xx": "Newstead"
      }
    },
    {
      "geometry": {
        "type": "Point",
        "coordinates": [
          -74.2667,
          40.75
        ]
      },
      "type": "Feature",
      "properties": {
        "hierarchy": [
          "tgn:2540496",
          "tgn:1000001",
          "tgn:1002360",
          "tgn:7012149",
          "tgn:7007565",
          "tgn:7029392"
        ],
        "placetype": [
          "aat:300008347"
        ],
        "id": 2540496,
        "name:xx": "Newstead"
      }
    },
    {
      "geometry": {
        "type": "Point",
        "coordinates": [
          -74.2667,
          40.75
        ]
      },
      "type": "Feature",
      "properties": {
        "hierarchy": [
          "tgn:2540498",
          "tgn:1000001",
          "tgn:1002360",
          "tgn:7012149",
          "tgn:7007565",
          "tgn:7029392"
        ],
        "placetype": [
          "aat:300008347"
        ],
        "id": 2540498,
        "name:xx": "Newstead North"
      }
    },
    {
      "geometry": {
        "type": "Point",
        "coordinates": [
          -76.8,
          39
        ]
      },
      "type": "Feature",
      "properties": {
        "hierarchy": [
          "tgn:2540499",
          "tgn:1000001",
          "tgn:2124001",
          "tgn:7012149",
          "tgn:7007516",
          "tgn:7029392"
        ],
        "placetype": [
          "aat:300008699"
        ],
        "id": 2540499,
        "name:xx": "Newstop Branch"
      }
    }
  ]
}
