{
  "geometry": {
    "type": "Point",
    "coordinates": [
      31.732282,
      26.45438
    ]
  },
  "type": "Feature",
  "properties": {
    "hierarchy": [
      "tgn:7535108",
      "tgn:7001242",
      "tgn:7016833",
      "tgn:7000124",
      "tgn:7029392"
    ],
    "placetype": [
      "aat:300008347"
    ],
    "name:en": "Kawm Baddār",
    "id": 7535108
  }
}
