{
  "geometry": {
    "type": "Point",
    "coordinates": [
      -84.75,
      38.8833
    ]
  },
  "type": "Feature",
  "properties": {
    "hierarchy": [
      "tgn:1102174",
      "tgn:1000001",
      "tgn:1002189",
      "tgn:7012149",
      "tgn:7007255",
      "tgn:7029392"
    ],
    "placetype": [
      "aat:300008192"
    ],
    "id": 1102174,
    "name:xx": "Big Bone Lick State Park"
  }
}
