{
  "geometry": {
    "type": "Point",
    "coordinates": [
      -81.9333,
      39.3333
    ]
  },
  "type": "Feature",
  "properties": {
    "hierarchy": [
      "tgn:2533204",
      "tgn:2001610",
      "tgn:1000001",
      "tgn:7012149",
      "tgn:7007706",
      "tgn:7029392"
    ],
    "placetype": [
      "aat:300008699"
    ],
    "id": 2533204,
    "name:xx": "Mush Run"
  }
}
