{
  "type": "FeatureCollection",
  "features": [
    {
      "geometry": {
        "type": "Point",
        "coordinates": [
          -87.4167,
          46.2667
        ]
      },
      "type": "Feature",
      "properties": {
        "hierarchy": [
          "tgn:2181920",
          "tgn:1000001",
          "tgn:7012149",
          "tgn:2000975",
          "tgn:7007520",
          "tgn:7029392"
        ],
        "placetype": [
          "aat:300008680"
        ],
        "id": 2181920,
        "name:xx": "Blue Lake"
      }
    },
    {
      "geometry": {
        "type": "Point",
        "coordinates": [
          -85.2833,
          43.6167
        ]
      },
      "type": "Feature",
      "properties": {
        "hierarchy": [
          "tgn:2181921",
          "tgn:1000001",
          "tgn:7012149",
          "tgn:2000977",
          "tgn:7007520",
          "tgn:7029392"
        ],
        "placetype": [
          "aat:300008680"
        ],
        "id": 2181921,
        "name:xx": "Blue Lake"
      }
    },
    {
      "geometry": {
        "type": "Point",
        "coordinates": [
          -91.2833,
          43.8167
        ]
      },
      "type": "Feature",
      "properties": {
        "hierarchy": [
          "tgn:2181922",
          "tgn:1000001",
          "tgn:7012149",
          "tgn:2001026",
          "tgn:7007521",
          "tgn:7029392"
        ],
        "placetype": [
          "aat:300008680"
        ],
        "id": 2181922,
        "name:xx": "Blue Lake"
      }
    },
    {
      "geometry": {
        "type": "Point",
        "coordinates": [
          -93.4167,
          44.8
        ]
      },
      "type": "Feature",
      "properties": {
        "hierarchy": [
          "tgn:2181923",
          "tgn:1000001",
          "tgn:7012149",
          "tgn:2001068",
          "tgn:7007521",
          "tgn:7029392"
        ],
        "placetype": [
          "aat:300008680"
        ],
        "id": 2181923,
        "name:xx": "Blue Lake"
      }
    },
    {
      "geometry": {
        "type": "Point",
        "coordinates": [
          -95.2667,
          47.85
        ]
      },
      "type": "Feature",
      "properties": {
        "hierarchy": [
          "tgn:2181924",
          "tgn:1000001",
          "tgn:2001013",
          "tgn:7012149",
          "tgn:7007521",
          "tgn:7029392"
        ],
        "placetype": [
          "aat:300008680"
        ],
        "id": 2181924,
        "name:xx": "Blue Lake"
      }
    },
    {
      "geometry": {
        "type": "Point",
        "coordinates": [
          -94.15,
          46.7833
        ]
      },
      "type": "Feature",
      "properties": {
        "hierarchy": [
          "tgn:2181925",
          "tgn:1000001",
          "tgn:2001016",
          "tgn:7012149",
          "tgn:7007521",
          "tgn:7029392"
        ],
        "placetype": [
          "aat:300008905"
        ],
        "id": 2181925,
        "name:xx": "Blue Lake"
      }
    },
    {
      "geometry": {
        "type": "Point",
        "coordinates": [
          -93.5,
          45.4667
        ]
      },
      "type": "Feature",
      "properties": {
        "hierarchy": [
          "tgn:2181926",
          "tgn:1000001",
          "tgn:7012149",
          "tgn:2001028",
          "tgn:7007521",
          "tgn:7029392"
        ],
        "placetype": [
          "aat:300008680"
        ],
        "id": 2181926,
        "name:xx": "Blue Lake"
      }
    },
    {
      "geometry": {
        "type": "Point",
        "coordinates": [
          -93.75,
          46.5
        ]
      },
      "type": "Feature",
      "properties": {
        "hierarchy": [
          "tgn:2181927",
          "tgn:2000999",
          "tgn:1000001",
          "tgn:7012149",
          "tgn:7007521",
          "tgn:7029392"
        ],
        "placetype": [
          "aat:300008680"
        ],
        "id": 2181927,
        "name:xx": "Blue Lake"
      }
    },
    {
      "geometry": {
        "type": "Point",
        "coordinates": [
          -93.9833,
          46.7667
        ]
      },
      "type": "Feature",
      "properties": {
        "hierarchy": [
          "tgn:2181928",
          "tgn:1000001",
          "tgn:2001016",
          "tgn:7012149",
          "tgn:7007521",
          "tgn:7029392"
        ],
        "placetype": [
          "aat:300008680"
        ],
        "id": 2181928,
        "name:xx": "Blue Lake"
      }
    },
    {
      "geometry": {
        "type": "Point",
        "coordinates": [
          -95,
          47.0167
        ]
      },
      "type": "Feature",
      "properties": {
        "hierarchy": [
          "tgn:2181929",
          "tgn:1000001",
          "tgn:7012149",
          "tgn:2001027",
          "tgn:7007521",
          "tgn:7029392"
        ],
        "placetype": [
          "aat:300008680"
        ],
        "id": 2181929,
        "name:xx": "Blue Lake"
      }
    }
  ]
}
