{
  "geometry": {
    "type": "Point",
    "coordinates": [
      -83.15,
      35.3667
    ]
  },
  "type": "Feature",
  "properties": {
    "hierarchy": [
      "tgn:2255482",
      "tgn:1000001",
      "tgn:7012149",
      "tgn:2001508",
      "tgn:7007709",
      "tgn:7029392"
    ],
    "placetype": [
      "aat:300008706"
    ],
    "id": 2255482,
    "name:xx": "Cope Creek"
  }
}
