{
  "geometry": {
    "type": "Point",
    "coordinates": [
      -76.3667,
      38.8333
    ]
  },
  "type": "Feature",
  "properties": {
    "hierarchy": [
      "tgn:2180561",
      "tgn:1000001",
      "tgn:2124025",
      "tgn:7012149",
      "tgn:7007516",
      "tgn:7029392"
    ],
    "placetype": [
      "aat:300132316"
    ],
    "id": 2180561,
    "name:xx": "Bloody Point Creek"
  }
}
