{
  "type": "FeatureCollection",
  "features": [
    {
      "geometry": {
        "type": "Point",
        "coordinates": [
          -85.2333,
          35.1667
        ]
      },
      "type": "Feature",
      "properties": {
        "hierarchy": [
          "tgn:2310490",
          "tgn:1000001",
          "tgn:7012149",
          "tgn:2001869",
          "tgn:7007825",
          "tgn:7029392"
        ],
        "placetype": [
          "aat:300008347"
        ],
        "id": 2310490,
        "name:xx": "Echo Glen"
      }
    },
    {
      "geometry": {
        "type": "Point",
        "coordinates": [
          -113.7333,
          45.8833
        ]
      },
      "type": "Feature",
      "properties": {
        "hierarchy": [
          "tgn:2310491",
          "tgn:1000001",
          "tgn:7012149",
          "tgn:2001300",
          "tgn:7007524",
          "tgn:7029392"
        ],
        "placetype": [
          "aat:300008761"
        ],
        "id": 2310491,
        "name:xx": "Echo Gulch"
      }
    },
    {
      "geometry": {
        "type": "Point",
        "coordinates": [
          -112.9,
          45.7
        ]
      },
      "type": "Feature",
      "properties": {
        "hierarchy": [
          "tgn:2310492",
          "tgn:1000001",
          "tgn:2001260",
          "tgn:7012149",
          "tgn:7007524",
          "tgn:7029392"
        ],
        "placetype": [
          "aat:300008761"
        ],
        "id": 2310492,
        "name:xx": "Echo Gulch"
      }
    },
    {
      "geometry": {
        "type": "Point",
        "coordinates": [
          -88.2667,
          46.8167
        ]
      },
      "type": "Feature",
      "properties": {
        "hierarchy": [
          "tgn:2310493",
          "tgn:2000947",
          "tgn:1000001",
          "tgn:7012149",
          "tgn:7007520",
          "tgn:7029392"
        ],
        "placetype": [
          "aat:300132316"
        ],
        "id": 2310493,
        "name:xx": "Echo Harbor"
      }
    },
    {
      "geometry": {
        "type": "Point",
        "coordinates": [
          -87.5,
          33.1833
        ]
      },
      "type": "Feature",
      "properties": {
        "hierarchy": [
          "tgn:2310494",
          "tgn:7002659",
          "tgn:1000001",
          "tgn:7012149",
          "tgn:2000062",
          "tgn:7029392"
        ],
        "placetype": [
          "aat:300008347"
        ],
        "id": 2310494,
        "name:xx": "Echo Hill"
      }
    },
    {
      "geometry": {
        "type": "Point",
        "coordinates": [
          -76.1,
          39.35
        ]
      },
      "type": "Feature",
      "properties": {
        "hierarchy": [
          "tgn:2310495",
          "tgn:1000001",
          "tgn:1002539",
          "tgn:7012149",
          "tgn:7007516",
          "tgn:7029392"
        ],
        "placetype": [
          "aat:300008347"
        ],
        "id": 2310495,
        "name:xx": "Echo Hill"
      }
    },
    {
      "geometry": {
        "type": "Point",
        "coordinates": [
          -72.0833,
          43.95
        ]
      },
      "type": "Feature",
      "properties": {
        "hierarchy": [
          "tgn:2310496",
          "tgn:1000001",
          "tgn:2001424",
          "tgn:7012149",
          "tgn:7007564",
          "tgn:7029392"
        ],
        "placetype": [
          "aat:300008798"
        ],
        "id": 2310496,
        "name:xx": "Echo Hill"
      }
    },
    {
      "geometry": {
        "type": "Point",
        "coordinates": [
          -86.1,
          33.5833
        ]
      },
      "type": "Feature",
      "properties": {
        "hierarchy": [
          "tgn:2310497",
          "tgn:7002659",
          "tgn:1000001",
          "tgn:7012149",
          "tgn:2000060",
          "tgn:7029392"
        ],
        "placetype": [
          "aat:300008347"
        ],
        "id": 2310497,
        "name:xx": "Echo Hills"
      }
    },
    {
      "geometry": {
        "type": "Point",
        "coordinates": [
          -114.5,
          36.25
        ]
      },
      "type": "Feature",
      "properties": {
        "hierarchy": [
          "tgn:2310498",
          "tgn:1000001",
          "tgn:2001410",
          "tgn:7012149",
          "tgn:7007526",
          "tgn:7029392"
        ],
        "placetype": [
          "aat:300008798"
        ],
        "id": 2310498,
        "name:xx": "Echo Hills"
      }
    },
    {
      "geometry": {
        "type": "Point",
        "coordinates": [
          -82.6,
          35.5833
        ]
      },
      "type": "Feature",
      "properties": {
        "hierarchy": [
          "tgn:2310499",
          "tgn:1000001",
          "tgn:2001473",
          "tgn:7012149",
          "tgn:7007709",
          "tgn:7029392"
        ],
        "placetype": [
          "aat:300008347"
        ],
        "id": 2310499,
        "name:xx": "Echo Hills"
      }
    }
  ]
}
