{
  "geometry": {
    "type": "Point",
    "coordinates": [
      -67.6667,
      58.25
    ]
  },
  "type": "Feature",
  "properties": {
    "hierarchy": [
      "tgn:1121631",
      "tgn:7005685",
      "tgn:1000001",
      "tgn:7005804",
      "tgn:7029392"
    ],
    "placetype": [
      "aat:300008707"
    ],
    "id": 1121631,
    "name:xx": "Baleine, Rivière à la"
  }
}
