{
  "geometry": {
    "type": "Point",
    "coordinates": [
      31.159045,
      29.97189
    ]
  },
  "type": "Feature",
  "properties": {
    "hierarchy": [
      "tgn:7538010",
      "tgn:7001242",
      "tgn:7016833",
      "tgn:1001083",
      "tgn:7029392"
    ],
    "placetype": [
      "aat:300008347"
    ],
    "name:en": "Nazlat al Baţrān",
    "id": 7538010
  }
}
