{
  "geometry": {
    "type": "Point",
    "coordinates": [
      23.05,
      47.1833
    ]
  },
  "type": "Feature",
  "properties": {
    "hierarchy": [
      "tgn:1050342",
      "tgn:1000003",
      "tgn:1000441",
      "tgn:1000091",
      "tgn:7029392"
    ],
    "placetype": [
      "aat:300008347",
      "aat:300008416",
      "aat:300008375",
      "aat:300387270",
      "aat:300387285"
    ],
    "id": 1050342,
    "name:xx": "Zalău"
  }
}
