{
  "geometry": {
    "type": "Point",
    "coordinates": [
      -117.0667,
      47.5667
    ]
  },
  "type": "Feature",
  "properties": {
    "hierarchy": [
      "tgn:2604055",
      "tgn:1000001",
      "tgn:7012149",
      "tgn:2002249",
      "tgn:7007920",
      "tgn:7029392"
    ],
    "placetype": [
      "aat:300008706"
    ],
    "id": 2604055,
    "name:xx": "Quinnamose Creek"
  }
}
