{
  "geometry": {
    "type": "Point",
    "coordinates": [
      -81.7833,
      39.6167
    ]
  },
  "type": "Feature",
  "properties": {
    "hierarchy": [
      "tgn:2490764",
      "tgn:1000001",
      "tgn:7012149",
      "tgn:2001618",
      "tgn:7007706",
      "tgn:7029392"
    ],
    "placetype": [
      "aat:300008699"
    ],
    "id": 2490764,
    "name:xx": "Manns Run"
  }
}
