{
  "geometry": {
    "type": "Point",
    "coordinates": [
      31.240425,
      30.04312
    ]
  },
  "type": "Feature",
  "properties": {
    "hierarchy": [
      "tgn:7532896",
      "tgn:7001242",
      "tgn:7016833",
      "tgn:1001091",
      "tgn:7029392"
    ],
    "placetype": [
      "aat:300004792"
    ],
    "id": 7532896,
    "name:xx": "Sintrāl Bāb al Lūq"
  }
}
