{
  "geometry": {
    "type": "Point",
    "coordinates": [
      -92.6667,
      35.25
    ]
  },
  "type": "Feature",
  "properties": {
    "hierarchy": [
      "tgn:2009533",
      "tgn:1000001",
      "tgn:7016172",
      "tgn:2000119",
      "tgn:7012149",
      "tgn:7029392"
    ],
    "placetype": [
      "aat:300008347"
    ],
    "id": 2009533,
    "name:xx": "Solgohachia"
  }
}
