{
  "type": "FeatureCollection",
  "features": [
    {
      "geometry": {
        "type": "Point",
        "coordinates": [
          8.533333,
          45.133333
        ]
      },
      "type": "Feature",
      "properties": {
        "hierarchy": [
          "tgn:4004060",
          "tgn:1003428",
          "tgn:1000003",
          "tgn:7003120",
          "tgn:1000080",
          "tgn:7029392"
        ],
        "placetype": [
          "aat:300008347"
        ],
        "id": 4004060,
        "name:xx": "Frassineto Po"
      }
    },
    {
      "geometry": {
        "type": "Point",
        "coordinates": [
          13.442222,
          45.908611
        ]
      },
      "type": "Feature",
      "properties": {
        "hierarchy": [
          "tgn:4004061",
          "tgn:1003459",
          "tgn:1000003",
          "tgn:7002993",
          "tgn:1000080",
          "tgn:7029392"
        ],
        "placetype": [
          "aat:300008347"
        ],
        "id": 4004061,
        "name:xx": "Fratta"
      }
    },
    {
      "geometry": {
        "type": "Point",
        "coordinates": [
          11.633333,
          45.033333
        ]
      },
      "type": "Feature",
      "properties": {
        "hierarchy": [
          "tgn:4004062",
          "tgn:7002995",
          "tgn:1000003",
          "tgn:7002997",
          "tgn:1000080",
          "tgn:7029392"
        ],
        "placetype": [
          "aat:300008347"
        ],
        "id": 4004062,
        "name:xx": "Fratta Polesine"
      }
    },
    {
      "geometry": {
        "type": "Point",
        "coordinates": [
          12.433333,
          47.866667
        ]
      },
      "type": "Feature",
      "properties": {
        "hierarchy": [
          "tgn:4004063",
          "tgn:7003669",
          "tgn:1000003",
          "tgn:7000084",
          "tgn:7029392"
        ],
        "placetype": [
          "aat:300008347"
        ],
        "id": 4004063,
        "name:xx": "Frauenchiemsee"
      }
    },
    {
      "geometry": {
        "type": "Point",
        "coordinates": [
          9.8,
          46.7833
        ]
      },
      "type": "Feature",
      "properties": {
        "hierarchy": [
          "tgn:4004065",
          "tgn:7003748",
          "tgn:1000003",
          "tgn:7011731",
          "tgn:7029392"
        ],
        "placetype": [
          "aat:300008347"
        ],
        "id": 4004065,
        "name:xx": "Frauenkirch"
      }
    }
  ]
}
