{
  "geometry": {
    "type": "Point",
    "coordinates": [
      -96.3167,
      36.5333
    ]
  },
  "type": "Feature",
  "properties": {
    "hierarchy": [
      "tgn:2737364",
      "tgn:1000001",
      "tgn:7012149",
      "tgn:2001679",
      "tgn:7007707",
      "tgn:7029392"
    ],
    "placetype": [
      "aat:300008706"
    ],
    "id": 2737364,
    "name:xx": "Twomile Creek"
  }
}
