{
  "geometry": {
    "type": "Point",
    "coordinates": [
      3.65,
      51.35
    ]
  },
  "type": "Feature",
  "properties": {
    "hierarchy": [
      "tgn:7270850",
      "tgn:1000003",
      "tgn:7003635",
      "tgn:7016845",
      "tgn:7029392"
    ],
    "placetype": [
      "aat:300006163"
    ],
    "name:nl": "Sint-Pieterspolder",
    "id": 7270850
  }
}
