{
  "geometry": {
    "type": "Point",
    "coordinates": [
      73.5833,
      34.3333
    ]
  },
  "type": "Feature",
  "properties": {
    "hierarchy": [
      "tgn:1125599",
      "tgn:1000004",
      "tgn:7029392"
    ],
    "placetype": [
      "aat:300008707"
    ],
    "id": 1125599,
    "name:xx": "Kishen Ganga"
  }
}
