{
  "type": "FeatureCollection",
  "features": [
    {
      "geometry": {
        "type": "Point",
        "coordinates": [
          9.206111,
          49.168056
        ]
      },
      "type": "Feature",
      "properties": {
        "hierarchy": [
          "tgn:1126030",
          "tgn:7003692",
          "tgn:1000003",
          "tgn:7000084",
          "tgn:7029392"
        ],
        "placetype": [
          "aat:300008707",
          "aat:300008699"
        ],
        "id": 1126030,
        "name:xx": "Lein"
      }
    },
    {
      "geometry": {
        "type": "Point",
        "coordinates": [
          9.6,
          52.716667
        ]
      },
      "type": "Feature",
      "properties": {
        "hierarchy": [
          "tgn:1126031",
          "tgn:1000003",
          "tgn:7003676",
          "tgn:7000084",
          "tgn:7029392"
        ],
        "placetype": [
          "aat:300008707",
          "aat:300008699"
        ],
        "id": 1126031,
        "name:xx": "Leine"
      }
    },
    {
      "geometry": {
        "type": "Point",
        "coordinates": [
          -75.6333,
          39.2167
        ]
      },
      "type": "Feature",
      "properties": {
        "hierarchy": [
          "tgn:1126032",
          "tgn:1002538",
          "tgn:1000001",
          "tgn:7012149",
          "tgn:7007239",
          "tgn:7029392"
        ],
        "placetype": [
          "aat:300008707"
        ],
        "id": 1126032,
        "name:xx": "Leipsic"
      }
    },
    {
      "geometry": {
        "type": "Point",
        "coordinates": [
          -3.166667,
          55.983333
        ]
      },
      "type": "Feature",
      "properties": {
        "hierarchy": [
          "tgn:1126033",
          "tgn:7002444",
          "tgn:1000003",
          "tgn:7008591",
          "tgn:7029392"
        ],
        "placetype": [
          "aat:300008707",
          "aat:300008699"
        ],
        "name:en": "Leith, Water of",
        "id": 1126033
      }
    },
    {
      "geometry": {
        "type": "Point",
        "coordinates": [
          4.75,
          51.9167
        ]
      },
      "type": "Feature",
      "properties": {
        "hierarchy": [
          "tgn:1126036",
          "tgn:1000003",
          "tgn:7016845",
          "tgn:7029392"
        ],
        "placetype": [
          "aat:300008707"
        ],
        "id": 1126036,
        "name:xx": "Lek"
      }
    },
    {
      "geometry": {
        "type": "Point",
        "coordinates": [
          -6.15,
          35.2
        ]
      },
      "type": "Feature",
      "properties": {
        "hierarchy": [
          "tgn:1126037",
          "tgn:7001242",
          "tgn:1000179",
          "tgn:7593695",
          "tgn:7029392"
        ],
        "placetype": [
          "aat:300008707"
        ],
        "id": 1126037,
        "name:xx": "Loukkos, Oued"
      }
    },
    {
      "geometry": {
        "type": "Point",
        "coordinates": [
          12.9,
          45.6167
        ]
      },
      "type": "Feature",
      "properties": {
        "hierarchy": [
          "tgn:1126039",
          "tgn:1000003",
          "tgn:1000080",
          "tgn:7029392"
        ],
        "placetype": [
          "aat:300008707"
        ],
        "id": 1126039,
        "name:it": "Lemene"
      }
    }
  ]
}
