{
  "geometry": {
    "type": "Point",
    "coordinates": [
      -104.85,
      31.95
    ]
  },
  "type": "Feature",
  "properties": {
    "hierarchy": [
      "tgn:7022693",
      "tgn:1000001",
      "tgn:7012149",
      "tgn:7029392"
    ],
    "placetype": [
      "aat:300008761"
    ],
    "id": 7022693,
    "name:xx": "West Dog Canyon"
  }
}
