{
  "geometry": {
    "type": "Point",
    "coordinates": [
      -88.8833,
      38.3833
    ]
  },
  "type": "Feature",
  "properties": {
    "hierarchy": [
      "tgn:2514648",
      "tgn:1000001",
      "tgn:7012149",
      "tgn:1002514",
      "tgn:7007251",
      "tgn:7029392"
    ],
    "placetype": [
      "aat:300006191"
    ],
    "id": 2514648,
    "name:xx": "Miller Lake"
  }
}
