{
  "geometry": {
    "type": "Point",
    "coordinates": [
      -91.55,
      38.45
    ]
  },
  "type": "Feature",
  "properties": {
    "hierarchy": [
      "tgn:2195230",
      "tgn:1000001",
      "tgn:7012149",
      "tgn:1002402",
      "tgn:7007523",
      "tgn:7029392"
    ],
    "placetype": [
      "aat:300008706"
    ],
    "id": 2195230,
    "name:xx": "Brinkman Creek"
  }
}
