{
  "geometry": {
    "type": "Point",
    "coordinates": [
      -93.7333,
      32.65
    ]
  },
  "type": "Feature",
  "properties": {
    "hierarchy": [
      "tgn:2773835",
      "tgn:1000001",
      "tgn:2000861",
      "tgn:7012149",
      "tgn:7007256",
      "tgn:7029392"
    ],
    "placetype": [
      "aat:300008347"
    ],
    "id": 2773835,
    "name:xx": "Willow Chute"
  }
}
