{
  "geometry": {
    "type": "Point",
    "coordinates": [
      0.3667,
      45.2333
    ]
  },
  "type": "Feature",
  "properties": {
    "hierarchy": [
      "tgn:7009466",
      "tgn:7002878",
      "tgn:1000003",
      "tgn:1000070",
      "tgn:7029392"
    ],
    "placetype": [
      "aat:300008347"
    ],
    "id": 7009466,
    "name:xx": "Ribérac"
  }
}
