{
  "type": "FeatureCollection",
  "features": [
    {
      "geometry": {
        "type": "Point",
        "coordinates": [
          -109.1667,
          36.8
        ]
      },
      "type": "Feature",
      "properties": {
        "hierarchy": [
          "tgn:1108870",
          "tgn:1000001",
          "tgn:7012149",
          "tgn:7029392"
        ],
        "placetype": [
          "aat:300008795"
        ],
        "id": 1108870,
        "name:xx": "Carrizo Mountains"
      }
    },
    {
      "geometry": {
        "type": "Point",
        "coordinates": [
          -121,
          49.3333
        ]
      },
      "type": "Feature",
      "properties": {
        "hierarchy": [
          "tgn:1108871",
          "tgn:7005735",
          "tgn:7005685",
          "tgn:1000001",
          "tgn:7029392"
        ],
        "placetype": [
          "aat:300008795"
        ],
        "id": 1108871,
        "name:xx": "Cascade Mountains"
      }
    },
    {
      "geometry": {
        "type": "Point",
        "coordinates": [
          -129,
          59
        ]
      },
      "type": "Feature",
      "properties": {
        "hierarchy": [
          "tgn:1108872",
          "tgn:7005685",
          "tgn:1000001",
          "tgn:7029392"
        ],
        "placetype": [
          "aat:300008795"
        ],
        "id": 1108872,
        "name:xx": "Cassiar Mountains"
      }
    },
    {
      "geometry": {
        "type": "Point",
        "coordinates": [
          -0.983333,
          41.933333
        ]
      },
      "type": "Feature",
      "properties": {
        "hierarchy": [
          "tgn:1108873",
          "tgn:7002759",
          "tgn:7002845",
          "tgn:1000003",
          "tgn:1000095",
          "tgn:7029392"
        ],
        "placetype": [
          "aat:300386831",
          "aat:300008795"
        ],
        "id": 1108873,
        "name:xx": "Castejón, Montes de"
      }
    },
    {
      "geometry": {
        "type": "Point",
        "coordinates": [
          -100.866667,
          23.6
        ]
      },
      "type": "Feature",
      "properties": {
        "hierarchy": [
          "tgn:1108875",
          "tgn:1000001",
          "tgn:7005594",
          "tgn:7005560",
          "tgn:7029392"
        ],
        "placetype": [
          "aat:300008795"
        ],
        "id": 1108875,
        "name:xx": "Catorce, Sierra de"
      }
    },
    {
      "geometry": {
        "type": "Point",
        "coordinates": [
          -66.0333,
          18.1167
        ]
      },
      "type": "Feature",
      "properties": {
        "hierarchy": [
          "tgn:1108877",
          "tgn:7017441",
          "tgn:1000001",
          "tgn:7004643",
          "tgn:7029392"
        ],
        "placetype": [
          "aat:300008795"
        ],
        "id": 1108877,
        "name:xx": "Cayey, Sierra de"
      }
    },
    {
      "geometry": {
        "type": "Point",
        "coordinates": [
          -83.972,
          10.021
        ]
      },
      "type": "Feature",
      "properties": {
        "hierarchy": [
          "tgn:1108879",
          "tgn:1000001",
          "tgn:7005364",
          "tgn:7029392"
        ],
        "placetype": [
          "aat:300386831"
        ],
        "id": 1108879,
        "name:xx": "Central, Cordillera"
      }
    }
  ]
}
