{
  "geometry": {
    "type": "Point",
    "coordinates": [
      115.65,
      38.9667
    ]
  },
  "type": "Feature",
  "properties": {
    "hierarchy": [
      "tgn:1070577",
      "tgn:1000004",
      "tgn:7002077",
      "tgn:1000111",
      "tgn:7029392"
    ],
    "placetype": [
      "aat:300008347"
    ],
    "id": 1070577,
    "name:xx": "Nanbaita"
  }
}
