{
  "geometry": {
    "type": "Point",
    "coordinates": [
      -95.4167,
      32.5167
    ]
  },
  "type": "Feature",
  "properties": {
    "hierarchy": [
      "tgn:2694648",
      "tgn:1000001",
      "tgn:7012149",
      "tgn:1002898",
      "tgn:7007826",
      "tgn:7029392"
    ],
    "placetype": [
      "aat:300006191"
    ],
    "id": 2694648,
    "name:xx": "Stewart Lakes"
  }
}
