{
  "geometry": {
    "type": "Point",
    "coordinates": [
      -98.2333,
      30.6333
    ]
  },
  "type": "Feature",
  "properties": {
    "hierarchy": [
      "tgn:2513646",
      "tgn:1000001",
      "tgn:7012149",
      "tgn:2001949",
      "tgn:7007826",
      "tgn:7029392"
    ],
    "placetype": [
      "aat:300008680"
    ],
    "id": 2513646,
    "name:xx": "Mill Pond"
  }
}
