{
  "type": "FeatureCollection",
  "features": [
    {
      "geometry": {
        "type": "Point",
        "coordinates": [
          30.984921,
          30.463187
        ]
      },
      "type": "Feature",
      "properties": {
        "hierarchy": [
          "tgn:7520701",
          "tgn:7001242",
          "tgn:7016833",
          "tgn:1001087",
          "tgn:7029392"
        ],
        "placetype": [
          "aat:300008347"
        ],
        "name:en": "Al Kawm al Aḩmar",
        "id": 7520701
      }
    },
    {
      "geometry": {
        "type": "Point",
        "coordinates": [
          31.269167,
          30.283333
        ]
      },
      "type": "Feature",
      "properties": {
        "hierarchy": [
          "tgn:7520702",
          "tgn:7001242",
          "tgn:7016833",
          "tgn:1001092",
          "tgn:7029392"
        ],
        "placetype": [
          "aat:300008347"
        ],
        "name:en": "Al Kawm al Aḩmar",
        "id": 7520702
      }
    },
    {
      "geometry": {
        "type": "Point",
        "coordinates": [
          31.080237,
          29.098342
        ]
      },
      "type": "Feature",
      "properties": {
        "hierarchy": [
          "tgn:7520704",
          "tgn:7001242",
          "tgn:7016833",
          "tgn:1001142",
          "tgn:7029392"
        ],
        "placetype": [
          "aat:300008347"
        ],
        "name:en": "Al Kawm al Aḩmar",
        "id": 7520704
      }
    },
    {
      "geometry": {
        "type": "Point",
        "coordinates": [
          30.866667,
          29.033333
        ]
      },
      "type": "Feature",
      "properties": {
        "hierarchy": [
          "tgn:7520705",
          "tgn:7001242",
          "tgn:7016833",
          "tgn:1001142",
          "tgn:7029392"
        ],
        "placetype": [
          "aat:300008347"
        ],
        "name:en": "Al Kawm al Aḩmar",
        "id": 7520705
      }
    },
    {
      "geometry": {
        "type": "Point",
        "coordinates": [
          31.383333,
          26.766667
        ]
      },
      "type": "Feature",
      "properties": {
        "hierarchy": [
          "tgn:7520706",
          "tgn:7001242",
          "tgn:7016833",
          "tgn:7000124",
          "tgn:7029392"
        ],
        "placetype": [
          "aat:300008347"
        ],
        "name:en": "Al Kawm al Aḩmar",
        "id": 7520706
      }
    },
    {
      "geometry": {
        "type": "Point",
        "coordinates": [
          31.829061,
          26.510085
        ]
      },
      "type": "Feature",
      "properties": {
        "hierarchy": [
          "tgn:7520707",
          "tgn:7001242",
          "tgn:7016833",
          "tgn:7000124",
          "tgn:7029392"
        ],
        "placetype": [
          "aat:300008347"
        ],
        "name:en": "Al Kawlah",
        "id": 7520707
      }
    },
    {
      "geometry": {
        "type": "Point",
        "coordinates": [
          32.716667,
          26.083333
        ]
      },
      "type": "Feature",
      "properties": {
        "hierarchy": [
          "tgn:7520708",
          "tgn:7001242",
          "tgn:7016833",
          "tgn:7000123",
          "tgn:7029392"
        ],
        "placetype": [
          "aat:300008777"
        ],
        "name:en": "Al Kawlah",
        "id": 7520708
      }
    },
    {
      "geometry": {
        "type": "Point",
        "coordinates": [
          30.7,
          26.45
        ]
      },
      "type": "Feature",
      "properties": {
        "hierarchy": [
          "tgn:7520709",
          "tgn:7001242",
          "tgn:7016833",
          "tgn:7001334",
          "tgn:7029392"
        ],
        "placetype": [
          "aat:300008347"
        ],
        "name:en": "Al Kawāmil Qiblī",
        "id": 7520709
      }
    }
  ]
}
