{
  "geometry": {
    "type": "Point",
    "coordinates": [
      31.45,
      26.983333
    ]
  },
  "type": "Feature",
  "properties": {
    "hierarchy": [
      "tgn:7537991",
      "tgn:7001242",
      "tgn:7016833",
      "tgn:1001114",
      "tgn:7029392"
    ],
    "placetype": [
      "aat:300008347"
    ],
    "name:en": "Nazlat al Kawāsitah",
    "id": 7537991
  }
}
