{
  "geometry": {
    "type": "Point",
    "coordinates": [
      -77.0667,
      40.55
    ]
  },
  "type": "Feature",
  "properties": {
    "hierarchy": [
      "tgn:2576523",
      "tgn:1000001",
      "tgn:7012149",
      "tgn:1002779",
      "tgn:7007710",
      "tgn:7029392"
    ],
    "placetype": [
      "aat:300008761"
    ],
    "id": 2576523,
    "name:xx": "Perry Valley"
  }
}
