{
  "geometry": {
    "type": "Point",
    "coordinates": [
      -149.25,
      70.5167
    ]
  },
  "type": "Feature",
  "properties": {
    "hierarchy": [
      "tgn:2184627",
      "tgn:7006450",
      "tgn:1000001",
      "tgn:7012149",
      "tgn:2124005",
      "tgn:7029392"
    ],
    "placetype": [
      "aat:300008791"
    ],
    "id": 2184627,
    "name:xx": "Bodfish Island"
  }
}
