{
  "geometry": {
    "type": "Point",
    "coordinates": [
      -123.2667,
      39.7167
    ]
  },
  "type": "Feature",
  "properties": {
    "hierarchy": [
      "tgn:2433614",
      "tgn:1000001",
      "tgn:7012149",
      "tgn:7007157",
      "tgn:2000185",
      "tgn:7029392"
    ],
    "placetype": [
      "aat:300008761"
    ],
    "id": 2433614,
    "name:xx": "Kelly Canyon"
  }
}
