{
  "geometry": {
    "type": "Point",
    "coordinates": [
      21.15,
      56.1667
    ]
  },
  "type": "Feature",
  "properties": {
    "hierarchy": [
      "tgn:1059020",
      "tgn:7012152",
      "tgn:1000003",
      "tgn:7006541",
      "tgn:7029392"
    ],
    "placetype": [
      "aat:300008347"
    ],
    "id": 1059020,
    "name:xx": "Rucava"
  }
}
