{
  "geometry": {
    "type": "Point",
    "coordinates": [
      -89.8833,
      29.65
    ]
  },
  "type": "Feature",
  "properties": {
    "hierarchy": [
      "tgn:2401387",
      "tgn:1000001",
      "tgn:7012149",
      "tgn:2000891",
      "tgn:7007256",
      "tgn:7029392"
    ],
    "placetype": [
      "aat:300006075"
    ],
    "id": 2401387,
    "name:xx": "Horsepower Canal"
  }
}
