{
  "type": "FeatureCollection",
  "features": [
    {
      "geometry": {
        "type": "Point",
        "coordinates": [
          3.583333,
          51.45
        ]
      },
      "type": "Feature",
      "properties": {
        "hierarchy": [
          "tgn:7006750",
          "tgn:1000003",
          "tgn:7003635",
          "tgn:7016845",
          "tgn:1009679",
          "tgn:7029392"
        ],
        "placetype": [
          "aat:300008347",
          "aat:300008375",
          "aat:300120599"
        ],
        "name:en": "Flushing",
        "id": 7006750
      }
    },
    {
      "geometry": {
        "type": "Point",
        "coordinates": [
          3.5,
          51.566667
        ]
      },
      "type": "Feature",
      "properties": {
        "hierarchy": [
          "tgn:7006751",
          "tgn:1000003",
          "tgn:7003635",
          "tgn:7016845",
          "tgn:1009679",
          "tgn:7029392"
        ],
        "placetype": [
          "aat:300008347"
        ],
        "name:nl": "Domburg",
        "id": 7006751
      }
    },
    {
      "geometry": {
        "type": "Point",
        "coordinates": [
          3.616667,
          51.5
        ]
      },
      "type": "Feature",
      "properties": {
        "hierarchy": [
          "tgn:7006752",
          "tgn:1000003",
          "tgn:7003635",
          "tgn:7016845",
          "tgn:1009679",
          "tgn:7029392"
        ],
        "placetype": [
          "aat:300008347",
          "aat:300387223",
          "aat:300387220"
        ],
        "name:nl": "Middelburg",
        "id": 7006752
      }
    },
    {
      "geometry": {
        "type": "Point",
        "coordinates": [
          3.666667,
          51.55
        ]
      },
      "type": "Feature",
      "properties": {
        "hierarchy": [
          "tgn:7006753",
          "tgn:1000003",
          "tgn:7003635",
          "tgn:7016845",
          "tgn:1009679",
          "tgn:7029392"
        ],
        "placetype": [
          "aat:300008347"
        ],
        "name:nl": "Veere",
        "id": 7006753
      }
    },
    {
      "geometry": {
        "type": "Point",
        "coordinates": [
          3.45,
          51.533333
        ]
      },
      "type": "Feature",
      "properties": {
        "hierarchy": [
          "tgn:7006754",
          "tgn:1000003",
          "tgn:7003635",
          "tgn:7016845",
          "tgn:1009679",
          "tgn:7029392"
        ],
        "placetype": [
          "aat:300008347"
        ],
        "name:nl": "Westkapelle",
        "id": 7006754
      }
    },
    {
      "geometry": {
        "type": "Point",
        "coordinates": [
          3.883333,
          51.5
        ]
      },
      "type": "Feature",
      "properties": {
        "hierarchy": [
          "tgn:7006755",
          "tgn:1000003",
          "tgn:7003635",
          "tgn:7016845",
          "tgn:1009815",
          "tgn:7029392"
        ],
        "placetype": [
          "aat:300008347"
        ],
        "name:nl": "Goes",
        "id": 7006755
      }
    },
    {
      "geometry": {
        "type": "Point",
        "coordinates": [
          3.666667,
          51.5
        ]
      },
      "type": "Feature",
      "properties": {
        "hierarchy": [
          "tgn:7006756",
          "tgn:1000003",
          "tgn:7003635",
          "tgn:7016845",
          "tgn:1009815",
          "tgn:7029392"
        ],
        "placetype": [
          "aat:300008347"
        ],
        "name:nl": "Arnemuiden",
        "id": 7006756
      }
    },
    {
      "geometry": {
        "type": "Point",
        "coordinates": [
          12.933333,
          42.133333
        ]
      },
      "type": "Feature",
      "properties": {
        "hierarchy": [
          "tgn:7006758",
          "tgn:7003137",
          "tgn:1000003",
          "tgn:7003080",
          "tgn:1000080",
          "tgn:7029392"
        ],
        "placetype": [
          "aat:300008347"
        ],
        "id": 7006758,
        "name:xx": "Orvinio"
      }
    }
  ]
}
