{
  "geometry": {
    "type": "Point",
    "coordinates": [
      30.2833,
      46.25
    ]
  },
  "type": "Feature",
  "properties": {
    "hierarchy": [
      "tgn:1116126",
      "tgn:1000003",
      "tgn:1003396",
      "tgn:7006660",
      "tgn:7029392"
    ],
    "placetype": [
      "aat:300008680"
    ],
    "id": 1116126,
    "name:xx": "Dnestrovskiy liman"
  }
}
