{
  "geometry": {
    "type": "Point",
    "coordinates": [
      119.4667,
      31.65
    ]
  },
  "type": "Feature",
  "properties": {
    "hierarchy": [
      "tgn:1071625",
      "tgn:1000004",
      "tgn:7002081",
      "tgn:1000111",
      "tgn:7029392"
    ],
    "placetype": [
      "aat:300008347"
    ],
    "id": 1071625,
    "name:xx": "Shetou"
  }
}
