{
  "geometry": {
    "type": "Point",
    "coordinates": [
      -100.0167,
      29.0167
    ]
  },
  "type": "Feature",
  "properties": {
    "hierarchy": [
      "tgn:2201900",
      "tgn:1000001",
      "tgn:7012149",
      "tgn:2002100",
      "tgn:7007826",
      "tgn:7029392"
    ],
    "placetype": [
      "aat:300008798"
    ],
    "id": 2201900,
    "name:xx": "Buck Hill"
  }
}
