{
  "geometry": {
    "type": "Point",
    "coordinates": [
      -119.5833,
      37.3333
    ]
  },
  "type": "Feature",
  "properties": {
    "hierarchy": [
      "tgn:2311889",
      "tgn:1000001",
      "tgn:7012149",
      "tgn:7007157",
      "tgn:1002621",
      "tgn:7029392"
    ],
    "placetype": [
      "aat:300055621"
    ],
    "id": 2311889,
    "name:xx": "Effluent Field"
  }
}
