{
  "geometry": {
    "type": "Point",
    "coordinates": [
      -97.0667,
      39.6333
    ]
  },
  "type": "Feature",
  "properties": {
    "hierarchy": [
      "tgn:2758886",
      "tgn:1000001",
      "tgn:7012149",
      "tgn:7007254",
      "tgn:7029392"
    ],
    "placetype": [
      "aat:300008706"
    ],
    "id": 2758886,
    "name:xx": "West Fancy Creek"
  }
}
