{
  "geometry": {
    "type": "Point",
    "coordinates": [
      -61.2667,
      15.5167
    ]
  },
  "type": "Feature",
  "properties": {
    "hierarchy": [
      "tgn:1113564",
      "tgn:1000001",
      "tgn:7004641",
      "tgn:7029392"
    ],
    "placetype": [
      "aat:300132316"
    ],
    "id": 1113564,
    "name:xx": "Pagua Bay"
  }
}
