{
  "type": "FeatureCollection",
  "features": [
    {
      "geometry": {
        "type": "Point",
        "coordinates": [
          -75.583333,
          -48.433333
        ]
      },
      "type": "Feature",
      "properties": {
        "hierarchy": [
          "tgn:7282320",
          "tgn:1001623",
          "tgn:1000049",
          "tgn:1000002",
          "tgn:7029392"
        ],
        "placetype": [
          "aat:300011692"
        ],
        "id": 7282320,
        "name:xx": "Promontorio, Roca"
      }
    },
    {
      "geometry": {
        "type": "Point",
        "coordinates": [
          -72.666667,
          -53.35
        ]
      },
      "type": "Feature",
      "properties": {
        "hierarchy": [
          "tgn:7282321",
          "tgn:1001702",
          "tgn:1000049",
          "tgn:1000002",
          "tgn:7029392"
        ],
        "placetype": [
          "aat:300386846"
        ],
        "id": 7282321,
        "name:xx": "Promontorio, Punta"
      }
    },
    {
      "geometry": {
        "type": "Point",
        "coordinates": [
          -73.7,
          -43.316667
        ]
      },
      "type": "Feature",
      "properties": {
        "hierarchy": [
          "tgn:7282322",
          "tgn:1001699",
          "tgn:1000049",
          "tgn:1000002",
          "tgn:7029392"
        ],
        "placetype": [
          "aat:300386846"
        ],
        "id": 7282322,
        "name:xx": "Promontorio, Punta"
      }
    },
    {
      "geometry": {
        "type": "Point",
        "coordinates": [
          -74.8,
          -52.366667
        ]
      },
      "type": "Feature",
      "properties": {
        "hierarchy": [
          "tgn:7282323",
          "tgn:1001702",
          "tgn:1000049",
          "tgn:1000002",
          "tgn:7029392"
        ],
        "placetype": [
          "aat:300008791"
        ],
        "id": 7282323,
        "name:xx": "Promontorio, Islote"
      }
    },
    {
      "geometry": {
        "type": "Point",
        "coordinates": [
          -70.133333,
          -55.016667
        ]
      },
      "type": "Feature",
      "properties": {
        "hierarchy": [
          "tgn:7282324",
          "tgn:1001702",
          "tgn:1000049",
          "tgn:1000002",
          "tgn:7029392"
        ],
        "placetype": [
          "aat:300008791"
        ],
        "id": 7282324,
        "name:xx": "Promontorio, Isla"
      }
    },
    {
      "geometry": {
        "type": "Point",
        "coordinates": [
          -72.933333,
          -53
        ]
      },
      "type": "Feature",
      "properties": {
        "hierarchy": [
          "tgn:7282325",
          "tgn:1001702",
          "tgn:1000049",
          "tgn:1000002",
          "tgn:7029392"
        ],
        "placetype": [
          "aat:300132317"
        ],
        "id": 7282325,
        "name:xx": "Promontorio, Ensenada"
      }
    },
    {
      "geometry": {
        "type": "Point",
        "coordinates": [
          -69.633333,
          -52.966667
        ]
      },
      "type": "Feature",
      "properties": {
        "hierarchy": [
          "tgn:7282326",
          "tgn:1001702",
          "tgn:1000049",
          "tgn:1000002",
          "tgn:7029392"
        ],
        "placetype": [
          "aat:300008699"
        ],
        "id": 7282326,
        "name:xx": "Progreso, Chorrillo"
      }
    },
    {
      "geometry": {
        "type": "Point",
        "coordinates": [
          -70.166667,
          -54.4
        ]
      },
      "type": "Feature",
      "properties": {
        "hierarchy": [
          "tgn:7282327",
          "tgn:1001702",
          "tgn:1000049",
          "tgn:1000002",
          "tgn:7029392"
        ],
        "placetype": [
          "aat:300008676"
        ],
        "id": 7282327,
        "name:xx": "Profundo, Seno"
      }
    },
    {
      "geometry": {
        "type": "Point",
        "coordinates": [
          -73.75,
          -53.616667
        ]
      },
      "type": "Feature",
      "properties": {
        "hierarchy": [
          "tgn:7282328",
          "tgn:1001702",
          "tgn:1000049",
          "tgn:1000002",
          "tgn:7029392"
        ],
        "placetype": [
          "aat:300132316"
        ],
        "id": 7282328,
        "name:xx": "Profundo, Seno"
      }
    },
    {
      "geometry": {
        "type": "Point",
        "coordinates": [
          -73.783333,
          -52.683333
        ]
      },
      "type": "Feature",
      "properties": {
        "hierarchy": [
          "tgn:7282329",
          "tgn:1001702",
          "tgn:1000049",
          "tgn:1000002",
          "tgn:7029392"
        ],
        "placetype": [
          "aat:300008678"
        ],
        "id": 7282329,
        "name:xx": "Profundo, Puerto"
      }
    }
  ]
}
