{
  "geometry": {
    "type": "Point",
    "coordinates": [
      -97.6333,
      33.3667
    ]
  },
  "type": "Feature",
  "properties": {
    "hierarchy": [
      "tgn:2193821",
      "tgn:1000001",
      "tgn:7012149",
      "tgn:1003031",
      "tgn:7007826",
      "tgn:7029392"
    ],
    "placetype": [
      "aat:300008699"
    ],
    "id": 2193821,
    "name:xx": "Briar Branch"
  }
}
