{
  "geometry": {
    "type": "Point",
    "coordinates": [
      -56.25,
      48.3333
    ]
  },
  "type": "Feature",
  "properties": {
    "hierarchy": [
      "tgn:1116481",
      "tgn:7005685",
      "tgn:7005807",
      "tgn:1000001",
      "tgn:7005801",
      "tgn:7029392"
    ],
    "placetype": [
      "aat:300008680"
    ],
    "id": 1116481,
    "name:xx": "Great Burnt Lake"
  }
}
