{
  "geometry": {
    "type": "Point",
    "coordinates": [
      -114.6167,
      36.0833
    ]
  },
  "type": "Feature",
  "properties": {
    "hierarchy": [
      "tgn:2220161",
      "tgn:1000001",
      "tgn:7006451",
      "tgn:7012149",
      "tgn:2000098",
      "tgn:7029392"
    ],
    "placetype": [
      "aat:300266640"
    ],
    "id": 2220161,
    "name:xx": "Canyon Ridge"
  }
}
