{
  "geometry": {
    "type": "Point",
    "coordinates": [
      -84.3167,
      39.0167
    ]
  },
  "type": "Feature",
  "properties": {
    "hierarchy": [
      "tgn:2041100",
      "tgn:1000001",
      "tgn:1002231",
      "tgn:7012149",
      "tgn:7007255",
      "tgn:7029392"
    ],
    "placetype": [
      "aat:300008347"
    ],
    "id": 2041100,
    "name:xx": "Ross"
  }
}
