{
  "geometry": {
    "type": "Point",
    "coordinates": [
      47.0167,
      -23.5833
    ]
  },
  "type": "Feature",
  "properties": {
    "hierarchy": [
      "tgn:1090980",
      "tgn:7001242",
      "tgn:7000556",
      "tgn:1000173",
      "tgn:7029392"
    ],
    "placetype": [
      "aat:300008347"
    ],
    "id": 1090980,
    "name:xx": "Midongy Sud"
  }
}
