{
  "geometry": {
    "type": "Point",
    "coordinates": [
      -122.4167,
      39.0333
    ]
  },
  "type": "Feature",
  "properties": {
    "hierarchy": [
      "tgn:2317406",
      "tgn:1000001",
      "tgn:7012149",
      "tgn:1002296",
      "tgn:7007157",
      "tgn:7029392"
    ],
    "placetype": [
      "aat:300000390"
    ],
    "id": 2317406,
    "name:xx": "Empire Mine"
  }
}
