{
  "type": "FeatureCollection",
  "features": [
    {
      "geometry": {
        "type": "Point",
        "coordinates": [
          -118.2833,
          36.5
        ]
      },
      "type": "Feature",
      "properties": {
        "hierarchy": [
          "tgn:2422880",
          "tgn:1000001",
          "tgn:7012149",
          "tgn:7007157",
          "tgn:1002956",
          "tgn:7029392"
        ],
        "placetype": [
          "aat:300008798"
        ],
        "id": 2422880,
        "name:xx": "Joe Devel Peak"
      }
    },
    {
      "geometry": {
        "type": "Point",
        "coordinates": [
          -147.05,
          66.4167
        ]
      },
      "type": "Feature",
      "properties": {
        "hierarchy": [
          "tgn:2422881",
          "tgn:7006450",
          "tgn:1000001",
          "tgn:7012149",
          "tgn:2000089",
          "tgn:7029392"
        ],
        "placetype": [
          "aat:300008791"
        ],
        "id": 2422881,
        "name:xx": "Joe Devlin Island"
      }
    },
    {
      "geometry": {
        "type": "Point",
        "coordinates": [
          -81.5167,
          33
        ]
      },
      "type": "Feature",
      "properties": {
        "hierarchy": [
          "tgn:2422882",
          "tgn:1000001",
          "tgn:7012149",
          "tgn:2000415",
          "tgn:7007248",
          "tgn:7029392"
        ],
        "placetype": [
          "aat:300008699"
        ],
        "id": 2422882,
        "name:xx": "Joe Ditch"
      }
    },
    {
      "geometry": {
        "type": "Point",
        "coordinates": [
          -105.7,
          42.2333
        ]
      },
      "type": "Feature",
      "properties": {
        "hierarchy": [
          "tgn:2422883",
          "tgn:2002365",
          "tgn:1000001",
          "tgn:7012149",
          "tgn:7007923",
          "tgn:7029392"
        ],
        "placetype": [
          "aat:300006075"
        ],
        "id": 2422883,
        "name:xx": "Joe Ditch"
      }
    },
    {
      "geometry": {
        "type": "Point",
        "coordinates": [
          -103.4667,
          43.9333
        ]
      },
      "type": "Feature",
      "properties": {
        "hierarchy": [
          "tgn:2422884",
          "tgn:1000001",
          "tgn:7012149",
          "tgn:2001821",
          "tgn:7007713",
          "tgn:7029392"
        ],
        "placetype": [
          "aat:300008761"
        ],
        "id": 2422884,
        "name:xx": "Joe Dollar Gulch"
      }
    },
    {
      "geometry": {
        "type": "Point",
        "coordinates": [
          -114.8167,
          47
        ]
      },
      "type": "Feature",
      "properties": {
        "hierarchy": [
          "tgn:2422885",
          "tgn:1000001",
          "tgn:7012149",
          "tgn:2001290",
          "tgn:7007524",
          "tgn:7029392"
        ],
        "placetype": [
          "aat:300000390"
        ],
        "id": 2422885,
        "name:xx": "Joe Doris Mine"
      }
    },
    {
      "geometry": {
        "type": "Point",
        "coordinates": [
          -81.7167,
          36.7
        ]
      },
      "type": "Feature",
      "properties": {
        "hierarchy": [
          "tgn:2422886",
          "tgn:1000001",
          "tgn:7012149",
          "tgn:2002194",
          "tgn:7007919",
          "tgn:7029392"
        ],
        "placetype": [
          "aat:300008761"
        ],
        "id": 2422886,
        "name:xx": "Joe Doss Hollow"
      }
    },
    {
      "geometry": {
        "type": "Point",
        "coordinates": [
          -87.3833,
          32.6
        ]
      },
      "type": "Feature",
      "properties": {
        "hierarchy": [
          "tgn:2422887",
          "tgn:7002659",
          "tgn:1000001",
          "tgn:7012149",
          "tgn:2000052",
          "tgn:7029392"
        ],
        "placetype": [
          "aat:300006191"
        ],
        "id": 2422887,
        "name:xx": "Joe Dozier Lake"
      }
    },
    {
      "geometry": {
        "type": "Point",
        "coordinates": [
          -84.7167,
          41.7833
        ]
      },
      "type": "Feature",
      "properties": {
        "hierarchy": [
          "tgn:2422888",
          "tgn:1000001",
          "tgn:7012149",
          "tgn:1002481",
          "tgn:7007520",
          "tgn:7029392"
        ],
        "placetype": [
          "aat:300008699"
        ],
        "id": 2422888,
        "name:xx": "Joe Drain"
      }
    },
    {
      "geometry": {
        "type": "Point",
        "coordinates": [
          -106.8167,
          44.9333
        ]
      },
      "type": "Feature",
      "properties": {
        "hierarchy": [
          "tgn:2422889",
          "tgn:1000001",
          "tgn:7012149",
          "tgn:2002381",
          "tgn:7007923",
          "tgn:7029392"
        ],
        "placetype": [
          "aat:300008761"
        ],
        "id": 2422889,
        "name:xx": "Joe Draw"
      }
    }
  ]
}
