{
  "geometry": {
    "type": "Point",
    "coordinates": [
      26.745,
      37.7275
    ]
  },
  "type": "Feature",
  "properties": {
    "hierarchy": [
      "tgn:7221246",
      "tgn:7011164",
      "tgn:7002674",
      "tgn:1000003",
      "tgn:1000074",
      "tgn:7029392"
    ],
    "placetype": [
      "aat:300007466"
    ],
    "id": 7221246,
    "name:xx": "Profítis Ilías"
  }
}
