{
  "type": "FeatureCollection",
  "features": [
    {
      "geometry": {
        "type": "Point",
        "coordinates": [
          -1.85,
          51.883333
        ]
      },
      "type": "Feature",
      "properties": {
        "hierarchy": [
          "tgn:7456920",
          "tgn:7002445",
          "tgn:1000003",
          "tgn:7008132",
          "tgn:7008591",
          "tgn:7029392"
        ],
        "placetype": [
          "aat:300007783"
        ],
        "name:en": "Notgrove Station",
        "id": 7456920
      }
    },
    {
      "geometry": {
        "type": "Point",
        "coordinates": [
          -1.033333,
          60.166667
        ]
      },
      "type": "Feature",
      "properties": {
        "hierarchy": [
          "tgn:7456922",
          "tgn:7002444",
          "tgn:1000003",
          "tgn:7029508",
          "tgn:7008591",
          "tgn:7029392"
        ],
        "placetype": [
          "aat:300266558"
        ],
        "name:en": "Noss Sound",
        "id": 7456922
      }
    },
    {
      "geometry": {
        "type": "Point",
        "coordinates": [
          -1,
          60.133333
        ]
      },
      "type": "Feature",
      "properties": {
        "hierarchy": [
          "tgn:7456923",
          "tgn:7002444",
          "tgn:1000003",
          "tgn:7029508",
          "tgn:7008591",
          "tgn:7029392"
        ],
        "placetype": [
          "aat:300386846"
        ],
        "name:en": "Noss Head",
        "id": 7456923
      }
    },
    {
      "geometry": {
        "type": "Point",
        "coordinates": [
          -0.366667,
          51.5
        ]
      },
      "type": "Feature",
      "properties": {
        "hierarchy": [
          "tgn:7456926",
          "tgn:7002445",
          "tgn:7018913",
          "tgn:1000003",
          "tgn:7008136",
          "tgn:7008591",
          "tgn:7029392"
        ],
        "placetype": [
          "aat:300000773"
        ],
        "name:en": "Norwood",
        "id": 7456926
      }
    },
    {
      "geometry": {
        "type": "Point",
        "coordinates": [
          -0.084035,
          51.419203
        ]
      },
      "type": "Feature",
      "properties": {
        "hierarchy": [
          "tgn:7456927",
          "tgn:7002445",
          "tgn:7026536",
          "tgn:1000003",
          "tgn:7008136",
          "tgn:7008591",
          "tgn:7029392"
        ],
        "placetype": [
          "aat:300008347"
        ],
        "name:en": "Norwood",
        "id": 7456927
      }
    },
    {
      "geometry": {
        "type": "Point",
        "coordinates": [
          -0.783333,
          60.816667
        ]
      },
      "type": "Feature",
      "properties": {
        "hierarchy": [
          "tgn:7456928",
          "tgn:7002444",
          "tgn:1000003",
          "tgn:7029508",
          "tgn:7008591",
          "tgn:7029392"
        ],
        "placetype": [
          "aat:300132316"
        ],
        "name:en": "Nor Wick",
        "id": 7456928
      }
    }
  ]
}
