{
  "geometry": {
    "type": "Point",
    "coordinates": [
      -90.2833,
      42.9667
    ]
  },
  "type": "Feature",
  "properties": {
    "hierarchy": [
      "tgn:2700678",
      "tgn:1000001",
      "tgn:7012149",
      "tgn:2002326",
      "tgn:7007922",
      "tgn:7029392"
    ],
    "placetype": [
      "aat:300008699"
    ],
    "id": 2700678,
    "name:xx": "Sudah Branch"
  }
}
