{
  "geometry": {
    "type": "Point",
    "coordinates": [
      -74.1833,
      44.3167
    ]
  },
  "type": "Feature",
  "properties": {
    "hierarchy": [
      "tgn:2659465",
      "tgn:1000001",
      "tgn:7012149",
      "tgn:7013941",
      "tgn:7007568",
      "tgn:7029392"
    ],
    "placetype": [
      "aat:300132316"
    ],
    "id": 2659465,
    "name:xx": "Shingle Bay"
  }
}
