{
  "geometry": {
    "type": "Point",
    "coordinates": [
      14.6833,
      56.4667
    ]
  },
  "type": "Feature",
  "properties": {
    "hierarchy": [
      "tgn:1063527",
      "tgn:1000003",
      "tgn:1000405",
      "tgn:1000097",
      "tgn:7029392"
    ],
    "placetype": [
      "aat:300008347"
    ],
    "id": 1063527,
    "name:xx": "Ryd"
  }
}
