{
  "geometry": {
    "type": "Point",
    "coordinates": [
      -80.55,
      35.6833
    ]
  },
  "type": "Feature",
  "properties": {
    "hierarchy": [
      "tgn:2749483",
      "tgn:1000001",
      "tgn:7012149",
      "tgn:2001536",
      "tgn:7007709",
      "tgn:7029392"
    ],
    "placetype": [
      "aat:300008699"
    ],
    "id": 2749483,
    "name:xx": "Walnut Branch"
  }
}
