{
  "geometry": {
    "type": "Point",
    "coordinates": [
      -75.85,
      45.3667
    ]
  },
  "type": "Feature",
  "properties": {
    "hierarchy": [
      "tgn:1116097",
      "tgn:7005685",
      "tgn:1000001",
      "tgn:7029392"
    ],
    "placetype": [
      "aat:300008680"
    ],
    "id": 1116097,
    "name:xx": "Deschênes, Lac"
  }
}
