{
  "type": "FeatureCollection",
  "features": [
    {
      "geometry": {
        "type": "Point",
        "coordinates": [
          -99.75,
          21.916667
        ]
      },
      "type": "Feature",
      "properties": {
        "hierarchy": [
          "tgn:7436370",
          "tgn:1000001",
          "tgn:7005594",
          "tgn:7005560",
          "tgn:7029392"
        ],
        "placetype": [
          "aat:300008347"
        ],
        "id": 7436370,
        "name:xx": "Terrero"
      }
    },
    {
      "geometry": {
        "type": "Point",
        "coordinates": [
          -97.816667,
          21.733333
        ]
      },
      "type": "Feature",
      "properties": {
        "hierarchy": [
          "tgn:7436371",
          "tgn:1000001",
          "tgn:7005599",
          "tgn:7005560",
          "tgn:7029392"
        ],
        "placetype": [
          "aat:300008347"
        ],
        "id": 7436371,
        "name:xx": "Terrero"
      }
    },
    {
      "geometry": {
        "type": "Point",
        "coordinates": [
          -98.416667,
          21.416667
        ]
      },
      "type": "Feature",
      "properties": {
        "hierarchy": [
          "tgn:7436373",
          "tgn:1000001",
          "tgn:7005599",
          "tgn:7005560",
          "tgn:7029392"
        ],
        "placetype": [
          "aat:300008347"
        ],
        "id": 7436373,
        "name:xx": "Terrero"
      }
    },
    {
      "geometry": {
        "type": "Point",
        "coordinates": [
          -102.466667,
          18.966667
        ]
      },
      "type": "Feature",
      "properties": {
        "hierarchy": [
          "tgn:7436374",
          "tgn:1000001",
          "tgn:7005590",
          "tgn:7005560",
          "tgn:7029392"
        ],
        "placetype": [
          "aat:300008347"
        ],
        "id": 7436374,
        "name:xx": "Terrero"
      }
    },
    {
      "geometry": {
        "type": "Point",
        "coordinates": [
          -99.65,
          18.766667
        ]
      },
      "type": "Feature",
      "properties": {
        "hierarchy": [
          "tgn:7436375",
          "tgn:1000001",
          "tgn:1001893",
          "tgn:7005560",
          "tgn:7029392"
        ],
        "placetype": [
          "aat:300008347"
        ],
        "id": 7436375,
        "name:xx": "Terrero"
      }
    },
    {
      "geometry": {
        "type": "Point",
        "coordinates": [
          -106.983333,
          28.266667
        ]
      },
      "type": "Feature",
      "properties": {
        "hierarchy": [
          "tgn:7436376",
          "tgn:7005581",
          "tgn:1000001",
          "tgn:7005560",
          "tgn:7029392"
        ],
        "placetype": [
          "aat:300008347"
        ],
        "id": 7436376,
        "name:xx": "Terreritos"
      }
    },
    {
      "geometry": {
        "type": "Point",
        "coordinates": [
          -107.616667,
          28.233333
        ]
      },
      "type": "Feature",
      "properties": {
        "hierarchy": [
          "tgn:7436377",
          "tgn:7005581",
          "tgn:1000001",
          "tgn:7005560",
          "tgn:7029392"
        ],
        "placetype": [
          "aat:300000241"
        ],
        "id": 7436377,
        "name:xx": "Rancho Terrerito"
      }
    },
    {
      "geometry": {
        "type": "Point",
        "coordinates": [
          -106.366667,
          26.833333
        ]
      },
      "type": "Feature",
      "properties": {
        "hierarchy": [
          "tgn:7436378",
          "tgn:7005581",
          "tgn:1000001",
          "tgn:7005560",
          "tgn:7029392"
        ],
        "placetype": [
          "aat:300000241"
        ],
        "id": 7436378,
        "name:xx": "Rancho Terrerito"
      }
    },
    {
      "geometry": {
        "type": "Point",
        "coordinates": [
          -101.133333,
          27
        ]
      },
      "type": "Feature",
      "properties": {
        "hierarchy": [
          "tgn:7436379",
          "tgn:1001853",
          "tgn:1000001",
          "tgn:7005560",
          "tgn:7029392"
        ],
        "placetype": [
          "aat:300008347"
        ],
        "id": 7436379,
        "name:xx": "Terreno del Cajón"
      }
    }
  ]
}
