{
  "geometry": {
    "type": "Point",
    "coordinates": [
      26.5667,
      65.9167
    ]
  },
  "type": "Feature",
  "properties": {
    "hierarchy": [
      "tgn:1031531",
      "tgn:1001385",
      "tgn:1000003",
      "tgn:1000069",
      "tgn:7029392"
    ],
    "placetype": [
      "aat:300008347"
    ],
    "id": 1031531,
    "name:xx": "Ranua"
  }
}
