{
  "type": "FeatureCollection",
  "features": [
    {
      "geometry": {
        "type": "Point",
        "coordinates": [
          -105,
          44.7333
        ]
      },
      "type": "Feature",
      "properties": {
        "hierarchy": [
          "tgn:2144280",
          "tgn:1000001",
          "tgn:7012149",
          "tgn:2002387",
          "tgn:7007923",
          "tgn:7029392"
        ],
        "placetype": [
          "aat:300006191"
        ],
        "id": 2144280,
        "name:xx": "Baker Number 1 Reservoir"
      }
    },
    {
      "geometry": {
        "type": "Point",
        "coordinates": [
          -105,
          44.1
        ]
      },
      "type": "Feature",
      "properties": {
        "hierarchy": [
          "tgn:2144281",
          "tgn:1000001",
          "tgn:7012149",
          "tgn:2002387",
          "tgn:7007923",
          "tgn:7029392"
        ],
        "placetype": [
          "aat:300006191"
        ],
        "id": 2144281,
        "name:xx": "Baker Number 2 Reservoir"
      }
    },
    {
      "geometry": {
        "type": "Point",
        "coordinates": [
          -77.8,
          39.8333
        ]
      },
      "type": "Feature",
      "properties": {
        "hierarchy": [
          "tgn:2144282",
          "tgn:1000001",
          "tgn:7012149",
          "tgn:1002387",
          "tgn:7007710",
          "tgn:7029392"
        ],
        "placetype": [
          "aat:300008746"
        ],
        "id": 2144282,
        "name:xx": "Baker Number Three Cave"
      }
    },
    {
      "geometry": {
        "type": "Point",
        "coordinates": [
          -118.5167,
          35.85
        ]
      },
      "type": "Feature",
      "properties": {
        "hierarchy": [
          "tgn:2144283",
          "tgn:1000001",
          "tgn:7012149",
          "tgn:7007157",
          "tgn:1002956",
          "tgn:7029392"
        ],
        "placetype": [
          "aat:300008798"
        ],
        "id": 2144283,
        "name:xx": "Baker Peak"
      }
    },
    {
      "geometry": {
        "type": "Point",
        "coordinates": [
          -108.0167,
          37.3833
        ]
      },
      "type": "Feature",
      "properties": {
        "hierarchy": [
          "tgn:2144284",
          "tgn:1000001",
          "tgn:7012149",
          "tgn:2000225",
          "tgn:7007158",
          "tgn:7029392"
        ],
        "placetype": [
          "aat:300008798"
        ],
        "id": 2144284,
        "name:xx": "Baker Peak"
      }
    },
    {
      "geometry": {
        "type": "Point",
        "coordinates": [
          -114.6667,
          43.6667
        ]
      },
      "type": "Feature",
      "properties": {
        "hierarchy": [
          "tgn:2144285",
          "tgn:1000001",
          "tgn:7012149",
          "tgn:7007250",
          "tgn:7029392"
        ],
        "placetype": [
          "aat:300008798"
        ],
        "id": 2144285,
        "name:xx": "Baker Peak"
      }
    },
    {
      "geometry": {
        "type": "Point",
        "coordinates": [
          -114.3,
          38.9667
        ]
      },
      "type": "Feature",
      "properties": {
        "hierarchy": [
          "tgn:2144286",
          "tgn:1000001",
          "tgn:7012149",
          "tgn:2001420",
          "tgn:7007526",
          "tgn:7029392"
        ],
        "placetype": [
          "aat:300008798"
        ],
        "id": 2144286,
        "name:xx": "Baker Peak"
      }
    },
    {
      "geometry": {
        "type": "Point",
        "coordinates": [
          -98.8,
          34.8
        ]
      },
      "type": "Feature",
      "properties": {
        "hierarchy": [
          "tgn:2144287",
          "tgn:1000001",
          "tgn:2001638",
          "tgn:7012149",
          "tgn:7007707",
          "tgn:7029392"
        ],
        "placetype": [
          "aat:300008798"
        ],
        "id": 2144287,
        "name:xx": "Baker Peak"
      }
    },
    {
      "geometry": {
        "type": "Point",
        "coordinates": [
          -72.95,
          43.3167
        ]
      },
      "type": "Feature",
      "properties": {
        "hierarchy": [
          "tgn:2144288",
          "tgn:1000001",
          "tgn:1002840",
          "tgn:7012149",
          "tgn:7007828",
          "tgn:7029392"
        ],
        "placetype": [
          "aat:300008798"
        ],
        "id": 2144288,
        "name:xx": "Baker Peak"
      }
    },
    {
      "geometry": {
        "type": "Point",
        "coordinates": [
          -113.9833,
          32.6333
        ]
      },
      "type": "Feature",
      "properties": {
        "hierarchy": [
          "tgn:2144289",
          "tgn:1000001",
          "tgn:7006451",
          "tgn:7012149",
          "tgn:2000104",
          "tgn:7029392"
        ],
        "placetype": [
          "aat:300008798"
        ],
        "id": 2144289,
        "name:xx": "Baker Peaks"
      }
    }
  ]
}
