{
  "geometry": {
    "type": "Point",
    "coordinates": [
      -77.5167,
      38.3667
    ]
  },
  "type": "Feature",
  "properties": {
    "hierarchy": [
      "tgn:2626735",
      "tgn:1000001",
      "tgn:7012149",
      "tgn:1002913",
      "tgn:7007919",
      "tgn:7029392"
    ],
    "placetype": [
      "aat:300008699"
    ],
    "id": 2626735,
    "name:xx": "Rocky Pen Run"
  }
}
