{
  "type": "FeatureCollection",
  "features": [
    {
      "geometry": {
        "type": "Point",
        "coordinates": [
          -84.9833,
          35.1
        ]
      },
      "type": "Feature",
      "properties": {
        "hierarchy": [
          "tgn:2165010",
          "tgn:1000001",
          "tgn:2001842",
          "tgn:7012149",
          "tgn:7007825",
          "tgn:7029392"
        ],
        "placetype": [
          "aat:300006191"
        ],
        "id": 2165010,
        "name:xx": "Bethea Pond"
      }
    },
    {
      "geometry": {
        "type": "Point",
        "coordinates": [
          -80.7167,
          34.6833
        ]
      },
      "type": "Feature",
      "properties": {
        "hierarchy": [
          "tgn:2165011",
          "tgn:1000001",
          "tgn:7012149",
          "tgn:2001753",
          "tgn:7007712",
          "tgn:7029392"
        ],
        "placetype": [
          "aat:300006191"
        ],
        "id": 2165011,
        "name:xx": "Betheas Pond"
      }
    },
    {
      "geometry": {
        "type": "Point",
        "coordinates": [
          -86.9,
          31.7
        ]
      },
      "type": "Feature",
      "properties": {
        "hierarchy": [
          "tgn:2165012",
          "tgn:7002659",
          "tgn:1000001",
          "tgn:2000017",
          "tgn:7012149",
          "tgn:7029392"
        ],
        "placetype": [
          "aat:300008347"
        ],
        "id": 2165012,
        "name:xx": "Bethel"
      }
    },
    {
      "geometry": {
        "type": "Point",
        "coordinates": [
          -87.45,
          34.75
        ]
      },
      "type": "Feature",
      "properties": {
        "hierarchy": [
          "tgn:2165013",
          "tgn:7002659",
          "tgn:1000001",
          "tgn:2000016",
          "tgn:7012149",
          "tgn:7029392"
        ],
        "placetype": [
          "aat:300008347"
        ],
        "id": 2165013,
        "name:xx": "Bethel"
      }
    },
    {
      "geometry": {
        "type": "Point",
        "coordinates": [
          -87.4667,
          32.1333
        ]
      },
      "type": "Feature",
      "properties": {
        "hierarchy": [
          "tgn:2165014",
          "tgn:7002659",
          "tgn:1000001",
          "tgn:7012149",
          "tgn:2000065",
          "tgn:7029392"
        ],
        "placetype": [
          "aat:300008347"
        ],
        "id": 2165014,
        "name:xx": "Bethel"
      }
    },
    {
      "geometry": {
        "type": "Point",
        "coordinates": [
          -85.3,
          33.3833
        ]
      },
      "type": "Feature",
      "properties": {
        "hierarchy": [
          "tgn:2165015",
          "tgn:7002659",
          "tgn:1000001",
          "tgn:7012149",
          "tgn:2000055",
          "tgn:7029392"
        ],
        "placetype": [
          "aat:300008347"
        ],
        "id": 2165015,
        "name:xx": "Bethel"
      }
    },
    {
      "geometry": {
        "type": "Point",
        "coordinates": [
          -85.9833,
          33.85
        ]
      },
      "type": "Feature",
      "properties": {
        "hierarchy": [
          "tgn:2165016",
          "tgn:7002659",
          "tgn:1000001",
          "tgn:2000007",
          "tgn:7012149",
          "tgn:7029392"
        ],
        "placetype": [
          "aat:300008347"
        ],
        "id": 2165016,
        "name:xx": "Bethel"
      }
    },
    {
      "geometry": {
        "type": "Point",
        "coordinates": [
          -87.4,
          33.6333
        ]
      },
      "type": "Feature",
      "properties": {
        "hierarchy": [
          "tgn:2165017",
          "tgn:7002659",
          "tgn:1000001",
          "tgn:7012149",
          "tgn:2000063",
          "tgn:7029392"
        ],
        "placetype": [
          "aat:300008347"
        ],
        "id": 2165017,
        "name:xx": "Bethel"
      }
    },
    {
      "geometry": {
        "type": "Point",
        "coordinates": [
          -86.1167,
          33.4833
        ]
      },
      "type": "Feature",
      "properties": {
        "hierarchy": [
          "tgn:2165018",
          "tgn:7002659",
          "tgn:1000001",
          "tgn:7012149",
          "tgn:2000060",
          "tgn:7029392"
        ],
        "placetype": [
          "aat:300008347"
        ],
        "id": 2165018,
        "name:xx": "Bethel"
      }
    },
    {
      "geometry": {
        "type": "Point",
        "coordinates": [
          -85.3667,
          33.8
        ]
      },
      "type": "Feature",
      "properties": {
        "hierarchy": [
          "tgn:2165019",
          "tgn:7002659",
          "tgn:1000001",
          "tgn:2000014",
          "tgn:7012149",
          "tgn:7029392"
        ],
        "placetype": [
          "aat:300008347"
        ],
        "id": 2165019,
        "name:xx": "Bethel"
      }
    }
  ]
}
