{
  "geometry": {
    "type": "Point",
    "coordinates": [
      79.100519,
      24.94619
    ]
  },
  "type": "Feature",
  "properties": {
    "hierarchy": [
      "tgn:7564754",
      "tgn:1000004",
      "tgn:7000198",
      "tgn:1001894",
      "tgn:7029392"
    ],
    "placetype": [
      "aat:300008347"
    ],
    "name:en": "Phūlpur",
    "id": 7564754
  }
}
