{
  "geometry": {
    "type": "Point",
    "coordinates": [
      -82.8833,
      36.6333
    ]
  },
  "type": "Feature",
  "properties": {
    "hierarchy": [
      "tgn:2412154",
      "tgn:1000001",
      "tgn:7012149",
      "tgn:2002189",
      "tgn:7007919",
      "tgn:7029392"
    ],
    "placetype": [
      "aat:300008746"
    ],
    "id": 2412154,
    "name:xx": "Indian Skull Cave"
  }
}
