{
  "type": "FeatureCollection",
  "features": [
    {
      "geometry": {
        "type": "Point",
        "coordinates": [
          20.4833,
          47.0667
        ]
      },
      "type": "Feature",
      "properties": {
        "hierarchy": [
          "tgn:4005480",
          "tgn:1000453",
          "tgn:1000003",
          "tgn:7006278",
          "tgn:7029392"
        ],
        "placetype": [
          "aat:300008347"
        ],
        "id": 4005480,
        "name:xx": "Kétpó"
      }
    },
    {
      "geometry": {
        "type": "Point",
        "coordinates": [
          36.9,
          35.8667
        ]
      },
      "type": "Feature",
      "properties": {
        "hierarchy": [
          "tgn:4005485",
          "tgn:1000004",
          "tgn:1002084",
          "tgn:1000140",
          "tgn:7029392"
        ],
        "placetype": [
          "aat:300008347",
          "aat:300008375"
        ],
        "id": 4005485,
        "name:xx": "Kūrīn"
      }
    },
    {
      "geometry": {
        "type": "Point",
        "coordinates": [
          13.1667,
          58.05
        ]
      },
      "type": "Feature",
      "properties": {
        "hierarchy": [
          "tgn:4005486",
          "tgn:1000003",
          "tgn:7024620",
          "tgn:1000097",
          "tgn:7029392"
        ],
        "placetype": [
          "aat:300008347"
        ],
        "id": 4005486,
        "name:xx": "Källunge"
      }
    },
    {
      "geometry": {
        "type": "Point",
        "coordinates": [
          18.7167,
          45.95
        ]
      },
      "type": "Feature",
      "properties": {
        "hierarchy": [
          "tgn:4005488",
          "tgn:7006349",
          "tgn:1000003",
          "tgn:7006278",
          "tgn:7029392"
        ],
        "placetype": [
          "aat:300008347"
        ],
        "id": 4005488,
        "name:xx": "Kölked"
      }
    }
  ]
}
