{
  "geometry": {
    "type": "Point",
    "coordinates": [
      -121.15,
      42.5333
    ]
  },
  "type": "Feature",
  "properties": {
    "hierarchy": [
      "tgn:2466221",
      "tgn:1000001",
      "tgn:7012149",
      "tgn:2001714",
      "tgn:7007708",
      "tgn:7029392"
    ],
    "placetype": [
      "aat:300008680"
    ],
    "id": 2466221,
    "name:xx": "Lonesome Pond"
  }
}
