{
  "geometry": {
    "type": "Point",
    "coordinates": [
      -80.8667,
      40.3667
    ]
  },
  "type": "Feature",
  "properties": {
    "hierarchy": [
      "tgn:2478616",
      "tgn:1000001",
      "tgn:7012149",
      "tgn:1002459",
      "tgn:7007706",
      "tgn:7029392"
    ],
    "placetype": [
      "aat:300006191"
    ],
    "id": 2478616,
    "name:xx": "Mader Pond"
  }
}
