{
  "geometry": {
    "type": "Point",
    "coordinates": [
      31.683333,
      30.85
    ]
  },
  "type": "Feature",
  "properties": {
    "hierarchy": [
      "tgn:7534898",
      "tgn:7001242",
      "tgn:7016833",
      "tgn:1001113",
      "tgn:7029392"
    ],
    "placetype": [
      "aat:300008777"
    ],
    "name:en": "Gharīr, Tall",
    "id": 7534898
  }
}
