{
  "type": "FeatureCollection",
  "features": [
    {
      "geometry": {
        "type": "Point",
        "coordinates": [
          -6.4,
          42.716667
        ]
      },
      "type": "Feature",
      "properties": {
        "hierarchy": [
          "tgn:7302290",
          "tgn:7002826",
          "tgn:7001158",
          "tgn:1000003",
          "tgn:1000095",
          "tgn:7029392"
        ],
        "placetype": [
          "aat:300008347"
        ],
        "id": 7302290,
        "name:xx": "Noceda"
      }
    },
    {
      "geometry": {
        "type": "Point",
        "coordinates": [
          -8.933333,
          42.7
        ]
      },
      "type": "Feature",
      "properties": {
        "hierarchy": [
          "tgn:7302291",
          "tgn:7002824",
          "tgn:1000003",
          "tgn:7002786",
          "tgn:1000095",
          "tgn:7029392"
        ],
        "placetype": [
          "aat:300008347"
        ],
        "id": 7302291,
        "name:xx": "Noceda"
      }
    },
    {
      "geometry": {
        "type": "Point",
        "coordinates": [
          -3.483333,
          43.1
        ]
      },
      "type": "Feature",
      "properties": {
        "hierarchy": [
          "tgn:7302295",
          "tgn:7002810",
          "tgn:7001158",
          "tgn:1000003",
          "tgn:1000095",
          "tgn:7029392"
        ],
        "placetype": [
          "aat:300008347"
        ],
        "id": 7302295,
        "name:xx": "Noceco"
      }
    },
    {
      "geometry": {
        "type": "Point",
        "coordinates": [
          -3.433333,
          39.983333
        ]
      },
      "type": "Feature",
      "properties": {
        "hierarchy": [
          "tgn:7302296",
          "tgn:7002847",
          "tgn:1001647",
          "tgn:1000003",
          "tgn:1000095",
          "tgn:7029392"
        ],
        "placetype": [
          "aat:300008347"
        ],
        "id": 7302296,
        "name:xx": "Noblejas"
      }
    },
    {
      "geometry": {
        "type": "Point",
        "coordinates": [
          -0.966667,
          42.583333
        ]
      },
      "type": "Feature",
      "properties": {
        "hierarchy": [
          "tgn:7302297",
          "tgn:7002759",
          "tgn:7002845",
          "tgn:1000003",
          "tgn:1000095",
          "tgn:7029392"
        ],
        "placetype": [
          "aat:300008795"
        ],
        "id": 7302297,
        "name:xx": "Nobla, Sierra"
      }
    },
    {
      "geometry": {
        "type": "Point",
        "coordinates": [
          -8.85,
          42.433333
        ]
      },
      "type": "Feature",
      "properties": {
        "hierarchy": [
          "tgn:7302298",
          "tgn:7002834",
          "tgn:1000003",
          "tgn:7002786",
          "tgn:1000095",
          "tgn:7029392"
        ],
        "placetype": [
          "aat:300008347"
        ],
        "id": 7302298,
        "name:xx": "Noalla"
      }
    },
    {
      "geometry": {
        "type": "Point",
        "coordinates": [
          -7.85,
          42.283333
        ]
      },
      "type": "Feature",
      "properties": {
        "hierarchy": [
          "tgn:7302299",
          "tgn:7002831",
          "tgn:1000003",
          "tgn:7002786",
          "tgn:1000095",
          "tgn:7029392"
        ],
        "placetype": [
          "aat:300008347"
        ],
        "id": 7302299,
        "name:xx": "Noalla"
      }
    }
  ]
}
