{
  "geometry": {
    "type": "Point",
    "coordinates": [
      -73.1333,
      40.95
    ]
  },
  "type": "Feature",
  "properties": {
    "hierarchy": [
      "tgn:2265500",
      "tgn:1000001",
      "tgn:7012149",
      "tgn:1002924",
      "tgn:7007568",
      "tgn:7029392"
    ],
    "placetype": [
      "aat:300008850"
    ],
    "id": 2265500,
    "name:xx": "Crane Neck"
  }
}
