{
  "geometry": {
    "type": "Point",
    "coordinates": [
      -109.35,
      42.8833
    ]
  },
  "type": "Feature",
  "properties": {
    "hierarchy": [
      "tgn:2294676",
      "tgn:1000001",
      "tgn:7012149",
      "tgn:2002382",
      "tgn:7007923",
      "tgn:7029392"
    ],
    "placetype": [
      "aat:300008798"
    ],
    "id": 2294676,
    "name:xx": "Dragon Head Peak"
  }
}
