{
  "geometry": {
    "type": "Point",
    "coordinates": [
      -123.5833,
      46.2167
    ]
  },
  "type": "Feature",
  "properties": {
    "hierarchy": [
      "tgn:2493603",
      "tgn:1000001",
      "tgn:1002276",
      "tgn:7012149",
      "tgn:7007708",
      "tgn:7029392"
    ],
    "placetype": [
      "aat:300008791"
    ],
    "id": 2493603,
    "name:xx": "Marsh Island"
  }
}
