{
  "geometry": {
    "type": "Point",
    "coordinates": [
      -109.8667,
      40.4667
    ]
  },
  "type": "Feature",
  "properties": {
    "hierarchy": [
      "tgn:2506118",
      "tgn:1000001",
      "tgn:7012149",
      "tgn:2002124",
      "tgn:7007827",
      "tgn:7029392"
    ],
    "placetype": [
      "aat:300006191"
    ],
    "id": 2506118,
    "name:xx": "Merkley Reservoir"
  }
}
