{
  "geometry": {
    "type": "Point",
    "coordinates": [
      30.833333,
      27.433333
    ]
  },
  "type": "Feature",
  "properties": {
    "hierarchy": [
      "tgn:7537716",
      "tgn:7001242",
      "tgn:7016833",
      "tgn:1001114",
      "tgn:7029392"
    ],
    "placetype": [
      "aat:300007783"
    ],
    "name:en": "Naz훮l카 J훮n큰b",
    "id": 7537716
  }
}
