{
  "geometry": {
    "type": "Point",
    "coordinates": [
      4.8667,
      45.1833
    ]
  },
  "type": "Feature",
  "properties": {
    "hierarchy": [
      "tgn:1035542",
      "tgn:1000003",
      "tgn:1000070",
      "tgn:7002897",
      "tgn:7029392"
    ],
    "placetype": [
      "aat:300008347"
    ],
    "id": 1035542,
    "name:xx": "Saint-Uze"
  }
}
