{
  "geometry": {
    "type": "Point",
    "coordinates": [
      -105.1833,
      33.3667
    ]
  },
  "type": "Feature",
  "properties": {
    "hierarchy": [
      "tgn:2211897",
      "tgn:1000001",
      "tgn:7012149",
      "tgn:2001442",
      "tgn:7007566",
      "tgn:7029392"
    ],
    "placetype": [
      "aat:300000390"
    ],
    "id": 2211897,
    "name:xx": "Butts Pit"
  }
}
