{
  "geometry": {
    "type": "Point",
    "coordinates": [
      31.872307,
      30.97478
    ]
  },
  "type": "Feature",
  "properties": {
    "hierarchy": [
      "tgn:7001450",
      "tgn:7001242",
      "tgn:7016833",
      "tgn:1001113",
      "tgn:7029392"
    ],
    "placetype": [
      "aat:300008347",
      "aat:300008375"
    ],
    "id": 7001450,
    "name:xx": "Şān al Ḩajar al Qiblīyah"
  }
}
