{
  "type": "FeatureCollection",
  "features": [
    {
      "geometry": {
        "type": "Point",
        "coordinates": [
          21.666667,
          36.933333
        ]
      },
      "type": "Feature",
      "properties": {
        "hierarchy": [
          "tgn:6005594",
          "tgn:7011369",
          "tgn:7017076",
          "tgn:1000003",
          "tgn:1000074",
          "tgn:7029392"
        ],
        "placetype": [
          "aat:300000835",
          "aat:300008791",
          "aat:300000833"
        ],
        "name:en": "Sphacteria",
        "id": 6005594
      }
    },
    {
      "geometry": {
        "type": "Point",
        "coordinates": [
          3.983333,
          50.416667
        ]
      },
      "type": "Feature",
      "properties": {
        "hierarchy": [
          "tgn:6005596",
          "tgn:7007877",
          "tgn:1000003",
          "tgn:1000063",
          "tgn:4012014",
          "tgn:7029392"
        ],
        "placetype": [
          "aat:300008347",
          "aat:300008375"
        ],
        "id": 6005596,
        "name:xx": "Spiennes"
      }
    }
  ]
}
