{
  "type": "FeatureCollection",
  "features": [
    {
      "geometry": {
        "type": "Point",
        "coordinates": [
          -73.95,
          43.8667
        ]
      },
      "type": "Feature",
      "properties": {
        "hierarchy": [
          "tgn:2177210",
          "tgn:1000001",
          "tgn:7012149",
          "tgn:2001461",
          "tgn:7007568",
          "tgn:7029392"
        ],
        "placetype": [
          "aat:300008680"
        ],
        "id": 2177210,
        "name:xx": "Black Pond"
      }
    },
    {
      "geometry": {
        "type": "Point",
        "coordinates": [
          -74.5833,
          44.1333
        ]
      },
      "type": "Feature",
      "properties": {
        "hierarchy": [
          "tgn:2177211",
          "tgn:1000001",
          "tgn:7012149",
          "tgn:7016021",
          "tgn:7007568",
          "tgn:7029392"
        ],
        "placetype": [
          "aat:300008680"
        ],
        "id": 2177211,
        "name:xx": "Black Pond"
      }
    },
    {
      "geometry": {
        "type": "Point",
        "coordinates": [
          -74.3667,
          44.3
        ]
      },
      "type": "Feature",
      "properties": {
        "hierarchy": [
          "tgn:2177212",
          "tgn:1000001",
          "tgn:7012149",
          "tgn:7013941",
          "tgn:7007568",
          "tgn:7029392"
        ],
        "placetype": [
          "aat:300008680"
        ],
        "id": 2177212,
        "name:xx": "Black Pond"
      }
    },
    {
      "geometry": {
        "type": "Point",
        "coordinates": [
          -79.8667,
          34.95
        ]
      },
      "type": "Feature",
      "properties": {
        "hierarchy": [
          "tgn:2177213",
          "tgn:1000001",
          "tgn:7012149",
          "tgn:2001533",
          "tgn:7007709",
          "tgn:7029392"
        ],
        "placetype": [
          "aat:300008680"
        ],
        "id": 2177213,
        "name:xx": "Black Pond"
      }
    },
    {
      "geometry": {
        "type": "Point",
        "coordinates": [
          -81.6,
          41.0667
        ]
      },
      "type": "Feature",
      "properties": {
        "hierarchy": [
          "tgn:2177214",
          "tgn:1000001",
          "tgn:7012149",
          "tgn:1002928",
          "tgn:7007706",
          "tgn:7029392"
        ],
        "placetype": [
          "aat:300006191"
        ],
        "id": 2177214,
        "name:xx": "Black Pond"
      }
    },
    {
      "geometry": {
        "type": "Point",
        "coordinates": [
          -84.3833,
          39.55
        ]
      },
      "type": "Feature",
      "properties": {
        "hierarchy": [
          "tgn:2177215",
          "tgn:1000001",
          "tgn:1002216",
          "tgn:7012149",
          "tgn:7007706",
          "tgn:7029392"
        ],
        "placetype": [
          "aat:300006191"
        ],
        "id": 2177215,
        "name:xx": "Black Pond"
      }
    },
    {
      "geometry": {
        "type": "Point",
        "coordinates": [
          -85.8833,
          35.6167
        ]
      },
      "type": "Feature",
      "properties": {
        "hierarchy": [
          "tgn:2177216",
          "tgn:1000001",
          "tgn:7012149",
          "tgn:2001925",
          "tgn:7007825",
          "tgn:7029392"
        ],
        "placetype": [
          "aat:300008680"
        ],
        "id": 2177216,
        "name:xx": "Black Pond"
      }
    },
    {
      "geometry": {
        "type": "Point",
        "coordinates": [
          -84.1833,
          35.6167
        ]
      },
      "type": "Feature",
      "properties": {
        "hierarchy": [
          "tgn:2177217",
          "tgn:1000001",
          "tgn:7012149",
          "tgn:2001889",
          "tgn:7007825",
          "tgn:7029392"
        ],
        "placetype": [
          "aat:300008680"
        ],
        "id": 2177217,
        "name:xx": "Black Pond"
      }
    },
    {
      "geometry": {
        "type": "Point",
        "coordinates": [
          -85.3333,
          35.7833
        ]
      },
      "type": "Feature",
      "properties": {
        "hierarchy": [
          "tgn:2177218",
          "tgn:1000001",
          "tgn:7012149",
          "tgn:2001924",
          "tgn:7007825",
          "tgn:7029392"
        ],
        "placetype": [
          "aat:300008680"
        ],
        "id": 2177218,
        "name:xx": "Black Pond"
      }
    },
    {
      "geometry": {
        "type": "Point",
        "coordinates": [
          -72.75,
          43.5333
        ]
      },
      "type": "Feature",
      "properties": {
        "hierarchy": [
          "tgn:2177219",
          "tgn:1000001",
          "tgn:2002136",
          "tgn:7012149",
          "tgn:7007828",
          "tgn:7029392"
        ],
        "placetype": [
          "aat:300008680"
        ],
        "id": 2177219,
        "name:xx": "Black Pond"
      }
    }
  ]
}
