{
  "geometry": {
    "type": "Point",
    "coordinates": [
      -92.35,
      39.15
    ]
  },
  "type": "Feature",
  "properties": {
    "hierarchy": [
      "tgn:2613549",
      "tgn:1000001",
      "tgn:1002190",
      "tgn:7012149",
      "tgn:7007523",
      "tgn:7029392"
    ],
    "placetype": [
      "aat:300008706"
    ],
    "id": 2613549,
    "name:xx": "Reeder Creek"
  }
}
