{
  "geometry": {
    "type": "Point",
    "coordinates": [
      -105.9333,
      32.2833
    ]
  },
  "type": "Feature",
  "properties": {
    "hierarchy": [
      "tgn:2457551",
      "tgn:1000001",
      "tgn:7012149",
      "tgn:2001447",
      "tgn:7007566",
      "tgn:7029392"
    ],
    "placetype": [
      "aat:300006191"
    ],
    "id": 2457551,
    "name:xx": "Little Mack Tank"
  }
}
