{
  "geometry": {
    "type": "Point",
    "coordinates": [
      -92.0333,
      39.25
    ]
  },
  "type": "Feature",
  "properties": {
    "hierarchy": [
      "tgn:2327539",
      "tgn:1002158",
      "tgn:1000001",
      "tgn:7012149",
      "tgn:7007523",
      "tgn:7029392"
    ],
    "placetype": [
      "aat:300008699"
    ],
    "id": 2327539,
    "name:xx": "Fish Branch"
  }
}
