{
  "geometry": {
    "type": "Point",
    "coordinates": [
      79.895,
      27.0407
    ]
  },
  "type": "Feature",
  "properties": {
    "hierarchy": [
      "tgn:7563197",
      "tgn:1000004",
      "tgn:7000198",
      "tgn:7016722",
      "tgn:7029392"
    ],
    "placetype": [
      "aat:300008347"
    ],
    "name:en": "Kanpatiāpur",
    "id": 7563197
  }
}
