{
  "type": "FeatureCollection",
  "features": [
    {
      "geometry": {
        "type": "Point",
        "coordinates": [
          -106.6333,
          38.3667
        ]
      },
      "type": "Feature",
      "properties": {
        "hierarchy": [
          "tgn:2674500",
          "tgn:1000001",
          "tgn:7012149",
          "tgn:7007158",
          "tgn:2000246",
          "tgn:7029392"
        ],
        "placetype": [
          "aat:300008761"
        ],
        "id": 2674500,
        "name:xx": "Snyder Gulch"
      }
    },
    {
      "geometry": {
        "type": "Point",
        "coordinates": [
          -113.35,
          46.7333
        ]
      },
      "type": "Feature",
      "properties": {
        "hierarchy": [
          "tgn:2674501",
          "tgn:1000001",
          "tgn:7012149",
          "tgn:2001279",
          "tgn:7007524",
          "tgn:7029392"
        ],
        "placetype": [
          "aat:300008761"
        ],
        "id": 2674501,
        "name:xx": "Snyder Gulch"
      }
    },
    {
      "geometry": {
        "type": "Point",
        "coordinates": [
          -111.1,
          32.15
        ]
      },
      "type": "Feature",
      "properties": {
        "hierarchy": [
          "tgn:2674502",
          "tgn:1000001",
          "tgn:7006451",
          "tgn:7012149",
          "tgn:2000100",
          "tgn:7029392"
        ],
        "placetype": [
          "aat:300008798"
        ],
        "id": 2674502,
        "name:xx": "Snyder Hill"
      }
    },
    {
      "geometry": {
        "type": "Point",
        "coordinates": [
          -86.8167,
          39.5333
        ]
      },
      "type": "Feature",
      "properties": {
        "hierarchy": [
          "tgn:2674503",
          "tgn:1000001",
          "tgn:7012149",
          "tgn:2000553",
          "tgn:7007252",
          "tgn:7029392"
        ],
        "placetype": [
          "aat:300008798"
        ],
        "id": 2674503,
        "name:xx": "Snyder Hill"
      }
    },
    {
      "geometry": {
        "type": "Point",
        "coordinates": [
          -76.3833,
          42.4167
        ]
      },
      "type": "Feature",
      "properties": {
        "hierarchy": [
          "tgn:2674504",
          "tgn:1000001",
          "tgn:7012149",
          "tgn:1002950",
          "tgn:7007568",
          "tgn:7029392"
        ],
        "placetype": [
          "aat:300008798"
        ],
        "id": 2674504,
        "name:xx": "Snyder Hill"
      }
    },
    {
      "geometry": {
        "type": "Point",
        "coordinates": [
          -76.1,
          42.5167
        ]
      },
      "type": "Feature",
      "properties": {
        "hierarchy": [
          "tgn:2674505",
          "tgn:1000001",
          "tgn:1002302",
          "tgn:7012149",
          "tgn:7007568",
          "tgn:7029392"
        ],
        "placetype": [
          "aat:300008798"
        ],
        "id": 2674505,
        "name:xx": "Snyder Hill"
      }
    },
    {
      "geometry": {
        "type": "Point",
        "coordinates": [
          -73.9167,
          43.8
        ]
      },
      "type": "Feature",
      "properties": {
        "hierarchy": [
          "tgn:2674506",
          "tgn:1000001",
          "tgn:7012149",
          "tgn:2001461",
          "tgn:7007568",
          "tgn:7029392"
        ],
        "placetype": [
          "aat:300008798"
        ],
        "id": 2674506,
        "name:xx": "Snyder Hill"
      }
    },
    {
      "geometry": {
        "type": "Point",
        "coordinates": [
          -80.3333,
          41.4
        ]
      },
      "type": "Feature",
      "properties": {
        "hierarchy": [
          "tgn:2674507",
          "tgn:1000001",
          "tgn:7012149",
          "tgn:1002659",
          "tgn:7007710",
          "tgn:7029392"
        ],
        "placetype": [
          "aat:300008798"
        ],
        "id": 2674507,
        "name:xx": "Snyder Hill"
      }
    },
    {
      "geometry": {
        "type": "Point",
        "coordinates": [
          -117.3167,
          48.7667
        ]
      },
      "type": "Feature",
      "properties": {
        "hierarchy": [
          "tgn:2674508",
          "tgn:1000001",
          "tgn:7012149",
          "tgn:2002248",
          "tgn:7007920",
          "tgn:7029392"
        ],
        "placetype": [
          "aat:300008798"
        ],
        "id": 2674508,
        "name:xx": "Snyder Hill"
      }
    },
    {
      "geometry": {
        "type": "Point",
        "coordinates": [
          -77.7833,
          39.2667
        ]
      },
      "type": "Feature",
      "properties": {
        "hierarchy": [
          "tgn:2674509",
          "tgn:1000001",
          "tgn:7012149",
          "tgn:2002269",
          "tgn:7013961",
          "tgn:7029392"
        ],
        "placetype": [
          "aat:300008798"
        ],
        "id": 2674509,
        "name:xx": "Snyder Hill"
      }
    }
  ]
}
