{
  "geometry": {
    "type": "Point",
    "coordinates": [
      70.134182,
      27.126499
    ]
  },
  "type": "Feature",
  "properties": {
    "hierarchy": [
      "tgn:7576752",
      "tgn:1000004",
      "tgn:7000198",
      "tgn:7016788",
      "tgn:7029392"
    ],
    "placetype": [
      "aat:300006207"
    ],
    "name:en": "Khāria Tala",
    "id": 7576752
  }
}
