{
  "geometry": {
    "type": "Point",
    "coordinates": [
      38.1667,
      63.1667
    ]
  },
  "type": "Feature",
  "properties": {
    "hierarchy": [
      "tgn:1055439",
      "tgn:4000818",
      "tgn:1000004",
      "tgn:7018214",
      "tgn:7002435",
      "tgn:7029392"
    ],
    "placetype": [
      "aat:300008347"
    ],
    "id": 1055439,
    "name:xx": "Kozhposelok"
  }
}
