{
  "geometry": {
    "type": "Point",
    "coordinates": [
      -85.3167,
      43.7667
    ]
  },
  "type": "Feature",
  "properties": {
    "hierarchy": [
      "tgn:2382125",
      "tgn:1000001",
      "tgn:7012149",
      "tgn:2000977",
      "tgn:7007520",
      "tgn:7029392"
    ],
    "placetype": [
      "aat:300008706"
    ],
    "id": 2382125,
    "name:xx": "Haymarsh Creek"
  }
}
