{
  "geometry": {
    "type": "Point",
    "coordinates": [
      -118.65,
      34.5667
    ]
  },
  "type": "Feature",
  "properties": {
    "hierarchy": [
      "tgn:2709872",
      "tgn:1000001",
      "tgn:7012149",
      "tgn:7007157",
      "tgn:1002608",
      "tgn:7029392"
    ],
    "placetype": [
      "aat:300006075"
    ],
    "id": 2709872,
    "name:xx": "Tailrace Canal"
  }
}
