{
  "geometry": {
    "type": "Point",
    "coordinates": [
      17.4167,
      59.05
    ]
  },
  "type": "Feature",
  "properties": {
    "hierarchy": [
      "tgn:1063351",
      "tgn:1000003",
      "tgn:7003777",
      "tgn:1000097",
      "tgn:7029392"
    ],
    "placetype": [
      "aat:300008347"
    ],
    "id": 1063351,
    "name:xx": "Mölnbo"
  }
}
