{
  "geometry": {
    "type": "Point",
    "coordinates": [
      79.718304,
      27.53573
    ]
  },
  "type": "Feature",
  "properties": {
    "hierarchy": [
      "tgn:7561121",
      "tgn:1000004",
      "tgn:7000198",
      "tgn:7016722",
      "tgn:7029392"
    ],
    "placetype": [
      "aat:300008347"
    ],
    "name:en": "Samādhi",
    "id": 7561121
  }
}
