{
  "geometry": {
    "type": "Point",
    "coordinates": [
      -121.9833,
      45.1333
    ]
  },
  "type": "Feature",
  "properties": {
    "hierarchy": [
      "tgn:2510352",
      "tgn:1000001",
      "tgn:1002270",
      "tgn:7012149",
      "tgn:7007708",
      "tgn:7029392"
    ],
    "placetype": [
      "aat:300008680"
    ],
    "id": 2510352,
    "name:xx": "Middle Rock Lake"
  }
}
