{
  "geometry": {
    "type": "Point",
    "coordinates": [
      -80.1667,
      25.9167
    ]
  },
  "type": "Feature",
  "properties": {
    "hierarchy": [
      "tgn:2632368",
      "tgn:1000001",
      "tgn:7012149",
      "tgn:1002314",
      "tgn:7007240",
      "tgn:7029392"
    ],
    "placetype": [
      "aat:300006075"
    ],
    "id": 2632368,
    "name:xx": "Royal Galdes Canal"
  }
}
