{
  "geometry": {
    "type": "Point",
    "coordinates": [
      -119.7667,
      38.0833
    ]
  },
  "type": "Feature",
  "properties": {
    "hierarchy": [
      "tgn:2149939",
      "tgn:1000001",
      "tgn:7012149",
      "tgn:7007157",
      "tgn:1002957",
      "tgn:7029392"
    ],
    "placetype": [
      "aat:300008798"
    ],
    "id": 2149939,
    "name:xx": "Bartlett Peak"
  }
}
