{
  "type": "FeatureCollection",
  "features": [
    {
      "geometry": {
        "type": "Point",
        "coordinates": [
          -105.316667,
          19.933333
        ]
      },
      "type": "Feature",
      "properties": {
        "hierarchy": [
          "tgn:7439800",
          "tgn:7005586",
          "tgn:1000001",
          "tgn:7005560",
          "tgn:7029392"
        ],
        "placetype": [
          "aat:300008347"
        ],
        "id": 7439800,
        "name:xx": "Santa María Oriente"
      }
    },
    {
      "geometry": {
        "type": "Point",
        "coordinates": [
          -98.733333,
          19.85
        ]
      },
      "type": "Feature",
      "properties": {
        "hierarchy": [
          "tgn:7439801",
          "tgn:1000001",
          "tgn:1001893",
          "tgn:7005560",
          "tgn:7029392"
        ],
        "placetype": [
          "aat:300008347"
        ],
        "id": 7439801,
        "name:xx": "Santa María Nopaltepec"
      }
    },
    {
      "geometry": {
        "type": "Point",
        "coordinates": [
          -96.583333,
          17.65
        ]
      },
      "type": "Feature",
      "properties": {
        "hierarchy": [
          "tgn:7439802",
          "tgn:1000001",
          "tgn:7005591",
          "tgn:7005560",
          "tgn:7029392"
        ],
        "placetype": [
          "aat:300008347"
        ],
        "id": 7439802,
        "name:xx": "Santa María Nieves"
      }
    },
    {
      "geometry": {
        "type": "Point",
        "coordinates": [
          -100.266667,
          20.616667
        ]
      },
      "type": "Feature",
      "properties": {
        "hierarchy": [
          "tgn:7439803",
          "tgn:1000001",
          "tgn:7005593",
          "tgn:7005560",
          "tgn:7029392"
        ],
        "placetype": [
          "aat:300008347"
        ],
        "id": 7439803,
        "name:xx": "Santa Cruz"
      }
    },
    {
      "geometry": {
        "type": "Point",
        "coordinates": [
          -89.133333,
          20.566667
        ]
      },
      "type": "Feature",
      "properties": {
        "hierarchy": [
          "tgn:7439804",
          "tgn:1000001",
          "tgn:7005600",
          "tgn:7005560",
          "tgn:7029392"
        ],
        "placetype": [
          "aat:300008347"
        ],
        "id": 7439804,
        "name:xx": "Santa Cruz"
      }
    },
    {
      "geometry": {
        "type": "Point",
        "coordinates": [
          -98.266667,
          20.483333
        ]
      },
      "type": "Feature",
      "properties": {
        "hierarchy": [
          "tgn:7439805",
          "tgn:7005587",
          "tgn:1000001",
          "tgn:7005560",
          "tgn:7029392"
        ],
        "placetype": [
          "aat:300008347"
        ],
        "id": 7439805,
        "name:xx": "Santa Cruz"
      }
    },
    {
      "geometry": {
        "type": "Point",
        "coordinates": [
          -90.25,
          20.45
        ]
      },
      "type": "Feature",
      "properties": {
        "hierarchy": [
          "tgn:7439806",
          "tgn:7005578",
          "tgn:1000001",
          "tgn:7005560",
          "tgn:7029392"
        ],
        "placetype": [
          "aat:300008347"
        ],
        "id": 7439806,
        "name:xx": "Santa Cruz"
      }
    },
    {
      "geometry": {
        "type": "Point",
        "coordinates": [
          -90.4,
          20.4
        ]
      },
      "type": "Feature",
      "properties": {
        "hierarchy": [
          "tgn:7439807",
          "tgn:7005578",
          "tgn:1000001",
          "tgn:7005560",
          "tgn:7029392"
        ],
        "placetype": [
          "aat:300008347"
        ],
        "id": 7439807,
        "name:xx": "Santa Cruz"
      }
    },
    {
      "geometry": {
        "type": "Point",
        "coordinates": [
          -98.55,
          20.333333
        ]
      },
      "type": "Feature",
      "properties": {
        "hierarchy": [
          "tgn:7439808",
          "tgn:7005587",
          "tgn:1000001",
          "tgn:7005560",
          "tgn:7029392"
        ],
        "placetype": [
          "aat:300008347"
        ],
        "id": 7439808,
        "name:xx": "Santa Cruz"
      }
    },
    {
      "geometry": {
        "type": "Point",
        "coordinates": [
          -90.1,
          20.316667
        ]
      },
      "type": "Feature",
      "properties": {
        "hierarchy": [
          "tgn:7439809",
          "tgn:7005578",
          "tgn:1000001",
          "tgn:7005560",
          "tgn:7029392"
        ],
        "placetype": [
          "aat:300008347"
        ],
        "id": 7439809,
        "name:xx": "Santa Cruz"
      }
    }
  ]
}
