{
  "geometry": {
    "type": "Point",
    "coordinates": [
      -70.6333,
      41.55
    ]
  },
  "type": "Feature",
  "properties": {
    "hierarchy": [
      "tgn:2737091",
      "tgn:1002165",
      "tgn:1000001",
      "tgn:7012149",
      "tgn:7007517",
      "tgn:7029392"
    ],
    "placetype": [
      "aat:300008680"
    ],
    "id": 2737091,
    "name:xx": "Two Ponds"
  }
}
