{
  "geometry": {
    "type": "Point",
    "coordinates": [
      -77.7333,
      42.75
    ]
  },
  "type": "Feature",
  "properties": {
    "hierarchy": [
      "tgn:2187196",
      "tgn:1000001",
      "tgn:7012149",
      "tgn:1002604",
      "tgn:7007568",
      "tgn:7029392"
    ],
    "placetype": [
      "aat:300008798"
    ],
    "id": 2187196,
    "name:xx": "Booher Hill"
  }
}
