{
  "geometry": {
    "type": "Point",
    "coordinates": [
      -83.3667,
      35.7333
    ]
  },
  "type": "Feature",
  "properties": {
    "hierarchy": [
      "tgn:2450009",
      "tgn:1000001",
      "tgn:7012149",
      "tgn:2001914",
      "tgn:7007825",
      "tgn:7029392"
    ],
    "placetype": [
      "aat:300008706"
    ],
    "id": 2450009,
    "name:xx": "Lindsey Creek"
  }
}
