{
  "geometry": {
    "type": "Point",
    "coordinates": [
      -94.85,
      42.8333
    ]
  },
  "type": "Feature",
  "properties": {
    "hierarchy": [
      "tgn:2035087",
      "tgn:1000001",
      "tgn:7012149",
      "tgn:2000636",
      "tgn:7007253",
      "tgn:7029392"
    ],
    "placetype": [
      "aat:300008347"
    ],
    "id": 2035087,
    "name:xx": "Laurens"
  }
}
