{
  "geometry": {
    "type": "Point",
    "coordinates": [
      -106.1667,
      35.9667
    ]
  },
  "type": "Feature",
  "properties": {
    "hierarchy": [
      "tgn:2643977",
      "tgn:1000001",
      "tgn:7012149",
      "tgn:2001449",
      "tgn:7007566",
      "tgn:7029392"
    ],
    "placetype": [
      "aat:300008347",
      "aat:300387324"
    ],
    "id": 2643977,
    "name:xx": "Santa Clara Indian Reservation"
  }
}
