{
  "geometry": {
    "type": "Point",
    "coordinates": [
      -99.9167,
      37.35
    ]
  },
  "type": "Feature",
  "properties": {
    "hierarchy": [
      "tgn:2460494",
      "tgn:1000001",
      "tgn:2000672",
      "tgn:7012149",
      "tgn:7007254",
      "tgn:7029392"
    ],
    "placetype": [
      "aat:300008706"
    ],
    "id": 2460494,
    "name:xx": "Little Sandy Creek"
  }
}
