{
  "geometry": {
    "type": "Point",
    "coordinates": [
      -109.2667,
      38.2833
    ]
  },
  "type": "Feature",
  "properties": {
    "hierarchy": [
      "tgn:2758611",
      "tgn:1000001",
      "tgn:7012149",
      "tgn:2002119",
      "tgn:7007827",
      "tgn:7029392"
    ],
    "placetype": [
      "aat:300008761"
    ],
    "id": 2758611,
    "name:xx": "West Coyote Wash"
  }
}
