{
  "geometry": {
    "type": "Point",
    "coordinates": [
      -121.5667,
      38.7833
    ]
  },
  "type": "Feature",
  "properties": {
    "hierarchy": [
      "tgn:2148924",
      "tgn:1000001",
      "tgn:7012149",
      "tgn:7007157",
      "tgn:1002937",
      "tgn:7029392"
    ],
    "placetype": [
      "aat:300008798"
    ],
    "id": 2148924,
    "name:xx": "Barney Mound"
  }
}
