{
  "geometry": {
    "type": "Point",
    "coordinates": [
      -106.95,
      40.65
    ]
  },
  "type": "Feature",
  "properties": {
    "hierarchy": [
      "tgn:2217544",
      "tgn:1000001",
      "tgn:7012149",
      "tgn:7007158",
      "tgn:2000245",
      "tgn:7029392"
    ],
    "placetype": [
      "aat:300006075"
    ],
    "id": 2217544,
    "name:xx": "Campbell Ditch"
  }
}
