{
  "geometry": {
    "type": "Point",
    "coordinates": [
      -99.55,
      21.35
    ]
  },
  "type": "Feature",
  "properties": {
    "hierarchy": [
      "tgn:7400020",
      "tgn:1000001",
      "tgn:7005593",
      "tgn:7005560",
      "tgn:7029392"
    ],
    "placetype": [
      "aat:300008347"
    ],
    "id": 7400020,
    "name:xx": "La Estancia"
  }
}
