{
  "geometry": {
    "type": "Point",
    "coordinates": [
      -3.1833,
      7.1667
    ]
  },
  "type": "Feature",
  "properties": {
    "hierarchy": [
      "tgn:1090306",
      "tgn:7001242",
      "tgn:7018265",
      "tgn:1000168",
      "tgn:7029392"
    ],
    "placetype": [
      "aat:300008347"
    ],
    "id": 1090306,
    "name:xx": "Agnibilékrou"
  }
}
