{
  "geometry": {
    "type": "Point",
    "coordinates": [
      35.0167,
      28.4667
    ]
  },
  "type": "Feature",
  "properties": {
    "hierarchy": [
      "tgn:7018826",
      "tgn:7000677",
      "tgn:1000004",
      "tgn:7003877",
      "tgn:1000137",
      "tgn:7029392"
    ],
    "placetype": [
      "aat:300008347"
    ],
    "id": 7018826,
    "name:xx": "Al-Bidʻ"
  }
}
