{
  "type": "FeatureCollection",
  "features": [
    {
      "geometry": {
        "type": "Point",
        "coordinates": [
          -82.8667,
          38.7833
        ]
      },
      "type": "Feature",
      "properties": {
        "hierarchy": [
          "tgn:2302350",
          "tgn:1000001",
          "tgn:7012149",
          "tgn:1002877",
          "tgn:7007706",
          "tgn:7029392"
        ],
        "placetype": [
          "aat:300266640"
        ],
        "id": 2302350,
        "name:xx": "Dutch Ridge"
      }
    },
    {
      "geometry": {
        "type": "Point",
        "coordinates": [
          -81.3167,
          38.3833
        ]
      },
      "type": "Feature",
      "properties": {
        "hierarchy": [
          "tgn:2302351",
          "tgn:1000001",
          "tgn:7012149",
          "tgn:2002270",
          "tgn:7013961",
          "tgn:7029392"
        ],
        "placetype": [
          "aat:300266640"
        ],
        "id": 2302351,
        "name:xx": "Dutch Ridge"
      }
    },
    {
      "geometry": {
        "type": "Point",
        "coordinates": [
          -81.45,
          38.8667
        ]
      },
      "type": "Feature",
      "properties": {
        "hierarchy": [
          "tgn:2302352",
          "tgn:1000001",
          "tgn:7012149",
          "tgn:2002293",
          "tgn:7013961",
          "tgn:7029392"
        ],
        "placetype": [
          "aat:300266640"
        ],
        "id": 2302352,
        "name:xx": "Dutch Ridge"
      }
    },
    {
      "geometry": {
        "type": "Point",
        "coordinates": [
          -81.6833,
          39.05
        ]
      },
      "type": "Feature",
      "properties": {
        "hierarchy": [
          "tgn:2302353",
          "tgn:1000001",
          "tgn:7012149",
          "tgn:2002268",
          "tgn:7013961",
          "tgn:7029392"
        ],
        "placetype": [
          "aat:300266640"
        ],
        "id": 2302353,
        "name:xx": "Dutch Ridge"
      }
    },
    {
      "geometry": {
        "type": "Point",
        "coordinates": [
          -81.5667,
          39.1
        ]
      },
      "type": "Feature",
      "properties": {
        "hierarchy": [
          "tgn:2302354",
          "tgn:1000001",
          "tgn:7012149",
          "tgn:2002303",
          "tgn:7013961",
          "tgn:7029392"
        ],
        "placetype": [
          "aat:300266640"
        ],
        "id": 2302354,
        "name:xx": "Dutch Ridge"
      }
    },
    {
      "geometry": {
        "type": "Point",
        "coordinates": [
          -90.9833,
          43.0833
        ]
      },
      "type": "Feature",
      "properties": {
        "hierarchy": [
          "tgn:2302355",
          "tgn:1000001",
          "tgn:2002316",
          "tgn:7012149",
          "tgn:7007922",
          "tgn:7029392"
        ],
        "placetype": [
          "aat:300266640"
        ],
        "id": 2302355,
        "name:xx": "Dutch Ridge"
      }
    },
    {
      "geometry": {
        "type": "Point",
        "coordinates": [
          -86.3833,
          38.9667
        ]
      },
      "type": "Feature",
      "properties": {
        "hierarchy": [
          "tgn:2302356",
          "tgn:1000001",
          "tgn:7012149",
          "tgn:1002678",
          "tgn:7007252",
          "tgn:7029392"
        ],
        "placetype": [
          "aat:300008680"
        ],
        "id": 2302356,
        "name:xx": "Dutch Ridge Lake"
      }
    },
    {
      "geometry": {
        "type": "Point",
        "coordinates": [
          -82.95,
          38.9667
        ]
      },
      "type": "Feature",
      "properties": {
        "hierarchy": [
          "tgn:2302357",
          "tgn:1000001",
          "tgn:7012149",
          "tgn:1002788",
          "tgn:7007706",
          "tgn:7029392"
        ],
        "placetype": [
          "aat:300008699"
        ],
        "id": 2302357,
        "name:xx": "Dutch Run"
      }
    },
    {
      "geometry": {
        "type": "Point",
        "coordinates": [
          -82.1167,
          40.4
        ]
      },
      "type": "Feature",
      "properties": {
        "hierarchy": [
          "tgn:2302358",
          "tgn:1000001",
          "tgn:1002304",
          "tgn:7012149",
          "tgn:7007706",
          "tgn:7029392"
        ],
        "placetype": [
          "aat:300008699"
        ],
        "id": 2302358,
        "name:xx": "Dutch Run"
      }
    },
    {
      "geometry": {
        "type": "Point",
        "coordinates": [
          -83.8833,
          40.9167
        ]
      },
      "type": "Feature",
      "properties": {
        "hierarchy": [
          "tgn:2302359",
          "tgn:1000001",
          "tgn:7012149",
          "tgn:7007706",
          "tgn:7029392"
        ],
        "placetype": [
          "aat:300008699"
        ],
        "id": 2302359,
        "name:xx": "Dutch Run"
      }
    }
  ]
}
