{
  "geometry": {
    "type": "Point",
    "coordinates": [
      -85.55,
      33.45
    ]
  },
  "type": "Feature",
  "properties": {
    "hierarchy": [
      "tgn:2267154",
      "tgn:7002659",
      "tgn:1000001",
      "tgn:7012149",
      "tgn:2000055",
      "tgn:7029392"
    ],
    "placetype": [
      "aat:300000390"
    ],
    "id": 2267154,
    "name:xx": "Crews Mine"
  }
}
