{
  "geometry": {
    "type": "Point",
    "coordinates": [
      -122.2333,
      49.1667
    ]
  },
  "type": "Feature",
  "properties": {
    "hierarchy": [
      "tgn:1116574",
      "tgn:7005735",
      "tgn:7005685",
      "tgn:1000001",
      "tgn:7029392"
    ],
    "placetype": [
      "aat:300008680"
    ],
    "id": 1116574,
    "name:xx": "Hatzic Lake"
  }
}
