{
  "geometry": {
    "type": "Point",
    "coordinates": [
      79.23806,
      24.141165
    ]
  },
  "type": "Feature",
  "properties": {
    "hierarchy": [
      "tgn:7563408",
      "tgn:1000004",
      "tgn:7000198",
      "tgn:1001894",
      "tgn:7029392"
    ],
    "placetype": [
      "aat:300167671"
    ],
    "name:en": "Rāmpur",
    "id": 7563408
  }
}
