{
  "geometry": {
    "type": "Point",
    "coordinates": [
      117.4333,
      36.7833
    ]
  },
  "type": "Feature",
  "properties": {
    "hierarchy": [
      "tgn:1073880",
      "tgn:1000004",
      "tgn:7002085",
      "tgn:1000111",
      "tgn:7029392"
    ],
    "placetype": [
      "aat:300008347"
    ],
    "id": 1073880,
    "name:xx": "Zhangqiu"
  }
}
