{
  "geometry": {
    "type": "Point",
    "coordinates": [
      -91.8333,
      38.35
    ]
  },
  "type": "Feature",
  "properties": {
    "hierarchy": [
      "tgn:2340720",
      "tgn:1000001",
      "tgn:7012149",
      "tgn:1002755",
      "tgn:7007523",
      "tgn:7029392"
    ],
    "placetype": [
      "aat:300008761"
    ],
    "id": 2340720,
    "name:xx": "Fresh Water Hollow"
  }
}
