{
  "geometry": {
    "type": "Point",
    "coordinates": [
      -85.3333,
      38.0167
    ]
  },
  "type": "Feature",
  "properties": {
    "hierarchy": [
      "tgn:2178541",
      "tgn:1000001",
      "tgn:7012149",
      "tgn:2000843",
      "tgn:7007255",
      "tgn:7029392"
    ],
    "placetype": [
      "aat:300008798"
    ],
    "id": 2178541,
    "name:xx": "Blacks Hill"
  }
}
