{
  "geometry": {
    "type": "Point",
    "coordinates": [
      -86.5333,
      32.8667
    ]
  },
  "type": "Feature",
  "properties": {
    "hierarchy": [
      "tgn:2478577",
      "tgn:7002659",
      "tgn:1000001",
      "tgn:2000010",
      "tgn:7012149",
      "tgn:7029392"
    ],
    "placetype": [
      "aat:300000390"
    ],
    "id": 2478577,
    "name:xx": "Maddox Mine"
  }
}
