{
  "geometry": {
    "type": "Point",
    "coordinates": [
      -66.5333,
      -30.5167
    ]
  },
  "type": "Feature",
  "properties": {
    "hierarchy": [
      "tgn:1020080",
      "tgn:7006477",
      "tgn:1001376",
      "tgn:1000002",
      "tgn:7029392"
    ],
    "placetype": [
      "aat:300008347"
    ],
    "id": 1020080,
    "name:xx": "Tama"
  }
}
