{
  "geometry": {
    "type": "Point",
    "coordinates": [
      -86.15,
      38.3667
    ]
  },
  "type": "Feature",
  "properties": {
    "hierarchy": [
      "tgn:2199195",
      "tgn:1000001",
      "tgn:7012149",
      "tgn:1002457",
      "tgn:7007252",
      "tgn:7029392"
    ],
    "placetype": [
      "aat:300008798"
    ],
    "id": 2199195,
    "name:xx": "Brunner Hill"
  }
}
