{
  "geometry": {
    "type": "Point",
    "coordinates": [
      -73.75,
      40.7833
    ]
  },
  "type": "Feature",
  "properties": {
    "hierarchy": [
      "tgn:2737963",
      "tgn:1000001",
      "tgn:7012149",
      "tgn:1002708",
      "tgn:7007568",
      "tgn:7029392"
    ],
    "placetype": [
      "aat:300006191"
    ],
    "id": 2737963,
    "name:xx": "Udalls Millpond"
  }
}
