{
  "geometry": {
    "type": "Point",
    "coordinates": [
      -97.063889,
      17.3675
    ]
  },
  "type": "Feature",
  "properties": {
    "hierarchy": [
      "tgn:7415082",
      "tgn:1000001",
      "tgn:7005591",
      "tgn:7005560",
      "tgn:7029392"
    ],
    "placetype": [
      "aat:300008347"
    ],
    "id": 7415082,
    "name:es": "Río Florido"
  }
}
