{
  "geometry": {
    "type": "Point",
    "coordinates": [
      -108.0667,
      38.8833
    ]
  },
  "type": "Feature",
  "properties": {
    "hierarchy": [
      "tgn:2288331",
      "tgn:1000001",
      "tgn:7012149",
      "tgn:2000206",
      "tgn:7007158",
      "tgn:7029392"
    ],
    "placetype": [
      "aat:300006075"
    ],
    "id": 2288331,
    "name:xx": "Dirty George Creek and Doughspoon Aqueduct"
  }
}
