{
  "type": "FeatureCollection",
  "features": [
    {
      "geometry": {
        "type": "Point",
        "coordinates": [
          -1.333333,
          51.333333
        ]
      },
      "type": "Feature",
      "properties": {
        "hierarchy": [
          "tgn:4005020",
          "tgn:7002445",
          "tgn:1000003",
          "tgn:7008139",
          "tgn:7008591",
          "tgn:7029392"
        ],
        "placetype": [
          "aat:300008347",
          "aat:300008372"
        ],
        "name:en": "Highclere",
        "id": 4005020
      }
    },
    {
      "geometry": {
        "type": "Point",
        "coordinates": [
          -1.691667,
          50.738889
        ]
      },
      "type": "Feature",
      "properties": {
        "hierarchy": [
          "tgn:4005021",
          "tgn:7002445",
          "tgn:1000003",
          "tgn:7011961",
          "tgn:7008591",
          "tgn:7029392"
        ],
        "placetype": [
          "aat:300008347"
        ],
        "name:en": "Highcliffe",
        "id": 4005021
      }
    },
    {
      "geometry": {
        "type": "Point",
        "coordinates": [
          -2.3,
          51.8667
        ]
      },
      "type": "Feature",
      "properties": {
        "hierarchy": [
          "tgn:4005026",
          "tgn:7002445",
          "tgn:1000003",
          "tgn:7008132",
          "tgn:7008591",
          "tgn:7029392"
        ],
        "placetype": [
          "aat:300008347",
          "aat:300008372"
        ],
        "id": 4005026,
        "name:xx": "Highnam"
      }
    }
  ]
}
