{
  "geometry": {
    "type": "Point",
    "coordinates": [
      -123.3333,
      43.2167
    ]
  },
  "type": "Feature",
  "properties": {
    "hierarchy": [
      "tgn:2085455",
      "tgn:1000001",
      "tgn:7012149",
      "tgn:2001706",
      "tgn:7007708",
      "tgn:7029392"
    ],
    "placetype": [
      "aat:300008347"
    ],
    "id": 2085455,
    "name:xx": "Roseburg"
  }
}
