{
  "type": "FeatureCollection",
  "features": [
    {
      "geometry": {
        "type": "Point",
        "coordinates": [
          -90.2167,
          38.4833
        ]
      },
      "type": "Feature",
      "properties": {
        "hierarchy": [
          "tgn:2029650",
          "tgn:1000001",
          "tgn:7012149",
          "tgn:7016022",
          "tgn:7007251",
          "tgn:7029392"
        ],
        "placetype": [
          "aat:300008347",
          "aat:300387210"
        ],
        "id": 2029650,
        "name:xx": "Phelps"
      }
    },
    {
      "geometry": {
        "type": "Point",
        "coordinates": [
          -90.1167,
          39.9167
        ]
      },
      "type": "Feature",
      "properties": {
        "hierarchy": [
          "tgn:2029651",
          "tgn:1000001",
          "tgn:1002241",
          "tgn:7012149",
          "tgn:7007251",
          "tgn:7029392"
        ],
        "placetype": [
          "aat:300008347"
        ],
        "id": 2029651,
        "name:xx": "Philadelphia"
      }
    },
    {
      "geometry": {
        "type": "Point",
        "coordinates": [
          -88.0167,
          38.1333
        ]
      },
      "type": "Feature",
      "properties": {
        "hierarchy": [
          "tgn:2029653",
          "tgn:1000001",
          "tgn:7012149",
          "tgn:2000537",
          "tgn:7007251",
          "tgn:7029392"
        ],
        "placetype": [
          "aat:300008347"
        ],
        "id": 2029653,
        "name:xx": "Phillipstown"
      }
    },
    {
      "geometry": {
        "type": "Point",
        "coordinates": [
          -88.15,
          40
        ]
      },
      "type": "Feature",
      "properties": {
        "hierarchy": [
          "tgn:2029654",
          "tgn:1000001",
          "tgn:1002253",
          "tgn:7012149",
          "tgn:7007251",
          "tgn:7029392"
        ],
        "placetype": [
          "aat:300008347"
        ],
        "id": 2029654,
        "name:xx": "Philo"
      }
    },
    {
      "geometry": {
        "type": "Point",
        "coordinates": [
          -87.6333,
          41.6
        ]
      },
      "type": "Feature",
      "properties": {
        "hierarchy": [
          "tgn:2029656",
          "tgn:1000001",
          "tgn:7013649",
          "tgn:7012149",
          "tgn:7007251",
          "tgn:7029392"
        ],
        "placetype": [
          "aat:300008347"
        ],
        "id": 2029656,
        "name:xx": "Phoenix"
      }
    },
    {
      "geometry": {
        "type": "Point",
        "coordinates": [
          -90.1167,
          39.1
        ]
      },
      "type": "Feature",
      "properties": {
        "hierarchy": [
          "tgn:2029657",
          "tgn:1000001",
          "tgn:7012149",
          "tgn:1002620",
          "tgn:7007251",
          "tgn:7029392"
        ],
        "placetype": [
          "aat:300008347"
        ],
        "id": 2029657,
        "name:xx": "Piasa"
      }
    }
  ]
}
