{
  "geometry": {
    "type": "Point",
    "coordinates": [
      -78.7333,
      35.9167
    ]
  },
  "type": "Feature",
  "properties": {
    "hierarchy": [
      "tgn:2739356",
      "tgn:1000001",
      "tgn:7012149",
      "tgn:2001548",
      "tgn:7007709",
      "tgn:7029392"
    ],
    "placetype": [
      "aat:300008706"
    ],
    "id": 2739356,
    "name:xx": "Upper Barton Creek"
  }
}
