{
  "geometry": {
    "type": "Point",
    "coordinates": [
      79.402699,
      27.124992
    ]
  },
  "type": "Feature",
  "properties": {
    "hierarchy": [
      "tgn:7561356",
      "tgn:1000004",
      "tgn:7000198",
      "tgn:7016722",
      "tgn:7029392"
    ],
    "placetype": [
      "aat:300008347"
    ],
    "name:en": "Kushālpur",
    "id": 7561356
  }
}
