{
  "geometry": {
    "type": "Point",
    "coordinates": [
      -156.0833,
      20.7833
    ]
  },
  "type": "Feature",
  "properties": {
    "hierarchy": [
      "tgn:2430603",
      "tgn:1002648",
      "tgn:1000001",
      "tgn:7019158",
      "tgn:7012149",
      "tgn:7007249",
      "tgn:7029392"
    ],
    "placetype": [
      "aat:300008761"
    ],
    "id": 2430603,
    "name:xx": "Kalepalehua Gulch"
  }
}
