{
  "geometry": {
    "type": "Point",
    "coordinates": [
      -108.1667,
      47.9167
    ]
  },
  "type": "Feature",
  "properties": {
    "hierarchy": [
      "tgn:2744424",
      "tgn:1000001",
      "tgn:7012149",
      "tgn:2001295",
      "tgn:7007524",
      "tgn:7029392"
    ],
    "placetype": [
      "aat:300006191"
    ],
    "id": 2744424,
    "name:xx": "Veseth Reservoir"
  }
}
