{
  "geometry": {
    "type": "Point",
    "coordinates": [
      -83.3833,
      35.8667
    ]
  },
  "type": "Feature",
  "properties": {
    "hierarchy": [
      "tgn:2657886",
      "tgn:1000001",
      "tgn:7012149",
      "tgn:2001914",
      "tgn:7007825",
      "tgn:7029392"
    ],
    "placetype": [
      "aat:300008798"
    ],
    "id": 2657886,
    "name:xx": "Shell Mountain"
  }
}
