{
  "geometry": {
    "type": "Point",
    "coordinates": [
      -79.4833,
      41.7333
    ]
  },
  "type": "Feature",
  "properties": {
    "hierarchy": [
      "tgn:1132675",
      "tgn:1000001",
      "tgn:7012149",
      "tgn:1002988",
      "tgn:7007710",
      "tgn:7029392"
    ],
    "placetype": [
      "aat:300008706"
    ],
    "id": 1132675,
    "name:xx": "Caldwell Creek"
  }
}
