{
  "type": "FeatureCollection",
  "features": [
    {
      "geometry": {
        "type": "Point",
        "coordinates": [
          -7.016667,
          42.816667
        ]
      },
      "type": "Feature",
      "properties": {
        "hierarchy": [
          "tgn:7293900",
          "tgn:7002829",
          "tgn:1000003",
          "tgn:7002786",
          "tgn:1000095",
          "tgn:7029392"
        ],
        "placetype": [
          "aat:300008347"
        ],
        "id": 7293900,
        "name:xx": "Vilachá"
      }
    },
    {
      "geometry": {
        "type": "Point",
        "coordinates": [
          -7.383333,
          42.466667
        ]
      },
      "type": "Feature",
      "properties": {
        "hierarchy": [
          "tgn:7293901",
          "tgn:7002829",
          "tgn:1000003",
          "tgn:7002786",
          "tgn:1000095",
          "tgn:7029392"
        ],
        "placetype": [
          "aat:300008347"
        ],
        "id": 7293901,
        "name:xx": "Vilachá"
      }
    },
    {
      "geometry": {
        "type": "Point",
        "coordinates": [
          0.849861,
          42.725154
        ]
      },
      "type": "Feature",
      "properties": {
        "hierarchy": [
          "tgn:7293902",
          "tgn:7008912",
          "tgn:7030216",
          "tgn:1000003",
          "tgn:1000095",
          "tgn:7029392"
        ],
        "placetype": [
          "aat:300266640"
        ],
        "id": 7293902,
        "name:xx": "Vilach, Sierra de"
      }
    },
    {
      "geometry": {
        "type": "Point",
        "coordinates": [
          0.798614,
          42.721173
        ]
      },
      "type": "Feature",
      "properties": {
        "hierarchy": [
          "tgn:7293903",
          "tgn:7008912",
          "tgn:7030216",
          "tgn:1000003",
          "tgn:1000095",
          "tgn:7029392"
        ],
        "placetype": [
          "aat:300008347"
        ],
        "id": 7293903,
        "name:xx": "Vilach"
      }
    },
    {
      "geometry": {
        "type": "Point",
        "coordinates": [
          -8.05,
          43.6
        ]
      },
      "type": "Feature",
      "properties": {
        "hierarchy": [
          "tgn:7293904",
          "tgn:7002824",
          "tgn:1000003",
          "tgn:7002786",
          "tgn:1000095",
          "tgn:7029392"
        ],
        "placetype": [
          "aat:300008347"
        ],
        "id": 7293904,
        "name:xx": "Vilaboa"
      }
    },
    {
      "geometry": {
        "type": "Point",
        "coordinates": [
          -8.916667,
          42.75
        ]
      },
      "type": "Feature",
      "properties": {
        "hierarchy": [
          "tgn:7293905",
          "tgn:7002824",
          "tgn:1000003",
          "tgn:7002786",
          "tgn:1000095",
          "tgn:7029392"
        ],
        "placetype": [
          "aat:300008347"
        ],
        "id": 7293905,
        "name:xx": "Vilaboa"
      }
    },
    {
      "geometry": {
        "type": "Point",
        "coordinates": [
          -7.033333,
          42.283333
        ]
      },
      "type": "Feature",
      "properties": {
        "hierarchy": [
          "tgn:7293907",
          "tgn:7002831",
          "tgn:1000003",
          "tgn:7002786",
          "tgn:1000095",
          "tgn:7029392"
        ],
        "placetype": [
          "aat:300008347"
        ],
        "id": 7293907,
        "name:xx": "Vilaboa"
      }
    },
    {
      "geometry": {
        "type": "Point",
        "coordinates": [
          2.773767,
          41.957459
        ]
      },
      "type": "Feature",
      "properties": {
        "hierarchy": [
          "tgn:7293908",
          "tgn:7002820",
          "tgn:7030216",
          "tgn:1000003",
          "tgn:1000095",
          "tgn:7029392"
        ],
        "placetype": [
          "aat:300008347"
        ],
        "id": 7293908,
        "name:xx": "Vilablareix"
      }
    }
  ]
}
