{
  "type": "FeatureCollection",
  "features": [
    {
      "geometry": {
        "type": "Point",
        "coordinates": [
          -108.25,
          37.8333
        ]
      },
      "type": "Feature",
      "properties": {
        "hierarchy": [
          "tgn:2535680",
          "tgn:1000001",
          "tgn:7012149",
          "tgn:2000208",
          "tgn:7007158",
          "tgn:7029392"
        ],
        "placetype": [
          "aat:300008706"
        ],
        "id": 2535680,
        "name:xx": "Nash Creek"
      }
    },
    {
      "geometry": {
        "type": "Point",
        "coordinates": [
          -84.4333,
          33.4667
        ]
      },
      "type": "Feature",
      "properties": {
        "hierarchy": [
          "tgn:2535681",
          "tgn:1000001",
          "tgn:7012149",
          "tgn:2000347",
          "tgn:7007248",
          "tgn:7029392"
        ],
        "placetype": [
          "aat:300008706"
        ],
        "id": 2535681,
        "name:xx": "Nash Creek"
      }
    },
    {
      "geometry": {
        "type": "Point",
        "coordinates": [
          -91.7,
          42.4333
        ]
      },
      "type": "Feature",
      "properties": {
        "hierarchy": [
          "tgn:2535682",
          "tgn:1000001",
          "tgn:2000570",
          "tgn:7012149",
          "tgn:7007253",
          "tgn:7029392"
        ],
        "placetype": [
          "aat:300008706"
        ],
        "id": 2535682,
        "name:xx": "Nash Creek"
      }
    },
    {
      "geometry": {
        "type": "Point",
        "coordinates": [
          -93.4167,
          31.3333
        ]
      },
      "type": "Feature",
      "properties": {
        "hierarchy": [
          "tgn:2535683",
          "tgn:1000001",
          "tgn:7012149",
          "tgn:2000896",
          "tgn:7007256",
          "tgn:7029392"
        ],
        "placetype": [
          "aat:300008706"
        ],
        "id": 2535683,
        "name:xx": "Nash Creek"
      }
    },
    {
      "geometry": {
        "type": "Point",
        "coordinates": [
          -88.7167,
          46.0833
        ]
      },
      "type": "Feature",
      "properties": {
        "hierarchy": [
          "tgn:2535684",
          "tgn:1000001",
          "tgn:7012149",
          "tgn:2000966",
          "tgn:7007520",
          "tgn:7029392"
        ],
        "placetype": [
          "aat:300008706"
        ],
        "id": 2535684,
        "name:xx": "Nash Creek"
      }
    },
    {
      "geometry": {
        "type": "Point",
        "coordinates": [
          -87.5833,
          46.6
        ]
      },
      "type": "Feature",
      "properties": {
        "hierarchy": [
          "tgn:2535685",
          "tgn:1000001",
          "tgn:7012149",
          "tgn:2000975",
          "tgn:7007520",
          "tgn:7029392"
        ],
        "placetype": [
          "aat:300008706"
        ],
        "id": 2535685,
        "name:xx": "Nash Creek"
      }
    },
    {
      "geometry": {
        "type": "Point",
        "coordinates": [
          -85.8,
          43.1167
        ]
      },
      "type": "Feature",
      "properties": {
        "hierarchy": [
          "tgn:2535686",
          "tgn:1000001",
          "tgn:7012149",
          "tgn:1002540",
          "tgn:7007520",
          "tgn:7029392"
        ],
        "placetype": [
          "aat:300008706"
        ],
        "id": 2535686,
        "name:xx": "Nash Creek"
      }
    },
    {
      "geometry": {
        "type": "Point",
        "coordinates": [
          -89.25,
          35.9
        ]
      },
      "type": "Feature",
      "properties": {
        "hierarchy": [
          "tgn:2535687",
          "tgn:1000001",
          "tgn:7012149",
          "tgn:7007825",
          "tgn:7029392"
        ],
        "placetype": [
          "aat:300008706"
        ],
        "id": 2535687,
        "name:xx": "Nash Creek"
      }
    },
    {
      "geometry": {
        "type": "Point",
        "coordinates": [
          -97.8167,
          29.6333
        ]
      },
      "type": "Feature",
      "properties": {
        "hierarchy": [
          "tgn:2535688",
          "tgn:1000001",
          "tgn:7012149",
          "tgn:1002431",
          "tgn:7007826",
          "tgn:7029392"
        ],
        "placetype": [
          "aat:300008706"
        ],
        "id": 2535688,
        "name:xx": "Nash Creek"
      }
    },
    {
      "geometry": {
        "type": "Point",
        "coordinates": [
          -98.8,
          32.2667
        ]
      },
      "type": "Feature",
      "properties": {
        "hierarchy": [
          "tgn:2535689",
          "tgn:1000001",
          "tgn:7012149",
          "tgn:2001978",
          "tgn:7007826",
          "tgn:7029392"
        ],
        "placetype": [
          "aat:300008706"
        ],
        "id": 2535689,
        "name:xx": "Nash Creek"
      }
    }
  ]
}
