{
  "geometry": {
    "type": "Point",
    "coordinates": [
      -76.2833,
      40.4667
    ]
  },
  "type": "Feature",
  "properties": {
    "hierarchy": [
      "tgn:2086383",
      "tgn:1000001",
      "tgn:7013387",
      "tgn:7012149",
      "tgn:7007710",
      "tgn:7029392"
    ],
    "placetype": [
      "aat:300008347"
    ],
    "id": 2086383,
    "name:xx": "Bethel"
  }
}
