{
  "geometry": {
    "type": "Point",
    "coordinates": [
      -81.4667,
      40.8833
    ]
  },
  "type": "Feature",
  "properties": {
    "hierarchy": [
      "tgn:2080510",
      "tgn:1000001",
      "tgn:7012149",
      "tgn:1002917",
      "tgn:7007706",
      "tgn:7029392"
    ],
    "placetype": [
      "aat:300008347"
    ],
    "id": 2080510,
    "name:xx": "McDonaldsville"
  }
}
