{
  "geometry": {
    "type": "Point",
    "coordinates": [
      -111.5833,
      35.85
    ]
  },
  "type": "Feature",
  "properties": {
    "hierarchy": [
      "tgn:2595688",
      "tgn:1000001",
      "tgn:7006451",
      "tgn:2000092",
      "tgn:7012149",
      "tgn:7029392"
    ],
    "placetype": [
      "aat:300008761"
    ],
    "id": 2595688,
    "name:xx": "Pothole Canyon"
  }
}
