{
  "type": "FeatureCollection",
  "features": [
    {
      "geometry": {
        "type": "Point",
        "coordinates": [
          -90.3,
          18.25
        ]
      },
      "type": "Feature",
      "properties": {
        "hierarchy": [
          "tgn:7355270",
          "tgn:7005578",
          "tgn:1000001",
          "tgn:7005560",
          "tgn:7029392"
        ],
        "placetype": [
          "aat:300008347"
        ],
        "id": 7355270,
        "name:xx": "Cedros"
      }
    },
    {
      "geometry": {
        "type": "Point",
        "coordinates": [
          -105.3,
          21.9
        ]
      },
      "type": "Feature",
      "properties": {
        "hierarchy": [
          "tgn:7355271",
          "tgn:1000001",
          "tgn:1001906",
          "tgn:7005560",
          "tgn:7029392"
        ],
        "placetype": [
          "aat:300008347"
        ],
        "id": 7355271,
        "name:xx": "Cedro Ramudo"
      }
    },
    {
      "geometry": {
        "type": "Point",
        "coordinates": [
          -98.416667,
          26.15
        ]
      },
      "type": "Feature",
      "properties": {
        "hierarchy": [
          "tgn:7355272",
          "tgn:1000001",
          "tgn:7005597",
          "tgn:7005560",
          "tgn:7029392"
        ],
        "placetype": [
          "aat:300000241"
        ],
        "id": 7355272,
        "name:xx": "Rancho del Cedro"
      }
    },
    {
      "geometry": {
        "type": "Point",
        "coordinates": [
          -100.966667,
          29.266667
        ]
      },
      "type": "Feature",
      "properties": {
        "hierarchy": [
          "tgn:7355273",
          "tgn:1001853",
          "tgn:1000001",
          "tgn:7005560",
          "tgn:7029392"
        ],
        "placetype": [
          "aat:300008699"
        ],
        "id": 7355273,
        "name:xx": "Cedro, Arroyo del"
      }
    },
    {
      "geometry": {
        "type": "Point",
        "coordinates": [
          -109.1,
          27.333333
        ]
      },
      "type": "Feature",
      "properties": {
        "hierarchy": [
          "tgn:7355274",
          "tgn:1000001",
          "tgn:1001960",
          "tgn:7005560",
          "tgn:7029392"
        ],
        "placetype": [
          "aat:300008699"
        ],
        "id": 7355274,
        "name:xx": "Cedro, Arroyo"
      }
    },
    {
      "geometry": {
        "type": "Point",
        "coordinates": [
          -109.1,
          27.233333
        ]
      },
      "type": "Feature",
      "properties": {
        "hierarchy": [
          "tgn:7355275",
          "tgn:1000001",
          "tgn:1001960",
          "tgn:7005560",
          "tgn:7029392"
        ],
        "placetype": [
          "aat:300008699"
        ],
        "id": 7355275,
        "name:xx": "Cedro, Arroyo"
      }
    },
    {
      "geometry": {
        "type": "Point",
        "coordinates": [
          -102.6,
          23.683333
        ]
      },
      "type": "Feature",
      "properties": {
        "hierarchy": [
          "tgn:7355276",
          "tgn:1000001",
          "tgn:7005601",
          "tgn:7005560",
          "tgn:7029392"
        ],
        "placetype": [
          "aat:300007783"
        ],
        "id": 7355276,
        "name:xx": "Cedro"
      }
    },
    {
      "geometry": {
        "type": "Point",
        "coordinates": [
          -101.033333,
          29.25
        ]
      },
      "type": "Feature",
      "properties": {
        "hierarchy": [
          "tgn:7355277",
          "tgn:1001853",
          "tgn:1000001",
          "tgn:7005560",
          "tgn:7029392"
        ],
        "placetype": [
          "aat:300008347"
        ],
        "id": 7355277,
        "name:xx": "Cedro"
      }
    },
    {
      "geometry": {
        "type": "Point",
        "coordinates": [
          -107.1,
          25.483333
        ]
      },
      "type": "Feature",
      "properties": {
        "hierarchy": [
          "tgn:7355278",
          "tgn:7005583",
          "tgn:1000001",
          "tgn:7005560",
          "tgn:7029392"
        ],
        "placetype": [
          "aat:300008347"
        ],
        "id": 7355278,
        "name:xx": "Cedro"
      }
    },
    {
      "geometry": {
        "type": "Point",
        "coordinates": [
          -102.6,
          23.683333
        ]
      },
      "type": "Feature",
      "properties": {
        "hierarchy": [
          "tgn:7355279",
          "tgn:1000001",
          "tgn:7005601",
          "tgn:7005560",
          "tgn:7029392"
        ],
        "placetype": [
          "aat:300008347"
        ],
        "id": 7355279,
        "name:xx": "Cedro"
      }
    }
  ]
}
