{
  "geometry": {
    "type": "Point",
    "coordinates": [
      -107.4667,
      33.55
    ]
  },
  "type": "Feature",
  "properties": {
    "hierarchy": [
      "tgn:2768454",
      "tgn:1000001",
      "tgn:7012149",
      "tgn:2001456",
      "tgn:7007566",
      "tgn:7029392"
    ],
    "placetype": [
      "aat:300006191"
    ],
    "id": 2768454,
    "name:xx": "Whitetail Tank"
  }
}
