{
  "geometry": {
    "type": "Point",
    "coordinates": [
      -74.3833,
      39.85
    ]
  },
  "type": "Feature",
  "properties": {
    "hierarchy": [
      "tgn:2677014",
      "tgn:1000001",
      "tgn:7012149",
      "tgn:7007565",
      "tgn:7029392"
    ],
    "placetype": [
      "aat:300008699"
    ],
    "id": 2677014,
    "name:xx": "South Branch Mount Misery Brook"
  }
}
