{
  "geometry": {
    "type": "Point",
    "coordinates": [
      -93.7833,
      42.2833
    ]
  },
  "type": "Feature",
  "properties": {
    "hierarchy": [
      "tgn:2035698",
      "tgn:1000001",
      "tgn:2000600",
      "tgn:7012149",
      "tgn:7007253",
      "tgn:7029392"
    ],
    "placetype": [
      "aat:300008347"
    ],
    "id": 2035698,
    "name:xx": "Stanhope"
  }
}
