{
  "geometry": {
    "type": "Point",
    "coordinates": [
      110.5333,
      -7.45
    ]
  },
  "type": "Feature",
  "properties": {
    "hierarchy": [
      "tgn:1077362",
      "tgn:1000004",
      "tgn:1001322",
      "tgn:1000116",
      "tgn:7029392"
    ],
    "placetype": [
      "aat:300008347"
    ],
    "id": 1077362,
    "name:xx": "Ampel"
  }
}
