{
  "type": "FeatureCollection",
  "features": [
    {
      "geometry": {
        "type": "Point",
        "coordinates": [
          -106.2333,
          46.0333
        ]
      },
      "type": "Feature",
      "properties": {
        "hierarchy": [
          "tgn:2157350",
          "tgn:1000001",
          "tgn:7012149",
          "tgn:2001303",
          "tgn:7007524",
          "tgn:7029392"
        ],
        "placetype": [
          "aat:300008706"
        ],
        "id": 2157350,
        "name:xx": "Beaver Creek"
      }
    },
    {
      "geometry": {
        "type": "Point",
        "coordinates": [
          -114.3,
          46.5167
        ]
      },
      "type": "Feature",
      "properties": {
        "hierarchy": [
          "tgn:2157351",
          "tgn:1000001",
          "tgn:7012149",
          "tgn:2001300",
          "tgn:7007524",
          "tgn:7029392"
        ],
        "placetype": [
          "aat:300008706"
        ],
        "id": 2157351,
        "name:xx": "Beaver Creek"
      }
    },
    {
      "geometry": {
        "type": "Point",
        "coordinates": [
          -111.4333,
          46.6833
        ]
      },
      "type": "Feature",
      "properties": {
        "hierarchy": [
          "tgn:2157352",
          "tgn:1000001",
          "tgn:7012149",
          "tgn:2001289",
          "tgn:7007524",
          "tgn:7029392"
        ],
        "placetype": [
          "aat:300008706"
        ],
        "id": 2157352,
        "name:xx": "Beaver Creek"
      }
    },
    {
      "geometry": {
        "type": "Point",
        "coordinates": [
          -109.45,
          46.85
        ]
      },
      "type": "Feature",
      "properties": {
        "hierarchy": [
          "tgn:2157353",
          "tgn:1000001",
          "tgn:7012149",
          "tgn:2001273",
          "tgn:7007524",
          "tgn:7029392"
        ],
        "placetype": [
          "aat:300008706"
        ],
        "id": 2157353,
        "name:xx": "Beaver Creek"
      }
    },
    {
      "geometry": {
        "type": "Point",
        "coordinates": [
          -106.9,
          48.0333
        ]
      },
      "type": "Feature",
      "properties": {
        "hierarchy": [
          "tgn:2157354",
          "tgn:1000001",
          "tgn:7012149",
          "tgn:2001312",
          "tgn:7007524",
          "tgn:7029392"
        ],
        "placetype": [
          "aat:300008706"
        ],
        "id": 2157354,
        "name:xx": "Beaver Creek"
      }
    },
    {
      "geometry": {
        "type": "Point",
        "coordinates": [
          -109.6833,
          48.15
        ]
      },
      "type": "Feature",
      "properties": {
        "hierarchy": [
          "tgn:2157355",
          "tgn:1000001",
          "tgn:7012149",
          "tgn:2001280",
          "tgn:7007524",
          "tgn:7029392"
        ],
        "placetype": [
          "aat:300008706"
        ],
        "id": 2157355,
        "name:xx": "Beaver Creek"
      }
    },
    {
      "geometry": {
        "type": "Point",
        "coordinates": [
          -114.9833,
          48.65
        ]
      },
      "type": "Feature",
      "properties": {
        "hierarchy": [
          "tgn:2157356",
          "tgn:1000001",
          "tgn:7012149",
          "tgn:2001286",
          "tgn:7007524",
          "tgn:7029392"
        ],
        "placetype": [
          "aat:300008706"
        ],
        "id": 2157356,
        "name:xx": "Beaver Creek"
      }
    },
    {
      "geometry": {
        "type": "Point",
        "coordinates": [
          -104.9333,
          48.9167
        ]
      },
      "type": "Feature",
      "properties": {
        "hierarchy": [
          "tgn:2157357",
          "tgn:1000001",
          "tgn:7012149",
          "tgn:2001305",
          "tgn:7007524",
          "tgn:7029392"
        ],
        "placetype": [
          "aat:300008706"
        ],
        "id": 2157357,
        "name:xx": "Beaver Creek"
      }
    },
    {
      "geometry": {
        "type": "Point",
        "coordinates": [
          -96.3333,
          40.8833
        ]
      },
      "type": "Feature",
      "properties": {
        "hierarchy": [
          "tgn:2157358",
          "tgn:1000001",
          "tgn:2001328",
          "tgn:7012149",
          "tgn:7007525",
          "tgn:7029392"
        ],
        "placetype": [
          "aat:300008706"
        ],
        "id": 2157358,
        "name:xx": "Beaver Creek"
      }
    },
    {
      "geometry": {
        "type": "Point",
        "coordinates": [
          -98.6667,
          42.95
        ]
      },
      "type": "Feature",
      "properties": {
        "hierarchy": [
          "tgn:2157359",
          "tgn:1000001",
          "tgn:2001323",
          "tgn:7012149",
          "tgn:7007525",
          "tgn:7029392"
        ],
        "placetype": [
          "aat:300008706"
        ],
        "id": 2157359,
        "name:xx": "Beaver Creek"
      }
    }
  ]
}
