{
  "geometry": {
    "type": "Point",
    "coordinates": [
      -81.0667,
      31.8833
    ]
  },
  "type": "Feature",
  "properties": {
    "hierarchy": [
      "tgn:2363680",
      "tgn:1000001",
      "tgn:2000316",
      "tgn:7012149",
      "tgn:7007248",
      "tgn:7029392"
    ],
    "placetype": [
      "aat:300008791"
    ],
    "id": 2363680,
    "name:xx": "Green Island"
  }
}
