{
  "geometry": {
    "type": "Point",
    "coordinates": [
      -89.6167,
      46.5833
    ]
  },
  "type": "Feature",
  "properties": {
    "hierarchy": [
      "tgn:2168932",
      "tgn:1000001",
      "tgn:7012149",
      "tgn:2000986",
      "tgn:7007520",
      "tgn:7029392"
    ],
    "placetype": [
      "aat:300008707"
    ],
    "id": 2168932,
    "name:xx": "Big Iron River"
  }
}
