{
  "geometry": {
    "type": "Point",
    "coordinates": [
      -71.35,
      -38.266667
    ]
  },
  "type": "Feature",
  "properties": {
    "hierarchy": [
      "tgn:7308409",
      "tgn:1001692",
      "tgn:1000049",
      "tgn:1000002",
      "tgn:7029392"
    ],
    "placetype": [
      "aat:300008680"
    ],
    "id": 7308409,
    "name:xx": "María Jesús, Laguna"
  }
}
