{
  "geometry": {
    "type": "Point",
    "coordinates": [
      -117.9167,
      42.1167
    ]
  },
  "type": "Feature",
  "properties": {
    "hierarchy": [
      "tgn:2307197",
      "tgn:1000001",
      "tgn:7012149",
      "tgn:2001718",
      "tgn:7007708",
      "tgn:7029392"
    ],
    "placetype": [
      "aat:300008706"
    ],
    "id": 2307197,
    "name:xx": "East Fork Oregon Canyon Creek"
  }
}
