{
  "geometry": {
    "type": "Point",
    "coordinates": [
      -68.8333,
      61.0833
    ]
  },
  "type": "Feature",
  "properties": {
    "hierarchy": [
      "tgn:7013570",
      "tgn:1000004",
      "tgn:7029392"
    ],
    "placetype": [
      "aat:300008707"
    ],
    "id": 7013570,
    "name:xx": "Irtysh"
  }
}
