{
  "geometry": {
    "type": "Point",
    "coordinates": [
      148.2333,
      -22.6167
    ]
  },
  "type": "Feature",
  "properties": {
    "hierarchy": [
      "tgn:1096654",
      "tgn:7000490",
      "tgn:1000006",
      "tgn:7001830",
      "tgn:7029392"
    ],
    "placetype": [
      "aat:300008347"
    ],
    "id": 1096654,
    "name:xx": "Cotherstone"
  }
}
