{
  "geometry": {
    "type": "Point",
    "coordinates": [
      -91.5167,
      45.3333
    ]
  },
  "type": "Feature",
  "properties": {
    "hierarchy": [
      "tgn:2441548",
      "tgn:1000001",
      "tgn:7012149",
      "tgn:2002350",
      "tgn:7007922",
      "tgn:7029392"
    ],
    "placetype": [
      "aat:300008680"
    ],
    "id": 2441548,
    "name:xx": "Koehler Lake"
  }
}
