{
  "geometry": {
    "type": "Point",
    "coordinates": [
      -81.0833,
      32.55
    ]
  },
  "type": "Feature",
  "properties": {
    "hierarchy": [
      "tgn:2214837",
      "tgn:1000001",
      "tgn:7012149",
      "tgn:2001751",
      "tgn:7007712",
      "tgn:7029392"
    ],
    "placetype": [
      "aat:300008905"
    ],
    "id": 2214837,
    "name:xx": "Calfpen Bay"
  }
}
