{
  "geometry": {
    "type": "Point",
    "coordinates": [
      31.781754,
      30.555072
    ]
  },
  "type": "Feature",
  "properties": {
    "hierarchy": [
      "tgn:7522211",
      "tgn:7001242",
      "tgn:7016833",
      "tgn:1001080",
      "tgn:7029392"
    ],
    "placetype": [
      "aat:300008347"
    ],
    "name:en": "Al Ḩammādah",
    "id": 7522211
  }
}
