{
  "geometry": {
    "type": "Point",
    "coordinates": [
      73.65,
      40.7333
    ]
  },
  "type": "Feature",
  "properties": {
    "hierarchy": [
      "tgn:1051178",
      "tgn:7011476",
      "tgn:1000004",
      "tgn:7006655",
      "tgn:7029392"
    ],
    "placetype": [
      "aat:300008347"
    ],
    "id": 1051178,
    "name:xx": "Čalkojdy"
  }
}
