{
  "geometry": {
    "type": "Point",
    "coordinates": [
      -116.7167,
      38.3833
    ]
  },
  "type": "Feature",
  "properties": {
    "hierarchy": [
      "tgn:2585261",
      "tgn:1000001",
      "tgn:2001418",
      "tgn:7012149",
      "tgn:7007526",
      "tgn:7029392"
    ],
    "placetype": [
      "aat:300008798"
    ],
    "id": 2585261,
    "name:xx": "Piñon Peak"
  }
}
