{
  "geometry": {
    "type": "Point",
    "coordinates": [
      -78.9833,
      38.7167
    ]
  },
  "type": "Feature",
  "properties": {
    "hierarchy": [
      "tgn:2479524",
      "tgn:1000001",
      "tgn:7012149",
      "tgn:2002187",
      "tgn:7007919",
      "tgn:7029392"
    ],
    "placetype": [
      "aat:300008699"
    ],
    "id": 2479524,
    "name:xx": "Lairs Run"
  }
}
