{
  "geometry": {
    "type": "Point",
    "coordinates": [
      -79.05,
      36.7333
    ]
  },
  "type": "Feature",
  "properties": {
    "hierarchy": [
      "tgn:2587400",
      "tgn:1000001",
      "tgn:7012149",
      "tgn:2002166",
      "tgn:7007919",
      "tgn:7029392"
    ],
    "placetype": [
      "aat:300008347"
    ],
    "id": 2587400,
    "name:xx": "Pleasant Grove"
  }
}
