{
  "geometry": {
    "type": "Point",
    "coordinates": [
      5.8833,
      46.6167
    ]
  },
  "type": "Feature",
  "properties": {
    "hierarchy": [
      "tgn:1033473",
      "tgn:1000003",
      "tgn:7002881",
      "tgn:1000070",
      "tgn:7029392"
    ],
    "placetype": [
      "aat:300008347"
    ],
    "id": 1033473,
    "name:xx": "Ilay"
  }
}
