{
  "geometry": {
    "type": "Point",
    "coordinates": [
      -155.4667,
      19.8167
    ]
  },
  "type": "Feature",
  "properties": {
    "hierarchy": [
      "tgn:2601784",
      "tgn:7023902",
      "tgn:1000001",
      "tgn:7012149",
      "tgn:7007249",
      "tgn:7029392"
    ],
    "placetype": [
      "aat:300008798"
    ],
    "id": 2601784,
    "name:xx": "Puu Hau Kea"
  }
}
