{
  "type": "FeatureCollection",
  "features": [
    {
      "geometry": {
        "type": "Point",
        "coordinates": [
          -113.7833,
          32.8
        ]
      },
      "type": "Feature",
      "properties": {
        "hierarchy": [
          "tgn:2550540",
          "tgn:1000001",
          "tgn:7006451",
          "tgn:7012149",
          "tgn:2000104",
          "tgn:7029392"
        ],
        "placetype": [
          "aat:300008347"
        ],
        "id": 2550540,
        "name:xx": "Norton"
      }
    },
    {
      "geometry": {
        "type": "Point",
        "coordinates": [
          -93.45,
          36.3333
        ]
      },
      "type": "Feature",
      "properties": {
        "hierarchy": [
          "tgn:2550541",
          "tgn:1000001",
          "tgn:7016172",
          "tgn:2000112",
          "tgn:7012149",
          "tgn:7029392"
        ],
        "placetype": [
          "aat:300008347"
        ],
        "id": 2550541,
        "name:xx": "Norton"
      }
    },
    {
      "geometry": {
        "type": "Point",
        "coordinates": [
          -121.9667,
          38.5833
        ]
      },
      "type": "Feature",
      "properties": {
        "hierarchy": [
          "tgn:2550542",
          "tgn:1000001",
          "tgn:7012149",
          "tgn:7007157",
          "tgn:1003046",
          "tgn:7029392"
        ],
        "placetype": [
          "aat:300008347"
        ],
        "id": 2550542,
        "name:xx": "Norton"
      }
    },
    {
      "geometry": {
        "type": "Point",
        "coordinates": [
          -84.85,
          34.85
        ]
      },
      "type": "Feature",
      "properties": {
        "hierarchy": [
          "tgn:2550543",
          "tgn:1000001",
          "tgn:7012149",
          "tgn:2000446",
          "tgn:7007248",
          "tgn:7029392"
        ],
        "placetype": [
          "aat:300008347"
        ],
        "id": 2550543,
        "name:xx": "Norton"
      }
    },
    {
      "geometry": {
        "type": "Point",
        "coordinates": [
          -93.6833,
          32.3167
        ]
      },
      "type": "Feature",
      "properties": {
        "hierarchy": [
          "tgn:2550544",
          "tgn:1000001",
          "tgn:2000862",
          "tgn:7012149",
          "tgn:7007256",
          "tgn:7029392"
        ],
        "placetype": [
          "aat:300008347"
        ],
        "id": 2550544,
        "name:xx": "Norton"
      }
    },
    {
      "geometry": {
        "type": "Point",
        "coordinates": [
          -83.3,
          42.3667
        ]
      },
      "type": "Feature",
      "properties": {
        "hierarchy": [
          "tgn:2550545",
          "tgn:1000001",
          "tgn:7012149",
          "tgn:1003005",
          "tgn:7007520",
          "tgn:7029392"
        ],
        "placetype": [
          "aat:300008347"
        ],
        "id": 2550545,
        "name:xx": "Norton"
      }
    },
    {
      "geometry": {
        "type": "Point",
        "coordinates": [
          -93.1333,
          39.1833
        ]
      },
      "type": "Feature",
      "properties": {
        "hierarchy": [
          "tgn:2550546",
          "tgn:1000001",
          "tgn:7012149",
          "tgn:2001243",
          "tgn:7007523",
          "tgn:7029392"
        ],
        "placetype": [
          "aat:300008347"
        ],
        "id": 2550546,
        "name:xx": "Norton"
      }
    },
    {
      "geometry": {
        "type": "Point",
        "coordinates": [
          -103.5167,
          34.9833
        ]
      },
      "type": "Feature",
      "properties": {
        "hierarchy": [
          "tgn:2550547",
          "tgn:1000001",
          "tgn:7012149",
          "tgn:2001448",
          "tgn:7007566",
          "tgn:7029392"
        ],
        "placetype": [
          "aat:300008347"
        ],
        "id": 2550547,
        "name:xx": "Norton"
      }
    },
    {
      "geometry": {
        "type": "Point",
        "coordinates": [
          -83.3667,
          35.0167
        ]
      },
      "type": "Feature",
      "properties": {
        "hierarchy": [
          "tgn:2550548",
          "tgn:1000001",
          "tgn:7012149",
          "tgn:2001515",
          "tgn:7007709",
          "tgn:7029392"
        ],
        "placetype": [
          "aat:300008347"
        ],
        "id": 2550548,
        "name:xx": "Norton"
      }
    },
    {
      "geometry": {
        "type": "Point",
        "coordinates": [
          -122.3833,
          45.3167
        ]
      },
      "type": "Feature",
      "properties": {
        "hierarchy": [
          "tgn:2550549",
          "tgn:1000001",
          "tgn:1002270",
          "tgn:7012149",
          "tgn:7007708",
          "tgn:7029392"
        ],
        "placetype": [
          "aat:300008347"
        ],
        "id": 2550549,
        "name:xx": "Norton"
      }
    }
  ]
}
