{
  "geometry": {
    "type": "Point",
    "coordinates": [
      -105.9833,
      44.1667
    ]
  },
  "type": "Feature",
  "properties": {
    "hierarchy": [
      "tgn:2431374",
      "tgn:1000001",
      "tgn:2002367",
      "tgn:7012149",
      "tgn:7007923",
      "tgn:7029392"
    ],
    "placetype": [
      "aat:300008761"
    ],
    "id": 2431374,
    "name:xx": "Karen Draw"
  }
}
