{
  "geometry": {
    "type": "Point",
    "coordinates": [
      -85.7167,
      40.4333
    ]
  },
  "type": "Feature",
  "properties": {
    "hierarchy": [
      "tgn:2711572",
      "tgn:1000001",
      "tgn:7012149",
      "tgn:1002416",
      "tgn:7007252",
      "tgn:7029392"
    ],
    "placetype": [
      "aat:300006075"
    ],
    "id": 2711572,
    "name:xx": "Tappin Ditch"
  }
}
