{
  "geometry": {
    "type": "Point",
    "coordinates": [
      -76.7167,
      38.0833
    ]
  },
  "type": "Feature",
  "properties": {
    "hierarchy": [
      "tgn:2113136",
      "tgn:1000001",
      "tgn:7012149",
      "tgn:1003018",
      "tgn:7007919",
      "tgn:7029392"
    ],
    "placetype": [
      "aat:300008347"
    ],
    "id": 2113136,
    "name:xx": "Mount Holly"
  }
}
