{
  "geometry": {
    "type": "Point",
    "coordinates": [
      -101.2833,
      48.0167
    ]
  },
  "type": "Feature",
  "properties": {
    "hierarchy": [
      "tgn:2178800",
      "tgn:1000001",
      "tgn:7012149",
      "tgn:2001607",
      "tgn:7007705",
      "tgn:7029392"
    ],
    "placetype": [
      "aat:300008761"
    ],
    "id": 2178800,
    "name:xx": "Blackwater Coulee"
  }
}
