{
  "geometry": {
    "type": "Point",
    "coordinates": [
      31.236363,
      29.238072
    ]
  },
  "type": "Feature",
  "properties": {
    "hierarchy": [
      "tgn:7539285",
      "tgn:7001242",
      "tgn:7016833",
      "tgn:1001083",
      "tgn:7029392"
    ],
    "placetype": [
      "aat:300379998"
    ],
    "name:en": "Mat카n al Qibl카, W훮d카",
    "id": 7539285
  }
}
