{
  "geometry": {
    "type": "Point",
    "coordinates": [
      -88.3667,
      32.65
    ]
  },
  "type": "Feature",
  "properties": {
    "hierarchy": [
      "tgn:2715145",
      "tgn:1000001",
      "tgn:7012149",
      "tgn:7029392"
    ],
    "placetype": [
      "aat:300008706"
    ],
    "id": 2715145,
    "name:xx": "Teoc Creek"
  }
}
