{
  "geometry": {
    "type": "Point",
    "coordinates": [
      21.3333,
      12.1667
    ]
  },
  "type": "Feature",
  "properties": {
    "hierarchy": [
      "tgn:1088511",
      "tgn:7001242",
      "tgn:7016848",
      "tgn:1000156",
      "tgn:7029392"
    ],
    "placetype": [
      "aat:300008347"
    ],
    "id": 1088511,
    "name:xx": "Goz-Beïda"
  }
}
