{
  "geometry": {
    "type": "Point",
    "coordinates": [
      -91.8667,
      35.0667
    ]
  },
  "type": "Feature",
  "properties": {
    "hierarchy": [
      "tgn:2007702",
      "tgn:1000001",
      "tgn:7016172",
      "tgn:7012149",
      "tgn:2000177",
      "tgn:7029392"
    ],
    "placetype": [
      "aat:300008347"
    ],
    "id": 2007702,
    "name:xx": "Beebe"
  }
}
