{
  "geometry": {
    "type": "Point",
    "coordinates": [
      -83.3333,
      38.15
    ]
  },
  "type": "Feature",
  "properties": {
    "hierarchy": [
      "tgn:2296809",
      "tgn:1000001",
      "tgn:7012149",
      "tgn:1002837",
      "tgn:7007255",
      "tgn:7029392"
    ],
    "placetype": [
      "aat:300008706"
    ],
    "id": 2296809,
    "name:xx": "Dry Creek"
  }
}
