{
  "geometry": {
    "type": "Point",
    "coordinates": [
      -112.15,
      41.9833
    ]
  },
  "type": "Feature",
  "properties": {
    "hierarchy": [
      "tgn:2656806",
      "tgn:1000001",
      "tgn:7012149",
      "tgn:7029392"
    ],
    "placetype": [
      "aat:300008761"
    ],
    "id": 2656806,
    "name:xx": "Sheep Dip Hollow"
  }
}
