{
  "geometry": {
    "type": "Point",
    "coordinates": [
      76.843154,
      30.64875
    ]
  },
  "type": "Feature",
  "properties": {
    "hierarchy": [
      "tgn:7585496",
      "tgn:1000004",
      "tgn:7000198",
      "tgn:7016883",
      "tgn:7029392"
    ],
    "placetype": [
      "aat:300008347"
    ],
    "name:en": "Ghāzīpur",
    "id": 7585496
  }
}
