{
  "geometry": {
    "type": "Point",
    "coordinates": [
      -71.2667,
      42.1833
    ]
  },
  "type": "Feature",
  "properties": {
    "hierarchy": [
      "tgn:2516085",
      "tgn:1000001",
      "tgn:1002724",
      "tgn:7012149",
      "tgn:7007517",
      "tgn:7029392"
    ],
    "placetype": [
      "aat:300008699"
    ],
    "id": 2516085,
    "name:xx": "Mine Brook"
  }
}
