{
  "geometry": {
    "type": "Point",
    "coordinates": [
      59.5333,
      22.5667
    ]
  },
  "type": "Feature",
  "properties": {
    "hierarchy": [
      "tgn:1083231",
      "tgn:7593217",
      "tgn:1000004",
      "tgn:1000131",
      "tgn:7029392"
    ],
    "placetype": [
      "aat:300008347",
      "aat:300387269"
    ],
    "id": 1083231,
    "name:xx": "Ṣūr"
  }
}
