{
  "geometry": {
    "type": "Point",
    "coordinates": [
      -117.7333,
      46.6667
    ]
  },
  "type": "Feature",
  "properties": {
    "hierarchy": [
      "tgn:2373976",
      "tgn:1000001",
      "tgn:2002245",
      "tgn:7012149",
      "tgn:7007920",
      "tgn:7029392"
    ],
    "placetype": [
      "aat:300008761"
    ],
    "id": 2373976,
    "name:xx": "Hammer Gulch"
  }
}
