{
  "geometry": {
    "type": "Point",
    "coordinates": [
      6.3167,
      45.6333
    ]
  },
  "type": "Feature",
  "properties": {
    "hierarchy": [
      "tgn:1033209",
      "tgn:1000003",
      "tgn:1000070",
      "tgn:7002897",
      "tgn:7029392"
    ],
    "placetype": [
      "aat:300008347"
    ],
    "id": 1033209,
    "name:xx": "Frontenex-Villard-Rosset"
  }
}
