{
  "geometry": {
    "type": "Point",
    "coordinates": [
      -86.6333,
      40.8667
    ]
  },
  "type": "Feature",
  "properties": {
    "hierarchy": [
      "tgn:2125293",
      "tgn:1000001",
      "tgn:7012149",
      "tgn:1003021",
      "tgn:7007252",
      "tgn:7029392"
    ],
    "placetype": [
      "aat:300006075"
    ],
    "id": 2125293,
    "name:xx": "Ackerman Ditch"
  }
}
