{
  "geometry": {
    "type": "Point",
    "coordinates": [
      -98.35,
      31.5833
    ]
  },
  "type": "Feature",
  "properties": {
    "hierarchy": [
      "tgn:7023002",
      "tgn:1000001",
      "tgn:7012149",
      "tgn:7007826",
      "tgn:7029392"
    ],
    "placetype": [
      "aat:300008706"
    ],
    "id": 7023002,
    "name:xx": "Gholson Creek"
  }
}
