{
  "geometry": {
    "type": "Point",
    "coordinates": [
      14.4833,
      35.8333
    ]
  },
  "type": "Feature",
  "properties": {
    "hierarchy": [
      "tgn:7005751",
      "tgn:1000003",
      "tgn:7594248",
      "tgn:7005729",
      "tgn:7029392"
    ],
    "placetype": [
      "aat:300008347"
    ],
    "id": 7005751,
    "name:xx": "Żurrieq"
  }
}
