{
  "geometry": {
    "type": "Point",
    "coordinates": [
      -85.1833,
      31.55
    ]
  },
  "type": "Feature",
  "properties": {
    "hierarchy": [
      "tgn:2721572",
      "tgn:7002659",
      "tgn:1000001",
      "tgn:7012149",
      "tgn:2000033",
      "tgn:7029392"
    ],
    "placetype": [
      "aat:300006191"
    ],
    "id": 2721572,
    "name:xx": "Tillis Pond"
  }
}
