{
  "geometry": {
    "type": "Point",
    "coordinates": [
      5.4167,
      51.3333
    ]
  },
  "type": "Feature",
  "properties": {
    "hierarchy": [
      "tgn:6003428",
      "tgn:1000003",
      "tgn:7029392"
    ],
    "placetype": [
      "aat:300387346"
    ],
    "name:en": "Limburg",
    "name:nl": "Limburg",
    "id": 6003428
  }
}
