{
  "geometry": {
    "type": "Point",
    "coordinates": [
      119.25,
      39.8667
    ]
  },
  "type": "Feature",
  "properties": {
    "hierarchy": [
      "tgn:1138974",
      "tgn:1000004",
      "tgn:7002077",
      "tgn:1000111",
      "tgn:7029392"
    ],
    "placetype": [
      "aat:300008347"
    ],
    "id": 1138974,
    "name:xx": "Funing"
  }
}
