{
  "geometry": {
    "type": "Point",
    "coordinates": [
      -69.3167,
      43.75
    ]
  },
  "type": "Feature",
  "properties": {
    "hierarchy": [
      "tgn:2490135",
      "tgn:1000001",
      "tgn:2000925",
      "tgn:7012149",
      "tgn:7007515",
      "tgn:7029392"
    ],
    "placetype": [
      "aat:300008791"
    ],
    "id": 2490135,
    "name:xx": "Manana Island"
  }
}
