{
  "geometry": {
    "type": "Point",
    "coordinates": [
      18.0833,
      42.6667
    ]
  },
  "type": "Feature",
  "properties": {
    "hierarchy": [
      "tgn:4006130",
      "tgn:7017310",
      "tgn:1000003",
      "tgn:7006663",
      "tgn:7029392"
    ],
    "placetype": [
      "aat:300008347"
    ],
    "id": 4006130,
    "name:xx": "Lapad"
  }
}
