{
  "geometry": {
    "type": "Point",
    "coordinates": [
      -100.5667,
      45.45
    ]
  },
  "type": "Feature",
  "properties": {
    "hierarchy": [
      "tgn:2485793",
      "tgn:1000001",
      "tgn:2001790",
      "tgn:7012149",
      "tgn:7007713",
      "tgn:7029392"
    ],
    "placetype": [
      "aat:300008706"
    ],
    "id": 2485793,
    "name:xx": "Le Beau Creek"
  }
}
