{
  "geometry": {
    "type": "Point",
    "coordinates": [
      110.2333,
      40.8667
    ]
  },
  "type": "Feature",
  "properties": {
    "hierarchy": [
      "tgn:1071662",
      "tgn:1000004",
      "tgn:7001838",
      "tgn:1000111",
      "tgn:7029392"
    ],
    "placetype": [
      "aat:300008347"
    ],
    "id": 1071662,
    "name:xx": "Shiguaigou"
  }
}
