{
  "geometry": {
    "type": "Point",
    "coordinates": [
      -103.0167,
      43.35
    ]
  },
  "type": "Feature",
  "properties": {
    "hierarchy": [
      "tgn:2767033",
      "tgn:1000001",
      "tgn:2001793",
      "tgn:7012149",
      "tgn:7007713",
      "tgn:7029392"
    ],
    "placetype": [
      "aat:300266640"
    ],
    "id": 2767033,
    "name:xx": "White River Divide"
  }
}
