{
  "geometry": {
    "type": "Point",
    "coordinates": [
      -149.55,
      61.3667
    ]
  },
  "type": "Feature",
  "properties": {
    "hierarchy": [
      "tgn:2600104",
      "tgn:2124017",
      "tgn:7006450",
      "tgn:1000001",
      "tgn:7012149",
      "tgn:7029392"
    ],
    "placetype": [
      "aat:300008680"
    ],
    "id": 2600104,
    "name:xx": "Psalm Lake"
  }
}
