{
  "type": "FeatureCollection",
  "features": [
    {
      "geometry": {
        "type": "Point",
        "coordinates": [
          -111.2167,
          45.5833
        ]
      },
      "type": "Feature",
      "properties": {
        "hierarchy": [
          "tgn:2327660",
          "tgn:1000001",
          "tgn:7012149",
          "tgn:2001275",
          "tgn:7007524",
          "tgn:7029392"
        ],
        "placetype": [
          "aat:300008706"
        ],
        "id": 2327660,
        "name:xx": "Fish Creek"
      }
    },
    {
      "geometry": {
        "type": "Point",
        "coordinates": [
          -114.8,
          46.9
        ]
      },
      "type": "Feature",
      "properties": {
        "hierarchy": [
          "tgn:2327661",
          "tgn:1000001",
          "tgn:7012149",
          "tgn:2001290",
          "tgn:7007524",
          "tgn:7029392"
        ],
        "placetype": [
          "aat:300008706"
        ],
        "id": 2327661,
        "name:xx": "Fish Creek"
      }
    },
    {
      "geometry": {
        "type": "Point",
        "coordinates": [
          -107.6333,
          46.9333
        ]
      },
      "type": "Feature",
      "properties": {
        "hierarchy": [
          "tgn:2327662",
          "tgn:1000001",
          "tgn:7012149",
          "tgn:2001276",
          "tgn:7007524",
          "tgn:7029392"
        ],
        "placetype": [
          "aat:300008706"
        ],
        "id": 2327662,
        "name:xx": "Fish Creek"
      }
    },
    {
      "geometry": {
        "type": "Point",
        "coordinates": [
          -113.4,
          47.1333
        ]
      },
      "type": "Feature",
      "properties": {
        "hierarchy": [
          "tgn:2327663",
          "tgn:1000001",
          "tgn:7012149",
          "tgn:2001291",
          "tgn:7007524",
          "tgn:7029392"
        ],
        "placetype": [
          "aat:300008706"
        ],
        "id": 2327663,
        "name:xx": "Fish Creek"
      }
    },
    {
      "geometry": {
        "type": "Point",
        "coordinates": [
          -109.35,
          47.2
        ]
      },
      "type": "Feature",
      "properties": {
        "hierarchy": [
          "tgn:2327664",
          "tgn:1000001",
          "tgn:7012149",
          "tgn:2001273",
          "tgn:7007524",
          "tgn:7029392"
        ],
        "placetype": [
          "aat:300008706"
        ],
        "id": 2327664,
        "name:xx": "Fish Creek"
      }
    },
    {
      "geometry": {
        "type": "Point",
        "coordinates": [
          -98.6167,
          41.5167
        ]
      },
      "type": "Feature",
      "properties": {
        "hierarchy": [
          "tgn:2327665",
          "tgn:1000001",
          "tgn:7012149",
          "tgn:7007525",
          "tgn:7029392"
        ],
        "placetype": [
          "aat:300008706"
        ],
        "id": 2327665,
        "name:xx": "Fish Creek"
      }
    },
    {
      "geometry": {
        "type": "Point",
        "coordinates": [
          -96.1,
          41.5333
        ]
      },
      "type": "Feature",
      "properties": {
        "hierarchy": [
          "tgn:2327666",
          "tgn:1000001",
          "tgn:7012149",
          "tgn:2001404",
          "tgn:7007525",
          "tgn:7029392"
        ],
        "placetype": [
          "aat:300008706"
        ],
        "id": 2327666,
        "name:xx": "Fish Creek"
      }
    },
    {
      "geometry": {
        "type": "Point",
        "coordinates": [
          -116.0333,
          39.2667
        ]
      },
      "type": "Feature",
      "properties": {
        "hierarchy": [
          "tgn:2327667",
          "tgn:1000001",
          "tgn:7012149",
          "tgn:7007526",
          "tgn:7029392"
        ],
        "placetype": [
          "aat:300008706"
        ],
        "id": 2327667,
        "name:xx": "Fish Creek"
      }
    },
    {
      "geometry": {
        "type": "Point",
        "coordinates": [
          -117.4,
          40.1833
        ]
      },
      "type": "Feature",
      "properties": {
        "hierarchy": [
          "tgn:2327668",
          "tgn:1000001",
          "tgn:2001415",
          "tgn:7012149",
          "tgn:7007526",
          "tgn:7029392"
        ],
        "placetype": [
          "aat:300008706"
        ],
        "id": 2327668,
        "name:xx": "Fish Creek"
      }
    },
    {
      "geometry": {
        "type": "Point",
        "coordinates": [
          -119.35,
          41.75
        ]
      },
      "type": "Feature",
      "properties": {
        "hierarchy": [
          "tgn:2327669",
          "tgn:1000001",
          "tgn:7012149",
          "tgn:1002999",
          "tgn:7007526",
          "tgn:7029392"
        ],
        "placetype": [
          "aat:300008706"
        ],
        "id": 2327669,
        "name:xx": "Fish Creek"
      }
    }
  ]
}
