{
  "geometry": {
    "type": "Point",
    "coordinates": [
      -67.5333,
      -16.2333
    ]
  },
  "type": "Feature",
  "properties": {
    "hierarchy": [
      "tgn:1020292",
      "tgn:1000662",
      "tgn:1000046",
      "tgn:1000002",
      "tgn:7029392"
    ],
    "placetype": [
      "aat:300008347"
    ],
    "id": 1020292,
    "name:xx": "Coripata"
  }
}
