{
  "geometry": {
    "type": "Point",
    "coordinates": [
      -123.9167,
      42.35
    ]
  },
  "type": "Feature",
  "properties": {
    "hierarchy": [
      "tgn:2786505",
      "tgn:1000001",
      "tgn:7012149",
      "tgn:2001713",
      "tgn:7007708",
      "tgn:7029392"
    ],
    "placetype": [
      "aat:300008706"
    ],
    "id": 2786505,
    "name:xx": "Yukon Creek"
  }
}
