{
  "geometry": {
    "type": "Point",
    "coordinates": [
      -57.616,
      -23.111
    ]
  },
  "type": "Feature",
  "properties": {
    "hierarchy": [
      "tgn:1121290",
      "tgn:7002637",
      "tgn:1000576",
      "tgn:1000002",
      "tgn:1000055",
      "tgn:7029392"
    ],
    "placetype": [
      "aat:300008707"
    ],
    "id": 1121290,
    "name:xx": "Aquidabán, Río"
  }
}
