{
  "geometry": {
    "type": "Point",
    "coordinates": [
      -80.1167,
      38.9667
    ]
  },
  "type": "Feature",
  "properties": {
    "hierarchy": [
      "tgn:2509119",
      "tgn:1000001",
      "tgn:7012149",
      "tgn:2002298",
      "tgn:7013961",
      "tgn:7029392"
    ],
    "placetype": [
      "aat:300008699"
    ],
    "id": 2509119,
    "name:xx": "Middle Fork Laurel Fork Sand Run"
  }
}
