{
  "geometry": {
    "type": "Point",
    "coordinates": [
      -71.2833,
      43.65
    ]
  },
  "type": "Feature",
  "properties": {
    "hierarchy": [
      "tgn:2646441",
      "tgn:2001423",
      "tgn:1000001",
      "tgn:7012149",
      "tgn:7007564",
      "tgn:7029392"
    ],
    "placetype": [
      "aat:300008850"
    ],
    "id": 2646441,
    "name:xx": "Sawyers Point"
  }
}
