{
  "geometry": {
    "type": "Point",
    "coordinates": [
      -98.4333,
      30.2167
    ]
  },
  "type": "Feature",
  "properties": {
    "hierarchy": [
      "tgn:2521767",
      "tgn:1000001",
      "tgn:2001942",
      "tgn:7012149",
      "tgn:7007826",
      "tgn:7029392"
    ],
    "placetype": [
      "aat:300008798"
    ],
    "id": 2521767,
    "name:xx": "Monument Hill"
  }
}
