{
  "geometry": {
    "type": "Point",
    "coordinates": [
      -92.1333,
      32.2833
    ]
  },
  "type": "Feature",
  "properties": {
    "hierarchy": [
      "tgn:2146090",
      "tgn:1000001",
      "tgn:7012149",
      "tgn:7007256",
      "tgn:7029392"
    ],
    "placetype": [
      "aat:300008699"
    ],
    "id": 2146090,
    "name:xx": "Ballard Bayou"
  }
}
