{
  "geometry": {
    "type": "Point",
    "coordinates": [
      -77.6667,
      24.2667
    ]
  },
  "type": "Feature",
  "properties": {
    "hierarchy": [
      "tgn:1008020",
      "tgn:7005332",
      "tgn:7593499",
      "tgn:1000001",
      "tgn:7029392"
    ],
    "placetype": [
      "aat:300008791"
    ],
    "id": 1008020,
    "name:xx": "Mangrove Cay"
  }
}
