{
  "geometry": {
    "type": "Point",
    "coordinates": [
      -90.9167,
      37.0167
    ]
  },
  "type": "Feature",
  "properties": {
    "hierarchy": [
      "tgn:2618445",
      "tgn:1000001",
      "tgn:2001181",
      "tgn:7012149",
      "tgn:7007523",
      "tgn:7029392"
    ],
    "placetype": [
      "aat:300008706"
    ],
    "id": 2618445,
    "name:xx": "Right Fork Carter Creek"
  }
}
