{
  "geometry": {
    "type": "Point",
    "coordinates": [
      -100.0833,
      29.9333
    ]
  },
  "type": "Feature",
  "properties": {
    "hierarchy": [
      "tgn:2634601",
      "tgn:1000001",
      "tgn:7012149",
      "tgn:2001980",
      "tgn:7007826",
      "tgn:7029392"
    ],
    "placetype": [
      "aat:300008761"
    ],
    "id": 2634601,
    "name:xx": "Ruth Draw"
  }
}
