{
  "geometry": {
    "type": "Point",
    "coordinates": [
      -111.9833,
      45.4667
    ]
  },
  "type": "Feature",
  "properties": {
    "hierarchy": [
      "tgn:2573901",
      "tgn:1000001",
      "tgn:7012149",
      "tgn:2001288",
      "tgn:7007524",
      "tgn:7029392"
    ],
    "placetype": [
      "aat:300008850"
    ],
    "id": 2573901,
    "name:xx": "Pedro Point"
  }
}
