{
  "geometry": {
    "type": "Point",
    "coordinates": [
      -78.0833,
      34.9833
    ]
  },
  "type": "Feature",
  "properties": {
    "hierarchy": [
      "tgn:2077093",
      "tgn:1000001",
      "tgn:7012149",
      "tgn:2001491",
      "tgn:7007709",
      "tgn:7029392"
    ],
    "placetype": [
      "aat:300008347"
    ],
    "id": 2077093,
    "name:xx": "Warsaw"
  }
}
