{
  "geometry": {
    "type": "Point",
    "coordinates": [
      -86.5167,
      30.65
    ]
  },
  "type": "Feature",
  "properties": {
    "hierarchy": [
      "tgn:2663186",
      "tgn:1000001",
      "tgn:7012149",
      "tgn:2000281",
      "tgn:7007240",
      "tgn:7029392"
    ],
    "placetype": [
      "aat:300008706"
    ],
    "id": 2663186,
    "name:xx": "Silver Creek"
  }
}
