{
  "geometry": {
    "type": "Point",
    "coordinates": [
      32.716667,
      25.15
    ]
  },
  "type": "Feature",
  "properties": {
    "hierarchy": [
      "tgn:7521797",
      "tgn:7001242",
      "tgn:7016833",
      "tgn:7000122",
      "tgn:7029392"
    ],
    "placetype": [
      "aat:300008347"
    ],
    "name:en": "Al Başalīyah Baḩrī",
    "id": 7521797
  }
}
