{
  "geometry": {
    "type": "Point",
    "coordinates": [
      -111.5667,
      39.9667
    ]
  },
  "type": "Feature",
  "properties": {
    "hierarchy": [
      "tgn:2264311",
      "tgn:1000001",
      "tgn:7012149",
      "tgn:2002125",
      "tgn:7007827",
      "tgn:7029392"
    ],
    "placetype": [
      "aat:300008706"
    ],
    "id": 2264311,
    "name:xx": "Crab Creek"
  }
}
