{
  "geometry": {
    "type": "Point",
    "coordinates": [
      -113.0833,
      37.1167
    ]
  },
  "type": "Feature",
  "properties": {
    "hierarchy": [
      "tgn:2682314",
      "tgn:1000001",
      "tgn:7012149",
      "tgn:2002127",
      "tgn:7007827",
      "tgn:7029392"
    ],
    "placetype": [
      "aat:300008761"
    ],
    "id": 2682314,
    "name:xx": "South Wash"
  }
}
