{
  "type": "FeatureCollection",
  "features": [
    {
      "geometry": {
        "type": "Point",
        "coordinates": [
          -15.733333,
          27.8
        ]
      },
      "type": "Feature",
      "properties": {
        "hierarchy": [
          "tgn:7297111",
          "tgn:7002825",
          "tgn:7016622",
          "tgn:1000003",
          "tgn:1000095",
          "tgn:7029392"
        ],
        "placetype": [
          "aat:300386846"
        ],
        "id": 7297111,
        "name:xx": "Tauro, Punta del"
      }
    },
    {
      "geometry": {
        "type": "Point",
        "coordinates": [
          -15.683333,
          27.9
        ]
      },
      "type": "Feature",
      "properties": {
        "hierarchy": [
          "tgn:7297112",
          "tgn:7002825",
          "tgn:7016622",
          "tgn:1000003",
          "tgn:1000095",
          "tgn:7029392"
        ],
        "placetype": [
          "aat:300008795"
        ],
        "id": 7297112,
        "name:xx": "Tauro, Montaña de"
      }
    },
    {
      "geometry": {
        "type": "Point",
        "coordinates": [
          -15.716667,
          27.8
        ]
      },
      "type": "Feature",
      "properties": {
        "hierarchy": [
          "tgn:7297113",
          "tgn:7002825",
          "tgn:7016622",
          "tgn:1000003",
          "tgn:1000095",
          "tgn:7029392"
        ],
        "placetype": [
          "aat:300266554",
          "aat:300008699"
        ],
        "id": 7297113,
        "name:xx": "Tauro, Barranco de"
      }
    },
    {
      "geometry": {
        "type": "Point",
        "coordinates": [
          -15.733333,
          27.833333
        ]
      },
      "type": "Feature",
      "properties": {
        "hierarchy": [
          "tgn:7297114",
          "tgn:7002825",
          "tgn:7016622",
          "tgn:1000003",
          "tgn:1000095",
          "tgn:7029392"
        ],
        "placetype": [
          "aat:300266640"
        ],
        "id": 7297114,
        "name:xx": "Taurito, Lomo de"
      }
    },
    {
      "geometry": {
        "type": "Point",
        "coordinates": [
          -16.716667,
          28.15
        ]
      },
      "type": "Feature",
      "properties": {
        "hierarchy": [
          "tgn:7297115",
          "tgn:7002836",
          "tgn:7016622",
          "tgn:1000003",
          "tgn:1000095",
          "tgn:7029392"
        ],
        "placetype": [
          "aat:300008347"
        ],
        "id": 7297115,
        "name:xx": "Taucho"
      }
    },
    {
      "geometry": {
        "type": "Point",
        "coordinates": [
          0.116667,
          40.883333
        ]
      },
      "type": "Feature",
      "properties": {
        "hierarchy": [
          "tgn:7297116",
          "tgn:7002759",
          "tgn:7002843",
          "tgn:1000003",
          "tgn:1000095",
          "tgn:7029392"
        ],
        "placetype": [
          "aat:300008699"
        ],
        "id": 7297116,
        "name:xx": "Tastavins, Río"
      }
    },
    {
      "geometry": {
        "type": "Point",
        "coordinates": [
          -15.8,
          27.933333
        ]
      },
      "type": "Feature",
      "properties": {
        "hierarchy": [
          "tgn:7297117",
          "tgn:7002825",
          "tgn:7016622",
          "tgn:1000003",
          "tgn:1000095",
          "tgn:7029392"
        ],
        "placetype": [
          "aat:300008347"
        ],
        "id": 7297117,
        "name:xx": "Tasartico"
      }
    },
    {
      "geometry": {
        "type": "Point",
        "coordinates": [
          -15.8,
          27.866667
        ]
      },
      "type": "Feature",
      "properties": {
        "hierarchy": [
          "tgn:7297118",
          "tgn:7002825",
          "tgn:7016622",
          "tgn:1000003",
          "tgn:1000095",
          "tgn:7029392"
        ],
        "placetype": [
          "aat:300266554",
          "aat:300008699"
        ],
        "id": 7297118,
        "name:xx": "Tasarte, Barranco de"
      }
    },
    {
      "geometry": {
        "type": "Point",
        "coordinates": [
          -15.75,
          27.916667
        ]
      },
      "type": "Feature",
      "properties": {
        "hierarchy": [
          "tgn:7297119",
          "tgn:7002825",
          "tgn:7016622",
          "tgn:1000003",
          "tgn:1000095",
          "tgn:7029392"
        ],
        "placetype": [
          "aat:300008347"
        ],
        "id": 7297119,
        "name:xx": "Tasarte"
      }
    }
  ]
}
