{
  "type": "FeatureCollection",
  "features": [
    {
      "geometry": {
        "type": "Point",
        "coordinates": [
          -104.6833,
          32.1333
        ]
      },
      "type": "Feature",
      "properties": {
        "hierarchy": [
          "tgn:2713270",
          "tgn:1000001",
          "tgn:2001436",
          "tgn:7012149",
          "tgn:7007566",
          "tgn:7029392"
        ],
        "placetype": [
          "aat:300006191"
        ],
        "id": 2713270,
        "name:xx": "Taylor Tank"
      }
    },
    {
      "geometry": {
        "type": "Point",
        "coordinates": [
          -106.7,
          33.0333
        ]
      },
      "type": "Feature",
      "properties": {
        "hierarchy": [
          "tgn:2713271",
          "tgn:1000001",
          "tgn:7012149",
          "tgn:2001455",
          "tgn:7007566",
          "tgn:7029392"
        ],
        "placetype": [
          "aat:300006191"
        ],
        "id": 2713271,
        "name:xx": "Taylor Tank"
      }
    },
    {
      "geometry": {
        "type": "Point",
        "coordinates": [
          -106.1833,
          33.8
        ]
      },
      "type": "Feature",
      "properties": {
        "hierarchy": [
          "tgn:2713272",
          "tgn:1000001",
          "tgn:7012149",
          "tgn:2001456",
          "tgn:7007566",
          "tgn:7029392"
        ],
        "placetype": [
          "aat:300006191"
        ],
        "id": 2713272,
        "name:xx": "Taylor Tank"
      }
    },
    {
      "geometry": {
        "type": "Point",
        "coordinates": [
          -108.3833,
          32.8667
        ]
      },
      "type": "Feature",
      "properties": {
        "hierarchy": [
          "tgn:2713273",
          "tgn:1000001",
          "tgn:7012149",
          "tgn:2001437",
          "tgn:7007566",
          "tgn:7029392"
        ],
        "placetype": [
          "aat:300006191"
        ],
        "id": 2713273,
        "name:xx": "Taylor Tank"
      }
    },
    {
      "geometry": {
        "type": "Point",
        "coordinates": [
          -108,
          33.4
        ]
      },
      "type": "Feature",
      "properties": {
        "hierarchy": [
          "tgn:2713274",
          "tgn:1000001",
          "tgn:2001429",
          "tgn:7012149",
          "tgn:7007566",
          "tgn:7029392"
        ],
        "placetype": [
          "aat:300006191"
        ],
        "id": 2713274,
        "name:xx": "Taylor Tank"
      }
    },
    {
      "geometry": {
        "type": "Point",
        "coordinates": [
          -106.6667,
          32.5667
        ]
      },
      "type": "Feature",
      "properties": {
        "hierarchy": [
          "tgn:2713275",
          "tgn:1000001",
          "tgn:2001435",
          "tgn:7012149",
          "tgn:7007566",
          "tgn:7029392"
        ],
        "placetype": [
          "aat:300006191"
        ],
        "id": 2713275,
        "name:xx": "Taylor Tank"
      }
    },
    {
      "geometry": {
        "type": "Point",
        "coordinates": [
          -108.8167,
          31.5
        ]
      },
      "type": "Feature",
      "properties": {
        "hierarchy": [
          "tgn:2713276",
          "tgn:1000001",
          "tgn:7012149",
          "tgn:2001440",
          "tgn:7007566",
          "tgn:7029392"
        ],
        "placetype": [
          "aat:300006191"
        ],
        "id": 2713276,
        "name:xx": "Taylor Tank"
      }
    },
    {
      "geometry": {
        "type": "Point",
        "coordinates": [
          -99.1667,
          27.6
        ]
      },
      "type": "Feature",
      "properties": {
        "hierarchy": [
          "tgn:2713277",
          "tgn:1000001",
          "tgn:7012149",
          "tgn:2002090",
          "tgn:7007826",
          "tgn:7029392"
        ],
        "placetype": [
          "aat:300006191"
        ],
        "id": 2713277,
        "name:xx": "Taylor Tank"
      }
    },
    {
      "geometry": {
        "type": "Point",
        "coordinates": [
          -100.6833,
          33.1833
        ]
      },
      "type": "Feature",
      "properties": {
        "hierarchy": [
          "tgn:2713278",
          "tgn:1000001",
          "tgn:7012149",
          "tgn:2002017",
          "tgn:7007826",
          "tgn:7029392"
        ],
        "placetype": [
          "aat:300006191"
        ],
        "id": 2713278,
        "name:xx": "Taylor Tank"
      }
    },
    {
      "geometry": {
        "type": "Point",
        "coordinates": [
          -109.2667,
          33.7
        ]
      },
      "type": "Feature",
      "properties": {
        "hierarchy": [
          "tgn:2713279",
          "tgn:1000001",
          "tgn:7006451",
          "tgn:2000095",
          "tgn:7012149",
          "tgn:7029392"
        ],
        "placetype": [
          "aat:300008697"
        ],
        "id": 2713279,
        "name:xx": "Taylor Tank and Spring"
      }
    }
  ]
}
