{
  "geometry": {
    "type": "Point",
    "coordinates": [
      9.75,
      47.75
    ]
  },
  "type": "Feature",
  "properties": {
    "hierarchy": [
      "tgn:7082035",
      "tgn:7003692",
      "tgn:1000003",
      "tgn:7000084",
      "tgn:7029392"
    ],
    "placetype": [
      "aat:300000206"
    ],
    "id": 7082035,
    "name:xx": "Wieser"
  }
}
