{
  "geometry": {
    "type": "Point",
    "coordinates": [
      -91.0833,
      36.4333
    ]
  },
  "type": "Feature",
  "properties": {
    "hierarchy": [
      "tgn:2741365",
      "tgn:1000001",
      "tgn:7016172",
      "tgn:7012149",
      "tgn:2000165",
      "tgn:7029392"
    ],
    "placetype": [
      "aat:300008706"
    ],
    "id": 2741365,
    "name:xx": "Upshaw Creek"
  }
}
