{
  "type": "FeatureCollection",
  "features": [
    {
      "geometry": {
        "type": "Point",
        "coordinates": [
          1.533333,
          51.2
        ]
      },
      "type": "Feature",
      "properties": {
        "hierarchy": [
          "tgn:7445900",
          "tgn:7002445",
          "tgn:1000003",
          "tgn:7008153",
          "tgn:7008591",
          "tgn:7029392"
        ],
        "placetype": [
          "aat:300386970"
        ],
        "name:en": "South Calliper",
        "id": 7445900
      }
    },
    {
      "geometry": {
        "type": "Point",
        "coordinates": [
          -4.033333,
          55.8
        ]
      },
      "type": "Feature",
      "properties": {
        "hierarchy": [
          "tgn:7445901",
          "tgn:7002444",
          "tgn:1000003",
          "tgn:7019100",
          "tgn:7008591",
          "tgn:7029392"
        ],
        "placetype": [
          "aat:300008699"
        ],
        "name:en": "South Calder Water",
        "id": 7445901
      }
    },
    {
      "geometry": {
        "type": "Point",
        "coordinates": [
          -3.383333,
          58.866667
        ]
      },
      "type": "Feature",
      "properties": {
        "hierarchy": [
          "tgn:7445903",
          "tgn:7002444",
          "tgn:1000003",
          "tgn:7009907",
          "tgn:7008591",
          "tgn:7029392"
        ],
        "placetype": [
          "aat:300008699"
        ],
        "name:en": "South Burn",
        "id": 7445903
      }
    },
    {
      "geometry": {
        "type": "Point",
        "coordinates": [
          -2.401667,
          51.123056
        ]
      },
      "type": "Feature",
      "properties": {
        "hierarchy": [
          "tgn:7445906",
          "tgn:7002445",
          "tgn:1000003",
          "tgn:7012032",
          "tgn:7008591",
          "tgn:7029392"
        ],
        "placetype": [
          "aat:300008347"
        ],
        "name:en": "South Brewham",
        "id": 7445906
      }
    },
    {
      "geometry": {
        "type": "Point",
        "coordinates": [
          -0.916667,
          50.85
        ]
      },
      "type": "Feature",
      "properties": {
        "hierarchy": [
          "tgn:7445908",
          "tgn:7002445",
          "tgn:1000003",
          "tgn:7008134",
          "tgn:7008591",
          "tgn:7029392"
        ],
        "placetype": [
          "aat:300008347"
        ],
        "name:en": "Southbourne",
        "id": 7445908
      }
    },
    {
      "geometry": {
        "type": "Point",
        "coordinates": [
          -1.8,
          50.716667
        ]
      },
      "type": "Feature",
      "properties": {
        "hierarchy": [
          "tgn:7445909",
          "tgn:7002445",
          "tgn:7026500",
          "tgn:1000003",
          "tgn:7008591",
          "tgn:7029392"
        ],
        "placetype": [
          "aat:300008347"
        ],
        "name:en": "Southbourne",
        "id": 7445909
      }
    }
  ]
}
