{
  "geometry": {
    "type": "Point",
    "coordinates": [
      -82.9833,
      42.55
    ]
  },
  "type": "Feature",
  "properties": {
    "hierarchy": [
      "tgn:2501658",
      "tgn:1000001",
      "tgn:7012149",
      "tgn:1002617",
      "tgn:7007520",
      "tgn:7029392"
    ],
    "placetype": [
      "aat:300008699"
    ],
    "id": 2501658,
    "name:xx": "McInerney Drain"
  }
}
