{
  "geometry": {
    "type": "Point",
    "coordinates": [
      3.5833,
      51.55
    ]
  },
  "type": "Feature",
  "properties": {
    "hierarchy": [
      "tgn:1009679",
      "tgn:1000003",
      "tgn:7003635",
      "tgn:7016845",
      "tgn:7029392"
    ],
    "placetype": [
      "aat:300008791"
    ],
    "id": 1009679,
    "name:xx": "Walcheren"
  }
}
