{
  "geometry": {
    "type": "Point",
    "coordinates": [
      -92.4833,
      37.0833
    ]
  },
  "type": "Feature",
  "properties": {
    "hierarchy": [
      "tgn:2059628",
      "tgn:1000001",
      "tgn:7012149",
      "tgn:2001258",
      "tgn:7007523",
      "tgn:7029392"
    ],
    "placetype": [
      "aat:300008347"
    ],
    "id": 2059628,
    "name:xx": "Macomb"
  }
}
