{
  "type": "FeatureCollection",
  "features": [
    {
      "geometry": {
        "type": "Point",
        "coordinates": [
          23.116667,
          38.85
        ]
      },
      "type": "Feature",
      "properties": {
        "hierarchy": [
          "tgn:7227381",
          "tgn:7002751",
          "tgn:7001399",
          "tgn:1000003",
          "tgn:1000074",
          "tgn:7029392"
        ],
        "placetype": [
          "aat:300008347"
        ],
        "id": 7227381,
        "name:xx": "Ília"
      }
    },
    {
      "geometry": {
        "type": "Point",
        "coordinates": [
          21.916667,
          37.3
        ]
      },
      "type": "Feature",
      "properties": {
        "hierarchy": [
          "tgn:7227382",
          "tgn:7011369",
          "tgn:7017076",
          "tgn:1000003",
          "tgn:1000074",
          "tgn:7029392"
        ],
        "placetype": [
          "aat:300008347"
        ],
        "id": 7227382,
        "name:xx": "Iléktra"
      }
    },
    {
      "geometry": {
        "type": "Point",
        "coordinates": [
          24.066667,
          40.966667
        ]
      },
      "type": "Feature",
      "properties": {
        "hierarchy": [
          "tgn:7227383",
          "tgn:7011170",
          "tgn:7002715",
          "tgn:1000003",
          "tgn:1000074",
          "tgn:7029392"
        ],
        "placetype": [
          "aat:300000641"
        ],
        "id": 7227383,
        "name:xx": "Moní Ikosifoiníssis"
      }
    },
    {
      "geometry": {
        "type": "Point",
        "coordinates": [
          26.8,
          37.133333
        ]
      },
      "type": "Feature",
      "properties": {
        "hierarchy": [
          "tgn:7227384",
          "tgn:7011330",
          "tgn:7002674",
          "tgn:1000003",
          "tgn:1000074",
          "tgn:7029392"
        ],
        "placetype": [
          "aat:300386846"
        ],
        "id": 7227384,
        "name:xx": "Ikónisma, Ákra"
      }
    },
    {
      "geometry": {
        "type": "Point",
        "coordinates": [
          21.716667,
          37
        ]
      },
      "type": "Feature",
      "properties": {
        "hierarchy": [
          "tgn:7227385",
          "tgn:7011369",
          "tgn:7017076",
          "tgn:1000003",
          "tgn:1000074",
          "tgn:7029392"
        ],
        "placetype": [
          "aat:300008347"
        ],
        "id": 7227385,
        "name:xx": "Íklaina"
      }
    },
    {
      "geometry": {
        "type": "Point",
        "coordinates": [
          24.366667,
          38.05
        ]
      },
      "type": "Feature",
      "properties": {
        "hierarchy": [
          "tgn:7227387",
          "tgn:7002681",
          "tgn:7001395",
          "tgn:1000003",
          "tgn:1000074",
          "tgn:7029392"
        ],
        "placetype": [
          "aat:300008347"
        ],
        "id": 7227387,
        "name:xx": "Ikaraíoi"
      }
    },
    {
      "geometry": {
        "type": "Point",
        "coordinates": [
          20.25,
          39.5
        ]
      },
      "type": "Feature",
      "properties": {
        "hierarchy": [
          "tgn:7227388",
          "tgn:7002709",
          "tgn:7002705",
          "tgn:1000003",
          "tgn:1000074",
          "tgn:7029392"
        ],
        "placetype": [
          "aat:300132316"
        ],
        "id": 7227388,
        "name:xx": "Igoumenítsis, Órmos"
      }
    }
  ]
}
