{
  "geometry": {
    "type": "Point",
    "coordinates": [
      -75.1333,
      42.8167
    ]
  },
  "type": "Feature",
  "properties": {
    "hierarchy": [
      "tgn:2407442",
      "tgn:1000001",
      "tgn:7012149",
      "tgn:7014318",
      "tgn:7007568",
      "tgn:7029392"
    ],
    "placetype": [
      "aat:300008347"
    ],
    "id": 2407442,
    "name:xx": "Huntly Corners"
  }
}
