{
  "geometry": {
    "type": "Point",
    "coordinates": [
      -108.7167,
      38.8333
    ]
  },
  "type": "Feature",
  "properties": {
    "hierarchy": [
      "tgn:2548439",
      "tgn:1000001",
      "tgn:7012149",
      "tgn:2000230",
      "tgn:7007158",
      "tgn:7029392"
    ],
    "placetype": [
      "aat:300008706"
    ],
    "id": 2548439,
    "name:xx": "North Lobe Creek"
  }
}
