{
  "type": "FeatureCollection",
  "features": [
    {
      "geometry": {
        "type": "Point",
        "coordinates": [
          -71.583333,
          -33.3
        ]
      },
      "type": "Feature",
      "properties": {
        "hierarchy": [
          "tgn:7280700",
          "tgn:1001768",
          "tgn:1000049",
          "tgn:1000002",
          "tgn:7029392"
        ],
        "placetype": [
          "aat:300008347"
        ],
        "id": 7280700,
        "name:xx": "San José"
      }
    },
    {
      "geometry": {
        "type": "Point",
        "coordinates": [
          -71.066667,
          -29.95
        ]
      },
      "type": "Feature",
      "properties": {
        "hierarchy": [
          "tgn:7280701",
          "tgn:1001657",
          "tgn:1000049",
          "tgn:1000002",
          "tgn:7029392"
        ],
        "placetype": [
          "aat:300008347"
        ],
        "id": 7280701,
        "name:xx": "San José"
      }
    },
    {
      "geometry": {
        "type": "Point",
        "coordinates": [
          -70.933333,
          -28.283333
        ]
      },
      "type": "Feature",
      "properties": {
        "hierarchy": [
          "tgn:7280702",
          "tgn:1001630",
          "tgn:1000049",
          "tgn:1000002",
          "tgn:7029392"
        ],
        "placetype": [
          "aat:300008347"
        ],
        "id": 7280702,
        "name:xx": "San José"
      }
    },
    {
      "geometry": {
        "type": "Point",
        "coordinates": [
          -69.183333,
          -23.216667
        ]
      },
      "type": "Feature",
      "properties": {
        "hierarchy": [
          "tgn:7280703",
          "tgn:7016598",
          "tgn:1000049",
          "tgn:1000002",
          "tgn:7029392"
        ],
        "placetype": [
          "aat:300387200"
        ],
        "id": 7280703,
        "name:xx": "San José"
      }
    },
    {
      "geometry": {
        "type": "Point",
        "coordinates": [
          -71.45,
          -35.683333
        ]
      },
      "type": "Feature",
      "properties": {
        "hierarchy": [
          "tgn:7280704",
          "tgn:1001705",
          "tgn:1000049",
          "tgn:1000002",
          "tgn:7029392"
        ],
        "placetype": [
          "aat:300005433"
        ],
        "id": 7280704,
        "name:xx": "San José"
      }
    },
    {
      "geometry": {
        "type": "Point",
        "coordinates": [
          -73.195,
          -41.783889
        ]
      },
      "type": "Feature",
      "properties": {
        "hierarchy": [
          "tgn:7280705",
          "tgn:1001699",
          "tgn:1000049",
          "tgn:1000002",
          "tgn:7029392"
        ],
        "placetype": [
          "aat:300008347"
        ],
        "id": 7280705,
        "name:xx": "San José"
      }
    },
    {
      "geometry": {
        "type": "Point",
        "coordinates": [
          -72.516667,
          -46.766667
        ]
      },
      "type": "Feature",
      "properties": {
        "hierarchy": [
          "tgn:7280706",
          "tgn:1001623",
          "tgn:1000049",
          "tgn:1000002",
          "tgn:7029392"
        ],
        "placetype": [
          "aat:300000206"
        ],
        "id": 7280706,
        "name:xx": "San José"
      }
    },
    {
      "geometry": {
        "type": "Point",
        "coordinates": [
          -72.15,
          -37.383333
        ]
      },
      "type": "Feature",
      "properties": {
        "hierarchy": [
          "tgn:7280707",
          "tgn:1001637",
          "tgn:1000049",
          "tgn:1000002",
          "tgn:7029392"
        ],
        "placetype": [
          "aat:300000206"
        ],
        "id": 7280707,
        "name:xx": "San José"
      }
    },
    {
      "geometry": {
        "type": "Point",
        "coordinates": [
          -72.683333,
          -37.366667
        ]
      },
      "type": "Feature",
      "properties": {
        "hierarchy": [
          "tgn:7280708",
          "tgn:1001637",
          "tgn:1000049",
          "tgn:1000002",
          "tgn:7029392"
        ],
        "placetype": [
          "aat:300000206"
        ],
        "id": 7280708,
        "name:xx": "San José"
      }
    },
    {
      "geometry": {
        "type": "Point",
        "coordinates": [
          -72.183333,
          -35.65
        ]
      },
      "type": "Feature",
      "properties": {
        "hierarchy": [
          "tgn:7280709",
          "tgn:1001705",
          "tgn:1000049",
          "tgn:1000002",
          "tgn:7029392"
        ],
        "placetype": [
          "aat:300000206"
        ],
        "id": 7280709,
        "name:xx": "San José"
      }
    }
  ]
}
