{
  "geometry": {
    "type": "Point",
    "coordinates": [
      -112.8667,
      38.7667
    ]
  },
  "type": "Feature",
  "properties": {
    "hierarchy": [
      "tgn:2264129",
      "tgn:1000001",
      "tgn:7012149",
      "tgn:2002114",
      "tgn:7007827",
      "tgn:7029392"
    ],
    "placetype": [
      "aat:300008697"
    ],
    "id": 2264129,
    "name:xx": "Coyote Spring"
  }
}
