{
  "geometry": {
    "type": "Point",
    "coordinates": [
      -121.9167,
      45.65
    ]
  },
  "type": "Feature",
  "properties": {
    "hierarchy": [
      "tgn:2452106",
      "tgn:1000001",
      "tgn:7012149",
      "tgn:1002897",
      "tgn:7007920",
      "tgn:7029392"
    ],
    "placetype": [
      "aat:300008680"
    ],
    "id": 2452106,
    "name:xx": "Little Black Lake"
  }
}
