{
  "geometry": {
    "type": "Point",
    "coordinates": [
      0.4167,
      51.7833
    ]
  },
  "type": "Feature",
  "properties": {
    "hierarchy": [
      "tgn:1028829",
      "tgn:7002445",
      "tgn:1000003",
      "tgn:7008131",
      "tgn:7008591",
      "tgn:7029392"
    ],
    "placetype": [
      "aat:300008347",
      "aat:300008372"
    ],
    "id": 1028829,
    "name:ang": "Cingehala"
  }
}
