{
  "geometry": {
    "type": "Point",
    "coordinates": [
      76.95019,
      30.192117
    ]
  },
  "type": "Feature",
  "properties": {
    "hierarchy": [
      "tgn:7582724",
      "tgn:1000004",
      "tgn:1001871",
      "tgn:7000198",
      "tgn:7029392"
    ],
    "placetype": [
      "aat:300008347"
    ],
    "name:en": "Dādlu",
    "id": 7582724
  }
}
