{
  "geometry": {
    "type": "Point",
    "coordinates": [
      16.6667,
      45.75
    ]
  },
  "type": "Feature",
  "properties": {
    "hierarchy": [
      "tgn:1064867",
      "tgn:7017298",
      "tgn:1000003",
      "tgn:7006663",
      "tgn:7029392"
    ],
    "placetype": [
      "aat:300008347"
    ],
    "id": 1064867,
    "name:xx": "Čazma"
  }
}
