{
  "type": "FeatureCollection",
  "features": [
    {
      "geometry": {
        "type": "Point",
        "coordinates": [
          -91.4833,
          39.3
        ]
      },
      "type": "Feature",
      "properties": {
        "hierarchy": [
          "tgn:2060781",
          "tgn:1002158",
          "tgn:1000001",
          "tgn:7012149",
          "tgn:7007523",
          "tgn:7029392"
        ],
        "placetype": [
          "aat:300008347"
        ],
        "id": 2060781,
        "name:xx": "Vandalia"
      }
    },
    {
      "geometry": {
        "type": "Point",
        "coordinates": [
          -91.8333,
          39.15
        ]
      },
      "type": "Feature",
      "properties": {
        "hierarchy": [
          "tgn:2060782",
          "tgn:1002158",
          "tgn:1000001",
          "tgn:7012149",
          "tgn:7007523",
          "tgn:7029392"
        ],
        "placetype": [
          "aat:300008347"
        ],
        "id": 2060782,
        "name:xx": "Vandiver"
      }
    },
    {
      "geometry": {
        "type": "Point",
        "coordinates": [
          -89.6833,
          36.9833
        ]
      },
      "type": "Feature",
      "properties": {
        "hierarchy": [
          "tgn:2060783",
          "tgn:1000001",
          "tgn:7012149",
          "tgn:2001246",
          "tgn:7007523",
          "tgn:7029392"
        ],
        "placetype": [
          "aat:300008347"
        ],
        "id": 2060783,
        "name:xx": "Vanduser"
      }
    },
    {
      "geometry": {
        "type": "Point",
        "coordinates": [
          -92.3,
          36.9667
        ]
      },
      "type": "Feature",
      "properties": {
        "hierarchy": [
          "tgn:2060784",
          "tgn:1000001",
          "tgn:7012149",
          "tgn:2001196",
          "tgn:7007523",
          "tgn:7029392"
        ],
        "placetype": [
          "aat:300008347"
        ],
        "id": 2060784,
        "name:xx": "Vanzant"
      }
    },
    {
      "geometry": {
        "type": "Point",
        "coordinates": [
          -90.4,
          36.55
        ]
      },
      "type": "Feature",
      "properties": {
        "hierarchy": [
          "tgn:2060785",
          "tgn:1000001",
          "tgn:2001176",
          "tgn:7012149",
          "tgn:7007523",
          "tgn:7029392"
        ],
        "placetype": [
          "aat:300008347",
          "aat:300387210"
        ],
        "id": 2060785,
        "name:xx": "Vastus"
      }
    },
    {
      "geometry": {
        "type": "Point",
        "coordinates": [
          -90.2833,
          38.6833
        ]
      },
      "type": "Feature",
      "properties": {
        "hierarchy": [
          "tgn:2060787",
          "tgn:1000001",
          "tgn:7012149",
          "tgn:7016167",
          "tgn:7007523",
          "tgn:7029392"
        ],
        "placetype": [
          "aat:300008347"
        ],
        "id": 2060787,
        "name:xx": "Velda Village Hills"
      }
    },
    {
      "geometry": {
        "type": "Point",
        "coordinates": [
          -91.1333,
          39.3667
        ]
      },
      "type": "Feature",
      "properties": {
        "hierarchy": [
          "tgn:2060788",
          "tgn:1000001",
          "tgn:7012149",
          "tgn:1002787",
          "tgn:7007523",
          "tgn:7029392"
        ],
        "placetype": [
          "aat:300008347",
          "aat:300387210"
        ],
        "id": 2060788,
        "name:xx": "Vera"
      }
    },
    {
      "geometry": {
        "type": "Point",
        "coordinates": [
          -94.4333,
          37.6
        ]
      },
      "type": "Feature",
      "properties": {
        "hierarchy": [
          "tgn:2060789",
          "tgn:2001171",
          "tgn:1000001",
          "tgn:7012149",
          "tgn:7007523",
          "tgn:7029392"
        ],
        "placetype": [
          "aat:300008347",
          "aat:300387210"
        ],
        "id": 2060789,
        "name:xx": "Verdella"
      }
    }
  ]
}
