{
  "geometry": {
    "type": "Point",
    "coordinates": [
      -72.3167,
      41.1333
    ]
  },
  "type": "Feature",
  "properties": {
    "hierarchy": [
      "tgn:2560753",
      "tgn:1000001",
      "tgn:7012149",
      "tgn:1002924",
      "tgn:7007568",
      "tgn:7029392"
    ],
    "placetype": [
      "aat:300132348"
    ],
    "id": 2560753,
    "name:xx": "Orient Shoal"
  }
}
