{
  "geometry": {
    "type": "Point",
    "coordinates": [
      -75.8167,
      39.5667
    ]
  },
  "type": "Feature",
  "properties": {
    "hierarchy": [
      "tgn:2555318",
      "tgn:1002247",
      "tgn:1000001",
      "tgn:7012149",
      "tgn:7007516",
      "tgn:7029392"
    ],
    "placetype": [
      "aat:300008347"
    ],
    "id": 2555318,
    "name:xx": "Oddessy"
  }
}
