{
  "geometry": {
    "type": "Point",
    "coordinates": [
      101.7333,
      2.6833
    ]
  },
  "type": "Feature",
  "properties": {
    "hierarchy": [
      "tgn:1082950",
      "tgn:7000317",
      "tgn:1000004",
      "tgn:7016804",
      "tgn:1000128",
      "tgn:7029392"
    ],
    "placetype": [
      "aat:300008347"
    ],
    "id": 1082950,
    "name:xx": "Sepang"
  }
}
