{
  "geometry": {
    "type": "Point",
    "coordinates": [
      -87.8833,
      34.1667
    ]
  },
  "type": "Feature",
  "properties": {
    "hierarchy": [
      "tgn:2724960",
      "tgn:7002659",
      "tgn:1000001",
      "tgn:7012149",
      "tgn:2000046",
      "tgn:7029392"
    ],
    "placetype": [
      "aat:300008699"
    ],
    "id": 2724960,
    "name:xx": "Toms Den Branch"
  }
}
