{
  "type": "FeatureCollection",
  "features": [
    {
      "geometry": {
        "type": "Point",
        "coordinates": [
          134.5,
          7.5
        ]
      },
      "type": "Feature",
      "properties": {
        "hierarchy": [
          "tgn:1010206",
          "tgn:7005668",
          "tgn:1000006",
          "tgn:7029392"
        ],
        "placetype": [
          "aat:300386853"
        ],
        "id": 1010206,
        "name:xx": "Palau Islands"
      }
    },
    {
      "geometry": {
        "type": "Point",
        "coordinates": [
          120.5,
          6.25
        ]
      },
      "type": "Feature",
      "properties": {
        "hierarchy": [
          "tgn:1010207",
          "tgn:1000004",
          "tgn:1001552",
          "tgn:1000135",
          "tgn:7029392"
        ],
        "placetype": [
          "aat:300386853"
        ],
        "id": 1010207,
        "name:xx": "Pangutaran Group"
      }
    },
    {
      "geometry": {
        "type": "Point",
        "coordinates": [
          -77.833,
          17
        ]
      },
      "type": "Feature",
      "properties": {
        "hierarchy": [
          "tgn:1010208",
          "tgn:1000001",
          "tgn:7005556",
          "tgn:7029392"
        ],
        "placetype": [
          "aat:300008791",
          "aat:300386853"
        ],
        "id": 1010208,
        "name:xx": "Pedro Cays"
      }
    },
    {
      "geometry": {
        "type": "Point",
        "coordinates": [
          12.666667,
          35.666667
        ]
      },
      "type": "Feature",
      "properties": {
        "hierarchy": [
          "tgn:1010209",
          "tgn:1001622",
          "tgn:1000003",
          "tgn:7003122",
          "tgn:1000080",
          "tgn:7029392"
        ],
        "placetype": [
          "aat:300386854",
          "aat:300008791"
        ],
        "id": 1010209,
        "name:xx": "Pelagie, Isole"
      }
    }
  ]
}
