{
  "geometry": {
    "type": "Point",
    "coordinates": [
      -110.6667,
      47.1833
    ]
  },
  "type": "Feature",
  "properties": {
    "hierarchy": [
      "tgn:2618102",
      "tgn:1000001",
      "tgn:7012149",
      "tgn:2001282",
      "tgn:7007524",
      "tgn:7029392"
    ],
    "placetype": [
      "aat:300008761"
    ],
    "id": 2618102,
    "name:xx": "Ridley Coulee"
  }
}
