{
  "geometry": {
    "type": "Point",
    "coordinates": [
      -118.2667,
      49.1167
    ]
  },
  "type": "Feature",
  "properties": {
    "hierarchy": [
      "tgn:1115915",
      "tgn:7005735",
      "tgn:7005685",
      "tgn:1000001",
      "tgn:7029392"
    ],
    "placetype": [
      "aat:300008680"
    ],
    "id": 1115915,
    "name:xx": "Christina Lake"
  }
}
