{
  "geometry": {
    "type": "Point",
    "coordinates": [
      76.12231,
      30.588279
    ]
  },
  "type": "Feature",
  "properties": {
    "hierarchy": [
      "tgn:7583519",
      "tgn:1000004",
      "tgn:7000198",
      "tgn:7016883",
      "tgn:7029392"
    ],
    "placetype": [
      "aat:300008347"
    ],
    "name:en": "Dīwa Gandhwān",
    "id": 7583519
  }
}
