{
  "geometry": {
    "type": "Point",
    "coordinates": [
      -100.0167,
      37.75
    ]
  },
  "type": "Feature",
  "properties": {
    "hierarchy": [
      "tgn:7013573",
      "tgn:1000001",
      "tgn:2000688",
      "tgn:7012149",
      "tgn:7007254",
      "tgn:7029392"
    ],
    "placetype": [
      "aat:300008347",
      "aat:300387233",
      "aat:300008375"
    ],
    "id": 7013573,
    "name:xx": "Dodge City"
  }
}
