{
  "geometry": {
    "type": "Point",
    "coordinates": [
      -88.4833,
      35.4333
    ]
  },
  "type": "Feature",
  "properties": {
    "hierarchy": [
      "tgn:2686809",
      "tgn:1000001",
      "tgn:7012149",
      "tgn:2001848",
      "tgn:7007825",
      "tgn:7029392"
    ],
    "placetype": [
      "aat:300006191"
    ],
    "id": 2686809,
    "name:xx": "Spring Creek Lake"
  }
}
