{
  "geometry": {
    "type": "Point",
    "coordinates": [
      -80.9333,
      32.0167
    ]
  },
  "type": "Feature",
  "properties": {
    "hierarchy": [
      "tgn:1102093",
      "tgn:1000001",
      "tgn:2000316",
      "tgn:7012149",
      "tgn:7007248",
      "tgn:7029392"
    ],
    "placetype": [
      "aat:300008187"
    ],
    "id": 1102093,
    "name:xx": "Fort Pulaski National Monument"
  }
}
