{
  "geometry": {
    "type": "Point",
    "coordinates": [
      -89.35,
      37.6833
    ]
  },
  "type": "Feature",
  "properties": {
    "hierarchy": [
      "tgn:2154104",
      "tgn:1000001",
      "tgn:7012149",
      "tgn:2000512",
      "tgn:7007251",
      "tgn:7029392"
    ],
    "placetype": [
      "aat:300008706"
    ],
    "id": 2154104,
    "name:xx": "Bear Creek"
  }
}
