{
  "type": "FeatureCollection",
  "features": [
    {
      "geometry": {
        "type": "Point",
        "coordinates": [
          13.966667,
          53.566667
        ]
      },
      "type": "Feature",
      "properties": {
        "hierarchy": [
          "tgn:7083580",
          "tgn:1000003",
          "tgn:7000094",
          "tgn:7000084",
          "tgn:7029392"
        ],
        "placetype": [
          "aat:300008347"
        ],
        "id": 7083580,
        "name:xx": "Wilhelmsthal"
      }
    },
    {
      "geometry": {
        "type": "Point",
        "coordinates": [
          13.233333,
          52.716667
        ]
      },
      "type": "Feature",
      "properties": {
        "hierarchy": [
          "tgn:7083581",
          "tgn:7000096",
          "tgn:1000003",
          "tgn:7000084",
          "tgn:7029392"
        ],
        "placetype": [
          "aat:300008347"
        ],
        "id": 7083581,
        "name:xx": "Wilhelmsthal"
      }
    },
    {
      "geometry": {
        "type": "Point",
        "coordinates": [
          12.25,
          52.5
        ]
      },
      "type": "Feature",
      "properties": {
        "hierarchy": [
          "tgn:7083582",
          "tgn:1000003",
          "tgn:7003687",
          "tgn:7000084",
          "tgn:7029392"
        ],
        "placetype": [
          "aat:300008347"
        ],
        "id": 7083582,
        "name:xx": "Wilhelmsthal"
      }
    },
    {
      "geometry": {
        "type": "Point",
        "coordinates": [
          14.383333,
          51.583333
        ]
      },
      "type": "Feature",
      "properties": {
        "hierarchy": [
          "tgn:7083583",
          "tgn:7000096",
          "tgn:1000003",
          "tgn:7000084",
          "tgn:7029392"
        ],
        "placetype": [
          "aat:300008347"
        ],
        "id": 7083583,
        "name:xx": "Wilhelmsthal"
      }
    },
    {
      "geometry": {
        "type": "Point",
        "coordinates": [
          7.3,
          51.2
        ]
      },
      "type": "Feature",
      "properties": {
        "hierarchy": [
          "tgn:7083584",
          "tgn:1000003",
          "tgn:7003677",
          "tgn:7000084",
          "tgn:7029392"
        ],
        "placetype": [
          "aat:300008347"
        ],
        "id": 7083584,
        "name:xx": "Wilhelmsthal"
      }
    },
    {
      "geometry": {
        "type": "Point",
        "coordinates": [
          10.3,
          50.916667
        ]
      },
      "type": "Feature",
      "properties": {
        "hierarchy": [
          "tgn:7083585",
          "tgn:1000003",
          "tgn:7003689",
          "tgn:7000084",
          "tgn:7029392"
        ],
        "placetype": [
          "aat:300008347"
        ],
        "id": 7083585,
        "name:xx": "Wilhelmsthal"
      }
    },
    {
      "geometry": {
        "type": "Point",
        "coordinates": [
          11.366667,
          50.3
        ]
      },
      "type": "Feature",
      "properties": {
        "hierarchy": [
          "tgn:7083586",
          "tgn:7003669",
          "tgn:1000003",
          "tgn:7000084",
          "tgn:7029392"
        ],
        "placetype": [
          "aat:300008347"
        ],
        "id": 7083586,
        "name:xx": "Wilhelmsthal"
      }
    },
    {
      "geometry": {
        "type": "Point",
        "coordinates": [
          9.85,
          54.45
        ]
      },
      "type": "Feature",
      "properties": {
        "hierarchy": [
          "tgn:7083587",
          "tgn:1000003",
          "tgn:7003688",
          "tgn:7000084",
          "tgn:7029392"
        ],
        "placetype": [
          "aat:300000206"
        ],
        "id": 7083587,
        "name:xx": "Wilhelmsthal"
      }
    },
    {
      "geometry": {
        "type": "Point",
        "coordinates": [
          9.416667,
          51.4
        ]
      },
      "type": "Feature",
      "properties": {
        "hierarchy": [
          "tgn:7083588",
          "tgn:1000003",
          "tgn:7003678",
          "tgn:7000084",
          "tgn:7029392"
        ],
        "placetype": [
          "aat:300000206"
        ],
        "id": 7083588,
        "name:xx": "Wilhelmsthal"
      }
    },
    {
      "geometry": {
        "type": "Point",
        "coordinates": [
          7.85,
          50.933333
        ]
      },
      "type": "Feature",
      "properties": {
        "hierarchy": [
          "tgn:7083589",
          "tgn:1000003",
          "tgn:7003677",
          "tgn:7000084",
          "tgn:7029392"
        ],
        "placetype": [
          "aat:300000206"
        ],
        "id": 7083589,
        "name:xx": "Wilhelmstal"
      }
    }
  ]
}
