{
  "geometry": {
    "type": "Point",
    "coordinates": [
      -109.7333,
      36.4333
    ]
  },
  "type": "Feature",
  "properties": {
    "hierarchy": [
      "tgn:2765963",
      "tgn:2000090",
      "tgn:1000001",
      "tgn:7006451",
      "tgn:7012149",
      "tgn:7029392"
    ],
    "placetype": [
      "aat:300008798"
    ],
    "id": 2765963,
    "name:xx": "White Hills"
  }
}
