{
  "geometry": {
    "type": "Point",
    "coordinates": [
      34.12869,
      28.281845
    ]
  },
  "type": "Feature",
  "properties": {
    "hierarchy": [
      "tgn:7541192",
      "tgn:7001242",
      "tgn:7016833",
      "tgn:7001336",
      "tgn:7029392"
    ],
    "placetype": [
      "aat:300379998"
    ],
    "name:en": "Retemat, Wâdi",
    "id": 7541192
  }
}
