{
  "geometry": {
    "type": "Point",
    "coordinates": [
      -95.6667,
      40.9167
    ]
  },
  "type": "Feature",
  "properties": {
    "hierarchy": [
      "tgn:2503214",
      "tgn:1000001",
      "tgn:7012149",
      "tgn:7007253",
      "tgn:7029392"
    ],
    "placetype": [
      "aat:300008706"
    ],
    "id": 2503214,
    "name:xx": "McPherron Creek"
  }
}
