{
  "geometry": {
    "type": "Point",
    "coordinates": [
      -104.3667,
      44.6833
    ]
  },
  "type": "Feature",
  "properties": {
    "hierarchy": [
      "tgn:2158527",
      "tgn:1000001",
      "tgn:2002370",
      "tgn:7012149",
      "tgn:7007923",
      "tgn:7029392"
    ],
    "placetype": [
      "aat:300008706"
    ],
    "id": 2158527,
    "name:xx": "Beaverdam Creek"
  }
}
