{
  "geometry": {
    "type": "Point",
    "coordinates": [
      -87.6833,
      36.0167
    ]
  },
  "type": "Feature",
  "properties": {
    "hierarchy": [
      "tgn:2193049",
      "tgn:1000001",
      "tgn:7012149",
      "tgn:2001879",
      "tgn:7007825",
      "tgn:7029392"
    ],
    "placetype": [
      "aat:300008697"
    ],
    "id": 2193049,
    "name:xx": "Breadens Spring"
  }
}
