{
  "geometry": {
    "type": "Point",
    "coordinates": [
      79.38105,
      26.45931
    ]
  },
  "type": "Feature",
  "properties": {
    "hierarchy": [
      "tgn:7560805",
      "tgn:1000004",
      "tgn:7000198",
      "tgn:7016722",
      "tgn:7029392"
    ],
    "placetype": [
      "aat:300008347"
    ],
    "name:en": "Bhāsaun",
    "id": 7560805
  }
}
