{
  "type": "FeatureCollection",
  "features": [
    {
      "geometry": {
        "type": "Point",
        "coordinates": [
          -105.25,
          35.0333
        ]
      },
      "type": "Feature",
      "properties": {
        "hierarchy": [
          "tgn:2309360",
          "tgn:1000001",
          "tgn:7012149",
          "tgn:2001438",
          "tgn:7007566",
          "tgn:7029392"
        ],
        "placetype": [
          "aat:300006191"
        ],
        "id": 2309360,
        "name:xx": "East Tank"
      }
    },
    {
      "geometry": {
        "type": "Point",
        "coordinates": [
          -105.1833,
          35.2667
        ]
      },
      "type": "Feature",
      "properties": {
        "hierarchy": [
          "tgn:2309361",
          "tgn:1000001",
          "tgn:7012149",
          "tgn:2001453",
          "tgn:7007566",
          "tgn:7029392"
        ],
        "placetype": [
          "aat:300006191"
        ],
        "id": 2309361,
        "name:xx": "East Tank"
      }
    },
    {
      "geometry": {
        "type": "Point",
        "coordinates": [
          -106.2667,
          36.8667
        ]
      },
      "type": "Feature",
      "properties": {
        "hierarchy": [
          "tgn:2309362",
          "tgn:1000001",
          "tgn:7012149",
          "tgn:2001449",
          "tgn:7007566",
          "tgn:7029392"
        ],
        "placetype": [
          "aat:300006191"
        ],
        "id": 2309362,
        "name:xx": "East Tank"
      }
    },
    {
      "geometry": {
        "type": "Point",
        "coordinates": [
          -105.4167,
          33.45
        ]
      },
      "type": "Feature",
      "properties": {
        "hierarchy": [
          "tgn:2309363",
          "tgn:1000001",
          "tgn:7012149",
          "tgn:2001442",
          "tgn:7007566",
          "tgn:7029392"
        ],
        "placetype": [
          "aat:300006191"
        ],
        "id": 2309363,
        "name:xx": "East Tank"
      }
    },
    {
      "geometry": {
        "type": "Point",
        "coordinates": [
          -101.1833,
          32.1833
        ]
      },
      "type": "Feature",
      "properties": {
        "hierarchy": [
          "tgn:2309364",
          "tgn:1000001",
          "tgn:7012149",
          "tgn:2002004",
          "tgn:7007826",
          "tgn:7029392"
        ],
        "placetype": [
          "aat:300006191"
        ],
        "id": 2309364,
        "name:xx": "East Tank"
      }
    },
    {
      "geometry": {
        "type": "Point",
        "coordinates": [
          -101.5167,
          32.6833
        ]
      },
      "type": "Feature",
      "properties": {
        "hierarchy": [
          "tgn:2309365",
          "tgn:1000001",
          "tgn:2001943",
          "tgn:7012149",
          "tgn:7007826",
          "tgn:7029392"
        ],
        "placetype": [
          "aat:300006191"
        ],
        "id": 2309365,
        "name:xx": "East Tank"
      }
    },
    {
      "geometry": {
        "type": "Point",
        "coordinates": [
          -100.3167,
          29.0167
        ]
      },
      "type": "Feature",
      "properties": {
        "hierarchy": [
          "tgn:2309366",
          "tgn:1000001",
          "tgn:7012149",
          "tgn:2002038",
          "tgn:7007826",
          "tgn:7029392"
        ],
        "placetype": [
          "aat:300006191"
        ],
        "id": 2309366,
        "name:xx": "East Tank"
      }
    },
    {
      "geometry": {
        "type": "Point",
        "coordinates": [
          -103.9833,
          31.0167
        ]
      },
      "type": "Feature",
      "properties": {
        "hierarchy": [
          "tgn:2309367",
          "tgn:1000001",
          "tgn:7012149",
          "tgn:2002010",
          "tgn:7007826",
          "tgn:7029392"
        ],
        "placetype": [
          "aat:300006191"
        ],
        "id": 2309367,
        "name:xx": "East Tank"
      }
    },
    {
      "geometry": {
        "type": "Point",
        "coordinates": [
          -104.5167,
          31.1167
        ]
      },
      "type": "Feature",
      "properties": {
        "hierarchy": [
          "tgn:2309368",
          "tgn:1000001",
          "tgn:7012149",
          "tgn:2001969",
          "tgn:7007826",
          "tgn:7029392"
        ],
        "placetype": [
          "aat:300006191"
        ],
        "id": 2309368,
        "name:xx": "East Tank"
      }
    },
    {
      "geometry": {
        "type": "Point",
        "coordinates": [
          -106.1333,
          31.8833
        ]
      },
      "type": "Feature",
      "properties": {
        "hierarchy": [
          "tgn:2309369",
          "tgn:1000001",
          "tgn:7012149",
          "tgn:2001981",
          "tgn:7007826",
          "tgn:7029392"
        ],
        "placetype": [
          "aat:300006191"
        ],
        "id": 2309369,
        "name:xx": "East Tank"
      }
    }
  ]
}
