{
  "geometry": {
    "type": "Point",
    "coordinates": [
      -107.3167,
      35.1667
    ]
  },
  "type": "Feature",
  "properties": {
    "hierarchy": [
      "tgn:2443280",
      "tgn:1000001",
      "tgn:2001431",
      "tgn:7012149",
      "tgn:7007566",
      "tgn:7029392"
    ],
    "placetype": [
      "aat:300000390"
    ],
    "id": 2443280,
    "name:xx": "L Bar Mine"
  }
}
