{
  "geometry": {
    "type": "Point",
    "coordinates": [
      -43.1667,
      -22.8333
    ]
  },
  "type": "Feature",
  "properties": {
    "hierarchy": [
      "tgn:1113079",
      "tgn:1001942",
      "tgn:1000047",
      "tgn:7002457",
      "tgn:1000002",
      "tgn:7029392"
    ],
    "placetype": [
      "aat:300132316"
    ],
    "id": 1113079,
    "name:xx": "Guanabara, Baía de"
  }
}
