{
  "geometry": {
    "type": "Point",
    "coordinates": [
      -75.4333,
      42.8333
    ]
  },
  "type": "Feature",
  "properties": {
    "hierarchy": [
      "tgn:2249169",
      "tgn:1000001",
      "tgn:7012149",
      "tgn:1002624",
      "tgn:7007568",
      "tgn:7029392"
    ],
    "placetype": [
      "aat:300008798"
    ],
    "id": 2249169,
    "name:xx": "Cole Hill"
  }
}
