{
  "geometry": {
    "type": "Point",
    "coordinates": [
      -105.9667,
      31.8667
    ]
  },
  "type": "Feature",
  "properties": {
    "hierarchy": [
      "tgn:2127602",
      "tgn:1000001",
      "tgn:7012149",
      "tgn:2002005",
      "tgn:7007826",
      "tgn:7029392"
    ],
    "placetype": [
      "aat:300008798"
    ],
    "id": 2127602,
    "name:xx": "Alacran Mountain"
  }
}
