{
  "type": "FeatureCollection",
  "features": [
    {
      "geometry": {
        "type": "Point",
        "coordinates": [
          8.4,
          39.2
        ]
      },
      "type": "Feature",
      "properties": {
        "hierarchy": [
          "tgn:7033890",
          "tgn:1001641",
          "tgn:1000003",
          "tgn:7003121",
          "tgn:1000080",
          "tgn:7029392"
        ],
        "placetype": [
          "aat:300120782"
        ],
        "id": 7033890,
        "name:xx": "Banchina Euroallumina"
      }
    },
    {
      "geometry": {
        "type": "Point",
        "coordinates": [
          8.383333,
          39.2
        ]
      },
      "type": "Feature",
      "properties": {
        "hierarchy": [
          "tgn:7033891",
          "tgn:1001641",
          "tgn:1000003",
          "tgn:7003121",
          "tgn:1000080",
          "tgn:7029392"
        ],
        "placetype": [
          "aat:300120786"
        ],
        "id": 7033891,
        "name:xx": "Pontile Alsar"
      }
    },
    {
      "geometry": {
        "type": "Point",
        "coordinates": [
          8.383333,
          39.2
        ]
      },
      "type": "Feature",
      "properties": {
        "hierarchy": [
          "tgn:7033892",
          "tgn:1001641",
          "tgn:1000003",
          "tgn:7003121",
          "tgn:1000080",
          "tgn:7029392"
        ],
        "placetype": [
          "aat:300011692"
        ],
        "id": 7033892,
        "name:xx": "Is Canneddas, Scoglio"
      }
    },
    {
      "geometry": {
        "type": "Point",
        "coordinates": [
          8.383333,
          39.2
        ]
      },
      "type": "Feature",
      "properties": {
        "hierarchy": [
          "tgn:7033893",
          "tgn:1001641",
          "tgn:1000003",
          "tgn:7003121",
          "tgn:1000080",
          "tgn:7029392"
        ],
        "placetype": [
          "aat:300386846"
        ],
        "id": 7033893,
        "name:xx": "Sa Furungonara, Punta de"
      }
    },
    {
      "geometry": {
        "type": "Point",
        "coordinates": [
          8.366667,
          39.2
        ]
      },
      "type": "Feature",
      "properties": {
        "hierarchy": [
          "tgn:7033894",
          "tgn:1001641",
          "tgn:1000003",
          "tgn:7003121",
          "tgn:1000080",
          "tgn:7029392"
        ],
        "placetype": [
          "aat:300387036"
        ],
        "id": 7033894,
        "name:xx": "Ghinghetta, Secche della"
      }
    },
    {
      "geometry": {
        "type": "Point",
        "coordinates": [
          8.366667,
          39.2
        ]
      },
      "type": "Feature",
      "properties": {
        "hierarchy": [
          "tgn:7033895",
          "tgn:1001641",
          "tgn:1000003",
          "tgn:7003121",
          "tgn:1000080",
          "tgn:7029392"
        ],
        "placetype": [
          "aat:300011692"
        ],
        "id": 7033895,
        "name:xx": "Su Scoglitteddu"
      }
    },
    {
      "geometry": {
        "type": "Point",
        "coordinates": [
          12.85,
          40.95
        ]
      },
      "type": "Feature",
      "properties": {
        "hierarchy": [
          "tgn:7033896",
          "tgn:7003136",
          "tgn:1000003",
          "tgn:7003080",
          "tgn:1000080",
          "tgn:7029392"
        ],
        "placetype": [
          "aat:300386846"
        ],
        "id": 7033896,
        "name:xx": "Tramontana, Punta di"
      }
    },
    {
      "geometry": {
        "type": "Point",
        "coordinates": [
          12.85,
          40.916667
        ]
      },
      "type": "Feature",
      "properties": {
        "hierarchy": [
          "tgn:7033898",
          "tgn:7003136",
          "tgn:1000003",
          "tgn:7003080",
          "tgn:1000080",
          "tgn:7029392"
        ],
        "placetype": [
          "aat:300386846"
        ],
        "id": 7033898,
        "name:xx": "Mezzogiorno, Punta di"
      }
    },
    {
      "geometry": {
        "type": "Point",
        "coordinates": [
          13,
          40.933333
        ]
      },
      "type": "Feature",
      "properties": {
        "hierarchy": [
          "tgn:7033899",
          "tgn:7003136",
          "tgn:1000003",
          "tgn:7003080",
          "tgn:1000080",
          "tgn:7029392"
        ],
        "placetype": [
          "aat:300386846"
        ],
        "id": 7033899,
        "name:xx": "Incenso, Punta dell'"
      }
    }
  ]
}
