{
  "geometry": {
    "type": "Point",
    "coordinates": [
      -98.0667,
      48.9167
    ]
  },
  "type": "Feature",
  "properties": {
    "hierarchy": [
      "tgn:2543359",
      "tgn:2001566",
      "tgn:1000001",
      "tgn:7012149",
      "tgn:7007705",
      "tgn:7029392"
    ],
    "placetype": [
      "aat:300008798"
    ],
    "id": 2543359,
    "name:xx": "Norman Otto Hill"
  }
}
