{
  "geometry": {
    "type": "Point",
    "coordinates": [
      -100.2167,
      33.55
    ]
  },
  "type": "Feature",
  "properties": {
    "hierarchy": [
      "tgn:2138601",
      "tgn:1000001",
      "tgn:7012149",
      "tgn:2002020",
      "tgn:7007826",
      "tgn:7029392"
    ],
    "placetype": [
      "aat:300008706"
    ],
    "id": 2138601,
    "name:xx": "Ash Creek"
  }
}
