{
  "type": "FeatureCollection",
  "features": [
    {
      "geometry": {
        "type": "Point",
        "coordinates": [
          -81.95,
          27.6833
        ]
      },
      "type": "Feature",
      "properties": {
        "hierarchy": [
          "tgn:2143670",
          "tgn:1000001",
          "tgn:7012149",
          "tgn:1002793",
          "tgn:7007240",
          "tgn:7029392"
        ],
        "placetype": [
          "aat:300008347"
        ],
        "id": 2143670,
        "name:xx": "Baird"
      }
    },
    {
      "geometry": {
        "type": "Point",
        "coordinates": [
          -95.65,
          41.7833
        ]
      },
      "type": "Feature",
      "properties": {
        "hierarchy": [
          "tgn:2143671",
          "tgn:1000001",
          "tgn:2000603",
          "tgn:7012149",
          "tgn:7007253",
          "tgn:7029392"
        ],
        "placetype": [
          "aat:300008347"
        ],
        "id": 2143671,
        "name:xx": "Baird"
      }
    },
    {
      "geometry": {
        "type": "Point",
        "coordinates": [
          -90.5833,
          33.4167
        ]
      },
      "type": "Feature",
      "properties": {
        "hierarchy": [
          "tgn:2143672",
          "tgn:1000001",
          "tgn:7012149",
          "tgn:2001152",
          "tgn:7007522",
          "tgn:7029392"
        ],
        "placetype": [
          "aat:300008347"
        ],
        "id": 2143672,
        "name:xx": "Baird"
      }
    },
    {
      "geometry": {
        "type": "Point",
        "coordinates": [
          -90,
          36.4333
        ]
      },
      "type": "Feature",
      "properties": {
        "hierarchy": [
          "tgn:2143673",
          "tgn:1000001",
          "tgn:7012149",
          "tgn:2001197",
          "tgn:7007523",
          "tgn:7029392"
        ],
        "placetype": [
          "aat:300008347"
        ],
        "id": 2143673,
        "name:xx": "Baird"
      }
    },
    {
      "geometry": {
        "type": "Point",
        "coordinates": [
          -81.4,
          35.7833
        ]
      },
      "type": "Feature",
      "properties": {
        "hierarchy": [
          "tgn:2143674",
          "tgn:1000001",
          "tgn:2001476",
          "tgn:7012149",
          "tgn:7007709",
          "tgn:7029392"
        ],
        "placetype": [
          "aat:300008347"
        ],
        "id": 2143674,
        "name:xx": "Baird"
      }
    },
    {
      "geometry": {
        "type": "Point",
        "coordinates": [
          -120.15,
          45.6167
        ]
      },
      "type": "Feature",
      "properties": {
        "hierarchy": [
          "tgn:2143675",
          "tgn:1000001",
          "tgn:7012149",
          "tgn:2001707",
          "tgn:7007708",
          "tgn:7029392"
        ],
        "placetype": [
          "aat:300008347"
        ],
        "id": 2143675,
        "name:xx": "Baird"
      }
    },
    {
      "geometry": {
        "type": "Point",
        "coordinates": [
          -95.1,
          30.8667
        ]
      },
      "type": "Feature",
      "properties": {
        "hierarchy": [
          "tgn:2143676",
          "tgn:1000001",
          "tgn:7012149",
          "tgn:1002795",
          "tgn:7007826",
          "tgn:7029392"
        ],
        "placetype": [
          "aat:300008699"
        ],
        "id": 2143676,
        "name:xx": "Baird Branch"
      }
    },
    {
      "geometry": {
        "type": "Point",
        "coordinates": [
          -104.1833,
          46.8833
        ]
      },
      "type": "Feature",
      "properties": {
        "hierarchy": [
          "tgn:2143677",
          "tgn:1000001",
          "tgn:7012149",
          "tgn:2001314",
          "tgn:7007524",
          "tgn:7029392"
        ],
        "placetype": [
          "aat:300008798"
        ],
        "id": 2143677,
        "name:xx": "Baird Butte"
      }
    },
    {
      "geometry": {
        "type": "Point",
        "coordinates": [
          -144.5167,
          60.7667
        ]
      },
      "type": "Feature",
      "properties": {
        "hierarchy": [
          "tgn:2143678",
          "tgn:7006450",
          "tgn:1000001",
          "tgn:7012149",
          "tgn:2000086",
          "tgn:7029392"
        ],
        "placetype": [
          "aat:300008761"
        ],
        "id": 2143678,
        "name:xx": "Baird Canyon"
      }
    },
    {
      "geometry": {
        "type": "Point",
        "coordinates": [
          -118.45,
          34.5333
        ]
      },
      "type": "Feature",
      "properties": {
        "hierarchy": [
          "tgn:2143679",
          "tgn:1000001",
          "tgn:7012149",
          "tgn:7007157",
          "tgn:1002608",
          "tgn:7029392"
        ],
        "placetype": [
          "aat:300008761"
        ],
        "id": 2143679,
        "name:xx": "Baird Canyon"
      }
    }
  ]
}
