{
  "geometry": {
    "type": "Point",
    "coordinates": [
      5.4333,
      49.0333
    ]
  },
  "type": "Feature",
  "properties": {
    "hierarchy": [
      "tgn:1033219",
      "tgn:1000003",
      "tgn:7002888",
      "tgn:1000070",
      "tgn:7029392"
    ],
    "placetype": [
      "aat:300008347"
    ],
    "id": 1033219,
    "name:xx": "Génicourt-sur-Meuse"
  }
}
