{
  "geometry": {
    "type": "Point",
    "coordinates": [
      -94.1333,
      34.8333
    ]
  },
  "type": "Feature",
  "properties": {
    "hierarchy": [
      "tgn:2595661",
      "tgn:1000001",
      "tgn:7016172",
      "tgn:7012149",
      "tgn:2000168",
      "tgn:7029392"
    ],
    "placetype": [
      "aat:300006191"
    ],
    "id": 2595661,
    "name:xx": "Poteau River Site 18 Lake"
  }
}
