{
  "geometry": {
    "type": "Point",
    "coordinates": [
      4.65,
      52.35
    ]
  },
  "type": "Feature",
  "properties": {
    "hierarchy": [
      "tgn:7270090",
      "tgn:1000003",
      "tgn:7006951",
      "tgn:7016845",
      "tgn:7029392"
    ],
    "placetype": [
      "aat:300008688"
    ],
    "name:nl": "Molenplas",
    "id": 7270090
  }
}
