{
  "geometry": {
    "type": "Point",
    "coordinates": [
      -76.8667,
      38.65
    ]
  },
  "type": "Feature",
  "properties": {
    "hierarchy": [
      "tgn:2496678",
      "tgn:7016100",
      "tgn:1000001",
      "tgn:7012149",
      "tgn:7007516",
      "tgn:7029392"
    ],
    "placetype": [
      "aat:300008347"
    ],
    "id": 2496678,
    "name:xx": "Mattawoman"
  }
}
