{
  "geometry": {
    "type": "Point",
    "coordinates": [
      -90.45,
      44.3333
    ]
  },
  "type": "Feature",
  "properties": {
    "hierarchy": [
      "tgn:2525268",
      "tgn:1000001",
      "tgn:7012149",
      "tgn:2002328",
      "tgn:7007922",
      "tgn:7029392"
    ],
    "placetype": [
      "aat:300008706"
    ],
    "id": 2525268,
    "name:xx": "Morrison Creek"
  }
}
