{
  "geometry": {
    "type": "Point",
    "coordinates": [
      -123.6667,
      41.4667
    ]
  },
  "type": "Feature",
  "properties": {
    "hierarchy": [
      "tgn:2648691",
      "tgn:1000001",
      "tgn:7012149",
      "tgn:2000180",
      "tgn:7007157",
      "tgn:7029392"
    ],
    "placetype": [
      "aat:300008706"
    ],
    "id": 2648691,
    "name:xx": "Scorpion Creek"
  }
}
