{
  "type": "FeatureCollection",
  "features": [
    {
      "geometry": {
        "type": "Point",
        "coordinates": [
          -86.2833,
          33.15
        ]
      },
      "type": "Feature",
      "properties": {
        "hierarchy": [
          "tgn:2491860",
          "tgn:7002659",
          "tgn:1000001",
          "tgn:7012149",
          "tgn:2000060",
          "tgn:7029392"
        ],
        "placetype": [
          "aat:300000390"
        ],
        "id": 2491860,
        "name:xx": "Marble City Quarry"
      }
    },
    {
      "geometry": {
        "type": "Point",
        "coordinates": [
          -134.7,
          57.6833
        ]
      },
      "type": "Feature",
      "properties": {
        "hierarchy": [
          "tgn:2491863",
          "tgn:7006450",
          "tgn:1000001",
          "tgn:7012149",
          "tgn:7019760",
          "tgn:7029392"
        ],
        "placetype": [
          "aat:300132316"
        ],
        "id": 2491863,
        "name:xx": "Marble Cove"
      }
    },
    {
      "geometry": {
        "type": "Point",
        "coordinates": [
          -133.4,
          56.2
        ]
      },
      "type": "Feature",
      "properties": {
        "hierarchy": [
          "tgn:2491864",
          "tgn:7006450",
          "tgn:1000001",
          "tgn:7012149",
          "tgn:2000082",
          "tgn:7029392"
        ],
        "placetype": [
          "aat:300008706"
        ],
        "id": 2491864,
        "name:xx": "Marble Creek"
      }
    },
    {
      "geometry": {
        "type": "Point",
        "coordinates": [
          -136.1333,
          58
        ]
      },
      "type": "Feature",
      "properties": {
        "hierarchy": [
          "tgn:2491865",
          "tgn:7006450",
          "tgn:1000001",
          "tgn:7012149",
          "tgn:7019760",
          "tgn:7029392"
        ],
        "placetype": [
          "aat:300008706"
        ],
        "id": 2491865,
        "name:xx": "Marble Creek"
      }
    },
    {
      "geometry": {
        "type": "Point",
        "coordinates": [
          -141.6833,
          60.8833
        ]
      },
      "type": "Feature",
      "properties": {
        "hierarchy": [
          "tgn:2491866",
          "tgn:7006450",
          "tgn:1000001",
          "tgn:7012149",
          "tgn:2000086",
          "tgn:7029392"
        ],
        "placetype": [
          "aat:300008706"
        ],
        "id": 2491866,
        "name:xx": "Marble Creek"
      }
    },
    {
      "geometry": {
        "type": "Point",
        "coordinates": [
          -131.2167,
          55.5
        ]
      },
      "type": "Feature",
      "properties": {
        "hierarchy": [
          "tgn:2491867",
          "tgn:7006450",
          "tgn:1000001",
          "tgn:2124076",
          "tgn:7012149",
          "tgn:7029392"
        ],
        "placetype": [
          "aat:300008706"
        ],
        "id": 2491867,
        "name:xx": "Marble Creek"
      }
    },
    {
      "geometry": {
        "type": "Point",
        "coordinates": [
          -121.9333,
          40.95
        ]
      },
      "type": "Feature",
      "properties": {
        "hierarchy": [
          "tgn:2491868",
          "tgn:1000001",
          "tgn:7012149",
          "tgn:7007157",
          "tgn:2000188",
          "tgn:7029392"
        ],
        "placetype": [
          "aat:300008706"
        ],
        "id": 2491868,
        "name:xx": "Marble Creek"
      }
    },
    {
      "geometry": {
        "type": "Point",
        "coordinates": [
          -122.8333,
          41.8833
        ]
      },
      "type": "Feature",
      "properties": {
        "hierarchy": [
          "tgn:2491869",
          "tgn:1000001",
          "tgn:7012149",
          "tgn:7007157",
          "tgn:2000189",
          "tgn:7029392"
        ],
        "placetype": [
          "aat:300008706"
        ],
        "id": 2491869,
        "name:xx": "Marble Creek"
      }
    }
  ]
}
