{
  "type": "FeatureCollection",
  "features": [
    {
      "geometry": {
        "type": "Point",
        "coordinates": [
          -83.75,
          35.9
        ]
      },
      "type": "Feature",
      "properties": {
        "hierarchy": [
          "tgn:2154890",
          "tgn:1000001",
          "tgn:7012149",
          "tgn:2001914",
          "tgn:7007825",
          "tgn:7029392"
        ],
        "placetype": [
          "aat:300008761"
        ],
        "id": 2154890,
        "name:xx": "Bear Hollow"
      }
    },
    {
      "geometry": {
        "type": "Point",
        "coordinates": [
          -86.8667,
          36.2833
        ]
      },
      "type": "Feature",
      "properties": {
        "hierarchy": [
          "tgn:2154891",
          "tgn:1000001",
          "tgn:7012149",
          "tgn:2001855",
          "tgn:7007825",
          "tgn:7029392"
        ],
        "placetype": [
          "aat:300008761"
        ],
        "id": 2154891,
        "name:xx": "Bear Hollow"
      }
    },
    {
      "geometry": {
        "type": "Point",
        "coordinates": [
          -82.8667,
          36.35
        ]
      },
      "type": "Feature",
      "properties": {
        "hierarchy": [
          "tgn:2154892",
          "tgn:1000001",
          "tgn:7012149",
          "tgn:7007825",
          "tgn:7029392"
        ],
        "placetype": [
          "aat:300008761"
        ],
        "id": 2154892,
        "name:xx": "Bear Hollow"
      }
    },
    {
      "geometry": {
        "type": "Point",
        "coordinates": [
          -83.1667,
          36.4667
        ]
      },
      "type": "Feature",
      "properties": {
        "hierarchy": [
          "tgn:2154893",
          "tgn:1000001",
          "tgn:7012149",
          "tgn:2001870",
          "tgn:7007825",
          "tgn:7029392"
        ],
        "placetype": [
          "aat:300008761"
        ],
        "id": 2154893,
        "name:xx": "Bear Hollow"
      }
    },
    {
      "geometry": {
        "type": "Point",
        "coordinates": [
          -97.8667,
          29.4333
        ]
      },
      "type": "Feature",
      "properties": {
        "hierarchy": [
          "tgn:2154894",
          "tgn:1000001",
          "tgn:7012149",
          "tgn:1002431",
          "tgn:7007826",
          "tgn:7029392"
        ],
        "placetype": [
          "aat:300008761"
        ],
        "id": 2154894,
        "name:xx": "Bear Hollow"
      }
    },
    {
      "geometry": {
        "type": "Point",
        "coordinates": [
          -99.1667,
          30.15
        ]
      },
      "type": "Feature",
      "properties": {
        "hierarchy": [
          "tgn:2154895",
          "tgn:1000001",
          "tgn:7012149",
          "tgn:7007826",
          "tgn:7029392"
        ],
        "placetype": [
          "aat:300008761"
        ],
        "id": 2154895,
        "name:xx": "Bear Hollow"
      }
    },
    {
      "geometry": {
        "type": "Point",
        "coordinates": [
          -98.5167,
          32.8167
        ]
      },
      "type": "Feature",
      "properties": {
        "hierarchy": [
          "tgn:2154896",
          "tgn:1000001",
          "tgn:7012149",
          "tgn:2002053",
          "tgn:7007826",
          "tgn:7029392"
        ],
        "placetype": [
          "aat:300008761"
        ],
        "id": 2154896,
        "name:xx": "Bear Hollow"
      }
    },
    {
      "geometry": {
        "type": "Point",
        "coordinates": [
          -97.9667,
          33.2167
        ]
      },
      "type": "Feature",
      "properties": {
        "hierarchy": [
          "tgn:2154897",
          "tgn:1000001",
          "tgn:7012149",
          "tgn:2002008",
          "tgn:7007826",
          "tgn:7029392"
        ],
        "placetype": [
          "aat:300008761"
        ],
        "id": 2154897,
        "name:xx": "Bear Hollow"
      }
    },
    {
      "geometry": {
        "type": "Point",
        "coordinates": [
          -99.2,
          30.4333
        ]
      },
      "type": "Feature",
      "properties": {
        "hierarchy": [
          "tgn:2154898",
          "tgn:1000001",
          "tgn:7012149",
          "tgn:2001990",
          "tgn:7007826",
          "tgn:7029392"
        ],
        "placetype": [
          "aat:300008761"
        ],
        "id": 2154898,
        "name:xx": "Bear Hollow"
      }
    },
    {
      "geometry": {
        "type": "Point",
        "coordinates": [
          -98.7333,
          31.0167
        ]
      },
      "type": "Feature",
      "properties": {
        "hierarchy": [
          "tgn:2154899",
          "tgn:1000001",
          "tgn:7012149",
          "tgn:2002069",
          "tgn:7007826",
          "tgn:7029392"
        ],
        "placetype": [
          "aat:300008761"
        ],
        "id": 2154899,
        "name:xx": "Bear Hollow"
      }
    }
  ]
}
