{
  "geometry": {
    "type": "Point",
    "coordinates": [
      76.841572,
      30.52101
    ]
  },
  "type": "Feature",
  "properties": {
    "hierarchy": [
      "tgn:7582175",
      "tgn:1000004",
      "tgn:7000198",
      "tgn:7016883",
      "tgn:7029392"
    ],
    "placetype": [
      "aat:300008347"
    ],
    "name:en": "Bhagwāsi",
    "id": 7582175
  }
}
