{
  "geometry": {
    "type": "Point",
    "coordinates": [
      -95.45,
      32.1833
    ]
  },
  "type": "Feature",
  "properties": {
    "hierarchy": [
      "tgn:2329835",
      "tgn:1000001",
      "tgn:7012149",
      "tgn:1002898",
      "tgn:7007826",
      "tgn:7029392"
    ],
    "placetype": [
      "aat:300132316"
    ],
    "id": 2329835,
    "name:xx": "Flag Bay"
  }
}
