{
  "geometry": {
    "type": "Point",
    "coordinates": [
      89.4167,
      23.7833
    ]
  },
  "type": "Feature",
  "properties": {
    "hierarchy": [
      "tgn:1065886",
      "tgn:7000189",
      "tgn:1000004",
      "tgn:1000105",
      "tgn:7029392"
    ],
    "placetype": [
      "aat:300008347"
    ],
    "id": 1065886,
    "name:xx": "Pangsa"
  }
}
