{
  "geometry": {
    "type": "Point",
    "coordinates": [
      -92.3833,
      43.8333
    ]
  },
  "type": "Feature",
  "properties": {
    "hierarchy": [
      "tgn:2569865",
      "tgn:1000001",
      "tgn:7012149",
      "tgn:7007521",
      "tgn:7029392"
    ],
    "placetype": [
      "aat:300008706"
    ],
    "id": 2569865,
    "name:xx": "Partridge Creek"
  }
}
