{
  "geometry": {
    "type": "Point",
    "coordinates": [
      -103.5667,
      36.25
    ]
  },
  "type": "Feature",
  "properties": {
    "hierarchy": [
      "tgn:2486191",
      "tgn:1000001",
      "tgn:7012149",
      "tgn:2001459",
      "tgn:7007566",
      "tgn:7029392"
    ],
    "placetype": [
      "aat:300008761"
    ],
    "id": 2486191,
    "name:xx": "Leal Canyon"
  }
}
