{
  "geometry": {
    "type": "Point",
    "coordinates": [
      -91.15,
      32.4833
    ]
  },
  "type": "Feature",
  "properties": {
    "hierarchy": [
      "tgn:2044123",
      "tgn:1000001",
      "tgn:7012149",
      "tgn:2000886",
      "tgn:7007256",
      "tgn:7029392"
    ],
    "placetype": [
      "aat:300008347"
    ],
    "id": 2044123,
    "name:xx": "Talla Bena"
  }
}
