{
  "type": "FeatureCollection",
  "features": [
    {
      "geometry": {
        "type": "Point",
        "coordinates": [
          -122,
          43.3833
        ]
      },
      "type": "Feature",
      "properties": {
        "hierarchy": [
          "tgn:2542010",
          "tgn:1000001",
          "tgn:7012149",
          "tgn:2001714",
          "tgn:7007708",
          "tgn:7029392"
        ],
        "placetype": [
          "aat:300008680"
        ],
        "id": 2542010,
        "name:xx": "Nip and Tuck Lakes"
      }
    },
    {
      "geometry": {
        "type": "Point",
        "coordinates": [
          -77.9167,
          39.5167
        ]
      },
      "type": "Feature",
      "properties": {
        "hierarchy": [
          "tgn:2542011",
          "tgn:1000001",
          "tgn:2002254",
          "tgn:7012149",
          "tgn:7013961",
          "tgn:7029392"
        ],
        "placetype": [
          "aat:300008347"
        ],
        "id": 2542011,
        "name:xx": "Nipetown"
      }
    },
    {
      "geometry": {
        "type": "Point",
        "coordinates": [
          -80.9333,
          39.6
        ]
      },
      "type": "Feature",
      "properties": {
        "hierarchy": [
          "tgn:2542012",
          "tgn:1000001",
          "tgn:7012149",
          "tgn:2001617",
          "tgn:7007706",
          "tgn:7029392"
        ],
        "placetype": [
          "aat:300008699"
        ],
        "id": 2542012,
        "name:xx": "Nipgut Run"
      }
    },
    {
      "geometry": {
        "type": "Point",
        "coordinates": [
          -84.55,
          45.7
        ]
      },
      "type": "Feature",
      "properties": {
        "hierarchy": [
          "tgn:2542013",
          "tgn:1000001",
          "tgn:2000951",
          "tgn:7012149",
          "tgn:7007520",
          "tgn:7029392"
        ],
        "placetype": [
          "aat:300008850"
        ],
        "id": 2542013,
        "name:xx": "Nipigon, Point"
      }
    },
    {
      "geometry": {
        "type": "Point",
        "coordinates": [
          -119.7167,
          37.4
        ]
      },
      "type": "Feature",
      "properties": {
        "hierarchy": [
          "tgn:2542014",
          "tgn:1000001",
          "tgn:7012149",
          "tgn:7007157",
          "tgn:1002621",
          "tgn:7029392"
        ],
        "placetype": [
          "aat:300008347"
        ],
        "id": 2542014,
        "name:xx": "Nipinnawasee"
      }
    },
    {
      "geometry": {
        "type": "Point",
        "coordinates": [
          -91.2333,
          47.35
        ]
      },
      "type": "Feature",
      "properties": {
        "hierarchy": [
          "tgn:2542015",
          "tgn:1000001",
          "tgn:7012149",
          "tgn:2001036",
          "tgn:7007521",
          "tgn:7029392"
        ],
        "placetype": [
          "aat:300008680"
        ],
        "id": 2542015,
        "name:xx": "Nipisiquit Lake"
      }
    },
    {
      "geometry": {
        "type": "Point",
        "coordinates": [
          -71.5667,
          42.0833
        ]
      },
      "type": "Feature",
      "properties": {
        "hierarchy": [
          "tgn:2542016",
          "tgn:1000001",
          "tgn:7012149",
          "tgn:1003038",
          "tgn:7007517",
          "tgn:7029392"
        ],
        "placetype": [
          "aat:300008680"
        ],
        "id": 2542016,
        "name:xx": "Nipmack Pond"
      }
    },
    {
      "geometry": {
        "type": "Point",
        "coordinates": [
          -73.4,
          42.8667
        ]
      },
      "type": "Feature",
      "properties": {
        "hierarchy": [
          "tgn:2542017",
          "tgn:1000001",
          "tgn:7012149",
          "tgn:1002821",
          "tgn:7007568",
          "tgn:7029392"
        ],
        "placetype": [
          "aat:300008699"
        ],
        "id": 2542017,
        "name:xx": "Nipmoose Brook"
      }
    },
    {
      "geometry": {
        "type": "Point",
        "coordinates": [
          -73.45,
          42.9
        ]
      },
      "type": "Feature",
      "properties": {
        "hierarchy": [
          "tgn:2542018",
          "tgn:1000001",
          "tgn:7012149",
          "tgn:1002821",
          "tgn:7007568",
          "tgn:7029392"
        ],
        "placetype": [
          "aat:300008798"
        ],
        "id": 2542018,
        "name:xx": "Nipmoose Hill"
      }
    },
    {
      "geometry": {
        "type": "Point",
        "coordinates": [
          -71.65,
          41.7167
        ]
      },
      "type": "Feature",
      "properties": {
        "hierarchy": [
          "tgn:2542019",
          "tgn:1002808",
          "tgn:1000001",
          "tgn:7012149",
          "tgn:7007711",
          "tgn:7029392"
        ],
        "placetype": [
          "aat:300008798"
        ],
        "id": 2542019,
        "name:xx": "Nipmuc Hill"
      }
    }
  ]
}
