{
  "geometry": {
    "type": "Point",
    "coordinates": [
      -83.0833,
      35.4667
    ]
  },
  "type": "Feature",
  "properties": {
    "hierarchy": [
      "tgn:2588124",
      "tgn:1000001",
      "tgn:7012149",
      "tgn:2001503",
      "tgn:7007709",
      "tgn:7029392"
    ],
    "placetype": [
      "aat:300008798"
    ],
    "id": 2588124,
    "name:xx": "Plott Balsam"
  }
}
