{
  "geometry": {
    "type": "Point",
    "coordinates": [
      -103.95,
      34.8667
    ]
  },
  "type": "Feature",
  "properties": {
    "hierarchy": [
      "tgn:2344627",
      "tgn:1000001",
      "tgn:7012149",
      "tgn:2001448",
      "tgn:7007566",
      "tgn:7029392"
    ],
    "placetype": [
      "aat:300008706"
    ],
    "id": 2344627,
    "name:xx": "Garcia Creek"
  }
}
