{
  "type": "FeatureCollection",
  "features": [
    {
      "geometry": {
        "type": "Point",
        "coordinates": [
          12.283333,
          53.8
        ]
      },
      "type": "Feature",
      "properties": {
        "hierarchy": [
          "tgn:7195690",
          "tgn:1000003",
          "tgn:7000094",
          "tgn:7000084",
          "tgn:7029392"
        ],
        "placetype": [
          "aat:300008680"
        ],
        "id": 7195690,
        "name:xx": "Dehmer See"
      }
    },
    {
      "geometry": {
        "type": "Point",
        "coordinates": [
          12.283333,
          53.8
        ]
      },
      "type": "Feature",
      "properties": {
        "hierarchy": [
          "tgn:7195691",
          "tgn:1000003",
          "tgn:7000094",
          "tgn:7000084",
          "tgn:7029392"
        ],
        "placetype": [
          "aat:300008347"
        ],
        "id": 7195691,
        "name:xx": "Dehmen"
      }
    },
    {
      "geometry": {
        "type": "Point",
        "coordinates": [
          11.516667,
          52.166667
        ]
      },
      "type": "Feature",
      "properties": {
        "hierarchy": [
          "tgn:7195692",
          "tgn:1000003",
          "tgn:7003687",
          "tgn:7000084",
          "tgn:7029392"
        ],
        "placetype": [
          "aat:300008777"
        ],
        "id": 7195692,
        "name:xx": "Dehm-Berg"
      }
    },
    {
      "geometry": {
        "type": "Point",
        "coordinates": [
          9.833333,
          51.066667
        ]
      },
      "type": "Feature",
      "properties": {
        "hierarchy": [
          "tgn:7195693",
          "tgn:1000003",
          "tgn:7003678",
          "tgn:7000084",
          "tgn:7029392"
        ],
        "placetype": [
          "aat:300008777"
        ],
        "id": 7195693,
        "name:xx": "Dehm-Berg"
      }
    },
    {
      "geometry": {
        "type": "Point",
        "coordinates": [
          8.5,
          53.033333
        ]
      },
      "type": "Feature",
      "properties": {
        "hierarchy": [
          "tgn:7195694",
          "tgn:1000003",
          "tgn:7003676",
          "tgn:7000084",
          "tgn:7029392"
        ],
        "placetype": [
          "aat:300008347"
        ],
        "id": 7195694,
        "name:xx": "Dehlthun"
      }
    },
    {
      "geometry": {
        "type": "Point",
        "coordinates": [
          12.016667,
          51.233333
        ]
      },
      "type": "Feature",
      "properties": {
        "hierarchy": [
          "tgn:7195695",
          "tgn:1000003",
          "tgn:7003687",
          "tgn:7000084",
          "tgn:7029392"
        ],
        "placetype": [
          "aat:300008347"
        ],
        "id": 7195695,
        "name:xx": "Dehlitz"
      }
    },
    {
      "geometry": {
        "type": "Point",
        "coordinates": [
          13.566667,
          52.3
        ]
      },
      "type": "Feature",
      "properties": {
        "hierarchy": [
          "tgn:7195696",
          "tgn:7000096",
          "tgn:1000003",
          "tgn:7000084",
          "tgn:7029392"
        ],
        "placetype": [
          "aat:300008777"
        ],
        "id": 7195696,
        "name:xx": "Dehlings-Berg"
      }
    },
    {
      "geometry": {
        "type": "Point",
        "coordinates": [
          7.866667,
          50.65
        ]
      },
      "type": "Feature",
      "properties": {
        "hierarchy": [
          "tgn:7195697",
          "tgn:1000003",
          "tgn:7003682",
          "tgn:7000084",
          "tgn:7029392"
        ],
        "placetype": [
          "aat:300008347"
        ],
        "id": 7195697,
        "name:xx": "Dehlingen"
      }
    },
    {
      "geometry": {
        "type": "Point",
        "coordinates": [
          10.35,
          48.8
        ]
      },
      "type": "Feature",
      "properties": {
        "hierarchy": [
          "tgn:7195698",
          "tgn:7003692",
          "tgn:1000003",
          "tgn:7000084",
          "tgn:7029392"
        ],
        "placetype": [
          "aat:300008347"
        ],
        "id": 7195698,
        "name:xx": "Dehlingen"
      }
    },
    {
      "geometry": {
        "type": "Point",
        "coordinates": [
          7.05,
          51.8
        ]
      },
      "type": "Feature",
      "properties": {
        "hierarchy": [
          "tgn:7195699",
          "tgn:1000003",
          "tgn:7003677",
          "tgn:7000084",
          "tgn:7029392"
        ],
        "placetype": [
          "aat:300000206"
        ],
        "id": 7195699,
        "name:xx": "Dehling"
      }
    }
  ]
}
