{
  "type": "FeatureCollection",
  "features": [
    {
      "geometry": {
        "type": "Point",
        "coordinates": [
          -85.7833,
          46.1167
        ]
      },
      "type": "Feature",
      "properties": {
        "hierarchy": [
          "tgn:2448430",
          "tgn:1000001",
          "tgn:7012149",
          "tgn:2000973",
          "tgn:7007520",
          "tgn:7029392"
        ],
        "placetype": [
          "aat:300008680"
        ],
        "id": 2448430,
        "name:xx": "Lilly Lake"
      }
    },
    {
      "geometry": {
        "type": "Point",
        "coordinates": [
          -93.7333,
          44.1667
        ]
      },
      "type": "Feature",
      "properties": {
        "hierarchy": [
          "tgn:2448431",
          "tgn:1000001",
          "tgn:7012149",
          "tgn:2001079",
          "tgn:7007521",
          "tgn:7029392"
        ],
        "placetype": [
          "aat:300008680"
        ],
        "id": 2448431,
        "name:xx": "Lilly Lake"
      }
    },
    {
      "geometry": {
        "type": "Point",
        "coordinates": [
          -93.0667,
          44.9
        ]
      },
      "type": "Feature",
      "properties": {
        "hierarchy": [
          "tgn:2448432",
          "tgn:1000001",
          "tgn:2001017",
          "tgn:7012149",
          "tgn:7007521",
          "tgn:7029392"
        ],
        "placetype": [
          "aat:300008680"
        ],
        "id": 2448432,
        "name:xx": "Lilly Lake"
      }
    },
    {
      "geometry": {
        "type": "Point",
        "coordinates": [
          -112.4333,
          46.5333
        ]
      },
      "type": "Feature",
      "properties": {
        "hierarchy": [
          "tgn:2448433",
          "tgn:1000001",
          "tgn:7012149",
          "tgn:2001298",
          "tgn:7007524",
          "tgn:7029392"
        ],
        "placetype": [
          "aat:300008680"
        ],
        "id": 2448433,
        "name:xx": "Lilly Lake"
      }
    },
    {
      "geometry": {
        "type": "Point",
        "coordinates": [
          -80.4,
          36.25
        ]
      },
      "type": "Feature",
      "properties": {
        "hierarchy": [
          "tgn:2448434",
          "tgn:1000001",
          "tgn:7012149",
          "tgn:2001541",
          "tgn:7007709",
          "tgn:7029392"
        ],
        "placetype": [
          "aat:300006191"
        ],
        "id": 2448434,
        "name:xx": "Lilly Lake"
      }
    },
    {
      "geometry": {
        "type": "Point",
        "coordinates": [
          -124.1,
          43.9167
        ]
      },
      "type": "Feature",
      "properties": {
        "hierarchy": [
          "tgn:2448435",
          "tgn:1000001",
          "tgn:7012149",
          "tgn:2001716",
          "tgn:7007708",
          "tgn:7029392"
        ],
        "placetype": [
          "aat:300008680"
        ],
        "id": 2448435,
        "name:xx": "Lilly Lake"
      }
    },
    {
      "geometry": {
        "type": "Point",
        "coordinates": [
          -75.7167,
          41.5333
        ]
      },
      "type": "Feature",
      "properties": {
        "hierarchy": [
          "tgn:2448436",
          "tgn:1000001",
          "tgn:7012149",
          "tgn:1002564",
          "tgn:7007710",
          "tgn:7029392"
        ],
        "placetype": [
          "aat:300008680"
        ],
        "id": 2448436,
        "name:xx": "Lilly Lake"
      }
    },
    {
      "geometry": {
        "type": "Point",
        "coordinates": [
          -97.7667,
          27.9167
        ]
      },
      "type": "Feature",
      "properties": {
        "hierarchy": [
          "tgn:2448437",
          "tgn:1000001",
          "tgn:7012149",
          "tgn:2002049",
          "tgn:7007826",
          "tgn:7029392"
        ],
        "placetype": [
          "aat:300008680"
        ],
        "id": 2448437,
        "name:xx": "Lilly Lake"
      }
    },
    {
      "geometry": {
        "type": "Point",
        "coordinates": [
          -94.9667,
          32.85
        ]
      },
      "type": "Feature",
      "properties": {
        "hierarchy": [
          "tgn:2448438",
          "tgn:1000001",
          "tgn:7012149",
          "tgn:1002966",
          "tgn:7007826",
          "tgn:7029392"
        ],
        "placetype": [
          "aat:300008680"
        ],
        "id": 2448438,
        "name:xx": "Lilly Lake"
      }
    },
    {
      "geometry": {
        "type": "Point",
        "coordinates": [
          -94,
          31.5167
        ]
      },
      "type": "Feature",
      "properties": {
        "hierarchy": [
          "tgn:2448439",
          "tgn:1000001",
          "tgn:7012149",
          "tgn:2002067",
          "tgn:7007826",
          "tgn:7029392"
        ],
        "placetype": [
          "aat:300006191"
        ],
        "id": 2448439,
        "name:xx": "Lilly Lake"
      }
    }
  ]
}
