{
  "geometry": {
    "type": "Point",
    "coordinates": [
      -84.35,
      36.8833
    ]
  },
  "type": "Feature",
  "properties": {
    "hierarchy": [
      "tgn:2216486",
      "tgn:1000001",
      "tgn:7012149",
      "tgn:2000818",
      "tgn:7007255",
      "tgn:7029392"
    ],
    "placetype": [
      "aat:300008706"
    ],
    "id": 2216486,
    "name:xx": "Camp Creek"
  }
}
