{
  "geometry": {
    "type": "Point",
    "coordinates": [
      -76.6833,
      45.7333
    ]
  },
  "type": "Feature",
  "properties": {
    "hierarchy": [
      "tgn:1007235",
      "tgn:7005685",
      "tgn:1000001",
      "tgn:7005804",
      "tgn:7029392"
    ],
    "placetype": [
      "aat:300008791"
    ],
    "id": 1007235,
    "name:xx": "Grand Calumet, Île du"
  }
}
