{
  "geometry": {
    "type": "Point",
    "coordinates": [
      -118.5333,
      34.6667
    ]
  },
  "type": "Feature",
  "properties": {
    "hierarchy": [
      "tgn:2209303",
      "tgn:1000001",
      "tgn:7012149",
      "tgn:7007157",
      "tgn:1002608",
      "tgn:7029392"
    ],
    "placetype": [
      "aat:300008761"
    ],
    "id": 2209303,
    "name:xx": "Burnt Peak Canyon"
  }
}
