{
  "type": "FeatureCollection",
  "features": [
    {
      "geometry": {
        "type": "Point",
        "coordinates": [
          -96.8167,
          32.9333
        ]
      },
      "type": "Feature",
      "properties": {
        "hierarchy": [
          "tgn:2323280",
          "tgn:1000001",
          "tgn:7012149",
          "tgn:1002315",
          "tgn:7007826",
          "tgn:7029392"
        ],
        "placetype": [
          "aat:300008699"
        ],
        "id": 2323280,
        "name:xx": "Farmers Branch"
      }
    },
    {
      "geometry": {
        "type": "Point",
        "coordinates": [
          -98.55,
          33.15
        ]
      },
      "type": "Feature",
      "properties": {
        "hierarchy": [
          "tgn:2323281",
          "tgn:1000001",
          "tgn:7012149",
          "tgn:2002098",
          "tgn:7007826",
          "tgn:7029392"
        ],
        "placetype": [
          "aat:300008699"
        ],
        "id": 2323281,
        "name:xx": "Farmers Branch"
      }
    },
    {
      "geometry": {
        "type": "Point",
        "coordinates": [
          -81.2333,
          36.6667
        ]
      },
      "type": "Feature",
      "properties": {
        "hierarchy": [
          "tgn:2323282",
          "tgn:1000001",
          "tgn:7012149",
          "tgn:2002164",
          "tgn:7007919",
          "tgn:7029392"
        ],
        "placetype": [
          "aat:300008699"
        ],
        "id": 2323282,
        "name:xx": "Farmers Branch"
      }
    },
    {
      "geometry": {
        "type": "Point",
        "coordinates": [
          -78.6833,
          36.9833
        ]
      },
      "type": "Feature",
      "properties": {
        "hierarchy": [
          "tgn:2323283",
          "tgn:1000001",
          "tgn:2002152",
          "tgn:7012149",
          "tgn:7007919",
          "tgn:7029392"
        ],
        "placetype": [
          "aat:300008699"
        ],
        "id": 2323283,
        "name:xx": "Farmers Branch"
      }
    },
    {
      "geometry": {
        "type": "Point",
        "coordinates": [
          -81.4,
          37.2833
        ]
      },
      "type": "Feature",
      "properties": {
        "hierarchy": [
          "tgn:2323284",
          "tgn:1000001",
          "tgn:7012149",
          "tgn:2002192",
          "tgn:7007919",
          "tgn:7029392"
        ],
        "placetype": [
          "aat:300008699"
        ],
        "id": 2323284,
        "name:xx": "Farmers Branch"
      }
    },
    {
      "geometry": {
        "type": "Point",
        "coordinates": [
          -122.5667,
          44.3
        ]
      },
      "type": "Feature",
      "properties": {
        "hierarchy": [
          "tgn:2323285",
          "tgn:1000001",
          "tgn:7012149",
          "tgn:2001717",
          "tgn:7007708",
          "tgn:7029392"
        ],
        "placetype": [
          "aat:300008798"
        ],
        "id": 2323285,
        "name:xx": "Farmers Butte"
      }
    },
    {
      "geometry": {
        "type": "Point",
        "coordinates": [
          -113.4167,
          32.9333
        ]
      },
      "type": "Feature",
      "properties": {
        "hierarchy": [
          "tgn:2323286",
          "tgn:1000001",
          "tgn:7006451",
          "tgn:7012149",
          "tgn:2000104",
          "tgn:7029392"
        ],
        "placetype": [
          "aat:300006075"
        ],
        "id": 2323286,
        "name:xx": "Farmers Canal"
      }
    },
    {
      "geometry": {
        "type": "Point",
        "coordinates": [
          -119.05,
          35.2833
        ]
      },
      "type": "Feature",
      "properties": {
        "hierarchy": [
          "tgn:2323287",
          "tgn:1000001",
          "tgn:7012149",
          "tgn:1002545",
          "tgn:7007157",
          "tgn:7029392"
        ],
        "placetype": [
          "aat:300006075"
        ],
        "id": 2323287,
        "name:xx": "Farmers Canal"
      }
    },
    {
      "geometry": {
        "type": "Point",
        "coordinates": [
          -96.25,
          42.3167
        ]
      },
      "type": "Feature",
      "properties": {
        "hierarchy": [
          "tgn:2323288",
          "tgn:1000001",
          "tgn:7012149",
          "tgn:2000657",
          "tgn:7007253",
          "tgn:7029392"
        ],
        "placetype": [
          "aat:300006075"
        ],
        "id": 2323288,
        "name:xx": "Farmers Canal"
      }
    },
    {
      "geometry": {
        "type": "Point",
        "coordinates": [
          -111.1667,
          45.6333
        ]
      },
      "type": "Feature",
      "properties": {
        "hierarchy": [
          "tgn:2323289",
          "tgn:1000001",
          "tgn:7012149",
          "tgn:7007524",
          "tgn:7029392"
        ],
        "placetype": [
          "aat:300006075"
        ],
        "id": 2323289,
        "name:xx": "Farmers Canal"
      }
    }
  ]
}
