{
  "geometry": {
    "type": "Point",
    "coordinates": [
      -77.2833,
      42.75
    ]
  },
  "type": "Feature",
  "properties": {
    "hierarchy": [
      "tgn:2328427",
      "tgn:1000001",
      "tgn:7012149",
      "tgn:1002747",
      "tgn:7007568",
      "tgn:7029392"
    ],
    "placetype": [
      "aat:300008761"
    ],
    "id": 2328427,
    "name:xx": "Fisher Gully"
  }
}
