{
  "geometry": {
    "type": "Point",
    "coordinates": [
      -115.9333,
      48.6667
    ]
  },
  "type": "Feature",
  "properties": {
    "hierarchy": [
      "tgn:2750319",
      "tgn:1000001",
      "tgn:7012149",
      "tgn:2001286",
      "tgn:7007524",
      "tgn:7029392"
    ],
    "placetype": [
      "aat:300008706"
    ],
    "id": 2750319,
    "name:xx": "Wampoo Creek"
  }
}
