{
  "geometry": {
    "type": "Point",
    "coordinates": [
      -93.2333,
      39.7167
    ]
  },
  "type": "Feature",
  "properties": {
    "hierarchy": [
      "tgn:2377108",
      "tgn:1000001",
      "tgn:7012149",
      "tgn:2001214",
      "tgn:7007523",
      "tgn:7029392"
    ],
    "placetype": [
      "aat:300008680"
    ],
    "id": 2377108,
    "name:xx": "Harlow Fay Lakes"
  }
}
