{
  "geometry": {
    "type": "Point",
    "coordinates": [
      21.0025,
      38.480833
    ]
  },
  "type": "Feature",
  "properties": {
    "hierarchy": [
      "tgn:7226496",
      "tgn:7011167",
      "tgn:7001338",
      "tgn:1000003",
      "tgn:1000074",
      "tgn:7029392"
    ],
    "placetype": [
      "aat:300008791"
    ],
    "id": 7226496,
    "name:xx": "Sofía, Nisída"
  }
}
