{
  "geometry": {
    "type": "Point",
    "coordinates": [
      -116.1333,
      42.3667
    ]
  },
  "type": "Feature",
  "properties": {
    "hierarchy": [
      "tgn:2733735",
      "tgn:1000001",
      "tgn:7012149",
      "tgn:2000488",
      "tgn:7007250",
      "tgn:7029392"
    ],
    "placetype": [
      "aat:300008798"
    ],
    "id": 2733735,
    "name:xx": "Turner Butte"
  }
}
