{
  "geometry": {
    "type": "Point",
    "coordinates": [
      -88.1667,
      36.3667
    ]
  },
  "type": "Feature",
  "properties": {
    "hierarchy": [
      "tgn:2706247",
      "tgn:1000001",
      "tgn:7012149",
      "tgn:2001876",
      "tgn:7007825",
      "tgn:7029392"
    ],
    "placetype": [
      "aat:300008706"
    ],
    "id": 2706247,
    "name:xx": "Swamp Creek"
  }
}
