{
  "geometry": {
    "type": "Point",
    "coordinates": [
      -114.7167,
      34.9333
    ]
  },
  "type": "Feature",
  "properties": {
    "hierarchy": [
      "tgn:2612255",
      "tgn:1000001",
      "tgn:7012149",
      "tgn:7007157",
      "tgn:1002857",
      "tgn:7029392"
    ],
    "placetype": [
      "aat:300008697"
    ],
    "id": 2612255,
    "name:xx": "Red Spring"
  }
}
