{
  "geometry": {
    "type": "Point",
    "coordinates": [
      -107.3833,
      35.4833
    ]
  },
  "type": "Feature",
  "properties": {
    "hierarchy": [
      "tgn:2384652",
      "tgn:1000001",
      "tgn:7012149",
      "tgn:7019676",
      "tgn:7007566",
      "tgn:7029392"
    ],
    "placetype": [
      "aat:300006191"
    ],
    "id": 2384652,
    "name:xx": "Heller Tank"
  }
}
