{
  "geometry": {
    "type": "Point",
    "coordinates": [
      -84.05,
      40.3833
    ]
  },
  "type": "Feature",
  "properties": {
    "hierarchy": [
      "tgn:2403988",
      "tgn:1000001",
      "tgn:7012149",
      "tgn:1002889",
      "tgn:7007706",
      "tgn:7029392"
    ],
    "placetype": [
      "aat:300006075"
    ],
    "id": 2403988,
    "name:xx": "Howell Ditch"
  }
}
