{
  "geometry": {
    "type": "Point",
    "coordinates": [
      30.908321,
      31.05306
    ]
  },
  "type": "Feature",
  "properties": {
    "hierarchy": [
      "tgn:7536045",
      "tgn:7001242",
      "tgn:7016833",
      "tgn:1001335",
      "tgn:7029392"
    ],
    "placetype": [
      "aat:300008347"
    ],
    "name:en": "Al Manshīyah",
    "id": 7536045
  }
}
