{
  "geometry": {
    "type": "Point",
    "coordinates": [
      79.195245,
      24.648482
    ]
  },
  "type": "Feature",
  "properties": {
    "hierarchy": [
      "tgn:7566101",
      "tgn:1000004",
      "tgn:7000198",
      "tgn:1001894",
      "tgn:7029392"
    ],
    "placetype": [
      "aat:300008699"
    ],
    "name:en": "Jamnāro Nāla",
    "id": 7566101
  }
}
