{
  "geometry": {
    "type": "Point",
    "coordinates": [
      -84.1167,
      33.4333
    ]
  },
  "type": "Feature",
  "properties": {
    "hierarchy": [
      "tgn:2501037",
      "tgn:1000001",
      "tgn:7012149",
      "tgn:2000366",
      "tgn:7007248",
      "tgn:7029392"
    ],
    "placetype": [
      "aat:300006191"
    ],
    "id": 2501037,
    "name:xx": "McGarity Lake"
  }
}
