{
  "geometry": {
    "type": "Point",
    "coordinates": [
      -111.95,
      41.3167
    ]
  },
  "type": "Feature",
  "properties": {
    "hierarchy": [
      "tgn:2495105",
      "tgn:1000001",
      "tgn:7012149",
      "tgn:2002129",
      "tgn:7007827",
      "tgn:7029392"
    ],
    "placetype": [
      "aat:300008347"
    ],
    "id": 2495105,
    "name:xx": "Marvella Heights"
  }
}
