{
  "geometry": {
    "type": "Point",
    "coordinates": [
      -87.6667,
      34.5833
    ]
  },
  "type": "Feature",
  "properties": {
    "hierarchy": [
      "tgn:2004258",
      "tgn:7002659",
      "tgn:1000001",
      "tgn:2000016",
      "tgn:7012149",
      "tgn:7029392"
    ],
    "placetype": [
      "aat:300008347"
    ],
    "id": 2004258,
    "name:xx": "Littleville"
  }
}
