{
  "type": "FeatureCollection",
  "features": [
    {
      "geometry": {
        "type": "Point",
        "coordinates": [
          -120.7,
          35.1833
        ]
      },
      "type": "Feature",
      "properties": {
        "hierarchy": [
          "tgn:2511590",
          "tgn:1000001",
          "tgn:7012149",
          "tgn:7007157",
          "tgn:1002863",
          "tgn:7029392"
        ],
        "placetype": [
          "aat:300008347"
        ],
        "id": 2511590,
        "name:xx": "Miles"
      }
    },
    {
      "geometry": {
        "type": "Point",
        "coordinates": [
          -91.0833,
          30.1333
        ]
      },
      "type": "Feature",
      "properties": {
        "hierarchy": [
          "tgn:2511591",
          "tgn:2000856",
          "tgn:1000001",
          "tgn:7012149",
          "tgn:7007256",
          "tgn:7029392"
        ],
        "placetype": [
          "aat:300008347"
        ],
        "id": 2511591,
        "name:xx": "Miles"
      }
    },
    {
      "geometry": {
        "type": "Point",
        "coordinates": [
          -90.7333,
          30
        ]
      },
      "type": "Feature",
      "properties": {
        "hierarchy": [
          "tgn:2511592",
          "tgn:1000001",
          "tgn:7012149",
          "tgn:2000900",
          "tgn:7007256",
          "tgn:7029392"
        ],
        "placetype": [
          "aat:300008347"
        ],
        "id": 2511592,
        "name:xx": "Miles"
      }
    },
    {
      "geometry": {
        "type": "Point",
        "coordinates": [
          -106.1833,
          35.2333
        ]
      },
      "type": "Feature",
      "properties": {
        "hierarchy": [
          "tgn:2511593",
          "tgn:1000001",
          "tgn:7012149",
          "tgn:2001454",
          "tgn:7007566",
          "tgn:7029392"
        ],
        "placetype": [
          "aat:300000390"
        ],
        "id": 2511593,
        "name:xx": "Miles"
      }
    },
    {
      "geometry": {
        "type": "Point",
        "coordinates": [
          -81.6,
          41.4333
        ]
      },
      "type": "Feature",
      "properties": {
        "hierarchy": [
          "tgn:2511594",
          "tgn:1000001",
          "tgn:1002313",
          "tgn:7012149",
          "tgn:7007706",
          "tgn:7029392"
        ],
        "placetype": [
          "aat:300008347"
        ],
        "id": 2511594,
        "name:xx": "Miles"
      }
    },
    {
      "geometry": {
        "type": "Point",
        "coordinates": [
          -117.6667,
          44.9167
        ]
      },
      "type": "Feature",
      "properties": {
        "hierarchy": [
          "tgn:2511595",
          "tgn:7013349",
          "tgn:1000001",
          "tgn:7012149",
          "tgn:7007708",
          "tgn:7029392"
        ],
        "placetype": [
          "aat:300008347"
        ],
        "id": 2511595,
        "name:xx": "Miles"
      }
    },
    {
      "geometry": {
        "type": "Point",
        "coordinates": [
          -79.1167,
          38.75
        ]
      },
      "type": "Feature",
      "properties": {
        "hierarchy": [
          "tgn:2511596",
          "tgn:1000001",
          "tgn:7012149",
          "tgn:7014398",
          "tgn:7013961",
          "tgn:7029392"
        ],
        "placetype": [
          "aat:300008347"
        ],
        "id": 2511596,
        "name:xx": "Miles"
      }
    },
    {
      "geometry": {
        "type": "Point",
        "coordinates": [
          -91.6333,
          30.9167
        ]
      },
      "type": "Feature",
      "properties": {
        "hierarchy": [
          "tgn:2511597",
          "tgn:1000001",
          "tgn:7012149",
          "tgn:2000916",
          "tgn:7007256",
          "tgn:7029392"
        ],
        "placetype": [
          "aat:300132348"
        ],
        "id": 2511597,
        "name:xx": "Miles Bar"
      }
    },
    {
      "geometry": {
        "type": "Point",
        "coordinates": [
          -85.5333,
          33.2667
        ]
      },
      "type": "Feature",
      "properties": {
        "hierarchy": [
          "tgn:2511598",
          "tgn:7002659",
          "tgn:1000001",
          "tgn:7012149",
          "tgn:2000055",
          "tgn:7029392"
        ],
        "placetype": [
          "aat:300008699"
        ],
        "id": 2511598,
        "name:xx": "Miles Branch"
      }
    },
    {
      "geometry": {
        "type": "Point",
        "coordinates": [
          -81.45,
          32.1667
        ]
      },
      "type": "Feature",
      "properties": {
        "hierarchy": [
          "tgn:2511599",
          "tgn:1000001",
          "tgn:2000306",
          "tgn:7012149",
          "tgn:7007248",
          "tgn:7029392"
        ],
        "placetype": [
          "aat:300008699"
        ],
        "id": 2511599,
        "name:xx": "Miles Branch"
      }
    }
  ]
}
