{
  "geometry": {
    "type": "Point",
    "coordinates": [
      -83.8833,
      32.4167
    ]
  },
  "type": "Feature",
  "properties": {
    "hierarchy": [
      "tgn:2147106",
      "tgn:1000001",
      "tgn:7012149",
      "tgn:7007248",
      "tgn:7029392"
    ],
    "placetype": [
      "aat:300008706"
    ],
    "id": 2147106,
    "name:xx": "Baptist Creek"
  }
}
