{
  "type": "FeatureCollection",
  "features": [
    {
      "geometry": {
        "type": "Point",
        "coordinates": [
          30.768299,
          30.814335
        ]
      },
      "type": "Feature",
      "properties": {
        "hierarchy": [
          "tgn:7535760",
          "tgn:7001242",
          "tgn:1001075",
          "tgn:7016833",
          "tgn:7029392"
        ],
        "placetype": [
          "aat:300008347"
        ],
        "name:en": "Kafr al 'Īş",
        "id": 7535760
      }
    },
    {
      "geometry": {
        "type": "Point",
        "coordinates": [
          31.360713,
          30.81192
        ]
      },
      "type": "Feature",
      "properties": {
        "hierarchy": [
          "tgn:7535761",
          "tgn:7001242",
          "tgn:1001059",
          "tgn:7016833",
          "tgn:7029392"
        ],
        "placetype": [
          "aat:300008347"
        ],
        "name:en": "Kafr al 'Inānīyah",
        "id": 7535761
      }
    },
    {
      "geometry": {
        "type": "Point",
        "coordinates": [
          31.966667,
          30.816667
        ]
      },
      "type": "Feature",
      "properties": {
        "hierarchy": [
          "tgn:7535762",
          "tgn:7001242",
          "tgn:7016833",
          "tgn:1001113",
          "tgn:7029392"
        ],
        "placetype": [
          "aat:300008347"
        ],
        "name:en": "Kafr al 'Imārāt",
        "id": 7535762
      }
    },
    {
      "geometry": {
        "type": "Point",
        "coordinates": [
          30.563185,
          31.211745
        ]
      },
      "type": "Feature",
      "properties": {
        "hierarchy": [
          "tgn:7535763",
          "tgn:7001242",
          "tgn:7016833",
          "tgn:1001335",
          "tgn:7029392"
        ],
        "placetype": [
          "aat:300008347"
        ],
        "name:en": "Kafr al 'Ilwī",
        "id": 7535763
      }
    },
    {
      "geometry": {
        "type": "Point",
        "coordinates": [
          31.492532,
          31.092342
        ]
      },
      "type": "Feature",
      "properties": {
        "hierarchy": [
          "tgn:7535764",
          "tgn:7001242",
          "tgn:1001059",
          "tgn:7016833",
          "tgn:7029392"
        ],
        "placetype": [
          "aat:300008347"
        ],
        "name:en": "Kafr al 'Ilw",
        "id": 7535764
      }
    },
    {
      "geometry": {
        "type": "Point",
        "coordinates": [
          30.827637,
          31.00563
        ]
      },
      "type": "Feature",
      "properties": {
        "hierarchy": [
          "tgn:7535765",
          "tgn:7001242",
          "tgn:7016833",
          "tgn:1001335",
          "tgn:7029392"
        ],
        "placetype": [
          "aat:300008347"
        ],
        "name:en": "Kafr al 'Ilw",
        "id": 7535765
      }
    },
    {
      "geometry": {
        "type": "Point",
        "coordinates": [
          31.3,
          29.816667
        ]
      },
      "type": "Feature",
      "properties": {
        "hierarchy": [
          "tgn:7535766",
          "tgn:7001242",
          "tgn:7016833",
          "tgn:1001083",
          "tgn:7029392"
        ],
        "placetype": [
          "aat:300008347"
        ],
        "name:en": "Kafr al 'Ilw",
        "id": 7535766
      }
    },
    {
      "geometry": {
        "type": "Point",
        "coordinates": [
          30.633571,
          29.396278
        ]
      },
      "type": "Feature",
      "properties": {
        "hierarchy": [
          "tgn:7535767",
          "tgn:7001242",
          "tgn:7001105",
          "tgn:7016833",
          "tgn:7029392"
        ],
        "placetype": [
          "aat:300008347"
        ],
        "name:en": "Kaḩk al Qiblīyah",
        "id": 7535767
      }
    },
    {
      "geometry": {
        "type": "Point",
        "coordinates": [
          31.334828,
          30.399688
        ]
      },
      "type": "Feature",
      "properties": {
        "hierarchy": [
          "tgn:7535768",
          "tgn:7001242",
          "tgn:7016833",
          "tgn:1001113",
          "tgn:7029392"
        ],
        "placetype": [
          "aat:300008347"
        ],
        "name:en": "Kafr 'Alī Ghālī",
        "id": 7535768
      }
    },
    {
      "geometry": {
        "type": "Point",
        "coordinates": [
          31.36138,
          30.6517
        ]
      },
      "type": "Feature",
      "properties": {
        "hierarchy": [
          "tgn:7535769",
          "tgn:7001242",
          "tgn:1001059",
          "tgn:7016833",
          "tgn:7029392"
        ],
        "placetype": [
          "aat:300008347"
        ],
        "id": 7535769,
        "name:xx": "Kafr 'Alī Badrah"
      }
    }
  ]
}
