{
  "geometry": {
    "type": "Point",
    "coordinates": [
      -122.55,
      48.4333
    ]
  },
  "type": "Feature",
  "properties": {
    "hierarchy": [
      "tgn:2664505",
      "tgn:1000001",
      "tgn:7012149",
      "tgn:7014510",
      "tgn:7007920",
      "tgn:7029392"
    ],
    "placetype": [
      "aat:300132316"
    ],
    "id": 2664505,
    "name:xx": "Similk Bay"
  }
}
