{
  "geometry": {
    "type": "Point",
    "coordinates": [
      -86.45,
      30.9667
    ]
  },
  "type": "Feature",
  "properties": {
    "hierarchy": [
      "tgn:2172998",
      "tgn:1000001",
      "tgn:7012149",
      "tgn:7029392"
    ],
    "placetype": [
      "aat:300008699"
    ],
    "id": 2172998,
    "name:xx": "Billys Branch"
  }
}
