{
  "type": "FeatureCollection",
  "features": [
    {
      "geometry": {
        "type": "Point",
        "coordinates": [
          -84.95,
          37.25
        ]
      },
      "type": "Feature",
      "properties": {
        "hierarchy": [
          "tgn:2713180",
          "tgn:1000001",
          "tgn:2000779",
          "tgn:7012149",
          "tgn:7007255",
          "tgn:7029392"
        ],
        "placetype": [
          "aat:300266640"
        ],
        "id": 2713180,
        "name:xx": "Taylor Ridge"
      }
    },
    {
      "geometry": {
        "type": "Point",
        "coordinates": [
          -92.1333,
          36.6667
        ]
      },
      "type": "Feature",
      "properties": {
        "hierarchy": [
          "tgn:2713181",
          "tgn:1000001",
          "tgn:7012149",
          "tgn:2001226",
          "tgn:7007523",
          "tgn:7029392"
        ],
        "placetype": [
          "aat:300266640"
        ],
        "id": 2713181,
        "name:xx": "Taylor Ridge"
      }
    },
    {
      "geometry": {
        "type": "Point",
        "coordinates": [
          -82.1,
          39.4667
        ]
      },
      "type": "Feature",
      "properties": {
        "hierarchy": [
          "tgn:2713182",
          "tgn:2001610",
          "tgn:1000001",
          "tgn:7012149",
          "tgn:7007706",
          "tgn:7029392"
        ],
        "placetype": [
          "aat:300266640"
        ],
        "id": 2713182,
        "name:xx": "Taylor Ridge"
      }
    },
    {
      "geometry": {
        "type": "Point",
        "coordinates": [
          -123.0667,
          43.4333
        ]
      },
      "type": "Feature",
      "properties": {
        "hierarchy": [
          "tgn:2713183",
          "tgn:1000001",
          "tgn:7012149",
          "tgn:2001706",
          "tgn:7007708",
          "tgn:7029392"
        ],
        "placetype": [
          "aat:300266640"
        ],
        "id": 2713183,
        "name:xx": "Taylor Ridge"
      }
    },
    {
      "geometry": {
        "type": "Point",
        "coordinates": [
          -123.6167,
          44.55
        ]
      },
      "type": "Feature",
      "properties": {
        "hierarchy": [
          "tgn:2713184",
          "tgn:1000001",
          "tgn:7012149",
          "tgn:1002599",
          "tgn:7007708",
          "tgn:7029392"
        ],
        "placetype": [
          "aat:300266640"
        ],
        "id": 2713184,
        "name:xx": "Taylor Ridge"
      }
    },
    {
      "geometry": {
        "type": "Point",
        "coordinates": [
          -123.8,
          44.15
        ]
      },
      "type": "Feature",
      "properties": {
        "hierarchy": [
          "tgn:2713185",
          "tgn:1000001",
          "tgn:7012149",
          "tgn:2001716",
          "tgn:7007708",
          "tgn:7029392"
        ],
        "placetype": [
          "aat:300266640"
        ],
        "id": 2713185,
        "name:xx": "Taylor Ridge"
      }
    },
    {
      "geometry": {
        "type": "Point",
        "coordinates": [
          -85.2,
          35.2833
        ]
      },
      "type": "Feature",
      "properties": {
        "hierarchy": [
          "tgn:2713186",
          "tgn:1000001",
          "tgn:7012149",
          "tgn:2001869",
          "tgn:7007825",
          "tgn:7029392"
        ],
        "placetype": [
          "aat:300266640"
        ],
        "id": 2713186,
        "name:xx": "Taylor Ridge"
      }
    },
    {
      "geometry": {
        "type": "Point",
        "coordinates": [
          -85.2667,
          35.3167
        ]
      },
      "type": "Feature",
      "properties": {
        "hierarchy": [
          "tgn:2713187",
          "tgn:1000001",
          "tgn:7012149",
          "tgn:2001913",
          "tgn:7007825",
          "tgn:7029392"
        ],
        "placetype": [
          "aat:300266640"
        ],
        "id": 2713187,
        "name:xx": "Taylor Ridge"
      }
    },
    {
      "geometry": {
        "type": "Point",
        "coordinates": [
          -82.5167,
          36.3833
        ]
      },
      "type": "Feature",
      "properties": {
        "hierarchy": [
          "tgn:2713188",
          "tgn:1000001",
          "tgn:7012149",
          "tgn:2001926",
          "tgn:7007825",
          "tgn:7029392"
        ],
        "placetype": [
          "aat:300266640"
        ],
        "id": 2713188,
        "name:xx": "Taylor Ridge"
      }
    },
    {
      "geometry": {
        "type": "Point",
        "coordinates": [
          -82.0833,
          36.4333
        ]
      },
      "type": "Feature",
      "properties": {
        "hierarchy": [
          "tgn:2713189",
          "tgn:1000001",
          "tgn:7012149",
          "tgn:2001846",
          "tgn:7007825",
          "tgn:7029392"
        ],
        "placetype": [
          "aat:300266640"
        ],
        "id": 2713189,
        "name:xx": "Taylor Ridge"
      }
    }
  ]
}
