{
  "geometry": {
    "type": "Point",
    "coordinates": [
      -107.4833,
      35.9667
    ]
  },
  "type": "Feature",
  "properties": {
    "hierarchy": [
      "tgn:2600332",
      "tgn:1000001",
      "tgn:7012149",
      "tgn:7019676",
      "tgn:7007566",
      "tgn:7029392"
    ],
    "placetype": [
      "aat:300008699"
    ],
    "id": 2600332,
    "name:xx": "Pueblo Alto, Arroyo"
  }
}
