{
  "geometry": {
    "type": "Point",
    "coordinates": [
      -92.8333,
      32.0167
    ]
  },
  "type": "Feature",
  "properties": {
    "hierarchy": [
      "tgn:2421863",
      "tgn:1000001",
      "tgn:7012149",
      "tgn:2000917",
      "tgn:7007256",
      "tgn:7029392"
    ],
    "placetype": [
      "aat:300008699"
    ],
    "id": 2421863,
    "name:xx": "Jilks Branch"
  }
}
