{
  "geometry": {
    "type": "Point",
    "coordinates": [
      -112.4167,
      38.5167
    ]
  },
  "type": "Feature",
  "properties": {
    "hierarchy": [
      "tgn:2629321",
      "tgn:1000001",
      "tgn:7012149",
      "tgn:2002121",
      "tgn:7007827",
      "tgn:7029392"
    ],
    "placetype": [
      "aat:300008706"
    ],
    "id": 2629321,
    "name:xx": "Rosebud Creek"
  }
}
