{
  "geometry": {
    "type": "Point",
    "coordinates": [
      -145.6667,
      65.1833
    ]
  },
  "type": "Feature",
  "properties": {
    "hierarchy": [
      "tgn:2489383",
      "tgn:7006450",
      "tgn:1000001",
      "tgn:7012149",
      "tgn:2000089",
      "tgn:7029392"
    ],
    "placetype": [
      "aat:300008706"
    ],
    "id": 2489383,
    "name:xx": "Malburn Creek"
  }
}
