{
  "geometry": {
    "type": "Point",
    "coordinates": [
      45.2167,
      -12.9167
    ]
  },
  "type": "Feature",
  "properties": {
    "hierarchy": [
      "tgn:1091328",
      "tgn:7006226",
      "tgn:7001242",
      "tgn:7001669",
      "tgn:7029392"
    ],
    "placetype": [
      "aat:300008347"
    ],
    "id": 1091328,
    "name:xx": "Bandeli"
  }
}
