{
  "geometry": {
    "type": "Point",
    "coordinates": [
      79.122535,
      24.044087
    ]
  },
  "type": "Feature",
  "properties": {
    "hierarchy": [
      "tgn:7563562",
      "tgn:1000004",
      "tgn:7000198",
      "tgn:1001894",
      "tgn:7029392"
    ],
    "placetype": [
      "aat:300008347"
    ],
    "name:en": "Atāri",
    "id": 7563562
  }
}
