{
  "geometry": {
    "type": "Point",
    "coordinates": [
      -115.3667,
      41.7667
    ]
  },
  "type": "Feature",
  "properties": {
    "hierarchy": [
      "tgn:2419436",
      "tgn:1000001",
      "tgn:2001411",
      "tgn:7012149",
      "tgn:7007526",
      "tgn:7029392"
    ],
    "placetype": [
      "aat:300008680"
    ],
    "id": 2419436,
    "name:xx": "Jarbidge Lake"
  }
}
