{
  "geometry": {
    "type": "Point",
    "coordinates": [
      124.7667,
      6.3167
    ]
  },
  "type": "Feature",
  "properties": {
    "hierarchy": [
      "tgn:1084478",
      "tgn:1000004",
      "tgn:1001541",
      "tgn:1000135",
      "tgn:7029392"
    ],
    "placetype": [
      "aat:300008347"
    ],
    "id": 1084478,
    "name:xx": "Naci"
  }
}
