{
  "geometry": {
    "type": "Point",
    "coordinates": [
      30.383333,
      31.066667
    ]
  },
  "type": "Feature",
  "properties": {
    "hierarchy": [
      "tgn:7539186",
      "tgn:7001242",
      "tgn:1001075",
      "tgn:7016833",
      "tgn:7029392"
    ],
    "placetype": [
      "aat:300007783"
    ],
    "name:en": "Maḩaţţat Saḩālī",
    "id": 7539186
  }
}
