{
  "geometry": {
    "type": "Point",
    "coordinates": [
      -82.7833,
      37.9333
    ]
  },
  "type": "Feature",
  "properties": {
    "hierarchy": [
      "tgn:2625325",
      "tgn:1000001",
      "tgn:7012149",
      "tgn:7007255",
      "tgn:7029392"
    ],
    "placetype": [
      "aat:300008699"
    ],
    "id": 2625325,
    "name:xx": "Rockhouse Fork"
  }
}
