{
  "geometry": {
    "type": "Point",
    "coordinates": [
      -113.25,
      38.0833
    ]
  },
  "type": "Feature",
  "properties": {
    "hierarchy": [
      "tgn:2181834",
      "tgn:1000001",
      "tgn:7012149",
      "tgn:2002111",
      "tgn:7007827",
      "tgn:7029392"
    ],
    "placetype": [
      "aat:300008798"
    ],
    "id": 2181834,
    "name:xx": "Blue Knoll"
  }
}
