{
  "geometry": {
    "type": "Point",
    "coordinates": [
      -92.7667,
      35.3167
    ]
  },
  "type": "Feature",
  "properties": {
    "hierarchy": [
      "tgn:2760137",
      "tgn:1000001",
      "tgn:7016172",
      "tgn:2000119",
      "tgn:7012149",
      "tgn:7029392"
    ],
    "placetype": [
      "aat:300006191"
    ],
    "id": 2760137,
    "name:xx": "West Fork Point Remove Creek Site 15 Reservoir"
  }
}
