{
  "geometry": {
    "type": "Point",
    "coordinates": [
      -115.65,
      32.6667
    ]
  },
  "type": "Feature",
  "properties": {
    "hierarchy": [
      "tgn:2780902",
      "tgn:1000001",
      "tgn:7012149",
      "tgn:2000182",
      "tgn:7007157",
      "tgn:7029392"
    ],
    "placetype": [
      "aat:300006075"
    ],
    "id": 2780902,
    "name:xx": "Woodbine Lateral Seven"
  }
}
