{
  "type": "FeatureCollection",
  "features": [
    {
      "geometry": {
        "type": "Point",
        "coordinates": [
          -80.9167,
          38.4167
        ]
      },
      "type": "Feature",
      "properties": {
        "hierarchy": [
          "tgn:2701630",
          "tgn:1000001",
          "tgn:2002259",
          "tgn:7012149",
          "tgn:7013961",
          "tgn:7029392"
        ],
        "placetype": [
          "aat:300008699"
        ],
        "id": 2701630,
        "name:xx": "Sugarcamp Run"
      }
    },
    {
      "geometry": {
        "type": "Point",
        "coordinates": [
          -80.4,
          38.8167
        ]
      },
      "type": "Feature",
      "properties": {
        "hierarchy": [
          "tgn:2701631",
          "tgn:1000001",
          "tgn:7012149",
          "tgn:2002271",
          "tgn:7013961",
          "tgn:7029392"
        ],
        "placetype": [
          "aat:300008699"
        ],
        "id": 2701631,
        "name:xx": "Sugarcamp Run"
      }
    },
    {
      "geometry": {
        "type": "Point",
        "coordinates": [
          -81.15,
          38.9833
        ]
      },
      "type": "Feature",
      "properties": {
        "hierarchy": [
          "tgn:2701632",
          "tgn:1000001",
          "tgn:2002258",
          "tgn:7012149",
          "tgn:7013961",
          "tgn:7029392"
        ],
        "placetype": [
          "aat:300008699"
        ],
        "id": 2701632,
        "name:xx": "Sugarcamp Run"
      }
    },
    {
      "geometry": {
        "type": "Point",
        "coordinates": [
          -79.6833,
          39.0167
        ]
      },
      "type": "Feature",
      "properties": {
        "hierarchy": [
          "tgn:2701633",
          "tgn:1000001",
          "tgn:7012149",
          "tgn:2002296",
          "tgn:7013961",
          "tgn:7029392"
        ],
        "placetype": [
          "aat:300008699"
        ],
        "id": 2701633,
        "name:xx": "Sugarcamp Run"
      }
    },
    {
      "geometry": {
        "type": "Point",
        "coordinates": [
          -81.6167,
          39.0833
        ]
      },
      "type": "Feature",
      "properties": {
        "hierarchy": [
          "tgn:2701634",
          "tgn:1000001",
          "tgn:7012149",
          "tgn:2002303",
          "tgn:7013961",
          "tgn:7029392"
        ],
        "placetype": [
          "aat:300008699"
        ],
        "id": 2701634,
        "name:xx": "Sugarcamp Run"
      }
    },
    {
      "geometry": {
        "type": "Point",
        "coordinates": [
          -80.2333,
          39.3667
        ]
      },
      "type": "Feature",
      "properties": {
        "hierarchy": [
          "tgn:2701635",
          "tgn:1000001",
          "tgn:7012149",
          "tgn:2002267",
          "tgn:7013961",
          "tgn:7029392"
        ],
        "placetype": [
          "aat:300008699"
        ],
        "id": 2701635,
        "name:xx": "Sugarcamp Run"
      }
    },
    {
      "geometry": {
        "type": "Point",
        "coordinates": [
          -78.7833,
          39.4167
        ]
      },
      "type": "Feature",
      "properties": {
        "hierarchy": [
          "tgn:2701636",
          "tgn:1000001",
          "tgn:7012149",
          "tgn:2002279",
          "tgn:7013961",
          "tgn:7029392"
        ],
        "placetype": [
          "aat:300008699"
        ],
        "id": 2701636,
        "name:xx": "Sugarcamp Run"
      }
    },
    {
      "geometry": {
        "type": "Point",
        "coordinates": [
          -80.8667,
          38.85
        ]
      },
      "type": "Feature",
      "properties": {
        "hierarchy": [
          "tgn:2701638",
          "tgn:1000001",
          "tgn:2002262",
          "tgn:7012149",
          "tgn:7013961",
          "tgn:7029392"
        ],
        "placetype": [
          "aat:300008699"
        ],
        "id": 2701638,
        "name:xx": "Sugarcamp Run"
      }
    }
  ]
}
