{
  "geometry": {
    "type": "Point",
    "coordinates": [
      -79.15,
      41.9167
    ]
  },
  "type": "Feature",
  "properties": {
    "hierarchy": [
      "tgn:2142368",
      "tgn:1000001",
      "tgn:7012149",
      "tgn:1002988",
      "tgn:7007710",
      "tgn:7029392"
    ],
    "placetype": [
      "aat:300008347"
    ],
    "id": 2142368,
    "name:xx": "Backup Corners"
  }
}
