{
  "geometry": {
    "type": "Point",
    "coordinates": [
      -75.4833,
      42.7667
    ]
  },
  "type": "Feature",
  "properties": {
    "hierarchy": [
      "tgn:2592473",
      "tgn:1000001",
      "tgn:7012149",
      "tgn:1002624",
      "tgn:7007568",
      "tgn:7029392"
    ],
    "placetype": [
      "aat:300008680"
    ],
    "id": 2592473,
    "name:xx": "Poolville Pond"
  }
}
