{
  "geometry": {
    "type": "Point",
    "coordinates": [
      -94.1667,
      37.4167
    ]
  },
  "type": "Feature",
  "properties": {
    "hierarchy": [
      "tgn:2658963",
      "tgn:2001171",
      "tgn:1000001",
      "tgn:7012149",
      "tgn:7007523",
      "tgn:7029392"
    ],
    "placetype": [
      "aat:300008347"
    ],
    "id": 2658963,
    "name:xx": "Sherwood"
  }
}
