{
  "geometry": {
    "type": "Point",
    "coordinates": [
      76.261944,
      12.561944
    ]
  },
  "type": "Feature",
  "properties": {
    "hierarchy": [
      "tgn:7557415",
      "tgn:1000004",
      "tgn:7000198",
      "tgn:1001882",
      "tgn:7029392"
    ],
    "placetype": [
      "aat:300008347"
    ],
    "name:en": "Sāligrāma",
    "id": 7557415
  }
}
