{
  "geometry": {
    "type": "Point",
    "coordinates": [
      18.4167,
      53.4167
    ]
  },
  "type": "Feature",
  "properties": {
    "hierarchy": [
      "tgn:1048855",
      "tgn:7024116",
      "tgn:1000003",
      "tgn:7006366",
      "tgn:7029392"
    ],
    "placetype": [
      "aat:300008347"
    ],
    "id": 1048855,
    "name:xx": "Świecie"
  }
}
