{
  "geometry": {
    "type": "Point",
    "coordinates": [
      77.35,
      14.65
    ]
  },
  "type": "Feature",
  "properties": {
    "hierarchy": [
      "tgn:7547958",
      "tgn:1001828",
      "tgn:1000004",
      "tgn:7000198",
      "tgn:7029392"
    ],
    "placetype": [
      "aat:300008347"
    ],
    "name:en": "Atmakūru",
    "id": 7547958
  }
}
