{
  "geometry": {
    "type": "Point",
    "coordinates": [
      15.3333,
      -0.7667
    ]
  },
  "type": "Feature",
  "properties": {
    "hierarchy": [
      "tgn:1088618",
      "tgn:7001242",
      "tgn:1001028",
      "tgn:1000158",
      "tgn:7029392"
    ],
    "placetype": [
      "aat:300008347"
    ],
    "id": 1088618,
    "name:xx": "Djokoumatoumbi"
  }
}
