{
  "geometry": {
    "type": "Point",
    "coordinates": [
      -121.3833,
      47.4833
    ]
  },
  "type": "Feature",
  "properties": {
    "hierarchy": [
      "tgn:2354392",
      "tgn:1000001",
      "tgn:7012149",
      "tgn:7018871",
      "tgn:7007920",
      "tgn:7029392"
    ],
    "placetype": [
      "aat:300008697"
    ],
    "id": 2354392,
    "name:xx": "Goldmyer Hot Springs"
  }
}
