{
  "type": "FeatureCollection",
  "features": [
    {
      "geometry": {
        "type": "Point",
        "coordinates": [
          -92.0667,
          34.65
        ]
      },
      "type": "Feature",
      "properties": {
        "hierarchy": [
          "tgn:2373840",
          "tgn:1000001",
          "tgn:7016172",
          "tgn:7012149",
          "tgn:2000147",
          "tgn:7029392"
        ],
        "placetype": [
          "aat:300008347"
        ],
        "id": 2373840,
        "name:xx": "Hamiter"
      }
    },
    {
      "geometry": {
        "type": "Point",
        "coordinates": [
          -114.8833,
          37.9333
        ]
      },
      "type": "Feature",
      "properties": {
        "hierarchy": [
          "tgn:2373841",
          "tgn:1000001",
          "tgn:2001416",
          "tgn:7012149",
          "tgn:7007526",
          "tgn:7029392"
        ],
        "placetype": [
          "aat:300008697"
        ],
        "id": 2373841,
        "name:xx": "Hamiton Spring"
      }
    },
    {
      "geometry": {
        "type": "Point",
        "coordinates": [
          -92.3,
          35.0667
        ]
      },
      "type": "Feature",
      "properties": {
        "hierarchy": [
          "tgn:2373842",
          "tgn:1000001",
          "tgn:7016172",
          "tgn:7012149",
          "tgn:2000127",
          "tgn:7029392"
        ],
        "placetype": [
          "aat:300008347"
        ],
        "id": 2373842,
        "name:xx": "Hamlet"
      }
    },
    {
      "geometry": {
        "type": "Point",
        "coordinates": [
          -122.9167,
          38.2
        ]
      },
      "type": "Feature",
      "properties": {
        "hierarchy": [
          "tgn:2373843",
          "tgn:1000001",
          "tgn:7012149",
          "tgn:7007157",
          "tgn:7014005",
          "tgn:7029392"
        ],
        "placetype": [
          "aat:300008347"
        ],
        "id": 2373843,
        "name:xx": "Hamlet"
      }
    },
    {
      "geometry": {
        "type": "Point",
        "coordinates": [
          -104.0833,
          38.15
        ]
      },
      "type": "Feature",
      "properties": {
        "hierarchy": [
          "tgn:2373844",
          "tgn:1000001",
          "tgn:7012149",
          "tgn:7007158",
          "tgn:2000242",
          "tgn:7029392"
        ],
        "placetype": [
          "aat:300008347"
        ],
        "id": 2373844,
        "name:xx": "Hamlet"
      }
    },
    {
      "geometry": {
        "type": "Point",
        "coordinates": [
          -85.0833,
          34.0667
        ]
      },
      "type": "Feature",
      "properties": {
        "hierarchy": [
          "tgn:2373845",
          "tgn:1000001",
          "tgn:7012149",
          "tgn:2000406",
          "tgn:7007248",
          "tgn:7029392"
        ],
        "placetype": [
          "aat:300008347"
        ],
        "id": 2373845,
        "name:xx": "Hamlet"
      }
    },
    {
      "geometry": {
        "type": "Point",
        "coordinates": [
          -86.5667,
          41.5333
        ]
      },
      "type": "Feature",
      "properties": {
        "hierarchy": [
          "tgn:2373846",
          "tgn:1000001",
          "tgn:7012149",
          "tgn:1002918",
          "tgn:7007252",
          "tgn:7029392"
        ],
        "placetype": [
          "aat:300008347"
        ],
        "id": 2373846,
        "name:xx": "Hamlet"
      }
    },
    {
      "geometry": {
        "type": "Point",
        "coordinates": [
          -89.2667,
          32.0167
        ]
      },
      "type": "Feature",
      "properties": {
        "hierarchy": [
          "tgn:2373847",
          "tgn:1000001",
          "tgn:7012149",
          "tgn:2001116",
          "tgn:7007522",
          "tgn:7029392"
        ],
        "placetype": [
          "aat:300008347"
        ],
        "id": 2373847,
        "name:xx": "Hamlet"
      }
    },
    {
      "geometry": {
        "type": "Point",
        "coordinates": [
          -93.6333,
          37.75
        ]
      },
      "type": "Feature",
      "properties": {
        "hierarchy": [
          "tgn:2373848",
          "tgn:1000001",
          "tgn:2001183",
          "tgn:7012149",
          "tgn:7007523",
          "tgn:7029392"
        ],
        "placetype": [
          "aat:300008347"
        ],
        "id": 2373848,
        "name:xx": "Hamlet"
      }
    },
    {
      "geometry": {
        "type": "Point",
        "coordinates": [
          -123.6833,
          45.8333
        ]
      },
      "type": "Feature",
      "properties": {
        "hierarchy": [
          "tgn:2373849",
          "tgn:1000001",
          "tgn:1002276",
          "tgn:7012149",
          "tgn:7007708",
          "tgn:7029392"
        ],
        "placetype": [
          "aat:300008347"
        ],
        "id": 2373849,
        "name:xx": "Hamlet"
      }
    }
  ]
}
