{
  "geometry": {
    "type": "Point",
    "coordinates": [
      -97.0667,
      46.2167
    ]
  },
  "type": "Feature",
  "properties": {
    "hierarchy": [
      "tgn:2077863",
      "tgn:1000001",
      "tgn:2001595",
      "tgn:7012149",
      "tgn:7007705",
      "tgn:7029392"
    ],
    "placetype": [
      "aat:300387016"
    ],
    "id": 2077863,
    "name:xx": "Moselle"
  }
}
