{
  "geometry": {
    "type": "Point",
    "coordinates": [
      -86.5333,
      39.3333
    ]
  },
  "type": "Feature",
  "properties": {
    "hierarchy": [
      "tgn:2588891",
      "tgn:1000001",
      "tgn:7012149",
      "tgn:7007252",
      "tgn:7029392"
    ],
    "placetype": [
      "aat:300008761"
    ],
    "id": 2588891,
    "name:xx": "Pocket Hollow"
  }
}
