{
  "type": "FeatureCollection",
  "features": [
    {
      "geometry": {
        "type": "Point",
        "coordinates": [
          -82.7333,
          28.9833
        ]
      },
      "type": "Feature",
      "properties": {
        "hierarchy": [
          "tgn:2209980",
          "tgn:1000001",
          "tgn:1002269",
          "tgn:7012149",
          "tgn:7007240",
          "tgn:7029392"
        ],
        "placetype": [
          "aat:300008791"
        ],
        "id": 2209980,
        "name:xx": "Burtine Island"
      }
    },
    {
      "geometry": {
        "type": "Point",
        "coordinates": [
          -79.2833,
          42.1
        ]
      },
      "type": "Feature",
      "properties": {
        "hierarchy": [
          "tgn:2209981",
          "tgn:1000001",
          "tgn:1002259",
          "tgn:7012149",
          "tgn:7007568",
          "tgn:7029392"
        ],
        "placetype": [
          "aat:300132316"
        ],
        "id": 2209981,
        "name:xx": "Burtis Bay"
      }
    },
    {
      "geometry": {
        "type": "Point",
        "coordinates": [
          -76.5,
          42.85
        ]
      },
      "type": "Feature",
      "properties": {
        "hierarchy": [
          "tgn:2209982",
          "tgn:1000001",
          "tgn:1002246",
          "tgn:7012149",
          "tgn:7007568",
          "tgn:7029392"
        ],
        "placetype": [
          "aat:300008850"
        ],
        "id": 2209982,
        "name:xx": "Burtis Point"
      }
    },
    {
      "geometry": {
        "type": "Point",
        "coordinates": [
          -110.1333,
          34.3167
        ]
      },
      "type": "Feature",
      "properties": {
        "hierarchy": [
          "tgn:2209983",
          "tgn:1000001",
          "tgn:7006451",
          "tgn:7012149",
          "tgn:2000099",
          "tgn:7029392"
        ],
        "placetype": [
          "aat:300008347"
        ],
        "id": 2209983,
        "name:xx": "Burton"
      }
    },
    {
      "geometry": {
        "type": "Point",
        "coordinates": [
          -89.85,
          35.9167
        ]
      },
      "type": "Feature",
      "properties": {
        "hierarchy": [
          "tgn:2209984",
          "tgn:1000001",
          "tgn:7016172",
          "tgn:7012149",
          "tgn:2000151",
          "tgn:7029392"
        ],
        "placetype": [
          "aat:300008347"
        ],
        "id": 2209984,
        "name:xx": "Burton"
      }
    },
    {
      "geometry": {
        "type": "Point",
        "coordinates": [
          -90.8667,
          30
        ]
      },
      "type": "Feature",
      "properties": {
        "hierarchy": [
          "tgn:2209985",
          "tgn:1000001",
          "tgn:7012149",
          "tgn:2000900",
          "tgn:7007256",
          "tgn:7029392"
        ],
        "placetype": [
          "aat:300008347"
        ],
        "id": 2209985,
        "name:xx": "Burton"
      }
    },
    {
      "geometry": {
        "type": "Point",
        "coordinates": [
          -88.3333,
          34.6333
        ]
      },
      "type": "Feature",
      "properties": {
        "hierarchy": [
          "tgn:2209986",
          "tgn:1000001",
          "tgn:7012149",
          "tgn:2001144",
          "tgn:7007522",
          "tgn:7029392"
        ],
        "placetype": [
          "aat:300008347"
        ],
        "id": 2209986,
        "name:xx": "Burton"
      }
    },
    {
      "geometry": {
        "type": "Point",
        "coordinates": [
          -78.8167,
          36.0333
        ]
      },
      "type": "Feature",
      "properties": {
        "hierarchy": [
          "tgn:2209987",
          "tgn:1000001",
          "tgn:7012149",
          "tgn:2001492",
          "tgn:7007709",
          "tgn:7029392"
        ],
        "placetype": [
          "aat:300008347"
        ],
        "id": 2209987,
        "name:xx": "Burton"
      }
    },
    {
      "geometry": {
        "type": "Point",
        "coordinates": [
          -102.15,
          36.7833
        ]
      },
      "type": "Feature",
      "properties": {
        "hierarchy": [
          "tgn:2209988",
          "tgn:1000001",
          "tgn:2001635",
          "tgn:7012149",
          "tgn:7007707",
          "tgn:7029392"
        ],
        "placetype": [
          "aat:300008347"
        ],
        "id": 2209988,
        "name:xx": "Burton"
      }
    },
    {
      "geometry": {
        "type": "Point",
        "coordinates": [
          -85.65,
          36.05
        ]
      },
      "type": "Feature",
      "properties": {
        "hierarchy": [
          "tgn:2209989",
          "tgn:1000001",
          "tgn:7012149",
          "tgn:2001907",
          "tgn:7007825",
          "tgn:7029392"
        ],
        "placetype": [
          "aat:300008347"
        ],
        "id": 2209989,
        "name:xx": "Burton"
      }
    }
  ]
}
