{
  "type": "FeatureCollection",
  "features": [
    {
      "geometry": {
        "type": "Point",
        "coordinates": [
          174.3,
          -41.716667
        ]
      },
      "type": "Feature",
      "properties": {
        "hierarchy": [
          "tgn:7505170",
          "tgn:1009227",
          "tgn:1000226",
          "tgn:7016729",
          "tgn:1000006",
          "tgn:7029392"
        ],
        "placetype": [
          "aat:300008808"
        ],
        "name:en": "Bowlers Reef",
        "id": 7505170
      }
    },
    {
      "geometry": {
        "type": "Point",
        "coordinates": [
          176.3,
          -38.5
        ]
      },
      "type": "Feature",
      "properties": {
        "hierarchy": [
          "tgn:7505172",
          "tgn:7000509",
          "tgn:1008380",
          "tgn:1000226",
          "tgn:1000006",
          "tgn:7029392"
        ],
        "placetype": [
          "aat:300008347"
        ],
        "name:en": "Tahorakui",
        "id": 7505172
      }
    },
    {
      "geometry": {
        "type": "Point",
        "coordinates": [
          173.6,
          -41.516667
        ]
      },
      "type": "Feature",
      "properties": {
        "hierarchy": [
          "tgn:7505174",
          "tgn:1009227",
          "tgn:1000226",
          "tgn:7016729",
          "tgn:1000006",
          "tgn:7029392"
        ],
        "placetype": [
          "aat:300008699"
        ],
        "name:en": "Bartlett Creek",
        "id": 7505174
      }
    },
    {
      "geometry": {
        "type": "Point",
        "coordinates": [
          177.883333,
          -38.85
        ]
      },
      "type": "Feature",
      "properties": {
        "hierarchy": [
          "tgn:7505175",
          "tgn:7520092",
          "tgn:1008380",
          "tgn:1000226",
          "tgn:1000006",
          "tgn:7029392"
        ],
        "placetype": [
          "aat:300008347"
        ],
        "name:en": "Bartlett",
        "id": 7505175
      }
    },
    {
      "geometry": {
        "type": "Point",
        "coordinates": [
          168.233333,
          -44.45
        ]
      },
      "type": "Feature",
      "properties": {
        "hierarchy": [
          "tgn:7505176",
          "tgn:1009227",
          "tgn:1000226",
          "tgn:7016822",
          "tgn:1000006",
          "tgn:7029392"
        ],
        "placetype": [
          "aat:300008699"
        ],
        "name:en": "Barrier Branch",
        "id": 7505176
      }
    },
    {
      "geometry": {
        "type": "Point",
        "coordinates": [
          174.433333,
          -39.683333
        ]
      },
      "type": "Feature",
      "properties": {
        "hierarchy": [
          "tgn:7505177",
          "tgn:1008380",
          "tgn:1000226",
          "tgn:7016827",
          "tgn:1000006",
          "tgn:7029392"
        ],
        "placetype": [
          "aat:300007783"
        ],
        "name:en": "Ball Road",
        "id": 7505177
      }
    },
    {
      "geometry": {
        "type": "Point",
        "coordinates": [
          177.05,
          -39.05
        ]
      },
      "type": "Feature",
      "properties": {
        "hierarchy": [
          "tgn:7505178",
          "tgn:7016670",
          "tgn:1008380",
          "tgn:1000226",
          "tgn:1000006",
          "tgn:7029392"
        ],
        "placetype": [
          "aat:300008699"
        ],
        "name:en": "Arawhata Stream",
        "id": 7505178
      }
    },
    {
      "geometry": {
        "type": "Point",
        "coordinates": [
          173.7,
          -41.033333
        ]
      },
      "type": "Feature",
      "properties": {
        "hierarchy": [
          "tgn:7505179",
          "tgn:1009227",
          "tgn:1000226",
          "tgn:7016729",
          "tgn:1000006",
          "tgn:7029392"
        ],
        "placetype": [
          "aat:300008795"
        ],
        "name:en": "Askew Hill",
        "id": 7505179
      }
    }
  ]
}
