{
  "geometry": {
    "type": "Point",
    "coordinates": [
      13.9833,
      49.9333
    ]
  },
  "type": "Feature",
  "properties": {
    "hierarchy": [
      "tgn:1027669",
      "tgn:1003530",
      "tgn:1000003",
      "tgn:1001780",
      "tgn:7029392"
    ],
    "placetype": [
      "aat:300008347"
    ],
    "id": 1027669,
    "name:xx": "Zdice"
  }
}
