{
  "geometry": {
    "type": "Point",
    "coordinates": [
      47.0167,
      49.5833
    ]
  },
  "type": "Feature",
  "properties": {
    "hierarchy": [
      "tgn:1055597",
      "tgn:1000004",
      "tgn:7011457",
      "tgn:7014786",
      "tgn:7029392"
    ],
    "placetype": [
      "aat:300008347"
    ],
    "id": 1055597,
    "name:xx": "Konyrat"
  }
}
