{
  "geometry": {
    "type": "Point",
    "coordinates": [
      -108.35,
      33.4667
    ]
  },
  "type": "Feature",
  "properties": {
    "hierarchy": [
      "tgn:2508359",
      "tgn:1000001",
      "tgn:2001429",
      "tgn:7012149",
      "tgn:7007566",
      "tgn:7029392"
    ],
    "placetype": [
      "aat:300006191"
    ],
    "id": 2508359,
    "name:xx": "Middle Canyon Creek Tank"
  }
}
