{
  "geometry": {
    "type": "Point",
    "coordinates": [
      -103.7833,
      30.7667
    ]
  },
  "type": "Feature",
  "properties": {
    "hierarchy": [
      "tgn:2691469",
      "tgn:1000001",
      "tgn:7012149",
      "tgn:2002010",
      "tgn:7007826",
      "tgn:7029392"
    ],
    "placetype": [
      "aat:300008798"
    ],
    "id": 2691469,
    "name:xx": "Star Mountain"
  }
}
