{
  "geometry": {
    "type": "Point",
    "coordinates": [
      11.3667,
      32.7333
    ]
  },
  "type": "Feature",
  "properties": {
    "hierarchy": [
      "tgn:1094910",
      "tgn:7001242",
      "tgn:1002091",
      "tgn:1000205",
      "tgn:7029392"
    ],
    "placetype": [
      "aat:300008347"
    ],
    "id": 1094910,
    "name:xx": "Burj Sīdī aṭ Ṭawī"
  }
}
