{
  "type": "FeatureCollection",
  "features": [
    {
      "geometry": {
        "type": "Point",
        "coordinates": [
          -61.6667,
          16.1667
        ]
      },
      "type": "Feature",
      "properties": {
        "hierarchy": [
          "tgn:1006440",
          "tgn:7018312",
          "tgn:1000001",
          "tgn:7004545",
          "tgn:7029392"
        ],
        "placetype": [
          "aat:300008791"
        ],
        "id": 1006440,
        "name:xx": "Basse Terre"
      }
    },
    {
      "geometry": {
        "type": "Point",
        "coordinates": [
          -82.1667,
          9.3667
        ]
      },
      "type": "Feature",
      "properties": {
        "hierarchy": [
          "tgn:1006441",
          "tgn:1001153",
          "tgn:1009886",
          "tgn:1000001",
          "tgn:7005565",
          "tgn:7029392"
        ],
        "placetype": [
          "aat:300008791"
        ],
        "id": 1006441,
        "name:xx": "Bastimentos"
      }
    },
    {
      "geometry": {
        "type": "Point",
        "coordinates": [
          124.3667,
          12.6667
        ]
      },
      "type": "Feature",
      "properties": {
        "hierarchy": [
          "tgn:1006443",
          "tgn:1000004",
          "tgn:1001462",
          "tgn:1000135",
          "tgn:7029392"
        ],
        "placetype": [
          "aat:300008791"
        ],
        "id": 1006443,
        "name:xx": "Batag Island"
      }
    },
    {
      "geometry": {
        "type": "Point",
        "coordinates": [
          123.7833,
          13.25
        ]
      },
      "type": "Feature",
      "properties": {
        "hierarchy": [
          "tgn:1006445",
          "tgn:1001094",
          "tgn:1000004",
          "tgn:1000135",
          "tgn:7029392"
        ],
        "placetype": [
          "aat:300008791"
        ],
        "id": 1006445,
        "name:xx": "Batan Island"
      }
    },
    {
      "geometry": {
        "type": "Point",
        "coordinates": [
          119.6,
          11.1667
        ]
      },
      "type": "Feature",
      "properties": {
        "hierarchy": [
          "tgn:1006447",
          "tgn:1000004",
          "tgn:1001481",
          "tgn:1000135",
          "tgn:7029392"
        ],
        "placetype": [
          "aat:300008791"
        ],
        "id": 1006447,
        "name:xx": "Batas Island"
      }
    },
    {
      "geometry": {
        "type": "Point",
        "coordinates": [
          121.9333,
          11.5
        ]
      },
      "type": "Feature",
      "properties": {
        "hierarchy": [
          "tgn:1006448",
          "tgn:1001104",
          "tgn:1000004",
          "tgn:1000135",
          "tgn:7029392"
        ],
        "placetype": [
          "aat:300008791"
        ],
        "id": 1006448,
        "name:xx": "Batbatan Island"
      }
    },
    {
      "geometry": {
        "type": "Point",
        "coordinates": [
          -84.5,
          46.8833
        ]
      },
      "type": "Feature",
      "properties": {
        "hierarchy": [
          "tgn:1006449",
          "tgn:7005685",
          "tgn:1000001",
          "tgn:7013154",
          "tgn:7029392"
        ],
        "placetype": [
          "aat:300008791"
        ],
        "id": 1006449,
        "name:xx": "Batchawana Island"
      }
    }
  ]
}
