{
  "geometry": {
    "type": "Point",
    "coordinates": [
      -122.8167,
      45.0333
    ]
  },
  "type": "Feature",
  "properties": {
    "hierarchy": [
      "tgn:2124443",
      "tgn:1000001",
      "tgn:7012149",
      "tgn:1002636",
      "tgn:7007708",
      "tgn:7029392"
    ],
    "placetype": [
      "aat:300006191"
    ],
    "id": 2124443,
    "name:xx": "Aarhus Reservoir"
  }
}
