{
  "geometry": {
    "type": "Point",
    "coordinates": [
      -74.85,
      44.5833
    ]
  },
  "type": "Feature",
  "properties": {
    "hierarchy": [
      "tgn:2637461",
      "tgn:1000001",
      "tgn:7012149",
      "tgn:7016021",
      "tgn:7007568",
      "tgn:7029392"
    ],
    "placetype": [
      "aat:300008863"
    ],
    "id": 2637461,
    "name:xx": "Saint Lawrence State Forest"
  }
}
