{
  "geometry": {
    "type": "Point",
    "coordinates": [
      -86.7167,
      34.8167
    ]
  },
  "type": "Feature",
  "properties": {
    "hierarchy": [
      "tgn:2452858",
      "tgn:7002659",
      "tgn:1000001",
      "tgn:7012149",
      "tgn:2000044",
      "tgn:7029392"
    ],
    "placetype": [
      "aat:300008798"
    ],
    "id": 2452858,
    "name:xx": "Little Burwell Mountain"
  }
}
