{
  "geometry": {
    "type": "Point",
    "coordinates": [
      -82.7167,
      32.3667
    ]
  },
  "type": "Feature",
  "properties": {
    "hierarchy": [
      "tgn:2565907",
      "tgn:1000001",
      "tgn:7012149",
      "tgn:2000378",
      "tgn:7007248",
      "tgn:7029392"
    ],
    "placetype": [
      "aat:300006191"
    ],
    "id": 2565907,
    "name:xx": "Palm Lake"
  }
}
