{
  "geometry": {
    "type": "Point",
    "coordinates": [
      -80.6667,
      38.5833
    ]
  },
  "type": "Feature",
  "properties": {
    "hierarchy": [
      "tgn:2328567",
      "tgn:1000001",
      "tgn:2002256",
      "tgn:7012149",
      "tgn:7013961",
      "tgn:7029392"
    ],
    "placetype": [
      "aat:300008699"
    ],
    "id": 2328567,
    "name:xx": "Fisher Run"
  }
}
