{
  "geometry": {
    "type": "Point",
    "coordinates": [
      -86.4833,
      33.9667
    ]
  },
  "type": "Feature",
  "properties": {
    "hierarchy": [
      "tgn:2767642",
      "tgn:7002659",
      "tgn:1000001",
      "tgn:2000004",
      "tgn:7012149",
      "tgn:7029392"
    ],
    "placetype": [
      "aat:300006191"
    ],
    "id": 2767642,
    "name:xx": "Whited Lake"
  }
}
