{
  "geometry": {
    "type": "Point",
    "coordinates": [
      121.0833,
      41.5667
    ]
  },
  "type": "Feature",
  "properties": {
    "hierarchy": [
      "tgn:1140085",
      "tgn:1000004",
      "tgn:1001390",
      "tgn:1000111",
      "tgn:7029392"
    ],
    "placetype": [
      "aat:300008347"
    ],
    "id": 1140085,
    "name:xx": "Zhoujiatun"
  }
}
