{
  "geometry": {
    "type": "Point",
    "coordinates": [
      -99.1667,
      32.5333
    ]
  },
  "type": "Feature",
  "properties": {
    "hierarchy": [
      "tgn:2523816",
      "tgn:1000001",
      "tgn:7012149",
      "tgn:2002072",
      "tgn:7007826",
      "tgn:7029392"
    ],
    "placetype": [
      "aat:300006191"
    ],
    "id": 2523816,
    "name:xx": "Moran Lake"
  }
}
