{
  "geometry": {
    "type": "Point",
    "coordinates": [
      26.0167,
      54.7333
    ]
  },
  "type": "Feature",
  "properties": {
    "hierarchy": [
      "tgn:1061350",
      "tgn:7012158",
      "tgn:1000003",
      "tgn:7006657",
      "tgn:7029392"
    ],
    "placetype": [
      "aat:300008347"
    ],
    "id": 1061350,
    "name:xx": "Vorn'any"
  }
}
