{
  "geometry": {
    "type": "Point",
    "coordinates": [
      -107.0667,
      44.7833
    ]
  },
  "type": "Feature",
  "properties": {
    "hierarchy": [
      "tgn:2130469",
      "tgn:1000001",
      "tgn:7012149",
      "tgn:2002381",
      "tgn:7007923",
      "tgn:7029392"
    ],
    "placetype": [
      "aat:300006075"
    ],
    "id": 2130469,
    "name:xx": "Alliance Lateral"
  }
}
