{
  "geometry": {
    "type": "Point",
    "coordinates": [
      29.15,
      70.8333
    ]
  },
  "type": "Feature",
  "properties": {
    "hierarchy": [
      "tgn:1048481",
      "tgn:7003642",
      "tgn:1000003",
      "tgn:1000088",
      "tgn:7029392"
    ],
    "placetype": [
      "aat:300008347"
    ],
    "id": 1048481,
    "name:xx": "Berlevåg"
  }
}
