{
  "geometry": {
    "type": "Point",
    "coordinates": [
      173.4167,
      52.8333
    ]
  },
  "type": "Feature",
  "properties": {
    "hierarchy": [
      "tgn:2201242",
      "tgn:7030516",
      "tgn:7006450",
      "tgn:1000001",
      "tgn:7012149",
      "tgn:7029392"
    ],
    "placetype": [
      "aat:300008850"
    ],
    "id": 2201242,
    "name:xx": "Buchanan Point"
  }
}
