{
  "geometry": {
    "type": "Point",
    "coordinates": [
      -110.8833,
      43.3833
    ]
  },
  "type": "Feature",
  "properties": {
    "hierarchy": [
      "tgn:2713100",
      "tgn:1000001",
      "tgn:7012149",
      "tgn:2002384",
      "tgn:7007923",
      "tgn:7029392"
    ],
    "placetype": [
      "aat:300008798"
    ],
    "id": 2713100,
    "name:xx": "Taylor Mountain"
  }
}
