{
  "geometry": {
    "type": "Point",
    "coordinates": [
      -91.9333,
      44.4167
    ]
  },
  "type": "Feature",
  "properties": {
    "hierarchy": [
      "tgn:2281844",
      "tgn:1000001",
      "tgn:2002310",
      "tgn:7012149",
      "tgn:7007922",
      "tgn:7029392"
    ],
    "placetype": [
      "aat:300008706"
    ],
    "id": 2281844,
    "name:xx": "Deer Creek"
  }
}
