{
  "geometry": {
    "type": "Point",
    "coordinates": [
      9.65,
      48.566667
    ]
  },
  "type": "Feature",
  "properties": {
    "hierarchy": [
      "tgn:7135229",
      "tgn:7003692",
      "tgn:1000003",
      "tgn:7000084",
      "tgn:7029392"
    ],
    "placetype": [
      "aat:300008347"
    ],
    "id": 7135229,
    "name:xx": "Mühlhausen"
  }
}
