{
  "type": "FeatureCollection",
  "features": [
    {
      "geometry": {
        "type": "Point",
        "coordinates": [
          -9.3,
          38.75
        ]
      },
      "type": "Feature",
      "properties": {
        "hierarchy": [
          "tgn:1107941",
          "tgn:1000882",
          "tgn:1000003",
          "tgn:1000090",
          "tgn:7029392"
        ],
        "placetype": [
          "aat:300008777"
        ],
        "id": 1107941,
        "name:xx": "Cotão"
      }
    },
    {
      "geometry": {
        "type": "Point",
        "coordinates": [
          -5.966667,
          54.333333
        ]
      },
      "type": "Feature",
      "properties": {
        "hierarchy": [
          "tgn:1107943",
          "tgn:7002448",
          "tgn:7008698",
          "tgn:1000003",
          "tgn:7008591",
          "tgn:7029392"
        ],
        "placetype": [
          "aat:300008777",
          "aat:300008795"
        ],
        "name:en": "Croob, Slieve",
        "id": 1107943
      }
    },
    {
      "geometry": {
        "type": "Point",
        "coordinates": [
          -1.9667,
          53.7
        ]
      },
      "type": "Feature",
      "properties": {
        "hierarchy": [
          "tgn:1107944",
          "tgn:1003573",
          "tgn:7002445",
          "tgn:1000003",
          "tgn:7029507",
          "tgn:7008591",
          "tgn:7029392"
        ],
        "placetype": [
          "aat:300008777"
        ],
        "id": 1107944,
        "name:xx": "Crow Hill"
      }
    },
    {
      "geometry": {
        "type": "Point",
        "coordinates": [
          -73.8667,
          -0.4667
        ]
      },
      "type": "Feature",
      "properties": {
        "hierarchy": [
          "tgn:1107945",
          "tgn:1002071",
          "tgn:1000050",
          "tgn:1000002",
          "tgn:7029392"
        ],
        "placetype": [
          "aat:300008777"
        ],
        "id": 1107945,
        "name:xx": "Cumare, Cerro"
      }
    },
    {
      "geometry": {
        "type": "Point",
        "coordinates": [
          -66.8333,
          -0.3833
        ]
      },
      "type": "Feature",
      "properties": {
        "hierarchy": [
          "tgn:1107946",
          "tgn:1001826",
          "tgn:1000047",
          "tgn:7002456",
          "tgn:1000002",
          "tgn:7029392"
        ],
        "placetype": [
          "aat:300008777"
        ],
        "id": 1107946,
        "name:xx": "Curicuriari, Serra"
      }
    },
    {
      "geometry": {
        "type": "Point",
        "coordinates": [
          26.9667,
          57.5
        ]
      },
      "type": "Feature",
      "properties": {
        "hierarchy": [
          "tgn:1107947",
          "tgn:7012152",
          "tgn:1000003",
          "tgn:7006541",
          "tgn:7029392"
        ],
        "placetype": [
          "aat:300008777"
        ],
        "id": 1107947,
        "name:xx": "Dēlinkalns"
      }
    },
    {
      "geometry": {
        "type": "Point",
        "coordinates": [
          36.05,
          32.6
        ]
      },
      "type": "Feature",
      "properties": {
        "hierarchy": [
          "tgn:1107948",
          "tgn:1002074",
          "tgn:1000004",
          "tgn:1000140",
          "tgn:7029392"
        ],
        "placetype": [
          "aat:300008777"
        ],
        "id": 1107948,
        "name:xx": "Daḥdāḥ, Tall"
      }
    },
    {
      "geometry": {
        "type": "Point",
        "coordinates": [
          6.5,
          51.5
        ]
      },
      "type": "Feature",
      "properties": {
        "hierarchy": [
          "tgn:1107949",
          "tgn:1000003",
          "tgn:7003677",
          "tgn:7000084",
          "tgn:7029392"
        ],
        "placetype": [
          "aat:300008777"
        ],
        "id": 1107949,
        "name:xx": "Dachsberg"
      }
    }
  ]
}
