{
  "geometry": {
    "type": "Point",
    "coordinates": [
      -78.4333,
      34.3833
    ]
  },
  "type": "Feature",
  "properties": {
    "hierarchy": [
      "tgn:2644890",
      "tgn:1000001",
      "tgn:2001471",
      "tgn:7012149",
      "tgn:7007709",
      "tgn:7029392"
    ],
    "placetype": [
      "aat:300008905"
    ],
    "id": 2644890,
    "name:xx": "Sasspan Bay"
  }
}
