{
  "geometry": {
    "type": "Point",
    "coordinates": [
      33.2667,
      19.4667
    ]
  },
  "type": "Feature",
  "properties": {
    "hierarchy": [
      "tgn:1008186",
      "tgn:7001242",
      "tgn:1000201",
      "tgn:1001097",
      "tgn:7029392"
    ],
    "placetype": [
      "aat:300008791"
    ],
    "id": 1008186,
    "name:xx": "Mograt Island"
  }
}
