{
  "geometry": {
    "type": "Point",
    "coordinates": [
      -112.1167,
      45.7167
    ]
  },
  "type": "Feature",
  "properties": {
    "hierarchy": [
      "tgn:2654763",
      "tgn:1000001",
      "tgn:7012149",
      "tgn:2001288",
      "tgn:7007524",
      "tgn:7029392"
    ],
    "placetype": [
      "aat:300008697"
    ],
    "id": 2654763,
    "name:xx": "Shaky Spring"
  }
}
