{
  "type": "FeatureCollection",
  "features": [
    {
      "geometry": {
        "type": "Point",
        "coordinates": [
          -105.65,
          28.883333
        ]
      },
      "type": "Feature",
      "properties": {
        "hierarchy": [
          "tgn:7434820",
          "tgn:7005581",
          "tgn:1000001",
          "tgn:7005560",
          "tgn:7029392"
        ],
        "placetype": [
          "aat:300007783"
        ],
        "id": 7434820,
        "name:xx": "Trancas"
      }
    },
    {
      "geometry": {
        "type": "Point",
        "coordinates": [
          -101.033333,
          21.283333
        ]
      },
      "type": "Feature",
      "properties": {
        "hierarchy": [
          "tgn:7434821",
          "tgn:7005584",
          "tgn:1000001",
          "tgn:7005560",
          "tgn:7029392"
        ],
        "placetype": [
          "aat:300007783"
        ],
        "id": 7434821,
        "name:xx": "Trancas"
      }
    },
    {
      "geometry": {
        "type": "Point",
        "coordinates": [
          -103.25,
          20.783333
        ]
      },
      "type": "Feature",
      "properties": {
        "hierarchy": [
          "tgn:7434822",
          "tgn:7005586",
          "tgn:1000001",
          "tgn:7005560",
          "tgn:7029392"
        ],
        "placetype": [
          "aat:300000241"
        ],
        "id": 7434822,
        "name:xx": "Trancas"
      }
    },
    {
      "geometry": {
        "type": "Point",
        "coordinates": [
          -99.533333,
          27.55
        ]
      },
      "type": "Feature",
      "properties": {
        "hierarchy": [
          "tgn:7434823",
          "tgn:1000001",
          "tgn:7005597",
          "tgn:7005560",
          "tgn:7029392"
        ],
        "placetype": [
          "aat:300008347"
        ],
        "id": 7434823,
        "name:xx": "Trancas"
      }
    },
    {
      "geometry": {
        "type": "Point",
        "coordinates": [
          -98.783333,
          23.083333
        ]
      },
      "type": "Feature",
      "properties": {
        "hierarchy": [
          "tgn:7434824",
          "tgn:1000001",
          "tgn:7005597",
          "tgn:7005560",
          "tgn:7029392"
        ],
        "placetype": [
          "aat:300008347"
        ],
        "id": 7434824,
        "name:xx": "Trancas"
      }
    },
    {
      "geometry": {
        "type": "Point",
        "coordinates": [
          -101.016667,
          21.25
        ]
      },
      "type": "Feature",
      "properties": {
        "hierarchy": [
          "tgn:7434825",
          "tgn:7005584",
          "tgn:1000001",
          "tgn:7005560",
          "tgn:7029392"
        ],
        "placetype": [
          "aat:300008347"
        ],
        "id": 7434825,
        "name:xx": "Trancas"
      }
    },
    {
      "geometry": {
        "type": "Point",
        "coordinates": [
          -94.416667,
          16.283333
        ]
      },
      "type": "Feature",
      "properties": {
        "hierarchy": [
          "tgn:7434827",
          "tgn:1000001",
          "tgn:7005591",
          "tgn:7005560",
          "tgn:7029392"
        ],
        "placetype": [
          "aat:300008347"
        ],
        "id": 7434827,
        "name:xx": "Trancas"
      }
    },
    {
      "geometry": {
        "type": "Point",
        "coordinates": [
          -96.633333,
          16.1
        ]
      },
      "type": "Feature",
      "properties": {
        "hierarchy": [
          "tgn:7434828",
          "tgn:1000001",
          "tgn:7005591",
          "tgn:7005560",
          "tgn:7029392"
        ],
        "placetype": [
          "aat:300008347"
        ],
        "id": 7434828,
        "name:xx": "Trancas"
      }
    },
    {
      "geometry": {
        "type": "Point",
        "coordinates": [
          -96.416667,
          15.933333
        ]
      },
      "type": "Feature",
      "properties": {
        "hierarchy": [
          "tgn:7434829",
          "tgn:1000001",
          "tgn:7005591",
          "tgn:7005560",
          "tgn:7029392"
        ],
        "placetype": [
          "aat:300008347"
        ],
        "id": 7434829,
        "name:xx": "Trancas"
      }
    }
  ]
}
