{
  "geometry": {
    "type": "Point",
    "coordinates": [
      -84.4333,
      42.15
    ]
  },
  "type": "Feature",
  "properties": {
    "hierarchy": [
      "tgn:2655464",
      "tgn:1000001",
      "tgn:7012149",
      "tgn:1002509",
      "tgn:7007520",
      "tgn:7029392"
    ],
    "placetype": [
      "aat:300008706"
    ],
    "id": 2655464,
    "name:xx": "Sharp Creek"
  }
}
