{
  "geometry": {
    "type": "Point",
    "coordinates": [
      -121.9167,
      45.6833
    ]
  },
  "type": "Feature",
  "properties": {
    "hierarchy": [
      "tgn:2485797",
      "tgn:1000001",
      "tgn:7012149",
      "tgn:1002897",
      "tgn:7007920",
      "tgn:7029392"
    ],
    "placetype": [
      "aat:300008706"
    ],
    "id": 2485797,
    "name:xx": "Le Bong Creek"
  }
}
