{
  "geometry": {
    "type": "Point",
    "coordinates": [
      -75.15,
      39.8667
    ]
  },
  "type": "Feature",
  "properties": {
    "hierarchy": [
      "tgn:2303875",
      "tgn:1000001",
      "tgn:1002410",
      "tgn:7012149",
      "tgn:7007565",
      "tgn:7029392"
    ],
    "placetype": [
      "aat:300008850"
    ],
    "id": 2303875,
    "name:xx": "Eagle Point"
  }
}
