{
  "geometry": {
    "type": "Point",
    "coordinates": [
      -85.9833,
      13.1833
    ]
  },
  "type": "Feature",
  "properties": {
    "hierarchy": [
      "tgn:1119393",
      "tgn:1000653",
      "tgn:1000001",
      "tgn:7005562",
      "tgn:7029392"
    ],
    "placetype": [
      "aat:300006191"
    ],
    "id": 1119393,
    "name:xx": "Apanas, Laguna de"
  }
}
