{
  "geometry": {
    "type": "Point",
    "coordinates": [
      -79.4167,
      38.4167
    ]
  },
  "type": "Feature",
  "properties": {
    "hierarchy": [
      "tgn:2136277",
      "tgn:1000001",
      "tgn:7012149",
      "tgn:2002168",
      "tgn:7007919",
      "tgn:7029392"
    ],
    "placetype": [
      "aat:300008746"
    ],
    "id": 2136277,
    "name:xx": "Arbegast Saltpetre Cave"
  }
}
