{
  "geometry": {
    "type": "Point",
    "coordinates": [
      -82.35,
      36.85
    ]
  },
  "type": "Feature",
  "properties": {
    "hierarchy": [
      "tgn:2603902",
      "tgn:1000001",
      "tgn:7012149",
      "tgn:2002188",
      "tgn:7007919",
      "tgn:7029392"
    ],
    "placetype": [
      "aat:300008746"
    ],
    "id": 2603902,
    "name:xx": "Quillens Lost Bear Cave"
  }
}
