{
  "geometry": {
    "type": "Point",
    "coordinates": [
      101.2667,
      47.9167
    ]
  },
  "type": "Feature",
  "properties": {
    "hierarchy": [
      "tgn:1083071",
      "tgn:1002065",
      "tgn:1000004",
      "tgn:7029379",
      "tgn:7029392"
    ],
    "placetype": [
      "aat:300008347"
    ],
    "id": 1083071,
    "name:xx": "Bugat"
  }
}
