{
  "geometry": {
    "type": "Point",
    "coordinates": [
      -91.3667,
      38.9167
    ]
  },
  "type": "Feature",
  "properties": {
    "hierarchy": [
      "tgn:2354050",
      "tgn:1000001",
      "tgn:7012149",
      "tgn:1002687",
      "tgn:7007523",
      "tgn:7029392"
    ],
    "placetype": [
      "aat:300006191"
    ],
    "id": 2354050,
    "name:xx": "Golden Eagle Lake"
  }
}
