{
  "geometry": {
    "type": "Point",
    "coordinates": [
      33.55406,
      27.762625
    ]
  },
  "type": "Feature",
  "properties": {
    "hierarchy": [
      "tgn:7525438",
      "tgn:7001242",
      "tgn:7001311",
      "tgn:7016833",
      "tgn:7029392"
    ],
    "placetype": [
      "aat:300386846"
    ],
    "name:en": "Baḩr, Ra's al",
    "id": 7525438
  }
}
