{
  "geometry": {
    "type": "Point",
    "coordinates": [
      -122.3667,
      45.5667
    ]
  },
  "type": "Feature",
  "properties": {
    "hierarchy": [
      "tgn:2568933",
      "tgn:1000001",
      "tgn:1002275",
      "tgn:7012149",
      "tgn:7007920",
      "tgn:7029392"
    ],
    "placetype": [
      "aat:300008347"
    ],
    "id": 2568933,
    "name:xx": "Parker Landing Light"
  }
}
