{
  "geometry": {
    "type": "Point",
    "coordinates": [
      29.6833,
      30.9667
    ]
  },
  "type": "Feature",
  "properties": {
    "hierarchy": [
      "tgn:1095263",
      "tgn:7001242",
      "tgn:7016833",
      "tgn:1001418",
      "tgn:7029392"
    ],
    "placetype": [
      "aat:300007783"
    ],
    "name:en": "Maḩaţţat al Hawwārīyah",
    "id": 1095263
  }
}
