{
  "geometry": {
    "type": "Point",
    "coordinates": [
      -81.4833,
      37.6333
    ]
  },
  "type": "Feature",
  "properties": {
    "hierarchy": [
      "tgn:2598322",
      "tgn:1000001",
      "tgn:7012149",
      "tgn:2002304",
      "tgn:7013961",
      "tgn:7029392"
    ],
    "placetype": [
      "aat:300266640"
    ],
    "id": 2598322,
    "name:xx": "Pretty Ridge"
  }
}
