{
  "geometry": {
    "type": "Point",
    "coordinates": [
      -75.1167,
      41.1833
    ]
  },
  "type": "Feature",
  "properties": {
    "hierarchy": [
      "tgn:2688641",
      "tgn:1000001",
      "tgn:7012149",
      "tgn:1002789",
      "tgn:7007710",
      "tgn:7029392"
    ],
    "placetype": [
      "aat:300008699"
    ],
    "id": 2688641,
    "name:xx": "Spruce Run"
  }
}
