{
  "geometry": {
    "type": "Point",
    "coordinates": [
      -93.25,
      46.3667
    ]
  },
  "type": "Feature",
  "properties": {
    "hierarchy": [
      "tgn:2735150",
      "tgn:2000999",
      "tgn:1000001",
      "tgn:7012149",
      "tgn:7007521",
      "tgn:7029392"
    ],
    "placetype": [
      "aat:300008680"
    ],
    "id": 2735150,
    "name:xx": "Twentyone Lake"
  }
}
