{
  "geometry": {
    "type": "Point",
    "coordinates": [
      -81.85,
      8.1667
    ]
  },
  "type": "Feature",
  "properties": {
    "hierarchy": [
      "tgn:1129534",
      "tgn:1001201",
      "tgn:1000001",
      "tgn:7005565",
      "tgn:7029392"
    ],
    "placetype": [
      "aat:300008707"
    ],
    "id": 1129534,
    "name:xx": "San Félix, Río"
  }
}
