{
  "geometry": {
    "type": "Point",
    "coordinates": [
      -110.1667,
      49.65
    ]
  },
  "type": "Feature",
  "properties": {
    "hierarchy": [
      "tgn:7022654",
      "tgn:7005685",
      "tgn:1000001",
      "tgn:7029392"
    ],
    "placetype": [
      "aat:300008195"
    ],
    "id": 7022654,
    "name:xx": "Cypress Hills Provincial Park"
  }
}
