{
  "geometry": {
    "type": "Point",
    "coordinates": [
      33.35,
      -18.9167
    ]
  },
  "type": "Feature",
  "properties": {
    "hierarchy": [
      "tgn:1091664",
      "tgn:7001242",
      "tgn:1000891",
      "tgn:1000180",
      "tgn:7029392"
    ],
    "placetype": [
      "aat:300008347"
    ],
    "id": 1091664,
    "name:xx": "Nova Vandúzi"
  }
}
