{
  "geometry": {
    "type": "Point",
    "coordinates": [
      -149.4667,
      60.8667
    ]
  },
  "type": "Feature",
  "properties": {
    "hierarchy": [
      "tgn:2704513",
      "tgn:7006450",
      "tgn:1000001",
      "tgn:7019698",
      "tgn:7012149",
      "tgn:7029392"
    ],
    "placetype": [
      "aat:300008706"
    ],
    "id": 2704513,
    "name:xx": "Sunrise Creek"
  }
}
