{
  "geometry": {
    "type": "Point",
    "coordinates": [
      -82.9333,
      35.45
    ]
  },
  "type": "Feature",
  "properties": {
    "hierarchy": [
      "tgn:2604719",
      "tgn:1000001",
      "tgn:7012149",
      "tgn:2001503",
      "tgn:7007709",
      "tgn:7029392"
    ],
    "placetype": [
      "aat:300008706"
    ],
    "id": 2604719,
    "name:xx": "Raccoon Creek"
  }
}
