{
  "geometry": {
    "type": "Point",
    "coordinates": [
      -101.4667,
      33.9833
    ]
  },
  "type": "Feature",
  "properties": {
    "hierarchy": [
      "tgn:2642703",
      "tgn:1000001",
      "tgn:7012149",
      "tgn:2001985",
      "tgn:7007826",
      "tgn:7029392"
    ],
    "placetype": [
      "aat:300008347"
    ],
    "id": 2642703,
    "name:xx": "Sandhill"
  }
}
