{
  "geometry": {
    "type": "Point",
    "coordinates": [
      -94.2833,
      32.3667
    ]
  },
  "type": "Feature",
  "properties": {
    "hierarchy": [
      "tgn:2712572",
      "tgn:1000001",
      "tgn:7012149",
      "tgn:1002460",
      "tgn:7007826",
      "tgn:7029392"
    ],
    "placetype": [
      "aat:300008699"
    ],
    "id": 2712572,
    "name:xx": "Taylor Branch"
  }
}
