{
  "geometry": {
    "type": "Point",
    "coordinates": [
      -93.7667,
      38.3167
    ]
  },
  "type": "Feature",
  "properties": {
    "hierarchy": [
      "tgn:2355843",
      "tgn:1000001",
      "tgn:7012149",
      "tgn:2001202",
      "tgn:7007523",
      "tgn:7029392"
    ],
    "placetype": [
      "aat:300006191"
    ],
    "id": 2355843,
    "name:xx": "Goose Lake"
  }
}
