{
  "geometry": {
    "type": "Point",
    "coordinates": [
      -116.1833,
      47.4833
    ]
  },
  "type": "Feature",
  "properties": {
    "hierarchy": [
      "tgn:2284254",
      "tgn:1000001",
      "tgn:7012149",
      "tgn:2000491",
      "tgn:7007250",
      "tgn:7029392"
    ],
    "placetype": [
      "aat:300008706"
    ],
    "id": 2284254,
    "name:xx": "Denver Creek"
  }
}
