{
  "geometry": {
    "type": "Point",
    "coordinates": [
      32.4333,
      -26.05
    ]
  },
  "type": "Feature",
  "properties": {
    "hierarchy": [
      "tgn:1130726",
      "tgn:7001242",
      "tgn:7029392"
    ],
    "placetype": [
      "aat:300008707"
    ],
    "id": 1130726,
    "name:xx": "Tembe, Rio"
  }
}
