{
  "geometry": {
    "type": "Point",
    "coordinates": [
      15.3667,
      45.0667
    ]
  },
  "type": "Feature",
  "properties": {
    "hierarchy": [
      "tgn:1065182",
      "tgn:7017295",
      "tgn:1000003",
      "tgn:7006663",
      "tgn:7029392"
    ],
    "placetype": [
      "aat:300008347"
    ],
    "id": 1065182,
    "name:xx": "Plaški"
  }
}
