{
  "geometry": {
    "type": "Point",
    "coordinates": [
      -81.6333,
      36.55
    ]
  },
  "type": "Feature",
  "properties": {
    "hierarchy": [
      "tgn:2450913",
      "tgn:2001467",
      "tgn:1000001",
      "tgn:7012149",
      "tgn:7007709",
      "tgn:7029392"
    ],
    "placetype": [
      "aat:300008347"
    ],
    "id": 2450913,
    "name:xx": "Listening Rock"
  }
}
