{
  "geometry": {
    "type": "Point",
    "coordinates": [
      -88.0667,
      30.8333
    ]
  },
  "type": "Feature",
  "properties": {
    "hierarchy": [
      "tgn:2772771",
      "tgn:7002659",
      "tgn:1000001",
      "tgn:7012149",
      "tgn:2000048",
      "tgn:7029392"
    ],
    "placetype": [
      "aat:300008347"
    ],
    "id": 2772771,
    "name:xx": "Williams Heights"
  }
}
