{
  "type": "FeatureCollection",
  "features": [
    {
      "geometry": {
        "type": "Point",
        "coordinates": [
          -79.2167,
          40.9
        ]
      },
      "type": "Feature",
      "properties": {
        "hierarchy": [
          "tgn:7014070",
          "tgn:1002153",
          "tgn:1000001",
          "tgn:7012149",
          "tgn:7007710",
          "tgn:7029392"
        ],
        "placetype": [
          "aat:300008347"
        ],
        "id": 7014070,
        "name:xx": "Milton"
      }
    },
    {
      "geometry": {
        "type": "Point",
        "coordinates": [
          -87.9,
          43.0333
        ]
      },
      "type": "Feature",
      "properties": {
        "hierarchy": [
          "tgn:7014071",
          "tgn:1000001",
          "tgn:7012149",
          "tgn:1002672",
          "tgn:7007922",
          "tgn:7029392"
        ],
        "placetype": [
          "aat:300008347",
          "aat:300008416",
          "aat:300008389",
          "aat:300005135",
          "aat:300264742",
          "aat:300387270",
          "aat:300387302",
          "aat:300120599"
        ],
        "id": 7014071,
        "name:xx": "Milwaukee"
      }
    },
    {
      "geometry": {
        "type": "Point",
        "coordinates": [
          -70.65,
          42.6
        ]
      },
      "type": "Feature",
      "properties": {
        "hierarchy": [
          "tgn:7014073",
          "tgn:1000001",
          "tgn:1002359",
          "tgn:7012149",
          "tgn:7007517",
          "tgn:7029392"
        ],
        "placetype": [
          "aat:300008347",
          "aat:300008389"
        ],
        "id": 7014073,
        "name:xx": "Gloucester"
      }
    },
    {
      "geometry": {
        "type": "Point",
        "coordinates": [
          -81.4333,
          40.35
        ]
      },
      "type": "Feature",
      "properties": {
        "hierarchy": [
          "tgn:7014074",
          "tgn:1000001",
          "tgn:7012149",
          "tgn:1002958",
          "tgn:7007706",
          "tgn:7029392"
        ],
        "placetype": [
          "aat:300008347",
          "aat:300008486",
          "aat:300008375"
        ],
        "id": 7014074,
        "name:xx": "Gnadenhutten"
      }
    },
    {
      "geometry": {
        "type": "Point",
        "coordinates": [
          -120.8167,
          45.8167
        ]
      },
      "type": "Feature",
      "properties": {
        "hierarchy": [
          "tgn:7014075",
          "tgn:1000001",
          "tgn:7012149",
          "tgn:1002554",
          "tgn:7007920",
          "tgn:7029392"
        ],
        "placetype": [
          "aat:300008347",
          "aat:300008416"
        ],
        "id": 7014075,
        "name:xx": "Goldendale"
      }
    },
    {
      "geometry": {
        "type": "Point",
        "coordinates": [
          -77.9833,
          35.3833
        ]
      },
      "type": "Feature",
      "properties": {
        "hierarchy": [
          "tgn:7014076",
          "tgn:1000001",
          "tgn:7012149",
          "tgn:2001552",
          "tgn:7007709",
          "tgn:7029392"
        ],
        "placetype": [
          "aat:300008347"
        ],
        "id": 7014076,
        "name:xx": "Goldsboro"
      }
    },
    {
      "geometry": {
        "type": "Point",
        "coordinates": [
          -70.4333,
          43.6667
        ]
      },
      "type": "Feature",
      "properties": {
        "hierarchy": [
          "tgn:7014077",
          "tgn:1000001",
          "tgn:2000920",
          "tgn:7012149",
          "tgn:7007515",
          "tgn:7029392"
        ],
        "placetype": [
          "aat:300008347"
        ],
        "id": 7014077,
        "name:xx": "Gorham"
      }
    },
    {
      "geometry": {
        "type": "Point",
        "coordinates": [
          -71.6833,
          42.2
        ]
      },
      "type": "Feature",
      "properties": {
        "hierarchy": [
          "tgn:7014078",
          "tgn:1000001",
          "tgn:7012149",
          "tgn:1003038",
          "tgn:7007517",
          "tgn:7029392"
        ],
        "placetype": [
          "aat:300008347"
        ],
        "id": 7014078,
        "name:xx": "Grafton"
      }
    }
  ]
}
