{
  "type": "FeatureCollection",
  "features": [
    {
      "geometry": {
        "type": "Point",
        "coordinates": [
          12.866667,
          53.1
        ]
      },
      "type": "Feature",
      "properties": {
        "hierarchy": [
          "tgn:7112160",
          "tgn:7000096",
          "tgn:1000003",
          "tgn:7000084",
          "tgn:7029392"
        ],
        "placetype": [
          "aat:300008863"
        ],
        "id": 7112160,
        "name:xx": "Rheinsberg, Forst"
      }
    },
    {
      "geometry": {
        "type": "Point",
        "coordinates": [
          8,
          47.566667
        ]
      },
      "type": "Feature",
      "properties": {
        "hierarchy": [
          "tgn:7112162",
          "tgn:7003692",
          "tgn:1000003",
          "tgn:7000084",
          "tgn:7029392"
        ],
        "placetype": [
          "aat:300000206"
        ],
        "id": 7112162,
        "name:xx": "Rheinsberg"
      }
    },
    {
      "geometry": {
        "type": "Point",
        "coordinates": [
          8.735,
          49.37
        ]
      },
      "type": "Feature",
      "properties": {
        "hierarchy": [
          "tgn:7112163",
          "tgn:7003692",
          "tgn:1000003",
          "tgn:7000084",
          "tgn:7029392"
        ],
        "placetype": [
          "aat:300387198"
        ],
        "id": 7112163,
        "name:xx": "Rhein-Neckar-Kreis"
      }
    },
    {
      "geometry": {
        "type": "Point",
        "coordinates": [
          8.666667,
          50
        ]
      },
      "type": "Feature",
      "properties": {
        "hierarchy": [
          "tgn:7112165",
          "tgn:1000003",
          "tgn:7003678",
          "tgn:7000084",
          "tgn:7029392"
        ],
        "placetype": [
          "aat:300387346"
        ],
        "id": 7112165,
        "name:xx": "Rhein-Main-Gebiet"
      }
    },
    {
      "geometry": {
        "type": "Point",
        "coordinates": [
          7.5,
          49.666667
        ]
      },
      "type": "Feature",
      "properties": {
        "hierarchy": [
          "tgn:7112167",
          "tgn:1000003",
          "tgn:7594165",
          "tgn:7000084",
          "tgn:7029392"
        ],
        "placetype": [
          "aat:300387064"
        ],
        "id": 7112167,
        "name:xx": "Land Rheinland-Pfalz"
      }
    },
    {
      "geometry": {
        "type": "Point",
        "coordinates": [
          6.933333,
          51.033333
        ]
      },
      "type": "Feature",
      "properties": {
        "hierarchy": [
          "tgn:7112168",
          "tgn:1000003",
          "tgn:7003677",
          "tgn:7000084",
          "tgn:7029392"
        ],
        "placetype": [
          "aat:300000745"
        ],
        "id": 7112168,
        "name:xx": "Rheinkassel"
      }
    },
    {
      "geometry": {
        "type": "Point",
        "coordinates": [
          8.366667,
          49.533333
        ]
      },
      "type": "Feature",
      "properties": {
        "hierarchy": [
          "tgn:7112169",
          "tgn:1000003",
          "tgn:7003682",
          "tgn:7000084",
          "tgn:7029392"
        ],
        "placetype": [
          "aat:300006075"
        ],
        "id": 7112169,
        "name:xx": "Rhein-Kanal"
      }
    }
  ]
}
