{
  "geometry": {
    "type": "Point",
    "coordinates": [
      -78.4833,
      34.0333
    ]
  },
  "type": "Feature",
  "properties": {
    "hierarchy": [
      "tgn:2515322",
      "tgn:1000001",
      "tgn:2001472",
      "tgn:7012149",
      "tgn:7007709",
      "tgn:7029392"
    ],
    "placetype": [
      "aat:300008699"
    ],
    "id": 2515322,
    "name:xx": "Milliken Swamp"
  }
}
