{
  "geometry": {
    "type": "Point",
    "coordinates": [
      58.05,
      37.9167
    ]
  },
  "type": "Feature",
  "properties": {
    "hierarchy": [
      "tgn:1053890",
      "tgn:7012221",
      "tgn:1000004",
      "tgn:7006659",
      "tgn:7029392"
    ],
    "placetype": [
      "aat:300008347"
    ],
    "id": 1053890,
    "name:xx": "Firyuza"
  }
}
