{
  "geometry": {
    "type": "Point",
    "coordinates": [
      -76.6333,
      37.0167
    ]
  },
  "type": "Feature",
  "properties": {
    "hierarchy": [
      "tgn:2485422",
      "tgn:1000001",
      "tgn:7012149",
      "tgn:1002506",
      "tgn:7007919",
      "tgn:7029392"
    ],
    "placetype": [
      "aat:300008706"
    ],
    "id": 2485422,
    "name:xx": "Lawson Creek"
  }
}
