{
  "geometry": {
    "type": "Point",
    "coordinates": [
      -112.8833,
      34.5667
    ]
  },
  "type": "Feature",
  "properties": {
    "hierarchy": [
      "tgn:2203444",
      "tgn:1000001",
      "tgn:7006451",
      "tgn:7012149",
      "tgn:2000103",
      "tgn:7029392"
    ],
    "placetype": [
      "aat:300006191"
    ],
    "id": 2203444,
    "name:xx": "Buckhorn Tanks"
  }
}
