{
  "geometry": {
    "type": "Point",
    "coordinates": [
      -89.0167,
      45.65
    ]
  },
  "type": "Feature",
  "properties": {
    "hierarchy": [
      "tgn:2120655",
      "tgn:1000001",
      "tgn:2002323",
      "tgn:7012149",
      "tgn:7007922",
      "tgn:7029392"
    ],
    "placetype": [
      "aat:300387016"
    ],
    "id": 2120655,
    "name:xx": "Atkins"
  }
}
