{
  "type": "FeatureCollection",
  "features": [
    {
      "geometry": {
        "type": "Point",
        "coordinates": [
          12.533,
          42.1333
        ]
      },
      "type": "Feature",
      "properties": {
        "hierarchy": [
          "tgn:7008310",
          "tgn:7003138",
          "tgn:1000003",
          "tgn:7003080",
          "tgn:1000080",
          "tgn:7029392"
        ],
        "placetype": [
          "aat:300008347"
        ],
        "id": 7008310,
        "name:xx": "Capena"
      }
    },
    {
      "geometry": {
        "type": "Point",
        "coordinates": [
          17.4,
          40.85
        ]
      },
      "type": "Feature",
      "properties": {
        "hierarchy": [
          "tgn:7008311",
          "tgn:1003442",
          "tgn:1000003",
          "tgn:7010380",
          "tgn:1000080",
          "tgn:7029392"
        ],
        "placetype": [
          "aat:300008347",
          "aat:300000810",
          "aat:300167671",
          "aat:300008394",
          "aat:300387235"
        ],
        "id": 7008311,
        "name:xx": "Egnazia"
      }
    },
    {
      "geometry": {
        "type": "Point",
        "coordinates": [
          9.25,
          45.8
        ]
      },
      "type": "Feature",
      "properties": {
        "hierarchy": [
          "tgn:7008313",
          "tgn:7005852",
          "tgn:1000003",
          "tgn:7003237",
          "tgn:1000080",
          "tgn:7029392"
        ],
        "placetype": [
          "aat:300008347"
        ],
        "id": 7008313,
        "name:xx": "Erba"
      }
    },
    {
      "geometry": {
        "type": "Point",
        "coordinates": [
          15.15,
          40.166667
        ]
      },
      "type": "Feature",
      "properties": {
        "hierarchy": [
          "tgn:7008314",
          "tgn:7003005",
          "tgn:7003014",
          "tgn:1000003",
          "tgn:1000080",
          "tgn:7029392"
        ],
        "placetype": [
          "aat:300008347",
          "aat:300000810",
          "aat:300167671",
          "aat:300008057",
          "aat:300263063"
        ],
        "id": 7008314,
        "name:xx": "Elea"
      }
    },
    {
      "geometry": {
        "type": "Point",
        "coordinates": [
          14.95,
          38.5
        ]
      },
      "type": "Feature",
      "properties": {
        "hierarchy": [
          "tgn:7008315",
          "tgn:1000003",
          "tgn:7003122",
          "tgn:7003157",
          "tgn:1000080",
          "tgn:7029392"
        ],
        "placetype": [
          "aat:300008791",
          "aat:300386853",
          "aat:300263063"
        ],
        "id": 7008315,
        "name:xx": "Eolie, Isole"
      }
    },
    {
      "geometry": {
        "type": "Point",
        "coordinates": [
          0.4333,
          47.35
        ]
      },
      "type": "Feature",
      "properties": {
        "hierarchy": [
          "tgn:7008316",
          "tgn:1000003",
          "tgn:7002877",
          "tgn:1000070",
          "tgn:7029392"
        ],
        "placetype": [
          "aat:300008347"
        ],
        "id": 7008316,
        "name:xx": "Langeais"
      }
    },
    {
      "geometry": {
        "type": "Point",
        "coordinates": [
          1,
          47.1333
        ]
      },
      "type": "Feature",
      "properties": {
        "hierarchy": [
          "tgn:7008317",
          "tgn:1000003",
          "tgn:7002877",
          "tgn:1000070",
          "tgn:7029392"
        ],
        "placetype": [
          "aat:300008347"
        ],
        "id": 7008317,
        "name:xx": "Loches"
      }
    },
    {
      "geometry": {
        "type": "Point",
        "coordinates": [
          1.2,
          47.15
        ]
      },
      "type": "Feature",
      "properties": {
        "hierarchy": [
          "tgn:7008318",
          "tgn:1000003",
          "tgn:7002877",
          "tgn:1000070",
          "tgn:7029392"
        ],
        "placetype": [
          "aat:300008347"
        ],
        "id": 7008318,
        "name:xx": "Montrésor"
      }
    },
    {
      "geometry": {
        "type": "Point",
        "coordinates": [
          0.6667,
          47.4
        ]
      },
      "type": "Feature",
      "properties": {
        "hierarchy": [
          "tgn:7008319",
          "tgn:1000003",
          "tgn:7002877",
          "tgn:1000070",
          "tgn:7029392"
        ],
        "placetype": [
          "aat:300008347"
        ],
        "id": 7008319,
        "name:xx": "Saint-Cyr-sur-Loire"
      }
    }
  ]
}
