{
  "geometry": {
    "type": "Point",
    "coordinates": [
      -76.3333,
      36.4667
    ]
  },
  "type": "Feature",
  "properties": {
    "hierarchy": [
      "tgn:1135892",
      "tgn:1000001",
      "tgn:7012149",
      "tgn:7029392"
    ],
    "placetype": [
      "aat:300006075"
    ],
    "id": 1135892,
    "name:xx": "Dismal Swamp Canal"
  }
}
