{
  "geometry": {
    "type": "Point",
    "coordinates": [
      -100.7333,
      32.9667
    ]
  },
  "type": "Feature",
  "properties": {
    "hierarchy": [
      "tgn:2168321",
      "tgn:1000001",
      "tgn:7012149",
      "tgn:2002017",
      "tgn:7007826",
      "tgn:7029392"
    ],
    "placetype": [
      "aat:300008761"
    ],
    "id": 2168321,
    "name:xx": "Big Gobbler"
  }
}
