{
  "type": "FeatureCollection",
  "features": [
    {
      "geometry": {
        "type": "Point",
        "coordinates": [
          44.4167,
          -12.25
        ]
      },
      "type": "Feature",
      "properties": {
        "hierarchy": [
          "tgn:1008410",
          "tgn:7001242",
          "tgn:1000157",
          "tgn:7029392"
        ],
        "placetype": [
          "aat:300387064",
          "aat:300008791",
          "aat:300235093"
        ],
        "id": 1008410,
        "name:xx": "Nzwane"
      }
    },
    {
      "geometry": {
        "type": "Point",
        "coordinates": [
          -73.2833,
          40.6333
        ]
      },
      "type": "Feature",
      "properties": {
        "hierarchy": [
          "tgn:1008412",
          "tgn:1000001",
          "tgn:7012149",
          "tgn:1002924",
          "tgn:7007568",
          "tgn:7029392"
        ],
        "placetype": [
          "aat:300008791"
        ],
        "id": 1008412,
        "name:xx": "Oak Island"
      }
    },
    {
      "geometry": {
        "type": "Point",
        "coordinates": [
          -64.3,
          44.5167
        ]
      },
      "type": "Feature",
      "properties": {
        "hierarchy": [
          "tgn:1008413",
          "tgn:7005685",
          "tgn:1000001",
          "tgn:7005802",
          "tgn:7029392"
        ],
        "placetype": [
          "aat:300008791"
        ],
        "id": 1008413,
        "name:xx": "Oak Island"
      }
    },
    {
      "geometry": {
        "type": "Point",
        "coordinates": [
          158.9333,
          -21.4667
        ]
      },
      "type": "Feature",
      "properties": {
        "hierarchy": [
          "tgn:1008416",
          "tgn:1000223",
          "tgn:1000006",
          "tgn:7029392"
        ],
        "placetype": [
          "aat:300008791"
        ],
        "id": 1008416,
        "name:xx": "Observatoire, Caye de l'"
      }
    },
    {
      "geometry": {
        "type": "Point",
        "coordinates": [
          -75.9,
          35.1167
        ]
      },
      "type": "Feature",
      "properties": {
        "hierarchy": [
          "tgn:1008417",
          "tgn:1000001",
          "tgn:7012149",
          "tgn:2001506",
          "tgn:7007709",
          "tgn:7029392"
        ],
        "placetype": [
          "aat:300008791"
        ],
        "id": 1008417,
        "name:xx": "Ocracoke Island"
      }
    }
  ]
}
