{
  "geometry": {
    "type": "Point",
    "coordinates": [
      31.045114,
      30.599677
    ]
  },
  "type": "Feature",
  "properties": {
    "hierarchy": [
      "tgn:7534799",
      "tgn:7001242",
      "tgn:7016833",
      "tgn:1001087",
      "tgn:7029392"
    ],
    "placetype": [
      "aat:300008347"
    ],
    "name:en": "Ḩişşat Milīj",
    "id": 7534799
  }
}
