{
  "geometry": {
    "type": "Point",
    "coordinates": [
      -78.0833,
      35.65
    ]
  },
  "type": "Feature",
  "properties": {
    "hierarchy": [
      "tgn:2487073",
      "tgn:1000001",
      "tgn:7012149",
      "tgn:2001554",
      "tgn:7007709",
      "tgn:7029392"
    ],
    "placetype": [
      "aat:300008699"
    ],
    "id": 2487073,
    "name:xx": "Lee Swamp"
  }
}
