{
  "type": "FeatureCollection",
  "features": [
    {
      "geometry": {
        "type": "Point",
        "coordinates": [
          -85.0667,
          32.2333
        ]
      },
      "type": "Feature",
      "properties": {
        "hierarchy": [
          "tgn:2672870",
          "tgn:7002659",
          "tgn:1000001",
          "tgn:7012149",
          "tgn:2000056",
          "tgn:7029392"
        ],
        "placetype": [
          "aat:300008706"
        ],
        "id": 2672870,
        "name:xx": "Snake Creek"
      }
    },
    {
      "geometry": {
        "type": "Point",
        "coordinates": [
          -85.3167,
          32.5167
        ]
      },
      "type": "Feature",
      "properties": {
        "hierarchy": [
          "tgn:2672871",
          "tgn:7002659",
          "tgn:1000001",
          "tgn:7012149",
          "tgn:7029392"
        ],
        "placetype": [
          "aat:300008706"
        ],
        "id": 2672871,
        "name:xx": "Snake Creek"
      }
    },
    {
      "geometry": {
        "type": "Point",
        "coordinates": [
          -85.6667,
          33.6
        ]
      },
      "type": "Feature",
      "properties": {
        "hierarchy": [
          "tgn:2672872",
          "tgn:7002659",
          "tgn:1000001",
          "tgn:2000014",
          "tgn:7012149",
          "tgn:7029392"
        ],
        "placetype": [
          "aat:300008706"
        ],
        "id": 2672872,
        "name:xx": "Snake Creek"
      }
    },
    {
      "geometry": {
        "type": "Point",
        "coordinates": [
          -87.05,
          32.0667
        ]
      },
      "type": "Feature",
      "properties": {
        "hierarchy": [
          "tgn:2672873",
          "tgn:7002659",
          "tgn:1000001",
          "tgn:7012149",
          "tgn:2000023",
          "tgn:7029392"
        ],
        "placetype": [
          "aat:300008706"
        ],
        "id": 2672873,
        "name:xx": "Snake Creek"
      }
    },
    {
      "geometry": {
        "type": "Point",
        "coordinates": [
          -88.1667,
          33.2833
        ]
      },
      "type": "Feature",
      "properties": {
        "hierarchy": [
          "tgn:2672874",
          "tgn:7002659",
          "tgn:1000001",
          "tgn:7012149",
          "tgn:2000053",
          "tgn:7029392"
        ],
        "placetype": [
          "aat:300008706"
        ],
        "id": 2672874,
        "name:xx": "Snake Creek"
      }
    },
    {
      "geometry": {
        "type": "Point",
        "coordinates": [
          -146.25,
          60.3833
        ]
      },
      "type": "Feature",
      "properties": {
        "hierarchy": [
          "tgn:2672875",
          "tgn:7006450",
          "tgn:1000001",
          "tgn:7012149",
          "tgn:2000086",
          "tgn:7029392"
        ],
        "placetype": [
          "aat:300008706"
        ],
        "id": 2672875,
        "name:xx": "Snake Creek"
      }
    },
    {
      "geometry": {
        "type": "Point",
        "coordinates": [
          -109.55,
          34
        ]
      },
      "type": "Feature",
      "properties": {
        "hierarchy": [
          "tgn:2672876",
          "tgn:2000090",
          "tgn:1000001",
          "tgn:7006451",
          "tgn:7012149",
          "tgn:7029392"
        ],
        "placetype": [
          "aat:300008706"
        ],
        "id": 2672876,
        "name:xx": "Snake Creek"
      }
    },
    {
      "geometry": {
        "type": "Point",
        "coordinates": [
          -109.4333,
          33.6167
        ]
      },
      "type": "Feature",
      "properties": {
        "hierarchy": [
          "tgn:2672877",
          "tgn:1000001",
          "tgn:7006451",
          "tgn:2000095",
          "tgn:7012149",
          "tgn:7029392"
        ],
        "placetype": [
          "aat:300008706"
        ],
        "id": 2672877,
        "name:xx": "Snake Creek"
      }
    },
    {
      "geometry": {
        "type": "Point",
        "coordinates": [
          -92.05,
          33.4833
        ]
      },
      "type": "Feature",
      "properties": {
        "hierarchy": [
          "tgn:2672878",
          "tgn:1000001",
          "tgn:7016172",
          "tgn:2000110",
          "tgn:7012149",
          "tgn:7029392"
        ],
        "placetype": [
          "aat:300008706"
        ],
        "id": 2672878,
        "name:xx": "Snake Creek"
      }
    },
    {
      "geometry": {
        "type": "Point",
        "coordinates": [
          -94.15,
          34.2333
        ]
      },
      "type": "Feature",
      "properties": {
        "hierarchy": [
          "tgn:2672879",
          "tgn:1000001",
          "tgn:7016172",
          "tgn:7012149",
          "tgn:2000135",
          "tgn:7029392"
        ],
        "placetype": [
          "aat:300008706"
        ],
        "id": 2672879,
        "name:xx": "Snake Creek"
      }
    }
  ]
}
