{
  "geometry": {
    "type": "Point",
    "coordinates": [
      -96.2167,
      38.8167
    ]
  },
  "type": "Feature",
  "properties": {
    "hierarchy": [
      "tgn:2758053",
      "tgn:1000001",
      "tgn:7012149",
      "tgn:2000758",
      "tgn:7007254",
      "tgn:7029392"
    ],
    "placetype": [
      "aat:300008706"
    ],
    "id": 2758053,
    "name:xx": "West Branch Rock Creek"
  }
}
