{
  "geometry": {
    "type": "Point",
    "coordinates": [
      -74.75,
      43.8667
    ]
  },
  "type": "Feature",
  "properties": {
    "hierarchy": [
      "tgn:2740954",
      "tgn:1000001",
      "tgn:7012149",
      "tgn:1002440",
      "tgn:7007568",
      "tgn:7029392"
    ],
    "placetype": [
      "aat:300008680"
    ],
    "id": 2740954,
    "name:xx": "Upper Sister Lake"
  }
}
