{
  "geometry": {
    "type": "Point",
    "coordinates": [
      13.75,
      46.15
    ]
  },
  "type": "Feature",
  "properties": {
    "hierarchy": [
      "tgn:7017205",
      "tgn:1000003",
      "tgn:7015085",
      "tgn:7006670",
      "tgn:7029392"
    ],
    "placetype": [
      "aat:300008347"
    ],
    "id": 7017205,
    "name:xx": "Most na Soči"
  }
}
