{
  "geometry": {
    "type": "Point",
    "coordinates": [
      121.8234,
      24.5272
    ]
  },
  "type": "Feature",
  "properties": {
    "hierarchy": [
      "tgn:7473886",
      "tgn:1000004",
      "tgn:7489179",
      "tgn:1000141",
      "tgn:7029392"
    ],
    "placetype": [
      "aat:300387173"
    ],
    "id": 7473886,
    "name:xx": "Dongyue Cun"
  }
}
