{
  "geometry": {
    "type": "Point",
    "coordinates": [
      -78.796,
      -0.747
    ]
  },
  "type": "Feature",
  "properties": {
    "hierarchy": [
      "tgn:1001211",
      "tgn:7002561",
      "tgn:1000051",
      "tgn:1000002",
      "tgn:7029392"
    ],
    "placetype": [
      "aat:300387064",
      "aat:300000774"
    ],
    "id": 1001211,
    "name:xx": "Cotopaxi"
  }
}
