{
  "geometry": {
    "type": "Point",
    "coordinates": [
      79.873,
      27.0427
    ]
  },
  "type": "Feature",
  "properties": {
    "hierarchy": [
      "tgn:7563194",
      "tgn:1000004",
      "tgn:7000198",
      "tgn:7016722",
      "tgn:7029392"
    ],
    "placetype": [
      "aat:300008347"
    ],
    "name:en": "Deodharāpur",
    "id": 7563194
  }
}
