{
  "geometry": {
    "type": "Point",
    "coordinates": [
      -111.1667,
      38.1167
    ]
  },
  "type": "Feature",
  "properties": {
    "hierarchy": [
      "tgn:2677805",
      "tgn:1000001",
      "tgn:7012149",
      "tgn:7007827",
      "tgn:7029392"
    ],
    "placetype": [
      "aat:300008761"
    ],
    "id": 2677805,
    "name:xx": "South Draw"
  }
}
