{
  "geometry": {
    "type": "Point",
    "coordinates": [
      -100.8833,
      41.15
    ]
  },
  "type": "Feature",
  "properties": {
    "hierarchy": [
      "tgn:2061971",
      "tgn:1000001",
      "tgn:7012149",
      "tgn:2001371",
      "tgn:7007525",
      "tgn:7029392"
    ],
    "placetype": [
      "aat:300387016"
    ],
    "id": 2061971,
    "name:xx": "Birdwood"
  }
}
