{
  "geometry": {
    "type": "Point",
    "coordinates": [
      114.8333,
      51.8333
    ]
  },
  "type": "Feature",
  "properties": {
    "hierarchy": [
      "tgn:1060718",
      "tgn:1003351",
      "tgn:1000004",
      "tgn:7018214",
      "tgn:7002435",
      "tgn:7029392"
    ],
    "placetype": [
      "aat:300008347"
    ],
    "id": 1060718,
    "name:xx": "Urulga"
  }
}
