{
  "geometry": {
    "type": "Point",
    "coordinates": [
      -114.05,
      38.1167
    ]
  },
  "type": "Feature",
  "properties": {
    "hierarchy": [
      "tgn:2149256",
      "tgn:1000001",
      "tgn:2001416",
      "tgn:7012149",
      "tgn:7007526",
      "tgn:7029392"
    ],
    "placetype": [
      "aat:300008697"
    ],
    "id": 2149256,
    "name:xx": "Barrel Spring"
  }
}
