{
  "geometry": {
    "type": "Point",
    "coordinates": [
      -87.15,
      33.45
    ]
  },
  "type": "Feature",
  "properties": {
    "hierarchy": [
      "tgn:2004739",
      "tgn:7002659",
      "tgn:1000001",
      "tgn:7012149",
      "tgn:2000036",
      "tgn:7029392"
    ],
    "placetype": [
      "aat:300008347"
    ],
    "id": 2004739,
    "name:xx": "Oak Grove"
  }
}
