{
  "geometry": {
    "type": "Point",
    "coordinates": [
      -114.4833,
      45.45
    ]
  },
  "type": "Feature",
  "properties": {
    "hierarchy": [
      "tgn:2560535",
      "tgn:1000001",
      "tgn:7012149",
      "tgn:2000481",
      "tgn:7007250",
      "tgn:7029392"
    ],
    "placetype": [
      "aat:300008697"
    ],
    "id": 2560535,
    "name:xx": "Oreana Spring"
  }
}
