{
  "geometry": {
    "type": "Point",
    "coordinates": [
      -111.5333,
      33.9667
    ]
  },
  "type": "Feature",
  "properties": {
    "hierarchy": [
      "tgn:2255763",
      "tgn:1000001",
      "tgn:7006451",
      "tgn:7012149",
      "tgn:2000097",
      "tgn:7029392"
    ],
    "placetype": [
      "aat:300008706"
    ],
    "id": 2255763,
    "name:xx": "Copper Camp Creek"
  }
}
