{
  "type": "FeatureCollection",
  "features": [
    {
      "geometry": {
        "type": "Point",
        "coordinates": [
          7.0167,
          48.6833
        ]
      },
      "type": "Feature",
      "properties": {
        "hierarchy": [
          "tgn:1129700",
          "tgn:1000003",
          "tgn:7002888",
          "tgn:1000070",
          "tgn:7029392"
        ],
        "placetype": [
          "aat:300008707"
        ],
        "id": 1129700,
        "name:xx": "Sarre"
      }
    },
    {
      "geometry": {
        "type": "Point",
        "coordinates": [
          7.0167,
          48.6833
        ]
      },
      "type": "Feature",
      "properties": {
        "hierarchy": [
          "tgn:1129701",
          "tgn:1000003",
          "tgn:7002888",
          "tgn:1000070",
          "tgn:7029392"
        ],
        "placetype": [
          "aat:300008707"
        ],
        "id": 1129701,
        "name:xx": "Sarre Rouge"
      }
    },
    {
      "geometry": {
        "type": "Point",
        "coordinates": [
          -88.9,
          15.9
        ]
      },
      "type": "Feature",
      "properties": {
        "hierarchy": [
          "tgn:1129702",
          "tgn:1000001",
          "tgn:7029392"
        ],
        "placetype": [
          "aat:300008707"
        ],
        "id": 1129702,
        "name:xx": "Sarstoon"
      }
    },
    {
      "geometry": {
        "type": "Point",
        "coordinates": [
          0.5333,
          47.5333
        ]
      },
      "type": "Feature",
      "properties": {
        "hierarchy": [
          "tgn:1129704",
          "tgn:1000003",
          "tgn:1000070",
          "tgn:7029392"
        ],
        "placetype": [
          "aat:300008707"
        ],
        "id": 1129704,
        "name:xx": "Sarthe"
      }
    },
    {
      "geometry": {
        "type": "Point",
        "coordinates": [
          66.5833,
          45.1667
        ]
      },
      "type": "Feature",
      "properties": {
        "hierarchy": [
          "tgn:1129705",
          "tgn:1000004",
          "tgn:7014786",
          "tgn:7029392"
        ],
        "placetype": [
          "aat:300008707"
        ],
        "id": 1129705,
        "name:xx": "Sarysu"
      }
    },
    {
      "geometry": {
        "type": "Point",
        "coordinates": [
          -6.0667,
          4.9833
        ]
      },
      "type": "Feature",
      "properties": {
        "hierarchy": [
          "tgn:1129709",
          "tgn:7001242",
          "tgn:1000168",
          "tgn:7029392"
        ],
        "placetype": [
          "aat:300008707"
        ],
        "id": 1129709,
        "name:xx": "Sassandra"
      }
    }
  ]
}
