{
  "geometry": {
    "type": "Point",
    "coordinates": [
      -75.6333,
      39.4667
    ]
  },
  "type": "Feature",
  "properties": {
    "hierarchy": [
      "tgn:2701291",
      "tgn:7014201",
      "tgn:1000001",
      "tgn:7012149",
      "tgn:7007239",
      "tgn:7029392"
    ],
    "placetype": [
      "aat:300008347"
    ],
    "id": 2701291,
    "name:xx": "Sugar Loaf Chase"
  }
}
