{
  "geometry": {
    "type": "Point",
    "coordinates": [
      174.15,
      -41.25
    ]
  },
  "type": "Feature",
  "properties": {
    "hierarchy": [
      "tgn:7511568",
      "tgn:1009227",
      "tgn:1000226",
      "tgn:7016729",
      "tgn:1000006",
      "tgn:7029392"
    ],
    "placetype": [
      "aat:300132316"
    ],
    "name:en": "Maraetai Bay",
    "id": 7511568
  }
}
