{
  "geometry": {
    "type": "Point",
    "coordinates": [
      -91.1667,
      44.9667
    ]
  },
  "type": "Feature",
  "properties": {
    "hierarchy": [
      "tgn:2302141",
      "tgn:1000001",
      "tgn:2002313",
      "tgn:7012149",
      "tgn:7007922",
      "tgn:7029392"
    ],
    "placetype": [
      "aat:300008706"
    ],
    "id": 2302141,
    "name:xx": "Dutch Creek"
  }
}
