{
  "geometry": {
    "type": "Point",
    "coordinates": [
      -87.95,
      30.7667
    ]
  },
  "type": "Feature",
  "properties": {
    "hierarchy": [
      "tgn:2264292",
      "tgn:2000001",
      "tgn:7002659",
      "tgn:1000001",
      "tgn:7012149",
      "tgn:7029392"
    ],
    "placetype": [
      "aat:300008706"
    ],
    "id": 2264292,
    "name:xx": "Crab Creek"
  }
}
