{
  "geometry": {
    "type": "Point",
    "coordinates": [
      -93.4667,
      47.8667
    ]
  },
  "type": "Feature",
  "properties": {
    "hierarchy": [
      "tgn:2716993",
      "tgn:1000001",
      "tgn:7012149",
      "tgn:2001029",
      "tgn:7007521",
      "tgn:7029392"
    ],
    "placetype": [
      "aat:300008680"
    ],
    "id": 2716993,
    "name:xx": "Thimble Lake"
  }
}
