{
  "geometry": {
    "type": "Point",
    "coordinates": [
      -119.7667,
      47.4333
    ]
  },
  "type": "Feature",
  "properties": {
    "hierarchy": [
      "tgn:2719456",
      "tgn:1000001",
      "tgn:7012149",
      "tgn:7007920",
      "tgn:7029392"
    ],
    "placetype": [
      "aat:300008761"
    ],
    "id": 2719456,
    "name:xx": "Three Devils"
  }
}
