{
  "geometry": {
    "type": "Point",
    "coordinates": [
      106.4333,
      29.45
    ]
  },
  "type": "Feature",
  "properties": {
    "hierarchy": [
      "tgn:1069721",
      "tgn:1000004",
      "tgn:7002087",
      "tgn:1000111",
      "tgn:7029392"
    ],
    "placetype": [
      "aat:300008347"
    ],
    "id": 1069721,
    "name:xx": "Lengshuichang"
  }
}
