{
  "geometry": {
    "type": "Point",
    "coordinates": [
      120.3862,
      23.0114
    ]
  },
  "type": "Feature",
  "properties": {
    "hierarchy": [
      "tgn:7491497",
      "tgn:1000004",
      "tgn:7490934",
      "tgn:1000141",
      "tgn:7029392"
    ],
    "placetype": [
      "aat:300008347"
    ],
    "id": 7491497,
    "name:xx": "Dakengwei"
  }
}
