{
  "geometry": {
    "type": "Point",
    "coordinates": [
      -118.25,
      38.7667
    ]
  },
  "type": "Feature",
  "properties": {
    "hierarchy": [
      "tgn:2589285",
      "tgn:1000001",
      "tgn:2001417",
      "tgn:7012149",
      "tgn:7007526",
      "tgn:7029392"
    ],
    "placetype": [
      "aat:300008697"
    ],
    "id": 2589285,
    "name:xx": "Poinsettia Spring"
  }
}
