{
  "geometry": {
    "type": "Point",
    "coordinates": [
      -69.8167,
      44.5667
    ]
  },
  "type": "Feature",
  "properties": {
    "hierarchy": [
      "tgn:2543713",
      "tgn:1000001",
      "tgn:2000923",
      "tgn:7012149",
      "tgn:7007515",
      "tgn:7029392"
    ],
    "placetype": [
      "aat:300132316"
    ],
    "id": 2543713,
    "name:xx": "North Bay"
  }
}
