{
  "geometry": {
    "type": "Point",
    "coordinates": [
      -89.8333,
      35.4667
    ]
  },
  "type": "Feature",
  "properties": {
    "hierarchy": [
      "tgn:2351848",
      "tgn:1000001",
      "tgn:7012149",
      "tgn:2001920",
      "tgn:7007825",
      "tgn:7029392"
    ],
    "placetype": [
      "aat:300006191"
    ],
    "id": 2351848,
    "name:xx": "Glenview Lake"
  }
}
