{
  "type": "FeatureCollection",
  "features": [
    {
      "geometry": {
        "type": "Point",
        "coordinates": [
          -90.7667,
          43.9667
        ]
      },
      "type": "Feature",
      "properties": {
        "hierarchy": [
          "tgn:2120610",
          "tgn:1000001",
          "tgn:7012149",
          "tgn:2002340",
          "tgn:7007922",
          "tgn:7029392"
        ],
        "placetype": [
          "aat:300008347"
        ],
        "id": 2120610,
        "name:xx": "Angelo"
      }
    },
    {
      "geometry": {
        "type": "Point",
        "coordinates": [
          -91.6,
          45.6333
        ]
      },
      "type": "Feature",
      "properties": {
        "hierarchy": [
          "tgn:2120611",
          "tgn:2002307",
          "tgn:1000001",
          "tgn:7012149",
          "tgn:7007922",
          "tgn:7029392"
        ],
        "placetype": [
          "aat:300008347",
          "aat:300387210"
        ],
        "id": 2120611,
        "name:xx": "Angus"
      }
    },
    {
      "geometry": {
        "type": "Point",
        "coordinates": [
          -89.2,
          45
        ]
      },
      "type": "Feature",
      "properties": {
        "hierarchy": [
          "tgn:2120612",
          "tgn:1000001",
          "tgn:7012149",
          "tgn:2002354",
          "tgn:7007922",
          "tgn:7029392"
        ],
        "placetype": [
          "aat:300008347"
        ],
        "id": 2120612,
        "name:xx": "Aniwa"
      }
    },
    {
      "geometry": {
        "type": "Point",
        "coordinates": [
          -90.5333,
          42.9
        ]
      },
      "type": "Feature",
      "properties": {
        "hierarchy": [
          "tgn:2120613",
          "tgn:1000001",
          "tgn:2002324",
          "tgn:7012149",
          "tgn:7007922",
          "tgn:7029392"
        ],
        "placetype": [
          "aat:300008347",
          "aat:300387210"
        ],
        "id": 2120613,
        "name:xx": "Annaton"
      }
    },
    {
      "geometry": {
        "type": "Point",
        "coordinates": [
          -88.15,
          44.6167
        ]
      },
      "type": "Feature",
      "properties": {
        "hierarchy": [
          "tgn:2120614",
          "tgn:1000001",
          "tgn:2002309",
          "tgn:7012149",
          "tgn:7007922",
          "tgn:7029392"
        ],
        "placetype": [
          "aat:300008347"
        ],
        "id": 2120614,
        "name:xx": "Anston"
      }
    },
    {
      "geometry": {
        "type": "Point",
        "coordinates": [
          -89.15,
          45.1333
        ]
      },
      "type": "Feature",
      "properties": {
        "hierarchy": [
          "tgn:2120616",
          "tgn:1000001",
          "tgn:7012149",
          "tgn:2002333",
          "tgn:7007922",
          "tgn:7029392"
        ],
        "placetype": [
          "aat:300008347"
        ],
        "id": 2120616,
        "name:xx": "Antigo"
      }
    }
  ]
}
