{
  "geometry": {
    "type": "Point",
    "coordinates": [
      -45.9667,
      -22.05
    ]
  },
  "type": "Feature",
  "properties": {
    "hierarchy": [
      "tgn:1021388",
      "tgn:7006237",
      "tgn:1000047",
      "tgn:7002457",
      "tgn:1000002",
      "tgn:7029392"
    ],
    "placetype": [
      "aat:300008347"
    ],
    "id": 1021388,
    "name:xx": "Espírito Santo do Dourado"
  }
}
