{
  "geometry": {
    "type": "Point",
    "coordinates": [
      -109.7167,
      32.6333
    ]
  },
  "type": "Feature",
  "properties": {
    "hierarchy": [
      "tgn:2695996",
      "tgn:1000001",
      "tgn:7006451",
      "tgn:2000094",
      "tgn:7012149",
      "tgn:7029392"
    ],
    "placetype": [
      "aat:300008699"
    ],
    "id": 2695996,
    "name:xx": "Stockton Wash"
  }
}
