{
  "geometry": {
    "type": "Point",
    "coordinates": [
      -85.4667,
      34.4667
    ]
  },
  "type": "Feature",
  "properties": {
    "hierarchy": [
      "tgn:2296100",
      "tgn:1000001",
      "tgn:2000318",
      "tgn:7012149",
      "tgn:7007248",
      "tgn:7029392"
    ],
    "placetype": [
      "aat:300008699"
    ],
    "id": 2296100,
    "name:xx": "Dry Branch"
  }
}
