{
  "geometry": {
    "type": "Point",
    "coordinates": [
      -121.8333,
      46.4667
    ]
  },
  "type": "Feature",
  "properties": {
    "hierarchy": [
      "tgn:2466028",
      "tgn:1000001",
      "tgn:7012149",
      "tgn:1002594",
      "tgn:7007920",
      "tgn:7029392"
    ],
    "placetype": [
      "aat:300008798"
    ],
    "id": 2466028,
    "name:xx": "Lone Tree Mountain"
  }
}
