{
  "geometry": {
    "type": "Point",
    "coordinates": [
      -72.15,
      42.3333
    ]
  },
  "type": "Feature",
  "properties": {
    "hierarchy": [
      "tgn:2050355",
      "tgn:1000001",
      "tgn:7012149",
      "tgn:1003038",
      "tgn:7007517",
      "tgn:7029392"
    ],
    "placetype": [
      "aat:300008347",
      "aat:300387210"
    ],
    "id": 2050355,
    "name:xx": "Furnace"
  }
}
