{
  "geometry": {
    "type": "Point",
    "coordinates": [
      94.1333,
      28.1833
    ]
  },
  "type": "Feature",
  "properties": {
    "hierarchy": [
      "tgn:1070366",
      "tgn:1000004",
      "tgn:7001319",
      "tgn:1000111",
      "tgn:7029392"
    ],
    "placetype": [
      "aat:300008347"
    ],
    "id": 1070366,
    "name:xx": "Mara"
  }
}
