{
  "geometry": {
    "type": "Point",
    "coordinates": [
      22.7167,
      10.3667
    ]
  },
  "type": "Feature",
  "properties": {
    "hierarchy": [
      "tgn:1111438",
      "tgn:7001242",
      "tgn:7029392"
    ],
    "placetype": [
      "aat:300008773"
    ],
    "id": 1111438,
    "name:xx": "Tiwal, Wâdi"
  }
}
