{
  "geometry": {
    "type": "Point",
    "coordinates": [
      -123.55,
      40.4333
    ]
  },
  "type": "Feature",
  "properties": {
    "hierarchy": [
      "tgn:2721072",
      "tgn:1000001",
      "tgn:7012149",
      "tgn:2000181",
      "tgn:7007157",
      "tgn:7029392"
    ],
    "placetype": [
      "aat:300008798"
    ],
    "id": 2721072,
    "name:xx": "Tierney Peak"
  }
}
