{
  "geometry": {
    "type": "Point",
    "coordinates": [
      -86.6167,
      39.4833
    ]
  },
  "type": "Feature",
  "properties": {
    "hierarchy": [
      "tgn:2497349",
      "tgn:1000001",
      "tgn:7012149",
      "tgn:1002694",
      "tgn:7007252",
      "tgn:7029392"
    ],
    "placetype": [
      "aat:300006191"
    ],
    "id": 2497349,
    "name:xx": "Maxine, Lake"
  }
}
