{
  "geometry": {
    "type": "Point",
    "coordinates": [
      -79.6833,
      41.55
    ]
  },
  "type": "Feature",
  "properties": {
    "hierarchy": [
      "tgn:2163327",
      "tgn:1000001",
      "tgn:7012149",
      "tgn:1002971",
      "tgn:7007710",
      "tgn:7029392"
    ],
    "placetype": [
      "aat:300008699"
    ],
    "id": 2163327,
    "name:xx": "Benninghof Run"
  }
}
