{
  "geometry": {
    "type": "Point",
    "coordinates": [
      -80.6333,
      39.2167
    ]
  },
  "type": "Feature",
  "properties": {
    "hierarchy": [
      "tgn:2612840",
      "tgn:1000001",
      "tgn:2002260",
      "tgn:7012149",
      "tgn:7013961",
      "tgn:7029392"
    ],
    "placetype": [
      "aat:300008699"
    ],
    "id": 2612840,
    "name:xx": "Redlick Run"
  }
}
