{
  "geometry": {
    "type": "Point",
    "coordinates": [
      -88.65,
      36.7333
    ]
  },
  "type": "Feature",
  "properties": {
    "hierarchy": [
      "tgn:2649834",
      "tgn:1000001",
      "tgn:7012149",
      "tgn:2000792",
      "tgn:7007255",
      "tgn:7029392"
    ],
    "placetype": [
      "aat:300006075"
    ],
    "id": 2649834,
    "name:xx": "Scroggins Ditch"
  }
}
