{
  "geometry": {
    "type": "Point",
    "coordinates": [
      -124.1333,
      43.1167
    ]
  },
  "type": "Feature",
  "properties": {
    "hierarchy": [
      "tgn:2661694",
      "tgn:1000001",
      "tgn:2001702",
      "tgn:7012149",
      "tgn:7007708",
      "tgn:7029392"
    ],
    "placetype": [
      "aat:300008798"
    ],
    "id": 2661694,
    "name:xx": "Shuck Mountain"
  }
}
