{
  "type": "FeatureCollection",
  "features": [
    {
      "geometry": {
        "type": "Point",
        "coordinates": [
          -100.2,
          46.0167
        ]
      },
      "type": "Feature",
      "properties": {
        "hierarchy": [
          "tgn:2078100",
          "tgn:1000001",
          "tgn:2001571",
          "tgn:7012149",
          "tgn:7007705",
          "tgn:7029392"
        ],
        "placetype": [
          "aat:300008347"
        ],
        "id": 2078100,
        "name:xx": "Westfield"
      }
    },
    {
      "geometry": {
        "type": "Point",
        "coordinates": [
          -101.0167,
          48.9
        ]
      },
      "type": "Feature",
      "properties": {
        "hierarchy": [
          "tgn:2078101",
          "tgn:7020393",
          "tgn:1000001",
          "tgn:7012149",
          "tgn:7007705",
          "tgn:7029392"
        ],
        "placetype": [
          "aat:300008347"
        ],
        "id": 2078101,
        "name:xx": "Westhope"
      }
    },
    {
      "geometry": {
        "type": "Point",
        "coordinates": [
          -97.3333,
          46.9
        ]
      },
      "type": "Feature",
      "properties": {
        "hierarchy": [
          "tgn:2078103",
          "tgn:2001565",
          "tgn:1000001",
          "tgn:7012149",
          "tgn:7007705",
          "tgn:7029392"
        ],
        "placetype": [
          "aat:300008347"
        ],
        "id": 2078103,
        "name:xx": "Wheatland"
      }
    },
    {
      "geometry": {
        "type": "Point",
        "coordinates": [
          -103.25,
          48.2833
        ]
      },
      "type": "Feature",
      "properties": {
        "hierarchy": [
          "tgn:2078104",
          "tgn:1000001",
          "tgn:7012149",
          "tgn:2001609",
          "tgn:7007705",
          "tgn:7029392"
        ],
        "placetype": [
          "aat:300008347"
        ],
        "id": 2078104,
        "name:xx": "Wheelock"
      }
    },
    {
      "geometry": {
        "type": "Point",
        "coordinates": [
          -102.7667,
          48.3667
        ]
      },
      "type": "Feature",
      "properties": {
        "hierarchy": [
          "tgn:2078105",
          "tgn:1000001",
          "tgn:2001587",
          "tgn:7012149",
          "tgn:7007705",
          "tgn:7029392"
        ],
        "placetype": [
          "aat:300008347"
        ],
        "id": 2078105,
        "name:xx": "White Earth"
      }
    },
    {
      "geometry": {
        "type": "Point",
        "coordinates": [
          -98.1167,
          48.15
        ]
      },
      "type": "Feature",
      "properties": {
        "hierarchy": [
          "tgn:2078107",
          "tgn:1000001",
          "tgn:2001588",
          "tgn:7012149",
          "tgn:7007705",
          "tgn:7029392"
        ],
        "placetype": [
          "aat:300008347"
        ],
        "id": 2078107,
        "name:xx": "Whitman"
      }
    },
    {
      "geometry": {
        "type": "Point",
        "coordinates": [
          -96.8,
          46.7333
        ]
      },
      "type": "Feature",
      "properties": {
        "hierarchy": [
          "tgn:2078108",
          "tgn:2001565",
          "tgn:1000001",
          "tgn:7012149",
          "tgn:7007705",
          "tgn:7029392"
        ],
        "placetype": [
          "aat:300008347",
          "aat:300387210"
        ],
        "id": 2078108,
        "name:xx": "Wild Rice"
      }
    },
    {
      "geometry": {
        "type": "Point",
        "coordinates": [
          -103.1833,
          48.6167
        ]
      },
      "type": "Feature",
      "properties": {
        "hierarchy": [
          "tgn:2078109",
          "tgn:1000001",
          "tgn:7012149",
          "tgn:2001609",
          "tgn:7007705",
          "tgn:7029392"
        ],
        "placetype": [
          "aat:300008347"
        ],
        "id": 2078109,
        "name:xx": "Wildrose"
      }
    }
  ]
}
