{
  "geometry": {
    "type": "Point",
    "coordinates": [
      -103.3833,
      37.05
    ]
  },
  "type": "Feature",
  "properties": {
    "hierarchy": [
      "tgn:2331293",
      "tgn:1000001",
      "tgn:7012149",
      "tgn:7029392"
    ],
    "placetype": [
      "aat:300008761"
    ],
    "id": 2331293,
    "name:xx": "Flathead Canyon"
  }
}
