{
  "geometry": {
    "type": "Point",
    "coordinates": [
      -105.2333,
      42.85
    ]
  },
  "type": "Feature",
  "properties": {
    "hierarchy": [
      "tgn:2664998",
      "tgn:1000001",
      "tgn:2002369",
      "tgn:7012149",
      "tgn:7007923",
      "tgn:7029392"
    ],
    "placetype": [
      "aat:300008761"
    ],
    "id": 2664998,
    "name:xx": "Simpson Draw"
  }
}
