{
  "geometry": {
    "type": "Point",
    "coordinates": [
      76.17262,
      30.648267
    ]
  },
  "type": "Feature",
  "properties": {
    "hierarchy": [
      "tgn:7583368",
      "tgn:1000004",
      "tgn:7000198",
      "tgn:7016883",
      "tgn:7029392"
    ],
    "placetype": [
      "aat:300008347"
    ],
    "name:en": "Ghotind",
    "id": 7583368
  }
}
