{
  "geometry": {
    "type": "Point",
    "coordinates": [
      -91.0667,
      38.2667
    ]
  },
  "type": "Feature",
  "properties": {
    "hierarchy": [
      "tgn:2621566",
      "tgn:1000001",
      "tgn:7012149",
      "tgn:1002384",
      "tgn:7007523",
      "tgn:7029392"
    ],
    "placetype": [
      "aat:300008697"
    ],
    "id": 2621566,
    "name:xx": "Roaring Spring"
  }
}
