{
  "geometry": {
    "type": "Point",
    "coordinates": [
      -119.7833,
      40.6167
    ]
  },
  "type": "Feature",
  "properties": {
    "hierarchy": [
      "tgn:2204780",
      "tgn:1000001",
      "tgn:7012149",
      "tgn:1002999",
      "tgn:7007526",
      "tgn:7029392"
    ],
    "placetype": [
      "aat:300008699"
    ],
    "id": 2204780,
    "name:xx": "Buffalo Slough"
  }
}
