{
  "geometry": {
    "type": "Point",
    "coordinates": [
      -83.8333,
      43.5167
    ]
  },
  "type": "Feature",
  "properties": {
    "hierarchy": [
      "tgn:2293895",
      "tgn:1000001",
      "tgn:7012149",
      "tgn:7007520",
      "tgn:7029392"
    ],
    "placetype": [
      "aat:300006075"
    ],
    "id": 2293895,
    "name:xx": "Douglas Drain"
  }
}
