{
  "geometry": {
    "type": "Point",
    "coordinates": [
      -57.85,
      -38.1167
    ]
  },
  "type": "Feature",
  "properties": {
    "hierarchy": [
      "tgn:1019340",
      "tgn:1001160",
      "tgn:7006477",
      "tgn:1000002",
      "tgn:7029392"
    ],
    "placetype": [
      "aat:300008347"
    ],
    "id": 1019340,
    "name:xx": "Comandante Nicanor Otamendi"
  }
}
