{
  "geometry": {
    "type": "Point",
    "coordinates": [
      -120.1167,
      47.2667
    ]
  },
  "type": "Feature",
  "properties": {
    "hierarchy": [
      "tgn:2649827",
      "tgn:1000001",
      "tgn:1002260",
      "tgn:7012149",
      "tgn:7007920",
      "tgn:7029392"
    ],
    "placetype": [
      "aat:300008761"
    ],
    "id": 2649827,
    "name:xx": "Scroggie Canyon"
  }
}
