{
  "geometry": {
    "type": "Point",
    "coordinates": [
      -91.1167,
      29.65
    ]
  },
  "type": "Feature",
  "properties": {
    "hierarchy": [
      "tgn:2317799",
      "tgn:1000001",
      "tgn:7012149",
      "tgn:2000904",
      "tgn:7007256",
      "tgn:7029392"
    ],
    "placetype": [
      "aat:300008347"
    ],
    "id": 2317799,
    "name:xx": "Englewood"
  }
}
