{
  "type": "FeatureCollection",
  "features": [
    {
      "geometry": {
        "type": "Point",
        "coordinates": [
          1.25,
          52.116667
        ]
      },
      "type": "Feature",
      "properties": {
        "hierarchy": [
          "tgn:4002730",
          "tgn:7002445",
          "tgn:1000003",
          "tgn:7012031",
          "tgn:7008591",
          "tgn:7029392"
        ],
        "placetype": [
          "aat:300008347",
          "aat:300008372"
        ],
        "name:en": "Clopton",
        "id": 4002730
      }
    },
    {
      "geometry": {
        "type": "Point",
        "coordinates": [
          -3.733333,
          55.216667
        ]
      },
      "type": "Feature",
      "properties": {
        "hierarchy": [
          "tgn:4002732",
          "tgn:7002444",
          "tgn:7008074",
          "tgn:1000003",
          "tgn:7008591",
          "tgn:7029392"
        ],
        "placetype": [
          "aat:300008347"
        ],
        "name:en": "Closeburn",
        "id": 4002732
      }
    }
  ]
}
