{
  "geometry": {
    "type": "Point",
    "coordinates": [
      103.95,
      1.3833
    ]
  },
  "type": "Feature",
  "properties": {
    "hierarchy": [
      "tgn:1114516",
      "tgn:1000004",
      "tgn:1000138",
      "tgn:7000381",
      "tgn:7029392"
    ],
    "placetype": [
      "aat:300008678"
    ],
    "id": 1114516,
    "name:xx": "Serangoon Harbour"
  }
}
