{
  "geometry": {
    "type": "Point",
    "coordinates": [
      91.266667,
      26.516667
    ]
  },
  "type": "Feature",
  "properties": {
    "hierarchy": [
      "tgn:1076488",
      "tgn:1000004",
      "tgn:1001832",
      "tgn:7000198",
      "tgn:7029392"
    ],
    "placetype": [
      "aat:300008347"
    ],
    "name:en": "Pātāchārkuchi",
    "id": 1076488
  }
}
