{
  "geometry": {
    "type": "Point",
    "coordinates": [
      -74.8833,
      22.85
    ]
  },
  "type": "Feature",
  "properties": {
    "hierarchy": [
      "tgn:1012499",
      "tgn:7005332",
      "tgn:7593498",
      "tgn:1000001",
      "tgn:7029392"
    ],
    "placetype": [
      "aat:300386846"
    ],
    "id": 1012499,
    "name:xx": "South Point"
  }
}
