{
  "geometry": {
    "type": "Point",
    "coordinates": [
      -109.0333,
      33.1167
    ]
  },
  "type": "Feature",
  "properties": {
    "hierarchy": [
      "tgn:2376269",
      "tgn:1000001",
      "tgn:7012149",
      "tgn:7029392"
    ],
    "placetype": [
      "aat:300008706"
    ],
    "id": 2376269,
    "name:xx": "Harden Cienega Creek"
  }
}
