{
  "geometry": {
    "type": "Point",
    "coordinates": [
      -90.2333,
      36.8833
    ]
  },
  "type": "Feature",
  "properties": {
    "hierarchy": [
      "tgn:2288727",
      "tgn:1000001",
      "tgn:7012149",
      "tgn:2001248",
      "tgn:7007523",
      "tgn:7029392"
    ],
    "placetype": [
      "aat:300006075"
    ],
    "id": 2288727,
    "name:xx": "Ditch Number 13"
  }
}
