{
  "geometry": {
    "type": "Point",
    "coordinates": [
      -116.9333,
      34.1833
    ]
  },
  "type": "Feature",
  "properties": {
    "hierarchy": [
      "tgn:2641233",
      "tgn:1000001",
      "tgn:7012149",
      "tgn:7007157",
      "tgn:1002857",
      "tgn:7029392"
    ],
    "placetype": [
      "aat:300008706"
    ],
    "id": 2641233,
    "name:xx": "Sand Creek"
  }
}
