{
  "geometry": {
    "type": "Point",
    "coordinates": [
      -90.0333,
      37.3333
    ]
  },
  "type": "Feature",
  "properties": {
    "hierarchy": [
      "tgn:2001174",
      "tgn:1000001",
      "tgn:7012149",
      "tgn:7007523",
      "tgn:7029392"
    ],
    "placetype": [
      "aat:300387145",
      "aat:300000771"
    ],
    "id": 2001174,
    "name:xx": "Bollinger"
  }
}
