{
  "geometry": {
    "type": "Point",
    "coordinates": [
      -90.15,
      38.4833
    ]
  },
  "type": "Feature",
  "properties": {
    "hierarchy": [
      "tgn:2683395",
      "tgn:1000001",
      "tgn:7012149",
      "tgn:7016022",
      "tgn:7007251",
      "tgn:7029392"
    ],
    "placetype": [
      "aat:300008706"
    ],
    "id": 2683395,
    "name:xx": "Sparrow Creek"
  }
}
