{
  "type": "FeatureCollection",
  "features": [
    {
      "geometry": {
        "type": "Point",
        "coordinates": [
          -94.1333,
          31.6667
        ]
      },
      "type": "Feature",
      "properties": {
        "hierarchy": [
          "tgn:2106251",
          "tgn:1000001",
          "tgn:7012149",
          "tgn:2002073",
          "tgn:7007826",
          "tgn:7029392"
        ],
        "placetype": [
          "aat:300008347"
        ],
        "id": 2106251,
        "name:xx": "Neuville"
      }
    },
    {
      "geometry": {
        "type": "Point",
        "coordinates": [
          -96.3667,
          33.0333
        ]
      },
      "type": "Feature",
      "properties": {
        "hierarchy": [
          "tgn:2106252",
          "tgn:1000001",
          "tgn:7012149",
          "tgn:1002290",
          "tgn:7007826",
          "tgn:7029392"
        ],
        "placetype": [
          "aat:300008347"
        ],
        "id": 2106252,
        "name:xx": "Nevada"
      }
    },
    {
      "geometry": {
        "type": "Point",
        "coordinates": [
          -97.4833,
          33
        ]
      },
      "type": "Feature",
      "properties": {
        "hierarchy": [
          "tgn:2106253",
          "tgn:1000001",
          "tgn:7012149",
          "tgn:1003031",
          "tgn:7007826",
          "tgn:7029392"
        ],
        "placetype": [
          "aat:300008347"
        ],
        "id": 2106253,
        "name:xx": "Newark"
      }
    },
    {
      "geometry": {
        "type": "Point",
        "coordinates": [
          -96.4167,
          31.05
        ]
      },
      "type": "Feature",
      "properties": {
        "hierarchy": [
          "tgn:2106254",
          "tgn:1000001",
          "tgn:7012149",
          "tgn:1002830",
          "tgn:7007826",
          "tgn:7029392"
        ],
        "placetype": [
          "aat:300008347"
        ],
        "id": 2106254,
        "name:xx": "New Baden"
      }
    },
    {
      "geometry": {
        "type": "Point",
        "coordinates": [
          -98.1,
          29.45
        ]
      },
      "type": "Feature",
      "properties": {
        "hierarchy": [
          "tgn:2106255",
          "tgn:1000001",
          "tgn:7012149",
          "tgn:1002431",
          "tgn:7007826",
          "tgn:7029392"
        ],
        "placetype": [
          "aat:300008347"
        ],
        "id": 2106255,
        "name:xx": "New Berlin"
      }
    },
    {
      "geometry": {
        "type": "Point",
        "coordinates": [
          -95.5833,
          33.2667
        ]
      },
      "type": "Feature",
      "properties": {
        "hierarchy": [
          "tgn:2106257",
          "tgn:1000001",
          "tgn:7012149",
          "tgn:1002485",
          "tgn:7007826",
          "tgn:7029392"
        ],
        "placetype": [
          "aat:300008347",
          "aat:300387210"
        ],
        "id": 2106257,
        "name:xx": "New Birthright"
      }
    },
    {
      "geometry": {
        "type": "Point",
        "coordinates": [
          -94.4,
          33.45
        ]
      },
      "type": "Feature",
      "properties": {
        "hierarchy": [
          "tgn:2106258",
          "tgn:1000001",
          "tgn:2001944",
          "tgn:7012149",
          "tgn:7007826",
          "tgn:7029392"
        ],
        "placetype": [
          "aat:300008347"
        ],
        "id": 2106258,
        "name:xx": "New Boston"
      }
    }
  ]
}
