{
  "type": "FeatureCollection",
  "features": [
    {
      "geometry": {
        "type": "Point",
        "coordinates": [
          10.75,
          53.2
        ]
      },
      "type": "Feature",
      "properties": {
        "hierarchy": [
          "tgn:7206322",
          "tgn:1000003",
          "tgn:7003676",
          "tgn:7000084",
          "tgn:7029392"
        ],
        "placetype": [
          "aat:300008347"
        ],
        "id": 7206322,
        "name:xx": "Dahlem"
      }
    },
    {
      "geometry": {
        "type": "Point",
        "coordinates": [
          6.6,
          49.916667
        ]
      },
      "type": "Feature",
      "properties": {
        "hierarchy": [
          "tgn:7206324",
          "tgn:1000003",
          "tgn:7003682",
          "tgn:7000084",
          "tgn:7029392"
        ],
        "placetype": [
          "aat:300008347"
        ],
        "id": 7206324,
        "name:xx": "Dahlem"
      }
    },
    {
      "geometry": {
        "type": "Point",
        "coordinates": [
          13.2,
          51.433333
        ]
      },
      "type": "Feature",
      "properties": {
        "hierarchy": [
          "tgn:7206326",
          "tgn:1000003",
          "tgn:7003685",
          "tgn:7000084",
          "tgn:7029392"
        ],
        "placetype": [
          "aat:300008699"
        ],
        "id": 7206326,
        "name:xx": "Dahle"
      }
    },
    {
      "geometry": {
        "type": "Point",
        "coordinates": [
          9.516667,
          52.2
        ]
      },
      "type": "Feature",
      "properties": {
        "hierarchy": [
          "tgn:7206327",
          "tgn:1000003",
          "tgn:7003676",
          "tgn:7000084",
          "tgn:7029392"
        ],
        "placetype": [
          "aat:300008347"
        ],
        "id": 7206327,
        "name:xx": "Dahle"
      }
    },
    {
      "geometry": {
        "type": "Point",
        "coordinates": [
          8.983333,
          53.383333
        ]
      },
      "type": "Feature",
      "properties": {
        "hierarchy": [
          "tgn:7206329",
          "tgn:1000003",
          "tgn:7003676",
          "tgn:7000084",
          "tgn:7029392"
        ],
        "placetype": [
          "aat:300008347"
        ],
        "id": 7206329,
        "name:xx": "Dahldorf"
      }
    }
  ]
}
