{
  "geometry": {
    "type": "Point",
    "coordinates": [
      -80.5833,
      39.7667
    ]
  },
  "type": "Feature",
  "properties": {
    "hierarchy": [
      "tgn:2328143",
      "tgn:1000001",
      "tgn:7012149",
      "tgn:2002276",
      "tgn:7013961",
      "tgn:7029392"
    ],
    "placetype": [
      "aat:300266640"
    ],
    "id": 2328143,
    "name:xx": "Fish Ridge"
  }
}
