{
  "geometry": {
    "type": "Point",
    "coordinates": [
      31.842906,
      30.706882
    ]
  },
  "type": "Feature",
  "properties": {
    "hierarchy": [
      "tgn:7540459",
      "tgn:7001242",
      "tgn:7016833",
      "tgn:1001113",
      "tgn:7029392"
    ],
    "placetype": [
      "aat:300008347"
    ],
    "name:en": "Sawādah",
    "id": 7540459
  }
}
