{
  "geometry": {
    "type": "Point",
    "coordinates": [
      -75.3167,
      41.3667
    ]
  },
  "type": "Feature",
  "properties": {
    "hierarchy": [
      "tgn:2090043",
      "tgn:1000001",
      "tgn:7012149",
      "tgn:1003008",
      "tgn:7007710",
      "tgn:7029392"
    ],
    "placetype": [
      "aat:300008347"
    ],
    "id": 2090043,
    "name:xx": "Ledgedale"
  }
}
