{
  "geometry": {
    "type": "Point",
    "coordinates": [
      152.95,
      -27.1667
    ]
  },
  "type": "Feature",
  "properties": {
    "hierarchy": [
      "tgn:1096434",
      "tgn:7000490",
      "tgn:1000006",
      "tgn:7001830",
      "tgn:7029392"
    ],
    "placetype": [
      "aat:300008347"
    ],
    "id": 1096434,
    "name:xx": "Burpengary"
  }
}
