{
  "geometry": {
    "type": "Point",
    "coordinates": [
      -121.8167,
      45.9333
    ]
  },
  "type": "Feature",
  "properties": {
    "hierarchy": [
      "tgn:2604869",
      "tgn:1000001",
      "tgn:7012149",
      "tgn:1002897",
      "tgn:7007920",
      "tgn:7029392"
    ],
    "placetype": [
      "aat:300008680"
    ],
    "id": 2604869,
    "name:xx": "Race Track Lakes"
  }
}
