{
  "geometry": {
    "type": "Point",
    "coordinates": [
      -117.6333,
      45.1667
    ]
  },
  "type": "Feature",
  "properties": {
    "hierarchy": [
      "tgn:2156624",
      "tgn:1000001",
      "tgn:7012149",
      "tgn:2001721",
      "tgn:7007708",
      "tgn:7029392"
    ],
    "placetype": [
      "aat:300008697"
    ],
    "id": 2156624,
    "name:xx": "Bearwallow Spring"
  }
}
