{
  "geometry": {
    "type": "Point",
    "coordinates": [
      -62.6333,
      -3.6167
    ]
  },
  "type": "Feature",
  "properties": {
    "hierarchy": [
      "tgn:1115349",
      "tgn:1001826",
      "tgn:1000047",
      "tgn:7002456",
      "tgn:1000002",
      "tgn:7029392"
    ],
    "placetype": [
      "aat:300008680"
    ],
    "id": 1115349,
    "name:xx": "Acará, Lago"
  }
}
