{
  "geometry": {
    "type": "Point",
    "coordinates": [
      -76.6333,
      43.3667
    ]
  },
  "type": "Feature",
  "properties": {
    "hierarchy": [
      "tgn:2662259",
      "tgn:1000001",
      "tgn:1002246",
      "tgn:7012149",
      "tgn:7007568",
      "tgn:7029392"
    ],
    "placetype": [
      "aat:300008798"
    ],
    "id": 2662259,
    "name:xx": "Sidmans Hill"
  }
}
