{
  "geometry": {
    "type": "Point",
    "coordinates": [
      -119.85,
      37.8667
    ]
  },
  "type": "Feature",
  "properties": {
    "hierarchy": [
      "tgn:2173504",
      "tgn:1000001",
      "tgn:7012149",
      "tgn:7007157",
      "tgn:1002957",
      "tgn:7029392"
    ],
    "placetype": [
      "aat:300008680"
    ],
    "id": 2173504,
    "name:xx": "Birch Lake"
  }
}
