{
  "geometry": {
    "type": "Point",
    "coordinates": [
      -112.3667,
      48.45
    ]
  },
  "type": "Feature",
  "properties": {
    "hierarchy": [
      "tgn:2534296",
      "tgn:1000001",
      "tgn:7012149",
      "tgn:2001296",
      "tgn:7007524",
      "tgn:7029392"
    ],
    "placetype": [
      "aat:300006075"
    ],
    "id": 2534296,
    "name:xx": "N Canal"
  }
}
