{
  "geometry": {
    "type": "Point",
    "coordinates": [
      -98.3833,
      43.1833
    ]
  },
  "type": "Feature",
  "properties": {
    "hierarchy": [
      "tgn:2424263",
      "tgn:1000001",
      "tgn:2001781",
      "tgn:7012149",
      "tgn:7007713",
      "tgn:7029392"
    ],
    "placetype": [
      "aat:300132316"
    ],
    "id": 2424263,
    "name:xx": "Johnson Bay"
  }
}
