{
  "geometry": {
    "type": "Point",
    "coordinates": [
      30.227139,
      31.14491
    ]
  },
  "type": "Feature",
  "properties": {
    "hierarchy": [
      "tgn:7529500",
      "tgn:7001242",
      "tgn:1001075",
      "tgn:7016833",
      "tgn:7029392"
    ],
    "placetype": [
      "aat:300008347"
    ],
    "name:en": "Tamāmah",
    "id": 7529500
  }
}
