{
  "geometry": {
    "type": "Point",
    "coordinates": [
      30.720567,
      31.283709
    ]
  },
  "type": "Feature",
  "properties": {
    "hierarchy": [
      "tgn:7531689",
      "tgn:7001242",
      "tgn:7016833",
      "tgn:1001335",
      "tgn:7029392"
    ],
    "placetype": [
      "aat:300008347"
    ],
    "name:en": "Al Ḩarīrī",
    "id": 7531689
  }
}
