{
  "geometry": {
    "type": "Point",
    "coordinates": [
      -74.95,
      39.4667
    ]
  },
  "type": "Feature",
  "properties": {
    "hierarchy": [
      "tgn:2505591",
      "tgn:1002309",
      "tgn:1000001",
      "tgn:7012149",
      "tgn:7007565",
      "tgn:7029392"
    ],
    "placetype": [
      "aat:300006191"
    ],
    "id": 2505591,
    "name:xx": "Memorial Park Pond"
  }
}
