{
  "geometry": {
    "type": "Point",
    "coordinates": [
      -98.25,
      38.8167
    ]
  },
  "type": "Feature",
  "properties": {
    "hierarchy": [
      "tgn:2761501",
      "tgn:1000001",
      "tgn:2000686",
      "tgn:7012149",
      "tgn:7007254",
      "tgn:7029392"
    ],
    "placetype": [
      "aat:300008706"
    ],
    "id": 2761501,
    "name:xx": "West Oak Creek"
  }
}
