{
  "geometry": {
    "type": "Point",
    "coordinates": [
      -81.4167,
      32.0167
    ]
  },
  "type": "Feature",
  "properties": {
    "hierarchy": [
      "tgn:2697274",
      "tgn:2001727",
      "tgn:1000001",
      "tgn:7012149",
      "tgn:7007712",
      "tgn:7029392"
    ],
    "placetype": [
      "aat:300008706"
    ],
    "id": 2697274,
    "name:xx": "Stony Creek"
  }
}
