{
  "geometry": {
    "type": "Point",
    "coordinates": [
      -81.1333,
      32.0667
    ]
  },
  "type": "Feature",
  "properties": {
    "hierarchy": [
      "tgn:2127577",
      "tgn:1000001",
      "tgn:2000316",
      "tgn:7012149",
      "tgn:7007248",
      "tgn:7029392"
    ],
    "placetype": [
      "aat:300008347"
    ],
    "id": 2127577,
    "name:xx": "Alabama Junction"
  }
}
