{
  "geometry": {
    "type": "Point",
    "coordinates": [
      -79.8833,
      39.9667
    ]
  },
  "type": "Feature",
  "properties": {
    "hierarchy": [
      "tgn:2726244",
      "tgn:1000001",
      "tgn:7012149",
      "tgn:7014185",
      "tgn:7007710",
      "tgn:7029392"
    ],
    "placetype": [
      "aat:300008347"
    ],
    "id": 2726244,
    "name:xx": "Tower Hill Number Two"
  }
}
