{
  "geometry": {
    "type": "Point",
    "coordinates": [
      -85.45,
      39.7333
    ]
  },
  "type": "Feature",
  "properties": {
    "hierarchy": [
      "tgn:2350046",
      "tgn:1000001",
      "tgn:7012149",
      "tgn:1002838",
      "tgn:7007252",
      "tgn:7029392"
    ],
    "placetype": [
      "aat:300008706"
    ],
    "id": 2350046,
    "name:xx": "Gilson Creek"
  }
}
