{
  "geometry": {
    "type": "Point",
    "coordinates": [
      -122.2167,
      41.6167
    ]
  },
  "type": "Feature",
  "properties": {
    "hierarchy": [
      "tgn:2386508",
      "tgn:1000001",
      "tgn:7012149",
      "tgn:7007157",
      "tgn:2000189",
      "tgn:7029392"
    ],
    "placetype": [
      "aat:300008798"
    ],
    "id": 2386508,
    "name:xx": "Herd Peak"
  }
}
