{
  "geometry": {
    "type": "Point",
    "coordinates": [
      -119.55,
      34.45
    ]
  },
  "type": "Feature",
  "properties": {
    "hierarchy": [
      "tgn:2725774",
      "tgn:1000001",
      "tgn:7012149",
      "tgn:7007157",
      "tgn:1002867",
      "tgn:7029392"
    ],
    "placetype": [
      "aat:300008706"
    ],
    "id": 2725774,
    "name:xx": "Toro Canyon Creek"
  }
}
