{
  "geometry": {
    "type": "Point",
    "coordinates": [
      -96.8167,
      35.4667
    ]
  },
  "type": "Feature",
  "properties": {
    "hierarchy": [
      "tgn:2690618",
      "tgn:1000001",
      "tgn:7012149",
      "tgn:7007707",
      "tgn:7029392"
    ],
    "placetype": [
      "aat:300008706"
    ],
    "id": 2690618,
    "name:xx": "Stamp Dance Creek"
  }
}
