{
  "geometry": {
    "type": "Point",
    "coordinates": [
      -76.6167,
      34.7667
    ]
  },
  "type": "Feature",
  "properties": {
    "hierarchy": [
      "tgn:2717789",
      "tgn:1000001",
      "tgn:2001477",
      "tgn:7012149",
      "tgn:7007709",
      "tgn:7029392"
    ],
    "placetype": [
      "aat:300008905"
    ],
    "id": 2717789,
    "name:xx": "Thomas Marsh"
  }
}
