{
  "geometry": {
    "type": "Point",
    "coordinates": [
      -105.3333,
      47.9333
    ]
  },
  "type": "Feature",
  "properties": {
    "hierarchy": [
      "tgn:2294494",
      "tgn:1000001",
      "tgn:7012149",
      "tgn:2001287",
      "tgn:7007524",
      "tgn:7029392"
    ],
    "placetype": [
      "aat:300008761"
    ],
    "id": 2294494,
    "name:xx": "Dowse Coulee"
  }
}
