{
  "geometry": {
    "type": "Point",
    "coordinates": [
      70.703102,
      25.869044
    ]
  },
  "type": "Feature",
  "properties": {
    "hierarchy": [
      "tgn:7577887",
      "tgn:1000004",
      "tgn:7000198",
      "tgn:7016788",
      "tgn:7029392"
    ],
    "placetype": [
      "aat:300008347"
    ],
    "name:en": "Khudāni",
    "id": 7577887
  }
}
