{
  "geometry": {
    "type": "Point",
    "coordinates": [
      -113.65,
      41.6333
    ]
  },
  "type": "Feature",
  "properties": {
    "hierarchy": [
      "tgn:2295985",
      "tgn:1000001",
      "tgn:2002102",
      "tgn:7012149",
      "tgn:7007827",
      "tgn:7029392"
    ],
    "placetype": [
      "aat:300386845"
    ],
    "id": 2295985,
    "name:xx": "Dry Basin"
  }
}
