{
  "geometry": {
    "type": "Point",
    "coordinates": [
      -83.2667,
      39.1833
    ]
  },
  "type": "Feature",
  "properties": {
    "hierarchy": [
      "tgn:2764834",
      "tgn:1000001",
      "tgn:7012149",
      "tgn:1002788",
      "tgn:7007706",
      "tgn:7029392"
    ],
    "placetype": [
      "aat:300008761"
    ],
    "id": 2764834,
    "name:xx": "Whiskey Hollow"
  }
}
