{
  "geometry": {
    "type": "Point",
    "coordinates": [
      31.244359,
      30.24356
    ]
  },
  "type": "Feature",
  "properties": {
    "hierarchy": [
      "tgn:1095143",
      "tgn:7001242",
      "tgn:7016833",
      "tgn:1001092",
      "tgn:7029392"
    ],
    "placetype": [
      "aat:300008347"
    ],
    "id": 1095143,
    "name:xx": "Ţanān"
  }
}
