{
  "type": "FeatureCollection",
  "features": [
    {
      "geometry": {
        "type": "Point",
        "coordinates": [
          -81.15,
          28.8
        ]
      },
      "type": "Feature",
      "properties": {
        "hierarchy": [
          "tgn:2718970",
          "tgn:1000001",
          "tgn:7012149",
          "tgn:1002977",
          "tgn:7007240",
          "tgn:7029392"
        ],
        "placetype": [
          "aat:300008680"
        ],
        "id": 2718970,
        "name:xx": "Thornhill Lake"
      }
    },
    {
      "geometry": {
        "type": "Point",
        "coordinates": [
          -80.8167,
          37.1
        ]
      },
      "type": "Feature",
      "properties": {
        "hierarchy": [
          "tgn:2718971",
          "tgn:1000001",
          "tgn:7012149",
          "tgn:2002183",
          "tgn:7007919",
          "tgn:7029392"
        ],
        "placetype": [
          "aat:300006191"
        ],
        "id": 2718971,
        "name:xx": "Thornhill Pond"
      }
    },
    {
      "geometry": {
        "type": "Point",
        "coordinates": [
          -75.6,
          41.2
        ]
      },
      "type": "Feature",
      "properties": {
        "hierarchy": [
          "tgn:2718973",
          "tgn:1000001",
          "tgn:7012149",
          "tgn:1002564",
          "tgn:7007710",
          "tgn:7029392"
        ],
        "placetype": [
          "aat:300055621"
        ],
        "id": 2718973,
        "name:xx": "Thornhurst Picnic Area"
      }
    },
    {
      "geometry": {
        "type": "Point",
        "coordinates": [
          -80,
          33.2167
        ]
      },
      "type": "Feature",
      "properties": {
        "hierarchy": [
          "tgn:2718974",
          "tgn:2001732",
          "tgn:1000001",
          "tgn:7012149",
          "tgn:7007712",
          "tgn:7029392"
        ],
        "placetype": [
          "aat:300006191"
        ],
        "id": 2718974,
        "name:xx": "Thornley Pond"
      }
    },
    {
      "geometry": {
        "type": "Point",
        "coordinates": [
          -112,
          41.1
        ]
      },
      "type": "Feature",
      "properties": {
        "hierarchy": [
          "tgn:2718975",
          "tgn:1000001",
          "tgn:2002106",
          "tgn:7012149",
          "tgn:7007827",
          "tgn:7029392"
        ],
        "placetype": [
          "aat:300008347"
        ],
        "id": 2718975,
        "name:xx": "Thornleys"
      }
    },
    {
      "geometry": {
        "type": "Point",
        "coordinates": [
          -82.4,
          39.9
        ]
      },
      "type": "Feature",
      "properties": {
        "hierarchy": [
          "tgn:2718976",
          "tgn:1000001",
          "tgn:7012149",
          "tgn:2001620",
          "tgn:7007706",
          "tgn:7029392"
        ],
        "placetype": [
          "aat:300008347"
        ],
        "id": 2718976,
        "name:xx": "Thornport"
      }
    },
    {
      "geometry": {
        "type": "Point",
        "coordinates": [
          -110.8833,
          46.7167
        ]
      },
      "type": "Feature",
      "properties": {
        "hierarchy": [
          "tgn:2718977",
          "tgn:1000001",
          "tgn:7012149",
          "tgn:2001289",
          "tgn:7007524",
          "tgn:7029392"
        ],
        "placetype": [
          "aat:300008761"
        ],
        "id": 2718977,
        "name:xx": "Thornquist Gulch"
      }
    },
    {
      "geometry": {
        "type": "Point",
        "coordinates": [
          -81.4333,
          38.95
        ]
      },
      "type": "Feature",
      "properties": {
        "hierarchy": [
          "tgn:2718978",
          "tgn:1000001",
          "tgn:7012149",
          "tgn:2002302",
          "tgn:7013961",
          "tgn:7029392"
        ],
        "placetype": [
          "aat:300008699"
        ],
        "id": 2718978,
        "name:xx": "Thorns Run"
      }
    },
    {
      "geometry": {
        "type": "Point",
        "coordinates": [
          -114.6167,
          43.0833
        ]
      },
      "type": "Feature",
      "properties": {
        "hierarchy": [
          "tgn:2718979",
          "tgn:1000001",
          "tgn:7012149",
          "tgn:2000475",
          "tgn:7007250",
          "tgn:7029392"
        ],
        "placetype": [
          "aat:300132451"
        ],
        "id": 2718979,
        "name:xx": "Thorns, The"
      }
    }
  ]
}
