{
  "type": "FeatureCollection",
  "features": [
    {
      "geometry": {
        "type": "Point",
        "coordinates": [
          9.366667,
          50.15
        ]
      },
      "type": "Feature",
      "properties": {
        "hierarchy": [
          "tgn:7207330",
          "tgn:1000003",
          "tgn:7003678",
          "tgn:7000084",
          "tgn:7029392"
        ],
        "placetype": [
          "aat:300008777"
        ],
        "id": 7207330,
        "name:xx": "Burg-Berg"
      }
    },
    {
      "geometry": {
        "type": "Point",
        "coordinates": [
          7.1,
          50.083333
        ]
      },
      "type": "Feature",
      "properties": {
        "hierarchy": [
          "tgn:7207331",
          "tgn:1000003",
          "tgn:7003682",
          "tgn:7000084",
          "tgn:7029392"
        ],
        "placetype": [
          "aat:300008777"
        ],
        "id": 7207331,
        "name:xx": "Burg Berg"
      }
    },
    {
      "geometry": {
        "type": "Point",
        "coordinates": [
          9.783333,
          50.083333
        ]
      },
      "type": "Feature",
      "properties": {
        "hierarchy": [
          "tgn:7207332",
          "tgn:7003669",
          "tgn:1000003",
          "tgn:7000084",
          "tgn:7029392"
        ],
        "placetype": [
          "aat:300008777"
        ],
        "id": 7207332,
        "name:xx": "Burg-Berg"
      }
    },
    {
      "geometry": {
        "type": "Point",
        "coordinates": [
          6.2,
          50.033333
        ]
      },
      "type": "Feature",
      "properties": {
        "hierarchy": [
          "tgn:7207334",
          "tgn:1000003",
          "tgn:7003682",
          "tgn:7000084",
          "tgn:7029392"
        ],
        "placetype": [
          "aat:300008777"
        ],
        "id": 7207334,
        "name:xx": "Burg-Berg"
      }
    },
    {
      "geometry": {
        "type": "Point",
        "coordinates": [
          6.716667,
          49.833333
        ]
      },
      "type": "Feature",
      "properties": {
        "hierarchy": [
          "tgn:7207335",
          "tgn:1000003",
          "tgn:7003682",
          "tgn:7000084",
          "tgn:7029392"
        ],
        "placetype": [
          "aat:300008777"
        ],
        "id": 7207335,
        "name:xx": "Burg Berg"
      }
    },
    {
      "geometry": {
        "type": "Point",
        "coordinates": [
          6.65,
          49.85
        ]
      },
      "type": "Feature",
      "properties": {
        "hierarchy": [
          "tgn:7207337",
          "tgn:1000003",
          "tgn:7003682",
          "tgn:7000084",
          "tgn:7029392"
        ],
        "placetype": [
          "aat:300008777"
        ],
        "id": 7207337,
        "name:xx": "Burg-Berg"
      }
    },
    {
      "geometry": {
        "type": "Point",
        "coordinates": [
          9.975,
          49.121111
        ]
      },
      "type": "Feature",
      "properties": {
        "hierarchy": [
          "tgn:7207339",
          "tgn:7003692",
          "tgn:1000003",
          "tgn:7000084",
          "tgn:7029392"
        ],
        "placetype": [
          "aat:300008795"
        ],
        "id": 7207339,
        "name:xx": "Burgberg"
      }
    }
  ]
}
