{
  "geometry": {
    "type": "Point",
    "coordinates": [
      -93.7333,
      36.75
    ]
  },
  "type": "Feature",
  "properties": {
    "hierarchy": [
      "tgn:2590215",
      "tgn:2001170",
      "tgn:1000001",
      "tgn:7012149",
      "tgn:7007523",
      "tgn:7029392"
    ],
    "placetype": [
      "aat:300008761"
    ],
    "id": 2590215,
    "name:xx": "Pokeberry Hollow"
  }
}
