{
  "geometry": {
    "type": "Point",
    "coordinates": [
      -73.5167,
      43.15
    ]
  },
  "type": "Feature",
  "properties": {
    "hierarchy": [
      "tgn:2346480",
      "tgn:1000001",
      "tgn:7012149",
      "tgn:1002993",
      "tgn:7007568",
      "tgn:7029392"
    ],
    "placetype": [
      "aat:300008798"
    ],
    "id": 2346480,
    "name:xx": "Gavettes Mountain"
  }
}
