{
  "geometry": {
    "type": "Point",
    "coordinates": [
      68.8833,
      43.5833
    ]
  },
  "type": "Feature",
  "properties": {
    "hierarchy": [
      "tgn:1051886",
      "tgn:1000004",
      "tgn:7012947",
      "tgn:7014786",
      "tgn:7029392"
    ],
    "placetype": [
      "aat:300008347"
    ],
    "id": 1051886,
    "name:xx": "Achisay"
  }
}
