{
  "geometry": {
    "type": "Point",
    "coordinates": [
      147.45,
      -35.4833
    ]
  },
  "type": "Feature",
  "properties": {
    "hierarchy": [
      "tgn:1098516",
      "tgn:7000490",
      "tgn:1000006",
      "tgn:7001828",
      "tgn:7029392"
    ],
    "placetype": [
      "aat:300008347"
    ],
    "id": 1098516,
    "name:xx": "Westby"
  }
}
