{
  "geometry": {
    "type": "Point",
    "coordinates": [
      -94.45,
      40.5833
    ]
  },
  "type": "Feature",
  "properties": {
    "hierarchy": [
      "tgn:2677647",
      "tgn:7019177",
      "tgn:1000001",
      "tgn:7012149",
      "tgn:7007253",
      "tgn:7029392"
    ],
    "placetype": [
      "aat:300008706"
    ],
    "id": 2677647,
    "name:xx": "South Creek"
  }
}
