{
  "type": "FeatureCollection",
  "features": [
    {
      "geometry": {
        "type": "Point",
        "coordinates": [
          -85.1333,
          36.5667
        ]
      },
      "type": "Feature",
      "properties": {
        "hierarchy": [
          "tgn:2726420",
          "tgn:1000001",
          "tgn:7012149",
          "tgn:2001905",
          "tgn:7007825",
          "tgn:7029392"
        ],
        "placetype": [
          "aat:300008699"
        ],
        "id": 2726420,
        "name:xx": "Town Branch"
      }
    },
    {
      "geometry": {
        "type": "Point",
        "coordinates": [
          -96.4667,
          32.0833
        ]
      },
      "type": "Feature",
      "properties": {
        "hierarchy": [
          "tgn:2726421",
          "tgn:1000001",
          "tgn:7012149",
          "tgn:1002709",
          "tgn:7007826",
          "tgn:7029392"
        ],
        "placetype": [
          "aat:300008699"
        ],
        "id": 2726421,
        "name:xx": "Town Branch"
      }
    },
    {
      "geometry": {
        "type": "Point",
        "coordinates": [
          -95.5833,
          33.1333
        ]
      },
      "type": "Feature",
      "properties": {
        "hierarchy": [
          "tgn:2726422",
          "tgn:1000001",
          "tgn:7012149",
          "tgn:1002485",
          "tgn:7007826",
          "tgn:7029392"
        ],
        "placetype": [
          "aat:300008699"
        ],
        "id": 2726422,
        "name:xx": "Town Branch"
      }
    },
    {
      "geometry": {
        "type": "Point",
        "coordinates": [
          -95.2167,
          33.1833
        ]
      },
      "type": "Feature",
      "properties": {
        "hierarchy": [
          "tgn:2726423",
          "tgn:1000001",
          "tgn:7012149",
          "tgn:1002388",
          "tgn:7007826",
          "tgn:7029392"
        ],
        "placetype": [
          "aat:300008699"
        ],
        "id": 2726423,
        "name:xx": "Town Branch"
      }
    },
    {
      "geometry": {
        "type": "Point",
        "coordinates": [
          -97.5,
          32.3333
        ]
      },
      "type": "Feature",
      "properties": {
        "hierarchy": [
          "tgn:2726424",
          "tgn:1000001",
          "tgn:7012149",
          "tgn:1002526",
          "tgn:7007826",
          "tgn:7029392"
        ],
        "placetype": [
          "aat:300008699"
        ],
        "id": 2726424,
        "name:xx": "Town Branch"
      }
    },
    {
      "geometry": {
        "type": "Point",
        "coordinates": [
          -98.3,
          32.7333
        ]
      },
      "type": "Feature",
      "properties": {
        "hierarchy": [
          "tgn:2726425",
          "tgn:1000001",
          "tgn:7012149",
          "tgn:2002053",
          "tgn:7007826",
          "tgn:7029392"
        ],
        "placetype": [
          "aat:300008699"
        ],
        "id": 2726425,
        "name:xx": "Town Branch"
      }
    },
    {
      "geometry": {
        "type": "Point",
        "coordinates": [
          -97.7,
          29.8833
        ]
      },
      "type": "Feature",
      "properties": {
        "hierarchy": [
          "tgn:2726426",
          "tgn:1000001",
          "tgn:7012149",
          "tgn:1002220",
          "tgn:7007826",
          "tgn:7029392"
        ],
        "placetype": [
          "aat:300008699"
        ],
        "id": 2726426,
        "name:xx": "Town Branch"
      }
    },
    {
      "geometry": {
        "type": "Point",
        "coordinates": [
          -97.4167,
          30.7833
        ]
      },
      "type": "Feature",
      "properties": {
        "hierarchy": [
          "tgn:2726427",
          "tgn:1000001",
          "tgn:1002174",
          "tgn:7012149",
          "tgn:7007826",
          "tgn:7029392"
        ],
        "placetype": [
          "aat:300008699"
        ],
        "id": 2726427,
        "name:xx": "Town Branch"
      }
    },
    {
      "geometry": {
        "type": "Point",
        "coordinates": [
          -95.9,
          30.9667
        ]
      },
      "type": "Feature",
      "properties": {
        "hierarchy": [
          "tgn:2726428",
          "tgn:1000001",
          "tgn:7012149",
          "tgn:1002626",
          "tgn:7007826",
          "tgn:7029392"
        ],
        "placetype": [
          "aat:300008699"
        ],
        "id": 2726428,
        "name:xx": "Town Branch"
      }
    },
    {
      "geometry": {
        "type": "Point",
        "coordinates": [
          -95.45,
          31.3
        ]
      },
      "type": "Feature",
      "properties": {
        "hierarchy": [
          "tgn:2726429",
          "tgn:1000001",
          "tgn:7012149",
          "tgn:1002486",
          "tgn:7007826",
          "tgn:7029392"
        ],
        "placetype": [
          "aat:300008699"
        ],
        "id": 2726429,
        "name:xx": "Town Branch"
      }
    }
  ]
}
