{
  "geometry": {
    "type": "Point",
    "coordinates": [
      12.333056,
      49.8825
    ]
  },
  "type": "Feature",
  "properties": {
    "hierarchy": [
      "tgn:1041423",
      "tgn:7003669",
      "tgn:1000003",
      "tgn:7000084",
      "tgn:7029392"
    ],
    "placetype": [
      "aat:300008347"
    ],
    "id": 1041423,
    "name:xx": "Tirschenreuth"
  }
}
