{
  "type": "FeatureCollection",
  "features": [
    {
      "geometry": {
        "type": "Point",
        "coordinates": [
          -89.6833,
          35.5
        ]
      },
      "type": "Feature",
      "properties": {
        "hierarchy": [
          "tgn:2426710",
          "tgn:1000001",
          "tgn:7012149",
          "tgn:2001893",
          "tgn:7007825",
          "tgn:7029392"
        ],
        "placetype": [
          "aat:300006191"
        ],
        "id": 2426710,
        "name:xx": "Jones Lake"
      }
    },
    {
      "geometry": {
        "type": "Point",
        "coordinates": [
          -96.7833,
          28.25
        ]
      },
      "type": "Feature",
      "properties": {
        "hierarchy": [
          "tgn:2426711",
          "tgn:1000001",
          "tgn:7012149",
          "tgn:2001950",
          "tgn:7007826",
          "tgn:7029392"
        ],
        "placetype": [
          "aat:300008680"
        ],
        "id": 2426711,
        "name:xx": "Jones Lake"
      }
    },
    {
      "geometry": {
        "type": "Point",
        "coordinates": [
          -97.3,
          29.5167
        ]
      },
      "type": "Feature",
      "properties": {
        "hierarchy": [
          "tgn:2426712",
          "tgn:1000001",
          "tgn:7012149",
          "tgn:1002414",
          "tgn:7007826",
          "tgn:7029392"
        ],
        "placetype": [
          "aat:300008680"
        ],
        "id": 2426712,
        "name:xx": "Jones Lake"
      }
    },
    {
      "geometry": {
        "type": "Point",
        "coordinates": [
          -95.7333,
          32.2333
        ]
      },
      "type": "Feature",
      "properties": {
        "hierarchy": [
          "tgn:2426713",
          "tgn:1000001",
          "tgn:7012149",
          "tgn:1002464",
          "tgn:7007826",
          "tgn:7029392"
        ],
        "placetype": [
          "aat:300008680"
        ],
        "id": 2426713,
        "name:xx": "Jones Lake"
      }
    },
    {
      "geometry": {
        "type": "Point",
        "coordinates": [
          -95.4167,
          28.8833
        ]
      },
      "type": "Feature",
      "properties": {
        "hierarchy": [
          "tgn:2426714",
          "tgn:1000001",
          "tgn:1002198",
          "tgn:7012149",
          "tgn:7007826",
          "tgn:7029392"
        ],
        "placetype": [
          "aat:300008680"
        ],
        "id": 2426714,
        "name:xx": "Jones Lake"
      }
    },
    {
      "geometry": {
        "type": "Point",
        "coordinates": [
          -94.7167,
          31.35
        ]
      },
      "type": "Feature",
      "properties": {
        "hierarchy": [
          "tgn:2426715",
          "tgn:1002149",
          "tgn:1000001",
          "tgn:7012149",
          "tgn:7007826",
          "tgn:7029392"
        ],
        "placetype": [
          "aat:300006191"
        ],
        "id": 2426715,
        "name:xx": "Jones Lake"
      }
    },
    {
      "geometry": {
        "type": "Point",
        "coordinates": [
          -94.75,
          31.9833
        ]
      },
      "type": "Feature",
      "properties": {
        "hierarchy": [
          "tgn:2426716",
          "tgn:1000001",
          "tgn:7012149",
          "tgn:1002839",
          "tgn:7007826",
          "tgn:7029392"
        ],
        "placetype": [
          "aat:300006191"
        ],
        "id": 2426716,
        "name:xx": "Jones Lake"
      }
    },
    {
      "geometry": {
        "type": "Point",
        "coordinates": [
          -77.9667,
          37.4833
        ]
      },
      "type": "Feature",
      "properties": {
        "hierarchy": [
          "tgn:2426717",
          "tgn:2002139",
          "tgn:1000001",
          "tgn:7012149",
          "tgn:7007919",
          "tgn:7029392"
        ],
        "placetype": [
          "aat:300006191"
        ],
        "id": 2426717,
        "name:xx": "Jones Lake"
      }
    },
    {
      "geometry": {
        "type": "Point",
        "coordinates": [
          -122,
          47.3
        ]
      },
      "type": "Feature",
      "properties": {
        "hierarchy": [
          "tgn:2426719",
          "tgn:1000001",
          "tgn:7012149",
          "tgn:7018871",
          "tgn:7007920",
          "tgn:7029392"
        ],
        "placetype": [
          "aat:300008680"
        ],
        "id": 2426719,
        "name:xx": "Jones Lake"
      }
    }
  ]
}
