{
  "geometry": {
    "type": "Point",
    "coordinates": [
      -106.3667,
      43.4167
    ]
  },
  "type": "Feature",
  "properties": {
    "hierarchy": [
      "tgn:2381559",
      "tgn:1000001",
      "tgn:7012149",
      "tgn:7007923",
      "tgn:7029392"
    ],
    "placetype": [
      "aat:300008761"
    ],
    "id": 2381559,
    "name:xx": "Hay Draw"
  }
}
