{
  "geometry": {
    "type": "Point",
    "coordinates": [
      -121.7333,
      46.6833
    ]
  },
  "type": "Feature",
  "properties": {
    "hierarchy": [
      "tgn:2487935",
      "tgn:1000001",
      "tgn:7012149",
      "tgn:1002594",
      "tgn:7007920",
      "tgn:7029392"
    ],
    "placetype": [
      "aat:300008706"
    ],
    "id": 2487935,
    "name:xx": "Maggie Creek"
  }
}
