{
  "geometry": {
    "type": "Point",
    "coordinates": [
      31.883333,
      31.15
    ]
  },
  "type": "Feature",
  "properties": {
    "hierarchy": [
      "tgn:7527488",
      "tgn:7001242",
      "tgn:1001059",
      "tgn:7016833",
      "tgn:7029392"
    ],
    "placetype": [
      "aat:300005926"
    ],
    "name:en": "Manāmat Sīdī Abū Ghubār",
    "id": 7527488
  }
}
