{
  "geometry": {
    "type": "Point",
    "coordinates": [
      -105.4167,
      32.0833
    ]
  },
  "type": "Feature",
  "properties": {
    "hierarchy": [
      "tgn:2356379",
      "tgn:1000001",
      "tgn:7012149",
      "tgn:2001447",
      "tgn:7007566",
      "tgn:7029392"
    ],
    "placetype": [
      "aat:300006191"
    ],
    "id": 2356379,
    "name:xx": "Gopher Tank"
  }
}
