{
  "geometry": {
    "type": "Point",
    "coordinates": [
      74.05,
      33.763889
    ]
  },
  "type": "Feature",
  "properties": {
    "hierarchy": [
      "tgn:7588677",
      "tgn:1000004",
      "tgn:7000198",
      "tgn:7000799",
      "tgn:7029392"
    ],
    "placetype": [
      "aat:300008347"
    ],
    "name:en": "Khati Dharmsāl",
    "id": 7588677
  }
}
