{
  "geometry": {
    "type": "Point",
    "coordinates": [
      -113.85,
      44.9167
    ]
  },
  "type": "Feature",
  "properties": {
    "hierarchy": [
      "tgn:2734883",
      "tgn:1000001",
      "tgn:7012149",
      "tgn:2000481",
      "tgn:7007250",
      "tgn:7029392"
    ],
    "placetype": [
      "aat:300008706"
    ],
    "id": 2734883,
    "name:xx": "Twelvemile Creek"
  }
}
