{
  "type": "FeatureCollection",
  "features": [
    {
      "geometry": {
        "type": "Point",
        "coordinates": [
          -102.6333,
          46
        ]
      },
      "type": "Feature",
      "properties": {
        "hierarchy": [
          "tgn:2077710",
          "tgn:2001557",
          "tgn:1000001",
          "tgn:7012149",
          "tgn:7007705",
          "tgn:7029392"
        ],
        "placetype": [
          "aat:300008347"
        ],
        "id": 2077710,
        "name:xx": "Hettinger"
      }
    },
    {
      "geometry": {
        "type": "Point",
        "coordinates": [
          -96.8,
          46.6667
        ]
      },
      "type": "Feature",
      "properties": {
        "hierarchy": [
          "tgn:2077711",
          "tgn:2001565",
          "tgn:1000001",
          "tgn:7012149",
          "tgn:7007705",
          "tgn:7029392"
        ],
        "placetype": [
          "aat:300008347",
          "aat:300387210"
        ],
        "id": 2077711,
        "name:xx": "Hickson"
      }
    },
    {
      "geometry": {
        "type": "Point",
        "coordinates": [
          -97.05,
          47.4
        ]
      },
      "type": "Feature",
      "properties": {
        "hierarchy": [
          "tgn:2077712",
          "tgn:1000001",
          "tgn:7012149",
          "tgn:2001605",
          "tgn:7007705",
          "tgn:7029392"
        ],
        "placetype": [
          "aat:300008347"
        ],
        "id": 2077712,
        "name:xx": "Hillsboro"
      }
    },
    {
      "geometry": {
        "type": "Point",
        "coordinates": [
          -97.2833,
          47.7
        ]
      },
      "type": "Feature",
      "properties": {
        "hierarchy": [
          "tgn:2077713",
          "tgn:1000001",
          "tgn:2001574",
          "tgn:7012149",
          "tgn:7007705",
          "tgn:7029392"
        ],
        "placetype": [
          "aat:300008347",
          "aat:300387210"
        ],
        "id": 2077713,
        "name:xx": "Holmes"
      }
    },
    {
      "geometry": {
        "type": "Point",
        "coordinates": [
          -97.4667,
          48.0333
        ]
      },
      "type": "Feature",
      "properties": {
        "hierarchy": [
          "tgn:2077715",
          "tgn:1000001",
          "tgn:2001574",
          "tgn:7012149",
          "tgn:7007705",
          "tgn:7029392"
        ],
        "placetype": [
          "aat:300008347",
          "aat:300387210"
        ],
        "id": 2077715,
        "name:xx": "Honeyford"
      }
    },
    {
      "geometry": {
        "type": "Point",
        "coordinates": [
          -97.6333,
          48.5333
        ]
      },
      "type": "Feature",
      "properties": {
        "hierarchy": [
          "tgn:2077716",
          "tgn:1000001",
          "tgn:7012149",
          "tgn:2001606",
          "tgn:7007705",
          "tgn:7029392"
        ],
        "placetype": [
          "aat:300008347"
        ],
        "id": 2077716,
        "name:xx": "Hoople"
      }
    },
    {
      "geometry": {
        "type": "Point",
        "coordinates": [
          -97.7167,
          47.3167
        ]
      },
      "type": "Feature",
      "properties": {
        "hierarchy": [
          "tgn:2077717",
          "tgn:1000001",
          "tgn:2001602",
          "tgn:7012149",
          "tgn:7007705",
          "tgn:7029392"
        ],
        "placetype": [
          "aat:300008347"
        ],
        "id": 2077717,
        "name:xx": "Hope"
      }
    },
    {
      "geometry": {
        "type": "Point",
        "coordinates": [
          -96.9,
          46.75
        ]
      },
      "type": "Feature",
      "properties": {
        "hierarchy": [
          "tgn:2077718",
          "tgn:2001565",
          "tgn:1000001",
          "tgn:7012149",
          "tgn:7007705",
          "tgn:7029392"
        ],
        "placetype": [
          "aat:300008347"
        ],
        "id": 2077718,
        "name:xx": "Horace"
      }
    }
  ]
}
