{
  "geometry": {
    "type": "Point",
    "coordinates": [
      -96.05,
      31.9167
    ]
  },
  "type": "Feature",
  "properties": {
    "hierarchy": [
      "tgn:2468072",
      "tgn:1000001",
      "tgn:7012149",
      "tgn:1002391",
      "tgn:7007826",
      "tgn:7029392"
    ],
    "placetype": [
      "aat:300008680"
    ],
    "id": 2468072,
    "name:xx": "Long Lake"
  }
}
