{
  "geometry": {
    "type": "Point",
    "coordinates": [
      -82.0333,
      29.8333
    ]
  },
  "type": "Feature",
  "properties": {
    "hierarchy": [
      "tgn:2526139",
      "tgn:1000001",
      "tgn:2000261",
      "tgn:7012149",
      "tgn:7007240",
      "tgn:7029392"
    ],
    "placetype": [
      "aat:300008680"
    ],
    "id": 2526139,
    "name:xx": "Mosquito Lake"
  }
}
