{
  "geometry": {
    "type": "Point",
    "coordinates": [
      -90.5833,
      31.4833
    ]
  },
  "type": "Feature",
  "properties": {
    "hierarchy": [
      "tgn:2566778",
      "tgn:1000001",
      "tgn:7012149",
      "tgn:2001128",
      "tgn:7007522",
      "tgn:7029392"
    ],
    "placetype": [
      "aat:300008706"
    ],
    "id": 2566778,
    "name:xx": "Panter Creek"
  }
}
