{
  "type": "FeatureCollection",
  "features": [
    {
      "geometry": {
        "type": "Point",
        "coordinates": [
          -99.183333,
          19.083333
        ]
      },
      "type": "Feature",
      "properties": {
        "hierarchy": [
          "tgn:7434261",
          "tgn:1000001",
          "tgn:1001893",
          "tgn:7005560",
          "tgn:7029392"
        ],
        "placetype": [
          "aat:300008795"
        ],
        "id": 7434261,
        "name:xx": "Xochisacapa, Cerro"
      }
    },
    {
      "geometry": {
        "type": "Point",
        "coordinates": [
          -99.6,
          17.933333
        ]
      },
      "type": "Feature",
      "properties": {
        "hierarchy": [
          "tgn:7434262",
          "tgn:7005585",
          "tgn:1000001",
          "tgn:7005560",
          "tgn:7029392"
        ],
        "placetype": [
          "aat:300008699"
        ],
        "id": 7434262,
        "name:xx": "Xochipala, Río"
      }
    },
    {
      "geometry": {
        "type": "Point",
        "coordinates": [
          -99.066667,
          18.416667
        ]
      },
      "type": "Feature",
      "properties": {
        "hierarchy": [
          "tgn:7434263",
          "tgn:1000001",
          "tgn:7005588",
          "tgn:7005560",
          "tgn:7029392"
        ],
        "placetype": [
          "aat:300008347"
        ],
        "id": 7434263,
        "name:xx": "Xochipala"
      }
    },
    {
      "geometry": {
        "type": "Point",
        "coordinates": [
          -98.216667,
          20.866667
        ]
      },
      "type": "Feature",
      "properties": {
        "hierarchy": [
          "tgn:7434265",
          "tgn:1000001",
          "tgn:7005599",
          "tgn:7005560",
          "tgn:7029392"
        ],
        "placetype": [
          "aat:300008347"
        ],
        "id": 7434265,
        "name:xx": "Xochioloco"
      }
    },
    {
      "geometry": {
        "type": "Point",
        "coordinates": [
          -97.9,
          20.2
        ]
      },
      "type": "Feature",
      "properties": {
        "hierarchy": [
          "tgn:7434266",
          "tgn:1000001",
          "tgn:7005592",
          "tgn:7005560",
          "tgn:7029392"
        ],
        "placetype": [
          "aat:300008347"
        ],
        "id": 7434266,
        "name:xx": "Xochinanacatlán"
      }
    },
    {
      "geometry": {
        "type": "Point",
        "coordinates": [
          -99.733333,
          18.683333
        ]
      },
      "type": "Feature",
      "properties": {
        "hierarchy": [
          "tgn:7434267",
          "tgn:7005585",
          "tgn:1000001",
          "tgn:7005560",
          "tgn:7029392"
        ],
        "placetype": [
          "aat:300008347"
        ],
        "id": 7434267,
        "name:xx": "Xochimilpan"
      }
    },
    {
      "geometry": {
        "type": "Point",
        "coordinates": [
          -97.9,
          20.066667
        ]
      },
      "type": "Feature",
      "properties": {
        "hierarchy": [
          "tgn:7434269",
          "tgn:1000001",
          "tgn:7005592",
          "tgn:7005560",
          "tgn:7029392"
        ],
        "placetype": [
          "aat:300008347"
        ],
        "id": 7434269,
        "name:xx": "Xochimilco"
      }
    }
  ]
}
