{
  "geometry": {
    "type": "Point",
    "coordinates": [
      -92.5833,
      38.0333
    ]
  },
  "type": "Feature",
  "properties": {
    "hierarchy": [
      "tgn:2058833",
      "tgn:1000001",
      "tgn:2001178",
      "tgn:7012149",
      "tgn:7007523",
      "tgn:7029392"
    ],
    "placetype": [
      "aat:300008347",
      "aat:300387210"
    ],
    "id": 2058833,
    "name:xx": "Freedom"
  }
}
