{
  "type": "FeatureCollection",
  "features": [
    {
      "geometry": {
        "type": "Point",
        "coordinates": [
          -66.9167,
          10.45
        ]
      },
      "type": "Feature",
      "properties": {
        "hierarchy": [
          "tgn:1004420",
          "tgn:7005022",
          "tgn:1000842",
          "tgn:1000002",
          "tgn:1000059",
          "tgn:7029392"
        ],
        "placetype": [
          "aat:300000745"
        ],
        "id": 1004420,
        "name:xx": "El Valle"
      }
    },
    {
      "geometry": {
        "type": "Point",
        "coordinates": [
          7.133333,
          51.266667
        ]
      },
      "type": "Feature",
      "properties": {
        "hierarchy": [
          "tgn:1004421",
          "tgn:1000003",
          "tgn:7003677",
          "tgn:7000084",
          "tgn:7004943",
          "tgn:7029392"
        ],
        "placetype": [
          "aat:300000745",
          "aat:300387332"
        ],
        "id": 1004421,
        "name:xx": "Elberfeld"
      }
    },
    {
      "geometry": {
        "type": "Point",
        "coordinates": [
          6.85,
          51.2
        ]
      },
      "type": "Feature",
      "properties": {
        "hierarchy": [
          "tgn:1004422",
          "tgn:1000003",
          "tgn:7003677",
          "tgn:7000084",
          "tgn:7004443",
          "tgn:7029392"
        ],
        "placetype": [
          "aat:300000745",
          "aat:300387332"
        ],
        "id": 1004422,
        "name:xx": "Eller"
      }
    },
    {
      "geometry": {
        "type": "Point",
        "coordinates": [
          6.95,
          51.566667
        ]
      },
      "type": "Feature",
      "properties": {
        "hierarchy": [
          "tgn:1004423",
          "tgn:1000003",
          "tgn:7003677",
          "tgn:7000084",
          "tgn:7029392"
        ],
        "placetype": [
          "aat:300000745"
        ],
        "id": 1004423,
        "name:xx": "Ellinghorst"
      }
    },
    {
      "geometry": {
        "type": "Point",
        "coordinates": [
          10.2,
          54.3
        ]
      },
      "type": "Feature",
      "properties": {
        "hierarchy": [
          "tgn:1004425",
          "tgn:1000003",
          "tgn:7003688",
          "tgn:7000084",
          "tgn:7004457",
          "tgn:7029392"
        ],
        "placetype": [
          "aat:300000745"
        ],
        "id": 1004425,
        "name:xx": "Elmschenhagen"
      }
    },
    {
      "geometry": {
        "type": "Point",
        "coordinates": [
          0.05,
          51.45
        ]
      },
      "type": "Feature",
      "properties": {
        "hierarchy": [
          "tgn:1004427",
          "tgn:7002445",
          "tgn:7018915",
          "tgn:7011781",
          "tgn:1000003",
          "tgn:7008136",
          "tgn:7008591",
          "tgn:7029392"
        ],
        "placetype": [
          "aat:300008347",
          "aat:300000745",
          "aat:300000874"
        ],
        "name:en": "Eltham",
        "id": 1004427
      }
    },
    {
      "geometry": {
        "type": "Point",
        "coordinates": [
          7.5,
          51.35
        ]
      },
      "type": "Feature",
      "properties": {
        "hierarchy": [
          "tgn:1004428",
          "tgn:1000003",
          "tgn:7003677",
          "tgn:7000084",
          "tgn:7005154",
          "tgn:7029392"
        ],
        "placetype": [
          "aat:300000745",
          "aat:300387332"
        ],
        "id": 1004428,
        "name:xx": "Emst"
      }
    }
  ]
}
