{
  "geometry": {
    "type": "Point",
    "coordinates": [
      -122.2833,
      37.7667
    ]
  },
  "type": "Feature",
  "properties": {
    "hierarchy": [
      "tgn:2146200",
      "tgn:1002138",
      "tgn:1000001",
      "tgn:7012149",
      "tgn:7007157",
      "tgn:7029392"
    ],
    "placetype": [
      "aat:300008678"
    ],
    "id": 2146200,
    "name:xx": "Ballena Bay"
  }
}
