{
  "geometry": {
    "type": "Point",
    "coordinates": [
      8.4167,
      47.6667
    ]
  },
  "type": "Feature",
  "properties": {
    "hierarchy": [
      "tgn:1064458",
      "tgn:1000003",
      "tgn:7003756",
      "tgn:7011731",
      "tgn:7029392"
    ],
    "placetype": [
      "aat:300008347"
    ],
    "id": 1064458,
    "name:xx": "Trasadingen"
  }
}
