{
  "geometry": {
    "type": "Point",
    "coordinates": [
      -87.0333,
      41.5167
    ]
  },
  "type": "Feature",
  "properties": {
    "hierarchy": [
      "tgn:2517080",
      "tgn:1000001",
      "tgn:7012149",
      "tgn:1002798",
      "tgn:7007252",
      "tgn:7029392"
    ],
    "placetype": [
      "aat:300006191"
    ],
    "id": 2517080,
    "name:xx": "Mink Lake"
  }
}
