{
  "geometry": {
    "type": "Point",
    "coordinates": [
      -72.433333,
      -38.55
    ]
  },
  "type": "Feature",
  "properties": {
    "hierarchy": [
      "tgn:7310174",
      "tgn:1001692",
      "tgn:1000049",
      "tgn:1000002",
      "tgn:7029392"
    ],
    "placetype": [
      "aat:300008699"
    ],
    "id": 7310174,
    "name:xx": "Ñirca, Estero"
  }
}
