{
  "geometry": {
    "type": "Point",
    "coordinates": [
      25.2167,
      14.45
    ]
  },
  "type": "Feature",
  "properties": {
    "hierarchy": [
      "tgn:1094065",
      "tgn:7001242",
      "tgn:1000201",
      "tgn:1001213",
      "tgn:7029392"
    ],
    "placetype": [
      "aat:300008347"
    ],
    "id": 1094065,
    "name:xx": "Amar Gedid"
  }
}
