{
  "geometry": {
    "type": "Point",
    "coordinates": [
      -110.3333,
      34.45
    ]
  },
  "type": "Feature",
  "properties": {
    "hierarchy": [
      "tgn:2170161",
      "tgn:1000001",
      "tgn:7006451",
      "tgn:7012149",
      "tgn:2000099",
      "tgn:7029392"
    ],
    "placetype": [
      "aat:300006191"
    ],
    "id": 2170161,
    "name:xx": "Big Pug Tank"
  }
}
