{
  "geometry": {
    "type": "Point",
    "coordinates": [
      100.866,
      45.083
    ]
  },
  "type": "Feature",
  "properties": {
    "hierarchy": [
      "tgn:1130502",
      "tgn:1001133",
      "tgn:1000004",
      "tgn:7029379",
      "tgn:7029392"
    ],
    "placetype": [
      "aat:300008707"
    ],
    "id": 1130502,
    "name:xx": "Tüyn Gol"
  }
}
