{
  "geometry": {
    "type": "Point",
    "coordinates": [
      -81.4833,
      35.8333
    ]
  },
  "type": "Feature",
  "properties": {
    "hierarchy": [
      "tgn:2075179",
      "tgn:1000001",
      "tgn:2001476",
      "tgn:7012149",
      "tgn:7007709",
      "tgn:7029392"
    ],
    "placetype": [
      "aat:300008347"
    ],
    "id": 2075179,
    "name:xx": "Hudson"
  }
}
