{
  "geometry": {
    "type": "Point",
    "coordinates": [
      -133.0333,
      55.0833
    ]
  },
  "type": "Feature",
  "properties": {
    "hierarchy": [
      "tgn:2240678",
      "tgn:7006450",
      "tgn:1000001",
      "tgn:7012149",
      "tgn:2000082",
      "tgn:7029392"
    ],
    "placetype": [
      "aat:300008791"
    ],
    "id": 2240678,
    "name:xx": "Clam Island"
  }
}
