{
  "geometry": {
    "type": "Point",
    "coordinates": [
      -120.6167,
      38.65
    ]
  },
  "type": "Feature",
  "properties": {
    "hierarchy": [
      "tgn:2546146",
      "tgn:1000001",
      "tgn:7012149",
      "tgn:1002350",
      "tgn:7007157",
      "tgn:7029392"
    ],
    "placetype": [
      "aat:300006075"
    ],
    "id": 2546146,
    "name:xx": "North Fork Extension Ditch"
  }
}
