{
  "geometry": {
    "type": "Point",
    "coordinates": [
      -68.75,
      -25.65
    ]
  },
  "type": "Feature",
  "properties": {
    "hierarchy": [
      "tgn:7290257",
      "tgn:1001630",
      "tgn:1000049",
      "tgn:1000002",
      "tgn:7029392"
    ],
    "placetype": [
      "aat:300008795"
    ],
    "id": 7290257,
    "name:xx": "Dos Conos, Cerro"
  }
}
