{
  "geometry": {
    "type": "Point",
    "coordinates": [
      -110.8667,
      32.3667
    ]
  },
  "type": "Feature",
  "properties": {
    "hierarchy": [
      "tgn:2744027",
      "tgn:1000001",
      "tgn:7006451",
      "tgn:7012149",
      "tgn:2000100",
      "tgn:7029392"
    ],
    "placetype": [
      "aat:300008699"
    ],
    "id": 2744027,
    "name:xx": "Ventana Canyon Wash"
  }
}
