{
  "geometry": {
    "type": "Point",
    "coordinates": [
      44.1833,
      43.4667
    ]
  },
  "type": "Feature",
  "properties": {
    "hierarchy": [
      "tgn:1138501",
      "tgn:1000004",
      "tgn:7011496",
      "tgn:7002435",
      "tgn:7029392"
    ],
    "placetype": [
      "aat:300008347"
    ],
    "id": 1138501,
    "name:xx": "Terek"
  }
}
