{
  "geometry": {
    "type": "Point",
    "coordinates": [
      79.23032,
      25.516407
    ]
  },
  "type": "Feature",
  "properties": {
    "hierarchy": [
      "tgn:7566656",
      "tgn:1000004",
      "tgn:7000198",
      "tgn:7016722",
      "tgn:7029392"
    ],
    "placetype": [
      "aat:300167671"
    ],
    "name:en": "Turka Lahchūra",
    "id": 7566656
  }
}
