{
  "geometry": {
    "type": "Point",
    "coordinates": [
      -86.2667,
      34.4833
    ]
  },
  "type": "Feature",
  "properties": {
    "hierarchy": [
      "tgn:2773502",
      "tgn:7002659",
      "tgn:1000001",
      "tgn:7012149",
      "tgn:2000047",
      "tgn:7029392"
    ],
    "placetype": [
      "aat:300008761"
    ],
    "id": 2773502,
    "name:xx": "Willis Hollow"
  }
}
