{
  "geometry": {
    "type": "Point",
    "coordinates": [
      -77.1667,
      41.1667
    ]
  },
  "type": "Feature",
  "properties": {
    "hierarchy": [
      "tgn:2170555",
      "tgn:1000001",
      "tgn:7012149",
      "tgn:1002613",
      "tgn:7007710",
      "tgn:7029392"
    ],
    "placetype": [
      "aat:300008699"
    ],
    "id": 2170555,
    "name:xx": "Big Run"
  }
}
