{
  "geometry": {
    "type": "Point",
    "coordinates": [
      -100.8667,
      42.2833
    ]
  },
  "type": "Feature",
  "properties": {
    "hierarchy": [
      "tgn:2532764",
      "tgn:1000001",
      "tgn:2001331",
      "tgn:7012149",
      "tgn:7007525",
      "tgn:7029392"
    ],
    "placetype": [
      "aat:300008905"
    ],
    "id": 2532764,
    "name:xx": "Murphy Swamp"
  }
}
