{
  "geometry": {
    "type": "Point",
    "coordinates": [
      -111.2333,
      39.3333
    ]
  },
  "type": "Feature",
  "properties": {
    "hierarchy": [
      "tgn:2727419",
      "tgn:1000001",
      "tgn:2002108",
      "tgn:7012149",
      "tgn:7007827",
      "tgn:7029392"
    ],
    "placetype": [
      "aat:300008761"
    ],
    "id": 2727419,
    "name:xx": "Trail Canyon"
  }
}
