{
  "geometry": {
    "type": "Point",
    "coordinates": [
      31.974533,
      31.19024
    ]
  },
  "type": "Feature",
  "properties": {
    "hierarchy": [
      "tgn:7521360",
      "tgn:7001242",
      "tgn:1001059",
      "tgn:7016833",
      "tgn:7029392"
    ],
    "placetype": [
      "aat:300008347"
    ],
    "name:en": "Al Aḩmadīyah",
    "id": 7521360
  }
}
