{
  "type": "FeatureCollection",
  "features": [
    {
      "geometry": {
        "type": "Point",
        "coordinates": [
          8.883333,
          51.216667
        ]
      },
      "type": "Feature",
      "properties": {
        "hierarchy": [
          "tgn:7150910",
          "tgn:1000003",
          "tgn:7003678",
          "tgn:7000084",
          "tgn:7029392"
        ],
        "placetype": [
          "aat:300008699"
        ],
        "id": 7150910,
        "name:xx": "Kuh-Bach"
      }
    },
    {
      "geometry": {
        "type": "Point",
        "coordinates": [
          9.783333,
          50.016667
        ]
      },
      "type": "Feature",
      "properties": {
        "hierarchy": [
          "tgn:7150911",
          "tgn:7003669",
          "tgn:1000003",
          "tgn:7000084",
          "tgn:7029392"
        ],
        "placetype": [
          "aat:300008699"
        ],
        "id": 7150911,
        "name:xx": "Küh-Bach"
      }
    },
    {
      "geometry": {
        "type": "Point",
        "coordinates": [
          11.133333,
          47.683333
        ]
      },
      "type": "Feature",
      "properties": {
        "hierarchy": [
          "tgn:7150912",
          "tgn:7003669",
          "tgn:1000003",
          "tgn:7000084",
          "tgn:7029392"
        ],
        "placetype": [
          "aat:300008699"
        ],
        "id": 7150912,
        "name:xx": "Küh-Bach"
      }
    },
    {
      "geometry": {
        "type": "Point",
        "coordinates": [
          7.916667,
          48.333333
        ]
      },
      "type": "Feature",
      "properties": {
        "hierarchy": [
          "tgn:7150913",
          "tgn:7003692",
          "tgn:1000003",
          "tgn:7000084",
          "tgn:7029392"
        ],
        "placetype": [
          "aat:300000745"
        ],
        "id": 7150913,
        "name:xx": "Kuhbach"
      }
    },
    {
      "geometry": {
        "type": "Point",
        "coordinates": [
          12.833333,
          48.55
        ]
      },
      "type": "Feature",
      "properties": {
        "hierarchy": [
          "tgn:7150914",
          "tgn:7003669",
          "tgn:1000003",
          "tgn:7000084",
          "tgn:7029392"
        ],
        "placetype": [
          "aat:300387200"
        ],
        "id": 7150914,
        "name:xx": "Kühbach"
      }
    },
    {
      "geometry": {
        "type": "Point",
        "coordinates": [
          12.283333,
          49.716667
        ]
      },
      "type": "Feature",
      "properties": {
        "hierarchy": [
          "tgn:7150915",
          "tgn:7003669",
          "tgn:1000003",
          "tgn:7000084",
          "tgn:7029392"
        ],
        "placetype": [
          "aat:300008347"
        ],
        "id": 7150915,
        "name:xx": "Kühbach"
      }
    },
    {
      "geometry": {
        "type": "Point",
        "coordinates": [
          13.466667,
          48.8
        ]
      },
      "type": "Feature",
      "properties": {
        "hierarchy": [
          "tgn:7150916",
          "tgn:7003669",
          "tgn:1000003",
          "tgn:7000084",
          "tgn:7029392"
        ],
        "placetype": [
          "aat:300008347"
        ],
        "id": 7150916,
        "name:xx": "Kühbach"
      }
    },
    {
      "geometry": {
        "type": "Point",
        "coordinates": [
          12.683333,
          48.633333
        ]
      },
      "type": "Feature",
      "properties": {
        "hierarchy": [
          "tgn:7150917",
          "tgn:7003669",
          "tgn:1000003",
          "tgn:7000084",
          "tgn:7029392"
        ],
        "placetype": [
          "aat:300008347"
        ],
        "id": 7150917,
        "name:xx": "Kühbach"
      }
    },
    {
      "geometry": {
        "type": "Point",
        "coordinates": [
          13.166667,
          48.366667
        ]
      },
      "type": "Feature",
      "properties": {
        "hierarchy": [
          "tgn:7150919",
          "tgn:7003669",
          "tgn:1000003",
          "tgn:7000084",
          "tgn:7029392"
        ],
        "placetype": [
          "aat:300008347"
        ],
        "id": 7150919,
        "name:xx": "Kühbach"
      }
    }
  ]
}
