{
  "geometry": {
    "type": "Point",
    "coordinates": [
      -86.2667,
      38.45
    ]
  },
  "type": "Feature",
  "properties": {
    "hierarchy": [
      "tgn:2594672",
      "tgn:1000001",
      "tgn:7012149",
      "tgn:1002992",
      "tgn:7007252",
      "tgn:7029392"
    ],
    "placetype": [
      "aat:300386845"
    ],
    "id": 2594672,
    "name:xx": "Posey Sink"
  }
}
