{
  "geometry": {
    "type": "Point",
    "coordinates": [
      -107.0833,
      44.8167
    ]
  },
  "type": "Feature",
  "properties": {
    "hierarchy": [
      "tgn:2405931",
      "tgn:1000001",
      "tgn:7012149",
      "tgn:2002381",
      "tgn:7007923",
      "tgn:7029392"
    ],
    "placetype": [
      "aat:300008761"
    ],
    "id": 2405931,
    "name:xx": "Hultz Draw"
  }
}
