{
  "geometry": {
    "type": "Point",
    "coordinates": [
      -87.3167,
      39.55
    ]
  },
  "type": "Feature",
  "properties": {
    "hierarchy": [
      "tgn:2033579",
      "tgn:1000001",
      "tgn:7012149",
      "tgn:2000559",
      "tgn:7007252",
      "tgn:7029392"
    ],
    "placetype": [
      "aat:300008347"
    ],
    "id": 2033579,
    "name:xx": "Sandcut"
  }
}
