{
  "geometry": {
    "type": "Point",
    "coordinates": [
      -82.3333,
      36.65
    ]
  },
  "type": "Feature",
  "properties": {
    "hierarchy": [
      "tgn:2261764",
      "tgn:1000001",
      "tgn:7012149",
      "tgn:7007919",
      "tgn:7029392"
    ],
    "placetype": [
      "aat:300266640"
    ],
    "id": 2261764,
    "name:xx": "Cove Ridge"
  }
}
