{
  "type": "FeatureCollection",
  "features": [
    {
      "geometry": {
        "type": "Point",
        "coordinates": [
          -101.95,
          41.8167
        ]
      },
      "type": "Feature",
      "properties": {
        "hierarchy": [
          "tgn:2469120",
          "tgn:1000001",
          "tgn:2001353",
          "tgn:7012149",
          "tgn:7007525",
          "tgn:7029392"
        ],
        "placetype": [
          "aat:300386845"
        ],
        "id": 2469120,
        "name:xx": "Long Valley"
      }
    },
    {
      "geometry": {
        "type": "Point",
        "coordinates": [
          -115.3833,
          39.7667
        ]
      },
      "type": "Feature",
      "properties": {
        "hierarchy": [
          "tgn:2469121",
          "tgn:1000001",
          "tgn:7012149",
          "tgn:2001420",
          "tgn:7007526",
          "tgn:7029392"
        ],
        "placetype": [
          "aat:300386845"
        ],
        "id": 2469121,
        "name:xx": "Long Valley"
      }
    },
    {
      "geometry": {
        "type": "Point",
        "coordinates": [
          -119.7167,
          38.8
        ]
      },
      "type": "Feature",
      "properties": {
        "hierarchy": [
          "tgn:2469122",
          "tgn:1000001",
          "tgn:1002340",
          "tgn:7012149",
          "tgn:7007526",
          "tgn:7029392"
        ],
        "placetype": [
          "aat:300008761"
        ],
        "id": 2469122,
        "name:xx": "Long Valley"
      }
    },
    {
      "geometry": {
        "type": "Point",
        "coordinates": [
          -118.8167,
          39.2
        ]
      },
      "type": "Feature",
      "properties": {
        "hierarchy": [
          "tgn:2469123",
          "tgn:1000001",
          "tgn:7012149",
          "tgn:7007526",
          "tgn:7029392"
        ],
        "placetype": [
          "aat:300008761"
        ],
        "id": 2469123,
        "name:xx": "Long Valley"
      }
    },
    {
      "geometry": {
        "type": "Point",
        "coordinates": [
          -119.6333,
          39.3333
        ]
      },
      "type": "Feature",
      "properties": {
        "hierarchy": [
          "tgn:2469124",
          "tgn:1000001",
          "tgn:7012149",
          "tgn:1002921",
          "tgn:7007526",
          "tgn:7029392"
        ],
        "placetype": [
          "aat:300008761"
        ],
        "id": 2469124,
        "name:xx": "Long Valley"
      }
    },
    {
      "geometry": {
        "type": "Point",
        "coordinates": [
          -115.2333,
          36.5333
        ]
      },
      "type": "Feature",
      "properties": {
        "hierarchy": [
          "tgn:2469125",
          "tgn:1000001",
          "tgn:2001410",
          "tgn:7012149",
          "tgn:7007526",
          "tgn:7029392"
        ],
        "placetype": [
          "aat:300008761"
        ],
        "id": 2469125,
        "name:xx": "Long Valley"
      }
    },
    {
      "geometry": {
        "type": "Point",
        "coordinates": [
          -119.8,
          41.6833
        ]
      },
      "type": "Feature",
      "properties": {
        "hierarchy": [
          "tgn:2469126",
          "tgn:1000001",
          "tgn:7012149",
          "tgn:1002999",
          "tgn:7007526",
          "tgn:7029392"
        ],
        "placetype": [
          "aat:300386845"
        ],
        "id": 2469126,
        "name:xx": "Long Valley"
      }
    },
    {
      "geometry": {
        "type": "Point",
        "coordinates": [
          -118.6667,
          38.3
        ]
      },
      "type": "Feature",
      "properties": {
        "hierarchy": [
          "tgn:2469127",
          "tgn:1000001",
          "tgn:2001417",
          "tgn:7012149",
          "tgn:7007526",
          "tgn:7029392"
        ],
        "placetype": [
          "aat:300008761"
        ],
        "id": 2469127,
        "name:xx": "Long Valley"
      }
    },
    {
      "geometry": {
        "type": "Point",
        "coordinates": [
          -117.4333,
          41.7333
        ]
      },
      "type": "Feature",
      "properties": {
        "hierarchy": [
          "tgn:2469128",
          "tgn:1000001",
          "tgn:2001414",
          "tgn:7012149",
          "tgn:7007526",
          "tgn:7029392"
        ],
        "placetype": [
          "aat:300386845"
        ],
        "id": 2469128,
        "name:xx": "Long Valley"
      }
    },
    {
      "geometry": {
        "type": "Point",
        "coordinates": [
          -114.4667,
          37.25
        ]
      },
      "type": "Feature",
      "properties": {
        "hierarchy": [
          "tgn:2469129",
          "tgn:1000001",
          "tgn:2001416",
          "tgn:7012149",
          "tgn:7007526",
          "tgn:7029392"
        ],
        "placetype": [
          "aat:300008761"
        ],
        "id": 2469129,
        "name:xx": "Long Valley"
      }
    }
  ]
}
