{
  "geometry": {
    "type": "Point",
    "coordinates": [
      -75.4667,
      39.8667
    ]
  },
  "type": "Feature",
  "properties": {
    "hierarchy": [
      "tgn:2087139",
      "tgn:1000001",
      "tgn:1002330",
      "tgn:7012149",
      "tgn:7007710",
      "tgn:7029392"
    ],
    "placetype": [
      "aat:300008347"
    ],
    "id": 2087139,
    "name:xx": "Chelsea"
  }
}
