{
  "geometry": {
    "type": "Point",
    "coordinates": [
      10.25,
      48.233333
    ]
  },
  "type": "Feature",
  "properties": {
    "hierarchy": [
      "tgn:7105014",
      "tgn:7003669",
      "tgn:1000003",
      "tgn:7000084",
      "tgn:7029392"
    ],
    "placetype": [
      "aat:300008777"
    ],
    "id": 7105014,
    "name:xx": "Schloßberg"
  }
}
