{
  "geometry": {
    "type": "Point",
    "coordinates": [
      -87.55,
      39.9667
    ]
  },
  "type": "Feature",
  "properties": {
    "hierarchy": [
      "tgn:2279677",
      "tgn:1000001",
      "tgn:7012149",
      "tgn:7029392"
    ],
    "placetype": [
      "aat:300008761"
    ],
    "id": 2279677,
    "name:xx": "Deadmans Hollow"
  }
}
