{
  "geometry": {
    "type": "Point",
    "coordinates": [
      118.3833,
      39.4833
    ]
  },
  "type": "Feature",
  "properties": {
    "hierarchy": [
      "tgn:1071829",
      "tgn:1000004",
      "tgn:7002077",
      "tgn:1000111",
      "tgn:7029392"
    ],
    "placetype": [
      "aat:300008347"
    ],
    "id": 1071829,
    "name:xx": "Shuangtuozhen"
  }
}
