{
  "geometry": {
    "type": "Point",
    "coordinates": [
      135.7167,
      70.0167
    ]
  },
  "type": "Feature",
  "properties": {
    "hierarchy": [
      "tgn:1060787",
      "tgn:1000004",
      "tgn:7011528",
      "tgn:7002435",
      "tgn:7029392"
    ],
    "placetype": [
      "aat:300008347"
    ],
    "id": 1060787,
    "name:xx": "Ust-Kuyga"
  }
}
