{
  "geometry": {
    "type": "Point",
    "coordinates": [
      -112.5167,
      39.9167
    ]
  },
  "type": "Feature",
  "properties": {
    "hierarchy": [
      "tgn:2333114",
      "tgn:1000001",
      "tgn:7012149",
      "tgn:2002123",
      "tgn:7007827",
      "tgn:7029392"
    ],
    "placetype": [
      "aat:300000390"
    ],
    "id": 2333114,
    "name:xx": "Flying Dutchman Mine"
  }
}
