{
  "geometry": {
    "type": "Point",
    "coordinates": [
      -88.0167,
      46.7333
    ]
  },
  "type": "Feature",
  "properties": {
    "hierarchy": [
      "tgn:2305004",
      "tgn:1000001",
      "tgn:7012149",
      "tgn:7007520",
      "tgn:7029392"
    ],
    "placetype": [
      "aat:300008707"
    ],
    "id": 2305004,
    "name:xx": "East Branch Huron River"
  }
}
