{
  "type": "FeatureCollection",
  "features": [
    {
      "geometry": {
        "type": "Point",
        "coordinates": [
          14.016667,
          52.233333
        ]
      },
      "type": "Feature",
      "properties": {
        "hierarchy": [
          "tgn:7198090",
          "tgn:7000096",
          "tgn:1000003",
          "tgn:7000084",
          "tgn:7029392"
        ],
        "placetype": [
          "aat:300008777"
        ],
        "id": 7198090,
        "name:xx": "Duberow-Berge"
      }
    },
    {
      "geometry": {
        "type": "Point",
        "coordinates": [
          10.2,
          54.25
        ]
      },
      "type": "Feature",
      "properties": {
        "hierarchy": [
          "tgn:7198091",
          "tgn:1000003",
          "tgn:7003688",
          "tgn:7000084",
          "tgn:7029392"
        ],
        "placetype": [
          "aat:300000206"
        ],
        "id": 7198091,
        "name:xx": "Dubenhorst"
      }
    },
    {
      "geometry": {
        "type": "Point",
        "coordinates": [
          13.783333,
          51.866667
        ]
      },
      "type": "Feature",
      "properties": {
        "hierarchy": [
          "tgn:7198093",
          "tgn:7000096",
          "tgn:1000003",
          "tgn:7000084",
          "tgn:7029392"
        ],
        "placetype": [
          "aat:300008777"
        ],
        "id": 7198093,
        "name:xx": "Dubener Berge"
      }
    },
    {
      "geometry": {
        "type": "Point",
        "coordinates": [
          13.816667,
          51.9
        ]
      },
      "type": "Feature",
      "properties": {
        "hierarchy": [
          "tgn:7198094",
          "tgn:7000096",
          "tgn:1000003",
          "tgn:7000084",
          "tgn:7029392"
        ],
        "placetype": [
          "aat:300008347"
        ],
        "id": 7198094,
        "name:xx": "Bahnhof Duben"
      }
    },
    {
      "geometry": {
        "type": "Point",
        "coordinates": [
          12.383333,
          51.933333
        ]
      },
      "type": "Feature",
      "properties": {
        "hierarchy": [
          "tgn:7198095",
          "tgn:1000003",
          "tgn:7003687",
          "tgn:7000084",
          "tgn:7029392"
        ],
        "placetype": [
          "aat:300008347"
        ],
        "id": 7198095,
        "name:xx": "Düben"
      }
    },
    {
      "geometry": {
        "type": "Point",
        "coordinates": [
          10.25,
          52.883333
        ]
      },
      "type": "Feature",
      "properties": {
        "hierarchy": [
          "tgn:7198097",
          "tgn:1000003",
          "tgn:7003676",
          "tgn:7000084",
          "tgn:7029392"
        ],
        "placetype": [
          "aat:300386887"
        ],
        "id": 7198097,
        "name:xx": "Dübelsheide"
      }
    },
    {
      "geometry": {
        "type": "Point",
        "coordinates": [
          8.2,
          52.316667
        ]
      },
      "type": "Feature",
      "properties": {
        "hierarchy": [
          "tgn:7198098",
          "tgn:1000003",
          "tgn:7003676",
          "tgn:7000084",
          "tgn:7029392"
        ],
        "placetype": [
          "aat:300000206"
        ],
        "id": 7198098,
        "name:xx": "Dübberort"
      }
    },
    {
      "geometry": {
        "type": "Point",
        "coordinates": [
          10.2,
          53.983333
        ]
      },
      "type": "Feature",
      "properties": {
        "hierarchy": [
          "tgn:7198099",
          "tgn:1000003",
          "tgn:7003688",
          "tgn:7000084",
          "tgn:7029392"
        ],
        "placetype": [
          "aat:300000206"
        ],
        "id": 7198099,
        "name:xx": "Dubbensahl"
      }
    }
  ]
}
