{
  "geometry": {
    "type": "Point",
    "coordinates": [
      -74.4667,
      40.8167
    ]
  },
  "type": "Feature",
  "properties": {
    "hierarchy": [
      "tgn:7014107",
      "tgn:1000001",
      "tgn:1002695",
      "tgn:7012149",
      "tgn:7007565",
      "tgn:7029392"
    ],
    "placetype": [
      "aat:300008347"
    ],
    "id": 7014107,
    "name:xx": "Morris Plains"
  }
}
