{
  "geometry": {
    "type": "Point",
    "coordinates": [
      17.8333,
      48.1667
    ]
  },
  "type": "Feature",
  "properties": {
    "hierarchy": [
      "tgn:1027032",
      "tgn:7027129",
      "tgn:1000003",
      "tgn:7011765",
      "tgn:7029392"
    ],
    "placetype": [
      "aat:300008347"
    ],
    "id": 1027032,
    "name:xx": "Šala"
  }
}
