{
  "geometry": {
    "type": "Point",
    "coordinates": [
      -71.0667,
      42.2667
    ]
  },
  "type": "Feature",
  "properties": {
    "hierarchy": [
      "tgn:2050150",
      "tgn:1000001",
      "tgn:1002724",
      "tgn:7012149",
      "tgn:7014069",
      "tgn:7007517",
      "tgn:7029392"
    ],
    "placetype": [
      "aat:300000745"
    ],
    "id": 2050150,
    "name:xx": "Milton Village"
  }
}
