{
  "geometry": {
    "type": "Point",
    "coordinates": [
      -116.5167,
      45.4833
    ]
  },
  "type": "Feature",
  "properties": {
    "hierarchy": [
      "tgn:2499152",
      "tgn:1000001",
      "tgn:7012149",
      "tgn:2000476",
      "tgn:7007250",
      "tgn:7029392"
    ],
    "placetype": [
      "aat:300008798"
    ],
    "id": 2499152,
    "name:xx": "McCatron Ridge"
  }
}
