{
  "geometry": {
    "type": "Point",
    "coordinates": [
      -89.45,
      45.3333
    ]
  },
  "type": "Feature",
  "properties": {
    "hierarchy": [
      "tgn:2121079",
      "tgn:1000001",
      "tgn:7012149",
      "tgn:2002334",
      "tgn:7007922",
      "tgn:7029392"
    ],
    "placetype": [
      "aat:300008347"
    ],
    "id": 2121079,
    "name:xx": "Dudley"
  }
}
