{
  "geometry": {
    "type": "Point",
    "coordinates": [
      -98.9833,
      31.7833
    ]
  },
  "type": "Feature",
  "properties": {
    "hierarchy": [
      "tgn:2001948",
      "tgn:1000001",
      "tgn:7012149",
      "tgn:7007826",
      "tgn:7029392"
    ],
    "placetype": [
      "aat:300387145",
      "aat:300000771"
    ],
    "id": 2001948,
    "name:xx": "Brown"
  }
}
