{
  "geometry": {
    "type": "Point",
    "coordinates": [
      -86.05,
      35.4167
    ]
  },
  "type": "Feature",
  "properties": {
    "hierarchy": [
      "tgn:2404723",
      "tgn:1000001",
      "tgn:7012149",
      "tgn:2001852",
      "tgn:7007825",
      "tgn:7029392"
    ],
    "placetype": [
      "aat:300008706"
    ],
    "id": 2404723,
    "name:xx": "Huckleberry Creek"
  }
}
