{
  "type": "FeatureCollection",
  "features": [
    {
      "geometry": {
        "type": "Point",
        "coordinates": [
          -0.75,
          54.516667
        ]
      },
      "type": "Feature",
      "properties": {
        "hierarchy": [
          "tgn:7448270",
          "tgn:7002445",
          "tgn:1000003",
          "tgn:7008166",
          "tgn:7008591",
          "tgn:7029392"
        ],
        "placetype": [
          "aat:300008347"
        ],
        "name:en": "Runswick",
        "id": 7448270
      }
    },
    {
      "geometry": {
        "type": "Point",
        "coordinates": [
          -5.666667,
          50.033333
        ]
      },
      "type": "Feature",
      "properties": {
        "hierarchy": [
          "tgn:7448272",
          "tgn:7002445",
          "tgn:7008116",
          "tgn:1000003",
          "tgn:7008591",
          "tgn:7029392"
        ],
        "placetype": [
          "aat:300011692"
        ],
        "name:en": "Runnel Stone",
        "id": 7448272
      }
    },
    {
      "geometry": {
        "type": "Point",
        "coordinates": [
          1.65,
          52.616667
        ]
      },
      "type": "Feature",
      "properties": {
        "hierarchy": [
          "tgn:7448273",
          "tgn:7002445",
          "tgn:1000003",
          "tgn:7008160",
          "tgn:7008591",
          "tgn:7029392"
        ],
        "placetype": [
          "aat:300008347"
        ],
        "name:en": "Runham",
        "id": 7448273
      }
    },
    {
      "geometry": {
        "type": "Point",
        "coordinates": [
          -7.55,
          57.6
        ]
      },
      "type": "Feature",
      "properties": {
        "hierarchy": [
          "tgn:7448276",
          "tgn:7002444",
          "tgn:1000003",
          "tgn:7008094",
          "tgn:7008591",
          "tgn:7029392"
        ],
        "placetype": [
          "aat:300386846"
        ],
        "name:en": "Rùnair, Àird an",
        "id": 7448276
      }
    },
    {
      "geometry": {
        "type": "Point",
        "coordinates": [
          -2.633333,
          59.366667
        ]
      },
      "type": "Feature",
      "properties": {
        "hierarchy": [
          "tgn:7448277",
          "tgn:7002444",
          "tgn:1000003",
          "tgn:7009907",
          "tgn:7008591",
          "tgn:7029392"
        ],
        "placetype": [
          "aat:300011692"
        ],
        "name:en": "Runabrake",
        "id": 7448277
      }
    },
    {
      "geometry": {
        "type": "Point",
        "coordinates": [
          0.833333,
          53
        ]
      },
      "type": "Feature",
      "properties": {
        "hierarchy": [
          "tgn:7448278",
          "tgn:7002445",
          "tgn:1000003",
          "tgn:7008160",
          "tgn:7008591",
          "tgn:7029392"
        ],
        "placetype": [
          "aat:300008713"
        ],
        "name:en": "Run, The",
        "id": 7448278
      }
    },
    {
      "geometry": {
        "type": "Point",
        "coordinates": [
          -3.7,
          58.333333
        ]
      },
      "type": "Feature",
      "properties": {
        "hierarchy": [
          "tgn:7448279",
          "tgn:7002444",
          "tgn:1000003",
          "tgn:7008082",
          "tgn:7008591",
          "tgn:7029392"
        ],
        "placetype": [
          "aat:300008699"
        ],
        "name:en": "Rumsdale Water",
        "id": 7448279
      }
    }
  ]
}
