{
  "geometry": {
    "type": "Point",
    "coordinates": [
      -73.9333,
      44.3333
    ]
  },
  "type": "Feature",
  "properties": {
    "hierarchy": [
      "tgn:2149202",
      "tgn:1000001",
      "tgn:7012149",
      "tgn:2001461",
      "tgn:7007568",
      "tgn:7029392"
    ],
    "placetype": [
      "aat:300132316"
    ],
    "id": 2149202,
    "name:xx": "Barrel Bay"
  }
}
