{
  "geometry": {
    "type": "Point",
    "coordinates": [
      -80.85,
      39.8167
    ]
  },
  "type": "Feature",
  "properties": {
    "hierarchy": [
      "tgn:2442324",
      "tgn:1000001",
      "tgn:7012149",
      "tgn:2001617",
      "tgn:7007706",
      "tgn:7029392"
    ],
    "placetype": [
      "aat:300266640"
    ],
    "id": 2442324,
    "name:xx": "Krebs Ridge"
  }
}
