{
  "geometry": {
    "type": "Point",
    "coordinates": [
      -3.75,
      5.2333
    ]
  },
  "type": "Feature",
  "properties": {
    "hierarchy": [
      "tgn:7016552",
      "tgn:1000484",
      "tgn:7001242",
      "tgn:1000168",
      "tgn:7029392"
    ],
    "placetype": [
      "aat:300008347"
    ],
    "id": 7016552,
    "name:xx": "Grand Bassam"
  }
}
