{
  "geometry": {
    "type": "Point",
    "coordinates": [
      -91.8333,
      33.9167
    ]
  },
  "type": "Feature",
  "properties": {
    "hierarchy": [
      "tgn:2297545",
      "tgn:1000001",
      "tgn:7016172",
      "tgn:7012149",
      "tgn:2000144",
      "tgn:7029392"
    ],
    "placetype": [
      "aat:300008706"
    ],
    "id": 2297545,
    "name:xx": "Dry Fork Creek"
  }
}
