{
  "geometry": {
    "type": "Point",
    "coordinates": [
      -107.8167,
      36.9833
    ]
  },
  "type": "Feature",
  "properties": {
    "hierarchy": [
      "tgn:2226762",
      "tgn:1000001",
      "tgn:7012149",
      "tgn:2001452",
      "tgn:7007566",
      "tgn:7029392"
    ],
    "placetype": [
      "aat:300008697"
    ],
    "id": 2226762,
    "name:xx": "Cattail Spring"
  }
}
