{
  "geometry": {
    "type": "Point",
    "coordinates": [
      -88.7167,
      44.5167
    ]
  },
  "type": "Feature",
  "properties": {
    "hierarchy": [
      "tgn:2120703",
      "tgn:1000001",
      "tgn:7012149",
      "tgn:2002343",
      "tgn:7007922",
      "tgn:7029392"
    ],
    "placetype": [
      "aat:300008347"
    ],
    "id": 2120703,
    "name:xx": "Bear Creek"
  }
}
