{
  "geometry": {
    "type": "Point",
    "coordinates": [
      -74.25,
      42.3667
    ]
  },
  "type": "Feature",
  "properties": {
    "hierarchy": [
      "tgn:2617537",
      "tgn:1000001",
      "tgn:7012149",
      "tgn:7007568",
      "tgn:7029392"
    ],
    "placetype": [
      "aat:300008798"
    ],
    "id": 2617537,
    "name:xx": "Richtmyer Peak"
  }
}
