{
  "geometry": {
    "type": "Point",
    "coordinates": [
      -72.5333,
      41.6667
    ]
  },
  "type": "Feature",
  "properties": {
    "hierarchy": [
      "tgn:2248133",
      "tgn:1000001",
      "tgn:1002461",
      "tgn:7012149",
      "tgn:7007159",
      "tgn:7029392"
    ],
    "placetype": [
      "aat:300006191"
    ],
    "id": 2248133,
    "name:xx": "Cold Brook Reservoir"
  }
}
