{
  "geometry": {
    "type": "Point",
    "coordinates": [
      -120.75,
      44.4167
    ]
  },
  "type": "Feature",
  "properties": {
    "hierarchy": [
      "tgn:2646183",
      "tgn:1000001",
      "tgn:2001703",
      "tgn:7012149",
      "tgn:7007708",
      "tgn:7029392"
    ],
    "placetype": [
      "aat:300008761"
    ],
    "id": 2646183,
    "name:xx": "Sawtell Canyon"
  }
}
