{
  "geometry": {
    "type": "Point",
    "coordinates": [
      -91.75,
      43.7333
    ]
  },
  "type": "Feature",
  "properties": {
    "hierarchy": [
      "tgn:2274460",
      "tgn:1000001",
      "tgn:7012149",
      "tgn:7007521",
      "tgn:7029392"
    ],
    "placetype": [
      "aat:300008706"
    ],
    "id": 2274460,
    "name:xx": "Daley Creek"
  }
}
