{
  "geometry": {
    "type": "Point",
    "coordinates": [
      43.6833,
      53.2833
    ]
  },
  "type": "Feature",
  "properties": {
    "hierarchy": [
      "tgn:1060323",
      "tgn:1000004",
      "tgn:1003399",
      "tgn:7018214",
      "tgn:7002435",
      "tgn:7029392"
    ],
    "placetype": [
      "aat:300008347"
    ],
    "id": 1060323,
    "name:xx": "Titovo"
  }
}
