{
  "geometry": {
    "type": "Point",
    "coordinates": [
      -110.6667,
      47.0667
    ]
  },
  "type": "Feature",
  "properties": {
    "hierarchy": [
      "tgn:2672351",
      "tgn:1000001",
      "tgn:2001266",
      "tgn:7012149",
      "tgn:7007524",
      "tgn:7029392"
    ],
    "placetype": [
      "aat:300008706"
    ],
    "id": 2672351,
    "name:xx": "Smoke-in-Hole Creek"
  }
}
