{
  "geometry": {
    "type": "Point",
    "coordinates": [
      120.5833,
      15.3333
    ]
  },
  "type": "Feature",
  "properties": {
    "hierarchy": [
      "tgn:1084118",
      "tgn:1000004",
      "tgn:1001565",
      "tgn:1000135",
      "tgn:7029392"
    ],
    "placetype": [
      "aat:300008347"
    ],
    "id": 1084118,
    "name:xx": "Capas"
  }
}
