{
  "type": "FeatureCollection",
  "features": [
    {
      "geometry": {
        "type": "Point",
        "coordinates": [
          -119.1667,
          40.0667
        ]
      },
      "type": "Feature",
      "properties": {
        "hierarchy": [
          "tgn:2636630",
          "tgn:1000001",
          "tgn:7012149",
          "tgn:7007526",
          "tgn:7029392"
        ],
        "placetype": [
          "aat:300386845"
        ],
        "id": 2636630,
        "name:xx": "Sage Hen Valley"
      }
    },
    {
      "geometry": {
        "type": "Point",
        "coordinates": [
          -119.15,
          43.4833
        ]
      },
      "type": "Feature",
      "properties": {
        "hierarchy": [
          "tgn:2636631",
          "tgn:1000001",
          "tgn:7012149",
          "tgn:2001709",
          "tgn:7007708",
          "tgn:7029392"
        ],
        "placetype": [
          "aat:300386845"
        ],
        "id": 2636631,
        "name:xx": "Sage Hen Valley"
      }
    },
    {
      "geometry": {
        "type": "Point",
        "coordinates": [
          -119.1833,
          40.1833
        ]
      },
      "type": "Feature",
      "properties": {
        "hierarchy": [
          "tgn:2636632",
          "tgn:1000001",
          "tgn:7012149",
          "tgn:7007526",
          "tgn:7029392"
        ],
        "placetype": [
          "aat:300008699"
        ],
        "id": 2636632,
        "name:xx": "Sage Hen Wash"
      }
    },
    {
      "geometry": {
        "type": "Point",
        "coordinates": [
          -114.3333,
          38.2
        ]
      },
      "type": "Feature",
      "properties": {
        "hierarchy": [
          "tgn:2636633",
          "tgn:1000001",
          "tgn:2001416",
          "tgn:7012149",
          "tgn:7007526",
          "tgn:7029392"
        ],
        "placetype": [
          "aat:300008699"
        ],
        "id": 2636633,
        "name:xx": "Sage Hen Wash"
      }
    },
    {
      "geometry": {
        "type": "Point",
        "coordinates": [
          -147.5167,
          64.85
        ]
      },
      "type": "Feature",
      "properties": {
        "hierarchy": [
          "tgn:2636634",
          "tgn:7006450",
          "tgn:1000001",
          "tgn:7019674",
          "tgn:7012149",
          "tgn:7029392"
        ],
        "placetype": [
          "aat:300008798"
        ],
        "id": 2636634,
        "name:xx": "Sage Hill"
      }
    },
    {
      "geometry": {
        "type": "Point",
        "coordinates": [
          -120.75,
          39.0167
        ]
      },
      "type": "Feature",
      "properties": {
        "hierarchy": [
          "tgn:2636635",
          "tgn:1000001",
          "tgn:7012149",
          "tgn:7007157",
          "tgn:1002791",
          "tgn:7029392"
        ],
        "placetype": [
          "aat:300008798"
        ],
        "id": 2636635,
        "name:xx": "Sage Hill"
      }
    },
    {
      "geometry": {
        "type": "Point",
        "coordinates": [
          -119.7833,
          34.55
        ]
      },
      "type": "Feature",
      "properties": {
        "hierarchy": [
          "tgn:2636636",
          "tgn:1000001",
          "tgn:7012149",
          "tgn:7007157",
          "tgn:1002867",
          "tgn:7029392"
        ],
        "placetype": [
          "aat:300008798"
        ],
        "id": 2636636,
        "name:xx": "Sage Hill"
      }
    },
    {
      "geometry": {
        "type": "Point",
        "coordinates": [
          -111.85,
          40.6667
        ]
      },
      "type": "Feature",
      "properties": {
        "hierarchy": [
          "tgn:2636637",
          "tgn:1000001",
          "tgn:7012149",
          "tgn:2002118",
          "tgn:7007827",
          "tgn:7029392"
        ],
        "placetype": [
          "aat:300008347"
        ],
        "id": 2636637,
        "name:xx": "Sage Hill"
      }
    },
    {
      "geometry": {
        "type": "Point",
        "coordinates": [
          -72.85,
          43.0833
        ]
      },
      "type": "Feature",
      "properties": {
        "hierarchy": [
          "tgn:2636638",
          "tgn:1000001",
          "tgn:1003029",
          "tgn:7012149",
          "tgn:7007828",
          "tgn:7029392"
        ],
        "placetype": [
          "aat:300008798"
        ],
        "id": 2636638,
        "name:xx": "Sage Hill"
      }
    },
    {
      "geometry": {
        "type": "Point",
        "coordinates": [
          -112.4833,
          38.2667
        ]
      },
      "type": "Feature",
      "properties": {
        "hierarchy": [
          "tgn:2636639",
          "tgn:2002101",
          "tgn:1000001",
          "tgn:7012149",
          "tgn:7007827",
          "tgn:7029392"
        ],
        "placetype": [
          "aat:300008697"
        ],
        "id": 2636639,
        "name:xx": "Sage Hill Spring"
      }
    }
  ]
}
