{
  "geometry": {
    "type": "Point",
    "coordinates": [
      34.494729,
      29.458945
    ]
  },
  "type": "Feature",
  "properties": {
    "hierarchy": [
      "tgn:7529959",
      "tgn:7001242",
      "tgn:7016833",
      "tgn:7001336",
      "tgn:7029392"
    ],
    "placetype": [
      "aat:300379998"
    ],
    "name:en": "Abū Buţaymah, Wādī",
    "id": 7529959
  }
}
