{
  "geometry": {
    "type": "Point",
    "coordinates": [
      -83.0333,
      33.9167
    ]
  },
  "type": "Feature",
  "properties": {
    "hierarchy": [
      "tgn:2515653",
      "tgn:1000001",
      "tgn:7012149",
      "tgn:2000400",
      "tgn:7007248",
      "tgn:7029392"
    ],
    "placetype": [
      "aat:300008706"
    ],
    "id": 2515653,
    "name:xx": "Millstone Creek"
  }
}
