{
  "geometry": {
    "type": "Point",
    "coordinates": [
      -105.3167,
      32.5167
    ]
  },
  "type": "Feature",
  "properties": {
    "hierarchy": [
      "tgn:2699480",
      "tgn:1000001",
      "tgn:2001430",
      "tgn:7012149",
      "tgn:7007566",
      "tgn:7029392"
    ],
    "placetype": [
      "aat:300006191"
    ],
    "id": 2699480,
    "name:xx": "Strong Tank"
  }
}
