{
  "geometry": {
    "type": "Point",
    "coordinates": [
      -83.5167,
      31.6167
    ]
  },
  "type": "Feature",
  "properties": {
    "hierarchy": [
      "tgn:2555467",
      "tgn:1000001",
      "tgn:7012149",
      "tgn:2000433",
      "tgn:7007248",
      "tgn:7029392"
    ],
    "placetype": [
      "aat:300006191"
    ],
    "id": 2555467,
    "name:xx": "Odum Lake"
  }
}
