{
  "geometry": {
    "type": "Point",
    "coordinates": [
      -122.05,
      42.9167
    ]
  },
  "type": "Feature",
  "properties": {
    "hierarchy": [
      "tgn:2244817",
      "tgn:1000001",
      "tgn:7012149",
      "tgn:2001714",
      "tgn:7007708",
      "tgn:7029392"
    ],
    "placetype": [
      "aat:300132316"
    ],
    "id": 2244817,
    "name:xx": "Cloudcap Bay"
  }
}
