{
  "geometry": {
    "type": "Point",
    "coordinates": [
      -94.9667,
      42.2333
    ]
  },
  "type": "Feature",
  "properties": {
    "hierarchy": [
      "tgn:2294834",
      "tgn:1000001",
      "tgn:7012149",
      "tgn:2000641",
      "tgn:7007253",
      "tgn:7029392"
    ],
    "placetype": [
      "aat:300006075"
    ],
    "id": 2294834,
    "name:xx": "Drainage Ditch Number 57"
  }
}
