{
  "type": "FeatureCollection",
  "features": [
    {
      "geometry": {
        "type": "Point",
        "coordinates": [
          0.783333,
          51.3
        ]
      },
      "type": "Feature",
      "properties": {
        "hierarchy": [
          "tgn:7457753",
          "tgn:7002445",
          "tgn:1000003",
          "tgn:7008153",
          "tgn:7008591",
          "tgn:7029392"
        ],
        "placetype": [
          "aat:300008347"
        ],
        "name:en": "Lynsted",
        "id": 7457753
      }
    },
    {
      "geometry": {
        "type": "Point",
        "coordinates": [
          -5.55,
          56.533333
        ]
      },
      "type": "Feature",
      "properties": {
        "hierarchy": [
          "tgn:7457754",
          "tgn:7002444",
          "tgn:1000003",
          "tgn:7008082",
          "tgn:7008591",
          "tgn:7029392"
        ],
        "placetype": [
          "aat:300008713"
        ],
        "name:en": "Morvern, Lynn of",
        "id": 7457754
      }
    },
    {
      "geometry": {
        "type": "Point",
        "coordinates": [
          0.45,
          53.083333
        ]
      },
      "type": "Feature",
      "properties": {
        "hierarchy": [
          "tgn:7457755",
          "tgn:7002445",
          "tgn:1000003",
          "tgn:7008160",
          "tgn:7008591",
          "tgn:7029392"
        ],
        "placetype": [
          "aat:300387036"
        ],
        "name:en": "Lynn Knock",
        "id": 7457755
      }
    },
    {
      "geometry": {
        "type": "Point",
        "coordinates": [
          0.333333,
          53
        ]
      },
      "type": "Feature",
      "properties": {
        "hierarchy": [
          "tgn:7457756",
          "tgn:7002445",
          "tgn:1000003",
          "tgn:7008157",
          "tgn:7008591",
          "tgn:7029392"
        ],
        "placetype": [
          "aat:300008713"
        ],
        "name:en": "Lynn Deeps",
        "id": 7457756
      }
    },
    {
      "geometry": {
        "type": "Point",
        "coordinates": [
          0.283333,
          52.916667
        ]
      },
      "type": "Feature",
      "properties": {
        "hierarchy": [
          "tgn:7457757",
          "tgn:7002445",
          "tgn:1000003",
          "tgn:7008160",
          "tgn:7008591",
          "tgn:7029392"
        ],
        "placetype": [
          "aat:300008713"
        ],
        "name:en": "Lynn Channel",
        "id": 7457757
      }
    }
  ]
}
