{
  "geometry": {
    "type": "Point",
    "coordinates": [
      29.8333,
      -12.15
    ]
  },
  "type": "Feature",
  "properties": {
    "hierarchy": [
      "tgn:1095988",
      "tgn:1001187",
      "tgn:7001242",
      "tgn:1000209",
      "tgn:7029392"
    ],
    "placetype": [
      "aat:300008347"
    ],
    "id": 1095988,
    "name:xx": "Mukuku"
  }
}
