{
  "geometry": {
    "type": "Point",
    "coordinates": [
      -105.5333,
      37.0333
    ]
  },
  "type": "Feature",
  "properties": {
    "hierarchy": [
      "tgn:2309679",
      "tgn:1000001",
      "tgn:7012149",
      "tgn:2000203",
      "tgn:7007158",
      "tgn:7029392"
    ],
    "placetype": [
      "aat:300006075"
    ],
    "id": 2309679,
    "name:xx": "Eastdale Canal Number 2"
  }
}
