{
  "geometry": {
    "type": "Point",
    "coordinates": [
      -120.4333,
      43.8667
    ]
  },
  "type": "Feature",
  "properties": {
    "hierarchy": [
      "tgn:2599068",
      "tgn:1000001",
      "tgn:2001703",
      "tgn:7012149",
      "tgn:7007708",
      "tgn:7029392"
    ],
    "placetype": [
      "aat:300006191"
    ],
    "id": 2599068,
    "name:xx": "Pringle Flat Reservoir"
  }
}
