{
  "geometry": {
    "type": "Point",
    "coordinates": [
      23.511094,
      37.33835
    ]
  },
  "type": "Feature",
  "properties": {
    "hierarchy": [
      "tgn:7228211",
      "tgn:7002681",
      "tgn:7001395",
      "tgn:1000003",
      "tgn:1000074",
      "tgn:7029392"
    ],
    "placetype": [
      "aat:300132316"
    ],
    "id": 7228211,
    "name:xx": "Limnióniza, Órmos"
  }
}
