{
  "geometry": {
    "type": "Point",
    "coordinates": [
      89.4333,
      26.8667
    ]
  },
  "type": "Feature",
  "properties": {
    "hierarchy": [
      "tgn:1065975",
      "tgn:7014836",
      "tgn:1000004",
      "tgn:7014831",
      "tgn:7029392"
    ],
    "placetype": [
      "aat:300008347"
    ],
    "id": 1065975,
    "name:xx": "Phuntsholing"
  }
}
