{
  "geometry": {
    "type": "Point",
    "coordinates": [
      -74.35,
      43.2167
    ]
  },
  "type": "Feature",
  "properties": {
    "hierarchy": [
      "tgn:2233686",
      "tgn:1000001",
      "tgn:7012149",
      "tgn:1002397",
      "tgn:7007568",
      "tgn:7029392"
    ],
    "placetype": [
      "aat:300008680"
    ],
    "id": 2233686,
    "name:xx": "Chase Lake"
  }
}
