{
  "geometry": {
    "type": "Point",
    "coordinates": [
      -81.9167,
      39.7667
    ]
  },
  "type": "Feature",
  "properties": {
    "hierarchy": [
      "tgn:2269461",
      "tgn:1000001",
      "tgn:7012149",
      "tgn:1002701",
      "tgn:7007706",
      "tgn:7029392"
    ],
    "placetype": [
      "aat:300008699"
    ],
    "id": 2269461,
    "name:xx": "Crow Run"
  }
}
