{
  "geometry": {
    "type": "Point",
    "coordinates": [
      -82.0833,
      37.5167
    ]
  },
  "type": "Feature",
  "properties": {
    "hierarchy": [
      "tgn:2592972",
      "tgn:1000001",
      "tgn:7012149",
      "tgn:2000837",
      "tgn:7007255",
      "tgn:7029392"
    ],
    "placetype": [
      "aat:300008706"
    ],
    "id": 2592972,
    "name:xx": "Poplar Creek"
  }
}
