{
  "geometry": {
    "type": "Point",
    "coordinates": [
      9.9167,
      50.4833
    ]
  },
  "type": "Feature",
  "properties": {
    "hierarchy": [
      "tgn:6005303",
      "tgn:1000003",
      "tgn:7003682",
      "tgn:7000084",
      "tgn:7029392"
    ],
    "placetype": [
      "aat:300387006"
    ],
    "id": 6005303,
    "name:xx": "Schwarzerden"
  }
}
