{
  "type": "FeatureCollection",
  "features": [
    {
      "geometry": {
        "type": "Point",
        "coordinates": [
          17.166667,
          39.016667
        ]
      },
      "type": "Feature",
      "properties": {
        "hierarchy": [
          "tgn:7040021",
          "tgn:7024841",
          "tgn:7007850",
          "tgn:1000003",
          "tgn:1000080",
          "tgn:7029392"
        ],
        "placetype": [
          "aat:300008347"
        ],
        "id": 7040021,
        "name:xx": "Scifo"
      }
    },
    {
      "geometry": {
        "type": "Point",
        "coordinates": [
          13.483333,
          41.7
        ]
      },
      "type": "Feature",
      "properties": {
        "hierarchy": [
          "tgn:7040022",
          "tgn:7003135",
          "tgn:1000003",
          "tgn:7003080",
          "tgn:1000080",
          "tgn:7029392"
        ],
        "placetype": [
          "aat:300008347"
        ],
        "id": 7040022,
        "name:xx": "Scifelli"
      }
    },
    {
      "geometry": {
        "type": "Point",
        "coordinates": [
          8.65,
          46.083333
        ]
      },
      "type": "Feature",
      "properties": {
        "hierarchy": [
          "tgn:7040023",
          "tgn:1003478",
          "tgn:1000003",
          "tgn:7003120",
          "tgn:1000080",
          "tgn:7029392"
        ],
        "placetype": [
          "aat:300008347"
        ],
        "id": 7040023,
        "name:xx": "Scierz"
      }
    },
    {
      "geometry": {
        "type": "Point",
        "coordinates": [
          15.933333,
          38.233333
        ]
      },
      "type": "Feature",
      "properties": {
        "hierarchy": [
          "tgn:7040024",
          "tgn:7007850",
          "tgn:1003491",
          "tgn:1000003",
          "tgn:1000080",
          "tgn:7029392"
        ],
        "placetype": [
          "aat:300008347"
        ],
        "id": 7040024,
        "name:xx": "Scido"
      }
    },
    {
      "geometry": {
        "type": "Point",
        "coordinates": [
          16.033333,
          38.7
        ]
      },
      "type": "Feature",
      "properties": {
        "hierarchy": [
          "tgn:7040025",
          "tgn:7007850",
          "tgn:7024842",
          "tgn:1000003",
          "tgn:1000080",
          "tgn:7029392"
        ],
        "placetype": [
          "aat:300008347"
        ],
        "id": 7040025,
        "name:xx": "Sciconi"
      }
    },
    {
      "geometry": {
        "type": "Point",
        "coordinates": [
          15.883333,
          40.266667
        ]
      },
      "type": "Feature",
      "properties": {
        "hierarchy": [
          "tgn:7040028",
          "tgn:1003489",
          "tgn:7004610",
          "tgn:1000003",
          "tgn:1000080",
          "tgn:7029392"
        ],
        "placetype": [
          "aat:300008699"
        ],
        "id": 7040028,
        "name:xx": "Sciaura, Fiume"
      }
    },
    {
      "geometry": {
        "type": "Point",
        "coordinates": [
          15.5,
          40.15
        ]
      },
      "type": "Feature",
      "properties": {
        "hierarchy": [
          "tgn:7040029",
          "tgn:7003005",
          "tgn:7003014",
          "tgn:1000003",
          "tgn:1000080",
          "tgn:7029392"
        ],
        "placetype": [
          "aat:300008761"
        ],
        "id": 7040029,
        "name:xx": "Sciarapatamo, Valle"
      }
    }
  ]
}
