{
  "geometry": {
    "type": "Point",
    "coordinates": [
      87.123326,
      21.514234
    ]
  },
  "type": "Feature",
  "properties": {
    "hierarchy": [
      "tgn:7553167",
      "tgn:1000004",
      "tgn:7000198",
      "tgn:7016694",
      "tgn:7029392"
    ],
    "placetype": [
      "aat:300008699"
    ],
    "name:en": "Pānchpāra Nadī",
    "id": 7553167
  }
}
