{
  "geometry": {
    "type": "Point",
    "coordinates": [
      -79.6667,
      37.7167
    ]
  },
  "type": "Feature",
  "properties": {
    "hierarchy": [
      "tgn:2670784",
      "tgn:1000001",
      "tgn:7012149",
      "tgn:7007919",
      "tgn:7029392"
    ],
    "placetype": [
      "aat:300008699"
    ],
    "id": 2670784,
    "name:xx": "Smith Branch"
  }
}
