{
  "geometry": {
    "type": "Point",
    "coordinates": [
      -89.0333,
      46.3833
    ]
  },
  "type": "Feature",
  "properties": {
    "hierarchy": [
      "tgn:2729951",
      "tgn:1000001",
      "tgn:7012149",
      "tgn:7007520",
      "tgn:7029392"
    ],
    "placetype": [
      "aat:300008706"
    ],
    "id": 2729951,
    "name:xx": "Trout Creek"
  }
}
