{
  "geometry": {
    "type": "Point",
    "coordinates": [
      -87.3667,
      35.65
    ]
  },
  "type": "Feature",
  "properties": {
    "hierarchy": [
      "tgn:2472714",
      "tgn:1000001",
      "tgn:7012149",
      "tgn:7015666",
      "tgn:7007825",
      "tgn:7029392"
    ],
    "placetype": [
      "aat:300008761"
    ],
    "id": 2472714,
    "name:xx": "Lovell Hollow"
  }
}
