{
  "geometry": {
    "type": "Point",
    "coordinates": [
      74.929758,
      32.60958
    ]
  },
  "type": "Feature",
  "properties": {
    "hierarchy": [
      "tgn:7591341",
      "tgn:1000004",
      "tgn:7000198",
      "tgn:7000799",
      "tgn:7029392"
    ],
    "placetype": [
      "aat:300008347"
    ],
    "name:en": "Khadargāi",
    "id": 7591341
  }
}
