{
  "type": "FeatureCollection",
  "features": [
    {
      "geometry": {
        "type": "Point",
        "coordinates": [
          47.0833,
          56.9167
        ]
      },
      "type": "Feature",
      "properties": {
        "hierarchy": [
          "tgn:1052970",
          "tgn:1000004",
          "tgn:7014795",
          "tgn:7002435",
          "tgn:7029392"
        ],
        "placetype": [
          "aat:300008347"
        ],
        "id": 1052970,
        "name:xx": "Bol'shoye Kibeyevo"
      }
    },
    {
      "geometry": {
        "type": "Point",
        "coordinates": [
          39.1333,
          54.5
        ]
      },
      "type": "Feature",
      "properties": {
        "hierarchy": [
          "tgn:1052971",
          "tgn:1000004",
          "tgn:1003404",
          "tgn:7018214",
          "tgn:7002435",
          "tgn:7029392"
        ],
        "placetype": [
          "aat:300008347"
        ],
        "id": 1052971,
        "name:xx": "Bol'shoye Korovino"
      }
    },
    {
      "geometry": {
        "type": "Point",
        "coordinates": [
          30.8167,
          59.8833
        ]
      },
      "type": "Feature",
      "properties": {
        "hierarchy": [
          "tgn:1052972",
          "tgn:1000004",
          "tgn:7011572",
          "tgn:7018214",
          "tgn:7002435",
          "tgn:7029392"
        ],
        "placetype": [
          "aat:300008347"
        ],
        "id": 1052972,
        "name:xx": "Bol'shoye Manushkino"
      }
    },
    {
      "geometry": {
        "type": "Point",
        "coordinates": [
          38.0667,
          56.75
        ]
      },
      "type": "Feature",
      "properties": {
        "hierarchy": [
          "tgn:1052973",
          "tgn:1000004",
          "tgn:7012941",
          "tgn:7018214",
          "tgn:7002435",
          "tgn:7029392"
        ],
        "placetype": [
          "aat:300008347"
        ],
        "id": 1052973,
        "name:xx": "Bol'shoye Mikhaylovskoye"
      }
    },
    {
      "geometry": {
        "type": "Point",
        "coordinates": [
          51.7,
          53.9333
        ]
      },
      "type": "Feature",
      "properties": {
        "hierarchy": [
          "tgn:1052974",
          "tgn:1000004",
          "tgn:1003407",
          "tgn:7018214",
          "tgn:7002435",
          "tgn:7029392"
        ],
        "placetype": [
          "aat:300008347"
        ],
        "id": 1052974,
        "name:xx": "Bol'šoje Mikuškino"
      }
    },
    {
      "geometry": {
        "type": "Point",
        "coordinates": [
          44.7667,
          55.7667
        ]
      },
      "type": "Feature",
      "properties": {
        "hierarchy": [
          "tgn:1052975",
          "tgn:1000004",
          "tgn:7011585",
          "tgn:7018214",
          "tgn:7002435",
          "tgn:7029392"
        ],
        "placetype": [
          "aat:300008347"
        ],
        "id": 1052975,
        "name:xx": "Bol'shoye Murashkino"
      }
    },
    {
      "geometry": {
        "type": "Point",
        "coordinates": [
          47.9833,
          54.5
        ]
      },
      "type": "Feature",
      "properties": {
        "hierarchy": [
          "tgn:1052976",
          "tgn:1000004",
          "tgn:7011609",
          "tgn:7018214",
          "tgn:7002435",
          "tgn:7029392"
        ],
        "placetype": [
          "aat:300008347"
        ],
        "id": 1052976,
        "name:xx": "Bol'shoye Nagatkino"
      }
    },
    {
      "geometry": {
        "type": "Point",
        "coordinates": [
          52.6667,
          55.3667
        ]
      },
      "type": "Feature",
      "properties": {
        "hierarchy": [
          "tgn:1052977",
          "tgn:1000004",
          "tgn:7002435",
          "tgn:7011524",
          "tgn:7029392"
        ],
        "placetype": [
          "aat:300008347"
        ],
        "id": 1052977,
        "name:xx": "Bol'shoye Nurkeyevo"
      }
    },
    {
      "geometry": {
        "type": "Point",
        "coordinates": [
          50.3167,
          55.7333
        ]
      },
      "type": "Feature",
      "properties": {
        "hierarchy": [
          "tgn:1052978",
          "tgn:1000004",
          "tgn:7002435",
          "tgn:7011524",
          "tgn:7029392"
        ],
        "placetype": [
          "aat:300008347"
        ],
        "id": 1052978,
        "name:xx": "Bol'šoje Nyrsy"
      }
    },
    {
      "geometry": {
        "type": "Point",
        "coordinates": [
          37.7167,
          53.55
        ]
      },
      "type": "Feature",
      "properties": {
        "hierarchy": [
          "tgn:1052979",
          "tgn:1000004",
          "tgn:1003418",
          "tgn:7018214",
          "tgn:7002435",
          "tgn:7029392"
        ],
        "placetype": [
          "aat:300008347"
        ],
        "id": 1052979,
        "name:xx": "Bol'shoye Ogar'ovo"
      }
    }
  ]
}
