{
  "geometry": {
    "type": "Point",
    "coordinates": [
      -75.6833,
      40.4667
    ]
  },
  "type": "Feature",
  "properties": {
    "hierarchy": [
      "tgn:2723231",
      "tgn:1000001",
      "tgn:7012149",
      "tgn:7007710",
      "tgn:7029392"
    ],
    "placetype": [
      "aat:300008706"
    ],
    "id": 2723231,
    "name:xx": "Toad Creek"
  }
}
