{
  "geometry": {
    "type": "Point",
    "coordinates": [
      -75.1167,
      38.5333
    ]
  },
  "type": "Feature",
  "properties": {
    "hierarchy": [
      "tgn:2284479",
      "tgn:1002933",
      "tgn:1000001",
      "tgn:7012149",
      "tgn:7007239",
      "tgn:7029392"
    ],
    "placetype": [
      "aat:300008699"
    ],
    "id": 2284479,
    "name:xx": "Derrickson Ditch"
  }
}
