{
  "geometry": {
    "type": "Point",
    "coordinates": [
      21.0833,
      -6.6167
    ]
  },
  "type": "Feature",
  "properties": {
    "hierarchy": [
      "tgn:7000624",
      "tgn:7001242",
      "tgn:7029392"
    ],
    "placetype": [
      "aat:300008707"
    ],
    "id": 7000624,
    "name:xx": "Luembe"
  }
}
