{
  "geometry": {
    "type": "Point",
    "coordinates": [
      -110.8833,
      39.0167
    ]
  },
  "type": "Feature",
  "properties": {
    "hierarchy": [
      "tgn:2785210",
      "tgn:1000001",
      "tgn:2002108",
      "tgn:7012149",
      "tgn:7007827",
      "tgn:7029392"
    ],
    "placetype": [
      "aat:300008697"
    ],
    "id": 2785210,
    "name:xx": "Yellow Seep"
  }
}
