{
  "geometry": {
    "type": "Point",
    "coordinates": [
      79.39893,
      27.044753
    ]
  },
  "type": "Feature",
  "properties": {
    "hierarchy": [
      "tgn:7562678",
      "tgn:1000004",
      "tgn:7000198",
      "tgn:7016722",
      "tgn:7029392"
    ],
    "placetype": [
      "aat:300008347"
    ],
    "name:en": "Nagla Āchchhelāl",
    "id": 7562678
  }
}
