{
  "geometry": {
    "type": "Point",
    "coordinates": [
      15.75,
      60.35
    ]
  },
  "type": "Feature",
  "properties": {
    "hierarchy": [
      "tgn:1063535",
      "tgn:1000403",
      "tgn:1000003",
      "tgn:1000097",
      "tgn:7029392"
    ],
    "placetype": [
      "aat:300008347"
    ],
    "id": 1063535,
    "name:xx": "Säter"
  }
}
