{
  "geometry": {
    "type": "Point",
    "coordinates": [
      -94.3667,
      30.6667
    ]
  },
  "type": "Feature",
  "properties": {
    "hierarchy": [
      "tgn:2104828",
      "tgn:1000001",
      "tgn:7012149",
      "tgn:1002959",
      "tgn:7007826",
      "tgn:7029392"
    ],
    "placetype": [
      "aat:300008347"
    ],
    "id": 2104828,
    "name:xx": "Hillister"
  }
}
