{
  "geometry": {
    "type": "Point",
    "coordinates": [
      -92.6667,
      40.6833
    ]
  },
  "type": "Feature",
  "properties": {
    "hierarchy": [
      "tgn:2035297",
      "tgn:7019177",
      "tgn:1000001",
      "tgn:7012149",
      "tgn:7007253",
      "tgn:7029392"
    ],
    "placetype": [
      "aat:300008347"
    ],
    "id": 2035297,
    "name:xx": "Moulton"
  }
}
