{
  "type": "FeatureCollection",
  "features": [
    {
      "geometry": {
        "type": "Point",
        "coordinates": [
          -96.2333,
          35.85
        ]
      },
      "type": "Feature",
      "properties": {
        "hierarchy": [
          "tgn:2527750",
          "tgn:1000001",
          "tgn:2001641",
          "tgn:7012149",
          "tgn:7007707",
          "tgn:7029392"
        ],
        "placetype": [
          "aat:300008706"
        ],
        "id": 2527750,
        "name:xx": "Mountain Creek"
      }
    },
    {
      "geometry": {
        "type": "Point",
        "coordinates": [
          -122.1333,
          43.5167
        ]
      },
      "type": "Feature",
      "properties": {
        "hierarchy": [
          "tgn:2527751",
          "tgn:1000001",
          "tgn:7012149",
          "tgn:2001714",
          "tgn:7007708",
          "tgn:7029392"
        ],
        "placetype": [
          "aat:300008706"
        ],
        "id": 2527751,
        "name:xx": "Mountain Creek"
      }
    },
    {
      "geometry": {
        "type": "Point",
        "coordinates": [
          -118.8167,
          43.9
        ]
      },
      "type": "Feature",
      "properties": {
        "hierarchy": [
          "tgn:2527752",
          "tgn:1000001",
          "tgn:7012149",
          "tgn:7007708",
          "tgn:7029392"
        ],
        "placetype": [
          "aat:300008706"
        ],
        "id": 2527752,
        "name:xx": "Mountain Creek"
      }
    },
    {
      "geometry": {
        "type": "Point",
        "coordinates": [
          -120.05,
          44.5167
        ]
      },
      "type": "Feature",
      "properties": {
        "hierarchy": [
          "tgn:2527753",
          "tgn:1000001",
          "tgn:7012149",
          "tgn:2001723",
          "tgn:7007708",
          "tgn:7029392"
        ],
        "placetype": [
          "aat:300008706"
        ],
        "id": 2527753,
        "name:xx": "Mountain Creek"
      }
    },
    {
      "geometry": {
        "type": "Point",
        "coordinates": [
          -79.7167,
          39.7833
        ]
      },
      "type": "Feature",
      "properties": {
        "hierarchy": [
          "tgn:2527754",
          "tgn:1000001",
          "tgn:7012149",
          "tgn:7014185",
          "tgn:7007710",
          "tgn:7029392"
        ],
        "placetype": [
          "aat:300008706"
        ],
        "id": 2527754,
        "name:xx": "Mountain Creek"
      }
    },
    {
      "geometry": {
        "type": "Point",
        "coordinates": [
          -82,
          33.9833
        ]
      },
      "type": "Feature",
      "properties": {
        "hierarchy": [
          "tgn:2527755",
          "tgn:1000001",
          "tgn:7012149",
          "tgn:7007712",
          "tgn:7029392"
        ],
        "placetype": [
          "aat:300008706"
        ],
        "id": 2527755,
        "name:xx": "Mountain Creek"
      }
    },
    {
      "geometry": {
        "type": "Point",
        "coordinates": [
          -82.3667,
          34.1167
        ]
      },
      "type": "Feature",
      "properties": {
        "hierarchy": [
          "tgn:2527756",
          "tgn:2001725",
          "tgn:1000001",
          "tgn:7012149",
          "tgn:7007712",
          "tgn:7029392"
        ],
        "placetype": [
          "aat:300008706"
        ],
        "id": 2527756,
        "name:xx": "Mountain Creek"
      }
    },
    {
      "geometry": {
        "type": "Point",
        "coordinates": [
          -82.7,
          34.4333
        ]
      },
      "type": "Feature",
      "properties": {
        "hierarchy": [
          "tgn:2527757",
          "tgn:2001728",
          "tgn:1000001",
          "tgn:7012149",
          "tgn:7007712",
          "tgn:7029392"
        ],
        "placetype": [
          "aat:300008706"
        ],
        "id": 2527757,
        "name:xx": "Mountain Creek"
      }
    },
    {
      "geometry": {
        "type": "Point",
        "coordinates": [
          -82.1167,
          34.6167
        ]
      },
      "type": "Feature",
      "properties": {
        "hierarchy": [
          "tgn:2527758",
          "tgn:1000001",
          "tgn:7012149",
          "tgn:2001754",
          "tgn:7007712",
          "tgn:7029392"
        ],
        "placetype": [
          "aat:300008706"
        ],
        "id": 2527758,
        "name:xx": "Mountain Creek"
      }
    },
    {
      "geometry": {
        "type": "Point",
        "coordinates": [
          -82.3667,
          34.9333
        ]
      },
      "type": "Feature",
      "properties": {
        "hierarchy": [
          "tgn:2527759",
          "tgn:1000001",
          "tgn:2001747",
          "tgn:7012149",
          "tgn:7007712",
          "tgn:7029392"
        ],
        "placetype": [
          "aat:300008706"
        ],
        "id": 2527759,
        "name:xx": "Mountain Creek"
      }
    }
  ]
}
