{
  "geometry": {
    "type": "Point",
    "coordinates": [
      -117.4833,
      38.0667
    ]
  },
  "type": "Feature",
  "properties": {
    "hierarchy": [
      "tgn:2384088",
      "tgn:1000001",
      "tgn:2001412",
      "tgn:7012149",
      "tgn:7007526",
      "tgn:7029392"
    ],
    "placetype": [
      "aat:300000390"
    ],
    "id": 2384088,
    "name:xx": "Heidi Mine"
  }
}
