{
  "geometry": {
    "type": "Point",
    "coordinates": [
      -107.85,
      39.3833
    ]
  },
  "type": "Feature",
  "properties": {
    "hierarchy": [
      "tgn:1107432",
      "tgn:1000001",
      "tgn:7012149",
      "tgn:2000214",
      "tgn:7007158",
      "tgn:7029392"
    ],
    "placetype": [
      "aat:300008798"
    ],
    "id": 1107432,
    "name:xx": "North Mamm Peak"
  }
}
