{
  "geometry": {
    "type": "Point",
    "coordinates": [
      -89.5167,
      36.45
    ]
  },
  "type": "Feature",
  "properties": {
    "hierarchy": [
      "tgn:2542861",
      "tgn:1000001",
      "tgn:7012149",
      "tgn:2001884",
      "tgn:7007825",
      "tgn:7029392"
    ],
    "placetype": [
      "aat:300132348"
    ],
    "id": 2542861,
    "name:xx": "Nolan Bar"
  }
}
