{
  "geometry": {
    "type": "Point",
    "coordinates": [
      -85.8833,
      33.5333
    ]
  },
  "type": "Feature",
  "properties": {
    "hierarchy": [
      "tgn:2664135",
      "tgn:7002659",
      "tgn:1000001",
      "tgn:7012149",
      "tgn:2000060",
      "tgn:7029392"
    ],
    "placetype": [
      "aat:300008706"
    ],
    "id": 2664135,
    "name:xx": "Silver Run Creek"
  }
}
