{
  "geometry": {
    "type": "Point",
    "coordinates": [
      -77.6167,
      42.4833
    ]
  },
  "type": "Feature",
  "properties": {
    "hierarchy": [
      "tgn:2685044",
      "tgn:1000001",
      "tgn:7012149",
      "tgn:1002920",
      "tgn:7007568",
      "tgn:7029392"
    ],
    "placetype": [
      "aat:300008761"
    ],
    "id": 2685044,
    "name:xx": "Sponable Gully"
  }
}
