{
  "type": "FeatureCollection",
  "features": [
    {
      "geometry": {
        "type": "Point",
        "coordinates": [
          -102.0167,
          33.8167
        ]
      },
      "type": "Feature",
      "properties": {
        "hierarchy": [
          "tgn:2103493",
          "tgn:1000001",
          "tgn:7012149",
          "tgn:2001994",
          "tgn:7007826",
          "tgn:7029392"
        ],
        "placetype": [
          "aat:300008347",
          "aat:300387210"
        ],
        "id": 2103493,
        "name:xx": "County Line"
      }
    },
    {
      "geometry": {
        "type": "Point",
        "coordinates": [
          -94.75,
          32.9
        ]
      },
      "type": "Feature",
      "properties": {
        "hierarchy": [
          "tgn:2103494",
          "tgn:1000001",
          "tgn:7012149",
          "tgn:1002230",
          "tgn:7007826",
          "tgn:7029392"
        ],
        "placetype": [
          "aat:300008347",
          "aat:300387210"
        ],
        "id": 2103494,
        "name:xx": "County Line"
      }
    },
    {
      "geometry": {
        "type": "Point",
        "coordinates": [
          -102.65,
          33.7667
        ]
      },
      "type": "Feature",
      "properties": {
        "hierarchy": [
          "tgn:2103495",
          "tgn:1000001",
          "tgn:7012149",
          "tgn:2001957",
          "tgn:7007826",
          "tgn:7029392"
        ],
        "placetype": [
          "aat:300008347",
          "aat:300387210"
        ],
        "id": 2103495,
        "name:xx": "County Line"
      }
    },
    {
      "geometry": {
        "type": "Point",
        "coordinates": [
          -97.3833,
          30.45
        ]
      },
      "type": "Feature",
      "properties": {
        "hierarchy": [
          "tgn:2103496",
          "tgn:1000001",
          "tgn:7012149",
          "tgn:1003026",
          "tgn:7007826",
          "tgn:7029392"
        ],
        "placetype": [
          "aat:300008347"
        ],
        "id": 2103496,
        "name:xx": "Coupland"
      }
    },
    {
      "geometry": {
        "type": "Point",
        "coordinates": [
          -96.05,
          30.2667
        ]
      },
      "type": "Feature",
      "properties": {
        "hierarchy": [
          "tgn:2103497",
          "tgn:1000001",
          "tgn:7012149",
          "tgn:1002429",
          "tgn:7007826",
          "tgn:7029392"
        ],
        "placetype": [
          "aat:300008347",
          "aat:300387210"
        ],
        "id": 2103497,
        "name:xx": "Courtney"
      }
    },
    {
      "geometry": {
        "type": "Point",
        "coordinates": [
          -94.8,
          29.8167
        ]
      },
      "type": "Feature",
      "properties": {
        "hierarchy": [
          "tgn:2103498",
          "tgn:1000001",
          "tgn:7012149",
          "tgn:1002251",
          "tgn:7007826",
          "tgn:7029392"
        ],
        "placetype": [
          "aat:300008347"
        ],
        "id": 2103498,
        "name:xx": "Cove"
      }
    }
  ]
}
