{
  "geometry": {
    "type": "Point",
    "coordinates": [
      -133.5167,
      58.4333
    ]
  },
  "type": "Feature",
  "properties": {
    "hierarchy": [
      "tgn:1105882",
      "tgn:1000001",
      "tgn:7029392"
    ],
    "placetype": [
      "aat:300008795"
    ],
    "id": 1105882,
    "name:xx": "Ogden, Mount"
  }
}
