{
  "geometry": {
    "type": "Point",
    "coordinates": [
      140.0833,
      -37.6833
    ]
  },
  "type": "Feature",
  "properties": {
    "hierarchy": [
      "tgn:1096974",
      "tgn:7000490",
      "tgn:1000006",
      "tgn:7001831",
      "tgn:7029392"
    ],
    "placetype": [
      "aat:300008347"
    ],
    "id": 1096974,
    "name:xx": "Glencoe"
  }
}
