{
  "geometry": {
    "type": "Point",
    "coordinates": [
      -54.1667,
      -29.5833
    ]
  },
  "type": "Feature",
  "properties": {
    "hierarchy": [
      "tgn:1022883",
      "tgn:1001941",
      "tgn:1000047",
      "tgn:7002458",
      "tgn:1000002",
      "tgn:7029392"
    ],
    "placetype": [
      "aat:300008347"
    ],
    "id": 1022883,
    "name:xx": "São Pedro do Sul"
  }
}
