{
  "geometry": {
    "type": "Point",
    "coordinates": [
      -108.7333,
      33.4833
    ]
  },
  "type": "Feature",
  "properties": {
    "hierarchy": [
      "tgn:2471581",
      "tgn:1000001",
      "tgn:2001429",
      "tgn:7012149",
      "tgn:7007566",
      "tgn:7029392"
    ],
    "placetype": [
      "aat:300006191"
    ],
    "id": 2471581,
    "name:xx": "Lost Lake Tank"
  }
}
