{
  "geometry": {
    "type": "Point",
    "coordinates": [
      -115.35,
      45.9167
    ]
  },
  "type": "Feature",
  "properties": {
    "hierarchy": [
      "tgn:2306679",
      "tgn:1000001",
      "tgn:7012149",
      "tgn:2000476",
      "tgn:7007250",
      "tgn:7029392"
    ],
    "placetype": [
      "aat:300008706"
    ],
    "id": 2306679,
    "name:xx": "East Fork Fivemile Creek"
  }
}
