{
  "geometry": {
    "type": "Point",
    "coordinates": [
      -78.8833,
      37.3667
    ]
  },
  "type": "Feature",
  "properties": {
    "hierarchy": [
      "tgn:2485493",
      "tgn:2002141",
      "tgn:1000001",
      "tgn:7012149",
      "tgn:7007919",
      "tgn:7029392"
    ],
    "placetype": [
      "aat:300006191"
    ],
    "id": 2485493,
    "name:xx": "Lawsons Pond"
  }
}
