{
  "geometry": {
    "type": "Point",
    "coordinates": [
      -77.5167,
      40.8333
    ]
  },
  "type": "Feature",
  "properties": {
    "hierarchy": [
      "tgn:2786890",
      "tgn:1000001",
      "tgn:1002249",
      "tgn:7012149",
      "tgn:7007710",
      "tgn:7029392"
    ],
    "placetype": [
      "aat:300008347"
    ],
    "id": 2786890,
    "name:xx": "Zerby"
  }
}
