{
  "geometry": {
    "type": "Point",
    "coordinates": [
      -74.7833,
      39.1333
    ]
  },
  "type": "Feature",
  "properties": {
    "hierarchy": [
      "tgn:2670213",
      "tgn:1002232",
      "tgn:1000001",
      "tgn:7012149",
      "tgn:7007565",
      "tgn:7029392"
    ],
    "placetype": [
      "aat:300008706"
    ],
    "id": 2670213,
    "name:xx": "Sluice Creek"
  }
}
