{
  "geometry": {
    "type": "Point",
    "coordinates": [
      1.8167,
      48.95
    ]
  },
  "type": "Feature",
  "properties": {
    "hierarchy": [
      "tgn:7008059",
      "tgn:1000003",
      "tgn:7002883",
      "tgn:1000070",
      "tgn:7029392"
    ],
    "placetype": [
      "aat:300008347"
    ],
    "id": 7008059,
    "name:xx": "Épône"
  }
}
