{
  "geometry": {
    "type": "Point",
    "coordinates": [
      -106.3667,
      33.8167
    ]
  },
  "type": "Feature",
  "properties": {
    "hierarchy": [
      "tgn:2507284",
      "tgn:1000001",
      "tgn:7012149",
      "tgn:2001456",
      "tgn:7007566",
      "tgn:7029392"
    ],
    "placetype": [
      "aat:300000390"
    ],
    "id": 2507284,
    "name:xx": "Mex Tex Mine"
  }
}
