{
  "geometry": {
    "type": "Point",
    "coordinates": [
      -76.0833,
      39.1167
    ]
  },
  "type": "Feature",
  "properties": {
    "hierarchy": [
      "tgn:2602825",
      "tgn:1000001",
      "tgn:1002539",
      "tgn:7012149",
      "tgn:7007516",
      "tgn:7029392"
    ],
    "placetype": [
      "aat:300008347"
    ],
    "id": 2602825,
    "name:xx": "Quaker Neck Landing"
  }
}
