{
  "geometry": {
    "type": "Point",
    "coordinates": [
      -152.2333,
      61.8167
    ]
  },
  "type": "Feature",
  "properties": {
    "hierarchy": [
      "tgn:2382042",
      "tgn:7006450",
      "tgn:1000001",
      "tgn:2124053",
      "tgn:7012149",
      "tgn:7029392"
    ],
    "placetype": [
      "aat:300008707"
    ],
    "id": 2382042,
    "name:xx": "Hayes River"
  }
}
