{
  "geometry": {
    "type": "Point",
    "coordinates": [
      121.5368,
      24.9845
    ]
  },
  "type": "Feature",
  "properties": {
    "hierarchy": [
      "tgn:7468185",
      "tgn:1000004",
      "tgn:1000959",
      "tgn:1000141",
      "tgn:7029392"
    ],
    "placetype": [
      "aat:300387173"
    ],
    "id": 7468185,
    "name:xx": "Jiangling Li"
  }
}
