{
  "geometry": {
    "type": "Point",
    "coordinates": [
      -107.5167,
      34.5833
    ]
  },
  "type": "Feature",
  "properties": {
    "hierarchy": [
      "tgn:2715325",
      "tgn:1000001",
      "tgn:7012149",
      "tgn:7007566",
      "tgn:7029392"
    ],
    "placetype": [
      "aat:300008761"
    ],
    "id": 2715325,
    "name:xx": "Ternera, Cañon de la"
  }
}
