{
  "geometry": {
    "type": "Point",
    "coordinates": [
      30.815629,
      28.480603
    ]
  },
  "type": "Feature",
  "properties": {
    "hierarchy": [
      "tgn:7537825",
      "tgn:7001242",
      "tgn:7016833",
      "tgn:1001088",
      "tgn:7029392"
    ],
    "placetype": [
      "aat:300008347"
    ],
    "name:en": "Nazlat ad Dalīl",
    "id": 7537825
  }
}
