{
  "geometry": {
    "type": "Point",
    "coordinates": [
      -89.7667,
      34.0167
    ]
  },
  "type": "Feature",
  "properties": {
    "hierarchy": [
      "tgn:2721518",
      "tgn:1000001",
      "tgn:7012149",
      "tgn:7007522",
      "tgn:7029392"
    ],
    "placetype": [
      "aat:300008706"
    ],
    "id": 2721518,
    "name:xx": "Tillatoba Creek"
  }
}
