{
  "geometry": {
    "type": "Point",
    "coordinates": [
      11.35,
      49.85
    ]
  },
  "type": "Feature",
  "properties": {
    "hierarchy": [
      "tgn:1041619",
      "tgn:7003669",
      "tgn:1000003",
      "tgn:7000084",
      "tgn:7029392"
    ],
    "placetype": [
      "aat:300008347"
    ],
    "id": 1041619,
    "name:xx": "Waischenfeld"
  }
}
