{
  "geometry": {
    "type": "Point",
    "coordinates": [
      -1.7167,
      53.3333
    ]
  },
  "type": "Feature",
  "properties": {
    "hierarchy": [
      "tgn:7025133",
      "tgn:7002445",
      "tgn:1000003",
      "tgn:7008118",
      "tgn:7008591",
      "tgn:7029392"
    ],
    "placetype": [
      "aat:300008347"
    ],
    "id": 7025133,
    "name:ang": "Estune"
  }
}
