{
  "geometry": {
    "type": "Point",
    "coordinates": [
      120.7521,
      23.9317
    ]
  },
  "type": "Feature",
  "properties": {
    "hierarchy": [
      "tgn:7490146",
      "tgn:7488858",
      "tgn:1000004",
      "tgn:1000141",
      "tgn:7029392"
    ],
    "placetype": [
      "aat:300008347"
    ],
    "id": 7490146,
    "name:xx": "Daqiuyuan"
  }
}
