{
  "type": "FeatureCollection",
  "features": [
    {
      "geometry": {
        "type": "Point",
        "coordinates": [
          -87.7167,
          34.6833
        ]
      },
      "type": "Feature",
      "properties": {
        "hierarchy": [
          "tgn:2424290",
          "tgn:7002659",
          "tgn:1000001",
          "tgn:2000016",
          "tgn:7012149",
          "tgn:7029392"
        ],
        "placetype": [
          "aat:300008699"
        ],
        "id": 2424290,
        "name:xx": "Johnson Branch"
      }
    },
    {
      "geometry": {
        "type": "Point",
        "coordinates": [
          -86.8,
          33.2333
        ]
      },
      "type": "Feature",
      "properties": {
        "hierarchy": [
          "tgn:2424291",
          "tgn:7002659",
          "tgn:1000001",
          "tgn:7012149",
          "tgn:2000058",
          "tgn:7029392"
        ],
        "placetype": [
          "aat:300008699"
        ],
        "id": 2424291,
        "name:xx": "Johnson Branch"
      }
    },
    {
      "geometry": {
        "type": "Point",
        "coordinates": [
          -86.8333,
          34.8333
        ]
      },
      "type": "Feature",
      "properties": {
        "hierarchy": [
          "tgn:2424292",
          "tgn:7002659",
          "tgn:1000001",
          "tgn:7012149",
          "tgn:2000041",
          "tgn:7029392"
        ],
        "placetype": [
          "aat:300008699"
        ],
        "id": 2424292,
        "name:xx": "Johnson Branch"
      }
    },
    {
      "geometry": {
        "type": "Point",
        "coordinates": [
          -88.1333,
          34.6667
        ]
      },
      "type": "Feature",
      "properties": {
        "hierarchy": [
          "tgn:2424293",
          "tgn:1000001",
          "tgn:7012149",
          "tgn:7029392"
        ],
        "placetype": [
          "aat:300008699"
        ],
        "id": 2424293,
        "name:xx": "Johnson Branch"
      }
    },
    {
      "geometry": {
        "type": "Point",
        "coordinates": [
          -91.5,
          35.9667
        ]
      },
      "type": "Feature",
      "properties": {
        "hierarchy": [
          "tgn:2424294",
          "tgn:1000001",
          "tgn:7016172",
          "tgn:7012149",
          "tgn:2000172",
          "tgn:7029392"
        ],
        "placetype": [
          "aat:300008699"
        ],
        "id": 2424294,
        "name:xx": "Johnson Branch"
      }
    },
    {
      "geometry": {
        "type": "Point",
        "coordinates": [
          -93.6167,
          34.1167
        ]
      },
      "type": "Feature",
      "properties": {
        "hierarchy": [
          "tgn:2424295",
          "tgn:1000001",
          "tgn:7016172",
          "tgn:7012149",
          "tgn:2000159",
          "tgn:7029392"
        ],
        "placetype": [
          "aat:300008699"
        ],
        "id": 2424295,
        "name:xx": "Johnson Branch"
      }
    },
    {
      "geometry": {
        "type": "Point",
        "coordinates": [
          -91.6333,
          34.8167
        ]
      },
      "type": "Feature",
      "properties": {
        "hierarchy": [
          "tgn:2424296",
          "tgn:1000001",
          "tgn:7016172",
          "tgn:7012149",
          "tgn:2000163",
          "tgn:7029392"
        ],
        "placetype": [
          "aat:300008699"
        ],
        "id": 2424296,
        "name:xx": "Johnson Branch"
      }
    },
    {
      "geometry": {
        "type": "Point",
        "coordinates": [
          -75.1,
          38.7167
        ]
      },
      "type": "Feature",
      "properties": {
        "hierarchy": [
          "tgn:2424297",
          "tgn:1002933",
          "tgn:1000001",
          "tgn:7012149",
          "tgn:7007239",
          "tgn:7029392"
        ],
        "placetype": [
          "aat:300008699"
        ],
        "id": 2424297,
        "name:xx": "Johnson Branch"
      }
    },
    {
      "geometry": {
        "type": "Point",
        "coordinates": [
          -84.9667,
          30.35
        ]
      },
      "type": "Feature",
      "properties": {
        "hierarchy": [
          "tgn:2424298",
          "tgn:1000001",
          "tgn:7012149",
          "tgn:2000278",
          "tgn:7007240",
          "tgn:7029392"
        ],
        "placetype": [
          "aat:300008699"
        ],
        "id": 2424298,
        "name:xx": "Johnson Branch"
      }
    },
    {
      "geometry": {
        "type": "Point",
        "coordinates": [
          -83.8667,
          31.7167
        ]
      },
      "type": "Feature",
      "properties": {
        "hierarchy": [
          "tgn:2424299",
          "tgn:1000001",
          "tgn:7012149",
          "tgn:2000450",
          "tgn:7007248",
          "tgn:7029392"
        ],
        "placetype": [
          "aat:300008699"
        ],
        "id": 2424299,
        "name:xx": "Johnson Branch"
      }
    }
  ]
}
