{
  "geometry": {
    "type": "Point",
    "coordinates": [
      -86.1833,
      41.2167
    ]
  },
  "type": "Feature",
  "properties": {
    "hierarchy": [
      "tgn:2578224",
      "tgn:1000001",
      "tgn:7012149",
      "tgn:1002640",
      "tgn:7007252",
      "tgn:7029392"
    ],
    "placetype": [
      "aat:300006075"
    ],
    "id": 2578224,
    "name:xx": "Pfiefer Ditch"
  }
}
