{
  "geometry": {
    "type": "Point",
    "coordinates": [
      -3.9167,
      47.8833
    ]
  },
  "type": "Feature",
  "properties": {
    "hierarchy": [
      "tgn:7009051",
      "tgn:1000003",
      "tgn:7012216",
      "tgn:1000070",
      "tgn:7029392"
    ],
    "placetype": [
      "aat:300008347"
    ],
    "id": 7009051,
    "name:xx": "Concarneau"
  }
}
