{
  "type": "FeatureCollection",
  "features": [
    {
      "geometry": {
        "type": "Point",
        "coordinates": [
          -121.4667,
          47.4167
        ]
      },
      "type": "Feature",
      "properties": {
        "hierarchy": [
          "tgn:2359100",
          "tgn:1000001",
          "tgn:7012149",
          "tgn:7018871",
          "tgn:7007920",
          "tgn:7029392"
        ],
        "placetype": [
          "aat:300008680"
        ],
        "id": 2359100,
        "name:xx": "Granite Mountain Lakes"
      }
    },
    {
      "geometry": {
        "type": "Point",
        "coordinates": [
          -112.5167,
          46.0167
        ]
      },
      "type": "Feature",
      "properties": {
        "hierarchy": [
          "tgn:2359101",
          "tgn:1000001",
          "tgn:7012149",
          "tgn:2001306",
          "tgn:7007524",
          "tgn:7029392"
        ],
        "placetype": [
          "aat:300000390"
        ],
        "id": 2359101,
        "name:xx": "Granite Mountain Mine"
      }
    },
    {
      "geometry": {
        "type": "Point",
        "coordinates": [
          -113.2333,
          46.3
        ]
      },
      "type": "Feature",
      "properties": {
        "hierarchy": [
          "tgn:2359102",
          "tgn:1000001",
          "tgn:7012149",
          "tgn:2001279",
          "tgn:7007524",
          "tgn:7029392"
        ],
        "placetype": [
          "aat:300000390"
        ],
        "id": 2359102,
        "name:xx": "Granite Mountain Mine"
      }
    },
    {
      "geometry": {
        "type": "Point",
        "coordinates": [
          -121.1,
          47.5833
        ]
      },
      "type": "Feature",
      "properties": {
        "hierarchy": [
          "tgn:2359104",
          "tgn:1000001",
          "tgn:1002260",
          "tgn:7012149",
          "tgn:7007920",
          "tgn:7029392"
        ],
        "placetype": [
          "aat:300008680"
        ],
        "id": 2359104,
        "name:xx": "Granite Mountain Potholes"
      }
    },
    {
      "geometry": {
        "type": "Point",
        "coordinates": [
          -112.5833,
          34.6333
        ]
      },
      "type": "Feature",
      "properties": {
        "hierarchy": [
          "tgn:2359106",
          "tgn:1000001",
          "tgn:7006451",
          "tgn:7012149",
          "tgn:2000103",
          "tgn:7029392"
        ],
        "placetype": [
          "aat:300008697"
        ],
        "id": 2359106,
        "name:xx": "Granite Mountain Spring"
      }
    },
    {
      "geometry": {
        "type": "Point",
        "coordinates": [
          -111.9167,
          34.2667
        ]
      },
      "type": "Feature",
      "properties": {
        "hierarchy": [
          "tgn:2359107",
          "tgn:1000001",
          "tgn:7006451",
          "tgn:7012149",
          "tgn:2000103",
          "tgn:7029392"
        ],
        "placetype": [
          "aat:300006191"
        ],
        "id": 2359107,
        "name:xx": "Granite Mountain Tank"
      }
    },
    {
      "geometry": {
        "type": "Point",
        "coordinates": [
          -111.9,
          34.25
        ]
      },
      "type": "Feature",
      "properties": {
        "hierarchy": [
          "tgn:2359108",
          "tgn:1000001",
          "tgn:7006451",
          "tgn:7012149",
          "tgn:2000103",
          "tgn:7029392"
        ],
        "placetype": [
          "aat:300006191"
        ],
        "id": 2359108,
        "name:xx": "Granite Mountain Tank Number Two"
      }
    },
    {
      "geometry": {
        "type": "Point",
        "coordinates": [
          -113.3,
          32.4
        ]
      },
      "type": "Feature",
      "properties": {
        "hierarchy": [
          "tgn:2359109",
          "tgn:1000001",
          "tgn:7006451",
          "tgn:7012149",
          "tgn:2000100",
          "tgn:7029392"
        ],
        "placetype": [
          "aat:300008798"
        ],
        "id": 2359109,
        "name:xx": "Granite Mountains"
      }
    }
  ]
}
