{
  "type": "FeatureCollection",
  "features": [
    {
      "geometry": {
        "type": "Point",
        "coordinates": [
          95.5,
          52.6667
        ]
      },
      "type": "Feature",
      "properties": {
        "hierarchy": [
          "tgn:1060020",
          "tgn:1000004",
          "tgn:7002435",
          "tgn:7014829",
          "tgn:7029392"
        ],
        "placetype": [
          "aat:300008347"
        ],
        "id": 1060020,
        "name:xx": "Systyg-Khem"
      }
    },
    {
      "geometry": {
        "type": "Point",
        "coordinates": [
          34,
          56.5333
        ]
      },
      "type": "Feature",
      "properties": {
        "hierarchy": [
          "tgn:1060021",
          "tgn:1000004",
          "tgn:7012941",
          "tgn:7018214",
          "tgn:7002435",
          "tgn:7029392"
        ],
        "placetype": [
          "aat:300008347"
        ],
        "id": 1060021,
        "name:xx": "Sytkovo"
      }
    },
    {
      "geometry": {
        "type": "Point",
        "coordinates": [
          23.5667,
          48.0333
        ]
      },
      "type": "Feature",
      "properties": {
        "hierarchy": [
          "tgn:1060023",
          "tgn:1000003",
          "tgn:7016798",
          "tgn:7006660",
          "tgn:7029392"
        ],
        "placetype": [
          "aat:300008347"
        ],
        "id": 1060023,
        "name:xx": "Tyachiv"
      }
    },
    {
      "geometry": {
        "type": "Point",
        "coordinates": [
          88.5,
          56.1833
        ]
      },
      "type": "Feature",
      "properties": {
        "hierarchy": [
          "tgn:1060024",
          "tgn:1000004",
          "tgn:6003034",
          "tgn:7018214",
          "tgn:7002435",
          "tgn:7029392"
        ],
        "placetype": [
          "aat:300008347"
        ],
        "id": 1060024,
        "name:xx": "Tyazhinskiy"
      }
    },
    {
      "geometry": {
        "type": "Point",
        "coordinates": [
          33.0667,
          46.7833
        ]
      },
      "type": "Feature",
      "properties": {
        "hierarchy": [
          "tgn:1060025",
          "tgn:7011651",
          "tgn:1000003",
          "tgn:7006660",
          "tgn:7029392"
        ],
        "placetype": [
          "aat:300008347"
        ],
        "id": 1060025,
        "name:xx": "Tyahynka"
      }
    },
    {
      "geometry": {
        "type": "Point",
        "coordinates": [
          85.6333,
          53.9333
        ]
      },
      "type": "Feature",
      "properties": {
        "hierarchy": [
          "tgn:1060026",
          "tgn:7013670",
          "tgn:1000004",
          "tgn:7018214",
          "tgn:7002435",
          "tgn:7029392"
        ],
        "placetype": [
          "aat:300008347"
        ],
        "id": 1060026,
        "name:xx": "Tyagun"
      }
    },
    {
      "geometry": {
        "type": "Point",
        "coordinates": [
          30.45,
          59.7
        ]
      },
      "type": "Feature",
      "properties": {
        "hierarchy": [
          "tgn:1060027",
          "tgn:1000004",
          "tgn:7011572",
          "tgn:7013394",
          "tgn:7018214",
          "tgn:7002435",
          "tgn:7029392"
        ],
        "placetype": [
          "aat:300008347"
        ],
        "id": 1060027,
        "name:xx": "Tyarlevo"
      }
    },
    {
      "geometry": {
        "type": "Point",
        "coordinates": [
          35.0167,
          55.0833
        ]
      },
      "type": "Feature",
      "properties": {
        "hierarchy": [
          "tgn:1060028",
          "tgn:1000004",
          "tgn:7011599",
          "tgn:7018214",
          "tgn:7002435",
          "tgn:7029392"
        ],
        "placetype": [
          "aat:300008347"
        ],
        "id": 1060028,
        "name:xx": "T'omkino"
      }
    },
    {
      "geometry": {
        "type": "Point",
        "coordinates": [
          118.5167,
          53.4
        ]
      },
      "type": "Feature",
      "properties": {
        "hierarchy": [
          "tgn:1060029",
          "tgn:1003351",
          "tgn:1000004",
          "tgn:7018214",
          "tgn:7002435",
          "tgn:7029392"
        ],
        "placetype": [
          "aat:300008347"
        ],
        "id": 1060029,
        "name:xx": "T'omnyj"
      }
    }
  ]
}
