{
  "geometry": {
    "type": "Point",
    "coordinates": [
      -110.7833,
      42.2833
    ]
  },
  "type": "Feature",
  "properties": {
    "hierarchy": [
      "tgn:2433344",
      "tgn:1000001",
      "tgn:7012149",
      "tgn:2002376",
      "tgn:7007923",
      "tgn:7029392"
    ],
    "placetype": [
      "aat:300008706"
    ],
    "id": 2433344,
    "name:xx": "Kelley Creek"
  }
}
