{
  "geometry": {
    "type": "Point",
    "coordinates": [
      -78.0833,
      41.7833
    ]
  },
  "type": "Feature",
  "properties": {
    "hierarchy": [
      "tgn:2729876",
      "tgn:1000001",
      "tgn:7012149",
      "tgn:1002800",
      "tgn:7007710",
      "tgn:7029392"
    ],
    "placetype": [
      "aat:300008699"
    ],
    "id": 2729876,
    "name:xx": "Trout Brook"
  }
}
