{
  "geometry": {
    "type": "Point",
    "coordinates": [
      -107.65,
      39.0167
    ]
  },
  "type": "Feature",
  "properties": {
    "hierarchy": [
      "tgn:2275998",
      "tgn:1000001",
      "tgn:7012149",
      "tgn:2000206",
      "tgn:7007158",
      "tgn:7029392"
    ],
    "placetype": [
      "aat:300008798"
    ],
    "id": 2275998,
    "name:xx": "Darline, Mount"
  }
}
