{
  "geometry": {
    "type": "Point",
    "coordinates": [
      -111.0667,
      31.9667
    ]
  },
  "type": "Feature",
  "properties": {
    "hierarchy": [
      "tgn:2384969",
      "tgn:1000001",
      "tgn:7006451",
      "tgn:7012149",
      "tgn:2000100",
      "tgn:7029392"
    ],
    "placetype": [
      "aat:300008798"
    ],
    "id": 2384969,
    "name:xx": "Helmet Peak"
  }
}
