{
  "geometry": {
    "type": "Point",
    "coordinates": [
      -74.5833,
      40.9667
    ]
  },
  "type": "Feature",
  "properties": {
    "hierarchy": [
      "tgn:1118122",
      "tgn:1000001",
      "tgn:1002695",
      "tgn:7012149",
      "tgn:7007565",
      "tgn:7029392"
    ],
    "placetype": [
      "aat:300008680"
    ],
    "id": 1118122,
    "name:xx": "Shawnee, Lake"
  }
}
