{
  "type": "FeatureCollection",
  "features": [
    {
      "geometry": {
        "type": "Point",
        "coordinates": [
          -98.266667,
          23.133333
        ]
      },
      "type": "Feature",
      "properties": {
        "hierarchy": [
          "tgn:7367460",
          "tgn:1000001",
          "tgn:7005597",
          "tgn:7005560",
          "tgn:7029392"
        ],
        "placetype": [
          "aat:300008347"
        ],
        "id": 7367460,
        "name:xx": "El Sabino"
      }
    },
    {
      "geometry": {
        "type": "Point",
        "coordinates": [
          -97.933333,
          22.916667
        ]
      },
      "type": "Feature",
      "properties": {
        "hierarchy": [
          "tgn:7367461",
          "tgn:1000001",
          "tgn:7005597",
          "tgn:7005560",
          "tgn:7029392"
        ],
        "placetype": [
          "aat:300008347"
        ],
        "id": 7367461,
        "name:xx": "El Sabino"
      }
    },
    {
      "geometry": {
        "type": "Point",
        "coordinates": [
          -98.983333,
          22.1
        ]
      },
      "type": "Feature",
      "properties": {
        "hierarchy": [
          "tgn:7367462",
          "tgn:1000001",
          "tgn:7005594",
          "tgn:7005560",
          "tgn:7029392"
        ],
        "placetype": [
          "aat:300008347"
        ],
        "id": 7367462,
        "name:xx": "El Sabino"
      }
    },
    {
      "geometry": {
        "type": "Point",
        "coordinates": [
          -99.083333,
          21.916667
        ]
      },
      "type": "Feature",
      "properties": {
        "hierarchy": [
          "tgn:7367463",
          "tgn:1000001",
          "tgn:7005594",
          "tgn:7005560",
          "tgn:7029392"
        ],
        "placetype": [
          "aat:300008347"
        ],
        "id": 7367463,
        "name:xx": "El Sabino"
      }
    },
    {
      "geometry": {
        "type": "Point",
        "coordinates": [
          -98.066667,
          21.566667
        ]
      },
      "type": "Feature",
      "properties": {
        "hierarchy": [
          "tgn:7367464",
          "tgn:1000001",
          "tgn:7005599",
          "tgn:7005560",
          "tgn:7029392"
        ],
        "placetype": [
          "aat:300008347"
        ],
        "id": 7367464,
        "name:xx": "El Sabino"
      }
    },
    {
      "geometry": {
        "type": "Point",
        "coordinates": [
          -102.816667,
          20.85
        ]
      },
      "type": "Feature",
      "properties": {
        "hierarchy": [
          "tgn:7367465",
          "tgn:7005586",
          "tgn:1000001",
          "tgn:7005560",
          "tgn:7029392"
        ],
        "placetype": [
          "aat:300008347"
        ],
        "id": 7367465,
        "name:xx": "El Sabino"
      }
    },
    {
      "geometry": {
        "type": "Point",
        "coordinates": [
          -99.383333,
          20.85
        ]
      },
      "type": "Feature",
      "properties": {
        "hierarchy": [
          "tgn:7367466",
          "tgn:7005587",
          "tgn:1000001",
          "tgn:7005560",
          "tgn:7029392"
        ],
        "placetype": [
          "aat:300008347"
        ],
        "id": 7367466,
        "name:xx": "El Sabino"
      }
    },
    {
      "geometry": {
        "type": "Point",
        "coordinates": [
          -104.05,
          20.466667
        ]
      },
      "type": "Feature",
      "properties": {
        "hierarchy": [
          "tgn:7367467",
          "tgn:7005586",
          "tgn:1000001",
          "tgn:7005560",
          "tgn:7029392"
        ],
        "placetype": [
          "aat:300008347"
        ],
        "id": 7367467,
        "name:xx": "El Sabino"
      }
    },
    {
      "geometry": {
        "type": "Point",
        "coordinates": [
          -101.716667,
          20.083333
        ]
      },
      "type": "Feature",
      "properties": {
        "hierarchy": [
          "tgn:7367468",
          "tgn:1000001",
          "tgn:7005590",
          "tgn:7005560",
          "tgn:7029392"
        ],
        "placetype": [
          "aat:300008347"
        ],
        "id": 7367468,
        "name:xx": "El Sabino"
      }
    },
    {
      "geometry": {
        "type": "Point",
        "coordinates": [
          -102.933333,
          20
        ]
      },
      "type": "Feature",
      "properties": {
        "hierarchy": [
          "tgn:7367469",
          "tgn:1000001",
          "tgn:7005590",
          "tgn:7005560",
          "tgn:7029392"
        ],
        "placetype": [
          "aat:300008347"
        ],
        "id": 7367469,
        "name:xx": "El Sabino"
      }
    }
  ]
}
