{
  "geometry": {
    "type": "Point",
    "coordinates": [
      18.1667,
      59.1167
    ]
  },
  "type": "Feature",
  "properties": {
    "hierarchy": [
      "tgn:1062707",
      "tgn:1000003",
      "tgn:7003777",
      "tgn:1000097",
      "tgn:7029392"
    ],
    "placetype": [
      "aat:300008347"
    ],
    "id": 1062707,
    "name:xx": "Österhaninge"
  }
}
