{
  "geometry": {
    "type": "Point",
    "coordinates": [
      -4.65,
      36.55
    ]
  },
  "type": "Feature",
  "properties": {
    "hierarchy": [
      "tgn:7343096",
      "tgn:7002758",
      "tgn:7002830",
      "tgn:1000003",
      "tgn:1000095",
      "tgn:7029392"
    ],
    "placetype": [
      "aat:300266554",
      "aat:300008699"
    ],
    "id": 7343096,
    "name:xx": "Cañadón, Arroyo"
  }
}
