{
  "geometry": {
    "type": "Point",
    "coordinates": [
      -82.2167,
      36.55
    ]
  },
  "type": "Feature",
  "properties": {
    "hierarchy": [
      "tgn:2692848",
      "tgn:1000001",
      "tgn:7012149",
      "tgn:2001918",
      "tgn:7007825",
      "tgn:7029392"
    ],
    "placetype": [
      "aat:300006191"
    ],
    "id": 2692848,
    "name:xx": "Steele Creek Park Lake"
  }
}
