{
  "geometry": {
    "type": "Point",
    "coordinates": [
      30.938229,
      31.511293
    ]
  },
  "type": "Feature",
  "properties": {
    "hierarchy": [
      "tgn:7528094",
      "tgn:7001242",
      "tgn:7016833",
      "tgn:1001335",
      "tgn:7029392"
    ],
    "placetype": [
      "aat:300008791"
    ],
    "name:en": "Sinjār, Jazīrat",
    "id": 7528094
  }
}
