{
  "geometry": {
    "type": "Point",
    "coordinates": [
      -95.3667,
      45.7667
    ]
  },
  "type": "Feature",
  "properties": {
    "hierarchy": [
      "tgn:2491493",
      "tgn:1000001",
      "tgn:2001019",
      "tgn:7012149",
      "tgn:7007521",
      "tgn:7029392"
    ],
    "placetype": [
      "aat:300008680"
    ],
    "id": 2491493,
    "name:xx": "Maple Lake"
  }
}
