{
  "geometry": {
    "type": "Point",
    "coordinates": [
      -82.9833,
      33.8167
    ]
  },
  "type": "Feature",
  "properties": {
    "hierarchy": [
      "tgn:2524351",
      "tgn:1000001",
      "tgn:7012149",
      "tgn:2000400",
      "tgn:7007248",
      "tgn:7029392"
    ],
    "placetype": [
      "aat:300000390"
    ],
    "id": 2524351,
    "name:xx": "Morgan Mine"
  }
}
