{
  "geometry": {
    "type": "Point",
    "coordinates": [
      -80.15,
      40.6333
    ]
  },
  "type": "Feature",
  "properties": {
    "hierarchy": [
      "tgn:2748940",
      "tgn:1002171",
      "tgn:1000001",
      "tgn:7012149",
      "tgn:7007710",
      "tgn:7029392"
    ],
    "placetype": [
      "aat:300008347"
    ],
    "id": 2748940,
    "name:xx": "Wall Rose"
  }
}
