{
  "geometry": {
    "type": "Point",
    "coordinates": [
      -91.25,
      36.1667
    ]
  },
  "type": "Feature",
  "properties": {
    "hierarchy": [
      "tgn:2456770",
      "tgn:1000001",
      "tgn:7016172",
      "tgn:7012149",
      "tgn:2000142",
      "tgn:7029392"
    ],
    "placetype": [
      "aat:300006191"
    ],
    "id": 2456770,
    "name:xx": "Little Joe Lake"
  }
}
