{
  "geometry": {
    "type": "Point",
    "coordinates": [
      -178.0833,
      -14.3167
    ]
  },
  "type": "Feature",
  "properties": {
    "hierarchy": [
      "tgn:1010044",
      "tgn:7006219",
      "tgn:1000006",
      "tgn:7029392"
    ],
    "placetype": [
      "aat:300235114",
      "aat:300386853"
    ],
    "id": 1010044,
    "name:xx": "Horn, Îles De"
  }
}
