{
  "geometry": {
    "type": "Point",
    "coordinates": [
      -88.5667,
      45.65
    ]
  },
  "type": "Feature",
  "properties": {
    "hierarchy": [
      "tgn:2382139",
      "tgn:1000001",
      "tgn:2002323",
      "tgn:7012149",
      "tgn:7007922",
      "tgn:7029392"
    ],
    "placetype": [
      "aat:300008706"
    ],
    "id": 2382139,
    "name:xx": "Haymeadow Creek"
  }
}
