{
  "type": "FeatureCollection",
  "features": [
    {
      "geometry": {
        "type": "Point",
        "coordinates": [
          -69.8833,
          44
        ]
      },
      "type": "Feature",
      "properties": {
        "hierarchy": [
          "tgn:2044490",
          "tgn:1000001",
          "tgn:7012149",
          "tgn:2000929",
          "tgn:7007515",
          "tgn:7029392"
        ],
        "placetype": [
          "aat:300008347"
        ],
        "id": 2044490,
        "name:xx": "Bowdoinham"
      }
    },
    {
      "geometry": {
        "type": "Point",
        "coordinates": [
          -68.9333,
          45.0667
        ]
      },
      "type": "Feature",
      "properties": {
        "hierarchy": [
          "tgn:2044491",
          "tgn:1000001",
          "tgn:7012149",
          "tgn:2000927",
          "tgn:7007515",
          "tgn:7029392"
        ],
        "placetype": [
          "aat:300008347"
        ],
        "id": 2044491,
        "name:xx": "Bradford"
      }
    },
    {
      "geometry": {
        "type": "Point",
        "coordinates": [
          -68.8833,
          45.0667
        ]
      },
      "type": "Feature",
      "properties": {
        "hierarchy": [
          "tgn:2044492",
          "tgn:1000001",
          "tgn:7012149",
          "tgn:2000927",
          "tgn:7007515",
          "tgn:7029392"
        ],
        "placetype": [
          "aat:300008347",
          "aat:300387210"
        ],
        "id": 2044492,
        "name:xx": "Bradford Center"
      }
    },
    {
      "geometry": {
        "type": "Point",
        "coordinates": [
          -68.6167,
          44.9167
        ]
      },
      "type": "Feature",
      "properties": {
        "hierarchy": [
          "tgn:2044493",
          "tgn:1000001",
          "tgn:7012149",
          "tgn:2000927",
          "tgn:7007515",
          "tgn:7029392"
        ],
        "placetype": [
          "aat:300008347"
        ],
        "id": 2044493,
        "name:xx": "Bradley"
      }
    },
    {
      "geometry": {
        "type": "Point",
        "coordinates": [
          -69.9,
          45.6167
        ]
      },
      "type": "Feature",
      "properties": {
        "hierarchy": [
          "tgn:2044495",
          "tgn:1000001",
          "tgn:7012149",
          "tgn:2000930",
          "tgn:7007515",
          "tgn:7029392"
        ],
        "placetype": [
          "aat:300387016"
        ],
        "id": 2044495,
        "name:xx": "Brassua"
      }
    },
    {
      "geometry": {
        "type": "Point",
        "coordinates": [
          -68.75,
          44.7833
        ]
      },
      "type": "Feature",
      "properties": {
        "hierarchy": [
          "tgn:2044496",
          "tgn:1000001",
          "tgn:7012149",
          "tgn:2000927",
          "tgn:7007515",
          "tgn:7029392"
        ],
        "placetype": [
          "aat:300008347"
        ],
        "id": 2044496,
        "name:xx": "Brewer"
      }
    }
  ]
}
