{
  "geometry": {
    "type": "Point",
    "coordinates": [
      -120.8333,
      45.6833
    ]
  },
  "type": "Feature",
  "properties": {
    "hierarchy": [
      "tgn:2764251",
      "tgn:1000001",
      "tgn:7012149",
      "tgn:1002554",
      "tgn:7007920",
      "tgn:7029392"
    ],
    "placetype": [
      "aat:300008680"
    ],
    "id": 2764251,
    "name:xx": "Wheelhouse Pond"
  }
}
