{
  "geometry": {
    "type": "Point",
    "coordinates": [
      -76.9167,
      36.0833
    ]
  },
  "type": "Feature",
  "properties": {
    "hierarchy": [
      "tgn:2574466",
      "tgn:1000001",
      "tgn:2001470",
      "tgn:7012149",
      "tgn:7007709",
      "tgn:7029392"
    ],
    "placetype": [
      "aat:300008905"
    ],
    "id": 2574466,
    "name:xx": "Pell Mell Pocosin"
  }
}
