{
  "type": "FeatureCollection",
  "features": [
    {
      "geometry": {
        "type": "Point",
        "coordinates": [
          -82.15,
          29.25
        ]
      },
      "type": "Feature",
      "properties": {
        "hierarchy": [
          "tgn:2021021",
          "tgn:1000001",
          "tgn:7012149",
          "tgn:1002631",
          "tgn:7007240",
          "tgn:7029392"
        ],
        "placetype": [
          "aat:300008347",
          "aat:300387210"
        ],
        "id": 2021021,
        "name:xx": "Regal Park"
      }
    },
    {
      "geometry": {
        "type": "Point",
        "coordinates": [
          -82.15,
          28.5667
        ]
      },
      "type": "Feature",
      "properties": {
        "hierarchy": [
          "tgn:2021025",
          "tgn:1000001",
          "tgn:1002473",
          "tgn:7012149",
          "tgn:7007240",
          "tgn:7029392"
        ],
        "placetype": [
          "aat:300008347"
        ],
        "id": 2021025,
        "name:xx": "Rerdell"
      }
    },
    {
      "geometry": {
        "type": "Point",
        "coordinates": [
          -82.0833,
          29.6167
        ]
      },
      "type": "Feature",
      "properties": {
        "hierarchy": [
          "tgn:2021026",
          "tgn:2000256",
          "tgn:1000001",
          "tgn:7012149",
          "tgn:7007240",
          "tgn:7029392"
        ],
        "placetype": [
          "aat:300008347",
          "aat:300387210"
        ],
        "id": 2021026,
        "name:xx": "Rex"
      }
    },
    {
      "geometry": {
        "type": "Point",
        "coordinates": [
          -81.65,
          29.7
        ]
      },
      "type": "Feature",
      "properties": {
        "hierarchy": [
          "tgn:2021028",
          "tgn:1000001",
          "tgn:7012149",
          "tgn:2000282",
          "tgn:7007240",
          "tgn:7029392"
        ],
        "placetype": [
          "aat:300008347",
          "aat:300387210"
        ],
        "id": 2021028,
        "name:xx": "Rice Creek"
      }
    },
    {
      "geometry": {
        "type": "Point",
        "coordinates": [
          -82.1,
          28.5
        ]
      },
      "type": "Feature",
      "properties": {
        "hierarchy": [
          "tgn:2021029",
          "tgn:1000001",
          "tgn:1002473",
          "tgn:7012149",
          "tgn:7007240",
          "tgn:7029392"
        ],
        "placetype": [
          "aat:300008347",
          "aat:300387210"
        ],
        "id": 2021029,
        "name:xx": "Richloam"
      }
    }
  ]
}
