{
  "geometry": {
    "type": "Point",
    "coordinates": [
      13.95,
      52.883333
    ]
  },
  "type": "Feature",
  "properties": {
    "hierarchy": [
      "tgn:7137496",
      "tgn:7000096",
      "tgn:1000003",
      "tgn:7000084",
      "tgn:7029392"
    ],
    "placetype": [
      "aat:300004792"
    ],
    "id": 7137496,
    "name:xx": "Försterei Liepe"
  }
}
