{
  "geometry": {
    "type": "Point",
    "coordinates": [
      120.5279,
      24.2444
    ]
  },
  "type": "Feature",
  "properties": {
    "hierarchy": [
      "tgn:7498346",
      "tgn:1000004",
      "tgn:7001009",
      "tgn:1000141",
      "tgn:7029392"
    ],
    "placetype": [
      "aat:300007836"
    ],
    "id": 7498346,
    "name:xx": "Wenhua Daqiao"
  }
}
