{
  "type": "FeatureCollection",
  "features": [
    {
      "geometry": {
        "type": "Point",
        "coordinates": [
          -82.9667,
          35.3833
        ]
      },
      "type": "Feature",
      "properties": {
        "hierarchy": [
          "tgn:2603460",
          "tgn:1000001",
          "tgn:7012149",
          "tgn:2001503",
          "tgn:7007709",
          "tgn:7029392"
        ],
        "placetype": [
          "aat:300008706"
        ],
        "id": 2603460,
        "name:xx": "Queen Creek"
      }
    },
    {
      "geometry": {
        "type": "Point",
        "coordinates": [
          -76.45,
          35.5667
        ]
      },
      "type": "Feature",
      "properties": {
        "hierarchy": [
          "tgn:2603461",
          "tgn:1000001",
          "tgn:7012149",
          "tgn:2001506",
          "tgn:7007709",
          "tgn:7029392"
        ],
        "placetype": [
          "aat:300008706"
        ],
        "id": 2603461,
        "name:xx": "Queen Creek"
      }
    },
    {
      "geometry": {
        "type": "Point",
        "coordinates": [
          -82.65,
          35.3833
        ]
      },
      "type": "Feature",
      "properties": {
        "hierarchy": [
          "tgn:2603462",
          "tgn:1000001",
          "tgn:7012149",
          "tgn:2001504",
          "tgn:7007709",
          "tgn:7029392"
        ],
        "placetype": [
          "aat:300008706"
        ],
        "id": 2603462,
        "name:xx": "Queen Creek"
      }
    },
    {
      "geometry": {
        "type": "Point",
        "coordinates": [
          -122.4167,
          44.3333
        ]
      },
      "type": "Feature",
      "properties": {
        "hierarchy": [
          "tgn:2603463",
          "tgn:1000001",
          "tgn:7012149",
          "tgn:2001717",
          "tgn:7007708",
          "tgn:7029392"
        ],
        "placetype": [
          "aat:300008706"
        ],
        "id": 2603463,
        "name:xx": "Queen Creek"
      }
    },
    {
      "geometry": {
        "type": "Point",
        "coordinates": [
          -79.2167,
          41.6667
        ]
      },
      "type": "Feature",
      "properties": {
        "hierarchy": [
          "tgn:2603464",
          "tgn:1000001",
          "tgn:7012149",
          "tgn:7007710",
          "tgn:7029392"
        ],
        "placetype": [
          "aat:300008706"
        ],
        "id": 2603464,
        "name:xx": "Queen Creek"
      }
    },
    {
      "geometry": {
        "type": "Point",
        "coordinates": [
          -76.7333,
          37.3333
        ]
      },
      "type": "Feature",
      "properties": {
        "hierarchy": [
          "tgn:2603465",
          "tgn:1000001",
          "tgn:7012149",
          "tgn:1003048",
          "tgn:7007919",
          "tgn:7029392"
        ],
        "placetype": [
          "aat:300008706"
        ],
        "id": 2603465,
        "name:xx": "Queen Creek"
      }
    },
    {
      "geometry": {
        "type": "Point",
        "coordinates": [
          -117.15,
          48.8167
        ]
      },
      "type": "Feature",
      "properties": {
        "hierarchy": [
          "tgn:2603466",
          "tgn:1000001",
          "tgn:7012149",
          "tgn:2002248",
          "tgn:7007920",
          "tgn:7029392"
        ],
        "placetype": [
          "aat:300008706"
        ],
        "id": 2603466,
        "name:xx": "Queen Creek"
      }
    },
    {
      "geometry": {
        "type": "Point",
        "coordinates": [
          -120.8,
          48.95
        ]
      },
      "type": "Feature",
      "properties": {
        "hierarchy": [
          "tgn:2603467",
          "tgn:1000001",
          "tgn:7012149",
          "tgn:1002742",
          "tgn:7007920",
          "tgn:7029392"
        ],
        "placetype": [
          "aat:300008706"
        ],
        "id": 2603467,
        "name:xx": "Queen Creek"
      }
    },
    {
      "geometry": {
        "type": "Point",
        "coordinates": [
          -111.6667,
          33.25
        ]
      },
      "type": "Feature",
      "properties": {
        "hierarchy": [
          "tgn:2603468",
          "tgn:1000001",
          "tgn:7006451",
          "tgn:7012149",
          "tgn:2000097",
          "tgn:7029392"
        ],
        "placetype": [
          "aat:300006075"
        ],
        "id": 2603468,
        "name:xx": "Queen Creek Canal"
      }
    },
    {
      "geometry": {
        "type": "Point",
        "coordinates": [
          -111.0667,
          33.35
        ]
      },
      "type": "Feature",
      "properties": {
        "hierarchy": [
          "tgn:2603469",
          "tgn:1000001",
          "tgn:7006451",
          "tgn:7012149",
          "tgn:2000101",
          "tgn:7029392"
        ],
        "placetype": [
          "aat:300008761"
        ],
        "id": 2603469,
        "name:xx": "Queen Creek Canyon"
      }
    }
  ]
}
