{
  "geometry": {
    "type": "Point",
    "coordinates": [
      -98.35,
      33.2667
    ]
  },
  "type": "Feature",
  "properties": {
    "hierarchy": [
      "tgn:2477169",
      "tgn:1000001",
      "tgn:7012149",
      "tgn:2002008",
      "tgn:7007826",
      "tgn:7029392"
    ],
    "placetype": [
      "aat:300008706"
    ],
    "id": 2477169,
    "name:xx": "Lynn Creek"
  }
}
