{
  "type": "FeatureCollection",
  "features": [
    {
      "geometry": {
        "type": "Point",
        "coordinates": [
          19.9,
          45.1333
        ]
      },
      "type": "Feature",
      "properties": {
        "hierarchy": [
          "tgn:4004582",
          "tgn:1000003",
          "tgn:4011927",
          "tgn:7006669",
          "tgn:7029392"
        ],
        "placetype": [
          "aat:300008347"
        ],
        "id": 4004582,
        "name:xx": "Grgeteg"
      }
    },
    {
      "geometry": {
        "type": "Point",
        "coordinates": [
          11.333333,
          46.516667
        ]
      },
      "type": "Feature",
      "properties": {
        "hierarchy": [
          "tgn:4004583",
          "tgn:7003158",
          "tgn:1000003",
          "tgn:7003124",
          "tgn:1000080",
          "tgn:7029392"
        ],
        "placetype": [
          "aat:300008347"
        ],
        "id": 4004583,
        "name:xx": "Gries"
      }
    },
    {
      "geometry": {
        "type": "Point",
        "coordinates": [
          0.55,
          52.766667
        ]
      },
      "type": "Feature",
      "properties": {
        "hierarchy": [
          "tgn:4004589",
          "tgn:7002445",
          "tgn:1000003",
          "tgn:7008160",
          "tgn:7008591",
          "tgn:7029392"
        ],
        "placetype": [
          "aat:300008347",
          "aat:300008372"
        ],
        "id": 4004589,
        "name:xx": "Grimston"
      }
    }
  ]
}
