{
  "geometry": {
    "type": "Point",
    "coordinates": [
      -71.35,
      42.5167
    ]
  },
  "type": "Feature",
  "properties": {
    "hierarchy": [
      "tgn:1135395",
      "tgn:1000001",
      "tgn:1002665",
      "tgn:7012149",
      "tgn:7007517",
      "tgn:7029392"
    ],
    "placetype": [
      "aat:300008703"
    ],
    "id": 1135395,
    "name:xx": "Spencer Brook"
  }
}
