{
  "geometry": {
    "type": "Point",
    "coordinates": [
      -92.85,
      45.7167
    ]
  },
  "type": "Feature",
  "properties": {
    "hierarchy": [
      "tgn:2163454",
      "tgn:1000001",
      "tgn:2002311",
      "tgn:7012149",
      "tgn:7007922",
      "tgn:7029392"
    ],
    "placetype": [
      "aat:300008347"
    ],
    "id": 2163454,
    "name:xx": "Benson"
  }
}
