{
  "geometry": {
    "type": "Point",
    "coordinates": [
      -72.55,
      -53.55
    ]
  },
  "type": "Feature",
  "properties": {
    "hierarchy": [
      "tgn:7280067",
      "tgn:1001702",
      "tgn:1000049",
      "tgn:1000002",
      "tgn:7029392"
    ],
    "placetype": [
      "aat:300386846"
    ],
    "id": 7280067,
    "name:xx": "Quod, Cabo"
  }
}
