{
  "geometry": {
    "type": "Point",
    "coordinates": [
      -117.5167,
      44.9333
    ]
  },
  "type": "Feature",
  "properties": {
    "hierarchy": [
      "tgn:2255760",
      "tgn:7013349",
      "tgn:1000001",
      "tgn:7012149",
      "tgn:7007708",
      "tgn:7029392"
    ],
    "placetype": [
      "aat:300008798"
    ],
    "id": 2255760,
    "name:xx": "Copper Buttes"
  }
}
