{
  "geometry": {
    "type": "Point",
    "coordinates": [
      -81.8667,
      40.2833
    ]
  },
  "type": "Feature",
  "properties": {
    "hierarchy": [
      "tgn:2628845",
      "tgn:1000001",
      "tgn:1002304",
      "tgn:7012149",
      "tgn:7007706",
      "tgn:7029392"
    ],
    "placetype": [
      "aat:300386845"
    ],
    "id": 2628845,
    "name:xx": "Roscoe Basin"
  }
}
