{
  "geometry": {
    "type": "Point",
    "coordinates": [
      37.4167,
      11.3333
    ]
  },
  "type": "Feature",
  "properties": {
    "hierarchy": [
      "tgn:1089771",
      "tgn:7001242",
      "tgn:1001266",
      "tgn:7000489",
      "tgn:7029392"
    ],
    "placetype": [
      "aat:300008347"
    ],
    "id": 1089771,
    "name:xx": "Debre May"
  }
}
