{
  "geometry": {
    "type": "Point",
    "coordinates": [
      -122.9833,
      48.5833
    ]
  },
  "type": "Feature",
  "properties": {
    "hierarchy": [
      "tgn:2265431",
      "tgn:1000001",
      "tgn:7012149",
      "tgn:1002862",
      "tgn:7007920",
      "tgn:7029392"
    ],
    "placetype": [
      "aat:300008791"
    ],
    "id": 2265431,
    "name:xx": "Crane Island"
  }
}
