{
  "geometry": {
    "type": "Point",
    "coordinates": [
      -56.3667,
      -34.6167
    ]
  },
  "type": "Feature",
  "properties": {
    "hierarchy": [
      "tgn:1024924",
      "tgn:1000550",
      "tgn:1000002",
      "tgn:1000058",
      "tgn:7029392"
    ],
    "placetype": [
      "aat:300008347"
    ],
    "id": 1024924,
    "name:xx": "Los Cerrillos"
  }
}
