{
  "geometry": {
    "type": "Point",
    "coordinates": [
      124.4833,
      8.6167
    ]
  },
  "type": "Feature",
  "properties": {
    "hierarchy": [
      "tgn:1012532",
      "tgn:1000004",
      "tgn:1001433",
      "tgn:1000135",
      "tgn:7029392"
    ],
    "placetype": [
      "aat:300386846"
    ],
    "id": 1012532,
    "name:xx": "Sulauan Point"
  }
}
