{
  "geometry": {
    "type": "Point",
    "coordinates": [
      -108.8833,
      35.2833
    ]
  },
  "type": "Feature",
  "properties": {
    "hierarchy": [
      "tgn:2453075",
      "tgn:1000001",
      "tgn:7012149",
      "tgn:7019676",
      "tgn:7007566",
      "tgn:7029392"
    ],
    "placetype": [
      "aat:300008761"
    ],
    "id": 2453075,
    "name:xx": "Little Canyon"
  }
}
