{
  "geometry": {
    "type": "Point",
    "coordinates": [
      -1.3167,
      49.3333
    ]
  },
  "type": "Feature",
  "properties": {
    "hierarchy": [
      "tgn:1012750",
      "tgn:7002872",
      "tgn:1000003",
      "tgn:1000070",
      "tgn:7029392"
    ],
    "placetype": [
      "aat:300008804"
    ],
    "id": 1012750,
    "name:xx": "Cotentin"
  }
}
