{
  "geometry": {
    "type": "Point",
    "coordinates": [
      -75.2333,
      42.6333
    ]
  },
  "type": "Feature",
  "properties": {
    "hierarchy": [
      "tgn:2221307",
      "tgn:1000001",
      "tgn:7012149",
      "tgn:7014318",
      "tgn:7007568",
      "tgn:7029392"
    ],
    "placetype": [
      "aat:300008347"
    ],
    "id": 2221307,
    "name:xx": "Cardtown"
  }
}
