{
  "type": "FeatureCollection",
  "features": [
    {
      "geometry": {
        "type": "Point",
        "coordinates": [
          5.966667,
          50.516667
        ]
      },
      "type": "Feature",
      "properties": {
        "hierarchy": [
          "tgn:7253780",
          "tgn:7003460",
          "tgn:1000003",
          "tgn:1000063",
          "tgn:4012014",
          "tgn:7029392"
        ],
        "placetype": [
          "aat:300008347"
        ],
        "id": 7253780,
        "name:xx": "Solwaster"
      }
    },
    {
      "geometry": {
        "type": "Point",
        "coordinates": [
          5.65,
          51.1
        ]
      },
      "type": "Feature",
      "properties": {
        "hierarchy": [
          "tgn:7253781",
          "tgn:7003461",
          "tgn:1000003",
          "tgn:1000063",
          "tgn:7018236",
          "tgn:7029392"
        ],
        "placetype": [
          "aat:300008863"
        ],
        "id": 7253781,
        "name:xx": "Solter Heide"
      }
    },
    {
      "geometry": {
        "type": "Point",
        "coordinates": [
          4.233333,
          50.2
        ]
      },
      "type": "Feature",
      "properties": {
        "hierarchy": [
          "tgn:7253784",
          "tgn:7007877",
          "tgn:1000003",
          "tgn:1000063",
          "tgn:4012014",
          "tgn:7029392"
        ],
        "placetype": [
          "aat:300008347"
        ],
        "id": 7253784,
        "name:xx": "Solre-Saint-Géry"
      }
    },
    {
      "geometry": {
        "type": "Point",
        "coordinates": [
          4.133333,
          50.266667
        ]
      },
      "type": "Feature",
      "properties": {
        "hierarchy": [
          "tgn:7253786",
          "tgn:7007877",
          "tgn:1000003",
          "tgn:1000063",
          "tgn:4012014",
          "tgn:7029392"
        ],
        "placetype": [
          "aat:300008863"
        ],
        "id": 7253786,
        "name:xx": "Solre, Bois de"
      }
    },
    {
      "geometry": {
        "type": "Point",
        "coordinates": [
          5.583333,
          50.366667
        ]
      },
      "type": "Feature",
      "properties": {
        "hierarchy": [
          "tgn:7253787",
          "tgn:7003465",
          "tgn:1000003",
          "tgn:1000063",
          "tgn:4012014",
          "tgn:7029392"
        ],
        "placetype": [
          "aat:300008347"
        ],
        "id": 7253787,
        "name:xx": "Sol Prangeleux"
      }
    },
    {
      "geometry": {
        "type": "Point",
        "coordinates": [
          5.166667,
          49.9
        ]
      },
      "type": "Feature",
      "properties": {
        "hierarchy": [
          "tgn:7253788",
          "tgn:7003465",
          "tgn:1000003",
          "tgn:1000063",
          "tgn:4012014",
          "tgn:7029392"
        ],
        "placetype": [
          "aat:300008863"
        ],
        "id": 7253788,
        "name:xx": "Solmon, Bois"
      }
    },
    {
      "geometry": {
        "type": "Point",
        "coordinates": [
          4.284179,
          50.75409
        ]
      },
      "type": "Feature",
      "properties": {
        "hierarchy": [
          "tgn:7253789",
          "tgn:7018239",
          "tgn:1000003",
          "tgn:1000063",
          "tgn:7018236",
          "tgn:7029392"
        ],
        "placetype": [
          "aat:300008347"
        ],
        "id": 7253789,
        "name:xx": "Sollemberg"
      }
    }
  ]
}
