{
  "geometry": {
    "type": "Point",
    "coordinates": [
      -81.7667,
      39.2833
    ]
  },
  "type": "Feature",
  "properties": {
    "hierarchy": [
      "tgn:2360252",
      "tgn:1000001",
      "tgn:7012149",
      "tgn:2001622",
      "tgn:7007706",
      "tgn:7029392"
    ],
    "placetype": [
      "aat:300008699"
    ],
    "id": 2360252,
    "name:xx": "Grass Run"
  }
}
