{
  "geometry": {
    "type": "Point",
    "coordinates": [
      -88.3167,
      43.95
    ]
  },
  "type": "Feature",
  "properties": {
    "hierarchy": [
      "tgn:2197119",
      "tgn:1000001",
      "tgn:2002312",
      "tgn:7012149",
      "tgn:7007922",
      "tgn:7029392"
    ],
    "placetype": [
      "aat:300132316"
    ],
    "id": 2197119,
    "name:xx": "Brothertown Harbor"
  }
}
