{
  "geometry": {
    "type": "Point",
    "coordinates": [
      73.653513,
      24.057901
    ]
  },
  "type": "Feature",
  "properties": {
    "hierarchy": [
      "tgn:7573701",
      "tgn:1000004",
      "tgn:7000198",
      "tgn:7016788",
      "tgn:7029392"
    ],
    "placetype": [
      "aat:300008347"
    ],
    "name:en": "Kāgdar ki Pāl",
    "id": 7573701
  }
}
