{
  "type": "FeatureCollection",
  "features": [
    {
      "geometry": {
        "type": "Point",
        "coordinates": [
          78.266667,
          9.833333
        ]
      },
      "type": "Feature",
      "properties": {
        "hierarchy": [
          "tgn:7581441",
          "tgn:1000004",
          "tgn:7000198",
          "tgn:7001797",
          "tgn:7029392"
        ],
        "placetype": [
          "aat:300008347"
        ],
        "name:en": "Tiruppuvanam",
        "id": 7581441
      }
    },
    {
      "geometry": {
        "type": "Point",
        "coordinates": [
          79.8,
          10.633333
        ]
      },
      "type": "Feature",
      "properties": {
        "hierarchy": [
          "tgn:7581443",
          "tgn:1000004",
          "tgn:7000198",
          "tgn:7001797",
          "tgn:7029392"
        ],
        "placetype": [
          "aat:300008347"
        ],
        "name:en": "Tiruppūndi",
        "id": 7581443
      }
    },
    {
      "geometry": {
        "type": "Point",
        "coordinates": [
          78.85,
          9.3
        ]
      },
      "type": "Feature",
      "properties": {
        "hierarchy": [
          "tgn:7581444",
          "tgn:1000004",
          "tgn:7000198",
          "tgn:7001797",
          "tgn:7029392"
        ],
        "placetype": [
          "aat:300008347"
        ],
        "name:en": "Tiruppullani",
        "id": 7581444
      }
    },
    {
      "geometry": {
        "type": "Point",
        "coordinates": [
          80.1825,
          12.741389
        ]
      },
      "type": "Feature",
      "properties": {
        "hierarchy": [
          "tgn:7581445",
          "tgn:1000004",
          "tgn:7000198",
          "tgn:7001797",
          "tgn:7029392"
        ],
        "placetype": [
          "aat:300008347"
        ],
        "name:en": "Tirupporūr",
        "id": 7581445
      }
    },
    {
      "geometry": {
        "type": "Point",
        "coordinates": [
          79.333333,
          11
        ]
      },
      "type": "Feature",
      "properties": {
        "hierarchy": [
          "tgn:7581446",
          "tgn:1000004",
          "tgn:7000198",
          "tgn:7001797",
          "tgn:7029392"
        ],
        "placetype": [
          "aat:300008347"
        ],
        "name:en": "Tiruppirambiyam",
        "id": 7581446
      }
    },
    {
      "geometry": {
        "type": "Point",
        "coordinates": [
          78.566667,
          10.883333
        ]
      },
      "type": "Feature",
      "properties": {
        "hierarchy": [
          "tgn:7581447",
          "tgn:1000004",
          "tgn:7000198",
          "tgn:7001797",
          "tgn:7029392"
        ],
        "placetype": [
          "aat:300008347"
        ],
        "name:en": "Tiruppiraitturai",
        "id": 7581447
      }
    }
  ]
}
