{
  "type": "FeatureCollection",
  "features": [
    {
      "geometry": {
        "type": "Point",
        "coordinates": [
          22.1,
          46.3667
        ]
      },
      "type": "Feature",
      "properties": {
        "hierarchy": [
          "tgn:1050271",
          "tgn:1000337",
          "tgn:1000003",
          "tgn:1000091",
          "tgn:7029392"
        ],
        "placetype": [
          "aat:300008347"
        ],
        "id": 1050271,
        "name:xx": "Sebiș"
      }
    },
    {
      "geometry": {
        "type": "Point",
        "coordinates": [
          25.7833,
          45.8667
        ]
      },
      "type": "Feature",
      "properties": {
        "hierarchy": [
          "tgn:1050272",
          "tgn:1000361",
          "tgn:1000003",
          "tgn:1000091",
          "tgn:7029392"
        ],
        "placetype": [
          "aat:300008347",
          "aat:300008416",
          "aat:300008375"
        ],
        "id": 1050272,
        "name:xx": "Sfîntu Gheorghe"
      }
    },
    {
      "geometry": {
        "type": "Point",
        "coordinates": [
          23,
          45.85
        ]
      },
      "type": "Feature",
      "properties": {
        "hierarchy": [
          "tgn:1050276",
          "tgn:1000003",
          "tgn:7004126",
          "tgn:1000091",
          "tgn:7029392"
        ],
        "placetype": [
          "aat:300008347"
        ],
        "id": 1050276,
        "name:xx": "Simeria"
      }
    },
    {
      "geometry": {
        "type": "Point",
        "coordinates": [
          25.55,
          45.3333
        ]
      },
      "type": "Feature",
      "properties": {
        "hierarchy": [
          "tgn:1050277",
          "tgn:1000003",
          "tgn:7002699",
          "tgn:1000091",
          "tgn:7029392"
        ],
        "placetype": [
          "aat:300008347"
        ],
        "id": 1050277,
        "name:xx": "Sinaia"
      }
    },
    {
      "geometry": {
        "type": "Point",
        "coordinates": [
          21.5,
          46.3333
        ]
      },
      "type": "Feature",
      "properties": {
        "hierarchy": [
          "tgn:1050278",
          "tgn:1000337",
          "tgn:1000003",
          "tgn:1000091",
          "tgn:7029392"
        ],
        "placetype": [
          "aat:300008347"
        ],
        "id": 1050278,
        "name:xx": "Sintana"
      }
    },
    {
      "geometry": {
        "type": "Point",
        "coordinates": [
          26.0833,
          47.9167
        ]
      },
      "type": "Feature",
      "properties": {
        "hierarchy": [
          "tgn:1050279",
          "tgn:1000003",
          "tgn:7002700",
          "tgn:1000091",
          "tgn:7029392"
        ],
        "placetype": [
          "aat:300008347"
        ],
        "id": 1050279,
        "name:xx": "Siret"
      }
    }
  ]
}
