{
  "type": "FeatureCollection",
  "features": [
    {
      "geometry": {
        "type": "Point",
        "coordinates": [
          -94,
          36.15
        ]
      },
      "type": "Feature",
      "properties": {
        "hierarchy": [
          "tgn:2182760",
          "tgn:1000001",
          "tgn:7016172",
          "tgn:7012149",
          "tgn:2000176",
          "tgn:7029392"
        ],
        "placetype": [
          "aat:300008697"
        ],
        "id": 2182760,
        "name:xx": "Blue Springs"
      }
    },
    {
      "geometry": {
        "type": "Point",
        "coordinates": [
          -81.8167,
          28.7333
        ]
      },
      "type": "Feature",
      "properties": {
        "hierarchy": [
          "tgn:2182761",
          "tgn:1000001",
          "tgn:7012149",
          "tgn:1002567",
          "tgn:7007240",
          "tgn:7029392"
        ],
        "placetype": [
          "aat:300008697"
        ],
        "id": 2182761,
        "name:xx": "Blue Springs"
      }
    },
    {
      "geometry": {
        "type": "Point",
        "coordinates": [
          -81.3333,
          28.9333
        ]
      },
      "type": "Feature",
      "properties": {
        "hierarchy": [
          "tgn:2182762",
          "tgn:1000001",
          "tgn:7012149",
          "tgn:1002977",
          "tgn:7007240",
          "tgn:7029392"
        ],
        "placetype": [
          "aat:300008697"
        ],
        "id": 2182762,
        "name:xx": "Blue Springs"
      }
    },
    {
      "geometry": {
        "type": "Point",
        "coordinates": [
          -81.85,
          29.5
        ]
      },
      "type": "Feature",
      "properties": {
        "hierarchy": [
          "tgn:2182763",
          "tgn:1000001",
          "tgn:7012149",
          "tgn:1002631",
          "tgn:7007240",
          "tgn:7029392"
        ],
        "placetype": [
          "aat:300008697"
        ],
        "id": 2182763,
        "name:xx": "Blue Springs"
      }
    },
    {
      "geometry": {
        "type": "Point",
        "coordinates": [
          -82.6667,
          29.8167
        ]
      },
      "type": "Feature",
      "properties": {
        "hierarchy": [
          "tgn:2182764",
          "tgn:1000001",
          "tgn:2000269",
          "tgn:7012149",
          "tgn:7007240",
          "tgn:7029392"
        ],
        "placetype": [
          "aat:300008697"
        ],
        "id": 2182764,
        "name:xx": "Blue Springs"
      }
    },
    {
      "geometry": {
        "type": "Point",
        "coordinates": [
          -83.2333,
          30.4667
        ]
      },
      "type": "Feature",
      "properties": {
        "hierarchy": [
          "tgn:2182765",
          "tgn:1000001",
          "tgn:7012149",
          "tgn:2000279",
          "tgn:7007240",
          "tgn:7029392"
        ],
        "placetype": [
          "aat:300008697"
        ],
        "id": 2182765,
        "name:xx": "Blue Springs"
      }
    },
    {
      "geometry": {
        "type": "Point",
        "coordinates": [
          -82.6833,
          29.45
        ]
      },
      "type": "Feature",
      "properties": {
        "hierarchy": [
          "tgn:2182766",
          "tgn:1000001",
          "tgn:7012149",
          "tgn:2000277",
          "tgn:7007240",
          "tgn:7029392"
        ],
        "placetype": [
          "aat:300008697"
        ],
        "id": 2182766,
        "name:xx": "Blue Springs"
      }
    },
    {
      "geometry": {
        "type": "Point",
        "coordinates": [
          -83.45,
          30.7833
        ]
      },
      "type": "Feature",
      "properties": {
        "hierarchy": [
          "tgn:2182767",
          "tgn:1000001",
          "tgn:2000305",
          "tgn:7012149",
          "tgn:7007248",
          "tgn:7029392"
        ],
        "placetype": [
          "aat:300008347"
        ],
        "id": 2182767,
        "name:xx": "Blue Springs"
      }
    },
    {
      "geometry": {
        "type": "Point",
        "coordinates": [
          -83.4667,
          32.1667
        ]
      },
      "type": "Feature",
      "properties": {
        "hierarchy": [
          "tgn:2182768",
          "tgn:1000001",
          "tgn:7012149",
          "tgn:2000407",
          "tgn:7007248",
          "tgn:7029392"
        ],
        "placetype": [
          "aat:300008697"
        ],
        "id": 2182768,
        "name:xx": "Blue Springs"
      }
    },
    {
      "geometry": {
        "type": "Point",
        "coordinates": [
          -82.05,
          32.8
        ]
      },
      "type": "Feature",
      "properties": {
        "hierarchy": [
          "tgn:2182769",
          "tgn:1000001",
          "tgn:7012149",
          "tgn:2000373",
          "tgn:7007248",
          "tgn:7029392"
        ],
        "placetype": [
          "aat:300008697"
        ],
        "id": 2182769,
        "name:xx": "Blue Springs"
      }
    }
  ]
}
