{
  "geometry": {
    "type": "Point",
    "coordinates": [
      -76.8333,
      42.8167
    ]
  },
  "type": "Feature",
  "properties": {
    "hierarchy": [
      "tgn:2663298",
      "tgn:1000001",
      "tgn:7012149",
      "tgn:1002882",
      "tgn:7007568",
      "tgn:7029392"
    ],
    "placetype": [
      "aat:300008706"
    ],
    "id": 2663298,
    "name:xx": "Silver Creek"
  }
}
