{
  "geometry": {
    "type": "Point",
    "coordinates": [
      -114.7667,
      44.55
    ]
  },
  "type": "Feature",
  "properties": {
    "hierarchy": [
      "tgn:2607848",
      "tgn:1000001",
      "tgn:2000470",
      "tgn:7012149",
      "tgn:7007250",
      "tgn:7029392"
    ],
    "placetype": [
      "aat:300008706"
    ],
    "id": 2607848,
    "name:xx": "Rat Creek"
  }
}
