{
  "geometry": {
    "type": "Point",
    "coordinates": [
      31.245694,
      30.076589
    ]
  },
  "type": "Feature",
  "properties": {
    "hierarchy": [
      "tgn:7531925",
      "tgn:7001242",
      "tgn:7016833",
      "tgn:1001091",
      "tgn:7029392"
    ],
    "placetype": [
      "aat:300006676"
    ],
    "id": 7531925,
    "name:xx": "Mustashfá ar Rā'ī aş Şāliḩ"
  }
}
