{
  "geometry": {
    "type": "Point",
    "coordinates": [
      -95.0833,
      43.8667
    ]
  },
  "type": "Feature",
  "properties": {
    "hierarchy": [
      "tgn:2259210",
      "tgn:1000001",
      "tgn:2001015",
      "tgn:7012149",
      "tgn:7007521",
      "tgn:7029392"
    ],
    "placetype": [
      "aat:300008680"
    ],
    "id": 2259210,
    "name:xx": "Cottonwood Lake"
  }
}
