{
  "geometry": {
    "type": "Point",
    "coordinates": [
      -80.8667,
      39.0667
    ]
  },
  "type": "Feature",
  "properties": {
    "hierarchy": [
      "tgn:2487849",
      "tgn:1000001",
      "tgn:7012149",
      "tgn:2002292",
      "tgn:7013961",
      "tgn:7029392"
    ],
    "placetype": [
      "aat:300008706"
    ],
    "id": 2487849,
    "name:xx": "Left Fork Spruce Creek"
  }
}
