{
  "geometry": {
    "type": "Point",
    "coordinates": [
      -60.1167,
      45.85
    ]
  },
  "type": "Feature",
  "properties": {
    "hierarchy": [
      "tgn:1113015",
      "tgn:7013022",
      "tgn:7005685",
      "tgn:1000001",
      "tgn:7005802",
      "tgn:7029392"
    ],
    "placetype": [
      "aat:300132316"
    ],
    "id": 1113015,
    "name:xx": "Gabarus Bay"
  }
}
