{
  "geometry": {
    "type": "Point",
    "coordinates": [
      -95.6667,
      32.8167
    ]
  },
  "type": "Feature",
  "properties": {
    "hierarchy": [
      "tgn:2102900",
      "tgn:1000001",
      "tgn:7012149",
      "tgn:1002816",
      "tgn:7007826",
      "tgn:7029392"
    ],
    "placetype": [
      "aat:300008347",
      "aat:300387210"
    ],
    "id": 2102900,
    "name:xx": "Bright Star"
  }
}
