{
  "geometry": {
    "type": "Point",
    "coordinates": [
      96.6833,
      38.8333
    ]
  },
  "type": "Feature",
  "properties": {
    "hierarchy": [
      "tgn:1068552",
      "tgn:1000004",
      "tgn:7002088",
      "tgn:1000111",
      "tgn:7029392"
    ],
    "placetype": [
      "aat:300008347"
    ],
    "id": 1068552,
    "name:xx": "Haitun"
  }
}
