{
  "type": "FeatureCollection",
  "features": [
    {
      "geometry": {
        "type": "Point",
        "coordinates": [
          -96.3167,
          44.0167
        ]
      },
      "type": "Feature",
      "properties": {
        "hierarchy": [
          "tgn:2411670",
          "tgn:1000001",
          "tgn:7012149",
          "tgn:2001057",
          "tgn:7007521",
          "tgn:7029392"
        ],
        "placetype": [
          "aat:300008680"
        ],
        "id": 2411670,
        "name:xx": "Indian Lake"
      }
    },
    {
      "geometry": {
        "type": "Point",
        "coordinates": [
          -93.7833,
          44.1
        ]
      },
      "type": "Feature",
      "properties": {
        "hierarchy": [
          "tgn:2411671",
          "tgn:1000001",
          "tgn:2001005",
          "tgn:7012149",
          "tgn:7007521",
          "tgn:7029392"
        ],
        "placetype": [
          "aat:300008680"
        ],
        "id": 2411671,
        "name:xx": "Indian Lake"
      }
    },
    {
      "geometry": {
        "type": "Point",
        "coordinates": [
          -94.3167,
          44.5667
        ]
      },
      "type": "Feature",
      "properties": {
        "hierarchy": [
          "tgn:2411672",
          "tgn:1000001",
          "tgn:7012149",
          "tgn:2001070",
          "tgn:7007521",
          "tgn:7029392"
        ],
        "placetype": [
          "aat:300008680"
        ],
        "id": 2411672,
        "name:xx": "Indian Lake"
      }
    },
    {
      "geometry": {
        "type": "Point",
        "coordinates": [
          -94.0167,
          45.3
        ]
      },
      "type": "Feature",
      "properties": {
        "hierarchy": [
          "tgn:2411673",
          "tgn:1000001",
          "tgn:7012149",
          "tgn:2001084",
          "tgn:7007521",
          "tgn:7029392"
        ],
        "placetype": [
          "aat:300008680"
        ],
        "id": 2411673,
        "name:xx": "Indian Lake"
      }
    },
    {
      "geometry": {
        "type": "Point",
        "coordinates": [
          -95.4667,
          46.0167
        ]
      },
      "type": "Feature",
      "properties": {
        "hierarchy": [
          "tgn:2411674",
          "tgn:1000001",
          "tgn:2001019",
          "tgn:7012149",
          "tgn:7007521",
          "tgn:7029392"
        ],
        "placetype": [
          "aat:300008680"
        ],
        "id": 2411674,
        "name:xx": "Indian Lake"
      }
    },
    {
      "geometry": {
        "type": "Point",
        "coordinates": [
          -92.9333,
          46.1833
        ]
      },
      "type": "Feature",
      "properties": {
        "hierarchy": [
          "tgn:2411675",
          "tgn:1000001",
          "tgn:7012149",
          "tgn:2001056",
          "tgn:7007521",
          "tgn:7029392"
        ],
        "placetype": [
          "aat:300008680"
        ],
        "id": 2411675,
        "name:xx": "Indian Lake"
      }
    },
    {
      "geometry": {
        "type": "Point",
        "coordinates": [
          -95.95,
          46.2167
        ]
      },
      "type": "Feature",
      "properties": {
        "hierarchy": [
          "tgn:2411676",
          "tgn:1000001",
          "tgn:7012149",
          "tgn:2001054",
          "tgn:7007521",
          "tgn:7029392"
        ],
        "placetype": [
          "aat:300008680"
        ],
        "id": 2411676,
        "name:xx": "Indian Lake"
      }
    },
    {
      "geometry": {
        "type": "Point",
        "coordinates": [
          -94.7833,
          47
        ]
      },
      "type": "Feature",
      "properties": {
        "hierarchy": [
          "tgn:2411677",
          "tgn:1000001",
          "tgn:7012149",
          "tgn:2001027",
          "tgn:7007521",
          "tgn:7029392"
        ],
        "placetype": [
          "aat:300008680"
        ],
        "id": 2411677,
        "name:xx": "Indian Lake"
      }
    },
    {
      "geometry": {
        "type": "Point",
        "coordinates": [
          -91.85,
          47.2667
        ]
      },
      "type": "Feature",
      "properties": {
        "hierarchy": [
          "tgn:2411678",
          "tgn:1000001",
          "tgn:7012149",
          "tgn:2001067",
          "tgn:7007521",
          "tgn:7029392"
        ],
        "placetype": [
          "aat:300008680"
        ],
        "id": 2411678,
        "name:xx": "Indian Lake"
      }
    },
    {
      "geometry": {
        "type": "Point",
        "coordinates": [
          -95.5,
          43.5
        ]
      },
      "type": "Feature",
      "properties": {
        "hierarchy": [
          "tgn:2411679",
          "tgn:1000001",
          "tgn:7012149",
          "tgn:2001051",
          "tgn:7007521",
          "tgn:7029392"
        ],
        "placetype": [
          "aat:300008680"
        ],
        "id": 2411679,
        "name:xx": "Indian Lake"
      }
    }
  ]
}
