{
  "geometry": {
    "type": "Point",
    "coordinates": [
      124.4167,
      48.0833
    ]
  },
  "type": "Feature",
  "properties": {
    "hierarchy": [
      "tgn:1127952",
      "tgn:1000004",
      "tgn:7001838",
      "tgn:1000111",
      "tgn:7029392"
    ],
    "placetype": [
      "aat:300008707"
    ],
    "id": 1127952,
    "name:xx": "Nuomin He"
  }
}
