{
  "geometry": {
    "type": "Point",
    "coordinates": [
      -90.7667,
      37.1333
    ]
  },
  "type": "Feature",
  "properties": {
    "hierarchy": [
      "tgn:2243462",
      "tgn:1000001",
      "tgn:7012149",
      "tgn:7007523",
      "tgn:7029392"
    ],
    "placetype": [
      "aat:300006191"
    ],
    "id": 2243462,
    "name:xx": "Clearwater Lake"
  }
}
