{
  "type": "FeatureCollection",
  "features": [
    {
      "geometry": {
        "type": "Point",
        "coordinates": [
          -122.4667,
          37.8167
        ]
      },
      "type": "Feature",
      "properties": {
        "hierarchy": [
          "tgn:2449000",
          "tgn:1000001",
          "tgn:7012149",
          "tgn:7007157",
          "tgn:7014005",
          "tgn:7029392"
        ],
        "placetype": [
          "aat:300008850"
        ],
        "id": 2449000,
        "name:xx": "Lime Point"
      }
    },
    {
      "geometry": {
        "type": "Point",
        "coordinates": [
          -118.3833,
          35.6333
        ]
      },
      "type": "Feature",
      "properties": {
        "hierarchy": [
          "tgn:2449001",
          "tgn:1000001",
          "tgn:7012149",
          "tgn:1002545",
          "tgn:7007157",
          "tgn:7029392"
        ],
        "placetype": [
          "aat:300008850"
        ],
        "id": 2449001,
        "name:xx": "Lime Point"
      }
    },
    {
      "geometry": {
        "type": "Point",
        "coordinates": [
          -71.4833,
          44.8667
        ]
      },
      "type": "Feature",
      "properties": {
        "hierarchy": [
          "tgn:2449002",
          "tgn:1002300",
          "tgn:1000001",
          "tgn:7012149",
          "tgn:7007564",
          "tgn:7029392"
        ],
        "placetype": [
          "aat:300008680"
        ],
        "id": 2449002,
        "name:xx": "Lime Pond"
      }
    },
    {
      "geometry": {
        "type": "Point",
        "coordinates": [
          -112.0667,
          39.9667
        ]
      },
      "type": "Feature",
      "properties": {
        "hierarchy": [
          "tgn:2449003",
          "tgn:1000001",
          "tgn:7012149",
          "tgn:2002125",
          "tgn:7007827",
          "tgn:7029392"
        ],
        "placetype": [
          "aat:300000390"
        ],
        "id": 2449003,
        "name:xx": "Lime Quarry Mine"
      }
    },
    {
      "geometry": {
        "type": "Point",
        "coordinates": [
          -121.9833,
          37.9333
        ]
      },
      "type": "Feature",
      "properties": {
        "hierarchy": [
          "tgn:2449004",
          "tgn:1000001",
          "tgn:7012149",
          "tgn:1002298",
          "tgn:7007157",
          "tgn:7029392"
        ],
        "placetype": [
          "aat:300266640"
        ],
        "id": 2449004,
        "name:xx": "Lime Ridge"
      }
    },
    {
      "geometry": {
        "type": "Point",
        "coordinates": [
          -106.3167,
          38.4333
        ]
      },
      "type": "Feature",
      "properties": {
        "hierarchy": [
          "tgn:2449005",
          "tgn:1000001",
          "tgn:7012149",
          "tgn:7007158",
          "tgn:7029392"
        ],
        "placetype": [
          "aat:300266640"
        ],
        "id": 2449005,
        "name:xx": "Lime Ridge"
      }
    },
    {
      "geometry": {
        "type": "Point",
        "coordinates": [
          -112.6833,
          47.4833
        ]
      },
      "type": "Feature",
      "properties": {
        "hierarchy": [
          "tgn:2449006",
          "tgn:1000001",
          "tgn:7012149",
          "tgn:2001284",
          "tgn:7007524",
          "tgn:7029392"
        ],
        "placetype": [
          "aat:300266640"
        ],
        "id": 2449006,
        "name:xx": "Lime Ridge"
      }
    },
    {
      "geometry": {
        "type": "Point",
        "coordinates": [
          -114.25,
          36.3833
        ]
      },
      "type": "Feature",
      "properties": {
        "hierarchy": [
          "tgn:2449007",
          "tgn:1000001",
          "tgn:2001410",
          "tgn:7012149",
          "tgn:7007526",
          "tgn:7029392"
        ],
        "placetype": [
          "aat:300266640"
        ],
        "id": 2449007,
        "name:xx": "Lime Ridge"
      }
    },
    {
      "geometry": {
        "type": "Point",
        "coordinates": [
          -77.0833,
          40.7
        ]
      },
      "type": "Feature",
      "properties": {
        "hierarchy": [
          "tgn:2449008",
          "tgn:1000001",
          "tgn:7012149",
          "tgn:1002900",
          "tgn:7007710",
          "tgn:7029392"
        ],
        "placetype": [
          "aat:300266640"
        ],
        "id": 2449008,
        "name:xx": "Lime Ridge"
      }
    },
    {
      "geometry": {
        "type": "Point",
        "coordinates": [
          -75.2833,
          40.6333
        ]
      },
      "type": "Feature",
      "properties": {
        "hierarchy": [
          "tgn:2449009",
          "tgn:1000001",
          "tgn:7012149",
          "tgn:1002729",
          "tgn:7007710",
          "tgn:7029392"
        ],
        "placetype": [
          "aat:300008347"
        ],
        "id": 2449009,
        "name:xx": "Lime Ridge"
      }
    }
  ]
}
