{
  "geometry": {
    "type": "Point",
    "coordinates": [
      15.05,
      -7.9333
    ]
  },
  "type": "Feature",
  "properties": {
    "hierarchy": [
      "tgn:1087786",
      "tgn:7001242",
      "tgn:1000149",
      "tgn:1000834",
      "tgn:7029392"
    ],
    "placetype": [
      "aat:300008347"
    ],
    "id": 1087786,
    "name:xx": "Dange"
  }
}
