{
  "geometry": {
    "type": "Point",
    "coordinates": [
      -110.6167,
      32.0833
    ]
  },
  "type": "Feature",
  "properties": {
    "hierarchy": [
      "tgn:2264205",
      "tgn:1000001",
      "tgn:7006451",
      "tgn:7012149",
      "tgn:2000100",
      "tgn:7029392"
    ],
    "placetype": [
      "aat:300008699"
    ],
    "id": 2264205,
    "name:xx": "Coyote Wash"
  }
}
