{
  "type": "FeatureCollection",
  "features": [
    {
      "geometry": {
        "type": "Point",
        "coordinates": [
          -77,
          39.25
        ]
      },
      "type": "Feature",
      "properties": {
        "hierarchy": [
          "tgn:2345910",
          "tgn:1000001",
          "tgn:1002488",
          "tgn:7012149",
          "tgn:7007516",
          "tgn:7029392"
        ],
        "placetype": [
          "aat:300008347"
        ],
        "id": 2345910,
        "name:xx": "Gary"
      }
    },
    {
      "geometry": {
        "type": "Point",
        "coordinates": [
          -81.7167,
          34.35
        ]
      },
      "type": "Feature",
      "properties": {
        "hierarchy": [
          "tgn:2345911",
          "tgn:1000001",
          "tgn:7012149",
          "tgn:2001760",
          "tgn:7007712",
          "tgn:7029392"
        ],
        "placetype": [
          "aat:300008347"
        ],
        "id": 2345911,
        "name:xx": "Gary"
      }
    },
    {
      "geometry": {
        "type": "Point",
        "coordinates": [
          -95.7167,
          30.3167
        ]
      },
      "type": "Feature",
      "properties": {
        "hierarchy": [
          "tgn:2345912",
          "tgn:1000001",
          "tgn:7012149",
          "tgn:1002691",
          "tgn:7007826",
          "tgn:7029392"
        ],
        "placetype": [
          "aat:300008347"
        ],
        "id": 2345912,
        "name:xx": "Gary"
      }
    },
    {
      "geometry": {
        "type": "Point",
        "coordinates": [
          -78.2,
          36.85
        ]
      },
      "type": "Feature",
      "properties": {
        "hierarchy": [
          "tgn:2345913",
          "tgn:1000001",
          "tgn:7012149",
          "tgn:2002171",
          "tgn:7007919",
          "tgn:7029392"
        ],
        "placetype": [
          "aat:300008347"
        ],
        "id": 2345913,
        "name:xx": "Gary"
      }
    },
    {
      "geometry": {
        "type": "Point",
        "coordinates": [
          -115.3167,
          35.8667
        ]
      },
      "type": "Feature",
      "properties": {
        "hierarchy": [
          "tgn:2345914",
          "tgn:1000001",
          "tgn:2001410",
          "tgn:7012149",
          "tgn:7007526",
          "tgn:7029392"
        ],
        "placetype": [
          "aat:300000390"
        ],
        "id": 2345914,
        "name:xx": "Gary Allen Quarry"
      }
    },
    {
      "geometry": {
        "type": "Point",
        "coordinates": [
          -74.9167,
          40.5167
        ]
      },
      "type": "Feature",
      "properties": {
        "hierarchy": [
          "tgn:2345915",
          "tgn:1000001",
          "tgn:1002493",
          "tgn:7012149",
          "tgn:7007565",
          "tgn:7029392"
        ],
        "placetype": [
          "aat:300008347"
        ],
        "id": 2345915,
        "name:xx": "Gary Corner"
      }
    },
    {
      "geometry": {
        "type": "Point",
        "coordinates": [
          -123.5833,
          40.7333
        ]
      },
      "type": "Feature",
      "properties": {
        "hierarchy": [
          "tgn:2345916",
          "tgn:1000001",
          "tgn:7012149",
          "tgn:2000181",
          "tgn:7007157",
          "tgn:7029392"
        ],
        "placetype": [
          "aat:300008706"
        ],
        "id": 2345916,
        "name:xx": "Gary Creek"
      }
    },
    {
      "geometry": {
        "type": "Point",
        "coordinates": [
          -113.6833,
          45.2
        ]
      },
      "type": "Feature",
      "properties": {
        "hierarchy": [
          "tgn:2345917",
          "tgn:1000001",
          "tgn:7012149",
          "tgn:2000481",
          "tgn:7007250",
          "tgn:7029392"
        ],
        "placetype": [
          "aat:300008706"
        ],
        "id": 2345917,
        "name:xx": "Gary Creek"
      }
    },
    {
      "geometry": {
        "type": "Point",
        "coordinates": [
          -86.5167,
          37.2333
        ]
      },
      "type": "Feature",
      "properties": {
        "hierarchy": [
          "tgn:2345918",
          "tgn:1000001",
          "tgn:2000775",
          "tgn:7012149",
          "tgn:7007255",
          "tgn:7029392"
        ],
        "placetype": [
          "aat:300008706"
        ],
        "id": 2345918,
        "name:xx": "Gary Creek"
      }
    },
    {
      "geometry": {
        "type": "Point",
        "coordinates": [
          -76.1667,
          38.5667
        ]
      },
      "type": "Feature",
      "properties": {
        "hierarchy": [
          "tgn:2345919",
          "tgn:1002338",
          "tgn:1000001",
          "tgn:7012149",
          "tgn:7007516",
          "tgn:7029392"
        ],
        "placetype": [
          "aat:300132316"
        ],
        "id": 2345919,
        "name:xx": "Gary Creek"
      }
    }
  ]
}
