{
  "geometry": {
    "type": "Point",
    "coordinates": [
      -103.85,
      38.2167
    ]
  },
  "type": "Feature",
  "properties": {
    "hierarchy": [
      "tgn:2250209",
      "tgn:1000001",
      "tgn:7012149",
      "tgn:2000204",
      "tgn:7007158",
      "tgn:7029392"
    ],
    "placetype": [
      "aat:300006075"
    ],
    "id": 2250209,
    "name:xx": "Collins Lateral"
  }
}
