{
  "geometry": {
    "type": "Point",
    "coordinates": [
      -114.2333,
      46.25
    ]
  },
  "type": "Feature",
  "properties": {
    "hierarchy": [
      "tgn:2628339",
      "tgn:1000001",
      "tgn:7012149",
      "tgn:2001300",
      "tgn:7007524",
      "tgn:7029392"
    ],
    "placetype": [
      "aat:300266640"
    ],
    "id": 2628339,
    "name:xx": "Romney Ridge"
  }
}
