{
  "type": "FeatureCollection",
  "features": [
    {
      "geometry": {
        "type": "Point",
        "coordinates": [
          -101.9667,
          29.9
        ]
      },
      "type": "Feature",
      "properties": {
        "hierarchy": [
          "tgn:2262310",
          "tgn:1000001",
          "tgn:7012149",
          "tgn:2002082",
          "tgn:7007826",
          "tgn:7029392"
        ],
        "placetype": [
          "aat:300008706"
        ],
        "id": 2262310,
        "name:xx": "Cow Creek"
      }
    },
    {
      "geometry": {
        "type": "Point",
        "coordinates": [
          -102.6,
          29.9833
        ]
      },
      "type": "Feature",
      "properties": {
        "hierarchy": [
          "tgn:2262311",
          "tgn:1000001",
          "tgn:2001945",
          "tgn:7012149",
          "tgn:7007826",
          "tgn:7029392"
        ],
        "placetype": [
          "aat:300008706"
        ],
        "id": 2262311,
        "name:xx": "Cow Creek"
      }
    },
    {
      "geometry": {
        "type": "Point",
        "coordinates": [
          -99.4833,
          31.9333
        ]
      },
      "type": "Feature",
      "properties": {
        "hierarchy": [
          "tgn:2262312",
          "tgn:1000001",
          "tgn:7012149",
          "tgn:2001959",
          "tgn:7007826",
          "tgn:7029392"
        ],
        "placetype": [
          "aat:300008706"
        ],
        "id": 2262312,
        "name:xx": "Cow Creek"
      }
    },
    {
      "geometry": {
        "type": "Point",
        "coordinates": [
          -112.1333,
          37.95
        ]
      },
      "type": "Feature",
      "properties": {
        "hierarchy": [
          "tgn:2262313",
          "tgn:1000001",
          "tgn:2002109",
          "tgn:7012149",
          "tgn:7007827",
          "tgn:7029392"
        ],
        "placetype": [
          "aat:300008706"
        ],
        "id": 2262313,
        "name:xx": "Cow Creek"
      }
    },
    {
      "geometry": {
        "type": "Point",
        "coordinates": [
          -109.3667,
          40.7167
        ]
      },
      "type": "Feature",
      "properties": {
        "hierarchy": [
          "tgn:2262314",
          "tgn:1000001",
          "tgn:7012149",
          "tgn:2002124",
          "tgn:7007827",
          "tgn:7029392"
        ],
        "placetype": [
          "aat:300008706"
        ],
        "id": 2262314,
        "name:xx": "Cow Creek"
      }
    },
    {
      "geometry": {
        "type": "Point",
        "coordinates": [
          -113.8,
          37.5333
        ]
      },
      "type": "Feature",
      "properties": {
        "hierarchy": [
          "tgn:2262315",
          "tgn:1000001",
          "tgn:7012149",
          "tgn:2002127",
          "tgn:7007827",
          "tgn:7029392"
        ],
        "placetype": [
          "aat:300008706"
        ],
        "id": 2262315,
        "name:xx": "Cow Creek"
      }
    },
    {
      "geometry": {
        "type": "Point",
        "coordinates": [
          -109.0833,
          38.8667
        ]
      },
      "type": "Feature",
      "properties": {
        "hierarchy": [
          "tgn:2262316",
          "tgn:1000001",
          "tgn:7012149",
          "tgn:2002110",
          "tgn:7007827",
          "tgn:7029392"
        ],
        "placetype": [
          "aat:300008706"
        ],
        "id": 2262316,
        "name:xx": "Cow Creek"
      }
    },
    {
      "geometry": {
        "type": "Point",
        "coordinates": [
          -79.0833,
          36.95
        ]
      },
      "type": "Feature",
      "properties": {
        "hierarchy": [
          "tgn:2262317",
          "tgn:1000001",
          "tgn:7012149",
          "tgn:2002166",
          "tgn:7007919",
          "tgn:7029392"
        ],
        "placetype": [
          "aat:300008706"
        ],
        "id": 2262317,
        "name:xx": "Cow Creek"
      }
    },
    {
      "geometry": {
        "type": "Point",
        "coordinates": [
          -76.4833,
          37.4667
        ]
      },
      "type": "Feature",
      "properties": {
        "hierarchy": [
          "tgn:2262318",
          "tgn:1000001",
          "tgn:7012149",
          "tgn:1002411",
          "tgn:7007919",
          "tgn:7029392"
        ],
        "placetype": [
          "aat:300008706"
        ],
        "id": 2262318,
        "name:xx": "Cow Creek"
      }
    },
    {
      "geometry": {
        "type": "Point",
        "coordinates": [
          -76.0833,
          36.7
        ]
      },
      "type": "Feature",
      "properties": {
        "hierarchy": [
          "tgn:2262319",
          "tgn:1000001",
          "tgn:2002202",
          "tgn:7012149",
          "tgn:7007919",
          "tgn:7029392"
        ],
        "placetype": [
          "aat:300008706"
        ],
        "id": 2262319,
        "name:xx": "Cow Creek"
      }
    }
  ]
}
