{
  "type": "FeatureCollection",
  "features": [
    {
      "geometry": {
        "type": "Point",
        "coordinates": [
          -106.3,
          44.8
        ]
      },
      "type": "Feature",
      "properties": {
        "hierarchy": [
          "tgn:2615240",
          "tgn:1000001",
          "tgn:7012149",
          "tgn:2002381",
          "tgn:7007923",
          "tgn:7029392"
        ],
        "placetype": [
          "aat:300008706"
        ],
        "id": 2615240,
        "name:xx": "Reservoir Creek"
      }
    },
    {
      "geometry": {
        "type": "Point",
        "coordinates": [
          -105.8333,
          44.75
        ]
      },
      "type": "Feature",
      "properties": {
        "hierarchy": [
          "tgn:2615241",
          "tgn:1000001",
          "tgn:2002367",
          "tgn:7012149",
          "tgn:7007923",
          "tgn:7029392"
        ],
        "placetype": [
          "aat:300008706"
        ],
        "id": 2615241,
        "name:xx": "Reservoir Creek"
      }
    },
    {
      "geometry": {
        "type": "Point",
        "coordinates": [
          -105.4167,
          42.25
        ]
      },
      "type": "Feature",
      "properties": {
        "hierarchy": [
          "tgn:2615242",
          "tgn:2002365",
          "tgn:1000001",
          "tgn:7012149",
          "tgn:7007923",
          "tgn:7029392"
        ],
        "placetype": [
          "aat:300008706"
        ],
        "id": 2615242,
        "name:xx": "Reservoir Creek"
      }
    },
    {
      "geometry": {
        "type": "Point",
        "coordinates": [
          -108.2833,
          44.25
        ]
      },
      "type": "Feature",
      "properties": {
        "hierarchy": [
          "tgn:2615243",
          "tgn:1000001",
          "tgn:7012149",
          "tgn:7007923",
          "tgn:7029392"
        ],
        "placetype": [
          "aat:300008706"
        ],
        "id": 2615243,
        "name:xx": "Reservoir Creek"
      }
    },
    {
      "geometry": {
        "type": "Point",
        "coordinates": [
          -104.85,
          39.8333
        ]
      },
      "type": "Feature",
      "properties": {
        "hierarchy": [
          "tgn:2615244",
          "tgn:2000192",
          "tgn:1000001",
          "tgn:7012149",
          "tgn:7007158",
          "tgn:7029392"
        ],
        "placetype": [
          "aat:300006191"
        ],
        "id": 2615244,
        "name:xx": "Reservoir D"
      }
    },
    {
      "geometry": {
        "type": "Point",
        "coordinates": [
          -108.2333,
          39.3333
        ]
      },
      "type": "Feature",
      "properties": {
        "hierarchy": [
          "tgn:2615245",
          "tgn:1000001",
          "tgn:7012149",
          "tgn:7007158",
          "tgn:7029392"
        ],
        "placetype": [
          "aat:300006075"
        ],
        "id": 2615245,
        "name:xx": "Reservoir Ditch"
      }
    },
    {
      "geometry": {
        "type": "Point",
        "coordinates": [
          -105.5833,
          37.0167
        ]
      },
      "type": "Feature",
      "properties": {
        "hierarchy": [
          "tgn:2615246",
          "tgn:1000001",
          "tgn:7012149",
          "tgn:2000203",
          "tgn:7007158",
          "tgn:7029392"
        ],
        "placetype": [
          "aat:300006075"
        ],
        "id": 2615246,
        "name:xx": "Reservoir Ditch"
      }
    },
    {
      "geometry": {
        "type": "Point",
        "coordinates": [
          -105.9167,
          35.9833
        ]
      },
      "type": "Feature",
      "properties": {
        "hierarchy": [
          "tgn:2615247",
          "tgn:1000001",
          "tgn:7012149",
          "tgn:2001454",
          "tgn:7007566",
          "tgn:7029392"
        ],
        "placetype": [
          "aat:300006075"
        ],
        "id": 2615247,
        "name:xx": "Reservoir Ditch"
      }
    },
    {
      "geometry": {
        "type": "Point",
        "coordinates": [
          -106.7167,
          41.1833
        ]
      },
      "type": "Feature",
      "properties": {
        "hierarchy": [
          "tgn:2615248",
          "tgn:1000001",
          "tgn:2002368",
          "tgn:7012149",
          "tgn:7007923",
          "tgn:7029392"
        ],
        "placetype": [
          "aat:300006075"
        ],
        "id": 2615248,
        "name:xx": "Reservoir Ditch"
      }
    },
    {
      "geometry": {
        "type": "Point",
        "coordinates": [
          -108.25,
          40.8667
        ]
      },
      "type": "Feature",
      "properties": {
        "hierarchy": [
          "tgn:2615249",
          "tgn:1000001",
          "tgn:7012149",
          "tgn:2000232",
          "tgn:7007158",
          "tgn:7029392"
        ],
        "placetype": [
          "aat:300008761"
        ],
        "id": 2615249,
        "name:xx": "Reservoir Draw"
      }
    }
  ]
}
