{
  "geometry": {
    "type": "Point",
    "coordinates": [
      -106.8167,
      34.4333
    ]
  },
  "type": "Feature",
  "properties": {
    "hierarchy": [
      "tgn:2640391",
      "tgn:1000001",
      "tgn:7012149",
      "tgn:2001456",
      "tgn:7007566",
      "tgn:7029392"
    ],
    "placetype": [
      "aat:300006075"
    ],
    "id": 2640391,
    "name:xx": "San Francisco Lateral"
  }
}
