{
  "geometry": {
    "type": "Point",
    "coordinates": [
      -78.85,
      21.6333
    ]
  },
  "type": "Feature",
  "properties": {
    "hierarchy": [
      "tgn:1122625",
      "tgn:1001204",
      "tgn:1000001",
      "tgn:7004624",
      "tgn:7029392"
    ],
    "placetype": [
      "aat:300008707"
    ],
    "id": 1122625,
    "name:xx": "Ceiba, Río"
  }
}
