{
  "geometry": {
    "type": "Point",
    "coordinates": [
      31.4333,
      -19.9667
    ]
  },
  "type": "Feature",
  "properties": {
    "hierarchy": [
      "tgn:1092383",
      "tgn:7001242",
      "tgn:7594001",
      "tgn:1000185",
      "tgn:7029392"
    ],
    "placetype": [
      "aat:300008347"
    ],
    "id": 1092383,
    "name:xx": "Glencova"
  }
}
