{
  "geometry": {
    "type": "Point",
    "coordinates": [
      -107.9833,
      43.4667
    ]
  },
  "type": "Feature",
  "properties": {
    "hierarchy": [
      "tgn:2306895",
      "tgn:1000001",
      "tgn:7012149",
      "tgn:2002373",
      "tgn:7007923",
      "tgn:7029392"
    ],
    "placetype": [
      "aat:300008706"
    ],
    "id": 2306895,
    "name:xx": "East Fork Jones Creek"
  }
}
