{
  "geometry": {
    "type": "Point",
    "coordinates": [
      -118.7833,
      47.45
    ]
  },
  "type": "Feature",
  "properties": {
    "hierarchy": [
      "tgn:2353086",
      "tgn:1000001",
      "tgn:7012149",
      "tgn:2002247",
      "tgn:7007920",
      "tgn:7029392"
    ],
    "placetype": [
      "aat:300008680"
    ],
    "id": 2353086,
    "name:xx": "Goetz Lake"
  }
}
