{
  "type": "FeatureCollection",
  "features": [
    {
      "geometry": {
        "type": "Point",
        "coordinates": [
          -149.05,
          60.95
        ]
      },
      "type": "Feature",
      "properties": {
        "hierarchy": [
          "tgn:2745600",
          "tgn:2124017",
          "tgn:7006450",
          "tgn:1000001",
          "tgn:7012149",
          "tgn:7029392"
        ],
        "placetype": [
          "aat:300008706"
        ],
        "id": 2745600,
        "name:xx": "Virgin Creek"
      }
    },
    {
      "geometry": {
        "type": "Point",
        "coordinates": [
          -123.75,
          39.45
        ]
      },
      "type": "Feature",
      "properties": {
        "hierarchy": [
          "tgn:2745601",
          "tgn:1000001",
          "tgn:7012149",
          "tgn:7007157",
          "tgn:2000185",
          "tgn:7029392"
        ],
        "placetype": [
          "aat:300008706"
        ],
        "id": 2745601,
        "name:xx": "Virgin Creek"
      }
    },
    {
      "geometry": {
        "type": "Point",
        "coordinates": [
          -123.3667,
          41.15
        ]
      },
      "type": "Feature",
      "properties": {
        "hierarchy": [
          "tgn:2745602",
          "tgn:1000001",
          "tgn:7012149",
          "tgn:7007157",
          "tgn:2000191",
          "tgn:7029392"
        ],
        "placetype": [
          "aat:300008706"
        ],
        "id": 2745602,
        "name:xx": "Virgin Creek"
      }
    },
    {
      "geometry": {
        "type": "Point",
        "coordinates": [
          -90.05,
          37.2
        ]
      },
      "type": "Feature",
      "properties": {
        "hierarchy": [
          "tgn:2745603",
          "tgn:1000001",
          "tgn:2001174",
          "tgn:7012149",
          "tgn:7007523",
          "tgn:7029392"
        ],
        "placetype": [
          "aat:300008706"
        ],
        "id": 2745603,
        "name:xx": "Virgin Creek"
      }
    },
    {
      "geometry": {
        "type": "Point",
        "coordinates": [
          -110.9,
          47.05
        ]
      },
      "type": "Feature",
      "properties": {
        "hierarchy": [
          "tgn:2745604",
          "tgn:1000001",
          "tgn:2001266",
          "tgn:7012149",
          "tgn:7007524",
          "tgn:7029392"
        ],
        "placetype": [
          "aat:300008706"
        ],
        "id": 2745604,
        "name:xx": "Virgin Creek"
      }
    },
    {
      "geometry": {
        "type": "Point",
        "coordinates": [
          -118.6333,
          41.8
        ]
      },
      "type": "Feature",
      "properties": {
        "hierarchy": [
          "tgn:2745605",
          "tgn:1000001",
          "tgn:2001414",
          "tgn:7012149",
          "tgn:7007526",
          "tgn:7029392"
        ],
        "placetype": [
          "aat:300008706"
        ],
        "id": 2745605,
        "name:xx": "Virgin Creek"
      }
    },
    {
      "geometry": {
        "type": "Point",
        "coordinates": [
          -100.8,
          45.0667
        ]
      },
      "type": "Feature",
      "properties": {
        "hierarchy": [
          "tgn:2745606",
          "tgn:1000001",
          "tgn:2001790",
          "tgn:7012149",
          "tgn:7007713",
          "tgn:7029392"
        ],
        "placetype": [
          "aat:300008706"
        ],
        "id": 2745606,
        "name:xx": "Virgin Creek"
      }
    },
    {
      "geometry": {
        "type": "Point",
        "coordinates": [
          -117.0667,
          48.5833
        ]
      },
      "type": "Feature",
      "properties": {
        "hierarchy": [
          "tgn:2745607",
          "tgn:1000001",
          "tgn:7012149",
          "tgn:2002248",
          "tgn:7007920",
          "tgn:7029392"
        ],
        "placetype": [
          "aat:300008706"
        ],
        "id": 2745607,
        "name:xx": "Virgin Creek"
      }
    },
    {
      "geometry": {
        "type": "Point",
        "coordinates": [
          -90,
          46.2667
        ]
      },
      "type": "Feature",
      "properties": {
        "hierarchy": [
          "tgn:2745608",
          "tgn:1000001",
          "tgn:7012149",
          "tgn:2002327",
          "tgn:7007922",
          "tgn:7029392"
        ],
        "placetype": [
          "aat:300008706"
        ],
        "id": 2745608,
        "name:xx": "Virgin Creek"
      }
    },
    {
      "geometry": {
        "type": "Point",
        "coordinates": [
          -88.2333,
          43.6167
        ]
      },
      "type": "Feature",
      "properties": {
        "hierarchy": [
          "tgn:2745609",
          "tgn:1000001",
          "tgn:7020939",
          "tgn:7012149",
          "tgn:7007922",
          "tgn:7029392"
        ],
        "placetype": [
          "aat:300008706"
        ],
        "id": 2745609,
        "name:xx": "Virgin Creek"
      }
    }
  ]
}
