{
  "geometry": {
    "type": "Point",
    "coordinates": [
      -103.9833,
      36.6667
    ]
  },
  "type": "Feature",
  "properties": {
    "hierarchy": [
      "tgn:2343780",
      "tgn:1000001",
      "tgn:7012149",
      "tgn:2001459",
      "tgn:7007566",
      "tgn:7029392"
    ],
    "placetype": [
      "aat:300008706"
    ],
    "id": 2343780,
    "name:xx": "Gallegos Creek"
  }
}
