{
  "geometry": {
    "type": "Point",
    "coordinates": [
      33.819309,
      27.12398
    ]
  },
  "type": "Feature",
  "properties": {
    "hierarchy": [
      "tgn:7528057",
      "tgn:7001242",
      "tgn:7001311",
      "tgn:7016833",
      "tgn:7029392"
    ],
    "placetype": [
      "aat:300379998"
    ],
    "name:en": "Umm Ḑalfah, Wādī",
    "id": 7528057
  }
}
