{
  "geometry": {
    "type": "Point",
    "coordinates": [
      -82.45,
      39.3667
    ]
  },
  "type": "Feature",
  "properties": {
    "hierarchy": [
      "tgn:2200136",
      "tgn:1000001",
      "tgn:7012149",
      "tgn:2001621",
      "tgn:7007706",
      "tgn:7029392"
    ],
    "placetype": [
      "aat:300008706"
    ],
    "id": 2200136,
    "name:xx": "Brushy Creek"
  }
}
