{
  "geometry": {
    "type": "Point",
    "coordinates": [
      -119.65,
      46.2333
    ]
  },
  "type": "Feature",
  "properties": {
    "hierarchy": [
      "tgn:2115849",
      "tgn:2002240",
      "tgn:1000001",
      "tgn:7012149",
      "tgn:7007920",
      "tgn:7029392"
    ],
    "placetype": [
      "aat:300387016"
    ],
    "id": 2115849,
    "name:xx": "Gibbon"
  }
}
