{
  "geometry": {
    "type": "Point",
    "coordinates": [
      32.883333,
      24.933333
    ]
  },
  "type": "Feature",
  "properties": {
    "hierarchy": [
      "tgn:7527394",
      "tgn:7001242",
      "tgn:7016833",
      "tgn:7000122",
      "tgn:7029392"
    ],
    "placetype": [
      "aat:300005926"
    ],
    "name:en": "Sīdī Sālim",
    "id": 7527394
  }
}
