{
  "type": "FeatureCollection",
  "features": [
    {
      "geometry": {
        "type": "Point",
        "coordinates": [
          37.6,
          56.1333
        ]
      },
      "type": "Feature",
      "properties": {
        "hierarchy": [
          "tgn:1138290",
          "tgn:1000004",
          "tgn:7011573",
          "tgn:7018214",
          "tgn:7002435",
          "tgn:7029392"
        ],
        "placetype": [
          "aat:300008347"
        ],
        "id": 1138290,
        "name:xx": "Protasovo"
      }
    },
    {
      "geometry": {
        "type": "Point",
        "coordinates": [
          47,
          51.25
        ]
      },
      "type": "Feature",
      "properties": {
        "hierarchy": [
          "tgn:1138291",
          "tgn:1000004",
          "tgn:1003408",
          "tgn:7018214",
          "tgn:7002435",
          "tgn:7029392"
        ],
        "placetype": [
          "aat:300008347"
        ],
        "id": 1138291,
        "name:xx": "Pushkino"
      }
    },
    {
      "geometry": {
        "type": "Point",
        "coordinates": [
          37.8667,
          56.0167
        ]
      },
      "type": "Feature",
      "properties": {
        "hierarchy": [
          "tgn:1138292",
          "tgn:1000004",
          "tgn:7011573",
          "tgn:7018214",
          "tgn:7002435",
          "tgn:7029392"
        ],
        "placetype": [
          "aat:300008347"
        ],
        "id": 1138292,
        "name:xx": "Pushkino"
      }
    },
    {
      "geometry": {
        "type": "Point",
        "coordinates": [
          35.7667,
          56.6
        ]
      },
      "type": "Feature",
      "properties": {
        "hierarchy": [
          "tgn:1138293",
          "tgn:1000004",
          "tgn:7012941",
          "tgn:7018214",
          "tgn:7002435",
          "tgn:7029392"
        ],
        "placetype": [
          "aat:300008347"
        ],
        "id": 1138293,
        "name:xx": "Pushkino"
      }
    },
    {
      "geometry": {
        "type": "Point",
        "coordinates": [
          49.4833,
          51.95
        ]
      },
      "type": "Feature",
      "properties": {
        "hierarchy": [
          "tgn:1138294",
          "tgn:1000004",
          "tgn:1003408",
          "tgn:7018214",
          "tgn:7002435",
          "tgn:7029392"
        ],
        "placetype": [
          "aat:300008347"
        ],
        "id": 1138294,
        "name:xx": "Rakhmanovka"
      }
    },
    {
      "geometry": {
        "type": "Point",
        "coordinates": [
          37.95,
          49.3667
        ]
      },
      "type": "Feature",
      "properties": {
        "hierarchy": [
          "tgn:1138295",
          "tgn:1000003",
          "tgn:7012067",
          "tgn:7006660",
          "tgn:7029392"
        ],
        "placetype": [
          "aat:300008347",
          "aat:300008375"
        ],
        "id": 1138295,
        "name:xx": "Rajgorodka"
      }
    },
    {
      "geometry": {
        "type": "Point",
        "coordinates": [
          37.75,
          48.9
        ]
      },
      "type": "Feature",
      "properties": {
        "hierarchy": [
          "tgn:1138296",
          "tgn:7012076",
          "tgn:1000003",
          "tgn:7006660",
          "tgn:7029392"
        ],
        "placetype": [
          "aat:300008347"
        ],
        "id": 1138296,
        "name:xx": "Raygorodok"
      }
    },
    {
      "geometry": {
        "type": "Point",
        "coordinates": [
          30.45,
          49.7
        ]
      },
      "type": "Feature",
      "properties": {
        "hierarchy": [
          "tgn:1138297",
          "tgn:1000003",
          "tgn:7011661",
          "tgn:7006660",
          "tgn:7029392"
        ],
        "placetype": [
          "aat:300008347"
        ],
        "id": 1138297,
        "name:xx": "Rokytne"
      }
    },
    {
      "geometry": {
        "type": "Point",
        "coordinates": [
          35.85,
          50.8667
        ]
      },
      "type": "Feature",
      "properties": {
        "hierarchy": [
          "tgn:1138298",
          "tgn:6000729",
          "tgn:1000004",
          "tgn:7018214",
          "tgn:7002435",
          "tgn:7029392"
        ],
        "placetype": [
          "aat:300008347"
        ],
        "id": 1138298,
        "name:xx": "Rakitnoye"
      }
    },
    {
      "geometry": {
        "type": "Point",
        "coordinates": [
          27.1667,
          51.3
        ]
      },
      "type": "Feature",
      "properties": {
        "hierarchy": [
          "tgn:1138299",
          "tgn:1000003",
          "tgn:7011667",
          "tgn:7006660",
          "tgn:7029392"
        ],
        "placetype": [
          "aat:300008347"
        ],
        "id": 1138299,
        "name:xx": "Rakitnoye"
      }
    }
  ]
}
