{
  "geometry": {
    "type": "Point",
    "coordinates": [
      -88.8333,
      34.8833
    ]
  },
  "type": "Feature",
  "properties": {
    "hierarchy": [
      "tgn:2247221",
      "tgn:1000001",
      "tgn:7012149",
      "tgn:7007522",
      "tgn:7029392"
    ],
    "placetype": [
      "aat:300008706"
    ],
    "id": 2247221,
    "name:xx": "Cody Creek"
  }
}
