{
  "geometry": {
    "type": "Point",
    "coordinates": [
      -104.9333,
      38.3333
    ]
  },
  "type": "Feature",
  "properties": {
    "hierarchy": [
      "tgn:2015767",
      "tgn:1000001",
      "tgn:7012149",
      "tgn:7007158",
      "tgn:2000242",
      "tgn:7029392"
    ],
    "placetype": [
      "aat:300387016"
    ],
    "id": 2015767,
    "name:xx": "Hobson"
  }
}
