{
  "geometry": {
    "type": "Point",
    "coordinates": [
      -90.3667,
      43.1333
    ]
  },
  "type": "Feature",
  "properties": {
    "hierarchy": [
      "tgn:2297301",
      "tgn:1000001",
      "tgn:7012149",
      "tgn:2002326",
      "tgn:7007922",
      "tgn:7029392"
    ],
    "placetype": [
      "aat:300266640"
    ],
    "id": 2297301,
    "name:xx": "Dry Dog Ridge"
  }
}
