{
  "geometry": {
    "type": "Point",
    "coordinates": [
      -67.8333,
      46.3333
    ]
  },
  "type": "Feature",
  "properties": {
    "hierarchy": [
      "tgn:2421759",
      "tgn:2000919",
      "tgn:1000001",
      "tgn:7012149",
      "tgn:7007515",
      "tgn:7029392"
    ],
    "placetype": [
      "aat:300008347"
    ],
    "id": 2421759,
    "name:xx": "Jewells Corner"
  }
}
