{
  "geometry": {
    "type": "Point",
    "coordinates": [
      -81.5833,
      30.0667
    ]
  },
  "type": "Feature",
  "properties": {
    "hierarchy": [
      "tgn:2753368",
      "tgn:1000001",
      "tgn:7012149",
      "tgn:2000283",
      "tgn:7007240",
      "tgn:7029392"
    ],
    "placetype": [
      "aat:300008905"
    ],
    "id": 2753368,
    "name:xx": "Waterhole"
  }
}
