{
  "geometry": {
    "type": "Point",
    "coordinates": [
      32.604164,
      29.26292
    ]
  },
  "type": "Feature",
  "properties": {
    "hierarchy": [
      "tgn:7536246",
      "tgn:7001242",
      "tgn:7016833",
      "tgn:1001110",
      "tgn:7029392"
    ],
    "placetype": [
      "aat:300379998"
    ],
    "id": 7536246,
    "name:xx": "Kh큰r카, W훮d카"
  }
}
