{
  "type": "FeatureCollection",
  "features": [
    {
      "geometry": {
        "type": "Point",
        "coordinates": [
          -92.0667,
          39.1667
        ]
      },
      "type": "Feature",
      "properties": {
        "hierarchy": [
          "tgn:2441850",
          "tgn:1002158",
          "tgn:1000001",
          "tgn:7012149",
          "tgn:7007523",
          "tgn:7029392"
        ],
        "placetype": [
          "aat:300006191"
        ],
        "id": 2441850,
        "name:xx": "Kon-Tiki Reservoir"
      }
    },
    {
      "geometry": {
        "type": "Point",
        "coordinates": [
          -87.5,
          46.4667
        ]
      },
      "type": "Feature",
      "properties": {
        "hierarchy": [
          "tgn:2441851",
          "tgn:1000001",
          "tgn:7012149",
          "tgn:2000975",
          "tgn:7007520",
          "tgn:7029392"
        ],
        "placetype": [
          "aat:300008798"
        ],
        "id": 2441851,
        "name:xx": "Kona Hills"
      }
    },
    {
      "geometry": {
        "type": "Point",
        "coordinates": [
          -157.7833,
          21.35
        ]
      },
      "type": "Feature",
      "properties": {
        "hierarchy": [
          "tgn:2441854",
          "tgn:1002483",
          "tgn:7019080",
          "tgn:1000001",
          "tgn:7012149",
          "tgn:7007249",
          "tgn:7029392"
        ],
        "placetype": [
          "aat:300008798"
        ],
        "id": 2441854,
        "name:xx": "Konahuanui"
      }
    },
    {
      "geometry": {
        "type": "Point",
        "coordinates": [
          -156.3,
          20.9
        ]
      },
      "type": "Feature",
      "properties": {
        "hierarchy": [
          "tgn:2441856",
          "tgn:1002648",
          "tgn:1000001",
          "tgn:7019158",
          "tgn:7012149",
          "tgn:7007249",
          "tgn:7029392"
        ],
        "placetype": [
          "aat:300008761"
        ],
        "id": 2441856,
        "name:xx": "Konanui Gulch"
      }
    },
    {
      "geometry": {
        "type": "Point",
        "coordinates": [
          -159.2833,
          60
        ]
      },
      "type": "Feature",
      "properties": {
        "hierarchy": [
          "tgn:2441857",
          "tgn:7006450",
          "tgn:1000001",
          "tgn:2000071",
          "tgn:7012149",
          "tgn:7029392"
        ],
        "placetype": [
          "aat:300008798"
        ],
        "id": 2441857,
        "name:xx": "Konarut Mountain"
      }
    },
    {
      "geometry": {
        "type": "Point",
        "coordinates": [
          -150.5667,
          60.6833
        ]
      },
      "type": "Feature",
      "properties": {
        "hierarchy": [
          "tgn:2441858",
          "tgn:7006450",
          "tgn:1000001",
          "tgn:7019698",
          "tgn:7012149",
          "tgn:7029392"
        ],
        "placetype": [
          "aat:300008680"
        ],
        "id": 2441858,
        "name:xx": "Konchanee Lake"
      }
    },
    {
      "geometry": {
        "type": "Point",
        "coordinates": [
          -97.9333,
          29.45
        ]
      },
      "type": "Feature",
      "properties": {
        "hierarchy": [
          "tgn:2441859",
          "tgn:1000001",
          "tgn:7012149",
          "tgn:1002431",
          "tgn:7007826",
          "tgn:7029392"
        ],
        "placetype": [
          "aat:300008699"
        ],
        "id": 2441859,
        "name:xx": "Konde Branch"
      }
    }
  ]
}
