{
  "type": "FeatureCollection",
  "features": [
    {
      "geometry": {
        "type": "Point",
        "coordinates": [
          22.983333,
          36.2
        ]
      },
      "type": "Feature",
      "properties": {
        "hierarchy": [
          "tgn:7237010",
          "tgn:7002745",
          "tgn:7017076",
          "tgn:1000003",
          "tgn:1000074",
          "tgn:7029392"
        ],
        "placetype": [
          "aat:300008347"
        ],
        "id": 7237010,
        "name:xx": "Áyios Ilías"
      }
    },
    {
      "geometry": {
        "type": "Point",
        "coordinates": [
          20.5,
          39.85
        ]
      },
      "type": "Feature",
      "properties": {
        "hierarchy": [
          "tgn:7237011",
          "tgn:7002707",
          "tgn:7002705",
          "tgn:1000003",
          "tgn:1000074",
          "tgn:7029392"
        ],
        "placetype": [
          "aat:300008798"
        ],
        "id": 7237011,
        "name:xx": "Áyios Ilías"
      }
    },
    {
      "geometry": {
        "type": "Point",
        "coordinates": [
          27.95,
          36.266667
        ]
      },
      "type": "Feature",
      "properties": {
        "hierarchy": [
          "tgn:7237012",
          "tgn:7011330",
          "tgn:7002674",
          "tgn:1000003",
          "tgn:1000074",
          "tgn:7029392"
        ],
        "placetype": [
          "aat:300008795"
        ],
        "id": 7237012,
        "name:xx": "Miasto, Monte"
      }
    },
    {
      "geometry": {
        "type": "Point",
        "coordinates": [
          25.183333,
          37.05
        ]
      },
      "type": "Feature",
      "properties": {
        "hierarchy": [
          "tgn:7237013",
          "tgn:7011270",
          "tgn:7002674",
          "tgn:1000003",
          "tgn:1000074",
          "tgn:7029392"
        ],
        "placetype": [
          "aat:300008777"
        ],
        "id": 7237013,
        "name:xx": "Áyios Ilías"
      }
    },
    {
      "geometry": {
        "type": "Point",
        "coordinates": [
          25.05,
          37
        ]
      },
      "type": "Feature",
      "properties": {
        "hierarchy": [
          "tgn:7237014",
          "tgn:7011270",
          "tgn:7002674",
          "tgn:1000003",
          "tgn:1000074",
          "tgn:7029392"
        ],
        "placetype": [
          "aat:300008777"
        ],
        "id": 7237014,
        "name:xx": "Áyios Ilías"
      }
    },
    {
      "geometry": {
        "type": "Point",
        "coordinates": [
          23.566667,
          35.466667
        ]
      },
      "type": "Feature",
      "properties": {
        "hierarchy": [
          "tgn:7237015",
          "tgn:7002690",
          "tgn:7012056",
          "tgn:1000003",
          "tgn:1000074",
          "tgn:7029392"
        ],
        "placetype": [
          "aat:300008347"
        ],
        "id": 7237015,
        "name:xx": "Áyios Fótios"
      }
    },
    {
      "geometry": {
        "type": "Point",
        "coordinates": [
          23.55,
          35.366667
        ]
      },
      "type": "Feature",
      "properties": {
        "hierarchy": [
          "tgn:7237016",
          "tgn:7002690",
          "tgn:7012056",
          "tgn:1000003",
          "tgn:1000074",
          "tgn:7029392"
        ],
        "placetype": [
          "aat:300008347"
        ],
        "id": 7237016,
        "name:xx": "Áyios Fótios"
      }
    },
    {
      "geometry": {
        "type": "Point",
        "coordinates": [
          23.066667,
          36.6
        ]
      },
      "type": "Feature",
      "properties": {
        "hierarchy": [
          "tgn:7237017",
          "tgn:7002745",
          "tgn:7017076",
          "tgn:1000003",
          "tgn:1000074",
          "tgn:7029392"
        ],
        "placetype": [
          "aat:300008791"
        ],
        "id": 7237017,
        "name:xx": "Áyios Fokás, Nisís"
      }
    },
    {
      "geometry": {
        "type": "Point",
        "coordinates": [
          26.166667,
          39
        ]
      },
      "type": "Feature",
      "properties": {
        "hierarchy": [
          "tgn:7237018",
          "tgn:7011163",
          "tgn:7002674",
          "tgn:1000003",
          "tgn:1000074",
          "tgn:7029392"
        ],
        "placetype": [
          "aat:300008850"
        ],
        "id": 7237018,
        "name:xx": "Áyios Fokás, Ákra"
      }
    },
    {
      "geometry": {
        "type": "Point",
        "coordinates": [
          25.133333,
          37.1
        ]
      },
      "type": "Feature",
      "properties": {
        "hierarchy": [
          "tgn:7237019",
          "tgn:7011270",
          "tgn:7002674",
          "tgn:1000003",
          "tgn:1000074",
          "tgn:7029392"
        ],
        "placetype": [
          "aat:300008850"
        ],
        "id": 7237019,
        "name:xx": "Áyios Fokás, Ákra"
      }
    }
  ]
}
