{
  "geometry": {
    "type": "Point",
    "coordinates": [
      79.9694,
      27.1724
    ]
  },
  "type": "Feature",
  "properties": {
    "hierarchy": [
      "tgn:7562035",
      "tgn:1000004",
      "tgn:7000198",
      "tgn:7016722",
      "tgn:7029392"
    ],
    "placetype": [
      "aat:300008347"
    ],
    "name:en": "Karīmāpur",
    "id": 7562035
  }
}
