{
  "geometry": {
    "type": "Point",
    "coordinates": [
      30.816667,
      28.95
    ]
  },
  "type": "Feature",
  "properties": {
    "hierarchy": [
      "tgn:7527482",
      "tgn:7001242",
      "tgn:7016833",
      "tgn:1001142",
      "tgn:7029392"
    ],
    "placetype": [
      "aat:300005926"
    ],
    "name:en": "S카d카 Ab큰 Hash카mah",
    "id": 7527482
  }
}
