{
  "type": "FeatureCollection",
  "features": [
    {
      "geometry": {
        "type": "Point",
        "coordinates": [
          -72.483333,
          -40.15
        ]
      },
      "type": "Feature",
      "properties": {
        "hierarchy": [
          "tgn:7316810",
          "tgn:1001699",
          "tgn:1000049",
          "tgn:1000002",
          "tgn:7029392"
        ],
        "placetype": [
          "aat:300008699"
        ],
        "id": 7316810,
        "name:xx": "Coique, Río"
      }
    },
    {
      "geometry": {
        "type": "Point",
        "coordinates": [
          -72.4,
          -40.15
        ]
      },
      "type": "Feature",
      "properties": {
        "hierarchy": [
          "tgn:7316811",
          "tgn:1001699",
          "tgn:1000049",
          "tgn:1000002",
          "tgn:7029392"
        ],
        "placetype": [
          "aat:300386846"
        ],
        "id": 7316811,
        "name:xx": "Coique, Punta"
      }
    },
    {
      "geometry": {
        "type": "Point",
        "coordinates": [
          -72.283333,
          -40.866667
        ]
      },
      "type": "Feature",
      "properties": {
        "hierarchy": [
          "tgn:7316812",
          "tgn:1001699",
          "tgn:1000049",
          "tgn:1000002",
          "tgn:7029392"
        ],
        "placetype": [
          "aat:300008699"
        ],
        "id": 7316812,
        "name:xx": "Coique, Estero"
      }
    },
    {
      "geometry": {
        "type": "Point",
        "coordinates": [
          -72.466667,
          -40.133333
        ]
      },
      "type": "Feature",
      "properties": {
        "hierarchy": [
          "tgn:7316813",
          "tgn:1001699",
          "tgn:1000049",
          "tgn:1000002",
          "tgn:7029392"
        ],
        "placetype": [
          "aat:300000206"
        ],
        "id": 7316813,
        "name:xx": "Coique"
      }
    },
    {
      "geometry": {
        "type": "Point",
        "coordinates": [
          -68.983333,
          -21.5
        ]
      },
      "type": "Feature",
      "properties": {
        "hierarchy": [
          "tgn:7316814",
          "tgn:7016598",
          "tgn:1000049",
          "tgn:1000002",
          "tgn:7029392"
        ],
        "placetype": [
          "aat:300266554",
          "aat:300008699"
        ],
        "id": 7316814,
        "name:xx": "Coipuno, Quebrada"
      }
    },
    {
      "geometry": {
        "type": "Point",
        "coordinates": [
          -72.4,
          -39.1
        ]
      },
      "type": "Feature",
      "properties": {
        "hierarchy": [
          "tgn:7316815",
          "tgn:1001692",
          "tgn:1000049",
          "tgn:1000002",
          "tgn:7029392"
        ],
        "placetype": [
          "aat:300000206"
        ],
        "id": 7316815,
        "name:xx": "Coipué Panco"
      }
    },
    {
      "geometry": {
        "type": "Point",
        "coordinates": [
          -73.1,
          -39.016667
        ]
      },
      "type": "Feature",
      "properties": {
        "hierarchy": [
          "tgn:7316816",
          "tgn:1001692",
          "tgn:1000049",
          "tgn:1000002",
          "tgn:7029392"
        ],
        "placetype": [
          "aat:300008699"
        ],
        "id": 7316816,
        "name:xx": "Coipué, Río"
      }
    },
    {
      "geometry": {
        "type": "Point",
        "coordinates": [
          -72.633333,
          -38.1
        ]
      },
      "type": "Feature",
      "properties": {
        "hierarchy": [
          "tgn:7316817",
          "tgn:1001692",
          "tgn:1000049",
          "tgn:1000002",
          "tgn:7029392"
        ],
        "placetype": [
          "aat:300008699"
        ],
        "id": 7316817,
        "name:xx": "Coipué, Estero"
      }
    },
    {
      "geometry": {
        "type": "Point",
        "coordinates": [
          -72.15,
          -35.2
        ]
      },
      "type": "Feature",
      "properties": {
        "hierarchy": [
          "tgn:7316818",
          "tgn:1001705",
          "tgn:1000049",
          "tgn:1000002",
          "tgn:7029392"
        ],
        "placetype": [
          "aat:300008699"
        ],
        "id": 7316818,
        "name:xx": "Coipué, Estero"
      }
    },
    {
      "geometry": {
        "type": "Point",
        "coordinates": [
          -72.133333,
          -35.25
        ]
      },
      "type": "Feature",
      "properties": {
        "hierarchy": [
          "tgn:7316819",
          "tgn:1001705",
          "tgn:1000049",
          "tgn:1000002",
          "tgn:7029392"
        ],
        "placetype": [
          "aat:300008899"
        ],
        "id": 7316819,
        "name:xx": "Coipué, Bajos de"
      }
    }
  ]
}
