{
  "geometry": {
    "type": "Point",
    "coordinates": [
      -68.5333,
      44.6333
    ]
  },
  "type": "Feature",
  "properties": {
    "hierarchy": [
      "tgn:2460088",
      "tgn:1000001",
      "tgn:2000922",
      "tgn:7012149",
      "tgn:7007515",
      "tgn:7029392"
    ],
    "placetype": [
      "aat:300008680"
    ],
    "id": 2460088,
    "name:xx": "Little Rocky Pond"
  }
}
