{
  "type": "FeatureCollection",
  "features": [
    {
      "geometry": {
        "type": "Point",
        "coordinates": [
          -85.2333,
          35.15
        ]
      },
      "type": "Feature",
      "properties": {
        "hierarchy": [
          "tgn:2098400",
          "tgn:1000001",
          "tgn:7017496",
          "tgn:7012149",
          "tgn:2001869",
          "tgn:7007825",
          "tgn:7029392"
        ],
        "placetype": [
          "aat:300000745"
        ],
        "id": 2098400,
        "name:xx": "Kings Ridge"
      }
    },
    {
      "geometry": {
        "type": "Point",
        "coordinates": [
          -83.8667,
          35.9167
        ]
      },
      "type": "Feature",
      "properties": {
        "hierarchy": [
          "tgn:2098401",
          "tgn:1000001",
          "tgn:7017496",
          "tgn:7012149",
          "tgn:2001869",
          "tgn:7007825",
          "tgn:7029392"
        ],
        "placetype": [
          "aat:300000745"
        ],
        "id": 2098401,
        "name:xx": "Lake Forest"
      }
    },
    {
      "geometry": {
        "type": "Point",
        "coordinates": [
          -85.1667,
          35.0667
        ]
      },
      "type": "Feature",
      "properties": {
        "hierarchy": [
          "tgn:2098403",
          "tgn:1000001",
          "tgn:7017496",
          "tgn:7012149",
          "tgn:2001869",
          "tgn:7007825",
          "tgn:7029392"
        ],
        "placetype": [
          "aat:300000745"
        ],
        "id": 2098403,
        "name:xx": "Lake Vista"
      }
    },
    {
      "geometry": {
        "type": "Point",
        "coordinates": [
          -85.2333,
          35.1667
        ]
      },
      "type": "Feature",
      "properties": {
        "hierarchy": [
          "tgn:2098404",
          "tgn:1000001",
          "tgn:7017496",
          "tgn:7012149",
          "tgn:2001869",
          "tgn:7007825",
          "tgn:7029392"
        ],
        "placetype": [
          "aat:300000745"
        ],
        "id": 2098404,
        "name:xx": "Long Branch"
      }
    },
    {
      "geometry": {
        "type": "Point",
        "coordinates": [
          -85.25,
          35.1
        ]
      },
      "type": "Feature",
      "properties": {
        "hierarchy": [
          "tgn:2098406",
          "tgn:1000001",
          "tgn:7017496",
          "tgn:7012149",
          "tgn:2001869",
          "tgn:7007825",
          "tgn:7029392"
        ],
        "placetype": [
          "aat:300000745"
        ],
        "id": 2098406,
        "name:xx": "Lupton City"
      }
    },
    {
      "geometry": {
        "type": "Point",
        "coordinates": [
          -85.2667,
          35.1
        ]
      },
      "type": "Feature",
      "properties": {
        "hierarchy": [
          "tgn:2098408",
          "tgn:1000001",
          "tgn:7017496",
          "tgn:7012149",
          "tgn:2001869",
          "tgn:7007825",
          "tgn:7029392"
        ],
        "placetype": [
          "aat:300000745"
        ],
        "id": 2098408,
        "name:xx": "Manchester Park"
      }
    },
    {
      "geometry": {
        "type": "Point",
        "coordinates": [
          -85.2,
          35.0833
        ]
      },
      "type": "Feature",
      "properties": {
        "hierarchy": [
          "tgn:2098409",
          "tgn:1000001",
          "tgn:7017496",
          "tgn:7012149",
          "tgn:2001869",
          "tgn:7007825",
          "tgn:7029392"
        ],
        "placetype": [
          "aat:300000745"
        ],
        "id": 2098409,
        "name:xx": "Murray Hills"
      }
    }
  ]
}
