{
  "geometry": {
    "type": "Point",
    "coordinates": [
      -115.45,
      47.2667
    ]
  },
  "type": "Feature",
  "properties": {
    "hierarchy": [
      "tgn:2306154",
      "tgn:1000001",
      "tgn:7012149",
      "tgn:2001290",
      "tgn:7007524",
      "tgn:7029392"
    ],
    "placetype": [
      "aat:300008706"
    ],
    "id": 2306154,
    "name:xx": "East Fork Big Creek"
  }
}
