{
  "geometry": {
    "type": "Point",
    "coordinates": [
      -82.8667,
      35.6167
    ]
  },
  "type": "Feature",
  "properties": {
    "hierarchy": [
      "tgn:2487005",
      "tgn:1000001",
      "tgn:7012149",
      "tgn:2001503",
      "tgn:7007709",
      "tgn:7029392"
    ],
    "placetype": [
      "aat:300008798"
    ],
    "id": 2487005,
    "name:xx": "Lee Mountain"
  }
}
