{
  "geometry": {
    "type": "Point",
    "coordinates": [
      -74.95,
      40.3833
    ]
  },
  "type": "Feature",
  "properties": {
    "hierarchy": [
      "tgn:2349285",
      "tgn:1000001",
      "tgn:1002493",
      "tgn:7012149",
      "tgn:7007565",
      "tgn:7029392"
    ],
    "placetype": [
      "aat:300008798"
    ],
    "id": 2349285,
    "name:xx": "Gilboa, Mount"
  }
}
