{
  "geometry": {
    "type": "Point",
    "coordinates": [
      107.0833,
      28.7167
    ]
  },
  "type": "Feature",
  "properties": {
    "hierarchy": [
      "tgn:1071841",
      "tgn:1000004",
      "tgn:7002080",
      "tgn:1000111",
      "tgn:7029392"
    ],
    "placetype": [
      "aat:300008347"
    ],
    "id": 1071841,
    "name:xx": "Shuibatang"
  }
}
