{
  "geometry": {
    "type": "Point",
    "coordinates": [
      77.966434,
      30.300174
    ]
  },
  "type": "Feature",
  "properties": {
    "hierarchy": [
      "tgn:7592131",
      "tgn:1000004",
      "tgn:7000198",
      "tgn:7031786",
      "tgn:7029392"
    ],
    "placetype": [
      "aat:300008347"
    ],
    "name:en": "Harbhajwāla",
    "id": 7592131
  }
}
