{
  "type": "FeatureCollection",
  "features": [
    {
      "geometry": {
        "type": "Point",
        "coordinates": [
          117.2,
          39.1333
        ]
      },
      "type": "Feature",
      "properties": {
        "hierarchy": [
          "tgn:1000960",
          "tgn:1000004",
          "tgn:1000111",
          "tgn:7029392"
        ],
        "placetype": [
          "aat:300387064",
          "aat:300265612"
        ],
        "id": 1000960,
        "name:xx": "Tianjin Shi"
      }
    },
    {
      "geometry": {
        "type": "Point",
        "coordinates": [
          131.5,
          33.25
        ]
      },
      "type": "Feature",
      "properties": {
        "hierarchy": [
          "tgn:1000961",
          "tgn:1000004",
          "tgn:7000901",
          "tgn:1000120",
          "tgn:7029392"
        ],
        "placetype": [
          "aat:300387145",
          "aat:300235099"
        ],
        "id": 1000961,
        "name:xx": "Ōita"
      }
    },
    {
      "geometry": {
        "type": "Point",
        "coordinates": [
          135.5,
          34.5
        ]
      },
      "type": "Feature",
      "properties": {
        "hierarchy": [
          "tgn:1000962",
          "tgn:1000004",
          "tgn:7000896",
          "tgn:1000120",
          "tgn:7029392"
        ],
        "placetype": [
          "aat:300387145",
          "aat:300387094"
        ],
        "id": 1000962,
        "name:xx": "Ōsaka"
      }
    },
    {
      "geometry": {
        "type": "Point",
        "coordinates": [
          20.6667,
          8.4167
        ]
      },
      "type": "Feature",
      "properties": {
        "hierarchy": [
          "tgn:1000964",
          "tgn:7001242",
          "tgn:1000155",
          "tgn:7029392"
        ],
        "placetype": [
          "aat:300387064",
          "aat:300235099"
        ],
        "id": 1000964,
        "name:xx": "Bamingui-Bangoran"
      }
    },
    {
      "geometry": {
        "type": "Point",
        "coordinates": [
          21.5,
          5
        ]
      },
      "type": "Feature",
      "properties": {
        "hierarchy": [
          "tgn:1000965",
          "tgn:7001242",
          "tgn:1000155",
          "tgn:7029392"
        ],
        "placetype": [
          "aat:300387064",
          "aat:300235099"
        ],
        "id": 1000965,
        "name:xx": "Basse-Kotto"
      }
    },
    {
      "geometry": {
        "type": "Point",
        "coordinates": [
          19.0833,
          14.0833
        ]
      },
      "type": "Feature",
      "properties": {
        "hierarchy": [
          "tgn:1000966",
          "tgn:7001242",
          "tgn:1000156",
          "tgn:7029392"
        ],
        "placetype": [
          "aat:300387064",
          "aat:300235099"
        ],
        "id": 1000966,
        "name:xx": "Batha"
      }
    },
    {
      "geometry": {
        "type": "Point",
        "coordinates": [
          21,
          15
        ]
      },
      "type": "Feature",
      "properties": {
        "hierarchy": [
          "tgn:1000967",
          "tgn:7001242",
          "tgn:1000156",
          "tgn:7029392"
        ],
        "placetype": [
          "aat:300387064",
          "aat:300235099"
        ],
        "id": 1000967,
        "name:xx": "Biltine"
      }
    },
    {
      "geometry": {
        "type": "Point",
        "coordinates": [
          19,
          18.3333
        ]
      },
      "type": "Feature",
      "properties": {
        "hierarchy": [
          "tgn:1000968",
          "tgn:7001242",
          "tgn:1000156",
          "tgn:7029392"
        ],
        "placetype": [
          "aat:300387064",
          "aat:300235099"
        ],
        "id": 1000968,
        "name:xx": "Bourkou-Ennedi-Tibesti"
      }
    },
    {
      "geometry": {
        "type": "Point",
        "coordinates": [
          13.75,
          4
        ]
      },
      "type": "Feature",
      "properties": {
        "hierarchy": [
          "tgn:1000969",
          "tgn:7001242",
          "tgn:1000158",
          "tgn:7029392"
        ],
        "placetype": [
          "aat:300387064",
          "aat:300000774"
        ],
        "id": 1000969,
        "name:xx": "Bouenza"
      }
    }
  ]
}
