{
  "type": "FeatureCollection",
  "features": [
    {
      "geometry": {
        "type": "Point",
        "coordinates": [
          6,
          49.977
        ]
      },
      "type": "Feature",
      "properties": {
        "hierarchy": [
          "tgn:7003531",
          "tgn:1000003",
          "tgn:7003514",
          "tgn:7029392"
        ],
        "placetype": [
          "aat:300387064",
          "aat:300387081"
        ],
        "id": 7003531,
        "name:xx": "Diekirch"
      }
    },
    {
      "geometry": {
        "type": "Point",
        "coordinates": [
          8.5,
          40.3
        ]
      },
      "type": "Feature",
      "properties": {
        "hierarchy": [
          "tgn:7003532",
          "tgn:1001724",
          "tgn:1000003",
          "tgn:7003121",
          "tgn:1000080",
          "tgn:7029392"
        ],
        "placetype": [
          "aat:300008347"
        ],
        "id": 7003532,
        "name:xx": "Bosa"
      }
    },
    {
      "geometry": {
        "type": "Point",
        "coordinates": [
          6.35,
          49.677
        ]
      },
      "type": "Feature",
      "properties": {
        "hierarchy": [
          "tgn:7003533",
          "tgn:1000003",
          "tgn:7003514",
          "tgn:7029392"
        ],
        "placetype": [
          "aat:300387064",
          "aat:300387081"
        ],
        "id": 7003533,
        "name:xx": "Grevenmacher"
      }
    },
    {
      "geometry": {
        "type": "Point",
        "coordinates": [
          6.09,
          49.627
        ]
      },
      "type": "Feature",
      "properties": {
        "hierarchy": [
          "tgn:7003534",
          "tgn:1000003",
          "tgn:7003514",
          "tgn:7029392"
        ],
        "placetype": [
          "aat:300387064",
          "aat:300387081"
        ],
        "id": 7003534,
        "name:xx": "Luxembourg"
      }
    },
    {
      "geometry": {
        "type": "Point",
        "coordinates": [
          9.2667,
          57
        ]
      },
      "type": "Feature",
      "properties": {
        "hierarchy": [
          "tgn:7003535",
          "tgn:7594007",
          "tgn:1000003",
          "tgn:1000066",
          "tgn:7029392"
        ],
        "placetype": [
          "aat:300008347",
          "aat:300006888",
          "aat:300008375"
        ],
        "name:en": "Aggersborg",
        "id": 7003535,
        "name:da": "Aggersborg"
      }
    },
    {
      "geometry": {
        "type": "Point",
        "coordinates": [
          9.9333,
          57.05
        ]
      },
      "type": "Feature",
      "properties": {
        "hierarchy": [
          "tgn:7003536",
          "tgn:7594007",
          "tgn:1000003",
          "tgn:1000066",
          "tgn:7029392"
        ],
        "placetype": [
          "aat:300008347",
          "aat:300008416",
          "aat:300008389",
          "aat:300387308",
          "aat:300005135",
          "aat:300387512",
          "aat:300387235",
          "aat:300387288",
          "aat:300387296"
        ],
        "name:en": "Ålborg",
        "id": 7003536,
        "name:da": "Ålborg"
      }
    },
    {
      "geometry": {
        "type": "Point",
        "coordinates": [
          9.5333,
          56.8167
        ]
      },
      "type": "Feature",
      "properties": {
        "hierarchy": [
          "tgn:7003539",
          "tgn:7594007",
          "tgn:1000003",
          "tgn:1000066",
          "tgn:7029392"
        ],
        "placetype": [
          "aat:300008347"
        ],
        "id": 7003539,
        "name:xx": "Års"
      }
    }
  ]
}
