{
  "geometry": {
    "type": "Point",
    "coordinates": [
      13.9667,
      -21.7833
    ]
  },
  "type": "Feature",
  "properties": {
    "hierarchy": [
      "tgn:1010860",
      "tgn:7001242",
      "tgn:7030583",
      "tgn:1000198",
      "tgn:7029392"
    ],
    "placetype": [
      "aat:300008850"
    ],
    "id": 1010860,
    "name:xx": "Cross, Cape"
  }
}
