{
  "geometry": {
    "type": "Point",
    "coordinates": [
      79.9903,
      27.0731
    ]
  },
  "type": "Feature",
  "properties": {
    "hierarchy": [
      "tgn:7559591",
      "tgn:1000004",
      "tgn:7000198",
      "tgn:7016722",
      "tgn:7029392"
    ],
    "placetype": [
      "aat:300008347"
    ],
    "name:en": "Mohānandi Purwa",
    "id": 7559591
  }
}
