{
  "type": "FeatureCollection",
  "features": [
    {
      "geometry": {
        "type": "Point",
        "coordinates": [
          -104.316667,
          20.766667
        ]
      },
      "type": "Feature",
      "properties": {
        "hierarchy": [
          "tgn:7349380",
          "tgn:1000001",
          "tgn:1001906",
          "tgn:7005560",
          "tgn:7029392"
        ],
        "placetype": [
          "aat:300008347"
        ],
        "id": 7349380,
        "name:xx": "Agua Escondida"
      }
    },
    {
      "geometry": {
        "type": "Point",
        "coordinates": [
          -103.083333,
          20.5
        ]
      },
      "type": "Feature",
      "properties": {
        "hierarchy": [
          "tgn:7349381",
          "tgn:7005586",
          "tgn:1000001",
          "tgn:7005560",
          "tgn:7029392"
        ],
        "placetype": [
          "aat:300008347"
        ],
        "id": 7349381,
        "name:xx": "Agua Escondida"
      }
    },
    {
      "geometry": {
        "type": "Point",
        "coordinates": [
          -96.6,
          18.866667
        ]
      },
      "type": "Feature",
      "properties": {
        "hierarchy": [
          "tgn:7349383",
          "tgn:1000001",
          "tgn:7005599",
          "tgn:7005560",
          "tgn:7029392"
        ],
        "placetype": [
          "aat:300008347"
        ],
        "id": 7349383,
        "name:xx": "Agua Escondida"
      }
    },
    {
      "geometry": {
        "type": "Point",
        "coordinates": [
          -94.816667,
          16.633333
        ]
      },
      "type": "Feature",
      "properties": {
        "hierarchy": [
          "tgn:7349384",
          "tgn:1000001",
          "tgn:7005591",
          "tgn:7005560",
          "tgn:7029392"
        ],
        "placetype": [
          "aat:300008347"
        ],
        "id": 7349384,
        "name:xx": "Agua Escondida"
      }
    },
    {
      "geometry": {
        "type": "Point",
        "coordinates": [
          -91.483333,
          16.616667
        ]
      },
      "type": "Feature",
      "properties": {
        "hierarchy": [
          "tgn:7349385",
          "tgn:7005580",
          "tgn:1000001",
          "tgn:7005560",
          "tgn:7029392"
        ],
        "placetype": [
          "aat:300008347"
        ],
        "id": 7349385,
        "name:xx": "Agua Escondida"
      }
    },
    {
      "geometry": {
        "type": "Point",
        "coordinates": [
          -92.283333,
          15.333333
        ]
      },
      "type": "Feature",
      "properties": {
        "hierarchy": [
          "tgn:7349386",
          "tgn:7005580",
          "tgn:1000001",
          "tgn:7005560",
          "tgn:7029392"
        ],
        "placetype": [
          "aat:300008347"
        ],
        "id": 7349386,
        "name:xx": "Agua Escondida"
      }
    },
    {
      "geometry": {
        "type": "Point",
        "coordinates": [
          -107.8,
          28.35
        ]
      },
      "type": "Feature",
      "properties": {
        "hierarchy": [
          "tgn:7349387",
          "tgn:7005581",
          "tgn:1000001",
          "tgn:7005560",
          "tgn:7029392"
        ],
        "placetype": [
          "aat:300387007"
        ],
        "id": 7349387,
        "name:xx": "Agua Escondida"
      }
    },
    {
      "geometry": {
        "type": "Point",
        "coordinates": [
          -110.233333,
          28.4
        ]
      },
      "type": "Feature",
      "properties": {
        "hierarchy": [
          "tgn:7349388",
          "tgn:1000001",
          "tgn:1001960",
          "tgn:7005560",
          "tgn:7029392"
        ],
        "placetype": [
          "aat:300000241"
        ],
        "id": 7349388,
        "name:xx": "Rancho Agua Ería"
      }
    },
    {
      "geometry": {
        "type": "Point",
        "coordinates": [
          -108.716667,
          25.85
        ]
      },
      "type": "Feature",
      "properties": {
        "hierarchy": [
          "tgn:7349389",
          "tgn:1000001",
          "tgn:7005595",
          "tgn:7005560",
          "tgn:7029392"
        ],
        "placetype": [
          "aat:300008347"
        ],
        "id": 7349389,
        "name:xx": "Aguaelarena"
      }
    }
  ]
}
