{
  "geometry": {
    "type": "Point",
    "coordinates": [
      -108.8667,
      39.0667
    ]
  },
  "type": "Feature",
  "properties": {
    "hierarchy": [
      "tgn:2441225",
      "tgn:1000001",
      "tgn:7012149",
      "tgn:2000230",
      "tgn:7007158",
      "tgn:7029392"
    ],
    "placetype": [
      "aat:300008761"
    ],
    "id": 2441225,
    "name:xx": "Knowles Canyon"
  }
}
