{
  "geometry": {
    "type": "Point",
    "coordinates": [
      -86.2167,
      38.8167
    ]
  },
  "type": "Feature",
  "properties": {
    "hierarchy": [
      "tgn:2362463",
      "tgn:1000001",
      "tgn:7012149",
      "tgn:1002508",
      "tgn:7007252",
      "tgn:7029392"
    ],
    "placetype": [
      "aat:300008706"
    ],
    "id": 2362463,
    "name:xx": "Greasy Creek"
  }
}
