{
  "geometry": {
    "type": "Point",
    "coordinates": [
      -79.2667,
      36.65
    ]
  },
  "type": "Feature",
  "properties": {
    "hierarchy": [
      "tgn:2293298",
      "tgn:1000001",
      "tgn:7012149",
      "tgn:7007919",
      "tgn:7029392"
    ],
    "placetype": [
      "aat:300008706"
    ],
    "id": 2293298,
    "name:xx": "Double Creek"
  }
}
