{
  "geometry": {
    "type": "Point",
    "coordinates": [
      -75.25,
      39.9667
    ]
  },
  "type": "Feature",
  "properties": {
    "hierarchy": [
      "tgn:2410947",
      "tgn:1000001",
      "tgn:7012149",
      "tgn:1002782",
      "tgn:7007710",
      "tgn:7029392"
    ],
    "placetype": [
      "aat:300008706"
    ],
    "id": 2410947,
    "name:xx": "Indian Creek"
  }
}
