{
  "type": "FeatureCollection",
  "features": [
    {
      "geometry": {
        "type": "Point",
        "coordinates": [
          -84.6167,
          34.05
        ]
      },
      "type": "Feature",
      "properties": {
        "hierarchy": [
          "tgn:2711430",
          "tgn:1000001",
          "tgn:7012149",
          "tgn:7007248",
          "tgn:7029392"
        ],
        "placetype": [
          "aat:300008706"
        ],
        "id": 2711430,
        "name:xx": "Tanyard Creek"
      }
    },
    {
      "geometry": {
        "type": "Point",
        "coordinates": [
          -92.4,
          31.9833
        ]
      },
      "type": "Feature",
      "properties": {
        "hierarchy": [
          "tgn:2711431",
          "tgn:1000001",
          "tgn:7012149",
          "tgn:2000917",
          "tgn:7007256",
          "tgn:7029392"
        ],
        "placetype": [
          "aat:300008706"
        ],
        "id": 2711431,
        "name:xx": "Tanyard Creek"
      }
    },
    {
      "geometry": {
        "type": "Point",
        "coordinates": [
          -93.25,
          32.4167
        ]
      },
      "type": "Feature",
      "properties": {
        "hierarchy": [
          "tgn:2711432",
          "tgn:1000001",
          "tgn:7012149",
          "tgn:2000913",
          "tgn:7007256",
          "tgn:7029392"
        ],
        "placetype": [
          "aat:300008706"
        ],
        "id": 2711432,
        "name:xx": "Tanyard Creek"
      }
    },
    {
      "geometry": {
        "type": "Point",
        "coordinates": [
          -90.7833,
          31.2333
        ]
      },
      "type": "Feature",
      "properties": {
        "hierarchy": [
          "tgn:2711433",
          "tgn:2001088",
          "tgn:1000001",
          "tgn:7012149",
          "tgn:7007522",
          "tgn:7029392"
        ],
        "placetype": [
          "aat:300008706"
        ],
        "id": 2711433,
        "name:xx": "Tanyard Creek"
      }
    },
    {
      "geometry": {
        "type": "Point",
        "coordinates": [
          -89.9333,
          31.8167
        ]
      },
      "type": "Feature",
      "properties": {
        "hierarchy": [
          "tgn:2711434",
          "tgn:1000001",
          "tgn:7012149",
          "tgn:2001149",
          "tgn:7007522",
          "tgn:7029392"
        ],
        "placetype": [
          "aat:300008706"
        ],
        "id": 2711434,
        "name:xx": "Tanyard Creek"
      }
    },
    {
      "geometry": {
        "type": "Point",
        "coordinates": [
          -92.7167,
          39.1333
        ]
      },
      "type": "Feature",
      "properties": {
        "hierarchy": [
          "tgn:2711435",
          "tgn:1000001",
          "tgn:7012149",
          "tgn:2001205",
          "tgn:7007523",
          "tgn:7029392"
        ],
        "placetype": [
          "aat:300008706"
        ],
        "id": 2711435,
        "name:xx": "Tanyard Creek"
      }
    },
    {
      "geometry": {
        "type": "Point",
        "coordinates": [
          -80.4333,
          35.8
        ]
      },
      "type": "Feature",
      "properties": {
        "hierarchy": [
          "tgn:2711437",
          "tgn:1000001",
          "tgn:7012149",
          "tgn:7007709",
          "tgn:7029392"
        ],
        "placetype": [
          "aat:300008706"
        ],
        "id": 2711437,
        "name:xx": "Tanyard Creek"
      }
    },
    {
      "geometry": {
        "type": "Point",
        "coordinates": [
          -81.3667,
          35.5333
        ]
      },
      "type": "Feature",
      "properties": {
        "hierarchy": [
          "tgn:2711438",
          "tgn:1000001",
          "tgn:7012149",
          "tgn:2001513",
          "tgn:7007709",
          "tgn:7029392"
        ],
        "placetype": [
          "aat:300008706"
        ],
        "id": 2711438,
        "name:xx": "Tanyard Creek"
      }
    },
    {
      "geometry": {
        "type": "Point",
        "coordinates": [
          -95.7167,
          34.1667
        ]
      },
      "type": "Feature",
      "properties": {
        "hierarchy": [
          "tgn:2711439",
          "tgn:1000001",
          "tgn:7012149",
          "tgn:7007707",
          "tgn:7029392"
        ],
        "placetype": [
          "aat:300008706"
        ],
        "id": 2711439,
        "name:xx": "Tanyard Creek"
      }
    }
  ]
}
