{
  "geometry": {
    "type": "Point",
    "coordinates": [
      -81.95,
      26.4667
    ]
  },
  "type": "Feature",
  "properties": {
    "hierarchy": [
      "tgn:2574316",
      "tgn:1000001",
      "tgn:7012149",
      "tgn:1002582",
      "tgn:7007240",
      "tgn:7029392"
    ],
    "placetype": [
      "aat:300132316"
    ],
    "id": 2574316,
    "name:xx": "Pelican Bay"
  }
}
