{
  "geometry": {
    "type": "Point",
    "coordinates": [
      121.9833,
      43.4167
    ]
  },
  "type": "Feature",
  "properties": {
    "hierarchy": [
      "tgn:1073740",
      "tgn:1000004",
      "tgn:7001838",
      "tgn:1000111",
      "tgn:7029392"
    ],
    "placetype": [
      "aat:300008347"
    ],
    "id": 1073740,
    "name:xx": "Yuliangpu"
  }
}
