{
  "geometry": {
    "type": "Point",
    "coordinates": [
      -95.9833,
      30.4167
    ]
  },
  "type": "Feature",
  "properties": {
    "hierarchy": [
      "tgn:2686673",
      "tgn:1000001",
      "tgn:7012149",
      "tgn:1002429",
      "tgn:7007826",
      "tgn:7029392"
    ],
    "placetype": [
      "aat:300008706"
    ],
    "id": 2686673,
    "name:xx": "Spring Creek"
  }
}
