{
  "type": "FeatureCollection",
  "features": [
    {
      "geometry": {
        "type": "Point",
        "coordinates": [
          11.483333,
          47.6
        ]
      },
      "type": "Feature",
      "properties": {
        "hierarchy": [
          "tgn:7160150",
          "tgn:7003669",
          "tgn:1000003",
          "tgn:7000084",
          "tgn:7029392"
        ],
        "placetype": [
          "aat:300008347"
        ],
        "id": 7160150,
        "name:xx": "Höfen"
      }
    },
    {
      "geometry": {
        "type": "Point",
        "coordinates": [
          10.016667,
          47.533333
        ]
      },
      "type": "Feature",
      "properties": {
        "hierarchy": [
          "tgn:7160151",
          "tgn:7003669",
          "tgn:1000003",
          "tgn:7000084",
          "tgn:7029392"
        ],
        "placetype": [
          "aat:300008347"
        ],
        "id": 7160151,
        "name:xx": "Höfen"
      }
    },
    {
      "geometry": {
        "type": "Point",
        "coordinates": [
          10.3,
          47.5
        ]
      },
      "type": "Feature",
      "properties": {
        "hierarchy": [
          "tgn:7160152",
          "tgn:7003669",
          "tgn:1000003",
          "tgn:7000084",
          "tgn:7029392"
        ],
        "placetype": [
          "aat:300008347"
        ],
        "id": 7160152,
        "name:xx": "Hofen"
      }
    },
    {
      "geometry": {
        "type": "Point",
        "coordinates": [
          10.3,
          54.15
        ]
      },
      "type": "Feature",
      "properties": {
        "hierarchy": [
          "tgn:7160153",
          "tgn:1000003",
          "tgn:7003688",
          "tgn:7000084",
          "tgn:7029392"
        ],
        "placetype": [
          "aat:300000206"
        ],
        "id": 7160153,
        "name:xx": "Höfen"
      }
    },
    {
      "geometry": {
        "type": "Point",
        "coordinates": [
          8.75,
          52.35
        ]
      },
      "type": "Feature",
      "properties": {
        "hierarchy": [
          "tgn:7160154",
          "tgn:1000003",
          "tgn:7003677",
          "tgn:7000084",
          "tgn:7029392"
        ],
        "placetype": [
          "aat:300000206"
        ],
        "id": 7160154,
        "name:xx": "Höfen"
      }
    },
    {
      "geometry": {
        "type": "Point",
        "coordinates": [
          7.3,
          50.733333
        ]
      },
      "type": "Feature",
      "properties": {
        "hierarchy": [
          "tgn:7160155",
          "tgn:1000003",
          "tgn:7003677",
          "tgn:7000084",
          "tgn:7029392"
        ],
        "placetype": [
          "aat:300000206"
        ],
        "id": 7160155,
        "name:xx": "Hofen"
      }
    },
    {
      "geometry": {
        "type": "Point",
        "coordinates": [
          7.4,
          50.683333
        ]
      },
      "type": "Feature",
      "properties": {
        "hierarchy": [
          "tgn:7160156",
          "tgn:1000003",
          "tgn:7003682",
          "tgn:7000084",
          "tgn:7029392"
        ],
        "placetype": [
          "aat:300000206"
        ],
        "id": 7160156,
        "name:xx": "Hofen"
      }
    },
    {
      "geometry": {
        "type": "Point",
        "coordinates": [
          12.7,
          49.1
        ]
      },
      "type": "Feature",
      "properties": {
        "hierarchy": [
          "tgn:7160157",
          "tgn:7003669",
          "tgn:1000003",
          "tgn:7000084",
          "tgn:7029392"
        ],
        "placetype": [
          "aat:300000206"
        ],
        "id": 7160157,
        "name:xx": "Hofen"
      }
    },
    {
      "geometry": {
        "type": "Point",
        "coordinates": [
          12.883333,
          49.05
        ]
      },
      "type": "Feature",
      "properties": {
        "hierarchy": [
          "tgn:7160158",
          "tgn:7003669",
          "tgn:1000003",
          "tgn:7000084",
          "tgn:7029392"
        ],
        "placetype": [
          "aat:300000206"
        ],
        "id": 7160158,
        "name:xx": "Höfen"
      }
    },
    {
      "geometry": {
        "type": "Point",
        "coordinates": [
          12.833333,
          48.616667
        ]
      },
      "type": "Feature",
      "properties": {
        "hierarchy": [
          "tgn:7160159",
          "tgn:7003669",
          "tgn:1000003",
          "tgn:7000084",
          "tgn:7029392"
        ],
        "placetype": [
          "aat:300000206"
        ],
        "id": 7160159,
        "name:xx": "Höfen"
      }
    }
  ]
}
