{
  "geometry": {
    "type": "Point",
    "coordinates": [
      -75.05,
      41.3833
    ]
  },
  "type": "Feature",
  "properties": {
    "hierarchy": [
      "tgn:2672238",
      "tgn:1000001",
      "tgn:7012149",
      "tgn:1002789",
      "tgn:7007710",
      "tgn:7029392"
    ],
    "placetype": [
      "aat:300008905"
    ],
    "id": 2672238,
    "name:xx": "Smiths Swamp"
  }
}
