{
  "geometry": {
    "type": "Point",
    "coordinates": [
      -75.9333,
      41.1833
    ]
  },
  "type": "Feature",
  "properties": {
    "hierarchy": [
      "tgn:2751946",
      "tgn:1000001",
      "tgn:7012149",
      "tgn:1002612",
      "tgn:7007710",
      "tgn:7029392"
    ],
    "placetype": [
      "aat:300008706"
    ],
    "id": 2751946,
    "name:xx": "Warrior Creek"
  }
}
