{
  "geometry": {
    "type": "Point",
    "coordinates": [
      75.622421,
      25.558913
    ]
  },
  "type": "Feature",
  "properties": {
    "hierarchy": [
      "tgn:7569637",
      "tgn:1000004",
      "tgn:7000198",
      "tgn:7016788",
      "tgn:7029392"
    ],
    "placetype": [
      "aat:300008347"
    ],
    "name:en": "Mūndghasa",
    "id": 7569637
  }
}
