{
  "geometry": {
    "type": "Point",
    "coordinates": [
      -83.2833,
      43.0667
    ]
  },
  "type": "Feature",
  "properties": {
    "hierarchy": [
      "tgn:2628425",
      "tgn:1000001",
      "tgn:7012149",
      "tgn:1002576",
      "tgn:7007520",
      "tgn:7029392"
    ],
    "placetype": [
      "aat:300006075"
    ],
    "id": 2628425,
    "name:xx": "Rood Lake Drain"
  }
}
