{
  "geometry": {
    "type": "Point",
    "coordinates": [
      -117.75,
      39.3333
    ]
  },
  "type": "Feature",
  "properties": {
    "hierarchy": [
      "tgn:2590592",
      "tgn:1000001",
      "tgn:2001415",
      "tgn:7012149",
      "tgn:7007526",
      "tgn:7029392"
    ],
    "placetype": [
      "aat:300008706"
    ],
    "id": 2590592,
    "name:xx": "Pole Creek"
  }
}
