{
  "geometry": {
    "type": "Point",
    "coordinates": [
      -111.6167,
      45.35
    ]
  },
  "type": "Feature",
  "properties": {
    "hierarchy": [
      "tgn:2370366",
      "tgn:1000001",
      "tgn:7012149",
      "tgn:2001288",
      "tgn:7007524",
      "tgn:7029392"
    ],
    "placetype": [
      "aat:300006075"
    ],
    "id": 2370366,
    "name:xx": "H Lazy Ditch"
  }
}
