{
  "type": "FeatureCollection",
  "features": [
    {
      "geometry": {
        "type": "Point",
        "coordinates": [
          7.95,
          43.9
        ]
      },
      "type": "Feature",
      "properties": {
        "hierarchy": [
          "tgn:4003322",
          "tgn:1000003",
          "tgn:7003141",
          "tgn:7003236",
          "tgn:1000080",
          "tgn:7029392"
        ],
        "placetype": [
          "aat:300008347"
        ],
        "id": 4003322,
        "name:xx": "Dolcedo"
      }
    },
    {
      "geometry": {
        "type": "Point",
        "coordinates": [
          19.2333,
          48.6833
        ]
      },
      "type": "Feature",
      "properties": {
        "hierarchy": [
          "tgn:4003325",
          "tgn:7027131",
          "tgn:1000003",
          "tgn:7011765",
          "tgn:7029392"
        ],
        "placetype": [
          "aat:300008347"
        ],
        "id": 4003325,
        "name:xx": "Dolná Mičiná"
      }
    }
  ]
}
