{
  "geometry": {
    "type": "Point",
    "coordinates": [
      -122.4167,
      48.3333
    ]
  },
  "type": "Feature",
  "properties": {
    "hierarchy": [
      "tgn:2372841",
      "tgn:1000001",
      "tgn:7012149",
      "tgn:7014510",
      "tgn:7007920",
      "tgn:7029392"
    ],
    "placetype": [
      "aat:300008699"
    ],
    "id": 2372841,
    "name:xx": "Hall Slough"
  }
}
