{
  "geometry": {
    "type": "Point",
    "coordinates": [
      78.2667,
      45.4167
    ]
  },
  "type": "Feature",
  "properties": {
    "hierarchy": [
      "tgn:1057207",
      "tgn:1000004",
      "tgn:1003416",
      "tgn:7014786",
      "tgn:7029392"
    ],
    "placetype": [
      "aat:300008347"
    ],
    "id": 1057207,
    "name:xx": "Mulaly"
  }
}
