{
  "geometry": {
    "type": "Point",
    "coordinates": [
      -98.35,
      27.3833
    ]
  },
  "type": "Feature",
  "properties": {
    "hierarchy": [
      "tgn:7021614",
      "tgn:1000001",
      "tgn:7012149",
      "tgn:2001977",
      "tgn:7007826",
      "tgn:7029392"
    ],
    "placetype": [
      "aat:300008347"
    ],
    "id": 7021614,
    "name:xx": "Concepcion"
  }
}
