{
  "geometry": {
    "type": "Point",
    "coordinates": [
      -120.8167,
      38.4333
    ]
  },
  "type": "Feature",
  "properties": {
    "hierarchy": [
      "tgn:2673003",
      "tgn:1002146",
      "tgn:1000001",
      "tgn:7012149",
      "tgn:7007157",
      "tgn:7029392"
    ],
    "placetype": [
      "aat:300008761"
    ],
    "id": 2673003,
    "name:xx": "Snake Gulch"
  }
}
