{
  "geometry": {
    "type": "Point",
    "coordinates": [
      40.3333,
      -1.0667
    ]
  },
  "type": "Feature",
  "properties": {
    "hierarchy": [
      "tgn:1090449",
      "tgn:7001242",
      "tgn:7593763",
      "tgn:1000169",
      "tgn:7029392"
    ],
    "placetype": [
      "aat:300008347"
    ],
    "id": 1090449,
    "name:xx": "Higlet"
  }
}
