{
  "geometry": {
    "type": "Point",
    "coordinates": [
      -91.8667,
      30.2333
    ]
  },
  "type": "Feature",
  "properties": {
    "hierarchy": [
      "tgn:2043906",
      "tgn:1000001",
      "tgn:7012149",
      "tgn:2000903",
      "tgn:7007256",
      "tgn:7029392"
    ],
    "placetype": [
      "aat:300008347",
      "aat:300387210"
    ],
    "id": 2043906,
    "name:xx": "Ruth"
  }
}
