{
  "type": "FeatureCollection",
  "features": [
    {
      "geometry": {
        "type": "Point",
        "coordinates": [
          -75.3,
          -50
        ]
      },
      "type": "Feature",
      "properties": {
        "hierarchy": [
          "tgn:7281230",
          "tgn:1001702",
          "tgn:1000049",
          "tgn:1000002",
          "tgn:7029392"
        ],
        "placetype": [
          "aat:300008791"
        ],
        "id": 7281230,
        "name:xx": "Seymour, Islas"
      }
    },
    {
      "geometry": {
        "type": "Point",
        "coordinates": [
          -74.55,
          -48.933333
        ]
      },
      "type": "Feature",
      "properties": {
        "hierarchy": [
          "tgn:7281231",
          "tgn:1001702",
          "tgn:1000049",
          "tgn:1000002",
          "tgn:7029392"
        ],
        "placetype": [
          "aat:300008676"
        ],
        "id": 7281231,
        "name:xx": "Seymour, Fiordo"
      }
    },
    {
      "geometry": {
        "type": "Point",
        "coordinates": [
          -69.783333,
          -54.316667
        ]
      },
      "type": "Feature",
      "properties": {
        "hierarchy": [
          "tgn:7281232",
          "tgn:1001702",
          "tgn:1000049",
          "tgn:1000002",
          "tgn:7029392"
        ],
        "placetype": [
          "aat:300008795"
        ],
        "id": 7281232,
        "name:xx": "Seymour, Cerro"
      }
    },
    {
      "geometry": {
        "type": "Point",
        "coordinates": [
          -67.033333,
          -55.45
        ]
      },
      "type": "Feature",
      "properties": {
        "hierarchy": [
          "tgn:7281234",
          "tgn:1001702",
          "tgn:1000049",
          "tgn:1000002",
          "tgn:7029392"
        ],
        "placetype": [
          "aat:300008791"
        ],
        "id": 7281234,
        "name:xx": "Sesambre, Isla"
      }
    },
    {
      "geometry": {
        "type": "Point",
        "coordinates": [
          -75.566667,
          -48.183333
        ]
      },
      "type": "Feature",
      "properties": {
        "hierarchy": [
          "tgn:7281235",
          "tgn:1001623",
          "tgn:1000049",
          "tgn:1000002",
          "tgn:7029392"
        ],
        "placetype": [
          "aat:300386846"
        ],
        "id": 7281235,
        "name:xx": "Serrucho, Punta"
      }
    },
    {
      "geometry": {
        "type": "Point",
        "coordinates": [
          -72.166667,
          -52.783333
        ]
      },
      "type": "Feature",
      "properties": {
        "hierarchy": [
          "tgn:7281236",
          "tgn:1001702",
          "tgn:1000049",
          "tgn:1000002",
          "tgn:7029392"
        ],
        "placetype": [
          "aat:300008795"
        ],
        "id": 7281236,
        "name:xx": "Serrucho, Cordillera"
      }
    },
    {
      "geometry": {
        "type": "Point",
        "coordinates": [
          -73.466667,
          -47.2
        ]
      },
      "type": "Feature",
      "properties": {
        "hierarchy": [
          "tgn:7281237",
          "tgn:1001623",
          "tgn:1000049",
          "tgn:1000002",
          "tgn:7029392"
        ],
        "placetype": [
          "aat:300387002"
        ],
        "id": 7281237,
        "name:xx": "Serrucho, Cerro"
      }
    },
    {
      "geometry": {
        "type": "Point",
        "coordinates": [
          -75.533333,
          -48.166667
        ]
      },
      "type": "Feature",
      "properties": {
        "hierarchy": [
          "tgn:7281238",
          "tgn:1001623",
          "tgn:1000049",
          "tgn:1000002",
          "tgn:7029392"
        ],
        "placetype": [
          "aat:300008795"
        ],
        "id": 7281238,
        "name:xx": "Serrucho, Monte"
      }
    },
    {
      "geometry": {
        "type": "Point",
        "coordinates": [
          -70.283333,
          -54.533333
        ]
      },
      "type": "Feature",
      "properties": {
        "hierarchy": [
          "tgn:7281239",
          "tgn:1001702",
          "tgn:1000049",
          "tgn:1000002",
          "tgn:7029392"
        ],
        "placetype": [
          "aat:300008676"
        ],
        "id": 7281239,
        "name:xx": "Serrano, Seno"
      }
    }
  ]
}
