{
  "geometry": {
    "type": "Point",
    "coordinates": [
      -108.1667,
      47.6333
    ]
  },
  "type": "Feature",
  "properties": {
    "hierarchy": [
      "tgn:2771560",
      "tgn:1000001",
      "tgn:7012149",
      "tgn:2001295",
      "tgn:7007524",
      "tgn:7029392"
    ],
    "placetype": [
      "aat:300006191"
    ],
    "id": 2771560,
    "name:xx": "Wildlife Reservoir"
  }
}
