{
  "geometry": {
    "type": "Point",
    "coordinates": [
      108.95,
      0.95
    ]
  },
  "type": "Feature",
  "properties": {
    "hierarchy": [
      "tgn:1078589",
      "tgn:1000004",
      "tgn:1001336",
      "tgn:1000116",
      "tgn:7029392"
    ],
    "placetype": [
      "aat:300008347"
    ],
    "id": 1078589,
    "name:xx": "Singkawang"
  }
}
