{
  "geometry": {
    "type": "Point",
    "coordinates": [
      88.466,
      22.516
    ]
  },
  "type": "Feature",
  "properties": {
    "hierarchy": [
      "tgn:1074524",
      "tgn:1000004",
      "tgn:7000198",
      "tgn:1001977",
      "tgn:7029392"
    ],
    "placetype": [
      "aat:300008347"
    ],
    "name:en": "Bāmanghata",
    "id": 1074524
  }
}
