{
  "geometry": {
    "type": "Point",
    "coordinates": [
      -62.8667,
      46.3667
    ]
  },
  "type": "Feature",
  "properties": {
    "hierarchy": [
      "tgn:1015251",
      "tgn:7005685",
      "tgn:1000001",
      "tgn:7005803",
      "tgn:7029392"
    ],
    "placetype": [
      "aat:300008347"
    ],
    "id": 1015251,
    "name:xx": "Mount Stewart"
  }
}
