{
  "geometry": {
    "type": "Point",
    "coordinates": [
      126.7167,
      37.5333
    ]
  },
  "type": "Feature",
  "properties": {
    "hierarchy": [
      "tgn:1082339",
      "tgn:7001322",
      "tgn:1000004",
      "tgn:7000299",
      "tgn:7029392"
    ],
    "placetype": [
      "aat:300008347"
    ],
    "id": 1082339,
    "name:xx": "Pup'yŏng"
  }
}
