{
  "geometry": {
    "type": "Point",
    "coordinates": [
      -112.6167,
      40.45
    ]
  },
  "type": "Feature",
  "properties": {
    "hierarchy": [
      "tgn:2298126",
      "tgn:1000001",
      "tgn:7012149",
      "tgn:2002123",
      "tgn:7007827",
      "tgn:7029392"
    ],
    "placetype": [
      "aat:300008699"
    ],
    "id": 2298126,
    "name:xx": "Dry Lake Fork"
  }
}
