{
  "geometry": {
    "type": "Point",
    "coordinates": [
      -93.1667,
      40.8333
    ]
  },
  "type": "Feature",
  "properties": {
    "hierarchy": [
      "tgn:2269243",
      "tgn:1000001",
      "tgn:7012149",
      "tgn:2000653",
      "tgn:7007253",
      "tgn:7029392"
    ],
    "placetype": [
      "aat:300008706"
    ],
    "id": 2269243,
    "name:xx": "Crow Creek"
  }
}
