{
  "geometry": {
    "type": "Point",
    "coordinates": [
      -81.6667,
      30.05
    ]
  },
  "type": "Feature",
  "properties": {
    "hierarchy": [
      "tgn:2539701",
      "tgn:1000001",
      "tgn:7012149",
      "tgn:2000283",
      "tgn:7007240",
      "tgn:7029392"
    ],
    "placetype": [
      "aat:300008850"
    ],
    "id": 2539701,
    "name:xx": "New Switzerland Point"
  }
}
