{
  "geometry": {
    "type": "Point",
    "coordinates": [
      73.726905,
      25.662714
    ]
  },
  "type": "Feature",
  "properties": {
    "hierarchy": [
      "tgn:7557438",
      "tgn:1000004",
      "tgn:7000198",
      "tgn:7016788",
      "tgn:7029392"
    ],
    "placetype": [
      "aat:300008347"
    ],
    "name:en": "Rānāwās",
    "id": 7557438
  }
}
