{
  "type": "FeatureCollection",
  "features": [
    {
      "geometry": {
        "type": "Point",
        "coordinates": [
          11.033333,
          43.8
        ]
      },
      "type": "Feature",
      "properties": {
        "hierarchy": [
          "tgn:7050501",
          "tgn:7003163",
          "tgn:1000003",
          "tgn:7009760",
          "tgn:1000080",
          "tgn:7029392"
        ],
        "placetype": [
          "aat:300008347"
        ],
        "id": 7050501,
        "name:xx": "La Serra"
      }
    },
    {
      "geometry": {
        "type": "Point",
        "coordinates": [
          11.733333,
          46.65
        ]
      },
      "type": "Feature",
      "properties": {
        "hierarchy": [
          "tgn:7050502",
          "tgn:1003440",
          "tgn:1000003",
          "tgn:7003124",
          "tgn:1000080",
          "tgn:7029392"
        ],
        "placetype": [
          "aat:300008347"
        ],
        "id": 7050502,
        "name:xx": "Lasei"
      }
    },
    {
      "geometry": {
        "type": "Point",
        "coordinates": [
          10.583333,
          42.983333
        ]
      },
      "type": "Feature",
      "properties": {
        "hierarchy": [
          "tgn:7050503",
          "tgn:7003164",
          "tgn:1000003",
          "tgn:7009760",
          "tgn:1000080",
          "tgn:7029392"
        ],
        "placetype": [
          "aat:300008347"
        ],
        "id": 7050503,
        "name:xx": "La Sdriscia"
      }
    },
    {
      "geometry": {
        "type": "Point",
        "coordinates": [
          16.5,
          39.3
        ]
      },
      "type": "Feature",
      "properties": {
        "hierarchy": [
          "tgn:7050504",
          "tgn:1003450",
          "tgn:7007850",
          "tgn:1000003",
          "tgn:1000080",
          "tgn:7029392"
        ],
        "placetype": [
          "aat:300008347"
        ],
        "id": 7050504,
        "name:xx": "La Scruca"
      }
    },
    {
      "geometry": {
        "type": "Point",
        "coordinates": [
          10.1,
          42.583333
        ]
      },
      "type": "Feature",
      "properties": {
        "hierarchy": [
          "tgn:7050505",
          "tgn:7003164",
          "tgn:1000003",
          "tgn:7009760",
          "tgn:1000080",
          "tgn:7029392"
        ],
        "placetype": [
          "aat:300011692"
        ],
        "id": 7050505,
        "name:xx": "La Scola"
      }
    },
    {
      "geometry": {
        "type": "Point",
        "coordinates": [
          15.033333,
          38.133333
        ]
      },
      "type": "Feature",
      "properties": {
        "hierarchy": [
          "tgn:7050507",
          "tgn:1000003",
          "tgn:7003122",
          "tgn:7003157",
          "tgn:1000080",
          "tgn:7029392"
        ],
        "placetype": [
          "aat:300008347"
        ],
        "id": 7050507,
        "name:xx": "Scala"
      }
    },
    {
      "geometry": {
        "type": "Point",
        "coordinates": [
          6.966667,
          45.8
        ]
      },
      "type": "Feature",
      "properties": {
        "hierarchy": [
          "tgn:7050508",
          "tgn:1003430",
          "tgn:1000003",
          "tgn:7003126",
          "tgn:1000080",
          "tgn:7029392"
        ],
        "placetype": [
          "aat:300008347"
        ],
        "id": 7050508,
        "name:xx": "La Saxe"
      }
    },
    {
      "geometry": {
        "type": "Point",
        "coordinates": [
          11.483333,
          44.75
        ]
      },
      "type": "Feature",
      "properties": {
        "hierarchy": [
          "tgn:7050509",
          "tgn:7003128",
          "tgn:1000003",
          "tgn:7008516",
          "tgn:1000080",
          "tgn:7029392"
        ],
        "placetype": [
          "aat:300008347"
        ],
        "id": 7050509,
        "name:xx": "La Sanguettola"
      }
    }
  ]
}
