{
  "geometry": {
    "type": "Point",
    "coordinates": [
      -104.2333,
      32.65
    ]
  },
  "type": "Feature",
  "properties": {
    "hierarchy": [
      "tgn:2772807",
      "tgn:1000001",
      "tgn:2001436",
      "tgn:7012149",
      "tgn:7007566",
      "tgn:7029392"
    ],
    "placetype": [
      "aat:300386845"
    ],
    "id": 2772807,
    "name:xx": "Williams Hollow"
  }
}
