{
  "type": "FeatureCollection",
  "features": [
    {
      "geometry": {
        "type": "Point",
        "coordinates": [
          16.5,
          11.5
        ]
      },
      "type": "Feature",
      "properties": {
        "hierarchy": [
          "tgn:1000970",
          "tgn:7001242",
          "tgn:1000156",
          "tgn:7029392"
        ],
        "placetype": [
          "aat:300387064",
          "aat:300235099"
        ],
        "id": 1000970,
        "name:xx": "Chari-Baguirmi"
      }
    },
    {
      "geometry": {
        "type": "Point",
        "coordinates": [
          140.3333,
          35.5
        ]
      },
      "type": "Feature",
      "properties": {
        "hierarchy": [
          "tgn:1000971",
          "tgn:1000004",
          "tgn:7000894",
          "tgn:1000120",
          "tgn:7029392"
        ],
        "placetype": [
          "aat:300387145",
          "aat:300235099"
        ],
        "id": 1000971,
        "name:xx": "Chiba-ken"
      }
    },
    {
      "geometry": {
        "type": "Point",
        "coordinates": [
          16,
          -0.5
        ]
      },
      "type": "Feature",
      "properties": {
        "hierarchy": [
          "tgn:1000972",
          "tgn:7001242",
          "tgn:1000158",
          "tgn:7029392"
        ],
        "placetype": [
          "aat:300387064",
          "aat:300000774"
        ],
        "id": 1000972,
        "name:xx": "Cuvette"
      }
    },
    {
      "geometry": {
        "type": "Point",
        "coordinates": [
          136.25,
          36
        ]
      },
      "type": "Feature",
      "properties": {
        "hierarchy": [
          "tgn:1000974",
          "tgn:7000895",
          "tgn:1000004",
          "tgn:1000120",
          "tgn:7029392"
        ],
        "placetype": [
          "aat:300387145",
          "aat:300235099"
        ],
        "id": 1000974,
        "name:xx": "Fukui"
      }
    },
    {
      "geometry": {
        "type": "Point",
        "coordinates": [
          130.5,
          33.75
        ]
      },
      "type": "Feature",
      "properties": {
        "hierarchy": [
          "tgn:1000975",
          "tgn:1000004",
          "tgn:7000901",
          "tgn:1000120",
          "tgn:7029392"
        ],
        "placetype": [
          "aat:300387145",
          "aat:300235099"
        ],
        "id": 1000975,
        "name:xx": "Fukuoka"
      }
    },
    {
      "geometry": {
        "type": "Point",
        "coordinates": [
          140,
          37.0833
        ]
      },
      "type": "Feature",
      "properties": {
        "hierarchy": [
          "tgn:1000976",
          "tgn:1000004",
          "tgn:7000893",
          "tgn:1000120",
          "tgn:7029392"
        ],
        "placetype": [
          "aat:300387145",
          "aat:300235099"
        ],
        "id": 1000976,
        "name:xx": "Fukushima"
      }
    },
    {
      "geometry": {
        "type": "Point",
        "coordinates": [
          137,
          35.75
        ]
      },
      "type": "Feature",
      "properties": {
        "hierarchy": [
          "tgn:1000977",
          "tgn:7000895",
          "tgn:1000004",
          "tgn:1000120",
          "tgn:7029392"
        ],
        "placetype": [
          "aat:300387145",
          "aat:300235099"
        ],
        "id": 1000977,
        "name:xx": "Gifu-ken"
      }
    },
    {
      "geometry": {
        "type": "Point",
        "coordinates": [
          19.25,
          7.0833
        ]
      },
      "type": "Feature",
      "properties": {
        "hierarchy": [
          "tgn:1000978",
          "tgn:7001242",
          "tgn:1000155",
          "tgn:7029392"
        ],
        "placetype": [
          "aat:300387064",
          "aat:300235099"
        ],
        "id": 1000978,
        "name:xx": "Nana-Gribizi"
      }
    },
    {
      "geometry": {
        "type": "Point",
        "coordinates": [
          18.5833,
          11.4667
        ]
      },
      "type": "Feature",
      "properties": {
        "hierarchy": [
          "tgn:1000979",
          "tgn:7001242",
          "tgn:1000156",
          "tgn:7029392"
        ],
        "placetype": [
          "aat:300387064",
          "aat:300235099"
        ],
        "id": 1000979,
        "name:xx": "Guéra"
      }
    }
  ]
}
