{
  "geometry": {
    "type": "Point",
    "coordinates": [
      77.005556,
      31.2125
    ]
  },
  "type": "Feature",
  "properties": {
    "hierarchy": [
      "tgn:7567582",
      "tgn:1000004",
      "tgn:7000198",
      "tgn:1001996",
      "tgn:7029392"
    ],
    "placetype": [
      "aat:300008347"
    ],
    "name:en": "Palāhata",
    "id": 7567582
  }
}
