{
  "geometry": {
    "type": "Point",
    "coordinates": [
      -104.1667,
      41.7667
    ]
  },
  "type": "Feature",
  "properties": {
    "hierarchy": [
      "tgn:2502859",
      "tgn:1000001",
      "tgn:7012149",
      "tgn:2002372",
      "tgn:7007923",
      "tgn:7029392"
    ],
    "placetype": [
      "aat:300006191"
    ],
    "id": 2502859,
    "name:xx": "McMillen Number 2 Reservoir"
  }
}
