{
  "type": "FeatureCollection",
  "features": [
    {
      "geometry": {
        "type": "Point",
        "coordinates": [
          -110.866667,
          28.533333
        ]
      },
      "type": "Feature",
      "properties": {
        "hierarchy": [
          "tgn:7366550",
          "tgn:1000001",
          "tgn:1001960",
          "tgn:7005560",
          "tgn:7029392"
        ],
        "placetype": [
          "aat:300008347"
        ],
        "id": 7366550,
        "name:xx": "Esperanza"
      }
    },
    {
      "geometry": {
        "type": "Point",
        "coordinates": [
          -108.783333,
          26.033333
        ]
      },
      "type": "Feature",
      "properties": {
        "hierarchy": [
          "tgn:7366551",
          "tgn:1000001",
          "tgn:7005595",
          "tgn:7005560",
          "tgn:7029392"
        ],
        "placetype": [
          "aat:300008347"
        ],
        "id": 7366551,
        "name:xx": "Esperanza"
      }
    },
    {
      "geometry": {
        "type": "Point",
        "coordinates": [
          -97.533333,
          25.883333
        ]
      },
      "type": "Feature",
      "properties": {
        "hierarchy": [
          "tgn:7366552",
          "tgn:1000001",
          "tgn:7005597",
          "tgn:7005560",
          "tgn:7029392"
        ],
        "placetype": [
          "aat:300008347"
        ],
        "id": 7366552,
        "name:xx": "Esperanza"
      }
    },
    {
      "geometry": {
        "type": "Point",
        "coordinates": [
          -103.583333,
          25.85
        ]
      },
      "type": "Feature",
      "properties": {
        "hierarchy": [
          "tgn:7366553",
          "tgn:7005583",
          "tgn:1000001",
          "tgn:7005560",
          "tgn:7029392"
        ],
        "placetype": [
          "aat:300008347"
        ],
        "id": 7366553,
        "name:xx": "Esperanza"
      }
    },
    {
      "geometry": {
        "type": "Point",
        "coordinates": [
          -108.433333,
          25.483333
        ]
      },
      "type": "Feature",
      "properties": {
        "hierarchy": [
          "tgn:7366554",
          "tgn:1000001",
          "tgn:7005595",
          "tgn:7005560",
          "tgn:7029392"
        ],
        "placetype": [
          "aat:300008347"
        ],
        "id": 7366554,
        "name:xx": "Esperanza"
      }
    },
    {
      "geometry": {
        "type": "Point",
        "coordinates": [
          -103.3,
          25.35
        ]
      },
      "type": "Feature",
      "properties": {
        "hierarchy": [
          "tgn:7366555",
          "tgn:1001853",
          "tgn:1000001",
          "tgn:7005560",
          "tgn:7029392"
        ],
        "placetype": [
          "aat:300008347"
        ],
        "id": 7366555,
        "name:xx": "Esperanza"
      }
    },
    {
      "geometry": {
        "type": "Point",
        "coordinates": [
          -107.568333,
          24.81
        ]
      },
      "type": "Feature",
      "properties": {
        "hierarchy": [
          "tgn:7366556",
          "tgn:1000001",
          "tgn:7005595",
          "tgn:7005560",
          "tgn:7029392"
        ],
        "placetype": [
          "aat:300008347"
        ],
        "id": 7366556,
        "name:xx": "Esperanza"
      }
    },
    {
      "geometry": {
        "type": "Point",
        "coordinates": [
          -107.138889,
          24.274167
        ]
      },
      "type": "Feature",
      "properties": {
        "hierarchy": [
          "tgn:7366557",
          "tgn:1000001",
          "tgn:7005595",
          "tgn:7005560",
          "tgn:7029392"
        ],
        "placetype": [
          "aat:300008347"
        ],
        "id": 7366557,
        "name:xx": "Esperanza"
      }
    },
    {
      "geometry": {
        "type": "Point",
        "coordinates": [
          -102.133333,
          23.183333
        ]
      },
      "type": "Feature",
      "properties": {
        "hierarchy": [
          "tgn:7366558",
          "tgn:1000001",
          "tgn:7005594",
          "tgn:7005560",
          "tgn:7029392"
        ],
        "placetype": [
          "aat:300008347"
        ],
        "id": 7366558,
        "name:xx": "Esperanza"
      }
    },
    {
      "geometry": {
        "type": "Point",
        "coordinates": [
          -90.266667,
          20.8
        ]
      },
      "type": "Feature",
      "properties": {
        "hierarchy": [
          "tgn:7366559",
          "tgn:1000001",
          "tgn:7005600",
          "tgn:7005560",
          "tgn:7029392"
        ],
        "placetype": [
          "aat:300008347"
        ],
        "id": 7366559,
        "name:xx": "Esperanza"
      }
    }
  ]
}
