{
  "geometry": {
    "type": "Point",
    "coordinates": [
      -88.3667,
      41.7833
    ]
  },
  "type": "Feature",
  "properties": {
    "hierarchy": [
      "tgn:2309070",
      "tgn:1000001",
      "tgn:7012149",
      "tgn:1002531",
      "tgn:7007251",
      "tgn:7029392"
    ],
    "placetype": [
      "aat:300008699"
    ],
    "id": 2309070,
    "name:xx": "East Run"
  }
}
