{
  "geometry": {
    "type": "Point",
    "coordinates": [
      -76.0333,
      42.35
    ]
  },
  "type": "Feature",
  "properties": {
    "hierarchy": [
      "tgn:2490737",
      "tgn:1000001",
      "tgn:1002206",
      "tgn:7012149",
      "tgn:7007568",
      "tgn:7029392"
    ],
    "placetype": [
      "aat:300008347"
    ],
    "id": 2490737,
    "name:xx": "Manningville"
  }
}
