{
  "geometry": {
    "type": "Point",
    "coordinates": [
      8.583333,
      48.75
    ]
  },
  "type": "Feature",
  "properties": {
    "hierarchy": [
      "tgn:7078664",
      "tgn:7003692",
      "tgn:1000003",
      "tgn:7000084",
      "tgn:7029392"
    ],
    "placetype": [
      "aat:300008699"
    ],
    "id": 7078664,
    "name:xx": "Würzbach"
  }
}
