{
  "geometry": {
    "type": "Point",
    "coordinates": [
      -81.6667,
      34.5333
    ]
  },
  "type": "Feature",
  "properties": {
    "hierarchy": [
      "tgn:2555372",
      "tgn:1000001",
      "tgn:7012149",
      "tgn:2001754",
      "tgn:7007712",
      "tgn:7029392"
    ],
    "placetype": [
      "aat:300008699"
    ],
    "id": 2555372,
    "name:xx": "Odells Branch"
  }
}
