{
  "geometry": {
    "type": "Point",
    "coordinates": [
      8.6667,
      52.2833
    ]
  },
  "type": "Feature",
  "properties": {
    "hierarchy": [
      "tgn:1109806",
      "tgn:1000003",
      "tgn:7000084",
      "tgn:7029392"
    ],
    "placetype": [
      "aat:300008795"
    ],
    "id": 1109806,
    "name:xx": "Wiehengebirge"
  }
}
