{
  "type": "FeatureCollection",
  "features": [
    {
      "geometry": {
        "type": "Point",
        "coordinates": [
          -0.016667,
          51.716667
        ]
      },
      "type": "Feature",
      "properties": {
        "hierarchy": [
          "tgn:1031220",
          "tgn:7002445",
          "tgn:1000003",
          "tgn:7008145",
          "tgn:7008591",
          "tgn:7029392"
        ],
        "placetype": [
          "aat:300008347",
          "aat:300008372"
        ],
        "name:en": "Wormley",
        "id": 1031220
      }
    },
    {
      "geometry": {
        "type": "Point",
        "coordinates": [
          0.7,
          51.266667
        ]
      },
      "type": "Feature",
      "properties": {
        "hierarchy": [
          "tgn:1031221",
          "tgn:7002445",
          "tgn:1000003",
          "tgn:7008153",
          "tgn:7008591",
          "tgn:7029392"
        ],
        "placetype": [
          "aat:300008347",
          "aat:300008372"
        ],
        "name:en": "Wormshill",
        "id": 1031221
      }
    },
    {
      "geometry": {
        "type": "Point",
        "coordinates": [
          -0.6,
          51.283333
        ]
      },
      "type": "Feature",
      "properties": {
        "hierarchy": [
          "tgn:1031222",
          "tgn:7002445",
          "tgn:1000003",
          "tgn:7008175",
          "tgn:7008591",
          "tgn:7029392"
        ],
        "placetype": [
          "aat:300008347"
        ],
        "name:en": "Worplesdon",
        "id": 1031222
      }
    },
    {
      "geometry": {
        "type": "Point",
        "coordinates": [
          -2.383333,
          53.5
        ]
      },
      "type": "Feature",
      "properties": {
        "hierarchy": [
          "tgn:1031224",
          "tgn:7002445",
          "tgn:1003640",
          "tgn:1000003",
          "tgn:7026570",
          "tgn:7008591",
          "tgn:7029392"
        ],
        "placetype": [
          "aat:300008347"
        ],
        "name:en": "Worsley",
        "id": 1031224
      }
    },
    {
      "geometry": {
        "type": "Point",
        "coordinates": [
          -2.183333,
          53.783333
        ]
      },
      "type": "Feature",
      "properties": {
        "hierarchy": [
          "tgn:1031225",
          "tgn:7002445",
          "tgn:1000003",
          "tgn:7008154",
          "tgn:7008591",
          "tgn:7029392"
        ],
        "placetype": [
          "aat:300008347"
        ],
        "name:en": "Worsthorne",
        "id": 1031225
      }
    },
    {
      "geometry": {
        "type": "Point",
        "coordinates": [
          -3,
          52.633333
        ]
      },
      "type": "Feature",
      "properties": {
        "hierarchy": [
          "tgn:1031226",
          "tgn:7002445",
          "tgn:1000003",
          "tgn:7012034",
          "tgn:7008591",
          "tgn:7029392"
        ],
        "placetype": [
          "aat:300008347"
        ],
        "name:en": "Worthen",
        "id": 1031226
      }
    },
    {
      "geometry": {
        "type": "Point",
        "coordinates": [
          -0.383333,
          51.2
        ]
      },
      "type": "Feature",
      "properties": {
        "hierarchy": [
          "tgn:1031228",
          "tgn:7002445",
          "tgn:1000003",
          "tgn:7008175",
          "tgn:7008591",
          "tgn:7029392"
        ],
        "placetype": [
          "aat:300008347"
        ],
        "name:en": "Wotton",
        "id": 1031228
      }
    }
  ]
}
