{
  "geometry": {
    "type": "Point",
    "coordinates": [
      -83.2667,
      39.9333
    ]
  },
  "type": "Feature",
  "properties": {
    "hierarchy": [
      "tgn:2082511",
      "tgn:1000001",
      "tgn:7012149",
      "tgn:1002625",
      "tgn:7007706",
      "tgn:7029392"
    ],
    "placetype": [
      "aat:300008347"
    ],
    "id": 2082511,
    "name:xx": "West Jefferson"
  }
}
