{
  "geometry": {
    "type": "Point",
    "coordinates": [
      -80.8167,
      28.55
    ]
  },
  "type": "Feature",
  "properties": {
    "hierarchy": [
      "tgn:2181628",
      "tgn:1000001",
      "tgn:1002200",
      "tgn:7012149",
      "tgn:7007240",
      "tgn:7029392"
    ],
    "placetype": [
      "aat:300386845"
    ],
    "id": 2181628,
    "name:xx": "Blue Hole"
  }
}
