{
  "geometry": {
    "type": "Point",
    "coordinates": [
      -78.9833,
      36.45
    ]
  },
  "type": "Feature",
  "properties": {
    "hierarchy": [
      "tgn:2632234",
      "tgn:1000001",
      "tgn:7012149",
      "tgn:2001529",
      "tgn:7007709",
      "tgn:7029392"
    ],
    "placetype": [
      "aat:300006191"
    ],
    "id": 2632234,
    "name:xx": "Roxboro Country Club Lake"
  }
}
