{
  "geometry": {
    "type": "Point",
    "coordinates": [
      -72.6667,
      40.9167
    ]
  },
  "type": "Feature",
  "properties": {
    "hierarchy": [
      "tgn:2506455",
      "tgn:1000001",
      "tgn:7012149",
      "tgn:1002924",
      "tgn:7007568",
      "tgn:7029392"
    ],
    "placetype": [
      "aat:300008680"
    ],
    "id": 2506455,
    "name:xx": "Merritts Pond"
  }
}
