{
  "geometry": {
    "type": "Point",
    "coordinates": [
      -80.8167,
      25.9333
    ]
  },
  "type": "Feature",
  "properties": {
    "hierarchy": [
      "tgn:2494089",
      "tgn:1000001",
      "tgn:7012149",
      "tgn:1002314",
      "tgn:7007240",
      "tgn:7029392"
    ],
    "placetype": [
      "aat:300008347"
    ],
    "id": 2494089,
    "name:xx": "Mart Law Seminole Village"
  }
}
