{
  "geometry": {
    "type": "Point",
    "coordinates": [
      -79.8667,
      37.8167
    ]
  },
  "type": "Feature",
  "properties": {
    "hierarchy": [
      "tgn:2297135",
      "tgn:1000001",
      "tgn:7012149",
      "tgn:7007919",
      "tgn:7029392"
    ],
    "placetype": [
      "aat:300008706"
    ],
    "id": 2297135,
    "name:xx": "Dry Creek"
  }
}
