{
  "geometry": {
    "type": "Point",
    "coordinates": [
      46.6333,
      51.6667
    ]
  },
  "type": "Feature",
  "properties": {
    "hierarchy": [
      "tgn:1122091",
      "tgn:1000004",
      "tgn:1003408",
      "tgn:7018214",
      "tgn:7002435",
      "tgn:7029392"
    ],
    "placetype": [
      "aat:300008707"
    ],
    "id": 1122091,
    "name:xx": "Bol'šoj Karaman"
  }
}
