{
  "geometry": {
    "type": "Point",
    "coordinates": [
      -83.0833,
      38.5333
    ]
  },
  "type": "Feature",
  "properties": {
    "hierarchy": [
      "tgn:2486336",
      "tgn:1000001",
      "tgn:7012149",
      "tgn:1002426",
      "tgn:7007255",
      "tgn:7029392"
    ],
    "placetype": [
      "aat:300008699"
    ],
    "id": 2486336,
    "name:xx": "Leatherwood Branch"
  }
}
