{
  "geometry": {
    "type": "Point",
    "coordinates": [
      81.5167,
      7.8667
    ]
  },
  "type": "Feature",
  "properties": {
    "hierarchy": [
      "tgn:1126651",
      "tgn:1000004",
      "tgn:1000110",
      "tgn:7029392"
    ],
    "placetype": [
      "aat:300008707"
    ],
    "id": 1126651,
    "name:xx": "Maduru Oya"
  }
}
