{
  "geometry": {
    "type": "Point",
    "coordinates": [
      45.2667,
      24.05
    ]
  },
  "type": "Feature",
  "properties": {
    "hierarchy": [
      "tgn:1084843",
      "tgn:7000680",
      "tgn:1000004",
      "tgn:7003879",
      "tgn:1000137",
      "tgn:7029392"
    ],
    "placetype": [
      "aat:300008347"
    ],
    "id": 1084843,
    "name:xx": "Al-Quwayʻīyah"
  }
}
