{
  "geometry": {
    "type": "Point",
    "coordinates": [
      53.8333,
      56.5167
    ]
  },
  "type": "Feature",
  "properties": {
    "hierarchy": [
      "tgn:1059418",
      "tgn:1000004",
      "tgn:7002435",
      "tgn:7011526",
      "tgn:7029392"
    ],
    "placetype": [
      "aat:300008347"
    ],
    "id": 1059418,
    "name:xx": "Simonikha"
  }
}
