{
  "geometry": {
    "type": "Point",
    "coordinates": [
      118.251111,
      24.4425
    ]
  },
  "type": "Feature",
  "properties": {
    "hierarchy": [
      "tgn:7467694",
      "tgn:7469009",
      "tgn:1000004",
      "tgn:1000141",
      "tgn:7029392"
    ],
    "placetype": [
      "aat:300008777"
    ],
    "id": 7467694,
    "name:xx": "Qilin Shan"
  }
}
