{
  "geometry": {
    "type": "Point",
    "coordinates": [
      -73.45,
      41.7333
    ]
  },
  "type": "Feature",
  "properties": {
    "hierarchy": [
      "tgn:2016884",
      "tgn:1000001",
      "tgn:1002601",
      "tgn:7012149",
      "tgn:7007159",
      "tgn:7029392"
    ],
    "placetype": [
      "aat:300008347"
    ],
    "id": 2016884,
    "name:xx": "Flanders"
  }
}
