{
  "geometry": {
    "type": "Point",
    "coordinates": [
      -119.5333,
      34.45
    ]
  },
  "type": "Feature",
  "properties": {
    "hierarchy": [
      "tgn:2555917",
      "tgn:1000001",
      "tgn:7012149",
      "tgn:7007157",
      "tgn:1002867",
      "tgn:7029392"
    ],
    "placetype": [
      "aat:300008761"
    ],
    "id": 2555917,
    "name:xx": "Oil Canyon"
  }
}
