{
  "geometry": {
    "type": "Point",
    "coordinates": [
      -92.0167,
      30.5167
    ]
  },
  "type": "Feature",
  "properties": {
    "hierarchy": [
      "tgn:2042364",
      "tgn:1000001",
      "tgn:7012149",
      "tgn:2000902",
      "tgn:7007256",
      "tgn:7029392"
    ],
    "placetype": [
      "aat:300008347",
      "aat:300387210"
    ],
    "id": 2042364,
    "name:xx": "Boscoville"
  }
}
