{
  "geometry": {
    "type": "Point",
    "coordinates": [
      -74.9667,
      42.9167
    ]
  },
  "type": "Feature",
  "properties": {
    "hierarchy": [
      "tgn:2330564",
      "tgn:1000001",
      "tgn:7012149",
      "tgn:1002472",
      "tgn:7007568",
      "tgn:7029392"
    ],
    "placetype": [
      "aat:300008706"
    ],
    "id": 2330564,
    "name:xx": "Flat Creek"
  }
}
