{
  "geometry": {
    "type": "Point",
    "coordinates": [
      -105.35,
      37.6333
    ]
  },
  "type": "Feature",
  "properties": {
    "hierarchy": [
      "tgn:2491108",
      "tgn:1000001",
      "tgn:7012149",
      "tgn:2000219",
      "tgn:7007158",
      "tgn:7029392"
    ],
    "placetype": [
      "aat:300008706"
    ],
    "id": 2491108,
    "name:xx": "Manzanares Creek"
  }
}
