{
  "geometry": {
    "type": "Point",
    "coordinates": [
      -99.778056,
      19.4625
    ]
  },
  "type": "Feature",
  "properties": {
    "hierarchy": [
      "tgn:7399085",
      "tgn:1000001",
      "tgn:1001893",
      "tgn:7005560",
      "tgn:7029392"
    ],
    "placetype": [
      "aat:300008699"
    ],
    "id": 7399085,
    "name:xx": "Lerma, Río"
  }
}
