{
  "geometry": {
    "type": "Point",
    "coordinates": [
      -120.8333,
      39.7333
    ]
  },
  "type": "Feature",
  "properties": {
    "hierarchy": [
      "tgn:2757623",
      "tgn:1000001",
      "tgn:7012149",
      "tgn:7007157",
      "tgn:1002894",
      "tgn:7029392"
    ],
    "placetype": [
      "aat:300008706"
    ],
    "id": 2757623,
    "name:xx": "West Branch Canyon Creek"
  }
}
