{
  "type": "FeatureCollection",
  "features": [
    {
      "geometry": {
        "type": "Point",
        "coordinates": [
          174.716667,
          -38.216667
        ]
      },
      "type": "Feature",
      "properties": {
        "hierarchy": [
          "tgn:7513000",
          "tgn:1008380",
          "tgn:1000226",
          "tgn:7018426",
          "tgn:1000006",
          "tgn:7029392"
        ],
        "placetype": [
          "aat:300008816"
        ],
        "name:en": "Harihari Beach",
        "id": 7513000
      }
    },
    {
      "geometry": {
        "type": "Point",
        "coordinates": [
          174.716667,
          -38.2
        ]
      },
      "type": "Feature",
      "properties": {
        "hierarchy": [
          "tgn:7513001",
          "tgn:1008380",
          "tgn:1000226",
          "tgn:7018426",
          "tgn:1000006",
          "tgn:7029392"
        ],
        "placetype": [
          "aat:300008680"
        ],
        "name:en": "Harihari, Lake",
        "id": 7513001
      }
    },
    {
      "geometry": {
        "type": "Point",
        "coordinates": [
          174.3,
          -36.266667
        ]
      },
      "type": "Feature",
      "properties": {
        "hierarchy": [
          "tgn:7513003",
          "tgn:1008380",
          "tgn:7000507",
          "tgn:1000226",
          "tgn:1000006",
          "tgn:7029392"
        ],
        "placetype": [
          "aat:300008777"
        ],
        "name:en": "Hargraves Run",
        "id": 7513003
      }
    },
    {
      "geometry": {
        "type": "Point",
        "coordinates": [
          166.816667,
          -45.283333
        ]
      },
      "type": "Feature",
      "properties": {
        "hierarchy": [
          "tgn:7513005",
          "tgn:1009227",
          "tgn:1000226",
          "tgn:7016822",
          "tgn:1000006",
          "tgn:7029392"
        ],
        "placetype": [
          "aat:300011692"
        ],
        "name:en": "Hares Ears",
        "id": 7513005
      }
    },
    {
      "geometry": {
        "type": "Point",
        "coordinates": [
          173.883333,
          -40.75
        ]
      },
      "type": "Feature",
      "properties": {
        "hierarchy": [
          "tgn:7513006",
          "tgn:1009227",
          "tgn:1000226",
          "tgn:7016729",
          "tgn:1000006",
          "tgn:7029392"
        ],
        "placetype": [
          "aat:300132316"
        ],
        "name:en": "Hardy, Port",
        "id": 7513006
      }
    },
    {
      "geometry": {
        "type": "Point",
        "coordinates": [
          172.616667,
          -40.866667
        ]
      },
      "type": "Feature",
      "properties": {
        "hierarchy": [
          "tgn:7513007",
          "tgn:1009227",
          "tgn:1000226",
          "tgn:7520095",
          "tgn:1000006",
          "tgn:7029392"
        ],
        "placetype": [
          "aat:300008795"
        ],
        "name:en": "Hardy, Mount",
        "id": 7513007
      }
    },
    {
      "geometry": {
        "type": "Point",
        "coordinates": [
          174.016667,
          -40.9
        ]
      },
      "type": "Feature",
      "properties": {
        "hierarchy": [
          "tgn:7513008",
          "tgn:1009227",
          "tgn:1000226",
          "tgn:7016729",
          "tgn:1000006",
          "tgn:7029392"
        ],
        "placetype": [
          "aat:300386846"
        ],
        "name:en": "Harding Point",
        "id": 7513008
      }
    },
    {
      "geometry": {
        "type": "Point",
        "coordinates": [
          171.9,
          -41.883333
        ]
      },
      "type": "Feature",
      "properties": {
        "hierarchy": [
          "tgn:7513009",
          "tgn:1009227",
          "tgn:1000226",
          "tgn:1000006",
          "tgn:7016850",
          "tgn:7029392"
        ],
        "placetype": [
          "aat:300008699"
        ],
        "name:en": "Hard Creek",
        "id": 7513009
      }
    }
  ]
}
