{
  "geometry": {
    "type": "Point",
    "coordinates": [
      -71.85,
      -41.25
    ]
  },
  "type": "Feature",
  "properties": {
    "hierarchy": [
      "tgn:7288503",
      "tgn:1001699",
      "tgn:1000049",
      "tgn:1000002",
      "tgn:7029392"
    ],
    "placetype": [
      "aat:300259572"
    ],
    "id": 7288503,
    "name:xx": "Laguna Cauquenes Número Nueve, Portezuelo"
  }
}
