{
  "geometry": {
    "type": "Point",
    "coordinates": [
      -91.3167,
      35.5167
    ]
  },
  "type": "Feature",
  "properties": {
    "hierarchy": [
      "tgn:2393844",
      "tgn:1000001",
      "tgn:7016172",
      "tgn:7012149",
      "tgn:2000138",
      "tgn:7029392"
    ],
    "placetype": [
      "aat:300008680"
    ],
    "id": 2393844,
    "name:xx": "Hog Lake"
  }
}
