{
  "type": "FeatureCollection",
  "features": [
    {
      "geometry": {
        "type": "Point",
        "coordinates": [
          8.85,
          50.633333
        ]
      },
      "type": "Feature",
      "properties": {
        "hierarchy": [
          "tgn:7198120",
          "tgn:1000003",
          "tgn:7003678",
          "tgn:7000084",
          "tgn:7029392"
        ],
        "placetype": [
          "aat:300008863"
        ],
        "id": 7198120,
        "name:xx": "Eichwald"
      }
    },
    {
      "geometry": {
        "type": "Point",
        "coordinates": [
          11.033333,
          49.85
        ]
      },
      "type": "Feature",
      "properties": {
        "hierarchy": [
          "tgn:7198121",
          "tgn:7003669",
          "tgn:1000003",
          "tgn:7000084",
          "tgn:7029392"
        ],
        "placetype": [
          "aat:300008863"
        ],
        "id": 7198121,
        "name:xx": "Eichwald"
      }
    },
    {
      "geometry": {
        "type": "Point",
        "coordinates": [
          10.75,
          49.7
        ]
      },
      "type": "Feature",
      "properties": {
        "hierarchy": [
          "tgn:7198122",
          "tgn:7003669",
          "tgn:1000003",
          "tgn:7000084",
          "tgn:7029392"
        ],
        "placetype": [
          "aat:300008863"
        ],
        "id": 7198122,
        "name:xx": "Eichwald"
      }
    },
    {
      "geometry": {
        "type": "Point",
        "coordinates": [
          10.05,
          49.7
        ]
      },
      "type": "Feature",
      "properties": {
        "hierarchy": [
          "tgn:7198123",
          "tgn:7003669",
          "tgn:1000003",
          "tgn:7000084",
          "tgn:7029392"
        ],
        "placetype": [
          "aat:300008863"
        ],
        "id": 7198123,
        "name:xx": "Eichwald"
      }
    },
    {
      "geometry": {
        "type": "Point",
        "coordinates": [
          9.266667,
          49.45
        ]
      },
      "type": "Feature",
      "properties": {
        "hierarchy": [
          "tgn:7198124",
          "tgn:7003692",
          "tgn:1000003",
          "tgn:7000084",
          "tgn:7029392"
        ],
        "placetype": [
          "aat:300008863"
        ],
        "id": 7198124,
        "name:xx": "Eichwald"
      }
    },
    {
      "geometry": {
        "type": "Point",
        "coordinates": [
          10.566667,
          47.883333
        ]
      },
      "type": "Feature",
      "properties": {
        "hierarchy": [
          "tgn:7198125",
          "tgn:7003669",
          "tgn:1000003",
          "tgn:7000084",
          "tgn:7029392"
        ],
        "placetype": [
          "aat:300008863"
        ],
        "id": 7198125,
        "name:xx": "Eich Wald"
      }
    },
    {
      "geometry": {
        "type": "Point",
        "coordinates": [
          7.65,
          47.783333
        ]
      },
      "type": "Feature",
      "properties": {
        "hierarchy": [
          "tgn:7198126",
          "tgn:7003692",
          "tgn:1000003",
          "tgn:7000084",
          "tgn:7029392"
        ],
        "placetype": [
          "aat:300008863"
        ],
        "id": 7198126,
        "name:xx": "Eichwald"
      }
    },
    {
      "geometry": {
        "type": "Point",
        "coordinates": [
          9.933333,
          48
        ]
      },
      "type": "Feature",
      "properties": {
        "hierarchy": [
          "tgn:7198127",
          "tgn:7003692",
          "tgn:1000003",
          "tgn:7000084",
          "tgn:7029392"
        ],
        "placetype": [
          "aat:300000206"
        ],
        "id": 7198127,
        "name:xx": "Eichwald"
      }
    },
    {
      "geometry": {
        "type": "Point",
        "coordinates": [
          11.916667,
          48.016667
        ]
      },
      "type": "Feature",
      "properties": {
        "hierarchy": [
          "tgn:7198128",
          "tgn:7003669",
          "tgn:1000003",
          "tgn:7000084",
          "tgn:7029392"
        ],
        "placetype": [
          "aat:300008347"
        ],
        "id": 7198128,
        "name:xx": "Eichtling"
      }
    },
    {
      "geometry": {
        "type": "Point",
        "coordinates": [
          11.033333,
          54.366667
        ]
      },
      "type": "Feature",
      "properties": {
        "hierarchy": [
          "tgn:7198129",
          "tgn:1000003",
          "tgn:7003688",
          "tgn:7000084",
          "tgn:7029392"
        ],
        "placetype": [
          "aat:300000206"
        ],
        "id": 7198129,
        "name:xx": "Eichthal"
      }
    }
  ]
}
