{
  "geometry": {
    "type": "Point",
    "coordinates": [
      -86.2333,
      38.0667
    ]
  },
  "type": "Feature",
  "properties": {
    "hierarchy": [
      "tgn:2659970",
      "tgn:1000001",
      "tgn:7012149",
      "tgn:1002457",
      "tgn:7007252",
      "tgn:7029392"
    ],
    "placetype": [
      "aat:300008798"
    ],
    "id": 2659970,
    "name:xx": "Shireman Hill"
  }
}
