{
  "geometry": {
    "type": "Point",
    "coordinates": [
      -108.7667,
      43.0167
    ]
  },
  "type": "Feature",
  "properties": {
    "hierarchy": [
      "tgn:2319427",
      "tgn:1000001",
      "tgn:7012149",
      "tgn:2002371",
      "tgn:7007923",
      "tgn:7029392"
    ],
    "placetype": [
      "aat:300008347"
    ],
    "id": 2319427,
    "name:xx": "Ethete Saint Michael Mission"
  }
}
