{
  "geometry": {
    "type": "Point",
    "coordinates": [
      15.3667,
      56.6833
    ]
  },
  "type": "Feature",
  "properties": {
    "hierarchy": [
      "tgn:1063610",
      "tgn:1000003",
      "tgn:1000405",
      "tgn:1000097",
      "tgn:7029392"
    ],
    "placetype": [
      "aat:300008347"
    ],
    "id": 1063610,
    "name:xx": "Skruv"
  }
}
