{
  "geometry": {
    "type": "Point",
    "coordinates": [
      110.3333,
      29.6333
    ]
  },
  "type": "Feature",
  "properties": {
    "hierarchy": [
      "tgn:1139157",
      "tgn:1000004",
      "tgn:7002079",
      "tgn:1000111",
      "tgn:7029392"
    ],
    "placetype": [
      "aat:300008347"
    ],
    "id": 1139157,
    "name:xx": "Jiangkou"
  }
}
