{
  "geometry": {
    "type": "Point",
    "coordinates": [
      -91.25,
      47.3333
    ]
  },
  "type": "Feature",
  "properties": {
    "hierarchy": [
      "tgn:2507875",
      "tgn:1000001",
      "tgn:7012149",
      "tgn:2001036",
      "tgn:7007521",
      "tgn:7029392"
    ],
    "placetype": [
      "aat:300008680"
    ],
    "id": 2507875,
    "name:xx": "Micmac Lake"
  }
}
