{
  "geometry": {
    "type": "Point",
    "coordinates": [
      -109.5167,
      42.8667
    ]
  },
  "type": "Feature",
  "properties": {
    "hierarchy": [
      "tgn:2319411",
      "tgn:1000001",
      "tgn:7012149",
      "tgn:2002382",
      "tgn:7007923",
      "tgn:7029392"
    ],
    "placetype": [
      "aat:300008680"
    ],
    "id": 2319411,
    "name:xx": "Ethel, Lake"
  }
}
