{
  "geometry": {
    "type": "Point",
    "coordinates": [
      -80.3333,
      39.2333
    ]
  },
  "type": "Feature",
  "properties": {
    "hierarchy": [
      "tgn:2552692",
      "tgn:1000001",
      "tgn:7012149",
      "tgn:2002267",
      "tgn:7013961",
      "tgn:7029392"
    ],
    "placetype": [
      "aat:300008699"
    ],
    "id": 2552692,
    "name:xx": "Nutter Run"
  }
}
