{
  "geometry": {
    "type": "Point",
    "coordinates": [
      -120.6667,
      45.7167
    ]
  },
  "type": "Feature",
  "properties": {
    "hierarchy": [
      "tgn:2353091",
      "tgn:1000001",
      "tgn:7012149",
      "tgn:1002891",
      "tgn:7007708",
      "tgn:7029392"
    ],
    "placetype": [
      "aat:300008347"
    ],
    "id": 2353091,
    "name:xx": "Goff"
  }
}
