{
  "geometry": {
    "type": "Point",
    "coordinates": [
      47.1833,
      -21.9333
    ]
  },
  "type": "Feature",
  "properties": {
    "hierarchy": [
      "tgn:1090772",
      "tgn:7001242",
      "tgn:7000556",
      "tgn:1000173",
      "tgn:7029392"
    ],
    "placetype": [
      "aat:300008347"
    ],
    "id": 1090772,
    "name:xx": "Ambohimahamasina"
  }
}
