{
  "type": "FeatureCollection",
  "features": [
    {
      "geometry": {
        "type": "Point",
        "coordinates": [
          -86.4667,
          31.3
        ]
      },
      "type": "Feature",
      "properties": {
        "hierarchy": [
          "tgn:2152190",
          "tgn:7002659",
          "tgn:1000001",
          "tgn:2000019",
          "tgn:7012149",
          "tgn:7029392"
        ],
        "placetype": [
          "aat:300008699"
        ],
        "id": 2152190,
        "name:xx": "Bay Branch"
      }
    },
    {
      "geometry": {
        "type": "Point",
        "coordinates": [
          -82.1,
          30.3
        ]
      },
      "type": "Feature",
      "properties": {
        "hierarchy": [
          "tgn:2152191",
          "tgn:2000257",
          "tgn:1000001",
          "tgn:7012149",
          "tgn:7007240",
          "tgn:7029392"
        ],
        "placetype": [
          "aat:300008699"
        ],
        "id": 2152191,
        "name:xx": "Bay Branch"
      }
    },
    {
      "geometry": {
        "type": "Point",
        "coordinates": [
          -87.4167,
          30.7333
        ]
      },
      "type": "Feature",
      "properties": {
        "hierarchy": [
          "tgn:2152192",
          "tgn:1000001",
          "tgn:2000265",
          "tgn:7012149",
          "tgn:7007240",
          "tgn:7029392"
        ],
        "placetype": [
          "aat:300008699"
        ],
        "id": 2152192,
        "name:xx": "Bay Branch"
      }
    },
    {
      "geometry": {
        "type": "Point",
        "coordinates": [
          -86.0667,
          30.8667
        ]
      },
      "type": "Feature",
      "properties": {
        "hierarchy": [
          "tgn:2152193",
          "tgn:1000001",
          "tgn:7012149",
          "tgn:2000290",
          "tgn:7007240",
          "tgn:7029392"
        ],
        "placetype": [
          "aat:300008699"
        ],
        "id": 2152193,
        "name:xx": "Bay Branch"
      }
    },
    {
      "geometry": {
        "type": "Point",
        "coordinates": [
          -86.4333,
          30.9667
        ]
      },
      "type": "Feature",
      "properties": {
        "hierarchy": [
          "tgn:2152194",
          "tgn:1000001",
          "tgn:7012149",
          "tgn:2000281",
          "tgn:7007240",
          "tgn:7029392"
        ],
        "placetype": [
          "aat:300008699"
        ],
        "id": 2152194,
        "name:xx": "Bay Branch"
      }
    },
    {
      "geometry": {
        "type": "Point",
        "coordinates": [
          -85.9333,
          30.85
        ]
      },
      "type": "Feature",
      "properties": {
        "hierarchy": [
          "tgn:2152195",
          "tgn:1000001",
          "tgn:2000272",
          "tgn:7012149",
          "tgn:7007240",
          "tgn:7029392"
        ],
        "placetype": [
          "aat:300008699"
        ],
        "id": 2152195,
        "name:xx": "Bay Branch"
      }
    },
    {
      "geometry": {
        "type": "Point",
        "coordinates": [
          -83.3333,
          30.9333
        ]
      },
      "type": "Feature",
      "properties": {
        "hierarchy": [
          "tgn:2152196",
          "tgn:1000001",
          "tgn:7012149",
          "tgn:2000383",
          "tgn:7007248",
          "tgn:7029392"
        ],
        "placetype": [
          "aat:300008699"
        ],
        "id": 2152196,
        "name:xx": "Bay Branch"
      }
    },
    {
      "geometry": {
        "type": "Point",
        "coordinates": [
          -83.95,
          30.9167
        ]
      },
      "type": "Feature",
      "properties": {
        "hierarchy": [
          "tgn:2152197",
          "tgn:1000001",
          "tgn:7012149",
          "tgn:7014371",
          "tgn:7007248",
          "tgn:7029392"
        ],
        "placetype": [
          "aat:300008699"
        ],
        "id": 2152197,
        "name:xx": "Bay Branch"
      }
    },
    {
      "geometry": {
        "type": "Point",
        "coordinates": [
          -83.5,
          30.9667
        ]
      },
      "type": "Feature",
      "properties": {
        "hierarchy": [
          "tgn:2152198",
          "tgn:1000001",
          "tgn:2000305",
          "tgn:7012149",
          "tgn:7007248",
          "tgn:7029392"
        ],
        "placetype": [
          "aat:300008699"
        ],
        "id": 2152198,
        "name:xx": "Bay Branch"
      }
    },
    {
      "geometry": {
        "type": "Point",
        "coordinates": [
          -83.95,
          31.4167
        ]
      },
      "type": "Feature",
      "properties": {
        "hierarchy": [
          "tgn:2152199",
          "tgn:1000001",
          "tgn:7012149",
          "tgn:2000450",
          "tgn:7007248",
          "tgn:7029392"
        ],
        "placetype": [
          "aat:300008699"
        ],
        "id": 2152199,
        "name:xx": "Bay Branch"
      }
    }
  ]
}
