{
  "type": "FeatureCollection",
  "features": [
    {
      "geometry": {
        "type": "Point",
        "coordinates": [
          -86.35,
          37.3
        ]
      },
      "type": "Feature",
      "properties": {
        "hierarchy": [
          "tgn:2753710",
          "tgn:1000001",
          "tgn:7012149",
          "tgn:2000787",
          "tgn:7007255",
          "tgn:7029392"
        ],
        "placetype": [
          "aat:300008699"
        ],
        "id": 2753710,
        "name:xx": "Watery Branch"
      }
    },
    {
      "geometry": {
        "type": "Point",
        "coordinates": [
          -77.8333,
          35.55
        ]
      },
      "type": "Feature",
      "properties": {
        "hierarchy": [
          "tgn:2753711",
          "tgn:1000001",
          "tgn:7012149",
          "tgn:2001552",
          "tgn:7007709",
          "tgn:7029392"
        ],
        "placetype": [
          "aat:300008347"
        ],
        "id": 2753711,
        "name:xx": "Watery Branch"
      }
    },
    {
      "geometry": {
        "type": "Point",
        "coordinates": [
          -78.4333,
          35.4167
        ]
      },
      "type": "Feature",
      "properties": {
        "hierarchy": [
          "tgn:2753712",
          "tgn:1000001",
          "tgn:7012149",
          "tgn:2001509",
          "tgn:7007709",
          "tgn:7029392"
        ],
        "placetype": [
          "aat:300008699"
        ],
        "id": 2753712,
        "name:xx": "Watery Branch"
      }
    },
    {
      "geometry": {
        "type": "Point",
        "coordinates": [
          -77.8667,
          35.5333
        ]
      },
      "type": "Feature",
      "properties": {
        "hierarchy": [
          "tgn:2753713",
          "tgn:1000001",
          "tgn:7012149",
          "tgn:7007709",
          "tgn:7029392"
        ],
        "placetype": [
          "aat:300008699"
        ],
        "id": 2753713,
        "name:xx": "Watery Branch"
      }
    },
    {
      "geometry": {
        "type": "Point",
        "coordinates": [
          -79.7667,
          34.85
        ]
      },
      "type": "Feature",
      "properties": {
        "hierarchy": [
          "tgn:2753714",
          "tgn:1000001",
          "tgn:7012149",
          "tgn:2001533",
          "tgn:7007709",
          "tgn:7029392"
        ],
        "placetype": [
          "aat:300008699"
        ],
        "id": 2753714,
        "name:xx": "Watery Branch"
      }
    },
    {
      "geometry": {
        "type": "Point",
        "coordinates": [
          -79.4,
          34.95
        ]
      },
      "type": "Feature",
      "properties": {
        "hierarchy": [
          "tgn:2753715",
          "tgn:1000001",
          "tgn:7012149",
          "tgn:2001539",
          "tgn:7007709",
          "tgn:7029392"
        ],
        "placetype": [
          "aat:300008699"
        ],
        "id": 2753715,
        "name:xx": "Watery Branch"
      }
    },
    {
      "geometry": {
        "type": "Point",
        "coordinates": [
          -79.9667,
          35.3667
        ]
      },
      "type": "Feature",
      "properties": {
        "hierarchy": [
          "tgn:2753716",
          "tgn:1000001",
          "tgn:7012149",
          "tgn:2001520",
          "tgn:7007709",
          "tgn:7029392"
        ],
        "placetype": [
          "aat:300008699"
        ],
        "id": 2753716,
        "name:xx": "Watery Branch"
      }
    },
    {
      "geometry": {
        "type": "Point",
        "coordinates": [
          -87.5167,
          35.4667
        ]
      },
      "type": "Feature",
      "properties": {
        "hierarchy": [
          "tgn:2753717",
          "tgn:1000001",
          "tgn:7012149",
          "tgn:2001887",
          "tgn:7007825",
          "tgn:7029392"
        ],
        "placetype": [
          "aat:300008699"
        ],
        "id": 2753717,
        "name:xx": "Watery Branch"
      }
    },
    {
      "geometry": {
        "type": "Point",
        "coordinates": [
          -94.0167,
          31.9
        ]
      },
      "type": "Feature",
      "properties": {
        "hierarchy": [
          "tgn:2753718",
          "tgn:1000001",
          "tgn:7012149",
          "tgn:2002073",
          "tgn:7007826",
          "tgn:7029392"
        ],
        "placetype": [
          "aat:300008706"
        ],
        "id": 2753718,
        "name:xx": "Watery Creek"
      }
    },
    {
      "geometry": {
        "type": "Point",
        "coordinates": [
          -79.1667,
          35.9833
        ]
      },
      "type": "Feature",
      "properties": {
        "hierarchy": [
          "tgn:2753719",
          "tgn:1000001",
          "tgn:7012149",
          "tgn:2001525",
          "tgn:7007709",
          "tgn:7029392"
        ],
        "placetype": [
          "aat:300008699"
        ],
        "id": 2753719,
        "name:xx": "Watery Fork"
      }
    }
  ]
}
