{
  "geometry": {
    "type": "Point",
    "coordinates": [
      -86.8833,
      35.9167
    ]
  },
  "type": "Feature",
  "properties": {
    "hierarchy": [
      "tgn:2614405",
      "tgn:1000001",
      "tgn:7012149",
      "tgn:2001930",
      "tgn:7007825",
      "tgn:7029392"
    ],
    "placetype": [
      "aat:300008699"
    ],
    "id": 2614405,
    "name:xx": "Reid Hill Branch"
  }
}
