{
  "geometry": {
    "type": "Point",
    "coordinates": [
      -91.3833,
      44.95
    ]
  },
  "type": "Feature",
  "properties": {
    "hierarchy": [
      "tgn:2351463",
      "tgn:1000001",
      "tgn:2002313",
      "tgn:7012149",
      "tgn:7007922",
      "tgn:7029392"
    ],
    "placetype": [
      "aat:300006191"
    ],
    "id": 2351463,
    "name:xx": "Glen Lock Lake"
  }
}
