{
  "type": "FeatureCollection",
  "features": [
    {
      "geometry": {
        "type": "Point",
        "coordinates": [
          -96.9,
          41.6167
        ]
      },
      "type": "Feature",
      "properties": {
        "hierarchy": [
          "tgn:2270250",
          "tgn:1000001",
          "tgn:7012149",
          "tgn:7007525",
          "tgn:7029392"
        ],
        "placetype": [
          "aat:300008706"
        ],
        "id": 2270250,
        "name:xx": "Crystal Creek"
      }
    },
    {
      "geometry": {
        "type": "Point",
        "coordinates": [
          -108.85,
          36.0833
        ]
      },
      "type": "Feature",
      "properties": {
        "hierarchy": [
          "tgn:2270251",
          "tgn:1000001",
          "tgn:7012149",
          "tgn:2001452",
          "tgn:7007566",
          "tgn:7029392"
        ],
        "placetype": [
          "aat:300008706"
        ],
        "id": 2270251,
        "name:xx": "Crystal Creek"
      }
    },
    {
      "geometry": {
        "type": "Point",
        "coordinates": [
          -75.2,
          43.4833
        ]
      },
      "type": "Feature",
      "properties": {
        "hierarchy": [
          "tgn:2270252",
          "tgn:1000001",
          "tgn:7012149",
          "tgn:7014287",
          "tgn:7007568",
          "tgn:7029392"
        ],
        "placetype": [
          "aat:300008706"
        ],
        "id": 2270252,
        "name:xx": "Crystal Creek"
      }
    },
    {
      "geometry": {
        "type": "Point",
        "coordinates": [
          -75.2667,
          43.8167
        ]
      },
      "type": "Feature",
      "properties": {
        "hierarchy": [
          "tgn:2270253",
          "tgn:1000001",
          "tgn:7012149",
          "tgn:1002593",
          "tgn:7007568",
          "tgn:7029392"
        ],
        "placetype": [
          "aat:300008706"
        ],
        "id": 2270253,
        "name:xx": "Crystal Creek"
      }
    },
    {
      "geometry": {
        "type": "Point",
        "coordinates": [
          -73.9167,
          44.9167
        ]
      },
      "type": "Feature",
      "properties": {
        "hierarchy": [
          "tgn:2270254",
          "tgn:1000001",
          "tgn:1002284",
          "tgn:7012149",
          "tgn:7007568",
          "tgn:7029392"
        ],
        "placetype": [
          "aat:300008706"
        ],
        "id": 2270254,
        "name:xx": "Crystal Creek"
      }
    },
    {
      "geometry": {
        "type": "Point",
        "coordinates": [
          -96.7667,
          36.3833
        ]
      },
      "type": "Feature",
      "properties": {
        "hierarchy": [
          "tgn:2270255",
          "tgn:1000001",
          "tgn:7012149",
          "tgn:2001681",
          "tgn:7007707",
          "tgn:7029392"
        ],
        "placetype": [
          "aat:300008706"
        ],
        "id": 2270255,
        "name:xx": "Crystal Creek"
      }
    },
    {
      "geometry": {
        "type": "Point",
        "coordinates": [
          -124.3667,
          42.85
        ]
      },
      "type": "Feature",
      "properties": {
        "hierarchy": [
          "tgn:2270256",
          "tgn:1000001",
          "tgn:2001704",
          "tgn:7012149",
          "tgn:7007708",
          "tgn:7029392"
        ],
        "placetype": [
          "aat:300008706"
        ],
        "id": 2270256,
        "name:xx": "Crystal Creek"
      }
    },
    {
      "geometry": {
        "type": "Point",
        "coordinates": [
          -122.0333,
          43.5667
        ]
      },
      "type": "Feature",
      "properties": {
        "hierarchy": [
          "tgn:2270257",
          "tgn:1000001",
          "tgn:7012149",
          "tgn:2001714",
          "tgn:7007708",
          "tgn:7029392"
        ],
        "placetype": [
          "aat:300008706"
        ],
        "id": 2270257,
        "name:xx": "Crystal Creek"
      }
    },
    {
      "geometry": {
        "type": "Point",
        "coordinates": [
          -122.6333,
          43.5833
        ]
      },
      "type": "Feature",
      "properties": {
        "hierarchy": [
          "tgn:2270258",
          "tgn:1000001",
          "tgn:7012149",
          "tgn:2001716",
          "tgn:7007708",
          "tgn:7029392"
        ],
        "placetype": [
          "aat:300008706"
        ],
        "id": 2270258,
        "name:xx": "Crystal Creek"
      }
    },
    {
      "geometry": {
        "type": "Point",
        "coordinates": [
          -123.8,
          44.6333
        ]
      },
      "type": "Feature",
      "properties": {
        "hierarchy": [
          "tgn:2270259",
          "tgn:1000001",
          "tgn:7012149",
          "tgn:1002599",
          "tgn:7007708",
          "tgn:7029392"
        ],
        "placetype": [
          "aat:300008706"
        ],
        "id": 2270259,
        "name:xx": "Crystal Creek"
      }
    }
  ]
}
