{
  "geometry": {
    "type": "Point",
    "coordinates": [
      47.1667,
      30.8333
    ]
  },
  "type": "Feature",
  "properties": {
    "hierarchy": [
      "tgn:1111162",
      "tgn:1000004",
      "tgn:1000118",
      "tgn:7029392"
    ],
    "placetype": [
      "aat:300387091"
    ],
    "id": 1111162,
    "name:xx": "Ghudād, Wādī al-"
  }
}
