{
  "geometry": {
    "type": "Point",
    "coordinates": [
      70.8667,
      41.0333
    ]
  },
  "type": "Feature",
  "properties": {
    "hierarchy": [
      "tgn:1051203",
      "tgn:7011683",
      "tgn:1000004",
      "tgn:7006661",
      "tgn:7029392"
    ],
    "placetype": [
      "aat:300008347"
    ],
    "id": 1051203,
    "name:xx": "Charkesar"
  }
}
