{
  "geometry": {
    "type": "Point",
    "coordinates": [
      95.1667,
      19.7333
    ]
  },
  "type": "Feature",
  "properties": {
    "hierarchy": [
      "tgn:1066277",
      "tgn:1000004",
      "tgn:1002093",
      "tgn:1000108",
      "tgn:7029392"
    ],
    "placetype": [
      "aat:300008347"
    ],
    "id": 1066277,
    "name:xx": "Sinbaungwe"
  }
}
