{
  "geometry": {
    "type": "Point",
    "coordinates": [
      78.555833,
      29.91
    ]
  },
  "type": "Feature",
  "properties": {
    "hierarchy": [
      "tgn:7569976",
      "tgn:1000004",
      "tgn:7000198",
      "tgn:7031786",
      "tgn:7029392"
    ],
    "placetype": [
      "aat:300008347"
    ],
    "name:en": "Devīkhet",
    "id": 7569976
  }
}
