{
  "geometry": {
    "type": "Point",
    "coordinates": [
      -75.7667,
      38.5167
    ]
  },
  "type": "Feature",
  "properties": {
    "hierarchy": [
      "tgn:2485676",
      "tgn:1002338",
      "tgn:1000001",
      "tgn:7012149",
      "tgn:7007516",
      "tgn:7029392"
    ],
    "placetype": [
      "aat:300006075"
    ],
    "id": 2485676,
    "name:xx": "Laytons Ditch"
  }
}
