{
  "type": "FeatureCollection",
  "features": [
    {
      "geometry": {
        "type": "Point",
        "coordinates": [
          -116.7,
          32.9833
        ]
      },
      "type": "Feature",
      "properties": {
        "hierarchy": [
          "tgn:2303810",
          "tgn:1000001",
          "tgn:7012149",
          "tgn:7007157",
          "tgn:1002858",
          "tgn:7029392"
        ],
        "placetype": [
          "aat:300008798"
        ],
        "id": 2303810,
        "name:xx": "Eagle Peak"
      }
    },
    {
      "geometry": {
        "type": "Point",
        "coordinates": [
          -114.75,
          34.7667
        ]
      },
      "type": "Feature",
      "properties": {
        "hierarchy": [
          "tgn:2303811",
          "tgn:1000001",
          "tgn:7012149",
          "tgn:7007157",
          "tgn:1002857",
          "tgn:7029392"
        ],
        "placetype": [
          "aat:300008798"
        ],
        "id": 2303811,
        "name:xx": "Eagle Peak"
      }
    },
    {
      "geometry": {
        "type": "Point",
        "coordinates": [
          -120.6833,
          35.4167
        ]
      },
      "type": "Feature",
      "properties": {
        "hierarchy": [
          "tgn:2303812",
          "tgn:1000001",
          "tgn:7012149",
          "tgn:7007157",
          "tgn:1002863",
          "tgn:7029392"
        ],
        "placetype": [
          "aat:300008798"
        ],
        "id": 2303812,
        "name:xx": "Eagle Peak"
      }
    },
    {
      "geometry": {
        "type": "Point",
        "coordinates": [
          -108.1,
          37.7
        ]
      },
      "type": "Feature",
      "properties": {
        "hierarchy": [
          "tgn:2303813",
          "tgn:1000001",
          "tgn:7012149",
          "tgn:2000208",
          "tgn:7007158",
          "tgn:7029392"
        ],
        "placetype": [
          "aat:300008798"
        ],
        "id": 2303813,
        "name:xx": "Eagle Peak"
      }
    },
    {
      "geometry": {
        "type": "Point",
        "coordinates": [
          -106.5667,
          39.4333
        ]
      },
      "type": "Feature",
      "properties": {
        "hierarchy": [
          "tgn:2303814",
          "tgn:1000001",
          "tgn:7012149",
          "tgn:2000210",
          "tgn:7007158",
          "tgn:7029392"
        ],
        "placetype": [
          "aat:300008798"
        ],
        "id": 2303814,
        "name:xx": "Eagle Peak"
      }
    },
    {
      "geometry": {
        "type": "Point",
        "coordinates": [
          -105.7167,
          38.2167
        ]
      },
      "type": "Feature",
      "properties": {
        "hierarchy": [
          "tgn:2303815",
          "tgn:1000001",
          "tgn:7012149",
          "tgn:2000205",
          "tgn:7007158",
          "tgn:7029392"
        ],
        "placetype": [
          "aat:300008798"
        ],
        "id": 2303815,
        "name:xx": "Eagle Peak"
      }
    },
    {
      "geometry": {
        "type": "Point",
        "coordinates": [
          -116.4833,
          47.4333
        ]
      },
      "type": "Feature",
      "properties": {
        "hierarchy": [
          "tgn:2303816",
          "tgn:1000001",
          "tgn:7012149",
          "tgn:2000479",
          "tgn:7007250",
          "tgn:7029392"
        ],
        "placetype": [
          "aat:300008798"
        ],
        "id": 2303816,
        "name:xx": "Eagle Peak"
      }
    },
    {
      "geometry": {
        "type": "Point",
        "coordinates": [
          -115.3667,
          47.2667
        ]
      },
      "type": "Feature",
      "properties": {
        "hierarchy": [
          "tgn:2303817",
          "tgn:1000001",
          "tgn:7012149",
          "tgn:2001290",
          "tgn:7007524",
          "tgn:7029392"
        ],
        "placetype": [
          "aat:300008798"
        ],
        "id": 2303817,
        "name:xx": "Eagle Peak"
      }
    },
    {
      "geometry": {
        "type": "Point",
        "coordinates": [
          -116.55,
          38.5333
        ]
      },
      "type": "Feature",
      "properties": {
        "hierarchy": [
          "tgn:2303818",
          "tgn:1000001",
          "tgn:2001418",
          "tgn:7012149",
          "tgn:7007526",
          "tgn:7029392"
        ],
        "placetype": [
          "aat:300008798"
        ],
        "id": 2303818,
        "name:xx": "Eagle Peak"
      }
    },
    {
      "geometry": {
        "type": "Point",
        "coordinates": [
          -108.5667,
          33.6667
        ]
      },
      "type": "Feature",
      "properties": {
        "hierarchy": [
          "tgn:2303819",
          "tgn:1000001",
          "tgn:2001429",
          "tgn:7012149",
          "tgn:7007566",
          "tgn:7029392"
        ],
        "placetype": [
          "aat:300008798"
        ],
        "id": 2303819,
        "name:xx": "Eagle Peak"
      }
    }
  ]
}
