{
  "geometry": {
    "type": "Point",
    "coordinates": [
      -110.5833,
      37.6667
    ]
  },
  "type": "Feature",
  "properties": {
    "hierarchy": [
      "tgn:2653367",
      "tgn:1000001",
      "tgn:2002109",
      "tgn:7012149",
      "tgn:7007827",
      "tgn:7029392"
    ],
    "placetype": [
      "aat:300008706"
    ],
    "id": 2653367,
    "name:xx": "Sevenmile Creek"
  }
}
