{
  "geometry": {
    "type": "Point",
    "coordinates": [
      -79.1167,
      40.0167
    ]
  },
  "type": "Feature",
  "properties": {
    "hierarchy": [
      "tgn:2729552",
      "tgn:1000001",
      "tgn:7012149",
      "tgn:1002904",
      "tgn:7007710",
      "tgn:7029392"
    ],
    "placetype": [
      "aat:300006191"
    ],
    "id": 2729552,
    "name:xx": "Trolls Lake"
  }
}
