{
  "geometry": {
    "type": "Point",
    "coordinates": [
      40.4833,
      -15.55
    ]
  },
  "type": "Feature",
  "properties": {
    "hierarchy": [
      "tgn:1091615",
      "tgn:7001242",
      "tgn:1000902",
      "tgn:1000180",
      "tgn:7029392"
    ],
    "placetype": [
      "aat:300008347"
    ],
    "id": 1091615,
    "name:xx": "Mogincual"
  }
}
