{
  "geometry": {
    "type": "Point",
    "coordinates": [
      55.65,
      -21.1166
    ]
  },
  "type": "Feature",
  "properties": {
    "hierarchy": [
      "tgn:7032250",
      "tgn:7001680",
      "tgn:7001242",
      "tgn:1000184",
      "tgn:7029392"
    ],
    "placetype": [
      "aat:300008798"
    ],
    "name:fr": "Saint-François, Mornes de",
    "id": 7032250
  }
}
