{
  "geometry": {
    "type": "Point",
    "coordinates": [
      32.659803,
      25.770604
    ]
  },
  "type": "Feature",
  "properties": {
    "hierarchy": [
      "tgn:7521455",
      "tgn:7001242",
      "tgn:7016833",
      "tgn:7001334",
      "tgn:7029392"
    ],
    "placetype": [
      "aat:300379998"
    ],
    "name:en": "Abū Ḩabashī, Wādī",
    "id": 7521455
  }
}
