{
  "geometry": {
    "type": "Point",
    "coordinates": [
      -155.3167,
      19.9667
    ]
  },
  "type": "Feature",
  "properties": {
    "hierarchy": [
      "tgn:2490834",
      "tgn:7023902",
      "tgn:1000001",
      "tgn:7012149",
      "tgn:7007249",
      "tgn:7029392"
    ],
    "placetype": [
      "aat:300008863"
    ],
    "id": 2490834,
    "name:xx": "Manowaialee Forest Reserve"
  }
}
