{
  "geometry": {
    "type": "Point",
    "coordinates": [
      -73.4833,
      41.55
    ]
  },
  "type": "Feature",
  "properties": {
    "hierarchy": [
      "tgn:2194841",
      "tgn:1002366",
      "tgn:1000001",
      "tgn:7012149",
      "tgn:7007159",
      "tgn:7029392"
    ],
    "placetype": [
      "aat:300008798"
    ],
    "id": 2194841,
    "name:xx": "Briggs Hill"
  }
}
