{
  "geometry": {
    "type": "Point",
    "coordinates": [
      21.1667,
      49.6667
    ]
  },
  "type": "Feature",
  "properties": {
    "hierarchy": [
      "tgn:7007719",
      "tgn:1000003",
      "tgn:7024127",
      "tgn:7006366",
      "tgn:7029392"
    ],
    "placetype": [
      "aat:300008347",
      "aat:300000835",
      "aat:300008375",
      "aat:300387302"
    ],
    "id": 7007719,
    "name:xx": "Gorlice"
  }
}
