{
  "geometry": {
    "type": "Point",
    "coordinates": [
      -122.6833,
      47.6333
    ]
  },
  "type": "Feature",
  "properties": {
    "hierarchy": [
      "tgn:2116792",
      "tgn:1000001",
      "tgn:7012149",
      "tgn:1002552",
      "tgn:7007920",
      "tgn:7029392"
    ],
    "placetype": [
      "aat:300008347"
    ],
    "id": 2116792,
    "name:xx": "Silverdale"
  }
}
