{
  "geometry": {
    "type": "Point",
    "coordinates": [
      -79.1333,
      33.9667
    ]
  },
  "type": "Feature",
  "properties": {
    "hierarchy": [
      "tgn:2095607",
      "tgn:1000001",
      "tgn:7012149",
      "tgn:2001750",
      "tgn:7007712",
      "tgn:7029392"
    ],
    "placetype": [
      "aat:300008347"
    ],
    "id": 2095607,
    "name:xx": "Cool Spring"
  }
}
