{
  "geometry": {
    "type": "Point",
    "coordinates": [
      -89.9167,
      35.4167
    ]
  },
  "type": "Feature",
  "properties": {
    "hierarchy": [
      "tgn:2632517",
      "tgn:1000001",
      "tgn:7012149",
      "tgn:7007825",
      "tgn:7029392"
    ],
    "placetype": [
      "aat:300008706"
    ],
    "id": 2632517,
    "name:xx": "Royster Creek"
  }
}
