{
  "geometry": {
    "type": "Point",
    "coordinates": [
      -111.8167,
      43.45
    ]
  },
  "type": "Feature",
  "properties": {
    "hierarchy": [
      "tgn:2178700",
      "tgn:1000001",
      "tgn:2000461",
      "tgn:7012149",
      "tgn:7007250",
      "tgn:7029392"
    ],
    "placetype": [
      "aat:300008706"
    ],
    "id": 2178700,
    "name:xx": "Blacktail Creek"
  }
}
