{
  "geometry": {
    "type": "Point",
    "coordinates": [
      -116.3333,
      41.9833
    ]
  },
  "type": "Feature",
  "properties": {
    "hierarchy": [
      "tgn:2627500",
      "tgn:1000001",
      "tgn:7012149",
      "tgn:7029392"
    ],
    "placetype": [
      "aat:300006191"
    ],
    "id": 2627500,
    "name:xx": "Roger Smith Reservoir"
  }
}
