{
  "geometry": {
    "type": "Point",
    "coordinates": [
      -94.7667,
      30.65
    ]
  },
  "type": "Feature",
  "properties": {
    "hierarchy": [
      "tgn:2784813",
      "tgn:1000001",
      "tgn:7012149",
      "tgn:1002795",
      "tgn:7007826",
      "tgn:7029392"
    ],
    "placetype": [
      "aat:300008699"
    ],
    "id": 2784813,
    "name:xx": "Yellow Branch"
  }
}
