{
  "geometry": {
    "type": "Point",
    "coordinates": [
      -107.4167,
      35.7833
    ]
  },
  "type": "Feature",
  "properties": {
    "hierarchy": [
      "tgn:2619532",
      "tgn:1000001",
      "tgn:7012149",
      "tgn:7019676",
      "tgn:7007566",
      "tgn:7029392"
    ],
    "placetype": [
      "aat:300008699"
    ],
    "id": 2619532,
    "name:xx": "Rincon Marquez Arroyo"
  }
}
