{
  "geometry": {
    "type": "Point",
    "coordinates": [
      76.394076,
      24.7312
    ]
  },
  "type": "Feature",
  "properties": {
    "hierarchy": [
      "tgn:7576311",
      "tgn:1000004",
      "tgn:7000198",
      "tgn:7016788",
      "tgn:7029392"
    ],
    "placetype": [
      "aat:300008347"
    ],
    "name:en": "Khānpur",
    "id": 7576311
  }
}
