{
  "type": "FeatureCollection",
  "features": [
    {
      "geometry": {
        "type": "Point",
        "coordinates": [
          13.3667,
          42.0833
        ]
      },
      "type": "Feature",
      "properties": {
        "hierarchy": [
          "tgn:1045181",
          "tgn:7009084",
          "tgn:7004154",
          "tgn:1000003",
          "tgn:1000080",
          "tgn:7029392"
        ],
        "placetype": [
          "aat:300008347"
        ],
        "id": 1045181,
        "name:xx": "Magliano de' Marsi"
      }
    },
    {
      "geometry": {
        "type": "Point",
        "coordinates": [
          11.283333,
          42.6
        ]
      },
      "type": "Feature",
      "properties": {
        "hierarchy": [
          "tgn:1045182",
          "tgn:1003460",
          "tgn:1000003",
          "tgn:7009760",
          "tgn:1000080",
          "tgn:7029392"
        ],
        "placetype": [
          "aat:300008347"
        ],
        "id": 1045182,
        "name:xx": "Magliano in Toscana"
      }
    },
    {
      "geometry": {
        "type": "Point",
        "coordinates": [
          8.8,
          45.583333
        ]
      },
      "type": "Feature",
      "properties": {
        "hierarchy": [
          "tgn:1045184",
          "tgn:7003150",
          "tgn:1000003",
          "tgn:7003237",
          "tgn:1000080",
          "tgn:7029392"
        ],
        "placetype": [
          "aat:300008347"
        ],
        "id": 1045184,
        "name:xx": "Magnago"
      }
    },
    {
      "geometry": {
        "type": "Point",
        "coordinates": [
          11.2,
          46.283333
        ]
      },
      "type": "Feature",
      "properties": {
        "hierarchy": [
          "tgn:1045185",
          "tgn:1003440",
          "tgn:1000003",
          "tgn:7003124",
          "tgn:1000080",
          "tgn:7029392"
        ],
        "placetype": [
          "aat:300008347"
        ],
        "id": 1045185,
        "name:xx": "Magrè"
      }
    },
    {
      "geometry": {
        "type": "Point",
        "coordinates": [
          13.074444,
          46.186667
        ]
      },
      "type": "Feature",
      "properties": {
        "hierarchy": [
          "tgn:1045186",
          "tgn:1003506",
          "tgn:1000003",
          "tgn:7002993",
          "tgn:1000080",
          "tgn:7029392"
        ],
        "placetype": [
          "aat:300008347"
        ],
        "id": 1045186,
        "name:xx": "Maiano"
      }
    },
    {
      "geometry": {
        "type": "Point",
        "coordinates": [
          16.366667,
          38.85
        ]
      },
      "type": "Feature",
      "properties": {
        "hierarchy": [
          "tgn:1045187",
          "tgn:1003447",
          "tgn:7007850",
          "tgn:1000003",
          "tgn:1000080",
          "tgn:7029392"
        ],
        "placetype": [
          "aat:300008347"
        ],
        "id": 1045187,
        "name:xx": "Maida"
      }
    },
    {
      "geometry": {
        "type": "Point",
        "coordinates": [
          16.183333,
          38.7
        ]
      },
      "type": "Feature",
      "properties": {
        "hierarchy": [
          "tgn:1045188",
          "tgn:7007850",
          "tgn:7024842",
          "tgn:1000003",
          "tgn:1000080",
          "tgn:7029392"
        ],
        "placetype": [
          "aat:300008347"
        ],
        "id": 1045188,
        "name:xx": "Maierato"
      }
    },
    {
      "geometry": {
        "type": "Point",
        "coordinates": [
          13.1,
          43.466667
        ]
      },
      "type": "Feature",
      "properties": {
        "hierarchy": [
          "tgn:1045189",
          "tgn:1003429",
          "tgn:1000003",
          "tgn:7003240",
          "tgn:1000080",
          "tgn:7029392"
        ],
        "placetype": [
          "aat:300008347"
        ],
        "id": 1045189,
        "name:xx": "Maiolati Spontini"
      }
    }
  ]
}
