{
  "geometry": {
    "type": "Point",
    "coordinates": [
      -75.05,
      40.7167
    ]
  },
  "type": "Feature",
  "properties": {
    "hierarchy": [
      "tgn:2064213",
      "tgn:1000001",
      "tgn:1002985",
      "tgn:7012149",
      "tgn:7007565",
      "tgn:7029392"
    ],
    "placetype": [
      "aat:300008347"
    ],
    "id": 2064213,
    "name:xx": "Broadway"
  }
}
