{
  "type": "FeatureCollection",
  "features": [
    {
      "geometry": {
        "type": "Point",
        "coordinates": [
          15.4833,
          58.4667
        ]
      },
      "type": "Feature",
      "properties": {
        "hierarchy": [
          "tgn:1100030",
          "tgn:1000003",
          "tgn:7003775",
          "tgn:1000097",
          "tgn:7029392"
        ],
        "placetype": [
          "aat:300007466"
        ],
        "id": 1100030,
        "name:xx": "Vreta kloster"
      }
    },
    {
      "geometry": {
        "type": "Point",
        "coordinates": [
          -3.2,
          53.2833
        ]
      },
      "type": "Feature",
      "properties": {
        "hierarchy": [
          "tgn:1100036",
          "tgn:7002443",
          "tgn:7026278",
          "tgn:1000003",
          "tgn:7008591",
          "tgn:7029392"
        ],
        "placetype": [
          "aat:300000642"
        ],
        "id": 1100036,
        "name:xx": "Basingwerk Abbey"
      }
    },
    {
      "geometry": {
        "type": "Point",
        "coordinates": [
          0.6667,
          51.7333
        ]
      },
      "type": "Feature",
      "properties": {
        "hierarchy": [
          "tgn:1100037",
          "tgn:7002445",
          "tgn:1000003",
          "tgn:7008131",
          "tgn:7008591",
          "tgn:7029392"
        ],
        "placetype": [
          "aat:300000642"
        ],
        "id": 1100037,
        "name:xx": "Beeleigh Abbey"
      }
    },
    {
      "geometry": {
        "type": "Point",
        "coordinates": [
          -1.9,
          53.9833
        ]
      },
      "type": "Feature",
      "properties": {
        "hierarchy": [
          "tgn:1100038",
          "tgn:7002445",
          "tgn:1000003",
          "tgn:7008166",
          "tgn:7008591",
          "tgn:7029392"
        ],
        "placetype": [
          "aat:300000642"
        ],
        "id": 1100038,
        "name:xx": "Bolton Abbey"
      }
    },
    {
      "geometry": {
        "type": "Point",
        "coordinates": [
          13.483333,
          41.666667
        ]
      },
      "type": "Feature",
      "properties": {
        "hierarchy": [
          "tgn:1100039",
          "tgn:7003135",
          "tgn:1000003",
          "tgn:7003080",
          "tgn:1000080",
          "tgn:7029392"
        ],
        "placetype": [
          "aat:300000642",
          "aat:300000641"
        ],
        "id": 1100039,
        "name:xx": "Casamari, Abbazia di"
      }
    }
  ]
}
