{
  "geometry": {
    "type": "Point",
    "coordinates": [
      7.4833,
      47.6333
    ]
  },
  "type": "Feature",
  "properties": {
    "hierarchy": [
      "tgn:1032027",
      "tgn:7002870",
      "tgn:1000003",
      "tgn:1000070",
      "tgn:7029392"
    ],
    "placetype": [
      "aat:300008347"
    ],
    "id": 1032027,
    "name:xx": "Bartenheim"
  }
}
