{
  "type": "FeatureCollection",
  "features": [
    {
      "geometry": {
        "type": "Point",
        "coordinates": [
          -72.1,
          41.4333
        ]
      },
      "type": "Feature",
      "properties": {
        "hierarchy": [
          "tgn:2017480",
          "tgn:1000001",
          "tgn:1002714",
          "tgn:7012149",
          "tgn:7007159",
          "tgn:7029392"
        ],
        "placetype": [
          "aat:300008347"
        ],
        "id": 2017480,
        "name:xx": "Uncasville"
      }
    },
    {
      "geometry": {
        "type": "Point",
        "coordinates": [
          -72.15,
          41.9833
        ]
      },
      "type": "Feature",
      "properties": {
        "hierarchy": [
          "tgn:2017481",
          "tgn:1000001",
          "tgn:1002949",
          "tgn:7012149",
          "tgn:7007159",
          "tgn:7029392"
        ],
        "placetype": [
          "aat:300008347"
        ],
        "id": 2017481,
        "name:xx": "Union"
      }
    },
    {
      "geometry": {
        "type": "Point",
        "coordinates": [
          -72.8833,
          41.75
        ]
      },
      "type": "Feature",
      "properties": {
        "hierarchy": [
          "tgn:2017482",
          "tgn:1000001",
          "tgn:1002461",
          "tgn:7012149",
          "tgn:7007159",
          "tgn:7029392"
        ],
        "placetype": [
          "aat:300008347"
        ],
        "id": 2017482,
        "name:xx": "Unionville"
      }
    },
    {
      "geometry": {
        "type": "Point",
        "coordinates": [
          -73.25,
          41.3167
        ]
      },
      "type": "Feature",
      "properties": {
        "hierarchy": [
          "tgn:2017483",
          "tgn:1002366",
          "tgn:1000001",
          "tgn:7012149",
          "tgn:7007159",
          "tgn:7029392"
        ],
        "placetype": [
          "aat:300008347"
        ],
        "id": 2017483,
        "name:xx": "Upper Stepney"
      }
    },
    {
      "geometry": {
        "type": "Point",
        "coordinates": [
          -72.4667,
          41.8167
        ]
      },
      "type": "Feature",
      "properties": {
        "hierarchy": [
          "tgn:2017484",
          "tgn:1000001",
          "tgn:1002949",
          "tgn:7012149",
          "tgn:7007159",
          "tgn:7029392"
        ],
        "placetype": [
          "aat:300008347"
        ],
        "id": 2017484,
        "name:xx": "Vernon"
      }
    }
  ]
}
