{
  "geometry": {
    "type": "Point",
    "coordinates": [
      -75.2833,
      38.5833
    ]
  },
  "type": "Feature",
  "properties": {
    "hierarchy": [
      "tgn:2515594",
      "tgn:1002933",
      "tgn:1000001",
      "tgn:7012149",
      "tgn:7007239",
      "tgn:7029392"
    ],
    "placetype": [
      "aat:300006191"
    ],
    "id": 2515594,
    "name:xx": "Millsboro Pond"
  }
}
