{
  "geometry": {
    "type": "Point",
    "coordinates": [
      -111.6333,
      46.9833
    ]
  },
  "type": "Feature",
  "properties": {
    "hierarchy": [
      "tgn:2219431",
      "tgn:1000001",
      "tgn:2001266",
      "tgn:7012149",
      "tgn:7007524",
      "tgn:7029392"
    ],
    "placetype": [
      "aat:300008680"
    ],
    "id": 2219431,
    "name:xx": "Cannon Lake"
  }
}
