{
  "geometry": {
    "type": "Point",
    "coordinates": [
      13.7667,
      46.1333
    ]
  },
  "type": "Feature",
  "properties": {
    "hierarchy": [
      "tgn:1124815",
      "tgn:1000003",
      "tgn:7006670",
      "tgn:7029392"
    ],
    "placetype": [
      "aat:300008707"
    ],
    "id": 1124815,
    "name:xx": "Idrijca"
  }
}
