{
  "geometry": {
    "type": "Point",
    "coordinates": [
      -75.7167,
      39.7833
    ]
  },
  "type": "Feature",
  "properties": {
    "hierarchy": [
      "tgn:2682866",
      "tgn:7014201",
      "tgn:1000001",
      "tgn:7012149",
      "tgn:7007239",
      "tgn:7029392"
    ],
    "placetype": [
      "aat:300008347"
    ],
    "id": 2682866,
    "name:xx": "Southwood"
  }
}
