{
  "geometry": {
    "type": "Point",
    "coordinates": [
      -72.5333,
      41.4667
    ]
  },
  "type": "Feature",
  "properties": {
    "hierarchy": [
      "tgn:2590443",
      "tgn:1000001",
      "tgn:1002664",
      "tgn:7012149",
      "tgn:7007159",
      "tgn:7029392"
    ],
    "placetype": [
      "aat:300008699"
    ],
    "id": 2590443,
    "name:xx": "Pole Bridge Brook"
  }
}
