{
  "type": "FeatureCollection",
  "features": [
    {
      "geometry": {
        "type": "Point",
        "coordinates": [
          30.105545,
          30.526997
        ]
      },
      "type": "Feature",
      "properties": {
        "hierarchy": [
          "tgn:7536930",
          "tgn:7001242",
          "tgn:1001075",
          "tgn:7016833",
          "tgn:7029392"
        ],
        "placetype": [
          "aat:300008777"
        ],
        "name:en": "Jabābīn, Tallāt al",
        "id": 7536930
      }
    },
    {
      "geometry": {
        "type": "Point",
        "coordinates": [
          27.65,
          26.666667
        ]
      },
      "type": "Feature",
      "properties": {
        "hierarchy": [
          "tgn:7536932",
          "tgn:7001242",
          "tgn:7016833",
          "tgn:7001334",
          "tgn:7029392"
        ],
        "placetype": [
          "aat:300008777"
        ],
        "name:en": "'Izzah, Qūr al",
        "id": 7536932
      }
    },
    {
      "geometry": {
        "type": "Point",
        "coordinates": [
          25.444135,
          30.899542
        ]
      },
      "type": "Feature",
      "properties": {
        "hierarchy": [
          "tgn:7536933",
          "tgn:7001242",
          "tgn:7016833",
          "tgn:1001418",
          "tgn:7029392"
        ],
        "placetype": [
          "aat:300008777"
        ],
        "name:en": "'Izzah, Qārat",
        "id": 7536933
      }
    },
    {
      "geometry": {
        "type": "Point",
        "coordinates": [
          28.638338,
          28.036393
        ]
      },
      "type": "Feature",
      "properties": {
        "hierarchy": [
          "tgn:7536934",
          "tgn:7001242",
          "tgn:7016833",
          "tgn:7029392"
        ],
        "placetype": [
          "aat:300008697"
        ],
        "name:en": "'Izzah, 'Ayn al",
        "id": 7536934
      }
    },
    {
      "geometry": {
        "type": "Point",
        "coordinates": [
          26.242122,
          31.476747
        ]
      },
      "type": "Feature",
      "properties": {
        "hierarchy": [
          "tgn:7536935",
          "tgn:7001242",
          "tgn:7016833",
          "tgn:1001418",
          "tgn:7029392"
        ],
        "placetype": [
          "aat:300006207"
        ],
        "name:en": "Sāniyat Iznīn",
        "id": 7536935
      }
    },
    {
      "geometry": {
        "type": "Point",
        "coordinates": [
          25.533333,
          29.216667
        ]
      },
      "type": "Feature",
      "properties": {
        "hierarchy": [
          "tgn:7536936",
          "tgn:7001242",
          "tgn:7016833",
          "tgn:1001418",
          "tgn:7029392"
        ],
        "placetype": [
          "aat:300008347"
        ],
        "name:en": "'Izbat Zaydān",
        "id": 7536936
      }
    },
    {
      "geometry": {
        "type": "Point",
        "coordinates": [
          31.233333,
          31.216667
        ]
      },
      "type": "Feature",
      "properties": {
        "hierarchy": [
          "tgn:7536937",
          "tgn:7001242",
          "tgn:7016833",
          "tgn:1001335",
          "tgn:7029392"
        ],
        "placetype": [
          "aat:300008347"
        ],
        "name:en": "'Izbat 'Uthmān",
        "id": 7536937
      }
    },
    {
      "geometry": {
        "type": "Point",
        "coordinates": [
          31.7,
          30.666667
        ]
      },
      "type": "Feature",
      "properties": {
        "hierarchy": [
          "tgn:7536938",
          "tgn:7001242",
          "tgn:7016833",
          "tgn:1001113",
          "tgn:7029392"
        ],
        "placetype": [
          "aat:300008347"
        ],
        "id": 7536938,
        "name:xx": "'Izbat 'Urbān Awlād 'Alī"
      }
    },
    {
      "geometry": {
        "type": "Point",
        "coordinates": [
          30.281851,
          31.064697
        ]
      },
      "type": "Feature",
      "properties": {
        "hierarchy": [
          "tgn:7536939",
          "tgn:7001242",
          "tgn:1001075",
          "tgn:7016833",
          "tgn:7029392"
        ],
        "placetype": [
          "aat:300008347"
        ],
        "name:en": "'Izbat Umm al Laban",
        "id": 7536939
      }
    }
  ]
}
