{
  "geometry": {
    "type": "Point",
    "coordinates": [
      -87.6833,
      39.8667
    ]
  },
  "type": "Feature",
  "properties": {
    "hierarchy": [
      "tgn:2028889",
      "tgn:1000001",
      "tgn:2000504",
      "tgn:7012149",
      "tgn:7007251",
      "tgn:7029392"
    ],
    "placetype": [
      "aat:300387016"
    ],
    "id": 2028889,
    "name:xx": "Mabel"
  }
}
