{
  "geometry": {
    "type": "Point",
    "coordinates": [
      -78.5333,
      33.9167
    ]
  },
  "type": "Feature",
  "properties": {
    "hierarchy": [
      "tgn:2453183",
      "tgn:1000001",
      "tgn:2001472",
      "tgn:7012149",
      "tgn:7007709",
      "tgn:7029392"
    ],
    "placetype": [
      "aat:300008699"
    ],
    "id": 2453183,
    "name:xx": "Little Cawcaw Swamp"
  }
}
