{
  "geometry": {
    "type": "Point",
    "coordinates": [
      -111.4333,
      46.1667
    ]
  },
  "type": "Feature",
  "properties": {
    "hierarchy": [
      "tgn:2171414",
      "tgn:1000001",
      "tgn:2001263",
      "tgn:7012149",
      "tgn:7007524",
      "tgn:7029392"
    ],
    "placetype": [
      "aat:300006075"
    ],
    "id": 2171414,
    "name:xx": "Big Springs Ditch"
  }
}
