{
  "geometry": {
    "type": "Point",
    "coordinates": [
      -89.1667,
      34.0833
    ]
  },
  "type": "Feature",
  "properties": {
    "hierarchy": [
      "tgn:2218947",
      "tgn:1000001",
      "tgn:7012149",
      "tgn:7007522",
      "tgn:7029392"
    ],
    "placetype": [
      "aat:300008699"
    ],
    "id": 2218947,
    "name:xx": "Caney Branch"
  }
}
