{
  "geometry": {
    "type": "Point",
    "coordinates": [
      -85.9667,
      35.9333
    ]
  },
  "type": "Feature",
  "properties": {
    "hierarchy": [
      "tgn:2372575",
      "tgn:1000001",
      "tgn:7012149",
      "tgn:7022246",
      "tgn:7007825",
      "tgn:7029392"
    ],
    "placetype": [
      "aat:300008746"
    ],
    "id": 2372575,
    "name:xx": "Hall Cave"
  }
}
