{
  "geometry": {
    "type": "Point",
    "coordinates": [
      -75.35,
      41.9833
    ]
  },
  "type": "Feature",
  "properties": {
    "hierarchy": [
      "tgn:2283211",
      "tgn:1000001",
      "tgn:7012149",
      "tgn:7007710",
      "tgn:7029392"
    ],
    "placetype": [
      "aat:300008761"
    ],
    "id": 2283211,
    "name:xx": "Delaware River Gorge"
  }
}
