{
  "geometry": {
    "type": "Point",
    "coordinates": [
      -90.2667,
      38.15
    ]
  },
  "type": "Feature",
  "properties": {
    "hierarchy": [
      "tgn:2434253",
      "tgn:1000001",
      "tgn:7012149",
      "tgn:1002677",
      "tgn:7007251",
      "tgn:7029392"
    ],
    "placetype": [
      "aat:300008347"
    ],
    "id": 2434253,
    "name:xx": "Kemper Landing"
  }
}
