{
  "geometry": {
    "type": "Point",
    "coordinates": [
      -83.4167,
      37.35
    ]
  },
  "type": "Feature",
  "properties": {
    "hierarchy": [
      "tgn:2189991",
      "tgn:1000001",
      "tgn:2000772",
      "tgn:7012149",
      "tgn:7007255",
      "tgn:7029392"
    ],
    "placetype": [
      "aat:300008706"
    ],
    "id": 2189991,
    "name:xx": "Bowling Creek"
  }
}
