{
  "geometry": {
    "type": "Point",
    "coordinates": [
      -74.5667,
      42.7833
    ]
  },
  "type": "Feature",
  "properties": {
    "hierarchy": [
      "tgn:2195125",
      "tgn:1000001",
      "tgn:7012149",
      "tgn:7007568",
      "tgn:7029392"
    ],
    "placetype": [
      "aat:300008706"
    ],
    "id": 2195125,
    "name:xx": "Brimstone Creek"
  }
}
