{
  "geometry": {
    "type": "Point",
    "coordinates": [
      -108.0167,
      32.8333
    ]
  },
  "type": "Feature",
  "properties": {
    "hierarchy": [
      "tgn:2534849",
      "tgn:1000001",
      "tgn:7012149",
      "tgn:2001437",
      "tgn:7007566",
      "tgn:7029392"
    ],
    "placetype": [
      "aat:300000390"
    ],
    "id": 2534849,
    "name:xx": "Naiad Queen Mine"
  }
}
