{
  "geometry": {
    "type": "Point",
    "coordinates": [
      -118.45,
      45.1833
    ]
  },
  "type": "Feature",
  "properties": {
    "hierarchy": [
      "tgn:2499114",
      "tgn:1000001",
      "tgn:7012149",
      "tgn:2001721",
      "tgn:7007708",
      "tgn:7029392"
    ],
    "placetype": [
      "aat:300008697"
    ],
    "id": 2499114,
    "name:xx": "McCarty Spring"
  }
}
