{
  "geometry": {
    "type": "Point",
    "coordinates": [
      -92.8333,
      29.9167
    ]
  },
  "type": "Feature",
  "properties": {
    "hierarchy": [
      "tgn:2483585",
      "tgn:1000001",
      "tgn:7020676",
      "tgn:7012149",
      "tgn:7007256",
      "tgn:7029392"
    ],
    "placetype": [
      "aat:300008699"
    ],
    "id": 2483585,
    "name:xx": "Latania Bayou"
  }
}
