{
  "geometry": {
    "type": "Point",
    "coordinates": [
      -9.1667,
      8.2667
    ]
  },
  "type": "Feature",
  "properties": {
    "hierarchy": [
      "tgn:1090244",
      "tgn:7001242",
      "tgn:7000795",
      "tgn:1000167",
      "tgn:7029392"
    ],
    "placetype": [
      "aat:300008347"
    ],
    "id": 1090244,
    "name:xx": "Irié"
  }
}
