{
  "type": "FeatureCollection",
  "features": [
    {
      "geometry": {
        "type": "Point",
        "coordinates": [
          12.216667,
          51.733333
        ]
      },
      "type": "Feature",
      "properties": {
        "hierarchy": [
          "tgn:7092000",
          "tgn:1000003",
          "tgn:7003687",
          "tgn:7000084",
          "tgn:7029392"
        ],
        "placetype": [
          "aat:300008347"
        ],
        "id": 7092000,
        "name:xx": "Vor der Heide"
      }
    },
    {
      "geometry": {
        "type": "Point",
        "coordinates": [
          14.283333,
          52.566667
        ]
      },
      "type": "Feature",
      "properties": {
        "hierarchy": [
          "tgn:7092001",
          "tgn:7000096",
          "tgn:1000003",
          "tgn:7000084",
          "tgn:7029392"
        ],
        "placetype": [
          "aat:300386887"
        ],
        "id": 7092001,
        "name:xx": "Vorderheide"
      }
    },
    {
      "geometry": {
        "type": "Point",
        "coordinates": [
          13.616667,
          52.433333
        ]
      },
      "type": "Feature",
      "properties": {
        "hierarchy": [
          "tgn:7092002",
          "tgn:7003712",
          "tgn:7003670",
          "tgn:1000003",
          "tgn:7000084",
          "tgn:7029392"
        ],
        "placetype": [
          "aat:300386887"
        ],
        "id": 7092002,
        "name:xx": "Vorderheide"
      }
    },
    {
      "geometry": {
        "type": "Point",
        "coordinates": [
          14.266667,
          52.366667
        ]
      },
      "type": "Feature",
      "properties": {
        "hierarchy": [
          "tgn:7092003",
          "tgn:7000096",
          "tgn:1000003",
          "tgn:7000084",
          "tgn:7029392"
        ],
        "placetype": [
          "aat:300386887"
        ],
        "id": 7092003,
        "name:xx": "Vorderheide"
      }
    },
    {
      "geometry": {
        "type": "Point",
        "coordinates": [
          12.7,
          51.666667
        ]
      },
      "type": "Feature",
      "properties": {
        "hierarchy": [
          "tgn:7092004",
          "tgn:1000003",
          "tgn:7003687",
          "tgn:7000084",
          "tgn:7029392"
        ],
        "placetype": [
          "aat:300386887"
        ],
        "id": 7092004,
        "name:xx": "Vorderheide"
      }
    },
    {
      "geometry": {
        "type": "Point",
        "coordinates": [
          11.866667,
          53.066667
        ]
      },
      "type": "Feature",
      "properties": {
        "hierarchy": [
          "tgn:7092005",
          "tgn:7000096",
          "tgn:1000003",
          "tgn:7000084",
          "tgn:7029392"
        ],
        "placetype": [
          "aat:300008863"
        ],
        "id": 7092005,
        "name:xx": "Vorderheide"
      }
    },
    {
      "geometry": {
        "type": "Point",
        "coordinates": [
          8.916667,
          52.4
        ]
      },
      "type": "Feature",
      "properties": {
        "hierarchy": [
          "tgn:7092006",
          "tgn:1000003",
          "tgn:7003677",
          "tgn:7000084",
          "tgn:7029392"
        ],
        "placetype": [
          "aat:300000206"
        ],
        "id": 7092006,
        "name:xx": "Vor der Heide"
      }
    },
    {
      "geometry": {
        "type": "Point",
        "coordinates": [
          11.466667,
          49.45
        ]
      },
      "type": "Feature",
      "properties": {
        "hierarchy": [
          "tgn:7092007",
          "tgn:7003669",
          "tgn:1000003",
          "tgn:7000084",
          "tgn:7029392"
        ],
        "placetype": [
          "aat:300008347"
        ],
        "id": 7092007,
        "name:xx": "Vorderhaslach"
      }
    },
    {
      "geometry": {
        "type": "Point",
        "coordinates": [
          8.066667,
          48.1
        ]
      },
      "type": "Feature",
      "properties": {
        "hierarchy": [
          "tgn:7092008",
          "tgn:7003692",
          "tgn:1000003",
          "tgn:7000084",
          "tgn:7029392"
        ],
        "placetype": [
          "aat:300008347"
        ],
        "id": 7092008,
        "name:xx": "Vorderhaslach"
      }
    },
    {
      "geometry": {
        "type": "Point",
        "coordinates": [
          12.966667,
          48.283333
        ]
      },
      "type": "Feature",
      "properties": {
        "hierarchy": [
          "tgn:7092009",
          "tgn:7003669",
          "tgn:1000003",
          "tgn:7000084",
          "tgn:7029392"
        ],
        "placetype": [
          "aat:300000206"
        ],
        "id": 7092009,
        "name:xx": "Vorder-Harpfing"
      }
    }
  ]
}
