{
  "geometry": {
    "type": "Point",
    "coordinates": [
      -79.8667,
      37.2333
    ]
  },
  "type": "Feature",
  "properties": {
    "hierarchy": [
      "tgn:2300978",
      "tgn:1000001",
      "tgn:7012149",
      "tgn:7014344",
      "tgn:7007919",
      "tgn:7029392"
    ],
    "placetype": [
      "aat:300008347"
    ],
    "id": 2300978,
    "name:xx": "Dundee"
  }
}
