{
  "geometry": {
    "type": "Point",
    "coordinates": [
      -112.8667,
      44.3333
    ]
  },
  "type": "Feature",
  "properties": {
    "hierarchy": [
      "tgn:2179988",
      "tgn:1000001",
      "tgn:7012149",
      "tgn:2000481",
      "tgn:7007250",
      "tgn:7029392"
    ],
    "placetype": [
      "aat:300008761"
    ],
    "id": 2179988,
    "name:xx": "Blind Canyon"
  }
}
