{
  "geometry": {
    "type": "Point",
    "coordinates": [
      -82.0167,
      26.7667
    ]
  },
  "type": "Feature",
  "properties": {
    "hierarchy": [
      "tgn:2393409",
      "tgn:1000001",
      "tgn:7012149",
      "tgn:7007240",
      "tgn:7029392"
    ],
    "placetype": [
      "aat:300008699"
    ],
    "id": 2393409,
    "name:xx": "Hog Branch"
  }
}
