{
  "geometry": {
    "type": "Point",
    "coordinates": [
      -163.3833,
      64.6667
    ]
  },
  "type": "Feature",
  "properties": {
    "hierarchy": [
      "tgn:2530963",
      "tgn:7006450",
      "tgn:1000001",
      "tgn:7012149",
      "tgn:2000079",
      "tgn:7029392"
    ],
    "placetype": [
      "aat:300008707"
    ],
    "id": 2530963,
    "name:xx": "Mudyutok River"
  }
}
