{
  "geometry": {
    "type": "Point",
    "coordinates": [
      -15.45,
      11.5833
    ]
  },
  "type": "Feature",
  "properties": {
    "hierarchy": [
      "tgn:1092335",
      "tgn:7001242",
      "tgn:7014990",
      "tgn:1000183",
      "tgn:7029392"
    ],
    "placetype": [
      "aat:300008347"
    ],
    "id": 1092335,
    "name:xx": "São João"
  }
}
