{
  "geometry": {
    "type": "Point",
    "coordinates": [
      -90.6667,
      38.5167
    ]
  },
  "type": "Feature",
  "properties": {
    "hierarchy": [
      "tgn:2222701",
      "tgn:1000001",
      "tgn:7012149",
      "tgn:7016167",
      "tgn:7007523",
      "tgn:7029392"
    ],
    "placetype": [
      "aat:300008706"
    ],
    "id": 2222701,
    "name:xx": "Carr Creek"
  }
}
