{
  "geometry": {
    "type": "Point",
    "coordinates": [
      120.4425,
      23.260833
    ]
  },
  "type": "Feature",
  "properties": {
    "hierarchy": [
      "tgn:7474144",
      "tgn:1000004",
      "tgn:7490934",
      "tgn:1000141",
      "tgn:7029392"
    ],
    "placetype": [
      "aat:300008347"
    ],
    "id": 7474144,
    "name:xx": "Yuantanzi"
  }
}
