{
  "geometry": {
    "type": "Point",
    "coordinates": [
      -112.3167,
      37.3333
    ]
  },
  "type": "Feature",
  "properties": {
    "hierarchy": [
      "tgn:2667974",
      "tgn:1000001",
      "tgn:7012149",
      "tgn:2002113",
      "tgn:7007827",
      "tgn:7029392"
    ],
    "placetype": [
      "aat:300008706"
    ],
    "id": 2667974,
    "name:xx": "Skutumpah Creek"
  }
}
