{
  "geometry": {
    "type": "Point",
    "coordinates": [
      -76.65,
      39.8833
    ]
  },
  "type": "Feature",
  "properties": {
    "hierarchy": [
      "tgn:2681701",
      "tgn:1000001",
      "tgn:7012149",
      "tgn:1003047",
      "tgn:7007710",
      "tgn:7029392"
    ],
    "placetype": [
      "aat:300008347"
    ],
    "id": 2681701,
    "name:xx": "South Ridge Estates"
  }
}
