{
  "geometry": {
    "type": "Point",
    "coordinates": [
      9.566667,
      50.25
    ]
  },
  "type": "Feature",
  "properties": {
    "hierarchy": [
      "tgn:7147807",
      "tgn:1000003",
      "tgn:7003678",
      "tgn:7000084",
      "tgn:7029392"
    ],
    "placetype": [
      "aat:300004792"
    ],
    "id": 7147807,
    "name:xx": "Försterei Kreuzgrund"
  }
}
