{
  "geometry": {
    "type": "Point",
    "coordinates": [
      33.620187,
      28.718672
    ]
  },
  "type": "Feature",
  "properties": {
    "hierarchy": [
      "tgn:7535888",
      "tgn:7001242",
      "tgn:7016833",
      "tgn:7001336",
      "tgn:7029392"
    ],
    "placetype": [
      "aat:300008686"
    ],
    "name:en": "Fayrān, Wāḩat",
    "id": 7535888
  }
}
