{
  "geometry": {
    "type": "Point",
    "coordinates": [
      -95.05,
      45.9167
    ]
  },
  "type": "Feature",
  "properties": {
    "hierarchy": [
      "tgn:2188232",
      "tgn:1000001",
      "tgn:7012149",
      "tgn:2001075",
      "tgn:7007521",
      "tgn:7029392"
    ],
    "placetype": [
      "aat:300008706"
    ],
    "id": 2188232,
    "name:xx": "Boss Creek"
  }
}
