{
  "geometry": {
    "type": "Point",
    "coordinates": [
      -85.3167,
      40.0167
    ]
  },
  "type": "Feature",
  "properties": {
    "hierarchy": [
      "tgn:2703495",
      "tgn:1000001",
      "tgn:7012149",
      "tgn:1002468",
      "tgn:7007252",
      "tgn:7029392"
    ],
    "placetype": [
      "aat:300006191"
    ],
    "id": 2703495,
    "name:xx": "Summit Lake Reservoir"
  }
}
