{
  "geometry": {
    "type": "Point",
    "coordinates": [
      -89.4667,
      14.3333
    ]
  },
  "type": "Feature",
  "properties": {
    "hierarchy": [
      "tgn:1016538",
      "tgn:7005465",
      "tgn:1000001",
      "tgn:7005441",
      "tgn:7029392"
    ],
    "placetype": [
      "aat:300008347"
    ],
    "id": 1016538,
    "name:xx": "Metapán"
  }
}
