{
  "type": "FeatureCollection",
  "features": [
    {
      "geometry": {
        "type": "Point",
        "coordinates": [
          -92.8667,
          32.0667
        ]
      },
      "type": "Feature",
      "properties": {
        "hierarchy": [
          "tgn:2151260",
          "tgn:1000001",
          "tgn:7012149",
          "tgn:2000917",
          "tgn:7007256",
          "tgn:7029392"
        ],
        "placetype": [
          "aat:300008699"
        ],
        "id": 2151260,
        "name:xx": "Bates Branch"
      }
    },
    {
      "geometry": {
        "type": "Point",
        "coordinates": [
          -91.5833,
          38.9333
        ]
      },
      "type": "Feature",
      "properties": {
        "hierarchy": [
          "tgn:2151261",
          "tgn:1000001",
          "tgn:7012149",
          "tgn:1002687",
          "tgn:7007523",
          "tgn:7029392"
        ],
        "placetype": [
          "aat:300008699"
        ],
        "id": 2151261,
        "name:xx": "Bates Branch"
      }
    },
    {
      "geometry": {
        "type": "Point",
        "coordinates": [
          -96.9333,
          41.1
        ]
      },
      "type": "Feature",
      "properties": {
        "hierarchy": [
          "tgn:2151264",
          "tgn:1000001",
          "tgn:7012149",
          "tgn:7007525",
          "tgn:7029392"
        ],
        "placetype": [
          "aat:300008699"
        ],
        "id": 2151264,
        "name:xx": "Bates Branch"
      }
    },
    {
      "geometry": {
        "type": "Point",
        "coordinates": [
          -80.6833,
          34.9167
        ]
      },
      "type": "Feature",
      "properties": {
        "hierarchy": [
          "tgn:2151265",
          "tgn:1000001",
          "tgn:7012149",
          "tgn:2001546",
          "tgn:7007709",
          "tgn:7029392"
        ],
        "placetype": [
          "aat:300008699"
        ],
        "id": 2151265,
        "name:xx": "Bates Branch"
      }
    },
    {
      "geometry": {
        "type": "Point",
        "coordinates": [
          -83.4,
          35.0833
        ]
      },
      "type": "Feature",
      "properties": {
        "hierarchy": [
          "tgn:2151266",
          "tgn:1000001",
          "tgn:7012149",
          "tgn:2001515",
          "tgn:7007709",
          "tgn:7029392"
        ],
        "placetype": [
          "aat:300008699"
        ],
        "id": 2151266,
        "name:xx": "Bates Branch"
      }
    },
    {
      "geometry": {
        "type": "Point",
        "coordinates": [
          -81.55,
          33.8833
        ]
      },
      "type": "Feature",
      "properties": {
        "hierarchy": [
          "tgn:2151267",
          "tgn:1000001",
          "tgn:7012149",
          "tgn:7007712",
          "tgn:7029392"
        ],
        "placetype": [
          "aat:300008699"
        ],
        "id": 2151267,
        "name:xx": "Bates Branch"
      }
    },
    {
      "geometry": {
        "type": "Point",
        "coordinates": [
          -86.3,
          35.5667
        ]
      },
      "type": "Feature",
      "properties": {
        "hierarchy": [
          "tgn:2151268",
          "tgn:1000001",
          "tgn:2001838",
          "tgn:7012149",
          "tgn:7007825",
          "tgn:7029392"
        ],
        "placetype": [
          "aat:300008699"
        ],
        "id": 2151268,
        "name:xx": "Bates Branch"
      }
    },
    {
      "geometry": {
        "type": "Point",
        "coordinates": [
          -88.05,
          35.6667
        ]
      },
      "type": "Feature",
      "properties": {
        "hierarchy": [
          "tgn:2151269",
          "tgn:1000001",
          "tgn:7012149",
          "tgn:2001856",
          "tgn:7007825",
          "tgn:7029392"
        ],
        "placetype": [
          "aat:300008699"
        ],
        "id": 2151269,
        "name:xx": "Bates Branch"
      }
    }
  ]
}
