{
  "geometry": {
    "type": "Point",
    "coordinates": [
      54.0667,
      55.15
    ]
  },
  "type": "Feature",
  "properties": {
    "hierarchy": [
      "tgn:1059766",
      "tgn:1000004",
      "tgn:7011498",
      "tgn:7002435",
      "tgn:7029392"
    ],
    "placetype": [
      "aat:300008347"
    ],
    "id": 1059766,
    "name:xx": "Starokuruchevo"
  }
}
