{
  "geometry": {
    "type": "Point",
    "coordinates": [
      -91.55,
      44.4167
    ]
  },
  "type": "Feature",
  "properties": {
    "hierarchy": [
      "tgn:2152051",
      "tgn:1000001",
      "tgn:7012149",
      "tgn:7007922",
      "tgn:7029392"
    ],
    "placetype": [
      "aat:300008761"
    ],
    "id": 2152051,
    "name:xx": "Bautch Valley"
  }
}
