{
  "geometry": {
    "type": "Point",
    "coordinates": [
      -122.9667,
      44.0167
    ]
  },
  "type": "Feature",
  "properties": {
    "hierarchy": [
      "tgn:2204930",
      "tgn:1000001",
      "tgn:7012149",
      "tgn:2001716",
      "tgn:7007708",
      "tgn:7029392"
    ],
    "placetype": [
      "aat:300055621"
    ],
    "id": 2204930,
    "name:xx": "Buford Recreational Area"
  }
}
