{
  "geometry": {
    "type": "Point",
    "coordinates": [
      -82.65,
      37.7167
    ]
  },
  "type": "Feature",
  "properties": {
    "hierarchy": [
      "tgn:2708421",
      "tgn:1000001",
      "tgn:7012149",
      "tgn:2000804",
      "tgn:7007255",
      "tgn:7029392"
    ],
    "placetype": [
      "aat:300008706"
    ],
    "id": 2708421,
    "name:xx": "Sycamore Creek"
  }
}
