{
  "geometry": {
    "type": "Point",
    "coordinates": [
      -78.75,
      40.1833
    ]
  },
  "type": "Feature",
  "properties": {
    "hierarchy": [
      "tgn:2243284",
      "tgn:1000001",
      "tgn:7012149",
      "tgn:1002904",
      "tgn:7007710",
      "tgn:7029392"
    ],
    "placetype": [
      "aat:300055621"
    ],
    "id": 2243284,
    "name:xx": "Clear Shade Wild Area"
  }
}
