{
  "geometry": {
    "type": "Point",
    "coordinates": [
      49.8667,
      55.5333
    ]
  },
  "type": "Feature",
  "properties": {
    "hierarchy": [
      "tgn:1055652",
      "tgn:1000004",
      "tgn:7002435",
      "tgn:7011524",
      "tgn:7029392"
    ],
    "placetype": [
      "aat:300008347"
    ],
    "id": 1055652,
    "name:xx": "Kornoukhovo"
  }
}
