{
  "geometry": {
    "type": "Point",
    "coordinates": [
      -104.9833,
      46.0333
    ]
  },
  "type": "Feature",
  "properties": {
    "hierarchy": [
      "tgn:2281716",
      "tgn:1000001",
      "tgn:7012149",
      "tgn:7007524",
      "tgn:7029392"
    ],
    "placetype": [
      "aat:300008706"
    ],
    "id": 2281716,
    "name:xx": "Deer Creek"
  }
}
