{
  "type": "FeatureCollection",
  "features": [
    {
      "geometry": {
        "type": "Point",
        "coordinates": [
          -93.3,
          44.45
        ]
      },
      "type": "Feature",
      "properties": {
        "hierarchy": [
          "tgn:2738840",
          "tgn:1000001",
          "tgn:7012149",
          "tgn:2001064",
          "tgn:7007521",
          "tgn:7029392"
        ],
        "placetype": [
          "aat:300008680"
        ],
        "id": 2738840,
        "name:xx": "Union Lake"
      }
    },
    {
      "geometry": {
        "type": "Point",
        "coordinates": [
          -95.3333,
          45.8167
        ]
      },
      "type": "Feature",
      "properties": {
        "hierarchy": [
          "tgn:2738841",
          "tgn:1000001",
          "tgn:2001019",
          "tgn:7012149",
          "tgn:7007521",
          "tgn:7029392"
        ],
        "placetype": [
          "aat:300008680"
        ],
        "id": 2738841,
        "name:xx": "Union Lake"
      }
    },
    {
      "geometry": {
        "type": "Point",
        "coordinates": [
          -96.0667,
          47.6
        ]
      },
      "type": "Feature",
      "properties": {
        "hierarchy": [
          "tgn:2738842",
          "tgn:1000001",
          "tgn:7012149",
          "tgn:2001058",
          "tgn:7007521",
          "tgn:7029392"
        ],
        "placetype": [
          "aat:300008680"
        ],
        "id": 2738842,
        "name:xx": "Union Lake"
      }
    },
    {
      "geometry": {
        "type": "Point",
        "coordinates": [
          -91.0667,
          38.3667
        ]
      },
      "type": "Feature",
      "properties": {
        "hierarchy": [
          "tgn:2738843",
          "tgn:1000001",
          "tgn:7012149",
          "tgn:1002384",
          "tgn:7007523",
          "tgn:7029392"
        ],
        "placetype": [
          "aat:300006191"
        ],
        "id": 2738843,
        "name:xx": "Union Lake"
      }
    },
    {
      "geometry": {
        "type": "Point",
        "coordinates": [
          -75.1833,
          41.8
        ]
      },
      "type": "Feature",
      "properties": {
        "hierarchy": [
          "tgn:2738844",
          "tgn:1000001",
          "tgn:7012149",
          "tgn:1003008",
          "tgn:7007710",
          "tgn:7029392"
        ],
        "placetype": [
          "aat:300008680"
        ],
        "id": 2738844,
        "name:xx": "Union Lake"
      }
    },
    {
      "geometry": {
        "type": "Point",
        "coordinates": [
          -78.9833,
          33.85
        ]
      },
      "type": "Feature",
      "properties": {
        "hierarchy": [
          "tgn:2738845",
          "tgn:1000001",
          "tgn:7012149",
          "tgn:2001750",
          "tgn:7007712",
          "tgn:7029392"
        ],
        "placetype": [
          "aat:300008680"
        ],
        "id": 2738845,
        "name:xx": "Union Lake"
      }
    },
    {
      "geometry": {
        "type": "Point",
        "coordinates": [
          -98.6167,
          32.9333
        ]
      },
      "type": "Feature",
      "properties": {
        "hierarchy": [
          "tgn:2738846",
          "tgn:1000001",
          "tgn:7012149",
          "tgn:2002076",
          "tgn:7007826",
          "tgn:7029392"
        ],
        "placetype": [
          "aat:300006191"
        ],
        "id": 2738846,
        "name:xx": "Union Lake"
      }
    },
    {
      "geometry": {
        "type": "Point",
        "coordinates": [
          -109.75,
          43.45
        ]
      },
      "type": "Feature",
      "properties": {
        "hierarchy": [
          "tgn:2738847",
          "tgn:1000001",
          "tgn:7012149",
          "tgn:7007923",
          "tgn:7029392"
        ],
        "placetype": [
          "aat:300008680"
        ],
        "id": 2738847,
        "name:xx": "Union Lake"
      }
    },
    {
      "geometry": {
        "type": "Point",
        "coordinates": [
          -122.8667,
          41.0333
        ]
      },
      "type": "Feature",
      "properties": {
        "hierarchy": [
          "tgn:2738848",
          "tgn:1000001",
          "tgn:7012149",
          "tgn:7007157",
          "tgn:2000191",
          "tgn:7029392"
        ],
        "placetype": [
          "aat:300008680"
        ],
        "id": 2738848,
        "name:xx": "Union Lakes"
      }
    },
    {
      "geometry": {
        "type": "Point",
        "coordinates": [
          -123.8,
          39.6833
        ]
      },
      "type": "Feature",
      "properties": {
        "hierarchy": [
          "tgn:2738849",
          "tgn:1000001",
          "tgn:7012149",
          "tgn:7007157",
          "tgn:2000185",
          "tgn:7029392"
        ],
        "placetype": [
          "aat:300008347"
        ],
        "id": 2738849,
        "name:xx": "Union Landing"
      }
    }
  ]
}
