{
  "geometry": {
    "type": "Point",
    "coordinates": [
      -132.15,
      55.5833
    ]
  },
  "type": "Feature",
  "properties": {
    "hierarchy": [
      "tgn:2540800",
      "tgn:7006450",
      "tgn:1000001",
      "tgn:7012149",
      "tgn:2000082",
      "tgn:7029392"
    ],
    "placetype": [
      "aat:300008699"
    ],
    "id": 2540800,
    "name:xx": "Niblack Hollow"
  }
}
