{
  "geometry": {
    "type": "Point",
    "coordinates": [
      -89.2333,
      39.5333
    ]
  },
  "type": "Feature",
  "properties": {
    "hierarchy": [
      "tgn:2533955",
      "tgn:1000001",
      "tgn:1002268",
      "tgn:7012149",
      "tgn:7007251",
      "tgn:7029392"
    ],
    "placetype": [
      "aat:300008680"
    ],
    "id": 2533955,
    "name:xx": "Myers Lake"
  }
}
