{
  "geometry": {
    "type": "Point",
    "coordinates": [
      115.55,
      40.4833
    ]
  },
  "type": "Feature",
  "properties": {
    "hierarchy": [
      "tgn:1067957",
      "tgn:1000004",
      "tgn:7002077",
      "tgn:1000111",
      "tgn:7029392"
    ],
    "placetype": [
      "aat:300008347"
    ],
    "id": 1067957,
    "name:xx": "Erpuzi"
  }
}
