{
  "type": "FeatureCollection",
  "features": [
    {
      "geometry": {
        "type": "Point",
        "coordinates": [
          -2.7,
          42.833333
        ]
      },
      "type": "Feature",
      "properties": {
        "hierarchy": [
          "tgn:7346161",
          "tgn:7007088",
          "tgn:1000003",
          "tgn:7009604",
          "tgn:1000095",
          "tgn:7029392"
        ],
        "placetype": [
          "aat:300008347"
        ],
        "id": 7346161,
        "name:xx": "Armentia"
      }
    },
    {
      "geometry": {
        "type": "Point",
        "coordinates": [
          -5.45,
          40.6
        ]
      },
      "type": "Feature",
      "properties": {
        "hierarchy": [
          "tgn:7346163",
          "tgn:7002835",
          "tgn:7001158",
          "tgn:1000003",
          "tgn:1000095",
          "tgn:7029392"
        ],
        "placetype": [
          "aat:300008347"
        ],
        "id": 7346163,
        "name:xx": "Armenteros"
      }
    },
    {
      "geometry": {
        "type": "Point",
        "coordinates": [
          -8.75,
          42.5
        ]
      },
      "type": "Feature",
      "properties": {
        "hierarchy": [
          "tgn:7346164",
          "tgn:7002834",
          "tgn:1000003",
          "tgn:7002786",
          "tgn:1000095",
          "tgn:7029392"
        ],
        "placetype": [
          "aat:300008699"
        ],
        "id": 7346164,
        "name:xx": "Armentera, Arroyo"
      }
    },
    {
      "geometry": {
        "type": "Point",
        "coordinates": [
          3.074909,
          42.17195
        ]
      },
      "type": "Feature",
      "properties": {
        "hierarchy": [
          "tgn:7346166",
          "tgn:7002820",
          "tgn:7030216",
          "tgn:1000003",
          "tgn:1000095",
          "tgn:7029392"
        ],
        "placetype": [
          "aat:300008347"
        ],
        "id": 7346166,
        "name:xx": "Armentera"
      }
    },
    {
      "geometry": {
        "type": "Point",
        "coordinates": [
          -7.816667,
          42.45
        ]
      },
      "type": "Feature",
      "properties": {
        "hierarchy": [
          "tgn:7346167",
          "tgn:7002831",
          "tgn:1000003",
          "tgn:7002786",
          "tgn:1000095",
          "tgn:7029392"
        ],
        "placetype": [
          "aat:300008699"
        ],
        "id": 7346167,
        "name:xx": "Armental, Arroyo de"
      }
    },
    {
      "geometry": {
        "type": "Point",
        "coordinates": [
          -6.716667,
          43.516667
        ]
      },
      "type": "Feature",
      "properties": {
        "hierarchy": [
          "tgn:7346168",
          "tgn:7008911",
          "tgn:1000003",
          "tgn:7002763",
          "tgn:1000095",
          "tgn:7029392"
        ],
        "placetype": [
          "aat:300008347"
        ],
        "id": 7346168,
        "name:xx": "Armental"
      }
    }
  ]
}
