{
  "geometry": {
    "type": "Point",
    "coordinates": [
      -92.7667,
      38.1833
    ]
  },
  "type": "Feature",
  "properties": {
    "hierarchy": [
      "tgn:2522445",
      "tgn:1000001",
      "tgn:7012149",
      "tgn:2001221",
      "tgn:7007523",
      "tgn:7029392"
    ],
    "placetype": [
      "aat:300132316"
    ],
    "id": 2522445,
    "name:xx": "Moonlight Bay"
  }
}
