{
  "geometry": {
    "type": "Point",
    "coordinates": [
      -121.1167,
      47.6167
    ]
  },
  "type": "Feature",
  "properties": {
    "hierarchy": [
      "tgn:2477756",
      "tgn:1000001",
      "tgn:7012149",
      "tgn:7007920",
      "tgn:7029392"
    ],
    "placetype": [
      "aat:300008798"
    ],
    "id": 2477756,
    "name:xx": "Mac Peak"
  }
}
