{
  "geometry": {
    "type": "Point",
    "coordinates": [
      -74.65,
      -52.85
    ]
  },
  "type": "Feature",
  "properties": {
    "hierarchy": [
      "tgn:7321174",
      "tgn:1001702",
      "tgn:1000049",
      "tgn:1000002",
      "tgn:7029392"
    ],
    "placetype": [
      "aat:300386846"
    ],
    "id": 7321174,
    "name:xx": "Baja, Punta"
  }
}
