{
  "type": "FeatureCollection",
  "features": [
    {
      "geometry": {
        "type": "Point",
        "coordinates": [
          -87.05,
          30.6833
        ]
      },
      "type": "Feature",
      "properties": {
        "hierarchy": [
          "tgn:2020931",
          "tgn:1000001",
          "tgn:7012149",
          "tgn:2000285",
          "tgn:7007240",
          "tgn:7029392"
        ],
        "placetype": [
          "aat:300008347",
          "aat:300387210"
        ],
        "id": 2020931,
        "name:xx": "Point Baker"
      }
    },
    {
      "geometry": {
        "type": "Point",
        "coordinates": [
          -86.1,
          30.3667
        ]
      },
      "type": "Feature",
      "properties": {
        "hierarchy": [
          "tgn:2020933",
          "tgn:1000001",
          "tgn:7012149",
          "tgn:2000290",
          "tgn:7007240",
          "tgn:7029392"
        ],
        "placetype": [
          "aat:300008347"
        ],
        "id": 2020933,
        "name:xx": "Point Washington"
      }
    },
    {
      "geometry": {
        "type": "Point",
        "coordinates": [
          -81.8167,
          28.1667
        ]
      },
      "type": "Feature",
      "properties": {
        "hierarchy": [
          "tgn:2020934",
          "tgn:1000001",
          "tgn:7012149",
          "tgn:1002793",
          "tgn:7007240",
          "tgn:7029392"
        ],
        "placetype": [
          "aat:300008347"
        ],
        "id": 2020934,
        "name:xx": "Polk City"
      }
    },
    {
      "geometry": {
        "type": "Point",
        "coordinates": [
          -81.5833,
          29.5
        ]
      },
      "type": "Feature",
      "properties": {
        "hierarchy": [
          "tgn:2020937",
          "tgn:1000001",
          "tgn:7012149",
          "tgn:2000282",
          "tgn:7007240",
          "tgn:7029392"
        ],
        "placetype": [
          "aat:300008347"
        ],
        "id": 2020937,
        "name:xx": "Pomona Park"
      }
    },
    {
      "geometry": {
        "type": "Point",
        "coordinates": [
          -80.1167,
          26.2333
        ]
      },
      "type": "Feature",
      "properties": {
        "hierarchy": [
          "tgn:2020938",
          "tgn:1000001",
          "tgn:1002207",
          "tgn:7012149",
          "tgn:7007240",
          "tgn:7029392"
        ],
        "placetype": [
          "aat:300008347"
        ],
        "id": 2020938,
        "name:xx": "Pompano Beach"
      }
    }
  ]
}
