{
  "geometry": {
    "type": "Point",
    "coordinates": [
      -97.0167,
      28.7167
    ]
  },
  "type": "Feature",
  "properties": {
    "hierarchy": [
      "tgn:2751006",
      "tgn:1000001",
      "tgn:7012149",
      "tgn:1002975",
      "tgn:7007826",
      "tgn:7029392"
    ],
    "placetype": [
      "aat:300008680"
    ],
    "id": 2751006,
    "name:xx": "Warden Lake"
  }
}
