{
  "geometry": {
    "type": "Point",
    "coordinates": [
      -83.2667,
      43.55
    ]
  },
  "type": "Feature",
  "properties": {
    "hierarchy": [
      "tgn:2370414",
      "tgn:1000001",
      "tgn:7012149",
      "tgn:2000997",
      "tgn:7007520",
      "tgn:7029392"
    ],
    "placetype": [
      "aat:300006075"
    ],
    "id": 2370414,
    "name:xx": "H and S Drain"
  }
}
