{
  "geometry": {
    "type": "Point",
    "coordinates": [
      -87.0667,
      40.8667
    ]
  },
  "type": "Feature",
  "properties": {
    "hierarchy": [
      "tgn:2432556",
      "tgn:1000001",
      "tgn:7012149",
      "tgn:7007252",
      "tgn:7029392"
    ],
    "placetype": [
      "aat:300006075"
    ],
    "id": 2432556,
    "name:xx": "Keefe Ditch"
  }
}
