{
  "geometry": {
    "type": "Point",
    "coordinates": [
      13.2667,
      60.4333
    ]
  },
  "type": "Feature",
  "properties": {
    "hierarchy": [
      "tgn:1063639",
      "tgn:1000003",
      "tgn:7010031",
      "tgn:1000097",
      "tgn:7029392"
    ],
    "placetype": [
      "aat:300008347"
    ],
    "id": 1063639,
    "name:xx": "Stöllet"
  }
}
