{
  "geometry": {
    "type": "Point",
    "coordinates": [
      34.6833,
      31.6667
    ]
  },
  "type": "Feature",
  "properties": {
    "hierarchy": [
      "tgn:1079576",
      "tgn:1000861",
      "tgn:1000004",
      "tgn:1000119",
      "tgn:7029392"
    ],
    "placetype": [
      "aat:300008347"
    ],
    "id": 1079576,
    "name:xx": "Negba"
  }
}
