{
  "geometry": {
    "type": "Point",
    "coordinates": [
      75.197222,
      34.566667
    ]
  },
  "type": "Feature",
  "properties": {
    "hierarchy": [
      "tgn:7591730",
      "tgn:1000004",
      "tgn:7000198",
      "tgn:7000799",
      "tgn:7029392"
    ],
    "placetype": [
      "aat:300008699"
    ],
    "name:en": "Baruāb Nāla",
    "id": 7591730
  }
}
