{
  "geometry": {
    "type": "Point",
    "coordinates": [
      -121.8833,
      45.3167
    ]
  },
  "type": "Feature",
  "properties": {
    "hierarchy": [
      "tgn:2325056",
      "tgn:1000001",
      "tgn:1002270",
      "tgn:7012149",
      "tgn:7007708",
      "tgn:7029392"
    ],
    "placetype": [
      "aat:300008706"
    ],
    "id": 2325056,
    "name:xx": "Fern Creek"
  }
}
