{
  "geometry": {
    "type": "Point",
    "coordinates": [
      -90.4167,
      33.3333
    ]
  },
  "type": "Feature",
  "properties": {
    "hierarchy": [
      "tgn:2458068",
      "tgn:1000001",
      "tgn:7012149",
      "tgn:2001127",
      "tgn:7007522",
      "tgn:7029392"
    ],
    "placetype": [
      "aat:300008680"
    ],
    "id": 2458068,
    "name:xx": "Little Mossy Lake"
  }
}
