{
  "type": "FeatureCollection",
  "features": [
    {
      "geometry": {
        "type": "Point",
        "coordinates": [
          -99.716667,
          19.25
        ]
      },
      "type": "Feature",
      "properties": {
        "hierarchy": [
          "tgn:7395090",
          "tgn:1000001",
          "tgn:1001893",
          "tgn:7005560",
          "tgn:7029392"
        ],
        "placetype": [
          "aat:300008347"
        ],
        "id": 7395090,
        "name:xx": "San Antonio"
      }
    },
    {
      "geometry": {
        "type": "Point",
        "coordinates": [
          -96.366667,
          19.25
        ]
      },
      "type": "Feature",
      "properties": {
        "hierarchy": [
          "tgn:7395091",
          "tgn:1000001",
          "tgn:7005599",
          "tgn:7005560",
          "tgn:7029392"
        ],
        "placetype": [
          "aat:300008347"
        ],
        "id": 7395091,
        "name:xx": "San Antonio"
      }
    },
    {
      "geometry": {
        "type": "Point",
        "coordinates": [
          -99.5,
          19.183333
        ]
      },
      "type": "Feature",
      "properties": {
        "hierarchy": [
          "tgn:7395092",
          "tgn:1000001",
          "tgn:1001893",
          "tgn:7005560",
          "tgn:7029392"
        ],
        "placetype": [
          "aat:300008347"
        ],
        "id": 7395092,
        "name:xx": "San Antonio"
      }
    },
    {
      "geometry": {
        "type": "Point",
        "coordinates": [
          -96.15,
          18.8
        ]
      },
      "type": "Feature",
      "properties": {
        "hierarchy": [
          "tgn:7395093",
          "tgn:1000001",
          "tgn:7005599",
          "tgn:7005560",
          "tgn:7029392"
        ],
        "placetype": [
          "aat:300008347"
        ],
        "id": 7395093,
        "name:xx": "San Antonio"
      }
    },
    {
      "geometry": {
        "type": "Point",
        "coordinates": [
          -95.716667,
          18.533333
        ]
      },
      "type": "Feature",
      "properties": {
        "hierarchy": [
          "tgn:7395094",
          "tgn:1000001",
          "tgn:7005599",
          "tgn:7005560",
          "tgn:7029392"
        ],
        "placetype": [
          "aat:300008347"
        ],
        "id": 7395094,
        "name:xx": "San Antonio"
      }
    },
    {
      "geometry": {
        "type": "Point",
        "coordinates": [
          -102.383333,
          18.483333
        ]
      },
      "type": "Feature",
      "properties": {
        "hierarchy": [
          "tgn:7395095",
          "tgn:1000001",
          "tgn:7005590",
          "tgn:7005560",
          "tgn:7029392"
        ],
        "placetype": [
          "aat:300008347"
        ],
        "id": 7395095,
        "name:xx": "San Antonio"
      }
    },
    {
      "geometry": {
        "type": "Point",
        "coordinates": [
          -89.883333,
          18.466667
        ]
      },
      "type": "Feature",
      "properties": {
        "hierarchy": [
          "tgn:7395096",
          "tgn:7005578",
          "tgn:1000001",
          "tgn:7005560",
          "tgn:7029392"
        ],
        "placetype": [
          "aat:300008347"
        ],
        "id": 7395096,
        "name:xx": "San Antonio"
      }
    },
    {
      "geometry": {
        "type": "Point",
        "coordinates": [
          -100.25,
          18.4
        ]
      },
      "type": "Feature",
      "properties": {
        "hierarchy": [
          "tgn:7395097",
          "tgn:1000001",
          "tgn:1001893",
          "tgn:7005560",
          "tgn:7029392"
        ],
        "placetype": [
          "aat:300008347"
        ],
        "id": 7395097,
        "name:xx": "San Antonio"
      }
    },
    {
      "geometry": {
        "type": "Point",
        "coordinates": [
          -92.383333,
          18.3
        ]
      },
      "type": "Feature",
      "properties": {
        "hierarchy": [
          "tgn:7395098",
          "tgn:1000001",
          "tgn:7005596",
          "tgn:7005560",
          "tgn:7029392"
        ],
        "placetype": [
          "aat:300008347"
        ],
        "id": 7395098,
        "name:xx": "San Antonio"
      }
    },
    {
      "geometry": {
        "type": "Point",
        "coordinates": [
          -101.75,
          18.266667
        ]
      },
      "type": "Feature",
      "properties": {
        "hierarchy": [
          "tgn:7395099",
          "tgn:7005585",
          "tgn:1000001",
          "tgn:7005560",
          "tgn:7029392"
        ],
        "placetype": [
          "aat:300008347"
        ],
        "id": 7395099,
        "name:xx": "San Antonio"
      }
    }
  ]
}
