{
  "geometry": {
    "type": "Point",
    "coordinates": [
      -82.7833,
      35.0833
    ]
  },
  "type": "Feature",
  "properties": {
    "hierarchy": [
      "tgn:2124938",
      "tgn:1000001",
      "tgn:7012149",
      "tgn:2001763",
      "tgn:7007712",
      "tgn:7029392"
    ],
    "placetype": [
      "aat:300008706"
    ],
    "id": 2124938,
    "name:xx": "Abner Creek"
  }
}
