{
  "geometry": {
    "type": "Point",
    "coordinates": [
      -74.8667,
      43.7333
    ]
  },
  "type": "Feature",
  "properties": {
    "hierarchy": [
      "tgn:2604164",
      "tgn:1000001",
      "tgn:7012149",
      "tgn:1002472",
      "tgn:7007568",
      "tgn:7029392"
    ],
    "placetype": [
      "aat:300008680"
    ],
    "id": 2604164,
    "name:xx": "Quiver Pond"
  }
}
