{
  "geometry": {
    "type": "Point",
    "coordinates": [
      -106.1667,
      44.75
    ]
  },
  "type": "Feature",
  "properties": {
    "hierarchy": [
      "tgn:2271375",
      "tgn:1000001",
      "tgn:7012149",
      "tgn:2002381",
      "tgn:7007923",
      "tgn:7029392"
    ],
    "placetype": [
      "aat:300006191"
    ],
    "id": 2271375,
    "name:xx": "Cultra Reservoir"
  }
}
