{
  "type": "FeatureCollection",
  "features": [
    {
      "geometry": {
        "type": "Point",
        "coordinates": [
          -116.25,
          31.283333
        ]
      },
      "type": "Feature",
      "properties": {
        "hierarchy": [
          "tgn:7390320",
          "tgn:1001835",
          "tgn:1000001",
          "tgn:7005560",
          "tgn:7029392"
        ],
        "placetype": [
          "aat:300008347"
        ],
        "id": 7390320,
        "name:xx": "Rancho San Antonio"
      }
    },
    {
      "geometry": {
        "type": "Point",
        "coordinates": [
          -105.983333,
          31
        ]
      },
      "type": "Feature",
      "properties": {
        "hierarchy": [
          "tgn:7390321",
          "tgn:7005581",
          "tgn:1000001",
          "tgn:7005560",
          "tgn:7029392"
        ],
        "placetype": [
          "aat:300008347"
        ],
        "id": 7390321,
        "name:xx": "Rancho San Antonio"
      }
    },
    {
      "geometry": {
        "type": "Point",
        "coordinates": [
          -109.533333,
          30.916667
        ]
      },
      "type": "Feature",
      "properties": {
        "hierarchy": [
          "tgn:7390322",
          "tgn:1000001",
          "tgn:1001960",
          "tgn:7005560",
          "tgn:7029392"
        ],
        "placetype": [
          "aat:300008347"
        ],
        "id": 7390322,
        "name:xx": "Rancho San Antonio"
      }
    },
    {
      "geometry": {
        "type": "Point",
        "coordinates": [
          -105.616667,
          28.55
        ]
      },
      "type": "Feature",
      "properties": {
        "hierarchy": [
          "tgn:7390323",
          "tgn:7005581",
          "tgn:1000001",
          "tgn:7005560",
          "tgn:7029392"
        ],
        "placetype": [
          "aat:300008347"
        ],
        "id": 7390323,
        "name:xx": "Rancho San Antonio"
      }
    },
    {
      "geometry": {
        "type": "Point",
        "coordinates": [
          -100.516667,
          27.6
        ]
      },
      "type": "Feature",
      "properties": {
        "hierarchy": [
          "tgn:7390324",
          "tgn:1001853",
          "tgn:1000001",
          "tgn:7005560",
          "tgn:7029392"
        ],
        "placetype": [
          "aat:300008347"
        ],
        "id": 7390324,
        "name:xx": "Rancho San Antonio"
      }
    },
    {
      "geometry": {
        "type": "Point",
        "coordinates": [
          -100.8,
          27.516667
        ]
      },
      "type": "Feature",
      "properties": {
        "hierarchy": [
          "tgn:7390325",
          "tgn:1001853",
          "tgn:1000001",
          "tgn:7005560",
          "tgn:7029392"
        ],
        "placetype": [
          "aat:300008347"
        ],
        "id": 7390325,
        "name:xx": "Rancho San Antonio"
      }
    },
    {
      "geometry": {
        "type": "Point",
        "coordinates": [
          -100.333333,
          27.166667
        ]
      },
      "type": "Feature",
      "properties": {
        "hierarchy": [
          "tgn:7390326",
          "tgn:1000001",
          "tgn:7005589",
          "tgn:7005560",
          "tgn:7029392"
        ],
        "placetype": [
          "aat:300008347"
        ],
        "id": 7390326,
        "name:xx": "Rancho San Antonio"
      }
    },
    {
      "geometry": {
        "type": "Point",
        "coordinates": [
          -101.2,
          27.066667
        ]
      },
      "type": "Feature",
      "properties": {
        "hierarchy": [
          "tgn:7390327",
          "tgn:1001853",
          "tgn:1000001",
          "tgn:7005560",
          "tgn:7029392"
        ],
        "placetype": [
          "aat:300008347"
        ],
        "id": 7390327,
        "name:xx": "Rancho San Antonio"
      }
    },
    {
      "geometry": {
        "type": "Point",
        "coordinates": [
          -100.233333,
          26.9
        ]
      },
      "type": "Feature",
      "properties": {
        "hierarchy": [
          "tgn:7390328",
          "tgn:1000001",
          "tgn:7005589",
          "tgn:7005560",
          "tgn:7029392"
        ],
        "placetype": [
          "aat:300008347"
        ],
        "id": 7390328,
        "name:xx": "Rancho San Antonio"
      }
    },
    {
      "geometry": {
        "type": "Point",
        "coordinates": [
          -99.4,
          26.233333
        ]
      },
      "type": "Feature",
      "properties": {
        "hierarchy": [
          "tgn:7390329",
          "tgn:1000001",
          "tgn:7005589",
          "tgn:7005560",
          "tgn:7029392"
        ],
        "placetype": [
          "aat:300008347"
        ],
        "id": 7390329,
        "name:xx": "Rancho San Antonio"
      }
    }
  ]
}
