{
  "geometry": {
    "type": "Point",
    "coordinates": [
      -108.7667,
      32.45
    ]
  },
  "type": "Feature",
  "properties": {
    "hierarchy": [
      "tgn:2541788",
      "tgn:1000001",
      "tgn:7012149",
      "tgn:2001440",
      "tgn:7007566",
      "tgn:7029392"
    ],
    "placetype": [
      "aat:300008798"
    ],
    "id": 2541788,
    "name:xx": "Ninemile Hill"
  }
}
