{
  "geometry": {
    "type": "Point",
    "coordinates": [
      -84.8333,
      34.0333
    ]
  },
  "type": "Feature",
  "properties": {
    "hierarchy": [
      "tgn:2506422",
      "tgn:1000001",
      "tgn:7012149",
      "tgn:2000401",
      "tgn:7007248",
      "tgn:7029392"
    ],
    "placetype": [
      "aat:300000390"
    ],
    "id": 2506422,
    "name:xx": "Merritt Mine"
  }
}
