{
  "geometry": {
    "type": "Point",
    "coordinates": [
      -85.8333,
      46.4833
    ]
  },
  "type": "Feature",
  "properties": {
    "hierarchy": [
      "tgn:2338797",
      "tgn:1000001",
      "tgn:7012149",
      "tgn:2000972",
      "tgn:7007520",
      "tgn:7029392"
    ],
    "placetype": [
      "aat:300008680"
    ],
    "id": 2338797,
    "name:xx": "Frank Lake"
  }
}
