{
  "geometry": {
    "type": "Point",
    "coordinates": [
      -93.5667,
      47.1667
    ]
  },
  "type": "Feature",
  "properties": {
    "hierarchy": [
      "tgn:2697481",
      "tgn:1000001",
      "tgn:7012149",
      "tgn:2001029",
      "tgn:7007521",
      "tgn:7029392"
    ],
    "placetype": [
      "aat:300008850"
    ],
    "id": 2697481,
    "name:xx": "Stony Point"
  }
}
