{
  "type": "FeatureCollection",
  "features": [
    {
      "geometry": {
        "type": "Point",
        "coordinates": [
          30.17343,
          30.970887
        ]
      },
      "type": "Feature",
      "properties": {
        "hierarchy": [
          "tgn:7523260",
          "tgn:7001242",
          "tgn:1001075",
          "tgn:7016833",
          "tgn:7029392"
        ],
        "placetype": [
          "aat:300008347"
        ],
        "name:en": "Turūjah",
        "id": 7523260
      }
    },
    {
      "geometry": {
        "type": "Point",
        "coordinates": [
          30.866667,
          29.466667
        ]
      },
      "type": "Feature",
      "properties": {
        "hierarchy": [
          "tgn:7523261",
          "tgn:7001242",
          "tgn:7001105",
          "tgn:7016833",
          "tgn:7029392"
        ],
        "placetype": [
          "aat:300008347"
        ],
        "name:en": "'Ezbet Tulba Sha'râwi",
        "id": 7523261
      }
    },
    {
      "geometry": {
        "type": "Point",
        "coordinates": [
          29.983333,
          31.083333
        ]
      },
      "type": "Feature",
      "properties": {
        "hierarchy": [
          "tgn:7523262",
          "tgn:7001242",
          "tgn:1001075",
          "tgn:7016833",
          "tgn:7029392"
        ],
        "placetype": [
          "aat:300008347"
        ],
        "name:en": "'Ezbet Tell",
        "id": 7523262
      }
    },
    {
      "geometry": {
        "type": "Point",
        "coordinates": [
          30.5425,
          31.015278
        ]
      },
      "type": "Feature",
      "properties": {
        "hierarchy": [
          "tgn:7523263",
          "tgn:7001242",
          "tgn:1001075",
          "tgn:7016833",
          "tgn:7029392"
        ],
        "placetype": [
          "aat:300008347"
        ],
        "name:en": "'Ezbet Ṭarâbamba",
        "id": 7523263
      }
    },
    {
      "geometry": {
        "type": "Point",
        "coordinates": [
          30.483333,
          31.123611
        ]
      },
      "type": "Feature",
      "properties": {
        "hierarchy": [
          "tgn:7523264",
          "tgn:7001242",
          "tgn:1001075",
          "tgn:7016833",
          "tgn:7029392"
        ],
        "placetype": [
          "aat:300008347"
        ],
        "name:en": "'Ezbet Ṭamba",
        "id": 7523264
      }
    },
    {
      "geometry": {
        "type": "Point",
        "coordinates": [
          31.723097,
          30.525446
        ]
      },
      "type": "Feature",
      "properties": {
        "hierarchy": [
          "tgn:7523265",
          "tgn:7001242",
          "tgn:7016833",
          "tgn:1001113",
          "tgn:7029392"
        ],
        "placetype": [
          "aat:300008347"
        ],
        "id": 7523265,
        "name:xx": "'Izbat Tall ar Rakham"
      }
    },
    {
      "geometry": {
        "type": "Point",
        "coordinates": [
          32.027599,
          30.927408
        ]
      },
      "type": "Feature",
      "properties": {
        "hierarchy": [
          "tgn:7523266",
          "tgn:7001242",
          "tgn:7016833",
          "tgn:1001113",
          "tgn:7029392"
        ],
        "placetype": [
          "aat:300008347"
        ],
        "name:en": "'Ezbet Tall el-Daqîq",
        "id": 7523266
      }
    },
    {
      "geometry": {
        "type": "Point",
        "coordinates": [
          31.415389,
          30.659013
        ]
      },
      "type": "Feature",
      "properties": {
        "hierarchy": [
          "tgn:7523267",
          "tgn:7001242",
          "tgn:7016833",
          "tgn:1001113",
          "tgn:7029392"
        ],
        "placetype": [
          "aat:300008347"
        ],
        "id": 7523267,
        "name:xx": "Duwaydah"
      }
    },
    {
      "geometry": {
        "type": "Point",
        "coordinates": [
          29.695329,
          30.311471
        ]
      },
      "type": "Feature",
      "properties": {
        "hierarchy": [
          "tgn:7523268",
          "tgn:7001242",
          "tgn:1001075",
          "tgn:7016833",
          "tgn:7029392"
        ],
        "placetype": [
          "aat:300008749"
        ],
        "name:en": "Dūwa, Manāqīr ad",
        "id": 7523268
      }
    },
    {
      "geometry": {
        "type": "Point",
        "coordinates": [
          32.866667,
          23.933333
        ]
      },
      "type": "Feature",
      "properties": {
        "hierarchy": [
          "tgn:7523269",
          "tgn:7001242",
          "tgn:7016833",
          "tgn:7000122",
          "tgn:7029392"
        ],
        "placetype": [
          "aat:300008777"
        ],
        "name:en": "Dūshī, Jabal",
        "id": 7523269
      }
    }
  ]
}
