{
  "geometry": {
    "type": "Point",
    "coordinates": [
      109.1167,
      -6.8667
    ]
  },
  "type": "Feature",
  "properties": {
    "hierarchy": [
      "tgn:1078745",
      "tgn:1000004",
      "tgn:1001322",
      "tgn:1000116",
      "tgn:7029392"
    ],
    "placetype": [
      "aat:300008347"
    ],
    "id": 1078745,
    "name:xx": "Tegal"
  }
}
