{
  "geometry": {
    "type": "Point",
    "coordinates": [
      -87.0833,
      33.1667
    ]
  },
  "type": "Feature",
  "properties": {
    "hierarchy": [
      "tgn:2453006",
      "tgn:7002659",
      "tgn:1000001",
      "tgn:2000003",
      "tgn:7012149",
      "tgn:7029392"
    ],
    "placetype": [
      "aat:300008706"
    ],
    "id": 2453006,
    "name:xx": "Little Cane Creek"
  }
}
