{
  "geometry": {
    "type": "Point",
    "coordinates": [
      -74.9833,
      43.0333
    ]
  },
  "type": "Feature",
  "properties": {
    "hierarchy": [
      "tgn:2517807",
      "tgn:1000001",
      "tgn:7012149",
      "tgn:1002472",
      "tgn:7007568",
      "tgn:7029392"
    ],
    "placetype": [
      "aat:300006191"
    ],
    "id": 2517807,
    "name:xx": "Mirror Lake"
  }
}
