{
  "geometry": {
    "type": "Point",
    "coordinates": [
      -100.85,
      32.0667
    ]
  },
  "type": "Feature",
  "properties": {
    "hierarchy": [
      "tgn:2682812",
      "tgn:1000001",
      "tgn:7012149",
      "tgn:2002077",
      "tgn:7007826",
      "tgn:7029392"
    ],
    "placetype": [
      "aat:300006191"
    ],
    "id": 2682812,
    "name:xx": "Southwest Peter Lake Tank"
  }
}
