{
  "geometry": {
    "type": "Point",
    "coordinates": [
      -68.8833,
      45.4167
    ]
  },
  "type": "Feature",
  "properties": {
    "hierarchy": [
      "tgn:2373982",
      "tgn:1000001",
      "tgn:7012149",
      "tgn:2000928",
      "tgn:7007515",
      "tgn:7029392"
    ],
    "placetype": [
      "aat:300008791"
    ],
    "id": 2373982,
    "name:xx": "Hammer Island"
  }
}
