{
  "geometry": {
    "type": "Point",
    "coordinates": [
      -147.0833,
      60.3667
    ]
  },
  "type": "Feature",
  "properties": {
    "hierarchy": [
      "tgn:2520977",
      "tgn:7006450",
      "tgn:1000001",
      "tgn:7012149",
      "tgn:2000086",
      "tgn:7029392"
    ],
    "placetype": [
      "aat:300008850"
    ],
    "id": 2520977,
    "name:xx": "Montague Point"
  }
}
