{
  "type": "FeatureCollection",
  "features": [
    {
      "geometry": {
        "type": "Point",
        "coordinates": [
          -81.2667,
          34
        ]
      },
      "type": "Feature",
      "properties": {
        "hierarchy": [
          "tgn:2312290",
          "tgn:1000001",
          "tgn:7012149",
          "tgn:2001756",
          "tgn:7007712",
          "tgn:7029392"
        ],
        "placetype": [
          "aat:300008706"
        ],
        "id": 2312290,
        "name:xx": "Eighteenmile Creek"
      }
    },
    {
      "geometry": {
        "type": "Point",
        "coordinates": [
          -82.6,
          34.8167
        ]
      },
      "type": "Feature",
      "properties": {
        "hierarchy": [
          "tgn:2312291",
          "tgn:1000001",
          "tgn:7012149",
          "tgn:7007712",
          "tgn:7029392"
        ],
        "placetype": [
          "aat:300008706"
        ],
        "id": 2312291,
        "name:xx": "Eighteenmile Creek"
      }
    },
    {
      "geometry": {
        "type": "Point",
        "coordinates": [
          -97.5,
          28.8833
        ]
      },
      "type": "Feature",
      "properties": {
        "hierarchy": [
          "tgn:2312292",
          "tgn:1000001",
          "tgn:7012149",
          "tgn:7007826",
          "tgn:7029392"
        ],
        "placetype": [
          "aat:300008706"
        ],
        "id": 2312292,
        "name:xx": "Eighteenmile Creek"
      }
    },
    {
      "geometry": {
        "type": "Point",
        "coordinates": [
          -81.6667,
          38.6667
        ]
      },
      "type": "Feature",
      "properties": {
        "hierarchy": [
          "tgn:2312293",
          "tgn:1000001",
          "tgn:7012149",
          "tgn:7013961",
          "tgn:7029392"
        ],
        "placetype": [
          "aat:300008706"
        ],
        "id": 2312293,
        "name:xx": "Eighteenmile Creek"
      }
    },
    {
      "geometry": {
        "type": "Point",
        "coordinates": [
          -91.6,
          45
        ]
      },
      "type": "Feature",
      "properties": {
        "hierarchy": [
          "tgn:2312294",
          "tgn:1000001",
          "tgn:7012149",
          "tgn:7007922",
          "tgn:7029392"
        ],
        "placetype": [
          "aat:300008706"
        ],
        "id": 2312294,
        "name:xx": "Eighteenmile Creek"
      }
    },
    {
      "geometry": {
        "type": "Point",
        "coordinates": [
          -91.15,
          46.2667
        ]
      },
      "type": "Feature",
      "properties": {
        "hierarchy": [
          "tgn:2312295",
          "tgn:2002308",
          "tgn:1000001",
          "tgn:7012149",
          "tgn:7007922",
          "tgn:7029392"
        ],
        "placetype": [
          "aat:300008706"
        ],
        "id": 2312295,
        "name:xx": "Eighteenmile Creek"
      }
    },
    {
      "geometry": {
        "type": "Point",
        "coordinates": [
          -91.1667,
          46.2833
        ]
      },
      "type": "Feature",
      "properties": {
        "hierarchy": [
          "tgn:2312296",
          "tgn:2002308",
          "tgn:1000001",
          "tgn:7012149",
          "tgn:7007922",
          "tgn:7029392"
        ],
        "placetype": [
          "aat:300008697"
        ],
        "id": 2312296,
        "name:xx": "Eighteenmile Creek Springs"
      }
    },
    {
      "geometry": {
        "type": "Point",
        "coordinates": [
          -104.2167,
          34.1333
        ]
      },
      "type": "Feature",
      "properties": {
        "hierarchy": [
          "tgn:2312297",
          "tgn:1000001",
          "tgn:7019560",
          "tgn:7012149",
          "tgn:7007566",
          "tgn:7029392"
        ],
        "placetype": [
          "aat:300008761"
        ],
        "id": 2312297,
        "name:xx": "Eighteenmile Draw"
      }
    },
    {
      "geometry": {
        "type": "Point",
        "coordinates": [
          -85.4833,
          38.45
        ]
      },
      "type": "Feature",
      "properties": {
        "hierarchy": [
          "tgn:2312298",
          "tgn:1000001",
          "tgn:7012149",
          "tgn:1002744",
          "tgn:7007255",
          "tgn:7029392"
        ],
        "placetype": [
          "aat:300008791"
        ],
        "id": 2312298,
        "name:xx": "Eighteenmile Island"
      }
    },
    {
      "geometry": {
        "type": "Point",
        "coordinates": [
          -121.4167,
          45.6833
        ]
      },
      "type": "Feature",
      "properties": {
        "hierarchy": [
          "tgn:2312299",
          "tgn:1000001",
          "tgn:7012149",
          "tgn:1002990",
          "tgn:7007708",
          "tgn:7029392"
        ],
        "placetype": [
          "aat:300008791"
        ],
        "id": 2312299,
        "name:xx": "Eighteenmile Island"
      }
    }
  ]
}
