{
  "geometry": {
    "type": "Point",
    "coordinates": [
      113.9333,
      23.7667
    ]
  },
  "type": "Feature",
  "properties": {
    "hierarchy": [
      "tgn:1069596",
      "tgn:1000004",
      "tgn:7005232",
      "tgn:1000111",
      "tgn:7029392"
    ],
    "placetype": [
      "aat:300008347"
    ],
    "id": 1069596,
    "name:xx": "Lütian"
  }
}
