{
  "geometry": {
    "type": "Point",
    "coordinates": [
      -93.4167,
      40.2667
    ]
  },
  "type": "Feature",
  "properties": {
    "hierarchy": [
      "tgn:2458535",
      "tgn:1000001",
      "tgn:7012149",
      "tgn:7007523",
      "tgn:7029392"
    ],
    "placetype": [
      "aat:300008706"
    ],
    "id": 2458535,
    "name:xx": "Little No Creek"
  }
}
