{
  "type": "FeatureCollection",
  "features": [
    {
      "geometry": {
        "type": "Point",
        "coordinates": [
          -77.7667,
          40.5
        ]
      },
      "type": "Feature",
      "properties": {
        "hierarchy": [
          "tgn:2726750",
          "tgn:1000001",
          "tgn:7012149",
          "tgn:1002669",
          "tgn:7007710",
          "tgn:7029392"
        ],
        "placetype": [
          "aat:300008699"
        ],
        "id": 2726750,
        "name:xx": "Town Run"
      }
    },
    {
      "geometry": {
        "type": "Point",
        "coordinates": [
          -77.6,
          38.5
        ]
      },
      "type": "Feature",
      "properties": {
        "hierarchy": [
          "tgn:2726751",
          "tgn:1000001",
          "tgn:7012149",
          "tgn:7007919",
          "tgn:7029392"
        ],
        "placetype": [
          "aat:300008699"
        ],
        "id": 2726751,
        "name:xx": "Town Run"
      }
    },
    {
      "geometry": {
        "type": "Point",
        "coordinates": [
          -78.15,
          39.1667
        ]
      },
      "type": "Feature",
      "properties": {
        "hierarchy": [
          "tgn:2726752",
          "tgn:1000001",
          "tgn:7012149",
          "tgn:7022221",
          "tgn:7007919",
          "tgn:7029392"
        ],
        "placetype": [
          "aat:300008699"
        ],
        "id": 2726752,
        "name:xx": "Town Run"
      }
    },
    {
      "geometry": {
        "type": "Point",
        "coordinates": [
          -78.35,
          39.0167
        ]
      },
      "type": "Feature",
      "properties": {
        "hierarchy": [
          "tgn:2726753",
          "tgn:1000001",
          "tgn:7012149",
          "tgn:2002190",
          "tgn:7007919",
          "tgn:7029392"
        ],
        "placetype": [
          "aat:300008699"
        ],
        "id": 2726753,
        "name:xx": "Town Run"
      }
    },
    {
      "geometry": {
        "type": "Point",
        "coordinates": [
          -80.8333,
          38.9167
        ]
      },
      "type": "Feature",
      "properties": {
        "hierarchy": [
          "tgn:2726754",
          "tgn:1000001",
          "tgn:2002262",
          "tgn:7012149",
          "tgn:7013961",
          "tgn:7029392"
        ],
        "placetype": [
          "aat:300008699"
        ],
        "id": 2726754,
        "name:xx": "Town Run"
      }
    },
    {
      "geometry": {
        "type": "Point",
        "coordinates": [
          -80.4333,
          39.0167
        ]
      },
      "type": "Feature",
      "properties": {
        "hierarchy": [
          "tgn:2726755",
          "tgn:1000001",
          "tgn:7012149",
          "tgn:2002271",
          "tgn:7013961",
          "tgn:7029392"
        ],
        "placetype": [
          "aat:300008699"
        ],
        "id": 2726755,
        "name:xx": "Town Run"
      }
    },
    {
      "geometry": {
        "type": "Point",
        "coordinates": [
          -77.8167,
          39.4167
        ]
      },
      "type": "Feature",
      "properties": {
        "hierarchy": [
          "tgn:2726756",
          "tgn:1000001",
          "tgn:7012149",
          "tgn:2002269",
          "tgn:7013961",
          "tgn:7029392"
        ],
        "placetype": [
          "aat:300008699"
        ],
        "id": 2726756,
        "name:xx": "Town Run"
      }
    },
    {
      "geometry": {
        "type": "Point",
        "coordinates": [
          -103.45,
          44.7167
        ]
      },
      "type": "Feature",
      "properties": {
        "hierarchy": [
          "tgn:2726757",
          "tgn:1000001",
          "tgn:2001779",
          "tgn:7012149",
          "tgn:7007713",
          "tgn:7029392"
        ],
        "placetype": [
          "aat:300006075"
        ],
        "id": 2726757,
        "name:xx": "Town Site Lateral"
      }
    },
    {
      "geometry": {
        "type": "Point",
        "coordinates": [
          -103.4333,
          44.7
        ]
      },
      "type": "Feature",
      "properties": {
        "hierarchy": [
          "tgn:2726758",
          "tgn:1000001",
          "tgn:2001779",
          "tgn:7012149",
          "tgn:7007713",
          "tgn:7029392"
        ],
        "placetype": [
          "aat:300006075"
        ],
        "id": 2726758,
        "name:xx": "Town Site Lateral A"
      }
    },
    {
      "geometry": {
        "type": "Point",
        "coordinates": [
          -103.4,
          44.6667
        ]
      },
      "type": "Feature",
      "properties": {
        "hierarchy": [
          "tgn:2726759",
          "tgn:1000001",
          "tgn:2001779",
          "tgn:7012149",
          "tgn:7007713",
          "tgn:7029392"
        ],
        "placetype": [
          "aat:300006075"
        ],
        "id": 2726759,
        "name:xx": "Town Site Lateral B"
      }
    }
  ]
}
