{
  "geometry": {
    "type": "Point",
    "coordinates": [
      -87.0833,
      33.6833
    ]
  },
  "type": "Feature",
  "properties": {
    "hierarchy": [
      "tgn:2784667",
      "tgn:7002659",
      "tgn:1000001",
      "tgn:7012149",
      "tgn:2000063",
      "tgn:7029392"
    ],
    "placetype": [
      "aat:300000390"
    ],
    "id": 2784667,
    "name:xx": "Yearkwood Mine"
  }
}
