{
  "geometry": {
    "type": "Point",
    "coordinates": [
      -82.8167,
      28.0667
    ]
  },
  "type": "Feature",
  "properties": {
    "hierarchy": [
      "tgn:2397649",
      "tgn:1000001",
      "tgn:7012149",
      "tgn:1002790",
      "tgn:7007240",
      "tgn:7029392"
    ],
    "placetype": [
      "aat:300008791"
    ],
    "id": 2397649,
    "name:xx": "Honeymoon Island"
  }
}
