{
  "geometry": {
    "type": "Point",
    "coordinates": [
      -89.3167,
      34.15
    ]
  },
  "type": "Feature",
  "properties": {
    "hierarchy": [
      "tgn:2595781",
      "tgn:1000001",
      "tgn:7012149",
      "tgn:7007522",
      "tgn:7029392"
    ],
    "placetype": [
      "aat:300008706"
    ],
    "id": 2595781,
    "name:xx": "Potlockney Creek"
  }
}
