{
  "geometry": {
    "type": "Point",
    "coordinates": [
      -119.5833,
      44.3667
    ]
  },
  "type": "Feature",
  "properties": {
    "hierarchy": [
      "tgn:2215962",
      "tgn:1000001",
      "tgn:7012149",
      "tgn:2001708",
      "tgn:7007708",
      "tgn:7029392"
    ],
    "placetype": [
      "aat:300008706"
    ],
    "id": 2215962,
    "name:xx": "Cameron Creek"
  }
}
