{
  "geometry": {
    "type": "Point",
    "coordinates": [
      -65.533,
      -13.716
    ]
  },
  "type": "Feature",
  "properties": {
    "hierarchy": [
      "tgn:1128948",
      "tgn:1000525",
      "tgn:1000046",
      "tgn:1000002",
      "tgn:7029392"
    ],
    "placetype": [
      "aat:300008707"
    ],
    "id": 1128948,
    "name:xx": "Rápulo, Río"
  }
}
