{
  "geometry": {
    "type": "Point",
    "coordinates": [
      -79.85,
      33.1333
    ]
  },
  "type": "Feature",
  "properties": {
    "hierarchy": [
      "tgn:2511094",
      "tgn:2001732",
      "tgn:1000001",
      "tgn:7012149",
      "tgn:7007712",
      "tgn:7029392"
    ],
    "placetype": [
      "aat:300006191"
    ],
    "id": 2511094,
    "name:xx": "Midway Reserve"
  }
}
