{
  "type": "FeatureCollection",
  "features": [
    {
      "geometry": {
        "type": "Point",
        "coordinates": [
          15.1,
          37.733333
        ]
      },
      "type": "Feature",
      "properties": {
        "hierarchy": [
          "tgn:7055681",
          "tgn:1000003",
          "tgn:1001651",
          "tgn:7003122",
          "tgn:1000080",
          "tgn:7029392"
        ],
        "placetype": [
          "aat:300008347"
        ],
        "id": 7055681,
        "name:xx": "Milo"
      }
    },
    {
      "geometry": {
        "type": "Point",
        "coordinates": [
          7.666667,
          45.033333
        ]
      },
      "type": "Feature",
      "properties": {
        "hierarchy": [
          "tgn:7055683",
          "tgn:7003154",
          "tgn:1000003",
          "tgn:7003120",
          "tgn:1000080",
          "tgn:7029392"
        ],
        "placetype": [
          "aat:300008347"
        ],
        "id": 7055683,
        "name:xx": "Millefonti"
      }
    },
    {
      "geometry": {
        "type": "Point",
        "coordinates": [
          14.066667,
          40.783333
        ]
      },
      "type": "Feature",
      "properties": {
        "hierarchy": [
          "tgn:7055686",
          "tgn:7003013",
          "tgn:7003005",
          "tgn:1000003",
          "tgn:1000080",
          "tgn:7029392"
        ],
        "placetype": [
          "aat:300008816"
        ],
        "id": 7055686,
        "name:xx": "Miliscola, Spiaggia"
      }
    },
    {
      "geometry": {
        "type": "Point",
        "coordinates": [
          15.483333,
          38.133333
        ]
      },
      "type": "Feature",
      "properties": {
        "hierarchy": [
          "tgn:7055687",
          "tgn:1000003",
          "tgn:7003122",
          "tgn:7003157",
          "tgn:1000080",
          "tgn:7029392"
        ],
        "placetype": [
          "aat:300008347"
        ],
        "id": 7055687,
        "name:xx": "Mili San Pietro"
      }
    },
    {
      "geometry": {
        "type": "Point",
        "coordinates": [
          15.5,
          38.116667
        ]
      },
      "type": "Feature",
      "properties": {
        "hierarchy": [
          "tgn:7055688",
          "tgn:1000003",
          "tgn:7003122",
          "tgn:7003157",
          "tgn:1000080",
          "tgn:7029392"
        ],
        "placetype": [
          "aat:300008347"
        ],
        "id": 7055688,
        "name:xx": "Mili San Marco"
      }
    }
  ]
}
