{
  "geometry": {
    "type": "Point",
    "coordinates": [
      -160.35,
      68.6667
    ]
  },
  "type": "Feature",
  "properties": {
    "hierarchy": [
      "tgn:2720388",
      "tgn:7006450",
      "tgn:1000001",
      "tgn:7012149",
      "tgn:2124005",
      "tgn:7029392"
    ],
    "placetype": [
      "aat:300008706"
    ],
    "id": 2720388,
    "name:xx": "Thunder Creek"
  }
}
