{
  "geometry": {
    "type": "Point",
    "coordinates": [
      86.4667,
      23.6167
    ]
  },
  "type": "Feature",
  "properties": {
    "hierarchy": [
      "tgn:1124225",
      "tgn:1000004",
      "tgn:7000198",
      "tgn:7029392"
    ],
    "placetype": [
      "aat:300008707"
    ],
    "id": 1124225,
    "name:xx": "Gobai"
  }
}
