{
  "type": "FeatureCollection",
  "features": [
    {
      "geometry": {
        "type": "Point",
        "coordinates": [
          -158.7833,
          56.5333
        ]
      },
      "type": "Feature",
      "properties": {
        "hierarchy": [
          "tgn:2138530",
          "tgn:7006450",
          "tgn:1000001",
          "tgn:7030517",
          "tgn:7012149",
          "tgn:7029392"
        ],
        "placetype": [
          "aat:300008706"
        ],
        "id": 2138530,
        "name:xx": "Ash Creek"
      }
    },
    {
      "geometry": {
        "type": "Point",
        "coordinates": [
          -152.8167,
          65.4
        ]
      },
      "type": "Feature",
      "properties": {
        "hierarchy": [
          "tgn:2138531",
          "tgn:7006450",
          "tgn:1000001",
          "tgn:7012149",
          "tgn:2000089",
          "tgn:7029392"
        ],
        "placetype": [
          "aat:300008706"
        ],
        "id": 2138531,
        "name:xx": "Ash Creek"
      }
    },
    {
      "geometry": {
        "type": "Point",
        "coordinates": [
          -111.3,
          34.2667
        ]
      },
      "type": "Feature",
      "properties": {
        "hierarchy": [
          "tgn:2138532",
          "tgn:1000001",
          "tgn:7006451",
          "tgn:2000093",
          "tgn:7012149",
          "tgn:7029392"
        ],
        "placetype": [
          "aat:300008706"
        ],
        "id": 2138532,
        "name:xx": "Ash Creek"
      }
    },
    {
      "geometry": {
        "type": "Point",
        "coordinates": [
          -113.4333,
          35.0833
        ]
      },
      "type": "Feature",
      "properties": {
        "hierarchy": [
          "tgn:2138533",
          "tgn:1000001",
          "tgn:7006451",
          "tgn:7012149",
          "tgn:2000098",
          "tgn:7029392"
        ],
        "placetype": [
          "aat:300008706"
        ],
        "id": 2138533,
        "name:xx": "Ash Creek"
      }
    },
    {
      "geometry": {
        "type": "Point",
        "coordinates": [
          -111.2,
          31.8833
        ]
      },
      "type": "Feature",
      "properties": {
        "hierarchy": [
          "tgn:2138534",
          "tgn:1000001",
          "tgn:7006451",
          "tgn:7012149",
          "tgn:2000100",
          "tgn:7029392"
        ],
        "placetype": [
          "aat:300008706"
        ],
        "id": 2138534,
        "name:xx": "Ash Creek"
      }
    },
    {
      "geometry": {
        "type": "Point",
        "coordinates": [
          -110.0167,
          32.5
        ]
      },
      "type": "Feature",
      "properties": {
        "hierarchy": [
          "tgn:2138535",
          "tgn:1000001",
          "tgn:7006451",
          "tgn:2000094",
          "tgn:7012149",
          "tgn:7029392"
        ],
        "placetype": [
          "aat:300008706"
        ],
        "id": 2138535,
        "name:xx": "Ash Creek"
      }
    },
    {
      "geometry": {
        "type": "Point",
        "coordinates": [
          -110.45,
          32.9833
        ]
      },
      "type": "Feature",
      "properties": {
        "hierarchy": [
          "tgn:2138536",
          "tgn:1000001",
          "tgn:7006451",
          "tgn:7012149",
          "tgn:2000101",
          "tgn:7029392"
        ],
        "placetype": [
          "aat:300008706"
        ],
        "id": 2138536,
        "name:xx": "Ash Creek"
      }
    },
    {
      "geometry": {
        "type": "Point",
        "coordinates": [
          -109.1,
          33.4333
        ]
      },
      "type": "Feature",
      "properties": {
        "hierarchy": [
          "tgn:2138537",
          "tgn:1000001",
          "tgn:7006451",
          "tgn:2000095",
          "tgn:7012149",
          "tgn:7029392"
        ],
        "placetype": [
          "aat:300008706"
        ],
        "id": 2138537,
        "name:xx": "Ash Creek"
      }
    },
    {
      "geometry": {
        "type": "Point",
        "coordinates": [
          -109.4167,
          31.85
        ]
      },
      "type": "Feature",
      "properties": {
        "hierarchy": [
          "tgn:2138538",
          "tgn:1000001",
          "tgn:7006451",
          "tgn:2000091",
          "tgn:7012149",
          "tgn:7029392"
        ],
        "placetype": [
          "aat:300008706"
        ],
        "id": 2138538,
        "name:xx": "Ash Creek"
      }
    },
    {
      "geometry": {
        "type": "Point",
        "coordinates": [
          -110.45,
          32.1167
        ]
      },
      "type": "Feature",
      "properties": {
        "hierarchy": [
          "tgn:2138539",
          "tgn:1000001",
          "tgn:7006451",
          "tgn:7012149",
          "tgn:7029392"
        ],
        "placetype": [
          "aat:300008706"
        ],
        "id": 2138539,
        "name:xx": "Ash Creek"
      }
    }
  ]
}
