{
  "geometry": {
    "type": "Point",
    "coordinates": [
      -105.1667,
      38.7333
    ]
  },
  "type": "Feature",
  "properties": {
    "hierarchy": [
      "tgn:2015429",
      "tgn:1000001",
      "tgn:7012149",
      "tgn:7007158",
      "tgn:2000251",
      "tgn:7029392"
    ],
    "placetype": [
      "aat:300008347"
    ],
    "id": 2015429,
    "name:xx": "Cripple Creek"
  }
}
