{
  "type": "FeatureCollection",
  "features": [
    {
      "geometry": {
        "type": "Point",
        "coordinates": [
          -119.35,
          44.3167
        ]
      },
      "type": "Feature",
      "properties": {
        "hierarchy": [
          "tgn:2300780",
          "tgn:1000001",
          "tgn:7012149",
          "tgn:2001708",
          "tgn:7007708",
          "tgn:7029392"
        ],
        "placetype": [
          "aat:300008706"
        ],
        "id": 2300780,
        "name:xx": "Duncan Creek"
      }
    },
    {
      "geometry": {
        "type": "Point",
        "coordinates": [
          -79.15,
          33.4333
        ]
      },
      "type": "Feature",
      "properties": {
        "hierarchy": [
          "tgn:2300781",
          "tgn:1000001",
          "tgn:2001746",
          "tgn:7012149",
          "tgn:7007712",
          "tgn:7029392"
        ],
        "placetype": [
          "aat:300008706"
        ],
        "id": 2300781,
        "name:xx": "Duncan Creek"
      }
    },
    {
      "geometry": {
        "type": "Point",
        "coordinates": [
          -81.5167,
          33.9
        ]
      },
      "type": "Feature",
      "properties": {
        "hierarchy": [
          "tgn:2300782",
          "tgn:1000001",
          "tgn:7012149",
          "tgn:7007712",
          "tgn:7029392"
        ],
        "placetype": [
          "aat:300008706"
        ],
        "id": 2300782,
        "name:xx": "Duncan Creek"
      }
    },
    {
      "geometry": {
        "type": "Point",
        "coordinates": [
          -102.2,
          45.4167
        ]
      },
      "type": "Feature",
      "properties": {
        "hierarchy": [
          "tgn:2300783",
          "tgn:1000001",
          "tgn:7012149",
          "tgn:2001822",
          "tgn:7007713",
          "tgn:7029392"
        ],
        "placetype": [
          "aat:300008706"
        ],
        "id": 2300783,
        "name:xx": "Duncan Creek"
      }
    },
    {
      "geometry": {
        "type": "Point",
        "coordinates": [
          -83.95,
          35.8
        ]
      },
      "type": "Feature",
      "properties": {
        "hierarchy": [
          "tgn:2300784",
          "tgn:1000001",
          "tgn:2001841",
          "tgn:7012149",
          "tgn:7007825",
          "tgn:7029392"
        ],
        "placetype": [
          "aat:300008706"
        ],
        "id": 2300784,
        "name:xx": "Duncan Creek"
      }
    },
    {
      "geometry": {
        "type": "Point",
        "coordinates": [
          -85.2167,
          36.0167
        ]
      },
      "type": "Feature",
      "properties": {
        "hierarchy": [
          "tgn:2300785",
          "tgn:1000001",
          "tgn:7012149",
          "tgn:2001854",
          "tgn:7007825",
          "tgn:7029392"
        ],
        "placetype": [
          "aat:300008706"
        ],
        "id": 2300785,
        "name:xx": "Duncan Creek"
      }
    },
    {
      "geometry": {
        "type": "Point",
        "coordinates": [
          -98.6667,
          31.9
        ]
      },
      "type": "Feature",
      "properties": {
        "hierarchy": [
          "tgn:2300786",
          "tgn:1000001",
          "tgn:7012149",
          "tgn:2001962",
          "tgn:7007826",
          "tgn:7029392"
        ],
        "placetype": [
          "aat:300008706"
        ],
        "id": 2300786,
        "name:xx": "Duncan Creek"
      }
    },
    {
      "geometry": {
        "type": "Point",
        "coordinates": [
          -99.45,
          29.7667
        ]
      },
      "type": "Feature",
      "properties": {
        "hierarchy": [
          "tgn:2300787",
          "tgn:1000001",
          "tgn:2001938",
          "tgn:7012149",
          "tgn:7007826",
          "tgn:7029392"
        ],
        "placetype": [
          "aat:300008706"
        ],
        "id": 2300787,
        "name:xx": "Duncan Creek"
      }
    },
    {
      "geometry": {
        "type": "Point",
        "coordinates": [
          -112.4333,
          38.3333
        ]
      },
      "type": "Feature",
      "properties": {
        "hierarchy": [
          "tgn:2300788",
          "tgn:2002101",
          "tgn:1000001",
          "tgn:7012149",
          "tgn:7007827",
          "tgn:7029392"
        ],
        "placetype": [
          "aat:300008706"
        ],
        "id": 2300788,
        "name:xx": "Duncan Creek"
      }
    },
    {
      "geometry": {
        "type": "Point",
        "coordinates": [
          -113.3333,
          37.5667
        ]
      },
      "type": "Feature",
      "properties": {
        "hierarchy": [
          "tgn:2300789",
          "tgn:1000001",
          "tgn:7012149",
          "tgn:2002111",
          "tgn:7007827",
          "tgn:7029392"
        ],
        "placetype": [
          "aat:300008706"
        ],
        "id": 2300789,
        "name:xx": "Duncan Creek"
      }
    }
  ]
}
