{
  "type": "FeatureCollection",
  "features": [
    {
      "geometry": {
        "type": "Point",
        "coordinates": [
          -77.3167,
          42.9833
        ]
      },
      "type": "Feature",
      "properties": {
        "hierarchy": [
          "tgn:2069161",
          "tgn:1000001",
          "tgn:7012149",
          "tgn:1002747",
          "tgn:7007568",
          "tgn:7029392"
        ],
        "placetype": [
          "aat:300008347"
        ],
        "id": 2069161,
        "name:xx": "Farmington"
      }
    },
    {
      "geometry": {
        "type": "Point",
        "coordinates": [
          -73.0167,
          40.8167
        ]
      },
      "type": "Feature",
      "properties": {
        "hierarchy": [
          "tgn:2069162",
          "tgn:1000001",
          "tgn:7012149",
          "tgn:1002924",
          "tgn:7007568",
          "tgn:7029392"
        ],
        "placetype": [
          "aat:300008347"
        ],
        "id": 2069162,
        "name:xx": "Farmingville"
      }
    },
    {
      "geometry": {
        "type": "Point",
        "coordinates": [
          -79.0833,
          42.5833
        ]
      },
      "type": "Feature",
      "properties": {
        "hierarchy": [
          "tgn:2069163",
          "tgn:1000001",
          "tgn:7012149",
          "tgn:1002356",
          "tgn:7007568",
          "tgn:7029392"
        ],
        "placetype": [
          "aat:300008347"
        ],
        "id": 2069163,
        "name:xx": "Farnham"
      }
    },
    {
      "geometry": {
        "type": "Point",
        "coordinates": [
          -76.8,
          42.8
        ]
      },
      "type": "Feature",
      "properties": {
        "hierarchy": [
          "tgn:2069165",
          "tgn:1000001",
          "tgn:7012149",
          "tgn:1002882",
          "tgn:7007568",
          "tgn:7029392"
        ],
        "placetype": [
          "aat:300008347"
        ],
        "id": 2069165,
        "name:xx": "Fayette"
      }
    },
    {
      "geometry": {
        "type": "Point",
        "coordinates": [
          -76,
          43.0167
        ]
      },
      "type": "Feature",
      "properties": {
        "hierarchy": [
          "tgn:2069166",
          "tgn:1000001",
          "tgn:7012149",
          "tgn:1002746",
          "tgn:7007568",
          "tgn:7029392"
        ],
        "placetype": [
          "aat:300008347"
        ],
        "id": 2069166,
        "name:xx": "Fayetteville"
      }
    },
    {
      "geometry": {
        "type": "Point",
        "coordinates": [
          -75.75,
          44.0167
        ]
      },
      "type": "Feature",
      "properties": {
        "hierarchy": [
          "tgn:2069169",
          "tgn:1000001",
          "tgn:7012149",
          "tgn:1002518",
          "tgn:7007568",
          "tgn:7029392"
        ],
        "placetype": [
          "aat:300008347"
        ],
        "id": 2069169,
        "name:xx": "Felts Mills"
      }
    }
  ]
}
