{
  "geometry": {
    "type": "Point",
    "coordinates": [
      -165.2667,
      64.55
    ]
  },
  "type": "Feature",
  "properties": {
    "hierarchy": [
      "tgn:2470871",
      "tgn:7006450",
      "tgn:1000001",
      "tgn:7012149",
      "tgn:2000079",
      "tgn:7029392"
    ],
    "placetype": [
      "aat:300008706"
    ],
    "id": 2470871,
    "name:xx": "Lost Creek"
  }
}
