{
  "geometry": {
    "type": "Point",
    "coordinates": [
      89.3167,
      56.5333
    ]
  },
  "type": "Feature",
  "properties": {
    "hierarchy": [
      "tgn:1060038",
      "tgn:1000004",
      "tgn:1003314",
      "tgn:7018214",
      "tgn:7002435",
      "tgn:7029392"
    ],
    "placetype": [
      "aat:300008347"
    ],
    "id": 1060038,
    "name:xx": "Tyukhtet"
  }
}
