{
  "type": "FeatureCollection",
  "features": [
    {
      "geometry": {
        "type": "Point",
        "coordinates": [
          15.65,
          41
        ]
      },
      "type": "Feature",
      "properties": {
        "hierarchy": [
          "tgn:7004230",
          "tgn:1003489",
          "tgn:7004610",
          "tgn:1000003",
          "tgn:1000080",
          "tgn:7029392"
        ],
        "placetype": [
          "aat:300387277",
          "aat:300008347",
          "aat:300000810",
          "aat:300008375",
          "aat:300387291"
        ],
        "id": 7004230,
        "name:xx": "Melfi"
      }
    },
    {
      "geometry": {
        "type": "Point",
        "coordinates": [
          15.816667,
          40.966667
        ]
      },
      "type": "Feature",
      "properties": {
        "hierarchy": [
          "tgn:7004231",
          "tgn:1003489",
          "tgn:7004610",
          "tgn:1000003",
          "tgn:1000080",
          "tgn:7029392"
        ],
        "placetype": [
          "aat:300008347",
          "aat:300008375"
        ],
        "id": 7004231,
        "name:xx": "Venosa"
      }
    },
    {
      "geometry": {
        "type": "Point",
        "coordinates": [
          15.716,
          40.916
        ]
      },
      "type": "Feature",
      "properties": {
        "hierarchy": [
          "tgn:7004232",
          "tgn:1003489",
          "tgn:7004610",
          "tgn:1000003",
          "tgn:1000080",
          "tgn:7029392"
        ],
        "placetype": [
          "aat:300008347"
        ],
        "id": 7004232,
        "name:xx": "Ripacandida"
      }
    },
    {
      "geometry": {
        "type": "Point",
        "coordinates": [
          102.6,
          17.9667
        ]
      },
      "type": "Feature",
      "properties": {
        "hierarchy": [
          "tgn:7004233",
          "tgn:1000004",
          "tgn:7018518",
          "tgn:7000851",
          "tgn:1000125",
          "tgn:7029392"
        ],
        "placetype": [
          "aat:300008347",
          "aat:300008389",
          "aat:300387219",
          "aat:300387512",
          "aat:300387223",
          "aat:300387270",
          "aat:300120599"
        ],
        "id": 7004233,
        "name:xx": "Vientiane"
      }
    },
    {
      "geometry": {
        "type": "Point",
        "coordinates": [
          101.1333,
          19.8833
        ]
      },
      "type": "Feature",
      "properties": {
        "hierarchy": [
          "tgn:7004234",
          "tgn:1000004",
          "tgn:1000125",
          "tgn:7029392"
        ],
        "placetype": [
          "aat:300008707"
        ],
        "id": 7004234,
        "name:xx": "Bèng"
      }
    },
    {
      "geometry": {
        "type": "Point",
        "coordinates": [
          103.0333,
          21.3833
        ]
      },
      "type": "Feature",
      "properties": {
        "hierarchy": [
          "tgn:7004238",
          "tgn:1000004",
          "tgn:7001048",
          "tgn:1000145",
          "tgn:7029392"
        ],
        "placetype": [
          "aat:300008347",
          "aat:300000835",
          "aat:300387275",
          "aat:300008372"
        ],
        "id": 7004238,
        "name:xx": "Diện Biên Phủ"
      }
    }
  ]
}
