{
  "type": "FeatureCollection",
  "features": [
    {
      "geometry": {
        "type": "Point",
        "coordinates": [
          -79.5833,
          37
        ]
      },
      "type": "Feature",
      "properties": {
        "hierarchy": [
          "tgn:2253970",
          "tgn:1000001",
          "tgn:7012149",
          "tgn:7007919",
          "tgn:7029392"
        ],
        "placetype": [
          "aat:300008699"
        ],
        "id": 2253970,
        "name:xx": "Cool Branch"
      }
    },
    {
      "geometry": {
        "type": "Point",
        "coordinates": [
          -85.0167,
          39.8167
        ]
      },
      "type": "Feature",
      "properties": {
        "hierarchy": [
          "tgn:2253971",
          "tgn:1000001",
          "tgn:7012149",
          "tgn:1003004",
          "tgn:7007252",
          "tgn:7029392"
        ],
        "placetype": [
          "aat:300008699"
        ],
        "id": 2253971,
        "name:xx": "Cool Brook"
      }
    },
    {
      "geometry": {
        "type": "Point",
        "coordinates": [
          -70.35,
          44.1333
        ]
      },
      "type": "Feature",
      "properties": {
        "hierarchy": [
          "tgn:2253972",
          "tgn:2000918",
          "tgn:1000001",
          "tgn:7012149",
          "tgn:7007515",
          "tgn:7029392"
        ],
        "placetype": [
          "aat:300008699"
        ],
        "id": 2253972,
        "name:xx": "Cool Brook"
      }
    },
    {
      "geometry": {
        "type": "Point",
        "coordinates": [
          -91.45,
          31.7
        ]
      },
      "type": "Feature",
      "properties": {
        "hierarchy": [
          "tgn:2253973",
          "tgn:1000001",
          "tgn:2000868",
          "tgn:7012149",
          "tgn:7007256",
          "tgn:7029392"
        ],
        "placetype": [
          "aat:300008347"
        ],
        "id": 2253973,
        "name:xx": "Cool Coosa"
      }
    },
    {
      "geometry": {
        "type": "Point",
        "coordinates": [
          -104.65,
          39.4167
        ]
      },
      "type": "Feature",
      "properties": {
        "hierarchy": [
          "tgn:2253974",
          "tgn:1000001",
          "tgn:7012149",
          "tgn:7007158",
          "tgn:7029392"
        ],
        "placetype": [
          "aat:300008706"
        ],
        "id": 2253974,
        "name:xx": "Cool Creek"
      }
    },
    {
      "geometry": {
        "type": "Point",
        "coordinates": [
          -116.3667,
          44.7167
        ]
      },
      "type": "Feature",
      "properties": {
        "hierarchy": [
          "tgn:2253975",
          "tgn:1000001",
          "tgn:7012149",
          "tgn:2000494",
          "tgn:7007250",
          "tgn:7029392"
        ],
        "placetype": [
          "aat:300008706"
        ],
        "id": 2253975,
        "name:xx": "Cool Creek"
      }
    },
    {
      "geometry": {
        "type": "Point",
        "coordinates": [
          -115.2833,
          46.75
        ]
      },
      "type": "Feature",
      "properties": {
        "hierarchy": [
          "tgn:2253976",
          "tgn:1000001",
          "tgn:2000469",
          "tgn:7012149",
          "tgn:7007250",
          "tgn:7029392"
        ],
        "placetype": [
          "aat:300008706"
        ],
        "id": 2253976,
        "name:xx": "Cool Creek"
      }
    },
    {
      "geometry": {
        "type": "Point",
        "coordinates": [
          -86.1333,
          40.05
        ]
      },
      "type": "Feature",
      "properties": {
        "hierarchy": [
          "tgn:2253977",
          "tgn:1000001",
          "tgn:7012149",
          "tgn:1002439",
          "tgn:7007252",
          "tgn:7029392"
        ],
        "placetype": [
          "aat:300008706"
        ],
        "id": 2253977,
        "name:xx": "Cool Creek"
      }
    },
    {
      "geometry": {
        "type": "Point",
        "coordinates": [
          -97.65,
          39.6667
        ]
      },
      "type": "Feature",
      "properties": {
        "hierarchy": [
          "tgn:2253978",
          "tgn:1000001",
          "tgn:7012149",
          "tgn:7007254",
          "tgn:7029392"
        ],
        "placetype": [
          "aat:300008706"
        ],
        "id": 2253978,
        "name:xx": "Cool Creek"
      }
    },
    {
      "geometry": {
        "type": "Point",
        "coordinates": [
          -88.1667,
          36.7333
        ]
      },
      "type": "Feature",
      "properties": {
        "hierarchy": [
          "tgn:2253979",
          "tgn:1000001",
          "tgn:7012149",
          "tgn:7007255",
          "tgn:7029392"
        ],
        "placetype": [
          "aat:300008706"
        ],
        "id": 2253979,
        "name:xx": "Cool Creek"
      }
    }
  ]
}
