{
  "geometry": {
    "type": "Point",
    "coordinates": [
      -82.3167,
      36.2667
    ]
  },
  "type": "Feature",
  "properties": {
    "hierarchy": [
      "tgn:2100849",
      "tgn:1000001",
      "tgn:7012149",
      "tgn:2001846",
      "tgn:7007825",
      "tgn:7029392"
    ],
    "placetype": [
      "aat:300008347",
      "aat:300387210"
    ],
    "id": 2100849,
    "name:xx": "Okolona"
  }
}
