{
  "geometry": {
    "type": "Point",
    "coordinates": [
      -86.75,
      34.7833
    ]
  },
  "type": "Feature",
  "properties": {
    "hierarchy": [
      "tgn:2441319",
      "tgn:7002659",
      "tgn:1000001",
      "tgn:7012149",
      "tgn:7029392"
    ],
    "placetype": [
      "aat:300008706"
    ],
    "id": 2441319,
    "name:xx": "Knox Creek"
  }
}
