{
  "geometry": {
    "type": "Point",
    "coordinates": [
      117.0167,
      39.0667
    ]
  },
  "type": "Feature",
  "properties": {
    "hierarchy": [
      "tgn:1067131",
      "tgn:1000004",
      "tgn:1000960",
      "tgn:1000111",
      "tgn:7029392"
    ],
    "placetype": [
      "aat:300008347"
    ],
    "id": 1067131,
    "name:xx": "Chaomidian"
  }
}
