{
  "geometry": {
    "type": "Point",
    "coordinates": [
      6.6833,
      60.8333
    ]
  },
  "type": "Feature",
  "properties": {
    "hierarchy": [
      "tgn:1048768",
      "tgn:7003646",
      "tgn:1000003",
      "tgn:1000088",
      "tgn:7029392"
    ],
    "placetype": [
      "aat:300008347"
    ],
    "id": 1048768,
    "name:xx": "Stalheim"
  }
}
