{
  "geometry": {
    "type": "Point",
    "coordinates": [
      -85.6833,
      38.1833
    ]
  },
  "type": "Feature",
  "properties": {
    "hierarchy": [
      "tgn:2041947",
      "tgn:1000001",
      "tgn:7012149",
      "tgn:1002516",
      "tgn:7007255",
      "tgn:7029392"
    ],
    "placetype": [
      "aat:300387016"
    ],
    "id": 2041947,
    "name:xx": "Whitner"
  }
}
