{
  "geometry": {
    "type": "Point",
    "coordinates": [
      23.35,
      39.95
    ]
  },
  "type": "Feature",
  "properties": {
    "hierarchy": [
      "tgn:7228443",
      "tgn:7002715",
      "tgn:7002731",
      "tgn:1000003",
      "tgn:1000074",
      "tgn:7029392"
    ],
    "placetype": [
      "aat:300008850"
    ],
    "id": 7228443,
    "name:xx": "Kassándras, Ákra"
  }
}
