{
  "geometry": {
    "type": "Point",
    "coordinates": [
      -119.1333,
      44.3667
    ]
  },
  "type": "Feature",
  "properties": {
    "hierarchy": [
      "tgn:2610854",
      "tgn:1000001",
      "tgn:7012149",
      "tgn:2001708",
      "tgn:7007708",
      "tgn:7029392"
    ],
    "placetype": [
      "aat:300008761"
    ],
    "id": 2610854,
    "name:xx": "Red Gulch"
  }
}
