{
  "geometry": {
    "type": "Point",
    "coordinates": [
      130.8333,
      -3.65
    ]
  },
  "type": "Feature",
  "properties": {
    "hierarchy": [
      "tgn:1077366",
      "tgn:1000004",
      "tgn:1001409",
      "tgn:1009102",
      "tgn:1000116",
      "tgn:7029392"
    ],
    "placetype": [
      "aat:300008347"
    ],
    "id": 1077366,
    "name:xx": "Angar"
  }
}
