{
  "type": "FeatureCollection",
  "features": [
    {
      "geometry": {
        "type": "Point",
        "coordinates": [
          12.8,
          48.566667
        ]
      },
      "type": "Feature",
      "properties": {
        "hierarchy": [
          "tgn:7200410",
          "tgn:7003669",
          "tgn:1000003",
          "tgn:7000084",
          "tgn:7029392"
        ],
        "placetype": [
          "aat:300000206"
        ],
        "id": 7200410,
        "name:xx": "Ed"
      }
    },
    {
      "geometry": {
        "type": "Point",
        "coordinates": [
          12.666667,
          48.433333
        ]
      },
      "type": "Feature",
      "properties": {
        "hierarchy": [
          "tgn:7200411",
          "tgn:7003669",
          "tgn:1000003",
          "tgn:7000084",
          "tgn:7029392"
        ],
        "placetype": [
          "aat:300000206"
        ],
        "id": 7200411,
        "name:xx": "Ed"
      }
    },
    {
      "geometry": {
        "type": "Point",
        "coordinates": [
          12.883333,
          48.4
        ]
      },
      "type": "Feature",
      "properties": {
        "hierarchy": [
          "tgn:7200412",
          "tgn:7003669",
          "tgn:1000003",
          "tgn:7000084",
          "tgn:7029392"
        ],
        "placetype": [
          "aat:300000206"
        ],
        "id": 7200412,
        "name:xx": "Ed"
      }
    },
    {
      "geometry": {
        "type": "Point",
        "coordinates": [
          13.283333,
          48.35
        ]
      },
      "type": "Feature",
      "properties": {
        "hierarchy": [
          "tgn:7200413",
          "tgn:7003669",
          "tgn:1000003",
          "tgn:7000084",
          "tgn:7029392"
        ],
        "placetype": [
          "aat:300000206"
        ],
        "id": 7200413,
        "name:xx": "Ed"
      }
    },
    {
      "geometry": {
        "type": "Point",
        "coordinates": [
          12.966667,
          48.283333
        ]
      },
      "type": "Feature",
      "properties": {
        "hierarchy": [
          "tgn:7200414",
          "tgn:7003669",
          "tgn:1000003",
          "tgn:7000084",
          "tgn:7029392"
        ],
        "placetype": [
          "aat:300000206"
        ],
        "id": 7200414,
        "name:xx": "Ed"
      }
    },
    {
      "geometry": {
        "type": "Point",
        "coordinates": [
          12.383333,
          48.016667
        ]
      },
      "type": "Feature",
      "properties": {
        "hierarchy": [
          "tgn:7200416",
          "tgn:7003669",
          "tgn:1000003",
          "tgn:7000084",
          "tgn:7029392"
        ],
        "placetype": [
          "aat:300000206"
        ],
        "id": 7200416,
        "name:xx": "Ed"
      }
    },
    {
      "geometry": {
        "type": "Point",
        "coordinates": [
          11,
          47.683333
        ]
      },
      "type": "Feature",
      "properties": {
        "hierarchy": [
          "tgn:7200417",
          "tgn:7003669",
          "tgn:1000003",
          "tgn:7000084",
          "tgn:7029392"
        ],
        "placetype": [
          "aat:300386990"
        ],
        "id": 7200417,
        "name:xx": "Eck Wiesen"
      }
    },
    {
      "geometry": {
        "type": "Point",
        "coordinates": [
          13.75,
          48.6
        ]
      },
      "type": "Feature",
      "properties": {
        "hierarchy": [
          "tgn:7200418",
          "tgn:7003669",
          "tgn:1000003",
          "tgn:7000084",
          "tgn:7029392"
        ],
        "placetype": [
          "aat:300000206"
        ],
        "id": 7200418,
        "name:xx": "Eckwies"
      }
    },
    {
      "geometry": {
        "type": "Point",
        "coordinates": [
          9.966667,
          50.583333
        ]
      },
      "type": "Feature",
      "properties": {
        "hierarchy": [
          "tgn:7200419",
          "tgn:1000003",
          "tgn:7003678",
          "tgn:7000084",
          "tgn:7029392"
        ],
        "placetype": [
          "aat:300008777"
        ],
        "id": 7200419,
        "name:xx": "Eckweisbacher Kuppe"
      }
    }
  ]
}
