{
  "geometry": {
    "type": "Point",
    "coordinates": [
      -65.8167,
      51.6667
    ]
  },
  "type": "Feature",
  "properties": {
    "hierarchy": [
      "tgn:1118837",
      "tgn:7005685",
      "tgn:1000001",
      "tgn:7005804",
      "tgn:7029392"
    ],
    "placetype": [
      "aat:300008680"
    ],
    "id": 1118837,
    "name:xx": "François, Lacs à"
  }
}
