{
  "geometry": {
    "type": "Point",
    "coordinates": [
      -86.1833,
      33.05
    ]
  },
  "type": "Feature",
  "properties": {
    "hierarchy": [
      "tgn:2464168",
      "tgn:7002659",
      "tgn:1000001",
      "tgn:2000018",
      "tgn:7012149",
      "tgn:7029392"
    ],
    "placetype": [
      "aat:300008798"
    ],
    "id": 2464168,
    "name:xx": "Locust Mountain"
  }
}
