{
  "geometry": {
    "type": "Point",
    "coordinates": [
      49.4833,
      14.8167
    ]
  },
  "type": "Feature",
  "properties": {
    "hierarchy": [
      "tgn:1084977",
      "tgn:1000139",
      "tgn:7004345",
      "tgn:1000004",
      "tgn:7000261",
      "tgn:7029392"
    ],
    "placetype": [
      "aat:300008347"
    ],
    "id": 1084977,
    "name:xx": "Ghayl Bā Wazīr"
  }
}
