{
  "geometry": {
    "type": "Point",
    "coordinates": [
      -56.4833,
      -28.7667
    ]
  },
  "type": "Feature",
  "properties": {
    "hierarchy": [
      "tgn:1020104",
      "tgn:7006477",
      "tgn:1001210",
      "tgn:1000002",
      "tgn:7029392"
    ],
    "placetype": [
      "aat:300008347"
    ],
    "id": 1020104,
    "name:xx": "Torrent"
  }
}
