{
  "type": "FeatureCollection",
  "features": [
    {
      "geometry": {
        "type": "Point",
        "coordinates": [
          -88.9167,
          41.1667
        ]
      },
      "type": "Feature",
      "properties": {
        "hierarchy": [
          "tgn:2775250",
          "tgn:1000001",
          "tgn:7012149",
          "tgn:1002562",
          "tgn:7007251",
          "tgn:7029392"
        ],
        "placetype": [
          "aat:300008347"
        ],
        "id": 2775250,
        "name:xx": "Wilsman"
      }
    },
    {
      "geometry": {
        "type": "Point",
        "coordinates": [
          -87.6667,
          34.9167
        ]
      },
      "type": "Feature",
      "properties": {
        "hierarchy": [
          "tgn:2775251",
          "tgn:7002659",
          "tgn:1000001",
          "tgn:7012149",
          "tgn:2000038",
          "tgn:7029392"
        ],
        "placetype": [
          "aat:300008347"
        ],
        "id": 2775251,
        "name:xx": "Wilson"
      }
    },
    {
      "geometry": {
        "type": "Point",
        "coordinates": [
          -121.6167,
          38.9667
        ]
      },
      "type": "Feature",
      "properties": {
        "hierarchy": [
          "tgn:2775252",
          "tgn:1000001",
          "tgn:7012149",
          "tgn:7007157",
          "tgn:1002937",
          "tgn:7029392"
        ],
        "placetype": [
          "aat:300008347"
        ],
        "id": 2775252,
        "name:xx": "Wilson"
      }
    },
    {
      "geometry": {
        "type": "Point",
        "coordinates": [
          -72.65,
          41.8
        ]
      },
      "type": "Feature",
      "properties": {
        "hierarchy": [
          "tgn:2775253",
          "tgn:1000001",
          "tgn:1002461",
          "tgn:7012149",
          "tgn:7007159",
          "tgn:7029392"
        ],
        "placetype": [
          "aat:300008347"
        ],
        "id": 2775253,
        "name:xx": "Wilson"
      }
    },
    {
      "geometry": {
        "type": "Point",
        "coordinates": [
          -75.7333,
          39.65
        ]
      },
      "type": "Feature",
      "properties": {
        "hierarchy": [
          "tgn:2775254",
          "tgn:7014201",
          "tgn:1000001",
          "tgn:7012149",
          "tgn:7007239",
          "tgn:7029392"
        ],
        "placetype": [
          "aat:300008347"
        ],
        "id": 2775254,
        "name:xx": "Wilson"
      }
    },
    {
      "geometry": {
        "type": "Point",
        "coordinates": [
          -80.6833,
          28.6333
        ]
      },
      "type": "Feature",
      "properties": {
        "hierarchy": [
          "tgn:2775255",
          "tgn:1000001",
          "tgn:1002200",
          "tgn:7012149",
          "tgn:7007240",
          "tgn:7029392"
        ],
        "placetype": [
          "aat:300008347"
        ],
        "id": 2775255,
        "name:xx": "Wilson"
      }
    },
    {
      "geometry": {
        "type": "Point",
        "coordinates": [
          -116.65,
          43.35
        ]
      },
      "type": "Feature",
      "properties": {
        "hierarchy": [
          "tgn:2775256",
          "tgn:1000001",
          "tgn:7012149",
          "tgn:2000488",
          "tgn:7007250",
          "tgn:7029392"
        ],
        "placetype": [
          "aat:300008347"
        ],
        "id": 2775256,
        "name:xx": "Wilson"
      }
    },
    {
      "geometry": {
        "type": "Point",
        "coordinates": [
          -87.9,
          42.3333
        ]
      },
      "type": "Feature",
      "properties": {
        "hierarchy": [
          "tgn:2775257",
          "tgn:1000001",
          "tgn:7012149",
          "tgn:7013855",
          "tgn:7007251",
          "tgn:7029392"
        ],
        "placetype": [
          "aat:300008347"
        ],
        "id": 2775257,
        "name:xx": "Wilson"
      }
    },
    {
      "geometry": {
        "type": "Point",
        "coordinates": [
          -93.0667,
          41.6333
        ]
      },
      "type": "Feature",
      "properties": {
        "hierarchy": [
          "tgn:2775258",
          "tgn:1000001",
          "tgn:7012149",
          "tgn:2000610",
          "tgn:7007253",
          "tgn:7029392"
        ],
        "placetype": [
          "aat:300008347"
        ],
        "id": 2775258,
        "name:xx": "Wilson"
      }
    },
    {
      "geometry": {
        "type": "Point",
        "coordinates": [
          -76.5167,
          38.6
        ]
      },
      "type": "Feature",
      "properties": {
        "hierarchy": [
          "tgn:2775259",
          "tgn:1002224",
          "tgn:1000001",
          "tgn:7012149",
          "tgn:7007516",
          "tgn:7029392"
        ],
        "placetype": [
          "aat:300008347"
        ],
        "id": 2775259,
        "name:xx": "Wilson"
      }
    }
  ]
}
