{
  "geometry": {
    "type": "Point",
    "coordinates": [
      72.0833,
      39.8833
    ]
  },
  "type": "Feature",
  "properties": {
    "hierarchy": [
      "tgn:1051650",
      "tgn:1000004",
      "tgn:7012212",
      "tgn:7006655",
      "tgn:7029392"
    ],
    "placetype": [
      "aat:300008347"
    ],
    "id": 1051650,
    "name:xx": "Shibbe"
  }
}
