{
  "geometry": {
    "type": "Point",
    "coordinates": [
      89.4167,
      23.95
    ]
  },
  "type": "Feature",
  "properties": {
    "hierarchy": [
      "tgn:1065952",
      "tgn:1000004",
      "tgn:7000191",
      "tgn:1000105",
      "tgn:7029392"
    ],
    "placetype": [
      "aat:300008347"
    ],
    "id": 1065952,
    "name:xx": "Sujānagar"
  }
}
