{
  "geometry": {
    "type": "Point",
    "coordinates": [
      -166.05,
      68.8333
    ]
  },
  "type": "Feature",
  "properties": {
    "hierarchy": [
      "tgn:2652076",
      "tgn:7006450",
      "tgn:1000001",
      "tgn:7012149",
      "tgn:2124005",
      "tgn:7029392"
    ],
    "placetype": [
      "aat:300008706"
    ],
    "id": 2652076,
    "name:xx": "Selin Creek"
  }
}
