{
  "geometry": {
    "type": "Point",
    "coordinates": [
      -114.0167,
      43.3167
    ]
  },
  "type": "Feature",
  "properties": {
    "hierarchy": [
      "tgn:2143898",
      "tgn:1000001",
      "tgn:2000458",
      "tgn:7012149",
      "tgn:7007250",
      "tgn:7029392"
    ],
    "placetype": [
      "aat:300008761"
    ],
    "id": 2143898,
    "name:xx": "Baker Canyon"
  }
}
