{
  "type": "FeatureCollection",
  "features": [
    {
      "geometry": {
        "type": "Point",
        "coordinates": [
          -88.2333,
          44.6667
        ]
      },
      "type": "Feature",
      "properties": {
        "hierarchy": [
          "tgn:2122190",
          "tgn:1000001",
          "tgn:2002309",
          "tgn:7012149",
          "tgn:7007922",
          "tgn:7029392"
        ],
        "placetype": [
          "aat:300008347"
        ],
        "id": 2122190,
        "name:xx": "Pulaski"
      }
    },
    {
      "geometry": {
        "type": "Point",
        "coordinates": [
          -88.35,
          44.8333
        ]
      },
      "type": "Feature",
      "properties": {
        "hierarchy": [
          "tgn:2122191",
          "tgn:1000001",
          "tgn:7012149",
          "tgn:2002354",
          "tgn:7007922",
          "tgn:7029392"
        ],
        "placetype": [
          "aat:300008347"
        ],
        "id": 2122191,
        "name:xx": "Pulcifer"
      }
    },
    {
      "geometry": {
        "type": "Point",
        "coordinates": [
          -91.0333,
          43.5167
        ]
      },
      "type": "Feature",
      "properties": {
        "hierarchy": [
          "tgn:2122192",
          "tgn:1000001",
          "tgn:7012149",
          "tgn:2002358",
          "tgn:7007922",
          "tgn:7029392"
        ],
        "placetype": [
          "aat:300008347",
          "aat:300387210"
        ],
        "id": 2122192,
        "name:xx": "Purdy"
      }
    },
    {
      "geometry": {
        "type": "Point",
        "coordinates": [
          -87.9167,
          44.0667
        ]
      },
      "type": "Feature",
      "properties": {
        "hierarchy": [
          "tgn:2122193",
          "tgn:1000001",
          "tgn:7012149",
          "tgn:2002335",
          "tgn:7007922",
          "tgn:7029392"
        ],
        "placetype": [
          "aat:300008347"
        ],
        "id": 2122193,
        "name:xx": "Quarry"
      }
    },
    {
      "geometry": {
        "type": "Point",
        "coordinates": [
          -88.3,
          44
        ]
      },
      "type": "Feature",
      "properties": {
        "hierarchy": [
          "tgn:2122194",
          "tgn:1000001",
          "tgn:2002312",
          "tgn:7012149",
          "tgn:7007922",
          "tgn:7029392"
        ],
        "placetype": [
          "aat:300008347"
        ],
        "id": 2122194,
        "name:xx": "Quinney"
      }
    }
  ]
}
