{
  "geometry": {
    "type": "Point",
    "coordinates": [
      121.31,
      24.6675
    ]
  },
  "type": "Feature",
  "properties": {
    "hierarchy": [
      "tgn:7472306",
      "tgn:1000004",
      "tgn:7001013",
      "tgn:1000141",
      "tgn:7029392"
    ],
    "placetype": [
      "aat:300008798"
    ],
    "id": 7472306,
    "name:xx": "Wulai Shan"
  }
}
