{
  "type": "FeatureCollection",
  "features": [
    {
      "geometry": {
        "type": "Point",
        "coordinates": [
          -78.7167,
          38.8167
        ]
      },
      "type": "Feature",
      "properties": {
        "hierarchy": [
          "tgn:2511300",
          "tgn:1000001",
          "tgn:7012149",
          "tgn:2002190",
          "tgn:7007919",
          "tgn:7029392"
        ],
        "placetype": [
          "aat:300008699"
        ],
        "id": 2511300,
        "name:xx": "Mikes Run"
      }
    },
    {
      "geometry": {
        "type": "Point",
        "coordinates": [
          -81.6833,
          38.1833
        ]
      },
      "type": "Feature",
      "properties": {
        "hierarchy": [
          "tgn:2511301",
          "tgn:1000001",
          "tgn:2002255",
          "tgn:7012149",
          "tgn:7013961",
          "tgn:7029392"
        ],
        "placetype": [
          "aat:300008699"
        ],
        "id": 2511301,
        "name:xx": "Mikes Run"
      }
    },
    {
      "geometry": {
        "type": "Point",
        "coordinates": [
          -80.7,
          38.95
        ]
      },
      "type": "Feature",
      "properties": {
        "hierarchy": [
          "tgn:2511302",
          "tgn:1000001",
          "tgn:2002262",
          "tgn:7012149",
          "tgn:7013961",
          "tgn:7029392"
        ],
        "placetype": [
          "aat:300008699"
        ],
        "id": 2511302,
        "name:xx": "Mikes Run"
      }
    },
    {
      "geometry": {
        "type": "Point",
        "coordinates": [
          -79.7333,
          38.7
        ]
      },
      "type": "Feature",
      "properties": {
        "hierarchy": [
          "tgn:2511303",
          "tgn:1000001",
          "tgn:7012149",
          "tgn:2002287",
          "tgn:7013961",
          "tgn:7029392"
        ],
        "placetype": [
          "aat:300008699"
        ],
        "id": 2511303,
        "name:xx": "Mikes Run"
      }
    },
    {
      "geometry": {
        "type": "Point",
        "coordinates": [
          -80.9667,
          38.8667
        ]
      },
      "type": "Feature",
      "properties": {
        "hierarchy": [
          "tgn:2511304",
          "tgn:1000001",
          "tgn:7012149",
          "tgn:7013961",
          "tgn:7029392"
        ],
        "placetype": [
          "aat:300008699"
        ],
        "id": 2511304,
        "name:xx": "Mikes Run"
      }
    },
    {
      "geometry": {
        "type": "Point",
        "coordinates": [
          -78.8833,
          39.4
        ]
      },
      "type": "Feature",
      "properties": {
        "hierarchy": [
          "tgn:2511305",
          "tgn:1000001",
          "tgn:7012149",
          "tgn:2002279",
          "tgn:7013961",
          "tgn:7029392"
        ],
        "placetype": [
          "aat:300008699"
        ],
        "id": 2511305,
        "name:xx": "Mikes Run"
      }
    },
    {
      "geometry": {
        "type": "Point",
        "coordinates": [
          -85.7,
          35.0333
        ]
      },
      "type": "Feature",
      "properties": {
        "hierarchy": [
          "tgn:2511306",
          "tgn:1000001",
          "tgn:7012149",
          "tgn:2001894",
          "tgn:7007825",
          "tgn:7029392"
        ],
        "placetype": [
          "aat:300008746"
        ],
        "id": 2511306,
        "name:xx": "Mikes Slit"
      }
    },
    {
      "geometry": {
        "type": "Point",
        "coordinates": [
          -115.8333,
          39.4833
        ]
      },
      "type": "Feature",
      "properties": {
        "hierarchy": [
          "tgn:2511307",
          "tgn:1000001",
          "tgn:7012149",
          "tgn:2001420",
          "tgn:7007526",
          "tgn:7029392"
        ],
        "placetype": [
          "aat:300008697"
        ],
        "id": 2511307,
        "name:xx": "Mikes Spring"
      }
    },
    {
      "geometry": {
        "type": "Point",
        "coordinates": [
          -110.45,
          34.45
        ]
      },
      "type": "Feature",
      "properties": {
        "hierarchy": [
          "tgn:2511308",
          "tgn:1000001",
          "tgn:7006451",
          "tgn:7012149",
          "tgn:2000099",
          "tgn:7029392"
        ],
        "placetype": [
          "aat:300006191"
        ],
        "id": 2511308,
        "name:xx": "Mikes Tank"
      }
    },
    {
      "geometry": {
        "type": "Point",
        "coordinates": [
          -113.05,
          34.8167
        ]
      },
      "type": "Feature",
      "properties": {
        "hierarchy": [
          "tgn:2511309",
          "tgn:1000001",
          "tgn:7006451",
          "tgn:7012149",
          "tgn:2000103",
          "tgn:7029392"
        ],
        "placetype": [
          "aat:300006191"
        ],
        "id": 2511309,
        "name:xx": "Mikes Tank"
      }
    }
  ]
}
