{
  "geometry": {
    "type": "Point",
    "coordinates": [
      -114.8333,
      48.2833
    ]
  },
  "type": "Feature",
  "properties": {
    "hierarchy": [
      "tgn:2642634",
      "tgn:1000001",
      "tgn:7012149",
      "tgn:2001274",
      "tgn:7007524",
      "tgn:7029392"
    ],
    "placetype": [
      "aat:300008798"
    ],
    "id": 2642634,
    "name:xx": "Sanders Mountain"
  }
}
