{
  "geometry": {
    "type": "Point",
    "coordinates": [
      17.203,
      50.23
    ]
  },
  "type": "Feature",
  "properties": {
    "hierarchy": [
      "tgn:1027242",
      "tgn:7593917",
      "tgn:1000003",
      "tgn:1001780",
      "tgn:7029392"
    ],
    "placetype": [
      "aat:300008347"
    ],
    "id": 1027242,
    "name:xx": "Jeseník"
  }
}
