{
  "geometry": {
    "type": "Point",
    "coordinates": [
      -95.9333,
      37.5667
    ]
  },
  "type": "Feature",
  "properties": {
    "hierarchy": [
      "tgn:2036863",
      "tgn:1000001",
      "tgn:7012149",
      "tgn:2000762",
      "tgn:7007254",
      "tgn:7029392"
    ],
    "placetype": [
      "aat:300008347"
    ],
    "id": 2036863,
    "name:xx": "New Albany"
  }
}
