{
  "geometry": {
    "type": "Point",
    "coordinates": [
      -83.4167,
      36.35
    ]
  },
  "type": "Feature",
  "properties": {
    "hierarchy": [
      "tgn:2101808",
      "tgn:1000001",
      "tgn:7012149",
      "tgn:2001865",
      "tgn:7007825",
      "tgn:7029392"
    ],
    "placetype": [
      "aat:300008347"
    ],
    "id": 2101808,
    "name:xx": "Thorn Hill"
  }
}
