{
  "type": "FeatureCollection",
  "features": [
    {
      "geometry": {
        "type": "Point",
        "coordinates": [
          174.65,
          -36.35
        ]
      },
      "type": "Feature",
      "properties": {
        "hierarchy": [
          "tgn:7514450",
          "tgn:7000508",
          "tgn:1008380",
          "tgn:1000226",
          "tgn:1000006",
          "tgn:7029392"
        ],
        "placetype": [
          "aat:300008795"
        ],
        "name:en": "Dome, The",
        "id": 7514450
      }
    },
    {
      "geometry": {
        "type": "Point",
        "coordinates": [
          177.5,
          -38.466667
        ]
      },
      "type": "Feature",
      "properties": {
        "hierarchy": [
          "tgn:7514451",
          "tgn:7520092",
          "tgn:1008380",
          "tgn:1000226",
          "tgn:1000006",
          "tgn:7029392"
        ],
        "placetype": [
          "aat:300008795"
        ],
        "name:en": "Dome",
        "id": 7514451
      }
    },
    {
      "geometry": {
        "type": "Point",
        "coordinates": [
          172.833333,
          -42.533333
        ]
      },
      "type": "Feature",
      "properties": {
        "hierarchy": [
          "tgn:7514452",
          "tgn:1009227",
          "tgn:7001866",
          "tgn:1000226",
          "tgn:1000006",
          "tgn:7029392"
        ],
        "placetype": [
          "aat:300008699"
        ],
        "name:en": "Dog Stream",
        "id": 7514452
      }
    },
    {
      "geometry": {
        "type": "Point",
        "coordinates": [
          167.183333,
          -45
        ]
      },
      "type": "Feature",
      "properties": {
        "hierarchy": [
          "tgn:7514453",
          "tgn:1009227",
          "tgn:1000226",
          "tgn:7016822",
          "tgn:1000006",
          "tgn:7029392"
        ],
        "placetype": [
          "aat:300386846"
        ],
        "name:en": "Dog Point",
        "id": 7514453
      }
    },
    {
      "geometry": {
        "type": "Point",
        "coordinates": [
          171.116667,
          -44.8
        ]
      },
      "type": "Feature",
      "properties": {
        "hierarchy": [
          "tgn:7514454",
          "tgn:1009227",
          "tgn:7001866",
          "tgn:1000226",
          "tgn:1000006",
          "tgn:7029392"
        ],
        "placetype": [
          "aat:300008699"
        ],
        "name:en": "Dog Kennel Stream",
        "id": 7514454
      }
    },
    {
      "geometry": {
        "type": "Point",
        "coordinates": [
          168.4,
          -46.65
        ]
      },
      "type": "Feature",
      "properties": {
        "hierarchy": [
          "tgn:7514455",
          "tgn:1009227",
          "tgn:1000226",
          "tgn:7016822",
          "tgn:1000006",
          "tgn:7029392"
        ],
        "placetype": [
          "aat:300008791"
        ],
        "name:en": "Dog Island",
        "id": 7514455
      }
    },
    {
      "geometry": {
        "type": "Point",
        "coordinates": [
          172.316667,
          -42.8
        ]
      },
      "type": "Feature",
      "properties": {
        "hierarchy": [
          "tgn:7514456",
          "tgn:1009227",
          "tgn:7001866",
          "tgn:1000226",
          "tgn:1000006",
          "tgn:7029392"
        ],
        "placetype": [
          "aat:300008795"
        ],
        "name:en": "Dog Hill",
        "id": 7514456
      }
    },
    {
      "geometry": {
        "type": "Point",
        "coordinates": [
          174.083333,
          -41.8
        ]
      },
      "type": "Feature",
      "properties": {
        "hierarchy": [
          "tgn:7514457",
          "tgn:1009227",
          "tgn:1000226",
          "tgn:7016729",
          "tgn:1000006",
          "tgn:7029392"
        ],
        "placetype": [
          "aat:300008795"
        ],
        "name:en": "Dog Hill",
        "id": 7514457
      }
    },
    {
      "geometry": {
        "type": "Point",
        "coordinates": [
          175.1,
          -41.366667
        ]
      },
      "type": "Feature",
      "properties": {
        "hierarchy": [
          "tgn:7514458",
          "tgn:1008380",
          "tgn:1000226",
          "tgn:7000512",
          "tgn:1000006",
          "tgn:7029392"
        ],
        "placetype": [
          "aat:300008777"
        ],
        "name:en": "Dog Hill",
        "id": 7514458
      }
    },
    {
      "geometry": {
        "type": "Point",
        "coordinates": [
          173.033333,
          -42.65
        ]
      },
      "type": "Feature",
      "properties": {
        "hierarchy": [
          "tgn:7514459",
          "tgn:1009227",
          "tgn:7001866",
          "tgn:1000226",
          "tgn:1000006",
          "tgn:7029392"
        ],
        "placetype": [
          "aat:300008699"
        ],
        "name:en": "Dog Brook",
        "id": 7514459
      }
    }
  ]
}
