{
  "geometry": {
    "type": "Point",
    "coordinates": [
      33.726666,
      30.438722
    ]
  },
  "type": "Feature",
  "properties": {
    "hierarchy": [
      "tgn:7542571",
      "tgn:7001242",
      "tgn:7016833",
      "tgn:7001335",
      "tgn:7029392"
    ],
    "placetype": [
      "aat:300379998"
    ],
    "name:en": "Ţala'h as Samrā', Wādī aţ",
    "id": 7542571
  }
}
