{
  "geometry": {
    "type": "Point",
    "coordinates": [
      74.17396,
      23.592764
    ]
  },
  "type": "Feature",
  "properties": {
    "hierarchy": [
      "tgn:7558297",
      "tgn:1000004",
      "tgn:7000198",
      "tgn:7016788",
      "tgn:7029392"
    ],
    "placetype": [
      "aat:300008347"
    ],
    "name:en": "Partāpur",
    "id": 7558297
  }
}
