{
  "type": "FeatureCollection",
  "features": [
    {
      "geometry": {
        "type": "Point",
        "coordinates": [
          -76.65,
          37.8
        ]
      },
      "type": "Feature",
      "properties": {
        "hierarchy": [
          "tgn:2575690",
          "tgn:1000001",
          "tgn:7012149",
          "tgn:7014334",
          "tgn:7007919",
          "tgn:7029392"
        ],
        "placetype": [
          "aat:300008706"
        ],
        "id": 2575690,
        "name:xx": "Perch Creek"
      }
    },
    {
      "geometry": {
        "type": "Point",
        "coordinates": [
          -71.85,
          41.3167
        ]
      },
      "type": "Feature",
      "properties": {
        "hierarchy": [
          "tgn:2575691",
          "tgn:1000001",
          "tgn:1002714",
          "tgn:7012149",
          "tgn:7007159",
          "tgn:7029392"
        ],
        "placetype": [
          "aat:300008791"
        ],
        "id": 2575691,
        "name:xx": "Perch Island"
      }
    },
    {
      "geometry": {
        "type": "Point",
        "coordinates": [
          -69.5833,
          43.85
        ]
      },
      "type": "Feature",
      "properties": {
        "hierarchy": [
          "tgn:2575692",
          "tgn:1000001",
          "tgn:2000925",
          "tgn:7012149",
          "tgn:7007515",
          "tgn:7029392"
        ],
        "placetype": [
          "aat:300008791"
        ],
        "id": 2575692,
        "name:xx": "Perch Island"
      }
    },
    {
      "geometry": {
        "type": "Point",
        "coordinates": [
          -68.1333,
          45.0833
        ]
      },
      "type": "Feature",
      "properties": {
        "hierarchy": [
          "tgn:2575693",
          "tgn:1000001",
          "tgn:2000922",
          "tgn:7012149",
          "tgn:7007515",
          "tgn:7029392"
        ],
        "placetype": [
          "aat:300008791"
        ],
        "id": 2575693,
        "name:xx": "Perch Island"
      }
    },
    {
      "geometry": {
        "type": "Point",
        "coordinates": [
          -71.55,
          43.7333
        ]
      },
      "type": "Feature",
      "properties": {
        "hierarchy": [
          "tgn:2575694",
          "tgn:1000001",
          "tgn:2001424",
          "tgn:7012149",
          "tgn:7007564",
          "tgn:7029392"
        ],
        "placetype": [
          "aat:300008791"
        ],
        "id": 2575694,
        "name:xx": "Perch Island"
      }
    },
    {
      "geometry": {
        "type": "Point",
        "coordinates": [
          -71.3167,
          43.65
        ]
      },
      "type": "Feature",
      "properties": {
        "hierarchy": [
          "tgn:2575695",
          "tgn:2001423",
          "tgn:1000001",
          "tgn:7012149",
          "tgn:7007564",
          "tgn:7029392"
        ],
        "placetype": [
          "aat:300008791"
        ],
        "id": 2575695,
        "name:xx": "Perch Island"
      }
    },
    {
      "geometry": {
        "type": "Point",
        "coordinates": [
          -73.6,
          43.55
        ]
      },
      "type": "Feature",
      "properties": {
        "hierarchy": [
          "tgn:2575696",
          "tgn:1000001",
          "tgn:7012149",
          "tgn:1002986",
          "tgn:7007568",
          "tgn:7029392"
        ],
        "placetype": [
          "aat:300008791"
        ],
        "id": 2575696,
        "name:xx": "Perch Island"
      }
    },
    {
      "geometry": {
        "type": "Point",
        "coordinates": [
          -81.7,
          27.85
        ]
      },
      "type": "Feature",
      "properties": {
        "hierarchy": [
          "tgn:2575697",
          "tgn:1000001",
          "tgn:7012149",
          "tgn:1002793",
          "tgn:7007240",
          "tgn:7029392"
        ],
        "placetype": [
          "aat:300008680"
        ],
        "id": 2575697,
        "name:xx": "Perch Lake"
      }
    },
    {
      "geometry": {
        "type": "Point",
        "coordinates": [
          -81.2833,
          28.6
        ]
      },
      "type": "Feature",
      "properties": {
        "hierarchy": [
          "tgn:2575698",
          "tgn:1000001",
          "tgn:7012149",
          "tgn:1002749",
          "tgn:7007240",
          "tgn:7029392"
        ],
        "placetype": [
          "aat:300008680"
        ],
        "id": 2575698,
        "name:xx": "Perch Lake"
      }
    },
    {
      "geometry": {
        "type": "Point",
        "coordinates": [
          -81.5167,
          28.9833
        ]
      },
      "type": "Feature",
      "properties": {
        "hierarchy": [
          "tgn:2575699",
          "tgn:1000001",
          "tgn:7012149",
          "tgn:1002567",
          "tgn:7007240",
          "tgn:7029392"
        ],
        "placetype": [
          "aat:300008680"
        ],
        "id": 2575699,
        "name:xx": "Perch Lake"
      }
    }
  ]
}
