{
  "geometry": {
    "type": "Point",
    "coordinates": [
      89.9667,
      24.2333
    ]
  },
  "type": "Feature",
  "properties": {
    "hierarchy": [
      "tgn:1065774",
      "tgn:7000189",
      "tgn:1000004",
      "tgn:1000105",
      "tgn:7029392"
    ],
    "placetype": [
      "aat:300008347"
    ],
    "id": 1065774,
    "name:xx": "Karatia"
  }
}
