{
  "type": "FeatureCollection",
  "features": [
    {
      "geometry": {
        "type": "Point",
        "coordinates": [
          -80.6167,
          37.7833
        ]
      },
      "type": "Feature",
      "properties": {
        "hierarchy": [
          "tgn:2331800",
          "tgn:1000001",
          "tgn:7012149",
          "tgn:2002264",
          "tgn:7013961",
          "tgn:7029392"
        ],
        "placetype": [
          "aat:300008697"
        ],
        "id": 2331800,
        "name:xx": "Fleshman Spring"
      }
    },
    {
      "geometry": {
        "type": "Point",
        "coordinates": [
          -94.2667,
          40.6
        ]
      },
      "type": "Feature",
      "properties": {
        "hierarchy": [
          "tgn:2331801",
          "tgn:1000001",
          "tgn:7012149",
          "tgn:7029392"
        ],
        "placetype": [
          "aat:300008706"
        ],
        "id": 2331801,
        "name:xx": "Fletchall Creek"
      }
    },
    {
      "geometry": {
        "type": "Point",
        "coordinates": [
          -120.75,
          41.4333
        ]
      },
      "type": "Feature",
      "properties": {
        "hierarchy": [
          "tgn:2331803",
          "tgn:1000001",
          "tgn:7012149",
          "tgn:7007157",
          "tgn:2000186",
          "tgn:7029392"
        ],
        "placetype": [
          "aat:300008347"
        ],
        "id": 2331803,
        "name:xx": "Fletcher"
      }
    },
    {
      "geometry": {
        "type": "Point",
        "coordinates": [
          -82.9833,
          29.7333
        ]
      },
      "type": "Feature",
      "properties": {
        "hierarchy": [
          "tgn:2331804",
          "tgn:1000001",
          "tgn:2000263",
          "tgn:7012149",
          "tgn:7007240",
          "tgn:7029392"
        ],
        "placetype": [
          "aat:300008347"
        ],
        "id": 2331804,
        "name:xx": "Fletcher"
      }
    },
    {
      "geometry": {
        "type": "Point",
        "coordinates": [
          -116.4,
          46.2833
        ]
      },
      "type": "Feature",
      "properties": {
        "hierarchy": [
          "tgn:2331805",
          "tgn:1000001",
          "tgn:7012149",
          "tgn:2000482",
          "tgn:7007250",
          "tgn:7029392"
        ],
        "placetype": [
          "aat:300008347"
        ],
        "id": 2331805,
        "name:xx": "Fletcher"
      }
    },
    {
      "geometry": {
        "type": "Point",
        "coordinates": [
          -86.3167,
          40.9
        ]
      },
      "type": "Feature",
      "properties": {
        "hierarchy": [
          "tgn:2331806",
          "tgn:1000001",
          "tgn:7012149",
          "tgn:1002396",
          "tgn:7007252",
          "tgn:7029392"
        ],
        "placetype": [
          "aat:300008347"
        ],
        "id": 2331806,
        "name:xx": "Fletcher"
      }
    },
    {
      "geometry": {
        "type": "Point",
        "coordinates": [
          -84.95,
          44.5333
        ]
      },
      "type": "Feature",
      "properties": {
        "hierarchy": [
          "tgn:2331807",
          "tgn:1000001",
          "tgn:7012149",
          "tgn:2000968",
          "tgn:7007520",
          "tgn:7029392"
        ],
        "placetype": [
          "aat:300008347"
        ],
        "id": 2331807,
        "name:xx": "Fletcher"
      }
    },
    {
      "geometry": {
        "type": "Point",
        "coordinates": [
          -118.8833,
          38.35
        ]
      },
      "type": "Feature",
      "properties": {
        "hierarchy": [
          "tgn:2331808",
          "tgn:1000001",
          "tgn:2001417",
          "tgn:7012149",
          "tgn:7007526",
          "tgn:7029392"
        ],
        "placetype": [
          "aat:300008347"
        ],
        "id": 2331808,
        "name:xx": "Fletcher"
      }
    },
    {
      "geometry": {
        "type": "Point",
        "coordinates": [
          -81.1167,
          36.15
        ]
      },
      "type": "Feature",
      "properties": {
        "hierarchy": [
          "tgn:2331809",
          "tgn:1000001",
          "tgn:7012149",
          "tgn:2001553",
          "tgn:7007709",
          "tgn:7029392"
        ],
        "placetype": [
          "aat:300008347"
        ],
        "id": 2331809,
        "name:xx": "Fletcher"
      }
    }
  ]
}
