{
  "geometry": {
    "type": "Point",
    "coordinates": [
      -70.6333,
      43.1667
    ]
  },
  "type": "Feature",
  "properties": {
    "hierarchy": [
      "tgn:2220529",
      "tgn:1000001",
      "tgn:7012149",
      "tgn:2000933",
      "tgn:7007515",
      "tgn:7029392"
    ],
    "placetype": [
      "aat:300008707"
    ],
    "id": 2220529,
    "name:xx": "Cape Neddick River"
  }
}
