{
  "geometry": {
    "type": "Point",
    "coordinates": [
      -69.9333,
      43.9167
    ]
  },
  "type": "Feature",
  "properties": {
    "hierarchy": [
      "tgn:2262485",
      "tgn:1000001",
      "tgn:7012149",
      "tgn:2000929",
      "tgn:7007515",
      "tgn:7029392"
    ],
    "placetype": [
      "aat:300008791"
    ],
    "id": 2262485,
    "name:xx": "Cow Island"
  }
}
