{
  "geometry": {
    "type": "Point",
    "coordinates": [
      -77.2167,
      39.8167
    ]
  },
  "type": "Feature",
  "properties": {
    "hierarchy": [
      "tgn:7016023",
      "tgn:1002137",
      "tgn:1000001",
      "tgn:7012149",
      "tgn:7007710",
      "tgn:7029392"
    ],
    "placetype": [
      "aat:300000835",
      "aat:300386978"
    ],
    "id": 7016023,
    "name:xx": "Gettysburg National Military Park"
  }
}
