{
  "geometry": {
    "type": "Point",
    "coordinates": [
      -81.6667,
      38.2167
    ]
  },
  "type": "Feature",
  "properties": {
    "hierarchy": [
      "tgn:2487477",
      "tgn:1000001",
      "tgn:2002255",
      "tgn:7012149",
      "tgn:7013961",
      "tgn:7029392"
    ],
    "placetype": [
      "aat:300008706"
    ],
    "id": 2487477,
    "name:xx": "Left Fork Bull Creek"
  }
}
