{
  "geometry": {
    "type": "Point",
    "coordinates": [
      -3.85,
      42.283333
    ]
  },
  "type": "Feature",
  "properties": {
    "hierarchy": [
      "tgn:7346580",
      "tgn:7002810",
      "tgn:7001158",
      "tgn:1000003",
      "tgn:1000095",
      "tgn:7029392"
    ],
    "placetype": [
      "aat:300008699"
    ],
    "id": 7346580,
    "name:xx": "Ausines, Río de los"
  }
}
