{
  "type": "FeatureCollection",
  "features": [
    {
      "geometry": {
        "type": "Point",
        "coordinates": [
          -81,
          32.3333
        ]
      },
      "type": "Feature",
      "properties": {
        "hierarchy": [
          "tgn:2484590",
          "tgn:1000001",
          "tgn:7012149",
          "tgn:2001751",
          "tgn:7007712",
          "tgn:7029392"
        ],
        "placetype": [
          "aat:300008798"
        ],
        "id": 2484590,
        "name:xx": "Laurel Knoll"
      }
    },
    {
      "geometry": {
        "type": "Point",
        "coordinates": [
          -118.85,
          37.45
        ]
      },
      "type": "Feature",
      "properties": {
        "hierarchy": [
          "tgn:2484591",
          "tgn:1000001",
          "tgn:7012149",
          "tgn:1002392",
          "tgn:7007157",
          "tgn:7029392"
        ],
        "placetype": [
          "aat:300008680"
        ],
        "id": 2484591,
        "name:xx": "Laurel Lake"
      }
    },
    {
      "geometry": {
        "type": "Point",
        "coordinates": [
          -119.7833,
          37.9833
        ]
      },
      "type": "Feature",
      "properties": {
        "hierarchy": [
          "tgn:2484592",
          "tgn:1000001",
          "tgn:7012149",
          "tgn:7007157",
          "tgn:1002957",
          "tgn:7029392"
        ],
        "placetype": [
          "aat:300008680"
        ],
        "id": 2484592,
        "name:xx": "Laurel Lake"
      }
    },
    {
      "geometry": {
        "type": "Point",
        "coordinates": [
          -73.3667,
          41.2167
        ]
      },
      "type": "Feature",
      "properties": {
        "hierarchy": [
          "tgn:2484593",
          "tgn:1002366",
          "tgn:1000001",
          "tgn:7012149",
          "tgn:7007159",
          "tgn:7029392"
        ],
        "placetype": [
          "aat:300008680"
        ],
        "id": 2484593,
        "name:xx": "Laurel Lake"
      }
    },
    {
      "geometry": {
        "type": "Point",
        "coordinates": [
          -72.5667,
          41.7667
        ]
      },
      "type": "Feature",
      "properties": {
        "hierarchy": [
          "tgn:2484594",
          "tgn:1000001",
          "tgn:1002461",
          "tgn:7012149",
          "tgn:7007159",
          "tgn:7029392"
        ],
        "placetype": [
          "aat:300008680"
        ],
        "id": 2484594,
        "name:xx": "Laurel Lake"
      }
    },
    {
      "geometry": {
        "type": "Point",
        "coordinates": [
          -84.5,
          33.8333
        ]
      },
      "type": "Feature",
      "properties": {
        "hierarchy": [
          "tgn:2484595",
          "tgn:1000001",
          "tgn:2000324",
          "tgn:7012149",
          "tgn:7007248",
          "tgn:7029392"
        ],
        "placetype": [
          "aat:300006191"
        ],
        "id": 2484595,
        "name:xx": "Laurel Lake"
      }
    },
    {
      "geometry": {
        "type": "Point",
        "coordinates": [
          -76.85,
          39.0833
        ]
      },
      "type": "Feature",
      "properties": {
        "hierarchy": [
          "tgn:2484596",
          "tgn:1000001",
          "tgn:2124001",
          "tgn:7012149",
          "tgn:7007516",
          "tgn:7029392"
        ],
        "placetype": [
          "aat:300008680"
        ],
        "id": 2484596,
        "name:xx": "Laurel Lake"
      }
    },
    {
      "geometry": {
        "type": "Point",
        "coordinates": [
          -73.2667,
          42.3
        ]
      },
      "type": "Feature",
      "properties": {
        "hierarchy": [
          "tgn:2484597",
          "tgn:7013388",
          "tgn:1000001",
          "tgn:7012149",
          "tgn:7007517",
          "tgn:7029392"
        ],
        "placetype": [
          "aat:300006191"
        ],
        "id": 2484597,
        "name:xx": "Laurel Lake"
      }
    },
    {
      "geometry": {
        "type": "Point",
        "coordinates": [
          -72.35,
          42.6167
        ]
      },
      "type": "Feature",
      "properties": {
        "hierarchy": [
          "tgn:2484598",
          "tgn:1000001",
          "tgn:7013942",
          "tgn:7012149",
          "tgn:7007517",
          "tgn:7029392"
        ],
        "placetype": [
          "aat:300006191"
        ],
        "id": 2484598,
        "name:xx": "Laurel Lake"
      }
    },
    {
      "geometry": {
        "type": "Point",
        "coordinates": [
          -85.3167,
          46.4333
        ]
      },
      "type": "Feature",
      "properties": {
        "hierarchy": [
          "tgn:2484599",
          "tgn:1000001",
          "tgn:7012149",
          "tgn:2000972",
          "tgn:7007520",
          "tgn:7029392"
        ],
        "placetype": [
          "aat:300008680"
        ],
        "id": 2484599,
        "name:xx": "Laurel Lake"
      }
    }
  ]
}
