{
  "geometry": {
    "type": "Point",
    "coordinates": [
      -112.4167,
      46.0667
    ]
  },
  "type": "Feature",
  "properties": {
    "hierarchy": [
      "tgn:2141555",
      "tgn:1000001",
      "tgn:7012149",
      "tgn:2001281",
      "tgn:7007524",
      "tgn:7029392"
    ],
    "placetype": [
      "aat:300006191"
    ],
    "id": 2141555,
    "name:xx": "B and B Fishpond"
  }
}
