{
  "geometry": {
    "type": "Point",
    "coordinates": [
      -85.75,
      37.05
    ]
  },
  "type": "Feature",
  "properties": {
    "hierarchy": [
      "tgn:2698285",
      "tgn:2000768",
      "tgn:1000001",
      "tgn:7012149",
      "tgn:7007255",
      "tgn:7029392"
    ],
    "placetype": [
      "aat:300008699"
    ],
    "id": 2698285,
    "name:xx": "Strader Branch"
  }
}
