{
  "geometry": {
    "type": "Point",
    "coordinates": [
      79.07631,
      26.34457
    ]
  },
  "type": "Feature",
  "properties": {
    "hierarchy": [
      "tgn:7562350",
      "tgn:1000004",
      "tgn:7000198",
      "tgn:1001894",
      "tgn:7029392"
    ],
    "placetype": [
      "aat:300008347"
    ],
    "name:en": "Bagiāpura",
    "id": 7562350
  }
}
