{
  "geometry": {
    "type": "Point",
    "coordinates": [
      -121.8667,
      46.5833
    ]
  },
  "type": "Feature",
  "properties": {
    "hierarchy": [
      "tgn:2763634",
      "tgn:1000001",
      "tgn:7012149",
      "tgn:1002594",
      "tgn:7007920",
      "tgn:7029392"
    ],
    "placetype": [
      "aat:300266640"
    ],
    "id": 2763634,
    "name:xx": "Whalehead Ridge"
  }
}
