{
  "geometry": {
    "type": "Point",
    "coordinates": [
      -85.7833,
      37.35
    ]
  },
  "type": "Feature",
  "properties": {
    "hierarchy": [
      "tgn:2397531",
      "tgn:1000001",
      "tgn:7012149",
      "tgn:2000798",
      "tgn:7007255",
      "tgn:7029392"
    ],
    "placetype": [
      "aat:300008699"
    ],
    "id": 2397531,
    "name:xx": "Honey Run"
  }
}
