{
  "geometry": {
    "type": "Point",
    "coordinates": [
      138.2333,
      35.75
    ]
  },
  "type": "Feature",
  "properties": {
    "hierarchy": [
      "tgn:1105260",
      "tgn:7000895",
      "tgn:1000004",
      "tgn:1000120",
      "tgn:7029392"
    ],
    "placetype": [
      "aat:300008795"
    ],
    "id": 1105260,
    "name:xx": "Komaga-take"
  }
}
