{
  "type": "FeatureCollection",
  "features": [
    {
      "geometry": {
        "type": "Point",
        "coordinates": [
          10.3,
          50.066667
        ]
      },
      "type": "Feature",
      "properties": {
        "hierarchy": [
          "tgn:7152740",
          "tgn:7003669",
          "tgn:1000003",
          "tgn:7000084",
          "tgn:7029392"
        ],
        "placetype": [
          "aat:300008347"
        ],
        "id": 7152740,
        "name:xx": "Kaltenhof"
      }
    },
    {
      "geometry": {
        "type": "Point",
        "coordinates": [
          10.033333,
          49.65
        ]
      },
      "type": "Feature",
      "properties": {
        "hierarchy": [
          "tgn:7152741",
          "tgn:7003669",
          "tgn:1000003",
          "tgn:7000084",
          "tgn:7029392"
        ],
        "placetype": [
          "aat:300008347"
        ],
        "id": 7152741,
        "name:xx": "Kaltenhof"
      }
    },
    {
      "geometry": {
        "type": "Point",
        "coordinates": [
          9.65,
          53.766667
        ]
      },
      "type": "Feature",
      "properties": {
        "hierarchy": [
          "tgn:7152742",
          "tgn:1000003",
          "tgn:7003688",
          "tgn:7000084",
          "tgn:7029392"
        ],
        "placetype": [
          "aat:300000206"
        ],
        "id": 7152742,
        "name:xx": "Kaltenhof"
      }
    },
    {
      "geometry": {
        "type": "Point",
        "coordinates": [
          7.333333,
          51.35
        ]
      },
      "type": "Feature",
      "properties": {
        "hierarchy": [
          "tgn:7152743",
          "tgn:1000003",
          "tgn:7003677",
          "tgn:7000084",
          "tgn:7029392"
        ],
        "placetype": [
          "aat:300000206"
        ],
        "id": 7152743,
        "name:xx": "Kaltenhof"
      }
    },
    {
      "geometry": {
        "type": "Point",
        "coordinates": [
          11.316667,
          49.616667
        ]
      },
      "type": "Feature",
      "properties": {
        "hierarchy": [
          "tgn:7152744",
          "tgn:7003669",
          "tgn:1000003",
          "tgn:7000084",
          "tgn:7029392"
        ],
        "placetype": [
          "aat:300000206"
        ],
        "id": 7152744,
        "name:xx": "Kaltenhof"
      }
    },
    {
      "geometry": {
        "type": "Point",
        "coordinates": [
          8.55,
          48.4
        ]
      },
      "type": "Feature",
      "properties": {
        "hierarchy": [
          "tgn:7152745",
          "tgn:7003692",
          "tgn:1000003",
          "tgn:7000084",
          "tgn:7029392"
        ],
        "placetype": [
          "aat:300000206"
        ],
        "id": 7152745,
        "name:xx": "Kaltenhof"
      }
    },
    {
      "geometry": {
        "type": "Point",
        "coordinates": [
          7.133333,
          51.083333
        ]
      },
      "type": "Feature",
      "properties": {
        "hierarchy": [
          "tgn:7152746",
          "tgn:1000003",
          "tgn:7003677",
          "tgn:7000084",
          "tgn:7029392"
        ],
        "placetype": [
          "aat:300008347"
        ],
        "id": 7152746,
        "name:xx": "Kaltenherberg"
      }
    },
    {
      "geometry": {
        "type": "Point",
        "coordinates": [
          10.866667,
          50.083333
        ]
      },
      "type": "Feature",
      "properties": {
        "hierarchy": [
          "tgn:7152747",
          "tgn:7003669",
          "tgn:1000003",
          "tgn:7000084",
          "tgn:7029392"
        ],
        "placetype": [
          "aat:300008347"
        ],
        "id": 7152747,
        "name:xx": "Kaltenherberg"
      }
    },
    {
      "geometry": {
        "type": "Point",
        "coordinates": [
          11.35,
          48.65
        ]
      },
      "type": "Feature",
      "properties": {
        "hierarchy": [
          "tgn:7152748",
          "tgn:7003669",
          "tgn:1000003",
          "tgn:7000084",
          "tgn:7029392"
        ],
        "placetype": [
          "aat:300008347"
        ],
        "id": 7152748,
        "name:xx": "Kaltenherberg"
      }
    },
    {
      "geometry": {
        "type": "Point",
        "coordinates": [
          12.266667,
          49.1
        ]
      },
      "type": "Feature",
      "properties": {
        "hierarchy": [
          "tgn:7152749",
          "tgn:7003669",
          "tgn:1000003",
          "tgn:7000084",
          "tgn:7029392"
        ],
        "placetype": [
          "aat:300000206"
        ],
        "id": 7152749,
        "name:xx": "Kaltenherberg"
      }
    }
  ]
}
