{
  "geometry": {
    "type": "Point",
    "coordinates": [
      112.55,
      -3.3833
    ]
  },
  "type": "Feature",
  "properties": {
    "hierarchy": [
      "tgn:1140242",
      "tgn:1000004",
      "tgn:1001338",
      "tgn:1000116",
      "tgn:7029392"
    ],
    "placetype": [
      "aat:300008347"
    ],
    "id": 1140242,
    "name:xx": "Kumai"
  }
}
