{
  "geometry": {
    "type": "Point",
    "coordinates": [
      -99.3167,
      29.2833
    ]
  },
  "type": "Feature",
  "properties": {
    "hierarchy": [
      "tgn:2309282",
      "tgn:1000001",
      "tgn:7012149",
      "tgn:2002039",
      "tgn:7007826",
      "tgn:7029392"
    ],
    "placetype": [
      "aat:300008706"
    ],
    "id": 2309282,
    "name:xx": "East Squirrel Creek"
  }
}
