{
  "geometry": {
    "type": "Point",
    "coordinates": [
      -91.85,
      39.5333
    ]
  },
  "type": "Feature",
  "properties": {
    "hierarchy": [
      "tgn:2060609",
      "tgn:1000001",
      "tgn:7012149",
      "tgn:1002680",
      "tgn:7007523",
      "tgn:7029392"
    ],
    "placetype": [
      "aat:300008347"
    ],
    "id": 2060609,
    "name:xx": "Stoutsville"
  }
}
