{
  "geometry": {
    "type": "Point",
    "coordinates": [
      -80.2333,
      34.8667
    ]
  },
  "type": "Feature",
  "properties": {
    "hierarchy": [
      "tgn:2159022",
      "tgn:2001466",
      "tgn:1000001",
      "tgn:7012149",
      "tgn:7007709",
      "tgn:7029392"
    ],
    "placetype": [
      "aat:300008798"
    ],
    "id": 2159022,
    "name:xx": "Becky Hill"
  }
}
