{
  "geometry": {
    "type": "Point",
    "coordinates": [
      -115.9833,
      47.7833
    ]
  },
  "type": "Feature",
  "properties": {
    "hierarchy": [
      "tgn:2555540",
      "tgn:1000001",
      "tgn:7012149",
      "tgn:2000491",
      "tgn:7007250",
      "tgn:7029392"
    ],
    "placetype": [
      "aat:300008761"
    ],
    "id": 2555540,
    "name:xx": "Offset Gulch"
  }
}
