{
  "geometry": {
    "type": "Point",
    "coordinates": [
      -84.0333,
      32.9833
    ]
  },
  "type": "Feature",
  "properties": {
    "hierarchy": [
      "tgn:2784868",
      "tgn:1000001",
      "tgn:7012149",
      "tgn:2000393",
      "tgn:7007248",
      "tgn:7029392"
    ],
    "placetype": [
      "aat:300008706"
    ],
    "id": 2784868,
    "name:xx": "Yellow Creek"
  }
}
