{
  "geometry": {
    "type": "Point",
    "coordinates": [
      -103.8375,
      18.869444
    ]
  },
  "type": "Feature",
  "properties": {
    "hierarchy": [
      "tgn:7404293",
      "tgn:7016644",
      "tgn:1000001",
      "tgn:7005560",
      "tgn:7029392"
    ],
    "placetype": [
      "aat:300008347"
    ],
    "id": 7404293,
    "name:xx": "Cofradía de Morelos"
  }
}
