{
  "geometry": {
    "type": "Point",
    "coordinates": [
      77.979016,
      30.3347
    ]
  },
  "type": "Feature",
  "properties": {
    "hierarchy": [
      "tgn:7591837",
      "tgn:1000004",
      "tgn:7000198",
      "tgn:7031786",
      "tgn:7029392"
    ],
    "placetype": [
      "aat:300008347"
    ],
    "name:en": "Rāngharwāla",
    "id": 7591837
  }
}
