{
  "geometry": {
    "type": "Point",
    "coordinates": [
      -71.45,
      42.9167
    ]
  },
  "type": "Feature",
  "properties": {
    "hierarchy": [
      "tgn:2582891",
      "tgn:1000001",
      "tgn:1002480",
      "tgn:7012149",
      "tgn:7007564",
      "tgn:7029392"
    ],
    "placetype": [
      "aat:300006191"
    ],
    "id": 2582891,
    "name:xx": "Pine Island Pond"
  }
}
