{
  "geometry": {
    "type": "Point",
    "coordinates": [
      -115.2667,
      38.3667
    ]
  },
  "type": "Feature",
  "properties": {
    "hierarchy": [
      "tgn:2334370",
      "tgn:1000001",
      "tgn:2001418",
      "tgn:7012149",
      "tgn:7007526",
      "tgn:7029392"
    ],
    "placetype": [
      "aat:300006191"
    ],
    "id": 2334370,
    "name:xx": "Forest Home Reservoir Number 5"
  }
}
