{
  "type": "FeatureCollection",
  "features": [
    {
      "geometry": {
        "type": "Point",
        "coordinates": [
          -107.7833,
          48.2
        ]
      },
      "type": "Feature",
      "properties": {
        "hierarchy": [
          "tgn:2163140",
          "tgn:1000001",
          "tgn:7012149",
          "tgn:2001295",
          "tgn:7007524",
          "tgn:7029392"
        ],
        "placetype": [
          "aat:300008680"
        ],
        "id": 2163140,
        "name:xx": "Bennett Lake"
      }
    },
    {
      "geometry": {
        "type": "Point",
        "coordinates": [
          -102.5667,
          42.2
        ]
      },
      "type": "Feature",
      "properties": {
        "hierarchy": [
          "tgn:2163141",
          "tgn:1000001",
          "tgn:7012149",
          "tgn:2001396",
          "tgn:7007525",
          "tgn:7029392"
        ],
        "placetype": [
          "aat:300008680"
        ],
        "id": 2163141,
        "name:xx": "Bennett Lake"
      }
    },
    {
      "geometry": {
        "type": "Point",
        "coordinates": [
          -74.1833,
          43.3
        ]
      },
      "type": "Feature",
      "properties": {
        "hierarchy": [
          "tgn:2163142",
          "tgn:1000001",
          "tgn:7012149",
          "tgn:1002440",
          "tgn:7007568",
          "tgn:7029392"
        ],
        "placetype": [
          "aat:300008680"
        ],
        "id": 2163142,
        "name:xx": "Bennett Lake"
      }
    },
    {
      "geometry": {
        "type": "Point",
        "coordinates": [
          -118.7333,
          43.55
        ]
      },
      "type": "Feature",
      "properties": {
        "hierarchy": [
          "tgn:2163143",
          "tgn:1000001",
          "tgn:7012149",
          "tgn:2001709",
          "tgn:7007708",
          "tgn:7029392"
        ],
        "placetype": [
          "aat:300008680"
        ],
        "id": 2163143,
        "name:xx": "Bennett Lake"
      }
    },
    {
      "geometry": {
        "type": "Point",
        "coordinates": [
          -85.5167,
          35.0667
        ]
      },
      "type": "Feature",
      "properties": {
        "hierarchy": [
          "tgn:2163144",
          "tgn:1000001",
          "tgn:7012149",
          "tgn:2001894",
          "tgn:7007825",
          "tgn:7029392"
        ],
        "placetype": [
          "aat:300008680"
        ],
        "id": 2163144,
        "name:xx": "Bennett Lake"
      }
    },
    {
      "geometry": {
        "type": "Point",
        "coordinates": [
          -87.3833,
          35.2167
        ]
      },
      "type": "Feature",
      "properties": {
        "hierarchy": [
          "tgn:2163145",
          "tgn:1000001",
          "tgn:7012149",
          "tgn:2001886",
          "tgn:7007825",
          "tgn:7029392"
        ],
        "placetype": [
          "aat:300006191"
        ],
        "id": 2163145,
        "name:xx": "Bennett Lake"
      }
    },
    {
      "geometry": {
        "type": "Point",
        "coordinates": [
          -94.9667,
          32.9333
        ]
      },
      "type": "Feature",
      "properties": {
        "hierarchy": [
          "tgn:2163146",
          "tgn:1000001",
          "tgn:7012149",
          "tgn:1002230",
          "tgn:7007826",
          "tgn:7029392"
        ],
        "placetype": [
          "aat:300006191"
        ],
        "id": 2163146,
        "name:xx": "Bennett Lake"
      }
    },
    {
      "geometry": {
        "type": "Point",
        "coordinates": [
          -119.6,
          47.7167
        ]
      },
      "type": "Feature",
      "properties": {
        "hierarchy": [
          "tgn:2163147",
          "tgn:1000001",
          "tgn:2002242",
          "tgn:7012149",
          "tgn:7007920",
          "tgn:7029392"
        ],
        "placetype": [
          "aat:300008680"
        ],
        "id": 2163147,
        "name:xx": "Bennett Lake"
      }
    },
    {
      "geometry": {
        "type": "Point",
        "coordinates": [
          -89.4333,
          45.4167
        ]
      },
      "type": "Feature",
      "properties": {
        "hierarchy": [
          "tgn:2163148",
          "tgn:1000001",
          "tgn:7012149",
          "tgn:2002334",
          "tgn:7007922",
          "tgn:7029392"
        ],
        "placetype": [
          "aat:300008680"
        ],
        "id": 2163148,
        "name:xx": "Bennett Lake"
      }
    },
    {
      "geometry": {
        "type": "Point",
        "coordinates": [
          -91.5333,
          45.6833
        ]
      },
      "type": "Feature",
      "properties": {
        "hierarchy": [
          "tgn:2163149",
          "tgn:1000001",
          "tgn:7012149",
          "tgn:2002353",
          "tgn:7007922",
          "tgn:7029392"
        ],
        "placetype": [
          "aat:300008680"
        ],
        "id": 2163149,
        "name:xx": "Bennett Lake"
      }
    }
  ]
}
