{
  "geometry": {
    "type": "Point",
    "coordinates": [
      80.361456,
      22.397429
    ]
  },
  "type": "Feature",
  "properties": {
    "hierarchy": [
      "tgn:7575727",
      "tgn:1000004",
      "tgn:7000198",
      "tgn:1001894",
      "tgn:7029392"
    ],
    "placetype": [
      "aat:300008699"
    ],
    "name:en": "Kanhār Nadī",
    "id": 7575727
  }
}
