{
  "geometry": {
    "type": "Point",
    "coordinates": [
      -94.05,
      39.4833
    ]
  },
  "type": "Feature",
  "properties": {
    "hierarchy": [
      "tgn:2276862",
      "tgn:1000001",
      "tgn:7012149",
      "tgn:2001235",
      "tgn:7007523",
      "tgn:7029392"
    ],
    "placetype": [
      "aat:300008699"
    ],
    "id": 2276862,
    "name:xx": "Davis Branch"
  }
}
