{
  "geometry": {
    "type": "Point",
    "coordinates": [
      75.066667,
      14.25
    ]
  },
  "type": "Feature",
  "properties": {
    "hierarchy": [
      "tgn:7575220",
      "tgn:1000004",
      "tgn:7000198",
      "tgn:1001882",
      "tgn:7029392"
    ],
    "placetype": [
      "aat:300008863"
    ],
    "name:en": "Kyāsanūr State Forest",
    "id": 7575220
  }
}
