{
  "geometry": {
    "type": "Point",
    "coordinates": [
      78.448911,
      24.89557
    ]
  },
  "type": "Feature",
  "properties": {
    "hierarchy": [
      "tgn:7585455",
      "tgn:1000004",
      "tgn:7000198",
      "tgn:7016722",
      "tgn:7029392"
    ],
    "placetype": [
      "aat:300008347"
    ],
    "name:en": "Majhgawān",
    "id": 7585455
  }
}
