{
  "geometry": {
    "type": "Point",
    "coordinates": [
      -83.0833,
      35.5667
    ]
  },
  "type": "Feature",
  "properties": {
    "hierarchy": [
      "tgn:2225991",
      "tgn:1000001",
      "tgn:7012149",
      "tgn:2001503",
      "tgn:7007709",
      "tgn:7029392"
    ],
    "placetype": [
      "aat:300266640"
    ],
    "id": 2225991,
    "name:xx": "Cataloochee Divide"
  }
}
