{
  "geometry": {
    "type": "Point",
    "coordinates": [
      -98.2667,
      36.5333
    ]
  },
  "type": "Feature",
  "properties": {
    "hierarchy": [
      "tgn:2083345",
      "tgn:2001624",
      "tgn:1000001",
      "tgn:7012149",
      "tgn:7007707",
      "tgn:7029392"
    ],
    "placetype": [
      "aat:300008347"
    ],
    "id": 2083345,
    "name:xx": "Helena"
  }
}
