{
  "geometry": {
    "type": "Point",
    "coordinates": [
      -94.8167,
      43.3333
    ]
  },
  "type": "Feature",
  "properties": {
    "hierarchy": [
      "tgn:2288737",
      "tgn:1000001",
      "tgn:2000592",
      "tgn:7012149",
      "tgn:7007253",
      "tgn:7029392"
    ],
    "placetype": [
      "aat:300006075"
    ],
    "id": 2288737,
    "name:xx": "Ditch Number 151"
  }
}
