{
  "geometry": {
    "type": "Point",
    "coordinates": [
      -70.9167,
      42.8667
    ]
  },
  "type": "Feature",
  "properties": {
    "hierarchy": [
      "tgn:2159930",
      "tgn:1000001",
      "tgn:1002359",
      "tgn:7012149",
      "tgn:7007517",
      "tgn:7029392"
    ],
    "placetype": [
      "aat:300008798"
    ],
    "id": 2159930,
    "name:xx": "Beech Hill"
  }
}
