{
  "geometry": {
    "type": "Point",
    "coordinates": [
      -91.5167,
      45.75
    ]
  },
  "type": "Feature",
  "properties": {
    "hierarchy": [
      "tgn:2460876",
      "tgn:1000001",
      "tgn:7012149",
      "tgn:2002353",
      "tgn:7007922",
      "tgn:7029392"
    ],
    "placetype": [
      "aat:300008680"
    ],
    "id": 2460876,
    "name:xx": "Little Sissabagama Lake"
  }
}
