{
  "type": "FeatureCollection",
  "features": [
    {
      "geometry": {
        "type": "Point",
        "coordinates": [
          5.85,
          50.683333
        ]
      },
      "type": "Feature",
      "properties": {
        "hierarchy": [
          "tgn:7252211",
          "tgn:7003460",
          "tgn:1000003",
          "tgn:1000063",
          "tgn:4012014",
          "tgn:7029392"
        ],
        "placetype": [
          "aat:300008347"
        ],
        "id": 7252211,
        "name:xx": "Messitert"
      }
    },
    {
      "geometry": {
        "type": "Point",
        "coordinates": [
          4.933333,
          51
        ]
      },
      "type": "Feature",
      "properties": {
        "hierarchy": [
          "tgn:7252212",
          "tgn:7018239",
          "tgn:1000003",
          "tgn:1000063",
          "tgn:7018236",
          "tgn:7029392"
        ],
        "placetype": [
          "aat:300008347"
        ],
        "id": 7252212,
        "name:xx": "Messelbroek"
      }
    },
    {
      "geometry": {
        "type": "Point",
        "coordinates": [
          5.833333,
          49.566667
        ]
      },
      "type": "Feature",
      "properties": {
        "hierarchy": [
          "tgn:7252214",
          "tgn:7003465",
          "tgn:1000003",
          "tgn:1000063",
          "tgn:4012014",
          "tgn:7029392"
        ],
        "placetype": [
          "aat:300008699"
        ],
        "id": 7252214,
        "name:xx": "Messancy"
      }
    },
    {
      "geometry": {
        "type": "Point",
        "coordinates": [
          5.816667,
          49.6
        ]
      },
      "type": "Feature",
      "properties": {
        "hierarchy": [
          "tgn:7252215",
          "tgn:7003465",
          "tgn:1000003",
          "tgn:1000063",
          "tgn:4012014",
          "tgn:7029392"
        ],
        "placetype": [
          "aat:300008347"
        ],
        "id": 7252215,
        "name:xx": "Messancy"
      }
    },
    {
      "geometry": {
        "type": "Point",
        "coordinates": [
          4.068833,
          50.996132
        ]
      },
      "type": "Feature",
      "properties": {
        "hierarchy": [
          "tgn:7252217",
          "tgn:7003457",
          "tgn:1000003",
          "tgn:1000063",
          "tgn:7018236",
          "tgn:7029392"
        ],
        "placetype": [
          "aat:300008347"
        ],
        "id": 7252217,
        "name:xx": "Mespelare"
      }
    },
    {
      "geometry": {
        "type": "Point",
        "coordinates": [
          4.083333,
          51.083333
        ]
      },
      "type": "Feature",
      "properties": {
        "hierarchy": [
          "tgn:7252219",
          "tgn:7003457",
          "tgn:1000003",
          "tgn:1000063",
          "tgn:7018236",
          "tgn:7029392"
        ],
        "placetype": [
          "aat:300008347"
        ],
        "id": 7252219,
        "name:xx": "Mespelaar"
      }
    }
  ]
}
