{
  "geometry": {
    "type": "Point",
    "coordinates": [
      -81.7333,
      33.4667
    ]
  },
  "type": "Feature",
  "properties": {
    "hierarchy": [
      "tgn:2207685",
      "tgn:2001726",
      "tgn:1000001",
      "tgn:7012149",
      "tgn:7007712",
      "tgn:7029392"
    ],
    "placetype": [
      "aat:300006191"
    ],
    "id": 2207685,
    "name:xx": "Burdens Deep Pond"
  }
}
