{
  "geometry": {
    "type": "Point",
    "coordinates": [
      -91.9333,
      30.8833
    ]
  },
  "type": "Feature",
  "properties": {
    "hierarchy": [
      "tgn:2197161",
      "tgn:2000858",
      "tgn:1000001",
      "tgn:7012149",
      "tgn:7007256",
      "tgn:7029392"
    ],
    "placetype": [
      "aat:300008347"
    ],
    "id": 2197161,
    "name:xx": "Broussard"
  }
}
