{
  "geometry": {
    "type": "Point",
    "coordinates": [
      -83.5833,
      36.9833
    ]
  },
  "type": "Feature",
  "properties": {
    "hierarchy": [
      "tgn:2487896",
      "tgn:1000001",
      "tgn:2000782",
      "tgn:7012149",
      "tgn:7007255",
      "tgn:7029392"
    ],
    "placetype": [
      "aat:300008706"
    ],
    "id": 2487896,
    "name:xx": "Left Fork Upper Bear Creek"
  }
}
