{
  "geometry": {
    "type": "Point",
    "coordinates": [
      -84.5333,
      36.8833
    ]
  },
  "type": "Feature",
  "properties": {
    "hierarchy": [
      "tgn:2278995",
      "tgn:1000001",
      "tgn:7012149",
      "tgn:2000839",
      "tgn:7007255",
      "tgn:7029392"
    ],
    "placetype": [
      "aat:300008761"
    ],
    "id": 2278995,
    "name:xx": "Dead Ox Hollow"
  }
}
