{
  "geometry": {
    "type": "Point",
    "coordinates": [
      74.111944,
      14.82
    ]
  },
  "type": "Feature",
  "properties": {
    "hierarchy": [
      "tgn:7577640",
      "tgn:1000004",
      "tgn:7000198",
      "tgn:1001882",
      "tgn:7029392"
    ],
    "placetype": [
      "aat:300132316"
    ],
    "name:en": "Kārwār Bay",
    "id": 7577640
  }
}
