{
  "type": "FeatureCollection",
  "features": [
    {
      "geometry": {
        "type": "Point",
        "coordinates": [
          -93.85,
          31.4833
        ]
      },
      "type": "Feature",
      "properties": {
        "hierarchy": [
          "tgn:2495790",
          "tgn:1000001",
          "tgn:7012149",
          "tgn:2002066",
          "tgn:7007826",
          "tgn:7029392"
        ],
        "placetype": [
          "aat:300008706"
        ],
        "id": 2495790,
        "name:xx": "Mason Creek"
      }
    },
    {
      "geometry": {
        "type": "Point",
        "coordinates": [
          -99.05,
          29.85
        ]
      },
      "type": "Feature",
      "properties": {
        "hierarchy": [
          "tgn:2495791",
          "tgn:1000001",
          "tgn:7012149",
          "tgn:7007826",
          "tgn:7029392"
        ],
        "placetype": [
          "aat:300008706"
        ],
        "id": 2495791,
        "name:xx": "Mason Creek"
      }
    },
    {
      "geometry": {
        "type": "Point",
        "coordinates": [
          -78.2167,
          36.9
        ]
      },
      "type": "Feature",
      "properties": {
        "hierarchy": [
          "tgn:2495792",
          "tgn:1000001",
          "tgn:7012149",
          "tgn:2002171",
          "tgn:7007919",
          "tgn:7029392"
        ],
        "placetype": [
          "aat:300008706"
        ],
        "id": 2495792,
        "name:xx": "Mason Creek"
      }
    },
    {
      "geometry": {
        "type": "Point",
        "coordinates": [
          -76.2333,
          36.9167
        ]
      },
      "type": "Feature",
      "properties": {
        "hierarchy": [
          "tgn:2495793",
          "tgn:1000001",
          "tgn:7012149",
          "tgn:7022201",
          "tgn:7007919",
          "tgn:7029392"
        ],
        "placetype": [
          "aat:300008706"
        ],
        "id": 2495793,
        "name:xx": "Mason Creek"
      }
    },
    {
      "geometry": {
        "type": "Point",
        "coordinates": [
          -80.1667,
          37.3167
        ]
      },
      "type": "Feature",
      "properties": {
        "hierarchy": [
          "tgn:2495794",
          "tgn:1000001",
          "tgn:7012149",
          "tgn:7007919",
          "tgn:7029392"
        ],
        "placetype": [
          "aat:300008706"
        ],
        "id": 2495794,
        "name:xx": "Mason Creek"
      }
    },
    {
      "geometry": {
        "type": "Point",
        "coordinates": [
          -121.55,
          47.4167
        ]
      },
      "type": "Feature",
      "properties": {
        "hierarchy": [
          "tgn:2495795",
          "tgn:1000001",
          "tgn:7012149",
          "tgn:7018871",
          "tgn:7007920",
          "tgn:7029392"
        ],
        "placetype": [
          "aat:300008706"
        ],
        "id": 2495795,
        "name:xx": "Mason Creek"
      }
    },
    {
      "geometry": {
        "type": "Point",
        "coordinates": [
          -122.5333,
          45.9
        ]
      },
      "type": "Feature",
      "properties": {
        "hierarchy": [
          "tgn:2495796",
          "tgn:1000001",
          "tgn:1002275",
          "tgn:7012149",
          "tgn:7007920",
          "tgn:7029392"
        ],
        "placetype": [
          "aat:300008706"
        ],
        "id": 2495796,
        "name:xx": "Mason Creek"
      }
    },
    {
      "geometry": {
        "type": "Point",
        "coordinates": [
          -120.75,
          47.2667
        ]
      },
      "type": "Feature",
      "properties": {
        "hierarchy": [
          "tgn:2495797",
          "tgn:1000001",
          "tgn:7012149",
          "tgn:1002553",
          "tgn:7007920",
          "tgn:7029392"
        ],
        "placetype": [
          "aat:300008706"
        ],
        "id": 2495797,
        "name:xx": "Mason Creek"
      }
    },
    {
      "geometry": {
        "type": "Point",
        "coordinates": [
          -88.4167,
          43.2167
        ]
      },
      "type": "Feature",
      "properties": {
        "hierarchy": [
          "tgn:2495798",
          "tgn:1000001",
          "tgn:7012149",
          "tgn:7007922",
          "tgn:7029392"
        ],
        "placetype": [
          "aat:300008706"
        ],
        "id": 2495798,
        "name:xx": "Mason Creek"
      }
    },
    {
      "geometry": {
        "type": "Point",
        "coordinates": [
          -90.7,
          45.8
        ]
      },
      "type": "Feature",
      "properties": {
        "hierarchy": [
          "tgn:2495799",
          "tgn:1000001",
          "tgn:7012149",
          "tgn:2002353",
          "tgn:7007922",
          "tgn:7029392"
        ],
        "placetype": [
          "aat:300008706"
        ],
        "id": 2495799,
        "name:xx": "Mason Creek"
      }
    }
  ]
}
