{
  "geometry": {
    "type": "Point",
    "coordinates": [
      -117.7333,
      47.8667
    ]
  },
  "type": "Feature",
  "properties": {
    "hierarchy": [
      "tgn:2174384",
      "tgn:1000001",
      "tgn:7012149",
      "tgn:2002250",
      "tgn:7007920",
      "tgn:7029392"
    ],
    "placetype": [
      "aat:300008761"
    ],
    "id": 2174384,
    "name:xx": "Bishop Canyon"
  }
}
