{
  "geometry": {
    "type": "Point",
    "coordinates": [
      -83.85,
      42.25
    ]
  },
  "type": "Feature",
  "properties": {
    "hierarchy": [
      "tgn:1003000",
      "tgn:1000001",
      "tgn:7012149",
      "tgn:7007520",
      "tgn:7029392"
    ],
    "placetype": [
      "aat:300387145",
      "aat:300000771"
    ],
    "id": 1003000,
    "name:xx": "Washtenaw"
  }
}
