{
  "geometry": {
    "type": "Point",
    "coordinates": [
      -96.3333,
      34.45
    ]
  },
  "type": "Feature",
  "properties": {
    "hierarchy": [
      "tgn:2557066",
      "tgn:1000001",
      "tgn:2001637",
      "tgn:7012149",
      "tgn:7007707",
      "tgn:7029392"
    ],
    "placetype": [
      "aat:300008680"
    ],
    "id": 2557066,
    "name:xx": "Old Grassy Lake"
  }
}
