{
  "geometry": {
    "type": "Point",
    "coordinates": [
      -113.5667,
      34.1667
    ]
  },
  "type": "Feature",
  "properties": {
    "hierarchy": [
      "tgn:2684214",
      "tgn:1000001",
      "tgn:7006451",
      "tgn:7012149",
      "tgn:2000104",
      "tgn:7029392"
    ],
    "placetype": [
      "aat:300008699"
    ],
    "id": 2684214,
    "name:xx": "Spenser Wash"
  }
}
