{
  "geometry": {
    "type": "Point",
    "coordinates": [
      -103.0167,
      40.5833
    ]
  },
  "type": "Feature",
  "properties": {
    "hierarchy": [
      "tgn:2546238",
      "tgn:1000001",
      "tgn:7012149",
      "tgn:7007158",
      "tgn:7029392"
    ],
    "placetype": [
      "aat:300008706"
    ],
    "id": 2546238,
    "name:xx": "North Fork Frenchman Creek"
  }
}
