{
  "geometry": {
    "type": "Point",
    "coordinates": [
      -147.3167,
      65.5167
    ]
  },
  "type": "Feature",
  "properties": {
    "hierarchy": [
      "tgn:1104105",
      "tgn:7006450",
      "tgn:1000001",
      "tgn:7012149",
      "tgn:2000089",
      "tgn:7029392"
    ],
    "placetype": [
      "aat:300008795"
    ],
    "id": 1104105,
    "name:xx": "Cache Mountain"
  }
}
