{
  "geometry": {
    "type": "Point",
    "coordinates": [
      -78.3167,
      36.2333
    ]
  },
  "type": "Feature",
  "properties": {
    "hierarchy": [
      "tgn:2285340",
      "tgn:1000001",
      "tgn:7012149",
      "tgn:7013940",
      "tgn:7007709",
      "tgn:7029392"
    ],
    "placetype": [
      "aat:300008706"
    ],
    "id": 2285340,
    "name:xx": "Devils Cradle Creek"
  }
}
