{
  "type": "FeatureCollection",
  "features": [
    {
      "geometry": {
        "type": "Point",
        "coordinates": [
          0.316667,
          51.166667
        ]
      },
      "type": "Feature",
      "properties": {
        "hierarchy": [
          "tgn:4011410",
          "tgn:7002445",
          "tgn:1000003",
          "tgn:7008153",
          "tgn:7008591",
          "tgn:7029392"
        ],
        "placetype": [
          "aat:300008347",
          "aat:300008372"
        ],
        "name:en": "Tudeley",
        "id": 4011410
      }
    },
    {
      "geometry": {
        "type": "Point",
        "coordinates": [
          5.233333,
          51.816667
        ]
      },
      "type": "Feature",
      "properties": {
        "hierarchy": [
          "tgn:4011411",
          "tgn:7003619",
          "tgn:1000003",
          "tgn:7016845",
          "tgn:7029392"
        ],
        "placetype": [
          "aat:300008347"
        ],
        "name:nl": "Tuil",
        "id": 4011411
      }
    },
    {
      "geometry": {
        "type": "Point",
        "coordinates": [
          9.733889,
          49.089722
        ]
      },
      "type": "Feature",
      "properties": {
        "hierarchy": [
          "tgn:4011415",
          "tgn:7003692",
          "tgn:1000003",
          "tgn:7000084",
          "tgn:7029392"
        ],
        "placetype": [
          "aat:300008347"
        ],
        "id": 4011415,
        "name:xx": "Tullau"
      }
    }
  ]
}
