{
  "geometry": {
    "type": "Point",
    "coordinates": [
      -105.1167,
      42.1167
    ]
  },
  "type": "Feature",
  "properties": {
    "hierarchy": [
      "tgn:2139942",
      "tgn:1000001",
      "tgn:7012149",
      "tgn:2002380",
      "tgn:7007923",
      "tgn:7029392"
    ],
    "placetype": [
      "aat:300006191"
    ],
    "id": 2139942,
    "name:xx": "Attebury Reservoir"
  }
}
