{
  "geometry": {
    "type": "Point",
    "coordinates": [
      -83.1833,
      35.1333
    ]
  },
  "type": "Feature",
  "properties": {
    "hierarchy": [
      "tgn:2440889",
      "tgn:1000001",
      "tgn:7012149",
      "tgn:2001508",
      "tgn:7007709",
      "tgn:7029392"
    ],
    "placetype": [
      "aat:300008706"
    ],
    "id": 2440889,
    "name:xx": "Knob Creek"
  }
}
