{
  "type": "FeatureCollection",
  "features": [
    {
      "geometry": {
        "type": "Point",
        "coordinates": [
          12.95,
          53.433333
        ]
      },
      "type": "Feature",
      "properties": {
        "hierarchy": [
          "tgn:7101290",
          "tgn:1000003",
          "tgn:7000094",
          "tgn:7000084",
          "tgn:7029392"
        ],
        "placetype": [
          "aat:300008680"
        ],
        "id": 7101290,
        "name:xx": "Röthsee"
      }
    },
    {
      "geometry": {
        "type": "Point",
        "coordinates": [
          12.85,
          53.366667
        ]
      },
      "type": "Feature",
      "properties": {
        "hierarchy": [
          "tgn:7101291",
          "tgn:1000003",
          "tgn:7000094",
          "tgn:7000084",
          "tgn:7029392"
        ],
        "placetype": [
          "aat:300008680"
        ],
        "id": 7101291,
        "name:xx": "Röth-See"
      }
    },
    {
      "geometry": {
        "type": "Point",
        "coordinates": [
          13.133333,
          53.25
        ]
      },
      "type": "Feature",
      "properties": {
        "hierarchy": [
          "tgn:7101292",
          "tgn:1000003",
          "tgn:7000094",
          "tgn:7000084",
          "tgn:7029392"
        ],
        "placetype": [
          "aat:300008680"
        ],
        "id": 7101292,
        "name:xx": "Röthsee"
      }
    },
    {
      "geometry": {
        "type": "Point",
        "coordinates": [
          13.883333,
          52.7
        ]
      },
      "type": "Feature",
      "properties": {
        "hierarchy": [
          "tgn:7101294",
          "tgn:7000096",
          "tgn:1000003",
          "tgn:7000084",
          "tgn:7029392"
        ],
        "placetype": [
          "aat:300008680"
        ],
        "id": 7101294,
        "name:xx": "Röth-See"
      }
    },
    {
      "geometry": {
        "type": "Point",
        "coordinates": [
          11.233333,
          47.8
        ]
      },
      "type": "Feature",
      "properties": {
        "hierarchy": [
          "tgn:7101296",
          "tgn:7003669",
          "tgn:1000003",
          "tgn:7000084",
          "tgn:7029392"
        ],
        "placetype": [
          "aat:300008680"
        ],
        "id": 7101296,
        "name:xx": "Roth-See"
      }
    },
    {
      "geometry": {
        "type": "Point",
        "coordinates": [
          11.233333,
          47.8
        ]
      },
      "type": "Feature",
      "properties": {
        "hierarchy": [
          "tgn:7101297",
          "tgn:7003669",
          "tgn:1000003",
          "tgn:7000084",
          "tgn:7029392"
        ],
        "placetype": [
          "aat:300000206"
        ],
        "id": 7101297,
        "name:xx": "Rothsee"
      }
    },
    {
      "geometry": {
        "type": "Point",
        "coordinates": [
          11.45,
          48.233333
        ]
      },
      "type": "Feature",
      "properties": {
        "hierarchy": [
          "tgn:7101298",
          "tgn:7003669",
          "tgn:1000003",
          "tgn:7000084",
          "tgn:7029392"
        ],
        "placetype": [
          "aat:300008347"
        ],
        "id": 7101298,
        "name:xx": "Rothschwaige"
      }
    },
    {
      "geometry": {
        "type": "Point",
        "coordinates": [
          11.2,
          48.166667
        ]
      },
      "type": "Feature",
      "properties": {
        "hierarchy": [
          "tgn:7101299",
          "tgn:7003669",
          "tgn:1000003",
          "tgn:7000084",
          "tgn:7029392"
        ],
        "placetype": [
          "aat:300008347"
        ],
        "id": 7101299,
        "name:xx": "Rothschwaig"
      }
    }
  ]
}
