{
  "geometry": {
    "type": "Point",
    "coordinates": [
      -86.85,
      39.3667
    ]
  },
  "type": "Feature",
  "properties": {
    "hierarchy": [
      "tgn:2306670",
      "tgn:1000001",
      "tgn:7012149",
      "tgn:2000548",
      "tgn:7007252",
      "tgn:7029392"
    ],
    "placetype": [
      "aat:300008706"
    ],
    "id": 2306670,
    "name:xx": "East Fork Fish Creek"
  }
}
