{
  "geometry": {
    "type": "Point",
    "coordinates": [
      -72.5667,
      43.0333
    ]
  },
  "type": "Feature",
  "properties": {
    "hierarchy": [
      "tgn:2635888",
      "tgn:1000001",
      "tgn:7012149",
      "tgn:7029392"
    ],
    "placetype": [
      "aat:300008699"
    ],
    "id": 2635888,
    "name:xx": "Sacketts Brook"
  }
}
