{
  "geometry": {
    "type": "Point",
    "coordinates": [
      -92.1833,
      37.1667
    ]
  },
  "type": "Feature",
  "properties": {
    "hierarchy": [
      "tgn:2743079",
      "tgn:1000001",
      "tgn:7012149",
      "tgn:7007523",
      "tgn:7029392"
    ],
    "placetype": [
      "aat:300008706"
    ],
    "id": 2743079,
    "name:xx": "Van Zant Creek"
  }
}
