{
  "geometry": {
    "type": "Point",
    "coordinates": [
      -106.3833,
      52.0167
    ]
  },
  "type": "Feature",
  "properties": {
    "hierarchy": [
      "tgn:1015872",
      "tgn:7005685",
      "tgn:1000001",
      "tgn:7005805",
      "tgn:7029392"
    ],
    "placetype": [
      "aat:300008347"
    ],
    "id": 1015872,
    "name:xx": "Clavet"
  }
}
