{
  "geometry": {
    "type": "Point",
    "coordinates": [
      -64.65,
      18.4167
    ]
  },
  "type": "Feature",
  "properties": {
    "hierarchy": [
      "tgn:1106270",
      "tgn:1009495",
      "tgn:7004677",
      "tgn:1000001",
      "tgn:7029392"
    ],
    "placetype": [
      "aat:300008795"
    ],
    "id": 1106270,
    "name:xx": "Sage, Mount"
  }
}
