{
  "geometry": {
    "type": "Point",
    "coordinates": [
      18.0167,
      60.0333
    ]
  },
  "type": "Feature",
  "properties": {
    "hierarchy": [
      "tgn:1063605",
      "tgn:1000003",
      "tgn:1000462",
      "tgn:1000097",
      "tgn:7029392"
    ],
    "placetype": [
      "aat:300008347"
    ],
    "id": 1063605,
    "name:xx": "Skoby"
  }
}
