{
  "geometry": {
    "type": "Point",
    "coordinates": [
      -87.75,
      45.45
    ]
  },
  "type": "Feature",
  "properties": {
    "hierarchy": [
      "tgn:2495399",
      "tgn:1000001",
      "tgn:7012149",
      "tgn:2000978",
      "tgn:7007520",
      "tgn:7029392"
    ],
    "placetype": [
      "aat:300008680"
    ],
    "id": 2495399,
    "name:xx": "Mary, Lake"
  }
}
