{
  "geometry": {
    "type": "Point",
    "coordinates": [
      31.2333,
      -15.7167
    ]
  },
  "type": "Feature",
  "properties": {
    "hierarchy": [
      "tgn:1127489",
      "tgn:7001242",
      "tgn:7029392"
    ],
    "placetype": [
      "aat:300008707"
    ],
    "id": 1127489,
    "name:xx": "Musengezi"
  }
}
