{
  "geometry": {
    "type": "Point",
    "coordinates": [
      -113.4833,
      34.4667
    ]
  },
  "type": "Feature",
  "properties": {
    "hierarchy": [
      "tgn:2588782",
      "tgn:1000001",
      "tgn:7006451",
      "tgn:7012149",
      "tgn:2000098",
      "tgn:7029392"
    ],
    "placetype": [
      "aat:300386831"
    ],
    "id": 2588782,
    "name:xx": "Poachie Range"
  }
}
