{
  "geometry": {
    "type": "Point",
    "coordinates": [
      31.38,
      29.505833
    ]
  },
  "type": "Feature",
  "properties": {
    "hierarchy": [
      "tgn:7521220",
      "tgn:7001242",
      "tgn:7016833",
      "tgn:1001083",
      "tgn:7029392"
    ],
    "placetype": [
      "aat:300008777"
    ],
    "name:en": "Abū Dibbān, 'Ajrat",
    "id": 7521220
  }
}
