{
  "geometry": {
    "type": "Point",
    "coordinates": [
      -76.7167,
      37.8833
    ]
  },
  "type": "Feature",
  "properties": {
    "hierarchy": [
      "tgn:2187216",
      "tgn:1000001",
      "tgn:7012149",
      "tgn:7014334",
      "tgn:7007919",
      "tgn:7029392"
    ],
    "placetype": [
      "aat:300132348"
    ],
    "id": 2187216,
    "name:xx": "Booker Bar"
  }
}
