{
  "geometry": {
    "type": "Point",
    "coordinates": [
      -74.75,
      39.1167
    ]
  },
  "type": "Feature",
  "properties": {
    "hierarchy": [
      "tgn:2720294",
      "tgn:1002232",
      "tgn:1000001",
      "tgn:7012149",
      "tgn:7007565",
      "tgn:7029392"
    ],
    "placetype": [
      "aat:300008706"
    ],
    "id": 2720294,
    "name:xx": "Through Creek"
  }
}
