{
  "geometry": {
    "type": "Point",
    "coordinates": [
      -121.2667,
      37.6167
    ]
  },
  "type": "Feature",
  "properties": {
    "hierarchy": [
      "tgn:2555872",
      "tgn:1000001",
      "tgn:7012149",
      "tgn:7007157",
      "tgn:1002915",
      "tgn:7029392"
    ],
    "placetype": [
      "aat:300008347"
    ],
    "id": 2555872,
    "name:xx": "Ohm"
  }
}
