{
  "geometry": {
    "type": "Point",
    "coordinates": [
      -111.7667,
      46.8833
    ]
  },
  "type": "Feature",
  "properties": {
    "hierarchy": [
      "tgn:2218403",
      "tgn:1000001",
      "tgn:7012149",
      "tgn:2001284",
      "tgn:7007524",
      "tgn:7029392"
    ],
    "placetype": [
      "aat:300008798"
    ],
    "id": 2218403,
    "name:xx": "Candle Mountain"
  }
}
