{
  "type": "FeatureCollection",
  "features": [
    {
      "geometry": {
        "type": "Point",
        "coordinates": [
          -94.5833,
          29.5833
        ]
      },
      "type": "Feature",
      "properties": {
        "hierarchy": [
          "tgn:1117903",
          "tgn:1000001",
          "tgn:7012149",
          "tgn:1002251",
          "tgn:7007826",
          "tgn:7029392"
        ],
        "placetype": [
          "aat:300008680"
        ],
        "id": 1117903,
        "name:xx": "Robinson Lake"
      }
    },
    {
      "geometry": {
        "type": "Point",
        "coordinates": [
          -88.05,
          41.65
        ]
      },
      "type": "Feature",
      "properties": {
        "hierarchy": [
          "tgn:1117905",
          "tgn:1000001",
          "tgn:7012149",
          "tgn:1003024",
          "tgn:7007251",
          "tgn:7029392"
        ],
        "placetype": [
          "aat:300008680"
        ],
        "id": 1117905,
        "name:xx": "Rock Lake"
      }
    },
    {
      "geometry": {
        "type": "Point",
        "coordinates": [
          -99.2,
          48.8167
        ]
      },
      "type": "Feature",
      "properties": {
        "hierarchy": [
          "tgn:1117906",
          "tgn:1000001",
          "tgn:7012149",
          "tgn:2001604",
          "tgn:7007705",
          "tgn:7029392"
        ],
        "placetype": [
          "aat:300008680"
        ],
        "id": 1117906,
        "name:xx": "Rock Lake"
      }
    },
    {
      "geometry": {
        "type": "Point",
        "coordinates": [
          -88.9167,
          43.0667
        ]
      },
      "type": "Feature",
      "properties": {
        "hierarchy": [
          "tgn:1117907",
          "tgn:1000001",
          "tgn:7012149",
          "tgn:1002522",
          "tgn:7007922",
          "tgn:7029392"
        ],
        "placetype": [
          "aat:300008680"
        ],
        "id": 1117907,
        "name:xx": "Rock Lake"
      }
    },
    {
      "geometry": {
        "type": "Point",
        "coordinates": [
          -99.1667,
          49.2167
        ]
      },
      "type": "Feature",
      "properties": {
        "hierarchy": [
          "tgn:1117908",
          "tgn:7005685",
          "tgn:1000001",
          "tgn:7005734",
          "tgn:7029392"
        ],
        "placetype": [
          "aat:300008680"
        ],
        "id": 1117908,
        "name:xx": "Rock Lake"
      }
    },
    {
      "geometry": {
        "type": "Point",
        "coordinates": [
          -78.3833,
          45.5
        ]
      },
      "type": "Feature",
      "properties": {
        "hierarchy": [
          "tgn:1117909",
          "tgn:7005685",
          "tgn:1000001",
          "tgn:7013154",
          "tgn:7029392"
        ],
        "placetype": [
          "aat:300008680"
        ],
        "id": 1117909,
        "name:xx": "Rock Lake"
      }
    }
  ]
}
