{
  "type": "FeatureCollection",
  "features": [
    {
      "geometry": {
        "type": "Point",
        "coordinates": [
          -80.2833,
          25.7
        ]
      },
      "type": "Feature",
      "properties": {
        "hierarchy": [
          "tgn:2021331",
          "tgn:1000001",
          "tgn:7012149",
          "tgn:1002314",
          "tgn:7007240",
          "tgn:7029392"
        ],
        "placetype": [
          "aat:300008347"
        ],
        "id": 2021331,
        "name:xx": "South Miami"
      }
    },
    {
      "geometry": {
        "type": "Point",
        "coordinates": [
          -80.3667,
          25.5833
        ]
      },
      "type": "Feature",
      "properties": {
        "hierarchy": [
          "tgn:2021333",
          "tgn:1000001",
          "tgn:7012149",
          "tgn:1002314",
          "tgn:7007240",
          "tgn:7029392"
        ],
        "placetype": [
          "aat:300008347"
        ],
        "id": 2021333,
        "name:xx": "South Miami Heights"
      }
    },
    {
      "geometry": {
        "type": "Point",
        "coordinates": [
          -81.9667,
          27.8833
        ]
      },
      "type": "Feature",
      "properties": {
        "hierarchy": [
          "tgn:2021334",
          "tgn:1000001",
          "tgn:7012149",
          "tgn:1002793",
          "tgn:7007240",
          "tgn:7029392"
        ],
        "placetype": [
          "aat:300008347"
        ],
        "id": 2021334,
        "name:xx": "South Mulberry"
      }
    },
    {
      "geometry": {
        "type": "Point",
        "coordinates": [
          -80.0333,
          26.5833
        ]
      },
      "type": "Feature",
      "properties": {
        "hierarchy": [
          "tgn:2021335",
          "tgn:1000001",
          "tgn:7012149",
          "tgn:1002768",
          "tgn:7007240",
          "tgn:7029392"
        ],
        "placetype": [
          "aat:300008347"
        ],
        "id": 2021335,
        "name:xx": "South Palm Beach"
      }
    },
    {
      "geometry": {
        "type": "Point",
        "coordinates": [
          -82.7333,
          27.75
        ]
      },
      "type": "Feature",
      "properties": {
        "hierarchy": [
          "tgn:2021336",
          "tgn:1000001",
          "tgn:7012149",
          "tgn:1002790",
          "tgn:7007240",
          "tgn:7029392"
        ],
        "placetype": [
          "aat:300008347"
        ],
        "id": 2021336,
        "name:xx": "South Pasadena"
      }
    }
  ]
}
