{
  "geometry": {
    "type": "Point",
    "coordinates": [
      -123.8667,
      41.6833
    ]
  },
  "type": "Feature",
  "properties": {
    "hierarchy": [
      "tgn:2426918",
      "tgn:1000001",
      "tgn:7012149",
      "tgn:2000180",
      "tgn:7007157",
      "tgn:7029392"
    ],
    "placetype": [
      "aat:300266640"
    ],
    "id": 2426918,
    "name:xx": "Jones Ridge"
  }
}
