{
  "geometry": {
    "type": "Point",
    "coordinates": [
      -121.6333,
      47.5667
    ]
  },
  "type": "Feature",
  "properties": {
    "hierarchy": [
      "tgn:2452956",
      "tgn:1000001",
      "tgn:7012149",
      "tgn:7018871",
      "tgn:7007920",
      "tgn:7029392"
    ],
    "placetype": [
      "aat:300008680"
    ],
    "id": 2452956,
    "name:xx": "Little Calligan Lake"
  }
}
