{
  "geometry": {
    "type": "Point",
    "coordinates": [
      -81.9333,
      27.55
    ]
  },
  "type": "Feature",
  "properties": {
    "hierarchy": [
      "tgn:2446001",
      "tgn:1000001",
      "tgn:1002452",
      "tgn:7012149",
      "tgn:7007240",
      "tgn:7029392"
    ],
    "placetype": [
      "aat:300008706"
    ],
    "id": 2446001,
    "name:xx": "Lettis Creek"
  }
}
