{
  "geometry": {
    "type": "Point",
    "coordinates": [
      -119.9333,
      37.9833
    ]
  },
  "type": "Feature",
  "properties": {
    "hierarchy": [
      "tgn:2265329",
      "tgn:1000001",
      "tgn:7012149",
      "tgn:7007157",
      "tgn:1002957",
      "tgn:7029392"
    ],
    "placetype": [
      "aat:300008706"
    ],
    "id": 2265329,
    "name:xx": "Crane Creek"
  }
}
