{
  "geometry": {
    "type": "Point",
    "coordinates": [
      -104.9667,
      40.7333
    ]
  },
  "type": "Feature",
  "properties": {
    "hierarchy": [
      "tgn:2241415",
      "tgn:1000001",
      "tgn:7012149",
      "tgn:2000226",
      "tgn:7007158",
      "tgn:7029392"
    ],
    "placetype": [
      "aat:300006191"
    ],
    "id": 2241415,
    "name:xx": "Clark Reservoir"
  }
}
