{
  "geometry": {
    "type": "Point",
    "coordinates": [
      -87.2667,
      33.9833
    ]
  },
  "type": "Feature",
  "properties": {
    "hierarchy": [
      "tgn:2461140",
      "tgn:7002659",
      "tgn:1000001",
      "tgn:7012149",
      "tgn:7029392"
    ],
    "placetype": [
      "aat:300008706"
    ],
    "id": 2461140,
    "name:xx": "Little Spring Creek"
  }
}
