{
  "geometry": {
    "type": "Point",
    "coordinates": [
      -132.25,
      54.7167
    ]
  },
  "type": "Feature",
  "properties": {
    "hierarchy": [
      "tgn:2198749",
      "tgn:7006450",
      "tgn:1000001",
      "tgn:7012149",
      "tgn:2000082",
      "tgn:7029392"
    ],
    "placetype": [
      "aat:300132316"
    ],
    "id": 2198749,
    "name:xx": "Brownson Bay"
  }
}
