{
  "geometry": {
    "type": "Point",
    "coordinates": [
      120.8456,
      24.5668
    ]
  },
  "type": "Feature",
  "properties": {
    "hierarchy": [
      "tgn:7470902",
      "tgn:7487020",
      "tgn:1000004",
      "tgn:1000141",
      "tgn:7029392"
    ],
    "placetype": [
      "aat:300008347"
    ],
    "id": 7470902,
    "name:xx": "Ergangping"
  }
}
