{
  "geometry": {
    "type": "Point",
    "coordinates": [
      -121.3667,
      48.7333
    ]
  },
  "type": "Feature",
  "properties": {
    "hierarchy": [
      "tgn:2284770",
      "tgn:1000001",
      "tgn:7012149",
      "tgn:1003020",
      "tgn:7007920",
      "tgn:7029392"
    ],
    "placetype": [
      "aat:300008798"
    ],
    "id": 2284770,
    "name:xx": "Despair, Mount"
  }
}
