{
  "type": "FeatureCollection",
  "features": [
    {
      "geometry": {
        "type": "Point",
        "coordinates": [
          -76.9667,
          38.3833
        ]
      },
      "type": "Feature",
      "properties": {
        "hierarchy": [
          "tgn:2207240",
          "tgn:7016100",
          "tgn:1000001",
          "tgn:7012149",
          "tgn:7007516",
          "tgn:7029392"
        ],
        "placetype": [
          "aat:300008798"
        ],
        "id": 2207240,
        "name:xx": "Bunker Hill"
      }
    },
    {
      "geometry": {
        "type": "Point",
        "coordinates": [
          -71.05,
          42.3667
        ]
      },
      "type": "Feature",
      "properties": {
        "hierarchy": [
          "tgn:2207241",
          "tgn:1000001",
          "tgn:1002923",
          "tgn:7012149",
          "tgn:7007517",
          "tgn:7029392"
        ],
        "placetype": [
          "aat:300008798"
        ],
        "id": 2207241,
        "name:xx": "Bunker Hill"
      }
    },
    {
      "geometry": {
        "type": "Point",
        "coordinates": [
          -89.5,
          31.8
        ]
      },
      "type": "Feature",
      "properties": {
        "hierarchy": [
          "tgn:2207242",
          "tgn:1000001",
          "tgn:7012149",
          "tgn:2001150",
          "tgn:7007522",
          "tgn:7029392"
        ],
        "placetype": [
          "aat:300008347"
        ],
        "id": 2207242,
        "name:xx": "Bunker Hill"
      }
    },
    {
      "geometry": {
        "type": "Point",
        "coordinates": [
          -88.3833,
          33.55
        ]
      },
      "type": "Feature",
      "properties": {
        "hierarchy": [
          "tgn:2207243",
          "tgn:1000001",
          "tgn:7012149",
          "tgn:2001129",
          "tgn:7007522",
          "tgn:7029392"
        ],
        "placetype": [
          "aat:300008347"
        ],
        "id": 2207243,
        "name:xx": "Bunker Hill"
      }
    },
    {
      "geometry": {
        "type": "Point",
        "coordinates": [
          -92.3833,
          40.5667
        ]
      },
      "type": "Feature",
      "properties": {
        "hierarchy": [
          "tgn:2207244",
          "tgn:1000001",
          "tgn:7012149",
          "tgn:2001244",
          "tgn:7007523",
          "tgn:7029392"
        ],
        "placetype": [
          "aat:300008347"
        ],
        "id": 2207244,
        "name:xx": "Bunker Hill"
      }
    },
    {
      "geometry": {
        "type": "Point",
        "coordinates": [
          -93.6333,
          37.4333
        ]
      },
      "type": "Feature",
      "properties": {
        "hierarchy": [
          "tgn:2207245",
          "tgn:1000001",
          "tgn:7012149",
          "tgn:2001191",
          "tgn:7007523",
          "tgn:7029392"
        ],
        "placetype": [
          "aat:300008798"
        ],
        "id": 2207245,
        "name:xx": "Bunker Hill"
      }
    },
    {
      "geometry": {
        "type": "Point",
        "coordinates": [
          -94.6333,
          40.45
        ]
      },
      "type": "Feature",
      "properties": {
        "hierarchy": [
          "tgn:2207246",
          "tgn:1000001",
          "tgn:7012149",
          "tgn:2001224",
          "tgn:7007523",
          "tgn:7029392"
        ],
        "placetype": [
          "aat:300008798"
        ],
        "id": 2207246,
        "name:xx": "Bunker Hill"
      }
    },
    {
      "geometry": {
        "type": "Point",
        "coordinates": [
          -89.9667,
          36.7
        ]
      },
      "type": "Feature",
      "properties": {
        "hierarchy": [
          "tgn:2207247",
          "tgn:1000001",
          "tgn:7012149",
          "tgn:2001248",
          "tgn:7007523",
          "tgn:7029392"
        ],
        "placetype": [
          "aat:300008347"
        ],
        "id": 2207247,
        "name:xx": "Bunker Hill"
      }
    },
    {
      "geometry": {
        "type": "Point",
        "coordinates": [
          -91.7333,
          40.1667
        ]
      },
      "type": "Feature",
      "properties": {
        "hierarchy": [
          "tgn:2207249",
          "tgn:1000001",
          "tgn:7012149",
          "tgn:1002592",
          "tgn:7007523",
          "tgn:7029392"
        ],
        "placetype": [
          "aat:300008347"
        ],
        "id": 2207249,
        "name:xx": "Bunker Hill"
      }
    }
  ]
}
