{
  "geometry": {
    "type": "Point",
    "coordinates": [
      -84.8167,
      39.8667
    ]
  },
  "type": "Feature",
  "properties": {
    "hierarchy": [
      "tgn:2319979",
      "tgn:1000001",
      "tgn:7012149",
      "tgn:7029392"
    ],
    "placetype": [
      "aat:300008706"
    ],
    "id": 2319979,
    "name:xx": "Evans Creek"
  }
}
