{
  "geometry": {
    "type": "Point",
    "coordinates": [
      -78.1833,
      37.9167
    ]
  },
  "type": "Feature",
  "properties": {
    "hierarchy": [
      "tgn:2759789",
      "tgn:1000001",
      "tgn:7012149",
      "tgn:2002159",
      "tgn:7007919",
      "tgn:7029392"
    ],
    "placetype": [
      "aat:300008699"
    ],
    "id": 2759789,
    "name:xx": "West Fork Kent Branch"
  }
}
