{
  "geometry": {
    "type": "Point",
    "coordinates": [
      -85.8667,
      33.3167
    ]
  },
  "type": "Feature",
  "properties": {
    "hierarchy": [
      "tgn:2127570",
      "tgn:7002659",
      "tgn:1000001",
      "tgn:2000013",
      "tgn:7012149",
      "tgn:7029392"
    ],
    "placetype": [
      "aat:300000390"
    ],
    "id": 2127570,
    "name:xx": "Alabama Gold and Mica Mine"
  }
}
