{
  "geometry": {
    "type": "Point",
    "coordinates": [
      -82.7833,
      41.2833
    ]
  },
  "type": "Feature",
  "properties": {
    "hierarchy": [
      "tgn:2699502",
      "tgn:1000001",
      "tgn:7012149",
      "tgn:1002497",
      "tgn:7007706",
      "tgn:7029392"
    ],
    "placetype": [
      "aat:300266640"
    ],
    "id": 2699502,
    "name:xx": "Strongs Ridge"
  }
}
