{
  "type": "FeatureCollection",
  "features": [
    {
      "geometry": {
        "type": "Point",
        "coordinates": [
          -115.5667,
          36.3167
        ]
      },
      "type": "Feature",
      "properties": {
        "hierarchy": [
          "tgn:2133850",
          "tgn:1000001",
          "tgn:2001410",
          "tgn:7012149",
          "tgn:7007526",
          "tgn:7029392"
        ],
        "placetype": [
          "aat:300008798"
        ],
        "id": 2133850,
        "name:xx": "Angel Peak"
      }
    },
    {
      "geometry": {
        "type": "Point",
        "coordinates": [
          -107.85,
          36.55
        ]
      },
      "type": "Feature",
      "properties": {
        "hierarchy": [
          "tgn:2133851",
          "tgn:1000001",
          "tgn:7012149",
          "tgn:2001452",
          "tgn:7007566",
          "tgn:7029392"
        ],
        "placetype": [
          "aat:300008798"
        ],
        "id": 2133851,
        "name:xx": "Angel Peak"
      }
    },
    {
      "geometry": {
        "type": "Point",
        "coordinates": [
          -120.7167,
          42.3
        ]
      },
      "type": "Feature",
      "properties": {
        "hierarchy": [
          "tgn:2133852",
          "tgn:1000001",
          "tgn:7012149",
          "tgn:2001715",
          "tgn:7007708",
          "tgn:7029392"
        ],
        "placetype": [
          "aat:300008798"
        ],
        "id": 2133852,
        "name:xx": "Angel Peak"
      }
    },
    {
      "geometry": {
        "type": "Point",
        "coordinates": [
          -109.55,
          43.0167
        ]
      },
      "type": "Feature",
      "properties": {
        "hierarchy": [
          "tgn:2133853",
          "tgn:1000001",
          "tgn:7012149",
          "tgn:7007923",
          "tgn:7029392"
        ],
        "placetype": [
          "aat:300008798"
        ],
        "id": 2133853,
        "name:xx": "Angel Peak"
      }
    },
    {
      "geometry": {
        "type": "Point",
        "coordinates": [
          -120.7167,
          42.3
        ]
      },
      "type": "Feature",
      "properties": {
        "hierarchy": [
          "tgn:2133854",
          "tgn:1000001",
          "tgn:7012149",
          "tgn:2001715",
          "tgn:7007708",
          "tgn:7029392"
        ],
        "placetype": [
          "aat:300000390"
        ],
        "id": 2133854,
        "name:xx": "Angel Peak Mine"
      }
    },
    {
      "geometry": {
        "type": "Point",
        "coordinates": [
          -114.3333,
          33.7667
        ]
      },
      "type": "Feature",
      "properties": {
        "hierarchy": [
          "tgn:2133855",
          "tgn:1000001",
          "tgn:7006451",
          "tgn:7012149",
          "tgn:2000096",
          "tgn:7029392"
        ],
        "placetype": [
          "aat:300008798"
        ],
        "id": 2133855,
        "name:xx": "Angel Point"
      }
    },
    {
      "geometry": {
        "type": "Point",
        "coordinates": [
          -114.1667,
          47.9833
        ]
      },
      "type": "Feature",
      "properties": {
        "hierarchy": [
          "tgn:2133856",
          "tgn:1000001",
          "tgn:7012149",
          "tgn:2001274",
          "tgn:7007524",
          "tgn:7029392"
        ],
        "placetype": [
          "aat:300008850"
        ],
        "id": 2133856,
        "name:xx": "Angel Point"
      }
    },
    {
      "geometry": {
        "type": "Point",
        "coordinates": [
          -117.5167,
          45.05
        ]
      },
      "type": "Feature",
      "properties": {
        "hierarchy": [
          "tgn:2133857",
          "tgn:7013349",
          "tgn:1000001",
          "tgn:7012149",
          "tgn:7007708",
          "tgn:7029392"
        ],
        "placetype": [
          "aat:300008798"
        ],
        "id": 2133857,
        "name:xx": "Angel Point"
      }
    },
    {
      "geometry": {
        "type": "Point",
        "coordinates": [
          -110.4667,
          38.3167
        ]
      },
      "type": "Feature",
      "properties": {
        "hierarchy": [
          "tgn:2133858",
          "tgn:1000001",
          "tgn:7012149",
          "tgn:2002128",
          "tgn:7007827",
          "tgn:7029392"
        ],
        "placetype": [
          "aat:300266640"
        ],
        "id": 2133858,
        "name:xx": "Angel Point"
      }
    },
    {
      "geometry": {
        "type": "Point",
        "coordinates": [
          -116.4833,
          46.4667
        ]
      },
      "type": "Feature",
      "properties": {
        "hierarchy": [
          "tgn:2133859",
          "tgn:1000001",
          "tgn:7012149",
          "tgn:2000486",
          "tgn:7007250",
          "tgn:7029392"
        ],
        "placetype": [
          "aat:300266640"
        ],
        "id": 2133859,
        "name:xx": "Angel Ridge"
      }
    }
  ]
}
