{
  "geometry": {
    "type": "Point",
    "coordinates": [
      -77.7167,
      40.2833
    ]
  },
  "type": "Feature",
  "properties": {
    "hierarchy": [
      "tgn:2086484",
      "tgn:1000001",
      "tgn:7012149",
      "tgn:1002494",
      "tgn:7007710",
      "tgn:7029392"
    ],
    "placetype": [
      "aat:300008347"
    ],
    "id": 2086484,
    "name:xx": "Blairs Mills"
  }
}
