{
  "type": "FeatureCollection",
  "features": [
    {
      "geometry": {
        "type": "Point",
        "coordinates": [
          -60.5833,
          -4.4833
        ]
      },
      "type": "Feature",
      "properties": {
        "hierarchy": [
          "tgn:1130520",
          "tgn:1001826",
          "tgn:1000047",
          "tgn:7002456",
          "tgn:1000002",
          "tgn:7029392"
        ],
        "placetype": [
          "aat:300008707"
        ],
        "id": 1130520,
        "name:xx": "Taciuã, Lago"
      }
    },
    {
      "geometry": {
        "type": "Point",
        "coordinates": [
          -92.913,
          17.959
        ]
      },
      "type": "Feature",
      "properties": {
        "hierarchy": [
          "tgn:1130521",
          "tgn:1000001",
          "tgn:7005560",
          "tgn:7029392"
        ],
        "placetype": [
          "aat:300008707",
          "aat:300008699"
        ],
        "id": 1130521,
        "name:xx": "Tacotalpa, Río"
      }
    },
    {
      "geometry": {
        "type": "Point",
        "coordinates": [
          -53.3,
          -32.7667
        ]
      },
      "type": "Feature",
      "properties": {
        "hierarchy": [
          "tgn:1130522",
          "tgn:1000002",
          "tgn:1000058",
          "tgn:7029392"
        ],
        "placetype": [
          "aat:300008707"
        ],
        "id": 1130522,
        "name:xx": "Tacuarí, Río"
      }
    },
    {
      "geometry": {
        "type": "Point",
        "coordinates": [
          -55.4833,
          -32.4167
        ]
      },
      "type": "Feature",
      "properties": {
        "hierarchy": [
          "tgn:1130523",
          "tgn:7002644",
          "tgn:1000002",
          "tgn:1000058",
          "tgn:7029392"
        ],
        "placetype": [
          "aat:300008707"
        ],
        "id": 1130523,
        "name:xx": "Tacuarembó, Río"
      }
    },
    {
      "geometry": {
        "type": "Point",
        "coordinates": [
          125.25,
          38.7
        ]
      },
      "type": "Feature",
      "properties": {
        "hierarchy": [
          "tgn:1130525",
          "tgn:1000004",
          "tgn:1000122",
          "tgn:7029392"
        ],
        "placetype": [
          "aat:300008707"
        ],
        "id": 1130525,
        "name:xx": "Taedong"
      }
    },
    {
      "geometry": {
        "type": "Point",
        "coordinates": [
          -3.175833,
          51.463889
        ]
      },
      "type": "Feature",
      "properties": {
        "hierarchy": [
          "tgn:1130527",
          "tgn:7002443",
          "tgn:1000003",
          "tgn:7008591",
          "tgn:7029392"
        ],
        "placetype": [
          "aat:300008707",
          "aat:300008699"
        ],
        "name:en": "Taff",
        "id": 1130527
      }
    },
    {
      "geometry": {
        "type": "Point",
        "coordinates": [
          -1.5,
          35.25
        ]
      },
      "type": "Feature",
      "properties": {
        "hierarchy": [
          "tgn:1130528",
          "tgn:7001242",
          "tgn:7593624",
          "tgn:7016752",
          "tgn:7029392"
        ],
        "placetype": [
          "aat:300008707"
        ],
        "id": 1130528,
        "name:xx": "Tafna"
      }
    },
    {
      "geometry": {
        "type": "Point",
        "coordinates": [
          -159.2,
          65.3833
        ]
      },
      "type": "Feature",
      "properties": {
        "hierarchy": [
          "tgn:1130529",
          "tgn:7006450",
          "tgn:1000001",
          "tgn:7012149",
          "tgn:7029392"
        ],
        "placetype": [
          "aat:300008707"
        ],
        "id": 1130529,
        "name:xx": "Tagagawik"
      }
    }
  ]
}
