{
  "geometry": {
    "type": "Point",
    "coordinates": [
      -111.7167,
      37.45
    ]
  },
  "type": "Feature",
  "properties": {
    "hierarchy": [
      "tgn:2724806",
      "tgn:1000001",
      "tgn:7012149",
      "tgn:2002113",
      "tgn:7007827",
      "tgn:7029392"
    ],
    "placetype": [
      "aat:300008706"
    ],
    "id": 2724806,
    "name:xx": "Tommy Smith Creek"
  }
}
