{
  "geometry": {
    "type": "Point",
    "coordinates": [
      -69.5833,
      43.9333
    ]
  },
  "type": "Feature",
  "properties": {
    "hierarchy": [
      "tgn:2163168",
      "tgn:1000001",
      "tgn:2000925",
      "tgn:7012149",
      "tgn:7007515",
      "tgn:7029392"
    ],
    "placetype": [
      "aat:300008850"
    ],
    "id": 2163168,
    "name:xx": "Bennett Neck"
  }
}
