{
  "geometry": {
    "type": "Point",
    "coordinates": [
      -118.6167,
      37.8167
    ]
  },
  "type": "Feature",
  "properties": {
    "hierarchy": [
      "tgn:2176786",
      "tgn:1000001",
      "tgn:7012149",
      "tgn:7007157",
      "tgn:1002675",
      "tgn:7029392"
    ],
    "placetype": [
      "aat:300008798"
    ],
    "id": 2176786,
    "name:xx": "Black Mountain"
  }
}
