{
  "geometry": {
    "type": "Point",
    "coordinates": [
      9.4333,
      55.05
    ]
  },
  "type": "Feature",
  "properties": {
    "name:en": "Åbenrå",
    "hierarchy": [
      "tgn:7003423",
      "tgn:1000003",
      "tgn:7594009",
      "tgn:1000066",
      "tgn:7029392"
    ],
    "name:da": "Åbenrå",
    "name:de": "Apenrade",
    "placetype": [
      "aat:300008347",
      "aat:300008416",
      "aat:300008375"
    ],
    "id": 7003423
  }
}
