{
  "geometry": {
    "type": "Point",
    "coordinates": [
      -98.1333,
      31.8333
    ]
  },
  "type": "Feature",
  "properties": {
    "hierarchy": [
      "tgn:2688868",
      "tgn:1000001",
      "tgn:7012149",
      "tgn:2001996",
      "tgn:7007826",
      "tgn:7029392"
    ],
    "placetype": [
      "aat:300008347"
    ],
    "id": 2688868,
    "name:xx": "Spurlin"
  }
}
