{
  "geometry": {
    "type": "Point",
    "coordinates": [
      -91.5667,
      30.2833
    ]
  },
  "type": "Feature",
  "properties": {
    "hierarchy": [
      "tgn:2698309",
      "tgn:1000001",
      "tgn:7012149",
      "tgn:2000877",
      "tgn:7007256",
      "tgn:7029392"
    ],
    "placetype": [
      "aat:300008699"
    ],
    "id": 2698309,
    "name:xx": "Straight Bayou"
  }
}
