{
  "geometry": {
    "type": "Point",
    "coordinates": [
      -91.5167,
      37.1667
    ]
  },
  "type": "Feature",
  "properties": {
    "hierarchy": [
      "tgn:2438177",
      "tgn:1000001",
      "tgn:7012149",
      "tgn:2001247",
      "tgn:7007523",
      "tgn:7029392"
    ],
    "placetype": [
      "aat:300008761"
    ],
    "id": 2438177,
    "name:xx": "Kingfisher Hollow"
  }
}
