{
  "geometry": {
    "type": "Point",
    "coordinates": [
      14.8333,
      65.0833
    ]
  },
  "type": "Feature",
  "properties": {
    "hierarchy": [
      "tgn:1063226",
      "tgn:1000003",
      "tgn:7003779",
      "tgn:1000097",
      "tgn:7029392"
    ],
    "placetype": [
      "aat:300008347"
    ],
    "id": 1063226,
    "name:xx": "Klimpfjäll"
  }
}
