{
  "geometry": {
    "type": "Point",
    "coordinates": [
      34.3333,
      53.2833
    ]
  },
  "type": "Feature",
  "properties": {
    "hierarchy": [
      "tgn:1122109",
      "tgn:1000004",
      "tgn:7002435",
      "tgn:7029392"
    ],
    "placetype": [
      "aat:300008707"
    ],
    "id": 1122109,
    "name:xx": "Bolva"
  }
}
