{
  "geometry": {
    "type": "Point",
    "coordinates": [
      -82.05,
      29.6333
    ]
  },
  "type": "Feature",
  "properties": {
    "hierarchy": [
      "tgn:2243453",
      "tgn:1000001",
      "tgn:7012149",
      "tgn:7007240",
      "tgn:7029392"
    ],
    "placetype": [
      "aat:300008680"
    ],
    "id": 2243453,
    "name:xx": "Clearwater Lake"
  }
}
