{
  "geometry": {
    "type": "Point",
    "coordinates": [
      65.3833,
      35.9667
    ]
  },
  "type": "Feature",
  "properties": {
    "hierarchy": [
      "tgn:1065415",
      "tgn:7016612",
      "tgn:1000004",
      "tgn:1001248",
      "tgn:7029392"
    ],
    "placetype": [
      "aat:300008347"
    ],
    "id": 1065415,
    "name:xx": "Darz Ab"
  }
}
