{
  "type": "FeatureCollection",
  "features": [
    {
      "geometry": {
        "type": "Point",
        "coordinates": [
          -118.7167,
          35.8167
        ]
      },
      "type": "Feature",
      "properties": {
        "hierarchy": [
          "tgn:2202360",
          "tgn:1000001",
          "tgn:7012149",
          "tgn:7007157",
          "tgn:1002956",
          "tgn:7029392"
        ],
        "placetype": [
          "aat:300008798"
        ],
        "id": 2202360,
        "name:xx": "Buck Peak"
      }
    },
    {
      "geometry": {
        "type": "Point",
        "coordinates": [
          -107.45,
          40.4333
        ]
      },
      "type": "Feature",
      "properties": {
        "hierarchy": [
          "tgn:2202361",
          "tgn:1000001",
          "tgn:7012149",
          "tgn:2000232",
          "tgn:7007158",
          "tgn:7029392"
        ],
        "placetype": [
          "aat:300008798"
        ],
        "id": 2202361,
        "name:xx": "Buck Peak"
      }
    },
    {
      "geometry": {
        "type": "Point",
        "coordinates": [
          -112.05,
          42.1833
        ]
      },
      "type": "Feature",
      "properties": {
        "hierarchy": [
          "tgn:2202362",
          "tgn:1000001",
          "tgn:7012149",
          "tgn:2000472",
          "tgn:7007250",
          "tgn:7029392"
        ],
        "placetype": [
          "aat:300008798"
        ],
        "id": 2202362,
        "name:xx": "Buck Peak"
      }
    },
    {
      "geometry": {
        "type": "Point",
        "coordinates": [
          -112.7833,
          42.3333
        ]
      },
      "type": "Feature",
      "properties": {
        "hierarchy": [
          "tgn:2202363",
          "tgn:1000001",
          "tgn:7012149",
          "tgn:2000490",
          "tgn:7007250",
          "tgn:7029392"
        ],
        "placetype": [
          "aat:300008798"
        ],
        "id": 2202363,
        "name:xx": "Buck Peak"
      }
    },
    {
      "geometry": {
        "type": "Point",
        "coordinates": [
          -107.1167,
          33.9667
        ]
      },
      "type": "Feature",
      "properties": {
        "hierarchy": [
          "tgn:2202364",
          "tgn:1000001",
          "tgn:7012149",
          "tgn:2001456",
          "tgn:7007566",
          "tgn:7029392"
        ],
        "placetype": [
          "aat:300008798"
        ],
        "id": 2202364,
        "name:xx": "Buck Peak"
      }
    },
    {
      "geometry": {
        "type": "Point",
        "coordinates": [
          -123.4,
          42.1167
        ]
      },
      "type": "Feature",
      "properties": {
        "hierarchy": [
          "tgn:2202365",
          "tgn:1000001",
          "tgn:7012149",
          "tgn:2001713",
          "tgn:7007708",
          "tgn:7029392"
        ],
        "placetype": [
          "aat:300008798"
        ],
        "id": 2202365,
        "name:xx": "Buck Peak"
      }
    },
    {
      "geometry": {
        "type": "Point",
        "coordinates": [
          -122.1167,
          42.2667
        ]
      },
      "type": "Feature",
      "properties": {
        "hierarchy": [
          "tgn:2202366",
          "tgn:1000001",
          "tgn:7012149",
          "tgn:2001714",
          "tgn:7007708",
          "tgn:7029392"
        ],
        "placetype": [
          "aat:300008798"
        ],
        "id": 2202366,
        "name:xx": "Buck Peak"
      }
    },
    {
      "geometry": {
        "type": "Point",
        "coordinates": [
          -123.0833,
          43.1667
        ]
      },
      "type": "Feature",
      "properties": {
        "hierarchy": [
          "tgn:2202367",
          "tgn:1000001",
          "tgn:7012149",
          "tgn:2001706",
          "tgn:7007708",
          "tgn:7029392"
        ],
        "placetype": [
          "aat:300008798"
        ],
        "id": 2202367,
        "name:xx": "Buck Peak"
      }
    },
    {
      "geometry": {
        "type": "Point",
        "coordinates": [
          -123.4833,
          44.3667
        ]
      },
      "type": "Feature",
      "properties": {
        "hierarchy": [
          "tgn:2202368",
          "tgn:1000001",
          "tgn:2001701",
          "tgn:7012149",
          "tgn:7007708",
          "tgn:7029392"
        ],
        "placetype": [
          "aat:300008798"
        ],
        "id": 2202368,
        "name:xx": "Buck Peak"
      }
    },
    {
      "geometry": {
        "type": "Point",
        "coordinates": [
          -121.85,
          45.4833
        ]
      },
      "type": "Feature",
      "properties": {
        "hierarchy": [
          "tgn:2202369",
          "tgn:1000001",
          "tgn:7012149",
          "tgn:7007708",
          "tgn:7029392"
        ],
        "placetype": [
          "aat:300008798"
        ],
        "id": 2202369,
        "name:xx": "Buck Peak"
      }
    }
  ]
}
