{
  "geometry": {
    "type": "Point",
    "coordinates": [
      -86.8667,
      41.5833
    ]
  },
  "type": "Feature",
  "properties": {
    "hierarchy": [
      "tgn:2396403",
      "tgn:1000001",
      "tgn:7012149",
      "tgn:1002561",
      "tgn:7007252",
      "tgn:7029392"
    ],
    "placetype": [
      "aat:300008347"
    ],
    "id": 2396403,
    "name:xx": "Holmesville"
  }
}
