{
  "geometry": {
    "type": "Point",
    "coordinates": [
      -92.9167,
      34.1333
    ]
  },
  "type": "Feature",
  "properties": {
    "hierarchy": [
      "tgn:2772434",
      "tgn:1000001",
      "tgn:7016172",
      "tgn:2000114",
      "tgn:7012149",
      "tgn:7029392"
    ],
    "placetype": [
      "aat:300008699"
    ],
    "id": 2772434,
    "name:xx": "Williams Branch"
  }
}
