{
  "type": "FeatureCollection",
  "features": [
    {
      "geometry": {
        "type": "Point",
        "coordinates": [
          -4.233333,
          57.2
        ]
      },
      "type": "Feature",
      "properties": {
        "hierarchy": [
          "tgn:7460140",
          "tgn:7002444",
          "tgn:1000003",
          "tgn:7008082",
          "tgn:7008591",
          "tgn:7029392"
        ],
        "placetype": [
          "aat:300008795"
        ],
        "name:en": "Odhar, Càrn",
        "id": 7460140
      }
    },
    {
      "geometry": {
        "type": "Point",
        "coordinates": [
          -4.7,
          56.466667
        ]
      },
      "type": "Feature",
      "properties": {
        "hierarchy": [
          "tgn:7460141",
          "tgn:7019094",
          "tgn:7002444",
          "tgn:1000003",
          "tgn:7008591",
          "tgn:7029392"
        ],
        "placetype": [
          "aat:300008795"
        ],
        "name:en": "Odhar, Beinn",
        "id": 7460141
      }
    },
    {
      "geometry": {
        "type": "Point",
        "coordinates": [
          -4.433333,
          57.133333
        ]
      },
      "type": "Feature",
      "properties": {
        "hierarchy": [
          "tgn:7460142",
          "tgn:7002444",
          "tgn:1000003",
          "tgn:7008082",
          "tgn:7008591",
          "tgn:7029392"
        ],
        "placetype": [
          "aat:300008699"
        ],
        "name:en": "Odhar, Allt",
        "id": 7460142
      }
    },
    {
      "geometry": {
        "type": "Point",
        "coordinates": [
          -0.583333,
          52.2
        ]
      },
      "type": "Feature",
      "properties": {
        "hierarchy": [
          "tgn:7460143",
          "tgn:7002445",
          "tgn:7008103",
          "tgn:1000003",
          "tgn:7008591",
          "tgn:7029392"
        ],
        "placetype": [
          "aat:300008347"
        ],
        "name:en": "Odell",
        "id": 7460143
      }
    },
    {
      "geometry": {
        "type": "Point",
        "coordinates": [
          -1.2,
          51.816667
        ]
      },
      "type": "Feature",
      "properties": {
        "hierarchy": [
          "tgn:7460144",
          "tgn:7002445",
          "tgn:1000003",
          "tgn:7008168",
          "tgn:7008591",
          "tgn:7029392"
        ],
        "placetype": [
          "aat:300008347"
        ],
        "name:en": "Oddington",
        "id": 7460144
      }
    },
    {
      "geometry": {
        "type": "Point",
        "coordinates": [
          -2.8,
          58.933333
        ]
      },
      "type": "Feature",
      "properties": {
        "hierarchy": [
          "tgn:7460145",
          "tgn:7002444",
          "tgn:1000003",
          "tgn:7009907",
          "tgn:7008591",
          "tgn:7029392"
        ],
        "placetype": [
          "aat:300386846"
        ],
        "name:en": "Od, Point of",
        "id": 7460145
      }
    },
    {
      "geometry": {
        "type": "Point",
        "coordinates": [
          -6.416667,
          55.7
        ]
      },
      "type": "Feature",
      "properties": {
        "hierarchy": [
          "tgn:7460146",
          "tgn:7019094",
          "tgn:7002444",
          "tgn:1000003",
          "tgn:7008591",
          "tgn:7029392"
        ],
        "placetype": [
          "aat:300004792"
        ],
        "name:en": "Octafad",
        "id": 7460146
      }
    }
  ]
}
