{
  "geometry": {
    "type": "Point",
    "coordinates": [
      11.85,
      49.65
    ]
  },
  "type": "Feature",
  "properties": {
    "hierarchy": [
      "tgn:7128423",
      "tgn:7003669",
      "tgn:1000003",
      "tgn:7000084",
      "tgn:7029392"
    ],
    "placetype": [
      "aat:300008863"
    ],
    "id": 7128423,
    "name:xx": "Obere Saugräben"
  }
}
