{
  "type": "FeatureCollection",
  "features": [
    {
      "geometry": {
        "type": "Point",
        "coordinates": [
          118,
          40.05
        ]
      },
      "type": "Feature",
      "properties": {
        "hierarchy": [
          "tgn:1139870",
          "tgn:1000004",
          "tgn:7002077",
          "tgn:1000111",
          "tgn:7029392"
        ],
        "placetype": [
          "aat:300008347"
        ],
        "id": 1139870,
        "name:xx": "Xindianzi"
      }
    },
    {
      "geometry": {
        "type": "Point",
        "coordinates": [
          116.8667,
          24.05
        ]
      },
      "type": "Feature",
      "properties": {
        "hierarchy": [
          "tgn:1139871",
          "tgn:1000004",
          "tgn:7005232",
          "tgn:1000111",
          "tgn:7029392"
        ],
        "placetype": [
          "aat:300008347"
        ],
        "id": 1139871,
        "name:xx": "Xinfeng"
      }
    },
    {
      "geometry": {
        "type": "Point",
        "coordinates": [
          114.9667,
          25.45
        ]
      },
      "type": "Feature",
      "properties": {
        "hierarchy": [
          "tgn:1139872",
          "tgn:1000004",
          "tgn:7002082",
          "tgn:1000111",
          "tgn:7029392"
        ],
        "placetype": [
          "aat:300008347"
        ],
        "id": 1139872,
        "name:xx": "Xinfeng"
      }
    },
    {
      "geometry": {
        "type": "Point",
        "coordinates": [
          116.55,
          27.4333
        ]
      },
      "type": "Feature",
      "properties": {
        "hierarchy": [
          "tgn:1139873",
          "tgn:1000004",
          "tgn:7002082",
          "tgn:1000111",
          "tgn:7029392"
        ],
        "placetype": [
          "aat:300008347"
        ],
        "id": 1139873,
        "name:xx": "Xinfeng"
      }
    },
    {
      "geometry": {
        "type": "Point",
        "coordinates": [
          120.9167,
          30.7167
        ]
      },
      "type": "Feature",
      "properties": {
        "hierarchy": [
          "tgn:1139874",
          "tgn:1000004",
          "tgn:7002076",
          "tgn:1000111",
          "tgn:7029392"
        ],
        "placetype": [
          "aat:300008347"
        ],
        "id": 1139874,
        "name:xx": "Xinfeng"
      }
    },
    {
      "geometry": {
        "type": "Point",
        "coordinates": [
          118.6833,
          31.1333
        ]
      },
      "type": "Feature",
      "properties": {
        "hierarchy": [
          "tgn:1139875",
          "tgn:7002075",
          "tgn:1000004",
          "tgn:1000111",
          "tgn:7029392"
        ],
        "placetype": [
          "aat:300008347"
        ],
        "id": 1139875,
        "name:xx": "Xinfeng"
      }
    },
    {
      "geometry": {
        "type": "Point",
        "coordinates": [
          119.5667,
          32.0833
        ]
      },
      "type": "Feature",
      "properties": {
        "hierarchy": [
          "tgn:1139876",
          "tgn:1000004",
          "tgn:7002081",
          "tgn:1000111",
          "tgn:7029392"
        ],
        "placetype": [
          "aat:300008347"
        ],
        "id": 1139876,
        "name:xx": "Xinfeng"
      }
    },
    {
      "geometry": {
        "type": "Point",
        "coordinates": [
          120.5,
          33.3167
        ]
      },
      "type": "Feature",
      "properties": {
        "hierarchy": [
          "tgn:1139877",
          "tgn:1000004",
          "tgn:7002081",
          "tgn:1000111",
          "tgn:7029392"
        ],
        "placetype": [
          "aat:300008347"
        ],
        "id": 1139877,
        "name:xx": "Xinfeng"
      }
    },
    {
      "geometry": {
        "type": "Point",
        "coordinates": [
          121.7,
          48.8
        ]
      },
      "type": "Feature",
      "properties": {
        "hierarchy": [
          "tgn:1139878",
          "tgn:1000004",
          "tgn:7001838",
          "tgn:1000111",
          "tgn:7029392"
        ],
        "placetype": [
          "aat:300008347"
        ],
        "id": 1139878,
        "name:xx": "Xing'anling"
      }
    },
    {
      "geometry": {
        "type": "Point",
        "coordinates": [
          106.3333,
          30.6
        ]
      },
      "type": "Feature",
      "properties": {
        "hierarchy": [
          "tgn:1139879",
          "tgn:1000004",
          "tgn:7024355",
          "tgn:1000111",
          "tgn:7029392"
        ],
        "placetype": [
          "aat:300008347"
        ],
        "id": 1139879,
        "name:xx": "Xinglong"
      }
    }
  ]
}
