{
  "type": "FeatureCollection",
  "features": [
    {
      "geometry": {
        "type": "Point",
        "coordinates": [
          -4.033333,
          52.433333
        ]
      },
      "type": "Feature",
      "properties": {
        "hierarchy": [
          "tgn:7464880",
          "tgn:7002443",
          "tgn:7017242",
          "tgn:1000003",
          "tgn:7008591",
          "tgn:7029392"
        ],
        "placetype": [
          "aat:300008347"
        ],
        "name:en": "Bow Street",
        "id": 7464880
      }
    },
    {
      "geometry": {
        "type": "Point",
        "coordinates": [
          -2,
          55.666667
        ]
      },
      "type": "Feature",
      "properties": {
        "hierarchy": [
          "tgn:7464881",
          "tgn:7002445",
          "tgn:1000003",
          "tgn:7008165",
          "tgn:7008591",
          "tgn:7029392"
        ],
        "placetype": [
          "aat:300008347"
        ],
        "name:en": "Bowsden",
        "id": 7464881
      }
    },
    {
      "geometry": {
        "type": "Point",
        "coordinates": [
          -4.483333,
          55.916667
        ]
      },
      "type": "Feature",
      "properties": {
        "hierarchy": [
          "tgn:7464886",
          "tgn:7002444",
          "tgn:1000003",
          "tgn:7019095",
          "tgn:7008591",
          "tgn:7029392"
        ],
        "placetype": [
          "aat:300008347"
        ],
        "name:en": "Bowling",
        "id": 7464886
      }
    },
    {
      "geometry": {
        "type": "Point",
        "coordinates": [
          -2.866667,
          55.65
        ]
      },
      "type": "Feature",
      "properties": {
        "hierarchy": [
          "tgn:7464887",
          "tgn:7002444",
          "tgn:1000003",
          "tgn:7008072",
          "tgn:7008591",
          "tgn:7029392"
        ],
        "placetype": [
          "aat:300007783"
        ],
        "name:en": "Bowland Station",
        "id": 7464887
      }
    },
    {
      "geometry": {
        "type": "Point",
        "coordinates": [
          -2.883333,
          54.283333
        ]
      },
      "type": "Feature",
      "properties": {
        "hierarchy": [
          "tgn:7464888",
          "tgn:7002445",
          "tgn:1000003",
          "tgn:7008117",
          "tgn:7008591",
          "tgn:7029392"
        ],
        "placetype": [
          "aat:300008347"
        ],
        "name:en": "Bowland Bridge",
        "id": 7464888
      }
    }
  ]
}
