{
  "type": "FeatureCollection",
  "features": [
    {
      "geometry": {
        "type": "Point",
        "coordinates": [
          169.416667,
          -43.8
        ]
      },
      "type": "Feature",
      "properties": {
        "hierarchy": [
          "tgn:7511530",
          "tgn:1009227",
          "tgn:1000226",
          "tgn:1000006",
          "tgn:7016850",
          "tgn:7029392"
        ],
        "placetype": [
          "aat:300008798"
        ],
        "name:en": "Mariners Peak",
        "id": 7511530
      }
    },
    {
      "geometry": {
        "type": "Point",
        "coordinates": [
          175.683333,
          -40.466667
        ]
      },
      "type": "Feature",
      "properties": {
        "hierarchy": [
          "tgn:7511531",
          "tgn:1008380",
          "tgn:7520093",
          "tgn:1000226",
          "tgn:1000006",
          "tgn:7029392"
        ],
        "placetype": [
          "aat:300008795"
        ],
        "name:en": "Marima",
        "id": 7511531
      }
    },
    {
      "geometry": {
        "type": "Point",
        "coordinates": [
          168.05,
          -44.766667
        ]
      },
      "type": "Feature",
      "properties": {
        "hierarchy": [
          "tgn:7511533",
          "tgn:1009227",
          "tgn:1000226",
          "tgn:7016822",
          "tgn:1000006",
          "tgn:7029392"
        ],
        "placetype": [
          "aat:300008680"
        ],
        "name:en": "Marianette, Lake",
        "id": 7511533
      }
    },
    {
      "geometry": {
        "type": "Point",
        "coordinates": [
          168.05,
          -44.766667
        ]
      },
      "type": "Feature",
      "properties": {
        "hierarchy": [
          "tgn:7511534",
          "tgn:1009227",
          "tgn:1000226",
          "tgn:7016822",
          "tgn:1000006",
          "tgn:7029392"
        ],
        "placetype": [
          "aat:300008680"
        ],
        "name:en": "Mariana, Lake",
        "id": 7511534
      }
    },
    {
      "geometry": {
        "type": "Point",
        "coordinates": [
          168.066667,
          -44.783333
        ]
      },
      "type": "Feature",
      "properties": {
        "hierarchy": [
          "tgn:7511535",
          "tgn:1009227",
          "tgn:1000226",
          "tgn:7016822",
          "tgn:1000006",
          "tgn:7029392"
        ],
        "placetype": [
          "aat:300008680"
        ],
        "name:en": "Marian, Lake",
        "id": 7511535
      }
    },
    {
      "geometry": {
        "type": "Point",
        "coordinates": [
          172.633333,
          -42.366667
        ]
      },
      "type": "Feature",
      "properties": {
        "hierarchy": [
          "tgn:7511536",
          "tgn:1009227",
          "tgn:7001866",
          "tgn:1000226",
          "tgn:1000006",
          "tgn:7029392"
        ],
        "placetype": [
          "aat:300008795"
        ],
        "name:en": "Maria, Mount",
        "id": 7511536
      }
    },
    {
      "geometry": {
        "type": "Point",
        "coordinates": [
          167.5,
          -45.016667
        ]
      },
      "type": "Feature",
      "properties": {
        "hierarchy": [
          "tgn:7511537",
          "tgn:1009227",
          "tgn:1000226",
          "tgn:7016822",
          "tgn:1000006",
          "tgn:7029392"
        ],
        "placetype": [
          "aat:300008798"
        ],
        "name:en": "Marguerite Peak",
        "id": 7511537
      }
    },
    {
      "geometry": {
        "type": "Point",
        "coordinates": [
          167.9,
          -45.35
        ]
      },
      "type": "Feature",
      "properties": {
        "hierarchy": [
          "tgn:7511538",
          "tgn:1009227",
          "tgn:1000226",
          "tgn:7016822",
          "tgn:1000006",
          "tgn:7029392"
        ],
        "placetype": [
          "aat:300008863"
        ],
        "name:en": "Margin Forest",
        "id": 7511538
      }
    },
    {
      "geometry": {
        "type": "Point",
        "coordinates": [
          166.9,
          -45.95
        ]
      },
      "type": "Feature",
      "properties": {
        "hierarchy": [
          "tgn:7511539",
          "tgn:1009227",
          "tgn:1000226",
          "tgn:7016822",
          "tgn:1000006",
          "tgn:7029392"
        ],
        "placetype": [
          "aat:300008699"
        ],
        "name:en": "Margaret Stream",
        "id": 7511539
      }
    }
  ]
}
