{
  "geometry": {
    "type": "Point",
    "coordinates": [
      -88.8167,
      33.4333
    ]
  },
  "type": "Feature",
  "properties": {
    "hierarchy": [
      "tgn:2001138",
      "tgn:1000001",
      "tgn:7012149",
      "tgn:7007522",
      "tgn:7029392"
    ],
    "placetype": [
      "aat:300387145",
      "aat:300000771"
    ],
    "id": 2001138,
    "name:xx": "Oktibbeha"
  }
}
