{
  "type": "FeatureCollection",
  "features": [
    {
      "geometry": {
        "type": "Point",
        "coordinates": [
          -109.55,
          28.9
        ]
      },
      "type": "Feature",
      "properties": {
        "hierarchy": [
          "tgn:7386030",
          "tgn:1000001",
          "tgn:1001960",
          "tgn:7005560",
          "tgn:7029392"
        ],
        "placetype": [
          "aat:300008795"
        ],
        "id": 7386030,
        "name:xx": "Pelón, Cerro"
      }
    },
    {
      "geometry": {
        "type": "Point",
        "coordinates": [
          -104.45,
          24.416667
        ]
      },
      "type": "Feature",
      "properties": {
        "hierarchy": [
          "tgn:7386031",
          "tgn:7005583",
          "tgn:1000001",
          "tgn:7005560",
          "tgn:7029392"
        ],
        "placetype": [
          "aat:300008795"
        ],
        "id": 7386031,
        "name:xx": "Pelon, Cerro"
      }
    },
    {
      "geometry": {
        "type": "Point",
        "coordinates": [
          -102.716667,
          20.916667
        ]
      },
      "type": "Feature",
      "properties": {
        "hierarchy": [
          "tgn:7386032",
          "tgn:7005586",
          "tgn:1000001",
          "tgn:7005560",
          "tgn:7029392"
        ],
        "placetype": [
          "aat:300008795"
        ],
        "id": 7386032,
        "name:xx": "Pelon, Cerro"
      }
    },
    {
      "geometry": {
        "type": "Point",
        "coordinates": [
          -105.033333,
          20.183333
        ]
      },
      "type": "Feature",
      "properties": {
        "hierarchy": [
          "tgn:7386033",
          "tgn:7005586",
          "tgn:1000001",
          "tgn:7005560",
          "tgn:7029392"
        ],
        "placetype": [
          "aat:300008795"
        ],
        "id": 7386033,
        "name:xx": "Pelon, Cerro"
      }
    },
    {
      "geometry": {
        "type": "Point",
        "coordinates": [
          -104.733333,
          19.6
        ]
      },
      "type": "Feature",
      "properties": {
        "hierarchy": [
          "tgn:7386034",
          "tgn:7005586",
          "tgn:1000001",
          "tgn:7005560",
          "tgn:7029392"
        ],
        "placetype": [
          "aat:300008795"
        ],
        "id": 7386034,
        "name:xx": "Pelon, Cerro"
      }
    },
    {
      "geometry": {
        "type": "Point",
        "coordinates": [
          -94.716667,
          18.283333
        ]
      },
      "type": "Feature",
      "properties": {
        "hierarchy": [
          "tgn:7386035",
          "tgn:1000001",
          "tgn:7005599",
          "tgn:7005560",
          "tgn:7029392"
        ],
        "placetype": [
          "aat:300008795"
        ],
        "id": 7386035,
        "name:xx": "Pelón, Cerro"
      }
    },
    {
      "geometry": {
        "type": "Point",
        "coordinates": [
          -93.9,
          17.6
        ]
      },
      "type": "Feature",
      "properties": {
        "hierarchy": [
          "tgn:7386036",
          "tgn:1000001",
          "tgn:7005599",
          "tgn:7005560",
          "tgn:7029392"
        ],
        "placetype": [
          "aat:300008795"
        ],
        "id": 7386036,
        "name:xx": "Pelón, Cerro"
      }
    },
    {
      "geometry": {
        "type": "Point",
        "coordinates": [
          -107.15,
          28.35
        ]
      },
      "type": "Feature",
      "properties": {
        "hierarchy": [
          "tgn:7386037",
          "tgn:7005581",
          "tgn:1000001",
          "tgn:7005560",
          "tgn:7029392"
        ],
        "placetype": [
          "aat:300008777"
        ],
        "id": 7386037,
        "name:xx": "Pelon, Cerro"
      }
    },
    {
      "geometry": {
        "type": "Point",
        "coordinates": [
          -108.890833,
          26.258056
        ]
      },
      "type": "Feature",
      "properties": {
        "hierarchy": [
          "tgn:7386038",
          "tgn:1000001",
          "tgn:7005595",
          "tgn:7005560",
          "tgn:7029392"
        ],
        "placetype": [
          "aat:300008777"
        ],
        "id": 7386038,
        "name:xx": "Pelon, Cerro"
      }
    },
    {
      "geometry": {
        "type": "Point",
        "coordinates": [
          -104.266667,
          20.2
        ]
      },
      "type": "Feature",
      "properties": {
        "hierarchy": [
          "tgn:7386039",
          "tgn:7005586",
          "tgn:1000001",
          "tgn:7005560",
          "tgn:7029392"
        ],
        "placetype": [
          "aat:300008777"
        ],
        "id": 7386039,
        "name:xx": "Pelon, Cerro"
      }
    }
  ]
}
