{
  "geometry": {
    "type": "Point",
    "coordinates": [
      -97.2333,
      29.4333
    ]
  },
  "type": "Feature",
  "properties": {
    "hierarchy": [
      "tgn:2626193",
      "tgn:1000001",
      "tgn:7012149",
      "tgn:1002414",
      "tgn:7007826",
      "tgn:7029392"
    ],
    "placetype": [
      "aat:300008706"
    ],
    "id": 2626193,
    "name:xx": "Rocky Creek"
  }
}
