{
  "type": "FeatureCollection",
  "features": [
    {
      "geometry": {
        "type": "Point",
        "coordinates": [
          -106.2,
          39.2333
        ]
      },
      "type": "Feature",
      "properties": {
        "hierarchy": [
          "tgn:2304570",
          "tgn:1000001",
          "tgn:7012149",
          "tgn:2000224",
          "tgn:7007158",
          "tgn:7029392"
        ],
        "placetype": [
          "aat:300008798"
        ],
        "id": 2304570,
        "name:xx": "East Ball Mountain"
      }
    },
    {
      "geometry": {
        "type": "Point",
        "coordinates": [
          -68.8,
          44.85
        ]
      },
      "type": "Feature",
      "properties": {
        "hierarchy": [
          "tgn:2304571",
          "tgn:1000001",
          "tgn:7012149",
          "tgn:2000927",
          "tgn:7007515",
          "tgn:7029392"
        ],
        "placetype": [
          "aat:300008347"
        ],
        "id": 2304571,
        "name:xx": "East Bangor"
      }
    },
    {
      "geometry": {
        "type": "Point",
        "coordinates": [
          -83.05,
          29.0667
        ]
      },
      "type": "Feature",
      "properties": {
        "hierarchy": [
          "tgn:2304572",
          "tgn:1000001",
          "tgn:7012149",
          "tgn:2000277",
          "tgn:7007240",
          "tgn:7029392"
        ],
        "placetype": [
          "aat:300132348"
        ],
        "id": 2304572,
        "name:xx": "East Bank"
      }
    },
    {
      "geometry": {
        "type": "Point",
        "coordinates": [
          -73.9833,
          40.5333
        ]
      },
      "type": "Feature",
      "properties": {
        "hierarchy": [
          "tgn:2304573",
          "tgn:1000001",
          "tgn:7012149",
          "tgn:7007568",
          "tgn:7029392"
        ],
        "placetype": [
          "aat:300132348"
        ],
        "id": 2304573,
        "name:xx": "East Bank"
      }
    },
    {
      "geometry": {
        "type": "Point",
        "coordinates": [
          -79.1333,
          33.15
        ]
      },
      "type": "Feature",
      "properties": {
        "hierarchy": [
          "tgn:2304574",
          "tgn:1000001",
          "tgn:2001746",
          "tgn:7012149",
          "tgn:7007712",
          "tgn:7029392"
        ],
        "placetype": [
          "aat:300132348"
        ],
        "id": 2304574,
        "name:xx": "East Bank"
      }
    },
    {
      "geometry": {
        "type": "Point",
        "coordinates": [
          -88.0333,
          30.2
        ]
      },
      "type": "Feature",
      "properties": {
        "hierarchy": [
          "tgn:2304575",
          "tgn:2000001",
          "tgn:7002659",
          "tgn:1000001",
          "tgn:7012149",
          "tgn:7029392"
        ],
        "placetype": [
          "aat:300132348"
        ],
        "id": 2304575,
        "name:xx": "East Banks"
      }
    },
    {
      "geometry": {
        "type": "Point",
        "coordinates": [
          -106.35,
          41.4
        ]
      },
      "type": "Feature",
      "properties": {
        "hierarchy": [
          "tgn:2304576",
          "tgn:1000001",
          "tgn:2002368",
          "tgn:7012149",
          "tgn:7007923",
          "tgn:7029392"
        ],
        "placetype": [
          "aat:300008680"
        ],
        "id": 2304576,
        "name:xx": "East Banner Lake"
      }
    },
    {
      "geometry": {
        "type": "Point",
        "coordinates": [
          -82.5,
          36.15
        ]
      },
      "type": "Feature",
      "properties": {
        "hierarchy": [
          "tgn:2304577",
          "tgn:1000001",
          "tgn:7012149",
          "tgn:2001922",
          "tgn:7007825",
          "tgn:7029392"
        ],
        "placetype": [
          "aat:300000390"
        ],
        "id": 2304577,
        "name:xx": "East Baptist Hollow Mine"
      }
    },
    {
      "geometry": {
        "type": "Point",
        "coordinates": [
          -85.4,
          37.8167
        ]
      },
      "type": "Feature",
      "properties": {
        "hierarchy": [
          "tgn:2304578",
          "tgn:1000001",
          "tgn:7012149",
          "tgn:2000833",
          "tgn:7007255",
          "tgn:7029392"
        ],
        "placetype": [
          "aat:300008347"
        ],
        "id": 2304578,
        "name:xx": "East Bardstown"
      }
    },
    {
      "geometry": {
        "type": "Point",
        "coordinates": [
          -68.4333,
          44.2167
        ]
      },
      "type": "Feature",
      "properties": {
        "hierarchy": [
          "tgn:2304579",
          "tgn:1000001",
          "tgn:2000922",
          "tgn:7012149",
          "tgn:7007515",
          "tgn:7029392"
        ],
        "placetype": [
          "aat:300008791"
        ],
        "id": 2304579,
        "name:xx": "East Barge"
      }
    }
  ]
}
