{
  "type": "FeatureCollection",
  "features": [
    {
      "geometry": {
        "type": "Point",
        "coordinates": [
          134.4,
          34.7333
        ]
      },
      "type": "Feature",
      "properties": {
        "hierarchy": [
          "tgn:1122780",
          "tgn:7016675",
          "tgn:1000004",
          "tgn:7000896",
          "tgn:1000120",
          "tgn:7029392"
        ],
        "placetype": [
          "aat:300008707"
        ],
        "id": 1122780,
        "name:xx": "Chikusa"
      }
    },
    {
      "geometry": {
        "type": "Point",
        "coordinates": [
          -122.9833,
          53.9
        ]
      },
      "type": "Feature",
      "properties": {
        "hierarchy": [
          "tgn:1122781",
          "tgn:7005735",
          "tgn:7005685",
          "tgn:1000001",
          "tgn:7029392"
        ],
        "placetype": [
          "aat:300008707"
        ],
        "id": 1122781,
        "name:xx": "Chilako"
      }
    },
    {
      "geometry": {
        "type": "Point",
        "coordinates": [
          -122.4,
          51.75
        ]
      },
      "type": "Feature",
      "properties": {
        "hierarchy": [
          "tgn:1122782",
          "tgn:7005735",
          "tgn:7005685",
          "tgn:1000001",
          "tgn:7029392"
        ],
        "placetype": [
          "aat:300008707"
        ],
        "id": 1122782,
        "name:xx": "Chilcotin"
      }
    },
    {
      "geometry": {
        "type": "Point",
        "coordinates": [
          -123.5,
          52.1333
        ]
      },
      "type": "Feature",
      "properties": {
        "hierarchy": [
          "tgn:1122784",
          "tgn:7005735",
          "tgn:7005685",
          "tgn:1000001",
          "tgn:7029392"
        ],
        "placetype": [
          "aat:300008707"
        ],
        "id": 1122784,
        "name:xx": "Chilko"
      }
    },
    {
      "geometry": {
        "type": "Point",
        "coordinates": [
          -121.9167,
          49.0833
        ]
      },
      "type": "Feature",
      "properties": {
        "hierarchy": [
          "tgn:1122786",
          "tgn:1000001",
          "tgn:7029392"
        ],
        "placetype": [
          "aat:300008707"
        ],
        "id": 1122786,
        "name:xx": "Chilliwack"
      }
    },
    {
      "geometry": {
        "type": "Point",
        "coordinates": [
          106.9833,
          51.3333
        ]
      },
      "type": "Feature",
      "properties": {
        "hierarchy": [
          "tgn:1122787",
          "tgn:1000004",
          "tgn:7002435",
          "tgn:7029392"
        ],
        "placetype": [
          "aat:300008707"
        ],
        "id": 1122787,
        "name:xx": "Khilok"
      }
    },
    {
      "geometry": {
        "type": "Point",
        "coordinates": [
          121.465909,
          25.111831
        ]
      },
      "type": "Feature",
      "properties": {
        "hierarchy": [
          "tgn:1122788",
          "tgn:1000004",
          "tgn:1009319",
          "tgn:1000141",
          "tgn:7029392"
        ],
        "placetype": [
          "aat:300008707",
          "aat:300008699"
        ],
        "id": 1122788,
        "name:xx": "Chi-lung Ho"
      }
    },
    {
      "geometry": {
        "type": "Point",
        "coordinates": [
          17.2833,
          -17.3333
        ]
      },
      "type": "Feature",
      "properties": {
        "hierarchy": [
          "tgn:1122789",
          "tgn:7001242",
          "tgn:1000836",
          "tgn:1000149",
          "tgn:7029392"
        ],
        "placetype": [
          "aat:300008707"
        ],
        "id": 1122789,
        "name:xx": "Chimpôro"
      }
    }
  ]
}
