{
  "geometry": {
    "type": "Point",
    "coordinates": [
      -93.2333,
      38.1667
    ]
  },
  "type": "Feature",
  "properties": {
    "hierarchy": [
      "tgn:2385031",
      "tgn:1000001",
      "tgn:2001173",
      "tgn:7012149",
      "tgn:7007523",
      "tgn:7029392"
    ],
    "placetype": [
      "aat:300008699"
    ],
    "id": 2385031,
    "name:xx": "Helton Branch"
  }
}
