{
  "geometry": {
    "type": "Point",
    "coordinates": [
      -112.5333,
      34.2667
    ]
  },
  "type": "Feature",
  "properties": {
    "hierarchy": [
      "tgn:2007516",
      "tgn:1000001",
      "tgn:7006451",
      "tgn:7012149",
      "tgn:2000103",
      "tgn:7029392"
    ],
    "placetype": [
      "aat:300008347"
    ],
    "id": 2007516,
    "name:xx": "Walnut Grove"
  }
}
