{
  "geometry": {
    "type": "Point",
    "coordinates": [
      31.383333,
      29.95
    ]
  },
  "type": "Feature",
  "properties": {
    "hierarchy": [
      "tgn:7533415",
      "tgn:7001242",
      "tgn:7016833",
      "tgn:1001091",
      "tgn:7029392"
    ],
    "placetype": [
      "aat:300132339"
    ],
    "name:en": "Ḩamdah, Ţal'at",
    "id": 7533415
  }
}
