{
  "geometry": {
    "type": "Point",
    "coordinates": [
      54.1667,
      36.0333
    ]
  },
  "type": "Feature",
  "properties": {
    "hierarchy": [
      "tgn:1140279",
      "tgn:1000004",
      "tgn:1001528",
      "tgn:7000231",
      "tgn:7029392"
    ],
    "placetype": [
      "aat:300008347"
    ],
    "id": 1140279,
    "name:xx": "Amīrābād"
  }
}
