{
  "geometry": {
    "type": "Point",
    "coordinates": [
      -90.55,
      43.3667
    ]
  },
  "type": "Feature",
  "properties": {
    "hierarchy": [
      "tgn:2510299",
      "tgn:1000001",
      "tgn:7012149",
      "tgn:2002349",
      "tgn:7007922",
      "tgn:7029392"
    ],
    "placetype": [
      "aat:300266640"
    ],
    "id": 2510299,
    "name:xx": "Middle Ridge"
  }
}
