{
  "geometry": {
    "type": "Point",
    "coordinates": [
      -83.2667,
      30.8833
    ]
  },
  "type": "Feature",
  "properties": {
    "hierarchy": [
      "tgn:2553385",
      "tgn:1000001",
      "tgn:7012149",
      "tgn:2000383",
      "tgn:7007248",
      "tgn:7029392"
    ],
    "placetype": [
      "aat:300008347"
    ],
    "id": 2553385,
    "name:xx": "Oak"
  }
}
