{
  "geometry": {
    "type": "Point",
    "coordinates": [
      -88.15,
      42.9167
    ]
  },
  "type": "Feature",
  "properties": {
    "hierarchy": [
      "tgn:2450320",
      "tgn:1000001",
      "tgn:7012149",
      "tgn:1003002",
      "tgn:7007922",
      "tgn:7029392"
    ],
    "placetype": [
      "aat:300008680"
    ],
    "id": 2450320,
    "name:xx": "Linie Lac"
  }
}
