{
  "type": "FeatureCollection",
  "features": [
    {
      "geometry": {
        "type": "Point",
        "coordinates": [
          30.627778,
          31.295833
        ]
      },
      "type": "Feature",
      "properties": {
        "hierarchy": [
          "tgn:7531870",
          "tgn:7001242",
          "tgn:7016833",
          "tgn:1001335",
          "tgn:7029392"
        ],
        "placetype": [
          "aat:300008347"
        ],
        "name:en": "'Izbat Mas'ūd Shukrī",
        "id": 7531870
      }
    },
    {
      "geometry": {
        "type": "Point",
        "coordinates": [
          30.582999,
          31.298581
        ]
      },
      "type": "Feature",
      "properties": {
        "hierarchy": [
          "tgn:7531871",
          "tgn:7001242",
          "tgn:7016833",
          "tgn:1001335",
          "tgn:7029392"
        ],
        "placetype": [
          "aat:300008347"
        ],
        "name:en": "'Izbat an Nawāşirīyah",
        "id": 7531871
      }
    },
    {
      "geometry": {
        "type": "Point",
        "coordinates": [
          30.546073,
          31.295615
        ]
      },
      "type": "Feature",
      "properties": {
        "hierarchy": [
          "tgn:7531872",
          "tgn:7001242",
          "tgn:7016833",
          "tgn:1001335",
          "tgn:7029392"
        ],
        "placetype": [
          "aat:300008347"
        ],
        "name:en": "'Izbat Qābil",
        "id": 7531872
      }
    },
    {
      "geometry": {
        "type": "Point",
        "coordinates": [
          30.571466,
          31.258982
        ]
      },
      "type": "Feature",
      "properties": {
        "hierarchy": [
          "tgn:7531873",
          "tgn:7001242",
          "tgn:7016833",
          "tgn:1001335",
          "tgn:7029392"
        ],
        "placetype": [
          "aat:300000206"
        ],
        "name:en": "'Izbat Muḩammad Rajab",
        "id": 7531873
      }
    },
    {
      "geometry": {
        "type": "Point",
        "coordinates": [
          30.603111,
          31.254615
        ]
      },
      "type": "Feature",
      "properties": {
        "hierarchy": [
          "tgn:7531874",
          "tgn:7001242",
          "tgn:7016833",
          "tgn:1001335",
          "tgn:7029392"
        ],
        "placetype": [
          "aat:300008347"
        ],
        "name:en": "'Izbat al Wazīr",
        "id": 7531874
      }
    },
    {
      "geometry": {
        "type": "Point",
        "coordinates": [
          30.619719,
          31.258954
        ]
      },
      "type": "Feature",
      "properties": {
        "hierarchy": [
          "tgn:7531875",
          "tgn:7001242",
          "tgn:7016833",
          "tgn:1001335",
          "tgn:7029392"
        ],
        "placetype": [
          "aat:300008347"
        ],
        "name:en": "'Izbat al 'Atalah",
        "id": 7531875
      }
    },
    {
      "geometry": {
        "type": "Point",
        "coordinates": [
          30.613163,
          31.269693
        ]
      },
      "type": "Feature",
      "properties": {
        "hierarchy": [
          "tgn:7531876",
          "tgn:7001242",
          "tgn:7016833",
          "tgn:1001335",
          "tgn:7029392"
        ],
        "placetype": [
          "aat:300008347"
        ],
        "name:en": "'Izbat al Ḩājj Sa'd",
        "id": 7531876
      }
    },
    {
      "geometry": {
        "type": "Point",
        "coordinates": [
          30.597544,
          31.262196
        ]
      },
      "type": "Feature",
      "properties": {
        "hierarchy": [
          "tgn:7531877",
          "tgn:7001242",
          "tgn:7016833",
          "tgn:1001335",
          "tgn:7029392"
        ],
        "placetype": [
          "aat:300008347"
        ],
        "name:en": "'Izbat al Kawm",
        "id": 7531877
      }
    },
    {
      "geometry": {
        "type": "Point",
        "coordinates": [
          31.900244,
          30.162625
        ]
      },
      "type": "Feature",
      "properties": {
        "hierarchy": [
          "tgn:7531878",
          "tgn:7001242",
          "tgn:7016833",
          "tgn:1001110",
          "tgn:7029392"
        ],
        "placetype": [
          "aat:300007783"
        ],
        "name:en": "Maḩaţţat Wādī as Sayl",
        "id": 7531878
      }
    },
    {
      "geometry": {
        "type": "Point",
        "coordinates": [
          31.961777,
          30.20188
        ]
      },
      "type": "Feature",
      "properties": {
        "hierarchy": [
          "tgn:7531879",
          "tgn:7001242",
          "tgn:7016833",
          "tgn:1001110",
          "tgn:7029392"
        ],
        "placetype": [
          "aat:300008795"
        ],
        "name:en": "Barshah, Jabal al",
        "id": 7531879
      }
    }
  ]
}
