{
  "geometry": {
    "type": "Point",
    "coordinates": [
      -107.6833,
      36.6833
    ]
  },
  "type": "Feature",
  "properties": {
    "hierarchy": [
      "tgn:2272986",
      "tgn:1000001",
      "tgn:7012149",
      "tgn:2001452",
      "tgn:7007566",
      "tgn:7029392"
    ],
    "placetype": [
      "aat:300006191"
    ],
    "id": 2272986,
    "name:xx": "Cutter Reservoir"
  }
}
