{
  "geometry": {
    "type": "Point",
    "coordinates": [
      -95.2333,
      41.45
    ]
  },
  "type": "Feature",
  "properties": {
    "hierarchy": [
      "tgn:2362102",
      "tgn:1000001",
      "tgn:7012149",
      "tgn:2000638",
      "tgn:7007253",
      "tgn:7029392"
    ],
    "placetype": [
      "aat:300008706"
    ],
    "id": 2362102,
    "name:xx": "Graybill Creek"
  }
}
