{
  "geometry": {
    "type": "Point",
    "coordinates": [
      -78.95,
      39.9167
    ]
  },
  "type": "Feature",
  "properties": {
    "hierarchy": [
      "tgn:2697637",
      "tgn:1000001",
      "tgn:7012149",
      "tgn:7007710",
      "tgn:7029392"
    ],
    "placetype": [
      "aat:300008707"
    ],
    "id": 2697637,
    "name:xx": "Stonycreek River"
  }
}
