{
  "type": "FeatureCollection",
  "features": [
    {
      "geometry": {
        "type": "Point",
        "coordinates": [
          -117.5333,
          33.6167
        ]
      },
      "type": "Feature",
      "properties": {
        "hierarchy": [
          "tgn:2269470",
          "tgn:1000001",
          "tgn:7012149",
          "tgn:7007157",
          "tgn:1002748",
          "tgn:7029392"
        ],
        "placetype": [
          "aat:300008697"
        ],
        "id": 2269470,
        "name:xx": "Crow Spring"
      }
    },
    {
      "geometry": {
        "type": "Point",
        "coordinates": [
          -84.8,
          34.3
        ]
      },
      "type": "Feature",
      "properties": {
        "hierarchy": [
          "tgn:2269471",
          "tgn:1000001",
          "tgn:2000299",
          "tgn:7012149",
          "tgn:7007248",
          "tgn:7029392"
        ],
        "placetype": [
          "aat:300008697"
        ],
        "id": 2269471,
        "name:xx": "Crow Spring"
      }
    },
    {
      "geometry": {
        "type": "Point",
        "coordinates": [
          -92.1667,
          43.9833
        ]
      },
      "type": "Feature",
      "properties": {
        "hierarchy": [
          "tgn:2269472",
          "tgn:1000001",
          "tgn:7012149",
          "tgn:2001053",
          "tgn:7007521",
          "tgn:7029392"
        ],
        "placetype": [
          "aat:300008699"
        ],
        "id": 2269472,
        "name:xx": "Crow Spring"
      }
    },
    {
      "geometry": {
        "type": "Point",
        "coordinates": [
          -114.05,
          39.8167
        ]
      },
      "type": "Feature",
      "properties": {
        "hierarchy": [
          "tgn:2269473",
          "tgn:1000001",
          "tgn:7012149",
          "tgn:2001420",
          "tgn:7007526",
          "tgn:7029392"
        ],
        "placetype": [
          "aat:300008697"
        ],
        "id": 2269473,
        "name:xx": "Crow Spring"
      }
    },
    {
      "geometry": {
        "type": "Point",
        "coordinates": [
          -114.55,
          40.3667
        ]
      },
      "type": "Feature",
      "properties": {
        "hierarchy": [
          "tgn:2269474",
          "tgn:1000001",
          "tgn:2001411",
          "tgn:7012149",
          "tgn:7007526",
          "tgn:7029392"
        ],
        "placetype": [
          "aat:300008697"
        ],
        "id": 2269474,
        "name:xx": "Crow Spring"
      }
    },
    {
      "geometry": {
        "type": "Point",
        "coordinates": [
          -116.6833,
          39.9333
        ]
      },
      "type": "Feature",
      "properties": {
        "hierarchy": [
          "tgn:2269475",
          "tgn:1000001",
          "tgn:2001415",
          "tgn:7012149",
          "tgn:7007526",
          "tgn:7029392"
        ],
        "placetype": [
          "aat:300008697"
        ],
        "id": 2269475,
        "name:xx": "Crow Spring"
      }
    },
    {
      "geometry": {
        "type": "Point",
        "coordinates": [
          -107.8333,
          36.8333
        ]
      },
      "type": "Feature",
      "properties": {
        "hierarchy": [
          "tgn:2269476",
          "tgn:1000001",
          "tgn:7012149",
          "tgn:2001452",
          "tgn:7007566",
          "tgn:7029392"
        ],
        "placetype": [
          "aat:300008697"
        ],
        "id": 2269476,
        "name:xx": "Crow Spring"
      }
    },
    {
      "geometry": {
        "type": "Point",
        "coordinates": [
          -120.2833,
          44.3
        ]
      },
      "type": "Feature",
      "properties": {
        "hierarchy": [
          "tgn:2269477",
          "tgn:1000001",
          "tgn:2001703",
          "tgn:7012149",
          "tgn:7007708",
          "tgn:7029392"
        ],
        "placetype": [
          "aat:300008697"
        ],
        "id": 2269477,
        "name:xx": "Crow Spring"
      }
    },
    {
      "geometry": {
        "type": "Point",
        "coordinates": [
          -105.05,
          31.9833
        ]
      },
      "type": "Feature",
      "properties": {
        "hierarchy": [
          "tgn:2269478",
          "tgn:1000001",
          "tgn:7012149",
          "tgn:2002030",
          "tgn:7007826",
          "tgn:7029392"
        ],
        "placetype": [
          "aat:300008697"
        ],
        "id": 2269478,
        "name:xx": "Crow Spring"
      }
    },
    {
      "geometry": {
        "type": "Point",
        "coordinates": [
          -121.3167,
          37.2667
        ]
      },
      "type": "Feature",
      "properties": {
        "hierarchy": [
          "tgn:2269479",
          "tgn:1000001",
          "tgn:7012149",
          "tgn:7007157",
          "tgn:1002915",
          "tgn:7029392"
        ],
        "placetype": [
          "aat:300008761"
        ],
        "id": 2269479,
        "name:xx": "Crow Spring Canyon"
      }
    }
  ]
}
