{
  "geometry": {
    "type": "Point",
    "coordinates": [
      75.682836,
      28.759959
    ]
  },
  "type": "Feature",
  "properties": {
    "hierarchy": [
      "tgn:7581949",
      "tgn:1000004",
      "tgn:1001871",
      "tgn:7000198",
      "tgn:7029392"
    ],
    "placetype": [
      "aat:300008347"
    ],
    "name:en": "Talwāni",
    "id": 7581949
  }
}
