{
  "geometry": {
    "type": "Point",
    "coordinates": [
      -94.6833,
      39.9167
    ]
  },
  "type": "Feature",
  "properties": {
    "hierarchy": [
      "tgn:2713011",
      "tgn:2001168",
      "tgn:1000001",
      "tgn:7012149",
      "tgn:7007523",
      "tgn:7029392"
    ],
    "placetype": [
      "aat:300008680"
    ],
    "id": 2713011,
    "name:xx": "Taylor Lake"
  }
}
