{
  "geometry": {
    "type": "Point",
    "coordinates": [
      12.7167,
      -0.8333
    ]
  },
  "type": "Feature",
  "properties": {
    "hierarchy": [
      "tgn:1090019",
      "tgn:7001242",
      "tgn:1001728",
      "tgn:1000164",
      "tgn:7029392"
    ],
    "placetype": [
      "aat:300008347"
    ],
    "id": 1090019,
    "name:xx": "Lastoursville"
  }
}
