{
  "geometry": {
    "type": "Point",
    "coordinates": [
      -82.7167,
      32.6333
    ]
  },
  "type": "Feature",
  "properties": {
    "hierarchy": [
      "tgn:2296739",
      "tgn:1000001",
      "tgn:7012149",
      "tgn:2000374",
      "tgn:7007248",
      "tgn:7029392"
    ],
    "placetype": [
      "aat:300008706"
    ],
    "id": 2296739,
    "name:xx": "Dry Creek"
  }
}
