{
  "type": "FeatureCollection",
  "features": [
    {
      "geometry": {
        "type": "Point",
        "coordinates": [
          31.677354,
          30.849993
        ]
      },
      "type": "Feature",
      "properties": {
        "hierarchy": [
          "tgn:7528660",
          "tgn:7001242",
          "tgn:7016833",
          "tgn:1001113",
          "tgn:7029392"
        ],
        "placetype": [
          "aat:300008347"
        ],
        "id": 7528660,
        "name:xx": "'Izbat Thaljī"
      }
    },
    {
      "geometry": {
        "type": "Point",
        "coordinates": [
          31.67254,
          30.829713
        ]
      },
      "type": "Feature",
      "properties": {
        "hierarchy": [
          "tgn:7528661",
          "tgn:7001242",
          "tgn:7016833",
          "tgn:1001113",
          "tgn:7029392"
        ],
        "placetype": [
          "aat:300008347"
        ],
        "id": 7528661,
        "name:xx": "'Izbat al Ḩaḑrah"
      }
    },
    {
      "geometry": {
        "type": "Point",
        "coordinates": [
          31.667415,
          30.837513
        ]
      },
      "type": "Feature",
      "properties": {
        "hierarchy": [
          "tgn:7528662",
          "tgn:7001242",
          "tgn:7016833",
          "tgn:1001113",
          "tgn:7029392"
        ],
        "placetype": [
          "aat:300008347"
        ],
        "id": 7528662,
        "name:xx": "'Izbat Niqūlā Mandīlah"
      }
    },
    {
      "geometry": {
        "type": "Point",
        "coordinates": [
          31.643658,
          30.81915
        ]
      },
      "type": "Feature",
      "properties": {
        "hierarchy": [
          "tgn:7528663",
          "tgn:7001242",
          "tgn:7016833",
          "tgn:1001113",
          "tgn:7029392"
        ],
        "placetype": [
          "aat:300008347"
        ],
        "id": 7528663,
        "name:xx": "'Izbat Muḩammad Thābit"
      }
    },
    {
      "geometry": {
        "type": "Point",
        "coordinates": [
          31.651904,
          30.804664
        ]
      },
      "type": "Feature",
      "properties": {
        "hierarchy": [
          "tgn:7528664",
          "tgn:7001242",
          "tgn:7016833",
          "tgn:1001113",
          "tgn:7029392"
        ],
        "placetype": [
          "aat:300008347"
        ],
        "id": 7528664,
        "name:xx": "'Izbat Manşūr"
      }
    },
    {
      "geometry": {
        "type": "Point",
        "coordinates": [
          31.640939,
          30.798201
        ]
      },
      "type": "Feature",
      "properties": {
        "hierarchy": [
          "tgn:7528665",
          "tgn:7001242",
          "tgn:7016833",
          "tgn:1001113",
          "tgn:7029392"
        ],
        "placetype": [
          "aat:300008347"
        ],
        "id": 7528665,
        "name:xx": "'Izbat an Nawāf'ah"
      }
    },
    {
      "geometry": {
        "type": "Point",
        "coordinates": [
          31.63831,
          30.759335
        ]
      },
      "type": "Feature",
      "properties": {
        "hierarchy": [
          "tgn:7528666",
          "tgn:7001242",
          "tgn:7016833",
          "tgn:1001113",
          "tgn:7029392"
        ],
        "placetype": [
          "aat:300008347"
        ],
        "id": 7528666,
        "name:xx": "'Izbat Karam ad Din"
      }
    },
    {
      "geometry": {
        "type": "Point",
        "coordinates": [
          31.643302,
          30.75675
        ]
      },
      "type": "Feature",
      "properties": {
        "hierarchy": [
          "tgn:7528667",
          "tgn:7001242",
          "tgn:7016833",
          "tgn:1001113",
          "tgn:7029392"
        ],
        "placetype": [
          "aat:300008347"
        ],
        "id": 7528667,
        "name:xx": "Kafr al Baghdādī"
      }
    },
    {
      "geometry": {
        "type": "Point",
        "coordinates": [
          31.6507,
          30.761475
        ]
      },
      "type": "Feature",
      "properties": {
        "hierarchy": [
          "tgn:7528668",
          "tgn:7001242",
          "tgn:7016833",
          "tgn:1001113",
          "tgn:7029392"
        ],
        "placetype": [
          "aat:300008347"
        ],
        "id": 7528668,
        "name:xx": "'Izbat al Manshar"
      }
    },
    {
      "geometry": {
        "type": "Point",
        "coordinates": [
          31.643747,
          30.77605
        ]
      },
      "type": "Feature",
      "properties": {
        "hierarchy": [
          "tgn:7528669",
          "tgn:7001242",
          "tgn:7016833",
          "tgn:1001113",
          "tgn:7029392"
        ],
        "placetype": [
          "aat:300008347"
        ],
        "id": 7528669,
        "name:xx": "Būhā al Balad"
      }
    }
  ]
}
