{
  "geometry": {
    "type": "Point",
    "coordinates": [
      -85.6167,
      36.8667
    ]
  },
  "type": "Feature",
  "properties": {
    "hierarchy": [
      "tgn:2668506",
      "tgn:1000001",
      "tgn:7012149",
      "tgn:2000828",
      "tgn:7007255",
      "tgn:7029392"
    ],
    "placetype": [
      "aat:300008706"
    ],
    "id": 2668506,
    "name:xx": "Slate Creek"
  }
}
