{
  "type": "FeatureCollection",
  "features": [
    {
      "geometry": {
        "type": "Point",
        "coordinates": [
          -87.5667,
          41.7667
        ]
      },
      "type": "Feature",
      "properties": {
        "hierarchy": [
          "tgn:1102881",
          "tgn:1000001",
          "tgn:7013596",
          "tgn:7013649",
          "tgn:7012149",
          "tgn:7007251",
          "tgn:7029392"
        ],
        "placetype": [
          "aat:300008187"
        ],
        "id": 1102881,
        "name:xx": "Jackson Park"
      }
    },
    {
      "geometry": {
        "type": "Point",
        "coordinates": [
          -76.7833,
          37.2167
        ]
      },
      "type": "Feature",
      "properties": {
        "hierarchy": [
          "tgn:1102885",
          "tgn:1000001",
          "tgn:7012149",
          "tgn:1002511",
          "tgn:7007919",
          "tgn:7029392"
        ],
        "placetype": [
          "aat:300008187"
        ],
        "id": 1102885,
        "name:xx": "Jamestown Festival Park"
      }
    },
    {
      "geometry": {
        "type": "Point",
        "coordinates": [
          27.9833,
          -26.1667
        ]
      },
      "type": "Feature",
      "properties": {
        "hierarchy": [
          "tgn:1102886",
          "tgn:7001242",
          "tgn:7017576",
          "tgn:1000193",
          "tgn:7029392"
        ],
        "placetype": [
          "aat:300008187"
        ],
        "id": 1102886,
        "name:xx": "Jan Van Riebeeck Park"
      }
    },
    {
      "geometry": {
        "type": "Point",
        "coordinates": [
          151.05,
          -34.0167
        ]
      },
      "type": "Feature",
      "properties": {
        "hierarchy": [
          "tgn:1102887",
          "tgn:7000490",
          "tgn:1000006",
          "tgn:7001828",
          "tgn:7029392"
        ],
        "placetype": [
          "aat:300008187"
        ],
        "id": 1102887,
        "name:xx": "Jannali Park"
      }
    }
  ]
}
