{
  "type": "FeatureCollection",
  "features": [
    {
      "geometry": {
        "type": "Point",
        "coordinates": [
          -71.9333,
          -12.6333
        ]
      },
      "type": "Feature",
      "properties": {
        "hierarchy": [
          "tgn:1103790",
          "tgn:1000584",
          "tgn:1000002",
          "tgn:1000056",
          "tgn:7029392"
        ],
        "placetype": [
          "aat:300008795"
        ],
        "id": 1103790,
        "name:xx": "Atalaya, Cerro"
      }
    },
    {
      "geometry": {
        "type": "Point",
        "coordinates": [
          -104.716667,
          26.133333
        ]
      },
      "type": "Feature",
      "properties": {
        "hierarchy": [
          "tgn:1103792",
          "tgn:7005583",
          "tgn:1000001",
          "tgn:7005560",
          "tgn:7029392"
        ],
        "placetype": [
          "aat:300008795"
        ],
        "id": 1103792,
        "name:xx": "Atotonilco, Cerro"
      }
    },
    {
      "geometry": {
        "type": "Point",
        "coordinates": [
          -68.9333,
          -37.7167
        ]
      },
      "type": "Feature",
      "properties": {
        "hierarchy": [
          "tgn:1103795",
          "tgn:7006477",
          "tgn:1001450",
          "tgn:1000002",
          "tgn:7029392"
        ],
        "placetype": [
          "aat:300008795"
        ],
        "id": 1103795,
        "name:xx": "Auca Mahuida, Cerro"
      }
    },
    {
      "geometry": {
        "type": "Point",
        "coordinates": [
          12.65,
          50.45
        ]
      },
      "type": "Feature",
      "properties": {
        "hierarchy": [
          "tgn:1103796",
          "tgn:1000003",
          "tgn:7003685",
          "tgn:7000084",
          "tgn:7029392"
        ],
        "placetype": [
          "aat:300008795"
        ],
        "id": 1103796,
        "name:xx": "Auersberg"
      }
    },
    {
      "geometry": {
        "type": "Point",
        "coordinates": [
          -133.2667,
          63.2
        ]
      },
      "type": "Feature",
      "properties": {
        "hierarchy": [
          "tgn:1103798",
          "tgn:7005685",
          "tgn:1000001",
          "tgn:7005806",
          "tgn:7029392"
        ],
        "placetype": [
          "aat:300008795"
        ],
        "id": 1103798,
        "name:xx": "Australia Mountain"
      }
    },
    {
      "geometry": {
        "type": "Point",
        "coordinates": [
          13.2,
          41.966667
        ]
      },
      "type": "Feature",
      "properties": {
        "hierarchy": [
          "tgn:1103799",
          "tgn:7003138",
          "tgn:1000003",
          "tgn:7003080",
          "tgn:1000080",
          "tgn:7029392"
        ],
        "placetype": [
          "aat:300008795"
        ],
        "id": 1103799,
        "name:xx": "Autore, Monte"
      }
    }
  ]
}
