{
  "geometry": {
    "type": "Point",
    "coordinates": [
      -109.45,
      37.9333
    ]
  },
  "type": "Feature",
  "properties": {
    "hierarchy": [
      "tgn:2418100",
      "tgn:1000001",
      "tgn:7012149",
      "tgn:2002119",
      "tgn:7007827",
      "tgn:7029392"
    ],
    "placetype": [
      "aat:300008697"
    ],
    "id": 2418100,
    "name:xx": "Jackson Spring"
  }
}
