{
  "geometry": {
    "type": "Point",
    "coordinates": [
      -93.4167,
      40.0667
    ]
  },
  "type": "Feature",
  "properties": {
    "hierarchy": [
      "tgn:2272509",
      "tgn:1000001",
      "tgn:7012149",
      "tgn:2001200",
      "tgn:7007523",
      "tgn:7029392"
    ],
    "placetype": [
      "aat:300006191"
    ],
    "id": 2272509,
    "name:xx": "Curtis Upper Lake"
  }
}
