{
  "type": "FeatureCollection",
  "features": [
    {
      "geometry": {
        "type": "Point",
        "coordinates": [
          13.883333,
          52.083333
        ]
      },
      "type": "Feature",
      "properties": {
        "hierarchy": [
          "tgn:1125630",
          "tgn:1000003",
          "tgn:7003685",
          "tgn:7000084",
          "tgn:7029392"
        ],
        "placetype": [
          "aat:300266560",
          "aat:300008707"
        ],
        "id": 1125630,
        "name:xx": "Kleine Spree"
      }
    },
    {
      "geometry": {
        "type": "Point",
        "coordinates": [
          -121.4167,
          46.4833
        ]
      },
      "type": "Feature",
      "properties": {
        "hierarchy": [
          "tgn:1125631",
          "tgn:1000001",
          "tgn:7012149",
          "tgn:7007920",
          "tgn:7029392"
        ],
        "placetype": [
          "aat:300008707"
        ],
        "id": 1125631,
        "name:xx": "Klickitat"
      }
    },
    {
      "geometry": {
        "type": "Point",
        "coordinates": [
          -125.6,
          51.0833
        ]
      },
      "type": "Feature",
      "properties": {
        "hierarchy": [
          "tgn:1125632",
          "tgn:7005735",
          "tgn:7005685",
          "tgn:1000001",
          "tgn:7029392"
        ],
        "placetype": [
          "aat:300008707"
        ],
        "id": 1125632,
        "name:xx": "Klinaklini"
      }
    },
    {
      "geometry": {
        "type": "Point",
        "coordinates": [
          12.666667,
          53.233333
        ]
      },
      "type": "Feature",
      "properties": {
        "hierarchy": [
          "tgn:1125633",
          "tgn:1000003",
          "tgn:7003682",
          "tgn:7000084",
          "tgn:7029392"
        ],
        "placetype": [
          "aat:300008707",
          "aat:300008699"
        ],
        "id": 1125633,
        "name:xx": "Klingbach"
      }
    },
    {
      "geometry": {
        "type": "Point",
        "coordinates": [
          27.6,
          -28.316
        ]
      },
      "type": "Feature",
      "properties": {
        "hierarchy": [
          "tgn:1125634",
          "tgn:7001242",
          "tgn:7016562",
          "tgn:1000193",
          "tgn:7029392"
        ],
        "placetype": [
          "aat:300008707"
        ],
        "id": 1125634,
        "name:xx": "Klip"
      }
    },
    {
      "geometry": {
        "type": "Point",
        "coordinates": [
          -3.866667,
          56.233333
        ]
      },
      "type": "Feature",
      "properties": {
        "hierarchy": [
          "tgn:1125638",
          "tgn:7002444",
          "tgn:1000003",
          "tgn:7019152",
          "tgn:7008591",
          "tgn:7029392"
        ],
        "placetype": [
          "aat:300008707",
          "aat:300008699"
        ],
        "name:en": "Knaik",
        "id": 1125638
      }
    },
    {
      "geometry": {
        "type": "Point",
        "coordinates": [
          -103.2,
          47.1833
        ]
      },
      "type": "Feature",
      "properties": {
        "hierarchy": [
          "tgn:1125639",
          "tgn:1000001",
          "tgn:7012149",
          "tgn:7007705",
          "tgn:7029392"
        ],
        "placetype": [
          "aat:300008707"
        ],
        "id": 1125639,
        "name:xx": "Knife"
      }
    }
  ]
}
