{
  "geometry": {
    "type": "Point",
    "coordinates": [
      -117.25,
      44.4667
    ]
  },
  "type": "Feature",
  "properties": {
    "hierarchy": [
      "tgn:2753198",
      "tgn:7013349",
      "tgn:1000001",
      "tgn:7012149",
      "tgn:7007708",
      "tgn:7029392"
    ],
    "placetype": [
      "aat:300008697"
    ],
    "id": 2753198,
    "name:xx": "Waterbirch Spring"
  }
}
