{
  "geometry": {
    "type": "Point",
    "coordinates": [
      -86.5333,
      32.3667
    ]
  },
  "type": "Feature",
  "properties": {
    "hierarchy": [
      "tgn:2172540",
      "tgn:2000000",
      "tgn:7002659",
      "tgn:1000001",
      "tgn:7012149",
      "tgn:7029392"
    ],
    "placetype": [
      "aat:300008706"
    ],
    "id": 2172540,
    "name:xx": "Billdee Creek"
  }
}
