{
  "geometry": {
    "type": "Point",
    "coordinates": [
      -107.4833,
      43.55
    ]
  },
  "type": "Feature",
  "properties": {
    "hierarchy": [
      "tgn:2560384",
      "tgn:1000001",
      "tgn:7012149",
      "tgn:2002386",
      "tgn:7007923",
      "tgn:7029392"
    ],
    "placetype": [
      "aat:300006191"
    ],
    "id": 2560384,
    "name:xx": "Orchard Reservoir"
  }
}
