{
  "geometry": {
    "type": "Point",
    "coordinates": [
      13.9167,
      47.0667
    ]
  },
  "type": "Feature",
  "properties": {
    "hierarchy": [
      "tgn:1025962",
      "tgn:7003028",
      "tgn:1000003",
      "tgn:1000062",
      "tgn:7029392"
    ],
    "placetype": [
      "aat:300008347"
    ],
    "id": 1025962,
    "name:xx": "Predlitz"
  }
}
