{
  "geometry": {
    "type": "Point",
    "coordinates": [
      -121.8667,
      45.6667
    ]
  },
  "type": "Feature",
  "properties": {
    "hierarchy": [
      "tgn:2224423",
      "tgn:1000001",
      "tgn:7012149",
      "tgn:2001710",
      "tgn:7007708",
      "tgn:7029392"
    ],
    "placetype": [
      "aat:300008697"
    ],
    "id": 2224423,
    "name:xx": "Cascade Spring"
  }
}
