{
  "geometry": {
    "type": "Point",
    "coordinates": [
      -92.4667,
      39.8167
    ]
  },
  "type": "Feature",
  "properties": {
    "hierarchy": [
      "tgn:2141207",
      "tgn:1000001",
      "tgn:7012149",
      "tgn:1002619",
      "tgn:7007523",
      "tgn:7029392"
    ],
    "placetype": [
      "aat:300008347"
    ],
    "id": 2141207,
    "name:xx": "Axtell"
  }
}
