{
  "geometry": {
    "type": "Point",
    "coordinates": [
      -74.9333,
      42.0167
    ]
  },
  "type": "Feature",
  "properties": {
    "hierarchy": [
      "tgn:2634103",
      "tgn:1000001",
      "tgn:1002328",
      "tgn:7012149",
      "tgn:7007568",
      "tgn:7029392"
    ],
    "placetype": [
      "aat:300008699"
    ],
    "id": 2634103,
    "name:xx": "Russell Brook"
  }
}
