{
  "geometry": {
    "type": "Point",
    "coordinates": [
      -72.5333,
      44.6167
    ]
  },
  "type": "Feature",
  "properties": {
    "hierarchy": [
      "tgn:2277237",
      "tgn:1000001",
      "tgn:2002133",
      "tgn:7012149",
      "tgn:7007828",
      "tgn:7029392"
    ],
    "placetype": [
      "aat:300008798"
    ],
    "id": 2277237,
    "name:xx": "Davis Hill"
  }
}
