{
  "geometry": {
    "type": "Point",
    "coordinates": [
      -82.8833,
      35.2833
    ]
  },
  "type": "Feature",
  "properties": {
    "hierarchy": [
      "tgn:2235784",
      "tgn:1000001",
      "tgn:7012149",
      "tgn:2001544",
      "tgn:7007709",
      "tgn:7029392"
    ],
    "placetype": [
      "aat:300266640"
    ],
    "id": 2235784,
    "name:xx": "Chestnut Ridge"
  }
}
