{
  "geometry": {
    "type": "Point",
    "coordinates": [
      -109.1333,
      37.3167
    ]
  },
  "type": "Feature",
  "properties": {
    "hierarchy": [
      "tgn:2536208",
      "tgn:1000001",
      "tgn:7012149",
      "tgn:2002119",
      "tgn:7007827",
      "tgn:7029392"
    ],
    "placetype": [
      "aat:300008761"
    ],
    "id": 2536208,
    "name:xx": "Navajo Canyon"
  }
}
