{
  "geometry": {
    "type": "Point",
    "coordinates": [
      -97.2667,
      33.9333
    ]
  },
  "type": "Feature",
  "properties": {
    "hierarchy": [
      "tgn:2300640",
      "tgn:1000001",
      "tgn:7012149",
      "tgn:2001665",
      "tgn:7007707",
      "tgn:7029392"
    ],
    "placetype": [
      "aat:300008347"
    ],
    "id": 2300640,
    "name:xx": "Dunbar"
  }
}
