{
  "geometry": {
    "type": "Point",
    "coordinates": [
      -91.0333,
      30.3833
    ]
  },
  "type": "Feature",
  "properties": {
    "hierarchy": [
      "tgn:2569343",
      "tgn:1000001",
      "tgn:2000870",
      "tgn:7012149",
      "tgn:7007256",
      "tgn:7029392"
    ],
    "placetype": [
      "aat:300008347"
    ],
    "id": 2569343,
    "name:xx": "Parkview Oaks South"
  }
}
