{
  "geometry": {
    "type": "Point",
    "coordinates": [
      -75.0667,
      44.2833
    ]
  },
  "type": "Feature",
  "properties": {
    "hierarchy": [
      "tgn:2164324",
      "tgn:1000001",
      "tgn:7012149",
      "tgn:7016021",
      "tgn:7007568",
      "tgn:7029392"
    ],
    "placetype": [
      "aat:300008699"
    ],
    "id": 2164324,
    "name:xx": "Berry Brook"
  }
}
