{
  "geometry": {
    "type": "Point",
    "coordinates": [
      122.5167,
      42.3667
    ]
  },
  "type": "Feature",
  "properties": {
    "hierarchy": [
      "tgn:1140054",
      "tgn:1000004",
      "tgn:1001390",
      "tgn:1000111",
      "tgn:7029392"
    ],
    "placetype": [
      "aat:300008347"
    ],
    "id": 1140054,
    "name:xx": "Zhangwu"
  }
}
