{
  "geometry": {
    "type": "Point",
    "coordinates": [
      -81.15,
      37.45
    ]
  },
  "type": "Feature",
  "properties": {
    "hierarchy": [
      "tgn:2661604",
      "tgn:1000001",
      "tgn:7012149",
      "tgn:2002278",
      "tgn:7013961",
      "tgn:7029392"
    ],
    "placetype": [
      "aat:300008699"
    ],
    "id": 2661604,
    "name:xx": "Shrewsbury Branch"
  }
}
