{
  "geometry": {
    "type": "Point",
    "coordinates": [
      -90.7667,
      30.3667
    ]
  },
  "type": "Feature",
  "properties": {
    "hierarchy": [
      "tgn:2216495",
      "tgn:1000001",
      "tgn:7012149",
      "tgn:2000885",
      "tgn:7007256",
      "tgn:7029392"
    ],
    "placetype": [
      "aat:300008706"
    ],
    "id": 2216495,
    "name:xx": "Camp Creek"
  }
}
