{
  "geometry": {
    "type": "Point",
    "coordinates": [
      -76.1333,
      38.9333
    ]
  },
  "type": "Feature",
  "properties": {
    "hierarchy": [
      "tgn:2046480",
      "tgn:1000001",
      "tgn:2124025",
      "tgn:7012149",
      "tgn:7007516",
      "tgn:7029392"
    ],
    "placetype": [
      "aat:300008347",
      "aat:300387210"
    ],
    "id": 2046480,
    "name:xx": "Carmichael"
  }
}
