{
  "geometry": {
    "type": "Point",
    "coordinates": [
      5.4167,
      36.75
    ]
  },
  "type": "Feature",
  "properties": {
    "hierarchy": [
      "tgn:1112347",
      "tgn:7001242",
      "tgn:1000524",
      "tgn:7016752",
      "tgn:7029392"
    ],
    "placetype": [
      "aat:300132315"
    ],
    "id": 1112347,
    "name:xx": "Bejaïa, Golfe de"
  }
}
