{
  "geometry": {
    "type": "Point",
    "coordinates": [
      -112.55,
      46.0167
    ]
  },
  "type": "Feature",
  "properties": {
    "hierarchy": [
      "tgn:2166977",
      "tgn:1000001",
      "tgn:7012149",
      "tgn:2001306",
      "tgn:7007524",
      "tgn:7029392"
    ],
    "placetype": [
      "aat:300008798"
    ],
    "id": 2166977,
    "name:xx": "Big Butte"
  }
}
