{
  "geometry": {
    "type": "Point",
    "coordinates": [
      -82.5333,
      40.3333
    ]
  },
  "type": "Feature",
  "properties": {
    "hierarchy": [
      "tgn:2180702",
      "tgn:1000001",
      "tgn:7012149",
      "tgn:1003007",
      "tgn:7007706",
      "tgn:7029392"
    ],
    "placetype": [
      "aat:300008347"
    ],
    "id": 2180702,
    "name:xx": "Bloomingdale"
  }
}
