{
  "geometry": {
    "type": "Point",
    "coordinates": [
      -80.9833,
      39.8667
    ]
  },
  "type": "Feature",
  "properties": {
    "hierarchy": [
      "tgn:2264411",
      "tgn:1002175",
      "tgn:1000001",
      "tgn:7012149",
      "tgn:7007706",
      "tgn:7029392"
    ],
    "placetype": [
      "aat:300008347"
    ],
    "id": 2264411,
    "name:xx": "Crabapple"
  }
}
