{
  "type": "FeatureCollection",
  "features": [
    {
      "geometry": {
        "type": "Point",
        "coordinates": [
          -122.3167,
          47.6667
        ]
      },
      "type": "Feature",
      "properties": {
        "hierarchy": [
          "tgn:2506030",
          "tgn:1000001",
          "tgn:7012149",
          "tgn:7018871",
          "tgn:7007920",
          "tgn:7029392"
        ],
        "placetype": [
          "aat:300008347"
        ],
        "id": 2506030,
        "name:xx": "Meridian"
      }
    },
    {
      "geometry": {
        "type": "Point",
        "coordinates": [
          -122.7167,
          47.2
        ]
      },
      "type": "Feature",
      "properties": {
        "hierarchy": [
          "tgn:2506031",
          "tgn:1000001",
          "tgn:7012149",
          "tgn:1002785",
          "tgn:7007920",
          "tgn:7029392"
        ],
        "placetype": [
          "aat:300008347"
        ],
        "id": 2506031,
        "name:xx": "Meridian"
      }
    },
    {
      "geometry": {
        "type": "Point",
        "coordinates": [
          -110,
          36.9
        ]
      },
      "type": "Feature",
      "properties": {
        "hierarchy": [
          "tgn:2506032",
          "tgn:1000001",
          "tgn:7006451",
          "tgn:7012149",
          "tgn:7029392"
        ],
        "placetype": [
          "aat:300008798"
        ],
        "id": 2506032,
        "name:xx": "Meridian Butte"
      }
    },
    {
      "geometry": {
        "type": "Point",
        "coordinates": [
          -86.5667,
          34.8
        ]
      },
      "type": "Feature",
      "properties": {
        "hierarchy": [
          "tgn:2506033",
          "tgn:7002659",
          "tgn:1000001",
          "tgn:7012149",
          "tgn:2000044",
          "tgn:7029392"
        ],
        "placetype": [
          "aat:300008746"
        ],
        "id": 2506033,
        "name:xx": "Meridian Cave"
      }
    },
    {
      "geometry": {
        "type": "Point",
        "coordinates": [
          -159.9833,
          68.8167
        ]
      },
      "type": "Feature",
      "properties": {
        "hierarchy": [
          "tgn:2506034",
          "tgn:7006450",
          "tgn:1000001",
          "tgn:7012149",
          "tgn:2124005",
          "tgn:7029392"
        ],
        "placetype": [
          "aat:300008706"
        ],
        "id": 2506034,
        "name:xx": "Meridian Creek"
      }
    },
    {
      "geometry": {
        "type": "Point",
        "coordinates": [
          -114.3167,
          43.95
        ]
      },
      "type": "Feature",
      "properties": {
        "hierarchy": [
          "tgn:2506035",
          "tgn:1000001",
          "tgn:2000470",
          "tgn:7012149",
          "tgn:7007250",
          "tgn:7029392"
        ],
        "placetype": [
          "aat:300008706"
        ],
        "id": 2506035,
        "name:xx": "Meridian Creek"
      }
    },
    {
      "geometry": {
        "type": "Point",
        "coordinates": [
          -86.1667,
          39.8833
        ]
      },
      "type": "Feature",
      "properties": {
        "hierarchy": [
          "tgn:2506036",
          "tgn:1000001",
          "tgn:7012149",
          "tgn:1002633",
          "tgn:7007252",
          "tgn:7029392"
        ],
        "placetype": [
          "aat:300008706"
        ],
        "id": 2506036,
        "name:xx": "Meridian Creek"
      }
    },
    {
      "geometry": {
        "type": "Point",
        "coordinates": [
          -97.35,
          37.15
        ]
      },
      "type": "Feature",
      "properties": {
        "hierarchy": [
          "tgn:2506037",
          "tgn:1000001",
          "tgn:7012149",
          "tgn:2000755",
          "tgn:7007254",
          "tgn:7029392"
        ],
        "placetype": [
          "aat:300008706"
        ],
        "id": 2506037,
        "name:xx": "Meridian Creek"
      }
    },
    {
      "geometry": {
        "type": "Point",
        "coordinates": [
          -92.3667,
          32.9667
        ]
      },
      "type": "Feature",
      "properties": {
        "hierarchy": [
          "tgn:2506038",
          "tgn:1000001",
          "tgn:7012149",
          "tgn:2000909",
          "tgn:7007256",
          "tgn:7029392"
        ],
        "placetype": [
          "aat:300008706"
        ],
        "id": 2506038,
        "name:xx": "Meridian Creek"
      }
    },
    {
      "geometry": {
        "type": "Point",
        "coordinates": [
          -89.2333,
          33.9667
        ]
      },
      "type": "Feature",
      "properties": {
        "hierarchy": [
          "tgn:2506039",
          "tgn:1000001",
          "tgn:2001092",
          "tgn:7012149",
          "tgn:7007522",
          "tgn:7029392"
        ],
        "placetype": [
          "aat:300008706"
        ],
        "id": 2506039,
        "name:xx": "Meridian Creek"
      }
    }
  ]
}
