{
  "geometry": {
    "type": "Point",
    "coordinates": [
      -85.4667,
      41.8833
    ]
  },
  "type": "Feature",
  "properties": {
    "hierarchy": [
      "tgn:2215795",
      "tgn:1000001",
      "tgn:7012149",
      "tgn:7016057",
      "tgn:7007520",
      "tgn:7029392"
    ],
    "placetype": [
      "aat:300008680"
    ],
    "id": 2215795,
    "name:xx": "Camel Lake"
  }
}
