{
  "geometry": {
    "type": "Point",
    "coordinates": [
      -86.2667,
      35.9667
    ]
  },
  "type": "Feature",
  "properties": {
    "hierarchy": [
      "tgn:2224824",
      "tgn:1000001",
      "tgn:7012149",
      "tgn:2001911",
      "tgn:7007825",
      "tgn:7029392"
    ],
    "placetype": [
      "aat:300008798"
    ],
    "id": 2224824,
    "name:xx": "Casons Knobs"
  }
}
