{
  "geometry": {
    "type": "Point",
    "coordinates": [
      -84.45,
      41.9167
    ]
  },
  "type": "Feature",
  "properties": {
    "hierarchy": [
      "tgn:2562401",
      "tgn:1000001",
      "tgn:7012149",
      "tgn:7007520",
      "tgn:7029392"
    ],
    "placetype": [
      "aat:300008699"
    ],
    "id": 2562401,
    "name:xx": "Otto Drain"
  }
}
