{
  "geometry": {
    "type": "Point",
    "coordinates": [
      -76.5333,
      41.0167
    ]
  },
  "type": "Feature",
  "properties": {
    "hierarchy": [
      "tgn:2341851",
      "tgn:1000001",
      "tgn:1002294",
      "tgn:7012149",
      "tgn:7007710",
      "tgn:7029392"
    ],
    "placetype": [
      "aat:300008699"
    ],
    "id": 2341851,
    "name:xx": "Frozen Run"
  }
}
