{
  "geometry": {
    "type": "Point",
    "coordinates": [
      28.0667,
      56.4333
    ]
  },
  "type": "Feature",
  "properties": {
    "hierarchy": [
      "tgn:1061622",
      "tgn:7012152",
      "tgn:1000003",
      "tgn:7006541",
      "tgn:7029392"
    ],
    "placetype": [
      "aat:300008347"
    ],
    "id": 1061622,
    "name:xx": "Zilupe"
  }
}
