{
  "geometry": {
    "type": "Point",
    "coordinates": [
      -101.95,
      41.8667
    ]
  },
  "type": "Feature",
  "properties": {
    "hierarchy": [
      "tgn:2707175",
      "tgn:1000001",
      "tgn:2001353",
      "tgn:7012149",
      "tgn:7007525",
      "tgn:7029392"
    ],
    "placetype": [
      "aat:300008680"
    ],
    "id": 2707175,
    "name:xx": "Swede Lake"
  }
}
