{
  "geometry": {
    "type": "Point",
    "coordinates": [
      -78.95,
      35.2333
    ]
  },
  "type": "Feature",
  "properties": {
    "hierarchy": [
      "tgn:2501892",
      "tgn:1000001",
      "tgn:7012149",
      "tgn:2001502",
      "tgn:7007709",
      "tgn:7029392"
    ],
    "placetype": [
      "aat:300006191"
    ],
    "id": 2501892,
    "name:xx": "McKay, Lake"
  }
}
