{
  "geometry": {
    "type": "Point",
    "coordinates": [
      -106.15,
      37.45
    ]
  },
  "type": "Feature",
  "properties": {
    "hierarchy": [
      "tgn:2686275",
      "tgn:1000001",
      "tgn:7012149",
      "tgn:7007158",
      "tgn:2000244",
      "tgn:7029392"
    ],
    "placetype": [
      "aat:300008706"
    ],
    "id": 2686275,
    "name:xx": "Spring Creek"
  }
}
