{
  "geometry": {
    "type": "Point",
    "coordinates": [
      92.290985,
      26.236335
    ]
  },
  "type": "Feature",
  "properties": {
    "hierarchy": [
      "tgn:7548057",
      "tgn:1000004",
      "tgn:1001832",
      "tgn:7000198",
      "tgn:7029392"
    ],
    "placetype": [
      "aat:300008347"
    ],
    "name:en": "Aujāri",
    "id": 7548057
  }
}
