{
  "geometry": {
    "type": "Point",
    "coordinates": [
      -112.3333,
      39.3333
    ]
  },
  "type": "Feature",
  "properties": {
    "hierarchy": [
      "tgn:2472715",
      "tgn:1000001",
      "tgn:7012149",
      "tgn:2002114",
      "tgn:7007827",
      "tgn:7029392"
    ],
    "placetype": [
      "aat:300008761"
    ],
    "id": 2472715,
    "name:xx": "Lovell Hollow"
  }
}
