{
  "geometry": {
    "type": "Point",
    "coordinates": [
      22.8833,
      51.65
    ]
  },
  "type": "Feature",
  "properties": {
    "hierarchy": [
      "tgn:1049349",
      "tgn:1000003",
      "tgn:7024128",
      "tgn:7006366",
      "tgn:7029392"
    ],
    "placetype": [
      "aat:300008347"
    ],
    "id": 1049349,
    "name:xx": "Parczew"
  }
}
