{
  "geometry": {
    "type": "Point",
    "coordinates": [
      -94.7833,
      35.7167
    ]
  },
  "type": "Feature",
  "properties": {
    "hierarchy": [
      "tgn:2207025",
      "tgn:2001623",
      "tgn:1000001",
      "tgn:7012149",
      "tgn:7007707",
      "tgn:7029392"
    ],
    "placetype": [
      "aat:300008798"
    ],
    "id": 2207025,
    "name:xx": "Bunch Mountain"
  }
}
