{
  "geometry": {
    "type": "Point",
    "coordinates": [
      -80.1833,
      38.1667
    ]
  },
  "type": "Feature",
  "properties": {
    "hierarchy": [
      "tgn:2337830",
      "tgn:1000001",
      "tgn:7012149",
      "tgn:2002287",
      "tgn:7013961",
      "tgn:7029392"
    ],
    "placetype": [
      "aat:300008746"
    ],
    "id": 2337830,
    "name:xx": "Fox Den Pits"
  }
}
