{
  "geometry": {
    "type": "Point",
    "coordinates": [
      68.1333,
      31.8167
    ]
  },
  "type": "Feature",
  "properties": {
    "hierarchy": [
      "tgn:1065413",
      "tgn:7016612",
      "tgn:1000004",
      "tgn:1001608",
      "tgn:7029392"
    ],
    "placetype": [
      "aat:300008347"
    ],
    "id": 1065413,
    "name:xx": "Darakht-e Yahya"
  }
}
