{
  "geometry": {
    "type": "Point",
    "coordinates": [
      -84.5667,
      34.7833
    ]
  },
  "type": "Feature",
  "properties": {
    "hierarchy": [
      "tgn:2672791",
      "tgn:1000001",
      "tgn:7012149",
      "tgn:2000352",
      "tgn:7007248",
      "tgn:7029392"
    ],
    "placetype": [
      "aat:300266640"
    ],
    "id": 2672791,
    "name:xx": "Snaggy Lead"
  }
}
