{
  "geometry": {
    "type": "Point",
    "coordinates": [
      -76.1833,
      24.9333
    ]
  },
  "type": "Feature",
  "properties": {
    "hierarchy": [
      "tgn:1013022",
      "tgn:7005332",
      "tgn:7593510",
      "tgn:1000001",
      "tgn:7029392"
    ],
    "placetype": [
      "aat:300008347",
      "aat:300008375"
    ],
    "id": 1013022,
    "name:xx": "Rock Sound"
  }
}
