{
  "geometry": {
    "type": "Point",
    "coordinates": [
      109.1667,
      34.4167
    ]
  },
  "type": "Feature",
  "properties": {
    "hierarchy": [
      "tgn:7001877",
      "tgn:1000004",
      "tgn:7002084",
      "tgn:1000111",
      "tgn:7029392"
    ],
    "placetype": [
      "aat:300008347",
      "aat:300008375"
    ],
    "id": 7001877,
    "name:xx": "Lintong"
  }
}
