{
  "geometry": {
    "type": "Point",
    "coordinates": [
      -81.55,
      40.3667
    ]
  },
  "type": "Feature",
  "properties": {
    "hierarchy": [
      "tgn:2203225",
      "tgn:1000001",
      "tgn:7012149",
      "tgn:7007706",
      "tgn:7029392"
    ],
    "placetype": [
      "aat:300008706"
    ],
    "id": 2203225,
    "name:xx": "Buckhorn Creek"
  }
}
