{
  "geometry": {
    "type": "Point",
    "coordinates": [
      125.7667,
      40.1833
    ]
  },
  "type": "Feature",
  "properties": {
    "hierarchy": [
      "tgn:1082087",
      "tgn:1000004",
      "tgn:1001478",
      "tgn:1000122",
      "tgn:7029392"
    ],
    "placetype": [
      "aat:300008347"
    ],
    "id": 1082087,
    "name:xx": "Pukchin"
  }
}
