{
  "geometry": {
    "type": "Point",
    "coordinates": [
      38.5667,
      40.0667
    ]
  },
  "type": "Feature",
  "properties": {
    "hierarchy": [
      "tgn:1085911",
      "tgn:1001511",
      "tgn:1000004",
      "tgn:7018453",
      "tgn:1000144",
      "tgn:7029392"
    ],
    "placetype": [
      "aat:300008347"
    ],
    "id": 1085911,
    "name:xx": "Ağvanis"
  }
}
