{
  "geometry": {
    "type": "Point",
    "coordinates": [
      -91.2833,
      34.1833
    ]
  },
  "type": "Feature",
  "properties": {
    "hierarchy": [
      "tgn:2236804",
      "tgn:2000105",
      "tgn:1000001",
      "tgn:7016172",
      "tgn:7012149",
      "tgn:7029392"
    ],
    "placetype": [
      "aat:300006191"
    ],
    "id": 2236804,
    "name:xx": "Childers Lake Dam"
  }
}
