{
  "type": "FeatureCollection",
  "features": [
    {
      "geometry": {
        "type": "Point",
        "coordinates": [
          -97.933333,
          20.85
        ]
      },
      "type": "Feature",
      "properties": {
        "hierarchy": [
          "tgn:7384300",
          "tgn:1000001",
          "tgn:7005599",
          "tgn:7005560",
          "tgn:7029392"
        ],
        "placetype": [
          "aat:300008347"
        ],
        "id": 7384300,
        "name:xx": "Naranjo Dulce"
      }
    },
    {
      "geometry": {
        "type": "Point",
        "coordinates": [
          -106.066667,
          31.116667
        ]
      },
      "type": "Feature",
      "properties": {
        "hierarchy": [
          "tgn:7384302",
          "tgn:7005581",
          "tgn:1000001",
          "tgn:7005560",
          "tgn:7029392"
        ],
        "placetype": [
          "aat:300000241"
        ],
        "id": 7384302,
        "name:xx": "Rancho Naranjo"
      }
    },
    {
      "geometry": {
        "type": "Point",
        "coordinates": [
          -105.216667,
          21.083333
        ]
      },
      "type": "Feature",
      "properties": {
        "hierarchy": [
          "tgn:7384303",
          "tgn:1000001",
          "tgn:1001906",
          "tgn:7005560",
          "tgn:7029392"
        ],
        "placetype": [
          "aat:300008816"
        ],
        "id": 7384303,
        "name:xx": "Naranjo, Playa El"
      }
    },
    {
      "geometry": {
        "type": "Point",
        "coordinates": [
          -99.316667,
          23.6
        ]
      },
      "type": "Feature",
      "properties": {
        "hierarchy": [
          "tgn:7384304",
          "tgn:1000001",
          "tgn:7005597",
          "tgn:7005560",
          "tgn:7029392"
        ],
        "placetype": [
          "aat:300008811"
        ],
        "id": 7384304,
        "name:xx": "Naranjo, Mesa el"
      }
    },
    {
      "geometry": {
        "type": "Point",
        "coordinates": [
          -103.133333,
          19.166667
        ]
      },
      "type": "Feature",
      "properties": {
        "hierarchy": [
          "tgn:7384305",
          "tgn:7005586",
          "tgn:1000001",
          "tgn:7005560",
          "tgn:7029392"
        ],
        "placetype": [
          "aat:300008777"
        ],
        "id": 7384305,
        "name:xx": "Naranjo, Cerro el"
      }
    },
    {
      "geometry": {
        "type": "Point",
        "coordinates": [
          -105.25,
          21.1
        ]
      },
      "type": "Feature",
      "properties": {
        "hierarchy": [
          "tgn:7384306",
          "tgn:1000001",
          "tgn:1001906",
          "tgn:7005560",
          "tgn:7029392"
        ],
        "placetype": [
          "aat:300387057"
        ],
        "id": 7384306,
        "name:xx": "Naranjo, Boca del"
      }
    },
    {
      "geometry": {
        "type": "Point",
        "coordinates": [
          -107.633333,
          26.066667
        ]
      },
      "type": "Feature",
      "properties": {
        "hierarchy": [
          "tgn:7384307",
          "tgn:1000001",
          "tgn:7005595",
          "tgn:7005560",
          "tgn:7029392"
        ],
        "placetype": [
          "aat:300008699"
        ],
        "id": 7384307,
        "name:xx": "Naranjo, Arroyo"
      }
    },
    {
      "geometry": {
        "type": "Point",
        "coordinates": [
          -98.516667,
          22.466667
        ]
      },
      "type": "Feature",
      "properties": {
        "hierarchy": [
          "tgn:7384308",
          "tgn:1000001",
          "tgn:7005597",
          "tgn:7005560",
          "tgn:7029392"
        ],
        "placetype": [
          "aat:300008699"
        ],
        "id": 7384308,
        "name:xx": "Naranjo, Arroyo"
      }
    },
    {
      "geometry": {
        "type": "Point",
        "coordinates": [
          -96.25,
          19.016667
        ]
      },
      "type": "Feature",
      "properties": {
        "hierarchy": [
          "tgn:7384309",
          "tgn:1000001",
          "tgn:7005599",
          "tgn:7005560",
          "tgn:7029392"
        ],
        "placetype": [
          "aat:300008699"
        ],
        "id": 7384309,
        "name:xx": "Naranjo, Arroyo"
      }
    }
  ]
}
