{
  "geometry": {
    "type": "Point",
    "coordinates": [
      19.3833,
      53.05
    ]
  },
  "type": "Feature",
  "properties": {
    "hierarchy": [
      "tgn:7007790",
      "tgn:7024116",
      "tgn:1000003",
      "tgn:7006366",
      "tgn:7029392"
    ],
    "placetype": [
      "aat:300008347"
    ],
    "id": 7007790,
    "name:xx": "Rypin"
  }
}
