{
  "geometry": {
    "type": "Point",
    "coordinates": [
      75.6886,
      28.4053
    ]
  },
  "type": "Feature",
  "properties": {
    "hierarchy": [
      "tgn:7582369",
      "tgn:1000004",
      "tgn:7000198",
      "tgn:7016788",
      "tgn:7029392"
    ],
    "placetype": [
      "aat:300008347"
    ],
    "name:en": "Dulānīya",
    "id": 7582369
  }
}
