{
  "geometry": {
    "type": "Point",
    "coordinates": [
      -116.85,
      42.1167
    ]
  },
  "type": "Feature",
  "properties": {
    "hierarchy": [
      "tgn:7020970",
      "tgn:1000001",
      "tgn:7012149",
      "tgn:2000488",
      "tgn:7007250",
      "tgn:7029392"
    ],
    "placetype": [
      "aat:300006191"
    ],
    "id": 7020970,
    "name:xx": "Pothole Reservoir"
  }
}
