{
  "geometry": {
    "type": "Point",
    "coordinates": [
      35.5667,
      32.6667
    ]
  },
  "type": "Feature",
  "properties": {
    "hierarchy": [
      "tgn:1079471",
      "tgn:7000249",
      "tgn:1000004",
      "tgn:1000119",
      "tgn:7029392"
    ],
    "placetype": [
      "aat:300008347"
    ],
    "id": 1079471,
    "name:xx": "Afiqim"
  }
}
