{
  "geometry": {
    "type": "Point",
    "coordinates": [
      -92.6333,
      45.6333
    ]
  },
  "type": "Feature",
  "properties": {
    "hierarchy": [
      "tgn:2465672",
      "tgn:1000001",
      "tgn:7012149",
      "tgn:2002346",
      "tgn:7007922",
      "tgn:7029392"
    ],
    "placetype": [
      "aat:300008680"
    ],
    "id": 2465672,
    "name:xx": "Lone Pine Lake"
  }
}
