{
  "geometry": {
    "type": "Point",
    "coordinates": [
      -78.8333,
      38.0167
    ]
  },
  "type": "Feature",
  "properties": {
    "hierarchy": [
      "tgn:2110241",
      "tgn:1000001",
      "tgn:7012149",
      "tgn:2002175",
      "tgn:7007919",
      "tgn:7029392"
    ],
    "placetype": [
      "aat:300008347"
    ],
    "id": 2110241,
    "name:xx": "Afton"
  }
}
