{
  "geometry": {
    "type": "Point",
    "coordinates": [
      -94.6667,
      34.1333
    ]
  },
  "type": "Feature",
  "properties": {
    "hierarchy": [
      "tgn:1119512",
      "tgn:1000001",
      "tgn:7012149",
      "tgn:2001667",
      "tgn:7007707",
      "tgn:7029392"
    ],
    "placetype": [
      "aat:300006191"
    ],
    "id": 1119512,
    "name:xx": "Broken Bow Lake"
  }
}
