{
  "geometry": {
    "type": "Point",
    "coordinates": [
      -59.0333,
      47.9167
    ]
  },
  "type": "Feature",
  "properties": {
    "hierarchy": [
      "tgn:1014325",
      "tgn:7005685",
      "tgn:7005807",
      "tgn:1000001",
      "tgn:7005801",
      "tgn:7029392"
    ],
    "placetype": [
      "aat:300008347"
    ],
    "id": 1014325,
    "name:xx": "South Branch"
  }
}
