{
  "type": "FeatureCollection",
  "features": [
    {
      "geometry": {
        "type": "Point",
        "coordinates": [
          -121.5667,
          38.4167
        ]
      },
      "type": "Feature",
      "properties": {
        "hierarchy": [
          "tgn:1131090",
          "tgn:1000001",
          "tgn:7012149",
          "tgn:7007157",
          "tgn:1003046",
          "tgn:7029392"
        ],
        "placetype": [
          "aat:300008707"
        ],
        "id": 1131090,
        "name:xx": "Tule"
      }
    },
    {
      "geometry": {
        "type": "Point",
        "coordinates": [
          -84.862,
          11.328
        ]
      },
      "type": "Feature",
      "properties": {
        "hierarchy": [
          "tgn:1131091",
          "tgn:1000738",
          "tgn:1000001",
          "tgn:7005562",
          "tgn:7029392"
        ],
        "placetype": [
          "aat:300008707"
        ],
        "id": 1131091,
        "name:xx": "Tule, Río"
      }
    },
    {
      "geometry": {
        "type": "Point",
        "coordinates": [
          120.9667,
          14.6833
        ]
      },
      "type": "Feature",
      "properties": {
        "hierarchy": [
          "tgn:1131095",
          "tgn:1000004",
          "tgn:7016720",
          "tgn:1000135",
          "tgn:7029392"
        ],
        "placetype": [
          "aat:300008707"
        ],
        "id": 1131095,
        "name:xx": "Tuliahan River"
      }
    },
    {
      "geometry": {
        "type": "Point",
        "coordinates": [
          30.8,
          66.6
        ]
      },
      "type": "Feature",
      "properties": {
        "hierarchy": [
          "tgn:1131099",
          "tgn:1000003",
          "tgn:7029392"
        ],
        "placetype": [
          "aat:300008707"
        ],
        "id": 1131099,
        "name:xx": "Tumcha",
        "name:fi": "Tuntsajoki"
      }
    }
  ]
}
