{
  "type": "FeatureCollection",
  "features": [
    {
      "geometry": {
        "type": "Point",
        "coordinates": [
          -117.5833,
          40.9
        ]
      },
      "type": "Feature",
      "properties": {
        "hierarchy": [
          "tgn:2285250",
          "tgn:1000001",
          "tgn:2001414",
          "tgn:7012149",
          "tgn:7007526",
          "tgn:7029392"
        ],
        "placetype": [
          "aat:300008761"
        ],
        "id": 2285250,
        "name:xx": "Devils Canyon"
      }
    },
    {
      "geometry": {
        "type": "Point",
        "coordinates": [
          -106.5167,
          32.2667
        ]
      },
      "type": "Feature",
      "properties": {
        "hierarchy": [
          "tgn:2285251",
          "tgn:1000001",
          "tgn:2001435",
          "tgn:7012149",
          "tgn:7007566",
          "tgn:7029392"
        ],
        "placetype": [
          "aat:300008761"
        ],
        "id": 2285251,
        "name:xx": "Devils Canyon"
      }
    },
    {
      "geometry": {
        "type": "Point",
        "coordinates": [
          -105.7667,
          32.9667
        ]
      },
      "type": "Feature",
      "properties": {
        "hierarchy": [
          "tgn:2285252",
          "tgn:1000001",
          "tgn:7012149",
          "tgn:2001447",
          "tgn:7007566",
          "tgn:7029392"
        ],
        "placetype": [
          "aat:300008761"
        ],
        "id": 2285252,
        "name:xx": "Devils Canyon"
      }
    },
    {
      "geometry": {
        "type": "Point",
        "coordinates": [
          -105.4833,
          33.45
        ]
      },
      "type": "Feature",
      "properties": {
        "hierarchy": [
          "tgn:2285253",
          "tgn:1000001",
          "tgn:7012149",
          "tgn:2001442",
          "tgn:7007566",
          "tgn:7029392"
        ],
        "placetype": [
          "aat:300008761"
        ],
        "id": 2285253,
        "name:xx": "Devils Canyon"
      }
    },
    {
      "geometry": {
        "type": "Point",
        "coordinates": [
          -104.4333,
          35.8333
        ]
      },
      "type": "Feature",
      "properties": {
        "hierarchy": [
          "tgn:2285254",
          "tgn:1000001",
          "tgn:7012149",
          "tgn:2001446",
          "tgn:7007566",
          "tgn:7029392"
        ],
        "placetype": [
          "aat:300008761"
        ],
        "id": 2285254,
        "name:xx": "Devils Canyon"
      }
    },
    {
      "geometry": {
        "type": "Point",
        "coordinates": [
          -107.2167,
          36.7167
        ]
      },
      "type": "Feature",
      "properties": {
        "hierarchy": [
          "tgn:2285255",
          "tgn:1000001",
          "tgn:7012149",
          "tgn:2001449",
          "tgn:7007566",
          "tgn:7029392"
        ],
        "placetype": [
          "aat:300008761"
        ],
        "id": 2285255,
        "name:xx": "Devils Canyon"
      }
    },
    {
      "geometry": {
        "type": "Point",
        "coordinates": [
          -108.7333,
          33.5167
        ]
      },
      "type": "Feature",
      "properties": {
        "hierarchy": [
          "tgn:2285256",
          "tgn:1000001",
          "tgn:2001429",
          "tgn:7012149",
          "tgn:7007566",
          "tgn:7029392"
        ],
        "placetype": [
          "aat:300008761"
        ],
        "id": 2285256,
        "name:xx": "Devils Canyon"
      }
    },
    {
      "geometry": {
        "type": "Point",
        "coordinates": [
          -104,
          35.75
        ]
      },
      "type": "Feature",
      "properties": {
        "hierarchy": [
          "tgn:2285257",
          "tgn:1000001",
          "tgn:7012149",
          "tgn:2001453",
          "tgn:7007566",
          "tgn:7029392"
        ],
        "placetype": [
          "aat:300008761"
        ],
        "id": 2285257,
        "name:xx": "Devils Canyon"
      }
    },
    {
      "geometry": {
        "type": "Point",
        "coordinates": [
          -107.7333,
          36.9833
        ]
      },
      "type": "Feature",
      "properties": {
        "hierarchy": [
          "tgn:2285258",
          "tgn:1000001",
          "tgn:7012149",
          "tgn:2001452",
          "tgn:7007566",
          "tgn:7029392"
        ],
        "placetype": [
          "aat:300008761"
        ],
        "id": 2285258,
        "name:xx": "Devils Canyon"
      }
    }
  ]
}
