{
  "geometry": {
    "type": "Point",
    "coordinates": [
      120.8833,
      41.0667
    ]
  },
  "type": "Feature",
  "properties": {
    "hierarchy": [
      "tgn:1067460",
      "tgn:1000004",
      "tgn:1001390",
      "tgn:1000111",
      "tgn:7029392"
    ],
    "placetype": [
      "aat:300008347"
    ],
    "id": 1067460,
    "name:xx": "Damengjialazi"
  }
}
