{
  "type": "FeatureCollection",
  "features": [
    {
      "geometry": {
        "type": "Point",
        "coordinates": [
          -84.9667,
          36.7
        ]
      },
      "type": "Feature",
      "properties": {
        "hierarchy": [
          "tgn:2202060",
          "tgn:1000001",
          "tgn:7012149",
          "tgn:2000850",
          "tgn:7007255",
          "tgn:7029392"
        ],
        "placetype": [
          "aat:300008798"
        ],
        "id": 2202060,
        "name:xx": "Buck Knob"
      }
    },
    {
      "geometry": {
        "type": "Point",
        "coordinates": [
          -85.75,
          37.0667
        ]
      },
      "type": "Feature",
      "properties": {
        "hierarchy": [
          "tgn:2202061",
          "tgn:2000768",
          "tgn:1000001",
          "tgn:7012149",
          "tgn:7007255",
          "tgn:7029392"
        ],
        "placetype": [
          "aat:300008798"
        ],
        "id": 2202061,
        "name:xx": "Buck Knob"
      }
    },
    {
      "geometry": {
        "type": "Point",
        "coordinates": [
          -87.1167,
          37.1833
        ]
      },
      "type": "Feature",
      "properties": {
        "hierarchy": [
          "tgn:2202062",
          "tgn:1000001",
          "tgn:7012149",
          "tgn:2000832",
          "tgn:7007255",
          "tgn:7029392"
        ],
        "placetype": [
          "aat:300008798"
        ],
        "id": 2202062,
        "name:xx": "Buck Knob"
      }
    },
    {
      "geometry": {
        "type": "Point",
        "coordinates": [
          -83.0833,
          38
        ]
      },
      "type": "Feature",
      "properties": {
        "hierarchy": [
          "tgn:2202063",
          "tgn:1000001",
          "tgn:7012149",
          "tgn:1002354",
          "tgn:7007255",
          "tgn:7029392"
        ],
        "placetype": [
          "aat:300008798"
        ],
        "id": 2202063,
        "name:xx": "Buck Knob"
      }
    },
    {
      "geometry": {
        "type": "Point",
        "coordinates": [
          -90.35,
          38.2
        ]
      },
      "type": "Feature",
      "properties": {
        "hierarchy": [
          "tgn:2202064",
          "tgn:1000001",
          "tgn:7012149",
          "tgn:1002517",
          "tgn:7007523",
          "tgn:7029392"
        ],
        "placetype": [
          "aat:300008798"
        ],
        "id": 2202064,
        "name:xx": "Buck Knob"
      }
    },
    {
      "geometry": {
        "type": "Point",
        "coordinates": [
          -92.3667,
          38.2333
        ]
      },
      "type": "Feature",
      "properties": {
        "hierarchy": [
          "tgn:2202065",
          "tgn:1000001",
          "tgn:7012149",
          "tgn:1002671",
          "tgn:7007523",
          "tgn:7029392"
        ],
        "placetype": [
          "aat:300008798"
        ],
        "id": 2202065,
        "name:xx": "Buck Knob"
      }
    },
    {
      "geometry": {
        "type": "Point",
        "coordinates": [
          -89.9333,
          37.45
        ]
      },
      "type": "Feature",
      "properties": {
        "hierarchy": [
          "tgn:2202066",
          "tgn:1000001",
          "tgn:2001174",
          "tgn:7012149",
          "tgn:7007523",
          "tgn:7029392"
        ],
        "placetype": [
          "aat:300008798"
        ],
        "id": 2202066,
        "name:xx": "Buck Knob"
      }
    },
    {
      "geometry": {
        "type": "Point",
        "coordinates": [
          -83.3333,
          35.0333
        ]
      },
      "type": "Feature",
      "properties": {
        "hierarchy": [
          "tgn:2202068",
          "tgn:1000001",
          "tgn:7012149",
          "tgn:2001515",
          "tgn:7007709",
          "tgn:7029392"
        ],
        "placetype": [
          "aat:300008798"
        ],
        "id": 2202068,
        "name:xx": "Buck Knob"
      }
    },
    {
      "geometry": {
        "type": "Point",
        "coordinates": [
          -83.0167,
          35.05
        ]
      },
      "type": "Feature",
      "properties": {
        "hierarchy": [
          "tgn:2202069",
          "tgn:1000001",
          "tgn:7012149",
          "tgn:2001544",
          "tgn:7007709",
          "tgn:7029392"
        ],
        "placetype": [
          "aat:300008798"
        ],
        "id": 2202069,
        "name:xx": "Buck Knob"
      }
    }
  ]
}
