{
  "geometry": {
    "type": "Point",
    "coordinates": [
      -119.1333,
      34.3333
    ]
  },
  "type": "Feature",
  "properties": {
    "hierarchy": [
      "tgn:2723512",
      "tgn:1000001",
      "tgn:7012149",
      "tgn:7007157",
      "tgn:1002972",
      "tgn:7029392"
    ],
    "placetype": [
      "aat:300008761"
    ],
    "id": 2723512,
    "name:xx": "Todd Barranca"
  }
}
