{
  "type": "FeatureCollection",
  "features": [
    {
      "geometry": {
        "type": "Point",
        "coordinates": [
          12.5,
          51
        ]
      },
      "type": "Feature",
      "properties": {
        "hierarchy": [
          "tgn:7075750",
          "tgn:1000003",
          "tgn:7594165",
          "tgn:7000084",
          "tgn:7029392"
        ],
        "placetype": [
          "aat:300055621"
        ],
        "id": 7075750,
        "name:xx": "Osterland"
      }
    },
    {
      "geometry": {
        "type": "Point",
        "coordinates": [
          14.5,
          50.866667
        ]
      },
      "type": "Feature",
      "properties": {
        "hierarchy": [
          "tgn:7075751",
          "tgn:1000003",
          "tgn:7003689",
          "tgn:7000084",
          "tgn:7029392"
        ],
        "placetype": [
          "aat:300055621"
        ],
        "id": 7075751,
        "name:xx": "Thüringer Holzland"
      }
    },
    {
      "geometry": {
        "type": "Point",
        "coordinates": [
          6.918333,
          53.395833
        ]
      },
      "type": "Feature",
      "properties": {
        "hierarchy": [
          "tgn:7075752",
          "tgn:1000003",
          "tgn:7003676",
          "tgn:7000084",
          "tgn:7029392"
        ],
        "placetype": [
          "aat:300132350"
        ],
        "id": 7075752,
        "name:xx": "Hund"
      }
    },
    {
      "geometry": {
        "type": "Point",
        "coordinates": [
          10.966667,
          51.1
        ]
      },
      "type": "Feature",
      "properties": {
        "hierarchy": [
          "tgn:7075753",
          "tgn:1000003",
          "tgn:7003689",
          "tgn:7000084",
          "tgn:7029392"
        ],
        "placetype": [
          "aat:300008903"
        ],
        "id": 7075753,
        "name:xx": "Großes Ried"
      }
    },
    {
      "geometry": {
        "type": "Point",
        "coordinates": [
          11,
          51.166667
        ]
      },
      "type": "Feature",
      "properties": {
        "hierarchy": [
          "tgn:7075754",
          "tgn:1000003",
          "tgn:7003689",
          "tgn:7000084",
          "tgn:7029392"
        ],
        "placetype": [
          "aat:300055621"
        ],
        "id": 7075754,
        "name:xx": "Thüringer Becken"
      }
    },
    {
      "geometry": {
        "type": "Point",
        "coordinates": [
          11.2,
          51.3
        ]
      },
      "type": "Feature",
      "properties": {
        "hierarchy": [
          "tgn:7075755",
          "tgn:1000003",
          "tgn:7003689",
          "tgn:7000084",
          "tgn:7029392"
        ],
        "placetype": [
          "aat:300259572"
        ],
        "id": 7075755,
        "name:xx": "Sachsenburger Pforte"
      }
    },
    {
      "geometry": {
        "type": "Point",
        "coordinates": [
          10.9,
          51.5
        ]
      },
      "type": "Feature",
      "properties": {
        "hierarchy": [
          "tgn:7075757",
          "tgn:1000003",
          "tgn:7003689",
          "tgn:7000084",
          "tgn:7029392"
        ],
        "placetype": [
          "aat:300266640"
        ],
        "id": 7075757,
        "name:xx": "Alter Stolberg"
      }
    },
    {
      "geometry": {
        "type": "Point",
        "coordinates": [
          13.116667,
          50.7
        ]
      },
      "type": "Feature",
      "properties": {
        "hierarchy": [
          "tgn:7075758",
          "tgn:1000003",
          "tgn:7003685",
          "tgn:7000084",
          "tgn:7029392"
        ],
        "placetype": [
          "aat:300008863"
        ],
        "id": 7075758,
        "name:xx": "Heinzewald"
      }
    },
    {
      "geometry": {
        "type": "Point",
        "coordinates": [
          13,
          50.583333
        ]
      },
      "type": "Feature",
      "properties": {
        "hierarchy": [
          "tgn:7075759",
          "tgn:1000003",
          "tgn:7003685",
          "tgn:7000084",
          "tgn:7029392"
        ],
        "placetype": [
          "aat:300008795"
        ],
        "id": 7075759,
        "name:xx": "Westerzgebirge"
      }
    }
  ]
}
