{
  "geometry": {
    "type": "Point",
    "coordinates": [
      -116.0333,
      44.7333
    ]
  },
  "type": "Feature",
  "properties": {
    "hierarchy": [
      "tgn:2760254",
      "tgn:1000001",
      "tgn:7012149",
      "tgn:2000494",
      "tgn:7007250",
      "tgn:7029392"
    ],
    "placetype": [
      "aat:300006075"
    ],
    "id": 2760254,
    "name:xx": "West Fork Roseberry Ditch"
  }
}
