{
  "geometry": {
    "type": "Point",
    "coordinates": [
      -78.0667,
      34.45
    ]
  },
  "type": "Feature",
  "properties": {
    "hierarchy": [
      "tgn:2272552",
      "tgn:1000001",
      "tgn:7012149",
      "tgn:2001527",
      "tgn:7007709",
      "tgn:7029392"
    ],
    "placetype": [
      "aat:300008905"
    ],
    "id": 2272552,
    "name:xx": "Curve of the Railroad Bay"
  }
}
