{
  "geometry": {
    "type": "Point",
    "coordinates": [
      -81.2167,
      39.7167
    ]
  },
  "type": "Feature",
  "properties": {
    "hierarchy": [
      "tgn:2671390",
      "tgn:1000001",
      "tgn:7012149",
      "tgn:2001617",
      "tgn:7007706",
      "tgn:7029392"
    ],
    "placetype": [
      "aat:300008761"
    ],
    "id": 2671390,
    "name:xx": "Smith Hollow"
  }
}
