{
  "geometry": {
    "type": "Point",
    "coordinates": [
      -85.3833,
      32.3333
    ]
  },
  "type": "Feature",
  "properties": {
    "hierarchy": [
      "tgn:2577147",
      "tgn:7002659",
      "tgn:1000001",
      "tgn:7012149",
      "tgn:7029392"
    ],
    "placetype": [
      "aat:300008699"
    ],
    "id": 2577147,
    "name:xx": "Peters Branch"
  }
}
