{
  "type": "FeatureCollection",
  "features": [
    {
      "geometry": {
        "type": "Point",
        "coordinates": [
          -5.183333,
          49.983333
        ]
      },
      "type": "Feature",
      "properties": {
        "hierarchy": [
          "tgn:7448320",
          "tgn:7002445",
          "tgn:7008116",
          "tgn:1000003",
          "tgn:7008591",
          "tgn:7029392"
        ],
        "placetype": [
          "aat:300008347"
        ],
        "name:en": "Ruan Minor",
        "id": 7448320
      }
    },
    {
      "geometry": {
        "type": "Point",
        "coordinates": [
          -5.2,
          50
        ]
      },
      "type": "Feature",
      "properties": {
        "hierarchy": [
          "tgn:7448321",
          "tgn:7002445",
          "tgn:7008116",
          "tgn:1000003",
          "tgn:7008591",
          "tgn:7029392"
        ],
        "placetype": [
          "aat:300008347"
        ],
        "name:en": "Ruan Major",
        "id": 7448321
      }
    },
    {
      "geometry": {
        "type": "Point",
        "coordinates": [
          -2.833333,
          56.9
        ]
      },
      "type": "Feature",
      "properties": {
        "hierarchy": [
          "tgn:7448322",
          "tgn:7019140",
          "tgn:7002444",
          "tgn:1000003",
          "tgn:7008591",
          "tgn:7029392"
        ],
        "placetype": [
          "aat:300008699"
        ],
        "name:en": "Tarf, Water of",
        "id": 7448322
      }
    },
    {
      "geometry": {
        "type": "Point",
        "coordinates": [
          -3.716667,
          56.883333
        ]
      },
      "type": "Feature",
      "properties": {
        "hierarchy": [
          "tgn:7448323",
          "tgn:7002444",
          "tgn:1000003",
          "tgn:7019152",
          "tgn:7008591",
          "tgn:7029392"
        ],
        "placetype": [
          "aat:300008736"
        ],
        "name:en": "Tarf, Falls of",
        "id": 7448323
      }
    },
    {
      "geometry": {
        "type": "Point",
        "coordinates": [
          -3.466667,
          51.916667
        ]
      },
      "type": "Feature",
      "properties": {
        "hierarchy": [
          "tgn:7448324",
          "tgn:7002443",
          "tgn:1000003",
          "tgn:7008050",
          "tgn:7008591",
          "tgn:7029392"
        ],
        "placetype": [
          "aat:300008761"
        ],
        "name:en": "Tarell, Glyn",
        "id": 7448324
      }
    },
    {
      "geometry": {
        "type": "Point",
        "coordinates": [
          -2,
          52.316667
        ]
      },
      "type": "Feature",
      "properties": {
        "hierarchy": [
          "tgn:7448325",
          "tgn:7002445",
          "tgn:1000003",
          "tgn:5000227",
          "tgn:7008591",
          "tgn:7029392"
        ],
        "placetype": [
          "aat:300008347"
        ],
        "name:en": "Tardebigge",
        "id": 7448325
      }
    },
    {
      "geometry": {
        "type": "Point",
        "coordinates": [
          -3.55,
          55.766667
        ]
      },
      "type": "Feature",
      "properties": {
        "hierarchy": [
          "tgn:7448326",
          "tgn:7002444",
          "tgn:1000003",
          "tgn:7019090",
          "tgn:7008591",
          "tgn:7029392"
        ],
        "placetype": [
          "aat:300008347"
        ],
        "name:en": "Tarbrax",
        "id": 7448326
      }
    }
  ]
}
