{
  "geometry": {
    "type": "Point",
    "coordinates": [
      2.966667,
      39.35
    ]
  },
  "type": "Feature",
  "properties": {
    "hierarchy": [
      "tgn:7329637",
      "tgn:7001122",
      "tgn:1000003",
      "tgn:7002765",
      "tgn:1000095",
      "tgn:7029392"
    ],
    "placetype": [
      "aat:300008816"
    ],
    "id": 7329637,
    "name:xx": "Rápita, Arenal de la"
  }
}
