{
  "geometry": {
    "type": "Point",
    "coordinates": [
      -93.1167,
      37.8833
    ]
  },
  "type": "Feature",
  "properties": {
    "hierarchy": [
      "tgn:2313951",
      "tgn:1000001",
      "tgn:7012149",
      "tgn:2001192",
      "tgn:7007523",
      "tgn:7029392"
    ],
    "placetype": [
      "aat:300008347"
    ],
    "id": 2313951,
    "name:xx": "Elixer"
  }
}
