{
  "geometry": {
    "type": "Point",
    "coordinates": [
      -84.0833,
      40.65
    ]
  },
  "type": "Feature",
  "properties": {
    "hierarchy": [
      "tgn:2458712",
      "tgn:1000001",
      "tgn:7012149",
      "tgn:7007706",
      "tgn:7029392"
    ],
    "placetype": [
      "aat:300008707"
    ],
    "id": 2458712,
    "name:xx": "Little Ottawa River"
  }
}
