{
  "geometry": {
    "type": "Point",
    "coordinates": [
      33.934444,
      29.1125
    ]
  },
  "type": "Feature",
  "properties": {
    "hierarchy": [
      "tgn:7533822",
      "tgn:7001242",
      "tgn:7016833",
      "tgn:7001336",
      "tgn:7029392"
    ],
    "placetype": [
      "aat:300379998"
    ],
    "name:en": "Harab, Wâdi",
    "id": 7533822
  }
}
