{
  "geometry": {
    "type": "Point",
    "coordinates": [
      40.0333,
      49.35
    ]
  },
  "type": "Feature",
  "properties": {
    "hierarchy": [
      "tgn:1061035",
      "tgn:1000003",
      "tgn:7012067",
      "tgn:7006660",
      "tgn:7029392"
    ],
    "placetype": [
      "aat:300008347"
    ],
    "id": 1061035,
    "name:xx": "Velykots'k"
  }
}
