{
  "geometry": {
    "type": "Point",
    "coordinates": [
      -110.1167,
      45.75
    ]
  },
  "type": "Feature",
  "properties": {
    "hierarchy": [
      "tgn:2222145",
      "tgn:1000001",
      "tgn:7012149",
      "tgn:2001308",
      "tgn:7007524",
      "tgn:7029392"
    ],
    "placetype": [
      "aat:300008347"
    ],
    "id": 2222145,
    "name:xx": "Carney"
  }
}
