{
  "type": "FeatureCollection",
  "features": [
    {
      "geometry": {
        "type": "Point",
        "coordinates": [
          -100.716667,
          28.083333
        ]
      },
      "type": "Feature",
      "properties": {
        "hierarchy": [
          "tgn:7367850",
          "tgn:1001853",
          "tgn:1000001",
          "tgn:7005560",
          "tgn:7029392"
        ],
        "placetype": [
          "aat:300008347"
        ],
        "id": 7367850,
        "name:xx": "El Potrero"
      }
    },
    {
      "geometry": {
        "type": "Point",
        "coordinates": [
          -107.45,
          28.016667
        ]
      },
      "type": "Feature",
      "properties": {
        "hierarchy": [
          "tgn:7367851",
          "tgn:7005581",
          "tgn:1000001",
          "tgn:7005560",
          "tgn:7029392"
        ],
        "placetype": [
          "aat:300008347"
        ],
        "id": 7367851,
        "name:xx": "El Potrero"
      }
    },
    {
      "geometry": {
        "type": "Point",
        "coordinates": [
          -107.983333,
          27.85
        ]
      },
      "type": "Feature",
      "properties": {
        "hierarchy": [
          "tgn:7367852",
          "tgn:7005581",
          "tgn:1000001",
          "tgn:7005560",
          "tgn:7029392"
        ],
        "placetype": [
          "aat:300008347"
        ],
        "id": 7367852,
        "name:xx": "El Potrero"
      }
    },
    {
      "geometry": {
        "type": "Point",
        "coordinates": [
          -101.433333,
          27.766667
        ]
      },
      "type": "Feature",
      "properties": {
        "hierarchy": [
          "tgn:7367854",
          "tgn:1001853",
          "tgn:1000001",
          "tgn:7005560",
          "tgn:7029392"
        ],
        "placetype": [
          "aat:300008347"
        ],
        "id": 7367854,
        "name:xx": "El Potrero"
      }
    },
    {
      "geometry": {
        "type": "Point",
        "coordinates": [
          -107.65,
          27.1
        ]
      },
      "type": "Feature",
      "properties": {
        "hierarchy": [
          "tgn:7367855",
          "tgn:7005581",
          "tgn:1000001",
          "tgn:7005560",
          "tgn:7029392"
        ],
        "placetype": [
          "aat:300008347"
        ],
        "id": 7367855,
        "name:xx": "El Potrero"
      }
    },
    {
      "geometry": {
        "type": "Point",
        "coordinates": [
          -107.766667,
          26.9
        ]
      },
      "type": "Feature",
      "properties": {
        "hierarchy": [
          "tgn:7367856",
          "tgn:7005581",
          "tgn:1000001",
          "tgn:7005560",
          "tgn:7029392"
        ],
        "placetype": [
          "aat:300008347"
        ],
        "id": 7367856,
        "name:xx": "El Potrero"
      }
    },
    {
      "geometry": {
        "type": "Point",
        "coordinates": [
          -112.05,
          26.65
        ]
      },
      "type": "Feature",
      "properties": {
        "hierarchy": [
          "tgn:7367857",
          "tgn:1001836",
          "tgn:1000001",
          "tgn:7005560",
          "tgn:7029392"
        ],
        "placetype": [
          "aat:300008347"
        ],
        "id": 7367857,
        "name:xx": "El Potrero"
      }
    },
    {
      "geometry": {
        "type": "Point",
        "coordinates": [
          -107.666667,
          26.65
        ]
      },
      "type": "Feature",
      "properties": {
        "hierarchy": [
          "tgn:7367858",
          "tgn:7005581",
          "tgn:1000001",
          "tgn:7005560",
          "tgn:7029392"
        ],
        "placetype": [
          "aat:300008347"
        ],
        "id": 7367858,
        "name:xx": "El Potrero"
      }
    }
  ]
}
