{
  "geometry": {
    "type": "Point",
    "coordinates": [
      -122.1667,
      47.9833
    ]
  },
  "type": "Feature",
  "properties": {
    "hierarchy": [
      "tgn:2692577",
      "tgn:1000001",
      "tgn:7012149",
      "tgn:1002899",
      "tgn:7007920",
      "tgn:7029392"
    ],
    "placetype": [
      "aat:300008699"
    ],
    "id": 2692577,
    "name:xx": "Steamboat Slough"
  }
}
