{
  "geometry": {
    "type": "Point",
    "coordinates": [
      -96.2167,
      31.4833
    ]
  },
  "type": "Feature",
  "properties": {
    "hierarchy": [
      "tgn:2161011",
      "tgn:1000001",
      "tgn:7012149",
      "tgn:1002391",
      "tgn:7007826",
      "tgn:7029392"
    ],
    "placetype": [
      "aat:300008699"
    ],
    "id": 2161011,
    "name:xx": "Bell Branch"
  }
}
