{
  "geometry": {
    "type": "Point",
    "coordinates": [
      -83.5333,
      46.0167
    ]
  },
  "type": "Feature",
  "properties": {
    "hierarchy": [
      "tgn:2640994",
      "tgn:1000001",
      "tgn:2000952",
      "tgn:7012149",
      "tgn:7007520",
      "tgn:7029392"
    ],
    "placetype": [
      "aat:300132316"
    ],
    "id": 2640994,
    "name:xx": "Sand Bay"
  }
}
