{
  "geometry": {
    "type": "Point",
    "coordinates": [
      82.988555,
      23.64956
    ]
  },
  "type": "Feature",
  "properties": {
    "hierarchy": [
      "tgn:7557017",
      "tgn:1000004",
      "tgn:7031781",
      "tgn:7000198",
      "tgn:7029392"
    ],
    "placetype": [
      "aat:300008347"
    ],
    "name:en": "Rāmkola",
    "id": 7557017
  }
}
