{
  "type": "FeatureCollection",
  "features": [
    {
      "geometry": {
        "type": "Point",
        "coordinates": [
          -82.2833,
          37.8833
        ]
      },
      "type": "Feature",
      "properties": {
        "hierarchy": [
          "tgn:2193250",
          "tgn:1000001",
          "tgn:7012149",
          "tgn:2002280",
          "tgn:7013961",
          "tgn:7029392"
        ],
        "placetype": [
          "aat:300008706"
        ],
        "id": 2193250,
        "name:xx": "Breeden Creek"
      }
    },
    {
      "geometry": {
        "type": "Point",
        "coordinates": [
          -84.3333,
          36.0667
        ]
      },
      "type": "Feature",
      "properties": {
        "hierarchy": [
          "tgn:2193251",
          "tgn:1000001",
          "tgn:7012149",
          "tgn:7007825",
          "tgn:7029392"
        ],
        "placetype": [
          "aat:300008761"
        ],
        "id": 2193251,
        "name:xx": "Breeden Hollow"
      }
    },
    {
      "geometry": {
        "type": "Point",
        "coordinates": [
          -84.8,
          35.4667
        ]
      },
      "type": "Feature",
      "properties": {
        "hierarchy": [
          "tgn:2193252",
          "tgn:1000001",
          "tgn:7012149",
          "tgn:2001897",
          "tgn:7007825",
          "tgn:7029392"
        ],
        "placetype": [
          "aat:300006191"
        ],
        "id": 2193252,
        "name:xx": "Breeden Pond"
      }
    },
    {
      "geometry": {
        "type": "Point",
        "coordinates": [
          -91.8333,
          35.8833
        ]
      },
      "type": "Feature",
      "properties": {
        "hierarchy": [
          "tgn:2193253",
          "tgn:1000001",
          "tgn:7016172",
          "tgn:7012149",
          "tgn:2000137",
          "tgn:7029392"
        ],
        "placetype": [
          "aat:300000390"
        ],
        "id": 2193253,
        "name:xx": "Breeden Prospect"
      }
    },
    {
      "geometry": {
        "type": "Point",
        "coordinates": [
          -82.9667,
          36.9
        ]
      },
      "type": "Feature",
      "properties": {
        "hierarchy": [
          "tgn:2193254",
          "tgn:1000001",
          "tgn:7012149",
          "tgn:2000797",
          "tgn:7007255",
          "tgn:7029392"
        ],
        "placetype": [
          "aat:300008706"
        ],
        "id": 2193254,
        "name:xx": "Breedens Creek"
      }
    },
    {
      "geometry": {
        "type": "Point",
        "coordinates": [
          -76.4833,
          38.4
        ]
      },
      "type": "Feature",
      "properties": {
        "hierarchy": [
          "tgn:2193255",
          "tgn:1002224",
          "tgn:1000001",
          "tgn:7012149",
          "tgn:7007516",
          "tgn:7029392"
        ],
        "placetype": [
          "aat:300008850"
        ],
        "id": 2193255,
        "name:xx": "Breedens Point"
      }
    },
    {
      "geometry": {
        "type": "Point",
        "coordinates": [
          -84.8,
          35.5333
        ]
      },
      "type": "Feature",
      "properties": {
        "hierarchy": [
          "tgn:2193256",
          "tgn:1000001",
          "tgn:7012149",
          "tgn:2001897",
          "tgn:7007825",
          "tgn:7029392"
        ],
        "placetype": [
          "aat:300008347"
        ],
        "id": 2193256,
        "name:xx": "Breedenton"
      }
    },
    {
      "geometry": {
        "type": "Point",
        "coordinates": [
          -82.9167,
          37.2167
        ]
      },
      "type": "Feature",
      "properties": {
        "hierarchy": [
          "tgn:2193257",
          "tgn:1000001",
          "tgn:7012149",
          "tgn:2000805",
          "tgn:7007255",
          "tgn:7029392"
        ],
        "placetype": [
          "aat:300008699"
        ],
        "id": 2193257,
        "name:xx": "Breeding Branch"
      }
    },
    {
      "geometry": {
        "type": "Point",
        "coordinates": [
          -82.9,
          37.2
        ]
      },
      "type": "Feature",
      "properties": {
        "hierarchy": [
          "tgn:2193258",
          "tgn:1000001",
          "tgn:7012149",
          "tgn:2000805",
          "tgn:7007255",
          "tgn:7029392"
        ],
        "placetype": [
          "aat:300008706"
        ],
        "id": 2193258,
        "name:xx": "Breeding Creek"
      }
    },
    {
      "geometry": {
        "type": "Point",
        "coordinates": [
          -86.3,
          41.2833
        ]
      },
      "type": "Feature",
      "properties": {
        "hierarchy": [
          "tgn:2193259",
          "tgn:1000001",
          "tgn:7012149",
          "tgn:1002640",
          "tgn:7007252",
          "tgn:7029392"
        ],
        "placetype": [
          "aat:300006075"
        ],
        "id": 2193259,
        "name:xx": "Breeding Ditch"
      }
    }
  ]
}
