{
  "geometry": {
    "type": "Point",
    "coordinates": [
      -149.75,
      60.9667
    ]
  },
  "type": "Feature",
  "properties": {
    "hierarchy": [
      "tgn:2368789",
      "tgn:7006450",
      "tgn:1000001",
      "tgn:7019698",
      "tgn:7012149",
      "tgn:7029392"
    ],
    "placetype": [
      "aat:300008850"
    ],
    "id": 2368789,
    "name:xx": "Gull Rock"
  }
}
