{
  "type": "FeatureCollection",
  "features": [
    {
      "geometry": {
        "type": "Point",
        "coordinates": [
          -89.0333,
          35.7833
        ]
      },
      "type": "Feature",
      "properties": {
        "hierarchy": [
          "tgn:2098320",
          "tgn:1000001",
          "tgn:7012149",
          "tgn:2001853",
          "tgn:7007825",
          "tgn:7029392"
        ],
        "placetype": [
          "aat:300008347"
        ],
        "id": 2098320,
        "name:xx": "Center"
      }
    },
    {
      "geometry": {
        "type": "Point",
        "coordinates": [
          -84.35,
          35.4667
        ]
      },
      "type": "Feature",
      "properties": {
        "hierarchy": [
          "tgn:2098321",
          "tgn:1000001",
          "tgn:7012149",
          "tgn:2001898",
          "tgn:7007825",
          "tgn:7029392"
        ],
        "placetype": [
          "aat:300008347",
          "aat:300387210"
        ],
        "id": 2098321,
        "name:xx": "Center"
      }
    },
    {
      "geometry": {
        "type": "Point",
        "coordinates": [
          -86.2167,
          35.2833
        ]
      },
      "type": "Feature",
      "properties": {
        "hierarchy": [
          "tgn:2098322",
          "tgn:1000001",
          "tgn:7012149",
          "tgn:2001862",
          "tgn:7007825",
          "tgn:7029392"
        ],
        "placetype": [
          "aat:300008347",
          "aat:300387210"
        ],
        "id": 2098322,
        "name:xx": "Center Grove"
      }
    },
    {
      "geometry": {
        "type": "Point",
        "coordinates": [
          -85.6,
          36.25
        ]
      },
      "type": "Feature",
      "properties": {
        "hierarchy": [
          "tgn:2098323",
          "tgn:1000001",
          "tgn:7012149",
          "tgn:2001880",
          "tgn:7007825",
          "tgn:7029392"
        ],
        "placetype": [
          "aat:300008347",
          "aat:300387210"
        ],
        "id": 2098323,
        "name:xx": "Center Grove"
      }
    },
    {
      "geometry": {
        "type": "Point",
        "coordinates": [
          -85.6333,
          35.55
        ]
      },
      "type": "Feature",
      "properties": {
        "hierarchy": [
          "tgn:2098324",
          "tgn:1000001",
          "tgn:7012149",
          "tgn:2001925",
          "tgn:7007825",
          "tgn:7029392"
        ],
        "placetype": [
          "aat:300008347",
          "aat:300387210"
        ],
        "id": 2098324,
        "name:xx": "Center Hill"
      }
    },
    {
      "geometry": {
        "type": "Point",
        "coordinates": [
          -85.95,
          35.7833
        ]
      },
      "type": "Feature",
      "properties": {
        "hierarchy": [
          "tgn:2098325",
          "tgn:1000001",
          "tgn:7012149",
          "tgn:2001844",
          "tgn:7007825",
          "tgn:7029392"
        ],
        "placetype": [
          "aat:300008347",
          "aat:300387210"
        ],
        "id": 2098325,
        "name:xx": "Center Hill"
      }
    },
    {
      "geometry": {
        "type": "Point",
        "coordinates": [
          -85.3667,
          35.3167
        ]
      },
      "type": "Feature",
      "properties": {
        "hierarchy": [
          "tgn:2098326",
          "tgn:1000001",
          "tgn:7012149",
          "tgn:2001913",
          "tgn:7007825",
          "tgn:7029392"
        ],
        "placetype": [
          "aat:300008347",
          "aat:300387210"
        ],
        "id": 2098326,
        "name:xx": "Center Point"
      }
    },
    {
      "geometry": {
        "type": "Point",
        "coordinates": [
          -85.6,
          35.8833
        ]
      },
      "type": "Feature",
      "properties": {
        "hierarchy": [
          "tgn:2098327",
          "tgn:1000001",
          "tgn:7012149",
          "tgn:2001929",
          "tgn:7007825",
          "tgn:7029392"
        ],
        "placetype": [
          "aat:300008347",
          "aat:300387210"
        ],
        "id": 2098327,
        "name:xx": "Center Point"
      }
    }
  ]
}
