{
  "geometry": {
    "type": "Point",
    "coordinates": [
      28.85,
      -27.5167
    ]
  },
  "type": "Feature",
  "properties": {
    "hierarchy": [
      "tgn:1093570",
      "tgn:7001242",
      "tgn:7016562",
      "tgn:1000193",
      "tgn:7029392"
    ],
    "placetype": [
      "aat:300008347"
    ],
    "id": 1093570,
    "name:xx": "Roadside"
  }
}
