{
  "geometry": {
    "type": "Point",
    "coordinates": [
      32.701,
      28.714
    ]
  },
  "type": "Feature",
  "properties": {
    "hierarchy": [
      "tgn:1111480",
      "tgn:7001242",
      "tgn:7001311",
      "tgn:7016833",
      "tgn:7029392"
    ],
    "placetype": [
      "aat:300008773",
      "aat:300379998"
    ],
    "name:en": "Dakhal, Wādī ad",
    "id": 1111480
  }
}
