{
  "geometry": {
    "type": "Point",
    "coordinates": [
      -88.9333,
      43.8333
    ]
  },
  "type": "Feature",
  "properties": {
    "hierarchy": [
      "tgn:2587585",
      "tgn:1000001",
      "tgn:2002325",
      "tgn:7012149",
      "tgn:7007922",
      "tgn:7029392"
    ],
    "placetype": [
      "aat:300008850"
    ],
    "id": 2587585,
    "name:xx": "Pleasant Point"
  }
}
