{
  "geometry": {
    "type": "Point",
    "coordinates": [
      -121.05,
      40.5333
    ]
  },
  "type": "Feature",
  "properties": {
    "hierarchy": [
      "tgn:2777012",
      "tgn:1000001",
      "tgn:7012149",
      "tgn:7007157",
      "tgn:2000184",
      "tgn:7029392"
    ],
    "placetype": [
      "aat:300386845"
    ],
    "id": 2777012,
    "name:xx": "Windy Hollow"
  }
}
