{
  "geometry": {
    "type": "Point",
    "coordinates": [
      29.8667,
      40.2333
    ]
  },
  "type": "Feature",
  "properties": {
    "hierarchy": [
      "tgn:1085868",
      "tgn:1001125",
      "tgn:1000004",
      "tgn:7018450",
      "tgn:1000144",
      "tgn:7029392"
    ],
    "placetype": [
      "aat:300008347"
    ],
    "id": 1085868,
    "name:xx": "İlyasbey"
  }
}
