{
  "geometry": {
    "type": "Point",
    "coordinates": [
      -102.2833,
      48.7667
    ]
  },
  "type": "Feature",
  "properties": {
    "hierarchy": [
      "tgn:2697252",
      "tgn:1000001",
      "tgn:7012149",
      "tgn:7007705",
      "tgn:7029392"
    ],
    "placetype": [
      "aat:300008706"
    ],
    "id": 2697252,
    "name:xx": "Stony Creek"
  }
}
