{
  "geometry": {
    "type": "Point",
    "coordinates": [
      -92.1333,
      31.4167
    ]
  },
  "type": "Feature",
  "properties": {
    "hierarchy": [
      "tgn:2130502",
      "tgn:1000001",
      "tgn:7012149",
      "tgn:2000883",
      "tgn:7007256",
      "tgn:7029392"
    ],
    "placetype": [
      "aat:300008699"
    ],
    "id": 2130502,
    "name:xx": "Alligator Bayou"
  }
}
