{
  "geometry": {
    "type": "Point",
    "coordinates": [
      -88.9167,
      16.8333
    ]
  },
  "type": "Feature",
  "properties": {
    "hierarchy": [
      "tgn:7005357",
      "tgn:7005346",
      "tgn:1000001",
      "tgn:7029392"
    ],
    "placetype": [
      "aat:300387064",
      "aat:300387081"
    ],
    "id": 7005357,
    "name:xx": "Cayo"
  }
}
