{
  "geometry": {
    "type": "Point",
    "coordinates": [
      31.279004,
      30.071334
    ]
  },
  "type": "Feature",
  "properties": {
    "hierarchy": [
      "tgn:7526775",
      "tgn:7001242",
      "tgn:7016833",
      "tgn:1001091",
      "tgn:7029392"
    ],
    "placetype": [
      "aat:300006676"
    ],
    "id": 7526775,
    "name:xx": "Mustashfá Dār ash Shifā'"
  }
}
