{
  "geometry": {
    "type": "Point",
    "coordinates": [
      -111.9667,
      46.4833
    ]
  },
  "type": "Feature",
  "properties": {
    "hierarchy": [
      "tgn:2334494",
      "tgn:1000001",
      "tgn:7012149",
      "tgn:2001281",
      "tgn:7007524",
      "tgn:7029392"
    ],
    "placetype": [
      "aat:300000390"
    ],
    "id": 2334494,
    "name:xx": "Forest Park Mine"
  }
}
