{
  "geometry": {
    "type": "Point",
    "coordinates": [
      -106.6667,
      34.7667
    ]
  },
  "type": "Feature",
  "properties": {
    "hierarchy": [
      "tgn:2312683",
      "tgn:1000001",
      "tgn:7012149",
      "tgn:2001460",
      "tgn:7007566",
      "tgn:7029392"
    ],
    "placetype": [
      "aat:300006075"
    ],
    "id": 2312683,
    "name:xx": "El Cerro Ditch"
  }
}
