{
  "geometry": {
    "type": "Point",
    "coordinates": [
      -119.4667,
      36.5833
    ]
  },
  "type": "Feature",
  "properties": {
    "hierarchy": [
      "tgn:2305265",
      "tgn:1000001",
      "tgn:7012149",
      "tgn:1002392",
      "tgn:7007157",
      "tgn:7029392"
    ],
    "placetype": [
      "aat:300006075"
    ],
    "id": 2305265,
    "name:xx": "East Branch Smith Ferry Canal"
  }
}
