{
  "geometry": {
    "type": "Point",
    "coordinates": [
      -103.6833,
      46.2667
    ]
  },
  "type": "Feature",
  "properties": {
    "hierarchy": [
      "tgn:2142432",
      "tgn:1000001",
      "tgn:7012149",
      "tgn:7007705",
      "tgn:7029392"
    ],
    "placetype": [
      "aat:300008706"
    ],
    "id": 2142432,
    "name:xx": "Bacon Creek"
  }
}
