{
  "geometry": {
    "type": "Point",
    "coordinates": [
      17.2333,
      60.3833
    ]
  },
  "type": "Feature",
  "properties": {
    "hierarchy": [
      "tgn:1063541",
      "tgn:1000003",
      "tgn:1000462",
      "tgn:1000097",
      "tgn:7029392"
    ],
    "placetype": [
      "aat:300008347"
    ],
    "id": 1063541,
    "name:xx": "Söderfors"
  }
}
