{
  "geometry": {
    "type": "Point",
    "coordinates": [
      -120.5333,
      41.9667
    ]
  },
  "type": "Feature",
  "properties": {
    "hierarchy": [
      "tgn:2507142",
      "tgn:1000001",
      "tgn:7012149",
      "tgn:7007157",
      "tgn:2000186",
      "tgn:7029392"
    ],
    "placetype": [
      "aat:300006191"
    ],
    "id": 2507142,
    "name:xx": "Meteorite Tank"
  }
}
