{
  "geometry": {
    "type": "Point",
    "coordinates": [
      -85.9833,
      34.8333
    ]
  },
  "type": "Feature",
  "properties": {
    "hierarchy": [
      "tgn:2373219",
      "tgn:7002659",
      "tgn:1000001",
      "tgn:7012149",
      "tgn:2000035",
      "tgn:7029392"
    ],
    "placetype": [
      "aat:300008746"
    ],
    "id": 2373219,
    "name:xx": "Halo Cave"
  }
}
