{
  "geometry": {
    "type": "Point",
    "coordinates": [
      79.257679,
      26.27232
    ]
  },
  "type": "Feature",
  "properties": {
    "hierarchy": [
      "tgn:7564776",
      "tgn:1000004",
      "tgn:7000198",
      "tgn:7016722",
      "tgn:7029392"
    ],
    "placetype": [
      "aat:300008347"
    ],
    "name:en": "Rupāpur",
    "id": 7564776
  }
}
