{
  "geometry": {
    "type": "Point",
    "coordinates": [
      -71.6167,
      -42.8833
    ]
  },
  "type": "Feature",
  "properties": {
    "hierarchy": [
      "tgn:1019651",
      "tgn:7006477",
      "tgn:1001203",
      "tgn:1000002",
      "tgn:7029392"
    ],
    "placetype": [
      "aat:300008347"
    ],
    "id": 1019651,
    "name:xx": "Lago Futalaufquen"
  }
}
