{
  "geometry": {
    "type": "Point",
    "coordinates": [
      -109.1667,
      38.8167
    ]
  },
  "type": "Feature",
  "properties": {
    "hierarchy": [
      "tgn:2647047",
      "tgn:1000001",
      "tgn:7012149",
      "tgn:2002110",
      "tgn:7007827",
      "tgn:7029392"
    ],
    "placetype": [
      "aat:300008798"
    ],
    "id": 2647047,
    "name:xx": "Scharf Mesa"
  }
}
