{
  "geometry": {
    "type": "Point",
    "coordinates": [
      -122.15,
      38.6833
    ]
  },
  "type": "Feature",
  "properties": {
    "hierarchy": [
      "tgn:2230175",
      "tgn:1000001",
      "tgn:7012149",
      "tgn:7007157",
      "tgn:1003046",
      "tgn:7029392"
    ],
    "placetype": [
      "aat:300008697"
    ],
    "id": 2230175,
    "name:xx": "Cement Spring"
  }
}
