{
  "geometry": {
    "type": "Point",
    "coordinates": [
      -72.5833,
      40.8167
    ]
  },
  "type": "Feature",
  "properties": {
    "hierarchy": [
      "tgn:2575086",
      "tgn:1000001",
      "tgn:7012149",
      "tgn:1002924",
      "tgn:7007568",
      "tgn:7029392"
    ],
    "placetype": [
      "aat:300132316"
    ],
    "id": 2575086,
    "name:xx": "Penniman Cove"
  }
}
