{
  "geometry": {
    "type": "Point",
    "coordinates": [
      120.955,
      23.095
    ]
  },
  "type": "Feature",
  "properties": {
    "hierarchy": [
      "tgn:7471475",
      "tgn:1000004",
      "tgn:7491221",
      "tgn:1000141",
      "tgn:7029392"
    ],
    "placetype": [
      "aat:300008798"
    ],
    "id": 7471475,
    "name:xx": "Zhouxi Shan"
  }
}
