{
  "geometry": {
    "type": "Point",
    "coordinates": [
      -93.3667,
      40.6833
    ]
  },
  "type": "Feature",
  "properties": {
    "hierarchy": [
      "tgn:2509177",
      "tgn:1000001",
      "tgn:7012149",
      "tgn:7029392"
    ],
    "placetype": [
      "aat:300008706"
    ],
    "id": 2509177,
    "name:xx": "Middle Fork Medicine Creek"
  }
}
