{
  "geometry": {
    "type": "Point",
    "coordinates": [
      -82.5833,
      34.6833
    ]
  },
  "type": "Feature",
  "properties": {
    "hierarchy": [
      "tgn:2217827",
      "tgn:2001728",
      "tgn:1000001",
      "tgn:7012149",
      "tgn:7007712",
      "tgn:7029392"
    ],
    "placetype": [
      "aat:300006191"
    ],
    "id": 2217827,
    "name:xx": "Campbells Lake"
  }
}
