{
  "geometry": {
    "type": "Point",
    "coordinates": [
      -111.4833,
      39.25
    ]
  },
  "type": "Feature",
  "properties": {
    "hierarchy": [
      "tgn:2707821",
      "tgn:1000001",
      "tgn:7012149",
      "tgn:2002120",
      "tgn:7007827",
      "tgn:7029392"
    ],
    "placetype": [
      "aat:300008697"
    ],
    "id": 2707821,
    "name:xx": "Swens Spring"
  }
}
