{
  "geometry": {
    "type": "Point",
    "coordinates": [
      -68.2167,
      -38.7167
    ]
  },
  "type": "Feature",
  "properties": {
    "hierarchy": [
      "tgn:1019201",
      "tgn:7006477",
      "tgn:7006348",
      "tgn:1000002",
      "tgn:7029392"
    ],
    "placetype": [
      "aat:300008347"
    ],
    "id": 1019201,
    "name:xx": "Barda del Medio"
  }
}
