{
  "type": "FeatureCollection",
  "features": [
    {
      "geometry": {
        "type": "Point",
        "coordinates": [
          -110.45,
          33.3
        ]
      },
      "type": "Feature",
      "properties": {
        "hierarchy": [
          "tgn:2007132",
          "tgn:1000001",
          "tgn:7006451",
          "tgn:2000093",
          "tgn:7012149",
          "tgn:7029392"
        ],
        "placetype": [
          "aat:300008347"
        ],
        "id": 2007132,
        "name:xx": "Peridot"
      }
    },
    {
      "geometry": {
        "type": "Point",
        "coordinates": [
          -112.1833,
          34.9
        ]
      },
      "type": "Feature",
      "properties": {
        "hierarchy": [
          "tgn:2007133",
          "tgn:1000001",
          "tgn:7006451",
          "tgn:7012149",
          "tgn:2000103",
          "tgn:7029392"
        ],
        "placetype": [
          "aat:300008347",
          "aat:300387210"
        ],
        "id": 2007133,
        "name:xx": "Perkinsville"
      }
    },
    {
      "geometry": {
        "type": "Point",
        "coordinates": [
          -112.45,
          33.4333
        ]
      },
      "type": "Feature",
      "properties": {
        "hierarchy": [
          "tgn:2007135",
          "tgn:1000001",
          "tgn:7006451",
          "tgn:7012149",
          "tgn:2000097",
          "tgn:7029392"
        ],
        "placetype": [
          "aat:300008347",
          "aat:300387210"
        ],
        "id": 2007135,
        "name:xx": "Perryville"
      }
    },
    {
      "geometry": {
        "type": "Point",
        "coordinates": [
          -111.9333,
          33.3667
        ]
      },
      "type": "Feature",
      "properties": {
        "hierarchy": [
          "tgn:2007136",
          "tgn:1000001",
          "tgn:7006451",
          "tgn:7012149",
          "tgn:2000097",
          "tgn:7029392"
        ],
        "placetype": [
          "aat:300387016"
        ],
        "id": 2007136,
        "name:xx": "Peterson"
      }
    }
  ]
}
