{
  "geometry": {
    "type": "Point",
    "coordinates": [
      -124.0833,
      43.8833
    ]
  },
  "type": "Feature",
  "properties": {
    "hierarchy": [
      "tgn:2436613",
      "tgn:1000001",
      "tgn:7012149",
      "tgn:2001716",
      "tgn:7007708",
      "tgn:7029392"
    ],
    "placetype": [
      "aat:300132316"
    ],
    "id": 2436613,
    "name:xx": "Kiechle Arm"
  }
}
