{
  "geometry": {
    "type": "Point",
    "coordinates": [
      -77.5333,
      36.8167
    ]
  },
  "type": "Feature",
  "properties": {
    "hierarchy": [
      "tgn:2325825",
      "tgn:1000001",
      "tgn:7012149",
      "tgn:1002425",
      "tgn:7007919",
      "tgn:7029392"
    ],
    "placetype": [
      "aat:300008347"
    ],
    "id": 2325825,
    "name:xx": "Fields Crossroads"
  }
}
