{
  "geometry": {
    "type": "Point",
    "coordinates": [
      -75.8667,
      41.1667
    ]
  },
  "type": "Feature",
  "properties": {
    "hierarchy": [
      "tgn:2090964",
      "tgn:1000001",
      "tgn:7012149",
      "tgn:1002612",
      "tgn:7007710",
      "tgn:7029392"
    ],
    "placetype": [
      "aat:300008347"
    ],
    "id": 2090964,
    "name:xx": "Mountain Top"
  }
}
