{
  "geometry": {
    "type": "Point",
    "coordinates": [
      51.35,
      35.65
    ]
  },
  "type": "Feature",
  "properties": {
    "hierarchy": [
      "tgn:1079351",
      "tgn:1000004",
      "tgn:7002004",
      "tgn:7000231",
      "tgn:7029392"
    ],
    "placetype": [
      "aat:300008347"
    ],
    "id": 1079351,
    "name:xx": "Wasfanārd"
  }
}
