{
  "geometry": {
    "type": "Point",
    "coordinates": [
      -116.55,
      33.4333
    ]
  },
  "type": "Feature",
  "properties": {
    "hierarchy": [
      "tgn:2569220",
      "tgn:1000001",
      "tgn:7012149",
      "tgn:7007157",
      "tgn:1002828",
      "tgn:7029392"
    ],
    "placetype": [
      "aat:300008761"
    ],
    "id": 2569220,
    "name:xx": "Parks Canyon"
  }
}
