{
  "type": "FeatureCollection",
  "features": [
    {
      "geometry": {
        "type": "Point",
        "coordinates": [
          -89.8167,
          31.2833
        ]
      },
      "type": "Feature",
      "properties": {
        "hierarchy": [
          "tgn:2175150",
          "tgn:1000001",
          "tgn:7012149",
          "tgn:2001131",
          "tgn:7007522",
          "tgn:7029392"
        ],
        "placetype": [
          "aat:300008699"
        ],
        "id": 2175150,
        "name:xx": "Black Branch"
      }
    },
    {
      "geometry": {
        "type": "Point",
        "coordinates": [
          -89.1167,
          31.8
        ]
      },
      "type": "Feature",
      "properties": {
        "hierarchy": [
          "tgn:2175151",
          "tgn:1000001",
          "tgn:7012149",
          "tgn:2001119",
          "tgn:7007522",
          "tgn:7029392"
        ],
        "placetype": [
          "aat:300008699"
        ],
        "id": 2175151,
        "name:xx": "Black Branch"
      }
    },
    {
      "geometry": {
        "type": "Point",
        "coordinates": [
          -89.6833,
          33.05
        ]
      },
      "type": "Feature",
      "properties": {
        "hierarchy": [
          "tgn:2175152",
          "tgn:2001089",
          "tgn:1000001",
          "tgn:7012149",
          "tgn:7007522",
          "tgn:7029392"
        ],
        "placetype": [
          "aat:300008699"
        ],
        "id": 2175152,
        "name:xx": "Black Branch"
      }
    },
    {
      "geometry": {
        "type": "Point",
        "coordinates": [
          -88.4833,
          34.1833
        ]
      },
      "type": "Feature",
      "properties": {
        "hierarchy": [
          "tgn:2175153",
          "tgn:1000001",
          "tgn:7012149",
          "tgn:2001114",
          "tgn:7007522",
          "tgn:7029392"
        ],
        "placetype": [
          "aat:300008699"
        ],
        "id": 2175153,
        "name:xx": "Black Branch"
      }
    },
    {
      "geometry": {
        "type": "Point",
        "coordinates": [
          -88.2667,
          34.7
        ]
      },
      "type": "Feature",
      "properties": {
        "hierarchy": [
          "tgn:2175154",
          "tgn:1000001",
          "tgn:7012149",
          "tgn:2001156",
          "tgn:7007522",
          "tgn:7029392"
        ],
        "placetype": [
          "aat:300008699"
        ],
        "id": 2175154,
        "name:xx": "Black Branch"
      }
    },
    {
      "geometry": {
        "type": "Point",
        "coordinates": [
          -92.45,
          38.9333
        ]
      },
      "type": "Feature",
      "properties": {
        "hierarchy": [
          "tgn:2175155",
          "tgn:1000001",
          "tgn:1002190",
          "tgn:7012149",
          "tgn:7007523",
          "tgn:7029392"
        ],
        "placetype": [
          "aat:300008699"
        ],
        "id": 2175155,
        "name:xx": "Black Branch"
      }
    },
    {
      "geometry": {
        "type": "Point",
        "coordinates": [
          -91.85,
          37.1167
        ]
      },
      "type": "Feature",
      "properties": {
        "hierarchy": [
          "tgn:2175156",
          "tgn:1000001",
          "tgn:7012149",
          "tgn:2001252",
          "tgn:7007523",
          "tgn:7029392"
        ],
        "placetype": [
          "aat:300008699"
        ],
        "id": 2175156,
        "name:xx": "Black Branch"
      }
    },
    {
      "geometry": {
        "type": "Point",
        "coordinates": [
          -79.4167,
          34.6667
        ]
      },
      "type": "Feature",
      "properties": {
        "hierarchy": [
          "tgn:2175157",
          "tgn:1000001",
          "tgn:7012149",
          "tgn:2001534",
          "tgn:7007709",
          "tgn:7029392"
        ],
        "placetype": [
          "aat:300008699"
        ],
        "id": 2175157,
        "name:xx": "Black Branch"
      }
    },
    {
      "geometry": {
        "type": "Point",
        "coordinates": [
          -79.75,
          34.8833
        ]
      },
      "type": "Feature",
      "properties": {
        "hierarchy": [
          "tgn:2175158",
          "tgn:1000001",
          "tgn:7012149",
          "tgn:2001533",
          "tgn:7007709",
          "tgn:7029392"
        ],
        "placetype": [
          "aat:300008699"
        ],
        "id": 2175158,
        "name:xx": "Black Branch"
      }
    },
    {
      "geometry": {
        "type": "Point",
        "coordinates": [
          -77.05,
          35
        ]
      },
      "type": "Feature",
      "properties": {
        "hierarchy": [
          "tgn:2175159",
          "tgn:1000001",
          "tgn:7012149",
          "tgn:2001486",
          "tgn:7007709",
          "tgn:7029392"
        ],
        "placetype": [
          "aat:300008699"
        ],
        "id": 2175159,
        "name:xx": "Black Branch"
      }
    }
  ]
}
