{
  "geometry": {
    "type": "Point",
    "coordinates": [
      -156.8833,
      56.9333
    ]
  },
  "type": "Feature",
  "properties": {
    "hierarchy": [
      "tgn:2534907",
      "tgn:7006450",
      "tgn:1000001",
      "tgn:7030517",
      "tgn:7012149",
      "tgn:7029392"
    ],
    "placetype": [
      "aat:300132316"
    ],
    "id": 2534907,
    "name:xx": "Nakalilok Bay"
  }
}
