{
  "geometry": {
    "type": "Point",
    "coordinates": [
      -90.7833,
      36.6167
    ]
  },
  "type": "Feature",
  "properties": {
    "hierarchy": [
      "tgn:2685625",
      "tgn:1000001",
      "tgn:7012149",
      "tgn:2001237",
      "tgn:7007523",
      "tgn:7029392"
    ],
    "placetype": [
      "aat:300008706"
    ],
    "id": 2685625,
    "name:xx": "Spring Bluff Creek"
  }
}
