{
  "geometry": {
    "type": "Point",
    "coordinates": [
      35.64,
      30.642
    ]
  },
  "type": "Feature",
  "properties": {
    "hierarchy": [
      "tgn:7018402",
      "tgn:7018396",
      "tgn:1000004",
      "tgn:1000121",
      "tgn:7029392"
    ],
    "placetype": [
      "aat:300008347"
    ],
    "id": 7018402,
    "name:xx": "Al Qādisiyah"
  }
}
