{
  "geometry": {
    "type": "Point",
    "coordinates": [
      -111.25,
      44.9333
    ]
  },
  "type": "Feature",
  "properties": {
    "hierarchy": [
      "tgn:2668129",
      "tgn:1000001",
      "tgn:7012149",
      "tgn:2001275",
      "tgn:7007524",
      "tgn:7029392"
    ],
    "placetype": [
      "aat:300266640"
    ],
    "id": 2668129,
    "name:xx": "Skyline Ridge"
  }
}
