{
  "geometry": {
    "type": "Point",
    "coordinates": [
      -115.6667,
      40.3167
    ]
  },
  "type": "Feature",
  "properties": {
    "hierarchy": [
      "tgn:2341764",
      "tgn:1000001",
      "tgn:2001411",
      "tgn:7012149",
      "tgn:7007526",
      "tgn:7029392"
    ],
    "placetype": [
      "aat:300008697"
    ],
    "id": 2341764,
    "name:xx": "Frost Springs"
  }
}
