{
  "geometry": {
    "type": "Point",
    "coordinates": [
      25.100387,
      31.56699
    ]
  },
  "type": "Feature",
  "properties": {
    "hierarchy": [
      "tgn:7539071",
      "tgn:7001242",
      "tgn:7016833",
      "tgn:1001418",
      "tgn:7029392"
    ],
    "placetype": [
      "aat:300006909"
    ],
    "name:en": "Musā'id",
    "id": 7539071
  }
}
