{
  "geometry": {
    "type": "Point",
    "coordinates": [
      -108.6667,
      40.5667
    ]
  },
  "type": "Feature",
  "properties": {
    "hierarchy": [
      "tgn:2670575",
      "tgn:1000001",
      "tgn:7012149",
      "tgn:2000232",
      "tgn:7007158",
      "tgn:7029392"
    ],
    "placetype": [
      "aat:300008347"
    ],
    "id": 2670575,
    "name:xx": "Smelter Place"
  }
}
