{
  "geometry": {
    "type": "Point",
    "coordinates": [
      -72.9167,
      44.15
    ]
  },
  "type": "Feature",
  "properties": {
    "hierarchy": [
      "tgn:2449639",
      "tgn:1000001",
      "tgn:7012149",
      "tgn:7007828",
      "tgn:7029392"
    ],
    "placetype": [
      "aat:300008798"
    ],
    "id": 2449639,
    "name:xx": "Lincoln Mountain"
  }
}
