{
  "geometry": {
    "type": "Point",
    "coordinates": [
      -0.508,
      43.266
    ]
  },
  "type": "Feature",
  "properties": {
    "hierarchy": [
      "tgn:7029729",
      "tgn:7002878",
      "tgn:1000003",
      "tgn:1000070",
      "tgn:7029392"
    ],
    "placetype": [
      "aat:300008347"
    ],
    "name:fr": "Lacommande",
    "id": 7029729
  }
}
