{
  "type": "FeatureCollection",
  "features": [
    {
      "geometry": {
        "type": "Point",
        "coordinates": [
          -88.7167,
          32.5
        ]
      },
      "type": "Feature",
      "properties": {
        "hierarchy": [
          "tgn:2057120",
          "tgn:1000001",
          "tgn:7012149",
          "tgn:2001123",
          "tgn:7007522",
          "tgn:7029392"
        ],
        "placetype": [
          "aat:300008347"
        ],
        "id": 2057120,
        "name:xx": "Obadiah"
      }
    },
    {
      "geometry": {
        "type": "Point",
        "coordinates": [
          -89.0167,
          32.75
        ]
      },
      "type": "Feature",
      "properties": {
        "hierarchy": [
          "tgn:2057122",
          "tgn:1000001",
          "tgn:7012149",
          "tgn:2001135",
          "tgn:7007522",
          "tgn:7029392"
        ],
        "placetype": [
          "aat:300008347",
          "aat:300387210"
        ],
        "id": 2057122,
        "name:xx": "Ocobla"
      }
    },
    {
      "geometry": {
        "type": "Point",
        "coordinates": [
          -89.7,
          32.7
        ]
      },
      "type": "Feature",
      "properties": {
        "hierarchy": [
          "tgn:2057123",
          "tgn:1000001",
          "tgn:7012149",
          "tgn:2001125",
          "tgn:7007522",
          "tgn:7029392"
        ],
        "placetype": [
          "aat:300008347"
        ],
        "id": 2057123,
        "name:xx": "Ofahoma"
      }
    },
    {
      "geometry": {
        "type": "Point",
        "coordinates": [
          -90.4333,
          32.6833
        ]
      },
      "type": "Feature",
      "properties": {
        "hierarchy": [
          "tgn:2057124",
          "tgn:1000001",
          "tgn:7012149",
          "tgn:2001167",
          "tgn:7007522",
          "tgn:7029392"
        ],
        "placetype": [
          "aat:300008347"
        ],
        "id": 2057124,
        "name:xx": "Oil City"
      }
    },
    {
      "geometry": {
        "type": "Point",
        "coordinates": [
          -89.3833,
          31.2
        ]
      },
      "type": "Feature",
      "properties": {
        "hierarchy": [
          "tgn:2057125",
          "tgn:1000001",
          "tgn:7012149",
          "tgn:2001122",
          "tgn:7007522",
          "tgn:7029392"
        ],
        "placetype": [
          "aat:300008347",
          "aat:300387210"
        ],
        "id": 2057125,
        "name:xx": "Okahola"
      }
    },
    {
      "geometry": {
        "type": "Point",
        "coordinates": [
          -90.1667,
          33.3333
        ]
      },
      "type": "Feature",
      "properties": {
        "hierarchy": [
          "tgn:2057126",
          "tgn:1000001",
          "tgn:2001093",
          "tgn:7012149",
          "tgn:7007522",
          "tgn:7029392"
        ],
        "placetype": [
          "aat:300008347",
          "aat:300387210"
        ],
        "id": 2057126,
        "name:xx": "Oklahoma"
      }
    },
    {
      "geometry": {
        "type": "Point",
        "coordinates": [
          -88.75,
          34
        ]
      },
      "type": "Feature",
      "properties": {
        "hierarchy": [
          "tgn:2057127",
          "tgn:1000001",
          "tgn:2001094",
          "tgn:7012149",
          "tgn:7007522",
          "tgn:7029392"
        ],
        "placetype": [
          "aat:300008347",
          "aat:300008416"
        ],
        "id": 2057127,
        "name:xx": "Okolona"
      }
    },
    {
      "geometry": {
        "type": "Point",
        "coordinates": [
          -88.75,
          33.3167
        ]
      },
      "type": "Feature",
      "properties": {
        "hierarchy": [
          "tgn:2057128",
          "tgn:1000001",
          "tgn:7012149",
          "tgn:2001138",
          "tgn:7007522",
          "tgn:7029392"
        ],
        "placetype": [
          "aat:300008347",
          "aat:300387210"
        ],
        "id": 2057128,
        "name:xx": "Oktoc"
      }
    }
  ]
}
