{
  "geometry": {
    "type": "Point",
    "coordinates": [
      -119.7167,
      44.35
    ]
  },
  "type": "Feature",
  "properties": {
    "hierarchy": [
      "tgn:2563394",
      "tgn:1000001",
      "tgn:7012149",
      "tgn:2001723",
      "tgn:7007708",
      "tgn:7029392"
    ],
    "placetype": [
      "aat:300008905"
    ],
    "id": 2563394,
    "name:xx": "Owl Creek Meadow"
  }
}
