{
  "type": "FeatureCollection",
  "features": [
    {
      "geometry": {
        "type": "Point",
        "coordinates": [
          -101.0667,
          31.1167
        ]
      },
      "type": "Feature",
      "properties": {
        "hierarchy": [
          "tgn:2107881",
          "tgn:1000001",
          "tgn:7012149",
          "tgn:2002007",
          "tgn:7007826",
          "tgn:7029392"
        ],
        "placetype": [
          "aat:300387016"
        ],
        "id": 2107881,
        "name:xx": "Suggs"
      }
    },
    {
      "geometry": {
        "type": "Point",
        "coordinates": [
          -98.55,
          26.2667
        ]
      },
      "type": "Feature",
      "properties": {
        "hierarchy": [
          "tgn:2107882",
          "tgn:1000001",
          "tgn:7012149",
          "tgn:2002002",
          "tgn:7007826",
          "tgn:7029392"
        ],
        "placetype": [
          "aat:300008347"
        ],
        "id": 2107882,
        "name:xx": "Sullivan City"
      }
    },
    {
      "geometry": {
        "type": "Point",
        "coordinates": [
          -95.3833,
          33.3167
        ]
      },
      "type": "Feature",
      "properties": {
        "hierarchy": [
          "tgn:2107883",
          "tgn:1000001",
          "tgn:7012149",
          "tgn:1002485",
          "tgn:7007826",
          "tgn:7029392"
        ],
        "placetype": [
          "aat:300008347"
        ],
        "id": 2107883,
        "name:xx": "Sulphur Bluff"
      }
    },
    {
      "geometry": {
        "type": "Point",
        "coordinates": [
          -94.75,
          31.8833
        ]
      },
      "type": "Feature",
      "properties": {
        "hierarchy": [
          "tgn:2107885",
          "tgn:1000001",
          "tgn:7012149",
          "tgn:1002839",
          "tgn:7007826",
          "tgn:7029392"
        ],
        "placetype": [
          "aat:300008347",
          "aat:300387210"
        ],
        "id": 2107885,
        "name:xx": "Sulphur Springs"
      }
    },
    {
      "geometry": {
        "type": "Point",
        "coordinates": [
          -95.6,
          33.1333
        ]
      },
      "type": "Feature",
      "properties": {
        "hierarchy": [
          "tgn:2107886",
          "tgn:1000001",
          "tgn:7012149",
          "tgn:1002485",
          "tgn:7007826",
          "tgn:7029392"
        ],
        "placetype": [
          "aat:300008347"
        ],
        "id": 2107886,
        "name:xx": "Sulphur Springs"
      }
    }
  ]
}
