{
  "type": "FeatureCollection",
  "features": [
    {
      "geometry": {
        "type": "Point",
        "coordinates": [
          -77.2833,
          38.6
        ]
      },
      "type": "Feature",
      "properties": {
        "hierarchy": [
          "tgn:2111890",
          "tgn:1000001",
          "tgn:7012149",
          "tgn:7015778",
          "tgn:7007919",
          "tgn:7029392"
        ],
        "placetype": [
          "aat:300008347"
        ],
        "id": 2111890,
        "name:xx": "Garfield Estates"
      }
    },
    {
      "geometry": {
        "type": "Point",
        "coordinates": [
          -75.5833,
          37.8
        ]
      },
      "type": "Feature",
      "properties": {
        "hierarchy": [
          "tgn:2111891",
          "tgn:1002132",
          "tgn:1000001",
          "tgn:7012149",
          "tgn:7007919",
          "tgn:7029392"
        ],
        "placetype": [
          "aat:300008347",
          "aat:300387210"
        ],
        "id": 2111891,
        "name:xx": "Gargatha"
      }
    },
    {
      "geometry": {
        "type": "Point",
        "coordinates": [
          -77.4167,
          38.4667
        ]
      },
      "type": "Feature",
      "properties": {
        "hierarchy": [
          "tgn:2111894",
          "tgn:1000001",
          "tgn:7012149",
          "tgn:1002913",
          "tgn:7007919",
          "tgn:7029392"
        ],
        "placetype": [
          "aat:300008347"
        ],
        "id": 2111894,
        "name:xx": "Garrisonville"
      }
    },
    {
      "geometry": {
        "type": "Point",
        "coordinates": [
          -77.15,
          37.2333
        ]
      },
      "type": "Feature",
      "properties": {
        "hierarchy": [
          "tgn:2111895",
          "tgn:1000001",
          "tgn:7012149",
          "tgn:1002805",
          "tgn:7007919",
          "tgn:7029392"
        ],
        "placetype": [
          "aat:300008347"
        ],
        "id": 2111895,
        "name:xx": "Garysville"
      }
    },
    {
      "geometry": {
        "type": "Point",
        "coordinates": [
          -77.8833,
          36.5667
        ]
      },
      "type": "Feature",
      "properties": {
        "hierarchy": [
          "tgn:2111896",
          "tgn:1000001",
          "tgn:2002147",
          "tgn:7012149",
          "tgn:7007919",
          "tgn:7029392"
        ],
        "placetype": [
          "aat:300008347"
        ],
        "id": 2111896,
        "name:xx": "Gasburg"
      }
    },
    {
      "geometry": {
        "type": "Point",
        "coordinates": [
          -82.5667,
          36.6333
        ]
      },
      "type": "Feature",
      "properties": {
        "hierarchy": [
          "tgn:2111897",
          "tgn:1000001",
          "tgn:7012149",
          "tgn:2002189",
          "tgn:7007919",
          "tgn:7029392"
        ],
        "placetype": [
          "aat:300008347"
        ],
        "id": 2111897,
        "name:xx": "Gate City"
      }
    }
  ]
}
