{
  "geometry": {
    "type": "Point",
    "coordinates": [
      -123.1667,
      42.1833
    ]
  },
  "type": "Feature",
  "properties": {
    "hierarchy": [
      "tgn:2487872",
      "tgn:1000001",
      "tgn:7012149",
      "tgn:2001711",
      "tgn:7007708",
      "tgn:7029392"
    ],
    "placetype": [
      "aat:300008706"
    ],
    "id": 2487872,
    "name:xx": "Left Fork Tallowbox Creek"
  }
}
