{
  "geometry": {
    "type": "Point",
    "coordinates": [
      -91.2167,
      34.5167
    ]
  },
  "type": "Feature",
  "properties": {
    "hierarchy": [
      "tgn:2739814",
      "tgn:1000001",
      "tgn:7016172",
      "tgn:7012149",
      "tgn:2000152",
      "tgn:7029392"
    ],
    "placetype": [
      "aat:300008680"
    ],
    "id": 2739814,
    "name:xx": "Upper Eagle Nest Lake"
  }
}
