{
  "geometry": {
    "type": "Point",
    "coordinates": [
      -93.7333,
      47.35
    ]
  },
  "type": "Feature",
  "properties": {
    "hierarchy": [
      "tgn:2233683",
      "tgn:1000001",
      "tgn:7012149",
      "tgn:2001029",
      "tgn:7007521",
      "tgn:7029392"
    ],
    "placetype": [
      "aat:300008680"
    ],
    "id": 2233683,
    "name:xx": "Chase Lake"
  }
}
