{
  "type": "FeatureCollection",
  "features": [
    {
      "geometry": {
        "type": "Point",
        "coordinates": [
          -3.75,
          51.6
        ]
      },
      "type": "Feature",
      "properties": {
        "hierarchy": [
          "tgn:7455230",
          "tgn:7002443",
          "tgn:1000003",
          "tgn:7018974",
          "tgn:7008591",
          "tgn:7029392"
        ],
        "placetype": [
          "aat:300008347"
        ],
        "name:en": "Cwmafan",
        "id": 7455230
      }
    },
    {
      "geometry": {
        "type": "Point",
        "coordinates": [
          -4.066667,
          52.1
        ]
      },
      "type": "Feature",
      "properties": {
        "hierarchy": [
          "tgn:7455231",
          "tgn:7002443",
          "tgn:5000552",
          "tgn:1000003",
          "tgn:7008591",
          "tgn:7029392"
        ],
        "placetype": [
          "aat:300008347"
        ],
        "name:en": "Cwmann",
        "id": 7455231
      }
    },
    {
      "geometry": {
        "type": "Point",
        "coordinates": [
          -3.4,
          53.283333
        ]
      },
      "type": "Feature",
      "properties": {
        "hierarchy": [
          "tgn:7455232",
          "tgn:7002443",
          "tgn:5000555",
          "tgn:1000003",
          "tgn:7008591",
          "tgn:7029392"
        ],
        "placetype": [
          "aat:300008347"
        ],
        "name:en": "Cwm",
        "id": 7455232
      }
    },
    {
      "geometry": {
        "type": "Point",
        "coordinates": [
          -3.180278,
          51.74
        ]
      },
      "type": "Feature",
      "properties": {
        "hierarchy": [
          "tgn:7455233",
          "tgn:7018958",
          "tgn:7002443",
          "tgn:1000003",
          "tgn:7008591",
          "tgn:7029392"
        ],
        "placetype": [
          "aat:300008347"
        ],
        "name:en": "Cwm",
        "id": 7455233
      }
    },
    {
      "geometry": {
        "type": "Point",
        "coordinates": [
          -4.15,
          53.066667
        ]
      },
      "type": "Feature",
      "properties": {
        "hierarchy": [
          "tgn:7455234",
          "tgn:7002443",
          "tgn:1000003",
          "tgn:7029493",
          "tgn:7008591",
          "tgn:7029392"
        ],
        "placetype": [
          "aat:300008680"
        ],
        "name:en": "Cwellyn, Llyn",
        "id": 7455234
      }
    },
    {
      "geometry": {
        "type": "Point",
        "coordinates": [
          -3.983333,
          50.616667
        ]
      },
      "type": "Feature",
      "properties": {
        "hierarchy": [
          "tgn:7455239",
          "tgn:7002445",
          "tgn:1000003",
          "tgn:7012077",
          "tgn:7008591",
          "tgn:7029392"
        ],
        "placetype": [
          "aat:300008795"
        ],
        "name:en": "Cut Hill",
        "id": 7455239
      }
    }
  ]
}
