{
  "geometry": {
    "type": "Point",
    "coordinates": [
      -68.2333,
      -38.9667
    ]
  },
  "type": "Feature",
  "properties": {
    "hierarchy": [
      "tgn:1019867",
      "tgn:7006477",
      "tgn:1001450",
      "tgn:1000002",
      "tgn:7029392"
    ],
    "placetype": [
      "aat:300008347"
    ],
    "id": 1019867,
    "name:xx": "Plottier"
  }
}
