{
  "geometry": {
    "type": "Point",
    "coordinates": [
      128.5167,
      36.05
    ]
  },
  "type": "Feature",
  "properties": {
    "hierarchy": [
      "tgn:1082374",
      "tgn:1000004",
      "tgn:1001372",
      "tgn:7000299",
      "tgn:7029392"
    ],
    "placetype": [
      "aat:300008347"
    ],
    "id": 1082374,
    "name:xx": "Tabu-dong"
  }
}
