{
  "geometry": {
    "type": "Point",
    "coordinates": [
      42.9167,
      24.7833
    ]
  },
  "type": "Feature",
  "properties": {
    "hierarchy": [
      "tgn:1111849",
      "tgn:1000004",
      "tgn:1000137",
      "tgn:7029392"
    ],
    "placetype": [
      "aat:300387346"
    ],
    "id": 1111849,
    "name:xx": "Al-ʻUrayq"
  }
}
