{
  "geometry": {
    "type": "Point",
    "coordinates": [
      31.608399,
      31.0824
    ]
  },
  "type": "Feature",
  "properties": {
    "hierarchy": [
      "tgn:7540780",
      "tgn:7001242",
      "tgn:1001059",
      "tgn:7016833",
      "tgn:7029392"
    ],
    "placetype": [
      "aat:300008347"
    ],
    "name:en": "Mît Migâhid",
    "id": 7540780
  }
}
