{
  "geometry": {
    "type": "Point",
    "coordinates": [
      -92.45,
      37.9667
    ]
  },
  "type": "Feature",
  "properties": {
    "hierarchy": [
      "tgn:2475333",
      "tgn:1000001",
      "tgn:2001178",
      "tgn:7012149",
      "tgn:7007523",
      "tgn:7029392"
    ],
    "placetype": [
      "aat:300008761"
    ],
    "id": 2475333,
    "name:xx": "Lucas Hollow"
  }
}
