{
  "geometry": {
    "type": "Point",
    "coordinates": [
      -108.4167,
      33.4667
    ]
  },
  "type": "Feature",
  "properties": {
    "hierarchy": [
      "tgn:2708943",
      "tgn:1000001",
      "tgn:2001429",
      "tgn:7012149",
      "tgn:7007566",
      "tgn:7029392"
    ],
    "placetype": [
      "aat:300266640"
    ],
    "id": 2708943,
    "name:xx": "T Bar Ridge"
  }
}
