{
  "geometry": {
    "type": "Point",
    "coordinates": [
      -90.5333,
      32.9167
    ]
  },
  "type": "Feature",
  "properties": {
    "hierarchy": [
      "tgn:2772086",
      "tgn:1000001",
      "tgn:7012149",
      "tgn:7007522",
      "tgn:7029392"
    ],
    "placetype": [
      "aat:300006075"
    ],
    "id": 2772086,
    "name:xx": "Will M Whittington Auxiliary Channel"
  }
}
