{
  "geometry": {
    "type": "Point",
    "coordinates": [
      -95.95,
      42.25
    ]
  },
  "type": "Feature",
  "properties": {
    "hierarchy": [
      "tgn:2523399",
      "tgn:1000001",
      "tgn:7012149",
      "tgn:2000657",
      "tgn:7007253",
      "tgn:7029392"
    ],
    "placetype": [
      "aat:300008706"
    ],
    "id": 2523399,
    "name:xx": "Moose Creek"
  }
}
