{
  "geometry": {
    "type": "Point",
    "coordinates": [
      41.15,
      55.9167
    ]
  },
  "type": "Feature",
  "properties": {
    "hierarchy": [
      "tgn:1052190",
      "tgn:1000004",
      "tgn:1003421",
      "tgn:7018214",
      "tgn:7002435",
      "tgn:7029392"
    ],
    "placetype": [
      "aat:300008347"
    ],
    "id": 1052190,
    "name:xx": "Andreyevo"
  }
}
