{
  "geometry": {
    "type": "Point",
    "coordinates": [
      -94.1333,
      38.1167
    ]
  },
  "type": "Feature",
  "properties": {
    "hierarchy": [
      "tgn:2455905",
      "tgn:1000001",
      "tgn:7012149",
      "tgn:7007254",
      "tgn:7029392"
    ],
    "placetype": [
      "aat:300008706"
    ],
    "id": 2455905,
    "name:xx": "Little Gus Creek"
  }
}
