{
  "geometry": {
    "type": "Point",
    "coordinates": [
      -89.1167,
      40.6167
    ]
  },
  "type": "Feature",
  "properties": {
    "hierarchy": [
      "tgn:2150178",
      "tgn:1000001",
      "tgn:7012149",
      "tgn:1003035",
      "tgn:7007251",
      "tgn:7029392"
    ],
    "placetype": [
      "aat:300006191"
    ],
    "id": 2150178,
    "name:xx": "Barwell Lake"
  }
}
