{
  "geometry": {
    "type": "Point",
    "coordinates": [
      -85.2167,
      34.7667
    ]
  },
  "type": "Feature",
  "properties": {
    "hierarchy": [
      "tgn:2573306",
      "tgn:1000001",
      "tgn:7012149",
      "tgn:7007248",
      "tgn:7029392"
    ],
    "placetype": [
      "aat:300008706"
    ],
    "id": 2573306,
    "name:xx": "Peavine Creek"
  }
}
