{
  "geometry": {
    "type": "Point",
    "coordinates": [
      -92.5333,
      47.7667
    ]
  },
  "type": "Feature",
  "properties": {
    "hierarchy": [
      "tgn:2644873",
      "tgn:1000001",
      "tgn:7012149",
      "tgn:2001067",
      "tgn:7007521",
      "tgn:7029392"
    ],
    "placetype": [
      "aat:300008706"
    ],
    "id": 2644873,
    "name:xx": "Sassas Creek"
  }
}
