{
  "geometry": {
    "type": "Point",
    "coordinates": [
      -93.8333,
      31.1667
    ]
  },
  "type": "Feature",
  "properties": {
    "hierarchy": [
      "tgn:2408802",
      "tgn:1000001",
      "tgn:7012149",
      "tgn:2002066",
      "tgn:7007826",
      "tgn:7029392"
    ],
    "placetype": [
      "aat:300008699"
    ],
    "id": 2408802,
    "name:xx": "Hyden Branch"
  }
}
