{
  "geometry": {
    "type": "Point",
    "coordinates": [
      -111.0167,
      33.3667
    ]
  },
  "type": "Feature",
  "properties": {
    "hierarchy": [
      "tgn:2656528",
      "tgn:1000001",
      "tgn:7006451",
      "tgn:7012149",
      "tgn:2000101",
      "tgn:7029392"
    ],
    "placetype": [
      "aat:300008697"
    ],
    "id": 2656528,
    "name:xx": "Sheep Camp Spring"
  }
}
