{
  "type": "FeatureCollection",
  "features": [
    {
      "geometry": {
        "type": "Point",
        "coordinates": [
          13.4,
          50.35
        ]
      },
      "type": "Feature",
      "properties": {
        "hierarchy": [
          "tgn:6006350",
          "tgn:7593920",
          "tgn:1000003",
          "tgn:1001780",
          "tgn:7029392"
        ],
        "placetype": [
          "aat:300008347"
        ],
        "id": 6006350,
        "name:xx": "Vikletice"
      }
    },
    {
      "geometry": {
        "type": "Point",
        "coordinates": [
          -8.846,
          39.214
        ]
      },
      "type": "Feature",
      "properties": {
        "hierarchy": [
          "tgn:6006351",
          "tgn:1000003",
          "tgn:1000926",
          "tgn:1000090",
          "tgn:7029392"
        ],
        "placetype": [
          "aat:300008347"
        ],
        "id": 6006351,
        "name:xx": "Vila Nova de São Pedro"
      }
    }
  ]
}
