{
  "type": "FeatureCollection",
  "features": [
    {
      "geometry": {
        "type": "Point",
        "coordinates": [
          8.733333,
          51.966667
        ]
      },
      "type": "Feature",
      "properties": {
        "hierarchy": [
          "tgn:7133340",
          "tgn:1000003",
          "tgn:7003677",
          "tgn:7000084",
          "tgn:7029392"
        ],
        "placetype": [
          "aat:300008777"
        ],
        "id": 7133340,
        "name:xx": "Münter-Berg"
      }
    },
    {
      "geometry": {
        "type": "Point",
        "coordinates": [
          8.85,
          53.1
        ]
      },
      "type": "Feature",
      "properties": {
        "hierarchy": [
          "tgn:7133341",
          "tgn:7003672",
          "tgn:1000003",
          "tgn:7000084",
          "tgn:7029392"
        ],
        "placetype": [
          "aat:300008347"
        ],
        "id": 7133341,
        "name:xx": "Munte"
      }
    },
    {
      "geometry": {
        "type": "Point",
        "coordinates": [
          7.383333,
          51.1
        ]
      },
      "type": "Feature",
      "properties": {
        "hierarchy": [
          "tgn:7133342",
          "tgn:1000003",
          "tgn:7003677",
          "tgn:7000084",
          "tgn:7029392"
        ],
        "placetype": [
          "aat:300008347"
        ],
        "id": 7133342,
        "name:xx": "Münte"
      }
    },
    {
      "geometry": {
        "type": "Point",
        "coordinates": [
          6.233333,
          50.716667
        ]
      },
      "type": "Feature",
      "properties": {
        "hierarchy": [
          "tgn:7133343",
          "tgn:1000003",
          "tgn:7003677",
          "tgn:7000084",
          "tgn:7029392"
        ],
        "placetype": [
          "aat:300008863"
        ],
        "id": 7133343,
        "name:xx": "Münster Wald"
      }
    },
    {
      "geometry": {
        "type": "Point",
        "coordinates": [
          10.35,
          54.316667
        ]
      },
      "type": "Feature",
      "properties": {
        "hierarchy": [
          "tgn:7133344",
          "tgn:1000003",
          "tgn:7003688",
          "tgn:7000084",
          "tgn:7029392"
        ],
        "placetype": [
          "aat:300000206"
        ],
        "id": 7133344,
        "name:xx": "Münsterthal"
      }
    },
    {
      "geometry": {
        "type": "Point",
        "coordinates": [
          14.683333,
          51.35
        ]
      },
      "type": "Feature",
      "properties": {
        "hierarchy": [
          "tgn:7133345",
          "tgn:1000003",
          "tgn:7003685",
          "tgn:7000084",
          "tgn:7029392"
        ],
        "placetype": [
          "aat:300008688"
        ],
        "id": 7133345,
        "name:xx": "Münsterteich"
      }
    },
    {
      "geometry": {
        "type": "Point",
        "coordinates": [
          10.116667,
          53
        ]
      },
      "type": "Feature",
      "properties": {
        "hierarchy": [
          "tgn:7133348",
          "tgn:1000003",
          "tgn:7003676",
          "tgn:7000084",
          "tgn:7029392"
        ],
        "placetype": [
          "aat:300008347"
        ],
        "id": 7133348,
        "name:xx": "Munster Nord"
      }
    },
    {
      "geometry": {
        "type": "Point",
        "coordinates": [
          8.4,
          51.866667
        ]
      },
      "type": "Feature",
      "properties": {
        "hierarchy": [
          "tgn:7133349",
          "tgn:1000003",
          "tgn:7003677",
          "tgn:7000084",
          "tgn:7029392"
        ],
        "placetype": [
          "aat:300000206"
        ],
        "id": 7133349,
        "name:xx": "Münstermann"
      }
    }
  ]
}
