{
  "geometry": {
    "type": "Point",
    "coordinates": [
      -122.4667,
      48.35
    ]
  },
  "type": "Feature",
  "properties": {
    "hierarchy": [
      "tgn:2328199",
      "tgn:1000001",
      "tgn:7012149",
      "tgn:7014510",
      "tgn:7007920",
      "tgn:7029392"
    ],
    "placetype": [
      "aat:300008347"
    ],
    "id": 2328199,
    "name:xx": "Fish Town"
  }
}
