{
  "geometry": {
    "type": "Point",
    "coordinates": [
      -75.9167,
      40.5833
    ]
  },
  "type": "Feature",
  "properties": {
    "hierarchy": [
      "tgn:2182527",
      "tgn:1000001",
      "tgn:7013387",
      "tgn:7012149",
      "tgn:7007710",
      "tgn:7029392"
    ],
    "placetype": [
      "aat:300008798"
    ],
    "id": 2182527,
    "name:xx": "Blue Rocks"
  }
}
