{
  "geometry": {
    "type": "Point",
    "coordinates": [
      -165.35,
      64.55
    ]
  },
  "type": "Feature",
  "properties": {
    "hierarchy": [
      "tgn:2153975",
      "tgn:7006450",
      "tgn:1000001",
      "tgn:7012149",
      "tgn:2000079",
      "tgn:7029392"
    ],
    "placetype": [
      "aat:300008706"
    ],
    "id": 2153975,
    "name:xx": "Bear Creek"
  }
}
