{
  "geometry": {
    "type": "Point",
    "coordinates": [
      74.44271,
      34.476974
    ]
  },
  "type": "Feature",
  "properties": {
    "hierarchy": [
      "tgn:7586762",
      "tgn:1000004",
      "tgn:7000198",
      "tgn:7000799",
      "tgn:7029392"
    ],
    "placetype": [
      "aat:300008347"
    ],
    "name:en": "Muqām Sharifdār",
    "id": 7586762
  }
}
