{
  "geometry": {
    "type": "Point",
    "coordinates": [
      -107.1833,
      44.05
    ]
  },
  "type": "Feature",
  "properties": {
    "hierarchy": [
      "tgn:2220076",
      "tgn:1000001",
      "tgn:7012149",
      "tgn:2002386",
      "tgn:7007923",
      "tgn:7029392"
    ],
    "placetype": [
      "aat:300386845"
    ],
    "id": 2220076,
    "name:xx": "Canyon Creek Sinks"
  }
}
