{
  "geometry": {
    "type": "Point",
    "coordinates": [
      -61.1833,
      1.7833
    ]
  },
  "type": "Feature",
  "properties": {
    "hierarchy": [
      "tgn:1021074",
      "tgn:1001826",
      "tgn:1000047",
      "tgn:7002456",
      "tgn:1000002",
      "tgn:7029392"
    ],
    "placetype": [
      "aat:300008347"
    ],
    "id": 1021074,
    "name:xx": "Caracaraí"
  }
}
