{
  "geometry": {
    "type": "Point",
    "coordinates": [
      -84.9167,
      32.3167
    ]
  },
  "type": "Feature",
  "properties": {
    "hierarchy": [
      "tgn:2633474",
      "tgn:1000001",
      "tgn:2000317",
      "tgn:7012149",
      "tgn:7007248",
      "tgn:7029392"
    ],
    "placetype": [
      "aat:300266640"
    ],
    "id": 2633474,
    "name:xx": "Running Ridge"
  }
}
