{
  "geometry": {
    "type": "Point",
    "coordinates": [
      11.0833,
      54.3833
    ]
  },
  "type": "Feature",
  "properties": {
    "hierarchy": [
      "tgn:1039354",
      "tgn:1000003",
      "tgn:7003688",
      "tgn:7000084",
      "tgn:7029392"
    ],
    "placetype": [
      "aat:300008347"
    ],
    "id": 1039354,
    "name:xx": "Grossenbrode"
  }
}
