{
  "geometry": {
    "type": "Point",
    "coordinates": [
      -87.3333,
      34.8833
    ]
  },
  "type": "Feature",
  "properties": {
    "hierarchy": [
      "tgn:2718010",
      "tgn:7002659",
      "tgn:1000001",
      "tgn:7012149",
      "tgn:2000038",
      "tgn:7029392"
    ],
    "placetype": [
      "aat:300008699"
    ],
    "id": 2718010,
    "name:xx": "Thompson Branch"
  }
}
