{
  "geometry": {
    "type": "Point",
    "coordinates": [
      -69.3333,
      8.1667
    ]
  },
  "type": "Feature",
  "properties": {
    "hierarchy": [
      "tgn:1025079",
      "tgn:1001837",
      "tgn:1000002",
      "tgn:1000059",
      "tgn:7029392"
    ],
    "placetype": [
      "aat:300008347"
    ],
    "id": 1025079,
    "name:xx": "Ciudad de Nutrias"
  }
}
