{
  "geometry": {
    "type": "Point",
    "coordinates": [
      -94.7167,
      29.7833
    ]
  },
  "type": "Feature",
  "properties": {
    "hierarchy": [
      "tgn:2417175",
      "tgn:1000001",
      "tgn:7012149",
      "tgn:1002456",
      "tgn:7007826",
      "tgn:7029392"
    ],
    "placetype": [
      "aat:300132316"
    ],
    "id": 2417175,
    "name:xx": "Jacks"
  }
}
