{
  "geometry": {
    "type": "Point",
    "coordinates": [
      -88.2667,
      46.8167
    ]
  },
  "type": "Feature",
  "properties": {
    "hierarchy": [
      "tgn:2310493",
      "tgn:2000947",
      "tgn:1000001",
      "tgn:7012149",
      "tgn:7007520",
      "tgn:7029392"
    ],
    "placetype": [
      "aat:300132316"
    ],
    "id": 2310493,
    "name:xx": "Echo Harbor"
  }
}
