{
  "geometry": {
    "type": "Point",
    "coordinates": [
      -65.8167,
      18.0667
    ]
  },
  "type": "Feature",
  "properties": {
    "hierarchy": [
      "tgn:1019006",
      "tgn:7017441",
      "tgn:1000001",
      "tgn:7004643",
      "tgn:7029392"
    ],
    "placetype": [
      "aat:300008347"
    ],
    "id": 1019006,
    "name:xx": "Playa de Guayanés"
  }
}
