{
  "geometry": {
    "type": "Point",
    "coordinates": [
      -122.45,
      37.6667
    ]
  },
  "type": "Feature",
  "properties": {
    "hierarchy": [
      "tgn:1132870",
      "tgn:1000001",
      "tgn:7012149",
      "tgn:7007157",
      "tgn:1002864",
      "tgn:7029392"
    ],
    "placetype": [
      "aat:300008706"
    ],
    "id": 1132870,
    "name:xx": "Colma Creek"
  }
}
