{
  "geometry": {
    "type": "Point",
    "coordinates": [
      49.2667,
      46.45
    ]
  },
  "type": "Feature",
  "properties": {
    "name:xx": "Kigach",
    "hierarchy": [
      "tgn:1125556",
      "tgn:1000003",
      "tgn:7029392"
    ],
    "name:kk": "Qyyghash",
    "placetype": [
      "aat:300008707"
    ],
    "name:slv": "Kigač",
    "id": 1125556
  }
}
