{
  "geometry": {
    "type": "Point",
    "coordinates": [
      -102.6667,
      47.7167
    ]
  },
  "type": "Feature",
  "properties": {
    "hierarchy": [
      "tgn:2077817",
      "tgn:1000001",
      "tgn:2001583",
      "tgn:7012149",
      "tgn:7007705",
      "tgn:7029392"
    ],
    "placetype": [
      "aat:300008347"
    ],
    "id": 2077817,
    "name:xx": "Mandaree"
  }
}
