{
  "type": "FeatureCollection",
  "features": [
    {
      "geometry": {
        "type": "Point",
        "coordinates": [
          36.1333,
          13.85
        ]
      },
      "type": "Feature",
      "properties": {
        "hierarchy": [
          "tgn:1121231",
          "tgn:7001242",
          "tgn:7029392"
        ],
        "placetype": [
          "aat:300008707"
        ],
        "id": 1121231,
        "name:xx": "Āngereb Wenz"
      }
    },
    {
      "geometry": {
        "type": "Point",
        "coordinates": [
          0.8667,
          46.7
        ]
      },
      "type": "Feature",
      "properties": {
        "hierarchy": [
          "tgn:1121234",
          "tgn:1000003",
          "tgn:7001095",
          "tgn:1000070",
          "tgn:7029392"
        ],
        "placetype": [
          "aat:300008707"
        ],
        "id": 1121234,
        "name:xx": "Anglin"
      }
    },
    {
      "geometry": {
        "type": "Point",
        "coordinates": [
          -93.6,
          56.75
        ]
      },
      "type": "Feature",
      "properties": {
        "hierarchy": [
          "tgn:1121235",
          "tgn:7005685",
          "tgn:1000001",
          "tgn:7005734",
          "tgn:7029392"
        ],
        "placetype": [
          "aat:300008707"
        ],
        "id": 1121235,
        "name:xx": "Angling"
      }
    },
    {
      "geometry": {
        "type": "Point",
        "coordinates": [
          68.8833,
          40.8
        ]
      },
      "type": "Feature",
      "properties": {
        "hierarchy": [
          "tgn:1121236",
          "tgn:1000004",
          "tgn:7012253",
          "tgn:7006661",
          "tgn:7029392"
        ],
        "placetype": [
          "aat:300008707"
        ],
        "id": 1121236,
        "name:xx": "Angren"
      }
    },
    {
      "geometry": {
        "type": "Point",
        "coordinates": [
          -42.5,
          -21.8
        ]
      },
      "type": "Feature",
      "properties": {
        "hierarchy": [
          "tgn:1121237",
          "tgn:7006237",
          "tgn:1000047",
          "tgn:7002457",
          "tgn:1000002",
          "tgn:7029392"
        ],
        "placetype": [
          "aat:300008707"
        ],
        "id": 1121237,
        "name:xx": "Angu, Rio do"
      }
    },
    {
      "geometry": {
        "type": "Point",
        "coordinates": [
          30.5833,
          -15.85
        ]
      },
      "type": "Feature",
      "properties": {
        "hierarchy": [
          "tgn:1121238",
          "tgn:7001242",
          "tgn:7029392"
        ],
        "placetype": [
          "aat:300008707"
        ],
        "id": 1121238,
        "name:xx": "Angwa"
      }
    },
    {
      "geometry": {
        "type": "Point",
        "coordinates": [
          -52.9833,
          -21.6167
        ]
      },
      "type": "Feature",
      "properties": {
        "hierarchy": [
          "tgn:1121239",
          "tgn:1001898",
          "tgn:7002454",
          "tgn:1000047",
          "tgn:1000002",
          "tgn:7029392"
        ],
        "placetype": [
          "aat:300008707"
        ],
        "id": 1121239,
        "name:xx": "Anhanduí"
      }
    }
  ]
}
