{
  "geometry": {
    "type": "Point",
    "coordinates": [
      -114.3667,
      36.4833
    ]
  },
  "type": "Feature",
  "properties": {
    "hierarchy": [
      "tgn:2470836",
      "tgn:1000001",
      "tgn:2001410",
      "tgn:7012149",
      "tgn:7007526",
      "tgn:7029392"
    ],
    "placetype": [
      "aat:300008347",
      "aat:300167671",
      "aat:300016956",
      "aat:300387655",
      "aat:300008375"
    ],
    "id": 2470836,
    "name:xx": "Lost City"
  }
}
