{
  "geometry": {
    "type": "Point",
    "coordinates": [
      -111.8333,
      33.2333
    ]
  },
  "type": "Feature",
  "properties": {
    "hierarchy": [
      "tgn:2006864",
      "tgn:1000001",
      "tgn:7006451",
      "tgn:7012149",
      "tgn:2000097",
      "tgn:7029392"
    ],
    "placetype": [
      "aat:300008347",
      "aat:300387210"
    ],
    "id": 2006864,
    "name:xx": "Hamilton Corner"
  }
}
