{
  "geometry": {
    "type": "Point",
    "coordinates": [
      31.151711,
      30.09667
    ]
  },
  "type": "Feature",
  "properties": {
    "hierarchy": [
      "tgn:7541236",
      "tgn:7001242",
      "tgn:7016833",
      "tgn:7029392"
    ],
    "placetype": [
      "aat:300006075"
    ],
    "id": 7541236,
    "name:xx": "Tur'at al Kawm al Aḩmar Raqam Wāḩid"
  }
}
