{
  "geometry": {
    "type": "Point",
    "coordinates": [
      -67.1833,
      44.8833
    ]
  },
  "type": "Feature",
  "properties": {
    "hierarchy": [
      "tgn:2407683",
      "tgn:1000001",
      "tgn:7012149",
      "tgn:7014589",
      "tgn:7007515",
      "tgn:7029392"
    ],
    "placetype": [
      "aat:300008850"
    ],
    "id": 2407683,
    "name:xx": "Hurley Point"
  }
}
