{
  "geometry": {
    "type": "Point",
    "coordinates": [
      23.1333,
      50.1833
    ]
  },
  "type": "Feature",
  "properties": {
    "hierarchy": [
      "tgn:1049216",
      "tgn:1000003",
      "tgn:7024126",
      "tgn:7006366",
      "tgn:7029392"
    ],
    "placetype": [
      "aat:300008347"
    ],
    "id": 1049216,
    "name:xx": "Lubaczów"
  }
}
