{
  "geometry": {
    "type": "Point",
    "coordinates": [
      -82.3667,
      34.25
    ]
  },
  "type": "Feature",
  "properties": {
    "hierarchy": [
      "tgn:2143311",
      "tgn:2001725",
      "tgn:1000001",
      "tgn:7012149",
      "tgn:7007712",
      "tgn:7029392"
    ],
    "placetype": [
      "aat:300008706"
    ],
    "id": 2143311,
    "name:xx": "Bailey Creek"
  }
}
