{
  "type": "FeatureCollection",
  "features": [
    {
      "geometry": {
        "type": "Point",
        "coordinates": [
          -85.6833,
          35.1
        ]
      },
      "type": "Feature",
      "properties": {
        "hierarchy": [
          "tgn:2433640",
          "tgn:1000001",
          "tgn:7012149",
          "tgn:2001894",
          "tgn:7007825",
          "tgn:7029392"
        ],
        "placetype": [
          "aat:300008761"
        ],
        "id": 2433640,
        "name:xx": "Kelly Cove"
      }
    },
    {
      "geometry": {
        "type": "Point",
        "coordinates": [
          -75.9,
          37.5
        ]
      },
      "type": "Feature",
      "properties": {
        "hierarchy": [
          "tgn:2433641",
          "tgn:1000001",
          "tgn:7012149",
          "tgn:1002730",
          "tgn:7007919",
          "tgn:7029392"
        ],
        "placetype": [
          "aat:300132316"
        ],
        "id": 2433641,
        "name:xx": "Kelly Cove"
      }
    },
    {
      "geometry": {
        "type": "Point",
        "coordinates": [
          -85.7,
          35.1
        ]
      },
      "type": "Feature",
      "properties": {
        "hierarchy": [
          "tgn:2433642",
          "tgn:1000001",
          "tgn:7012149",
          "tgn:2001894",
          "tgn:7007825",
          "tgn:7029392"
        ],
        "placetype": [
          "aat:300008699"
        ],
        "id": 2433642,
        "name:xx": "Kelly Cove Branch"
      }
    },
    {
      "geometry": {
        "type": "Point",
        "coordinates": [
          -86.5833,
          34.4333
        ]
      },
      "type": "Feature",
      "properties": {
        "hierarchy": [
          "tgn:2433643",
          "tgn:7002659",
          "tgn:1000001",
          "tgn:7012149",
          "tgn:2000051",
          "tgn:7029392"
        ],
        "placetype": [
          "aat:300008746"
        ],
        "id": 2433643,
        "name:xx": "Kelly Crawl Cave"
      }
    },
    {
      "geometry": {
        "type": "Point",
        "coordinates": [
          -86.6667,
          33.85
        ]
      },
      "type": "Feature",
      "properties": {
        "hierarchy": [
          "tgn:2433644",
          "tgn:7002659",
          "tgn:1000001",
          "tgn:2000004",
          "tgn:7012149",
          "tgn:7029392"
        ],
        "placetype": [
          "aat:300008706"
        ],
        "id": 2433644,
        "name:xx": "Kelly Creek"
      }
    },
    {
      "geometry": {
        "type": "Point",
        "coordinates": [
          -85.9667,
          33.4
        ]
      },
      "type": "Feature",
      "properties": {
        "hierarchy": [
          "tgn:2433645",
          "tgn:7002659",
          "tgn:1000001",
          "tgn:7012149",
          "tgn:2000060",
          "tgn:7029392"
        ],
        "placetype": [
          "aat:300008706"
        ],
        "id": 2433645,
        "name:xx": "Kelly Creek"
      }
    },
    {
      "geometry": {
        "type": "Point",
        "coordinates": [
          -85.45,
          31.3333
        ]
      },
      "type": "Feature",
      "properties": {
        "hierarchy": [
          "tgn:2433646",
          "tgn:7002659",
          "tgn:1000001",
          "tgn:7012149",
          "tgn:2000022",
          "tgn:7029392"
        ],
        "placetype": [
          "aat:300008706"
        ],
        "id": 2433646,
        "name:xx": "Kelly Creek"
      }
    },
    {
      "geometry": {
        "type": "Point",
        "coordinates": [
          -85.45,
          32.4
        ]
      },
      "type": "Feature",
      "properties": {
        "hierarchy": [
          "tgn:2433647",
          "tgn:7002659",
          "tgn:1000001",
          "tgn:7012149",
          "tgn:2000043",
          "tgn:7029392"
        ],
        "placetype": [
          "aat:300008706"
        ],
        "id": 2433647,
        "name:xx": "Kelly Creek"
      }
    },
    {
      "geometry": {
        "type": "Point",
        "coordinates": [
          -86.3833,
          33.65
        ]
      },
      "type": "Feature",
      "properties": {
        "hierarchy": [
          "tgn:2433648",
          "tgn:7002659",
          "tgn:1000001",
          "tgn:7012149",
          "tgn:7029392"
        ],
        "placetype": [
          "aat:300008706"
        ],
        "id": 2433648,
        "name:xx": "Kelly Creek"
      }
    },
    {
      "geometry": {
        "type": "Point",
        "coordinates": [
          -161.9333,
          65.0333
        ]
      },
      "type": "Feature",
      "properties": {
        "hierarchy": [
          "tgn:2433649",
          "tgn:7006450",
          "tgn:1000001",
          "tgn:7012149",
          "tgn:2000079",
          "tgn:7029392"
        ],
        "placetype": [
          "aat:300008706"
        ],
        "id": 2433649,
        "name:xx": "Kelly Creek"
      }
    }
  ]
}
