{
  "type": "FeatureCollection",
  "features": [
    {
      "geometry": {
        "type": "Point",
        "coordinates": [
          -1.916667,
          54.383333
        ]
      },
      "type": "Feature",
      "properties": {
        "hierarchy": [
          "tgn:7465801",
          "tgn:7002445",
          "tgn:1000003",
          "tgn:7008166",
          "tgn:7008591",
          "tgn:7029392"
        ],
        "placetype": [
          "aat:300008699"
        ],
        "name:en": "Arkle Beck",
        "id": 7465801
      }
    },
    {
      "geometry": {
        "type": "Point",
        "coordinates": [
          -4.9,
          58.366667
        ]
      },
      "type": "Feature",
      "properties": {
        "hierarchy": [
          "tgn:7465802",
          "tgn:7002444",
          "tgn:1000003",
          "tgn:7008082",
          "tgn:7008591",
          "tgn:7029392"
        ],
        "placetype": [
          "aat:300008795"
        ],
        "name:en": "Arkle, Ben",
        "id": 7465802
      }
    },
    {
      "geometry": {
        "type": "Point",
        "coordinates": [
          -4.75,
          57.85
        ]
      },
      "type": "Feature",
      "properties": {
        "hierarchy": [
          "tgn:7465807",
          "tgn:7002444",
          "tgn:1000003",
          "tgn:7008082",
          "tgn:7008591",
          "tgn:7029392"
        ],
        "placetype": [
          "aat:300008795"
        ],
        "name:en": "Bodach Mòr",
        "id": 7465807
      }
    },
    {
      "geometry": {
        "type": "Point",
        "coordinates": [
          -4.616667,
          50.416667
        ]
      },
      "type": "Feature",
      "properties": {
        "hierarchy": [
          "tgn:7465808",
          "tgn:7002445",
          "tgn:7008116",
          "tgn:1000003",
          "tgn:7008591",
          "tgn:7029392"
        ],
        "placetype": [
          "aat:300387502"
        ],
        "name:en": "Boconnoc",
        "id": 7465808
      }
    },
    {
      "geometry": {
        "type": "Point",
        "coordinates": [
          -2.6,
          52.25
        ]
      },
      "type": "Feature",
      "properties": {
        "hierarchy": [
          "tgn:7465809",
          "tgn:7002445",
          "tgn:1000003",
          "tgn:5000227",
          "tgn:7008591",
          "tgn:7029392"
        ],
        "placetype": [
          "aat:300008347"
        ],
        "name:en": "Bockleton",
        "id": 7465809
      }
    }
  ]
}
