{
  "type": "FeatureCollection",
  "features": [
    {
      "geometry": {
        "type": "Point",
        "coordinates": [
          -6,
          38.583333
        ]
      },
      "type": "Feature",
      "properties": {
        "hierarchy": [
          "tgn:7330540",
          "tgn:7002807",
          "tgn:1000003",
          "tgn:7003837",
          "tgn:1000095",
          "tgn:7029392"
        ],
        "placetype": [
          "aat:300266554",
          "aat:300008699"
        ],
        "id": 7330540,
        "name:xx": "Herreras, Arroyo de las"
      }
    },
    {
      "geometry": {
        "type": "Point",
        "coordinates": [
          -3.5,
          42.766667
        ]
      },
      "type": "Feature",
      "properties": {
        "hierarchy": [
          "tgn:7330541",
          "tgn:7002810",
          "tgn:7001158",
          "tgn:1000003",
          "tgn:1000095",
          "tgn:7029392"
        ],
        "placetype": [
          "aat:300008347"
        ],
        "id": 7330541,
        "name:xx": "Herrera de Valdivielso"
      }
    },
    {
      "geometry": {
        "type": "Point",
        "coordinates": [
          -4.2,
          42.05
        ]
      },
      "type": "Feature",
      "properties": {
        "hierarchy": [
          "tgn:7330542",
          "tgn:7002832",
          "tgn:7001158",
          "tgn:1000003",
          "tgn:1000095",
          "tgn:7029392"
        ],
        "placetype": [
          "aat:300008347"
        ],
        "id": 7330542,
        "name:xx": "Herrera de Valdecañas"
      }
    },
    {
      "geometry": {
        "type": "Point",
        "coordinates": [
          -3.016667,
          41.766667
        ]
      },
      "type": "Feature",
      "properties": {
        "hierarchy": [
          "tgn:7330543",
          "tgn:7002842",
          "tgn:7001158",
          "tgn:1000003",
          "tgn:1000095",
          "tgn:7029392"
        ],
        "placetype": [
          "aat:300008347"
        ],
        "id": 7330543,
        "name:xx": "Herrera de Soria"
      }
    },
    {
      "geometry": {
        "type": "Point",
        "coordinates": [
          -1.083333,
          41.2
        ]
      },
      "type": "Feature",
      "properties": {
        "hierarchy": [
          "tgn:7330545",
          "tgn:7002759",
          "tgn:7002845",
          "tgn:1000003",
          "tgn:1000095",
          "tgn:7029392"
        ],
        "placetype": [
          "aat:300008347"
        ],
        "id": 7330545,
        "name:xx": "Herrera de los Navarros"
      }
    },
    {
      "geometry": {
        "type": "Point",
        "coordinates": [
          -4.166667,
          43.3
        ]
      },
      "type": "Feature",
      "properties": {
        "hierarchy": [
          "tgn:7330547",
          "tgn:7002760",
          "tgn:1000003",
          "tgn:1000095",
          "tgn:7029392"
        ],
        "placetype": [
          "aat:300008347"
        ],
        "id": 7330547,
        "name:xx": "Herrera de Ibio"
      }
    },
    {
      "geometry": {
        "type": "Point",
        "coordinates": [
          -4.65,
          41.566667
        ]
      },
      "type": "Feature",
      "properties": {
        "hierarchy": [
          "tgn:7330548",
          "tgn:7001158",
          "tgn:7002848",
          "tgn:1000003",
          "tgn:1000095",
          "tgn:7029392"
        ],
        "placetype": [
          "aat:300008347"
        ],
        "id": 7330548,
        "name:xx": "Herrera de Duero"
      }
    },
    {
      "geometry": {
        "type": "Point",
        "coordinates": [
          -7.4,
          39.633333
        ]
      },
      "type": "Feature",
      "properties": {
        "hierarchy": [
          "tgn:7330549",
          "tgn:7002811",
          "tgn:1000003",
          "tgn:7003837",
          "tgn:1000095",
          "tgn:7029392"
        ],
        "placetype": [
          "aat:300008347"
        ],
        "id": 7330549,
        "name:xx": "Herrera de Alcántara"
      }
    }
  ]
}
