{
  "geometry": {
    "type": "Point",
    "coordinates": [
      -75.9667,
      36.65
    ]
  },
  "type": "Feature",
  "properties": {
    "hierarchy": [
      "tgn:2481753",
      "tgn:1000001",
      "tgn:7012149",
      "tgn:7022218",
      "tgn:7007919",
      "tgn:7029392"
    ],
    "placetype": [
      "aat:300132316"
    ],
    "id": 2481753,
    "name:xx": "Landing Cove"
  }
}
