{
  "geometry": {
    "type": "Point",
    "coordinates": [
      79.8333,
      9.05
    ]
  },
  "type": "Feature",
  "properties": {
    "hierarchy": [
      "tgn:1008025",
      "tgn:7000406",
      "tgn:1000004",
      "tgn:1000110",
      "tgn:7029392"
    ],
    "placetype": [
      "aat:300008791"
    ],
    "id": 1008025,
    "name:xx": "Mannar Island"
  }
}
