{
  "geometry": {
    "type": "Point",
    "coordinates": [
      21.203,
      44.485
    ]
  },
  "type": "Feature",
  "properties": {
    "hierarchy": [
      "tgn:7032175",
      "tgn:1000003",
      "tgn:7006669",
      "tgn:7029392"
    ],
    "placetype": [
      "aat:300008347"
    ],
    "id": 7032175,
    "name:xx": "Vlaški Do"
  }
}
