{
  "geometry": {
    "type": "Point",
    "coordinates": [
      -112.1667,
      45.5167
    ]
  },
  "type": "Feature",
  "properties": {
    "hierarchy": [
      "tgn:2551315",
      "tgn:1000001",
      "tgn:7012149",
      "tgn:2001288",
      "tgn:7007524",
      "tgn:7029392"
    ],
    "placetype": [
      "aat:300000390"
    ],
    "id": 2551315,
    "name:xx": "Nuggett Creek Mine"
  }
}
