{
  "type": "FeatureCollection",
  "features": [
    {
      "geometry": {
        "type": "Point",
        "coordinates": [
          -77.3833,
          38.8333
        ]
      },
      "type": "Feature",
      "properties": {
        "hierarchy": [
          "tgn:2270690",
          "tgn:1000001",
          "tgn:7012149",
          "tgn:7014160",
          "tgn:7007919",
          "tgn:7029392"
        ],
        "placetype": [
          "aat:300008347"
        ],
        "id": 2270690,
        "name:xx": "Crystal Springs"
      }
    },
    {
      "geometry": {
        "type": "Point",
        "coordinates": [
          -122.5667,
          47.6
        ]
      },
      "type": "Feature",
      "properties": {
        "hierarchy": [
          "tgn:2270691",
          "tgn:1000001",
          "tgn:7012149",
          "tgn:1002552",
          "tgn:7007920",
          "tgn:7029392"
        ],
        "placetype": [
          "aat:300008347"
        ],
        "id": 2270691,
        "name:xx": "Crystal Springs"
      }
    },
    {
      "geometry": {
        "type": "Point",
        "coordinates": [
          -86.4333,
          35.0667
        ]
      },
      "type": "Feature",
      "properties": {
        "hierarchy": [
          "tgn:2270693",
          "tgn:1000001",
          "tgn:7012149",
          "tgn:2001888",
          "tgn:7007825",
          "tgn:7029392"
        ],
        "placetype": [
          "aat:300008699"
        ],
        "id": 2270693,
        "name:xx": "Crystal Springs Branch"
      }
    },
    {
      "geometry": {
        "type": "Point",
        "coordinates": [
          -115.4,
          33.5667
        ]
      },
      "type": "Feature",
      "properties": {
        "hierarchy": [
          "tgn:2270694",
          "tgn:1000001",
          "tgn:7012149",
          "tgn:7007157",
          "tgn:1002828",
          "tgn:7029392"
        ],
        "placetype": [
          "aat:300008761"
        ],
        "id": 2270694,
        "name:xx": "Crystal Springs Canyon"
      }
    },
    {
      "geometry": {
        "type": "Point",
        "coordinates": [
          -110.5333,
          37.5167
        ]
      },
      "type": "Feature",
      "properties": {
        "hierarchy": [
          "tgn:2270695",
          "tgn:1000001",
          "tgn:7012149",
          "tgn:2002119",
          "tgn:7007827",
          "tgn:7029392"
        ],
        "placetype": [
          "aat:300008761"
        ],
        "id": 2270695,
        "name:xx": "Crystal Springs Canyon"
      }
    },
    {
      "geometry": {
        "type": "Point",
        "coordinates": [
          -92.4,
          44.6167
        ]
      },
      "type": "Feature",
      "properties": {
        "hierarchy": [
          "tgn:2270696",
          "tgn:1000001",
          "tgn:7012149",
          "tgn:2002345",
          "tgn:7007922",
          "tgn:7029392"
        ],
        "placetype": [
          "aat:300008761"
        ],
        "id": 2270696,
        "name:xx": "Crystal Springs Coulee"
      }
    },
    {
      "geometry": {
        "type": "Point",
        "coordinates": [
          -122.6167,
          45.4667
        ]
      },
      "type": "Feature",
      "properties": {
        "hierarchy": [
          "tgn:2270697",
          "tgn:1000001",
          "tgn:7012149",
          "tgn:7007708",
          "tgn:7029392"
        ],
        "placetype": [
          "aat:300008706"
        ],
        "id": 2270697,
        "name:xx": "Crystal Springs Creek"
      }
    },
    {
      "geometry": {
        "type": "Point",
        "coordinates": [
          -85.9,
          33.85
        ]
      },
      "type": "Feature",
      "properties": {
        "hierarchy": [
          "tgn:2270698",
          "tgn:7002659",
          "tgn:1000001",
          "tgn:2000007",
          "tgn:7012149",
          "tgn:7029392"
        ],
        "placetype": [
          "aat:300006191"
        ],
        "id": 2270698,
        "name:xx": "Crystal Springs Lake"
      }
    },
    {
      "geometry": {
        "type": "Point",
        "coordinates": [
          -80.9,
          35.0833
        ]
      },
      "type": "Feature",
      "properties": {
        "hierarchy": [
          "tgn:2270699",
          "tgn:1000001",
          "tgn:7012149",
          "tgn:7014021",
          "tgn:7007709",
          "tgn:7029392"
        ],
        "placetype": [
          "aat:300006191"
        ],
        "id": 2270699,
        "name:xx": "Crystal Springs Lake"
      }
    }
  ]
}
