{
  "geometry": {
    "type": "Point",
    "coordinates": [
      -86.7667,
      37.95
    ]
  },
  "type": "Feature",
  "properties": {
    "hierarchy": [
      "tgn:2033865",
      "tgn:1000001",
      "tgn:7012149",
      "tgn:2000550",
      "tgn:7007252",
      "tgn:7029392"
    ],
    "placetype": [
      "aat:300008347"
    ],
    "id": 2033865,
    "name:xx": "Tell City"
  }
}
