{
  "type": "FeatureCollection",
  "features": [
    {
      "geometry": {
        "type": "Point",
        "coordinates": [
          32.6667,
          -15.25
        ]
      },
      "type": "Feature",
      "properties": {
        "hierarchy": [
          "tgn:1000940",
          "tgn:7001242",
          "tgn:1000180",
          "tgn:7029392"
        ],
        "placetype": [
          "aat:300387064",
          "aat:300000774"
        ],
        "id": 1000940,
        "name:xx": "Tete"
      }
    },
    {
      "geometry": {
        "type": "Point",
        "coordinates": [
          -88.75,
          16.3333
        ]
      },
      "type": "Feature",
      "properties": {
        "hierarchy": [
          "tgn:1000941",
          "tgn:7005346",
          "tgn:1000001",
          "tgn:7029392"
        ],
        "placetype": [
          "aat:300008631",
          "aat:300387064",
          "aat:300387081"
        ],
        "id": 1000941,
        "name:xx": "Toledo"
      }
    },
    {
      "geometry": {
        "type": "Point",
        "coordinates": [
          17,
          -19
        ]
      },
      "type": "Feature",
      "properties": {
        "hierarchy": [
          "tgn:1000942",
          "tgn:7001242",
          "tgn:1000198",
          "tgn:7029392"
        ],
        "placetype": [
          "aat:300387179",
          "aat:300387064",
          "aat:300387081"
        ],
        "id": 1000942,
        "name:xx": "Tsumeb"
      }
    },
    {
      "geometry": {
        "type": "Point",
        "coordinates": [
          15.44,
          -7.107
        ]
      },
      "type": "Feature",
      "properties": {
        "hierarchy": [
          "tgn:1000943",
          "tgn:7001242",
          "tgn:1000149",
          "tgn:7029392"
        ],
        "placetype": [
          "aat:300387064",
          "aat:300000774"
        ],
        "id": 1000943,
        "name:xx": "Uíge"
      }
    },
    {
      "geometry": {
        "type": "Point",
        "coordinates": [
          149.5,
          -5.75
        ]
      },
      "type": "Feature",
      "properties": {
        "hierarchy": [
          "tgn:1000946",
          "tgn:7006160",
          "tgn:1000006",
          "tgn:7029392"
        ],
        "placetype": [
          "aat:300387064",
          "aat:300000774"
        ],
        "id": 1000946,
        "name:xx": "West New Britain"
      }
    },
    {
      "geometry": {
        "type": "Point",
        "coordinates": [
          141.5,
          -4
        ]
      },
      "type": "Feature",
      "properties": {
        "hierarchy": [
          "tgn:1000947",
          "tgn:7006160",
          "tgn:1000006",
          "tgn:7029392"
        ],
        "placetype": [
          "aat:300387064",
          "aat:300000774"
        ],
        "id": 1000947,
        "name:xx": "West Sepik"
      }
    },
    {
      "geometry": {
        "type": "Point",
        "coordinates": [
          31,
          1
        ]
      },
      "type": "Feature",
      "properties": {
        "hierarchy": [
          "tgn:1000948",
          "tgn:7001242",
          "tgn:1000206",
          "tgn:7029392"
        ],
        "placetype": [
          "aat:300387064",
          "aat:300000774"
        ],
        "id": 1000948,
        "name:xx": "Western"
      }
    },
    {
      "geometry": {
        "type": "Point",
        "coordinates": [
          142,
          -7
        ]
      },
      "type": "Feature",
      "properties": {
        "hierarchy": [
          "tgn:1000949",
          "tgn:7006160",
          "tgn:1000006",
          "tgn:7029392"
        ],
        "placetype": [
          "aat:300387064",
          "aat:300000774"
        ],
        "id": 1000949,
        "name:xx": "Western"
      }
    }
  ]
}
