{
  "geometry": {
    "type": "Point",
    "coordinates": [
      120.65,
      27.85
    ]
  },
  "type": "Feature",
  "properties": {
    "hierarchy": [
      "tgn:1071245",
      "tgn:1000004",
      "tgn:7002076",
      "tgn:1000111",
      "tgn:7029392"
    ],
    "placetype": [
      "aat:300008347"
    ],
    "id": 1071245,
    "name:xx": "Rui An"
  }
}
