{
  "type": "FeatureCollection",
  "features": [
    {
      "geometry": {
        "type": "Point",
        "coordinates": [
          -76.6833,
          38.4167
        ]
      },
      "type": "Feature",
      "properties": {
        "hierarchy": [
          "tgn:2048168",
          "tgn:1000001",
          "tgn:7016098",
          "tgn:7012149",
          "tgn:7007516",
          "tgn:7029392"
        ],
        "placetype": [
          "aat:300008347",
          "aat:300387210"
        ],
        "id": 2048168,
        "name:xx": "Oraville"
      }
    },
    {
      "geometry": {
        "type": "Point",
        "coordinates": [
          -76.5167,
          39.1667
        ]
      },
      "type": "Feature",
      "properties": {
        "hierarchy": [
          "tgn:2048169",
          "tgn:7014651",
          "tgn:1000001",
          "tgn:7012149",
          "tgn:7007516",
          "tgn:7029392"
        ],
        "placetype": [
          "aat:300008347"
        ],
        "id": 2048169,
        "name:xx": "Orchard Beach"
      }
    }
  ]
}
