{
  "geometry": {
    "type": "Point",
    "coordinates": [
      -109.5667,
      33.95
    ]
  },
  "type": "Feature",
  "properties": {
    "hierarchy": [
      "tgn:2158824",
      "tgn:2000090",
      "tgn:1000001",
      "tgn:7006451",
      "tgn:7012149",
      "tgn:7029392"
    ],
    "placetype": [
      "aat:300008706"
    ],
    "id": 2158824,
    "name:xx": "Becker Creek"
  }
}
