{
  "geometry": {
    "type": "Point",
    "coordinates": [
      -103.1833,
      34.9167
    ]
  },
  "type": "Feature",
  "properties": {
    "hierarchy": [
      "tgn:2204647",
      "tgn:1000001",
      "tgn:2001433",
      "tgn:7012149",
      "tgn:7007566",
      "tgn:7029392"
    ],
    "placetype": [
      "aat:300008680"
    ],
    "id": 2204647,
    "name:xx": "Buffalo Lake"
  }
}
