{
  "geometry": {
    "type": "Point",
    "coordinates": [
      116.4333,
      -31.5833
    ]
  },
  "type": "Feature",
  "properties": {
    "hierarchy": [
      "tgn:1098345",
      "tgn:7000490",
      "tgn:1000006",
      "tgn:7001834",
      "tgn:7029392"
    ],
    "placetype": [
      "aat:300008347"
    ],
    "id": 1098345,
    "name:xx": "Toodyay"
  }
}
