{
  "type": "FeatureCollection",
  "features": [
    {
      "geometry": {
        "type": "Point",
        "coordinates": [
          -93.9,
          36.4667
        ]
      },
      "type": "Feature",
      "properties": {
        "hierarchy": [
          "tgn:2399340",
          "tgn:1000001",
          "tgn:2000108",
          "tgn:7016172",
          "tgn:7012149",
          "tgn:7029392"
        ],
        "placetype": [
          "aat:300008761"
        ],
        "id": 2399340,
        "name:xx": "Horn Hollow"
      }
    },
    {
      "geometry": {
        "type": "Point",
        "coordinates": [
          -93.6333,
          35.8333
        ]
      },
      "type": "Feature",
      "properties": {
        "hierarchy": [
          "tgn:2399341",
          "tgn:1000001",
          "tgn:7016172",
          "tgn:7012149",
          "tgn:2000148",
          "tgn:7029392"
        ],
        "placetype": [
          "aat:300008761"
        ],
        "id": 2399341,
        "name:xx": "Horn Hollow"
      }
    },
    {
      "geometry": {
        "type": "Point",
        "coordinates": [
          -90.6833,
          34.65
        ]
      },
      "type": "Feature",
      "properties": {
        "hierarchy": [
          "tgn:2399342",
          "tgn:1000001",
          "tgn:7016172",
          "tgn:7012149",
          "tgn:2000143",
          "tgn:7029392"
        ],
        "placetype": [
          "aat:300008761"
        ],
        "id": 2399342,
        "name:xx": "Horn Hollow"
      }
    },
    {
      "geometry": {
        "type": "Point",
        "coordinates": [
          -91.05,
          39.6667
        ]
      },
      "type": "Feature",
      "properties": {
        "hierarchy": [
          "tgn:2399343",
          "tgn:1000001",
          "tgn:7012149",
          "tgn:1002786",
          "tgn:7007251",
          "tgn:7029392"
        ],
        "placetype": [
          "aat:300008761"
        ],
        "id": 2399343,
        "name:xx": "Horn Hollow"
      }
    },
    {
      "geometry": {
        "type": "Point",
        "coordinates": [
          -83.1167,
          38.3833
        ]
      },
      "type": "Feature",
      "properties": {
        "hierarchy": [
          "tgn:2399344",
          "tgn:1000001",
          "tgn:1002240",
          "tgn:7012149",
          "tgn:7007255",
          "tgn:7029392"
        ],
        "placetype": [
          "aat:300008761"
        ],
        "id": 2399344,
        "name:xx": "Horn Hollow"
      }
    },
    {
      "geometry": {
        "type": "Point",
        "coordinates": [
          -93.4167,
          37.8
        ]
      },
      "type": "Feature",
      "properties": {
        "hierarchy": [
          "tgn:2399345",
          "tgn:1000001",
          "tgn:7012149",
          "tgn:7007523",
          "tgn:7029392"
        ],
        "placetype": [
          "aat:300008761"
        ],
        "id": 2399345,
        "name:xx": "Horn Hollow"
      }
    },
    {
      "geometry": {
        "type": "Point",
        "coordinates": [
          -78.1167,
          41.6333
        ]
      },
      "type": "Feature",
      "properties": {
        "hierarchy": [
          "tgn:2399346",
          "tgn:1000001",
          "tgn:7012149",
          "tgn:1002800",
          "tgn:7007710",
          "tgn:7029392"
        ],
        "placetype": [
          "aat:300008761"
        ],
        "id": 2399346,
        "name:xx": "Horn Hollow"
      }
    },
    {
      "geometry": {
        "type": "Point",
        "coordinates": [
          -87.0667,
          35.4333
        ]
      },
      "type": "Feature",
      "properties": {
        "hierarchy": [
          "tgn:2399347",
          "tgn:1000001",
          "tgn:7012149",
          "tgn:2001864",
          "tgn:7007825",
          "tgn:7029392"
        ],
        "placetype": [
          "aat:300008761"
        ],
        "id": 2399347,
        "name:xx": "Horn Hollow"
      }
    },
    {
      "geometry": {
        "type": "Point",
        "coordinates": [
          -85.2,
          36.0333
        ]
      },
      "type": "Feature",
      "properties": {
        "hierarchy": [
          "tgn:2399348",
          "tgn:1000001",
          "tgn:7012149",
          "tgn:2001854",
          "tgn:7007825",
          "tgn:7029392"
        ],
        "placetype": [
          "aat:300008761"
        ],
        "id": 2399348,
        "name:xx": "Horn Hollow"
      }
    },
    {
      "geometry": {
        "type": "Point",
        "coordinates": [
          -70.6833,
          43.05
        ]
      },
      "type": "Feature",
      "properties": {
        "hierarchy": [
          "tgn:2399349",
          "tgn:1000001",
          "tgn:7012149",
          "tgn:2000933",
          "tgn:7007515",
          "tgn:7029392"
        ],
        "placetype": [
          "aat:300008791"
        ],
        "id": 2399349,
        "name:xx": "Horn Island"
      }
    }
  ]
}
