{
  "type": "FeatureCollection",
  "features": [
    {
      "geometry": {
        "type": "Point",
        "coordinates": [
          117.6667,
          49
        ]
      },
      "type": "Feature",
      "properties": {
        "hierarchy": [
          "tgn:1128170",
          "tgn:1000004",
          "tgn:7001838",
          "tgn:1000111",
          "tgn:7029392"
        ],
        "placetype": [
          "aat:300008707"
        ],
        "id": 1128170,
        "name:xx": "Orxon Gol"
      }
    },
    {
      "geometry": {
        "type": "Point",
        "coordinates": [
          21.228323,
          52.768635
        ]
      },
      "type": "Feature",
      "properties": {
        "hierarchy": [
          "tgn:1128171",
          "tgn:1000003",
          "tgn:7024122",
          "tgn:7006366",
          "tgn:7029392"
        ],
        "placetype": [
          "aat:300008707"
        ],
        "id": 1128171,
        "name:xx": "Orzyc"
      }
    },
    {
      "geometry": {
        "type": "Point",
        "coordinates": [
          24.85,
          43.7
        ]
      },
      "type": "Feature",
      "properties": {
        "hierarchy": [
          "tgn:1128174",
          "tgn:7593867",
          "tgn:1000003",
          "tgn:7006413",
          "tgn:7029392"
        ],
        "placetype": [
          "aat:300008707"
        ],
        "id": 1128174,
        "name:xx": "Osŭm"
      }
    },
    {
      "geometry": {
        "type": "Point",
        "coordinates": [
          -124.4833,
          56.0833
        ]
      },
      "type": "Feature",
      "properties": {
        "hierarchy": [
          "tgn:1128176",
          "tgn:7005735",
          "tgn:7005685",
          "tgn:1000001",
          "tgn:7029392"
        ],
        "placetype": [
          "aat:300008707"
        ],
        "id": 1128176,
        "name:xx": "Osilinka"
      }
    },
    {
      "geometry": {
        "type": "Point",
        "coordinates": [
          37.4167,
          49.0833
        ]
      },
      "type": "Feature",
      "properties": {
        "hierarchy": [
          "tgn:1128177",
          "tgn:1000003",
          "tgn:7029392"
        ],
        "placetype": [
          "aat:300008707"
        ],
        "id": 1128177,
        "name:xx": "Oskol"
      }
    },
    {
      "geometry": {
        "type": "Point",
        "coordinates": [
          16.364247,
          49.097498
        ]
      },
      "type": "Feature",
      "properties": {
        "hierarchy": [
          "tgn:1128179",
          "tgn:1003523",
          "tgn:1000003",
          "tgn:1001780",
          "tgn:7029392"
        ],
        "placetype": [
          "aat:300008707"
        ],
        "id": 1128179,
        "name:xx": "Oslava"
      }
    }
  ]
}
