{
  "geometry": {
    "type": "Point",
    "coordinates": [
      31.233333,
      30.616667
    ]
  },
  "type": "Feature",
  "properties": {
    "hierarchy": [
      "tgn:7536435",
      "tgn:7001242",
      "tgn:7016833",
      "tgn:7001312",
      "tgn:7029392"
    ],
    "placetype": [
      "aat:300008347"
    ],
    "name:en": "Kafr aş Şārim al Qiblī",
    "id": 7536435
  }
}
