{
  "geometry": {
    "type": "Point",
    "coordinates": [
      -89.5167,
      34.4167
    ]
  },
  "type": "Feature",
  "properties": {
    "hierarchy": [
      "tgn:2636325",
      "tgn:1000001",
      "tgn:7012149",
      "tgn:2001121",
      "tgn:7007522",
      "tgn:7029392"
    ],
    "placetype": [
      "aat:300008798"
    ],
    "id": 2636325,
    "name:xx": "Saddlers Hill"
  }
}
