{
  "geometry": {
    "type": "Point",
    "coordinates": [
      31.292994,
      31.000426
    ]
  },
  "type": "Feature",
  "properties": {
    "hierarchy": [
      "tgn:7537470",
      "tgn:7001242",
      "tgn:7016833",
      "tgn:7001312",
      "tgn:7029392"
    ],
    "placetype": [
      "aat:300008347"
    ],
    "name:en": "Mīt 'Assās",
    "id": 7537470
  }
}
