{
  "geometry": {
    "type": "Point",
    "coordinates": [
      -6.35,
      39.95
    ]
  },
  "type": "Feature",
  "properties": {
    "hierarchy": [
      "tgn:7341499",
      "tgn:7002811",
      "tgn:1000003",
      "tgn:7003837",
      "tgn:1000095",
      "tgn:7029392"
    ],
    "placetype": [
      "aat:300008699"
    ],
    "id": 7341499,
    "name:xx": "Boquerón del Rivero, Arroyo del"
  }
}
