{
  "geometry": {
    "type": "Point",
    "coordinates": [
      -87.75,
      33.0833
    ]
  },
  "type": "Feature",
  "properties": {
    "hierarchy": [
      "tgn:2157167",
      "tgn:7002659",
      "tgn:1000001",
      "tgn:7012149",
      "tgn:7029392"
    ],
    "placetype": [
      "aat:300008706"
    ],
    "id": 2157167,
    "name:xx": "Beaver Creek"
  }
}
