{
  "geometry": {
    "type": "Point",
    "coordinates": [
      -77.35,
      41.8333
    ]
  },
  "type": "Feature",
  "properties": {
    "hierarchy": [
      "tgn:2520658",
      "tgn:1000001",
      "tgn:7012149",
      "tgn:1002945",
      "tgn:7007710",
      "tgn:7029392"
    ],
    "placetype": [
      "aat:300008761"
    ],
    "id": 2520658,
    "name:xx": "Monks Hollow"
  }
}
