{
  "geometry": {
    "type": "Point",
    "coordinates": [
      -88.0667,
      44.7333
    ]
  },
  "type": "Feature",
  "properties": {
    "hierarchy": [
      "tgn:2720724",
      "tgn:1000001",
      "tgn:7012149",
      "tgn:2002341",
      "tgn:7007922",
      "tgn:7029392"
    ],
    "placetype": [
      "aat:300008706"
    ],
    "id": 2720724,
    "name:xx": "Tibbet Creek"
  }
}
