{
  "geometry": {
    "type": "Point",
    "coordinates": [
      -76.5833,
      34.6667
    ]
  },
  "type": "Feature",
  "properties": {
    "hierarchy": [
      "tgn:2144778",
      "tgn:1000001",
      "tgn:2001477",
      "tgn:7012149",
      "tgn:7007709",
      "tgn:7029392"
    ],
    "placetype": [
      "aat:300008798"
    ],
    "id": 2144778,
    "name:xx": "Bald Hill"
  }
}
