{
  "geometry": {
    "type": "Point",
    "coordinates": [
      -78.9167,
      45.3667
    ]
  },
  "type": "Feature",
  "properties": {
    "hierarchy": [
      "tgn:1117643",
      "tgn:7005685",
      "tgn:1000001",
      "tgn:7013154",
      "tgn:7029392"
    ],
    "placetype": [
      "aat:300008680"
    ],
    "id": 1117643,
    "name:xx": "Oxtongue Lake"
  }
}
