{
  "geometry": {
    "type": "Point",
    "coordinates": [
      -149.9333,
      62.3833
    ]
  },
  "type": "Feature",
  "properties": {
    "hierarchy": [
      "tgn:2567382",
      "tgn:7006450",
      "tgn:1000001",
      "tgn:2124053",
      "tgn:7012149",
      "tgn:7029392"
    ],
    "placetype": [
      "aat:300008680"
    ],
    "id": 2567382,
    "name:xx": "Papa Bear Lake"
  }
}
