{
  "geometry": {
    "type": "Point",
    "coordinates": [
      -72.6167,
      44.55
    ]
  },
  "type": "Feature",
  "properties": {
    "hierarchy": [
      "tgn:2715574",
      "tgn:1000001",
      "tgn:2002133",
      "tgn:7012149",
      "tgn:7007828",
      "tgn:7029392"
    ],
    "placetype": [
      "aat:300008761"
    ],
    "id": 2715574,
    "name:xx": "Terrill Gorge"
  }
}
