{
  "type": "FeatureCollection",
  "features": [
    {
      "geometry": {
        "type": "Point",
        "coordinates": [
          8.816667,
          53.233333
        ]
      },
      "type": "Feature",
      "properties": {
        "hierarchy": [
          "tgn:7161910",
          "tgn:1000003",
          "tgn:7003676",
          "tgn:7000084",
          "tgn:7029392"
        ],
        "placetype": [
          "aat:300008347"
        ],
        "id": 7161910,
        "name:xx": "Horst"
      }
    },
    {
      "geometry": {
        "type": "Point",
        "coordinates": [
          12.05,
          53.15
        ]
      },
      "type": "Feature",
      "properties": {
        "hierarchy": [
          "tgn:7161911",
          "tgn:7000096",
          "tgn:1000003",
          "tgn:7000084",
          "tgn:7029392"
        ],
        "placetype": [
          "aat:300008347"
        ],
        "id": 7161911,
        "name:xx": "Horst"
      }
    },
    {
      "geometry": {
        "type": "Point",
        "coordinates": [
          8.616667,
          53.083333
        ]
      },
      "type": "Feature",
      "properties": {
        "hierarchy": [
          "tgn:7161912",
          "tgn:1000003",
          "tgn:7003676",
          "tgn:7000084",
          "tgn:7029392"
        ],
        "placetype": [
          "aat:300008347"
        ],
        "id": 7161912,
        "name:xx": "Horst"
      }
    },
    {
      "geometry": {
        "type": "Point",
        "coordinates": [
          12.35,
          53.066667
        ]
      },
      "type": "Feature",
      "properties": {
        "hierarchy": [
          "tgn:7161913",
          "tgn:7000096",
          "tgn:1000003",
          "tgn:7000084",
          "tgn:7029392"
        ],
        "placetype": [
          "aat:300008347"
        ],
        "id": 7161913,
        "name:xx": "Horst"
      }
    },
    {
      "geometry": {
        "type": "Point",
        "coordinates": [
          12.55,
          53.016667
        ]
      },
      "type": "Feature",
      "properties": {
        "hierarchy": [
          "tgn:7161914",
          "tgn:7000096",
          "tgn:1000003",
          "tgn:7000084",
          "tgn:7029392"
        ],
        "placetype": [
          "aat:300008347"
        ],
        "id": 7161914,
        "name:xx": "Horst"
      }
    },
    {
      "geometry": {
        "type": "Point",
        "coordinates": [
          9.316667,
          50.733333
        ]
      },
      "type": "Feature",
      "properties": {
        "hierarchy": [
          "tgn:7161915",
          "tgn:1000003",
          "tgn:7003678",
          "tgn:7000084",
          "tgn:7029392"
        ],
        "placetype": [
          "aat:300008863"
        ],
        "id": 7161915,
        "name:xx": "Homberg"
      }
    },
    {
      "geometry": {
        "type": "Point",
        "coordinates": [
          9.133333,
          47.733333
        ]
      },
      "type": "Feature",
      "properties": {
        "hierarchy": [
          "tgn:7161916",
          "tgn:7003692",
          "tgn:1000003",
          "tgn:7000084",
          "tgn:7029392"
        ],
        "placetype": [
          "aat:300008863"
        ],
        "id": 7161916,
        "name:xx": "Homberg"
      }
    },
    {
      "geometry": {
        "type": "Point",
        "coordinates": [
          9.416667,
          47.816667
        ]
      },
      "type": "Feature",
      "properties": {
        "hierarchy": [
          "tgn:7161917",
          "tgn:7003692",
          "tgn:1000003",
          "tgn:7000084",
          "tgn:7029392"
        ],
        "placetype": [
          "aat:300387173"
        ],
        "id": 7161917,
        "name:xx": "Homberg"
      }
    },
    {
      "geometry": {
        "type": "Point",
        "coordinates": [
          10.6,
          49.7
        ]
      },
      "type": "Feature",
      "properties": {
        "hierarchy": [
          "tgn:7161918",
          "tgn:7003669",
          "tgn:1000003",
          "tgn:7000084",
          "tgn:7029392"
        ],
        "placetype": [
          "aat:300008347"
        ],
        "id": 7161918,
        "name:xx": "Hombeer"
      }
    },
    {
      "geometry": {
        "type": "Point",
        "coordinates": [
          8.816667,
          53
        ]
      },
      "type": "Feature",
      "properties": {
        "hierarchy": [
          "tgn:7161919",
          "tgn:1000003",
          "tgn:7003676",
          "tgn:7000084",
          "tgn:7029392"
        ],
        "placetype": [
          "aat:300008699"
        ],
        "id": 7161919,
        "name:xx": "Hombach"
      }
    }
  ]
}
