{
  "type": "FeatureCollection",
  "features": [
    {
      "geometry": {
        "type": "Point",
        "coordinates": [
          11.083333,
          42.616667
        ]
      },
      "type": "Feature",
      "properties": {
        "hierarchy": [
          "tgn:7046581",
          "tgn:1003460",
          "tgn:1000003",
          "tgn:7009760",
          "tgn:1000080",
          "tgn:7029392"
        ],
        "placetype": [
          "aat:300008347"
        ],
        "id": 7046581,
        "name:xx": "Cala di Forno"
      }
    },
    {
      "geometry": {
        "type": "Point",
        "coordinates": [
          8.6,
          46.066667
        ]
      },
      "type": "Feature",
      "properties": {
        "hierarchy": [
          "tgn:7046582",
          "tgn:1003478",
          "tgn:1000003",
          "tgn:7003120",
          "tgn:1000080",
          "tgn:7029392"
        ],
        "placetype": [
          "aat:300008347"
        ],
        "id": 7046582,
        "name:xx": "Calachina"
      }
    },
    {
      "geometry": {
        "type": "Point",
        "coordinates": [
          12.304722,
          44.1825
        ]
      },
      "type": "Feature",
      "properties": {
        "hierarchy": [
          "tgn:7046584",
          "tgn:7003129",
          "tgn:1000003",
          "tgn:7008516",
          "tgn:1000080",
          "tgn:7029392"
        ],
        "placetype": [
          "aat:300008347"
        ],
        "id": 7046584,
        "name:xx": "Calabrina"
      }
    },
    {
      "geometry": {
        "type": "Point",
        "coordinates": [
          14.316667,
          40.583333
        ]
      },
      "type": "Feature",
      "properties": {
        "hierarchy": [
          "tgn:7046587",
          "tgn:7003013",
          "tgn:7003005",
          "tgn:1000003",
          "tgn:1000080",
          "tgn:7029392"
        ],
        "placetype": [
          "aat:300386846"
        ],
        "id": 7046587,
        "name:xx": "Cala Baccoli, Punta di"
      }
    }
  ]
}
