{
  "type": "FeatureCollection",
  "features": [
    {
      "geometry": {
        "type": "Point",
        "coordinates": [
          -121.65,
          41.7667
        ]
      },
      "type": "Feature",
      "properties": {
        "hierarchy": [
          "tgn:2566661",
          "tgn:1000001",
          "tgn:7012149",
          "tgn:7007157",
          "tgn:2000189",
          "tgn:7029392"
        ],
        "placetype": [
          "aat:300386831"
        ],
        "id": 2566661,
        "name:xx": "Panhandle Hills"
      }
    },
    {
      "geometry": {
        "type": "Point",
        "coordinates": [
          -132.85,
          55.1833
        ]
      },
      "type": "Feature",
      "properties": {
        "hierarchy": [
          "tgn:2566662",
          "tgn:7006450",
          "tgn:1000001",
          "tgn:7012149",
          "tgn:2000082",
          "tgn:7029392"
        ],
        "placetype": [
          "aat:300008791"
        ],
        "id": 2566662,
        "name:xx": "Panhandle Island"
      }
    },
    {
      "geometry": {
        "type": "Point",
        "coordinates": [
          -80.7167,
          24.9833
        ]
      },
      "type": "Feature",
      "properties": {
        "hierarchy": [
          "tgn:2566663",
          "tgn:1000001",
          "tgn:7012149",
          "tgn:1002676",
          "tgn:7007240",
          "tgn:7029392"
        ],
        "placetype": [
          "aat:300008791"
        ],
        "id": 2566663,
        "name:xx": "Panhandle Key"
      }
    },
    {
      "geometry": {
        "type": "Point",
        "coordinates": [
          -121.65,
          41.7667
        ]
      },
      "type": "Feature",
      "properties": {
        "hierarchy": [
          "tgn:2566664",
          "tgn:1000001",
          "tgn:7012149",
          "tgn:7007157",
          "tgn:2000189",
          "tgn:7029392"
        ],
        "placetype": [
          "aat:300008680"
        ],
        "id": 2566664,
        "name:xx": "Panhandle Lake"
      }
    },
    {
      "geometry": {
        "type": "Point",
        "coordinates": [
          -91.0667,
          47.9833
        ]
      },
      "type": "Feature",
      "properties": {
        "hierarchy": [
          "tgn:2566665",
          "tgn:1000001",
          "tgn:7012149",
          "tgn:2001036",
          "tgn:7007521",
          "tgn:7029392"
        ],
        "placetype": [
          "aat:300008680"
        ],
        "id": 2566665,
        "name:xx": "Panhandle Lake"
      }
    },
    {
      "geometry": {
        "type": "Point",
        "coordinates": [
          -109.9333,
          45.0833
        ]
      },
      "type": "Feature",
      "properties": {
        "hierarchy": [
          "tgn:2566666",
          "tgn:1000001",
          "tgn:7012149",
          "tgn:2001293",
          "tgn:7007524",
          "tgn:7029392"
        ],
        "placetype": [
          "aat:300008680"
        ],
        "id": 2566666,
        "name:xx": "Panhandle Lake"
      }
    },
    {
      "geometry": {
        "type": "Point",
        "coordinates": [
          -122.1167,
          46.3167
        ]
      },
      "type": "Feature",
      "properties": {
        "hierarchy": [
          "tgn:2566667",
          "tgn:1000001",
          "tgn:7012149",
          "tgn:1002897",
          "tgn:7007920",
          "tgn:7029392"
        ],
        "placetype": [
          "aat:300008680"
        ],
        "id": 2566667,
        "name:xx": "Panhandle Lake"
      }
    },
    {
      "geometry": {
        "type": "Point",
        "coordinates": [
          -123.25,
          47.1667
        ]
      },
      "type": "Feature",
      "properties": {
        "hierarchy": [
          "tgn:2566668",
          "tgn:1000001",
          "tgn:7012149",
          "tgn:1002645",
          "tgn:7007920",
          "tgn:7029392"
        ],
        "placetype": [
          "aat:300008680"
        ],
        "id": 2566668,
        "name:xx": "Panhandle Lake"
      }
    },
    {
      "geometry": {
        "type": "Point",
        "coordinates": [
          -117.2167,
          48.15
        ]
      },
      "type": "Feature",
      "properties": {
        "hierarchy": [
          "tgn:2566669",
          "tgn:1000001",
          "tgn:7012149",
          "tgn:2002248",
          "tgn:7007920",
          "tgn:7029392"
        ],
        "placetype": [
          "aat:300008680"
        ],
        "id": 2566669,
        "name:xx": "Panhandle Lake"
      }
    }
  ]
}
