{
  "geometry": {
    "type": "Point",
    "coordinates": [
      -97.7333,
      29.3667
    ]
  },
  "type": "Feature",
  "properties": {
    "hierarchy": [
      "tgn:2599973",
      "tgn:1000001",
      "tgn:7012149",
      "tgn:1002414",
      "tgn:7007826",
      "tgn:7029392"
    ],
    "placetype": [
      "aat:300006191"
    ],
    "id": 2599973,
    "name:xx": "Pruett, Lake"
  }
}
