{
  "geometry": {
    "type": "Point",
    "coordinates": [
      -72.05,
      -41.766667
    ]
  },
  "type": "Feature",
  "properties": {
    "hierarchy": [
      "tgn:7309972",
      "tgn:1001699",
      "tgn:1000049",
      "tgn:1000002",
      "tgn:7029392"
    ],
    "placetype": [
      "aat:300004792"
    ],
    "id": 7309972,
    "name:xx": "Ñadis"
  }
}
