{
  "geometry": {
    "type": "Point",
    "coordinates": [
      -90.6333,
      45.9333
    ]
  },
  "type": "Feature",
  "properties": {
    "hierarchy": [
      "tgn:2129340",
      "tgn:1000001",
      "tgn:7012149",
      "tgn:2002348",
      "tgn:7007922",
      "tgn:7029392"
    ],
    "placetype": [
      "aat:300008680"
    ],
    "id": 2129340,
    "name:xx": "Alice, Lake"
  }
}
