{
  "geometry": {
    "type": "Point",
    "coordinates": [
      117.7833,
      27.8333
    ]
  },
  "type": "Feature",
  "properties": {
    "hierarchy": [
      "tgn:1104977",
      "tgn:1000004",
      "tgn:7002082",
      "tgn:1000111",
      "tgn:7029392"
    ],
    "placetype": [
      "aat:300008795"
    ],
    "id": 1104977,
    "name:xx": "Huanggang Shan"
  }
}
