{
  "geometry": {
    "type": "Point",
    "coordinates": [
      -111.1333,
      31.3833
    ]
  },
  "type": "Feature",
  "properties": {
    "hierarchy": [
      "tgn:2703543",
      "tgn:1000001",
      "tgn:7006451",
      "tgn:7012149",
      "tgn:2000102",
      "tgn:7029392"
    ],
    "placetype": [
      "aat:300006191"
    ],
    "id": 2703543,
    "name:xx": "Summit Reservoir"
  }
}
