{
  "geometry": {
    "type": "Point",
    "coordinates": [
      -96.25,
      31.1333
    ]
  },
  "type": "Feature",
  "properties": {
    "hierarchy": [
      "tgn:2512193",
      "tgn:1000001",
      "tgn:7012149",
      "tgn:1002590",
      "tgn:7007826",
      "tgn:7029392"
    ],
    "placetype": [
      "aat:300008699"
    ],
    "id": 2512193,
    "name:xx": "Mill Branch"
  }
}
