{
  "geometry": {
    "type": "Point",
    "coordinates": [
      -59.85,
      8.15
    ]
  },
  "type": "Feature",
  "properties": {
    "hierarchy": [
      "tgn:1024219",
      "tgn:7002565",
      "tgn:1000054",
      "tgn:1000002",
      "tgn:7029392"
    ],
    "placetype": [
      "aat:300008347",
      "aat:300387220",
      "aat:300008375"
    ],
    "id": 1024219,
    "name:xx": "Mabaruma"
  }
}
