{
  "geometry": {
    "type": "Point",
    "coordinates": [
      -88.1833,
      36.2667
    ]
  },
  "type": "Feature",
  "properties": {
    "hierarchy": [
      "tgn:2762013",
      "tgn:1000001",
      "tgn:7012149",
      "tgn:2001876",
      "tgn:7007825",
      "tgn:7029392"
    ],
    "placetype": [
      "aat:300006075"
    ],
    "id": 2762013,
    "name:xx": "West Sandy Creek Drainage Ditch"
  }
}
