{
  "geometry": {
    "type": "Point",
    "coordinates": [
      -116.7333,
      42.4167
    ]
  },
  "type": "Feature",
  "properties": {
    "hierarchy": [
      "tgn:2708174",
      "tgn:1000001",
      "tgn:7012149",
      "tgn:2000488",
      "tgn:7007250",
      "tgn:7029392"
    ],
    "placetype": [
      "aat:300008697"
    ],
    "id": 2708174,
    "name:xx": "Swisher Spring"
  }
}
