{
  "geometry": {
    "type": "Point",
    "coordinates": [
      6.7167,
      49.1667
    ]
  },
  "type": "Feature",
  "properties": {
    "hierarchy": [
      "tgn:1032418",
      "tgn:1000003",
      "tgn:7002888",
      "tgn:1000070",
      "tgn:7029392"
    ],
    "placetype": [
      "aat:300008347"
    ],
    "id": 1032418,
    "name:xx": "Carling"
  }
}
