{
  "geometry": {
    "type": "Point",
    "coordinates": [
      -85.35,
      42.2167
    ]
  },
  "type": "Feature",
  "properties": {
    "hierarchy": [
      "tgn:2356032",
      "tgn:1000001",
      "tgn:7012149",
      "tgn:1002529",
      "tgn:7007520",
      "tgn:7029392"
    ],
    "placetype": [
      "aat:300008680"
    ],
    "id": 2356032,
    "name:xx": "Goose Pond"
  }
}
