{
  "geometry": {
    "type": "Point",
    "coordinates": [
      -105.5667,
      31.55
    ]
  },
  "type": "Feature",
  "properties": {
    "hierarchy": [
      "tgn:2773214",
      "tgn:1000001",
      "tgn:7012149",
      "tgn:2002005",
      "tgn:7007826",
      "tgn:7029392"
    ],
    "placetype": [
      "aat:300006191"
    ],
    "id": 2773214,
    "name:xx": "Williamsburg Tank"
  }
}
