{
  "geometry": {
    "type": "Point",
    "coordinates": [
      -87.65,
      30.2667
    ]
  },
  "type": "Feature",
  "properties": {
    "hierarchy": [
      "tgn:2530480",
      "tgn:2000001",
      "tgn:7002659",
      "tgn:1000001",
      "tgn:7012149",
      "tgn:7029392"
    ],
    "placetype": [
      "aat:300387088",
      "aat:300008706"
    ],
    "id": 2530480,
    "name:xx": "Muddy Creek"
  }
}
