{
  "geometry": {
    "type": "Point",
    "coordinates": [
      41.0833,
      35.25
    ]
  },
  "type": "Feature",
  "properties": {
    "hierarchy": [
      "tgn:1118988",
      "tgn:1002075",
      "tgn:1000004",
      "tgn:1000140",
      "tgn:7029392"
    ],
    "placetype": [
      "aat:300266556"
    ],
    "id": 1118988,
    "name:xx": "Rawḍah"
  }
}
