{
  "geometry": {
    "type": "Point",
    "coordinates": [
      75.699511,
      28.872654
    ]
  },
  "type": "Feature",
  "properties": {
    "hierarchy": [
      "tgn:7585434",
      "tgn:1000004",
      "tgn:1001871",
      "tgn:7000198",
      "tgn:7029392"
    ],
    "placetype": [
      "aat:300008347"
    ],
    "name:en": "Dhāni Mīrān",
    "id": 7585434
  }
}
