{
  "geometry": {
    "type": "Point",
    "coordinates": [
      -85.8333,
      36.9667
    ]
  },
  "type": "Feature",
  "properties": {
    "hierarchy": [
      "tgn:2191013",
      "tgn:2000768",
      "tgn:1000001",
      "tgn:7012149",
      "tgn:7007255",
      "tgn:7029392"
    ],
    "placetype": [
      "aat:300008706"
    ],
    "id": 2191013,
    "name:xx": "Boyds Creek"
  }
}
