{
  "type": "FeatureCollection",
  "features": [
    {
      "geometry": {
        "type": "Point",
        "coordinates": [
          170.866667,
          -45.05
        ]
      },
      "type": "Feature",
      "properties": {
        "hierarchy": [
          "tgn:1098920",
          "tgn:1009227",
          "tgn:1000226",
          "tgn:7018437",
          "tgn:1000006",
          "tgn:7029392"
        ],
        "placetype": [
          "aat:300008347"
        ],
        "name:en": "Enfield",
        "id": 1098920
      }
    },
    {
      "geometry": {
        "type": "Point",
        "coordinates": [
          175.4,
          -39.233333
        ]
      },
      "type": "Feature",
      "properties": {
        "hierarchy": [
          "tgn:1098921",
          "tgn:1008380",
          "tgn:7520093",
          "tgn:1000226",
          "tgn:1000006",
          "tgn:7029392"
        ],
        "placetype": [
          "aat:300008347"
        ],
        "name:en": "Erua",
        "id": 1098921
      }
    },
    {
      "geometry": {
        "type": "Point",
        "coordinates": [
          176.833333,
          -39.4
        ]
      },
      "type": "Feature",
      "properties": {
        "hierarchy": [
          "tgn:1098922",
          "tgn:7016670",
          "tgn:1008380",
          "tgn:1000226",
          "tgn:1000006",
          "tgn:7029392"
        ],
        "placetype": [
          "aat:300008347"
        ],
        "name:en": "Eskdale",
        "id": 1098922
      }
    },
    {
      "geometry": {
        "type": "Point",
        "coordinates": [
          170.833333,
          -44.1
        ]
      },
      "type": "Feature",
      "properties": {
        "hierarchy": [
          "tgn:1098923",
          "tgn:1009227",
          "tgn:7001866",
          "tgn:1000226",
          "tgn:1000006",
          "tgn:7029392"
        ],
        "placetype": [
          "aat:300008347"
        ],
        "name:en": "Fairlie",
        "id": 1098923
      }
    },
    {
      "geometry": {
        "type": "Point",
        "coordinates": [
          168.8,
          -46.566667
        ]
      },
      "type": "Feature",
      "properties": {
        "hierarchy": [
          "tgn:1098926",
          "tgn:1009227",
          "tgn:1000226",
          "tgn:7016822",
          "tgn:1000006",
          "tgn:7029392"
        ],
        "placetype": [
          "aat:300008347"
        ],
        "name:en": "Fortrose",
        "id": 1098926
      }
    },
    {
      "geometry": {
        "type": "Point",
        "coordinates": [
          170.0833,
          -43.5
        ]
      },
      "type": "Feature",
      "properties": {
        "hierarchy": [
          "tgn:1098927",
          "tgn:1009227",
          "tgn:1000226",
          "tgn:1000006",
          "tgn:7016850",
          "tgn:7029392"
        ],
        "placetype": [
          "aat:300008347"
        ],
        "id": 1098927,
        "name:xx": "Fox Glacier"
      }
    },
    {
      "geometry": {
        "type": "Point",
        "coordinates": [
          175.3,
          -40.466667
        ]
      },
      "type": "Feature",
      "properties": {
        "hierarchy": [
          "tgn:1098928",
          "tgn:1008380",
          "tgn:7520093",
          "tgn:1000226",
          "tgn:1000006",
          "tgn:7029392"
        ],
        "placetype": [
          "aat:300008347"
        ],
        "name:en": "Foxton",
        "id": 1098928
      }
    },
    {
      "geometry": {
        "type": "Point",
        "coordinates": [
          175.216667,
          -40.466667
        ]
      },
      "type": "Feature",
      "properties": {
        "hierarchy": [
          "tgn:1098929",
          "tgn:1008380",
          "tgn:7520093",
          "tgn:1000226",
          "tgn:1000006",
          "tgn:7029392"
        ],
        "placetype": [
          "aat:300008347"
        ],
        "name:en": "Foxton Beach",
        "id": 1098929
      }
    }
  ]
}
