{
  "type": "FeatureCollection",
  "features": [
    {
      "geometry": {
        "type": "Point",
        "coordinates": [
          139.5,
          35.5
        ]
      },
      "type": "Feature",
      "properties": {
        "hierarchy": [
          "tgn:1004511",
          "tgn:7016696",
          "tgn:1000004",
          "tgn:7000894",
          "tgn:7004836",
          "tgn:1000120",
          "tgn:7029392"
        ],
        "placetype": [
          "aat:300000745"
        ],
        "id": 1004511,
        "name:xx": "Futamatagawa"
      }
    },
    {
      "geometry": {
        "type": "Point",
        "coordinates": [
          139.5,
          35.4667
        ]
      },
      "type": "Feature",
      "properties": {
        "hierarchy": [
          "tgn:1004512",
          "tgn:7016696",
          "tgn:1000004",
          "tgn:7000894",
          "tgn:7004836",
          "tgn:1000120",
          "tgn:7029392"
        ],
        "placetype": [
          "aat:300000745"
        ],
        "id": 1004512,
        "name:xx": "Futatsubashi"
      }
    },
    {
      "geometry": {
        "type": "Point",
        "coordinates": [
          -43.2333,
          -22.9667
        ]
      },
      "type": "Feature",
      "properties": {
        "hierarchy": [
          "tgn:1004513",
          "tgn:1001942",
          "tgn:1000047",
          "tgn:7002457",
          "tgn:1000002",
          "tgn:7017095",
          "tgn:7029392"
        ],
        "placetype": [
          "aat:300000745"
        ],
        "id": 1004513,
        "name:xx": "Gavea"
      }
    },
    {
      "geometry": {
        "type": "Point",
        "coordinates": [
          7.5333,
          51.6
        ]
      },
      "type": "Feature",
      "properties": {
        "hierarchy": [
          "tgn:1004514",
          "tgn:1000003",
          "tgn:7003677",
          "tgn:7000084",
          "tgn:1039980",
          "tgn:7029392"
        ],
        "placetype": [
          "aat:300000745",
          "aat:300387332"
        ],
        "id": 1004514,
        "name:xx": "Gahmen"
      }
    },
    {
      "geometry": {
        "type": "Point",
        "coordinates": [
          12.4833,
          41.8667
        ]
      },
      "type": "Feature",
      "properties": {
        "hierarchy": [
          "tgn:1004516",
          "tgn:7003138",
          "tgn:1000003",
          "tgn:7003080",
          "tgn:1000080",
          "tgn:7000874",
          "tgn:7029392"
        ],
        "placetype": [
          "aat:300008347",
          "aat:300000745"
        ],
        "id": 1004516,
        "name:xx": "Garbatella"
      }
    },
    {
      "geometry": {
        "type": "Point",
        "coordinates": [
          -2.9,
          53.3333
        ]
      },
      "type": "Feature",
      "properties": {
        "hierarchy": [
          "tgn:1004517",
          "tgn:1003614",
          "tgn:7002445",
          "tgn:7010597",
          "tgn:1000003",
          "tgn:7029504",
          "tgn:7008591",
          "tgn:7029392"
        ],
        "placetype": [
          "aat:300000745"
        ],
        "id": 1004517,
        "name:xx": "Garston"
      }
    },
    {
      "geometry": {
        "type": "Point",
        "coordinates": [
          7.4333,
          51.5
        ]
      },
      "type": "Feature",
      "properties": {
        "hierarchy": [
          "tgn:1004518",
          "tgn:1000003",
          "tgn:7003677",
          "tgn:7000084",
          "tgn:7004982",
          "tgn:7029392"
        ],
        "placetype": [
          "aat:300000745",
          "aat:300387332"
        ],
        "id": 1004518,
        "name:xx": "Gartenstadt"
      }
    },
    {
      "geometry": {
        "type": "Point",
        "coordinates": [
          -2.85,
          53.3833
        ]
      },
      "type": "Feature",
      "properties": {
        "hierarchy": [
          "tgn:1004519",
          "tgn:1003614",
          "tgn:7002445",
          "tgn:7010597",
          "tgn:1000003",
          "tgn:7029504",
          "tgn:7008591",
          "tgn:7029392"
        ],
        "placetype": [
          "aat:300000745"
        ],
        "id": 1004519,
        "name:xx": "Gateacre"
      }
    }
  ]
}
