{
  "geometry": {
    "type": "Point",
    "coordinates": [
      -98.5167,
      33.15
    ]
  },
  "type": "Feature",
  "properties": {
    "hierarchy": [
      "tgn:2454800",
      "tgn:1000001",
      "tgn:7012149",
      "tgn:2002098",
      "tgn:7007826",
      "tgn:7029392"
    ],
    "placetype": [
      "aat:300008706"
    ],
    "id": 2454800,
    "name:xx": "Little Dry Creek"
  }
}
