{
  "geometry": {
    "type": "Point",
    "coordinates": [
      7.916667,
      51.35
    ]
  },
  "type": "Feature",
  "properties": {
    "hierarchy": [
      "tgn:1039107",
      "tgn:1000003",
      "tgn:7003677",
      "tgn:7000084",
      "tgn:7029392"
    ],
    "placetype": [
      "aat:300008347"
    ],
    "id": 1039107,
    "name:xx": "Frönsberg"
  }
}
