{
  "geometry": {
    "type": "Point",
    "coordinates": [
      79.099468,
      26.914919
    ]
  },
  "type": "Feature",
  "properties": {
    "hierarchy": [
      "tgn:7561180",
      "tgn:1000004",
      "tgn:7000198",
      "tgn:7016722",
      "tgn:7029392"
    ],
    "placetype": [
      "aat:300008347"
    ],
    "name:en": "Kalyānpur Rāhan",
    "id": 7561180
  }
}
