{
  "type": "FeatureCollection",
  "features": [
    {
      "geometry": {
        "type": "Point",
        "coordinates": [
          -92.05,
          47.4833
        ]
      },
      "type": "Feature",
      "properties": {
        "hierarchy": [
          "tgn:2173960",
          "tgn:1000001",
          "tgn:7012149",
          "tgn:2001067",
          "tgn:7007521",
          "tgn:7029392"
        ],
        "placetype": [
          "aat:300008680"
        ],
        "id": 2173960,
        "name:xx": "Bird Lake"
      }
    },
    {
      "geometry": {
        "type": "Point",
        "coordinates": [
          -88.4333,
          30.5167
        ]
      },
      "type": "Feature",
      "properties": {
        "hierarchy": [
          "tgn:2173961",
          "tgn:1000001",
          "tgn:7012149",
          "tgn:2001115",
          "tgn:7007522",
          "tgn:7029392"
        ],
        "placetype": [
          "aat:300008680"
        ],
        "id": 2173961,
        "name:xx": "Bird Lake"
      }
    },
    {
      "geometry": {
        "type": "Point",
        "coordinates": [
          -99.7,
          46.9833
        ]
      },
      "type": "Feature",
      "properties": {
        "hierarchy": [
          "tgn:2173962",
          "tgn:1000001",
          "tgn:2001578",
          "tgn:7012149",
          "tgn:7007705",
          "tgn:7029392"
        ],
        "placetype": [
          "aat:300008680"
        ],
        "id": 2173962,
        "name:xx": "Bird Lake"
      }
    },
    {
      "geometry": {
        "type": "Point",
        "coordinates": [
          -95.0667,
          29.8167
        ]
      },
      "type": "Feature",
      "properties": {
        "hierarchy": [
          "tgn:2173963",
          "tgn:1000001",
          "tgn:7012149",
          "tgn:1002456",
          "tgn:7007826",
          "tgn:7029392"
        ],
        "placetype": [
          "aat:300008680"
        ],
        "id": 2173963,
        "name:xx": "Bird Lake"
      }
    },
    {
      "geometry": {
        "type": "Point",
        "coordinates": [
          -95.4,
          30.1833
        ]
      },
      "type": "Feature",
      "properties": {
        "hierarchy": [
          "tgn:2173964",
          "tgn:1000001",
          "tgn:7012149",
          "tgn:1002691",
          "tgn:7007826",
          "tgn:7029392"
        ],
        "placetype": [
          "aat:300008680"
        ],
        "id": 2173964,
        "name:xx": "Bird Lake"
      }
    },
    {
      "geometry": {
        "type": "Point",
        "coordinates": [
          -93.55,
          31.0833
        ]
      },
      "type": "Feature",
      "properties": {
        "hierarchy": [
          "tgn:2173965",
          "tgn:1000001",
          "tgn:7012149",
          "tgn:2002047",
          "tgn:7007826",
          "tgn:7029392"
        ],
        "placetype": [
          "aat:300008680"
        ],
        "id": 2173965,
        "name:xx": "Bird Lake"
      }
    },
    {
      "geometry": {
        "type": "Point",
        "coordinates": [
          -121.4333,
          46.1333
        ]
      },
      "type": "Feature",
      "properties": {
        "hierarchy": [
          "tgn:2173966",
          "tgn:1000001",
          "tgn:7012149",
          "tgn:1003042",
          "tgn:7007920",
          "tgn:7029392"
        ],
        "placetype": [
          "aat:300008680"
        ],
        "id": 2173966,
        "name:xx": "Bird Lake"
      }
    },
    {
      "geometry": {
        "type": "Point",
        "coordinates": [
          -89.6667,
          45.7833
        ]
      },
      "type": "Feature",
      "properties": {
        "hierarchy": [
          "tgn:2173967",
          "tgn:1000001",
          "tgn:7012149",
          "tgn:2002342",
          "tgn:7007922",
          "tgn:7029392"
        ],
        "placetype": [
          "aat:300008680"
        ],
        "id": 2173967,
        "name:xx": "Bird Lake"
      }
    },
    {
      "geometry": {
        "type": "Point",
        "coordinates": [
          -120.4667,
          37.3833
        ]
      },
      "type": "Feature",
      "properties": {
        "hierarchy": [
          "tgn:2173968",
          "tgn:1000001",
          "tgn:7012149",
          "tgn:7007157",
          "tgn:1002656",
          "tgn:7029392"
        ],
        "placetype": [
          "aat:300006075"
        ],
        "id": 2173968,
        "name:xx": "Bird Lateral"
      }
    },
    {
      "geometry": {
        "type": "Point",
        "coordinates": [
          -116.9833,
          39.75
        ]
      },
      "type": "Feature",
      "properties": {
        "hierarchy": [
          "tgn:2173969",
          "tgn:1000001",
          "tgn:2001415",
          "tgn:7012149",
          "tgn:7007526",
          "tgn:7029392"
        ],
        "placetype": [
          "aat:300000390"
        ],
        "id": 2173969,
        "name:xx": "Bird Mine"
      }
    }
  ]
}
