{
  "geometry": {
    "type": "Point",
    "coordinates": [
      -72.0333,
      41.8333
    ]
  },
  "type": "Feature",
  "properties": {
    "hierarchy": [
      "tgn:2491682",
      "tgn:1000001",
      "tgn:1003028",
      "tgn:7012149",
      "tgn:7007159",
      "tgn:7029392"
    ],
    "placetype": [
      "aat:300008905"
    ],
    "id": 2491682,
    "name:xx": "Maple Swamp"
  }
}
