{
  "geometry": {
    "type": "Point",
    "coordinates": [
      138.4167,
      36.2667
    ]
  },
  "type": "Feature",
  "properties": {
    "hierarchy": [
      "tgn:1079828",
      "tgn:7000895",
      "tgn:1000004",
      "tgn:1001010",
      "tgn:1000120",
      "tgn:7029392"
    ],
    "placetype": [
      "aat:300008347"
    ],
    "id": 1079828,
    "name:xx": "Asashina"
  }
}
