{
  "type": "FeatureCollection",
  "features": [
    {
      "geometry": {
        "type": "Point",
        "coordinates": [
          -99.65,
          18.95
        ]
      },
      "type": "Feature",
      "properties": {
        "hierarchy": [
          "tgn:7378901",
          "tgn:1000001",
          "tgn:1001893",
          "tgn:7005560",
          "tgn:7029392"
        ],
        "placetype": [
          "aat:300008347"
        ],
        "id": 7378901,
        "name:xx": "Mexicapan"
      }
    },
    {
      "geometry": {
        "type": "Point",
        "coordinates": [
          -99.316667,
          18.975
        ]
      },
      "type": "Feature",
      "properties": {
        "hierarchy": [
          "tgn:7378902",
          "tgn:1000001",
          "tgn:1001893",
          "tgn:7005560",
          "tgn:7029392"
        ],
        "placetype": [
          "aat:300008347"
        ],
        "id": 7378902,
        "name:xx": "Mexicapa"
      }
    },
    {
      "geometry": {
        "type": "Point",
        "coordinates": [
          -106.95,
          28.15
        ]
      },
      "type": "Feature",
      "properties": {
        "hierarchy": [
          "tgn:7378903",
          "tgn:7005581",
          "tgn:1000001",
          "tgn:7005560",
          "tgn:7029392"
        ],
        "placetype": [
          "aat:300008680"
        ],
        "id": 7378903,
        "name:xx": "Mexicanos, Laguna de los"
      }
    },
    {
      "geometry": {
        "type": "Point",
        "coordinates": [
          -101.966667,
          22.2
        ]
      },
      "type": "Feature",
      "properties": {
        "hierarchy": [
          "tgn:7378904",
          "tgn:1000001",
          "tgn:7005601",
          "tgn:7005560",
          "tgn:7029392"
        ],
        "placetype": [
          "aat:300008347"
        ],
        "id": 7378904,
        "name:xx": "Mexicanos"
      }
    },
    {
      "geometry": {
        "type": "Point",
        "coordinates": [
          -102,
          24
        ]
      },
      "type": "Feature",
      "properties": {
        "hierarchy": [
          "tgn:7378905",
          "tgn:7005583",
          "tgn:1000001",
          "tgn:7005560",
          "tgn:7029392"
        ],
        "placetype": [
          "aat:300132339"
        ],
        "id": 7378905,
        "name:es": "Mexicana, Altiplanicie"
      }
    },
    {
      "geometry": {
        "type": "Point",
        "coordinates": [
          -99.116667,
          19.35
        ]
      },
      "type": "Feature",
      "properties": {
        "hierarchy": [
          "tgn:7378906",
          "tgn:7005575",
          "tgn:1000001",
          "tgn:7005560",
          "tgn:7029392"
        ],
        "placetype": [
          "aat:300008347"
        ],
        "id": 7378906,
        "name:xx": "Mexicaltzingo"
      }
    },
    {
      "geometry": {
        "type": "Point",
        "coordinates": [
          -105.5,
          21.75
        ]
      },
      "type": "Feature",
      "properties": {
        "hierarchy": [
          "tgn:7378908",
          "tgn:1000001",
          "tgn:1001906",
          "tgn:7005560",
          "tgn:7029392"
        ],
        "placetype": [
          "aat:300386885"
        ],
        "id": 7378908,
        "name:xx": "Mexcaltitán, Barra"
      }
    },
    {
      "geometry": {
        "type": "Point",
        "coordinates": [
          -105.466667,
          21.9
        ]
      },
      "type": "Feature",
      "properties": {
        "hierarchy": [
          "tgn:7378909",
          "tgn:1000001",
          "tgn:1001906",
          "tgn:7005560",
          "tgn:7029392"
        ],
        "placetype": [
          "aat:300008347"
        ],
        "id": 7378909,
        "name:xx": "Mexcaltitán"
      }
    }
  ]
}
