{
  "geometry": {
    "type": "Point",
    "coordinates": [
      -89.0167,
      39.8333
    ]
  },
  "type": "Feature",
  "properties": {
    "hierarchy": [
      "tgn:2783560",
      "tgn:1000001",
      "tgn:7012149",
      "tgn:1002618",
      "tgn:7007251",
      "tgn:7029392"
    ],
    "placetype": [
      "aat:300008347"
    ],
    "id": 2783560,
    "name:xx": "Wyckles Corners"
  }
}
