{
  "geometry": {
    "type": "Point",
    "coordinates": [
      5.2167,
      45.1667
    ]
  },
  "type": "Feature",
  "properties": {
    "hierarchy": [
      "tgn:1035249",
      "tgn:1000003",
      "tgn:1000070",
      "tgn:7002897",
      "tgn:7029392"
    ],
    "placetype": [
      "aat:300008347"
    ],
    "id": 1035249,
    "name:xx": "Saint-Antoine"
  }
}
