{
  "geometry": {
    "type": "Point",
    "coordinates": [
      -77.7167,
      41.6833
    ]
  },
  "type": "Feature",
  "properties": {
    "hierarchy": [
      "tgn:2669540",
      "tgn:1000001",
      "tgn:7012149",
      "tgn:1002800",
      "tgn:7007710",
      "tgn:7029392"
    ],
    "placetype": [
      "aat:300008761"
    ],
    "id": 2669540,
    "name:xx": "Slide Hollow"
  }
}
