{
  "type": "FeatureCollection",
  "features": [
    {
      "geometry": {
        "type": "Point",
        "coordinates": [
          28.2333,
          -26.2333
        ]
      },
      "type": "Feature",
      "properties": {
        "hierarchy": [
          "tgn:1119610",
          "tgn:7001242",
          "tgn:7017576",
          "tgn:1000193",
          "tgn:7029392"
        ],
        "placetype": [
          "aat:300006191"
        ],
        "id": 1119610,
        "name:xx": "Cinderella Dam"
      }
    },
    {
      "geometry": {
        "type": "Point",
        "coordinates": [
          -3.683333,
          52.283333
        ]
      },
      "type": "Feature",
      "properties": {
        "hierarchy": [
          "tgn:1119611",
          "tgn:7002443",
          "tgn:1000003",
          "tgn:7008050",
          "tgn:7008591",
          "tgn:7029392"
        ],
        "placetype": [
          "aat:300006191"
        ],
        "name:en": "Claerwen Reservoir",
        "id": 1119611
      }
    },
    {
      "geometry": {
        "type": "Point",
        "coordinates": [
          -79.65,
          43.7333
        ]
      },
      "type": "Feature",
      "properties": {
        "hierarchy": [
          "tgn:1119613",
          "tgn:7005685",
          "tgn:1000001",
          "tgn:7013154",
          "tgn:7029392"
        ],
        "placetype": [
          "aat:300006191"
        ],
        "id": 1119613,
        "name:xx": "Claireville Reservoir"
      }
    },
    {
      "geometry": {
        "type": "Point",
        "coordinates": [
          -112.85,
          44.9833
        ]
      },
      "type": "Feature",
      "properties": {
        "hierarchy": [
          "tgn:1119615",
          "tgn:1000001",
          "tgn:2001260",
          "tgn:7012149",
          "tgn:7007524",
          "tgn:7029392"
        ],
        "placetype": [
          "aat:300006191"
        ],
        "id": 1119615,
        "name:xx": "Clark Canyon Reservoir"
      }
    },
    {
      "geometry": {
        "type": "Point",
        "coordinates": [
          -82.6,
          40.6833
        ]
      },
      "type": "Feature",
      "properties": {
        "hierarchy": [
          "tgn:1119619",
          "tgn:1000001",
          "tgn:7012149",
          "tgn:7007706",
          "tgn:7029392"
        ],
        "placetype": [
          "aat:300006191"
        ],
        "id": 1119619,
        "name:xx": "Clear Fork Reservoir"
      }
    }
  ]
}
