{
  "geometry": {
    "type": "Point",
    "coordinates": [
      -42.9167,
      -22.8333
    ]
  },
  "type": "Feature",
  "properties": {
    "hierarchy": [
      "tgn:1136509",
      "tgn:1001942",
      "tgn:1000047",
      "tgn:7002457",
      "tgn:1000002",
      "tgn:7029392"
    ],
    "placetype": [
      "aat:300008347"
    ],
    "id": 1136509,
    "name:xx": "Cabuçu"
  }
}
