{
  "type": "FeatureCollection",
  "features": [
    {
      "geometry": {
        "type": "Point",
        "coordinates": [
          -71.816667,
          -38.55
        ]
      },
      "type": "Feature",
      "properties": {
        "hierarchy": [
          "tgn:7310870",
          "tgn:1001692",
          "tgn:1000049",
          "tgn:1000002",
          "tgn:7029392"
        ],
        "placetype": [
          "aat:300008699"
        ],
        "id": 7310870,
        "name:xx": "Negro, Río"
      }
    },
    {
      "geometry": {
        "type": "Point",
        "coordinates": [
          -71.866667,
          -38.433333
        ]
      },
      "type": "Feature",
      "properties": {
        "hierarchy": [
          "tgn:7310871",
          "tgn:1001692",
          "tgn:1000049",
          "tgn:1000002",
          "tgn:7029392"
        ],
        "placetype": [
          "aat:300008699"
        ],
        "id": 7310871,
        "name:xx": "Negro, Río"
      }
    },
    {
      "geometry": {
        "type": "Point",
        "coordinates": [
          -73.316667,
          -37.5
        ]
      },
      "type": "Feature",
      "properties": {
        "hierarchy": [
          "tgn:7310872",
          "tgn:1001637",
          "tgn:1000049",
          "tgn:1000002",
          "tgn:7029392"
        ],
        "placetype": [
          "aat:300008699"
        ],
        "id": 7310872,
        "name:xx": "Negro, Río"
      }
    },
    {
      "geometry": {
        "type": "Point",
        "coordinates": [
          -70.666667,
          -35.333333
        ]
      },
      "type": "Feature",
      "properties": {
        "hierarchy": [
          "tgn:7310873",
          "tgn:1001705",
          "tgn:1000049",
          "tgn:1000002",
          "tgn:7029392"
        ],
        "placetype": [
          "aat:300008699"
        ],
        "id": 7310873,
        "name:xx": "Negro, Río"
      }
    },
    {
      "geometry": {
        "type": "Point",
        "coordinates": [
          -70.066667,
          -34.1
        ]
      },
      "type": "Feature",
      "properties": {
        "hierarchy": [
          "tgn:7310874",
          "tgn:1001708",
          "tgn:1000049",
          "tgn:1000002",
          "tgn:7029392"
        ],
        "placetype": [
          "aat:300008699"
        ],
        "id": 7310874,
        "name:xx": "Negro, Río"
      }
    },
    {
      "geometry": {
        "type": "Point",
        "coordinates": [
          -70.633333,
          -31.383333
        ]
      },
      "type": "Feature",
      "properties": {
        "hierarchy": [
          "tgn:7310875",
          "tgn:1001657",
          "tgn:1000049",
          "tgn:1000002",
          "tgn:7029392"
        ],
        "placetype": [
          "aat:300008699"
        ],
        "id": 7310875,
        "name:xx": "Negro, Río"
      }
    },
    {
      "geometry": {
        "type": "Point",
        "coordinates": [
          -71.166667,
          -28.466667
        ]
      },
      "type": "Feature",
      "properties": {
        "hierarchy": [
          "tgn:7310876",
          "tgn:1001630",
          "tgn:1000049",
          "tgn:1000002",
          "tgn:7029392"
        ],
        "placetype": [
          "aat:300266554",
          "aat:300008699"
        ],
        "id": 7310876,
        "name:xx": "Negro, Quebrada del"
      }
    },
    {
      "geometry": {
        "type": "Point",
        "coordinates": [
          -71.05,
          -34.133333
        ]
      },
      "type": "Feature",
      "properties": {
        "hierarchy": [
          "tgn:7310877",
          "tgn:1001708",
          "tgn:1000049",
          "tgn:1000002",
          "tgn:7029392"
        ],
        "placetype": [
          "aat:300008699"
        ],
        "id": 7310877,
        "name:xx": "Negro, Quebrada del"
      }
    },
    {
      "geometry": {
        "type": "Point",
        "coordinates": [
          -71.1,
          -28.966667
        ]
      },
      "type": "Feature",
      "properties": {
        "hierarchy": [
          "tgn:7310878",
          "tgn:1001630",
          "tgn:1000049",
          "tgn:1000002",
          "tgn:7029392"
        ],
        "placetype": [
          "aat:300008699"
        ],
        "id": 7310878,
        "name:xx": "Negro, Quebrada del"
      }
    },
    {
      "geometry": {
        "type": "Point",
        "coordinates": [
          -70.816667,
          -27.083333
        ]
      },
      "type": "Feature",
      "properties": {
        "hierarchy": [
          "tgn:7310879",
          "tgn:1001630",
          "tgn:1000049",
          "tgn:1000002",
          "tgn:7029392"
        ],
        "placetype": [
          "aat:300386846"
        ],
        "id": 7310879,
        "name:xx": "Negro, Punta"
      }
    }
  ]
}
