{
  "geometry": {
    "type": "Point",
    "coordinates": [
      -72.3167,
      41.0333
    ]
  },
  "type": "Feature",
  "properties": {
    "hierarchy": [
      "tgn:2677888",
      "tgn:1000001",
      "tgn:7012149",
      "tgn:1002924",
      "tgn:7007568",
      "tgn:7029392"
    ],
    "placetype": [
      "aat:300386831"
    ],
    "id": 2677888,
    "name:xx": "South Ferry Hills"
  }
}
