{
  "geometry": {
    "type": "Point",
    "coordinates": [
      -71.7667,
      -2.1167
    ]
  },
  "type": "Feature",
  "properties": {
    "hierarchy": [
      "tgn:1023709",
      "tgn:1000499",
      "tgn:1000050",
      "tgn:1000002",
      "tgn:7029392"
    ],
    "placetype": [
      "aat:300008347"
    ],
    "id": 1023709,
    "name:xx": "Arica"
  }
}
