{
  "geometry": {
    "type": "Point",
    "coordinates": [
      -73.1167,
      42.0833
    ]
  },
  "type": "Feature",
  "properties": {
    "hierarchy": [
      "tgn:2549428",
      "tgn:7013388",
      "tgn:1000001",
      "tgn:7012149",
      "tgn:7007517",
      "tgn:7029392"
    ],
    "placetype": [
      "aat:300006191"
    ],
    "id": 2549428,
    "name:xx": "North Silver Lake Reservoir"
  }
}
