{
  "geometry": {
    "type": "Point",
    "coordinates": [
      116.6833,
      2.6333
    ]
  },
  "type": "Feature",
  "properties": {
    "hierarchy": [
      "tgn:1078175",
      "tgn:1000004",
      "tgn:1001339",
      "tgn:1000116",
      "tgn:7029392"
    ],
    "placetype": [
      "aat:300008347"
    ],
    "id": 1078175,
    "name:xx": "Muarapangean"
  }
}
