{
  "type": "FeatureCollection",
  "features": [
    {
      "geometry": {
        "type": "Point",
        "coordinates": [
          12.333333,
          49
        ]
      },
      "type": "Feature",
      "properties": {
        "hierarchy": [
          "tgn:7063760",
          "tgn:7003669",
          "tgn:1000003",
          "tgn:7000084",
          "tgn:7029392"
        ],
        "placetype": [
          "aat:300000206"
        ],
        "id": 7063760,
        "name:xx": "Auhof"
      }
    },
    {
      "geometry": {
        "type": "Point",
        "coordinates": [
          9.3,
          52.416667
        ]
      },
      "type": "Feature",
      "properties": {
        "hierarchy": [
          "tgn:7063762",
          "tgn:1000003",
          "tgn:7003676",
          "tgn:7000084",
          "tgn:7029392"
        ],
        "placetype": [
          "aat:300008777"
        ],
        "id": 7063762,
        "name:xx": "Atge-Berg"
      }
    },
    {
      "geometry": {
        "type": "Point",
        "coordinates": [
          12.633333,
          51.733333
        ]
      },
      "type": "Feature",
      "properties": {
        "hierarchy": [
          "tgn:7063763",
          "tgn:1000003",
          "tgn:7003687",
          "tgn:7000084",
          "tgn:7029392"
        ],
        "placetype": [
          "aat:300008347"
        ],
        "id": 7063763,
        "name:xx": "Ateritz"
      }
    },
    {
      "geometry": {
        "type": "Point",
        "coordinates": [
          8.466667,
          53.483333
        ]
      },
      "type": "Feature",
      "properties": {
        "hierarchy": [
          "tgn:7063764",
          "tgn:1000003",
          "tgn:7003676",
          "tgn:7000084",
          "tgn:7029392"
        ],
        "placetype": [
          "aat:300386990"
        ],
        "id": 7063764,
        "name:xx": "Atensersand"
      }
    },
    {
      "geometry": {
        "type": "Point",
        "coordinates": [
          8.483333,
          53.5
        ]
      },
      "type": "Feature",
      "properties": {
        "hierarchy": [
          "tgn:7063765",
          "tgn:1000003",
          "tgn:7003676",
          "tgn:7000084",
          "tgn:7029392"
        ],
        "placetype": [
          "aat:300008347"
        ],
        "id": 7063765,
        "name:xx": "Atenseraltensiel"
      }
    },
    {
      "geometry": {
        "type": "Point",
        "coordinates": [
          8.466667,
          53.5
        ]
      },
      "type": "Feature",
      "properties": {
        "hierarchy": [
          "tgn:7063766",
          "tgn:1000003",
          "tgn:7003676",
          "tgn:7000084",
          "tgn:7029392"
        ],
        "placetype": [
          "aat:300008347"
        ],
        "id": 7063766,
        "name:xx": "Atens"
      }
    },
    {
      "geometry": {
        "type": "Point",
        "coordinates": [
          7.95,
          47.65
        ]
      },
      "type": "Feature",
      "properties": {
        "hierarchy": [
          "tgn:7063767",
          "tgn:7003692",
          "tgn:1000003",
          "tgn:7000084",
          "tgn:7029392"
        ],
        "placetype": [
          "aat:300008347"
        ],
        "id": 7063767,
        "name:xx": "Atdorf"
      }
    },
    {
      "geometry": {
        "type": "Point",
        "coordinates": [
          7.2,
          49.55
        ]
      },
      "type": "Feature",
      "properties": {
        "hierarchy": [
          "tgn:7063768",
          "tgn:1000003",
          "tgn:7003684",
          "tgn:7000084",
          "tgn:7029392"
        ],
        "placetype": [
          "aat:300008347"
        ],
        "id": 7063768,
        "name:xx": "Asweiler"
      }
    },
    {
      "geometry": {
        "type": "Point",
        "coordinates": [
          8.1,
          52.483333
        ]
      },
      "type": "Feature",
      "properties": {
        "hierarchy": [
          "tgn:7063769",
          "tgn:1000003",
          "tgn:7003676",
          "tgn:7000084",
          "tgn:7029392"
        ],
        "placetype": [
          "aat:300008699"
        ],
        "id": 7063769,
        "name:xx": "Astruper Bach"
      }
    }
  ]
}
