{
  "geometry": {
    "type": "Point",
    "coordinates": [
      -78.9667,
      33.75
    ]
  },
  "type": "Feature",
  "properties": {
    "hierarchy": [
      "tgn:2268929",
      "tgn:1000001",
      "tgn:7012149",
      "tgn:2001750",
      "tgn:7007712",
      "tgn:7029392"
    ],
    "placetype": [
      "aat:300008699"
    ],
    "id": 2268929,
    "name:xx": "Cross Swamp"
  }
}
