{
  "geometry": {
    "type": "Point",
    "coordinates": [
      -82.1667,
      37.9833
    ]
  },
  "type": "Feature",
  "properties": {
    "hierarchy": [
      "tgn:2625333",
      "tgn:1000001",
      "tgn:7012149",
      "tgn:7013961",
      "tgn:7029392"
    ],
    "placetype": [
      "aat:300008699"
    ],
    "id": 2625333,
    "name:xx": "Rockhouse Fork"
  }
}
