{
  "geometry": {
    "type": "Point",
    "coordinates": [
      -80.0333,
      26.65
    ]
  },
  "type": "Feature",
  "properties": {
    "hierarchy": [
      "tgn:2407151",
      "tgn:1000001",
      "tgn:7012149",
      "tgn:1002768",
      "tgn:7007240",
      "tgn:7029392"
    ],
    "placetype": [
      "aat:300008791"
    ],
    "id": 2407151,
    "name:xx": "Hunters Island"
  }
}
