{
  "geometry": {
    "type": "Point",
    "coordinates": [
      -87.9833,
      34.5667
    ]
  },
  "type": "Feature",
  "properties": {
    "hierarchy": [
      "tgn:2166500",
      "tgn:7002659",
      "tgn:1000001",
      "tgn:2000016",
      "tgn:7012149",
      "tgn:7029392"
    ],
    "placetype": [
      "aat:300008699"
    ],
    "id": 2166500,
    "name:xx": "Big Branch"
  }
}
