{
  "type": "FeatureCollection",
  "features": [
    {
      "geometry": {
        "type": "Point",
        "coordinates": [
          8.95,
          45.9
        ]
      },
      "type": "Feature",
      "properties": {
        "hierarchy": [
          "tgn:4007124",
          "tgn:1000003",
          "tgn:7004723",
          "tgn:7011731",
          "tgn:7029392"
        ],
        "placetype": [
          "aat:300008347"
        ],
        "id": 4007124,
        "name:xx": "Meride"
      }
    },
    {
      "geometry": {
        "type": "Point",
        "coordinates": [
          12.195556,
          45.713056
        ]
      },
      "type": "Feature",
      "properties": {
        "hierarchy": [
          "tgn:4007127",
          "tgn:7002996",
          "tgn:1000003",
          "tgn:7002997",
          "tgn:1000080",
          "tgn:7029392"
        ],
        "placetype": [
          "aat:300008347"
        ],
        "id": 4007127,
        "name:xx": "Merlengo"
      }
    },
    {
      "geometry": {
        "type": "Point",
        "coordinates": [
          -0.516667,
          51.233333
        ]
      },
      "type": "Feature",
      "properties": {
        "hierarchy": [
          "tgn:4007129",
          "tgn:7002445",
          "tgn:1000003",
          "tgn:7008175",
          "tgn:7008591",
          "tgn:7029392"
        ],
        "placetype": [
          "aat:300008347"
        ],
        "name:en": "Merrow",
        "id": 4007129
      }
    }
  ]
}
