{
  "geometry": {
    "type": "Point",
    "coordinates": [
      -102.6667,
      42.4833
    ]
  },
  "type": "Feature",
  "properties": {
    "hierarchy": [
      "tgn:2700234",
      "tgn:1000001",
      "tgn:7012149",
      "tgn:2001396",
      "tgn:7007525",
      "tgn:7029392"
    ],
    "placetype": [
      "aat:300006075"
    ],
    "id": 2700234,
    "name:xx": "Sturgeon Lateral"
  }
}
