{
  "geometry": {
    "type": "Point",
    "coordinates": [
      -74.45,
      43.8167
    ]
  },
  "type": "Feature",
  "properties": {
    "hierarchy": [
      "tgn:2191952",
      "tgn:1000001",
      "tgn:7012149",
      "tgn:1002440",
      "tgn:7007568",
      "tgn:7029392"
    ],
    "placetype": [
      "aat:300008680"
    ],
    "id": 2191952,
    "name:xx": "Brady Pond"
  }
}
