{
  "type": "FeatureCollection",
  "features": [
    {
      "geometry": {
        "type": "Point",
        "coordinates": [
          76,
          29
        ]
      },
      "type": "Feature",
      "properties": {
        "hierarchy": [
          "tgn:1001871",
          "tgn:1000004",
          "tgn:7000198",
          "tgn:7029392"
        ],
        "placetype": [
          "aat:300387064",
          "aat:300000776"
        ],
        "id": 1001871,
        "name:xx": "Haryāna"
      }
    },
    {
      "geometry": {
        "type": "Point",
        "coordinates": [
          7.0167,
          5.6833
        ]
      },
      "type": "Feature",
      "properties": {
        "hierarchy": [
          "tgn:1001874",
          "tgn:7001242",
          "tgn:1000182",
          "tgn:7029392"
        ],
        "placetype": [
          "aat:300387064",
          "aat:300000776"
        ],
        "id": 1001874,
        "name:xx": "Imo"
      }
    },
    {
      "geometry": {
        "type": "Point",
        "coordinates": [
          7.7333,
          11.0167
        ]
      },
      "type": "Feature",
      "properties": {
        "hierarchy": [
          "tgn:1001879",
          "tgn:7001242",
          "tgn:1000182",
          "tgn:7029392"
        ],
        "placetype": [
          "aat:300387064",
          "aat:300000776"
        ],
        "name:en": "Kaduna",
        "id": 1001879
      }
    }
  ]
}
