{
  "geometry": {
    "type": "Point",
    "coordinates": [
      -108.3333,
      39.1167
    ]
  },
  "type": "Feature",
  "properties": {
    "hierarchy": [
      "tgn:2565830",
      "tgn:1000001",
      "tgn:7012149",
      "tgn:2000230",
      "tgn:7007158",
      "tgn:7029392"
    ],
    "placetype": [
      "aat:300000390"
    ],
    "id": 2565830,
    "name:xx": "Palisade Mines"
  }
}
