{
  "type": "FeatureCollection",
  "features": [
    {
      "geometry": {
        "type": "Point",
        "coordinates": [
          174.166667,
          -36.2
        ]
      },
      "type": "Feature",
      "properties": {
        "hierarchy": [
          "tgn:7516380",
          "tgn:1008380",
          "tgn:7000507",
          "tgn:1000226",
          "tgn:1000006",
          "tgn:7029392"
        ],
        "placetype": [
          "aat:300008777"
        ],
        "name:en": "Okaroro",
        "id": 7516380
      }
    },
    {
      "geometry": {
        "type": "Point",
        "coordinates": [
          176.4,
          -38.3
        ]
      },
      "type": "Feature",
      "properties": {
        "hierarchy": [
          "tgn:7516381",
          "tgn:7000509",
          "tgn:1008380",
          "tgn:1000226",
          "tgn:1000006",
          "tgn:7029392"
        ],
        "placetype": [
          "aat:300008680"
        ],
        "name:en": "Okaro Lake",
        "id": 7516381
      }
    },
    {
      "geometry": {
        "type": "Point",
        "coordinates": [
          174.15,
          -36.3
        ]
      },
      "type": "Feature",
      "properties": {
        "hierarchy": [
          "tgn:7516382",
          "tgn:1008380",
          "tgn:7000507",
          "tgn:1000226",
          "tgn:1000006",
          "tgn:7029392"
        ],
        "placetype": [
          "aat:300132316"
        ],
        "name:en": "Okaro Creek",
        "id": 7516382
      }
    },
    {
      "geometry": {
        "type": "Point",
        "coordinates": [
          170.166667,
          -43.233333
        ]
      },
      "type": "Feature",
      "properties": {
        "hierarchy": [
          "tgn:7516383",
          "tgn:1009227",
          "tgn:1000226",
          "tgn:1000006",
          "tgn:7016850",
          "tgn:7029392"
        ],
        "placetype": [
          "aat:300008699"
        ],
        "name:en": "Okarito River",
        "id": 7516383
      }
    },
    {
      "geometry": {
        "type": "Point",
        "coordinates": [
          170.216667,
          -43.2
        ]
      },
      "type": "Feature",
      "properties": {
        "hierarchy": [
          "tgn:7516384",
          "tgn:1009227",
          "tgn:1000226",
          "tgn:1000006",
          "tgn:7016850",
          "tgn:7029392"
        ],
        "placetype": [
          "aat:300008679"
        ],
        "name:en": "Okarito Lagoon",
        "id": 7516384
      }
    },
    {
      "geometry": {
        "type": "Point",
        "coordinates": [
          171.466667,
          -41.833333
        ]
      },
      "type": "Feature",
      "properties": {
        "hierarchy": [
          "tgn:7516386",
          "tgn:1009227",
          "tgn:1000226",
          "tgn:1000006",
          "tgn:7016850",
          "tgn:7029392"
        ],
        "placetype": [
          "aat:300008699"
        ],
        "name:en": "Okari River",
        "id": 7516386
      }
    },
    {
      "geometry": {
        "type": "Point",
        "coordinates": [
          177,
          -38.4
        ]
      },
      "type": "Feature",
      "properties": {
        "hierarchy": [
          "tgn:7516387",
          "tgn:7000509",
          "tgn:1008380",
          "tgn:1000226",
          "tgn:1000006",
          "tgn:7029392"
        ],
        "placetype": [
          "aat:300008699"
        ],
        "name:en": "Okarika River",
        "id": 7516387
      }
    },
    {
      "geometry": {
        "type": "Point",
        "coordinates": [
          174.7,
          -37.4
        ]
      },
      "type": "Feature",
      "properties": {
        "hierarchy": [
          "tgn:7516388",
          "tgn:1008380",
          "tgn:1000226",
          "tgn:7018426",
          "tgn:1000006",
          "tgn:7029392"
        ],
        "placetype": [
          "aat:300386846"
        ],
        "name:en": "Okariha Point",
        "id": 7516388
      }
    },
    {
      "geometry": {
        "type": "Point",
        "coordinates": [
          173.766667,
          -40.9
        ]
      },
      "type": "Feature",
      "properties": {
        "hierarchy": [
          "tgn:7516389",
          "tgn:1009227",
          "tgn:1000226",
          "tgn:7016729",
          "tgn:1000006",
          "tgn:7029392"
        ],
        "placetype": [
          "aat:300386846"
        ],
        "name:en": "Okarewa",
        "id": 7516389
      }
    }
  ]
}
