{
  "geometry": {
    "type": "Point",
    "coordinates": [
      -107.3833,
      35.3333
    ]
  },
  "type": "Feature",
  "properties": {
    "hierarchy": [
      "tgn:2744881",
      "tgn:1000001",
      "tgn:7012149",
      "tgn:7019676",
      "tgn:7007566",
      "tgn:7029392"
    ],
    "placetype": [
      "aat:300008680"
    ],
    "id": 2744881,
    "name:xx": "Vieja, Laguna"
  }
}
