{
  "geometry": {
    "type": "Point",
    "coordinates": [
      -131.5667,
      55.1333
    ]
  },
  "type": "Feature",
  "properties": {
    "hierarchy": [
      "tgn:2593832",
      "tgn:7006450",
      "tgn:1000001",
      "tgn:7012149",
      "tgn:2000082",
      "tgn:7029392"
    ],
    "placetype": [
      "aat:300132316"
    ],
    "id": 2593832,
    "name:xx": "Port Chester"
  }
}
