{
  "geometry": {
    "type": "Point",
    "coordinates": [
      -88.3667,
      30.3833
    ]
  },
  "type": "Feature",
  "properties": {
    "hierarchy": [
      "tgn:2152726",
      "tgn:7002659",
      "tgn:1000001",
      "tgn:7012149",
      "tgn:2000048",
      "tgn:7029392"
    ],
    "placetype": [
      "aat:300132316"
    ],
    "id": 2152726,
    "name:xx": "Bayou La Fourche Bay"
  }
}
