{
  "geometry": {
    "type": "Point",
    "coordinates": [
      121.5667,
      42.3333
    ]
  },
  "type": "Feature",
  "properties": {
    "hierarchy": [
      "tgn:1072661",
      "tgn:1000004",
      "tgn:1001390",
      "tgn:1000111",
      "tgn:7029392"
    ],
    "placetype": [
      "aat:300008347"
    ],
    "id": 1072661,
    "name:xx": "Wuluhayingzi"
  }
}
