{
  "geometry": {
    "type": "Point",
    "coordinates": [
      -88.95,
      32.4167
    ]
  },
  "type": "Feature",
  "properties": {
    "hierarchy": [
      "tgn:2641053",
      "tgn:1000001",
      "tgn:7012149",
      "tgn:2001136",
      "tgn:7007522",
      "tgn:7029392"
    ],
    "placetype": [
      "aat:300008699"
    ],
    "id": 2641053,
    "name:xx": "Sand Branch"
  }
}
