{
  "geometry": {
    "type": "Point",
    "coordinates": [
      -85.0167,
      41.1833
    ]
  },
  "type": "Feature",
  "properties": {
    "hierarchy": [
      "tgn:1119575",
      "tgn:1002143",
      "tgn:1000001",
      "tgn:7012149",
      "tgn:7007252",
      "tgn:7029392"
    ],
    "placetype": [
      "aat:300006191"
    ],
    "id": 1119575,
    "name:xx": "Cedarville Reservoir"
  }
}
