{
  "geometry": {
    "type": "Point",
    "coordinates": [
      164.1667,
      -20.1667
    ]
  },
  "type": "Feature",
  "properties": {
    "hierarchy": [
      "tgn:1006389",
      "tgn:1000223",
      "tgn:1000006",
      "tgn:7029392"
    ],
    "placetype": [
      "aat:300008791"
    ],
    "id": 1006389,
    "name:xx": "Balabio"
  }
}
