{
  "geometry": {
    "type": "Point",
    "coordinates": [
      -90.4333,
      42.3667
    ]
  },
  "type": "Feature",
  "properties": {
    "hierarchy": [
      "tgn:2027958",
      "tgn:1000001",
      "tgn:7012149",
      "tgn:2000514",
      "tgn:7007251",
      "tgn:7029392"
    ],
    "placetype": [
      "aat:300387016"
    ],
    "id": 2027958,
    "name:xx": "Galena Junction"
  }
}
