{
  "geometry": {
    "type": "Point",
    "coordinates": [
      -76.6833,
      36.2833
    ]
  },
  "type": "Feature",
  "properties": {
    "hierarchy": [
      "tgn:2395332",
      "tgn:1000001",
      "tgn:2001482",
      "tgn:7012149",
      "tgn:7007709",
      "tgn:7029392"
    ],
    "placetype": [
      "aat:300008791"
    ],
    "id": 2395332,
    "name:xx": "Holidays Island"
  }
}
