{
  "geometry": {
    "type": "Point",
    "coordinates": [
      -109.8833,
      35.8667
    ]
  },
  "type": "Feature",
  "properties": {
    "hierarchy": [
      "tgn:2692593",
      "tgn:1000001",
      "tgn:7006451",
      "tgn:7012149",
      "tgn:7029392"
    ],
    "placetype": [
      "aat:300008761"
    ],
    "id": 2692593,
    "name:xx": "Steamboat Wash"
  }
}
