{
  "geometry": {
    "type": "Point",
    "coordinates": [
      -108.9833,
      43.5667
    ]
  },
  "type": "Feature",
  "properties": {
    "hierarchy": [
      "tgn:2135025",
      "tgn:1000001",
      "tgn:7012149",
      "tgn:2002371",
      "tgn:7007923",
      "tgn:7029392"
    ],
    "placetype": [
      "aat:300008697"
    ],
    "id": 2135025,
    "name:xx": "Antelope Springs"
  }
}
