{
  "geometry": {
    "type": "Point",
    "coordinates": [
      -77.7333,
      40.0167
    ]
  },
  "type": "Feature",
  "properties": {
    "hierarchy": [
      "tgn:2491389",
      "tgn:1000001",
      "tgn:7012149",
      "tgn:1002387",
      "tgn:7007710",
      "tgn:7029392"
    ],
    "placetype": [
      "aat:300008347"
    ],
    "id": 2491389,
    "name:xx": "Maple Grove"
  }
}
