{
  "geometry": {
    "type": "Point",
    "coordinates": [
      -105.3833,
      40.25
    ]
  },
  "type": "Feature",
  "properties": {
    "hierarchy": [
      "tgn:2211810",
      "tgn:1000001",
      "tgn:7012149",
      "tgn:7007158",
      "tgn:7029392"
    ],
    "placetype": [
      "aat:300008798"
    ],
    "id": 2211810,
    "name:xx": "Button Rock Mountain"
  }
}
