{
  "geometry": {
    "type": "Point",
    "coordinates": [
      -82.35,
      38.2833
    ]
  },
  "type": "Feature",
  "properties": {
    "hierarchy": [
      "tgn:2528480",
      "tgn:1000001",
      "tgn:7012149",
      "tgn:2002299",
      "tgn:7013961",
      "tgn:7029392"
    ],
    "placetype": [
      "aat:300008699"
    ],
    "id": 2528480,
    "name:xx": "Moxley Branch"
  }
}
