{
  "geometry": {
    "type": "Point",
    "coordinates": [
      -122.2167,
      47.7167
    ]
  },
  "type": "Feature",
  "properties": {
    "hierarchy": [
      "tgn:2326666",
      "tgn:1000001",
      "tgn:7012149",
      "tgn:7018871",
      "tgn:7007920",
      "tgn:7029392"
    ],
    "placetype": [
      "aat:300008347"
    ],
    "id": 2326666,
    "name:xx": "Finn Hill"
  }
}
