{
  "geometry": {
    "type": "Point",
    "coordinates": [
      -80.6167,
      40.6167
    ]
  },
  "type": "Feature",
  "properties": {
    "hierarchy": [
      "tgn:2441948",
      "tgn:1000001",
      "tgn:7012149",
      "tgn:7029392"
    ],
    "placetype": [
      "aat:300132348"
    ],
    "id": 2441948,
    "name:xx": "Koontz Bar"
  }
}
