{
  "geometry": {
    "type": "Point",
    "coordinates": [
      13.95,
      53.95
    ]
  },
  "type": "Feature",
  "properties": {
    "hierarchy": [
      "tgn:7197016",
      "tgn:1000003",
      "tgn:7000094",
      "tgn:7000084",
      "tgn:7029392"
    ],
    "placetype": [
      "aat:300055621"
    ],
    "id": 7197016,
    "name:xx": "Der Ubu"
  }
}
