{
  "geometry": {
    "type": "Point",
    "coordinates": [
      -96.45,
      42.3333
    ]
  },
  "type": "Feature",
  "properties": {
    "hierarchy": [
      "tgn:2580516",
      "tgn:1000001",
      "tgn:2001337",
      "tgn:7012149",
      "tgn:7007525",
      "tgn:7029392"
    ],
    "placetype": [
      "aat:300006075"
    ],
    "id": 2580516,
    "name:xx": "Pigeon Creek Ditch"
  }
}
