{
  "geometry": {
    "type": "Point",
    "coordinates": [
      -88.15,
      35.8167
    ]
  },
  "type": "Feature",
  "properties": {
    "hierarchy": [
      "tgn:2774086",
      "tgn:1000001",
      "tgn:7012149",
      "tgn:2001856",
      "tgn:7007825",
      "tgn:7029392"
    ],
    "placetype": [
      "aat:300008706"
    ],
    "id": 2774086,
    "name:xx": "Willow Creek"
  }
}
