{
  "geometry": {
    "type": "Point",
    "coordinates": [
      -107.95,
      39.0833
    ]
  },
  "type": "Feature",
  "properties": {
    "hierarchy": [
      "tgn:2259246",
      "tgn:1000001",
      "tgn:7012149",
      "tgn:2000230",
      "tgn:7007158",
      "tgn:7029392"
    ],
    "placetype": [
      "aat:300006191"
    ],
    "id": 2259246,
    "name:xx": "Cottonwood Lake Number 5"
  }
}
