{
  "geometry": {
    "type": "Point",
    "coordinates": [
      -85.6333,
      41.75
    ]
  },
  "type": "Feature",
  "properties": {
    "hierarchy": [
      "tgn:2327949",
      "tgn:1000001",
      "tgn:7012149",
      "tgn:7029392"
    ],
    "placetype": [
      "aat:300008680"
    ],
    "id": 2327949,
    "name:xx": "Fish Lake"
  }
}
