{
  "geometry": {
    "type": "Point",
    "coordinates": [
      10.8667,
      45.4167
    ]
  },
  "type": "Feature",
  "properties": {
    "hierarchy": [
      "tgn:1112195",
      "tgn:1000003",
      "tgn:7002997",
      "tgn:1000080",
      "tgn:7029392"
    ],
    "placetype": [
      "aat:300387346"
    ],
    "id": 1112195,
    "name:xx": "Valpolicella"
  }
}
