{
  "geometry": {
    "type": "Point",
    "coordinates": [
      -95.0833,
      40.6667
    ]
  },
  "type": "Feature",
  "properties": {
    "hierarchy": [
      "tgn:2509864",
      "tgn:1000001",
      "tgn:7012149",
      "tgn:7029392"
    ],
    "placetype": [
      "aat:300008706"
    ],
    "id": 2509864,
    "name:xx": "Middle Mill Creek"
  }
}
