{
  "geometry": {
    "type": "Point",
    "coordinates": [
      -115.5333,
      43.2667
    ]
  },
  "type": "Feature",
  "properties": {
    "hierarchy": [
      "tgn:2590563",
      "tgn:1000001",
      "tgn:7012149",
      "tgn:2000471",
      "tgn:7007250",
      "tgn:7029392"
    ],
    "placetype": [
      "aat:300008706"
    ],
    "id": 2590563,
    "name:xx": "Pole Creek"
  }
}
