{
  "geometry": {
    "type": "Point",
    "coordinates": [
      112.6833,
      -8.1667
    ]
  },
  "type": "Feature",
  "properties": {
    "hierarchy": [
      "tgn:1078827",
      "tgn:1000004",
      "tgn:1001323",
      "tgn:1000116",
      "tgn:7029392"
    ],
    "placetype": [
      "aat:300008347"
    ],
    "id": 1078827,
    "name:xx": "Turen"
  }
}
