{
  "geometry": {
    "type": "Point",
    "coordinates": [
      -120.4167,
      41.1833
    ]
  },
  "type": "Feature",
  "properties": {
    "hierarchy": [
      "tgn:2529275",
      "tgn:1000001",
      "tgn:7012149",
      "tgn:7007157",
      "tgn:2000186",
      "tgn:7029392"
    ],
    "placetype": [
      "aat:300006191"
    ],
    "id": 2529275,
    "name:xx": "Mud Lake"
  }
}
