{
  "geometry": {
    "type": "Point",
    "coordinates": [
      -70.9667,
      41.6667
    ]
  },
  "type": "Feature",
  "properties": {
    "hierarchy": [
      "tgn:2569990",
      "tgn:1002201",
      "tgn:1000001",
      "tgn:7012149",
      "tgn:7007517",
      "tgn:7029392"
    ],
    "placetype": [
      "aat:300008707"
    ],
    "id": 2569990,
    "name:xx": "Paskamanset River"
  }
}
