{
  "geometry": {
    "type": "Point",
    "coordinates": [
      120.7318,
      23.8172
    ]
  },
  "type": "Feature",
  "properties": {
    "hierarchy": [
      "tgn:7475895",
      "tgn:7488858",
      "tgn:1000004",
      "tgn:1000141",
      "tgn:7029392"
    ],
    "placetype": [
      "aat:300008347"
    ],
    "id": 7475895,
    "name:xx": "Tianzhongzi"
  }
}
