{
  "geometry": {
    "type": "Point",
    "coordinates": [
      -80.1167,
      36.9833
    ]
  },
  "type": "Feature",
  "properties": {
    "hierarchy": [
      "tgn:2329743",
      "tgn:1000001",
      "tgn:7012149",
      "tgn:2002160",
      "tgn:7007919",
      "tgn:7029392"
    ],
    "placetype": [
      "aat:300008798"
    ],
    "id": 2329743,
    "name:xx": "Fivemile Mountain"
  }
}
