{
  "type": "FeatureCollection",
  "features": [
    {
      "geometry": {
        "type": "Point",
        "coordinates": [
          -84.6167,
          33.3
        ]
      },
      "type": "Feature",
      "properties": {
        "hierarchy": [
          "tgn:2146860",
          "tgn:1000001",
          "tgn:7012149",
          "tgn:2000329",
          "tgn:7007248",
          "tgn:7029392"
        ],
        "placetype": [
          "aat:300006191"
        ],
        "id": 2146860,
        "name:xx": "Banks Lake"
      }
    },
    {
      "geometry": {
        "type": "Point",
        "coordinates": [
          -82.05,
          32.3667
        ]
      },
      "type": "Feature",
      "properties": {
        "hierarchy": [
          "tgn:2146861",
          "tgn:1000001",
          "tgn:2000312",
          "tgn:7012149",
          "tgn:7007248",
          "tgn:7029392"
        ],
        "placetype": [
          "aat:300006191"
        ],
        "id": 2146861,
        "name:xx": "Banks Lake"
      }
    },
    {
      "geometry": {
        "type": "Point",
        "coordinates": [
          -83.0833,
          31.0333
        ]
      },
      "type": "Feature",
      "properties": {
        "hierarchy": [
          "tgn:2146862",
          "tgn:1000001",
          "tgn:7012149",
          "tgn:2000377",
          "tgn:7007248",
          "tgn:7029392"
        ],
        "placetype": [
          "aat:300006191"
        ],
        "id": 2146862,
        "name:xx": "Banks Lake"
      }
    },
    {
      "geometry": {
        "type": "Point",
        "coordinates": [
          -86.7333,
          29.6833
        ]
      },
      "type": "Feature",
      "properties": {
        "hierarchy": [
          "tgn:2146863",
          "tgn:1000001",
          "tgn:7012149",
          "tgn:2000553",
          "tgn:7007252",
          "tgn:7029392"
        ],
        "placetype": [
          "aat:300006191"
        ],
        "id": 2146863,
        "name:xx": "Banks Lake"
      }
    },
    {
      "geometry": {
        "type": "Point",
        "coordinates": [
          -89.7,
          30.35
        ]
      },
      "type": "Feature",
      "properties": {
        "hierarchy": [
          "tgn:2146864",
          "tgn:1000001",
          "tgn:7012149",
          "tgn:2000905",
          "tgn:7007256",
          "tgn:7029392"
        ],
        "placetype": [
          "aat:300008680"
        ],
        "id": 2146864,
        "name:xx": "Banks Lake"
      }
    },
    {
      "geometry": {
        "type": "Point",
        "coordinates": [
          -85.3333,
          43.2
        ]
      },
      "type": "Feature",
      "properties": {
        "hierarchy": [
          "tgn:2146865",
          "tgn:1000001",
          "tgn:7012149",
          "tgn:1002540",
          "tgn:7007520",
          "tgn:7029392"
        ],
        "placetype": [
          "aat:300008680"
        ],
        "id": 2146865,
        "name:xx": "Banks Lake"
      }
    },
    {
      "geometry": {
        "type": "Point",
        "coordinates": [
          -89.2833,
          46.2
        ]
      },
      "type": "Feature",
      "properties": {
        "hierarchy": [
          "tgn:2146866",
          "tgn:1000001",
          "tgn:7012149",
          "tgn:2000960",
          "tgn:7007520",
          "tgn:7029392"
        ],
        "placetype": [
          "aat:300008680"
        ],
        "id": 2146866,
        "name:xx": "Banks Lake"
      }
    },
    {
      "geometry": {
        "type": "Point",
        "coordinates": [
          -119.3,
          47.6167
        ]
      },
      "type": "Feature",
      "properties": {
        "hierarchy": [
          "tgn:2146868",
          "tgn:1000001",
          "tgn:7012149",
          "tgn:2002246",
          "tgn:7007920",
          "tgn:7029392"
        ],
        "placetype": [
          "aat:300006191"
        ],
        "id": 2146868,
        "name:xx": "Banks Lake"
      }
    },
    {
      "geometry": {
        "type": "Point",
        "coordinates": [
          -91.9667,
          46.0667
        ]
      },
      "type": "Feature",
      "properties": {
        "hierarchy": [
          "tgn:2146869",
          "tgn:1000001",
          "tgn:7012149",
          "tgn:2002360",
          "tgn:7007922",
          "tgn:7029392"
        ],
        "placetype": [
          "aat:300008680"
        ],
        "id": 2146869,
        "name:xx": "Banks Lake"
      }
    }
  ]
}
