{
  "geometry": {
    "type": "Point",
    "coordinates": [
      -108.2667,
      39.1833
    ]
  },
  "type": "Feature",
  "properties": {
    "hierarchy": [
      "tgn:2158670",
      "tgn:1000001",
      "tgn:7012149",
      "tgn:2000230",
      "tgn:7007158",
      "tgn:7029392"
    ],
    "placetype": [
      "aat:300008850"
    ],
    "id": 2158670,
    "name:xx": "Beavertail Mountain"
  }
}
