{
  "geometry": {
    "type": "Point",
    "coordinates": [
      -85.75,
      38.1667
    ]
  },
  "type": "Feature",
  "properties": {
    "hierarchy": [
      "tgn:2160157",
      "tgn:1000001",
      "tgn:7012149",
      "tgn:1002516",
      "tgn:7007255",
      "tgn:7029392"
    ],
    "placetype": [
      "aat:300008347"
    ],
    "id": 2160157,
    "name:xx": "Beechmont"
  }
}
