{
  "geometry": {
    "type": "Point",
    "coordinates": [
      113.4333,
      27.2333
    ]
  },
  "type": "Feature",
  "properties": {
    "hierarchy": [
      "tgn:1072465",
      "tgn:1000004",
      "tgn:7002079",
      "tgn:1000111",
      "tgn:7029392"
    ],
    "placetype": [
      "aat:300008347"
    ],
    "id": 1072465,
    "name:xx": "Wangling"
  }
}
