{
  "geometry": {
    "type": "Point",
    "coordinates": [
      -71.9833,
      42.7667
    ]
  },
  "type": "Feature",
  "properties": {
    "hierarchy": [
      "tgn:2206366",
      "tgn:7019618",
      "tgn:1000001",
      "tgn:7012149",
      "tgn:7007564",
      "tgn:7029392"
    ],
    "placetype": [
      "aat:300008680"
    ],
    "id": 2206366,
    "name:xx": "Bullet Pond"
  }
}
