{
  "geometry": {
    "type": "Point",
    "coordinates": [
      -96.8667,
      34.1833
    ]
  },
  "type": "Feature",
  "properties": {
    "hierarchy": [
      "tgn:2083572",
      "tgn:1000001",
      "tgn:7012149",
      "tgn:2001657",
      "tgn:7007707",
      "tgn:7029392"
    ],
    "placetype": [
      "aat:300008347"
    ],
    "id": 2083572,
    "name:xx": "Mannsville"
  }
}
