{
  "geometry": {
    "type": "Point",
    "coordinates": [
      66.2667,
      33.3667
    ]
  },
  "type": "Feature",
  "properties": {
    "hierarchy": [
      "tgn:1065429",
      "tgn:7016612",
      "tgn:1000004",
      "tgn:1001469",
      "tgn:7029392"
    ],
    "placetype": [
      "aat:300008347"
    ],
    "id": 1065429,
    "name:xx": "Gizab"
  }
}
