{
  "geometry": {
    "type": "Point",
    "coordinates": [
      10.966667,
      47.55
    ]
  },
  "type": "Feature",
  "properties": {
    "hierarchy": [
      "tgn:7203090",
      "tgn:7003669",
      "tgn:1000003",
      "tgn:7000084",
      "tgn:7029392"
    ],
    "placetype": [
      "aat:300008795"
    ],
    "id": 7203090,
    "name:xx": "Brunnen-Köpfel"
  }
}
