{
  "geometry": {
    "type": "Point",
    "coordinates": [
      -81.0667,
      38.4667
    ]
  },
  "type": "Feature",
  "properties": {
    "hierarchy": [
      "tgn:2242083",
      "tgn:1000001",
      "tgn:2002259",
      "tgn:7012149",
      "tgn:7013961",
      "tgn:7029392"
    ],
    "placetype": [
      "aat:300008347"
    ],
    "id": 2242083,
    "name:xx": "Clay Junction"
  }
}
