{
  "geometry": {
    "type": "Point",
    "coordinates": [
      31.207555,
      30.009929
    ]
  },
  "type": "Feature",
  "properties": {
    "hierarchy": [
      "tgn:7530786",
      "tgn:7001242",
      "tgn:7016833",
      "tgn:1001083",
      "tgn:7029392"
    ],
    "placetype": [
      "aat:300007783"
    ],
    "id": 7530786,
    "name:xx": "Maḩaţţat Qiţārāt al Jīzah"
  }
}
