{
  "geometry": {
    "type": "Point",
    "coordinates": [
      -115.7667,
      43.85
    ]
  },
  "type": "Feature",
  "properties": {
    "hierarchy": [
      "tgn:2338732",
      "tgn:1000001",
      "tgn:2000459",
      "tgn:7012149",
      "tgn:7007250",
      "tgn:7029392"
    ],
    "placetype": [
      "aat:300006075"
    ],
    "id": 2338732,
    "name:xx": "Franer Canal"
  }
}
