{
  "geometry": {
    "type": "Point",
    "coordinates": [
      -109.2833,
      43.8667
    ]
  },
  "type": "Feature",
  "properties": {
    "hierarchy": [
      "tgn:2779815",
      "tgn:1000001",
      "tgn:7012149",
      "tgn:2002379",
      "tgn:7007923",
      "tgn:7029392"
    ],
    "placetype": [
      "aat:300000390"
    ],
    "id": 2779815,
    "name:xx": "Wolf Shaft"
  }
}
