{
  "geometry": {
    "type": "Point",
    "coordinates": [
      -120.35,
      39.3667
    ]
  },
  "type": "Feature",
  "properties": {
    "hierarchy": [
      "tgn:2631636",
      "tgn:1000001",
      "tgn:7012149",
      "tgn:7007157",
      "tgn:1002710",
      "tgn:7029392"
    ],
    "placetype": [
      "aat:300386845"
    ],
    "id": 2631636,
    "name:xx": "Round Valley"
  }
}
