{
  "geometry": {
    "type": "Point",
    "coordinates": [
      33.516667,
      29.233333
    ]
  },
  "type": "Feature",
  "properties": {
    "hierarchy": [
      "tgn:7520779",
      "tgn:7001242",
      "tgn:7016833",
      "tgn:7001336",
      "tgn:7029392"
    ],
    "placetype": [
      "aat:300379998"
    ],
    "name:en": "Abu Alaga, Wâdi",
    "id": 7520779
  }
}
