{
  "geometry": {
    "type": "Point",
    "coordinates": [
      -80.9833,
      39.5333
    ]
  },
  "type": "Feature",
  "properties": {
    "hierarchy": [
      "tgn:2671932",
      "tgn:1000001",
      "tgn:7012149",
      "tgn:2002297",
      "tgn:7013961",
      "tgn:7029392"
    ],
    "placetype": [
      "aat:300266640"
    ],
    "id": 2671932,
    "name:xx": "Smith Ridge"
  }
}
