{
  "geometry": {
    "type": "Point",
    "coordinates": [
      109.8333,
      26.6667
    ]
  },
  "type": "Feature",
  "properties": {
    "hierarchy": [
      "tgn:1131895",
      "tgn:1000004",
      "tgn:1000111",
      "tgn:7029392"
    ],
    "placetype": [
      "aat:300008707"
    ],
    "id": 1131895,
    "name:xx": "Wu Shui"
  }
}
