{
  "geometry": {
    "type": "Point",
    "coordinates": [
      13.3333,
      47.3333
    ]
  },
  "type": "Feature",
  "properties": {
    "name:en": "Austria",
    "name:nl": "Oostenrijk",
    "hierarchy": [
      "tgn:1000062",
      "tgn:1000003",
      "tgn:7029392"
    ],
    "name:ar": "ا نٍمسا",
    "name:de": "Österreich",
    "placetype": [
      "aat:300387054",
      "aat:300179493",
      "aat:300128214",
      "aat:300128207",
      "aat:300387174",
      "aat:300235088",
      "aat:300235096",
      "aat:300235098"
    ],
    "name:fr": "Autriche",
    "name:ru": "Австрия",
    "name:zh": "奥地利",
    "id": 1000062,
    "name:es": "Austria"
  }
}
