{
  "geometry": {
    "type": "Point",
    "coordinates": [
      2.1167,
      50.4667
    ]
  },
  "type": "Feature",
  "properties": {
    "hierarchy": [
      "tgn:7016442",
      "tgn:1000003",
      "tgn:7001097",
      "tgn:1000070",
      "tgn:7029392"
    ],
    "placetype": [
      "aat:300008347",
      "aat:300000835",
      "aat:300008375"
    ],
    "name:fr": "Azincourt",
    "name:en": "Azincourt",
    "id": 7016442
  }
}
