{
  "geometry": {
    "type": "Point",
    "coordinates": [
      -112.8333,
      48.05
    ]
  },
  "type": "Feature",
  "properties": {
    "hierarchy": [
      "tgn:2163308",
      "tgn:1000001",
      "tgn:7012149",
      "tgn:2001309",
      "tgn:7007524",
      "tgn:7029392"
    ],
    "placetype": [
      "aat:300008706"
    ],
    "id": 2163308,
    "name:xx": "Bennie Creek"
  }
}
