{
  "type": "FeatureCollection",
  "features": [
    {
      "geometry": {
        "type": "Point",
        "coordinates": [
          12.5,
          46.683333
        ]
      },
      "type": "Feature",
      "properties": {
        "hierarchy": [
          "tgn:7037882",
          "tgn:7002991",
          "tgn:1000003",
          "tgn:7002997",
          "tgn:1000080",
          "tgn:7029392"
        ],
        "placetype": [
          "aat:300008798"
        ],
        "id": 7037882,
        "name:xx": "Pfannspitze"
      }
    },
    {
      "geometry": {
        "type": "Point",
        "coordinates": [
          8.35,
          46.383333
        ]
      },
      "type": "Feature",
      "properties": {
        "hierarchy": [
          "tgn:7037884",
          "tgn:1003478",
          "tgn:1000003",
          "tgn:7003120",
          "tgn:1000080",
          "tgn:7029392"
        ],
        "placetype": [
          "aat:300008680"
        ],
        "id": 7037884,
        "name:xx": "Vannino, Lago"
      }
    },
    {
      "geometry": {
        "type": "Point",
        "coordinates": [
          8.366667,
          40.55
        ]
      },
      "type": "Feature",
      "properties": {
        "hierarchy": [
          "tgn:7037885",
          "tgn:7015163",
          "tgn:1000003",
          "tgn:7003121",
          "tgn:1000080",
          "tgn:7029392"
        ],
        "placetype": [
          "aat:300008795"
        ],
        "id": 7037885,
        "name:xx": "Vangelex, Monte"
      }
    },
    {
      "geometry": {
        "type": "Point",
        "coordinates": [
          13.95,
          41.333333
        ]
      },
      "type": "Feature",
      "properties": {
        "hierarchy": [
          "tgn:7037886",
          "tgn:7003011",
          "tgn:7003005",
          "tgn:1000003",
          "tgn:1000080",
          "tgn:7029392"
        ],
        "placetype": [
          "aat:300008347"
        ],
        "id": 7037886,
        "name:xx": "Vandria"
      }
    },
    {
      "geometry": {
        "type": "Point",
        "coordinates": [
          14.2,
          41.666667
        ]
      },
      "type": "Feature",
      "properties": {
        "hierarchy": [
          "tgn:7037887",
          "tgn:1003464",
          "tgn:1000003",
          "tgn:7003241",
          "tgn:1000080",
          "tgn:7029392"
        ],
        "placetype": [
          "aat:300008699"
        ],
        "id": 7037887,
        "name:xx": "Vandrella, Torrente"
      }
    },
    {
      "geometry": {
        "type": "Point",
        "coordinates": [
          14.133333,
          41.55
        ]
      },
      "type": "Feature",
      "properties": {
        "hierarchy": [
          "tgn:7037888",
          "tgn:1003464",
          "tgn:1000003",
          "tgn:7003241",
          "tgn:1000080",
          "tgn:7029392"
        ],
        "placetype": [
          "aat:300008699"
        ],
        "id": 7037888,
        "name:xx": "Vandra, Torrente"
      }
    },
    {
      "geometry": {
        "type": "Point",
        "coordinates": [
          11.733333,
          46.8
        ]
      },
      "type": "Feature",
      "properties": {
        "hierarchy": [
          "tgn:7037889",
          "tgn:1003440",
          "tgn:1000003",
          "tgn:7003124",
          "tgn:1000080",
          "tgn:7029392"
        ],
        "placetype": [
          "aat:300008347"
        ],
        "id": 7037889,
        "name:xx": "Vandoies di Sotto"
      }
    }
  ]
}
