{
  "geometry": {
    "type": "Point",
    "coordinates": [
      15.2333,
      31.3667
    ]
  },
  "type": "Feature",
  "properties": {
    "hierarchy": [
      "tgn:1090695",
      "tgn:7001242",
      "tgn:7000607",
      "tgn:1000172",
      "tgn:7029392"
    ],
    "placetype": [
      "aat:300008347"
    ],
    "id": 1090695,
    "name:xx": "Qaryat al Qaddāḥīyah"
  }
}
