{
  "geometry": {
    "type": "Point",
    "coordinates": [
      -97.8167,
      48.9667
    ]
  },
  "type": "Feature",
  "properties": {
    "hierarchy": [
      "tgn:2408779",
      "tgn:1000001",
      "tgn:7012149",
      "tgn:7007705",
      "tgn:7029392"
    ],
    "placetype": [
      "aat:300008761"
    ],
    "id": 2408779,
    "name:xx": "Hyde Park Coulee"
  }
}
