{
  "geometry": {
    "type": "Point",
    "coordinates": [
      30.240833,
      31.228056
    ]
  },
  "type": "Feature",
  "properties": {
    "hierarchy": [
      "tgn:7527266",
      "tgn:7001242",
      "tgn:1001075",
      "tgn:7016833",
      "tgn:7029392"
    ],
    "placetype": [
      "aat:300008791"
    ],
    "name:en": "Z̧āhirah, Jazā'ir az̧",
    "id": 7527266
  }
}
