{
  "geometry": {
    "type": "Point",
    "coordinates": [
      -99.75,
      28.8667
    ]
  },
  "type": "Feature",
  "properties": {
    "hierarchy": [
      "tgn:2339094",
      "tgn:1000001",
      "tgn:7012149",
      "tgn:2002100",
      "tgn:7007826",
      "tgn:7029392"
    ],
    "placetype": [
      "aat:300006191"
    ],
    "id": 2339094,
    "name:xx": "Franklin Tank"
  }
}
