{
  "geometry": {
    "type": "Point",
    "coordinates": [
      -93.2833,
      35.1333
    ]
  },
  "type": "Feature",
  "properties": {
    "hierarchy": [
      "tgn:2185322",
      "tgn:1000001",
      "tgn:7016172",
      "tgn:7012149",
      "tgn:2000179",
      "tgn:7029392"
    ],
    "placetype": [
      "aat:300006191"
    ],
    "id": 2185322,
    "name:xx": "Bogs Lake"
  }
}
