{
  "geometry": {
    "type": "Point",
    "coordinates": [
      87.218,
      21.839
    ]
  },
  "type": "Feature",
  "properties": {
    "hierarchy": [
      "tgn:1076015",
      "tgn:1000004",
      "tgn:7000198",
      "tgn:7016694",
      "tgn:7029392"
    ],
    "placetype": [
      "aat:300008347"
    ],
    "name:en": "Lakshmannāth",
    "id": 1076015
  }
}
