{
  "geometry": {
    "type": "Point",
    "coordinates": [
      109.9167,
      -7.75
    ]
  },
  "type": "Feature",
  "properties": {
    "hierarchy": [
      "tgn:1077933",
      "tgn:1000004",
      "tgn:1001322",
      "tgn:1000116",
      "tgn:7029392"
    ],
    "placetype": [
      "aat:300008347"
    ],
    "id": 1077933,
    "name:xx": "Kutoarjo"
  }
}
