{
  "type": "FeatureCollection",
  "features": [
    {
      "geometry": {
        "type": "Point",
        "coordinates": [
          31.473162,
          30.859924
        ]
      },
      "type": "Feature",
      "properties": {
        "hierarchy": [
          "tgn:7542420",
          "tgn:7001242",
          "tgn:1001059",
          "tgn:7016833",
          "tgn:7029392"
        ],
        "placetype": [
          "aat:300008347"
        ],
        "name:en": "'Izbat Mūsá Bidayr",
        "id": 7542420
      }
    },
    {
      "geometry": {
        "type": "Point",
        "coordinates": [
          31.358926,
          30.858407
        ]
      },
      "type": "Feature",
      "properties": {
        "hierarchy": [
          "tgn:7542421",
          "tgn:7001242",
          "tgn:1001059",
          "tgn:7016833",
          "tgn:7029392"
        ],
        "placetype": [
          "aat:300000206"
        ],
        "name:en": "'Izbat al 'Arab",
        "id": 7542421
      }
    },
    {
      "geometry": {
        "type": "Point",
        "coordinates": [
          31.270938,
          30.867035
        ]
      },
      "type": "Feature",
      "properties": {
        "hierarchy": [
          "tgn:7542422",
          "tgn:7001242",
          "tgn:1001059",
          "tgn:7016833",
          "tgn:7029392"
        ],
        "placetype": [
          "aat:300006075"
        ],
        "name:en": "Tir'at Samāḩah",
        "id": 7542422
      }
    },
    {
      "geometry": {
        "type": "Point",
        "coordinates": [
          31.486416,
          30.856128
        ]
      },
      "type": "Feature",
      "properties": {
        "hierarchy": [
          "tgn:7542423",
          "tgn:7001242",
          "tgn:1001059",
          "tgn:7016833",
          "tgn:7029392"
        ],
        "placetype": [
          "aat:300000206"
        ],
        "name:en": "'Izbat Jabr",
        "id": 7542423
      }
    },
    {
      "geometry": {
        "type": "Point",
        "coordinates": [
          31.426075,
          30.855052
        ]
      },
      "type": "Feature",
      "properties": {
        "hierarchy": [
          "tgn:7542424",
          "tgn:7001242",
          "tgn:1001059",
          "tgn:7016833",
          "tgn:7029392"
        ],
        "placetype": [
          "aat:300000206"
        ],
        "name:en": "'Izbat Sha'bān",
        "id": 7542424
      }
    },
    {
      "geometry": {
        "type": "Point",
        "coordinates": [
          31.42576,
          30.857493
        ]
      },
      "type": "Feature",
      "properties": {
        "hierarchy": [
          "tgn:7542425",
          "tgn:7001242",
          "tgn:1001059",
          "tgn:7016833",
          "tgn:7029392"
        ],
        "placetype": [
          "aat:300006075"
        ],
        "name:en": "Tir'at aţ Ţūkhīyah",
        "id": 7542425
      }
    },
    {
      "geometry": {
        "type": "Point",
        "coordinates": [
          31.426141,
          30.856331
        ]
      },
      "type": "Feature",
      "properties": {
        "hierarchy": [
          "tgn:7542426",
          "tgn:7001242",
          "tgn:1001059",
          "tgn:7016833",
          "tgn:7029392"
        ],
        "placetype": [
          "aat:300006075"
        ],
        "id": 7542426,
        "name:xx": "Tir'at aş Şāfūrīyah"
      }
    },
    {
      "geometry": {
        "type": "Point",
        "coordinates": [
          31.472596,
          30.850418
        ]
      },
      "type": "Feature",
      "properties": {
        "hierarchy": [
          "tgn:7542427",
          "tgn:7001242",
          "tgn:1001059",
          "tgn:7016833",
          "tgn:7029392"
        ],
        "placetype": [
          "aat:300000206"
        ],
        "name:en": "'Izbat aţ Ţabāykhī",
        "id": 7542427
      }
    },
    {
      "geometry": {
        "type": "Point",
        "coordinates": [
          31.430169,
          30.849721
        ]
      },
      "type": "Feature",
      "properties": {
        "hierarchy": [
          "tgn:7542428",
          "tgn:7001242",
          "tgn:1001059",
          "tgn:7016833",
          "tgn:7029392"
        ],
        "placetype": [
          "aat:300008347"
        ],
        "name:en": "'Izbat al Ḩāzmī",
        "id": 7542428
      }
    },
    {
      "geometry": {
        "type": "Point",
        "coordinates": [
          31.268288,
          30.850171
        ]
      },
      "type": "Feature",
      "properties": {
        "hierarchy": [
          "tgn:7542429",
          "tgn:7001242",
          "tgn:1001059",
          "tgn:7016833",
          "tgn:7029392"
        ],
        "placetype": [
          "aat:300006075"
        ],
        "name:en": "Tir'at Mīt Mi'ānid",
        "id": 7542429
      }
    }
  ]
}
