{
  "geometry": {
    "type": "Point",
    "coordinates": [
      -116.05,
      47.9667
    ]
  },
  "type": "Feature",
  "properties": {
    "hierarchy": [
      "tgn:2427463",
      "tgn:1000001",
      "tgn:7012149",
      "tgn:2000491",
      "tgn:7007250",
      "tgn:7029392"
    ],
    "placetype": [
      "aat:300008697"
    ],
    "id": 2427463,
    "name:xx": "Jordan Spring"
  }
}
