{
  "geometry": {
    "type": "Point",
    "coordinates": [
      29.55,
      46.9833
    ]
  },
  "type": "Feature",
  "properties": {
    "hierarchy": [
      "tgn:1056930",
      "tgn:1000003",
      "tgn:7594267",
      "tgn:7006656",
      "tgn:7029392"
    ],
    "placetype": [
      "aat:300008347"
    ],
    "id": 1056930,
    "name:xx": "Mălăiești"
  }
}
