{
  "geometry": {
    "type": "Point",
    "coordinates": [
      -72.3667,
      41.8333
    ]
  },
  "type": "Feature",
  "properties": {
    "hierarchy": [
      "tgn:2507086",
      "tgn:1000001",
      "tgn:1002949",
      "tgn:7012149",
      "tgn:7007159",
      "tgn:7029392"
    ],
    "placetype": [
      "aat:300008699"
    ],
    "id": 2507086,
    "name:xx": "Metcalf Brook"
  }
}
