{
  "geometry": {
    "type": "Point",
    "coordinates": [
      -83.95,
      32.0167
    ]
  },
  "type": "Feature",
  "properties": {
    "hierarchy": [
      "tgn:2352056",
      "tgn:1000001",
      "tgn:7012149",
      "tgn:2000337",
      "tgn:7007248",
      "tgn:7029392"
    ],
    "placetype": [
      "aat:300132316"
    ],
    "id": 2352056,
    "name:xx": "Glory Hole"
  }
}
