{
  "geometry": {
    "type": "Point",
    "coordinates": [
      -90.9667,
      36.2333
    ]
  },
  "type": "Feature",
  "properties": {
    "hierarchy": [
      "tgn:2288487",
      "tgn:1000001",
      "tgn:7016172",
      "tgn:7012149",
      "tgn:2000165",
      "tgn:7029392"
    ],
    "placetype": [
      "aat:300008680"
    ],
    "id": 2288487,
    "name:xx": "Dishpan Lake"
  }
}
