{
  "geometry": {
    "type": "Point",
    "coordinates": [
      -155.3667,
      20.0167
    ]
  },
  "type": "Feature",
  "properties": {
    "hierarchy": [
      "tgn:2124440",
      "tgn:7023902",
      "tgn:1000001",
      "tgn:7012149",
      "tgn:7007249",
      "tgn:7029392"
    ],
    "placetype": [
      "aat:300008761"
    ],
    "id": 2124440,
    "name:xx": "Aamanu Gulch"
  }
}
