{
  "geometry": {
    "type": "Point",
    "coordinates": [
      -122.0167,
      43.5667
    ]
  },
  "type": "Feature",
  "properties": {
    "hierarchy": [
      "tgn:2193352",
      "tgn:1000001",
      "tgn:7012149",
      "tgn:2001714",
      "tgn:7007708",
      "tgn:7029392"
    ],
    "placetype": [
      "aat:300008850"
    ],
    "id": 2193352,
    "name:xx": "Breezy Point"
  }
}
