{
  "geometry": {
    "type": "Point",
    "coordinates": [
      31.45,
      29.933333
    ]
  },
  "type": "Feature",
  "properties": {
    "hierarchy": [
      "tgn:7534713",
      "tgn:7001242",
      "tgn:7016833",
      "tgn:1001091",
      "tgn:7029392"
    ],
    "placetype": [
      "aat:300379998"
    ],
    "name:en": "Ḩimārah, Rawḑ al",
    "id": 7534713
  }
}
