{
  "geometry": {
    "type": "Point",
    "coordinates": [
      -105.3333,
      45.0333
    ]
  },
  "type": "Feature",
  "properties": {
    "hierarchy": [
      "tgn:2189769",
      "tgn:1000001",
      "tgn:7012149",
      "tgn:7029392"
    ],
    "placetype": [
      "aat:300008706"
    ],
    "id": 2189769,
    "name:xx": "Bowers Creek"
  }
}
