{
  "geometry": {
    "type": "Point",
    "coordinates": [
      -78.3167,
      38.55
    ]
  },
  "type": "Feature",
  "properties": {
    "hierarchy": [
      "tgn:2558244",
      "tgn:1000001",
      "tgn:7012149",
      "tgn:2002172",
      "tgn:7007919",
      "tgn:7029392"
    ],
    "placetype": [
      "aat:300008347"
    ],
    "id": 2558244,
    "name:xx": "Oldrag"
  }
}
