{
  "geometry": {
    "type": "Point",
    "coordinates": [
      -102.95,
      20.833333
    ]
  },
  "type": "Feature",
  "properties": {
    "hierarchy": [
      "tgn:7437319",
      "tgn:7005586",
      "tgn:1000001",
      "tgn:7005560",
      "tgn:7029392"
    ],
    "placetype": [
      "aat:300266554",
      "aat:300008699"
    ],
    "id": 7437319,
    "name:xx": "Tepatitlán"
  }
}
