{
  "type": "FeatureCollection",
  "features": [
    {
      "geometry": {
        "type": "Point",
        "coordinates": [
          -105.433333,
          25.083333
        ]
      },
      "type": "Feature",
      "properties": {
        "hierarchy": [
          "tgn:7372410",
          "tgn:7005583",
          "tgn:1000001",
          "tgn:7005560",
          "tgn:7029392"
        ],
        "placetype": [
          "aat:300008347"
        ],
        "id": 7372410,
        "name:xx": "La Estancia"
      }
    },
    {
      "geometry": {
        "type": "Point",
        "coordinates": [
          -107.022222,
          24.895
        ]
      },
      "type": "Feature",
      "properties": {
        "hierarchy": [
          "tgn:7372411",
          "tgn:1000001",
          "tgn:7005595",
          "tgn:7005560",
          "tgn:7029392"
        ],
        "placetype": [
          "aat:300008347"
        ],
        "id": 7372411,
        "name:xx": "La Estancia"
      }
    },
    {
      "geometry": {
        "type": "Point",
        "coordinates": [
          -106.664722,
          24.42
        ]
      },
      "type": "Feature",
      "properties": {
        "hierarchy": [
          "tgn:7372412",
          "tgn:1000001",
          "tgn:7005595",
          "tgn:7005560",
          "tgn:7029392"
        ],
        "placetype": [
          "aat:300008347"
        ],
        "id": 7372412,
        "name:xx": "La Estancia"
      }
    },
    {
      "geometry": {
        "type": "Point",
        "coordinates": [
          -106.75,
          23.716667
        ]
      },
      "type": "Feature",
      "properties": {
        "hierarchy": [
          "tgn:7372413",
          "tgn:1000001",
          "tgn:7005595",
          "tgn:7005560",
          "tgn:7029392"
        ],
        "placetype": [
          "aat:300008347"
        ],
        "id": 7372413,
        "name:xx": "La Estancia"
      }
    },
    {
      "geometry": {
        "type": "Point",
        "coordinates": [
          -102.35,
          22.083333
        ]
      },
      "type": "Feature",
      "properties": {
        "hierarchy": [
          "tgn:7372414",
          "tgn:7005579",
          "tgn:1000001",
          "tgn:7005560",
          "tgn:7029392"
        ],
        "placetype": [
          "aat:300008347"
        ],
        "id": 7372414,
        "name:xx": "La Estancia"
      }
    },
    {
      "geometry": {
        "type": "Point",
        "coordinates": [
          -102.418056,
          21.916667
        ]
      },
      "type": "Feature",
      "properties": {
        "hierarchy": [
          "tgn:7372415",
          "tgn:7005579",
          "tgn:1000001",
          "tgn:7005560",
          "tgn:7029392"
        ],
        "placetype": [
          "aat:300008347"
        ],
        "id": 7372415,
        "name:xx": "La Estancia"
      }
    },
    {
      "geometry": {
        "type": "Point",
        "coordinates": [
          -103,
          21.833333
        ]
      },
      "type": "Feature",
      "properties": {
        "hierarchy": [
          "tgn:7372416",
          "tgn:1000001",
          "tgn:7005601",
          "tgn:7005560",
          "tgn:7029392"
        ],
        "placetype": [
          "aat:300008347"
        ],
        "id": 7372416,
        "name:xx": "La Estancia"
      }
    },
    {
      "geometry": {
        "type": "Point",
        "coordinates": [
          -101.083333,
          21.65
        ]
      },
      "type": "Feature",
      "properties": {
        "hierarchy": [
          "tgn:7372417",
          "tgn:7005584",
          "tgn:1000001",
          "tgn:7005560",
          "tgn:7029392"
        ],
        "placetype": [
          "aat:300008347"
        ],
        "id": 7372417,
        "name:xx": "La Estancia"
      }
    },
    {
      "geometry": {
        "type": "Point",
        "coordinates": [
          -100.366667,
          21.483333
        ]
      },
      "type": "Feature",
      "properties": {
        "hierarchy": [
          "tgn:7372418",
          "tgn:7005584",
          "tgn:1000001",
          "tgn:7005560",
          "tgn:7029392"
        ],
        "placetype": [
          "aat:300008347"
        ],
        "id": 7372418,
        "name:xx": "La Estancia"
      }
    },
    {
      "geometry": {
        "type": "Point",
        "coordinates": [
          -103.85,
          20.933333
        ]
      },
      "type": "Feature",
      "properties": {
        "hierarchy": [
          "tgn:7372419",
          "tgn:7005586",
          "tgn:1000001",
          "tgn:7005560",
          "tgn:7029392"
        ],
        "placetype": [
          "aat:300008347"
        ],
        "id": 7372419,
        "name:xx": "La Estancia"
      }
    }
  ]
}
