{
  "type": "FeatureCollection",
  "features": [
    {
      "geometry": {
        "type": "Point",
        "coordinates": [
          10.333333,
          51.883333
        ]
      },
      "type": "Feature",
      "properties": {
        "hierarchy": [
          "tgn:7099350",
          "tgn:1000003",
          "tgn:7003676",
          "tgn:7000084",
          "tgn:7029392"
        ],
        "placetype": [
          "aat:300008777"
        ],
        "id": 7099350,
        "name:xx": "Sommer-Berg"
      }
    },
    {
      "geometry": {
        "type": "Point",
        "coordinates": [
          9.533333,
          51.833333
        ]
      },
      "type": "Feature",
      "properties": {
        "hierarchy": [
          "tgn:7099351",
          "tgn:1000003",
          "tgn:7003676",
          "tgn:7000084",
          "tgn:7029392"
        ],
        "placetype": [
          "aat:300008777"
        ],
        "id": 7099351,
        "name:xx": "Sommer Berg"
      }
    },
    {
      "geometry": {
        "type": "Point",
        "coordinates": [
          8.8,
          51.833333
        ]
      },
      "type": "Feature",
      "properties": {
        "hierarchy": [
          "tgn:7099352",
          "tgn:1000003",
          "tgn:7003677",
          "tgn:7000084",
          "tgn:7029392"
        ],
        "placetype": [
          "aat:300008777"
        ],
        "id": 7099352,
        "name:xx": "Sommer-Berg"
      }
    },
    {
      "geometry": {
        "type": "Point",
        "coordinates": [
          8.95,
          51.766667
        ]
      },
      "type": "Feature",
      "properties": {
        "hierarchy": [
          "tgn:7099353",
          "tgn:1000003",
          "tgn:7003677",
          "tgn:7000084",
          "tgn:7029392"
        ],
        "placetype": [
          "aat:300008777"
        ],
        "id": 7099353,
        "name:xx": "Sommer-Berg"
      }
    },
    {
      "geometry": {
        "type": "Point",
        "coordinates": [
          10.333333,
          51.5
        ]
      },
      "type": "Feature",
      "properties": {
        "hierarchy": [
          "tgn:7099354",
          "tgn:1000003",
          "tgn:7003689",
          "tgn:7000084",
          "tgn:7029392"
        ],
        "placetype": [
          "aat:300008777"
        ],
        "id": 7099354,
        "name:xx": "Sommer-Berg"
      }
    },
    {
      "geometry": {
        "type": "Point",
        "coordinates": [
          10.366667,
          51.383333
        ]
      },
      "type": "Feature",
      "properties": {
        "hierarchy": [
          "tgn:7099355",
          "tgn:1000003",
          "tgn:7003689",
          "tgn:7000084",
          "tgn:7029392"
        ],
        "placetype": [
          "aat:300008777"
        ],
        "id": 7099355,
        "name:xx": "Sommer-Berg"
      }
    },
    {
      "geometry": {
        "type": "Point",
        "coordinates": [
          8.266667,
          51.316667
        ]
      },
      "type": "Feature",
      "properties": {
        "hierarchy": [
          "tgn:7099356",
          "tgn:1000003",
          "tgn:7003677",
          "tgn:7000084",
          "tgn:7029392"
        ],
        "placetype": [
          "aat:300008777"
        ],
        "id": 7099356,
        "name:xx": "Sommer-Berg"
      }
    },
    {
      "geometry": {
        "type": "Point",
        "coordinates": [
          10.383333,
          51.233333
        ]
      },
      "type": "Feature",
      "properties": {
        "hierarchy": [
          "tgn:7099357",
          "tgn:1000003",
          "tgn:7003689",
          "tgn:7000084",
          "tgn:7029392"
        ],
        "placetype": [
          "aat:300008777"
        ],
        "id": 7099357,
        "name:xx": "Sommer-Berg"
      }
    },
    {
      "geometry": {
        "type": "Point",
        "coordinates": [
          10.083333,
          51.15
        ]
      },
      "type": "Feature",
      "properties": {
        "hierarchy": [
          "tgn:7099358",
          "tgn:1000003",
          "tgn:7003678",
          "tgn:7000084",
          "tgn:7029392"
        ],
        "placetype": [
          "aat:300008777"
        ],
        "id": 7099358,
        "name:xx": "Sommer-Berg"
      }
    },
    {
      "geometry": {
        "type": "Point",
        "coordinates": [
          9.8,
          51.15
        ]
      },
      "type": "Feature",
      "properties": {
        "hierarchy": [
          "tgn:7099359",
          "tgn:1000003",
          "tgn:7003678",
          "tgn:7000084",
          "tgn:7029392"
        ],
        "placetype": [
          "aat:300008777"
        ],
        "id": 7099359,
        "name:xx": "Sommer-Berg"
      }
    }
  ]
}
