{
  "geometry": {
    "type": "Point",
    "coordinates": [
      77.90281,
      30.407792
    ]
  },
  "type": "Feature",
  "properties": {
    "hierarchy": [
      "tgn:7591398",
      "tgn:1000004",
      "tgn:7000198",
      "tgn:7031786",
      "tgn:7029392"
    ],
    "placetype": [
      "aat:300008347"
    ],
    "name:en": "Jūlon",
    "id": 7591398
  }
}
