{
  "geometry": {
    "type": "Point",
    "coordinates": [
      -83.4667,
      36.0167
    ]
  },
  "type": "Feature",
  "properties": {
    "hierarchy": [
      "tgn:2364922",
      "tgn:1000001",
      "tgn:7012149",
      "tgn:2001881",
      "tgn:7007825",
      "tgn:7029392"
    ],
    "placetype": [
      "aat:300008347"
    ],
    "id": 2364922,
    "name:xx": "Greenhill"
  }
}
