{
  "geometry": {
    "type": "Point",
    "coordinates": [
      -96.5833,
      28.65
    ]
  },
  "type": "Feature",
  "properties": {
    "hierarchy": [
      "tgn:1113318",
      "tgn:1000001",
      "tgn:7012149",
      "tgn:2001950",
      "tgn:7007826",
      "tgn:7029392"
    ],
    "placetype": [
      "aat:300132316"
    ],
    "id": 1113318,
    "name:xx": "Lavaca Bay"
  }
}
