{
  "geometry": {
    "type": "Point",
    "coordinates": [
      -85.5333,
      40.6833
    ]
  },
  "type": "Feature",
  "properties": {
    "hierarchy": [
      "tgn:2033325",
      "tgn:1000001",
      "tgn:7012149",
      "tgn:1002496",
      "tgn:7007252",
      "tgn:7029392"
    ],
    "placetype": [
      "aat:300008347",
      "aat:300387210"
    ],
    "id": 2033325,
    "name:xx": "Pleasant Plain"
  }
}
