{
  "geometry": {
    "type": "Point",
    "coordinates": [
      -112.0333,
      33.3333
    ]
  },
  "type": "Feature",
  "properties": {
    "hierarchy": [
      "tgn:2389129",
      "tgn:1000001",
      "tgn:7006451",
      "tgn:7012149",
      "tgn:2000097",
      "tgn:7029392"
    ],
    "placetype": [
      "aat:300008761"
    ],
    "id": 2389129,
    "name:xx": "Hidden Valley"
  }
}
