{
  "geometry": {
    "type": "Point",
    "coordinates": [
      15.0333,
      45.9167
    ]
  },
  "type": "Feature",
  "properties": {
    "hierarchy": [
      "tgn:7015143",
      "tgn:1000003",
      "tgn:7006670",
      "tgn:7029392"
    ],
    "placetype": [
      "aat:300387064",
      "aat:300387081"
    ],
    "id": 7015143,
    "name:xx": "Terbnje, Občina"
  }
}
