{
  "geometry": {
    "type": "Point",
    "coordinates": [
      -82.7167,
      27.7667
    ]
  },
  "type": "Feature",
  "properties": {
    "hierarchy": [
      "tgn:2569932",
      "tgn:1000001",
      "tgn:7012149",
      "tgn:1002790",
      "tgn:7007240",
      "tgn:7029392"
    ],
    "placetype": [
      "aat:300008680"
    ],
    "id": 2569932,
    "name:xx": "Pasadena Lake"
  }
}
