{
  "type": "FeatureCollection",
  "features": [
    {
      "geometry": {
        "type": "Point",
        "coordinates": [
          0.5,
          51.4333
        ]
      },
      "type": "Feature",
      "properties": {
        "hierarchy": [
          "tgn:1028882",
          "tgn:7002445",
          "tgn:1000003",
          "tgn:7008153",
          "tgn:7008591",
          "tgn:7029392"
        ],
        "placetype": [
          "aat:300008347"
        ],
        "id": 1028882,
        "name:xx": "Cliffe Woods"
      }
    },
    {
      "geometry": {
        "type": "Point",
        "coordinates": [
          -2.716667,
          53.416667
        ]
      },
      "type": "Feature",
      "properties": {
        "hierarchy": [
          "tgn:1028885",
          "tgn:1003639",
          "tgn:7002445",
          "tgn:1000003",
          "tgn:7029504",
          "tgn:7008591",
          "tgn:7029392"
        ],
        "placetype": [
          "aat:300008347"
        ],
        "name:en": "Clock Face",
        "id": 1028885
      }
    },
    {
      "geometry": {
        "type": "Point",
        "coordinates": [
          -2.1333,
          53.7167
        ]
      },
      "type": "Feature",
      "properties": {
        "hierarchy": [
          "tgn:1028886",
          "tgn:1003573",
          "tgn:7002445",
          "tgn:1000003",
          "tgn:7029507",
          "tgn:7008591",
          "tgn:7029392"
        ],
        "placetype": [
          "aat:300008347"
        ],
        "id": 1028886,
        "name:xx": "Clough Foot"
      }
    },
    {
      "geometry": {
        "type": "Point",
        "coordinates": [
          -4.4,
          51
        ]
      },
      "type": "Feature",
      "properties": {
        "hierarchy": [
          "tgn:1028887",
          "tgn:7002445",
          "tgn:1000003",
          "tgn:7012077",
          "tgn:7008591",
          "tgn:7029392"
        ],
        "placetype": [
          "aat:300008347",
          "aat:300008375"
        ],
        "name:en": "Clovelly",
        "id": 1028887
      }
    },
    {
      "geometry": {
        "type": "Point",
        "coordinates": [
          -1.25,
          53.266667
        ]
      },
      "type": "Feature",
      "properties": {
        "hierarchy": [
          "tgn:1028888",
          "tgn:7002445",
          "tgn:1000003",
          "tgn:7008118",
          "tgn:7008591",
          "tgn:7029392"
        ],
        "placetype": [
          "aat:300008347",
          "aat:300008372"
        ],
        "id": 1028888,
        "name:ang": "Clune"
      }
    },
    {
      "geometry": {
        "type": "Point",
        "coordinates": [
          -3.033333,
          52.416667
        ]
      },
      "type": "Feature",
      "properties": {
        "hierarchy": [
          "tgn:1028889",
          "tgn:7002445",
          "tgn:1000003",
          "tgn:7012034",
          "tgn:7008591",
          "tgn:7029392"
        ],
        "placetype": [
          "aat:300008347"
        ],
        "name:en": "Clun",
        "id": 1028889
      }
    }
  ]
}
