{
  "geometry": {
    "type": "Point",
    "coordinates": [
      -94.2833,
      37.2333
    ]
  },
  "type": "Feature",
  "properties": {
    "hierarchy": [
      "tgn:2759293",
      "tgn:1000001",
      "tgn:7012149",
      "tgn:1002634",
      "tgn:7007523",
      "tgn:7029392"
    ],
    "placetype": [
      "aat:300008706"
    ],
    "id": 2759293,
    "name:xx": "West Fork Clear Creek"
  }
}
