{
  "geometry": {
    "type": "Point",
    "coordinates": [
      -86.25,
      41.3667
    ]
  },
  "type": "Feature",
  "properties": {
    "hierarchy": [
      "tgn:2222342",
      "tgn:1000001",
      "tgn:7012149",
      "tgn:1002640",
      "tgn:7007252",
      "tgn:7029392"
    ],
    "placetype": [
      "aat:300006075"
    ],
    "id": 2222342,
    "name:xx": "Carothers Ditch"
  }
}
