{
  "geometry": {
    "type": "Point",
    "coordinates": [
      -84.1167,
      35.15
    ]
  },
  "type": "Feature",
  "properties": {
    "hierarchy": [
      "tgn:2202070",
      "tgn:1000001",
      "tgn:2001481",
      "tgn:7012149",
      "tgn:7007709",
      "tgn:7029392"
    ],
    "placetype": [
      "aat:300008798"
    ],
    "id": 2202070,
    "name:xx": "Buck Knob"
  }
}
