{
  "geometry": {
    "type": "Point",
    "coordinates": [
      45.728,
      40.18
    ]
  },
  "type": "Feature",
  "properties": {
    "hierarchy": [
      "tgn:1060940",
      "tgn:1000004",
      "tgn:7024035",
      "tgn:7006651",
      "tgn:7029392"
    ],
    "placetype": [
      "aat:300008347",
      "aat:300008389",
      "aat:300387220"
    ],
    "name:en": "Vardenis",
    "id": 1060940
  }
}
