{
  "type": "FeatureCollection",
  "features": [
    {
      "geometry": {
        "type": "Point",
        "coordinates": [
          -73.65,
          44.1333
        ]
      },
      "type": "Feature",
      "properties": {
        "hierarchy": [
          "tgn:2282340",
          "tgn:1000001",
          "tgn:7012149",
          "tgn:2001461",
          "tgn:7007568",
          "tgn:7029392"
        ],
        "placetype": [
          "aat:300008798"
        ],
        "id": 2282340,
        "name:xx": "Deer Mountain"
      }
    },
    {
      "geometry": {
        "type": "Point",
        "coordinates": [
          -82.25,
          35.8
        ]
      },
      "type": "Feature",
      "properties": {
        "hierarchy": [
          "tgn:2282341",
          "tgn:1000001",
          "tgn:7012149",
          "tgn:2001556",
          "tgn:7007709",
          "tgn:7029392"
        ],
        "placetype": [
          "aat:300008798"
        ],
        "id": 2282341,
        "name:xx": "Deer Mountain"
      }
    },
    {
      "geometry": {
        "type": "Point",
        "coordinates": [
          -122.65,
          43.9833
        ]
      },
      "type": "Feature",
      "properties": {
        "hierarchy": [
          "tgn:2282342",
          "tgn:1000001",
          "tgn:7012149",
          "tgn:2001716",
          "tgn:7007708",
          "tgn:7029392"
        ],
        "placetype": [
          "aat:300008798"
        ],
        "id": 2282342,
        "name:xx": "Deer Mountain"
      }
    },
    {
      "geometry": {
        "type": "Point",
        "coordinates": [
          -75.35,
          41.0833
        ]
      },
      "type": "Feature",
      "properties": {
        "hierarchy": [
          "tgn:2282343",
          "tgn:1000001",
          "tgn:7012149",
          "tgn:1002682",
          "tgn:7007710",
          "tgn:7029392"
        ],
        "placetype": [
          "aat:300008798"
        ],
        "id": 2282343,
        "name:xx": "Deer Mountain"
      }
    },
    {
      "geometry": {
        "type": "Point",
        "coordinates": [
          -103.8167,
          44.3
        ]
      },
      "type": "Feature",
      "properties": {
        "hierarchy": [
          "tgn:2282344",
          "tgn:1000001",
          "tgn:2001810",
          "tgn:7012149",
          "tgn:7007713",
          "tgn:7029392"
        ],
        "placetype": [
          "aat:300008798"
        ],
        "id": 2282344,
        "name:xx": "Deer Mountain"
      }
    },
    {
      "geometry": {
        "type": "Point",
        "coordinates": [
          -105.9167,
          31.8833
        ]
      },
      "type": "Feature",
      "properties": {
        "hierarchy": [
          "tgn:2282345",
          "tgn:1000001",
          "tgn:7012149",
          "tgn:2002005",
          "tgn:7007826",
          "tgn:7029392"
        ],
        "placetype": [
          "aat:300008798"
        ],
        "id": 2282345,
        "name:xx": "Deer Mountain"
      }
    },
    {
      "geometry": {
        "type": "Point",
        "coordinates": [
          -104.0167,
          30.6
        ]
      },
      "type": "Feature",
      "properties": {
        "hierarchy": [
          "tgn:2282346",
          "tgn:1000001",
          "tgn:7012149",
          "tgn:2002010",
          "tgn:7007826",
          "tgn:7029392"
        ],
        "placetype": [
          "aat:300008798"
        ],
        "id": 2282346,
        "name:xx": "Deer Mountain"
      }
    },
    {
      "geometry": {
        "type": "Point",
        "coordinates": [
          -98.85,
          30.85
        ]
      },
      "type": "Feature",
      "properties": {
        "hierarchy": [
          "tgn:2282347",
          "tgn:1000001",
          "tgn:7012149",
          "tgn:2002030",
          "tgn:7007826",
          "tgn:7029392"
        ],
        "placetype": [
          "aat:300008798"
        ],
        "id": 2282347,
        "name:xx": "Deer Mountain"
      }
    },
    {
      "geometry": {
        "type": "Point",
        "coordinates": [
          -112.2167,
          37.5
        ]
      },
      "type": "Feature",
      "properties": {
        "hierarchy": [
          "tgn:2282348",
          "tgn:1000001",
          "tgn:7012149",
          "tgn:2002113",
          "tgn:7007827",
          "tgn:7029392"
        ],
        "placetype": [
          "aat:300008798"
        ],
        "id": 2282348,
        "name:xx": "Deer Mountain"
      }
    },
    {
      "geometry": {
        "type": "Point",
        "coordinates": [
          -111.3833,
          37.9833
        ]
      },
      "type": "Feature",
      "properties": {
        "hierarchy": [
          "tgn:2282349",
          "tgn:1000001",
          "tgn:2002109",
          "tgn:7012149",
          "tgn:7007827",
          "tgn:7029392"
        ],
        "placetype": [
          "aat:300008798"
        ],
        "id": 2282349,
        "name:xx": "Deer Mountain"
      }
    }
  ]
}
