{
  "geometry": {
    "type": "Point",
    "coordinates": [
      -123.3167,
      44.9333
    ]
  },
  "type": "Feature",
  "properties": {
    "hierarchy": [
      "tgn:2267230",
      "tgn:1000001",
      "tgn:7012149",
      "tgn:1002794",
      "tgn:7007708",
      "tgn:7029392"
    ],
    "placetype": [
      "aat:300008680"
    ],
    "id": 2267230,
    "name:xx": "Crider Pond"
  }
}
