{
  "geometry": {
    "type": "Point",
    "coordinates": [
      -80.1167,
      40.6667
    ]
  },
  "type": "Feature",
  "properties": {
    "hierarchy": [
      "tgn:1132472",
      "tgn:1000001",
      "tgn:7012149",
      "tgn:7007710",
      "tgn:7029392"
    ],
    "placetype": [
      "aat:300008706"
    ],
    "id": 1132472,
    "name:xx": "Big Sewickley Creek"
  }
}
