{
  "geometry": {
    "type": "Point",
    "coordinates": [
      -122.1833,
      38.3333
    ]
  },
  "type": "Feature",
  "properties": {
    "hierarchy": [
      "tgn:2765654",
      "tgn:1000001",
      "tgn:7012149",
      "tgn:7007157",
      "tgn:1002706",
      "tgn:7029392"
    ],
    "placetype": [
      "aat:300008706"
    ],
    "id": 2765654,
    "name:xx": "White Creek"
  }
}
