{
  "geometry": {
    "type": "Point",
    "coordinates": [
      27.6667,
      56.75
    ]
  },
  "type": "Feature",
  "properties": {
    "hierarchy": [
      "tgn:1054821",
      "tgn:7012152",
      "tgn:1000003",
      "tgn:7006541",
      "tgn:7029392"
    ],
    "placetype": [
      "aat:300008347"
    ],
    "id": 1054821,
    "name:xx": "Kārsava"
  }
}
