{
  "geometry": {
    "type": "Point",
    "coordinates": [
      78.83,
      9.16
    ]
  },
  "type": "Feature",
  "properties": {
    "hierarchy": [
      "tgn:7546789",
      "tgn:1000004",
      "tgn:7000198",
      "tgn:7001797",
      "tgn:7029392"
    ],
    "placetype": [
      "aat:300008791"
    ],
    "name:en": "Appa Tīvu",
    "id": 7546789
  }
}
