{
  "geometry": {
    "type": "Point",
    "coordinates": [
      59.35,
      25.4667
    ]
  },
  "type": "Feature",
  "properties": {
    "hierarchy": [
      "tgn:1128955",
      "tgn:1000004",
      "tgn:7002176",
      "tgn:7000231",
      "tgn:7029392"
    ],
    "placetype": [
      "aat:300387091"
    ],
    "id": 1128955,
    "name:xx": "Rāpch"
  }
}
