{
  "geometry": {
    "type": "Point",
    "coordinates": [
      -112.3833,
      34.0167
    ]
  },
  "type": "Feature",
  "properties": {
    "hierarchy": [
      "tgn:2259367",
      "tgn:1000001",
      "tgn:7006451",
      "tgn:7012149",
      "tgn:2000103",
      "tgn:7029392"
    ],
    "placetype": [
      "aat:300008697"
    ],
    "id": 2259367,
    "name:xx": "Cottonwood Spring"
  }
}
