{
  "geometry": {
    "type": "Point",
    "coordinates": [
      -81.8667,
      34.4667
    ]
  },
  "type": "Feature",
  "properties": {
    "hierarchy": [
      "tgn:2657791",
      "tgn:1000001",
      "tgn:7012149",
      "tgn:2001754",
      "tgn:7007712",
      "tgn:7029392"
    ],
    "placetype": [
      "aat:300008706"
    ],
    "id": 2657791,
    "name:xx": "Shell Creek"
  }
}
