{
  "geometry": {
    "type": "Point",
    "coordinates": [
      -89.5167,
      43.1833
    ]
  },
  "type": "Feature",
  "properties": {
    "hierarchy": [
      "tgn:2754379",
      "tgn:1000001",
      "tgn:1002316",
      "tgn:7012149",
      "tgn:7007922",
      "tgn:7029392"
    ],
    "placetype": [
      "aat:300008905"
    ],
    "id": 2754379,
    "name:xx": "Waunakee Marsh"
  }
}
