{
  "geometry": {
    "type": "Point",
    "coordinates": [
      75.583333,
      25.416667
    ]
  },
  "type": "Feature",
  "properties": {
    "hierarchy": [
      "tgn:7548610",
      "tgn:1000004",
      "tgn:7000198",
      "tgn:7016788",
      "tgn:7029392"
    ],
    "placetype": [
      "aat:300008777"
    ],
    "name:en": "Būndi Hills",
    "id": 7548610
  }
}
