{
  "geometry": {
    "type": "Point",
    "coordinates": [
      -90.2833,
      35.05
    ]
  },
  "type": "Feature",
  "properties": {
    "hierarchy": [
      "tgn:2256257",
      "tgn:1000001",
      "tgn:7016172",
      "tgn:2000122",
      "tgn:7012149",
      "tgn:7029392"
    ],
    "placetype": [
      "aat:300008905"
    ],
    "id": 2256257,
    "name:xx": "Copperas Lake"
  }
}
