{
  "geometry": {
    "type": "Point",
    "coordinates": [
      -94.25,
      45.9333
    ]
  },
  "type": "Feature",
  "properties": {
    "hierarchy": [
      "tgn:2616557",
      "tgn:1000001",
      "tgn:7012149",
      "tgn:2001047",
      "tgn:7007521",
      "tgn:7029392"
    ],
    "placetype": [
      "aat:300006191"
    ],
    "id": 2616557,
    "name:xx": "Rice Lake"
  }
}
