{
  "type": "FeatureCollection",
  "features": [
    {
      "geometry": {
        "type": "Point",
        "coordinates": [
          -113.9333,
          45.6833
        ]
      },
      "type": "Feature",
      "properties": {
        "hierarchy": [
          "tgn:1108460",
          "tgn:1000001",
          "tgn:7012149",
          "tgn:7029392"
        ],
        "placetype": [
          "aat:300259572"
        ],
        "id": 1108460,
        "name:xx": "Lost Trail Pass"
      }
    },
    {
      "geometry": {
        "type": "Point",
        "coordinates": [
          13.2,
          47.5667
        ]
      },
      "type": "Feature",
      "properties": {
        "hierarchy": [
          "tgn:1108462",
          "tgn:7003027",
          "tgn:1000003",
          "tgn:1000062",
          "tgn:7029392"
        ],
        "placetype": [
          "aat:300259572"
        ],
        "id": 1108462,
        "name:xx": "Lueg, Pass"
      }
    },
    {
      "geometry": {
        "type": "Point",
        "coordinates": [
          -112.3,
          46.55
        ]
      },
      "type": "Feature",
      "properties": {
        "hierarchy": [
          "tgn:1108463",
          "tgn:1000001",
          "tgn:7012149",
          "tgn:7007524",
          "tgn:7029392"
        ],
        "placetype": [
          "aat:300259572"
        ],
        "id": 1108463,
        "name:xx": "MacDonald Pass"
      }
    },
    {
      "geometry": {
        "type": "Point",
        "coordinates": [
          117.6667,
          40.2
        ]
      },
      "type": "Feature",
      "properties": {
        "hierarchy": [
          "tgn:1108465",
          "tgn:1000004",
          "tgn:7002077",
          "tgn:1000111",
          "tgn:7029392"
        ],
        "placetype": [
          "aat:300259572"
        ],
        "id": 1108465,
        "name:xx": "Malanguan"
      }
    },
    {
      "geometry": {
        "type": "Point",
        "coordinates": [
          43.8,
          42.7167
        ]
      },
      "type": "Feature",
      "properties": {
        "hierarchy": [
          "tgn:1108467",
          "tgn:1000004",
          "tgn:7006653",
          "tgn:7029392"
        ],
        "placetype": [
          "aat:300259572"
        ],
        "id": 1108467,
        "name:xx": "Mamisonskiy Pereval"
      }
    },
    {
      "geometry": {
        "type": "Point",
        "coordinates": [
          -71.6333,
          -39.5667
        ]
      },
      "type": "Feature",
      "properties": {
        "hierarchy": [
          "tgn:1108468",
          "tgn:1000002",
          "tgn:7029392"
        ],
        "placetype": [
          "aat:300259572"
        ],
        "id": 1108468,
        "name:xx": "Mamuil Mamal, Paso"
      }
    },
    {
      "geometry": {
        "type": "Point",
        "coordinates": [
          11.916667,
          43.8
        ]
      },
      "type": "Feature",
      "properties": {
        "hierarchy": [
          "tgn:1108469",
          "tgn:7003162",
          "tgn:1000003",
          "tgn:7009760",
          "tgn:1000080",
          "tgn:7029392"
        ],
        "placetype": [
          "aat:300259572"
        ],
        "id": 1108469,
        "name:xx": "Mandrioli, Passo dei"
      }
    }
  ]
}
