{
  "geometry": {
    "type": "Point",
    "coordinates": [
      -76.0333,
      38.1167
    ]
  },
  "type": "Feature",
  "properties": {
    "hierarchy": [
      "tgn:2369471",
      "tgn:1000001",
      "tgn:1002902",
      "tgn:7012149",
      "tgn:7007516",
      "tgn:7029392"
    ],
    "placetype": [
      "aat:300008850"
    ],
    "id": 2369471,
    "name:xx": "Gunbarrel Point"
  }
}
