{
  "geometry": {
    "type": "Point",
    "coordinates": [
      -85.8167,
      46.6667
    ]
  },
  "type": "Feature",
  "properties": {
    "hierarchy": [
      "tgn:2607257",
      "tgn:1000001",
      "tgn:7012149",
      "tgn:2000972",
      "tgn:7007520",
      "tgn:7029392"
    ],
    "placetype": [
      "aat:300008680"
    ],
    "id": 2607257,
    "name:xx": "Randolph Lake"
  }
}
