{
  "geometry": {
    "type": "Point",
    "coordinates": [
      -113.5333,
      47.45
    ]
  },
  "type": "Feature",
  "properties": {
    "hierarchy": [
      "tgn:2644379",
      "tgn:1000001",
      "tgn:7012149",
      "tgn:2001291",
      "tgn:7007524",
      "tgn:7029392"
    ],
    "placetype": [
      "aat:300008680"
    ],
    "id": 2644379,
    "name:xx": "Sapphire Lake"
  }
}
