{
  "geometry": {
    "type": "Point",
    "coordinates": [
      -76.0167,
      38.0667
    ]
  },
  "type": "Feature",
  "properties": {
    "hierarchy": [
      "tgn:2762756",
      "tgn:1000001",
      "tgn:1002902",
      "tgn:7012149",
      "tgn:7007516",
      "tgn:7029392"
    ],
    "placetype": [
      "aat:300386853"
    ],
    "id": 2762756,
    "name:xx": "Western Islands"
  }
}
