{
  "geometry": {
    "type": "Point",
    "coordinates": [
      -83.7833,
      11.5167
    ]
  },
  "type": "Feature",
  "properties": {
    "hierarchy": [
      "tgn:1018704",
      "tgn:7593359",
      "tgn:1000001",
      "tgn:7005562",
      "tgn:7029392"
    ],
    "placetype": [
      "aat:300008347"
    ],
    "id": 1018704,
    "name:xx": "Punta Gorda"
  }
}
