{
  "geometry": {
    "type": "Point",
    "coordinates": [
      -87.75,
      37.0667
    ]
  },
  "type": "Feature",
  "properties": {
    "hierarchy": [
      "tgn:2312556",
      "tgn:1000001",
      "tgn:2000776",
      "tgn:7012149",
      "tgn:7007255",
      "tgn:7029392"
    ],
    "placetype": [
      "aat:300008699"
    ],
    "id": 2312556,
    "name:xx": "Eison Branch"
  }
}
