{
  "geometry": {
    "type": "Point",
    "coordinates": [
      -79.15,
      34.25
    ]
  },
  "type": "Feature",
  "properties": {
    "hierarchy": [
      "tgn:2605193",
      "tgn:1000001",
      "tgn:7012149",
      "tgn:2001758",
      "tgn:7007712",
      "tgn:7029392"
    ],
    "placetype": [
      "aat:300008905"
    ],
    "id": 2605193,
    "name:xx": "Raft Swamp"
  }
}
