{
  "geometry": {
    "type": "Point",
    "coordinates": [
      -79.95,
      44.1833
    ]
  },
  "type": "Feature",
  "properties": {
    "hierarchy": [
      "tgn:1014758",
      "tgn:7005685",
      "tgn:1000001",
      "tgn:7013154",
      "tgn:7029392"
    ],
    "placetype": [
      "aat:300008347"
    ],
    "id": 1014758,
    "name:xx": "Everett"
  }
}
