{
  "geometry": {
    "type": "Point",
    "coordinates": [
      -80.1667,
      39.8833
    ]
  },
  "type": "Feature",
  "properties": {
    "hierarchy": [
      "tgn:2094233",
      "tgn:1000001",
      "tgn:7012149",
      "tgn:2001724",
      "tgn:7007710",
      "tgn:7029392"
    ],
    "placetype": [
      "aat:300008347"
    ],
    "id": 2094233,
    "name:xx": "Waynesburg"
  }
}
