{
  "geometry": {
    "type": "Point",
    "coordinates": [
      81.39532,
      25.334389
    ]
  },
  "type": "Feature",
  "properties": {
    "hierarchy": [
      "tgn:7576295",
      "tgn:1000004",
      "tgn:7000198",
      "tgn:7016722",
      "tgn:7029392"
    ],
    "placetype": [
      "aat:300008347"
    ],
    "name:en": "Kosam Khirāj",
    "id": 7576295
  }
}
