{
  "geometry": {
    "type": "Point",
    "coordinates": [
      -83.2167,
      36.8167
    ]
  },
  "type": "Feature",
  "properties": {
    "hierarchy": [
      "tgn:2618817",
      "tgn:1000001",
      "tgn:7012149",
      "tgn:2000797",
      "tgn:7007255",
      "tgn:7029392"
    ],
    "placetype": [
      "aat:300008706"
    ],
    "id": 2618817,
    "name:xx": "Right Fork Turtle Creek"
  }
}
