{
  "geometry": {
    "type": "Point",
    "coordinates": [
      -84.4667,
      36.8333
    ]
  },
  "type": "Feature",
  "properties": {
    "hierarchy": [
      "tgn:2688321",
      "tgn:1000001",
      "tgn:7012149",
      "tgn:2000818",
      "tgn:7007255",
      "tgn:7029392"
    ],
    "placetype": [
      "aat:300008706"
    ],
    "id": 2688321,
    "name:xx": "Spruce Creek"
  }
}
