{
  "geometry": {
    "type": "Point",
    "coordinates": [
      -53.2667,
      48.0167
    ]
  },
  "type": "Feature",
  "properties": {
    "hierarchy": [
      "tgn:1014221",
      "tgn:7005685",
      "tgn:7005807",
      "tgn:1000001",
      "tgn:7005801",
      "tgn:7029392"
    ],
    "placetype": [
      "aat:300008347"
    ],
    "id": 1014221,
    "name:xx": "Hants Harbour"
  }
}
