{
  "geometry": {
    "type": "Point",
    "coordinates": [
      -99.1167,
      31.4833
    ]
  },
  "type": "Feature",
  "properties": {
    "hierarchy": [
      "tgn:2252661",
      "tgn:1000001",
      "tgn:7012149",
      "tgn:7007826",
      "tgn:7029392"
    ],
    "placetype": [
      "aat:300008699"
    ],
    "id": 2252661,
    "name:xx": "Conner Branch"
  }
}
