{
  "geometry": {
    "type": "Point",
    "coordinates": [
      -123.2667,
      44.1833
    ]
  },
  "type": "Feature",
  "properties": {
    "hierarchy": [
      "tgn:2450313",
      "tgn:1000001",
      "tgn:7012149",
      "tgn:2001716",
      "tgn:7007708",
      "tgn:7029392"
    ],
    "placetype": [
      "aat:300008699"
    ],
    "id": 2450313,
    "name:xx": "Lingo Slough"
  }
}
