{
  "geometry": {
    "type": "Point",
    "coordinates": [
      -95.6333,
      46.05
    ]
  },
  "type": "Feature",
  "properties": {
    "hierarchy": [
      "tgn:2695899",
      "tgn:1000001",
      "tgn:2001019",
      "tgn:7012149",
      "tgn:7007521",
      "tgn:7029392"
    ],
    "placetype": [
      "aat:300008680"
    ],
    "id": 2695899,
    "name:xx": "Stockhousen Lake"
  }
}
