{
  "type": "FeatureCollection",
  "features": [
    {
      "geometry": {
        "type": "Point",
        "coordinates": [
          -2.2333,
          53.4167
        ]
      },
      "type": "Feature",
      "properties": {
        "hierarchy": [
          "tgn:1100782",
          "tgn:7002445",
          "tgn:7010477",
          "tgn:7027477",
          "tgn:1000003",
          "tgn:7026570",
          "tgn:7008591",
          "tgn:7029392"
        ],
        "placetype": [
          "aat:300005768"
        ],
        "id": 1100782,
        "name:xx": "Fletcher Moss Museum"
      }
    },
    {
      "geometry": {
        "type": "Point",
        "coordinates": [
          -149.3833,
          -17.75
        ]
      },
      "type": "Feature",
      "properties": {
        "hierarchy": [
          "tgn:1100789",
          "tgn:7006218",
          "tgn:7006211",
          "tgn:1000216",
          "tgn:1000006",
          "tgn:7029392"
        ],
        "placetype": [
          "aat:300005768"
        ],
        "id": 1100789,
        "name:xx": "Gauguin, Musée"
      }
    }
  ]
}
