{
  "geometry": {
    "type": "Point",
    "coordinates": [
      -115.2333,
      42.4167
    ]
  },
  "type": "Feature",
  "properties": {
    "hierarchy": [
      "tgn:2399819",
      "tgn:1000001",
      "tgn:7012149",
      "tgn:2000488",
      "tgn:7007250",
      "tgn:7029392"
    ],
    "placetype": [
      "aat:300008798"
    ],
    "id": 2399819,
    "name:xx": "Horse Butte"
  }
}
