{
  "geometry": {
    "type": "Point",
    "coordinates": [
      -124.3667,
      43.3333
    ]
  },
  "type": "Feature",
  "properties": {
    "hierarchy": [
      "tgn:2365759",
      "tgn:1000001",
      "tgn:2001702",
      "tgn:7012149",
      "tgn:7007708",
      "tgn:7029392"
    ],
    "placetype": [
      "aat:300008850"
    ],
    "id": 2365759,
    "name:xx": "Gregory Point"
  }
}
