{
  "geometry": {
    "type": "Point",
    "coordinates": [
      -106.1167,
      40.8333
    ]
  },
  "type": "Feature",
  "properties": {
    "hierarchy": [
      "tgn:2658747",
      "tgn:1000001",
      "tgn:7012149",
      "tgn:2000220",
      "tgn:7007158",
      "tgn:7029392"
    ],
    "placetype": [
      "aat:300008706"
    ],
    "id": 2658747,
    "name:xx": "Sherman Creek"
  }
}
