{
  "geometry": {
    "type": "Point",
    "coordinates": [
      10.85,
      53.85
    ]
  },
  "type": "Feature",
  "properties": {
    "hierarchy": [
      "tgn:7143475",
      "tgn:1000003",
      "tgn:7000094",
      "tgn:7000084",
      "tgn:7029392"
    ],
    "placetype": [
      "aat:300008347"
    ],
    "id": 7143475,
    "name:xx": "Lockwisch-Dorf"
  }
}
