{
  "geometry": {
    "type": "Point",
    "coordinates": [
      121.8833,
      41.8667
    ]
  },
  "type": "Feature",
  "properties": {
    "hierarchy": [
      "tgn:1068417",
      "tgn:1000004",
      "tgn:1001390",
      "tgn:1000111",
      "tgn:7029392"
    ],
    "placetype": [
      "aat:300008347"
    ],
    "id": 1068417,
    "name:xx": "Guanyingzicun"
  }
}
