{
  "geometry": {
    "type": "Point",
    "coordinates": [
      -109.1167,
      33.7833
    ]
  },
  "type": "Feature",
  "properties": {
    "hierarchy": [
      "tgn:2598820",
      "tgn:2000090",
      "tgn:1000001",
      "tgn:7006451",
      "tgn:7012149",
      "tgn:7029392"
    ],
    "placetype": [
      "aat:300006191"
    ],
    "id": 2598820,
    "name:xx": "Prime Canyon Tank"
  }
}
