{
  "geometry": {
    "type": "Point",
    "coordinates": [
      5.95,
      52.866667
    ]
  },
  "type": "Feature",
  "properties": {
    "hierarchy": [
      "tgn:7267124",
      "tgn:7003616",
      "tgn:1000003",
      "tgn:7016845",
      "tgn:7029392"
    ],
    "placetype": [
      "aat:300008347"
    ],
    "name:nl": "Oldetrijne",
    "id": 7267124
  }
}
