{
  "geometry": {
    "type": "Point",
    "coordinates": [
      -68.2167,
      47.15
    ]
  },
  "type": "Feature",
  "properties": {
    "hierarchy": [
      "tgn:2137339",
      "tgn:2000919",
      "tgn:1000001",
      "tgn:7012149",
      "tgn:7007515",
      "tgn:7029392"
    ],
    "placetype": [
      "aat:300008699"
    ],
    "id": 2137339,
    "name:xx": "Armstrong Brook"
  }
}
