{
  "type": "FeatureCollection",
  "features": [
    {
      "geometry": {
        "type": "Point",
        "coordinates": [
          -80.2333,
          40.65
        ]
      },
      "type": "Feature",
      "properties": {
        "hierarchy": [
          "tgn:2393790",
          "tgn:1002171",
          "tgn:1000001",
          "tgn:7012149",
          "tgn:7007710",
          "tgn:7029392"
        ],
        "placetype": [
          "aat:300008791"
        ],
        "id": 2393790,
        "name:xx": "Hog Island"
      }
    },
    {
      "geometry": {
        "type": "Point",
        "coordinates": [
          -71.2667,
          41.6333
        ]
      },
      "type": "Feature",
      "properties": {
        "hierarchy": [
          "tgn:2393791",
          "tgn:1002716",
          "tgn:1000001",
          "tgn:7012149",
          "tgn:7007711",
          "tgn:7029392"
        ],
        "placetype": [
          "aat:300008791"
        ],
        "id": 2393791,
        "name:xx": "Hog Island"
      }
    },
    {
      "geometry": {
        "type": "Point",
        "coordinates": [
          -78.5833,
          33.8333
        ]
      },
      "type": "Feature",
      "properties": {
        "hierarchy": [
          "tgn:2393792",
          "tgn:1000001",
          "tgn:7012149",
          "tgn:2001750",
          "tgn:7007712",
          "tgn:7029392"
        ],
        "placetype": [
          "aat:300008850"
        ],
        "id": 2393792,
        "name:xx": "Hog Island"
      }
    },
    {
      "geometry": {
        "type": "Point",
        "coordinates": [
          -80.7667,
          32.2167
        ]
      },
      "type": "Feature",
      "properties": {
        "hierarchy": [
          "tgn:2393793",
          "tgn:2001731",
          "tgn:1000001",
          "tgn:7012149",
          "tgn:7007712",
          "tgn:7029392"
        ],
        "placetype": [
          "aat:300008791"
        ],
        "id": 2393793,
        "name:xx": "Hog Island"
      }
    },
    {
      "geometry": {
        "type": "Point",
        "coordinates": [
          -79.9,
          32.7833
        ]
      },
      "type": "Feature",
      "properties": {
        "hierarchy": [
          "tgn:2393794",
          "tgn:1000001",
          "tgn:2001734",
          "tgn:7012149",
          "tgn:7007712",
          "tgn:7029392"
        ],
        "placetype": [
          "aat:300008791"
        ],
        "id": 2393794,
        "name:xx": "Hog Island"
      }
    },
    {
      "geometry": {
        "type": "Point",
        "coordinates": [
          -80.9667,
          32.1
        ]
      },
      "type": "Feature",
      "properties": {
        "hierarchy": [
          "tgn:2393795",
          "tgn:1000001",
          "tgn:7012149",
          "tgn:2001751",
          "tgn:7007712",
          "tgn:7029392"
        ],
        "placetype": [
          "aat:300008791"
        ],
        "id": 2393795,
        "name:xx": "Hog Island"
      }
    },
    {
      "geometry": {
        "type": "Point",
        "coordinates": [
          -97.1,
          27.8833
        ]
      },
      "type": "Feature",
      "properties": {
        "hierarchy": [
          "tgn:2393796",
          "tgn:1000001",
          "tgn:7012149",
          "tgn:2002049",
          "tgn:7007826",
          "tgn:7029392"
        ],
        "placetype": [
          "aat:300008791"
        ],
        "id": 2393796,
        "name:xx": "Hog Island"
      }
    },
    {
      "geometry": {
        "type": "Point",
        "coordinates": [
          -95.0667,
          29.7667
        ]
      },
      "type": "Feature",
      "properties": {
        "hierarchy": [
          "tgn:2393797",
          "tgn:1000001",
          "tgn:7012149",
          "tgn:1002456",
          "tgn:7007826",
          "tgn:7029392"
        ],
        "placetype": [
          "aat:300008791"
        ],
        "id": 2393797,
        "name:xx": "Hog Island"
      }
    },
    {
      "geometry": {
        "type": "Point",
        "coordinates": [
          -94.1,
          29.8
        ]
      },
      "type": "Feature",
      "properties": {
        "hierarchy": [
          "tgn:2393798",
          "tgn:1000001",
          "tgn:7012149",
          "tgn:2002011",
          "tgn:7007826",
          "tgn:7029392"
        ],
        "placetype": [
          "aat:300008791"
        ],
        "id": 2393798,
        "name:xx": "Hog Island"
      }
    },
    {
      "geometry": {
        "type": "Point",
        "coordinates": [
          -95.8667,
          28.65
        ]
      },
      "type": "Feature",
      "properties": {
        "hierarchy": [
          "tgn:2393799",
          "tgn:1000001",
          "tgn:7012149",
          "tgn:1002646",
          "tgn:7007826",
          "tgn:7029392"
        ],
        "placetype": [
          "aat:300008791"
        ],
        "id": 2393799,
        "name:xx": "Hog Island"
      }
    }
  ]
}
