{
  "geometry": {
    "type": "Point",
    "coordinates": [
      -91.5667,
      45.9333
    ]
  },
  "type": "Feature",
  "properties": {
    "hierarchy": [
      "tgn:2153406",
      "tgn:1000001",
      "tgn:7012149",
      "tgn:2002360",
      "tgn:7007922",
      "tgn:7029392"
    ],
    "placetype": [
      "aat:300008680"
    ],
    "id": 2153406,
    "name:xx": "Bean Lake"
  }
}
