{
  "geometry": {
    "type": "Point",
    "coordinates": [
      -82.05,
      26.4667
    ]
  },
  "type": "Feature",
  "properties": {
    "hierarchy": [
      "tgn:2781627",
      "tgn:1000001",
      "tgn:7012149",
      "tgn:1002582",
      "tgn:7007240",
      "tgn:7029392"
    ],
    "placetype": [
      "aat:300008850"
    ],
    "id": 2781627,
    "name:xx": "Woodrings Point"
  }
}
