{
  "geometry": {
    "type": "Point",
    "coordinates": [
      -85.2667,
      44.55
    ]
  },
  "type": "Feature",
  "properties": {
    "hierarchy": [
      "tgn:2180643",
      "tgn:1000001",
      "tgn:7012149",
      "tgn:2000968",
      "tgn:7007520",
      "tgn:7029392"
    ],
    "placetype": [
      "aat:300008680"
    ],
    "id": 2180643,
    "name:xx": "Bloom Lake"
  }
}
