{
  "geometry": {
    "type": "Point",
    "coordinates": [
      115.5667,
      40.7833
    ]
  },
  "type": "Feature",
  "properties": {
    "hierarchy": [
      "tgn:1070063",
      "tgn:1000004",
      "tgn:7002077",
      "tgn:1000111",
      "tgn:7029392"
    ],
    "placetype": [
      "aat:300008347"
    ],
    "id": 1070063,
    "name:xx": "Longguan"
  }
}
