{
  "type": "FeatureCollection",
  "features": [
    {
      "geometry": {
        "type": "Point",
        "coordinates": [
          120.7833,
          6.4333
        ]
      },
      "type": "Feature",
      "properties": {
        "hierarchy": [
          "tgn:1009520",
          "tgn:1010207",
          "tgn:1000004",
          "tgn:1001552",
          "tgn:1000135",
          "tgn:7029392"
        ],
        "placetype": [
          "aat:300008791"
        ],
        "id": 1009520,
        "name:xx": "Tubigan Island"
      }
    },
    {
      "geometry": {
        "type": "Point",
        "coordinates": [
          -70.25,
          41.3
        ]
      },
      "type": "Feature",
      "properties": {
        "hierarchy": [
          "tgn:1009521",
          "tgn:1000001",
          "tgn:1002705",
          "tgn:7012149",
          "tgn:7007517",
          "tgn:7029392"
        ],
        "placetype": [
          "aat:300008791"
        ],
        "id": 1009521,
        "name:xx": "Tuckernuck Island"
      }
    },
    {
      "geometry": {
        "type": "Point",
        "coordinates": [
          -154.6167,
          56.5
        ]
      },
      "type": "Feature",
      "properties": {
        "hierarchy": [
          "tgn:1009522",
          "tgn:7006450",
          "tgn:1000001",
          "tgn:2124012",
          "tgn:7012149",
          "tgn:7019714",
          "tgn:7029392"
        ],
        "placetype": [
          "aat:300008791"
        ],
        "id": 1009522,
        "name:xx": "Tugidak Island"
      }
    },
    {
      "geometry": {
        "type": "Point",
        "coordinates": [
          119.2833,
          10.9833
        ]
      },
      "type": "Feature",
      "properties": {
        "hierarchy": [
          "tgn:1009523",
          "tgn:1000004",
          "tgn:1001481",
          "tgn:1000135",
          "tgn:7029392"
        ],
        "placetype": [
          "aat:300008791"
        ],
        "id": 1009523,
        "name:xx": "Tuluran Island"
      }
    },
    {
      "geometry": {
        "type": "Point",
        "coordinates": [
          119.975,
          25.959444
        ]
      },
      "type": "Feature",
      "properties": {
        "hierarchy": [
          "tgn:1009527",
          "tgn:7498210",
          "tgn:1000004",
          "tgn:1000141",
          "tgn:7029392"
        ],
        "placetype": [
          "aat:300008791"
        ],
        "id": 1009527,
        "name:xx": "Dongquan Dao"
      }
    },
    {
      "geometry": {
        "type": "Point",
        "coordinates": [
          119.6725,
          23.255833
        ]
      },
      "type": "Feature",
      "properties": {
        "hierarchy": [
          "tgn:1009528",
          "tgn:1000004",
          "tgn:7004300",
          "tgn:1000141",
          "tgn:7029392"
        ],
        "placetype": [
          "aat:300008791"
        ],
        "id": 1009528,
        "name:xx": "Tung-chi Yü"
      }
    }
  ]
}
