{
  "type": "FeatureCollection",
  "features": [
    {
      "geometry": {
        "type": "Point",
        "coordinates": [
          -106.8667,
          38.1167
        ]
      },
      "type": "Feature",
      "properties": {
        "hierarchy": [
          "tgn:2205400",
          "tgn:1000001",
          "tgn:7012149",
          "tgn:7007158",
          "tgn:2000246",
          "tgn:7029392"
        ],
        "placetype": [
          "aat:300008706"
        ],
        "id": 2205400,
        "name:xx": "Bull Creek"
      }
    },
    {
      "geometry": {
        "type": "Point",
        "coordinates": [
          -81.4167,
          29.4333
        ]
      },
      "type": "Feature",
      "properties": {
        "hierarchy": [
          "tgn:2205401",
          "tgn:1000001",
          "tgn:2000266",
          "tgn:7012149",
          "tgn:7007240",
          "tgn:7029392"
        ],
        "placetype": [
          "aat:300008706"
        ],
        "id": 2205401,
        "name:xx": "Bull Creek"
      }
    },
    {
      "geometry": {
        "type": "Point",
        "coordinates": [
          -86.4333,
          30.6333
        ]
      },
      "type": "Feature",
      "properties": {
        "hierarchy": [
          "tgn:2205402",
          "tgn:1000001",
          "tgn:7012149",
          "tgn:2000281",
          "tgn:7007240",
          "tgn:7029392"
        ],
        "placetype": [
          "aat:300008706"
        ],
        "id": 2205402,
        "name:xx": "Bull Creek"
      }
    },
    {
      "geometry": {
        "type": "Point",
        "coordinates": [
          -83.1,
          29.2833
        ]
      },
      "type": "Feature",
      "properties": {
        "hierarchy": [
          "tgn:2205403",
          "tgn:1000001",
          "tgn:7012149",
          "tgn:2000277",
          "tgn:7007240",
          "tgn:7029392"
        ],
        "placetype": [
          "aat:300008706"
        ],
        "id": 2205403,
        "name:xx": "Bull Creek"
      }
    },
    {
      "geometry": {
        "type": "Point",
        "coordinates": [
          -81.9333,
          29.95
        ]
      },
      "type": "Feature",
      "properties": {
        "hierarchy": [
          "tgn:2205404",
          "tgn:1000001",
          "tgn:2000261",
          "tgn:7012149",
          "tgn:7007240",
          "tgn:7029392"
        ],
        "placetype": [
          "aat:300008706"
        ],
        "id": 2205404,
        "name:xx": "Bull Creek"
      }
    },
    {
      "geometry": {
        "type": "Point",
        "coordinates": [
          -84.7,
          30.4
        ]
      },
      "type": "Feature",
      "properties": {
        "hierarchy": [
          "tgn:2205405",
          "tgn:1000001",
          "tgn:7012149",
          "tgn:2000278",
          "tgn:7007240",
          "tgn:7029392"
        ],
        "placetype": [
          "aat:300008706"
        ],
        "id": 2205405,
        "name:xx": "Bull Creek"
      }
    },
    {
      "geometry": {
        "type": "Point",
        "coordinates": [
          -81.1333,
          28.05
        ]
      },
      "type": "Feature",
      "properties": {
        "hierarchy": [
          "tgn:2205406",
          "tgn:1000001",
          "tgn:7012149",
          "tgn:1002756",
          "tgn:7007240",
          "tgn:7029392"
        ],
        "placetype": [
          "aat:300008706"
        ],
        "id": 2205406,
        "name:xx": "Bull Creek"
      }
    },
    {
      "geometry": {
        "type": "Point",
        "coordinates": [
          -81.1333,
          28.05
        ]
      },
      "type": "Feature",
      "properties": {
        "hierarchy": [
          "tgn:2205407",
          "tgn:1000001",
          "tgn:7012149",
          "tgn:1002756",
          "tgn:7007240",
          "tgn:7029392"
        ],
        "placetype": [
          "aat:300008680"
        ],
        "id": 2205407,
        "name:xx": "Bull Creek"
      }
    },
    {
      "geometry": {
        "type": "Point",
        "coordinates": [
          -83.8167,
          31.3833
        ]
      },
      "type": "Feature",
      "properties": {
        "hierarchy": [
          "tgn:2205408",
          "tgn:1000001",
          "tgn:7012149",
          "tgn:2000450",
          "tgn:7007248",
          "tgn:7029392"
        ],
        "placetype": [
          "aat:300008706"
        ],
        "id": 2205408,
        "name:xx": "Bull Creek"
      }
    },
    {
      "geometry": {
        "type": "Point",
        "coordinates": [
          -84.3833,
          33.0167
        ]
      },
      "type": "Feature",
      "properties": {
        "hierarchy": [
          "tgn:2205409",
          "tgn:1000001",
          "tgn:7012149",
          "tgn:2000405",
          "tgn:7007248",
          "tgn:7029392"
        ],
        "placetype": [
          "aat:300008706"
        ],
        "id": 2205409,
        "name:xx": "Bull Creek"
      }
    }
  ]
}
