{
  "type": "FeatureCollection",
  "features": [
    {
      "geometry": {
        "type": "Point",
        "coordinates": [
          -91.95,
          17
        ]
      },
      "type": "Feature",
      "properties": {
        "hierarchy": [
          "tgn:7435890",
          "tgn:7005580",
          "tgn:1000001",
          "tgn:7005560",
          "tgn:7029392"
        ],
        "placetype": [
          "aat:300008347"
        ],
        "id": 7435890,
        "name:xx": "San Vicente"
      }
    },
    {
      "geometry": {
        "type": "Point",
        "coordinates": [
          -93.25,
          16.666667
        ]
      },
      "type": "Feature",
      "properties": {
        "hierarchy": [
          "tgn:7435891",
          "tgn:7005580",
          "tgn:1000001",
          "tgn:7005560",
          "tgn:7029392"
        ],
        "placetype": [
          "aat:300008347"
        ],
        "id": 7435891,
        "name:xx": "San Vicente"
      }
    },
    {
      "geometry": {
        "type": "Point",
        "coordinates": [
          -93.666667,
          16.45
        ]
      },
      "type": "Feature",
      "properties": {
        "hierarchy": [
          "tgn:7435892",
          "tgn:7005580",
          "tgn:1000001",
          "tgn:7005560",
          "tgn:7029392"
        ],
        "placetype": [
          "aat:300008347"
        ],
        "id": 7435892,
        "name:xx": "San Vicente"
      }
    },
    {
      "geometry": {
        "type": "Point",
        "coordinates": [
          -96.783333,
          16.216667
        ]
      },
      "type": "Feature",
      "properties": {
        "hierarchy": [
          "tgn:7435893",
          "tgn:1000001",
          "tgn:7005591",
          "tgn:7005560",
          "tgn:7029392"
        ],
        "placetype": [
          "aat:300008347"
        ],
        "id": 7435893,
        "name:xx": "San Vicente"
      }
    },
    {
      "geometry": {
        "type": "Point",
        "coordinates": [
          -93.383333,
          16.183333
        ]
      },
      "type": "Feature",
      "properties": {
        "hierarchy": [
          "tgn:7435894",
          "tgn:7005580",
          "tgn:1000001",
          "tgn:7005560",
          "tgn:7029392"
        ],
        "placetype": [
          "aat:300008347"
        ],
        "id": 7435894,
        "name:xx": "San Vicente"
      }
    },
    {
      "geometry": {
        "type": "Point",
        "coordinates": [
          -96.6,
          16.066667
        ]
      },
      "type": "Feature",
      "properties": {
        "hierarchy": [
          "tgn:7435895",
          "tgn:1000001",
          "tgn:7005591",
          "tgn:7005560",
          "tgn:7029392"
        ],
        "placetype": [
          "aat:300008347"
        ],
        "id": 7435895,
        "name:xx": "San Vicente"
      }
    },
    {
      "geometry": {
        "type": "Point",
        "coordinates": [
          -91.816667,
          16
        ]
      },
      "type": "Feature",
      "properties": {
        "hierarchy": [
          "tgn:7435896",
          "tgn:7005580",
          "tgn:1000001",
          "tgn:7005560",
          "tgn:7029392"
        ],
        "placetype": [
          "aat:300008347"
        ],
        "id": 7435896,
        "name:xx": "San Vicente"
      }
    },
    {
      "geometry": {
        "type": "Point",
        "coordinates": [
          -93.033333,
          15.366667
        ]
      },
      "type": "Feature",
      "properties": {
        "hierarchy": [
          "tgn:7435897",
          "tgn:7005580",
          "tgn:1000001",
          "tgn:7005560",
          "tgn:7029392"
        ],
        "placetype": [
          "aat:300008347"
        ],
        "id": 7435897,
        "name:xx": "San Vicente"
      }
    },
    {
      "geometry": {
        "type": "Point",
        "coordinates": [
          -92.283333,
          14.816667
        ]
      },
      "type": "Feature",
      "properties": {
        "hierarchy": [
          "tgn:7435898",
          "tgn:7005580",
          "tgn:1000001",
          "tgn:7005560",
          "tgn:7029392"
        ],
        "placetype": [
          "aat:300008347"
        ],
        "id": 7435898,
        "name:xx": "San Vicente"
      }
    },
    {
      "geometry": {
        "type": "Point",
        "coordinates": [
          -90.116667,
          20.816667
        ]
      },
      "type": "Feature",
      "properties": {
        "hierarchy": [
          "tgn:7435899",
          "tgn:1000001",
          "tgn:7005600",
          "tgn:7005560",
          "tgn:7029392"
        ],
        "placetype": [
          "aat:300387007"
        ],
        "id": 7435899,
        "name:xx": "San Vicente"
      }
    }
  ]
}
