{
  "geometry": {
    "type": "Point",
    "coordinates": [
      6.915,
      43.45
    ]
  },
  "type": "Feature",
  "properties": {
    "hierarchy": [
      "tgn:7032187",
      "tgn:1000003",
      "tgn:1000070",
      "tgn:7002895",
      "tgn:7029392"
    ],
    "placetype": [
      "aat:300132317"
    ],
    "id": 7032187,
    "name:xx": "Saint-Barthélemy, Calanques de"
  }
}
