{
  "geometry": {
    "type": "Point",
    "coordinates": [
      -76.7167,
      37.9833
    ]
  },
  "type": "Feature",
  "properties": {
    "hierarchy": [
      "tgn:2192558",
      "tgn:1000001",
      "tgn:7012149",
      "tgn:7014334",
      "tgn:7007919",
      "tgn:7029392"
    ],
    "placetype": [
      "aat:300008905"
    ],
    "id": 2192558,
    "name:xx": "Branham Mill Swamp"
  }
}
