{
  "geometry": {
    "type": "Point",
    "coordinates": [
      -91.7167,
      39.9833
    ]
  },
  "type": "Feature",
  "properties": {
    "hierarchy": [
      "tgn:2440287",
      "tgn:1000001",
      "tgn:7012149",
      "tgn:1002592",
      "tgn:7007523",
      "tgn:7029392"
    ],
    "placetype": [
      "aat:300006191"
    ],
    "id": 2440287,
    "name:xx": "Klocke Lake"
  }
}
