{
  "type": "FeatureCollection",
  "features": [
    {
      "geometry": {
        "type": "Point",
        "coordinates": [
          133.25,
          36.3333
        ]
      },
      "type": "Feature",
      "properties": {
        "hierarchy": [
          "tgn:1006900",
          "tgn:7016808",
          "tgn:7000897",
          "tgn:1000004",
          "tgn:1010194",
          "tgn:1000120",
          "tgn:7029392"
        ],
        "placetype": [
          "aat:300008791"
        ],
        "id": 1006900,
        "name:xx": "Dōgo"
      }
    },
    {
      "geometry": {
        "type": "Point",
        "coordinates": [
          122.6,
          39.2667
        ]
      },
      "type": "Feature",
      "properties": {
        "hierarchy": [
          "tgn:1006901",
          "tgn:1000004",
          "tgn:1001390",
          "tgn:1000111",
          "tgn:7029392"
        ],
        "placetype": [
          "aat:300008791"
        ],
        "id": 1006901,
        "name:xx": "Dachangshan Dao"
      }
    },
    {
      "geometry": {
        "type": "Point",
        "coordinates": [
          121.9,
          30.3333
        ]
      },
      "type": "Feature",
      "properties": {
        "hierarchy": [
          "tgn:1006902",
          "tgn:1000004",
          "tgn:7002076",
          "tgn:1000111",
          "tgn:7029392"
        ],
        "placetype": [
          "aat:300008791"
        ],
        "id": 1006902,
        "name:xx": "Dazhi Shan"
      }
    },
    {
      "geometry": {
        "type": "Point",
        "coordinates": [
          113.5,
          22.1
        ]
      },
      "type": "Feature",
      "properties": {
        "hierarchy": [
          "tgn:1006903",
          "tgn:1000004",
          "tgn:7005232",
          "tgn:1000111",
          "tgn:7029392"
        ],
        "placetype": [
          "aat:300008791"
        ],
        "id": 1006903,
        "name:xx": "Dahenqin Dao"
      }
    },
    {
      "geometry": {
        "type": "Point",
        "coordinates": [
          160.6167,
          -7.95
        ]
      },
      "type": "Feature",
      "properties": {
        "hierarchy": [
          "tgn:1006905",
          "tgn:1001407",
          "tgn:1000233",
          "tgn:1000006",
          "tgn:7029392"
        ],
        "placetype": [
          "aat:300008791"
        ],
        "id": 1006905,
        "name:xx": "Dai"
      }
    },
    {
      "geometry": {
        "type": "Point",
        "coordinates": [
          88.743153,
          21.626534
        ]
      },
      "type": "Feature",
      "properties": {
        "hierarchy": [
          "tgn:1006907",
          "tgn:1000004",
          "tgn:7000198",
          "tgn:1001977",
          "tgn:7029392"
        ],
        "placetype": [
          "aat:300008791"
        ],
        "name:en": "Dalhousie Island",
        "id": 1006907
      }
    },
    {
      "geometry": {
        "type": "Point",
        "coordinates": [
          119.6833,
          25.65
        ]
      },
      "type": "Feature",
      "properties": {
        "hierarchy": [
          "tgn:1006908",
          "tgn:1000004",
          "tgn:7001796",
          "tgn:1000111",
          "tgn:7029392"
        ],
        "placetype": [
          "aat:300008791"
        ],
        "id": 1006908,
        "name:xx": "Dalian Dao"
      }
    }
  ]
}
