{
  "type": "FeatureCollection",
  "features": [
    {
      "geometry": {
        "type": "Point",
        "coordinates": [
          -122.7333,
          39.5667
        ]
      },
      "type": "Feature",
      "properties": {
        "hierarchy": [
          "tgn:2582980",
          "tgn:1000001",
          "tgn:7012149",
          "tgn:7007157",
          "tgn:1002566",
          "tgn:7029392"
        ],
        "placetype": [
          "aat:300008798"
        ],
        "id": 2582980,
        "name:xx": "Pine Kop"
      }
    },
    {
      "geometry": {
        "type": "Point",
        "coordinates": [
          -86.5333,
          34.3333
        ]
      },
      "type": "Feature",
      "properties": {
        "hierarchy": [
          "tgn:2582981",
          "tgn:7002659",
          "tgn:1000001",
          "tgn:7012149",
          "tgn:2000047",
          "tgn:7029392"
        ],
        "placetype": [
          "aat:300006191"
        ],
        "id": 2582981,
        "name:xx": "Pine Lake"
      }
    },
    {
      "geometry": {
        "type": "Point",
        "coordinates": [
          -85.3167,
          31.15
        ]
      },
      "type": "Feature",
      "properties": {
        "hierarchy": [
          "tgn:2582982",
          "tgn:7002659",
          "tgn:1000001",
          "tgn:7012149",
          "tgn:2000034",
          "tgn:7029392"
        ],
        "placetype": [
          "aat:300006191"
        ],
        "id": 2582982,
        "name:xx": "Pine Lake"
      }
    },
    {
      "geometry": {
        "type": "Point",
        "coordinates": [
          -85.8333,
          31.8167
        ]
      },
      "type": "Feature",
      "properties": {
        "hierarchy": [
          "tgn:2582983",
          "tgn:7002659",
          "tgn:1000001",
          "tgn:7012149",
          "tgn:2000054",
          "tgn:7029392"
        ],
        "placetype": [
          "aat:300006191"
        ],
        "id": 2582983,
        "name:xx": "Pine Lake"
      }
    },
    {
      "geometry": {
        "type": "Point",
        "coordinates": [
          -87.7333,
          33.4333
        ]
      },
      "type": "Feature",
      "properties": {
        "hierarchy": [
          "tgn:2582984",
          "tgn:7002659",
          "tgn:1000001",
          "tgn:7012149",
          "tgn:2000062",
          "tgn:7029392"
        ],
        "placetype": [
          "aat:300006191"
        ],
        "id": 2582984,
        "name:xx": "Pine Lake"
      }
    },
    {
      "geometry": {
        "type": "Point",
        "coordinates": [
          -131.5667,
          55.9
        ]
      },
      "type": "Feature",
      "properties": {
        "hierarchy": [
          "tgn:2582985",
          "tgn:7006450",
          "tgn:1000001",
          "tgn:2124076",
          "tgn:7012149",
          "tgn:7029392"
        ],
        "placetype": [
          "aat:300008680"
        ],
        "id": 2582985,
        "name:xx": "Pine Lake"
      }
    },
    {
      "geometry": {
        "type": "Point",
        "coordinates": [
          -134.1833,
          57.65
        ]
      },
      "type": "Feature",
      "properties": {
        "hierarchy": [
          "tgn:2582986",
          "tgn:7006450",
          "tgn:1000001",
          "tgn:7012149",
          "tgn:7019760",
          "tgn:7029392"
        ],
        "placetype": [
          "aat:300008680"
        ],
        "id": 2582986,
        "name:xx": "Pine Lake"
      }
    },
    {
      "geometry": {
        "type": "Point",
        "coordinates": [
          -109.7667,
          34.3833
        ]
      },
      "type": "Feature",
      "properties": {
        "hierarchy": [
          "tgn:2582987",
          "tgn:2000090",
          "tgn:1000001",
          "tgn:7006451",
          "tgn:7012149",
          "tgn:7029392"
        ],
        "placetype": [
          "aat:300008680"
        ],
        "id": 2582987,
        "name:xx": "Pine Lake"
      }
    },
    {
      "geometry": {
        "type": "Point",
        "coordinates": [
          -111.3667,
          34.9167
        ]
      },
      "type": "Feature",
      "properties": {
        "hierarchy": [
          "tgn:2582988",
          "tgn:1000001",
          "tgn:7006451",
          "tgn:2000092",
          "tgn:7012149",
          "tgn:7029392"
        ],
        "placetype": [
          "aat:300008680"
        ],
        "id": 2582988,
        "name:xx": "Pine Lake"
      }
    },
    {
      "geometry": {
        "type": "Point",
        "coordinates": [
          -109.9167,
          34.1
        ]
      },
      "type": "Feature",
      "properties": {
        "hierarchy": [
          "tgn:2582989",
          "tgn:1000001",
          "tgn:7006451",
          "tgn:7012149",
          "tgn:2000099",
          "tgn:7029392"
        ],
        "placetype": [
          "aat:300006191"
        ],
        "id": 2582989,
        "name:xx": "Pine Lake"
      }
    }
  ]
}
