{
  "geometry": {
    "type": "Point",
    "coordinates": [
      -74.7833,
      39.15
    ]
  },
  "type": "Feature",
  "properties": {
    "hierarchy": [
      "tgn:2722058",
      "tgn:1002232",
      "tgn:1000001",
      "tgn:7012149",
      "tgn:7007565",
      "tgn:7029392"
    ],
    "placetype": [
      "aat:300008905"
    ],
    "id": 2722058,
    "name:xx": "Timber and Beaver Swamp"
  }
}
