{
  "geometry": {
    "type": "Point",
    "coordinates": [
      -111.9667,
      45.2333
    ]
  },
  "type": "Feature",
  "properties": {
    "hierarchy": [
      "tgn:7020565",
      "tgn:1000001",
      "tgn:7012149",
      "tgn:2001288",
      "tgn:7007524",
      "tgn:7029392"
    ],
    "placetype": [
      "aat:300000390"
    ],
    "id": 7020565,
    "name:xx": "Easton-Pacific Mine"
  }
}
