{
  "geometry": {
    "type": "Point",
    "coordinates": [
      -117.7333,
      45.9833
    ]
  },
  "type": "Feature",
  "properties": {
    "hierarchy": [
      "tgn:2366941",
      "tgn:1000001",
      "tgn:7012149",
      "tgn:7029392"
    ],
    "placetype": [
      "aat:300266640"
    ],
    "id": 2366941,
    "name:xx": "Grizzly Bear Ridge"
  }
}
