{
  "geometry": {
    "type": "Point",
    "coordinates": [
      -90.35,
      42.6333
    ]
  },
  "type": "Feature",
  "properties": {
    "hierarchy": [
      "tgn:2539056",
      "tgn:1000001",
      "tgn:7012149",
      "tgn:2002332",
      "tgn:7007922",
      "tgn:7029392"
    ],
    "placetype": [
      "aat:300000390"
    ],
    "id": 2539056,
    "name:xx": "New Dall Mine"
  }
}
