{
  "geometry": {
    "type": "Point",
    "coordinates": [
      -83.8167,
      34.8667
    ]
  },
  "type": "Feature",
  "properties": {
    "hierarchy": [
      "tgn:2237363",
      "tgn:1000001",
      "tgn:7012149",
      "tgn:2000435",
      "tgn:7007248",
      "tgn:7029392"
    ],
    "placetype": [
      "aat:300008798"
    ],
    "id": 2237363,
    "name:xx": "Chimneytop Mountain"
  }
}
