{
  "geometry": {
    "type": "Point",
    "coordinates": [
      -75.8167,
      38.7667
    ]
  },
  "type": "Feature",
  "properties": {
    "hierarchy": [
      "tgn:2132012",
      "tgn:1002234",
      "tgn:1000001",
      "tgn:7012149",
      "tgn:7007516",
      "tgn:7029392"
    ],
    "placetype": [
      "aat:300008347"
    ],
    "id": 2132012,
    "name:xx": "American Corner"
  }
}
