{
  "type": "FeatureCollection",
  "features": [
    {
      "geometry": {
        "type": "Point",
        "coordinates": [
          -92.4667,
          44.15
        ]
      },
      "type": "Feature",
      "properties": {
        "hierarchy": [
          "tgn:1132200",
          "tgn:1000001",
          "tgn:7012149",
          "tgn:7007521",
          "tgn:7029392"
        ],
        "placetype": [
          "aat:300008707"
        ],
        "id": 1132200,
        "name:xx": "Zumbro"
      }
    },
    {
      "geometry": {
        "type": "Point",
        "coordinates": [
          10.75,
          48.7
        ]
      },
      "type": "Feature",
      "properties": {
        "hierarchy": [
          "tgn:1132206",
          "tgn:7003669",
          "tgn:1000003",
          "tgn:7000084",
          "tgn:7029392"
        ],
        "placetype": [
          "aat:300008707",
          "aat:300008699"
        ],
        "id": 1132206,
        "name:xx": "Zusam"
      }
    },
    {
      "geometry": {
        "type": "Point",
        "coordinates": [
          -45.4833,
          -3.7167
        ]
      },
      "type": "Feature",
      "properties": {
        "hierarchy": [
          "tgn:1132207",
          "tgn:7006246",
          "tgn:1000047",
          "tgn:7002455",
          "tgn:1000002",
          "tgn:7029392"
        ],
        "placetype": [
          "aat:300008707"
        ],
        "id": 1132207,
        "name:xx": "Zutiua"
      }
    },
    {
      "geometry": {
        "type": "Point",
        "coordinates": [
          12.8,
          51
        ]
      },
      "type": "Feature",
      "properties": {
        "hierarchy": [
          "tgn:1132208",
          "tgn:1000003",
          "tgn:7000084",
          "tgn:7029392"
        ],
        "placetype": [
          "aat:300008707"
        ],
        "id": 1132208,
        "name:xx": "Zwickauer Mulde"
      }
    },
    {
      "geometry": {
        "type": "Point",
        "coordinates": [
          -128.4333,
          54.55
        ]
      },
      "type": "Feature",
      "properties": {
        "hierarchy": [
          "tgn:1132209",
          "tgn:7005735",
          "tgn:7005685",
          "tgn:1000001",
          "tgn:7029392"
        ],
        "placetype": [
          "aat:300008707"
        ],
        "id": 1132209,
        "name:xx": "Zymoetz"
      }
    }
  ]
}
