{
  "geometry": {
    "type": "Point",
    "coordinates": [
      24.25,
      41.516667
    ]
  },
  "type": "Feature",
  "properties": {
    "hierarchy": [
      "tgn:7237120",
      "tgn:7011170",
      "tgn:7002715",
      "tgn:1000003",
      "tgn:1000074",
      "tgn:7029392"
    ],
    "placetype": [
      "aat:300008057"
    ],
    "id": 7237120,
    "name:xx": "Erípia Andilálou"
  }
}
