{
  "geometry": {
    "type": "Point",
    "coordinates": [
      -74.3333,
      40.6667
    ]
  },
  "type": "Feature",
  "properties": {
    "hierarchy": [
      "tgn:2310568",
      "tgn:1000001",
      "tgn:1002963",
      "tgn:7012149",
      "tgn:7007565",
      "tgn:7029392"
    ],
    "placetype": [
      "aat:300008680"
    ],
    "id": 2310568,
    "name:xx": "Echo Lake"
  }
}
