{
  "geometry": {
    "type": "Point",
    "coordinates": [
      -108.4667,
      32.5167
    ]
  },
  "type": "Feature",
  "properties": {
    "hierarchy": [
      "tgn:2440687",
      "tgn:1000001",
      "tgn:7012149",
      "tgn:2001437",
      "tgn:7007566",
      "tgn:7029392"
    ],
    "placetype": [
      "aat:300006191"
    ],
    "id": 2440687,
    "name:xx": "Knight Canyon Tank"
  }
}
