{
  "geometry": {
    "type": "Point",
    "coordinates": [
      114.0333,
      31.35
    ]
  },
  "type": "Feature",
  "properties": {
    "hierarchy": [
      "tgn:1068753",
      "tgn:1000004",
      "tgn:7002078",
      "tgn:1000111",
      "tgn:7029392"
    ],
    "placetype": [
      "aat:300008347"
    ],
    "id": 1068753,
    "name:xx": "Hiaohexi"
  }
}
