{
  "geometry": {
    "type": "Point",
    "coordinates": [
      34.578404,
      28.845773
    ]
  },
  "type": "Feature",
  "properties": {
    "hierarchy": [
      "tgn:7532667",
      "tgn:7001242",
      "tgn:7016833",
      "tgn:7001336",
      "tgn:7029392"
    ],
    "placetype": [
      "aat:300379998"
    ],
    "id": 7532667,
    "name:xx": "Ḥibeiqîya, Wâdi-el"
  }
}
