{
  "type": "FeatureCollection",
  "features": [
    {
      "geometry": {
        "type": "Point",
        "coordinates": [
          -79.05,
          38.7667
        ]
      },
      "type": "Feature",
      "properties": {
        "hierarchy": [
          "tgn:2163210",
          "tgn:1000001",
          "tgn:7012149",
          "tgn:2002187",
          "tgn:7007919",
          "tgn:7029392"
        ],
        "placetype": [
          "aat:300008699"
        ],
        "id": 2163210,
        "name:xx": "Bennett Run"
      }
    },
    {
      "geometry": {
        "type": "Point",
        "coordinates": [
          -80.4667,
          38.85
        ]
      },
      "type": "Feature",
      "properties": {
        "hierarchy": [
          "tgn:2163211",
          "tgn:1000001",
          "tgn:7012149",
          "tgn:2002271",
          "tgn:7013961",
          "tgn:7029392"
        ],
        "placetype": [
          "aat:300008699"
        ],
        "id": 2163211,
        "name:xx": "Bennett Run"
      }
    },
    {
      "geometry": {
        "type": "Point",
        "coordinates": [
          -81.7167,
          38.95
        ]
      },
      "type": "Feature",
      "properties": {
        "hierarchy": [
          "tgn:2163212",
          "tgn:1000001",
          "tgn:7012149",
          "tgn:2002268",
          "tgn:7013961",
          "tgn:7029392"
        ],
        "placetype": [
          "aat:300008699"
        ],
        "id": 2163212,
        "name:xx": "Bennett Run"
      }
    },
    {
      "geometry": {
        "type": "Point",
        "coordinates": [
          -80.4333,
          39.4
        ]
      },
      "type": "Feature",
      "properties": {
        "hierarchy": [
          "tgn:2163213",
          "tgn:1000001",
          "tgn:7012149",
          "tgn:2002267",
          "tgn:7013961",
          "tgn:7029392"
        ],
        "placetype": [
          "aat:300008699"
        ],
        "id": 2163213,
        "name:xx": "Bennett Run"
      }
    },
    {
      "geometry": {
        "type": "Point",
        "coordinates": [
          -79.6,
          38.8
        ]
      },
      "type": "Feature",
      "properties": {
        "hierarchy": [
          "tgn:2163214",
          "tgn:1000001",
          "tgn:7012149",
          "tgn:2002291",
          "tgn:7013961",
          "tgn:7029392"
        ],
        "placetype": [
          "aat:300008699"
        ],
        "id": 2163214,
        "name:xx": "Bennett Run"
      }
    },
    {
      "geometry": {
        "type": "Point",
        "coordinates": [
          -79.6167,
          38.65
        ]
      },
      "type": "Feature",
      "properties": {
        "hierarchy": [
          "tgn:2163215",
          "tgn:1000001",
          "tgn:7012149",
          "tgn:2002287",
          "tgn:7013961",
          "tgn:7029392"
        ],
        "placetype": [
          "aat:300008699"
        ],
        "id": 2163215,
        "name:xx": "Bennett Run"
      }
    },
    {
      "geometry": {
        "type": "Point",
        "coordinates": [
          -81.5,
          39.0333
        ]
      },
      "type": "Feature",
      "properties": {
        "hierarchy": [
          "tgn:2163216",
          "tgn:1000001",
          "tgn:7012149",
          "tgn:2002302",
          "tgn:7013961",
          "tgn:7029392"
        ],
        "placetype": [
          "aat:300008699"
        ],
        "id": 2163216,
        "name:xx": "Bennett Run"
      }
    },
    {
      "geometry": {
        "type": "Point",
        "coordinates": [
          -102.85,
          35.9833
        ]
      },
      "type": "Feature",
      "properties": {
        "hierarchy": [
          "tgn:2163217",
          "tgn:1000001",
          "tgn:7012149",
          "tgn:2001999",
          "tgn:7007826",
          "tgn:7029392"
        ],
        "placetype": [
          "aat:300008798"
        ],
        "id": 2163217,
        "name:xx": "Bennett Sand Hills"
      }
    },
    {
      "geometry": {
        "type": "Point",
        "coordinates": [
          -112.2,
          35.2167
        ]
      },
      "type": "Feature",
      "properties": {
        "hierarchy": [
          "tgn:2163218",
          "tgn:1000001",
          "tgn:7006451",
          "tgn:2000092",
          "tgn:7012149",
          "tgn:7029392"
        ],
        "placetype": [
          "aat:300008697"
        ],
        "id": 2163218,
        "name:xx": "Bennett Spring"
      }
    },
    {
      "geometry": {
        "type": "Point",
        "coordinates": [
          -121.7167,
          40.0167
        ]
      },
      "type": "Feature",
      "properties": {
        "hierarchy": [
          "tgn:2163219",
          "tgn:1000001",
          "tgn:7012149",
          "tgn:7007157",
          "tgn:2000190",
          "tgn:7029392"
        ],
        "placetype": [
          "aat:300008697"
        ],
        "id": 2163219,
        "name:xx": "Bennett Spring"
      }
    }
  ]
}
