{
  "geometry": {
    "type": "Point",
    "coordinates": [
      -43.3833,
      -22.8333
    ]
  },
  "type": "Feature",
  "properties": {
    "hierarchy": [
      "tgn:1004573",
      "tgn:1001942",
      "tgn:1000047",
      "tgn:7002457",
      "tgn:1000002",
      "tgn:7017095",
      "tgn:7029392"
    ],
    "placetype": [
      "aat:300000745"
    ],
    "id": 1004573,
    "name:xx": "Guadalupe"
  }
}
