{
  "geometry": {
    "type": "Point",
    "coordinates": [
      -72.3833,
      41.8667
    ]
  },
  "type": "Feature",
  "properties": {
    "hierarchy": [
      "tgn:2589095",
      "tgn:1000001",
      "tgn:1002949",
      "tgn:7012149",
      "tgn:7007159",
      "tgn:7029392"
    ],
    "placetype": [
      "aat:300006191"
    ],
    "id": 2589095,
    "name:xx": "Poehnerts Pond"
  }
}
