{
  "geometry": {
    "type": "Point",
    "coordinates": [
      31.592151,
      30.713984
    ]
  },
  "type": "Feature",
  "properties": {
    "hierarchy": [
      "tgn:7529193",
      "tgn:7001242",
      "tgn:7016833",
      "tgn:1001113",
      "tgn:7029392"
    ],
    "placetype": [
      "aat:300006075"
    ],
    "id": 7529193,
    "name:xx": "Tur'at aţ Ţarrādīyah"
  }
}
