{
  "geometry": {
    "type": "Point",
    "coordinates": [
      -111.35,
      37.4833
    ]
  },
  "type": "Feature",
  "properties": {
    "hierarchy": [
      "tgn:2607922",
      "tgn:1000001",
      "tgn:7012149",
      "tgn:7007827",
      "tgn:7029392"
    ],
    "placetype": [
      "aat:300008761"
    ],
    "id": 2607922,
    "name:xx": "Rat Seep Hollow"
  }
}
