{
  "geometry": {
    "type": "Point",
    "coordinates": [
      25.6667,
      64.5167
    ]
  },
  "type": "Feature",
  "properties": {
    "hierarchy": [
      "tgn:1031530",
      "tgn:1001475",
      "tgn:1000003",
      "tgn:1000069",
      "tgn:7029392"
    ],
    "placetype": [
      "aat:300008347"
    ],
    "id": 1031530,
    "name:xx": "Rantsila"
  }
}
