{
  "geometry": {
    "type": "Point",
    "coordinates": [
      -149.8167,
      61.1833
    ]
  },
  "type": "Feature",
  "properties": {
    "hierarchy": [
      "tgn:2355747",
      "tgn:2124017",
      "tgn:7006450",
      "tgn:1000001",
      "tgn:7012149",
      "tgn:7029392"
    ],
    "placetype": [
      "aat:300008680"
    ],
    "id": 2355747,
    "name:xx": "Goose Lake"
  }
}
