{
  "geometry": {
    "type": "Point",
    "coordinates": [
      -93.55,
      44.9167
    ]
  },
  "type": "Feature",
  "properties": {
    "hierarchy": [
      "tgn:2343519",
      "tgn:1000001",
      "tgn:2001025",
      "tgn:7012149",
      "tgn:7007521",
      "tgn:7029392"
    ],
    "placetype": [
      "aat:300008791"
    ],
    "id": 2343519,
    "name:xx": "Gale Island"
  }
}
