{
  "geometry": {
    "type": "Point",
    "coordinates": [
      -77.0167,
      35.4333
    ]
  },
  "type": "Feature",
  "properties": {
    "hierarchy": [
      "tgn:2393684",
      "tgn:1000001",
      "tgn:7013368",
      "tgn:7012149",
      "tgn:7007709",
      "tgn:7029392"
    ],
    "placetype": [
      "aat:300008699"
    ],
    "id": 2393684,
    "name:xx": "Hog Hole Branch"
  }
}
