{
  "geometry": {
    "type": "Point",
    "coordinates": [
      74.54423,
      31.528771
    ]
  },
  "type": "Feature",
  "properties": {
    "hierarchy": [
      "tgn:7552274",
      "tgn:1000004",
      "tgn:7000198",
      "tgn:7016883",
      "tgn:7029392"
    ],
    "placetype": [
      "aat:300008347"
    ],
    "name:en": "Manhiāla",
    "id": 7552274
  }
}
