{
  "geometry": {
    "type": "Point",
    "coordinates": [
      -109.35,
      33.4333
    ]
  },
  "type": "Feature",
  "properties": {
    "hierarchy": [
      "tgn:2631900",
      "tgn:1000001",
      "tgn:7006451",
      "tgn:2000095",
      "tgn:7012149",
      "tgn:7029392"
    ],
    "placetype": [
      "aat:300008761"
    ],
    "id": 2631900,
    "name:xx": "Rousensock Canyon"
  }
}
