{
  "geometry": {
    "type": "Point",
    "coordinates": [
      -79.05,
      39.0833
    ]
  },
  "type": "Feature",
  "properties": {
    "hierarchy": [
      "tgn:2200649",
      "tgn:1000001",
      "tgn:2002263",
      "tgn:7012149",
      "tgn:7013961",
      "tgn:7029392"
    ],
    "placetype": [
      "aat:300008699"
    ],
    "id": 2200649,
    "name:xx": "Brushy Run"
  }
}
