{
  "geometry": {
    "type": "Point",
    "coordinates": [
      -83.7667,
      36.9167
    ]
  },
  "type": "Feature",
  "properties": {
    "hierarchy": [
      "tgn:2371683",
      "tgn:1000001",
      "tgn:7012149",
      "tgn:2000806",
      "tgn:7007255",
      "tgn:7029392"
    ],
    "placetype": [
      "aat:300008699"
    ],
    "id": 2371683,
    "name:xx": "Hale Fork"
  }
}
