{
  "geometry": {
    "type": "Point",
    "coordinates": [
      -83.55,
      44.1667
    ]
  },
  "type": "Feature",
  "properties": {
    "hierarchy": [
      "tgn:2228841",
      "tgn:1000001",
      "tgn:7012149",
      "tgn:2000965",
      "tgn:7007520",
      "tgn:7029392"
    ],
    "placetype": [
      "aat:300008347"
    ],
    "id": 2228841,
    "name:xx": "Cedar Haven"
  }
}
