{
  "geometry": {
    "type": "Point",
    "coordinates": [
      -113.8167,
      38.1333
    ]
  },
  "type": "Feature",
  "properties": {
    "hierarchy": [
      "tgn:2459207",
      "tgn:1000001",
      "tgn:7012149",
      "tgn:2002111",
      "tgn:7007827",
      "tgn:7029392"
    ],
    "placetype": [
      "aat:300008697"
    ],
    "id": 2459207,
    "name:xx": "Little Pinto Spring"
  }
}
