{
  "type": "FeatureCollection",
  "features": [
    {
      "geometry": {
        "type": "Point",
        "coordinates": [
          -97.866667,
          25.416667
        ]
      },
      "type": "Feature",
      "properties": {
        "hierarchy": [
          "tgn:7394500",
          "tgn:1000001",
          "tgn:7005597",
          "tgn:7005560",
          "tgn:7029392"
        ],
        "placetype": [
          "aat:300008347"
        ],
        "id": 7394500,
        "name:xx": "San Ignacio"
      }
    },
    {
      "geometry": {
        "type": "Point",
        "coordinates": [
          -100.683333,
          25.266667
        ]
      },
      "type": "Feature",
      "properties": {
        "hierarchy": [
          "tgn:7394501",
          "tgn:1001853",
          "tgn:1000001",
          "tgn:7005560",
          "tgn:7029392"
        ],
        "placetype": [
          "aat:300008347"
        ],
        "id": 7394501,
        "name:xx": "San Ignacio"
      }
    },
    {
      "geometry": {
        "type": "Point",
        "coordinates": [
          -99.183333,
          25.216667
        ]
      },
      "type": "Feature",
      "properties": {
        "hierarchy": [
          "tgn:7394502",
          "tgn:1000001",
          "tgn:7005589",
          "tgn:7005560",
          "tgn:7029392"
        ],
        "placetype": [
          "aat:300008347"
        ],
        "id": 7394502,
        "name:xx": "San Ignacio"
      }
    },
    {
      "geometry": {
        "type": "Point",
        "coordinates": [
          -105.133333,
          25.083333
        ]
      },
      "type": "Feature",
      "properties": {
        "hierarchy": [
          "tgn:7394503",
          "tgn:7005583",
          "tgn:1000001",
          "tgn:7005560",
          "tgn:7029392"
        ],
        "placetype": [
          "aat:300008347"
        ],
        "id": 7394503,
        "name:xx": "San Ignacio"
      }
    },
    {
      "geometry": {
        "type": "Point",
        "coordinates": [
          -104.916667,
          24.366667
        ]
      },
      "type": "Feature",
      "properties": {
        "hierarchy": [
          "tgn:7394505",
          "tgn:7005583",
          "tgn:1000001",
          "tgn:7005560",
          "tgn:7029392"
        ],
        "placetype": [
          "aat:300008347"
        ],
        "id": 7394505,
        "name:xx": "San Ignacio"
      }
    },
    {
      "geometry": {
        "type": "Point",
        "coordinates": [
          -98.566667,
          24.333333
        ]
      },
      "type": "Feature",
      "properties": {
        "hierarchy": [
          "tgn:7394506",
          "tgn:1000001",
          "tgn:7005597",
          "tgn:7005560",
          "tgn:7029392"
        ],
        "placetype": [
          "aat:300008347"
        ],
        "id": 7394506,
        "name:xx": "San Ignacio"
      }
    },
    {
      "geometry": {
        "type": "Point",
        "coordinates": [
          -105.833333,
          24.3
        ]
      },
      "type": "Feature",
      "properties": {
        "hierarchy": [
          "tgn:7394507",
          "tgn:7005583",
          "tgn:1000001",
          "tgn:7005560",
          "tgn:7029392"
        ],
        "placetype": [
          "aat:300008347"
        ],
        "id": 7394507,
        "name:xx": "San Ignacio"
      }
    },
    {
      "geometry": {
        "type": "Point",
        "coordinates": [
          -104.616667,
          24.05
        ]
      },
      "type": "Feature",
      "properties": {
        "hierarchy": [
          "tgn:7394508",
          "tgn:7005583",
          "tgn:1000001",
          "tgn:7005560",
          "tgn:7029392"
        ],
        "placetype": [
          "aat:300008347"
        ],
        "id": 7394508,
        "name:xx": "San Ignacio"
      }
    },
    {
      "geometry": {
        "type": "Point",
        "coordinates": [
          -101.916667,
          23.983333
        ]
      },
      "type": "Feature",
      "properties": {
        "hierarchy": [
          "tgn:7394509",
          "tgn:1000001",
          "tgn:7005601",
          "tgn:7005560",
          "tgn:7029392"
        ],
        "placetype": [
          "aat:300008347"
        ],
        "id": 7394509,
        "name:xx": "San Ignacio"
      }
    }
  ]
}
