{
  "geometry": {
    "type": "Point",
    "coordinates": [
      -93.1833,
      47.6833
    ]
  },
  "type": "Feature",
  "properties": {
    "hierarchy": [
      "tgn:2347521",
      "tgn:1000001",
      "tgn:7012149",
      "tgn:7007521",
      "tgn:7029392"
    ],
    "placetype": [
      "aat:300008863"
    ],
    "id": 2347521,
    "name:xx": "George Washington State Forest"
  }
}
