{
  "geometry": {
    "type": "Point",
    "coordinates": [
      -111.7333,
      46.25
    ]
  },
  "type": "Feature",
  "properties": {
    "hierarchy": [
      "tgn:2353285",
      "tgn:1000001",
      "tgn:2001263",
      "tgn:7012149",
      "tgn:7007524",
      "tgn:7029392"
    ],
    "placetype": [
      "aat:300000390"
    ],
    "id": 2353285,
    "name:xx": "Gold Bug Mine"
  }
}
