{
  "geometry": {
    "type": "Point",
    "coordinates": [
      -86.0167,
      42.8833
    ]
  },
  "type": "Feature",
  "properties": {
    "hierarchy": [
      "tgn:2051352",
      "tgn:1000001",
      "tgn:7012149",
      "tgn:1002760",
      "tgn:7007520",
      "tgn:7029392"
    ],
    "placetype": [
      "aat:300008347"
    ],
    "id": 2051352,
    "name:xx": "Borculo"
  }
}
