{
  "geometry": {
    "type": "Point",
    "coordinates": [
      -75.35,
      38.05
    ]
  },
  "type": "Feature",
  "properties": {
    "hierarchy": [
      "tgn:2156635",
      "tgn:1000001",
      "tgn:1003037",
      "tgn:7012149",
      "tgn:7007516",
      "tgn:7029392"
    ],
    "placetype": [
      "aat:300008680"
    ],
    "id": 2156635,
    "name:xx": "Beasey Pond"
  }
}
