{
  "geometry": {
    "type": "Point",
    "coordinates": [
      -73.8167,
      43.7667
    ]
  },
  "type": "Feature",
  "properties": {
    "hierarchy": [
      "tgn:2342309",
      "tgn:1000001",
      "tgn:7012149",
      "tgn:7007568",
      "tgn:7029392"
    ],
    "placetype": [
      "aat:300008699"
    ],
    "id": 2342309,
    "name:xx": "Fuller Brook"
  }
}
