{
  "geometry": {
    "type": "Point",
    "coordinates": [
      -111.7667,
      34.0667
    ]
  },
  "type": "Feature",
  "properties": {
    "hierarchy": [
      "tgn:2457381",
      "tgn:1000001",
      "tgn:7006451",
      "tgn:7012149",
      "tgn:2000103",
      "tgn:7029392"
    ],
    "placetype": [
      "aat:300008706"
    ],
    "id": 2457381,
    "name:xx": "Little Lime Creek"
  }
}
