{
  "geometry": {
    "type": "Point",
    "coordinates": [
      -82.9333,
      41.15
    ]
  },
  "type": "Feature",
  "properties": {
    "hierarchy": [
      "tgn:2082524",
      "tgn:1000001",
      "tgn:7012149",
      "tgn:1002883",
      "tgn:7007706",
      "tgn:7029392"
    ],
    "placetype": [
      "aat:300008347"
    ],
    "id": 2082524,
    "name:xx": "West Lodi"
  }
}
