{
  "type": "FeatureCollection",
  "features": [
    {
      "geometry": {
        "type": "Point",
        "coordinates": [
          14.8833,
          50.45
        ]
      },
      "type": "Feature",
      "properties": {
        "hierarchy": [
          "tgn:4003197",
          "tgn:1003530",
          "tgn:1000003",
          "tgn:1001780",
          "tgn:7029392"
        ],
        "placetype": [
          "aat:300008347"
        ],
        "id": 4003197,
        "name:xx": "Debř"
      }
    },
    {
      "geometry": {
        "type": "Point",
        "coordinates": [
          25.1833,
          42.8667
        ]
      },
      "type": "Feature",
      "properties": {
        "hierarchy": [
          "tgn:4003198",
          "tgn:7593862",
          "tgn:1000003",
          "tgn:7006413",
          "tgn:7029392"
        ],
        "placetype": [
          "aat:300008347"
        ],
        "id": 4003198,
        "name:xx": "Debel Dyal"
      }
    }
  ]
}
