{
  "geometry": {
    "type": "Point",
    "coordinates": [
      -95.1667,
      30.4833
    ]
  },
  "type": "Feature",
  "properties": {
    "hierarchy": [
      "tgn:2445956",
      "tgn:1000001",
      "tgn:7012149",
      "tgn:1002860",
      "tgn:7007826",
      "tgn:7029392"
    ],
    "placetype": [
      "aat:300006191"
    ],
    "id": 2445956,
    "name:xx": "Letbetter Lake"
  }
}
