{
  "geometry": {
    "type": "Point",
    "coordinates": [
      95.4833,
      5.35
    ]
  },
  "type": "Feature",
  "properties": {
    "hierarchy": [
      "tgn:1078546",
      "tgn:7016479",
      "tgn:1000004",
      "tgn:1000116",
      "tgn:7029392"
    ],
    "placetype": [
      "aat:300008347"
    ],
    "id": 1078546,
    "name:xx": "Seulimeum"
  }
}
