{
  "type": "FeatureCollection",
  "features": [
    {
      "geometry": {
        "type": "Point",
        "coordinates": [
          -121.8833,
          44.5333
        ]
      },
      "type": "Feature",
      "properties": {
        "hierarchy": [
          "tgn:2277360",
          "tgn:1000001",
          "tgn:7012149",
          "tgn:2001717",
          "tgn:7007708",
          "tgn:7029392"
        ],
        "placetype": [
          "aat:300008680"
        ],
        "id": 2277360,
        "name:xx": "Davis Lake"
      }
    },
    {
      "geometry": {
        "type": "Point",
        "coordinates": [
          -121.8333,
          43.6
        ]
      },
      "type": "Feature",
      "properties": {
        "hierarchy": [
          "tgn:2277361",
          "tgn:1000001",
          "tgn:7012149",
          "tgn:7007708",
          "tgn:7029392"
        ],
        "placetype": [
          "aat:300008680"
        ],
        "id": 2277361,
        "name:xx": "Davis Lake"
      }
    },
    {
      "geometry": {
        "type": "Point",
        "coordinates": [
          -85.4833,
          35.15
        ]
      },
      "type": "Feature",
      "properties": {
        "hierarchy": [
          "tgn:2277362",
          "tgn:1000001",
          "tgn:7012149",
          "tgn:2001894",
          "tgn:7007825",
          "tgn:7029392"
        ],
        "placetype": [
          "aat:300008680"
        ],
        "id": 2277362,
        "name:xx": "Davis Lake"
      }
    },
    {
      "geometry": {
        "type": "Point",
        "coordinates": [
          -84.9333,
          35.0667
        ]
      },
      "type": "Feature",
      "properties": {
        "hierarchy": [
          "tgn:2277363",
          "tgn:1000001",
          "tgn:2001842",
          "tgn:7012149",
          "tgn:7007825",
          "tgn:7029392"
        ],
        "placetype": [
          "aat:300006191"
        ],
        "id": 2277363,
        "name:xx": "Davis Lake"
      }
    },
    {
      "geometry": {
        "type": "Point",
        "coordinates": [
          -86.4667,
          35.4
        ]
      },
      "type": "Feature",
      "properties": {
        "hierarchy": [
          "tgn:2277364",
          "tgn:1000001",
          "tgn:2001838",
          "tgn:7012149",
          "tgn:7007825",
          "tgn:7029392"
        ],
        "placetype": [
          "aat:300006191"
        ],
        "id": 2277364,
        "name:xx": "Davis Lake"
      }
    },
    {
      "geometry": {
        "type": "Point",
        "coordinates": [
          -96.2333,
          30.9833
        ]
      },
      "type": "Feature",
      "properties": {
        "hierarchy": [
          "tgn:2277365",
          "tgn:1000001",
          "tgn:7012149",
          "tgn:1002830",
          "tgn:7007826",
          "tgn:7029392"
        ],
        "placetype": [
          "aat:300008680"
        ],
        "id": 2277365,
        "name:xx": "Davis Lake"
      }
    },
    {
      "geometry": {
        "type": "Point",
        "coordinates": [
          -117.7167,
          47.7667
        ]
      },
      "type": "Feature",
      "properties": {
        "hierarchy": [
          "tgn:2277366",
          "tgn:1000001",
          "tgn:7012149",
          "tgn:2002249",
          "tgn:7007920",
          "tgn:7029392"
        ],
        "placetype": [
          "aat:300008680"
        ],
        "id": 2277366,
        "name:xx": "Davis Lake"
      }
    },
    {
      "geometry": {
        "type": "Point",
        "coordinates": [
          -117.2833,
          48.2167
        ]
      },
      "type": "Feature",
      "properties": {
        "hierarchy": [
          "tgn:2277367",
          "tgn:1000001",
          "tgn:7012149",
          "tgn:2002248",
          "tgn:7007920",
          "tgn:7029392"
        ],
        "placetype": [
          "aat:300006191"
        ],
        "id": 2277367,
        "name:xx": "Davis Lake"
      }
    },
    {
      "geometry": {
        "type": "Point",
        "coordinates": [
          -119.3167,
          48.5667
        ]
      },
      "type": "Feature",
      "properties": {
        "hierarchy": [
          "tgn:2277368",
          "tgn:1000001",
          "tgn:7012149",
          "tgn:1002742",
          "tgn:7007920",
          "tgn:7029392"
        ],
        "placetype": [
          "aat:300008680"
        ],
        "id": 2277368,
        "name:xx": "Davis Lake"
      }
    },
    {
      "geometry": {
        "type": "Point",
        "coordinates": [
          -118.2167,
          48.7333
        ]
      },
      "type": "Feature",
      "properties": {
        "hierarchy": [
          "tgn:2277369",
          "tgn:1000001",
          "tgn:2002243",
          "tgn:7012149",
          "tgn:7007920",
          "tgn:7029392"
        ],
        "placetype": [
          "aat:300008680"
        ],
        "id": 2277369,
        "name:xx": "Davis Lake"
      }
    }
  ]
}
