{
  "type": "FeatureCollection",
  "features": [
    {
      "geometry": {
        "type": "Point",
        "coordinates": [
          -111.4167,
          41.6833
        ]
      },
      "type": "Feature",
      "properties": {
        "hierarchy": [
          "tgn:2356690",
          "tgn:1000001",
          "tgn:2002103",
          "tgn:7012149",
          "tgn:7007827",
          "tgn:7029392"
        ],
        "placetype": [
          "aat:300008761"
        ],
        "id": 2356690,
        "name:xx": "Gorge Canyon"
      }
    },
    {
      "geometry": {
        "type": "Point",
        "coordinates": [
          -154.8667,
          58.7333
        ]
      },
      "type": "Feature",
      "properties": {
        "hierarchy": [
          "tgn:2356691",
          "tgn:7006450",
          "tgn:1000001",
          "tgn:7030517",
          "tgn:7012149",
          "tgn:7029392"
        ],
        "placetype": [
          "aat:300008706"
        ],
        "id": 2356691,
        "name:xx": "Gorge Creek"
      }
    },
    {
      "geometry": {
        "type": "Point",
        "coordinates": [
          -150.2,
          63.4167
        ]
      },
      "type": "Feature",
      "properties": {
        "hierarchy": [
          "tgn:2356692",
          "tgn:7006450",
          "tgn:1000001",
          "tgn:7030547",
          "tgn:7012149",
          "tgn:7029392"
        ],
        "placetype": [
          "aat:300008706"
        ],
        "id": 2356692,
        "name:xx": "Gorge Creek"
      }
    },
    {
      "geometry": {
        "type": "Point",
        "coordinates": [
          -120.8667,
          36.4167
        ]
      },
      "type": "Feature",
      "properties": {
        "hierarchy": [
          "tgn:2356693",
          "tgn:1000001",
          "tgn:7012149",
          "tgn:7007157",
          "tgn:1002856",
          "tgn:7029392"
        ],
        "placetype": [
          "aat:300008706"
        ],
        "id": 2356693,
        "name:xx": "Gorge Creek"
      }
    },
    {
      "geometry": {
        "type": "Point",
        "coordinates": [
          -111.3667,
          45.1333
        ]
      },
      "type": "Feature",
      "properties": {
        "hierarchy": [
          "tgn:2356694",
          "tgn:1000001",
          "tgn:7012149",
          "tgn:2001288",
          "tgn:7007524",
          "tgn:7029392"
        ],
        "placetype": [
          "aat:300008706"
        ],
        "id": 2356694,
        "name:xx": "Gorge Creek"
      }
    },
    {
      "geometry": {
        "type": "Point",
        "coordinates": [
          -110.5833,
          45.2
        ]
      },
      "type": "Feature",
      "properties": {
        "hierarchy": [
          "tgn:2356695",
          "tgn:1000001",
          "tgn:7012149",
          "tgn:2001293",
          "tgn:7007524",
          "tgn:7029392"
        ],
        "placetype": [
          "aat:300008706"
        ],
        "id": 2356695,
        "name:xx": "Gorge Creek"
      }
    },
    {
      "geometry": {
        "type": "Point",
        "coordinates": [
          -112.95,
          45.4833
        ]
      },
      "type": "Feature",
      "properties": {
        "hierarchy": [
          "tgn:2356696",
          "tgn:1000001",
          "tgn:2001260",
          "tgn:7012149",
          "tgn:7007524",
          "tgn:7029392"
        ],
        "placetype": [
          "aat:300008706"
        ],
        "id": 2356696,
        "name:xx": "Gorge Creek"
      }
    },
    {
      "geometry": {
        "type": "Point",
        "coordinates": [
          -118.5833,
          44.6
        ]
      },
      "type": "Feature",
      "properties": {
        "hierarchy": [
          "tgn:2356697",
          "tgn:1000001",
          "tgn:7012149",
          "tgn:2001708",
          "tgn:7007708",
          "tgn:7029392"
        ],
        "placetype": [
          "aat:300008706"
        ],
        "id": 2356697,
        "name:xx": "Gorge Creek"
      }
    },
    {
      "geometry": {
        "type": "Point",
        "coordinates": [
          -109.3667,
          40.8167
        ]
      },
      "type": "Feature",
      "properties": {
        "hierarchy": [
          "tgn:2356698",
          "tgn:1000001",
          "tgn:7012149",
          "tgn:7007827",
          "tgn:7029392"
        ],
        "placetype": [
          "aat:300008706"
        ],
        "id": 2356698,
        "name:xx": "Gorge Creek"
      }
    },
    {
      "geometry": {
        "type": "Point",
        "coordinates": [
          -121.2333,
          48.7167
        ]
      },
      "type": "Feature",
      "properties": {
        "hierarchy": [
          "tgn:2356699",
          "tgn:1000001",
          "tgn:7012149",
          "tgn:1003020",
          "tgn:7007920",
          "tgn:7029392"
        ],
        "placetype": [
          "aat:300008706"
        ],
        "id": 2356699,
        "name:xx": "Gorge Creek"
      }
    }
  ]
}
