{
  "geometry": {
    "type": "Point",
    "coordinates": [
      -84.8167,
      42.1833
    ]
  },
  "type": "Feature",
  "properties": {
    "hierarchy": [
      "tgn:2145909",
      "tgn:1000001",
      "tgn:1002222",
      "tgn:7012149",
      "tgn:7007520",
      "tgn:7029392"
    ],
    "placetype": [
      "aat:300006075"
    ],
    "id": 2145909,
    "name:xx": "Ball And Patterson Drain"
  }
}
