{
  "geometry": {
    "type": "Point",
    "coordinates": [
      121.595,
      24.0551
    ]
  },
  "type": "Feature",
  "properties": {
    "hierarchy": [
      "tgn:7490463",
      "tgn:7001010",
      "tgn:1000004",
      "tgn:1000141",
      "tgn:7029392"
    ],
    "placetype": [
      "aat:300008347"
    ],
    "id": 7490463,
    "name:xx": "Sanzhan"
  }
}
