{
  "geometry": {
    "type": "Point",
    "coordinates": [
      -111.3667,
      39.9167
    ]
  },
  "type": "Feature",
  "properties": {
    "hierarchy": [
      "tgn:2274184",
      "tgn:1000001",
      "tgn:7012149",
      "tgn:2002125",
      "tgn:7007827",
      "tgn:7029392"
    ],
    "placetype": [
      "aat:300008699"
    ],
    "id": 2274184,
    "name:xx": "Dairy Fork"
  }
}
