{
  "geometry": {
    "type": "Point",
    "coordinates": [
      -93.25,
      44.9667
    ]
  },
  "type": "Feature",
  "properties": {
    "hierarchy": [
      "tgn:2385846",
      "tgn:1000001",
      "tgn:2001025",
      "tgn:7012149",
      "tgn:7007521",
      "tgn:7029392"
    ],
    "placetype": [
      "aat:300008791"
    ],
    "id": 2385846,
    "name:xx": "Hennepin Island"
  }
}
