{
  "geometry": {
    "type": "Point",
    "coordinates": [
      30.782169,
      29.278636
    ]
  },
  "type": "Feature",
  "properties": {
    "hierarchy": [
      "tgn:7540693",
      "tgn:7001242",
      "tgn:7001105",
      "tgn:7016833",
      "tgn:7029392"
    ],
    "placetype": [
      "aat:300008347"
    ],
    "name:en": "Minshāt Raḩmī",
    "id": 7540693
  }
}
