{
  "geometry": {
    "type": "Point",
    "coordinates": [
      -122.4667,
      40.7167
    ]
  },
  "type": "Feature",
  "properties": {
    "hierarchy": [
      "tgn:2297352",
      "tgn:1000001",
      "tgn:7012149",
      "tgn:7007157",
      "tgn:2000188",
      "tgn:7029392"
    ],
    "placetype": [
      "aat:300008699"
    ],
    "id": 2297352,
    "name:xx": "Dry Fork"
  }
}
