{
  "type": "FeatureCollection",
  "features": [
    {
      "geometry": {
        "type": "Point",
        "coordinates": [
          -89.0167,
          36.4
        ]
      },
      "type": "Feature",
      "properties": {
        "hierarchy": [
          "tgn:2390300",
          "tgn:1000001",
          "tgn:7012149",
          "tgn:2001902",
          "tgn:7007825",
          "tgn:7029392"
        ],
        "placetype": [
          "aat:300008347"
        ],
        "id": 2390300,
        "name:xx": "Highland"
      }
    },
    {
      "geometry": {
        "type": "Point",
        "coordinates": [
          -96.9,
          32.8667
        ]
      },
      "type": "Feature",
      "properties": {
        "hierarchy": [
          "tgn:2390301",
          "tgn:1000001",
          "tgn:7012149",
          "tgn:1002315",
          "tgn:7007826",
          "tgn:7029392"
        ],
        "placetype": [
          "aat:300008347"
        ],
        "id": 2390301,
        "name:xx": "Highland"
      }
    },
    {
      "geometry": {
        "type": "Point",
        "coordinates": [
          -97.35,
          31.5333
        ]
      },
      "type": "Feature",
      "properties": {
        "hierarchy": [
          "tgn:2390302",
          "tgn:1000001",
          "tgn:7012149",
          "tgn:7021748",
          "tgn:7007826",
          "tgn:7029392"
        ],
        "placetype": [
          "aat:300008347"
        ],
        "id": 2390302,
        "name:xx": "Highland"
      }
    },
    {
      "geometry": {
        "type": "Point",
        "coordinates": [
          -112.1,
          40.7
        ]
      },
      "type": "Feature",
      "properties": {
        "hierarchy": [
          "tgn:2390303",
          "tgn:1000001",
          "tgn:7012149",
          "tgn:2002118",
          "tgn:7007827",
          "tgn:7029392"
        ],
        "placetype": [
          "aat:300008347"
        ],
        "id": 2390303,
        "name:xx": "Highland"
      }
    },
    {
      "geometry": {
        "type": "Point",
        "coordinates": [
          -117.5167,
          47.6833
        ]
      },
      "type": "Feature",
      "properties": {
        "hierarchy": [
          "tgn:2390304",
          "tgn:1000001",
          "tgn:7012149",
          "tgn:2002249",
          "tgn:7007920",
          "tgn:7029392"
        ],
        "placetype": [
          "aat:300008347"
        ],
        "id": 2390304,
        "name:xx": "Highland"
      }
    },
    {
      "geometry": {
        "type": "Point",
        "coordinates": [
          -93.1333,
          31.7667
        ]
      },
      "type": "Feature",
      "properties": {
        "hierarchy": [
          "tgn:2390305",
          "tgn:1000001",
          "tgn:7012149",
          "tgn:2000888",
          "tgn:7007256",
          "tgn:7029392"
        ],
        "placetype": [
          "aat:300008347"
        ],
        "id": 2390305,
        "name:xx": "Highland Acres"
      }
    },
    {
      "geometry": {
        "type": "Point",
        "coordinates": [
          -78.85,
          35.05
        ]
      },
      "type": "Feature",
      "properties": {
        "hierarchy": [
          "tgn:2390306",
          "tgn:1000001",
          "tgn:7012149",
          "tgn:2001487",
          "tgn:7007709",
          "tgn:7029392"
        ],
        "placetype": [
          "aat:300008347"
        ],
        "id": 2390306,
        "name:xx": "Highland Acres"
      }
    },
    {
      "geometry": {
        "type": "Point",
        "coordinates": [
          -79.2167,
          35.5
        ]
      },
      "type": "Feature",
      "properties": {
        "hierarchy": [
          "tgn:2390307",
          "tgn:1000001",
          "tgn:7012149",
          "tgn:2001511",
          "tgn:7007709",
          "tgn:7029392"
        ],
        "placetype": [
          "aat:300008347"
        ],
        "id": 2390307,
        "name:xx": "Highland Acres"
      }
    },
    {
      "geometry": {
        "type": "Point",
        "coordinates": [
          -82.6167,
          34.5
        ]
      },
      "type": "Feature",
      "properties": {
        "hierarchy": [
          "tgn:2390308",
          "tgn:2001728",
          "tgn:1000001",
          "tgn:7012149",
          "tgn:7007712",
          "tgn:7029392"
        ],
        "placetype": [
          "aat:300008347"
        ],
        "id": 2390308,
        "name:xx": "Highland Acres"
      }
    },
    {
      "geometry": {
        "type": "Point",
        "coordinates": [
          -86.6333,
          36.3
        ]
      },
      "type": "Feature",
      "properties": {
        "hierarchy": [
          "tgn:2390309",
          "tgn:1000001",
          "tgn:7012149",
          "tgn:2001919",
          "tgn:7007825",
          "tgn:7029392"
        ],
        "placetype": [
          "aat:300008347"
        ],
        "id": 2390309,
        "name:xx": "Highland Acres"
      }
    }
  ]
}
