{
  "type": "FeatureCollection",
  "features": [
    {
      "geometry": {
        "type": "Point",
        "coordinates": [
          -95.25,
          40.25
        ]
      },
      "type": "Feature",
      "properties": {
        "hierarchy": [
          "tgn:2770820",
          "tgn:1000001",
          "tgn:7012149",
          "tgn:2001204",
          "tgn:7007523",
          "tgn:7029392"
        ],
        "placetype": [
          "aat:300008706"
        ],
        "id": 2770820,
        "name:xx": "Wildcat Creek"
      }
    },
    {
      "geometry": {
        "type": "Point",
        "coordinates": [
          -90.4667,
          37.6667
        ]
      },
      "type": "Feature",
      "properties": {
        "hierarchy": [
          "tgn:2770821",
          "tgn:1000001",
          "tgn:7012149",
          "tgn:2001241",
          "tgn:7007523",
          "tgn:7029392"
        ],
        "placetype": [
          "aat:300008706"
        ],
        "id": 2770821,
        "name:xx": "Wildcat Creek"
      }
    },
    {
      "geometry": {
        "type": "Point",
        "coordinates": [
          -113.95,
          48.1833
        ]
      },
      "type": "Feature",
      "properties": {
        "hierarchy": [
          "tgn:2770822",
          "tgn:1000001",
          "tgn:7012149",
          "tgn:2001274",
          "tgn:7007524",
          "tgn:7029392"
        ],
        "placetype": [
          "aat:300008706"
        ],
        "id": 2770822,
        "name:xx": "Wildcat Creek"
      }
    },
    {
      "geometry": {
        "type": "Point",
        "coordinates": [
          -109.5833,
          45.9833
        ]
      },
      "type": "Feature",
      "properties": {
        "hierarchy": [
          "tgn:2770823",
          "tgn:1000001",
          "tgn:7012149",
          "tgn:2001308",
          "tgn:7007524",
          "tgn:7029392"
        ],
        "placetype": [
          "aat:300008706"
        ],
        "id": 2770823,
        "name:xx": "Wildcat Creek"
      }
    },
    {
      "geometry": {
        "type": "Point",
        "coordinates": [
          -106.9833,
          47
        ]
      },
      "type": "Feature",
      "properties": {
        "hierarchy": [
          "tgn:2770824",
          "tgn:1000001",
          "tgn:7012149",
          "tgn:2001276",
          "tgn:7007524",
          "tgn:7029392"
        ],
        "placetype": [
          "aat:300008706"
        ],
        "id": 2770824,
        "name:xx": "Wildcat Creek"
      }
    },
    {
      "geometry": {
        "type": "Point",
        "coordinates": [
          -97.35,
          41.0333
        ]
      },
      "type": "Feature",
      "properties": {
        "hierarchy": [
          "tgn:2770825",
          "tgn:1000001",
          "tgn:7012149",
          "tgn:7007525",
          "tgn:7029392"
        ],
        "placetype": [
          "aat:300008706"
        ],
        "id": 2770825,
        "name:xx": "Wildcat Creek"
      }
    },
    {
      "geometry": {
        "type": "Point",
        "coordinates": [
          -95.7,
          40
        ]
      },
      "type": "Feature",
      "properties": {
        "hierarchy": [
          "tgn:2770826",
          "tgn:1000001",
          "tgn:7012149",
          "tgn:2001389",
          "tgn:7007525",
          "tgn:7029392"
        ],
        "placetype": [
          "aat:300008706"
        ],
        "id": 2770826,
        "name:xx": "Wildcat Creek"
      }
    },
    {
      "geometry": {
        "type": "Point",
        "coordinates": [
          -96.4833,
          40.2167
        ]
      },
      "type": "Feature",
      "properties": {
        "hierarchy": [
          "tgn:2770827",
          "tgn:1000001",
          "tgn:2001349",
          "tgn:7012149",
          "tgn:7007525",
          "tgn:7029392"
        ],
        "placetype": [
          "aat:300008706"
        ],
        "id": 2770827,
        "name:xx": "Wildcat Creek"
      }
    },
    {
      "geometry": {
        "type": "Point",
        "coordinates": [
          -96.3333,
          40.0167
        ]
      },
      "type": "Feature",
      "properties": {
        "hierarchy": [
          "tgn:2770828",
          "tgn:1000001",
          "tgn:7012149",
          "tgn:2001382",
          "tgn:7007525",
          "tgn:7029392"
        ],
        "placetype": [
          "aat:300008706"
        ],
        "id": 2770828,
        "name:xx": "Wildcat Creek"
      }
    },
    {
      "geometry": {
        "type": "Point",
        "coordinates": [
          -118.0167,
          41.85
        ]
      },
      "type": "Feature",
      "properties": {
        "hierarchy": [
          "tgn:2770829",
          "tgn:1000001",
          "tgn:2001414",
          "tgn:7012149",
          "tgn:7007526",
          "tgn:7029392"
        ],
        "placetype": [
          "aat:300008706"
        ],
        "id": 2770829,
        "name:xx": "Wildcat Creek"
      }
    }
  ]
}
