{
  "geometry": {
    "type": "Point",
    "coordinates": [
      -86.8833,
      33.3667
    ]
  },
  "type": "Feature",
  "properties": {
    "hierarchy": [
      "tgn:2625955",
      "tgn:7002659",
      "tgn:1000001",
      "tgn:7012149",
      "tgn:2000036",
      "tgn:7029392"
    ],
    "placetype": [
      "aat:300008699"
    ],
    "id": 2625955,
    "name:xx": "Rocky Brook"
  }
}
