{
  "type": "FeatureCollection",
  "features": [
    {
      "geometry": {
        "type": "Point",
        "coordinates": [
          -2.116667,
          51.866667
        ]
      },
      "type": "Feature",
      "properties": {
        "hierarchy": [
          "tgn:4010410",
          "tgn:7002445",
          "tgn:1000003",
          "tgn:7008132",
          "tgn:7008591",
          "tgn:7029392"
        ],
        "placetype": [
          "aat:300008347"
        ],
        "name:en": "Shurdington",
        "id": 4010410
      }
    },
    {
      "geometry": {
        "type": "Point",
        "coordinates": [
          21.1833,
          49.6333
        ]
      },
      "type": "Feature",
      "properties": {
        "hierarchy": [
          "tgn:4010411",
          "tgn:1000003",
          "tgn:7024127",
          "tgn:7006366",
          "tgn:7029392"
        ],
        "placetype": [
          "aat:300008347"
        ],
        "id": 4010411,
        "name:xx": "Siary"
      }
    }
  ]
}
