{
  "geometry": {
    "type": "Point",
    "coordinates": [
      -107.0833,
      47.2333
    ]
  },
  "type": "Feature",
  "properties": {
    "hierarchy": [
      "tgn:2682537",
      "tgn:1000001",
      "tgn:7012149",
      "tgn:2001276",
      "tgn:7007524",
      "tgn:7029392"
    ],
    "placetype": [
      "aat:300008761"
    ],
    "id": 2682537,
    "name:xx": "Southerland Coulee"
  }
}
