{
  "geometry": {
    "type": "Point",
    "coordinates": [
      -85.2333,
      37.5167
    ]
  },
  "type": "Feature",
  "properties": {
    "hierarchy": [
      "tgn:2321092",
      "tgn:1000001",
      "tgn:7012149",
      "tgn:2000822",
      "tgn:7007255",
      "tgn:7029392"
    ],
    "placetype": [
      "aat:300008699"
    ],
    "id": 2321092,
    "name:xx": "Fagan Branch"
  }
}
