{
  "geometry": {
    "type": "Point",
    "coordinates": [
      48.5833,
      18.25
    ]
  },
  "type": "Feature",
  "properties": {
    "hierarchy": [
      "tgn:1111864",
      "tgn:1000139",
      "tgn:7004345",
      "tgn:1000004",
      "tgn:7000261",
      "tgn:7029392"
    ],
    "placetype": [
      "aat:300387346"
    ],
    "id": 1111864,
    "name:xx": "Al-Qaʻāmīyāt"
  }
}
