{
  "geometry": {
    "type": "Point",
    "coordinates": [
      -76.1667,
      39.0833
    ]
  },
  "type": "Feature",
  "properties": {
    "hierarchy": [
      "tgn:2541009",
      "tgn:1000001",
      "tgn:1002539",
      "tgn:7012149",
      "tgn:7007516",
      "tgn:7029392"
    ],
    "placetype": [
      "aat:300008850"
    ],
    "id": 2541009,
    "name:xx": "Nichols Point"
  }
}
