{
  "geometry": {
    "type": "Point",
    "coordinates": [
      11.65,
      52.45
    ]
  },
  "type": "Feature",
  "properties": {
    "hierarchy": [
      "tgn:7188648",
      "tgn:1000003",
      "tgn:7003687",
      "tgn:7000084",
      "tgn:7029392"
    ],
    "placetype": [
      "aat:300004792"
    ],
    "id": 7188648,
    "name:xx": "Försterei Eisergrund"
  }
}
