{
  "geometry": {
    "type": "Point",
    "coordinates": [
      78.58,
      17.289444
    ]
  },
  "type": "Feature",
  "properties": {
    "hierarchy": [
      "tgn:7570074",
      "tgn:1001828",
      "tgn:1000004",
      "tgn:7000198",
      "tgn:7029392"
    ],
    "placetype": [
      "aat:300006191"
    ],
    "name:en": "Masāb Cheruvu",
    "id": 7570074
  }
}
