{
  "geometry": {
    "type": "Point",
    "coordinates": [
      -90.8667,
      43.3167
    ]
  },
  "type": "Feature",
  "properties": {
    "hierarchy": [
      "tgn:2346646",
      "tgn:1000001",
      "tgn:2002316",
      "tgn:7012149",
      "tgn:7007922",
      "tgn:7029392"
    ],
    "placetype": [
      "aat:300266640"
    ],
    "id": 2346646,
    "name:xx": "Gays Mills Ridge"
  }
}
