{
  "geometry": {
    "type": "Point",
    "coordinates": [
      -108.0167,
      32.8167
    ]
  },
  "type": "Feature",
  "properties": {
    "hierarchy": [
      "tgn:2312277",
      "tgn:1000001",
      "tgn:7012149",
      "tgn:2001437",
      "tgn:7007566",
      "tgn:7029392"
    ],
    "placetype": [
      "aat:300006191"
    ],
    "id": 2312277,
    "name:xx": "Eighteen Tank"
  }
}
