{
  "geometry": {
    "type": "Point",
    "coordinates": [
      78.875514,
      25.1254
    ]
  },
  "type": "Feature",
  "properties": {
    "hierarchy": [
      "tgn:7583878",
      "tgn:1000004",
      "tgn:7000198",
      "tgn:1001894",
      "tgn:7029392"
    ],
    "placetype": [
      "aat:300008347"
    ],
    "name:en": "Bāri",
    "id": 7583878
  }
}
