{
  "geometry": {
    "type": "Point",
    "coordinates": [
      -85.0333,
      36.0167
    ]
  },
  "type": "Feature",
  "properties": {
    "hierarchy": [
      "tgn:2101752",
      "tgn:1000001",
      "tgn:7012149",
      "tgn:2001854",
      "tgn:7007825",
      "tgn:7029392"
    ],
    "placetype": [
      "aat:300008347",
      "aat:300387210"
    ],
    "id": 2101752,
    "name:xx": "Tabor"
  }
}
