{
  "geometry": {
    "type": "Point",
    "coordinates": [
      -111.6167,
      40.5667
    ]
  },
  "type": "Feature",
  "properties": {
    "hierarchy": [
      "tgn:2128145",
      "tgn:1000001",
      "tgn:7012149",
      "tgn:2002118",
      "tgn:7007827",
      "tgn:7029392"
    ],
    "placetype": [
      "aat:300008347"
    ],
    "id": 2128145,
    "name:xx": "Albion Basin"
  }
}
