{
  "geometry": {
    "type": "Point",
    "coordinates": [
      -122.1167,
      43.4167
    ]
  },
  "type": "Feature",
  "properties": {
    "hierarchy": [
      "tgn:2559648",
      "tgn:1000001",
      "tgn:7012149",
      "tgn:2001706",
      "tgn:7007708",
      "tgn:7029392"
    ],
    "placetype": [
      "aat:300008680"
    ],
    "id": 2559648,
    "name:xx": "Opal Lake"
  }
}
