{
  "geometry": {
    "type": "Point",
    "coordinates": [
      -80.4667,
      39.8833
    ]
  },
  "type": "Feature",
  "properties": {
    "hierarchy": [
      "tgn:2301156",
      "tgn:1000001",
      "tgn:7012149",
      "tgn:7029392"
    ],
    "placetype": [
      "aat:300008699"
    ],
    "id": 2301156,
    "name:xx": "Dunkard Fork"
  }
}
