{
  "geometry": {
    "type": "Point",
    "coordinates": [
      -111.2167,
      39.3833
    ]
  },
  "type": "Feature",
  "properties": {
    "hierarchy": [
      "tgn:2777453",
      "tgn:1000001",
      "tgn:2002108",
      "tgn:7012149",
      "tgn:7007827",
      "tgn:7029392"
    ],
    "placetype": [
      "aat:300008761"
    ],
    "id": 2777453,
    "name:xx": "Winks Canyon"
  }
}
