{
  "geometry": {
    "type": "Point",
    "coordinates": [
      -109.8333,
      39.3667
    ]
  },
  "type": "Feature",
  "properties": {
    "hierarchy": [
      "tgn:2378107",
      "tgn:1000001",
      "tgn:7012149",
      "tgn:2002110",
      "tgn:7007827",
      "tgn:7029392"
    ],
    "placetype": [
      "aat:300008699"
    ],
    "id": 2378107,
    "name:xx": "Harris Fork"
  }
}
