{
  "geometry": {
    "type": "Point",
    "coordinates": [
      -75.55,
      43.0167
    ]
  },
  "type": "Feature",
  "properties": {
    "hierarchy": [
      "tgn:2712754",
      "tgn:1000001",
      "tgn:7012149",
      "tgn:7007568",
      "tgn:7029392"
    ],
    "placetype": [
      "aat:300008706"
    ],
    "id": 2712754,
    "name:xx": "Taylor Creek"
  }
}
