{
  "geometry": {
    "type": "Point",
    "coordinates": [
      -71.9833,
      41.2833
    ]
  },
  "type": "Feature",
  "properties": {
    "hierarchy": [
      "tgn:2600701",
      "tgn:1000001",
      "tgn:7012149",
      "tgn:1002924",
      "tgn:7007568",
      "tgn:7029392"
    ],
    "placetype": [
      "aat:300132348"
    ],
    "id": 2600701,
    "name:xx": "Pulpit Rock"
  }
}
