{
  "geometry": {
    "type": "Point",
    "coordinates": [
      -119.2833,
      36.45
    ]
  },
  "type": "Feature",
  "properties": {
    "hierarchy": [
      "tgn:2655470",
      "tgn:1000001",
      "tgn:7012149",
      "tgn:7007157",
      "tgn:1002956",
      "tgn:7029392"
    ],
    "placetype": [
      "aat:300006075"
    ],
    "id": 2655470,
    "name:xx": "Sharp Ditch"
  }
}
