{
  "type": "FeatureCollection",
  "features": [
    {
      "geometry": {
        "type": "Point",
        "coordinates": [
          -6.5,
          42.183333
        ]
      },
      "type": "Feature",
      "properties": {
        "hierarchy": [
          "tgn:7326720",
          "tgn:7002826",
          "tgn:7001158",
          "tgn:1000003",
          "tgn:1000095",
          "tgn:7029392"
        ],
        "placetype": [
          "aat:300008798"
        ],
        "id": 7326720,
        "name:xx": "Peña Negra, Alto de"
      }
    },
    {
      "geometry": {
        "type": "Point",
        "coordinates": [
          -7.3,
          43.166667
        ]
      },
      "type": "Feature",
      "properties": {
        "hierarchy": [
          "tgn:7326722",
          "tgn:7002829",
          "tgn:1000003",
          "tgn:7002786",
          "tgn:1000095",
          "tgn:7029392"
        ],
        "placetype": [
          "aat:300008347"
        ],
        "id": 7326722,
        "name:xx": "Penamazada"
      }
    },
    {
      "geometry": {
        "type": "Point",
        "coordinates": [
          -7,
          43.116667
        ]
      },
      "type": "Feature",
      "properties": {
        "hierarchy": [
          "tgn:7326723",
          "tgn:7002829",
          "tgn:1000003",
          "tgn:7002786",
          "tgn:1000095",
          "tgn:7029392"
        ],
        "placetype": [
          "aat:300008347"
        ],
        "id": 7326723,
        "name:xx": "Penamayor"
      }
    },
    {
      "geometry": {
        "type": "Point",
        "coordinates": [
          -1.916667,
          37.9
        ]
      },
      "type": "Feature",
      "properties": {
        "hierarchy": [
          "tgn:7326724",
          "tgn:1001439",
          "tgn:1000003",
          "tgn:7002797",
          "tgn:1000095",
          "tgn:7029392"
        ],
        "placetype": [
          "aat:300008795"
        ],
        "id": 7326724,
        "name:xx": "Peña María, Cerro de"
      }
    },
    {
      "geometry": {
        "type": "Point",
        "coordinates": [
          -1.933333,
          37.883333
        ]
      },
      "type": "Feature",
      "properties": {
        "hierarchy": [
          "tgn:7326725",
          "tgn:1001439",
          "tgn:1000003",
          "tgn:7002797",
          "tgn:1000095",
          "tgn:7029392"
        ],
        "placetype": [
          "aat:300008347"
        ],
        "id": 7326725,
        "name:xx": "Peña María"
      }
    },
    {
      "geometry": {
        "type": "Point",
        "coordinates": [
          -2.883333,
          40.583333
        ]
      },
      "type": "Feature",
      "properties": {
        "hierarchy": [
          "tgn:7326726",
          "tgn:7002822",
          "tgn:1001647",
          "tgn:1000003",
          "tgn:1000095",
          "tgn:7029392"
        ],
        "placetype": [
          "aat:300008347"
        ],
        "id": 7326726,
        "name:xx": "Peñalver"
      }
    },
    {
      "geometry": {
        "type": "Point",
        "coordinates": [
          -1.016667,
          40.6
        ]
      },
      "type": "Feature",
      "properties": {
        "hierarchy": [
          "tgn:7326727",
          "tgn:7002759",
          "tgn:7002843",
          "tgn:1000003",
          "tgn:1000095",
          "tgn:7029392"
        ],
        "placetype": [
          "aat:300266554",
          "aat:300008699"
        ],
        "id": 7326727,
        "name:xx": "Peñalva, Barranco de"
      }
    },
    {
      "geometry": {
        "type": "Point",
        "coordinates": [
          -5.066667,
          43.316667
        ]
      },
      "type": "Feature",
      "properties": {
        "hierarchy": [
          "tgn:7326728",
          "tgn:7008911",
          "tgn:1000003",
          "tgn:7002763",
          "tgn:1000095",
          "tgn:7029392"
        ],
        "placetype": [
          "aat:300008347"
        ],
        "id": 7326728,
        "name:xx": "Peñalva"
      }
    },
    {
      "geometry": {
        "type": "Point",
        "coordinates": [
          -5.116667,
          38.816667
        ]
      },
      "type": "Feature",
      "properties": {
        "hierarchy": [
          "tgn:7326729",
          "tgn:7002807",
          "tgn:1000003",
          "tgn:7003837",
          "tgn:1000095",
          "tgn:7029392"
        ],
        "placetype": [
          "aat:300008347"
        ],
        "id": 7326729,
        "name:xx": "Peñalsordo"
      }
    }
  ]
}
