{
  "geometry": {
    "type": "Point",
    "coordinates": [
      -89.1333,
      42.3667
    ]
  },
  "type": "Feature",
  "properties": {
    "hierarchy": [
      "tgn:2528833",
      "tgn:1000001",
      "tgn:7012149",
      "tgn:1003030",
      "tgn:7007251",
      "tgn:7029392"
    ],
    "placetype": [
      "aat:300008706"
    ],
    "id": 2528833,
    "name:xx": "Mud Creek"
  }
}
