{
  "geometry": {
    "type": "Point",
    "coordinates": [
      -85.2333,
      32.3333
    ]
  },
  "type": "Feature",
  "properties": {
    "hierarchy": [
      "tgn:2445421",
      "tgn:7002659",
      "tgn:1000001",
      "tgn:7012149",
      "tgn:2000056",
      "tgn:7029392"
    ],
    "placetype": [
      "aat:300006191"
    ],
    "id": 2445421,
    "name:xx": "Lenora, Lake"
  }
}
