{
  "geometry": {
    "type": "Point",
    "coordinates": [
      71.756647,
      26.698561
    ]
  },
  "type": "Feature",
  "properties": {
    "hierarchy": [
      "tgn:7588906",
      "tgn:1000004",
      "tgn:7000198",
      "tgn:7016788",
      "tgn:7029392"
    ],
    "placetype": [
      "aat:300008347"
    ],
    "name:en": "Gamnān Ki Dhāni",
    "id": 7588906
  }
}
