{
  "geometry": {
    "type": "Point",
    "coordinates": [
      -104.5167,
      31.4333
    ]
  },
  "type": "Feature",
  "properties": {
    "hierarchy": [
      "tgn:2637342",
      "tgn:1000001",
      "tgn:7012149",
      "tgn:2001969",
      "tgn:7007826",
      "tgn:7029392"
    ],
    "placetype": [
      "aat:300006191"
    ],
    "id": 2637342,
    "name:xx": "Saint John Tank"
  }
}
