{
  "geometry": {
    "type": "Point",
    "coordinates": [
      -76.6333,
      41.9667
    ]
  },
  "type": "Feature",
  "properties": {
    "hierarchy": [
      "tgn:2295025",
      "tgn:1000001",
      "tgn:1002194",
      "tgn:7012149",
      "tgn:7007710",
      "tgn:7029392"
    ],
    "placetype": [
      "aat:300266640"
    ],
    "id": 2295025,
    "name:xx": "Draper Ridge"
  }
}
