{
  "geometry": {
    "type": "Point",
    "coordinates": [
      -87.3167,
      36.1667
    ]
  },
  "type": "Feature",
  "properties": {
    "hierarchy": [
      "tgn:2677506",
      "tgn:1000001",
      "tgn:7012149",
      "tgn:2001858",
      "tgn:7007825",
      "tgn:7029392"
    ],
    "placetype": [
      "aat:300000390"
    ],
    "id": 2677506,
    "name:xx": "South Charlotte Mine"
  }
}
