{
  "geometry": {
    "type": "Point",
    "coordinates": [
      -76.2667,
      37.4667
    ]
  },
  "type": "Feature",
  "properties": {
    "hierarchy": [
      "tgn:2511723",
      "tgn:1000001",
      "tgn:7012149",
      "tgn:1002647",
      "tgn:7007919",
      "tgn:7029392"
    ],
    "placetype": [
      "aat:300132316"
    ],
    "id": 2511723,
    "name:xx": "Milford Haven"
  }
}
