{
  "geometry": {
    "type": "Point",
    "coordinates": [
      -84.8667,
      42.1833
    ]
  },
  "type": "Feature",
  "properties": {
    "hierarchy": [
      "tgn:2404732",
      "tgn:1000001",
      "tgn:1002222",
      "tgn:7012149",
      "tgn:7007520",
      "tgn:7029392"
    ],
    "placetype": [
      "aat:300006075"
    ],
    "id": 2404732,
    "name:xx": "Huckleberry Drain"
  }
}
