{
  "geometry": {
    "type": "Point",
    "coordinates": [
      106.6833,
      10.8167
    ]
  },
  "type": "Feature",
  "properties": {
    "hierarchy": [
      "tgn:1087120",
      "tgn:1000004",
      "tgn:7001063",
      "tgn:1000145",
      "tgn:7029392"
    ],
    "placetype": [
      "aat:300008347"
    ],
    "id": 1087120,
    "name:xx": "Gò Vấp"
  }
}
