{
  "geometry": {
    "type": "Point",
    "coordinates": [
      -85.3167,
      40.4333
    ]
  },
  "type": "Feature",
  "properties": {
    "hierarchy": [
      "tgn:2586819",
      "tgn:1000001",
      "tgn:1002184",
      "tgn:7012149",
      "tgn:7007252",
      "tgn:7029392"
    ],
    "placetype": [
      "aat:300006191"
    ],
    "id": 2586819,
    "name:xx": "Placid, Lake"
  }
}
