{
  "geometry": {
    "type": "Point",
    "coordinates": [
      -82.25,
      41.35
    ]
  },
  "type": "Feature",
  "properties": {
    "hierarchy": [
      "tgn:2081931",
      "tgn:1000001",
      "tgn:7012149",
      "tgn:1002607",
      "tgn:7007706",
      "tgn:7029392"
    ],
    "placetype": [
      "aat:300008347"
    ],
    "id": 2081931,
    "name:xx": "South Amherst"
  }
}
