{
  "geometry": {
    "type": "Point",
    "coordinates": [
      -153.2167,
      58.15
    ]
  },
  "type": "Feature",
  "properties": {
    "hierarchy": [
      "tgn:2220539",
      "tgn:7006450",
      "tgn:1000001",
      "tgn:2124012",
      "tgn:7012149",
      "tgn:7029392"
    ],
    "placetype": [
      "aat:300008850"
    ],
    "id": 2220539,
    "name:xx": "Cape Nuniliak"
  }
}
