{
  "geometry": {
    "type": "Point",
    "coordinates": [
      -109.7833,
      44.6167
    ]
  },
  "type": "Feature",
  "properties": {
    "hierarchy": [
      "tgn:2320276",
      "tgn:1000001",
      "tgn:7012149",
      "tgn:2002379",
      "tgn:7007923",
      "tgn:7029392"
    ],
    "placetype": [
      "aat:300000390"
    ],
    "id": 2320276,
    "name:xx": "Evening Star Mine"
  }
}
