{
  "geometry": {
    "type": "Point",
    "coordinates": [
      76.545128,
      30.10096
    ]
  },
  "type": "Feature",
  "properties": {
    "hierarchy": [
      "tgn:7584668",
      "tgn:1000004",
      "tgn:7000198",
      "tgn:7016883",
      "tgn:7029392"
    ],
    "placetype": [
      "aat:300008347"
    ],
    "name:en": "Bībīpur",
    "id": 7584668
  }
}
