{
  "geometry": {
    "type": "Point",
    "coordinates": [
      -79.95,
      40.6667
    ]
  },
  "type": "Feature",
  "properties": {
    "hierarchy": [
      "tgn:2350814",
      "tgn:1000001",
      "tgn:7012149",
      "tgn:7007710",
      "tgn:7029392"
    ],
    "placetype": [
      "aat:300008699"
    ],
    "id": 2350814,
    "name:xx": "Glade Run"
  }
}
