{
  "geometry": {
    "type": "Point",
    "coordinates": [
      67.1833,
      40.55
    ]
  },
  "type": "Feature",
  "properties": {
    "hierarchy": [
      "tgn:1060870",
      "tgn:7012256",
      "tgn:1000004",
      "tgn:7006661",
      "tgn:7029392"
    ],
    "placetype": [
      "aat:300008347"
    ],
    "id": 1060870,
    "name:xx": "Uzunkuduk"
  }
}
