{
  "geometry": {
    "type": "Point",
    "coordinates": [
      -112.3167,
      42.3333
    ]
  },
  "type": "Feature",
  "properties": {
    "hierarchy": [
      "tgn:2314904",
      "tgn:1000001",
      "tgn:7012149",
      "tgn:7007250",
      "tgn:7029392"
    ],
    "placetype": [
      "aat:300008798"
    ],
    "id": 2314904,
    "name:xx": "Elkhorn Peak"
  }
}
