{
  "geometry": {
    "type": "Point",
    "coordinates": [
      -97.6667,
      39.35
    ]
  },
  "type": "Feature",
  "properties": {
    "hierarchy": [
      "tgn:2385993",
      "tgn:1000001",
      "tgn:7012149",
      "tgn:7007254",
      "tgn:7029392"
    ],
    "placetype": [
      "aat:300008706"
    ],
    "id": 2385993,
    "name:xx": "Henry Creek"
  }
}
