{
  "geometry": {
    "type": "Point",
    "coordinates": [
      2.5833,
      50.8167
    ]
  },
  "type": "Feature",
  "properties": {
    "hierarchy": [
      "tgn:1035783",
      "tgn:1000003",
      "tgn:7001097",
      "tgn:1000070",
      "tgn:7029392"
    ],
    "placetype": [
      "aat:300008347"
    ],
    "id": 1035783,
    "name:xx": "Steenvoorde"
  }
}
