{
  "type": "FeatureCollection",
  "features": [
    {
      "geometry": {
        "type": "Point",
        "coordinates": [
          -82.8667,
          41.1167
        ]
      },
      "type": "Feature",
      "properties": {
        "hierarchy": [
          "tgn:2081223",
          "tgn:1000001",
          "tgn:7012149",
          "tgn:1002883",
          "tgn:7007706",
          "tgn:7029392"
        ],
        "placetype": [
          "aat:300387016"
        ],
        "id": 2081223,
        "name:xx": "Omar"
      }
    },
    {
      "geometry": {
        "type": "Point",
        "coordinates": [
          -82.9,
          39.15
        ]
      },
      "type": "Feature",
      "properties": {
        "hierarchy": [
          "tgn:2081224",
          "tgn:1000001",
          "tgn:7012149",
          "tgn:1002788",
          "tgn:7007706",
          "tgn:7029392"
        ],
        "placetype": [
          "aat:300008347"
        ],
        "id": 2081224,
        "name:xx": "Omega"
      }
    },
    {
      "geometry": {
        "type": "Point",
        "coordinates": [
          -81.1333,
          40.6833
        ]
      },
      "type": "Feature",
      "properties": {
        "hierarchy": [
          "tgn:2081225",
          "tgn:1000001",
          "tgn:1002239",
          "tgn:7012149",
          "tgn:7007706",
          "tgn:7029392"
        ],
        "placetype": [
          "aat:300008347"
        ],
        "id": 2081225,
        "name:xx": "Oneida"
      }
    },
    {
      "geometry": {
        "type": "Point",
        "coordinates": [
          -84.3833,
          39.4667
        ]
      },
      "type": "Feature",
      "properties": {
        "hierarchy": [
          "tgn:2081226",
          "tgn:1000001",
          "tgn:1002216",
          "tgn:7012149",
          "tgn:7007706",
          "tgn:7029392"
        ],
        "placetype": [
          "aat:300008347"
        ],
        "id": 2081226,
        "name:xx": "Oneida"
      }
    },
    {
      "geometry": {
        "type": "Point",
        "coordinates": [
          -82.5833,
          40.75
        ]
      },
      "type": "Feature",
      "properties": {
        "hierarchy": [
          "tgn:2081229",
          "tgn:1000001",
          "tgn:7012149",
          "tgn:1002823",
          "tgn:7007706",
          "tgn:7029392"
        ],
        "placetype": [
          "aat:300008347"
        ],
        "id": 2081229,
        "name:xx": "Ontario"
      }
    }
  ]
}
