{
  "geometry": {
    "type": "Point",
    "coordinates": [
      -83.4333,
      36.0833
    ]
  },
  "type": "Feature",
  "properties": {
    "hierarchy": [
      "tgn:2100520",
      "tgn:1000001",
      "tgn:7012149",
      "tgn:2001881",
      "tgn:7007825",
      "tgn:7029392"
    ],
    "placetype": [
      "aat:300008347",
      "aat:300387210"
    ],
    "id": 2100520,
    "name:xx": "Mount Horeb"
  }
}
