{
  "geometry": {
    "type": "Point",
    "coordinates": [
      77.35,
      12.966667
    ]
  },
  "type": "Feature",
  "properties": {
    "hierarchy": [
      "tgn:7580160",
      "tgn:1000004",
      "tgn:7000198",
      "tgn:1001882",
      "tgn:7029392"
    ],
    "placetype": [
      "aat:300006191"
    ],
    "name:en": "Sri Chamrājendra Reservoir",
    "id": 7580160
  }
}
