{
  "geometry": {
    "type": "Point",
    "coordinates": [
      121.494167,
      22.6375
    ]
  },
  "type": "Feature",
  "properties": {
    "hierarchy": [
      "tgn:7492731",
      "tgn:1000004",
      "tgn:7491221",
      "tgn:1000141",
      "tgn:7029392"
    ],
    "placetype": [
      "aat:300008816"
    ],
    "id": 7492731,
    "name:xx": "Dabaisha"
  }
}
