{
  "geometry": {
    "type": "Point",
    "coordinates": [
      -89.55,
      46.3167
    ]
  },
  "type": "Feature",
  "properties": {
    "hierarchy": [
      "tgn:2668639",
      "tgn:1000001",
      "tgn:7012149",
      "tgn:2000960",
      "tgn:7007520",
      "tgn:7029392"
    ],
    "placetype": [
      "aat:300008707"
    ],
    "id": 2668639,
    "name:xx": "Slate River"
  }
}
