{
  "geometry": {
    "type": "Point",
    "coordinates": [
      -91.0333,
      30.5667
    ]
  },
  "type": "Feature",
  "properties": {
    "hierarchy": [
      "tgn:2043814",
      "tgn:1000001",
      "tgn:2000870",
      "tgn:7012149",
      "tgn:7007256",
      "tgn:7029392"
    ],
    "placetype": [
      "aat:300008347",
      "aat:300387210"
    ],
    "id": 2043814,
    "name:xx": "Puckett"
  }
}
