{
  "geometry": {
    "type": "Point",
    "coordinates": [
      -105.9833,
      39.3333
    ]
  },
  "type": "Feature",
  "properties": {
    "hierarchy": [
      "tgn:2664346",
      "tgn:1000001",
      "tgn:7012149",
      "tgn:2000238",
      "tgn:7007158",
      "tgn:7029392"
    ],
    "placetype": [
      "aat:300008706"
    ],
    "id": 2664346,
    "name:xx": "Silverheels Creek"
  }
}
