{
  "geometry": {
    "type": "Point",
    "coordinates": [
      -61.05,
      14.8333
    ]
  },
  "type": "Feature",
  "properties": {
    "hierarchy": [
      "tgn:1126364",
      "tgn:7015035",
      "tgn:1000001",
      "tgn:7005870",
      "tgn:7029392"
    ],
    "placetype": [
      "aat:300008707"
    ],
    "id": 1126364,
    "name:xx": "Lorrain, Rivière du"
  }
}
