{
  "geometry": {
    "type": "Point",
    "coordinates": [
      -76.0833,
      38.7667
    ]
  },
  "type": "Feature",
  "properties": {
    "hierarchy": [
      "tgn:2000939",
      "tgn:1000001",
      "tgn:7012149",
      "tgn:7007516",
      "tgn:7029392"
    ],
    "placetype": [
      "aat:300387145",
      "aat:300000771"
    ],
    "id": 2000939,
    "name:xx": "Talbot"
  }
}
