{
  "geometry": {
    "type": "Point",
    "coordinates": [
      -93.9833,
      45.8833
    ]
  },
  "type": "Feature",
  "properties": {
    "hierarchy": [
      "tgn:2203621",
      "tgn:1000001",
      "tgn:7012149",
      "tgn:2001047",
      "tgn:7007521",
      "tgn:7029392"
    ],
    "placetype": [
      "aat:300008706"
    ],
    "id": 2203621,
    "name:xx": "Buckman Creek"
  }
}
