{
  "geometry": {
    "type": "Point",
    "coordinates": [
      9.175,
      39.377
    ]
  },
  "type": "Feature",
  "properties": {
    "hierarchy": [
      "tgn:7003510",
      "tgn:1001641",
      "tgn:1000003",
      "tgn:7003121",
      "tgn:1000080",
      "tgn:7029392"
    ],
    "placetype": [
      "aat:300008347"
    ],
    "id": 7003510,
    "name:xx": "Dolianova"
  }
}
