{
  "geometry": {
    "type": "Point",
    "coordinates": [
      -106.0833,
      40.4833
    ]
  },
  "type": "Feature",
  "properties": {
    "hierarchy": [
      "tgn:2410667",
      "tgn:1000001",
      "tgn:7012149",
      "tgn:2000220",
      "tgn:7007158",
      "tgn:7029392"
    ],
    "placetype": [
      "aat:300008706"
    ],
    "id": 2410667,
    "name:xx": "Indian Creek"
  }
}
