{
  "geometry": {
    "type": "Point",
    "coordinates": [
      -95.5833,
      43.2333
    ]
  },
  "type": "Feature",
  "properties": {
    "hierarchy": [
      "tgn:2588084",
      "tgn:1000001",
      "tgn:7012149",
      "tgn:2000631",
      "tgn:7007253",
      "tgn:7029392"
    ],
    "placetype": [
      "aat:300008706"
    ],
    "id": 2588084,
    "name:xx": "Plessis Creek"
  }
}
