{
  "geometry": {
    "type": "Point",
    "coordinates": [
      -86.9833,
      35.4167
    ]
  },
  "type": "Feature",
  "properties": {
    "hierarchy": [
      "tgn:2729058",
      "tgn:1000001",
      "tgn:7012149",
      "tgn:2001864",
      "tgn:7007825",
      "tgn:7029392"
    ],
    "placetype": [
      "aat:300008699"
    ],
    "id": 2729058,
    "name:xx": "Trigg Branch"
  }
}
