{
  "geometry": {
    "type": "Point",
    "coordinates": [
      -108.7667,
      42.4833
    ]
  },
  "type": "Feature",
  "properties": {
    "hierarchy": [
      "tgn:2451877",
      "tgn:1000001",
      "tgn:7012149",
      "tgn:2002371",
      "tgn:7007923",
      "tgn:7029392"
    ],
    "placetype": [
      "aat:300008706"
    ],
    "id": 2451877,
    "name:xx": "Little Beaver Creek"
  }
}
