{
  "geometry": {
    "type": "Point",
    "coordinates": [
      -117.2667,
      38.2833
    ]
  },
  "type": "Feature",
  "properties": {
    "hierarchy": [
      "tgn:2447081",
      "tgn:1000001",
      "tgn:2001418",
      "tgn:7012149",
      "tgn:7007526",
      "tgn:7029392"
    ],
    "placetype": [
      "aat:300008697"
    ],
    "id": 2447081,
    "name:xx": "Liberty Springs"
  }
}
