{
  "geometry": {
    "type": "Point",
    "coordinates": [
      -112.0667,
      45.75
    ]
  },
  "type": "Feature",
  "properties": {
    "hierarchy": [
      "tgn:2186432",
      "tgn:1000001",
      "tgn:7012149",
      "tgn:2001288",
      "tgn:7007524",
      "tgn:7029392"
    ],
    "placetype": [
      "aat:300386845"
    ],
    "id": 2186432,
    "name:xx": "Bone Basin"
  }
}
