{
  "type": "FeatureCollection",
  "features": [
    {
      "geometry": {
        "type": "Point",
        "coordinates": [
          136.9833,
          34.5333
        ]
      },
      "type": "Feature",
      "properties": {
        "hierarchy": [
          "tgn:1007620",
          "tgn:1000004",
          "tgn:1001007",
          "tgn:7000896",
          "tgn:1000120",
          "tgn:7029392"
        ],
        "placetype": [
          "aat:300008791"
        ],
        "id": 1007620,
        "name:xx": "Kami-jima"
      }
    },
    {
      "geometry": {
        "type": "Point",
        "coordinates": [
          132.7167,
          34.1833
        ]
      },
      "type": "Feature",
      "properties": {
        "hierarchy": [
          "tgn:1007621",
          "tgn:1000984",
          "tgn:7000897",
          "tgn:1000004",
          "tgn:1000120",
          "tgn:7029392"
        ],
        "placetype": [
          "aat:300008791"
        ],
        "id": 1007621,
        "name:xx": "Kamikamagari-shima"
      }
    },
    {
      "geometry": {
        "type": "Point",
        "coordinates": [
          23.396794,
          37.904734
        ]
      },
      "type": "Feature",
      "properties": {
        "hierarchy": [
          "tgn:1007624",
          "tgn:7002681",
          "tgn:7001395",
          "tgn:1000003",
          "tgn:1000074",
          "tgn:7029392"
        ],
        "placetype": [
          "aat:300008791"
        ],
        "id": 1007624,
        "name:xx": "Kanáki, Nisís"
      }
    },
    {
      "geometry": {
        "type": "Point",
        "coordinates": [
          178.2167,
          -19.05
        ]
      },
      "type": "Feature",
      "properties": {
        "hierarchy": [
          "tgn:1007626",
          "tgn:1000849",
          "tgn:7000493",
          "tgn:1000006",
          "tgn:7029392"
        ],
        "placetype": [
          "aat:300008791"
        ],
        "id": 1007626,
        "name:xx": "Kandavu Island"
      }
    }
  ]
}
