{
  "type": "FeatureCollection",
  "features": [
    {
      "geometry": {
        "type": "Point",
        "coordinates": [
          -123.5667,
          46.2
        ]
      },
      "type": "Feature",
      "properties": {
        "hierarchy": [
          "tgn:2440540",
          "tgn:1000001",
          "tgn:1002276",
          "tgn:7012149",
          "tgn:7007708",
          "tgn:7029392"
        ],
        "placetype": [
          "aat:300008699"
        ],
        "id": 2440540,
        "name:xx": "Knappa Slough"
      }
    },
    {
      "geometry": {
        "type": "Point",
        "coordinates": [
          -84.6167,
          44.2667
        ]
      },
      "type": "Feature",
      "properties": {
        "hierarchy": [
          "tgn:2440541",
          "tgn:1000001",
          "tgn:7012149",
          "tgn:2000991",
          "tgn:7007520",
          "tgn:7029392"
        ],
        "placetype": [
          "aat:300008706"
        ],
        "id": 2440541,
        "name:xx": "Knappen Creek"
      }
    },
    {
      "geometry": {
        "type": "Point",
        "coordinates": [
          -83.3,
          36.6667
        ]
      },
      "type": "Feature",
      "properties": {
        "hierarchy": [
          "tgn:2440542",
          "tgn:1000001",
          "tgn:7012149",
          "tgn:2002169",
          "tgn:7007919",
          "tgn:7029392"
        ],
        "placetype": [
          "aat:300008746"
        ],
        "id": 2440542,
        "name:xx": "Knapper Cave"
      }
    },
    {
      "geometry": {
        "type": "Point",
        "coordinates": [
          -116.7333,
          45.6
        ]
      },
      "type": "Feature",
      "properties": {
        "hierarchy": [
          "tgn:2440543",
          "tgn:1000001",
          "tgn:7012149",
          "tgn:2001722",
          "tgn:7007708",
          "tgn:7029392"
        ],
        "placetype": [
          "aat:300008761"
        ],
        "id": 2440543,
        "name:xx": "Knapper Gulch"
      }
    },
    {
      "geometry": {
        "type": "Point",
        "coordinates": [
          -103.4333,
          43.3667
        ]
      },
      "type": "Feature",
      "properties": {
        "hierarchy": [
          "tgn:2440544",
          "tgn:1000001",
          "tgn:2001793",
          "tgn:7012149",
          "tgn:7007713",
          "tgn:7029392"
        ],
        "placetype": [
          "aat:300008761"
        ],
        "id": 2440544,
        "name:xx": "Knapple Canyon"
      }
    },
    {
      "geometry": {
        "type": "Point",
        "coordinates": [
          -92.75,
          45.2833
        ]
      },
      "type": "Feature",
      "properties": {
        "hierarchy": [
          "tgn:2440545",
          "tgn:1000001",
          "tgn:7012149",
          "tgn:2001080",
          "tgn:7007521",
          "tgn:7029392"
        ],
        "placetype": [
          "aat:300008746"
        ],
        "id": 2440545,
        "name:xx": "Knapps Cave"
      }
    },
    {
      "geometry": {
        "type": "Point",
        "coordinates": [
          -90.3,
          40.1167
        ]
      },
      "type": "Feature",
      "properties": {
        "hierarchy": [
          "tgn:2440546",
          "tgn:1000001",
          "tgn:7012149",
          "tgn:1002643",
          "tgn:7007251",
          "tgn:7029392"
        ],
        "placetype": [
          "aat:300008791"
        ],
        "id": 2440546,
        "name:xx": "Knapps Island"
      }
    },
    {
      "geometry": {
        "type": "Point",
        "coordinates": [
          -73.2,
          40.7167
        ]
      },
      "type": "Feature",
      "properties": {
        "hierarchy": [
          "tgn:2440547",
          "tgn:1000001",
          "tgn:7012149",
          "tgn:1002924",
          "tgn:7007568",
          "tgn:7029392"
        ],
        "placetype": [
          "aat:300008680"
        ],
        "id": 2440547,
        "name:xx": "Knapps Lake"
      }
    },
    {
      "geometry": {
        "type": "Point",
        "coordinates": [
          -74.6,
          43.2333
        ]
      },
      "type": "Feature",
      "properties": {
        "hierarchy": [
          "tgn:2440548",
          "tgn:1000001",
          "tgn:7012149",
          "tgn:1002397",
          "tgn:7007568",
          "tgn:7029392"
        ],
        "placetype": [
          "aat:300008680"
        ],
        "id": 2440548,
        "name:xx": "Knapps Long Lake"
      }
    },
    {
      "geometry": {
        "type": "Point",
        "coordinates": [
          -82.0667,
          26.4167
        ]
      },
      "type": "Feature",
      "properties": {
        "hierarchy": [
          "tgn:2440549",
          "tgn:1000001",
          "tgn:7012149",
          "tgn:1002582",
          "tgn:7007240",
          "tgn:7029392"
        ],
        "placetype": [
          "aat:300008850"
        ],
        "id": 2440549,
        "name:xx": "Knapps Point"
      }
    }
  ]
}
