{
  "geometry": {
    "type": "Point",
    "coordinates": [
      27.37198,
      31.216
    ]
  },
  "type": "Feature",
  "properties": {
    "hierarchy": [
      "tgn:7533632",
      "tgn:7001242",
      "tgn:7016833",
      "tgn:1001418",
      "tgn:7029392"
    ],
    "placetype": [
      "aat:300379998"
    ],
    "name:en": "Jarāwilah, Wādī al",
    "id": 7533632
  }
}
