{
  "geometry": {
    "type": "Point",
    "coordinates": [
      -84.4167,
      39.1667
    ]
  },
  "type": "Feature",
  "properties": {
    "hierarchy": [
      "tgn:2274550",
      "tgn:1000001",
      "tgn:7012149",
      "tgn:1002441",
      "tgn:7007706",
      "tgn:7029392"
    ],
    "placetype": [
      "aat:300008347"
    ],
    "id": 2274550,
    "name:xx": "Dallmans Corner"
  }
}
