{
  "type": "FeatureCollection",
  "features": [
    {
      "geometry": {
        "type": "Point",
        "coordinates": [
          -104.0833,
          35.1667
        ]
      },
      "type": "Feature",
      "properties": {
        "hierarchy": [
          "tgn:2324330",
          "tgn:1000001",
          "tgn:7012149",
          "tgn:2001453",
          "tgn:7007566",
          "tgn:7029392"
        ],
        "placetype": [
          "aat:300006191"
        ],
        "id": 2324330,
        "name:xx": "Feed Pasture Tank"
      }
    },
    {
      "geometry": {
        "type": "Point",
        "coordinates": [
          -112.6,
          35.3667
        ]
      },
      "type": "Feature",
      "properties": {
        "hierarchy": [
          "tgn:2324332",
          "tgn:1000001",
          "tgn:7006451",
          "tgn:2000092",
          "tgn:7012149",
          "tgn:7029392"
        ],
        "placetype": [
          "aat:300006191"
        ],
        "id": 2324332,
        "name:xx": "Feed Trough Tank"
      }
    },
    {
      "geometry": {
        "type": "Point",
        "coordinates": [
          -89.7833,
          41.4
        ]
      },
      "type": "Feature",
      "properties": {
        "hierarchy": [
          "tgn:2324333",
          "tgn:1000001",
          "tgn:2000497",
          "tgn:7012149",
          "tgn:7007251",
          "tgn:7029392"
        ],
        "placetype": [
          "aat:300386845"
        ],
        "id": 2324333,
        "name:xx": "Feeder Basin"
      }
    },
    {
      "geometry": {
        "type": "Point",
        "coordinates": [
          -115.6667,
          43.1833
        ]
      },
      "type": "Feature",
      "properties": {
        "hierarchy": [
          "tgn:2324334",
          "tgn:1000001",
          "tgn:7012149",
          "tgn:2000471",
          "tgn:7007250",
          "tgn:7029392"
        ],
        "placetype": [
          "aat:300006075"
        ],
        "id": 2324334,
        "name:xx": "Feeder Canal"
      }
    },
    {
      "geometry": {
        "type": "Point",
        "coordinates": [
          -81.3,
          41.0833
        ]
      },
      "type": "Feature",
      "properties": {
        "hierarchy": [
          "tgn:2324335",
          "tgn:1000001",
          "tgn:7012149",
          "tgn:1002797",
          "tgn:7007706",
          "tgn:7029392"
        ],
        "placetype": [
          "aat:300006075"
        ],
        "id": 2324335,
        "name:xx": "Feeder Canal"
      }
    },
    {
      "geometry": {
        "type": "Point",
        "coordinates": [
          -115.8333,
          48.6
        ]
      },
      "type": "Feature",
      "properties": {
        "hierarchy": [
          "tgn:2324336",
          "tgn:1000001",
          "tgn:7012149",
          "tgn:2001286",
          "tgn:7007524",
          "tgn:7029392"
        ],
        "placetype": [
          "aat:300008706"
        ],
        "id": 2324336,
        "name:xx": "Feeder Creek"
      }
    },
    {
      "geometry": {
        "type": "Point",
        "coordinates": [
          -76.4167,
          36.5833
        ]
      },
      "type": "Feature",
      "properties": {
        "hierarchy": [
          "tgn:2324337",
          "tgn:1000001",
          "tgn:2002202",
          "tgn:7012149",
          "tgn:7007919",
          "tgn:7029392"
        ],
        "placetype": [
          "aat:300006075"
        ],
        "id": 2324337,
        "name:xx": "Feeder Ditch"
      }
    },
    {
      "geometry": {
        "type": "Point",
        "coordinates": [
          -105.0333,
          42
        ]
      },
      "type": "Feature",
      "properties": {
        "hierarchy": [
          "tgn:2324338",
          "tgn:1000001",
          "tgn:7012149",
          "tgn:2002380",
          "tgn:7007923",
          "tgn:7029392"
        ],
        "placetype": [
          "aat:300006075"
        ],
        "id": 2324338,
        "name:xx": "Feeder Ditch Number 2"
      }
    },
    {
      "geometry": {
        "type": "Point",
        "coordinates": [
          -114.3,
          34.0833
        ]
      },
      "type": "Feature",
      "properties": {
        "hierarchy": [
          "tgn:2324339",
          "tgn:1000001",
          "tgn:7006451",
          "tgn:7012149",
          "tgn:2000104",
          "tgn:7029392"
        ],
        "placetype": [
          "aat:300006075"
        ],
        "id": 2324339,
        "name:xx": "Feeder Drain Number Five"
      }
    }
  ]
}
