{
  "type": "FeatureCollection",
  "features": [
    {
      "geometry": {
        "type": "Point",
        "coordinates": [
          -94.9667,
          49.3333
        ]
      },
      "type": "Feature",
      "properties": {
        "hierarchy": [
          "tgn:2786210",
          "tgn:1000001",
          "tgn:7012149",
          "tgn:7021313",
          "tgn:7007521",
          "tgn:7029392"
        ],
        "placetype": [
          "aat:300132316"
        ],
        "id": 2786210,
        "name:xx": "Youngs Bay"
      }
    },
    {
      "geometry": {
        "type": "Point",
        "coordinates": [
          -123.85,
          46.1667
        ]
      },
      "type": "Feature",
      "properties": {
        "hierarchy": [
          "tgn:2786211",
          "tgn:1000001",
          "tgn:1002276",
          "tgn:7012149",
          "tgn:7007708",
          "tgn:7029392"
        ],
        "placetype": [
          "aat:300132316"
        ],
        "id": 2786211,
        "name:xx": "Youngs Bay"
      }
    },
    {
      "geometry": {
        "type": "Point",
        "coordinates": [
          -123.3167,
          43.2
        ]
      },
      "type": "Feature",
      "properties": {
        "hierarchy": [
          "tgn:2786212",
          "tgn:1000001",
          "tgn:7012149",
          "tgn:2001706",
          "tgn:7007708",
          "tgn:7029392"
        ],
        "placetype": [
          "aat:300006191"
        ],
        "id": 2786212,
        "name:xx": "Youngs Bay Log Pond"
      }
    },
    {
      "geometry": {
        "type": "Point",
        "coordinates": [
          -93.1833,
          31.7
        ]
      },
      "type": "Feature",
      "properties": {
        "hierarchy": [
          "tgn:2786213",
          "tgn:1000001",
          "tgn:7012149",
          "tgn:2000888",
          "tgn:7007256",
          "tgn:7029392"
        ],
        "placetype": [
          "aat:300008699"
        ],
        "id": 2786213,
        "name:xx": "Youngs Bayou"
      }
    },
    {
      "geometry": {
        "type": "Point",
        "coordinates": [
          -92.0833,
          32.5
        ]
      },
      "type": "Feature",
      "properties": {
        "hierarchy": [
          "tgn:2786214",
          "tgn:1000001",
          "tgn:7012149",
          "tgn:2000890",
          "tgn:7007256",
          "tgn:7029392"
        ],
        "placetype": [
          "aat:300008699"
        ],
        "id": 2786214,
        "name:xx": "Youngs Bayou"
      }
    },
    {
      "geometry": {
        "type": "Point",
        "coordinates": [
          -82.7167,
          37.9
        ]
      },
      "type": "Feature",
      "properties": {
        "hierarchy": [
          "tgn:2786215",
          "tgn:1000001",
          "tgn:7012149",
          "tgn:7007255",
          "tgn:7029392"
        ],
        "placetype": [
          "aat:300008699"
        ],
        "id": 2786215,
        "name:xx": "Youngs Branch"
      }
    },
    {
      "geometry": {
        "type": "Point",
        "coordinates": [
          -78.85,
          35.3667
        ]
      },
      "type": "Feature",
      "properties": {
        "hierarchy": [
          "tgn:2786216",
          "tgn:1000001",
          "tgn:7012149",
          "tgn:2001502",
          "tgn:7007709",
          "tgn:7029392"
        ],
        "placetype": [
          "aat:300008699"
        ],
        "id": 2786216,
        "name:xx": "Youngs Branch"
      }
    },
    {
      "geometry": {
        "type": "Point",
        "coordinates": [
          -82.6667,
          38.7167
        ]
      },
      "type": "Feature",
      "properties": {
        "hierarchy": [
          "tgn:2786217",
          "tgn:1000001",
          "tgn:7012149",
          "tgn:7007706",
          "tgn:7029392"
        ],
        "placetype": [
          "aat:300008699"
        ],
        "id": 2786217,
        "name:xx": "Youngs Branch"
      }
    },
    {
      "geometry": {
        "type": "Point",
        "coordinates": [
          -82.7833,
          34.9333
        ]
      },
      "type": "Feature",
      "properties": {
        "hierarchy": [
          "tgn:2786218",
          "tgn:1000001",
          "tgn:7012149",
          "tgn:2001763",
          "tgn:7007712",
          "tgn:7029392"
        ],
        "placetype": [
          "aat:300008699"
        ],
        "id": 2786218,
        "name:xx": "Youngs Branch"
      }
    },
    {
      "geometry": {
        "type": "Point",
        "coordinates": [
          -97.1167,
          29.6333
        ]
      },
      "type": "Feature",
      "properties": {
        "hierarchy": [
          "tgn:2786219",
          "tgn:1000001",
          "tgn:7012149",
          "tgn:7007826",
          "tgn:7029392"
        ],
        "placetype": [
          "aat:300008699"
        ],
        "id": 2786219,
        "name:xx": "Youngs Branch"
      }
    }
  ]
}
