{
  "geometry": {
    "type": "Point",
    "coordinates": [
      -119.8167,
      38.1833
    ]
  },
  "type": "Feature",
  "properties": {
    "hierarchy": [
      "tgn:2359008",
      "tgn:1000001",
      "tgn:7012149",
      "tgn:7007157",
      "tgn:1002957",
      "tgn:7029392"
    ],
    "placetype": [
      "aat:300008680"
    ],
    "id": 2359008,
    "name:xx": "Granite Lake"
  }
}
