{
  "geometry": {
    "type": "Point",
    "coordinates": [
      77.960097,
      25.512393
    ]
  },
  "type": "Feature",
  "properties": {
    "hierarchy": [
      "tgn:7546049",
      "tgn:1000004",
      "tgn:7000198",
      "tgn:1001894",
      "tgn:7029392"
    ],
    "placetype": [
      "aat:300008347"
    ],
    "name:en": "Amoi Pathā",
    "id": 7546049
  }
}
