{
  "geometry": {
    "type": "Point",
    "coordinates": [
      -119.1167,
      48.9833
    ]
  },
  "type": "Feature",
  "properties": {
    "hierarchy": [
      "tgn:2546731",
      "tgn:1000001",
      "tgn:7012149",
      "tgn:1002742",
      "tgn:7007920",
      "tgn:7029392"
    ],
    "placetype": [
      "aat:300008706"
    ],
    "id": 2546731,
    "name:xx": "North Fork Mary Ann Creek"
  }
}
