{
  "geometry": {
    "type": "Point",
    "coordinates": [
      -116.3667,
      35.6833
    ]
  },
  "type": "Feature",
  "properties": {
    "hierarchy": [
      "tgn:2409026",
      "tgn:1000001",
      "tgn:7012149",
      "tgn:7007157",
      "tgn:1002857",
      "tgn:7029392"
    ],
    "placetype": [
      "aat:300008798"
    ],
    "id": 2409026,
    "name:xx": "Ibex Dunes"
  }
}
