{
  "geometry": {
    "type": "Point",
    "coordinates": [
      -82.8167,
      41.65
    ]
  },
  "type": "Feature",
  "properties": {
    "hierarchy": [
      "tgn:2349286",
      "tgn:1000001",
      "tgn:7012149",
      "tgn:1002761",
      "tgn:7007706",
      "tgn:7029392"
    ],
    "placetype": [
      "aat:300008791"
    ],
    "id": 2349286,
    "name:xx": "Gilbraltar Island"
  }
}
