{
  "geometry": {
    "type": "Point",
    "coordinates": [
      -112.05,
      40.6833
    ]
  },
  "type": "Feature",
  "properties": {
    "hierarchy": [
      "tgn:2255967",
      "tgn:1000001",
      "tgn:7012149",
      "tgn:2002118",
      "tgn:7007827",
      "tgn:7029392"
    ],
    "placetype": [
      "aat:300008347"
    ],
    "id": 2255967,
    "name:xx": "Copper Hill Heights Eleven"
  }
}
