{
  "geometry": {
    "type": "Point",
    "coordinates": [
      -84.25,
      40.25
    ]
  },
  "type": "Feature",
  "properties": {
    "hierarchy": [
      "tgn:2734318",
      "tgn:1000001",
      "tgn:7012149",
      "tgn:1002889",
      "tgn:7007706",
      "tgn:7029392"
    ],
    "placetype": [
      "aat:300008706"
    ],
    "id": 2734318,
    "name:xx": "Turtle Creek"
  }
}
