{
  "type": "FeatureCollection",
  "features": [
    {
      "geometry": {
        "type": "Point",
        "coordinates": [
          -89,
          14
        ]
      },
      "type": "Feature",
      "properties": {
        "hierarchy": [
          "tgn:1119580",
          "tgn:1000001",
          "tgn:7029392"
        ],
        "placetype": [
          "aat:300006191"
        ],
        "id": 1119580,
        "name:xx": "Cerrón Grande"
      }
    },
    {
      "geometry": {
        "type": "Point",
        "coordinates": [
          -68.7,
          -38.5333
        ]
      },
      "type": "Feature",
      "properties": {
        "hierarchy": [
          "tgn:1119581",
          "tgn:7006477",
          "tgn:1001450",
          "tgn:1000002",
          "tgn:7029392"
        ],
        "placetype": [
          "aat:300006191"
        ],
        "id": 1119581,
        "name:xx": "Cerros Colorados, Embalse"
      }
    },
    {
      "geometry": {
        "type": "Point",
        "coordinates": [
          127.5,
          37.6667
        ]
      },
      "type": "Feature",
      "properties": {
        "hierarchy": [
          "tgn:1119582",
          "tgn:1000004",
          "tgn:7000299",
          "tgn:7029392"
        ],
        "placetype": [
          "aat:300006191"
        ],
        "id": 1119582,
        "name:xx": "Chŏngp'yŏng-chŏsuji"
      }
    },
    {
      "geometry": {
        "type": "Point",
        "coordinates": [
          1.6167,
          46.45
        ]
      },
      "type": "Feature",
      "properties": {
        "hierarchy": [
          "tgn:1119583",
          "tgn:1000003",
          "tgn:7002877",
          "tgn:1000070",
          "tgn:7029392"
        ],
        "placetype": [
          "aat:300006191"
        ],
        "id": 1119583,
        "name:xx": "Chambon, Lac"
      }
    },
    {
      "geometry": {
        "type": "Point",
        "coordinates": [
          104.6667,
          29.7
        ]
      },
      "type": "Feature",
      "properties": {
        "hierarchy": [
          "tgn:1119584",
          "tgn:1000004",
          "tgn:7002087",
          "tgn:1000111",
          "tgn:7029392"
        ],
        "placetype": [
          "aat:300006191"
        ],
        "id": 1119584,
        "name:xx": "Changshaba Shuiku"
      }
    },
    {
      "geometry": {
        "type": "Point",
        "coordinates": [
          88,
          68
        ]
      },
      "type": "Feature",
      "properties": {
        "hierarchy": [
          "tgn:1119585",
          "tgn:1000004",
          "tgn:7017024",
          "tgn:7018214",
          "tgn:7002435",
          "tgn:7029392"
        ],
        "placetype": [
          "aat:300006191"
        ],
        "id": 1119585,
        "name:xx": "Khantayskoye Vodokhranilishche"
      }
    },
    {
      "geometry": {
        "type": "Point",
        "coordinates": [
          -121.8167,
          47.9333
        ]
      },
      "type": "Feature",
      "properties": {
        "hierarchy": [
          "tgn:1119586",
          "tgn:1000001",
          "tgn:7012149",
          "tgn:1002899",
          "tgn:7007920",
          "tgn:7029392"
        ],
        "placetype": [
          "aat:300006191"
        ],
        "id": 1119586,
        "name:xx": "Chaplain, Lake"
      }
    },
    {
      "geometry": {
        "type": "Point",
        "coordinates": [
          -118.6167,
          34.2167
        ]
      },
      "type": "Feature",
      "properties": {
        "hierarchy": [
          "tgn:1119589",
          "tgn:1000001",
          "tgn:7012149",
          "tgn:7007157",
          "tgn:1002608",
          "tgn:7029392"
        ],
        "placetype": [
          "aat:300006191"
        ],
        "id": 1119589,
        "name:xx": "Chatsworth Reservoir"
      }
    }
  ]
}
