{
  "geometry": {
    "type": "Point",
    "coordinates": [
      -82.9333,
      37.0833
    ]
  },
  "type": "Feature",
  "properties": {
    "hierarchy": [
      "tgn:2564366",
      "tgn:1000001",
      "tgn:7012149",
      "tgn:2000812",
      "tgn:7007255",
      "tgn:7029392"
    ],
    "placetype": [
      "aat:300008699"
    ],
    "id": 2564366,
    "name:xx": "Pacies Branch"
  }
}
