{
  "geometry": {
    "type": "Point",
    "coordinates": [
      -80.4167,
      25.7167
    ]
  },
  "type": "Feature",
  "properties": {
    "hierarchy": [
      "tgn:2548292",
      "tgn:1000001",
      "tgn:7012149",
      "tgn:1002314",
      "tgn:7007240",
      "tgn:7029392"
    ],
    "placetype": [
      "aat:300008680"
    ],
    "id": 2548292,
    "name:xx": "North Lake"
  }
}
