{
  "geometry": {
    "type": "Point",
    "coordinates": [
      32.25,
      48.7833
    ]
  },
  "type": "Feature",
  "properties": {
    "hierarchy": [
      "tgn:1058492",
      "tgn:1000003",
      "tgn:7011662",
      "tgn:7006660",
      "tgn:7029392"
    ],
    "placetype": [
      "aat:300008347"
    ],
    "id": 1058492,
    "name:xx": "Pidlisne"
  }
}
