{
  "geometry": {
    "type": "Point",
    "coordinates": [
      -84.3833,
      31.3333
    ]
  },
  "type": "Feature",
  "properties": {
    "hierarchy": [
      "tgn:2150500",
      "tgn:2000295",
      "tgn:1000001",
      "tgn:7012149",
      "tgn:7007248",
      "tgn:7029392"
    ],
    "placetype": [
      "aat:300008680"
    ],
    "id": 2150500,
    "name:xx": "Basin Pond"
  }
}
