{
  "geometry": {
    "type": "Point",
    "coordinates": [
      -8.94,
      19.011
    ]
  },
  "type": "Feature",
  "properties": {
    "hierarchy": [
      "tgn:7593398",
      "tgn:7005395",
      "tgn:1000001",
      "tgn:7005388",
      "tgn:7029392"
    ],
    "placetype": [
      "aat:300008679"
    ],
    "id": 7593398,
    "name:xx": "Redonda, Laguna"
  }
}
