{
  "geometry": {
    "type": "Point",
    "coordinates": [
      -117.25,
      46.4833
    ]
  },
  "type": "Feature",
  "properties": {
    "hierarchy": [
      "tgn:2242367",
      "tgn:1000001",
      "tgn:2002245",
      "tgn:7012149",
      "tgn:7007920",
      "tgn:7029392"
    ],
    "placetype": [
      "aat:300008761"
    ],
    "id": 2242367,
    "name:xx": "Clayton Gulch"
  }
}
