{
  "geometry": {
    "type": "Point",
    "coordinates": [
      -123.6833,
      41.1833
    ]
  },
  "type": "Feature",
  "properties": {
    "hierarchy": [
      "tgn:2637805",
      "tgn:1000001",
      "tgn:7012149",
      "tgn:2000181",
      "tgn:7007157",
      "tgn:7029392"
    ],
    "placetype": [
      "aat:300008706"
    ],
    "id": 2637805,
    "name:xx": "Saints Rest Creek"
  }
}
