{
  "geometry": {
    "type": "Point",
    "coordinates": [
      -83.4833,
      34.4833
    ]
  },
  "type": "Feature",
  "properties": {
    "hierarchy": [
      "tgn:2634365",
      "tgn:1000001",
      "tgn:7012149",
      "tgn:7007248",
      "tgn:7029392"
    ],
    "placetype": [
      "aat:300006191"
    ],
    "id": 2634365,
    "name:xx": "Russell, Lake"
  }
}
