{
  "type": "FeatureCollection",
  "features": [
    {
      "geometry": {
        "type": "Point",
        "coordinates": [
          -107.3,
          28.766667
        ]
      },
      "type": "Feature",
      "properties": {
        "hierarchy": [
          "tgn:7378230",
          "tgn:7005581",
          "tgn:1000001",
          "tgn:7005560",
          "tgn:7029392"
        ],
        "placetype": [
          "aat:300008347"
        ],
        "id": 7378230,
        "name:xx": "La Virgen"
      }
    },
    {
      "geometry": {
        "type": "Point",
        "coordinates": [
          -103.366667,
          25.933333
        ]
      },
      "type": "Feature",
      "properties": {
        "hierarchy": [
          "tgn:7378231",
          "tgn:1001853",
          "tgn:1000001",
          "tgn:7005560",
          "tgn:7029392"
        ],
        "placetype": [
          "aat:300008347"
        ],
        "id": 7378231,
        "name:xx": "La Virgen"
      }
    },
    {
      "geometry": {
        "type": "Point",
        "coordinates": [
          -107.833333,
          25.716667
        ]
      },
      "type": "Feature",
      "properties": {
        "hierarchy": [
          "tgn:7378232",
          "tgn:1000001",
          "tgn:7005595",
          "tgn:7005560",
          "tgn:7029392"
        ],
        "placetype": [
          "aat:300008347"
        ],
        "id": 7378232,
        "name:xx": "La Virgen"
      }
    },
    {
      "geometry": {
        "type": "Point",
        "coordinates": [
          -106.625278,
          24.373056
        ]
      },
      "type": "Feature",
      "properties": {
        "hierarchy": [
          "tgn:7378233",
          "tgn:1000001",
          "tgn:7005595",
          "tgn:7005560",
          "tgn:7029392"
        ],
        "placetype": [
          "aat:300008347"
        ],
        "id": 7378233,
        "name:xx": "Las Cruces"
      }
    },
    {
      "geometry": {
        "type": "Point",
        "coordinates": [
          -99,
          23.45
        ]
      },
      "type": "Feature",
      "properties": {
        "hierarchy": [
          "tgn:7378234",
          "tgn:1000001",
          "tgn:7005597",
          "tgn:7005560",
          "tgn:7029392"
        ],
        "placetype": [
          "aat:300008347"
        ],
        "id": 7378234,
        "name:xx": "Las Cruces"
      }
    },
    {
      "geometry": {
        "type": "Point",
        "coordinates": [
          -105.966667,
          23.3
        ]
      },
      "type": "Feature",
      "properties": {
        "hierarchy": [
          "tgn:7378235",
          "tgn:1000001",
          "tgn:7005595",
          "tgn:7005560",
          "tgn:7029392"
        ],
        "placetype": [
          "aat:300008347"
        ],
        "id": 7378235,
        "name:xx": "Las Cruces"
      }
    },
    {
      "geometry": {
        "type": "Point",
        "coordinates": [
          -99.683333,
          22.766667
        ]
      },
      "type": "Feature",
      "properties": {
        "hierarchy": [
          "tgn:7378236",
          "tgn:1000001",
          "tgn:7005597",
          "tgn:7005560",
          "tgn:7029392"
        ],
        "placetype": [
          "aat:300008347"
        ],
        "id": 7378236,
        "name:xx": "Las Cruces"
      }
    },
    {
      "geometry": {
        "type": "Point",
        "coordinates": [
          -103.116667,
          21.033333
        ]
      },
      "type": "Feature",
      "properties": {
        "hierarchy": [
          "tgn:7378237",
          "tgn:1000001",
          "tgn:7005601",
          "tgn:7005560",
          "tgn:7029392"
        ],
        "placetype": [
          "aat:300008347"
        ],
        "id": 7378237,
        "name:xx": "Las Cruces"
      }
    },
    {
      "geometry": {
        "type": "Point",
        "coordinates": [
          -102.15,
          20.616667
        ]
      },
      "type": "Feature",
      "properties": {
        "hierarchy": [
          "tgn:7378238",
          "tgn:7005586",
          "tgn:1000001",
          "tgn:7005560",
          "tgn:7029392"
        ],
        "placetype": [
          "aat:300008347"
        ],
        "id": 7378238,
        "name:xx": "Las Cruces"
      }
    }
  ]
}
