{
  "geometry": {
    "type": "Point",
    "coordinates": [
      -96.3833,
      28.6833
    ]
  },
  "type": "Feature",
  "properties": {
    "hierarchy": [
      "tgn:2103115",
      "tgn:1000001",
      "tgn:7012149",
      "tgn:1002510",
      "tgn:7007826",
      "tgn:7029392"
    ],
    "placetype": [
      "aat:300008347",
      "aat:300387210"
    ],
    "id": 2103115,
    "name:xx": "Carancahua"
  }
}
