{
  "geometry": {
    "type": "Point",
    "coordinates": [
      -109.7167,
      37.9667
    ]
  },
  "type": "Feature",
  "properties": {
    "hierarchy": [
      "tgn:2226416",
      "tgn:1000001",
      "tgn:7012149",
      "tgn:2002119",
      "tgn:7007827",
      "tgn:7029392"
    ],
    "placetype": [
      "aat:300008850"
    ],
    "id": 2226416,
    "name:xx": "Cathedral Point"
  }
}
