{
  "geometry": {
    "type": "Point",
    "coordinates": [
      -99.05,
      38.0333
    ]
  },
  "type": "Feature",
  "properties": {
    "hierarchy": [
      "tgn:2404421",
      "tgn:1000001",
      "tgn:7012149",
      "tgn:2000732",
      "tgn:7007254",
      "tgn:7029392"
    ],
    "placetype": [
      "aat:300008706"
    ],
    "id": 2404421,
    "name:xx": "Hubbard Creek"
  }
}
