{
  "geometry": {
    "type": "Point",
    "coordinates": [
      -108.25,
      38.15
    ]
  },
  "type": "Feature",
  "properties": {
    "hierarchy": [
      "tgn:2538055",
      "tgn:1000001",
      "tgn:7012149",
      "tgn:7007158",
      "tgn:7029392"
    ],
    "placetype": [
      "aat:300006075"
    ],
    "id": 2538055,
    "name:xx": "Nelson Ditch"
  }
}
