{
  "geometry": {
    "type": "Point",
    "coordinates": [
      -110.0167,
      42.8333
    ]
  },
  "type": "Feature",
  "properties": {
    "hierarchy": [
      "tgn:2723566",
      "tgn:1000001",
      "tgn:7012149",
      "tgn:2002382",
      "tgn:7007923",
      "tgn:7029392"
    ],
    "placetype": [
      "aat:300006075"
    ],
    "id": 2723566,
    "name:xx": "Todd Ditch"
  }
}
