{
  "geometry": {
    "type": "Point",
    "coordinates": [
      -112.3333,
      34.1667
    ]
  },
  "type": "Feature",
  "properties": {
    "hierarchy": [
      "tgn:2495595",
      "tgn:1000001",
      "tgn:7006451",
      "tgn:7012149",
      "tgn:2000103",
      "tgn:7029392"
    ],
    "placetype": [
      "aat:300000390"
    ],
    "id": 2495595,
    "name:xx": "Mascot Mine"
  }
}
