{
  "geometry": {
    "type": "Point",
    "coordinates": [
      64.8333,
      29.1667
    ]
  },
  "type": "Feature",
  "properties": {
    "hierarchy": [
      "tgn:7002250",
      "tgn:1000004",
      "tgn:7029392"
    ],
    "placetype": [
      "aat:300008707"
    ],
    "id": 7002250,
    "name:xx": "Lowṟah"
  }
}
