{
  "geometry": {
    "type": "Point",
    "coordinates": [
      -93.3667,
      43.2667
    ]
  },
  "type": "Feature",
  "properties": {
    "hierarchy": [
      "tgn:2034900",
      "tgn:1000001",
      "tgn:7012149",
      "tgn:2000658",
      "tgn:7007253",
      "tgn:7029392"
    ],
    "placetype": [
      "aat:300008347"
    ],
    "id": 2034900,
    "name:xx": "Hanlontown"
  }
}
