{
  "geometry": {
    "type": "Point",
    "coordinates": [
      -85.4833,
      36.3333
    ]
  },
  "type": "Feature",
  "properties": {
    "hierarchy": [
      "tgn:2101097",
      "tgn:1000001",
      "tgn:7012149",
      "tgn:2001903",
      "tgn:7007825",
      "tgn:7029392"
    ],
    "placetype": [
      "aat:300008347",
      "aat:300387210"
    ],
    "id": 2101097,
    "name:xx": "Poplar Springs"
  }
}
