{
  "geometry": {
    "type": "Point",
    "coordinates": [
      19.0167,
      47.4167
    ]
  },
  "type": "Feature",
  "properties": {
    "hierarchy": [
      "tgn:1004187",
      "tgn:7010547",
      "tgn:7006280",
      "tgn:7017994",
      "tgn:1000003",
      "tgn:7006278",
      "tgn:7029392"
    ],
    "placetype": [
      "aat:300000745"
    ],
    "id": 1004187,
    "name:xx": "Budatétény"
  }
}
