{
  "geometry": {
    "type": "Point",
    "coordinates": [
      -79.8833,
      36.15
    ]
  },
  "type": "Feature",
  "properties": {
    "hierarchy": [
      "tgn:2667063",
      "tgn:1000001",
      "tgn:7012149",
      "tgn:2001500",
      "tgn:7007709",
      "tgn:7029392"
    ],
    "placetype": [
      "aat:300006191"
    ],
    "id": 2667063,
    "name:xx": "Ski Lake"
  }
}
