{
  "geometry": {
    "type": "Point",
    "coordinates": [
      -118.6167,
      39.7167
    ]
  },
  "type": "Feature",
  "properties": {
    "hierarchy": [
      "tgn:2188646",
      "tgn:1000001",
      "tgn:2001409",
      "tgn:7012149",
      "tgn:7007526",
      "tgn:7029392"
    ],
    "placetype": [
      "aat:300132316"
    ],
    "id": 2188646,
    "name:xx": "Botulism Bay"
  }
}
