{
  "geometry": {
    "type": "Point",
    "coordinates": [
      -70.8833,
      42.6667
    ]
  },
  "type": "Feature",
  "properties": {
    "hierarchy": [
      "tgn:2149824",
      "tgn:1000001",
      "tgn:1002359",
      "tgn:7012149",
      "tgn:7007517",
      "tgn:7029392"
    ],
    "placetype": [
      "aat:300008798"
    ],
    "id": 2149824,
    "name:xx": "Bartholomew Hill"
  }
}
