{
  "type": "FeatureCollection",
  "features": [
    {
      "geometry": {
        "type": "Point",
        "coordinates": [
          4.813541,
          50.62426
        ]
      },
      "type": "Feature",
      "properties": {
        "hierarchy": [
          "tgn:7250860",
          "tgn:7018238",
          "tgn:1000003",
          "tgn:1000063",
          "tgn:4012014",
          "tgn:7029392"
        ],
        "placetype": [
          "aat:300008347"
        ],
        "id": 7250860,
        "name:xx": "Perwez"
      }
    },
    {
      "geometry": {
        "type": "Point",
        "coordinates": [
          5.172931,
          50.453429
        ]
      },
      "type": "Feature",
      "properties": {
        "hierarchy": [
          "tgn:7250861",
          "tgn:7003466",
          "tgn:1000003",
          "tgn:1000063",
          "tgn:4012014",
          "tgn:7029392"
        ],
        "placetype": [
          "aat:300008347"
        ],
        "id": 7250861,
        "name:xx": "Perwez"
      }
    },
    {
      "geometry": {
        "type": "Point",
        "coordinates": [
          5.733333,
          49.583333
        ]
      },
      "type": "Feature",
      "properties": {
        "hierarchy": [
          "tgn:7250868",
          "tgn:7003465",
          "tgn:1000003",
          "tgn:1000063",
          "tgn:4012014",
          "tgn:7029392"
        ],
        "placetype": [
          "aat:300008863"
        ],
        "id": 7250868,
        "name:xx": "Pertot, Bois"
      }
    },
    {
      "geometry": {
        "type": "Point",
        "coordinates": [
          4.583333,
          51.183333
        ]
      },
      "type": "Feature",
      "properties": {
        "hierarchy": [
          "tgn:7250869",
          "tgn:7003456",
          "tgn:1000003",
          "tgn:1000063",
          "tgn:7018236",
          "tgn:7029392"
        ],
        "placetype": [
          "aat:300008347"
        ],
        "id": 7250869,
        "name:xx": "Pertendonk"
      }
    }
  ]
}
