{
  "geometry": {
    "type": "Point",
    "coordinates": [
      174.95,
      -39.75
    ]
  },
  "type": "Feature",
  "properties": {
    "hierarchy": [
      "tgn:7504411",
      "tgn:1008380",
      "tgn:7520093",
      "tgn:1000226",
      "tgn:1000006",
      "tgn:7029392"
    ],
    "placetype": [
      "aat:300008347"
    ],
    "name:en": "Waitahinga",
    "id": 7504411
  }
}
