{
  "geometry": {
    "type": "Point",
    "coordinates": [
      -86.2667,
      41.4667
    ]
  },
  "type": "Feature",
  "properties": {
    "hierarchy": [
      "tgn:2444815",
      "tgn:1000001",
      "tgn:7012149",
      "tgn:1002640",
      "tgn:7007252",
      "tgn:7029392"
    ],
    "placetype": [
      "aat:300006075"
    ],
    "id": 2444815,
    "name:xx": "Lehman Ditch"
  }
}
