{
  "type": "FeatureCollection",
  "features": [
    {
      "geometry": {
        "type": "Point",
        "coordinates": [
          -86.15,
          31.4
        ]
      },
      "type": "Feature",
      "properties": {
        "hierarchy": [
          "tgn:2523150",
          "tgn:7002659",
          "tgn:1000001",
          "tgn:2000015",
          "tgn:7012149",
          "tgn:7029392"
        ],
        "placetype": [
          "aat:300008706"
        ],
        "id": 2523150,
        "name:xx": "Moores Creek"
      }
    },
    {
      "geometry": {
        "type": "Point",
        "coordinates": [
          -85.2833,
          32.8667
        ]
      },
      "type": "Feature",
      "properties": {
        "hierarchy": [
          "tgn:2523151",
          "tgn:7002659",
          "tgn:1000001",
          "tgn:2000008",
          "tgn:7012149",
          "tgn:7029392"
        ],
        "placetype": [
          "aat:300008706"
        ],
        "id": 2523151,
        "name:xx": "Moores Creek"
      }
    },
    {
      "geometry": {
        "type": "Point",
        "coordinates": [
          -93.8667,
          35.4333
        ]
      },
      "type": "Feature",
      "properties": {
        "hierarchy": [
          "tgn:2523152",
          "tgn:1000001",
          "tgn:7016172",
          "tgn:7012149",
          "tgn:7029392"
        ],
        "placetype": [
          "aat:300008706"
        ],
        "id": 2523152,
        "name:xx": "Moores Creek"
      }
    },
    {
      "geometry": {
        "type": "Point",
        "coordinates": [
          -93.3667,
          34.0667
        ]
      },
      "type": "Feature",
      "properties": {
        "hierarchy": [
          "tgn:2523153",
          "tgn:1000001",
          "tgn:7016172",
          "tgn:2000114",
          "tgn:7012149",
          "tgn:7029392"
        ],
        "placetype": [
          "aat:300008706"
        ],
        "id": 2523153,
        "name:xx": "Moores Creek"
      }
    },
    {
      "geometry": {
        "type": "Point",
        "coordinates": [
          -94.4,
          35.9167
        ]
      },
      "type": "Feature",
      "properties": {
        "hierarchy": [
          "tgn:2523154",
          "tgn:1000001",
          "tgn:7016172",
          "tgn:7012149",
          "tgn:2000176",
          "tgn:7029392"
        ],
        "placetype": [
          "aat:300008706"
        ],
        "id": 2523154,
        "name:xx": "Moores Creek"
      }
    },
    {
      "geometry": {
        "type": "Point",
        "coordinates": [
          -83.0167,
          33.4833
        ]
      },
      "type": "Feature",
      "properties": {
        "hierarchy": [
          "tgn:2523155",
          "tgn:1000001",
          "tgn:7012149",
          "tgn:2000357",
          "tgn:7007248",
          "tgn:7029392"
        ],
        "placetype": [
          "aat:300008706"
        ],
        "id": 2523155,
        "name:xx": "Moores Creek"
      }
    },
    {
      "geometry": {
        "type": "Point",
        "coordinates": [
          -116.65,
          43.1167
        ]
      },
      "type": "Feature",
      "properties": {
        "hierarchy": [
          "tgn:2523156",
          "tgn:1000001",
          "tgn:7012149",
          "tgn:2000488",
          "tgn:7007250",
          "tgn:7029392"
        ],
        "placetype": [
          "aat:300008706"
        ],
        "id": 2523156,
        "name:xx": "Moores Creek"
      }
    },
    {
      "geometry": {
        "type": "Point",
        "coordinates": [
          -115.1333,
          43.3667
        ]
      },
      "type": "Feature",
      "properties": {
        "hierarchy": [
          "tgn:2523157",
          "tgn:1000001",
          "tgn:7012149",
          "tgn:2000471",
          "tgn:7007250",
          "tgn:7029392"
        ],
        "placetype": [
          "aat:300008706"
        ],
        "id": 2523157,
        "name:xx": "Moores Creek"
      }
    },
    {
      "geometry": {
        "type": "Point",
        "coordinates": [
          -116.1,
          44.45
        ]
      },
      "type": "Feature",
      "properties": {
        "hierarchy": [
          "tgn:2523158",
          "tgn:1000001",
          "tgn:7012149",
          "tgn:2000494",
          "tgn:7007250",
          "tgn:7029392"
        ],
        "placetype": [
          "aat:300008706"
        ],
        "id": 2523158,
        "name:xx": "Moores Creek"
      }
    },
    {
      "geometry": {
        "type": "Point",
        "coordinates": [
          -115.8833,
          45.6
        ]
      },
      "type": "Feature",
      "properties": {
        "hierarchy": [
          "tgn:2523159",
          "tgn:1000001",
          "tgn:7012149",
          "tgn:2000476",
          "tgn:7007250",
          "tgn:7029392"
        ],
        "placetype": [
          "aat:300008706"
        ],
        "id": 2523159,
        "name:xx": "Moores Creek"
      }
    }
  ]
}
