{
  "geometry": {
    "type": "Point",
    "coordinates": [
      16.6667,
      47.5333
    ]
  },
  "type": "Feature",
  "properties": {
    "hierarchy": [
      "tgn:1025891",
      "tgn:7003023",
      "tgn:1000003",
      "tgn:1000062",
      "tgn:7029392"
    ],
    "placetype": [
      "aat:300008347"
    ],
    "id": 1025891,
    "name:xx": "Nikitsch"
  }
}
