{
  "geometry": {
    "type": "Point",
    "coordinates": [
      -80.1833,
      35.6167
    ]
  },
  "type": "Feature",
  "properties": {
    "hierarchy": [
      "tgn:2390094",
      "tgn:1000001",
      "tgn:7012149",
      "tgn:2001489",
      "tgn:7007709",
      "tgn:7029392"
    ],
    "placetype": [
      "aat:300008347"
    ],
    "id": 2390094,
    "name:xx": "High Rock Mountain Shores"
  }
}
