{
  "geometry": {
    "type": "Point",
    "coordinates": [
      -82.3667,
      35.7667
    ]
  },
  "type": "Feature",
  "properties": {
    "hierarchy": [
      "tgn:2726410",
      "tgn:1000001",
      "tgn:2001473",
      "tgn:7012149",
      "tgn:7007709",
      "tgn:7029392"
    ],
    "placetype": [
      "aat:300008699"
    ],
    "id": 2726410,
    "name:xx": "Town Branch"
  }
}
