{
  "type": "FeatureCollection",
  "features": [
    {
      "geometry": {
        "type": "Point",
        "coordinates": [
          -94.25,
          44.3
        ]
      },
      "type": "Feature",
      "properties": {
        "hierarchy": [
          "tgn:2196820",
          "tgn:1000001",
          "tgn:7012149",
          "tgn:2001050",
          "tgn:7007521",
          "tgn:7029392"
        ],
        "placetype": [
          "aat:300008791"
        ],
        "id": 2196820,
        "name:xx": "Brooks Island"
      }
    },
    {
      "geometry": {
        "type": "Point",
        "coordinates": [
          -83.1167,
          36.5333
        ]
      },
      "type": "Feature",
      "properties": {
        "hierarchy": [
          "tgn:2196821",
          "tgn:1000001",
          "tgn:7012149",
          "tgn:2001870",
          "tgn:7007825",
          "tgn:7029392"
        ],
        "placetype": [
          "aat:300008791"
        ],
        "id": 2196821,
        "name:xx": "Brooks Island"
      }
    },
    {
      "geometry": {
        "type": "Point",
        "coordinates": [
          -85.6833,
          36.3667
        ]
      },
      "type": "Feature",
      "properties": {
        "hierarchy": [
          "tgn:2196822",
          "tgn:1000001",
          "tgn:7012149",
          "tgn:2001880",
          "tgn:7007825",
          "tgn:7029392"
        ],
        "placetype": [
          "aat:300008791"
        ],
        "id": 2196822,
        "name:xx": "Brooks Island"
      }
    },
    {
      "geometry": {
        "type": "Point",
        "coordinates": [
          -80.9,
          37.7167
        ]
      },
      "type": "Feature",
      "properties": {
        "hierarchy": [
          "tgn:2196823",
          "tgn:1000001",
          "tgn:7012149",
          "tgn:2002290",
          "tgn:7013961",
          "tgn:7029392"
        ],
        "placetype": [
          "aat:300008791"
        ],
        "id": 2196823,
        "name:xx": "Brooks Island"
      }
    },
    {
      "geometry": {
        "type": "Point",
        "coordinates": [
          -86.2,
          37.1833
        ]
      },
      "type": "Feature",
      "properties": {
        "hierarchy": [
          "tgn:2196824",
          "tgn:1000001",
          "tgn:7012149",
          "tgn:2000787",
          "tgn:7007255",
          "tgn:7029392"
        ],
        "placetype": [
          "aat:300008798"
        ],
        "id": 2196824,
        "name:xx": "Brooks Knob"
      }
    },
    {
      "geometry": {
        "type": "Point",
        "coordinates": [
          -81.1667,
          36.4
        ]
      },
      "type": "Feature",
      "properties": {
        "hierarchy": [
          "tgn:2196825",
          "tgn:1000001",
          "tgn:7012149",
          "tgn:2001553",
          "tgn:7007709",
          "tgn:7029392"
        ],
        "placetype": [
          "aat:300008798"
        ],
        "id": 2196825,
        "name:xx": "Brooks Knob"
      }
    },
    {
      "geometry": {
        "type": "Point",
        "coordinates": [
          -106.6833,
          41.9667
        ]
      },
      "type": "Feature",
      "properties": {
        "hierarchy": [
          "tgn:2196826",
          "tgn:1000001",
          "tgn:2002368",
          "tgn:7012149",
          "tgn:7007923",
          "tgn:7029392"
        ],
        "placetype": [
          "aat:300008798"
        ],
        "id": 2196826,
        "name:xx": "Brooks Knob"
      }
    },
    {
      "geometry": {
        "type": "Point",
        "coordinates": [
          -86.0833,
          33.65
        ]
      },
      "type": "Feature",
      "properties": {
        "hierarchy": [
          "tgn:2196827",
          "tgn:7002659",
          "tgn:1000001",
          "tgn:7012149",
          "tgn:2000060",
          "tgn:7029392"
        ],
        "placetype": [
          "aat:300006191"
        ],
        "id": 2196827,
        "name:xx": "Brooks Lake"
      }
    },
    {
      "geometry": {
        "type": "Point",
        "coordinates": [
          -91.15,
          34.1
        ]
      },
      "type": "Feature",
      "properties": {
        "hierarchy": [
          "tgn:2196828",
          "tgn:2000105",
          "tgn:1000001",
          "tgn:7016172",
          "tgn:7012149",
          "tgn:7029392"
        ],
        "placetype": [
          "aat:300008680"
        ],
        "id": 2196828,
        "name:xx": "Brooks Lake"
      }
    },
    {
      "geometry": {
        "type": "Point",
        "coordinates": [
          -81.9167,
          28.8167
        ]
      },
      "type": "Feature",
      "properties": {
        "hierarchy": [
          "tgn:2196829",
          "tgn:1000001",
          "tgn:7012149",
          "tgn:1002567",
          "tgn:7007240",
          "tgn:7029392"
        ],
        "placetype": [
          "aat:300008680"
        ],
        "id": 2196829,
        "name:xx": "Brooks Lake"
      }
    }
  ]
}
