{
  "geometry": {
    "type": "Point",
    "coordinates": [
      -92.8667,
      44.95
    ]
  },
  "type": "Feature",
  "properties": {
    "hierarchy": [
      "tgn:2704049",
      "tgn:1000001",
      "tgn:7012149",
      "tgn:2001080",
      "tgn:7007521",
      "tgn:7029392"
    ],
    "placetype": [
      "aat:300008680"
    ],
    "id": 2704049,
    "name:xx": "Sunfish Lake"
  }
}
