{
  "geometry": {
    "type": "Point",
    "coordinates": [
      -42.7333,
      -2.5667
    ]
  },
  "type": "Feature",
  "properties": {
    "hierarchy": [
      "tgn:1128826",
      "tgn:7006246",
      "tgn:1000047",
      "tgn:7002455",
      "tgn:1000002",
      "tgn:7029392"
    ],
    "placetype": [
      "aat:300008707"
    ],
    "id": 1128826,
    "name:xx": "Preguiças"
  }
}
