{
  "geometry": {
    "type": "Point",
    "coordinates": [
      -93.5167,
      36.2667
    ]
  },
  "type": "Feature",
  "properties": {
    "hierarchy": [
      "tgn:2213025",
      "tgn:1000001",
      "tgn:7016172",
      "tgn:2000112",
      "tgn:7012149",
      "tgn:7029392"
    ],
    "placetype": [
      "aat:300008347"
    ],
    "id": 2213025,
    "name:xx": "Cabanal"
  }
}
