{
  "geometry": {
    "type": "Point",
    "coordinates": [
      113.9833,
      34.45
    ]
  },
  "type": "Feature",
  "properties": {
    "hierarchy": [
      "tgn:1138899",
      "tgn:1000004",
      "tgn:7016672",
      "tgn:1000111",
      "tgn:7029392"
    ],
    "placetype": [
      "aat:300008347"
    ],
    "id": 1138899,
    "name:xx": "Daying"
  }
}
