{
  "geometry": {
    "type": "Point",
    "coordinates": [
      77.627431,
      28.769733
    ]
  },
  "type": "Feature",
  "properties": {
    "hierarchy": [
      "tgn:1075261",
      "tgn:1000004",
      "tgn:7000198",
      "tgn:7016722",
      "tgn:7029392"
    ],
    "placetype": [
      "aat:300008347"
    ],
    "name:en": "Farīdnagar",
    "id": 1075261
  }
}
