{
  "geometry": {
    "type": "Point",
    "coordinates": [
      -121.1833,
      37.1833
    ]
  },
  "type": "Feature",
  "properties": {
    "hierarchy": [
      "tgn:2630282",
      "tgn:1000001",
      "tgn:7012149",
      "tgn:7007157",
      "tgn:1002915",
      "tgn:7029392"
    ],
    "placetype": [
      "aat:300008761"
    ],
    "id": 2630282,
    "name:xx": "Rough Gulch"
  }
}
