{
  "geometry": {
    "type": "Point",
    "coordinates": [
      70.15,
      39.0167
    ]
  },
  "type": "Feature",
  "properties": {
    "hierarchy": [
      "tgn:1138025",
      "tgn:7011627",
      "tgn:1000004",
      "tgn:7014835",
      "tgn:7029392"
    ],
    "placetype": [
      "aat:300008347"
    ],
    "id": 1138025,
    "name:xx": "Novabad"
  }
}
