{
  "geometry": {
    "type": "Point",
    "coordinates": [
      30.916667,
      28.783333
    ]
  },
  "type": "Feature",
  "properties": {
    "hierarchy": [
      "tgn:7520219",
      "tgn:7001242",
      "tgn:7016833",
      "tgn:1001142",
      "tgn:7029392"
    ],
    "placetype": [
      "aat:300008347"
    ],
    "name:en": "Al Ḩībah al Gharbī",
    "id": 7520219
  }
}
