{
  "geometry": {
    "type": "Point",
    "coordinates": [
      -71.6667,
      42.5167
    ]
  },
  "type": "Feature",
  "properties": {
    "hierarchy": [
      "tgn:2189485",
      "tgn:1000001",
      "tgn:7012149",
      "tgn:7007517",
      "tgn:7029392"
    ],
    "placetype": [
      "aat:300008699"
    ],
    "id": 2189485,
    "name:xx": "Bow Brook"
  }
}
