{
  "geometry": {
    "type": "Point",
    "coordinates": [
      15.9167,
      50.5667
    ]
  },
  "type": "Feature",
  "properties": {
    "hierarchy": [
      "tgn:1027602",
      "tgn:7593914",
      "tgn:1000003",
      "tgn:1001780",
      "tgn:7029392"
    ],
    "placetype": [
      "aat:300008347"
    ],
    "id": 1027602,
    "name:xx": "Trutnov"
  }
}
