{
  "geometry": {
    "type": "Point",
    "coordinates": [
      78.833333,
      21.583333
    ]
  },
  "type": "Feature",
  "properties": {
    "hierarchy": [
      "tgn:7577320",
      "tgn:1000004",
      "tgn:7000198",
      "tgn:1001894",
      "tgn:7029392"
    ],
    "placetype": [
      "aat:300008347"
    ],
    "name:en": "Lodhīkhedā",
    "id": 7577320
  }
}
