{
  "geometry": {
    "type": "Point",
    "coordinates": [
      -71.9167,
      44.7833
    ]
  },
  "type": "Feature",
  "properties": {
    "hierarchy": [
      "tgn:2629296",
      "tgn:1000001",
      "tgn:1002361",
      "tgn:7012149",
      "tgn:7007828",
      "tgn:7029392"
    ],
    "placetype": [
      "aat:300008798"
    ],
    "id": 2629296,
    "name:xx": "Rosebrook Hill"
  }
}
