{
  "geometry": {
    "type": "Point",
    "coordinates": [
      -78.4833,
      34.7167
    ]
  },
  "type": "Feature",
  "properties": {
    "hierarchy": [
      "tgn:2263086",
      "tgn:1000001",
      "tgn:2001471",
      "tgn:7012149",
      "tgn:7007709",
      "tgn:7029392"
    ],
    "placetype": [
      "aat:300008905"
    ],
    "id": 2263086,
    "name:xx": "Cowpen Bay"
  }
}
