{
  "geometry": {
    "type": "Point",
    "coordinates": [
      -108.6167,
      31.9667
    ]
  },
  "type": "Feature",
  "properties": {
    "hierarchy": [
      "tgn:2776648",
      "tgn:1000001",
      "tgn:7012149",
      "tgn:2001440",
      "tgn:7007566",
      "tgn:7029392"
    ],
    "placetype": [
      "aat:300008347"
    ],
    "id": 2776648,
    "name:xx": "Windmill"
  }
}
