{
  "geometry": {
    "type": "Point",
    "coordinates": [
      82.412061,
      25.686921
    ]
  },
  "type": "Feature",
  "properties": {
    "hierarchy": [
      "tgn:1076089",
      "tgn:1000004",
      "tgn:7000198",
      "tgn:7016722",
      "tgn:7029392"
    ],
    "placetype": [
      "aat:300008347"
    ],
    "name:en": "Machhlīshahr",
    "id": 1076089
  }
}
