{
  "geometry": {
    "type": "Point",
    "coordinates": [
      -74.25,
      40.3333
    ]
  },
  "type": "Feature",
  "properties": {
    "hierarchy": [
      "tgn:2281267",
      "tgn:1000001",
      "tgn:7012149",
      "tgn:7007565",
      "tgn:7029392"
    ],
    "placetype": [
      "aat:300008699"
    ],
    "id": 2281267,
    "name:xx": "Deep Run"
  }
}
