{
  "geometry": {
    "type": "Point",
    "coordinates": [
      -82.2667,
      36.0833
    ]
  },
  "type": "Feature",
  "properties": {
    "hierarchy": [
      "tgn:2740620",
      "tgn:1000001",
      "tgn:7012149",
      "tgn:2001519",
      "tgn:7007709",
      "tgn:7029392"
    ],
    "placetype": [
      "aat:300008347"
    ],
    "id": 2740620,
    "name:xx": "Upper Pigeonroost"
  }
}
