{
  "geometry": {
    "type": "Point",
    "coordinates": [
      -95.8667,
      29.6333
    ]
  },
  "type": "Feature",
  "properties": {
    "hierarchy": [
      "tgn:2258972",
      "tgn:1000001",
      "tgn:7012149",
      "tgn:1002379",
      "tgn:7007826",
      "tgn:7029392"
    ],
    "placetype": [
      "aat:300008706"
    ],
    "id": 2258972,
    "name:xx": "Cottonwood Creek"
  }
}
