{
  "type": "FeatureCollection",
  "features": [
    {
      "geometry": {
        "type": "Point",
        "coordinates": [
          -48.5167,
          -20.1167
        ]
      },
      "type": "Feature",
      "properties": {
        "hierarchy": [
          "tgn:1131200",
          "tgn:7006237",
          "tgn:1000047",
          "tgn:7002457",
          "tgn:1000002",
          "tgn:7029392"
        ],
        "placetype": [
          "aat:300008707"
        ],
        "id": 1131200,
        "name:xx": "Uberaba"
      }
    },
    {
      "geometry": {
        "type": "Point",
        "coordinates": [
          28.5,
          52.0833
        ]
      },
      "type": "Feature",
      "properties": {
        "hierarchy": [
          "tgn:1131201",
          "tgn:1000003",
          "tgn:7029392"
        ],
        "placetype": [
          "aat:300008707"
        ],
        "id": 1131201,
        "name:be": "Ubort'"
      }
    },
    {
      "geometry": {
        "type": "Point",
        "coordinates": [
          -73.448,
          -4.452
        ]
      },
      "type": "Feature",
      "properties": {
        "hierarchy": [
          "tgn:1131202",
          "tgn:1000675",
          "tgn:1000002",
          "tgn:1000056",
          "tgn:7029392"
        ],
        "placetype": [
          "aat:300008707"
        ],
        "id": 1131202,
        "name:xx": "Uyacali, Río"
      }
    },
    {
      "geometry": {
        "type": "Point",
        "coordinates": [
          11.766667,
          52.8
        ]
      },
      "type": "Feature",
      "properties": {
        "hierarchy": [
          "tgn:1131204",
          "tgn:1000003",
          "tgn:7003687",
          "tgn:7000084",
          "tgn:7029392"
        ],
        "placetype": [
          "aat:300008707",
          "aat:300008699"
        ],
        "id": 1131204,
        "name:xx": "Uchte"
      }
    },
    {
      "geometry": {
        "type": "Point",
        "coordinates": [
          14.066667,
          53.75
        ]
      },
      "type": "Feature",
      "properties": {
        "hierarchy": [
          "tgn:1131207",
          "tgn:1000003",
          "tgn:7000094",
          "tgn:7000084",
          "tgn:7029392"
        ],
        "placetype": [
          "aat:300008707",
          "aat:300008699"
        ],
        "id": 1131207,
        "name:xx": "Uecker"
      }
    }
  ]
}
