{
  "geometry": {
    "type": "Point",
    "coordinates": [
      -80.5833,
      34.3667
    ]
  },
  "type": "Feature",
  "properties": {
    "hierarchy": [
      "tgn:2282976",
      "tgn:1000001",
      "tgn:7012149",
      "tgn:2001752",
      "tgn:7007712",
      "tgn:7029392"
    ],
    "placetype": [
      "aat:300008347"
    ],
    "id": 2282976,
    "name:xx": "Dekalb"
  }
}
