{
  "geometry": {
    "type": "Point",
    "coordinates": [
      -108.6167,
      47.7833
    ]
  },
  "type": "Feature",
  "properties": {
    "hierarchy": [
      "tgn:2273785",
      "tgn:1000001",
      "tgn:7012149",
      "tgn:2001295",
      "tgn:7007524",
      "tgn:7029392"
    ],
    "placetype": [
      "aat:300008347"
    ],
    "id": 2273785,
    "name:xx": "DY Junction"
  }
}
