{
  "geometry": {
    "type": "Point",
    "coordinates": [
      -112.3833,
      34.8167
    ]
  },
  "type": "Feature",
  "properties": {
    "hierarchy": [
      "tgn:2189299",
      "tgn:1000001",
      "tgn:7006451",
      "tgn:7012149",
      "tgn:2000103",
      "tgn:7029392"
    ],
    "placetype": [
      "aat:300006191"
    ],
    "id": 2189299,
    "name:xx": "Boundary Tank"
  }
}
