{
  "geometry": {
    "type": "Point",
    "coordinates": [
      -71.1833,
      41.9167
    ]
  },
  "type": "Feature",
  "properties": {
    "hierarchy": [
      "tgn:2503754",
      "tgn:1002201",
      "tgn:1000001",
      "tgn:7012149",
      "tgn:7007517",
      "tgn:7029392"
    ],
    "placetype": [
      "aat:300008699"
    ],
    "id": 2503754,
    "name:xx": "Meadow Brook"
  }
}
