{
  "geometry": {
    "type": "Point",
    "coordinates": [
      28.6167,
      -27.0333
    ]
  },
  "type": "Feature",
  "properties": {
    "hierarchy": [
      "tgn:1093761",
      "tgn:7001242",
      "tgn:7016562",
      "tgn:1000193",
      "tgn:7029392"
    ],
    "placetype": [
      "aat:300008347"
    ],
    "id": 1093761,
    "name:xx": "Villiers"
  }
}
