{
  "geometry": {
    "type": "Point",
    "coordinates": [
      -119.4333,
      34.4833
    ]
  },
  "type": "Feature",
  "properties": {
    "hierarchy": [
      "tgn:2532419",
      "tgn:1000001",
      "tgn:7012149",
      "tgn:7007157",
      "tgn:1002972",
      "tgn:7029392"
    ],
    "placetype": [
      "aat:300008761"
    ],
    "id": 2532419,
    "name:xx": "Murietta Canyon"
  }
}
