{
  "geometry": {
    "type": "Point",
    "coordinates": [
      -114.2667,
      37.95
    ]
  },
  "type": "Feature",
  "properties": {
    "hierarchy": [
      "tgn:2466919",
      "tgn:1000001",
      "tgn:2001416",
      "tgn:7012149",
      "tgn:7007526",
      "tgn:7029392"
    ],
    "placetype": [
      "aat:300008761"
    ],
    "id": 2466919,
    "name:xx": "Long Canyon"
  }
}
