{
  "geometry": {
    "type": "Point",
    "coordinates": [
      -107.95,
      39.3667
    ]
  },
  "type": "Feature",
  "properties": {
    "hierarchy": [
      "tgn:2296708",
      "tgn:1000001",
      "tgn:7012149",
      "tgn:2000214",
      "tgn:7007158",
      "tgn:7029392"
    ],
    "placetype": [
      "aat:300008706"
    ],
    "id": 2296708,
    "name:xx": "Dry Creek"
  }
}
