{
  "geometry": {
    "type": "Point",
    "coordinates": [
      -117.7167,
      33.9833
    ]
  },
  "type": "Feature",
  "properties": {
    "hierarchy": [
      "tgn:2010347",
      "tgn:1000001",
      "tgn:7012149",
      "tgn:7007157",
      "tgn:1002857",
      "tgn:7029392"
    ],
    "placetype": [
      "aat:300008347"
    ],
    "id": 2010347,
    "name:xx": "Boys Republic"
  }
}
