{
  "geometry": {
    "type": "Point",
    "coordinates": [
      -104.8833,
      35.8167
    ]
  },
  "type": "Feature",
  "properties": {
    "hierarchy": [
      "tgn:2544786",
      "tgn:1000001",
      "tgn:7012149",
      "tgn:2001446",
      "tgn:7007566",
      "tgn:7029392"
    ],
    "placetype": [
      "aat:300006075"
    ],
    "id": 2544786,
    "name:xx": "North Company Ditch"
  }
}
