{
  "geometry": {
    "type": "Point",
    "coordinates": [
      116.3333,
      4.2667
    ]
  },
  "type": "Feature",
  "properties": {
    "hierarchy": [
      "tgn:1078045",
      "tgn:1000004",
      "tgn:1001339",
      "tgn:1000116",
      "tgn:7029392"
    ],
    "placetype": [
      "aat:300008347"
    ],
    "id": 1078045,
    "name:xx": "Lumbis"
  }
}
