{
  "geometry": {
    "type": "Point",
    "coordinates": [
      -97.2833,
      32.3167
    ]
  },
  "type": "Feature",
  "properties": {
    "hierarchy": [
      "tgn:2641566",
      "tgn:1000001",
      "tgn:7012149",
      "tgn:1002526",
      "tgn:7007826",
      "tgn:7029392"
    ],
    "placetype": [
      "aat:300008347"
    ],
    "id": 2641566,
    "name:xx": "Sand Flat"
  }
}
