{
  "geometry": {
    "type": "Point",
    "coordinates": [
      -119.4333,
      41.0833
    ]
  },
  "type": "Feature",
  "properties": {
    "hierarchy": [
      "tgn:2486129",
      "tgn:1000001",
      "tgn:7012149",
      "tgn:1002999",
      "tgn:7007526",
      "tgn:7029392"
    ],
    "placetype": [
      "aat:300008697"
    ],
    "id": 2486129,
    "name:xx": "Leadville Springs"
  }
}
