{
  "geometry": {
    "type": "Point",
    "coordinates": [
      -70.25,
      -29.55
    ]
  },
  "type": "Feature",
  "properties": {
    "hierarchy": [
      "tgn:7282342",
      "tgn:1001630",
      "tgn:1000049",
      "tgn:1000002",
      "tgn:7029392"
    ],
    "placetype": [
      "aat:300008699"
    ],
    "id": 7282342,
    "name:xx": "Primero, Río"
  }
}
