{
  "type": "FeatureCollection",
  "features": [
    {
      "geometry": {
        "type": "Point",
        "coordinates": [
          -98.483333,
          24.5
        ]
      },
      "type": "Feature",
      "properties": {
        "hierarchy": [
          "tgn:7363830",
          "tgn:1000001",
          "tgn:7005597",
          "tgn:7005560",
          "tgn:7029392"
        ],
        "placetype": [
          "aat:300008347"
        ],
        "id": 7363830,
        "name:xx": "El Barranco"
      }
    },
    {
      "geometry": {
        "type": "Point",
        "coordinates": [
          -99.1,
          24.4
        ]
      },
      "type": "Feature",
      "properties": {
        "hierarchy": [
          "tgn:7363831",
          "tgn:1000001",
          "tgn:7005597",
          "tgn:7005560",
          "tgn:7029392"
        ],
        "placetype": [
          "aat:300008347"
        ],
        "id": 7363831,
        "name:xx": "El Barranco Azul"
      }
    },
    {
      "geometry": {
        "type": "Point",
        "coordinates": [
          -103.283333,
          23.25
        ]
      },
      "type": "Feature",
      "properties": {
        "hierarchy": [
          "tgn:7363832",
          "tgn:1000001",
          "tgn:7005601",
          "tgn:7005560",
          "tgn:7029392"
        ],
        "placetype": [
          "aat:300008347"
        ],
        "id": 7363832,
        "name:xx": "El Barranco"
      }
    },
    {
      "geometry": {
        "type": "Point",
        "coordinates": [
          -98.2,
          22.866667
        ]
      },
      "type": "Feature",
      "properties": {
        "hierarchy": [
          "tgn:7363833",
          "tgn:1000001",
          "tgn:7005597",
          "tgn:7005560",
          "tgn:7029392"
        ],
        "placetype": [
          "aat:300008347"
        ],
        "id": 7363833,
        "name:xx": "El Barranco"
      }
    },
    {
      "geometry": {
        "type": "Point",
        "coordinates": [
          -98.583333,
          21.683333
        ]
      },
      "type": "Feature",
      "properties": {
        "hierarchy": [
          "tgn:7363834",
          "tgn:1000001",
          "tgn:7005599",
          "tgn:7005560",
          "tgn:7029392"
        ],
        "placetype": [
          "aat:300008347"
        ],
        "id": 7363834,
        "name:xx": "El Barranco"
      }
    },
    {
      "geometry": {
        "type": "Point",
        "coordinates": [
          -107.066667,
          25.266667
        ]
      },
      "type": "Feature",
      "properties": {
        "hierarchy": [
          "tgn:7363835",
          "tgn:7005583",
          "tgn:1000001",
          "tgn:7005560",
          "tgn:7029392"
        ],
        "placetype": [
          "aat:300008347"
        ],
        "id": 7363835,
        "name:xx": "El Barco"
      }
    },
    {
      "geometry": {
        "type": "Point",
        "coordinates": [
          -97.95,
          22.583333
        ]
      },
      "type": "Feature",
      "properties": {
        "hierarchy": [
          "tgn:7363836",
          "tgn:1000001",
          "tgn:7005597",
          "tgn:7005560",
          "tgn:7029392"
        ],
        "placetype": [
          "aat:300008347"
        ],
        "id": 7363836,
        "name:xx": "El Barco"
      }
    },
    {
      "geometry": {
        "type": "Point",
        "coordinates": [
          -98.033333,
          22.166667
        ]
      },
      "type": "Feature",
      "properties": {
        "hierarchy": [
          "tgn:7363837",
          "tgn:1000001",
          "tgn:7005599",
          "tgn:7005560",
          "tgn:7029392"
        ],
        "placetype": [
          "aat:300008347"
        ],
        "id": 7363837,
        "name:xx": "El Barco"
      }
    },
    {
      "geometry": {
        "type": "Point",
        "coordinates": [
          -98.883333,
          21.166667
        ]
      },
      "type": "Feature",
      "properties": {
        "hierarchy": [
          "tgn:7363838",
          "tgn:7005587",
          "tgn:1000001",
          "tgn:7005560",
          "tgn:7029392"
        ],
        "placetype": [
          "aat:300008347"
        ],
        "id": 7363838,
        "name:xx": "El Barco"
      }
    },
    {
      "geometry": {
        "type": "Point",
        "coordinates": [
          -116.016667,
          32.05
        ]
      },
      "type": "Feature",
      "properties": {
        "hierarchy": [
          "tgn:7363839",
          "tgn:1001835",
          "tgn:1000001",
          "tgn:7005560",
          "tgn:7029392"
        ],
        "placetype": [
          "aat:300008777"
        ],
        "id": 7363839,
        "name:xx": "El Barbón"
      }
    }
  ]
}
