{
  "geometry": {
    "type": "Point",
    "coordinates": [
      -78.6833,
      38.9833
    ]
  },
  "type": "Feature",
  "properties": {
    "hierarchy": [
      "tgn:2185962",
      "tgn:1000001",
      "tgn:7012149",
      "tgn:2002266",
      "tgn:7013961",
      "tgn:7029392"
    ],
    "placetype": [
      "aat:300008798"
    ],
    "id": 2185962,
    "name:xx": "Bollinger Knob"
  }
}
