{
  "type": "FeatureCollection",
  "features": [
    {
      "geometry": {
        "type": "Point",
        "coordinates": [
          -102.5333,
          48.3
        ]
      },
      "type": "Feature",
      "properties": {
        "hierarchy": [
          "tgn:2077980",
          "tgn:1000001",
          "tgn:2001587",
          "tgn:7012149",
          "tgn:7007705",
          "tgn:7029392"
        ],
        "placetype": [
          "aat:300008347"
        ],
        "id": 2077980,
        "name:xx": "Ross"
      }
    },
    {
      "geometry": {
        "type": "Point",
        "coordinates": [
          -100.8,
          48.9
        ]
      },
      "type": "Feature",
      "properties": {
        "hierarchy": [
          "tgn:2077981",
          "tgn:7020393",
          "tgn:1000001",
          "tgn:7012149",
          "tgn:7007705",
          "tgn:7029392"
        ],
        "placetype": [
          "aat:300008347"
        ],
        "id": 2077981,
        "name:xx": "Roth"
      }
    },
    {
      "geometry": {
        "type": "Point",
        "coordinates": [
          -99.9833,
          48.3667
        ]
      },
      "type": "Feature",
      "properties": {
        "hierarchy": [
          "tgn:2077982",
          "tgn:1000001",
          "tgn:2001591",
          "tgn:7012149",
          "tgn:7007705",
          "tgn:7029392"
        ],
        "placetype": [
          "aat:300008347"
        ],
        "id": 2077982,
        "name:xx": "Rugby"
      }
    },
    {
      "geometry": {
        "type": "Point",
        "coordinates": [
          -100.9167,
          47.8333
        ]
      },
      "type": "Feature",
      "properties": {
        "hierarchy": [
          "tgn:2077983",
          "tgn:1000001",
          "tgn:2001584",
          "tgn:7012149",
          "tgn:7007705",
          "tgn:7029392"
        ],
        "placetype": [
          "aat:300008347"
        ],
        "id": 2077983,
        "name:xx": "Ruso"
      }
    },
    {
      "geometry": {
        "type": "Point",
        "coordinates": [
          -100.9,
          48.6667
        ]
      },
      "type": "Feature",
      "properties": {
        "hierarchy": [
          "tgn:2077984",
          "tgn:7020393",
          "tgn:1000001",
          "tgn:7012149",
          "tgn:7007705",
          "tgn:7029392"
        ],
        "placetype": [
          "aat:300008347"
        ],
        "id": 2077984,
        "name:xx": "Russell"
      }
    },
    {
      "geometry": {
        "type": "Point",
        "coordinates": [
          -101.2833,
          48.3667
        ]
      },
      "type": "Feature",
      "properties": {
        "hierarchy": [
          "tgn:2077985",
          "tgn:1000001",
          "tgn:7012149",
          "tgn:2001607",
          "tgn:7007705",
          "tgn:7029392"
        ],
        "placetype": [
          "aat:300008347"
        ],
        "id": 2077985,
        "name:xx": "Ruthville"
      }
    },
    {
      "geometry": {
        "type": "Point",
        "coordinates": [
          -97.5,
          46.05
        ]
      },
      "type": "Feature",
      "properties": {
        "hierarchy": [
          "tgn:2077986",
          "tgn:1000001",
          "tgn:2001597",
          "tgn:7012149",
          "tgn:7007705",
          "tgn:7029392"
        ],
        "placetype": [
          "aat:300008347"
        ],
        "id": 2077986,
        "name:xx": "Rutland"
      }
    },
    {
      "geometry": {
        "type": "Point",
        "coordinates": [
          -101.6667,
          47.9167
        ]
      },
      "type": "Feature",
      "properties": {
        "hierarchy": [
          "tgn:2077987",
          "tgn:1000001",
          "tgn:7012149",
          "tgn:2001607",
          "tgn:7007705",
          "tgn:7029392"
        ],
        "placetype": [
          "aat:300008347"
        ],
        "id": 2077987,
        "name:xx": "Ryder"
      }
    }
  ]
}
