{
  "geometry": {
    "type": "Point",
    "coordinates": [
      -112.1667,
      43.0667
    ]
  },
  "type": "Feature",
  "properties": {
    "hierarchy": [
      "tgn:2297837",
      "tgn:1000001",
      "tgn:2000457",
      "tgn:7012149",
      "tgn:7007250",
      "tgn:7029392"
    ],
    "placetype": [
      "aat:300008761"
    ],
    "id": 2297837,
    "name:xx": "Dry Hollow"
  }
}
