{
  "geometry": {
    "type": "Point",
    "coordinates": [
      -80.4667,
      41.55
    ]
  },
  "type": "Feature",
  "properties": {
    "hierarchy": [
      "tgn:2094333",
      "tgn:1000001",
      "tgn:1002308",
      "tgn:7012149",
      "tgn:7007710",
      "tgn:7029392"
    ],
    "placetype": [
      "aat:300008347"
    ],
    "id": 2094333,
    "name:xx": "Westford"
  }
}
