{
  "geometry": {
    "type": "Point",
    "coordinates": [
      -83.6167,
      38.9167
    ]
  },
  "type": "Feature",
  "properties": {
    "hierarchy": [
      "tgn:2357744",
      "tgn:1002136",
      "tgn:1000001",
      "tgn:7012149",
      "tgn:7007706",
      "tgn:7029392"
    ],
    "placetype": [
      "aat:300008699"
    ],
    "id": 2357744,
    "name:xx": "Grace Run"
  }
}
