{
  "geometry": {
    "type": "Point",
    "coordinates": [
      -119.3833,
      44.95
    ]
  },
  "type": "Feature",
  "properties": {
    "hierarchy": [
      "tgn:2173357",
      "tgn:1000001",
      "tgn:7012149",
      "tgn:2001708",
      "tgn:7007708",
      "tgn:7029392"
    ],
    "placetype": [
      "aat:300008706"
    ],
    "id": 2173357,
    "name:xx": "Birch Creek"
  }
}
