{
  "geometry": {
    "type": "Point",
    "coordinates": [
      10.4833,
      1.75
    ]
  },
  "type": "Feature",
  "properties": {
    "hierarchy": [
      "tgn:1089650",
      "tgn:1001736",
      "tgn:7001242",
      "tgn:1000161",
      "tgn:7029392"
    ],
    "placetype": [
      "aat:300008347"
    ],
    "id": 1089650,
    "name:xx": "Amvamg"
  }
}
