{
  "geometry": {
    "type": "Point",
    "coordinates": [
      -121.6167,
      37.8333
    ]
  },
  "type": "Feature",
  "properties": {
    "hierarchy": [
      "tgn:2212670",
      "tgn:1000001",
      "tgn:7012149",
      "tgn:1002298",
      "tgn:7007157",
      "tgn:7029392"
    ],
    "placetype": [
      "aat:300008697"
    ],
    "id": 2212670,
    "name:xx": "Byron Hot Springs"
  }
}
