{
  "type": "FeatureCollection",
  "features": [
    {
      "geometry": {
        "type": "Point",
        "coordinates": [
          -3.802222,
          51.656111
        ]
      },
      "type": "Feature",
      "properties": {
        "hierarchy": [
          "tgn:7008430",
          "tgn:7002443",
          "tgn:1000003",
          "tgn:7018974",
          "tgn:7008591",
          "tgn:7029392"
        ],
        "placetype": [
          "aat:300008347",
          "aat:300387305",
          "aat:300006909",
          "aat:300008375",
          "aat:300387302"
        ],
        "name:en": "Neath",
        "id": 7008430
      }
    },
    {
      "geometry": {
        "type": "Point",
        "coordinates": [
          2.0333,
          44.35
        ]
      },
      "type": "Feature",
      "properties": {
        "hierarchy": [
          "tgn:7008433",
          "tgn:1000003",
          "tgn:7002889",
          "tgn:1000070",
          "tgn:7029392"
        ],
        "placetype": [
          "aat:300008347"
        ],
        "id": 7008433,
        "name:xx": "Villefranche-de-Rouergue"
      }
    },
    {
      "geometry": {
        "type": "Point",
        "coordinates": [
          -1.816667,
          42.666667
        ]
      },
      "type": "Feature",
      "properties": {
        "hierarchy": [
          "tgn:7008436",
          "tgn:7001155",
          "tgn:1000003",
          "tgn:7002790",
          "tgn:1000095",
          "tgn:7029392"
        ],
        "placetype": [
          "aat:300008347"
        ],
        "id": 7008436,
        "name:xx": "Puente la Reina"
      }
    },
    {
      "geometry": {
        "type": "Point",
        "coordinates": [
          -4.116667,
          38.683333
        ]
      },
      "type": "Feature",
      "properties": {
        "hierarchy": [
          "tgn:7008437",
          "tgn:7002816",
          "tgn:1001647",
          "tgn:1000003",
          "tgn:1000095",
          "tgn:7029392"
        ],
        "placetype": [
          "aat:300008347"
        ],
        "id": 7008437,
        "name:xx": "Puertollano"
      }
    }
  ]
}
