{
  "geometry": {
    "type": "Point",
    "coordinates": [
      -109.75,
      37.9833
    ]
  },
  "type": "Feature",
  "properties": {
    "hierarchy": [
      "tgn:2439313",
      "tgn:1000001",
      "tgn:7012149",
      "tgn:2002119",
      "tgn:7007827",
      "tgn:7029392"
    ],
    "placetype": [
      "aat:300386837"
    ],
    "id": 2439313,
    "name:xx": "Kirk Arch"
  }
}
