{
  "geometry": {
    "type": "Point",
    "coordinates": [
      -86.4333,
      39.2833
    ]
  },
  "type": "Feature",
  "properties": {
    "hierarchy": [
      "tgn:2153459",
      "tgn:1000001",
      "tgn:7012149",
      "tgn:1002678",
      "tgn:7007252",
      "tgn:7029392"
    ],
    "placetype": [
      "aat:300006191"
    ],
    "id": 2153459,
    "name:xx": "Beanblossom Lake"
  }
}
