{
  "geometry": {
    "type": "Point",
    "coordinates": [
      -86.1333,
      46.55
    ]
  },
  "type": "Feature",
  "properties": {
    "hierarchy": [
      "tgn:2574371",
      "tgn:2000943",
      "tgn:1000001",
      "tgn:7012149",
      "tgn:7007520",
      "tgn:7029392"
    ],
    "placetype": [
      "aat:300008680"
    ],
    "id": 2574371,
    "name:xx": "Pelican Lake"
  }
}
