{
  "type": "FeatureCollection",
  "features": [
    {
      "geometry": {
        "type": "Point",
        "coordinates": [
          22.493333,
          40.636111
        ]
      },
      "type": "Feature",
      "properties": {
        "hierarchy": [
          "tgn:7222740",
          "tgn:7002718",
          "tgn:7002715",
          "tgn:1000003",
          "tgn:1000074",
          "tgn:7029392"
        ],
        "placetype": [
          "aat:300008347"
        ],
        "id": 7222740,
        "name:xx": "Palaiochórion"
      }
    },
    {
      "geometry": {
        "type": "Point",
        "coordinates": [
          23.65,
          40.5
        ]
      },
      "type": "Feature",
      "properties": {
        "hierarchy": [
          "tgn:7222741",
          "tgn:7002715",
          "tgn:7002731",
          "tgn:1000003",
          "tgn:1000074",
          "tgn:7029392"
        ],
        "placetype": [
          "aat:300008347"
        ],
        "id": 7222741,
        "name:xx": "Palaiokhórion"
      }
    },
    {
      "geometry": {
        "type": "Point",
        "coordinates": [
          21.683333,
          40.05
        ]
      },
      "type": "Feature",
      "properties": {
        "hierarchy": [
          "tgn:7222742",
          "tgn:7002752",
          "tgn:7001399",
          "tgn:1000003",
          "tgn:1000074",
          "tgn:7029392"
        ],
        "placetype": [
          "aat:300008347"
        ],
        "id": 7222742,
        "name:xx": "Palaiokhórion"
      }
    },
    {
      "geometry": {
        "type": "Point",
        "coordinates": [
          21.316667,
          40.016667
        ]
      },
      "type": "Feature",
      "properties": {
        "hierarchy": [
          "tgn:7222743",
          "tgn:7002721",
          "tgn:7002715",
          "tgn:1000003",
          "tgn:1000074",
          "tgn:7029392"
        ],
        "placetype": [
          "aat:300008347"
        ],
        "id": 7222743,
        "name:xx": "Palaiokhórion"
      }
    },
    {
      "geometry": {
        "type": "Point",
        "coordinates": [
          21.419444,
          39.608333
        ]
      },
      "type": "Feature",
      "properties": {
        "hierarchy": [
          "tgn:7222744",
          "tgn:7002752",
          "tgn:7001399",
          "tgn:1000003",
          "tgn:1000074",
          "tgn:7029392"
        ],
        "placetype": [
          "aat:300008347"
        ],
        "id": 7222744,
        "name:xx": "Palaiochórion"
      }
    },
    {
      "geometry": {
        "type": "Point",
        "coordinates": [
          20.436389,
          39.546667
        ]
      },
      "type": "Feature",
      "properties": {
        "hierarchy": [
          "tgn:7222745",
          "tgn:7002709",
          "tgn:7002705",
          "tgn:1000003",
          "tgn:1000074",
          "tgn:7029392"
        ],
        "placetype": [
          "aat:300008347"
        ],
        "id": 7222745,
        "name:xx": "Palaiochórion"
      }
    },
    {
      "geometry": {
        "type": "Point",
        "coordinates": [
          21.079444,
          39.491667
        ]
      },
      "type": "Feature",
      "properties": {
        "hierarchy": [
          "tgn:7222746",
          "tgn:7002706",
          "tgn:7002705",
          "tgn:1000003",
          "tgn:1000074",
          "tgn:7029392"
        ],
        "placetype": [
          "aat:300008347"
        ],
        "id": 7222746,
        "name:xx": "Palaiochórion"
      }
    },
    {
      "geometry": {
        "type": "Point",
        "coordinates": [
          21.824167,
          39.470278
        ]
      },
      "type": "Feature",
      "properties": {
        "hierarchy": [
          "tgn:7222747",
          "tgn:7002748",
          "tgn:7001399",
          "tgn:1000003",
          "tgn:1000074",
          "tgn:7029392"
        ],
        "placetype": [
          "aat:300008347"
        ],
        "id": 7222747,
        "name:xx": "Palaiochórion"
      }
    },
    {
      "geometry": {
        "type": "Point",
        "coordinates": [
          21.028056,
          39.378889
        ]
      },
      "type": "Feature",
      "properties": {
        "hierarchy": [
          "tgn:7222749",
          "tgn:7002706",
          "tgn:7002705",
          "tgn:1000003",
          "tgn:1000074",
          "tgn:7029392"
        ],
        "placetype": [
          "aat:300008347"
        ],
        "id": 7222749,
        "name:xx": "Palaiochórion"
      }
    }
  ]
}
