{
  "geometry": {
    "type": "Point",
    "coordinates": [
      -94.7167,
      41.2333
    ]
  },
  "type": "Feature",
  "properties": {
    "hierarchy": [
      "tgn:2718166",
      "tgn:1000001",
      "tgn:7012149",
      "tgn:7007253",
      "tgn:7029392"
    ],
    "placetype": [
      "aat:300008706"
    ],
    "id": 2718166,
    "name:xx": "Thompson Creek"
  }
}
