{
  "geometry": {
    "type": "Point",
    "coordinates": [
      -104.4833,
      44.1333
    ]
  },
  "type": "Feature",
  "properties": {
    "hierarchy": [
      "tgn:2229108",
      "tgn:1000001",
      "tgn:7012149",
      "tgn:2002387",
      "tgn:7007923",
      "tgn:7029392"
    ],
    "placetype": [
      "aat:300008798"
    ],
    "id": 2229108,
    "name:xx": "Cedar Knoll"
  }
}
