{
  "type": "FeatureCollection",
  "features": [
    {
      "geometry": {
        "type": "Point",
        "coordinates": [
          31.813889,
          31.450833
        ]
      },
      "type": "Feature",
      "properties": {
        "hierarchy": [
          "tgn:7532510",
          "tgn:7001242",
          "tgn:1001059",
          "tgn:7016833",
          "tgn:7029392"
        ],
        "placetype": [
          "aat:300007558"
        ],
        "name:en": "Sîdi Miftâḥ",
        "id": 7532510
      }
    },
    {
      "geometry": {
        "type": "Point",
        "coordinates": [
          31.811111,
          31.432778
        ]
      },
      "type": "Feature",
      "properties": {
        "hierarchy": [
          "tgn:7532511",
          "tgn:7001242",
          "tgn:1001059",
          "tgn:7016833",
          "tgn:7029392"
        ],
        "placetype": [
          "aat:300000206"
        ],
        "name:en": "'Ezbet Nishwân",
        "id": 7532511
      }
    },
    {
      "geometry": {
        "type": "Point",
        "coordinates": [
          31.821032,
          31.43335
        ]
      },
      "type": "Feature",
      "properties": {
        "hierarchy": [
          "tgn:7532512",
          "tgn:7001242",
          "tgn:1001059",
          "tgn:7016833",
          "tgn:7029392"
        ],
        "placetype": [
          "aat:300000206"
        ],
        "name:en": "'Ezbet Fakhr el-Dîn",
        "id": 7532512
      }
    },
    {
      "geometry": {
        "type": "Point",
        "coordinates": [
          31.824795,
          31.434464
        ]
      },
      "type": "Feature",
      "properties": {
        "hierarchy": [
          "tgn:7532513",
          "tgn:7001242",
          "tgn:1001059",
          "tgn:7016833",
          "tgn:7029392"
        ],
        "placetype": [
          "aat:300000206"
        ],
        "name:en": "'Ezbet Sibell",
        "id": 7532513
      }
    },
    {
      "geometry": {
        "type": "Point",
        "coordinates": [
          31.831026,
          31.436096
        ]
      },
      "type": "Feature",
      "properties": {
        "hierarchy": [
          "tgn:7532514",
          "tgn:7001242",
          "tgn:1001059",
          "tgn:7016833",
          "tgn:7029392"
        ],
        "placetype": [
          "aat:300000206"
        ],
        "name:en": "'Ezbet el-Raml",
        "id": 7532514
      }
    },
    {
      "geometry": {
        "type": "Point",
        "coordinates": [
          31.816667,
          31.434444
        ]
      },
      "type": "Feature",
      "properties": {
        "hierarchy": [
          "tgn:7532515",
          "tgn:7001242",
          "tgn:1001059",
          "tgn:7016833",
          "tgn:7029392"
        ],
        "placetype": [
          "aat:300000206"
        ],
        "name:en": "'Ezbet el-Hindi",
        "id": 7532515
      }
    },
    {
      "geometry": {
        "type": "Point",
        "coordinates": [
          31.813333,
          31.438333
        ]
      },
      "type": "Feature",
      "properties": {
        "hierarchy": [
          "tgn:7532516",
          "tgn:7001242",
          "tgn:1001059",
          "tgn:7016833",
          "tgn:7029392"
        ],
        "placetype": [
          "aat:300000206"
        ],
        "name:en": "'Ezbet el-Gharb",
        "id": 7532516
      }
    },
    {
      "geometry": {
        "type": "Point",
        "coordinates": [
          31.805469,
          31.438744
        ]
      },
      "type": "Feature",
      "properties": {
        "hierarchy": [
          "tgn:7532517",
          "tgn:7001242",
          "tgn:1001059",
          "tgn:7016833",
          "tgn:7029392"
        ],
        "placetype": [
          "aat:300000206"
        ],
        "name:en": "'Ezbet Muṣṭafa Mûsa",
        "id": 7532517
      }
    },
    {
      "geometry": {
        "type": "Point",
        "coordinates": [
          31.804722,
          31.443889
        ]
      },
      "type": "Feature",
      "properties": {
        "hierarchy": [
          "tgn:7532518",
          "tgn:7001242",
          "tgn:7016833",
          "tgn:1001225",
          "tgn:7029392"
        ],
        "placetype": [
          "aat:300000206"
        ],
        "name:en": "'Ezbet el-Gawâyla",
        "id": 7532518
      }
    },
    {
      "geometry": {
        "type": "Point",
        "coordinates": [
          31.813056,
          31.445833
        ]
      },
      "type": "Feature",
      "properties": {
        "hierarchy": [
          "tgn:7532519",
          "tgn:7001242",
          "tgn:7016833",
          "tgn:1001225",
          "tgn:7029392"
        ],
        "placetype": [
          "aat:300000206"
        ],
        "name:en": "'Ezbet el-Baṣâyla",
        "id": 7532519
      }
    }
  ]
}
