{
  "geometry": {
    "type": "Point",
    "coordinates": [
      -98.2833,
      47.55
    ]
  },
  "type": "Feature",
  "properties": {
    "hierarchy": [
      "tgn:2421544",
      "tgn:1000001",
      "tgn:2001576",
      "tgn:7012149",
      "tgn:7007705",
      "tgn:7029392"
    ],
    "placetype": [
      "aat:300008680"
    ],
    "id": 2421544,
    "name:xx": "Jessie, Lake"
  }
}
