{
  "geometry": {
    "type": "Point",
    "coordinates": [
      -105.1333,
      37.9167
    ]
  },
  "type": "Feature",
  "properties": {
    "hierarchy": [
      "tgn:2590557",
      "tgn:1000001",
      "tgn:7012149",
      "tgn:2000219",
      "tgn:7007158",
      "tgn:7029392"
    ],
    "placetype": [
      "aat:300008706"
    ],
    "id": 2590557,
    "name:xx": "Pole Creek"
  }
}
