{
  "geometry": {
    "type": "Point",
    "coordinates": [
      -96.2833,
      38.2667
    ]
  },
  "type": "Feature",
  "properties": {
    "hierarchy": [
      "tgn:2578470",
      "tgn:1000001",
      "tgn:7012149",
      "tgn:2000715",
      "tgn:7007254",
      "tgn:7029392"
    ],
    "placetype": [
      "aat:300008706"
    ],
    "id": 2578470,
    "name:xx": "Phenis Creek"
  }
}
