{
  "geometry": {
    "type": "Point",
    "coordinates": [
      -70.55,
      -33.833333
    ]
  },
  "type": "Feature",
  "properties": {
    "hierarchy": [
      "tgn:7312002",
      "tgn:1001708",
      "tgn:1000049",
      "tgn:1000002",
      "tgn:7029392"
    ],
    "placetype": [
      "aat:300387002"
    ],
    "id": 7312002,
    "name:xx": "Las Funíones, Loma de"
  }
}
