{
  "geometry": {
    "type": "Point",
    "coordinates": [
      -94.1167,
      30.8833
    ]
  },
  "type": "Feature",
  "properties": {
    "hierarchy": [
      "tgn:2433583",
      "tgn:1000001",
      "tgn:7012149",
      "tgn:2002009",
      "tgn:7007826",
      "tgn:7029392"
    ],
    "placetype": [
      "aat:300008699"
    ],
    "id": 2433583,
    "name:xx": "Kelly Branch"
  }
}
