{
  "geometry": {
    "type": "Point",
    "coordinates": [
      41.5167,
      0.1167
    ]
  },
  "type": "Feature",
  "properties": {
    "hierarchy": [
      "tgn:1092770",
      "tgn:7001242",
      "tgn:1001687",
      "tgn:1000192",
      "tgn:7029392"
    ],
    "placetype": [
      "aat:300008347"
    ],
    "id": 1092770,
    "name:xx": "Solola"
  }
}
