{
  "type": "FeatureCollection",
  "features": [
    {
      "geometry": {
        "type": "Point",
        "coordinates": [
          -87.5167,
          35.5333
        ]
      },
      "type": "Feature",
      "properties": {
        "hierarchy": [
          "tgn:2296250",
          "tgn:1000001",
          "tgn:7012149",
          "tgn:2001887",
          "tgn:7007825",
          "tgn:7029392"
        ],
        "placetype": [
          "aat:300008699"
        ],
        "id": 2296250,
        "name:xx": "Dry Branch"
      }
    },
    {
      "geometry": {
        "type": "Point",
        "coordinates": [
          -88.85,
          35.5667
        ]
      },
      "type": "Feature",
      "properties": {
        "hierarchy": [
          "tgn:2296251",
          "tgn:1000001",
          "tgn:7012149",
          "tgn:2001893",
          "tgn:7007825",
          "tgn:7029392"
        ],
        "placetype": [
          "aat:300008699"
        ],
        "id": 2296251,
        "name:xx": "Dry Branch"
      }
    },
    {
      "geometry": {
        "type": "Point",
        "coordinates": [
          -83.7333,
          35.65
        ]
      },
      "type": "Feature",
      "properties": {
        "hierarchy": [
          "tgn:2296252",
          "tgn:1000001",
          "tgn:2001841",
          "tgn:7012149",
          "tgn:7007825",
          "tgn:7029392"
        ],
        "placetype": [
          "aat:300008699"
        ],
        "id": 2296252,
        "name:xx": "Dry Branch"
      }
    },
    {
      "geometry": {
        "type": "Point",
        "coordinates": [
          -88.5833,
          35.7
        ]
      },
      "type": "Feature",
      "properties": {
        "hierarchy": [
          "tgn:2296253",
          "tgn:1000001",
          "tgn:7012149",
          "tgn:2001875",
          "tgn:7007825",
          "tgn:7029392"
        ],
        "placetype": [
          "aat:300008699"
        ],
        "id": 2296253,
        "name:xx": "Dry Branch"
      }
    },
    {
      "geometry": {
        "type": "Point",
        "coordinates": [
          -85.7333,
          35.7333
        ]
      },
      "type": "Feature",
      "properties": {
        "hierarchy": [
          "tgn:2296254",
          "tgn:1000001",
          "tgn:7012149",
          "tgn:2001925",
          "tgn:7007825",
          "tgn:7029392"
        ],
        "placetype": [
          "aat:300008699"
        ],
        "id": 2296254,
        "name:xx": "Dry Branch"
      }
    },
    {
      "geometry": {
        "type": "Point",
        "coordinates": [
          -83.1833,
          35.7167
        ]
      },
      "type": "Feature",
      "properties": {
        "hierarchy": [
          "tgn:2296255",
          "tgn:1000001",
          "tgn:7012149",
          "tgn:2001851",
          "tgn:7007825",
          "tgn:7029392"
        ],
        "placetype": [
          "aat:300008699"
        ],
        "id": 2296255,
        "name:xx": "Dry Branch"
      }
    },
    {
      "geometry": {
        "type": "Point",
        "coordinates": [
          -83.7,
          35.7833
        ]
      },
      "type": "Feature",
      "properties": {
        "hierarchy": [
          "tgn:2296256",
          "tgn:1000001",
          "tgn:7012149",
          "tgn:2001914",
          "tgn:7007825",
          "tgn:7029392"
        ],
        "placetype": [
          "aat:300008699"
        ],
        "id": 2296256,
        "name:xx": "Dry Branch"
      }
    },
    {
      "geometry": {
        "type": "Point",
        "coordinates": [
          -86.2833,
          35.7833
        ]
      },
      "type": "Feature",
      "properties": {
        "hierarchy": [
          "tgn:2296257",
          "tgn:1000001",
          "tgn:7012149",
          "tgn:2001911",
          "tgn:7007825",
          "tgn:7029392"
        ],
        "placetype": [
          "aat:300008699"
        ],
        "id": 2296257,
        "name:xx": "Dry Branch"
      }
    },
    {
      "geometry": {
        "type": "Point",
        "coordinates": [
          -86.8167,
          35.9833
        ]
      },
      "type": "Feature",
      "properties": {
        "hierarchy": [
          "tgn:2296258",
          "tgn:1000001",
          "tgn:7012149",
          "tgn:2001930",
          "tgn:7007825",
          "tgn:7029392"
        ],
        "placetype": [
          "aat:300008699"
        ],
        "id": 2296258,
        "name:xx": "Dry Branch"
      }
    },
    {
      "geometry": {
        "type": "Point",
        "coordinates": [
          -88.35,
          35.9833
        ]
      },
      "type": "Feature",
      "properties": {
        "hierarchy": [
          "tgn:2296259",
          "tgn:1000001",
          "tgn:7012149",
          "tgn:2001845",
          "tgn:7007825",
          "tgn:7029392"
        ],
        "placetype": [
          "aat:300008699"
        ],
        "id": 2296259,
        "name:xx": "Dry Branch"
      }
    }
  ]
}
