{
  "geometry": {
    "type": "Point",
    "coordinates": [
      -56.6833,
      -2.25
    ]
  },
  "type": "Feature",
  "properties": {
    "hierarchy": [
      "tgn:1022209",
      "tgn:1001826",
      "tgn:1000047",
      "tgn:7002456",
      "tgn:1000002",
      "tgn:7029392"
    ],
    "placetype": [
      "aat:300008347"
    ],
    "id": 1022209,
    "name:xx": "Nhamundá"
  }
}
