{
  "geometry": {
    "type": "Point",
    "coordinates": [
      -75.0667,
      3.1833
    ]
  },
  "type": "Feature",
  "properties": {
    "hierarchy": [
      "tgn:1023718",
      "tgn:1000640",
      "tgn:1000050",
      "tgn:1000002",
      "tgn:7029392"
    ],
    "placetype": [
      "aat:300008347"
    ],
    "id": 1023718,
    "name:xx": "Baraya"
  }
}
