{
  "geometry": {
    "type": "Point",
    "coordinates": [
      31.1025,
      30.932222
    ]
  },
  "type": "Feature",
  "properties": {
    "hierarchy": [
      "tgn:7524610",
      "tgn:7001242",
      "tgn:7016833",
      "tgn:7001312",
      "tgn:7029392"
    ],
    "placetype": [
      "aat:300006075"
    ],
    "name:en": "Tur'et Buqîna",
    "id": 7524610
  }
}
