{
  "type": "FeatureCollection",
  "features": [
    {
      "geometry": {
        "type": "Point",
        "coordinates": [
          -82.4167,
          28.5333
        ]
      },
      "type": "Feature",
      "properties": {
        "hierarchy": [
          "tgn:2400530",
          "tgn:1000001",
          "tgn:1002473",
          "tgn:7012149",
          "tgn:7007240",
          "tgn:7029392"
        ],
        "placetype": [
          "aat:300008680"
        ],
        "id": 2400530,
        "name:xx": "Horse Lake"
      }
    },
    {
      "geometry": {
        "type": "Point",
        "coordinates": [
          -111.55,
          42.0167
        ]
      },
      "type": "Feature",
      "properties": {
        "hierarchy": [
          "tgn:2400531",
          "tgn:1000001",
          "tgn:7012149",
          "tgn:2000472",
          "tgn:7007250",
          "tgn:7029392"
        ],
        "placetype": [
          "aat:300008680"
        ],
        "id": 2400531,
        "name:xx": "Horse Lake"
      }
    },
    {
      "geometry": {
        "type": "Point",
        "coordinates": [
          -112.5,
          42.7833
        ]
      },
      "type": "Feature",
      "properties": {
        "hierarchy": [
          "tgn:2400532",
          "tgn:2000454",
          "tgn:1000001",
          "tgn:7012149",
          "tgn:7007250",
          "tgn:7029392"
        ],
        "placetype": [
          "aat:300008680"
        ],
        "id": 2400532,
        "name:xx": "Horse Lake"
      }
    },
    {
      "geometry": {
        "type": "Point",
        "coordinates": [
          -112.0667,
          42.8333
        ]
      },
      "type": "Feature",
      "properties": {
        "hierarchy": [
          "tgn:2400533",
          "tgn:1000001",
          "tgn:2000466",
          "tgn:7012149",
          "tgn:7007250",
          "tgn:7029392"
        ],
        "placetype": [
          "aat:300008680"
        ],
        "id": 2400533,
        "name:xx": "Horse Lake"
      }
    },
    {
      "geometry": {
        "type": "Point",
        "coordinates": [
          -113.3667,
          44.3333
        ]
      },
      "type": "Feature",
      "properties": {
        "hierarchy": [
          "tgn:2400534",
          "tgn:1000001",
          "tgn:2000470",
          "tgn:7012149",
          "tgn:7007250",
          "tgn:7029392"
        ],
        "placetype": [
          "aat:300008680"
        ],
        "id": 2400534,
        "name:xx": "Horse Lake"
      }
    },
    {
      "geometry": {
        "type": "Point",
        "coordinates": [
          -115.3,
          42.0667
        ]
      },
      "type": "Feature",
      "properties": {
        "hierarchy": [
          "tgn:2400535",
          "tgn:1000001",
          "tgn:7012149",
          "tgn:2000488",
          "tgn:7007250",
          "tgn:7029392"
        ],
        "placetype": [
          "aat:300008680"
        ],
        "id": 2400535,
        "name:xx": "Horse Lake"
      }
    },
    {
      "geometry": {
        "type": "Point",
        "coordinates": [
          -67.7833,
          45.0167
        ]
      },
      "type": "Feature",
      "properties": {
        "hierarchy": [
          "tgn:2400536",
          "tgn:1000001",
          "tgn:7012149",
          "tgn:7014589",
          "tgn:7007515",
          "tgn:7029392"
        ],
        "placetype": [
          "aat:300008680"
        ],
        "id": 2400536,
        "name:xx": "Horse Lake"
      }
    },
    {
      "geometry": {
        "type": "Point",
        "coordinates": [
          -95.4833,
          45.7
        ]
      },
      "type": "Feature",
      "properties": {
        "hierarchy": [
          "tgn:2400537",
          "tgn:1000001",
          "tgn:7012149",
          "tgn:2001059",
          "tgn:7007521",
          "tgn:7029392"
        ],
        "placetype": [
          "aat:300008680"
        ],
        "id": 2400537,
        "name:xx": "Horse Lake"
      }
    },
    {
      "geometry": {
        "type": "Point",
        "coordinates": [
          -94.4167,
          46.7833
        ]
      },
      "type": "Feature",
      "properties": {
        "hierarchy": [
          "tgn:2400538",
          "tgn:1000001",
          "tgn:2001009",
          "tgn:7012149",
          "tgn:7007521",
          "tgn:7029392"
        ],
        "placetype": [
          "aat:300008680"
        ],
        "id": 2400538,
        "name:xx": "Horse Lake"
      }
    },
    {
      "geometry": {
        "type": "Point",
        "coordinates": [
          -91.75,
          48.0667
        ]
      },
      "type": "Feature",
      "properties": {
        "hierarchy": [
          "tgn:2400539",
          "tgn:1000001",
          "tgn:7012149",
          "tgn:2001036",
          "tgn:7007521",
          "tgn:7029392"
        ],
        "placetype": [
          "aat:300008680"
        ],
        "id": 2400539,
        "name:xx": "Horse Lake"
      }
    }
  ]
}
