{
  "geometry": {
    "type": "Point",
    "coordinates": [
      44.4333,
      35.1333
    ]
  },
  "type": "Feature",
  "properties": {
    "hierarchy": [
      "tgn:1079374",
      "tgn:1000004",
      "tgn:1000118",
      "tgn:1001054",
      "tgn:7029392"
    ],
    "placetype": [
      "aat:300008347"
    ],
    "id": 1079374,
    "name:xx": "Ṭāwūq"
  }
}
