{
  "geometry": {
    "type": "Point",
    "coordinates": [
      -83.3167,
      40.2833
    ]
  },
  "type": "Feature",
  "properties": {
    "hierarchy": [
      "tgn:2578458",
      "tgn:1000001",
      "tgn:7012149",
      "tgn:1002964",
      "tgn:7007706",
      "tgn:7029392"
    ],
    "placetype": [
      "aat:300008699"
    ],
    "id": 2578458,
    "name:xx": "Phelps Run"
  }
}
