{
  "geometry": {
    "type": "Point",
    "coordinates": [
      -92.9833,
      45.2833
    ]
  },
  "type": "Feature",
  "properties": {
    "hierarchy": [
      "tgn:2428418",
      "tgn:1000001",
      "tgn:7012149",
      "tgn:2001080",
      "tgn:7007521",
      "tgn:7029392"
    ],
    "placetype": [
      "aat:300006075"
    ],
    "id": 2428418,
    "name:xx": "Judicial Ditch Number Two"
  }
}
