{
  "geometry": {
    "type": "Point",
    "coordinates": [
      -118.6667,
      35.3167
    ]
  },
  "type": "Feature",
  "properties": {
    "hierarchy": [
      "tgn:2605646",
      "tgn:1000001",
      "tgn:7012149",
      "tgn:1002545",
      "tgn:7007157",
      "tgn:7029392"
    ],
    "placetype": [
      "aat:300008697"
    ],
    "id": 2605646,
    "name:xx": "Railroad Spring"
  }
}
