{
  "geometry": {
    "type": "Point",
    "coordinates": [
      -62.4167,
      -35.9667
    ]
  },
  "type": "Feature",
  "properties": {
    "hierarchy": [
      "tgn:1116991",
      "tgn:1001160",
      "tgn:7006477",
      "tgn:1000002",
      "tgn:7029392"
    ],
    "placetype": [
      "aat:300008680"
    ],
    "id": 1116991,
    "name:xx": "Las Tunas Grandes, Laguna"
  }
}
