{
  "geometry": {
    "type": "Point",
    "coordinates": [
      -98.5833,
      26.5333
    ]
  },
  "type": "Feature",
  "properties": {
    "hierarchy": [
      "tgn:2443733",
      "tgn:1000001",
      "tgn:7012149",
      "tgn:7007826",
      "tgn:7029392"
    ],
    "placetype": [
      "aat:300008706"
    ],
    "id": 2443733,
    "name:xx": "La Joya Creek"
  }
}
