{
  "geometry": {
    "type": "Point",
    "coordinates": [
      75.210591,
      28.463894
    ]
  },
  "type": "Feature",
  "properties": {
    "hierarchy": [
      "tgn:7584180",
      "tgn:1000004",
      "tgn:7000198",
      "tgn:7016788",
      "tgn:7029392"
    ],
    "placetype": [
      "aat:300008347"
    ],
    "name:en": "Dhannrām ka Bās",
    "id": 7584180
  }
}
