{
  "geometry": {
    "type": "Point",
    "coordinates": [
      -161.5333,
      55.5333
    ]
  },
  "type": "Feature",
  "properties": {
    "hierarchy": [
      "tgn:1113588",
      "tgn:7030515",
      "tgn:7006450",
      "tgn:1000001",
      "tgn:7012149",
      "tgn:7029392"
    ],
    "placetype": [
      "aat:300132316"
    ],
    "id": 1113588,
    "name:xx": "Pavlof Bay"
  }
}
