{
  "geometry": {
    "type": "Point",
    "coordinates": [
      -97.9333,
      43.5333
    ]
  },
  "type": "Feature",
  "properties": {
    "hierarchy": [
      "tgn:2319375",
      "tgn:1000001",
      "tgn:2001800",
      "tgn:7012149",
      "tgn:7007713",
      "tgn:7029392"
    ],
    "placetype": [
      "aat:300006191"
    ],
    "id": 2319375,
    "name:xx": "Ethan Lake"
  }
}
