{
  "geometry": {
    "type": "Point",
    "coordinates": [
      -1.25,
      45.6833
    ]
  },
  "type": "Feature",
  "properties": {
    "hierarchy": [
      "tgn:7016426",
      "tgn:1000003",
      "tgn:7002892",
      "tgn:1000070",
      "tgn:7029392"
    ],
    "placetype": [
      "aat:300008850"
    ],
    "id": 7016426,
    "name:xx": "Coubre, Pointe de la"
  }
}
