{
  "geometry": {
    "type": "Point",
    "coordinates": [
      -85.2833,
      35.2667
    ]
  },
  "type": "Feature",
  "properties": {
    "hierarchy": [
      "tgn:2566844",
      "tgn:1000001",
      "tgn:7012149",
      "tgn:7007825",
      "tgn:7029392"
    ],
    "placetype": [
      "aat:300008699"
    ],
    "id": 2566844,
    "name:xx": "Panther Branch"
  }
}
