{
  "geometry": {
    "type": "Point",
    "coordinates": [
      -93.6667,
      35.1667
    ]
  },
  "type": "Feature",
  "properties": {
    "hierarchy": [
      "tgn:2670009",
      "tgn:1000001",
      "tgn:7016172",
      "tgn:7012149",
      "tgn:2000146",
      "tgn:7029392"
    ],
    "placetype": [
      "aat:300008697"
    ],
    "id": 2670009,
    "name:xx": "Slocum Spring"
  }
}
