{
  "type": "FeatureCollection",
  "features": [
    {
      "geometry": {
        "type": "Point",
        "coordinates": [
          -1.3,
          54.366667
        ]
      },
      "type": "Feature",
      "properties": {
        "hierarchy": [
          "tgn:7459411",
          "tgn:7002445",
          "tgn:1000003",
          "tgn:7008166",
          "tgn:7008591",
          "tgn:7029392"
        ],
        "placetype": [
          "aat:300008347"
        ],
        "name:en": "Osmotherley",
        "id": 7459411
      }
    },
    {
      "geometry": {
        "type": "Point",
        "coordinates": [
          -5.316667,
          58.05
        ]
      },
      "type": "Feature",
      "properties": {
        "hierarchy": [
          "tgn:7459414",
          "tgn:7002444",
          "tgn:1000003",
          "tgn:7008082",
          "tgn:7008591",
          "tgn:7029392"
        ],
        "placetype": [
          "aat:300008680"
        ],
        "name:en": "Osgaig, Loch",
        "id": 7459414
      }
    },
    {
      "geometry": {
        "type": "Point",
        "coordinates": [
          0.766667,
          51.716667
        ]
      },
      "type": "Feature",
      "properties": {
        "hierarchy": [
          "tgn:7459415",
          "tgn:7002445",
          "tgn:1000003",
          "tgn:7008131",
          "tgn:7008591",
          "tgn:7029392"
        ],
        "placetype": [
          "aat:300008791"
        ],
        "name:en": "Osea Island",
        "id": 7459415
      }
    },
    {
      "geometry": {
        "type": "Point",
        "coordinates": [
          -6.433333,
          57.4
        ]
      },
      "type": "Feature",
      "properties": {
        "hierarchy": [
          "tgn:7459416",
          "tgn:7002444",
          "tgn:1000003",
          "tgn:7008082",
          "tgn:7008591",
          "tgn:7029392"
        ],
        "placetype": [
          "aat:300008761"
        ],
        "name:en": "Ose, Glen",
        "id": 7459416
      }
    },
    {
      "geometry": {
        "type": "Point",
        "coordinates": [
          -6.583333,
          57.416667
        ]
      },
      "type": "Feature",
      "properties": {
        "hierarchy": [
          "tgn:7459417",
          "tgn:7002444",
          "tgn:1000003",
          "tgn:7008082",
          "tgn:7008591",
          "tgn:7029392"
        ],
        "placetype": [
          "aat:300008699"
        ],
        "name:en": "Osdale River",
        "id": 7459417
      }
    },
    {
      "geometry": {
        "type": "Point",
        "coordinates": [
          -1.266667,
          50.733333
        ]
      },
      "type": "Feature",
      "properties": {
        "hierarchy": [
          "tgn:7459419",
          "tgn:7002445",
          "tgn:1000003",
          "tgn:7011430",
          "tgn:7008591",
          "tgn:7029392"
        ],
        "placetype": [
          "aat:300008347"
        ],
        "name:en": "Osborne",
        "id": 7459419
      }
    }
  ]
}
