{
  "geometry": {
    "type": "Point",
    "coordinates": [
      7.3333,
      46.6667
    ]
  },
  "type": "Feature",
  "properties": {
    "hierarchy": [
      "tgn:1064394",
      "tgn:7003745",
      "tgn:1000003",
      "tgn:7011731",
      "tgn:7029392"
    ],
    "placetype": [
      "aat:300008347"
    ],
    "id": 1064394,
    "name:xx": "Schwarzsee"
  }
}
