{
  "type": "FeatureCollection",
  "features": [
    {
      "geometry": {
        "type": "Point",
        "coordinates": [
          -1.766667,
          37.25
        ]
      },
      "type": "Feature",
      "properties": {
        "hierarchy": [
          "tgn:4011841",
          "tgn:7002805",
          "tgn:7002758",
          "tgn:1000003",
          "tgn:1000095",
          "tgn:7029392"
        ],
        "placetype": [
          "aat:300008347"
        ],
        "id": 4011841,
        "name:xx": "Villaricos"
      }
    },
    {
      "geometry": {
        "type": "Point",
        "coordinates": [
          -4.916667,
          42.05
        ]
      },
      "type": "Feature",
      "properties": {
        "hierarchy": [
          "tgn:4011842",
          "tgn:7002832",
          "tgn:7001158",
          "tgn:1000003",
          "tgn:1000095",
          "tgn:7029392"
        ],
        "placetype": [
          "aat:300008347"
        ],
        "id": 4011842,
        "name:xx": "Villarramiel"
      }
    },
    {
      "geometry": {
        "type": "Point",
        "coordinates": [
          -1.783333,
          41.466667
        ]
      },
      "type": "Feature",
      "properties": {
        "hierarchy": [
          "tgn:4011844",
          "tgn:7002759",
          "tgn:7002845",
          "tgn:1000003",
          "tgn:1000095",
          "tgn:7029392"
        ],
        "placetype": [
          "aat:300008347"
        ],
        "id": 4011844,
        "name:xx": "Villarroya de la Sierra"
      }
    },
    {
      "geometry": {
        "type": "Point",
        "coordinates": [
          -4.15,
          42.333333
        ]
      },
      "type": "Feature",
      "properties": {
        "hierarchy": [
          "tgn:4011845",
          "tgn:7002810",
          "tgn:7001158",
          "tgn:1000003",
          "tgn:1000095",
          "tgn:7029392"
        ],
        "placetype": [
          "aat:300008347"
        ],
        "id": 4011845,
        "name:xx": "Villaveta"
      }
    },
    {
      "geometry": {
        "type": "Point",
        "coordinates": [
          -3.9,
          40.366667
        ]
      },
      "type": "Feature",
      "properties": {
        "hierarchy": [
          "tgn:4011847",
          "tgn:7010420",
          "tgn:1000003",
          "tgn:7002795",
          "tgn:1000095",
          "tgn:7029392"
        ],
        "placetype": [
          "aat:300008347"
        ],
        "id": 4011847,
        "name:xx": "Villaviciosa de Odón"
      }
    }
  ]
}
