{
  "geometry": {
    "type": "Point",
    "coordinates": [
      -122.1333,
      41.5167
    ]
  },
  "type": "Feature",
  "properties": {
    "hierarchy": [
      "tgn:2763619",
      "tgn:1000001",
      "tgn:7012149",
      "tgn:7007157",
      "tgn:2000189",
      "tgn:7029392"
    ],
    "placetype": [
      "aat:300008798"
    ],
    "id": 2763619,
    "name:xx": "Whaleback, The"
  }
}
