{
  "geometry": {
    "type": "Point",
    "coordinates": [
      -51.5833,
      -20.6667
    ]
  },
  "type": "Feature",
  "properties": {
    "hierarchy": [
      "tgn:1130839",
      "tgn:1001945",
      "tgn:1000047",
      "tgn:7002457",
      "tgn:1000002",
      "tgn:7029392"
    ],
    "placetype": [
      "aat:300008707"
    ],
    "id": 1130839,
    "name:xx": "Tietê"
  }
}
