{
  "geometry": {
    "type": "Point",
    "coordinates": [
      -94.5667,
      47.1333
    ]
  },
  "type": "Feature",
  "properties": {
    "hierarchy": [
      "tgn:2229464",
      "tgn:1000001",
      "tgn:2001009",
      "tgn:7012149",
      "tgn:7007521",
      "tgn:7029392"
    ],
    "placetype": [
      "aat:300008850"
    ],
    "id": 2229464,
    "name:xx": "Cedar Point"
  }
}
