{
  "geometry": {
    "type": "Point",
    "coordinates": [
      -151.2667,
      59.5667
    ]
  },
  "type": "Feature",
  "properties": {
    "hierarchy": [
      "tgn:2577434",
      "tgn:7006450",
      "tgn:1000001",
      "tgn:7019698",
      "tgn:7012149",
      "tgn:7029392"
    ],
    "placetype": [
      "aat:300132316"
    ],
    "id": 2577434,
    "name:xx": "Peterson Bay"
  }
}
