{
  "geometry": {
    "type": "Point",
    "coordinates": [
      -116.05,
      32.65
    ]
  },
  "type": "Feature",
  "properties": {
    "hierarchy": [
      "tgn:2585382",
      "tgn:1000001",
      "tgn:7012149",
      "tgn:2000182",
      "tgn:7007157",
      "tgn:7029392"
    ],
    "placetype": [
      "aat:300008761"
    ],
    "id": 2585382,
    "name:xx": "Pinto Canyon"
  }
}
