{
  "geometry": {
    "type": "Point",
    "coordinates": [
      -120.8833,
      43.6167
    ]
  },
  "type": "Feature",
  "properties": {
    "hierarchy": [
      "tgn:2603282",
      "tgn:1000001",
      "tgn:2001705",
      "tgn:7012149",
      "tgn:7007708",
      "tgn:7029392"
    ],
    "placetype": [
      "aat:300008798"
    ],
    "id": 2603282,
    "name:xx": "Quartz Mountain"
  }
}
