{
  "type": "FeatureCollection",
  "features": [
    {
      "geometry": {
        "type": "Point",
        "coordinates": [
          -161.3833,
          59.45
        ]
      },
      "type": "Feature",
      "properties": {
        "hierarchy": [
          "tgn:2727440",
          "tgn:7006450",
          "tgn:2000069",
          "tgn:1000001",
          "tgn:7012149",
          "tgn:7029392"
        ],
        "placetype": [
          "aat:300008706"
        ],
        "id": 2727440,
        "name:xx": "Trail Creek"
      }
    },
    {
      "geometry": {
        "type": "Point",
        "coordinates": [
          -153.2667,
          59.7833
        ]
      },
      "type": "Feature",
      "properties": {
        "hierarchy": [
          "tgn:2727441",
          "tgn:7006450",
          "tgn:1000001",
          "tgn:7019698",
          "tgn:7012149",
          "tgn:7029392"
        ],
        "placetype": [
          "aat:300008706"
        ],
        "id": 2727441,
        "name:xx": "Trail Creek"
      }
    },
    {
      "geometry": {
        "type": "Point",
        "coordinates": [
          -143.6667,
          61.5333
        ]
      },
      "type": "Feature",
      "properties": {
        "hierarchy": [
          "tgn:2727442",
          "tgn:7006450",
          "tgn:1000001",
          "tgn:7012149",
          "tgn:2000086",
          "tgn:7029392"
        ],
        "placetype": [
          "aat:300008706"
        ],
        "id": 2727442,
        "name:xx": "Trail Creek"
      }
    },
    {
      "geometry": {
        "type": "Point",
        "coordinates": [
          -160.7333,
          63.9167
        ]
      },
      "type": "Feature",
      "properties": {
        "hierarchy": [
          "tgn:2727443",
          "tgn:7006450",
          "tgn:1000001",
          "tgn:7012149",
          "tgn:2000079",
          "tgn:7029392"
        ],
        "placetype": [
          "aat:300008706"
        ],
        "id": 2727443,
        "name:xx": "Trail Creek"
      }
    },
    {
      "geometry": {
        "type": "Point",
        "coordinates": [
          -151.0667,
          65.1833
        ]
      },
      "type": "Feature",
      "properties": {
        "hierarchy": [
          "tgn:2727444",
          "tgn:7006450",
          "tgn:1000001",
          "tgn:7012149",
          "tgn:2000089",
          "tgn:7029392"
        ],
        "placetype": [
          "aat:300008706"
        ],
        "id": 2727444,
        "name:xx": "Trail Creek"
      }
    },
    {
      "geometry": {
        "type": "Point",
        "coordinates": [
          -163.35,
          65.8167
        ]
      },
      "type": "Feature",
      "properties": {
        "hierarchy": [
          "tgn:2727445",
          "tgn:7006450",
          "tgn:1000001",
          "tgn:7012149",
          "tgn:2124014",
          "tgn:7029392"
        ],
        "placetype": [
          "aat:300008706"
        ],
        "id": 2727445,
        "name:xx": "Trail Creek"
      }
    },
    {
      "geometry": {
        "type": "Point",
        "coordinates": [
          -165.75,
          68.15
        ]
      },
      "type": "Feature",
      "properties": {
        "hierarchy": [
          "tgn:2727446",
          "tgn:7006450",
          "tgn:1000001",
          "tgn:7012149",
          "tgn:2124005",
          "tgn:7029392"
        ],
        "placetype": [
          "aat:300008706"
        ],
        "id": 2727446,
        "name:xx": "Trail Creek"
      }
    },
    {
      "geometry": {
        "type": "Point",
        "coordinates": [
          -159.5167,
          59.9833
        ]
      },
      "type": "Feature",
      "properties": {
        "hierarchy": [
          "tgn:2727447",
          "tgn:7006450",
          "tgn:1000001",
          "tgn:2000071",
          "tgn:7012149",
          "tgn:7029392"
        ],
        "placetype": [
          "aat:300008706"
        ],
        "id": 2727447,
        "name:xx": "Trail Creek"
      }
    },
    {
      "geometry": {
        "type": "Point",
        "coordinates": [
          -150.7833,
          61.5667
        ]
      },
      "type": "Feature",
      "properties": {
        "hierarchy": [
          "tgn:2727448",
          "tgn:7006450",
          "tgn:1000001",
          "tgn:2124053",
          "tgn:7012149",
          "tgn:7029392"
        ],
        "placetype": [
          "aat:300008706"
        ],
        "id": 2727448,
        "name:xx": "Trail Creek"
      }
    },
    {
      "geometry": {
        "type": "Point",
        "coordinates": [
          -143.1333,
          63
        ]
      },
      "type": "Feature",
      "properties": {
        "hierarchy": [
          "tgn:2727449",
          "tgn:7006450",
          "tgn:1000001",
          "tgn:7012149",
          "tgn:2000085",
          "tgn:7029392"
        ],
        "placetype": [
          "aat:300008706"
        ],
        "id": 2727449,
        "name:xx": "Trail Creek"
      }
    }
  ]
}
