{
  "geometry": {
    "type": "Point",
    "coordinates": [
      -77.3667,
      41.3333
    ]
  },
  "type": "Feature",
  "properties": {
    "hierarchy": [
      "tgn:2210416",
      "tgn:1000001",
      "tgn:7012149",
      "tgn:1002613",
      "tgn:7007710",
      "tgn:7029392"
    ],
    "placetype": [
      "aat:300008699"
    ],
    "id": 2210416,
    "name:xx": "Bush Run"
  }
}
