{
  "geometry": {
    "type": "Point",
    "coordinates": [
      -105.8167,
      45.2667
    ]
  },
  "type": "Feature",
  "properties": {
    "hierarchy": [
      "tgn:2497210",
      "tgn:1000001",
      "tgn:7012149",
      "tgn:2001297",
      "tgn:7007524",
      "tgn:7029392"
    ],
    "placetype": [
      "aat:300008699"
    ],
    "id": 2497210,
    "name:xx": "Maverick Prong"
  }
}
