{
  "type": "FeatureCollection",
  "features": [
    {
      "geometry": {
        "type": "Point",
        "coordinates": [
          15.233333,
          37.15
        ]
      },
      "type": "Feature",
      "properties": {
        "hierarchy": [
          "tgn:7053250",
          "tgn:1000003",
          "tgn:7003122",
          "tgn:1000080",
          "tgn:7029392"
        ],
        "placetype": [
          "aat:300008804"
        ],
        "id": 7053250,
        "name:xx": "Magnisi, Penisola"
      }
    },
    {
      "geometry": {
        "type": "Point",
        "coordinates": [
          9.4,
          44.516667
        ]
      },
      "type": "Feature",
      "properties": {
        "hierarchy": [
          "tgn:7053251",
          "tgn:1000003",
          "tgn:7003142",
          "tgn:7003236",
          "tgn:1000080",
          "tgn:7029392"
        ],
        "placetype": [
          "aat:300008347"
        ],
        "id": 7053251,
        "name:xx": "Magnasco"
      }
    },
    {
      "geometry": {
        "type": "Point",
        "coordinates": [
          13.178611,
          46.234444
        ]
      },
      "type": "Feature",
      "properties": {
        "hierarchy": [
          "tgn:7053252",
          "tgn:1003506",
          "tgn:1000003",
          "tgn:7002993",
          "tgn:1000080",
          "tgn:7029392"
        ],
        "placetype": [
          "aat:300008347"
        ],
        "id": 7053252,
        "name:xx": "Magnano"
      }
    },
    {
      "geometry": {
        "type": "Point",
        "coordinates": [
          10.4,
          44.166667
        ]
      },
      "type": "Feature",
      "properties": {
        "hierarchy": [
          "tgn:7053253",
          "tgn:7003165",
          "tgn:1000003",
          "tgn:7009760",
          "tgn:1000080",
          "tgn:7029392"
        ],
        "placetype": [
          "aat:300008347"
        ],
        "id": 7053253,
        "name:xx": "Magnano"
      }
    },
    {
      "geometry": {
        "type": "Point",
        "coordinates": [
          14.033333,
          41.3
        ]
      },
      "type": "Feature",
      "properties": {
        "hierarchy": [
          "tgn:7053254",
          "tgn:7003011",
          "tgn:7003005",
          "tgn:1000003",
          "tgn:1000080",
          "tgn:7029392"
        ],
        "placetype": [
          "aat:300008347"
        ],
        "id": 7053254,
        "name:xx": "Magnano"
      }
    },
    {
      "geometry": {
        "type": "Point",
        "coordinates": [
          13.633333,
          42.683333
        ]
      },
      "type": "Feature",
      "properties": {
        "hierarchy": [
          "tgn:7053255",
          "tgn:7009084",
          "tgn:7003001",
          "tgn:1000003",
          "tgn:1000080",
          "tgn:7029392"
        ],
        "placetype": [
          "aat:300008347"
        ],
        "id": 7053255,
        "name:xx": "Magnanella"
      }
    },
    {
      "geometry": {
        "type": "Point",
        "coordinates": [
          14.6,
          41.45
        ]
      },
      "type": "Feature",
      "properties": {
        "hierarchy": [
          "tgn:7053256",
          "tgn:7004595",
          "tgn:7003005",
          "tgn:1000003",
          "tgn:1000080",
          "tgn:7029392"
        ],
        "placetype": [
          "aat:300008699"
        ],
        "id": 7053256,
        "name:xx": "Magnaluno, Torrente"
      }
    },
    {
      "geometry": {
        "type": "Point",
        "coordinates": [
          12.05,
          42.1
        ]
      },
      "type": "Feature",
      "properties": {
        "hierarchy": [
          "tgn:7053258",
          "tgn:7003138",
          "tgn:1000003",
          "tgn:7003080",
          "tgn:1000080",
          "tgn:7029392"
        ],
        "placetype": [
          "aat:300008699"
        ],
        "id": 7053258,
        "name:xx": "Magnaferro, Fosso"
      }
    },
    {
      "geometry": {
        "type": "Point",
        "coordinates": [
          12.6,
          45.716667
        ]
      },
      "type": "Feature",
      "properties": {
        "hierarchy": [
          "tgn:7053259",
          "tgn:7002996",
          "tgn:1000003",
          "tgn:7002997",
          "tgn:1000080",
          "tgn:7029392"
        ],
        "placetype": [
          "aat:300008347"
        ],
        "id": 7053259,
        "name:xx": "Magnadola"
      }
    }
  ]
}
