{
  "geometry": {
    "type": "Point",
    "coordinates": [
      30.827318,
      30.8717
    ]
  },
  "type": "Feature",
  "properties": {
    "hierarchy": [
      "tgn:7539502",
      "tgn:7001242",
      "tgn:7016833",
      "tgn:7001312",
      "tgn:7029392"
    ],
    "placetype": [
      "aat:300008347"
    ],
    "name:en": "Qalīb Abyār",
    "id": 7539502
  }
}
