{
  "geometry": {
    "type": "Point",
    "coordinates": [
      -106.1667,
      35.2333
    ]
  },
  "type": "Feature",
  "properties": {
    "hierarchy": [
      "tgn:2488098",
      "tgn:1000001",
      "tgn:7012149",
      "tgn:2001454",
      "tgn:7007566",
      "tgn:7029392"
    ],
    "placetype": [
      "aat:300000390"
    ],
    "id": 2488098,
    "name:xx": "Magnolia"
  }
}
