{
  "geometry": {
    "type": "Point",
    "coordinates": [
      -53.55,
      1.3667
    ]
  },
  "type": "Feature",
  "properties": {
    "hierarchy": [
      "tgn:1123178",
      "tgn:1001986",
      "tgn:1000047",
      "tgn:7002456",
      "tgn:1000002",
      "tgn:7029392"
    ],
    "placetype": [
      "aat:300008707"
    ],
    "id": 1123178,
    "name:xx": "Cuc"
  }
}
