{
  "geometry": {
    "type": "Point",
    "coordinates": [
      -99.1333,
      32.1667
    ]
  },
  "type": "Feature",
  "properties": {
    "hierarchy": [
      "tgn:2159315",
      "tgn:1000001",
      "tgn:7012149",
      "tgn:2001951",
      "tgn:7007826",
      "tgn:7029392"
    ],
    "placetype": [
      "aat:300008699"
    ],
    "id": 2159315,
    "name:xx": "Bee Branch"
  }
}
