{
  "geometry": {
    "type": "Point",
    "coordinates": [
      -92.05,
      32.75
    ]
  },
  "type": "Feature",
  "properties": {
    "hierarchy": [
      "tgn:2501389",
      "tgn:1000001",
      "tgn:7012149",
      "tgn:2000887",
      "tgn:7007256",
      "tgn:7029392"
    ],
    "placetype": [
      "aat:300008905"
    ],
    "id": 2501389,
    "name:xx": "McGowen Brake"
  }
}
