{
  "type": "FeatureCollection",
  "features": [
    {
      "geometry": {
        "type": "Point",
        "coordinates": [
          -122.1,
          42.9667
        ]
      },
      "type": "Feature",
      "properties": {
        "hierarchy": [
          "tgn:2692700",
          "tgn:1000001",
          "tgn:7012149",
          "tgn:2001714",
          "tgn:7007708",
          "tgn:7029392"
        ],
        "placetype": [
          "aat:300132316"
        ],
        "id": 2692700,
        "name:xx": "Steel Bay"
      }
    },
    {
      "geometry": {
        "type": "Point",
        "coordinates": [
          -87.4833,
          35.4833
        ]
      },
      "type": "Feature",
      "properties": {
        "hierarchy": [
          "tgn:2692701",
          "tgn:1000001",
          "tgn:7012149",
          "tgn:2001887",
          "tgn:7007825",
          "tgn:7029392"
        ],
        "placetype": [
          "aat:300008699"
        ],
        "id": 2692701,
        "name:xx": "Steel Branch"
      }
    },
    {
      "geometry": {
        "type": "Point",
        "coordinates": [
          -88.6333,
          36.2833
        ]
      },
      "type": "Feature",
      "properties": {
        "hierarchy": [
          "tgn:2692702",
          "tgn:1000001",
          "tgn:7012149",
          "tgn:2001928",
          "tgn:7007825",
          "tgn:7029392"
        ],
        "placetype": [
          "aat:300008699"
        ],
        "id": 2692702,
        "name:xx": "Steel Branch"
      }
    },
    {
      "geometry": {
        "type": "Point",
        "coordinates": [
          -97.9167,
          29.2333
        ]
      },
      "type": "Feature",
      "properties": {
        "hierarchy": [
          "tgn:2692703",
          "tgn:1000001",
          "tgn:7012149",
          "tgn:2002095",
          "tgn:7007826",
          "tgn:7029392"
        ],
        "placetype": [
          "aat:300008699"
        ],
        "id": 2692703,
        "name:xx": "Steel Branch"
      }
    },
    {
      "geometry": {
        "type": "Point",
        "coordinates": [
          -81.8833,
          37.05
        ]
      },
      "type": "Feature",
      "properties": {
        "hierarchy": [
          "tgn:2692704",
          "tgn:1000001",
          "tgn:7012149",
          "tgn:2002188",
          "tgn:7007919",
          "tgn:7029392"
        ],
        "placetype": [
          "aat:300008699"
        ],
        "id": 2692704,
        "name:xx": "Steel Branch"
      }
    },
    {
      "geometry": {
        "type": "Point",
        "coordinates": [
          -73.05,
          41.3833
        ]
      },
      "type": "Feature",
      "properties": {
        "hierarchy": [
          "tgn:2692705",
          "tgn:1000001",
          "tgn:1002712",
          "tgn:7012149",
          "tgn:7007159",
          "tgn:7029392"
        ],
        "placetype": [
          "aat:300008699"
        ],
        "id": 2692705,
        "name:xx": "Steel Brook"
      }
    },
    {
      "geometry": {
        "type": "Point",
        "coordinates": [
          -88.65,
          42.8
        ]
      },
      "type": "Feature",
      "properties": {
        "hierarchy": [
          "tgn:2692706",
          "tgn:1000001",
          "tgn:7012149",
          "tgn:7007922",
          "tgn:7029392"
        ],
        "placetype": [
          "aat:300008699"
        ],
        "id": 2692706,
        "name:xx": "Steel Brook"
      }
    },
    {
      "geometry": {
        "type": "Point",
        "coordinates": [
          -122.1667,
          38.45
        ]
      },
      "type": "Feature",
      "properties": {
        "hierarchy": [
          "tgn:2692707",
          "tgn:1000001",
          "tgn:7012149",
          "tgn:7007157",
          "tgn:1002706",
          "tgn:7029392"
        ],
        "placetype": [
          "aat:300008761"
        ],
        "id": 2692707,
        "name:xx": "Steel Canyon"
      }
    },
    {
      "geometry": {
        "type": "Point",
        "coordinates": [
          -107.95,
          38.4
        ]
      },
      "type": "Feature",
      "properties": {
        "hierarchy": [
          "tgn:2692708",
          "tgn:1000001",
          "tgn:7012149",
          "tgn:2000234",
          "tgn:7007158",
          "tgn:7029392"
        ],
        "placetype": [
          "aat:300008761"
        ],
        "id": 2692708,
        "name:xx": "Steel Canyon"
      }
    },
    {
      "geometry": {
        "type": "Point",
        "coordinates": [
          -105.7833,
          38.2333
        ]
      },
      "type": "Feature",
      "properties": {
        "hierarchy": [
          "tgn:2692709",
          "tgn:1000001",
          "tgn:7012149",
          "tgn:7007158",
          "tgn:2000246",
          "tgn:7029392"
        ],
        "placetype": [
          "aat:300008761"
        ],
        "id": 2692709,
        "name:xx": "Steel Canyon"
      }
    }
  ]
}
