{
  "type": "FeatureCollection",
  "features": [
    {
      "geometry": {
        "type": "Point",
        "coordinates": [
          11.55,
          48.433333
        ]
      },
      "type": "Feature",
      "properties": {
        "hierarchy": [
          "tgn:4003540",
          "tgn:7003669",
          "tgn:1000003",
          "tgn:7000084",
          "tgn:7029392"
        ],
        "placetype": [
          "aat:300008347"
        ],
        "id": 4003540,
        "name:xx": "Eglhausen"
      }
    },
    {
      "geometry": {
        "type": "Point",
        "coordinates": [
          4.65,
          52.616667
        ]
      },
      "type": "Feature",
      "properties": {
        "hierarchy": [
          "tgn:4003541",
          "tgn:1000003",
          "tgn:7006951",
          "tgn:7016845",
          "tgn:7029392"
        ],
        "placetype": [
          "aat:300008347"
        ],
        "name:nl": "Egmond aan den Hoef",
        "id": 4003541
      }
    },
    {
      "geometry": {
        "type": "Point",
        "coordinates": [
          7.216667,
          50.966667
        ]
      },
      "type": "Feature",
      "properties": {
        "hierarchy": [
          "tgn:4003546",
          "tgn:1000003",
          "tgn:7003677",
          "tgn:7000084",
          "tgn:7029392"
        ],
        "placetype": [
          "aat:300008347"
        ],
        "id": 4003546,
        "name:xx": "Ehrenfeld"
      }
    },
    {
      "geometry": {
        "type": "Point",
        "coordinates": [
          11.316667,
          50.2
        ]
      },
      "type": "Feature",
      "properties": {
        "hierarchy": [
          "tgn:4003547",
          "tgn:7003669",
          "tgn:1000003",
          "tgn:7000084",
          "tgn:7029392"
        ],
        "placetype": [
          "aat:300008347"
        ],
        "id": 4003547,
        "name:xx": "Eichenbühl"
      }
    },
    {
      "geometry": {
        "type": "Point",
        "coordinates": [
          9.7,
          50.483333
        ]
      },
      "type": "Feature",
      "properties": {
        "hierarchy": [
          "tgn:4003548",
          "tgn:1000003",
          "tgn:7003678",
          "tgn:7000084",
          "tgn:7029392"
        ],
        "placetype": [
          "aat:300008347"
        ],
        "id": 4003548,
        "name:xx": "Eichenzell"
      }
    }
  ]
}
