{
  "geometry": {
    "type": "Point",
    "coordinates": [
      -91.4833,
      35.65
    ]
  },
  "type": "Feature",
  "properties": {
    "hierarchy": [
      "tgn:2564863",
      "tgn:1000001",
      "tgn:7016172",
      "tgn:7012149",
      "tgn:2000136",
      "tgn:7029392"
    ],
    "placetype": [
      "aat:300008791"
    ],
    "id": 2564863,
    "name:xx": "Padgett Island"
  }
}
