{
  "geometry": {
    "type": "Point",
    "coordinates": [
      49.1167,
      36.7833
    ]
  },
  "type": "Feature",
  "properties": {
    "hierarchy": [
      "tgn:1128897",
      "tgn:1000004",
      "tgn:7000231",
      "tgn:7029392"
    ],
    "placetype": [
      "aat:300008707"
    ],
    "id": 1128897,
    "name:xx": "Rūdkhāneh-ye Qezel Owzan"
  }
}
