{
  "type": "FeatureCollection",
  "features": [
    {
      "geometry": {
        "type": "Point",
        "coordinates": [
          -2.833333,
          52.433333
        ]
      },
      "type": "Feature",
      "properties": {
        "hierarchy": [
          "tgn:4004746",
          "tgn:7002445",
          "tgn:1000003",
          "tgn:7012034",
          "tgn:7008591",
          "tgn:7029392"
        ],
        "placetype": [
          "aat:300008347"
        ],
        "name:en": "Halford",
        "id": 4004746
      }
    },
    {
      "geometry": {
        "type": "Point",
        "coordinates": [
          19.5833,
          48.35
        ]
      },
      "type": "Feature",
      "properties": {
        "hierarchy": [
          "tgn:4004747",
          "tgn:7027131",
          "tgn:1000003",
          "tgn:7011765",
          "tgn:7029392"
        ],
        "placetype": [
          "aat:300008347"
        ],
        "id": 4004747,
        "name:xx": "Halič"
      }
    }
  ]
}
