{
  "geometry": {
    "type": "Point",
    "coordinates": [
      -86.8667,
      41.2833
    ]
  },
  "type": "Feature",
  "properties": {
    "hierarchy": [
      "tgn:2486867",
      "tgn:1000001",
      "tgn:7012149",
      "tgn:1002561",
      "tgn:7007252",
      "tgn:7029392"
    ],
    "placetype": [
      "aat:300006075"
    ],
    "id": 2486867,
    "name:xx": "Lee Ditch"
  }
}
