{
  "type": "FeatureCollection",
  "features": [
    {
      "geometry": {
        "type": "Point",
        "coordinates": [
          -1.766667,
          54.266667
        ]
      },
      "type": "Feature",
      "properties": {
        "hierarchy": [
          "tgn:7449952",
          "tgn:7002445",
          "tgn:1000003",
          "tgn:7008166",
          "tgn:7008591",
          "tgn:7029392"
        ],
        "placetype": [
          "aat:300008347"
        ],
        "name:en": "East Witton",
        "id": 7449952
      }
    },
    {
      "geometry": {
        "type": "Point",
        "coordinates": [
          -4.753611,
          51.71
        ]
      },
      "type": "Feature",
      "properties": {
        "hierarchy": [
          "tgn:7449955",
          "tgn:7002443",
          "tgn:1000003",
          "tgn:7018993",
          "tgn:7008591",
          "tgn:7029392"
        ],
        "placetype": [
          "aat:300008347"
        ],
        "name:en": "East Williamston",
        "id": 7449955
      }
    },
    {
      "geometry": {
        "type": "Point",
        "coordinates": [
          0.866667,
          51.183333
        ]
      },
      "type": "Feature",
      "properties": {
        "hierarchy": [
          "tgn:7449957",
          "tgn:7002445",
          "tgn:1000003",
          "tgn:7008153",
          "tgn:7008591",
          "tgn:7029392"
        ],
        "placetype": [
          "aat:300387502"
        ],
        "name:en": "Eastwell Park",
        "id": 7449957
      }
    }
  ]
}
