{
  "geometry": {
    "type": "Point",
    "coordinates": [
      -88.7167,
      45.1833
    ]
  },
  "type": "Feature",
  "properties": {
    "hierarchy": [
      "tgn:2121589",
      "tgn:1000001",
      "tgn:7012149",
      "tgn:2002333",
      "tgn:7007922",
      "tgn:7029392"
    ],
    "placetype": [
      "aat:300008347"
    ],
    "id": 2121589,
    "name:xx": "Langlade"
  }
}
