{
  "geometry": {
    "type": "Point",
    "coordinates": [
      -117.65,
      48.3167
    ]
  },
  "type": "Feature",
  "properties": {
    "hierarchy": [
      "tgn:2256014",
      "tgn:1000001",
      "tgn:7012149",
      "tgn:2002250",
      "tgn:7007920",
      "tgn:7029392"
    ],
    "placetype": [
      "aat:300000390"
    ],
    "id": 2256014,
    "name:xx": "Copper King Number 2 Mine"
  }
}
