{
  "type": "FeatureCollection",
  "features": [
    {
      "geometry": {
        "type": "Point",
        "coordinates": [
          -2.5,
          53.466667
        ]
      },
      "type": "Feature",
      "properties": {
        "hierarchy": [
          "tgn:1029320",
          "tgn:7002445",
          "tgn:1003664",
          "tgn:1000003",
          "tgn:7026570",
          "tgn:7008591",
          "tgn:7029392"
        ],
        "placetype": [
          "aat:300008347"
        ],
        "name:en": "Glazebury",
        "id": 1029320
      }
    },
    {
      "geometry": {
        "type": "Point",
        "coordinates": [
          0.666667,
          52.1
        ]
      },
      "type": "Feature",
      "properties": {
        "hierarchy": [
          "tgn:1029321",
          "tgn:7002445",
          "tgn:1000003",
          "tgn:7008185",
          "tgn:7008591",
          "tgn:7029392"
        ],
        "placetype": [
          "aat:300008347"
        ],
        "name:en": "Glemsford",
        "id": 1029321
      }
    },
    {
      "geometry": {
        "type": "Point",
        "coordinates": [
          -1.2,
          52.633333
        ]
      },
      "type": "Feature",
      "properties": {
        "hierarchy": [
          "tgn:1029322",
          "tgn:7002445",
          "tgn:1000003",
          "tgn:7008155",
          "tgn:7008591",
          "tgn:7029392"
        ],
        "placetype": [
          "aat:300008347"
        ],
        "name:en": "Glenfield",
        "id": 1029322
      }
    },
    {
      "geometry": {
        "type": "Point",
        "coordinates": [
          -1.9,
          53.416667
        ]
      },
      "type": "Feature",
      "properties": {
        "hierarchy": [
          "tgn:1029323",
          "tgn:7002445",
          "tgn:1000003",
          "tgn:7008118",
          "tgn:7008591",
          "tgn:7029392"
        ],
        "placetype": [
          "aat:300008347"
        ],
        "id": 1029323,
        "name:ang": "Glosop"
      }
    },
    {
      "geometry": {
        "type": "Point",
        "coordinates": [
          -2,
          53.9
        ]
      },
      "type": "Feature",
      "properties": {
        "hierarchy": [
          "tgn:1029325",
          "tgn:7002445",
          "tgn:1000003",
          "tgn:7008166",
          "tgn:7008591",
          "tgn:7029392"
        ],
        "placetype": [
          "aat:300008347"
        ],
        "name:en": "Glusburn",
        "id": 1029325
      }
    },
    {
      "geometry": {
        "type": "Point",
        "coordinates": [
          -2.25,
          52.783333
        ]
      },
      "type": "Feature",
      "properties": {
        "hierarchy": [
          "tgn:1029327",
          "tgn:7002445",
          "tgn:1000003",
          "tgn:7008174",
          "tgn:7008591",
          "tgn:7029392"
        ],
        "placetype": [
          "aat:300008347"
        ],
        "name:en": "Gnosall",
        "id": 1029327
      }
    },
    {
      "geometry": {
        "type": "Point",
        "coordinates": [
          -0.716667,
          54.383333
        ]
      },
      "type": "Feature",
      "properties": {
        "hierarchy": [
          "tgn:1029328",
          "tgn:7002445",
          "tgn:1000003",
          "tgn:7008166",
          "tgn:7008591",
          "tgn:7029392"
        ],
        "placetype": [
          "aat:300008347"
        ],
        "name:en": "Goathland",
        "id": 1029328
      }
    }
  ]
}
