{
  "type": "FeatureCollection",
  "features": [
    {
      "geometry": {
        "type": "Point",
        "coordinates": [
          -98.7,
          20.466667
        ]
      },
      "type": "Feature",
      "properties": {
        "hierarchy": [
          "tgn:7368780",
          "tgn:7005587",
          "tgn:1000001",
          "tgn:7005560",
          "tgn:7029392"
        ],
        "placetype": [
          "aat:300008347"
        ],
        "id": 7368780,
        "name:xx": "Guadalupe"
      }
    },
    {
      "geometry": {
        "type": "Point",
        "coordinates": [
          -102.866667,
          20.35
        ]
      },
      "type": "Feature",
      "properties": {
        "hierarchy": [
          "tgn:7368781",
          "tgn:7005586",
          "tgn:1000001",
          "tgn:7005560",
          "tgn:7029392"
        ],
        "placetype": [
          "aat:300008347"
        ],
        "id": 7368781,
        "name:xx": "Guadalupe"
      }
    },
    {
      "geometry": {
        "type": "Point",
        "coordinates": [
          -100.95,
          20.283333
        ]
      },
      "type": "Feature",
      "properties": {
        "hierarchy": [
          "tgn:7368782",
          "tgn:7005584",
          "tgn:1000001",
          "tgn:7005560",
          "tgn:7029392"
        ],
        "placetype": [
          "aat:300008347"
        ],
        "id": 7368782,
        "name:xx": "Guadalupe"
      }
    },
    {
      "geometry": {
        "type": "Point",
        "coordinates": [
          -99.783333,
          20.283333
        ]
      },
      "type": "Feature",
      "properties": {
        "hierarchy": [
          "tgn:7368783",
          "tgn:7005587",
          "tgn:1000001",
          "tgn:7005560",
          "tgn:7029392"
        ],
        "placetype": [
          "aat:300008347"
        ],
        "id": 7368783,
        "name:xx": "Guadalupe"
      }
    },
    {
      "geometry": {
        "type": "Point",
        "coordinates": [
          -100.716667,
          20.05
        ]
      },
      "type": "Feature",
      "properties": {
        "hierarchy": [
          "tgn:7368784",
          "tgn:7005584",
          "tgn:1000001",
          "tgn:7005560",
          "tgn:7029392"
        ],
        "placetype": [
          "aat:300008347"
        ],
        "id": 7368784,
        "name:xx": "Guadalupe"
      }
    },
    {
      "geometry": {
        "type": "Point",
        "coordinates": [
          -102.683333,
          19.883333
        ]
      },
      "type": "Feature",
      "properties": {
        "hierarchy": [
          "tgn:7368785",
          "tgn:1000001",
          "tgn:7005590",
          "tgn:7005560",
          "tgn:7029392"
        ],
        "placetype": [
          "aat:300008347"
        ],
        "id": 7368785,
        "name:xx": "Guadalupe"
      }
    },
    {
      "geometry": {
        "type": "Point",
        "coordinates": [
          -98.566667,
          19.766667
        ]
      },
      "type": "Feature",
      "properties": {
        "hierarchy": [
          "tgn:7368786",
          "tgn:7005587",
          "tgn:1000001",
          "tgn:7005560",
          "tgn:7029392"
        ],
        "placetype": [
          "aat:300008347"
        ],
        "id": 7368786,
        "name:xx": "Guadalupe"
      }
    },
    {
      "geometry": {
        "type": "Point",
        "coordinates": [
          -99.266667,
          19.616667
        ]
      },
      "type": "Feature",
      "properties": {
        "hierarchy": [
          "tgn:7368787",
          "tgn:1000001",
          "tgn:1001893",
          "tgn:7005560",
          "tgn:7029392"
        ],
        "placetype": [
          "aat:300008347"
        ],
        "id": 7368787,
        "name:xx": "Guadalupe"
      }
    },
    {
      "geometry": {
        "type": "Point",
        "coordinates": [
          -110.633333,
          29.15
        ]
      },
      "type": "Feature",
      "properties": {
        "hierarchy": [
          "tgn:7368788",
          "tgn:1000001",
          "tgn:1001960",
          "tgn:7005560",
          "tgn:7029392"
        ],
        "placetype": [
          "aat:300008347"
        ],
        "id": 7368788,
        "name:xx": "Italia"
      }
    },
    {
      "geometry": {
        "type": "Point",
        "coordinates": [
          -100.316667,
          21.833333
        ]
      },
      "type": "Feature",
      "properties": {
        "hierarchy": [
          "tgn:7368789",
          "tgn:1000001",
          "tgn:7005594",
          "tgn:7005560",
          "tgn:7029392"
        ],
        "placetype": [
          "aat:300008347"
        ],
        "id": 7368789,
        "name:xx": "Itacate"
      }
    }
  ]
}
