{
  "geometry": {
    "type": "Point",
    "coordinates": [
      -91.6333,
      41.3667
    ]
  },
  "type": "Feature",
  "properties": {
    "hierarchy": [
      "tgn:2355476",
      "tgn:1000001",
      "tgn:7012149",
      "tgn:7007253",
      "tgn:7029392"
    ],
    "placetype": [
      "aat:300008706"
    ],
    "id": 2355476,
    "name:xx": "Goose Creek"
  }
}
