{
  "geometry": {
    "type": "Point",
    "coordinates": [
      80.888,
      17.668
    ]
  },
  "type": "Feature",
  "properties": {
    "hierarchy": [
      "tgn:1074771",
      "tgn:1001828",
      "tgn:1000004",
      "tgn:7000198",
      "tgn:7029392"
    ],
    "placetype": [
      "aat:300008347"
    ],
    "name:en": "Bhadrāchalam",
    "id": 1074771
  }
}
