{
  "geometry": {
    "type": "Point",
    "coordinates": [
      66.65,
      51.6667
    ]
  },
  "type": "Feature",
  "properties": {
    "hierarchy": [
      "tgn:1137689",
      "tgn:1000004",
      "tgn:7012925",
      "tgn:7014786",
      "tgn:7029392"
    ],
    "placetype": [
      "aat:300008347"
    ],
    "id": 1137689,
    "name:xx": "Komsomol'skiy"
  }
}
