{
  "geometry": {
    "type": "Point",
    "coordinates": [
      -99.79,
      19.3125
    ]
  },
  "type": "Feature",
  "properties": {
    "hierarchy": [
      "tgn:7399144",
      "tgn:1000001",
      "tgn:1001893",
      "tgn:7005560",
      "tgn:7029392"
    ],
    "placetype": [
      "aat:300008347"
    ],
    "id": 7399144,
    "name:xx": "Cañada de Guadarrama"
  }
}
