{
  "geometry": {
    "type": "Point",
    "coordinates": [
      -81.0333,
      36.8833
    ]
  },
  "type": "Feature",
  "properties": {
    "hierarchy": [
      "tgn:2744017",
      "tgn:1000001",
      "tgn:7012149",
      "tgn:2002196",
      "tgn:7007919",
      "tgn:7029392"
    ],
    "placetype": [
      "aat:300008699"
    ],
    "id": 2744017,
    "name:xx": "Venrick Run"
  }
}
