{
  "geometry": {
    "type": "Point",
    "coordinates": [
      -119.3333,
      48.0167
    ]
  },
  "type": "Feature",
  "properties": {
    "hierarchy": [
      "tgn:2652172",
      "tgn:1000001",
      "tgn:2002242",
      "tgn:7012149",
      "tgn:7007920",
      "tgn:7029392"
    ],
    "placetype": [
      "aat:300008697"
    ],
    "id": 2652172,
    "name:xx": "Sellers Spring"
  }
}
