{
  "geometry": {
    "type": "Point",
    "coordinates": [
      13.2667,
      -1.1833
    ]
  },
  "type": "Feature",
  "properties": {
    "hierarchy": [
      "tgn:1125866",
      "tgn:1001680",
      "tgn:7001242",
      "tgn:1000164",
      "tgn:7029392"
    ],
    "placetype": [
      "aat:300008707"
    ],
    "id": 1125866,
    "name:xx": "Lékoni"
  }
}
