{
  "geometry": {
    "type": "Point",
    "coordinates": [
      -99.05,
      16.95
    ]
  },
  "type": "Feature",
  "properties": {
    "hierarchy": [
      "tgn:7407042",
      "tgn:7005585",
      "tgn:1000001",
      "tgn:7005560",
      "tgn:7029392"
    ],
    "placetype": [
      "aat:300008795"
    ],
    "id": 7407042,
    "name:xx": "Dcozalzin, Cerro"
  }
}
