{
  "geometry": {
    "type": "Point",
    "coordinates": [
      -120.2167,
      41.75
    ]
  },
  "type": "Feature",
  "properties": {
    "hierarchy": [
      "tgn:2655691",
      "tgn:1000001",
      "tgn:7012149",
      "tgn:7007157",
      "tgn:2000186",
      "tgn:7029392"
    ],
    "placetype": [
      "aat:300008761"
    ],
    "id": 2655691,
    "name:xx": "Shartell Canyon"
  }
}
