{
  "geometry": {
    "type": "Point",
    "coordinates": [
      -88.6833,
      45.2833
    ]
  },
  "type": "Feature",
  "properties": {
    "hierarchy": [
      "tgn:2495309",
      "tgn:1000001",
      "tgn:7012149",
      "tgn:2002333",
      "tgn:7007922",
      "tgn:7029392"
    ],
    "placetype": [
      "aat:300008680"
    ],
    "id": 2495309,
    "name:xx": "Mary Lake"
  }
}
