{
  "geometry": {
    "type": "Point",
    "coordinates": [
      -104.7167,
      39.0833
    ]
  },
  "type": "Feature",
  "properties": {
    "hierarchy": [
      "tgn:2339216",
      "tgn:1000001",
      "tgn:7012149",
      "tgn:7014097",
      "tgn:7007158",
      "tgn:7029392"
    ],
    "placetype": [
      "aat:300006191"
    ],
    "id": 2339216,
    "name:xx": "Franktown Parker FPE-5 Reservoir"
  }
}
