{
  "geometry": {
    "type": "Point",
    "coordinates": [
      -107.5333,
      47.8333
    ]
  },
  "type": "Feature",
  "properties": {
    "hierarchy": [
      "tgn:2245960",
      "tgn:1000001",
      "tgn:7012149",
      "tgn:2001295",
      "tgn:7007524",
      "tgn:7029392"
    ],
    "placetype": [
      "aat:300008761"
    ],
    "id": 2245960,
    "name:xx": "Coal Mine Coulee"
  }
}
