{
  "type": "FeatureCollection",
  "features": [
    {
      "geometry": {
        "type": "Point",
        "coordinates": [
          -74.65,
          5.7333
        ]
      },
      "type": "Feature",
      "properties": {
        "hierarchy": [
          "tgn:1127670",
          "tgn:1000583",
          "tgn:1000050",
          "tgn:1000002",
          "tgn:7029392"
        ],
        "placetype": [
          "aat:300008707"
        ],
        "id": 1127670,
        "name:xx": "Negro"
      }
    },
    {
      "geometry": {
        "type": "Point",
        "coordinates": [
          -57.1833,
          -24.3833
        ]
      },
      "type": "Feature",
      "properties": {
        "hierarchy": [
          "tgn:1127671",
          "tgn:7002636",
          "tgn:1000730",
          "tgn:1000002",
          "tgn:1000055",
          "tgn:7029392"
        ],
        "placetype": [
          "aat:300008707"
        ],
        "id": 1127671,
        "name:xx": "Negro, Río"
      }
    },
    {
      "geometry": {
        "type": "Point",
        "coordinates": [
          -63.5,
          -0.5
        ]
      },
      "type": "Feature",
      "properties": {
        "hierarchy": [
          "tgn:1127672",
          "tgn:1000002",
          "tgn:7029392"
        ],
        "placetype": [
          "aat:300008707"
        ],
        "id": 1127672,
        "name:xx": "Negro"
      }
    },
    {
      "geometry": {
        "type": "Point",
        "coordinates": [
          -72.2,
          9.5833
        ]
      },
      "type": "Feature",
      "properties": {
        "hierarchy": [
          "tgn:1127673",
          "tgn:1001985",
          "tgn:1000002",
          "tgn:1000059",
          "tgn:7029392"
        ],
        "placetype": [
          "aat:300008707"
        ],
        "id": 1127673,
        "name:xx": "Negro, Río"
      }
    },
    {
      "geometry": {
        "type": "Point",
        "coordinates": [
          -123.4167,
          45.7167
        ]
      },
      "type": "Feature",
      "properties": {
        "hierarchy": [
          "tgn:1127674",
          "tgn:1000001",
          "tgn:7012149",
          "tgn:7007708",
          "tgn:7029392"
        ],
        "placetype": [
          "aat:300008707"
        ],
        "id": 1127674,
        "name:xx": "Nehalem"
      }
    },
    {
      "geometry": {
        "type": "Point",
        "coordinates": [
          115.6333,
          22.9
        ]
      },
      "type": "Feature",
      "properties": {
        "hierarchy": [
          "tgn:1127675",
          "tgn:1000004",
          "tgn:7005232",
          "tgn:1000111",
          "tgn:7029392"
        ],
        "placetype": [
          "aat:300008707"
        ],
        "id": 1127675,
        "name:xx": "Neihe"
      }
    },
    {
      "geometry": {
        "type": "Point",
        "coordinates": [
          -92.5,
          57.0667
        ]
      },
      "type": "Feature",
      "properties": {
        "hierarchy": [
          "tgn:1127679",
          "tgn:7005685",
          "tgn:1000001",
          "tgn:7005734",
          "tgn:7029392"
        ],
        "placetype": [
          "aat:300008707"
        ],
        "id": 1127679,
        "name:xx": "Nelson River"
      }
    }
  ]
}
