{
  "geometry": {
    "type": "Point",
    "coordinates": [
      101.35,
      3.8667
    ]
  },
  "type": "Feature",
  "properties": {
    "hierarchy": [
      "tgn:1082997",
      "tgn:7000317",
      "tgn:1000004",
      "tgn:7016763",
      "tgn:1000128",
      "tgn:7029392"
    ],
    "placetype": [
      "aat:300008347"
    ],
    "id": 1082997,
    "name:xx": "Terolak"
  }
}
