{
  "geometry": {
    "type": "Point",
    "coordinates": [
      -89.0667,
      42.3333
    ]
  },
  "type": "Feature",
  "properties": {
    "hierarchy": [
      "tgn:2777498",
      "tgn:1000001",
      "tgn:7012149",
      "tgn:1003030",
      "tgn:7007251",
      "tgn:7029392"
    ],
    "placetype": [
      "aat:300008863"
    ],
    "id": 2777498,
    "name:xx": "Winnebago County Forest"
  }
}
