{
  "geometry": {
    "type": "Point",
    "coordinates": [
      5.75,
      47.7833
    ]
  },
  "type": "Feature",
  "properties": {
    "hierarchy": [
      "tgn:7009036",
      "tgn:1000003",
      "tgn:7002881",
      "tgn:1000070",
      "tgn:7029392"
    ],
    "placetype": [
      "aat:300008347"
    ],
    "id": 7009036,
    "name:xx": "Chauvirey-le-Châtel"
  }
}
