{
  "geometry": {
    "type": "Point",
    "coordinates": [
      -74.15,
      41.2833
    ]
  },
  "type": "Feature",
  "properties": {
    "hierarchy": [
      "tgn:2644387",
      "tgn:1000001",
      "tgn:7012149",
      "tgn:1002751",
      "tgn:7007568",
      "tgn:7029392"
    ],
    "placetype": [
      "aat:300008680"
    ],
    "id": 2644387,
    "name:xx": "Sapphire, Lake"
  }
}
