{
  "geometry": {
    "type": "Point",
    "coordinates": [
      -120.6333,
      41.75
    ]
  },
  "type": "Feature",
  "properties": {
    "hierarchy": [
      "tgn:2262410",
      "tgn:1000001",
      "tgn:7012149",
      "tgn:7007157",
      "tgn:2000186",
      "tgn:7029392"
    ],
    "placetype": [
      "aat:300006191"
    ],
    "id": 2262410,
    "name:xx": "Cow Head Tank"
  }
}
