{
  "geometry": {
    "type": "Point",
    "coordinates": [
      -94.4333,
      34.1833
    ]
  },
  "type": "Feature",
  "properties": {
    "hierarchy": [
      "tgn:2138542",
      "tgn:1000001",
      "tgn:7012149",
      "tgn:7029392"
    ],
    "placetype": [
      "aat:300008706"
    ],
    "id": 2138542,
    "name:xx": "Ash Creek"
  }
}
