{
  "geometry": {
    "type": "Point",
    "coordinates": [
      -91.7667,
      35.7667
    ]
  },
  "type": "Feature",
  "properties": {
    "hierarchy": [
      "tgn:2237771",
      "tgn:1000001",
      "tgn:7016172",
      "tgn:7012149",
      "tgn:2000136",
      "tgn:7029392"
    ],
    "placetype": [
      "aat:300008706"
    ],
    "id": 2237771,
    "name:xx": "Chinquapin Creek"
  }
}
