{
  "geometry": {
    "type": "Point",
    "coordinates": [
      -80.4167,
      36.2333
    ]
  },
  "type": "Feature",
  "properties": {
    "hierarchy": [
      "tgn:2386624",
      "tgn:1000001",
      "tgn:7012149",
      "tgn:2001494",
      "tgn:7007709",
      "tgn:7029392"
    ],
    "placetype": [
      "aat:300008347"
    ],
    "id": 2386624,
    "name:xx": "Heritage Village"
  }
}
