{
  "geometry": {
    "type": "Point",
    "coordinates": [
      -77.6333,
      43.0167
    ]
  },
  "type": "Feature",
  "properties": {
    "hierarchy": [
      "tgn:2610640",
      "tgn:1000001",
      "tgn:7012149",
      "tgn:1002681",
      "tgn:7007568",
      "tgn:7029392"
    ],
    "placetype": [
      "aat:300008706"
    ],
    "id": 2610640,
    "name:xx": "Red Creek"
  }
}
