{
  "geometry": {
    "type": "Point",
    "coordinates": [
      -111.4667,
      33.4333
    ]
  },
  "type": "Feature",
  "properties": {
    "hierarchy": [
      "tgn:2566124",
      "tgn:1000001",
      "tgn:7006451",
      "tgn:7012149",
      "tgn:2000101",
      "tgn:7029392"
    ],
    "placetype": [
      "aat:300000390"
    ],
    "id": 2566124,
    "name:xx": "Palmer Mine"
  }
}
