{
  "geometry": {
    "type": "Point",
    "coordinates": [
      -106.3333,
      39.0333
    ]
  },
  "type": "Feature",
  "properties": {
    "hierarchy": [
      "tgn:2332933",
      "tgn:1000001",
      "tgn:7012149",
      "tgn:7007158",
      "tgn:7029392"
    ],
    "placetype": [
      "aat:300008706"
    ],
    "id": 2332933,
    "name:xx": "Flume Creek"
  }
}
