{
  "geometry": {
    "type": "Point",
    "coordinates": [
      78.99713,
      24.786999
    ]
  },
  "type": "Feature",
  "properties": {
    "hierarchy": [
      "tgn:7584544",
      "tgn:1000004",
      "tgn:7000198",
      "tgn:1001894",
      "tgn:7029392"
    ],
    "placetype": [
      "aat:300008347"
    ],
    "name:en": "Karmāsin Chhoti",
    "id": 7584544
  }
}
