{
  "geometry": {
    "type": "Point",
    "coordinates": [
      -84.1667,
      42.6667
    ]
  },
  "type": "Feature",
  "properties": {
    "hierarchy": [
      "tgn:2053672",
      "tgn:1000001",
      "tgn:7012149",
      "tgn:1002502",
      "tgn:7007520",
      "tgn:7029392"
    ],
    "placetype": [
      "aat:300008347"
    ],
    "id": 2053672,
    "name:xx": "Webberville"
  }
}
