{
  "geometry": {
    "type": "Point",
    "coordinates": [
      24.372,
      58.288
    ]
  },
  "type": "Feature",
  "properties": {
    "hierarchy": [
      "tgn:1113556",
      "tgn:7006638",
      "tgn:1000003",
      "tgn:7006540",
      "tgn:7029392"
    ],
    "placetype": [
      "aat:300132316"
    ],
    "name:en": "Pärnu Laht",
    "id": 1113556
  }
}
