{
  "geometry": {
    "type": "Point",
    "coordinates": [
      78.384642,
      24.967147
    ]
  },
  "type": "Feature",
  "properties": {
    "hierarchy": [
      "tgn:7585294",
      "tgn:1000004",
      "tgn:7000198",
      "tgn:7016722",
      "tgn:7029392"
    ],
    "placetype": [
      "aat:300008347"
    ],
    "name:en": "Bādībar",
    "id": 7585294
  }
}
