{
  "geometry": {
    "type": "Point",
    "coordinates": [
      -78.2833,
      37.8167
    ]
  },
  "type": "Feature",
  "properties": {
    "hierarchy": [
      "tgn:2772692",
      "tgn:1000001",
      "tgn:7012149",
      "tgn:2002159",
      "tgn:7007919",
      "tgn:7029392"
    ],
    "placetype": [
      "aat:300008706"
    ],
    "id": 2772692,
    "name:xx": "Williams Creek"
  }
}
