{
  "geometry": {
    "type": "Point",
    "coordinates": [
      -123.1833,
      45.5833
    ]
  },
  "type": "Feature",
  "properties": {
    "hierarchy": [
      "tgn:2543376",
      "tgn:1000001",
      "tgn:7012149",
      "tgn:1002994",
      "tgn:7007708",
      "tgn:7029392"
    ],
    "placetype": [
      "aat:300008697"
    ],
    "id": 2543376,
    "name:xx": "Normandin Spring"
  }
}
