{
  "geometry": {
    "type": "Point",
    "coordinates": [
      -86.8333,
      32.0833
    ]
  },
  "type": "Feature",
  "properties": {
    "hierarchy": [
      "tgn:2602757",
      "tgn:7002659",
      "tgn:1000001",
      "tgn:7012149",
      "tgn:2000042",
      "tgn:7029392"
    ],
    "placetype": [
      "aat:300006191"
    ],
    "id": 2602757,
    "name:xx": "Quailwood Farms Lakes"
  }
}
