{
  "geometry": {
    "type": "Point",
    "coordinates": [
      -79.5667,
      34.9833
    ]
  },
  "type": "Feature",
  "properties": {
    "hierarchy": [
      "tgn:2075624",
      "tgn:1000001",
      "tgn:7012149",
      "tgn:2001533",
      "tgn:7007709",
      "tgn:7029392"
    ],
    "placetype": [
      "aat:300008347"
    ],
    "id": 2075624,
    "name:xx": "Marston"
  }
}
