{
  "geometry": {
    "type": "Point",
    "coordinates": [
      -87.25,
      38.3667
    ]
  },
  "type": "Feature",
  "properties": {
    "hierarchy": [
      "tgn:2149358",
      "tgn:1000001",
      "tgn:7012149",
      "tgn:2000551",
      "tgn:7007252",
      "tgn:7029392"
    ],
    "placetype": [
      "aat:300006075"
    ],
    "id": 2149358,
    "name:xx": "Barren Ditch"
  }
}
