{
  "geometry": {
    "type": "Point",
    "coordinates": [
      -82.45,
      35.3833
    ]
  },
  "type": "Feature",
  "properties": {
    "hierarchy": [
      "tgn:2159995",
      "tgn:1000001",
      "tgn:7012149",
      "tgn:2001504",
      "tgn:7007709",
      "tgn:7029392"
    ],
    "placetype": [
      "aat:300006191"
    ],
    "id": 2159995,
    "name:xx": "Beech Lake"
  }
}
