{
  "geometry": {
    "type": "Point",
    "coordinates": [
      -81.2833,
      38.0667
    ]
  },
  "type": "Feature",
  "properties": {
    "hierarchy": [
      "tgn:2170346",
      "tgn:1000001",
      "tgn:2002261",
      "tgn:7012149",
      "tgn:7013961",
      "tgn:7029392"
    ],
    "placetype": [
      "aat:300008699"
    ],
    "id": 2170346,
    "name:xx": "Big Righthand Fork"
  }
}
