{
  "geometry": {
    "type": "Point",
    "coordinates": [
      46.8333,
      14.9833
    ]
  },
  "type": "Feature",
  "properties": {
    "hierarchy": [
      "tgn:1084951",
      "tgn:1000139",
      "tgn:7004345",
      "tgn:1000004",
      "tgn:7000261",
      "tgn:7029392"
    ],
    "placetype": [
      "aat:300008347"
    ],
    "id": 1084951,
    "name:xx": "ʻIyādh"
  }
}
