{
  "geometry": {
    "type": "Point",
    "coordinates": [
      -73.6333,
      43.8333
    ]
  },
  "type": "Feature",
  "properties": {
    "hierarchy": [
      "tgn:7022634",
      "tgn:1000001",
      "tgn:7012149",
      "tgn:7007568",
      "tgn:7029392"
    ],
    "placetype": [
      "aat:300008680"
    ],
    "id": 7022634,
    "name:xx": "Crab Pond"
  }
}
