{
  "type": "FeatureCollection",
  "features": [
    {
      "geometry": {
        "type": "Point",
        "coordinates": [
          2.9,
          48.8833
        ]
      },
      "type": "Feature",
      "properties": {
        "hierarchy": [
          "tgn:1034430",
          "tgn:1000003",
          "tgn:7002883",
          "tgn:1000070",
          "tgn:7029392"
        ],
        "placetype": [
          "aat:300008347"
        ],
        "id": 1034430,
        "name:xx": "Mont-Pichet"
      }
    },
    {
      "geometry": {
        "type": "Point",
        "coordinates": [
          1.0833,
          49.4667
        ]
      },
      "type": "Feature",
      "properties": {
        "hierarchy": [
          "tgn:1034431",
          "tgn:1000003",
          "tgn:7002882",
          "tgn:1000070",
          "tgn:7029392"
        ],
        "placetype": [
          "aat:300008347"
        ],
        "id": 1034431,
        "name:xx": "Mont-Saint-Aignan"
      }
    },
    {
      "geometry": {
        "type": "Point",
        "coordinates": [
          5.6,
          46.9167
        ]
      },
      "type": "Feature",
      "properties": {
        "hierarchy": [
          "tgn:1034435",
          "tgn:1000003",
          "tgn:7002881",
          "tgn:1000070",
          "tgn:7029392"
        ],
        "placetype": [
          "aat:300008347"
        ],
        "id": 1034435,
        "name:xx": "Mont-sous-Vaudrey"
      }
    },
    {
      "geometry": {
        "type": "Point",
        "coordinates": [
          0.5,
          45.2667
        ]
      },
      "type": "Feature",
      "properties": {
        "hierarchy": [
          "tgn:1034438",
          "tgn:7002878",
          "tgn:1000003",
          "tgn:1000070",
          "tgn:7029392"
        ],
        "placetype": [
          "aat:300008347"
        ],
        "id": 1034438,
        "name:xx": "Montagrier"
      }
    },
    {
      "geometry": {
        "type": "Point",
        "coordinates": [
          -1.3,
          46.9667
        ]
      },
      "type": "Feature",
      "properties": {
        "hierarchy": [
          "tgn:1034439",
          "tgn:1000003",
          "tgn:7002893",
          "tgn:1000070",
          "tgn:7029392"
        ],
        "placetype": [
          "aat:300008347"
        ],
        "id": 1034439,
        "name:xx": "Montaigu"
      }
    }
  ]
}
