{
  "geometry": {
    "type": "Point",
    "coordinates": [
      -124.0667,
      44.05
    ]
  },
  "type": "Feature",
  "properties": {
    "hierarchy": [
      "tgn:2518548",
      "tgn:1000001",
      "tgn:7012149",
      "tgn:2001716",
      "tgn:7007708",
      "tgn:7029392"
    ],
    "placetype": [
      "aat:300008706"
    ],
    "id": 2518548,
    "name:xx": "Mitchell Creek"
  }
}
