{
  "geometry": {
    "type": "Point",
    "coordinates": [
      -93.3833,
      36.7167
    ]
  },
  "type": "Feature",
  "properties": {
    "hierarchy": [
      "tgn:2785596",
      "tgn:1000001",
      "tgn:7012149",
      "tgn:2001249",
      "tgn:7007523",
      "tgn:7029392"
    ],
    "placetype": [
      "aat:300008680"
    ],
    "id": 2785596,
    "name:xx": "Yocum Pond"
  }
}
