{
  "geometry": {
    "type": "Point",
    "coordinates": [
      128.0667,
      34.9167
    ]
  },
  "type": "Feature",
  "properties": {
    "hierarchy": [
      "tgn:1082352",
      "tgn:1000004",
      "tgn:1001371",
      "tgn:7000299",
      "tgn:7029392"
    ],
    "placetype": [
      "aat:300008347"
    ],
    "id": 1082352,
    "name:xx": "Samch'ŏnp'o"
  }
}
