{
  "geometry": {
    "type": "Point",
    "coordinates": [
      -85.45,
      30.5667
    ]
  },
  "type": "Feature",
  "properties": {
    "hierarchy": [
      "tgn:2734086",
      "tgn:1000001",
      "tgn:7012149",
      "tgn:2000291",
      "tgn:7007240",
      "tgn:7029392"
    ],
    "placetype": [
      "aat:300008680"
    ],
    "id": 2734086,
    "name:xx": "Turnip Pond"
  }
}
