{
  "geometry": {
    "type": "Point",
    "coordinates": [
      -115.5167,
      35.3667
    ]
  },
  "type": "Feature",
  "properties": {
    "hierarchy": [
      "tgn:2690754",
      "tgn:1000001",
      "tgn:7012149",
      "tgn:7007157",
      "tgn:1002857",
      "tgn:7029392"
    ],
    "placetype": [
      "aat:300000390"
    ],
    "id": 2690754,
    "name:xx": "Standard Mine Number One"
  }
}
