{
  "geometry": {
    "type": "Point",
    "coordinates": [
      -135.0333,
      58.8333
    ]
  },
  "type": "Feature",
  "properties": {
    "hierarchy": [
      "tgn:2427975",
      "tgn:7006450",
      "tgn:1000001",
      "tgn:2124089",
      "tgn:7012149",
      "tgn:7029392"
    ],
    "placetype": [
      "aat:300000390"
    ],
    "id": 2427975,
    "name:xx": "Jualin Mine"
  }
}
