{
  "geometry": {
    "type": "Point",
    "coordinates": [
      -86.8167,
      32.1667
    ]
  },
  "type": "Feature",
  "properties": {
    "hierarchy": [
      "tgn:2239339",
      "tgn:7002659",
      "tgn:1000001",
      "tgn:7012149",
      "tgn:2000042",
      "tgn:7029392"
    ],
    "placetype": [
      "aat:300008699"
    ],
    "id": 2239339,
    "name:xx": "Church Branch"
  }
}
