{
  "geometry": {
    "type": "Point",
    "coordinates": [
      -115.95,
      47.35
    ]
  },
  "type": "Feature",
  "properties": {
    "hierarchy": [
      "tgn:2332938",
      "tgn:1000001",
      "tgn:7012149",
      "tgn:2000491",
      "tgn:7007250",
      "tgn:7029392"
    ],
    "placetype": [
      "aat:300008706"
    ],
    "id": 2332938,
    "name:xx": "Flume Creek"
  }
}
