{
  "type": "FeatureCollection",
  "features": [
    {
      "geometry": {
        "type": "Point",
        "coordinates": [
          -70.3167,
          43.9667
        ]
      },
      "type": "Feature",
      "properties": {
        "hierarchy": [
          "tgn:2448670",
          "tgn:1000001",
          "tgn:2000920",
          "tgn:7012149",
          "tgn:7007515",
          "tgn:7029392"
        ],
        "placetype": [
          "aat:300008680"
        ],
        "id": 2448670,
        "name:xx": "Lily Pond"
      }
    },
    {
      "geometry": {
        "type": "Point",
        "coordinates": [
          -68.6667,
          44.2167
        ]
      },
      "type": "Feature",
      "properties": {
        "hierarchy": [
          "tgn:2448671",
          "tgn:1000001",
          "tgn:2000922",
          "tgn:7012149",
          "tgn:7007515",
          "tgn:7029392"
        ],
        "placetype": [
          "aat:300008680"
        ],
        "id": 2448671,
        "name:xx": "Lily Pond"
      }
    },
    {
      "geometry": {
        "type": "Point",
        "coordinates": [
          -70.2667,
          44.2333
        ]
      },
      "type": "Feature",
      "properties": {
        "hierarchy": [
          "tgn:2448672",
          "tgn:2000918",
          "tgn:1000001",
          "tgn:7012149",
          "tgn:7007515",
          "tgn:7029392"
        ],
        "placetype": [
          "aat:300008680"
        ],
        "id": 2448672,
        "name:xx": "Lily Pond"
      }
    },
    {
      "geometry": {
        "type": "Point",
        "coordinates": [
          -69.9,
          44.2667
        ]
      },
      "type": "Feature",
      "properties": {
        "hierarchy": [
          "tgn:2448673",
          "tgn:1000001",
          "tgn:2000923",
          "tgn:7012149",
          "tgn:7007515",
          "tgn:7029392"
        ],
        "placetype": [
          "aat:300008680"
        ],
        "id": 2448673,
        "name:xx": "Lily Pond"
      }
    },
    {
      "geometry": {
        "type": "Point",
        "coordinates": [
          -69.0333,
          44.65
        ]
      },
      "type": "Feature",
      "properties": {
        "hierarchy": [
          "tgn:2448674",
          "tgn:1000001",
          "tgn:7012149",
          "tgn:2000931",
          "tgn:7007515",
          "tgn:7029392"
        ],
        "placetype": [
          "aat:300008680"
        ],
        "id": 2448674,
        "name:xx": "Lily Pond"
      }
    },
    {
      "geometry": {
        "type": "Point",
        "coordinates": [
          -70.1333,
          44.7833
        ]
      },
      "type": "Feature",
      "properties": {
        "hierarchy": [
          "tgn:2448675",
          "tgn:1000001",
          "tgn:2000921",
          "tgn:7012149",
          "tgn:7007515",
          "tgn:7029392"
        ],
        "placetype": [
          "aat:300008680"
        ],
        "id": 2448675,
        "name:xx": "Lily Pond"
      }
    },
    {
      "geometry": {
        "type": "Point",
        "coordinates": [
          -69.7333,
          44.95
        ]
      },
      "type": "Feature",
      "properties": {
        "hierarchy": [
          "tgn:2448676",
          "tgn:1000001",
          "tgn:7012149",
          "tgn:2000930",
          "tgn:7007515",
          "tgn:7029392"
        ],
        "placetype": [
          "aat:300008680"
        ],
        "id": 2448676,
        "name:xx": "Lily Pond"
      }
    },
    {
      "geometry": {
        "type": "Point",
        "coordinates": [
          -69.25,
          45.05
        ]
      },
      "type": "Feature",
      "properties": {
        "hierarchy": [
          "tgn:2448677",
          "tgn:1000001",
          "tgn:7012149",
          "tgn:2000927",
          "tgn:7007515",
          "tgn:7029392"
        ],
        "placetype": [
          "aat:300008680"
        ],
        "id": 2448677,
        "name:xx": "Lily Pond"
      }
    },
    {
      "geometry": {
        "type": "Point",
        "coordinates": [
          -69.5667,
          45.3333
        ]
      },
      "type": "Feature",
      "properties": {
        "hierarchy": [
          "tgn:2448678",
          "tgn:1000001",
          "tgn:7012149",
          "tgn:2000928",
          "tgn:7007515",
          "tgn:7029392"
        ],
        "placetype": [
          "aat:300008680"
        ],
        "id": 2448678,
        "name:xx": "Lily Pond"
      }
    }
  ]
}
