{
  "geometry": {
    "type": "Point",
    "coordinates": [
      -89.1833,
      36.5167
    ]
  },
  "type": "Feature",
  "properties": {
    "hierarchy": [
      "tgn:2251328",
      "tgn:1000001",
      "tgn:7012149",
      "tgn:2000790",
      "tgn:7007255",
      "tgn:7029392"
    ],
    "placetype": [
      "aat:300008697"
    ],
    "id": 2251328,
    "name:xx": "Combs Spring"
  }
}
