{
  "geometry": {
    "type": "Point",
    "coordinates": [
      30.621229,
      24.514402
    ]
  },
  "type": "Feature",
  "properties": {
    "hierarchy": [
      "tgn:7535503",
      "tgn:7001242",
      "tgn:7016833",
      "tgn:7001334",
      "tgn:7029392"
    ],
    "placetype": [
      "aat:300008697"
    ],
    "name:en": "Ibrāhīm Wadā'ah, 'Ayn",
    "id": 7535503
  }
}
