{
  "geometry": {
    "type": "Point",
    "coordinates": [
      32.190185,
      29.410081
    ]
  },
  "type": "Feature",
  "properties": {
    "hierarchy": [
      "tgn:7533230",
      "tgn:7001242",
      "tgn:7016833",
      "tgn:1001110",
      "tgn:7029392"
    ],
    "placetype": [
      "aat:300379998"
    ],
    "name:en": "Umm Ashţān, Wādī",
    "id": 7533230
  }
}
