{
  "geometry": {
    "type": "Point",
    "coordinates": [
      -92.7333,
      37.85
    ]
  },
  "type": "Feature",
  "properties": {
    "hierarchy": [
      "tgn:2146776",
      "tgn:1000001",
      "tgn:7012149",
      "tgn:7007523",
      "tgn:7029392"
    ],
    "placetype": [
      "aat:300008699"
    ],
    "id": 2146776,
    "name:xx": "Bank Branch"
  }
}
