{
  "geometry": {
    "type": "Point",
    "coordinates": [
      -70.0167,
      41.9667
    ]
  },
  "type": "Feature",
  "properties": {
    "hierarchy": [
      "tgn:2635005",
      "tgn:1002165",
      "tgn:1000001",
      "tgn:7012149",
      "tgn:7007517",
      "tgn:7029392"
    ],
    "placetype": [
      "aat:300008680"
    ],
    "id": 2635005,
    "name:xx": "Ryder Pond"
  }
}
