{
  "geometry": {
    "type": "Point",
    "coordinates": [
      -117.0333,
      39.5333
    ]
  },
  "type": "Feature",
  "properties": {
    "hierarchy": [
      "tgn:2248408",
      "tgn:1000001",
      "tgn:2001415",
      "tgn:7012149",
      "tgn:7007526",
      "tgn:7029392"
    ],
    "placetype": [
      "aat:300008697"
    ],
    "id": 2248408,
    "name:xx": "Cold Spring"
  }
}
