{
  "geometry": {
    "type": "Point",
    "coordinates": [
      -72.6667,
      44.5667
    ]
  },
  "type": "Feature",
  "properties": {
    "hierarchy": [
      "tgn:2434436",
      "tgn:1000001",
      "tgn:2002133",
      "tgn:7012149",
      "tgn:7007828",
      "tgn:7029392"
    ],
    "placetype": [
      "aat:300008699"
    ],
    "id": 2434436,
    "name:xx": "Kenfield Brook"
  }
}
