{
  "geometry": {
    "type": "Point",
    "coordinates": [
      -89.406,
      16.542
    ]
  },
  "type": "Feature",
  "properties": {
    "hierarchy": [
      "tgn:7441503",
      "tgn:1000727",
      "tgn:1000001",
      "tgn:7005493",
      "tgn:7029392"
    ],
    "placetype": [
      "aat:300008347",
      "aat:300387007",
      "aat:300000810"
    ],
    "id": 7441503,
    "name:xx": "Ixcún, Sitio Arqueológico"
  }
}
