{
  "geometry": {
    "type": "Point",
    "coordinates": [
      -81.9667,
      27.0833
    ]
  },
  "type": "Feature",
  "properties": {
    "hierarchy": [
      "tgn:2317899",
      "tgn:1000001",
      "tgn:7021603",
      "tgn:7012149",
      "tgn:7007240",
      "tgn:7029392"
    ],
    "placetype": [
      "aat:300008680"
    ],
    "id": 2317899,
    "name:xx": "English Lake"
  }
}
