{
  "geometry": {
    "type": "Point",
    "coordinates": [
      -63.05,
      -4.25
    ]
  },
  "type": "Feature",
  "properties": {
    "hierarchy": [
      "tgn:1117179",
      "tgn:1001826",
      "tgn:1000047",
      "tgn:7002456",
      "tgn:1000002",
      "tgn:7029392"
    ],
    "placetype": [
      "aat:300008680"
    ],
    "id": 1117179,
    "name:xx": "Mamiá, Lago"
  }
}
