{
  "type": "FeatureCollection",
  "features": [
    {
      "geometry": {
        "type": "Point",
        "coordinates": [
          -79.05,
          36.15
        ]
      },
      "type": "Feature",
      "properties": {
        "hierarchy": [
          "tgn:2076540",
          "tgn:1000001",
          "tgn:7012149",
          "tgn:2001525",
          "tgn:7007709",
          "tgn:7029392"
        ],
        "placetype": [
          "aat:300008347",
          "aat:300387210"
        ],
        "id": 2076540,
        "name:xx": "Schley"
      }
    },
    {
      "geometry": {
        "type": "Point",
        "coordinates": [
          -77.4167,
          36.1167
        ]
      },
      "type": "Feature",
      "properties": {
        "hierarchy": [
          "tgn:2076545",
          "tgn:1000001",
          "tgn:7012149",
          "tgn:2001501",
          "tgn:7007709",
          "tgn:7029392"
        ],
        "placetype": [
          "aat:300008347"
        ],
        "id": 2076545,
        "name:xx": "Scotland Neck"
      }
    },
    {
      "geometry": {
        "type": "Point",
        "coordinates": [
          -78.0167,
          35.6667
        ]
      },
      "type": "Feature",
      "properties": {
        "hierarchy": [
          "tgn:2076548",
          "tgn:1000001",
          "tgn:7012149",
          "tgn:2001554",
          "tgn:7007709",
          "tgn:7029392"
        ],
        "placetype": [
          "aat:300008347"
        ],
        "id": 2076548,
        "name:xx": "Scotts"
      }
    },
    {
      "geometry": {
        "type": "Point",
        "coordinates": [
          -81,
          35.8333
        ]
      },
      "type": "Feature",
      "properties": {
        "hierarchy": [
          "tgn:2076549",
          "tgn:1000001",
          "tgn:7012149",
          "tgn:2001507",
          "tgn:7007709",
          "tgn:7029392"
        ],
        "placetype": [
          "aat:300008347"
        ],
        "id": 2076549,
        "name:xx": "Scotts"
      }
    }
  ]
}
