{
  "geometry": {
    "type": "Point",
    "coordinates": [
      -80.2333,
      39.0167
    ]
  },
  "type": "Feature",
  "properties": {
    "hierarchy": [
      "tgn:2719657",
      "tgn:1000001",
      "tgn:7012149",
      "tgn:2002298",
      "tgn:7013961",
      "tgn:7029392"
    ],
    "placetype": [
      "aat:300008699"
    ],
    "id": 2719657,
    "name:xx": "Three Lick Run"
  }
}
