{
  "geometry": {
    "type": "Point",
    "coordinates": [
      -0.75,
      60.833333
    ]
  },
  "type": "Feature",
  "properties": {
    "hierarchy": [
      "tgn:7447088",
      "tgn:7002444",
      "tgn:1000003",
      "tgn:7029508",
      "tgn:7008591",
      "tgn:7029392"
    ],
    "placetype": [
      "aat:300386114"
    ],
    "name:en": "Skaw Röst",
    "id": 7447088
  }
}
