{
  "type": "FeatureCollection",
  "features": [
    {
      "geometry": {
        "type": "Point",
        "coordinates": [
          12.616667,
          47.766667
        ]
      },
      "type": "Feature",
      "properties": {
        "hierarchy": [
          "tgn:7083450",
          "tgn:7003669",
          "tgn:1000003",
          "tgn:7000084",
          "tgn:7029392"
        ],
        "placetype": [
          "aat:300008795"
        ],
        "id": 7083450,
        "name:xx": "Wester-Berg"
      }
    },
    {
      "geometry": {
        "type": "Point",
        "coordinates": [
          11.95,
          47.7
        ]
      },
      "type": "Feature",
      "properties": {
        "hierarchy": [
          "tgn:7083451",
          "tgn:7003669",
          "tgn:1000003",
          "tgn:7000084",
          "tgn:7029392"
        ],
        "placetype": [
          "aat:300008795"
        ],
        "id": 7083451,
        "name:xx": "Westerberg"
      }
    },
    {
      "geometry": {
        "type": "Point",
        "coordinates": [
          9.083333,
          53.666667
        ]
      },
      "type": "Feature",
      "properties": {
        "hierarchy": [
          "tgn:7083452",
          "tgn:1000003",
          "tgn:7003676",
          "tgn:7000084",
          "tgn:7029392"
        ],
        "placetype": [
          "aat:300008777"
        ],
        "id": 7083452,
        "name:xx": "Westerberg"
      }
    },
    {
      "geometry": {
        "type": "Point",
        "coordinates": [
          7.45,
          52.883333
        ]
      },
      "type": "Feature",
      "properties": {
        "hierarchy": [
          "tgn:7083453",
          "tgn:1000003",
          "tgn:7003676",
          "tgn:7000084",
          "tgn:7029392"
        ],
        "placetype": [
          "aat:300008777"
        ],
        "id": 7083453,
        "name:xx": "Wester-Berg"
      }
    },
    {
      "geometry": {
        "type": "Point",
        "coordinates": [
          8.083333,
          52.383333
        ]
      },
      "type": "Feature",
      "properties": {
        "hierarchy": [
          "tgn:7083454",
          "tgn:1000003",
          "tgn:7003676",
          "tgn:7000084",
          "tgn:7029392"
        ],
        "placetype": [
          "aat:300008777"
        ],
        "id": 7083454,
        "name:xx": "Wester-Berg"
      }
    },
    {
      "geometry": {
        "type": "Point",
        "coordinates": [
          8.366667,
          52.3
        ]
      },
      "type": "Feature",
      "properties": {
        "hierarchy": [
          "tgn:7083455",
          "tgn:1000003",
          "tgn:7003676",
          "tgn:7000084",
          "tgn:7029392"
        ],
        "placetype": [
          "aat:300008777"
        ],
        "id": 7083455,
        "name:xx": "Wester-Berg"
      }
    },
    {
      "geometry": {
        "type": "Point",
        "coordinates": [
          8.016667,
          52.283333
        ]
      },
      "type": "Feature",
      "properties": {
        "hierarchy": [
          "tgn:7083457",
          "tgn:1000003",
          "tgn:7003676",
          "tgn:7000084",
          "tgn:7029392"
        ],
        "placetype": [
          "aat:300008777"
        ],
        "id": 7083457,
        "name:xx": "Wester-Berg"
      }
    },
    {
      "geometry": {
        "type": "Point",
        "coordinates": [
          10.633333,
          52.216667
        ]
      },
      "type": "Feature",
      "properties": {
        "hierarchy": [
          "tgn:7083458",
          "tgn:1000003",
          "tgn:7003676",
          "tgn:7000084",
          "tgn:7029392"
        ],
        "placetype": [
          "aat:300008777"
        ],
        "id": 7083458,
        "name:xx": "Wester-Berg"
      }
    },
    {
      "geometry": {
        "type": "Point",
        "coordinates": [
          9.333333,
          52.183333
        ]
      },
      "type": "Feature",
      "properties": {
        "hierarchy": [
          "tgn:7083459",
          "tgn:1000003",
          "tgn:7003676",
          "tgn:7000084",
          "tgn:7029392"
        ],
        "placetype": [
          "aat:300008777"
        ],
        "id": 7083459,
        "name:xx": "Wester-Berg"
      }
    }
  ]
}
