{
  "geometry": {
    "type": "Point",
    "coordinates": [
      -94.0167,
      46.75
    ]
  },
  "type": "Feature",
  "properties": {
    "hierarchy": [
      "tgn:2211488",
      "tgn:1000001",
      "tgn:2001016",
      "tgn:7012149",
      "tgn:7007521",
      "tgn:7029392"
    ],
    "placetype": [
      "aat:300008680"
    ],
    "id": 2211488,
    "name:xx": "Butterfield Lake"
  }
}
