{
  "geometry": {
    "type": "Point",
    "coordinates": [
      -75.8333,
      42.4167
    ]
  },
  "type": "Feature",
  "properties": {
    "hierarchy": [
      "tgn:2468633",
      "tgn:1000001",
      "tgn:1002262",
      "tgn:7012149",
      "tgn:7007568",
      "tgn:7029392"
    ],
    "placetype": [
      "aat:300008680"
    ],
    "id": 2468633,
    "name:xx": "Long Pond"
  }
}
