{
  "type": "FeatureCollection",
  "features": [
    {
      "geometry": {
        "type": "Point",
        "coordinates": [
          -110.4167,
          47.1667
        ]
      },
      "type": "Feature",
      "properties": {
        "hierarchy": [
          "tgn:2337680",
          "tgn:1000001",
          "tgn:7012149",
          "tgn:2001282",
          "tgn:7007524",
          "tgn:7029392"
        ],
        "placetype": [
          "aat:300008761"
        ],
        "id": 2337680,
        "name:xx": "Fox Coulee"
      }
    },
    {
      "geometry": {
        "type": "Point",
        "coordinates": [
          -106.5333,
          48.8833
        ]
      },
      "type": "Feature",
      "properties": {
        "hierarchy": [
          "tgn:2337681",
          "tgn:1000001",
          "tgn:7012149",
          "tgn:2001312",
          "tgn:7007524",
          "tgn:7029392"
        ],
        "placetype": [
          "aat:300008761"
        ],
        "id": 2337681,
        "name:xx": "Fox Coulee"
      }
    },
    {
      "geometry": {
        "type": "Point",
        "coordinates": [
          -91.3833,
          44.15
        ]
      },
      "type": "Feature",
      "properties": {
        "hierarchy": [
          "tgn:2337682",
          "tgn:1000001",
          "tgn:7012149",
          "tgn:2002357",
          "tgn:7007922",
          "tgn:7029392"
        ],
        "placetype": [
          "aat:300008761"
        ],
        "id": 2337682,
        "name:xx": "Fox Coulee"
      }
    },
    {
      "geometry": {
        "type": "Point",
        "coordinates": [
          -91.9833,
          44.45
        ]
      },
      "type": "Feature",
      "properties": {
        "hierarchy": [
          "tgn:2337683",
          "tgn:1000001",
          "tgn:2002310",
          "tgn:7012149",
          "tgn:7007922",
          "tgn:7029392"
        ],
        "placetype": [
          "aat:300008761"
        ],
        "id": 2337683,
        "name:xx": "Fox Coulee"
      }
    },
    {
      "geometry": {
        "type": "Point",
        "coordinates": [
          -114.6667,
          35.6333
        ]
      },
      "type": "Feature",
      "properties": {
        "hierarchy": [
          "tgn:2337684",
          "tgn:1000001",
          "tgn:2001410",
          "tgn:7012149",
          "tgn:7007526",
          "tgn:7029392"
        ],
        "placetype": [
          "aat:300132316"
        ],
        "id": 2337684,
        "name:xx": "Fox Cove"
      }
    },
    {
      "geometry": {
        "type": "Point",
        "coordinates": [
          -122.9,
          48.75
        ]
      },
      "type": "Feature",
      "properties": {
        "hierarchy": [
          "tgn:2337685",
          "tgn:1000001",
          "tgn:7012149",
          "tgn:1002862",
          "tgn:7007920",
          "tgn:7029392"
        ],
        "placetype": [
          "aat:300132316"
        ],
        "id": 2337685,
        "name:xx": "Fox Cove"
      }
    },
    {
      "geometry": {
        "type": "Point",
        "coordinates": [
          -85.7833,
          32.9833
        ]
      },
      "type": "Feature",
      "properties": {
        "hierarchy": [
          "tgn:2337686",
          "tgn:7002659",
          "tgn:1000001",
          "tgn:7012149",
          "tgn:2000061",
          "tgn:7029392"
        ],
        "placetype": [
          "aat:300008706"
        ],
        "id": 2337686,
        "name:xx": "Fox Creek"
      }
    },
    {
      "geometry": {
        "type": "Point",
        "coordinates": [
          -87.2667,
          33.4167
        ]
      },
      "type": "Feature",
      "properties": {
        "hierarchy": [
          "tgn:2337687",
          "tgn:7002659",
          "tgn:1000001",
          "tgn:7012149",
          "tgn:2000036",
          "tgn:7029392"
        ],
        "placetype": [
          "aat:300008706"
        ],
        "id": 2337687,
        "name:xx": "Fox Creek"
      }
    },
    {
      "geometry": {
        "type": "Point",
        "coordinates": [
          -86.3333,
          33.65
        ]
      },
      "type": "Feature",
      "properties": {
        "hierarchy": [
          "tgn:2337688",
          "tgn:7002659",
          "tgn:1000001",
          "tgn:7012149",
          "tgn:2000057",
          "tgn:7029392"
        ],
        "placetype": [
          "aat:300008706"
        ],
        "id": 2337688,
        "name:xx": "Fox Creek"
      }
    },
    {
      "geometry": {
        "type": "Point",
        "coordinates": [
          -86.5333,
          32.65
        ]
      },
      "type": "Feature",
      "properties": {
        "hierarchy": [
          "tgn:2337689",
          "tgn:2000000",
          "tgn:7002659",
          "tgn:1000001",
          "tgn:7012149",
          "tgn:7029392"
        ],
        "placetype": [
          "aat:300008706"
        ],
        "id": 2337689,
        "name:xx": "Fox Creek"
      }
    }
  ]
}
