{
  "type": "FeatureCollection",
  "features": [
    {
      "geometry": {
        "type": "Point",
        "coordinates": [
          19.3,
          47.5667
        ]
      },
      "type": "Feature",
      "properties": {
        "hierarchy": [
          "tgn:1042371",
          "tgn:1000003",
          "tgn:1000431",
          "tgn:7006278",
          "tgn:7029392"
        ],
        "placetype": [
          "aat:300008347"
        ],
        "id": 1042371,
        "name:xx": "Kerepes"
      }
    },
    {
      "geometry": {
        "type": "Point",
        "coordinates": [
          16.5,
          46.7667
        ]
      },
      "type": "Feature",
      "properties": {
        "hierarchy": [
          "tgn:1042372",
          "tgn:1000003",
          "tgn:1000481",
          "tgn:7006278",
          "tgn:7029392"
        ],
        "placetype": [
          "aat:300008347"
        ],
        "id": 1042372,
        "name:xx": "Kerkafalva"
      }
    },
    {
      "geometry": {
        "type": "Point",
        "coordinates": [
          20.75,
          47.2333
        ]
      },
      "type": "Feature",
      "properties": {
        "hierarchy": [
          "tgn:1042374",
          "tgn:1000453",
          "tgn:1000003",
          "tgn:7006278",
          "tgn:7029392"
        ],
        "placetype": [
          "aat:300008347"
        ],
        "id": 1042374,
        "name:xx": "Kisújszállás"
      }
    },
    {
      "geometry": {
        "type": "Point",
        "coordinates": [
          18,
          47.5
        ]
      },
      "type": "Feature",
      "properties": {
        "hierarchy": [
          "tgn:1042375",
          "tgn:1000402",
          "tgn:1000003",
          "tgn:7006278",
          "tgn:7029392"
        ],
        "placetype": [
          "aat:300008347"
        ],
        "id": 1042375,
        "name:xx": "Kisbér"
      }
    },
    {
      "geometry": {
        "type": "Point",
        "coordinates": [
          19.3333,
          46.65
        ]
      },
      "type": "Feature",
      "properties": {
        "hierarchy": [
          "tgn:1042376",
          "tgn:1000340",
          "tgn:1000003",
          "tgn:7006278",
          "tgn:7029392"
        ],
        "placetype": [
          "aat:300008347"
        ],
        "id": 1042376,
        "name:xx": "Kiskőrös"
      }
    },
    {
      "geometry": {
        "type": "Point",
        "coordinates": [
          19.8667,
          46.7
        ]
      },
      "type": "Feature",
      "properties": {
        "hierarchy": [
          "tgn:1042377",
          "tgn:1000340",
          "tgn:1000003",
          "tgn:7006278",
          "tgn:7029392"
        ],
        "placetype": [
          "aat:300008347"
        ],
        "id": 1042377,
        "name:xx": "Kiskunfélegyháza"
      }
    },
    {
      "geometry": {
        "type": "Point",
        "coordinates": [
          19.7667,
          46.5
        ]
      },
      "type": "Feature",
      "properties": {
        "hierarchy": [
          "tgn:1042379",
          "tgn:1000340",
          "tgn:1000003",
          "tgn:7006278",
          "tgn:7029392"
        ],
        "placetype": [
          "aat:300008347"
        ],
        "id": 1042379,
        "name:xx": "Kiskunmajsa"
      }
    }
  ]
}
