{
  "geometry": {
    "type": "Point",
    "coordinates": [
      -76.5667,
      37.8167
    ]
  },
  "type": "Feature",
  "properties": {
    "hierarchy": [
      "tgn:2237707",
      "tgn:1000001",
      "tgn:7012149",
      "tgn:7014334",
      "tgn:7007919",
      "tgn:7029392"
    ],
    "placetype": [
      "aat:300006191"
    ],
    "id": 2237707,
    "name:xx": "Chinns Millpond"
  }
}
