{
  "geometry": {
    "type": "Point",
    "coordinates": [
      -120.8167,
      38.7667
    ]
  },
  "type": "Feature",
  "properties": {
    "hierarchy": [
      "tgn:2479023",
      "tgn:1000001",
      "tgn:7012149",
      "tgn:1002350",
      "tgn:7007157",
      "tgn:7029392"
    ],
    "placetype": [
      "aat:300008761"
    ],
    "id": 2479023,
    "name:xx": "Ladies Canyon"
  }
}
