{
  "geometry": {
    "type": "Point",
    "coordinates": [
      -10.3667,
      52.1333
    ]
  },
  "type": "Feature",
  "properties": {
    "hierarchy": [
      "tgn:1043048",
      "tgn:7003498",
      "tgn:7001201",
      "tgn:1000003",
      "tgn:1000078",
      "tgn:7029392"
    ],
    "placetype": [
      "aat:300008347"
    ],
    "id": 1043048,
    "name:xx": "Ventry"
  }
}
