{
  "geometry": {
    "type": "Point",
    "coordinates": [
      -86.65,
      34.3333
    ]
  },
  "type": "Feature",
  "properties": {
    "hierarchy": [
      "tgn:2297262",
      "tgn:7002659",
      "tgn:1000001",
      "tgn:7012149",
      "tgn:2000051",
      "tgn:7029392"
    ],
    "placetype": [
      "aat:300008697"
    ],
    "id": 2297262,
    "name:xx": "Dry Creek Spring"
  }
}
