{
  "geometry": {
    "type": "Point",
    "coordinates": [
      -84.4167,
      34.0833
    ]
  },
  "type": "Feature",
  "properties": {
    "hierarchy": [
      "tgn:2479670",
      "tgn:1000001",
      "tgn:2000319",
      "tgn:7012149",
      "tgn:7007248",
      "tgn:7029392"
    ],
    "placetype": [
      "aat:300006191"
    ],
    "id": 2479670,
    "name:xx": "Lake Cherful Dam"
  }
}
