{
  "type": "FeatureCollection",
  "features": [
    {
      "geometry": {
        "type": "Point",
        "coordinates": [
          6.066667,
          50.7
        ]
      },
      "type": "Feature",
      "properties": {
        "hierarchy": [
          "tgn:7244350",
          "tgn:7003460",
          "tgn:1000003",
          "tgn:1000063",
          "tgn:4012014",
          "tgn:7029392"
        ],
        "placetype": [
          "aat:300008863"
        ],
        "id": 7244350,
        "name:xx": "Kerresbusch"
      }
    },
    {
      "geometry": {
        "type": "Point",
        "coordinates": [
          3.527166,
          51.026473
        ]
      },
      "type": "Feature",
      "properties": {
        "hierarchy": [
          "tgn:7244351",
          "tgn:7003457",
          "tgn:1000003",
          "tgn:1000063",
          "tgn:7018236",
          "tgn:7029392"
        ],
        "placetype": [
          "aat:300008347"
        ],
        "id": 7244351,
        "name:xx": "Kerrebroek"
      }
    },
    {
      "geometry": {
        "type": "Point",
        "coordinates": [
          3.8,
          51.2
        ]
      },
      "type": "Feature",
      "properties": {
        "hierarchy": [
          "tgn:7244352",
          "tgn:7003457",
          "tgn:1000003",
          "tgn:1000063",
          "tgn:7018236",
          "tgn:7029392"
        ],
        "placetype": [
          "aat:300006163"
        ],
        "id": 7244352,
        "name:xx": "Kernmelk Polder"
      }
    },
    {
      "geometry": {
        "type": "Point",
        "coordinates": [
          5.365087,
          50.816667
        ]
      },
      "type": "Feature",
      "properties": {
        "hierarchy": [
          "tgn:7244353",
          "tgn:7003461",
          "tgn:1000003",
          "tgn:1000063",
          "tgn:7018236",
          "tgn:7029392"
        ],
        "placetype": [
          "aat:300008347"
        ],
        "id": 7244353,
        "name:xx": "Kerniel"
      }
    },
    {
      "geometry": {
        "type": "Point",
        "coordinates": [
          5.25,
          50.95
        ]
      },
      "type": "Feature",
      "properties": {
        "hierarchy": [
          "tgn:7244355",
          "tgn:7003461",
          "tgn:1000003",
          "tgn:1000063",
          "tgn:7018236",
          "tgn:7029392"
        ],
        "placetype": [
          "aat:300008699"
        ],
        "id": 7244355,
        "name:xx": "Kermterbeek"
      }
    },
    {
      "geometry": {
        "type": "Point",
        "coordinates": [
          5.25,
          50.95
        ]
      },
      "type": "Feature",
      "properties": {
        "hierarchy": [
          "tgn:7244356",
          "tgn:7003461",
          "tgn:1000003",
          "tgn:1000063",
          "tgn:7018236",
          "tgn:7029392"
        ],
        "placetype": [
          "aat:300008347"
        ],
        "id": 7244356,
        "name:xx": "Kermt"
      }
    },
    {
      "geometry": {
        "type": "Point",
        "coordinates": [
          5.516667,
          51.3
        ]
      },
      "type": "Feature",
      "properties": {
        "hierarchy": [
          "tgn:7244358",
          "tgn:7003461",
          "tgn:1000003",
          "tgn:1000063",
          "tgn:7018236",
          "tgn:7029392"
        ],
        "placetype": [
          "aat:300008903"
        ],
        "id": 7244358,
        "name:xx": "Kerkven"
      }
    },
    {
      "geometry": {
        "type": "Point",
        "coordinates": [
          4.45,
          51.216667
        ]
      },
      "type": "Feature",
      "properties": {
        "hierarchy": [
          "tgn:7244359",
          "tgn:7003456",
          "tgn:1000003",
          "tgn:1000063",
          "tgn:7018236",
          "tgn:7029392"
        ],
        "placetype": [
          "aat:300008347"
        ],
        "id": 7244359,
        "name:xx": "Kerkveld"
      }
    }
  ]
}
