{
  "geometry": {
    "type": "Point",
    "coordinates": [
      16.1667,
      43.85
    ]
  },
  "type": "Feature",
  "properties": {
    "hierarchy": [
      "tgn:1064982",
      "tgn:7017306",
      "tgn:1000003",
      "tgn:7006663",
      "tgn:7029392"
    ],
    "placetype": [
      "aat:300008347"
    ],
    "id": 1064982,
    "name:xx": "Drniš"
  }
}
