{
  "geometry": {
    "type": "Point",
    "coordinates": [
      -83.75,
      38.3333
    ]
  },
  "type": "Feature",
  "properties": {
    "hierarchy": [
      "tgn:2529938",
      "tgn:1000001",
      "tgn:7012149",
      "tgn:1002375",
      "tgn:7007255",
      "tgn:7029392"
    ],
    "placetype": [
      "aat:300008699"
    ],
    "id": 2529938,
    "name:xx": "Mud Sock Branch"
  }
}
