{
  "geometry": {
    "type": "Point",
    "coordinates": [
      -91.5833,
      29.9667
    ]
  },
  "type": "Feature",
  "properties": {
    "hierarchy": [
      "tgn:2323847",
      "tgn:1000001",
      "tgn:7012149",
      "tgn:7007256",
      "tgn:7029392"
    ],
    "placetype": [
      "aat:300008680"
    ],
    "id": 2323847,
    "name:xx": "Fausse Pointe, Lake"
  }
}
