{
  "geometry": {
    "type": "Point",
    "coordinates": [
      46.5333,
      -18.4167
    ]
  },
  "type": "Feature",
  "properties": {
    "hierarchy": [
      "tgn:1090889",
      "tgn:1001103",
      "tgn:7001242",
      "tgn:1000173",
      "tgn:7029392"
    ],
    "placetype": [
      "aat:300008347"
    ],
    "id": 1090889,
    "name:xx": "Fenoarivo"
  }
}
