{
  "geometry": {
    "type": "Point",
    "coordinates": [
      -87.6167,
      32.1833
    ]
  },
  "type": "Feature",
  "properties": {
    "hierarchy": [
      "tgn:2507772",
      "tgn:7002659",
      "tgn:1000001",
      "tgn:7012149",
      "tgn:2000045",
      "tgn:7029392"
    ],
    "placetype": [
      "aat:300008706"
    ],
    "id": 2507772,
    "name:xx": "Michigan Creek"
  }
}
