{
  "geometry": {
    "type": "Point",
    "coordinates": [
      -98.1667,
      34.15
    ]
  },
  "type": "Feature",
  "properties": {
    "hierarchy": [
      "tgn:2398272",
      "tgn:1000001",
      "tgn:2001639",
      "tgn:7012149",
      "tgn:7007707",
      "tgn:7029392"
    ],
    "placetype": [
      "aat:300008347"
    ],
    "id": 2398272,
    "name:xx": "Hooper"
  }
}
