{
  "geometry": {
    "type": "Point",
    "coordinates": [
      -70.766667,
      -32.283333
    ]
  },
  "type": "Feature",
  "properties": {
    "hierarchy": [
      "tgn:7287474",
      "tgn:1001768",
      "tgn:1000049",
      "tgn:1000002",
      "tgn:7029392"
    ],
    "placetype": [
      "aat:300266640"
    ],
    "id": 7287474,
    "name:xx": "Gálvez, Cordón de"
  }
}
