{
  "geometry": {
    "type": "Point",
    "coordinates": [
      -82.3667,
      38.1667
    ]
  },
  "type": "Feature",
  "properties": {
    "hierarchy": [
      "tgn:2118081",
      "tgn:1000001",
      "tgn:7012149",
      "tgn:2002299",
      "tgn:7013961",
      "tgn:7029392"
    ],
    "placetype": [
      "aat:300008347"
    ],
    "id": 2118081,
    "name:xx": "East Lynn"
  }
}
