{
  "geometry": {
    "type": "Point",
    "coordinates": [
      33.922892,
      22.273997
    ]
  },
  "type": "Feature",
  "properties": {
    "hierarchy": [
      "tgn:7521305",
      "tgn:7001242",
      "tgn:7001311",
      "tgn:7016833",
      "tgn:7029392"
    ],
    "placetype": [
      "aat:300379998"
    ],
    "name:en": "Ab큰 F훮s, W훮d카",
    "id": 7521305
  }
}
