{
  "geometry": {
    "type": "Point",
    "coordinates": [
      -71.4333,
      42.0167
    ]
  },
  "type": "Feature",
  "properties": {
    "hierarchy": [
      "tgn:2207145",
      "tgn:1000001",
      "tgn:1002724",
      "tgn:7012149",
      "tgn:7007517",
      "tgn:7029392"
    ],
    "placetype": [
      "aat:300008905"
    ],
    "id": 2207145,
    "name:xx": "Bungay Swamp"
  }
}
