{
  "geometry": {
    "type": "Point",
    "coordinates": [
      -85.4833,
      45.6167
    ]
  },
  "type": "Feature",
  "properties": {
    "hierarchy": [
      "tgn:2494684",
      "tgn:1000001",
      "tgn:2000950",
      "tgn:7012149",
      "tgn:7007520",
      "tgn:7029392"
    ],
    "placetype": [
      "aat:300008850"
    ],
    "id": 2494684,
    "name:xx": "Martin Point"
  }
}
