{
  "geometry": {
    "type": "Point",
    "coordinates": [
      -101.5833,
      48.35
    ]
  },
  "type": "Feature",
  "properties": {
    "hierarchy": [
      "tgn:2614473",
      "tgn:1000001",
      "tgn:7012149",
      "tgn:2001607",
      "tgn:7007705",
      "tgn:7029392"
    ],
    "placetype": [
      "aat:300008761"
    ],
    "id": 2614473,
    "name:xx": "Reihle Coulee"
  }
}
