{
  "geometry": {
    "type": "Point",
    "coordinates": [
      -85.4833,
      32.5167
    ]
  },
  "type": "Feature",
  "properties": {
    "hierarchy": [
      "tgn:2536520",
      "tgn:7002659",
      "tgn:1000001",
      "tgn:7012149",
      "tgn:2000040",
      "tgn:7029392"
    ],
    "placetype": [
      "aat:300006191"
    ],
    "id": 2536520,
    "name:xx": "Neals Pond"
  }
}
