{
  "geometry": {
    "type": "Point",
    "coordinates": [
      -110.6667,
      38.6667
    ]
  },
  "type": "Feature",
  "properties": {
    "hierarchy": [
      "tgn:2714499",
      "tgn:1000001",
      "tgn:2002108",
      "tgn:7012149",
      "tgn:7007827",
      "tgn:7029392"
    ],
    "placetype": [
      "aat:300008761"
    ],
    "id": 2714499,
    "name:xx": "Temple Wash"
  }
}
