{
  "geometry": {
    "type": "Point",
    "coordinates": [
      -90.2167,
      37.0667
    ]
  },
  "type": "Feature",
  "properties": {
    "hierarchy": [
      "tgn:2278354",
      "tgn:1000001",
      "tgn:7012149",
      "tgn:2001255",
      "tgn:7007523",
      "tgn:7029392"
    ],
    "placetype": [
      "aat:300008699"
    ],
    "id": 2278354,
    "name:xx": "DeCelis Branch"
  }
}
