{
  "geometry": {
    "type": "Point",
    "coordinates": [
      18.9833,
      45.4833
    ]
  },
  "type": "Feature",
  "properties": {
    "hierarchy": [
      "tgn:1064968",
      "tgn:7017305",
      "tgn:1000003",
      "tgn:7006663",
      "tgn:7029392"
    ],
    "placetype": [
      "aat:300008347"
    ],
    "id": 1064968,
    "name:xx": "Dalj"
  }
}
