{
  "geometry": {
    "type": "Point",
    "coordinates": [
      -117.8833,
      37.45
    ]
  },
  "type": "Feature",
  "properties": {
    "hierarchy": [
      "tgn:2328063",
      "tgn:1000001",
      "tgn:7012149",
      "tgn:7029392"
    ],
    "placetype": [
      "aat:300008699"
    ],
    "id": 2328063,
    "name:xx": "Fish Lake Valley Wash"
  }
}
