{
  "geometry": {
    "type": "Point",
    "coordinates": [
      79.8042,
      27.2059
    ]
  },
  "type": "Feature",
  "properties": {
    "hierarchy": [
      "tgn:7561414",
      "tgn:1000004",
      "tgn:7000198",
      "tgn:7016722",
      "tgn:7029392"
    ],
    "placetype": [
      "aat:300008347"
    ],
    "name:en": "Dulārpur",
    "id": 7561414
  }
}
