{
  "geometry": {
    "type": "Point",
    "coordinates": [
      47.6667,
      34.4833
    ]
  },
  "type": "Feature",
  "properties": {
    "hierarchy": [
      "tgn:1078943",
      "tgn:1000004",
      "tgn:1001134",
      "tgn:7000231",
      "tgn:7029392"
    ],
    "placetype": [
      "aat:300008347"
    ],
    "id": 1078943,
    "name:xx": "Ṣaḥneh"
  }
}
