{
  "type": "FeatureCollection",
  "features": [
    {
      "geometry": {
        "type": "Point",
        "coordinates": [
          -76.3833,
          39.2333
        ]
      },
      "type": "Feature",
      "properties": {
        "hierarchy": [
          "tgn:2588040",
          "tgn:7016099",
          "tgn:1000001",
          "tgn:7012149",
          "tgn:7007516",
          "tgn:7029392"
        ],
        "placetype": [
          "aat:300008791"
        ],
        "id": 2588040,
        "name:xx": "Pleasure Island"
      }
    },
    {
      "geometry": {
        "type": "Point",
        "coordinates": [
          -77.9,
          34.0167
        ]
      },
      "type": "Feature",
      "properties": {
        "hierarchy": [
          "tgn:2588041",
          "tgn:1000001",
          "tgn:7012149",
          "tgn:7007709",
          "tgn:7029392"
        ],
        "placetype": [
          "aat:300008791"
        ],
        "id": 2588041,
        "name:xx": "Pleasure Island"
      }
    },
    {
      "geometry": {
        "type": "Point",
        "coordinates": [
          -97.0167,
          28.8
        ]
      },
      "type": "Feature",
      "properties": {
        "hierarchy": [
          "tgn:2588042",
          "tgn:1000001",
          "tgn:7012149",
          "tgn:1002975",
          "tgn:7007826",
          "tgn:7029392"
        ],
        "placetype": [
          "aat:300008791"
        ],
        "id": 2588042,
        "name:xx": "Pleasure Island"
      }
    },
    {
      "geometry": {
        "type": "Point",
        "coordinates": [
          -93.8833,
          29.9
        ]
      },
      "type": "Feature",
      "properties": {
        "hierarchy": [
          "tgn:2588043",
          "tgn:1000001",
          "tgn:7012149",
          "tgn:2002011",
          "tgn:7007826",
          "tgn:7029392"
        ],
        "placetype": [
          "aat:300008791"
        ],
        "id": 2588043,
        "name:xx": "Pleasure Island"
      }
    },
    {
      "geometry": {
        "type": "Point",
        "coordinates": [
          -89.7167,
          44.4333
        ]
      },
      "type": "Feature",
      "properties": {
        "hierarchy": [
          "tgn:2588044",
          "tgn:1000001",
          "tgn:7012149",
          "tgn:2002364",
          "tgn:7007922",
          "tgn:7029392"
        ],
        "placetype": [
          "aat:300008791"
        ],
        "id": 2588044,
        "name:xx": "Pleasure Island"
      }
    },
    {
      "geometry": {
        "type": "Point",
        "coordinates": [
          -96.35,
          41.3167
        ]
      },
      "type": "Feature",
      "properties": {
        "hierarchy": [
          "tgn:2588045",
          "tgn:1000001",
          "tgn:2001343",
          "tgn:7012149",
          "tgn:7007525",
          "tgn:7029392"
        ],
        "placetype": [
          "aat:300008680"
        ],
        "id": 2588045,
        "name:xx": "Pleasure Lake"
      }
    },
    {
      "geometry": {
        "type": "Point",
        "coordinates": [
          -103.0833,
          34.3667
        ]
      },
      "type": "Feature",
      "properties": {
        "hierarchy": [
          "tgn:2588046",
          "tgn:1000001",
          "tgn:2001433",
          "tgn:7012149",
          "tgn:7007566",
          "tgn:7029392"
        ],
        "placetype": [
          "aat:300008680"
        ],
        "id": 2588046,
        "name:xx": "Pleasure Lake"
      }
    },
    {
      "geometry": {
        "type": "Point",
        "coordinates": [
          -74.6167,
          41.6833
        ]
      },
      "type": "Feature",
      "properties": {
        "hierarchy": [
          "tgn:2588047",
          "tgn:1000001",
          "tgn:7012149",
          "tgn:1002926",
          "tgn:7007568",
          "tgn:7029392"
        ],
        "placetype": [
          "aat:300006191"
        ],
        "id": 2588047,
        "name:xx": "Pleasure Lake"
      }
    },
    {
      "geometry": {
        "type": "Point",
        "coordinates": [
          -71.4,
          41.7833
        ]
      },
      "type": "Feature",
      "properties": {
        "hierarchy": [
          "tgn:2588048",
          "tgn:1002808",
          "tgn:1000001",
          "tgn:7012149",
          "tgn:7007711",
          "tgn:7029392"
        ],
        "placetype": [
          "aat:300008850"
        ],
        "id": 2588048,
        "name:xx": "Pleasure Lake"
      }
    },
    {
      "geometry": {
        "type": "Point",
        "coordinates": [
          -71.4167,
          42.1833
        ]
      },
      "type": "Feature",
      "properties": {
        "hierarchy": [
          "tgn:2588049",
          "tgn:1000001",
          "tgn:1002665",
          "tgn:7012149",
          "tgn:7007517",
          "tgn:7029392"
        ],
        "placetype": [
          "aat:300008850"
        ],
        "id": 2588049,
        "name:xx": "Pleasure Point"
      }
    }
  ]
}
