{
  "geometry": {
    "type": "Point",
    "coordinates": [
      -74.2667,
      40.4167
    ]
  },
  "type": "Feature",
  "properties": {
    "hierarchy": [
      "tgn:2714965",
      "tgn:1000001",
      "tgn:1002666",
      "tgn:7012149",
      "tgn:7007565",
      "tgn:7029392"
    ],
    "placetype": [
      "aat:300008699"
    ],
    "id": 2714965,
    "name:xx": "Tennent Brook"
  }
}
