{
  "type": "FeatureCollection",
  "features": [
    {
      "geometry": {
        "type": "Point",
        "coordinates": [
          -92.65,
          38.3333
        ]
      },
      "type": "Feature",
      "properties": {
        "hierarchy": [
          "tgn:2658200",
          "tgn:1000001",
          "tgn:7012149",
          "tgn:7007523",
          "tgn:7029392"
        ],
        "placetype": [
          "aat:300008761"
        ],
        "id": 2658200,
        "name:xx": "Shelton Hollow"
      }
    },
    {
      "geometry": {
        "type": "Point",
        "coordinates": [
          -90.85,
          36.9
        ]
      },
      "type": "Feature",
      "properties": {
        "hierarchy": [
          "tgn:2658201",
          "tgn:1000001",
          "tgn:2001181",
          "tgn:7012149",
          "tgn:7007523",
          "tgn:7029392"
        ],
        "placetype": [
          "aat:300008761"
        ],
        "id": 2658201,
        "name:xx": "Shelton Hollow"
      }
    },
    {
      "geometry": {
        "type": "Point",
        "coordinates": [
          -82.6,
          38.6333
        ]
      },
      "type": "Feature",
      "properties": {
        "hierarchy": [
          "tgn:2658202",
          "tgn:1000001",
          "tgn:7012149",
          "tgn:2001615",
          "tgn:7007706",
          "tgn:7029392"
        ],
        "placetype": [
          "aat:300008761"
        ],
        "id": 2658202,
        "name:xx": "Shelton Hollow"
      }
    },
    {
      "geometry": {
        "type": "Point",
        "coordinates": [
          -87.7833,
          35.6167
        ]
      },
      "type": "Feature",
      "properties": {
        "hierarchy": [
          "tgn:2658203",
          "tgn:1000001",
          "tgn:7012149",
          "tgn:2001904",
          "tgn:7007825",
          "tgn:7029392"
        ],
        "placetype": [
          "aat:300008761"
        ],
        "id": 2658203,
        "name:xx": "Shelton Hollow"
      }
    },
    {
      "geometry": {
        "type": "Point",
        "coordinates": [
          -86.0667,
          35.7167
        ]
      },
      "type": "Feature",
      "properties": {
        "hierarchy": [
          "tgn:2658204",
          "tgn:1000001",
          "tgn:7012149",
          "tgn:2001844",
          "tgn:7007825",
          "tgn:7029392"
        ],
        "placetype": [
          "aat:300008761"
        ],
        "id": 2658204,
        "name:xx": "Shelton Hollow"
      }
    },
    {
      "geometry": {
        "type": "Point",
        "coordinates": [
          -86.9833,
          35.9667
        ]
      },
      "type": "Feature",
      "properties": {
        "hierarchy": [
          "tgn:2658205",
          "tgn:1000001",
          "tgn:7012149",
          "tgn:2001930",
          "tgn:7007825",
          "tgn:7029392"
        ],
        "placetype": [
          "aat:300008761"
        ],
        "id": 2658205,
        "name:xx": "Shelton Hollow"
      }
    },
    {
      "geometry": {
        "type": "Point",
        "coordinates": [
          -98.1333,
          29.9333
        ]
      },
      "type": "Feature",
      "properties": {
        "hierarchy": [
          "tgn:2658206",
          "tgn:1000001",
          "tgn:7012149",
          "tgn:1002463",
          "tgn:7007826",
          "tgn:7029392"
        ],
        "placetype": [
          "aat:300008761"
        ],
        "id": 2658206,
        "name:xx": "Shelton Hollow"
      }
    },
    {
      "geometry": {
        "type": "Point",
        "coordinates": [
          -81.4167,
          34.5167
        ]
      },
      "type": "Feature",
      "properties": {
        "hierarchy": [
          "tgn:2658207",
          "tgn:1000001",
          "tgn:2001744",
          "tgn:7012149",
          "tgn:7007712",
          "tgn:7029392"
        ],
        "placetype": [
          "aat:300008791"
        ],
        "id": 2658207,
        "name:xx": "Shelton Island"
      }
    },
    {
      "geometry": {
        "type": "Point",
        "coordinates": [
          -86.2833,
          32.75
        ]
      },
      "type": "Feature",
      "properties": {
        "hierarchy": [
          "tgn:2658208",
          "tgn:7002659",
          "tgn:1000001",
          "tgn:2000018",
          "tgn:7012149",
          "tgn:7029392"
        ],
        "placetype": [
          "aat:300006191"
        ],
        "id": 2658208,
        "name:xx": "Shelton Lake"
      }
    },
    {
      "geometry": {
        "type": "Point",
        "coordinates": [
          -86.5167,
          33.3667
        ]
      },
      "type": "Feature",
      "properties": {
        "hierarchy": [
          "tgn:2658209",
          "tgn:7002659",
          "tgn:1000001",
          "tgn:7012149",
          "tgn:2000058",
          "tgn:7029392"
        ],
        "placetype": [
          "aat:300006191"
        ],
        "id": 2658209,
        "name:xx": "Shelton Lake"
      }
    }
  ]
}
