{
  "geometry": {
    "type": "Point",
    "coordinates": [
      -70.5833,
      41.7167
    ]
  },
  "type": "Feature",
  "properties": {
    "hierarchy": [
      "tgn:2142200",
      "tgn:1002165",
      "tgn:1000001",
      "tgn:7012149",
      "tgn:7007517",
      "tgn:7029392"
    ],
    "placetype": [
      "aat:300008707"
    ],
    "id": 2142200,
    "name:xx": "Back River"
  }
}
