{
  "geometry": {
    "type": "Point",
    "coordinates": [
      -105.55,
      41.15
    ]
  },
  "type": "Feature",
  "properties": {
    "hierarchy": [
      "tgn:2377382",
      "tgn:2002365",
      "tgn:1000001",
      "tgn:7012149",
      "tgn:7007923",
      "tgn:7029392"
    ],
    "placetype": [
      "aat:300006191"
    ],
    "id": 2377382,
    "name:xx": "Harney Creek Reservoir"
  }
}
