{
  "type": "FeatureCollection",
  "features": [
    {
      "geometry": {
        "type": "Point",
        "coordinates": [
          -101.8333,
          39.85
        ]
      },
      "type": "Feature",
      "properties": {
        "hierarchy": [
          "tgn:2686370",
          "tgn:1000001",
          "tgn:2000671",
          "tgn:7012149",
          "tgn:7007254",
          "tgn:7029392"
        ],
        "placetype": [
          "aat:300008706"
        ],
        "id": 2686370,
        "name:xx": "Spring Creek"
      }
    },
    {
      "geometry": {
        "type": "Point",
        "coordinates": [
          -101.1667,
          38.9
        ]
      },
      "type": "Feature",
      "properties": {
        "hierarchy": [
          "tgn:2686371",
          "tgn:1000001",
          "tgn:7012149",
          "tgn:2000714",
          "tgn:7007254",
          "tgn:7029392"
        ],
        "placetype": [
          "aat:300008706"
        ],
        "id": 2686371,
        "name:xx": "Spring Creek"
      }
    },
    {
      "geometry": {
        "type": "Point",
        "coordinates": [
          -100.0667,
          37.95
        ]
      },
      "type": "Feature",
      "properties": {
        "hierarchy": [
          "tgn:2686372",
          "tgn:1000001",
          "tgn:2000701",
          "tgn:7012149",
          "tgn:7007254",
          "tgn:7029392"
        ],
        "placetype": [
          "aat:300008706"
        ],
        "id": 2686372,
        "name:xx": "Spring Creek"
      }
    },
    {
      "geometry": {
        "type": "Point",
        "coordinates": [
          -99.9,
          39.9167
        ]
      },
      "type": "Feature",
      "properties": {
        "hierarchy": [
          "tgn:2686373",
          "tgn:1000001",
          "tgn:7012149",
          "tgn:2000728",
          "tgn:7007254",
          "tgn:7029392"
        ],
        "placetype": [
          "aat:300008706"
        ],
        "id": 2686373,
        "name:xx": "Spring Creek"
      }
    },
    {
      "geometry": {
        "type": "Point",
        "coordinates": [
          -99.3167,
          39.9
        ]
      },
      "type": "Feature",
      "properties": {
        "hierarchy": [
          "tgn:2686374",
          "tgn:1000001",
          "tgn:7012149",
          "tgn:2000733",
          "tgn:7007254",
          "tgn:7029392"
        ],
        "placetype": [
          "aat:300008706"
        ],
        "id": 2686374,
        "name:xx": "Spring Creek"
      }
    },
    {
      "geometry": {
        "type": "Point",
        "coordinates": [
          -98.7,
          39.9
        ]
      },
      "type": "Feature",
      "properties": {
        "hierarchy": [
          "tgn:2686375",
          "tgn:1000001",
          "tgn:7012149",
          "tgn:2000751",
          "tgn:7007254",
          "tgn:7029392"
        ],
        "placetype": [
          "aat:300008706"
        ],
        "id": 2686375,
        "name:xx": "Spring Creek"
      }
    },
    {
      "geometry": {
        "type": "Point",
        "coordinates": [
          -98.2167,
          39.85
        ]
      },
      "type": "Feature",
      "properties": {
        "hierarchy": [
          "tgn:2686376",
          "tgn:1000001",
          "tgn:2000704",
          "tgn:7012149",
          "tgn:7007254",
          "tgn:7029392"
        ],
        "placetype": [
          "aat:300008706"
        ],
        "id": 2686376,
        "name:xx": "Spring Creek"
      }
    },
    {
      "geometry": {
        "type": "Point",
        "coordinates": [
          -99.8,
          39.4833
        ]
      },
      "type": "Feature",
      "properties": {
        "hierarchy": [
          "tgn:2686377",
          "tgn:1000001",
          "tgn:2000692",
          "tgn:7012149",
          "tgn:7007254",
          "tgn:7029392"
        ],
        "placetype": [
          "aat:300008706"
        ],
        "id": 2686377,
        "name:xx": "Spring Creek"
      }
    },
    {
      "geometry": {
        "type": "Point",
        "coordinates": [
          -66.5333,
          39.2333
        ]
      },
      "type": "Feature",
      "properties": {
        "hierarchy": [
          "tgn:2686378",
          "tgn:1000001",
          "tgn:7012149",
          "tgn:2000741",
          "tgn:7007254",
          "tgn:7029392"
        ],
        "placetype": [
          "aat:300008706"
        ],
        "id": 2686378,
        "name:xx": "Spring Creek"
      }
    },
    {
      "geometry": {
        "type": "Point",
        "coordinates": [
          -96.4667,
          39.9167
        ]
      },
      "type": "Feature",
      "properties": {
        "hierarchy": [
          "tgn:2686379",
          "tgn:1000001",
          "tgn:7012149",
          "tgn:2000718",
          "tgn:7007254",
          "tgn:7029392"
        ],
        "placetype": [
          "aat:300008706"
        ],
        "id": 2686379,
        "name:xx": "Spring Creek"
      }
    }
  ]
}
