{
  "geometry": {
    "type": "Point",
    "coordinates": [
      -88.9667,
      45.1667
    ]
  },
  "type": "Feature",
  "properties": {
    "hierarchy": [
      "tgn:2281852",
      "tgn:1000001",
      "tgn:7012149",
      "tgn:2002333",
      "tgn:7007922",
      "tgn:7029392"
    ],
    "placetype": [
      "aat:300008706"
    ],
    "id": 2281852,
    "name:xx": "Deer Creek"
  }
}
