{
  "geometry": {
    "type": "Point",
    "coordinates": [
      5.55,
      45.4167
    ]
  },
  "type": "Feature",
  "properties": {
    "hierarchy": [
      "tgn:1032669",
      "tgn:1000003",
      "tgn:1000070",
      "tgn:7002897",
      "tgn:7029392"
    ],
    "placetype": [
      "aat:300008347"
    ],
    "id": 1032669,
    "name:xx": "Chirens"
  }
}
