{
  "geometry": {
    "type": "Point",
    "coordinates": [
      -131.5333,
      55.6167
    ]
  },
  "type": "Feature",
  "properties": {
    "hierarchy": [
      "tgn:2317168",
      "tgn:7006450",
      "tgn:1000001",
      "tgn:2124076",
      "tgn:7012149",
      "tgn:7029392"
    ],
    "placetype": [
      "aat:300008680"
    ],
    "id": 2317168,
    "name:xx": "Emma Lake"
  }
}
