{
  "geometry": {
    "type": "Point",
    "coordinates": [
      121.0667,
      13.6333
    ]
  },
  "type": "Feature",
  "properties": {
    "hierarchy": [
      "tgn:1084262",
      "tgn:1000004",
      "tgn:1001147",
      "tgn:1000135",
      "tgn:7029392"
    ],
    "placetype": [
      "aat:300008347"
    ],
    "id": 1084262,
    "name:xx": "Ilijan"
  }
}
