{
  "geometry": {
    "type": "Point",
    "coordinates": [
      -86.2833,
      32.0833
    ]
  },
  "type": "Feature",
  "properties": {
    "hierarchy": [
      "tgn:2226916",
      "tgn:7002659",
      "tgn:1000001",
      "tgn:7012149",
      "tgn:2000050",
      "tgn:7029392"
    ],
    "placetype": [
      "aat:300006191"
    ],
    "id": 2226916,
    "name:xx": "Cauthen Lake Number Two"
  }
}
