{
  "type": "FeatureCollection",
  "features": [
    {
      "geometry": {
        "type": "Point",
        "coordinates": [
          36.5,
          -13.3333
        ]
      },
      "type": "Feature",
      "properties": {
        "hierarchy": [
          "tgn:1091680",
          "tgn:7001242",
          "tgn:1000906",
          "tgn:1000180",
          "tgn:7029392"
        ],
        "placetype": [
          "aat:300008347"
        ],
        "id": 1091680,
        "name:xx": "Révia"
      }
    },
    {
      "geometry": {
        "type": "Point",
        "coordinates": [
          38.3167,
          -14.95
        ]
      },
      "type": "Feature",
      "properties": {
        "hierarchy": [
          "tgn:1091681",
          "tgn:7001242",
          "tgn:1000902",
          "tgn:1000180",
          "tgn:7029392"
        ],
        "placetype": [
          "aat:300008347"
        ],
        "id": 1091681,
        "name:xx": "Ribauè"
      }
    },
    {
      "geometry": {
        "type": "Point",
        "coordinates": [
          35.4,
          -23.2
        ]
      },
      "type": "Feature",
      "properties": {
        "hierarchy": [
          "tgn:1091682",
          "tgn:7001242",
          "tgn:1000869",
          "tgn:1000180",
          "tgn:7029392"
        ],
        "placetype": [
          "aat:300008347"
        ],
        "id": 1091682,
        "name:xx": "Rio das Pedras"
      }
    },
    {
      "geometry": {
        "type": "Point",
        "coordinates": [
          32.8333,
          -19.55
        ]
      },
      "type": "Feature",
      "properties": {
        "hierarchy": [
          "tgn:1091683",
          "tgn:7001242",
          "tgn:1000891",
          "tgn:1000180",
          "tgn:7029392"
        ],
        "placetype": [
          "aat:300008347"
        ],
        "id": 1091683,
        "name:xx": "Rotanda"
      }
    },
    {
      "geometry": {
        "type": "Point",
        "coordinates": [
          32.6667,
          -26.4833
        ]
      },
      "type": "Feature",
      "properties": {
        "hierarchy": [
          "tgn:1091684",
          "tgn:7001242",
          "tgn:1000893",
          "tgn:1000180",
          "tgn:7029392"
        ],
        "placetype": [
          "aat:300008347"
        ],
        "id": 1091684,
        "name:xx": "Salamanga"
      }
    },
    {
      "geometry": {
        "type": "Point",
        "coordinates": [
          32.5333,
          -26.6167
        ]
      },
      "type": "Feature",
      "properties": {
        "hierarchy": [
          "tgn:1091685",
          "tgn:7001242",
          "tgn:1000893",
          "tgn:1000180",
          "tgn:7029392"
        ],
        "placetype": [
          "aat:300008347"
        ],
        "id": 1091685,
        "name:xx": "Santaca"
      }
    },
    {
      "geometry": {
        "type": "Point",
        "coordinates": [
          34.2333,
          -16.7
        ]
      },
      "type": "Feature",
      "properties": {
        "hierarchy": [
          "tgn:1091687",
          "tgn:7001242",
          "tgn:1000891",
          "tgn:1000180",
          "tgn:7029392"
        ],
        "placetype": [
          "aat:300008347"
        ],
        "id": 1091687,
        "name:xx": "Tambara"
      }
    },
    {
      "geometry": {
        "type": "Point",
        "coordinates": [
          32.8833,
          -14.9
        ]
      },
      "type": "Feature",
      "properties": {
        "hierarchy": [
          "tgn:1091688",
          "tgn:7001242",
          "tgn:1000940",
          "tgn:1000180",
          "tgn:7029392"
        ],
        "placetype": [
          "aat:300008347"
        ],
        "id": 1091688,
        "name:xx": "Tembuè"
      }
    }
  ]
}
