{
  "geometry": {
    "type": "Point",
    "coordinates": [
      -123.1167,
      45.0667
    ]
  },
  "type": "Feature",
  "properties": {
    "hierarchy": [
      "tgn:2318284",
      "tgn:1000001",
      "tgn:7012149",
      "tgn:7007708",
      "tgn:7029392"
    ],
    "placetype": [
      "aat:300386831"
    ],
    "id": 2318284,
    "name:xx": "Eola Hills"
  }
}
