{
  "geometry": {
    "type": "Point",
    "coordinates": [
      24.474167,
      38.871667
    ]
  },
  "type": "Feature",
  "properties": {
    "hierarchy": [
      "tgn:7235672",
      "tgn:7011171",
      "tgn:7001395",
      "tgn:1000003",
      "tgn:1000074",
      "tgn:7029392"
    ],
    "placetype": [
      "aat:300132316"
    ],
    "id": 7235672,
    "name:xx": "Ayíou Foká, Órmos"
  }
}
