{
  "geometry": {
    "type": "Point",
    "coordinates": [
      -113.3667,
      48.4167
    ]
  },
  "type": "Feature",
  "properties": {
    "hierarchy": [
      "tgn:2211448",
      "tgn:1000001",
      "tgn:7012149",
      "tgn:2001277",
      "tgn:7007524",
      "tgn:7029392"
    ],
    "placetype": [
      "aat:300386845"
    ],
    "id": 2211448,
    "name:xx": "Buttercup Park"
  }
}
