{
  "geometry": {
    "type": "Point",
    "coordinates": [
      -94.8333,
      30.1667
    ]
  },
  "type": "Feature",
  "properties": {
    "hierarchy": [
      "tgn:2571963",
      "tgn:1000001",
      "tgn:7012149",
      "tgn:1002595",
      "tgn:7007826",
      "tgn:7029392"
    ],
    "placetype": [
      "aat:300008680"
    ],
    "id": 2571963,
    "name:xx": "Payne Lake"
  }
}
