{
  "type": "FeatureCollection",
  "features": [
    {
      "geometry": {
        "type": "Point",
        "coordinates": [
          -166.0833,
          65.3167
        ]
      },
      "type": "Feature",
      "properties": {
        "hierarchy": [
          "tgn:2627590",
          "tgn:7006450",
          "tgn:1000001",
          "tgn:7012149",
          "tgn:2000079",
          "tgn:7029392"
        ],
        "placetype": [
          "aat:300008706"
        ],
        "id": 2627590,
        "name:xx": "Rogers Creek"
      }
    },
    {
      "geometry": {
        "type": "Point",
        "coordinates": [
          -93.6,
          34.5
        ]
      },
      "type": "Feature",
      "properties": {
        "hierarchy": [
          "tgn:2627591",
          "tgn:1000001",
          "tgn:7016172",
          "tgn:7012149",
          "tgn:2000153",
          "tgn:7029392"
        ],
        "placetype": [
          "aat:300008706"
        ],
        "id": 2627591,
        "name:xx": "Rogers Creek"
      }
    },
    {
      "geometry": {
        "type": "Point",
        "coordinates": [
          -93.6,
          35.0333
        ]
      },
      "type": "Feature",
      "properties": {
        "hierarchy": [
          "tgn:2627592",
          "tgn:1000001",
          "tgn:7016172",
          "tgn:7012149",
          "tgn:2000179",
          "tgn:7029392"
        ],
        "placetype": [
          "aat:300008706"
        ],
        "id": 2627592,
        "name:xx": "Rogers Creek"
      }
    },
    {
      "geometry": {
        "type": "Point",
        "coordinates": [
          -122.2167,
          37.1833
        ]
      },
      "type": "Feature",
      "properties": {
        "hierarchy": [
          "tgn:2627593",
          "tgn:1000001",
          "tgn:7012149",
          "tgn:7007157",
          "tgn:1002869",
          "tgn:7029392"
        ],
        "placetype": [
          "aat:300008706"
        ],
        "id": 2627593,
        "name:xx": "Rogers Creek"
      }
    },
    {
      "geometry": {
        "type": "Point",
        "coordinates": [
          -120.55,
          37.9333
        ]
      },
      "type": "Feature",
      "properties": {
        "hierarchy": [
          "tgn:2627594",
          "tgn:1000001",
          "tgn:1002219",
          "tgn:7012149",
          "tgn:7007157",
          "tgn:7029392"
        ],
        "placetype": [
          "aat:300008706"
        ],
        "id": 2627594,
        "name:xx": "Rogers Creek"
      }
    },
    {
      "geometry": {
        "type": "Point",
        "coordinates": [
          -123.8333,
          40.4833
        ]
      },
      "type": "Feature",
      "properties": {
        "hierarchy": [
          "tgn:2627595",
          "tgn:1000001",
          "tgn:7012149",
          "tgn:2000181",
          "tgn:7007157",
          "tgn:7029392"
        ],
        "placetype": [
          "aat:300008706"
        ],
        "id": 2627595,
        "name:xx": "Rogers Creek"
      }
    },
    {
      "geometry": {
        "type": "Point",
        "coordinates": [
          -123.4,
          41.45
        ]
      },
      "type": "Feature",
      "properties": {
        "hierarchy": [
          "tgn:2627596",
          "tgn:1000001",
          "tgn:7012149",
          "tgn:7007157",
          "tgn:2000189",
          "tgn:7029392"
        ],
        "placetype": [
          "aat:300008706"
        ],
        "id": 2627596,
        "name:xx": "Rogers Creek"
      }
    },
    {
      "geometry": {
        "type": "Point",
        "coordinates": [
          -118.25,
          34.5667
        ]
      },
      "type": "Feature",
      "properties": {
        "hierarchy": [
          "tgn:2627597",
          "tgn:1000001",
          "tgn:7012149",
          "tgn:7007157",
          "tgn:1002608",
          "tgn:7029392"
        ],
        "placetype": [
          "aat:300008706"
        ],
        "id": 2627597,
        "name:xx": "Rogers Creek"
      }
    },
    {
      "geometry": {
        "type": "Point",
        "coordinates": [
          -120.0833,
          35.2
        ]
      },
      "type": "Feature",
      "properties": {
        "hierarchy": [
          "tgn:2627598",
          "tgn:1000001",
          "tgn:7012149",
          "tgn:7007157",
          "tgn:1002863",
          "tgn:7029392"
        ],
        "placetype": [
          "aat:300008706"
        ],
        "id": 2627598,
        "name:xx": "Rogers Creek"
      }
    },
    {
      "geometry": {
        "type": "Point",
        "coordinates": [
          -83.5833,
          34.6833
        ]
      },
      "type": "Feature",
      "properties": {
        "hierarchy": [
          "tgn:2627599",
          "tgn:1000001",
          "tgn:7012149",
          "tgn:2000359",
          "tgn:7007248",
          "tgn:7029392"
        ],
        "placetype": [
          "aat:300008706"
        ],
        "id": 2627599,
        "name:xx": "Rogers Creek"
      }
    }
  ]
}
