{
  "geometry": {
    "type": "Point",
    "coordinates": [
      -81.5833,
      37.8333
    ]
  },
  "type": "Feature",
  "properties": {
    "hierarchy": [
      "tgn:2419539",
      "tgn:1000001",
      "tgn:2002255",
      "tgn:7012149",
      "tgn:7013961",
      "tgn:7029392"
    ],
    "placetype": [
      "aat:300266640"
    ],
    "id": 2419539,
    "name:xx": "Jarrells Ridge"
  }
}
