{
  "geometry": {
    "type": "Point",
    "coordinates": [
      55.2833,
      -20.95
    ]
  },
  "type": "Feature",
  "properties": {
    "hierarchy": [
      "tgn:7032297",
      "tgn:7001680",
      "tgn:7001242",
      "tgn:1000184",
      "tgn:7029392"
    ],
    "placetype": [
      "aat:300008699"
    ],
    "name:fr": "Galets, Rivière des",
    "id": 7032297
  }
}
