{
  "geometry": {
    "type": "Point",
    "coordinates": [
      -90.4167,
      35.6167
    ]
  },
  "type": "Feature",
  "properties": {
    "hierarchy": [
      "tgn:2414140",
      "tgn:1000001",
      "tgn:7016172",
      "tgn:7012149",
      "tgn:2000160",
      "tgn:7029392"
    ],
    "placetype": [
      "aat:300008706"
    ],
    "id": 2414140,
    "name:xx": "Iron Mines Creek"
  }
}
