{
  "geometry": {
    "type": "Point",
    "coordinates": [
      -82.3667,
      33.1833
    ]
  },
  "type": "Feature",
  "properties": {
    "hierarchy": [
      "tgn:2438413",
      "tgn:1000001",
      "tgn:7012149",
      "tgn:2000372",
      "tgn:7007248",
      "tgn:7029392"
    ],
    "placetype": [
      "aat:300006191"
    ],
    "id": 2438413,
    "name:xx": "Kings Mill Pond"
  }
}
