{
  "type": "FeatureCollection",
  "features": [
    {
      "geometry": {
        "type": "Point",
        "coordinates": [
          -84.1333,
          38.7833
        ]
      },
      "type": "Feature",
      "properties": {
        "hierarchy": [
          "tgn:2078846",
          "tgn:1000001",
          "tgn:1002279",
          "tgn:7012149",
          "tgn:7007706",
          "tgn:7029392"
        ],
        "placetype": [
          "aat:300008347"
        ],
        "id": 2078846,
        "name:xx": "Chilo"
      }
    },
    {
      "geometry": {
        "type": "Point",
        "coordinates": [
          -81.9,
          41.0667
        ]
      },
      "type": "Feature",
      "properties": {
        "hierarchy": [
          "tgn:2078848",
          "tgn:1000001",
          "tgn:7012149",
          "tgn:1002654",
          "tgn:7007706",
          "tgn:7029392"
        ],
        "placetype": [
          "aat:300008347"
        ],
        "id": 2078848,
        "name:xx": "Chippewa-on-the-Lake"
      }
    },
    {
      "geometry": {
        "type": "Point",
        "coordinates": [
          -81.8833,
          41.05
        ]
      },
      "type": "Feature",
      "properties": {
        "hierarchy": [
          "tgn:2078849",
          "tgn:1000001",
          "tgn:7012149",
          "tgn:1002654",
          "tgn:7007706",
          "tgn:7029392"
        ],
        "placetype": [
          "aat:300008347"
        ],
        "id": 2078849,
        "name:xx": "Chippewa Lake Park"
      }
    }
  ]
}
