{
  "geometry": {
    "type": "Point",
    "coordinates": [
      -81.7333,
      39.8667
    ]
  },
  "type": "Feature",
  "properties": {
    "hierarchy": [
      "tgn:2498108",
      "tgn:1000001",
      "tgn:7012149",
      "tgn:7007706",
      "tgn:7029392"
    ],
    "placetype": [
      "aat:300008699"
    ],
    "id": 2498108,
    "name:xx": "Mays Fork"
  }
}
