{
  "geometry": {
    "type": "Point",
    "coordinates": [
      -81.6833,
      31.8333
    ]
  },
  "type": "Feature",
  "properties": {
    "hierarchy": [
      "tgn:2456279",
      "tgn:1000001",
      "tgn:7012149",
      "tgn:2000380",
      "tgn:7007248",
      "tgn:7029392"
    ],
    "placetype": [
      "aat:300008706"
    ],
    "id": 2456279,
    "name:xx": "Little Horse Creek"
  }
}
