{
  "geometry": {
    "type": "Point",
    "coordinates": [
      74.104167,
      33.202778
    ]
  },
  "type": "Feature",
  "properties": {
    "hierarchy": [
      "tgn:7591225",
      "tgn:1000004",
      "tgn:7000198",
      "tgn:7000799",
      "tgn:7029392"
    ],
    "placetype": [
      "aat:300008347"
    ],
    "name:en": "Kambīla",
    "id": 7591225
  }
}
