{
  "type": "FeatureCollection",
  "features": [
    {
      "geometry": {
        "type": "Point",
        "coordinates": [
          -86.2667,
          33.3
        ]
      },
      "type": "Feature",
      "properties": {
        "hierarchy": [
          "tgn:2227260",
          "tgn:7002659",
          "tgn:1000001",
          "tgn:7012149",
          "tgn:2000060",
          "tgn:7029392"
        ],
        "placetype": [
          "aat:300008798"
        ],
        "id": 2227260,
        "name:xx": "Cave Mountain"
      }
    },
    {
      "geometry": {
        "type": "Point",
        "coordinates": [
          -112.2333,
          32.3833
        ]
      },
      "type": "Feature",
      "properties": {
        "hierarchy": [
          "tgn:2227261",
          "tgn:1000001",
          "tgn:7006451",
          "tgn:7012149",
          "tgn:2000100",
          "tgn:7029392"
        ],
        "placetype": [
          "aat:300008798"
        ],
        "id": 2227261,
        "name:xx": "Cave Mountain"
      }
    },
    {
      "geometry": {
        "type": "Point",
        "coordinates": [
          -110.2833,
          35.5333
        ]
      },
      "type": "Feature",
      "properties": {
        "hierarchy": [
          "tgn:2227262",
          "tgn:1000001",
          "tgn:7006451",
          "tgn:7012149",
          "tgn:2000099",
          "tgn:7029392"
        ],
        "placetype": [
          "aat:300008798"
        ],
        "id": 2227262,
        "name:xx": "Cave Mountain"
      }
    },
    {
      "geometry": {
        "type": "Point",
        "coordinates": [
          -93.4333,
          35.9167
        ]
      },
      "type": "Feature",
      "properties": {
        "hierarchy": [
          "tgn:2227263",
          "tgn:1000001",
          "tgn:7016172",
          "tgn:7012149",
          "tgn:2000155",
          "tgn:7029392"
        ],
        "placetype": [
          "aat:300008798"
        ],
        "id": 2227263,
        "name:xx": "Cave Mountain"
      }
    },
    {
      "geometry": {
        "type": "Point",
        "coordinates": [
          -120.85,
          40.7
        ]
      },
      "type": "Feature",
      "properties": {
        "hierarchy": [
          "tgn:2227264",
          "tgn:1000001",
          "tgn:7012149",
          "tgn:7007157",
          "tgn:2000184",
          "tgn:7029392"
        ],
        "placetype": [
          "aat:300008798"
        ],
        "id": 2227264,
        "name:xx": "Cave Mountain"
      }
    },
    {
      "geometry": {
        "type": "Point",
        "coordinates": [
          -116.3167,
          35.0667
        ]
      },
      "type": "Feature",
      "properties": {
        "hierarchy": [
          "tgn:2227265",
          "tgn:1000001",
          "tgn:7012149",
          "tgn:7007157",
          "tgn:1002857",
          "tgn:7029392"
        ],
        "placetype": [
          "aat:300008798"
        ],
        "id": 2227265,
        "name:xx": "Cave Mountain"
      }
    },
    {
      "geometry": {
        "type": "Point",
        "coordinates": [
          -111.75,
          44.9
        ]
      },
      "type": "Feature",
      "properties": {
        "hierarchy": [
          "tgn:2227266",
          "tgn:1000001",
          "tgn:7012149",
          "tgn:2001288",
          "tgn:7007524",
          "tgn:7029392"
        ],
        "placetype": [
          "aat:300008798"
        ],
        "id": 2227266,
        "name:xx": "Cave Mountain"
      }
    },
    {
      "geometry": {
        "type": "Point",
        "coordinates": [
          -112.7333,
          47.9
        ]
      },
      "type": "Feature",
      "properties": {
        "hierarchy": [
          "tgn:2227267",
          "tgn:1000001",
          "tgn:7012149",
          "tgn:2001309",
          "tgn:7007524",
          "tgn:7029392"
        ],
        "placetype": [
          "aat:300008798"
        ],
        "id": 2227267,
        "name:xx": "Cave Mountain"
      }
    },
    {
      "geometry": {
        "type": "Point",
        "coordinates": [
          -114.6,
          39.15
        ]
      },
      "type": "Feature",
      "properties": {
        "hierarchy": [
          "tgn:2227268",
          "tgn:1000001",
          "tgn:7012149",
          "tgn:2001420",
          "tgn:7007526",
          "tgn:7029392"
        ],
        "placetype": [
          "aat:300008798"
        ],
        "id": 2227268,
        "name:xx": "Cave Mountain"
      }
    },
    {
      "geometry": {
        "type": "Point",
        "coordinates": [
          -71.2833,
          44.0833
        ]
      },
      "type": "Feature",
      "properties": {
        "hierarchy": [
          "tgn:2227269",
          "tgn:2001423",
          "tgn:1000001",
          "tgn:7012149",
          "tgn:7007564",
          "tgn:7029392"
        ],
        "placetype": [
          "aat:300008798"
        ],
        "id": 2227269,
        "name:xx": "Cave Mountain"
      }
    }
  ]
}
