{
  "geometry": {
    "type": "Point",
    "coordinates": [
      -89.25,
      31.2167
    ]
  },
  "type": "Feature",
  "properties": {
    "hierarchy": [
      "tgn:2703728",
      "tgn:1000001",
      "tgn:7012149",
      "tgn:2001103",
      "tgn:7007522",
      "tgn:7029392"
    ],
    "placetype": [
      "aat:300006191"
    ],
    "id": 2703728,
    "name:xx": "Sumrall Lake"
  }
}
