{
  "geometry": {
    "type": "Point",
    "coordinates": [
      -98.4833,
      32.3333
    ]
  },
  "type": "Feature",
  "properties": {
    "hierarchy": [
      "tgn:2758976",
      "tgn:1000001",
      "tgn:7012149",
      "tgn:7007826",
      "tgn:7029392"
    ],
    "placetype": [
      "aat:300008706"
    ],
    "id": 2758976,
    "name:xx": "West Fork Armstrong Creek"
  }
}
