{
  "geometry": {
    "type": "Point",
    "coordinates": [
      7.25,
      50.1667
    ]
  },
  "type": "Feature",
  "properties": {
    "name:en": "Mosel",
    "hierarchy": [
      "tgn:7016544",
      "tgn:1000003",
      "tgn:7029392"
    ],
    "name:de": "Mosel",
    "placetype": [
      "aat:300008707"
    ],
    "name:fr": "Moselle",
    "name:la": "Mosella",
    "name:it": "Mosella",
    "id": 7016544,
    "name:es": "Mosela"
  }
}
