{
  "geometry": {
    "type": "Point",
    "coordinates": [
      -75.1667,
      38.25
    ]
  },
  "type": "Feature",
  "properties": {
    "hierarchy": [
      "tgn:2302195",
      "tgn:1000001",
      "tgn:1003037",
      "tgn:7012149",
      "tgn:7007516",
      "tgn:7029392"
    ],
    "placetype": [
      "aat:300008678"
    ],
    "id": 2302195,
    "name:xx": "Dutch Harbor"
  }
}
