{
  "geometry": {
    "type": "Point",
    "coordinates": [
      -106.5167,
      45.25
    ]
  },
  "type": "Feature",
  "properties": {
    "hierarchy": [
      "tgn:2501189",
      "tgn:1000001",
      "tgn:7012149",
      "tgn:2001303",
      "tgn:7007524",
      "tgn:7029392"
    ],
    "placetype": [
      "aat:300008761"
    ],
    "id": 2501189,
    "name:xx": "McGhee Gulch"
  }
}
