{
  "geometry": {
    "type": "Point",
    "coordinates": [
      27.3475,
      36.4275
    ]
  },
  "type": "Feature",
  "properties": {
    "hierarchy": [
      "tgn:7236354",
      "tgn:7011330",
      "tgn:7002674",
      "tgn:1000003",
      "tgn:1000074",
      "tgn:7029392"
    ],
    "placetype": [
      "aat:300132316"
    ],
    "id": 7236354,
    "name:xx": "Éristos, Ormískos"
  }
}
