{
  "geometry": {
    "type": "Point",
    "coordinates": [
      -87.1167,
      34.8667
    ]
  },
  "type": "Feature",
  "properties": {
    "hierarchy": [
      "tgn:2183297",
      "tgn:7002659",
      "tgn:1000001",
      "tgn:7012149",
      "tgn:2000041",
      "tgn:7029392"
    ],
    "placetype": [
      "aat:300008746"
    ],
    "id": 2183297,
    "name:xx": "Bluff Cave"
  }
}
