{
  "geometry": {
    "type": "Point",
    "coordinates": [
      -86.2333,
      39.0833
    ]
  },
  "type": "Feature",
  "properties": {
    "hierarchy": [
      "tgn:2591308",
      "tgn:1000001",
      "tgn:1002209",
      "tgn:7012149",
      "tgn:7007252",
      "tgn:7029392"
    ],
    "placetype": [
      "aat:300008798"
    ],
    "id": 2591308,
    "name:xx": "Polly Hill"
  }
}
