{
  "geometry": {
    "type": "Point",
    "coordinates": [
      -109.6333,
      37.85
    ]
  },
  "type": "Feature",
  "properties": {
    "hierarchy": [
      "tgn:2771405",
      "tgn:1000001",
      "tgn:7012149",
      "tgn:2002119",
      "tgn:7007827",
      "tgn:7029392"
    ],
    "placetype": [
      "aat:300055621"
    ],
    "id": 2771405,
    "name:xx": "Wilderness, The"
  }
}
