{
  "geometry": {
    "type": "Point",
    "coordinates": [
      -105.3833,
      42.1167
    ]
  },
  "type": "Feature",
  "properties": {
    "hierarchy": [
      "tgn:2324448",
      "tgn:2002365",
      "tgn:1000001",
      "tgn:7012149",
      "tgn:7007923",
      "tgn:7029392"
    ],
    "placetype": [
      "aat:300008706"
    ],
    "id": 2324448,
    "name:xx": "Felix Creek"
  }
}
