{
  "geometry": {
    "type": "Point",
    "coordinates": [
      -77.9667,
      42.8833
    ]
  },
  "type": "Feature",
  "properties": {
    "hierarchy": [
      "tgn:2485900",
      "tgn:1000001",
      "tgn:7012149",
      "tgn:1002407",
      "tgn:7007568",
      "tgn:7029392"
    ],
    "placetype": [
      "aat:300006191"
    ],
    "id": 2485900,
    "name:xx": "LeRoy Reservoir"
  }
}
