{
  "geometry": {
    "type": "Point",
    "coordinates": [
      -91.1667,
      48.0833
    ]
  },
  "type": "Feature",
  "properties": {
    "hierarchy": [
      "tgn:2652257",
      "tgn:1000001",
      "tgn:7012149",
      "tgn:2001036",
      "tgn:7007521",
      "tgn:7029392"
    ],
    "placetype": [
      "aat:300008680"
    ],
    "id": 2652257,
    "name:xx": "Sema Lake"
  }
}
