{
  "geometry": {
    "type": "Point",
    "coordinates": [
      -84.0667,
      32.3333
    ]
  },
  "type": "Feature",
  "properties": {
    "hierarchy": [
      "tgn:2768543",
      "tgn:1000001",
      "tgn:7012149",
      "tgn:2000387",
      "tgn:7007248",
      "tgn:7029392"
    ],
    "placetype": [
      "aat:300006191"
    ],
    "id": 2768543,
    "name:xx": "Whitewater Pond"
  }
}
