{
  "geometry": {
    "type": "Point",
    "coordinates": [
      -87.8667,
      36.0167
    ]
  },
  "type": "Feature",
  "properties": {
    "hierarchy": [
      "tgn:2586997",
      "tgn:1000001",
      "tgn:7012149",
      "tgn:2001879",
      "tgn:7007825",
      "tgn:7029392"
    ],
    "placetype": [
      "aat:300386851",
      "aat:300008791"
    ],
    "id": 2586997,
    "name:xx": "Plant Island"
  }
}
