{
  "geometry": {
    "type": "Point",
    "coordinates": [
      75.3333,
      38.6167
    ]
  },
  "type": "Feature",
  "properties": {
    "hierarchy": [
      "tgn:1104721",
      "tgn:1000004",
      "tgn:7001745",
      "tgn:1000111",
      "tgn:7029392"
    ],
    "placetype": [
      "aat:300008795"
    ],
    "id": 1104721,
    "name:xx": "Gonggeershan"
  }
}
