{
  "geometry": {
    "type": "Point",
    "coordinates": [
      -84.95,
      35.9833
    ]
  },
  "type": "Feature",
  "properties": {
    "hierarchy": [
      "tgn:2234651",
      "tgn:1000001",
      "tgn:7012149",
      "tgn:2001854",
      "tgn:7007825",
      "tgn:7029392"
    ],
    "placetype": [
      "aat:300008347"
    ],
    "id": 2234651,
    "name:xx": "Cherry Branch"
  }
}
