{
  "geometry": {
    "type": "Point",
    "coordinates": [
      -87.1833,
      32.75
    ]
  },
  "type": "Feature",
  "properties": {
    "hierarchy": [
      "tgn:2216161",
      "tgn:7002659",
      "tgn:1000001",
      "tgn:7012149",
      "tgn:2000052",
      "tgn:7029392"
    ],
    "placetype": [
      "aat:300008699"
    ],
    "id": 2216161,
    "name:xx": "Camp Branch"
  }
}
