{
  "geometry": {
    "type": "Point",
    "coordinates": [
      -91.5667,
      34.6833
    ]
  },
  "type": "Feature",
  "properties": {
    "hierarchy": [
      "tgn:2443662",
      "tgn:1000001",
      "tgn:7016172",
      "tgn:7012149",
      "tgn:2000163",
      "tgn:7029392"
    ],
    "placetype": [
      "aat:300008347"
    ],
    "id": 2443662,
    "name:xx": "La Grue"
  }
}
