{
  "geometry": {
    "type": "Point",
    "coordinates": [
      18.8333,
      50.1667
    ]
  },
  "type": "Feature",
  "properties": {
    "hierarchy": [
      "tgn:1049256",
      "tgn:1000003",
      "tgn:7024125",
      "tgn:7006366",
      "tgn:7029392"
    ],
    "placetype": [
      "aat:300008347"
    ],
    "id": 1049256,
    "name:xx": "Mikolów"
  }
}
