{
  "geometry": {
    "type": "Point",
    "coordinates": [
      -96.6667,
      38.2667
    ]
  },
  "type": "Feature",
  "properties": {
    "hierarchy": [
      "tgn:2333533",
      "tgn:1000001",
      "tgn:2000668",
      "tgn:7012149",
      "tgn:7007254",
      "tgn:7029392"
    ],
    "placetype": [
      "aat:300008706"
    ],
    "id": 2333533,
    "name:xx": "Folsom Creek"
  }
}
