{
  "geometry": {
    "type": "Point",
    "coordinates": [
      -96.4667,
      32.05
    ]
  },
  "type": "Feature",
  "properties": {
    "hierarchy": [
      "tgn:2506862",
      "tgn:1000001",
      "tgn:7012149",
      "tgn:1002709",
      "tgn:7007826",
      "tgn:7029392"
    ],
    "placetype": [
      "aat:300008699"
    ],
    "id": 2506862,
    "name:xx": "Mesquite Branch"
  }
}
