{
  "geometry": {
    "type": "Point",
    "coordinates": [
      -115.4833,
      43.6833
    ]
  },
  "type": "Feature",
  "properties": {
    "hierarchy": [
      "tgn:2657023",
      "tgn:1000001",
      "tgn:7012149",
      "tgn:7007250",
      "tgn:7029392"
    ],
    "placetype": [
      "aat:300008798"
    ],
    "id": 2657023,
    "name:xx": "Sheep Mountain"
  }
}
