{
  "geometry": {
    "type": "Point",
    "coordinates": [
      -118.5667,
      34.0333
    ]
  },
  "type": "Feature",
  "properties": {
    "hierarchy": [
      "tgn:2012576",
      "tgn:1000001",
      "tgn:7012149",
      "tgn:7007157",
      "tgn:1002608",
      "tgn:7013987",
      "tgn:7029392"
    ],
    "placetype": [
      "aat:300008347"
    ],
    "id": 2012576,
    "name:xx": "Topanga Beach"
  }
}
