{
  "geometry": {
    "type": "Point",
    "coordinates": [
      -74.8667,
      40.1667
    ]
  },
  "type": "Feature",
  "properties": {
    "hierarchy": [
      "tgn:2090168",
      "tgn:1000001",
      "tgn:1002213",
      "tgn:7012149",
      "tgn:7007710",
      "tgn:7029392"
    ],
    "placetype": [
      "aat:300247594"
    ],
    "id": 2090168,
    "name:xx": "Lincoln Plaza"
  }
}
