{
  "geometry": {
    "type": "Point",
    "coordinates": [
      12.9667,
      -5.9167
    ]
  },
  "type": "Feature",
  "properties": {
    "hierarchy": [
      "tgn:1087802",
      "tgn:7001242",
      "tgn:1000149",
      "tgn:1000954",
      "tgn:7029392"
    ],
    "placetype": [
      "aat:300008347"
    ],
    "id": 1087802,
    "name:xx": "Emílio de Carvalho"
  }
}
