{
  "geometry": {
    "type": "Point",
    "coordinates": [
      -99.8667,
      31.7667
    ]
  },
  "type": "Feature",
  "properties": {
    "hierarchy": [
      "tgn:2156380",
      "tgn:1000001",
      "tgn:7012149",
      "tgn:2002065",
      "tgn:7007826",
      "tgn:7029392"
    ],
    "placetype": [
      "aat:300008706"
    ],
    "id": 2156380,
    "name:xx": "Bears Foot Creek"
  }
}
