{
  "geometry": {
    "type": "Point",
    "coordinates": [
      5.15,
      50.266667
    ]
  },
  "type": "Feature",
  "properties": {
    "hierarchy": [
      "tgn:7243062",
      "tgn:7003466",
      "tgn:1000003",
      "tgn:1000063",
      "tgn:4012014",
      "tgn:7029392"
    ],
    "placetype": [
      "aat:300008347"
    ],
    "id": 7243062,
    "name:xx": "Les Culées"
  }
}
