{
  "type": "FeatureCollection",
  "features": [
    {
      "geometry": {
        "type": "Point",
        "coordinates": [
          -91.6833,
          48.0167
        ]
      },
      "type": "Feature",
      "properties": {
        "hierarchy": [
          "tgn:2539900",
          "tgn:1000001",
          "tgn:7012149",
          "tgn:2001036",
          "tgn:7007521",
          "tgn:7029392"
        ],
        "placetype": [
          "aat:300008791"
        ],
        "id": 2539900,
        "name:xx": "New York Island"
      }
    },
    {
      "geometry": {
        "type": "Point",
        "coordinates": [
          -117.8667,
          46.6
        ]
      },
      "type": "Feature",
      "properties": {
        "hierarchy": [
          "tgn:2539901",
          "tgn:1000001",
          "tgn:2002241",
          "tgn:7012149",
          "tgn:7007920",
          "tgn:7029392"
        ],
        "placetype": [
          "aat:300008791"
        ],
        "id": 2539901,
        "name:xx": "New York Island"
      }
    },
    {
      "geometry": {
        "type": "Point",
        "coordinates": [
          -110.6833,
          31.3667
        ]
      },
      "type": "Feature",
      "properties": {
        "hierarchy": [
          "tgn:2539903",
          "tgn:1000001",
          "tgn:7006451",
          "tgn:7012149",
          "tgn:2000102",
          "tgn:7029392"
        ],
        "placetype": [
          "aat:300000390"
        ],
        "id": 2539903,
        "name:xx": "New York Mine"
      }
    },
    {
      "geometry": {
        "type": "Point",
        "coordinates": [
          -120.95,
          40.1167
        ]
      },
      "type": "Feature",
      "properties": {
        "hierarchy": [
          "tgn:2539904",
          "tgn:1000001",
          "tgn:7012149",
          "tgn:7007157",
          "tgn:2000187",
          "tgn:7029392"
        ],
        "placetype": [
          "aat:300000390"
        ],
        "id": 2539904,
        "name:xx": "New York Mine"
      }
    },
    {
      "geometry": {
        "type": "Point",
        "coordinates": [
          -122.8333,
          41.6833
        ]
      },
      "type": "Feature",
      "properties": {
        "hierarchy": [
          "tgn:2539905",
          "tgn:1000001",
          "tgn:7012149",
          "tgn:7007157",
          "tgn:2000189",
          "tgn:7029392"
        ],
        "placetype": [
          "aat:300000390"
        ],
        "id": 2539905,
        "name:xx": "New York Mine"
      }
    },
    {
      "geometry": {
        "type": "Point",
        "coordinates": [
          -117.1667,
          35.7167
        ]
      },
      "type": "Feature",
      "properties": {
        "hierarchy": [
          "tgn:2539906",
          "tgn:1000001",
          "tgn:7012149",
          "tgn:7007157",
          "tgn:1002857",
          "tgn:7029392"
        ],
        "placetype": [
          "aat:300000390"
        ],
        "id": 2539906,
        "name:xx": "New York Mine"
      }
    },
    {
      "geometry": {
        "type": "Point",
        "coordinates": [
          -105.85,
          39.5667
        ]
      },
      "type": "Feature",
      "properties": {
        "hierarchy": [
          "tgn:2539907",
          "tgn:1000001",
          "tgn:7012149",
          "tgn:7007158",
          "tgn:2000250",
          "tgn:7029392"
        ],
        "placetype": [
          "aat:300000390"
        ],
        "id": 2539907,
        "name:xx": "New York Mine"
      }
    },
    {
      "geometry": {
        "type": "Point",
        "coordinates": [
          -115.6667,
          45.8333
        ]
      },
      "type": "Feature",
      "properties": {
        "hierarchy": [
          "tgn:2539908",
          "tgn:1000001",
          "tgn:7012149",
          "tgn:2000476",
          "tgn:7007250",
          "tgn:7029392"
        ],
        "placetype": [
          "aat:300000390"
        ],
        "id": 2539908,
        "name:xx": "New York Mine"
      }
    },
    {
      "geometry": {
        "type": "Point",
        "coordinates": [
          -119.65,
          39.2667
        ]
      },
      "type": "Feature",
      "properties": {
        "hierarchy": [
          "tgn:2539909",
          "tgn:1000001",
          "tgn:7012149",
          "tgn:1002921",
          "tgn:7007526",
          "tgn:7029392"
        ],
        "placetype": [
          "aat:300000390"
        ],
        "id": 2539909,
        "name:xx": "New York Mine"
      }
    }
  ]
}
