{
  "geometry": {
    "type": "Point",
    "coordinates": [
      -123.1833,
      45.85
    ]
  },
  "type": "Feature",
  "properties": {
    "hierarchy": [
      "tgn:2085700",
      "tgn:1000001",
      "tgn:1002293",
      "tgn:7012149",
      "tgn:7007708",
      "tgn:7029392"
    ],
    "placetype": [
      "aat:300008347"
    ],
    "id": 2085700,
    "name:xx": "Vernonia"
  }
}
