{
  "geometry": {
    "type": "Point",
    "coordinates": [
      -86.15,
      42.4833
    ]
  },
  "type": "Feature",
  "properties": {
    "hierarchy": [
      "tgn:2316020",
      "tgn:1002140",
      "tgn:1000001",
      "tgn:7012149",
      "tgn:7007520",
      "tgn:7029392"
    ],
    "placetype": [
      "aat:300008706"
    ],
    "id": 2316020,
    "name:xx": "Elm Creek Drain"
  }
}
