{
  "geometry": {
    "type": "Point",
    "coordinates": [
      -72.083333,
      -36.65
    ]
  },
  "type": "Feature",
  "properties": {
    "hierarchy": [
      "tgn:7321972",
      "tgn:1001637",
      "tgn:1000049",
      "tgn:1000002",
      "tgn:7029392"
    ],
    "placetype": [
      "aat:300008699"
    ],
    "id": 7321972,
    "name:xx": "Boyén, Estero"
  }
}
