{
  "geometry": {
    "type": "Point",
    "coordinates": [
      -111.8167,
      35.9333
    ]
  },
  "type": "Feature",
  "properties": {
    "hierarchy": [
      "tgn:2739358",
      "tgn:1000001",
      "tgn:7006451",
      "tgn:2000092",
      "tgn:7012149",
      "tgn:7029392"
    ],
    "placetype": [
      "aat:300386845"
    ],
    "id": 2739358,
    "name:xx": "Upper Basin"
  }
}
