{
  "geometry": {
    "type": "Point",
    "coordinates": [
      71.8333,
      36.4333
    ]
  },
  "type": "Feature",
  "properties": {
    "hierarchy": [
      "tgn:1105859",
      "tgn:1000004",
      "tgn:7029392"
    ],
    "placetype": [
      "aat:300008795"
    ],
    "id": 1105859,
    "name:xx": "Nowshāk"
  }
}
