{
  "geometry": {
    "type": "Point",
    "coordinates": [
      -116.1667,
      37.7833
    ]
  },
  "type": "Feature",
  "properties": {
    "hierarchy": [
      "tgn:2615579",
      "tgn:1000001",
      "tgn:2001418",
      "tgn:7012149",
      "tgn:7007526",
      "tgn:7029392"
    ],
    "placetype": [
      "aat:300008761"
    ],
    "id": 2615579,
    "name:xx": "Reveille Valley"
  }
}
