{
  "geometry": {
    "type": "Point",
    "coordinates": [
      -78.8833,
      41.2833
    ]
  },
  "type": "Feature",
  "properties": {
    "hierarchy": [
      "tgn:2707197",
      "tgn:1000001",
      "tgn:7012149",
      "tgn:1002520",
      "tgn:7007710",
      "tgn:7029392"
    ],
    "placetype": [
      "aat:300008699"
    ],
    "id": 2707197,
    "name:xx": "Swede Run"
  }
}
