{
  "geometry": {
    "type": "Point",
    "coordinates": [
      -114.7167,
      38.65
    ]
  },
  "type": "Feature",
  "properties": {
    "hierarchy": [
      "tgn:2750282",
      "tgn:1000001",
      "tgn:2001416",
      "tgn:7012149",
      "tgn:7007526",
      "tgn:7029392"
    ],
    "placetype": [
      "aat:300008706"
    ],
    "id": 2750282,
    "name:xx": "Wambolt Creek"
  }
}
