{
  "geometry": {
    "type": "Point",
    "coordinates": [
      -112.1833,
      32.5833
    ]
  },
  "type": "Feature",
  "properties": {
    "hierarchy": [
      "tgn:2441624",
      "tgn:1000001",
      "tgn:7006451",
      "tgn:7012149",
      "tgn:2000101",
      "tgn:7029392"
    ],
    "placetype": [
      "aat:300008761"
    ],
    "id": 2441624,
    "name:xx": "Kohatk Valley"
  }
}
