{
  "geometry": {
    "type": "Point",
    "coordinates": [
      136.9167,
      34.4167
    ]
  },
  "type": "Feature",
  "properties": {
    "hierarchy": [
      "tgn:1011388",
      "tgn:1000004",
      "tgn:1001007",
      "tgn:7000896",
      "tgn:1000120",
      "tgn:7029392"
    ],
    "placetype": [
      "aat:300008850"
    ],
    "id": 1011388,
    "name:xx": "Yoroi-zaki"
  }
}
