{
  "geometry": {
    "type": "Point",
    "coordinates": [
      27.8833,
      56.9167
    ]
  },
  "type": "Feature",
  "properties": {
    "hierarchy": [
      "tgn:1053965",
      "tgn:1000004",
      "tgn:7011590",
      "tgn:7018214",
      "tgn:7002435",
      "tgn:7029392"
    ],
    "placetype": [
      "aat:300008347"
    ],
    "id": 1053965,
    "name:xx": "Gavry"
  }
}
