{
  "geometry": {
    "type": "Point",
    "coordinates": [
      -75.3167,
      37.9667
    ]
  },
  "type": "Feature",
  "properties": {
    "hierarchy": [
      "tgn:2377177",
      "tgn:1002132",
      "tgn:1000001",
      "tgn:7012149",
      "tgn:7007919",
      "tgn:7029392"
    ],
    "placetype": [
      "aat:300132316"
    ],
    "id": 2377177,
    "name:xx": "Harmon Cove"
  }
}
