{
  "type": "FeatureCollection",
  "features": [
    {
      "geometry": {
        "type": "Point",
        "coordinates": [
          -117.5833,
          45.55
        ]
      },
      "type": "Feature",
      "properties": {
        "hierarchy": [
          "tgn:2657790",
          "tgn:1000001",
          "tgn:7012149",
          "tgn:2001722",
          "tgn:7007708",
          "tgn:7029392"
        ],
        "placetype": [
          "aat:300008706"
        ],
        "id": 2657790,
        "name:xx": "Shell Creek"
      }
    },
    {
      "geometry": {
        "type": "Point",
        "coordinates": [
          -81.8667,
          34.4667
        ]
      },
      "type": "Feature",
      "properties": {
        "hierarchy": [
          "tgn:2657791",
          "tgn:1000001",
          "tgn:7012149",
          "tgn:2001754",
          "tgn:7007712",
          "tgn:7029392"
        ],
        "placetype": [
          "aat:300008706"
        ],
        "id": 2657791,
        "name:xx": "Shell Creek"
      }
    },
    {
      "geometry": {
        "type": "Point",
        "coordinates": [
          -82.0167,
          36.1333
        ]
      },
      "type": "Feature",
      "properties": {
        "hierarchy": [
          "tgn:2657792",
          "tgn:1000001",
          "tgn:7012149",
          "tgn:2001846",
          "tgn:7007825",
          "tgn:7029392"
        ],
        "placetype": [
          "aat:300008706"
        ],
        "id": 2657792,
        "name:xx": "Shell Creek"
      }
    },
    {
      "geometry": {
        "type": "Point",
        "coordinates": [
          -84.8833,
          36.1667
        ]
      },
      "type": "Feature",
      "properties": {
        "hierarchy": [
          "tgn:2657793",
          "tgn:1000001",
          "tgn:7012149",
          "tgn:2001901",
          "tgn:7007825",
          "tgn:7029392"
        ],
        "placetype": [
          "aat:300008706"
        ],
        "id": 2657793,
        "name:xx": "Shell Creek"
      }
    },
    {
      "geometry": {
        "type": "Point",
        "coordinates": [
          -75.7833,
          37.2667
        ]
      },
      "type": "Feature",
      "properties": {
        "hierarchy": [
          "tgn:2657794",
          "tgn:1000001",
          "tgn:7012149",
          "tgn:1002730",
          "tgn:7007919",
          "tgn:7029392"
        ],
        "placetype": [
          "aat:300008706"
        ],
        "id": 2657794,
        "name:xx": "Shell Creek"
      }
    },
    {
      "geometry": {
        "type": "Point",
        "coordinates": [
          -76.3167,
          37.8167
        ]
      },
      "type": "Feature",
      "properties": {
        "hierarchy": [
          "tgn:2657795",
          "tgn:1000001",
          "tgn:7012149",
          "tgn:1002733",
          "tgn:7007919",
          "tgn:7029392"
        ],
        "placetype": [
          "aat:300008706"
        ],
        "id": 2657795,
        "name:xx": "Shell Creek"
      }
    },
    {
      "geometry": {
        "type": "Point",
        "coordinates": [
          -121.2167,
          46.7
        ]
      },
      "type": "Feature",
      "properties": {
        "hierarchy": [
          "tgn:2657796",
          "tgn:1000001",
          "tgn:7012149",
          "tgn:1003042",
          "tgn:7007920",
          "tgn:7029392"
        ],
        "placetype": [
          "aat:300008706"
        ],
        "id": 2657796,
        "name:xx": "Shell Creek"
      }
    },
    {
      "geometry": {
        "type": "Point",
        "coordinates": [
          -122.35,
          47.8
        ]
      },
      "type": "Feature",
      "properties": {
        "hierarchy": [
          "tgn:2657797",
          "tgn:1000001",
          "tgn:7012149",
          "tgn:1002899",
          "tgn:7007920",
          "tgn:7029392"
        ],
        "placetype": [
          "aat:300008706"
        ],
        "id": 2657797,
        "name:xx": "Shell Creek"
      }
    },
    {
      "geometry": {
        "type": "Point",
        "coordinates": [
          -91.8167,
          46.1
        ]
      },
      "type": "Feature",
      "properties": {
        "hierarchy": [
          "tgn:2657798",
          "tgn:1000001",
          "tgn:7012149",
          "tgn:2002360",
          "tgn:7007922",
          "tgn:7029392"
        ],
        "placetype": [
          "aat:300008706"
        ],
        "id": 2657798,
        "name:xx": "Shell Creek"
      }
    },
    {
      "geometry": {
        "type": "Point",
        "coordinates": [
          -106.8667,
          42.7
        ]
      },
      "type": "Feature",
      "properties": {
        "hierarchy": [
          "tgn:2657799",
          "tgn:1000001",
          "tgn:7012149",
          "tgn:2002377",
          "tgn:7007923",
          "tgn:7029392"
        ],
        "placetype": [
          "aat:300008706"
        ],
        "id": 2657799,
        "name:xx": "Shell Creek"
      }
    }
  ]
}
