{
  "geometry": {
    "type": "Point",
    "coordinates": [
      -86.6167,
      37.8667
    ]
  },
  "type": "Feature",
  "properties": {
    "hierarchy": [
      "tgn:2295429",
      "tgn:1000001",
      "tgn:7012149",
      "tgn:2000550",
      "tgn:7007252",
      "tgn:7029392"
    ],
    "placetype": [
      "aat:300008798"
    ],
    "id": 2295429,
    "name:xx": "Drinkwater Hill"
  }
}
