{
  "geometry": {
    "type": "Point",
    "coordinates": [
      -93.2333,
      36.8833
    ]
  },
  "type": "Feature",
  "properties": {
    "hierarchy": [
      "tgn:2363944",
      "tgn:1000001",
      "tgn:2001185",
      "tgn:7012149",
      "tgn:7007523",
      "tgn:7029392"
    ],
    "placetype": [
      "aat:300266640"
    ],
    "id": 2363944,
    "name:xx": "Green Mound Ridge"
  }
}
