{
  "geometry": {
    "type": "Point",
    "coordinates": [
      -93.3667,
      41.9333
    ]
  },
  "type": "Feature",
  "properties": {
    "hierarchy": [
      "tgn:2633592",
      "tgn:1000001",
      "tgn:7012149",
      "tgn:2000645",
      "tgn:7007253",
      "tgn:7029392"
    ],
    "placetype": [
      "aat:300008706"
    ],
    "id": 2633592,
    "name:xx": "Rupple Creek"
  }
}
