{
  "geometry": {
    "type": "Point",
    "coordinates": [
      -100.0625,
      26.5275
    ]
  },
  "type": "Feature",
  "properties": {
    "hierarchy": [
      "tgn:7419849",
      "tgn:1000001",
      "tgn:7005589",
      "tgn:7005560",
      "tgn:7029392"
    ],
    "placetype": [
      "aat:300008347"
    ],
    "id": 7419849,
    "name:es": "El Salitre"
  }
}
