{
  "type": "FeatureCollection",
  "features": [
    {
      "geometry": {
        "type": "Point",
        "coordinates": [
          -82.4667,
          31.2333
        ]
      },
      "type": "Feature",
      "properties": {
        "hierarchy": [
          "tgn:2024650",
          "tgn:1000001",
          "tgn:7012149",
          "tgn:2000439",
          "tgn:7007248",
          "tgn:7029392"
        ],
        "placetype": [
          "aat:300008347"
        ],
        "id": 2024650,
        "name:xx": "Waresboro"
      }
    },
    {
      "geometry": {
        "type": "Point",
        "coordinates": [
          -85.0667,
          33.1
        ]
      },
      "type": "Feature",
      "properties": {
        "hierarchy": [
          "tgn:2024651",
          "tgn:1000001",
          "tgn:7012149",
          "tgn:2000432",
          "tgn:7007248",
          "tgn:7029392"
        ],
        "placetype": [
          "aat:300008347"
        ],
        "id": 2024651,
        "name:xx": "Wares Crossroads"
      }
    },
    {
      "geometry": {
        "type": "Point",
        "coordinates": [
          -85.2333,
          33.2167
        ]
      },
      "type": "Feature",
      "properties": {
        "hierarchy": [
          "tgn:2024652",
          "tgn:1000001",
          "tgn:7012149",
          "tgn:2000365",
          "tgn:7007248",
          "tgn:7029392"
        ],
        "placetype": [
          "aat:300008347"
        ],
        "id": 2024652,
        "name:xx": "Waresville"
      }
    },
    {
      "geometry": {
        "type": "Point",
        "coordinates": [
          -84.9667,
          34.8333
        ]
      },
      "type": "Feature",
      "properties": {
        "hierarchy": [
          "tgn:2024653",
          "tgn:1000001",
          "tgn:7012149",
          "tgn:2000446",
          "tgn:7007248",
          "tgn:7029392"
        ],
        "placetype": [
          "aat:300008347"
        ],
        "id": 2024653,
        "name:xx": "Waring"
      }
    },
    {
      "geometry": {
        "type": "Point",
        "coordinates": [
          -84.6667,
          32.8833
        ]
      },
      "type": "Feature",
      "properties": {
        "hierarchy": [
          "tgn:2024654",
          "tgn:1000001",
          "tgn:7012149",
          "tgn:2000390",
          "tgn:7007248",
          "tgn:7029392"
        ],
        "placetype": [
          "aat:300008347"
        ],
        "id": 2024654,
        "name:xx": "Warm Springs"
      }
    },
    {
      "geometry": {
        "type": "Point",
        "coordinates": [
          -83.6,
          32.6167
        ]
      },
      "type": "Feature",
      "properties": {
        "hierarchy": [
          "tgn:2024655",
          "tgn:1000001",
          "tgn:7012149",
          "tgn:2000367",
          "tgn:7007248",
          "tgn:7029392"
        ],
        "placetype": [
          "aat:300008347"
        ],
        "id": 2024655,
        "name:xx": "Warner Robins"
      }
    }
  ]
}
