{
  "geometry": {
    "type": "Point",
    "coordinates": [
      -113.7667,
      48.6833
    ]
  },
  "type": "Feature",
  "properties": {
    "hierarchy": [
      "tgn:2219469",
      "tgn:1000001",
      "tgn:7012149",
      "tgn:2001274",
      "tgn:7007524",
      "tgn:7029392"
    ],
    "placetype": [
      "aat:300008798"
    ],
    "id": 2219469,
    "name:xx": "Cannon, Mount"
  }
}
