{
  "geometry": {
    "type": "Point",
    "coordinates": [
      -113.2833,
      36.6333
    ]
  },
  "type": "Feature",
  "properties": {
    "hierarchy": [
      "tgn:2291485",
      "tgn:1000001",
      "tgn:7006451",
      "tgn:7012149",
      "tgn:2000098",
      "tgn:7029392"
    ],
    "placetype": [
      "aat:300006191"
    ],
    "id": 2291485,
    "name:xx": "Dolittle Pond"
  }
}
