{
  "geometry": {
    "type": "Point",
    "coordinates": [
      -83.5167,
      43.2667
    ]
  },
  "type": "Feature",
  "properties": {
    "hierarchy": [
      "tgn:2052673",
      "tgn:1000001",
      "tgn:7012149",
      "tgn:2000997",
      "tgn:7007520",
      "tgn:7029392"
    ],
    "placetype": [
      "aat:300008347"
    ],
    "id": 2052673,
    "name:xx": "Millington"
  }
}
