{
  "type": "FeatureCollection",
  "features": [
    {
      "geometry": {
        "type": "Point",
        "coordinates": [
          -3.2167,
          56.3333
        ]
      },
      "type": "Feature",
      "properties": {
        "hierarchy": [
          "tgn:4000361",
          "tgn:7002445",
          "tgn:1000003",
          "tgn:7029505",
          "tgn:7008591",
          "tgn:7029392"
        ],
        "placetype": [
          "aat:300008347"
        ],
        "id": 4000361,
        "name:xx": "Abdie"
      }
    },
    {
      "geometry": {
        "type": "Point",
        "coordinates": [
          -1.333333,
          53.816667
        ]
      },
      "type": "Feature",
      "properties": {
        "hierarchy": [
          "tgn:4000364",
          "tgn:7019038",
          "tgn:7002445",
          "tgn:1000003",
          "tgn:7029507",
          "tgn:7008591",
          "tgn:7029392"
        ],
        "placetype": [
          "aat:300008347"
        ],
        "name:en": "Aberford",
        "id": 4000364
      }
    }
  ]
}
