{
  "geometry": {
    "type": "Point",
    "coordinates": [
      18.0333,
      -2.0333
    ]
  },
  "type": "Feature",
  "properties": {
    "hierarchy": [
      "tgn:1088620",
      "tgn:7001242",
      "tgn:1001001",
      "tgn:1000158",
      "tgn:7029392"
    ],
    "placetype": [
      "aat:300008347"
    ],
    "id": 1088620,
    "name:xx": "Dongou"
  }
}
