{
  "type": "FeatureCollection",
  "features": [
    {
      "geometry": {
        "type": "Point",
        "coordinates": [
          -155.9833,
          19.7167
        ]
      },
      "type": "Feature",
      "properties": {
        "hierarchy": [
          "tgn:2025000",
          "tgn:7023902",
          "tgn:1000001",
          "tgn:7012149",
          "tgn:7007249",
          "tgn:7029392"
        ],
        "placetype": [
          "aat:300008347",
          "aat:300008372"
        ],
        "id": 2025000,
        "name:xx": "Kailua-Kona"
      }
    },
    {
      "geometry": {
        "type": "Point",
        "coordinates": [
          -155.8667,
          19.4
        ]
      },
      "type": "Feature",
      "properties": {
        "hierarchy": [
          "tgn:2025001",
          "tgn:7023902",
          "tgn:1000001",
          "tgn:7012149",
          "tgn:7007249",
          "tgn:7029392"
        ],
        "placetype": [
          "aat:300008347"
        ],
        "id": 2025001,
        "name:xx": "Kealia"
      }
    },
    {
      "geometry": {
        "type": "Point",
        "coordinates": [
          -154.9667,
          19.4
        ]
      },
      "type": "Feature",
      "properties": {
        "hierarchy": [
          "tgn:2025002",
          "tgn:7023902",
          "tgn:1000001",
          "tgn:7012149",
          "tgn:7007249",
          "tgn:7029392"
        ],
        "placetype": [
          "aat:300008347"
        ],
        "id": 2025002,
        "name:xx": "Kaimu"
      }
    },
    {
      "geometry": {
        "type": "Point",
        "coordinates": [
          -155.9167,
          19.5333
        ]
      },
      "type": "Feature",
      "properties": {
        "hierarchy": [
          "tgn:2025003",
          "tgn:7023902",
          "tgn:1000001",
          "tgn:7012149",
          "tgn:7007249",
          "tgn:7029392"
        ],
        "placetype": [
          "aat:300008347"
        ],
        "id": 2025003,
        "name:xx": "Kainaliu"
      }
    },
    {
      "geometry": {
        "type": "Point",
        "coordinates": [
          -156.7833,
          21.1
        ]
      },
      "type": "Feature",
      "properties": {
        "hierarchy": [
          "tgn:2025004",
          "tgn:1002648",
          "tgn:1000001",
          "tgn:1008191",
          "tgn:7012149",
          "tgn:7007249",
          "tgn:7029392"
        ],
        "placetype": [
          "aat:300008347",
          "aat:300387210"
        ],
        "id": 2025004,
        "name:xx": "Kainalu"
      }
    },
    {
      "geometry": {
        "type": "Point",
        "coordinates": [
          -157,
          21.15
        ]
      },
      "type": "Feature",
      "properties": {
        "hierarchy": [
          "tgn:2025005",
          "tgn:1002648",
          "tgn:1000001",
          "tgn:1008191",
          "tgn:7012149",
          "tgn:7007249",
          "tgn:7029392"
        ],
        "placetype": [
          "aat:300008347",
          "aat:300387210"
        ],
        "id": 2025005,
        "name:xx": "Kalae"
      }
    },
    {
      "geometry": {
        "type": "Point",
        "coordinates": [
          -159.5,
          21.95
        ]
      },
      "type": "Feature",
      "properties": {
        "hierarchy": [
          "tgn:2025006",
          "tgn:1007657",
          "tgn:1002534",
          "tgn:1000001",
          "tgn:7012149",
          "tgn:7007249",
          "tgn:7029392"
        ],
        "placetype": [
          "aat:300008347"
        ],
        "id": 2025006,
        "name:xx": "Kalaheo"
      }
    }
  ]
}
