{
  "geometry": {
    "type": "Point",
    "coordinates": [
      -75.2833,
      39.9167
    ]
  },
  "type": "Feature",
  "properties": {
    "hierarchy": [
      "tgn:2085903",
      "tgn:1000001",
      "tgn:1002330",
      "tgn:7012149",
      "tgn:7007710",
      "tgn:7029392"
    ],
    "placetype": [
      "aat:300008347"
    ],
    "id": 2085903,
    "name:xx": "Aldan"
  }
}
