{
  "geometry": {
    "type": "Point",
    "coordinates": [
      -90.1833,
      30.4833
    ]
  },
  "type": "Feature",
  "properties": {
    "hierarchy": [
      "tgn:2354836",
      "tgn:1000001",
      "tgn:7012149",
      "tgn:2000905",
      "tgn:7007256",
      "tgn:7029392"
    ],
    "placetype": [
      "aat:300008347"
    ],
    "id": 2354836,
    "name:xx": "Goodbee"
  }
}
