{
  "geometry": {
    "type": "Point",
    "coordinates": [
      29.333333,
      30.866667
    ]
  },
  "type": "Feature",
  "properties": {
    "hierarchy": [
      "tgn:7522327",
      "tgn:7001242",
      "tgn:7016833",
      "tgn:1001418",
      "tgn:7029392"
    ],
    "placetype": [
      "aat:300008347"
    ],
    "name:en": "Dawwār Muşādif Yūnus",
    "id": 7522327
  }
}
