{
  "type": "FeatureCollection",
  "features": [
    {
      "geometry": {
        "type": "Point",
        "coordinates": [
          -100.066667,
          26.45
        ]
      },
      "type": "Feature",
      "properties": {
        "hierarchy": [
          "tgn:7355071",
          "tgn:1000001",
          "tgn:7005589",
          "tgn:7005560",
          "tgn:7029392"
        ],
        "placetype": [
          "aat:300008347"
        ],
        "id": 7355071,
        "name:xx": "Ciénega"
      }
    },
    {
      "geometry": {
        "type": "Point",
        "coordinates": [
          -105.283333,
          25.783333
        ]
      },
      "type": "Feature",
      "properties": {
        "hierarchy": [
          "tgn:7355072",
          "tgn:7005583",
          "tgn:1000001",
          "tgn:7005560",
          "tgn:7029392"
        ],
        "placetype": [
          "aat:300008347"
        ],
        "id": 7355072,
        "name:xx": "Ciénega"
      }
    },
    {
      "geometry": {
        "type": "Point",
        "coordinates": [
          -106.4,
          25.683333
        ]
      },
      "type": "Feature",
      "properties": {
        "hierarchy": [
          "tgn:7355073",
          "tgn:7005583",
          "tgn:1000001",
          "tgn:7005560",
          "tgn:7029392"
        ],
        "placetype": [
          "aat:300008347"
        ],
        "id": 7355073,
        "name:xx": "Ciénega"
      }
    },
    {
      "geometry": {
        "type": "Point",
        "coordinates": [
          -107.65,
          29.283333
        ]
      },
      "type": "Feature",
      "properties": {
        "hierarchy": [
          "tgn:7355075",
          "tgn:7005581",
          "tgn:1000001",
          "tgn:7005560",
          "tgn:7029392"
        ],
        "placetype": [
          "aat:300008795"
        ],
        "id": 7355075,
        "name:xx": "Chávez, Sierra de"
      }
    },
    {
      "geometry": {
        "type": "Point",
        "coordinates": [
          -106.483333,
          28.233333
        ]
      },
      "type": "Feature",
      "properties": {
        "hierarchy": [
          "tgn:7355076",
          "tgn:7005581",
          "tgn:1000001",
          "tgn:7005560",
          "tgn:7029392"
        ],
        "placetype": [
          "aat:300008347"
        ],
        "id": 7355076,
        "name:xx": "Chávez"
      }
    },
    {
      "geometry": {
        "type": "Point",
        "coordinates": [
          -107.566667,
          27
        ]
      },
      "type": "Feature",
      "properties": {
        "hierarchy": [
          "tgn:7355077",
          "tgn:7005581",
          "tgn:1000001",
          "tgn:7005560",
          "tgn:7029392"
        ],
        "placetype": [
          "aat:300008347"
        ],
        "id": 7355077,
        "name:xx": "Chávez"
      }
    },
    {
      "geometry": {
        "type": "Point",
        "coordinates": [
          -101.4,
          17.716667
        ]
      },
      "type": "Feature",
      "properties": {
        "hierarchy": [
          "tgn:7355078",
          "tgn:7005585",
          "tgn:1000001",
          "tgn:7005560",
          "tgn:7029392"
        ],
        "placetype": [
          "aat:300008347"
        ],
        "id": 7355078,
        "name:xx": "Chaveta"
      }
    },
    {
      "geometry": {
        "type": "Point",
        "coordinates": [
          -107.7,
          29.35
        ]
      },
      "type": "Feature",
      "properties": {
        "hierarchy": [
          "tgn:7355079",
          "tgn:7005581",
          "tgn:1000001",
          "tgn:7005560",
          "tgn:7029392"
        ],
        "placetype": [
          "aat:300008347"
        ],
        "id": 7355079,
        "name:xx": "Chaves"
      }
    }
  ]
}
