{
  "type": "FeatureCollection",
  "features": [
    {
      "geometry": {
        "type": "Point",
        "coordinates": [
          16.583333,
          38.966667
        ]
      },
      "type": "Feature",
      "properties": {
        "hierarchy": [
          "tgn:7040950",
          "tgn:1003447",
          "tgn:7007850",
          "tgn:1000003",
          "tgn:1000080",
          "tgn:7029392"
        ],
        "placetype": [
          "aat:300008347"
        ],
        "id": 7040950,
        "name:xx": "Sant'Elia"
      }
    },
    {
      "geometry": {
        "type": "Point",
        "coordinates": [
          15.683333,
          37.966667
        ]
      },
      "type": "Feature",
      "properties": {
        "hierarchy": [
          "tgn:7040951",
          "tgn:7007850",
          "tgn:1003491",
          "tgn:1000003",
          "tgn:1000080",
          "tgn:7029392"
        ],
        "placetype": [
          "aat:300008347"
        ],
        "id": 7040951,
        "name:xx": "Sant'Elia"
      }
    },
    {
      "geometry": {
        "type": "Point",
        "coordinates": [
          16.1,
          39.1
        ]
      },
      "type": "Feature",
      "properties": {
        "hierarchy": [
          "tgn:7040952",
          "tgn:1003450",
          "tgn:7007850",
          "tgn:1000003",
          "tgn:1000080",
          "tgn:7029392"
        ],
        "placetype": [
          "aat:300008486"
        ],
        "id": 7040952,
        "name:xx": "Sant'Elia"
      }
    },
    {
      "geometry": {
        "type": "Point",
        "coordinates": [
          14.466667,
          41.566667
        ]
      },
      "type": "Feature",
      "properties": {
        "hierarchy": [
          "tgn:7040953",
          "tgn:1003464",
          "tgn:1000003",
          "tgn:7003241",
          "tgn:1000080",
          "tgn:7029392"
        ],
        "placetype": [
          "aat:300008347"
        ],
        "id": 7040953,
        "name:xx": "Sant'Elena Sannita"
      }
    },
    {
      "geometry": {
        "type": "Point",
        "coordinates": [
          12.366667,
          45.433333
        ]
      },
      "type": "Feature",
      "properties": {
        "hierarchy": [
          "tgn:7040954",
          "tgn:7003006",
          "tgn:1000003",
          "tgn:7002997",
          "tgn:1000080",
          "tgn:7029392"
        ],
        "placetype": [
          "aat:300008791"
        ],
        "id": 7040954,
        "name:xx": "Sant'Elena, Isola"
      }
    },
    {
      "geometry": {
        "type": "Point",
        "coordinates": [
          12.315,
          45.620556
        ]
      },
      "type": "Feature",
      "properties": {
        "hierarchy": [
          "tgn:7040955",
          "tgn:7002996",
          "tgn:1000003",
          "tgn:7002997",
          "tgn:1000080",
          "tgn:7029392"
        ],
        "placetype": [
          "aat:300008347"
        ],
        "id": 7040955,
        "name:xx": "Sant'Elena"
      }
    },
    {
      "geometry": {
        "type": "Point",
        "coordinates": [
          14.2,
          41.866667
        ]
      },
      "type": "Feature",
      "properties": {
        "hierarchy": [
          "tgn:7040957",
          "tgn:1003464",
          "tgn:1000003",
          "tgn:7003241",
          "tgn:1000080",
          "tgn:7029392"
        ],
        "placetype": [
          "aat:300008347"
        ],
        "id": 7040957,
        "name:xx": "Sant'Elena"
      }
    },
    {
      "geometry": {
        "type": "Point",
        "coordinates": [
          13.85,
          43.016667
        ]
      },
      "type": "Feature",
      "properties": {
        "hierarchy": [
          "tgn:7040959",
          "tgn:1003432",
          "tgn:1000003",
          "tgn:7003240",
          "tgn:1000080",
          "tgn:7029392"
        ],
        "placetype": [
          "aat:300008699"
        ],
        "id": 7040959,
        "name:xx": "Sant'Egidio, Fosso"
      }
    }
  ]
}
