{
  "type": "FeatureCollection",
  "features": [
    {
      "geometry": {
        "type": "Point",
        "coordinates": [
          -112.0833,
          34.7833
        ]
      },
      "type": "Feature",
      "properties": {
        "hierarchy": [
          "tgn:2507371",
          "tgn:1000001",
          "tgn:7006451",
          "tgn:7012149",
          "tgn:2000103",
          "tgn:7029392"
        ],
        "placetype": [
          "aat:300008697"
        ],
        "id": 2507371,
        "name:xx": "Mexican Seep"
      }
    },
    {
      "geometry": {
        "type": "Point",
        "coordinates": [
          -110.7333,
          38.9833
        ]
      },
      "type": "Feature",
      "properties": {
        "hierarchy": [
          "tgn:2507372",
          "tgn:1000001",
          "tgn:2002108",
          "tgn:7012149",
          "tgn:7007827",
          "tgn:7029392"
        ],
        "placetype": [
          "aat:300008697"
        ],
        "id": 2507372,
        "name:xx": "Mexican Seep"
      }
    },
    {
      "geometry": {
        "type": "Point",
        "coordinates": [
          -109.5333,
          32.1833
        ]
      },
      "type": "Feature",
      "properties": {
        "hierarchy": [
          "tgn:2507373",
          "tgn:1000001",
          "tgn:7006451",
          "tgn:2000091",
          "tgn:7012149",
          "tgn:7029392"
        ],
        "placetype": [
          "aat:300008697"
        ],
        "id": 2507373,
        "name:xx": "Mexican Spring"
      }
    },
    {
      "geometry": {
        "type": "Point",
        "coordinates": [
          -109.3833,
          36.55
        ]
      },
      "type": "Feature",
      "properties": {
        "hierarchy": [
          "tgn:2507374",
          "tgn:2000090",
          "tgn:1000001",
          "tgn:7006451",
          "tgn:7012149",
          "tgn:7029392"
        ],
        "placetype": [
          "aat:300008697"
        ],
        "id": 2507374,
        "name:xx": "Mexican Spring"
      }
    },
    {
      "geometry": {
        "type": "Point",
        "coordinates": [
          -122.5167,
          40.6333
        ]
      },
      "type": "Feature",
      "properties": {
        "hierarchy": [
          "tgn:2507375",
          "tgn:1000001",
          "tgn:7012149",
          "tgn:7007157",
          "tgn:2000188",
          "tgn:7029392"
        ],
        "placetype": [
          "aat:300008697"
        ],
        "id": 2507375,
        "name:xx": "Mexican Spring"
      }
    },
    {
      "geometry": {
        "type": "Point",
        "coordinates": [
          -117.8167,
          36.5833
        ]
      },
      "type": "Feature",
      "properties": {
        "hierarchy": [
          "tgn:2507376",
          "tgn:1000001",
          "tgn:7012149",
          "tgn:2000183",
          "tgn:7007157",
          "tgn:7029392"
        ],
        "placetype": [
          "aat:300008697"
        ],
        "id": 2507376,
        "name:xx": "Mexican Spring"
      }
    },
    {
      "geometry": {
        "type": "Point",
        "coordinates": [
          -107.4,
          37.3167
        ]
      },
      "type": "Feature",
      "properties": {
        "hierarchy": [
          "tgn:2507377",
          "tgn:2000195",
          "tgn:1000001",
          "tgn:7012149",
          "tgn:7007158",
          "tgn:7029392"
        ],
        "placetype": [
          "aat:300008697"
        ],
        "id": 2507377,
        "name:xx": "Mexican Spring"
      }
    },
    {
      "geometry": {
        "type": "Point",
        "coordinates": [
          -108.3,
          38.0667
        ]
      },
      "type": "Feature",
      "properties": {
        "hierarchy": [
          "tgn:2507378",
          "tgn:1000001",
          "tgn:7012149",
          "tgn:7007158",
          "tgn:2000248",
          "tgn:7029392"
        ],
        "placetype": [
          "aat:300008697"
        ],
        "id": 2507378,
        "name:xx": "Mexican Spring"
      }
    },
    {
      "geometry": {
        "type": "Point",
        "coordinates": [
          -115.5167,
          35.9167
        ]
      },
      "type": "Feature",
      "properties": {
        "hierarchy": [
          "tgn:2507379",
          "tgn:1000001",
          "tgn:2001410",
          "tgn:7012149",
          "tgn:7007526",
          "tgn:7029392"
        ],
        "placetype": [
          "aat:300008697"
        ],
        "id": 2507379,
        "name:xx": "Mexican Spring"
      }
    }
  ]
}
