{
  "geometry": {
    "type": "Point",
    "coordinates": [
      -72.15,
      42.5167
    ]
  },
  "type": "Feature",
  "properties": {
    "hierarchy": [
      "tgn:2305307",
      "tgn:1000001",
      "tgn:7012149",
      "tgn:7007517",
      "tgn:7029392"
    ],
    "placetype": [
      "aat:300008707"
    ],
    "id": 2305307,
    "name:xx": "East Branch Swift River"
  }
}
