{
  "geometry": {
    "type": "Point",
    "coordinates": [
      -108.95,
      42.7833
    ]
  },
  "type": "Feature",
  "properties": {
    "hierarchy": [
      "tgn:2145539",
      "tgn:1000001",
      "tgn:7012149",
      "tgn:2002371",
      "tgn:7007923",
      "tgn:7029392"
    ],
    "placetype": [
      "aat:300008706"
    ],
    "id": 2145539,
    "name:xx": "Baldwin Creek"
  }
}
