{
  "geometry": {
    "type": "Point",
    "coordinates": [
      -78.75,
      40.2167
    ]
  },
  "type": "Feature",
  "properties": {
    "hierarchy": [
      "tgn:2621464",
      "tgn:1000001",
      "tgn:7012149",
      "tgn:1002904",
      "tgn:7007710",
      "tgn:7029392"
    ],
    "placetype": [
      "aat:300008699"
    ],
    "id": 2621464,
    "name:xx": "Roaring Fork"
  }
}
