{
  "geometry": {
    "type": "Point",
    "coordinates": [
      -101.15,
      32.0167
    ]
  },
  "type": "Feature",
  "properties": {
    "hierarchy": [
      "tgn:2625574",
      "tgn:1000001",
      "tgn:7012149",
      "tgn:2002077",
      "tgn:7007826",
      "tgn:7029392"
    ],
    "placetype": [
      "aat:300008680"
    ],
    "id": 2625574,
    "name:xx": "Rockwater Hole"
  }
}
