{
  "geometry": {
    "type": "Point",
    "coordinates": [
      -2.95,
      35.4333
    ]
  },
  "type": "Feature",
  "properties": {
    "hierarchy": [
      "tgn:1011335",
      "tgn:7001242",
      "tgn:1000179",
      "tgn:7593681",
      "tgn:7029392"
    ],
    "placetype": [
      "aat:300008850"
    ],
    "id": 1011335,
    "name:xx": "Trois Fourches, Cap des"
  }
}
