{
  "geometry": {
    "type": "Point",
    "coordinates": [
      -76.0833,
      38.6667
    ]
  },
  "type": "Feature",
  "properties": {
    "hierarchy": [
      "tgn:2464098",
      "tgn:1000001",
      "tgn:2000939",
      "tgn:7012149",
      "tgn:7007516",
      "tgn:7029392"
    ],
    "placetype": [
      "aat:300008347"
    ],
    "id": 2464098,
    "name:xx": "Locust Grove"
  }
}
