{
  "geometry": {
    "type": "Point",
    "coordinates": [
      26.214237,
      29.158677
    ]
  },
  "type": "Feature",
  "properties": {
    "hierarchy": [
      "tgn:7536877",
      "tgn:7001242",
      "tgn:7016833",
      "tgn:1001418",
      "tgn:7029392"
    ],
    "placetype": [
      "aat:300379998"
    ],
    "name:en": "Ḩaddūnah, Wādī",
    "id": 7536877
  }
}
