{
  "type": "FeatureCollection",
  "features": [
    {
      "geometry": {
        "type": "Point",
        "coordinates": [
          -6.233333,
          40.35
        ]
      },
      "type": "Feature",
      "properties": {
        "hierarchy": [
          "tgn:7340650",
          "tgn:7002811",
          "tgn:1000003",
          "tgn:7003837",
          "tgn:1000095",
          "tgn:7029392"
        ],
        "placetype": [
          "aat:300008347"
        ],
        "id": 7340650,
        "name:xx": "Cambroncino"
      }
    },
    {
      "geometry": {
        "type": "Point",
        "coordinates": [
          -3.333333,
          38.483333
        ]
      },
      "type": "Feature",
      "properties": {
        "hierarchy": [
          "tgn:7340651",
          "tgn:7002816",
          "tgn:1001647",
          "tgn:1000003",
          "tgn:1000095",
          "tgn:7029392"
        ],
        "placetype": [
          "aat:300266640"
        ],
        "id": 7340651,
        "name:xx": "Cambrón, Sierra del"
      }
    },
    {
      "geometry": {
        "type": "Point",
        "coordinates": [
          -3.116667,
          37.7
        ]
      },
      "type": "Feature",
      "properties": {
        "hierarchy": [
          "tgn:7340652",
          "tgn:7002758",
          "tgn:1001316",
          "tgn:1000003",
          "tgn:1000095",
          "tgn:7029392"
        ],
        "placetype": [
          "aat:300008795"
        ],
        "id": 7340652,
        "name:xx": "Cambrón, Peña"
      }
    },
    {
      "geometry": {
        "type": "Point",
        "coordinates": [
          -2.066667,
          40.216667
        ]
      },
      "type": "Feature",
      "properties": {
        "hierarchy": [
          "tgn:7340653",
          "tgn:7002818",
          "tgn:1001647",
          "tgn:1000003",
          "tgn:1000095",
          "tgn:7029392"
        ],
        "placetype": [
          "aat:300266554",
          "aat:300008699"
        ],
        "id": 7340653,
        "name:xx": "Cambrón, Arroyo del"
      }
    },
    {
      "geometry": {
        "type": "Point",
        "coordinates": [
          -3.8,
          39.15
        ]
      },
      "type": "Feature",
      "properties": {
        "hierarchy": [
          "tgn:7340654",
          "tgn:7002816",
          "tgn:1001647",
          "tgn:1000003",
          "tgn:1000095",
          "tgn:7029392"
        ],
        "placetype": [
          "aat:300266554",
          "aat:300008699"
        ],
        "id": 7340654,
        "name:xx": "Cambrón, Arroyo del"
      }
    },
    {
      "geometry": {
        "type": "Point",
        "coordinates": [
          -6.25,
          40.35
        ]
      },
      "type": "Feature",
      "properties": {
        "hierarchy": [
          "tgn:7340655",
          "tgn:7002811",
          "tgn:1000003",
          "tgn:7003837",
          "tgn:1000095",
          "tgn:7029392"
        ],
        "placetype": [
          "aat:300008347"
        ],
        "id": 7340655,
        "name:xx": "Cambrón"
      }
    },
    {
      "geometry": {
        "type": "Point",
        "coordinates": [
          -8.766667,
          43.283333
        ]
      },
      "type": "Feature",
      "properties": {
        "hierarchy": [
          "tgn:7340657",
          "tgn:7002824",
          "tgn:1000003",
          "tgn:7002786",
          "tgn:1000095",
          "tgn:7029392"
        ],
        "placetype": [
          "aat:300008347"
        ],
        "id": 7340657,
        "name:xx": "Cambre"
      }
    },
    {
      "geometry": {
        "type": "Point",
        "coordinates": [
          -8.333333,
          43.283333
        ]
      },
      "type": "Feature",
      "properties": {
        "hierarchy": [
          "tgn:7340658",
          "tgn:7002824",
          "tgn:1000003",
          "tgn:7002786",
          "tgn:1000095",
          "tgn:7029392"
        ],
        "placetype": [
          "aat:300008347"
        ],
        "id": 7340658,
        "name:xx": "Cambre"
      }
    }
  ]
}
