{
  "geometry": {
    "type": "Point",
    "coordinates": [
      -94.7833,
      40.4167
    ]
  },
  "type": "Feature",
  "properties": {
    "hierarchy": [
      "tgn:2584761",
      "tgn:1000001",
      "tgn:7012149",
      "tgn:2001224",
      "tgn:7007523",
      "tgn:7029392"
    ],
    "placetype": [
      "aat:300008706"
    ],
    "id": 2584761,
    "name:xx": "Pinhook Creek"
  }
}
