{
  "type": "FeatureCollection",
  "features": [
    {
      "geometry": {
        "type": "Point",
        "coordinates": [
          -71.2167,
          42.2667
        ]
      },
      "type": "Feature",
      "properties": {
        "hierarchy": [
          "tgn:2128350",
          "tgn:1000001",
          "tgn:1002724",
          "tgn:7012149",
          "tgn:7007517",
          "tgn:7029392"
        ],
        "placetype": [
          "aat:300008699"
        ],
        "id": 2128350,
        "name:xx": "Alder Brook"
      }
    },
    {
      "geometry": {
        "type": "Point",
        "coordinates": [
          -87.5333,
          45.6667
        ]
      },
      "type": "Feature",
      "properties": {
        "hierarchy": [
          "tgn:2128351",
          "tgn:1000001",
          "tgn:7012149",
          "tgn:2000978",
          "tgn:7007520",
          "tgn:7029392"
        ],
        "placetype": [
          "aat:300008699"
        ],
        "id": 2128351,
        "name:xx": "Alder Brook"
      }
    },
    {
      "geometry": {
        "type": "Point",
        "coordinates": [
          -71.5333,
          44.2833
        ]
      },
      "type": "Feature",
      "properties": {
        "hierarchy": [
          "tgn:2128352",
          "tgn:1002300",
          "tgn:1000001",
          "tgn:7012149",
          "tgn:7007564",
          "tgn:7029392"
        ],
        "placetype": [
          "aat:300008699"
        ],
        "id": 2128352,
        "name:xx": "Alder Brook"
      }
    },
    {
      "geometry": {
        "type": "Point",
        "coordinates": [
          -73.5,
          42.5667
        ]
      },
      "type": "Feature",
      "properties": {
        "hierarchy": [
          "tgn:2128353",
          "tgn:1000001",
          "tgn:7012149",
          "tgn:1002821",
          "tgn:7007568",
          "tgn:7029392"
        ],
        "placetype": [
          "aat:300008699"
        ],
        "id": 2128353,
        "name:xx": "Alder Brook"
      }
    },
    {
      "geometry": {
        "type": "Point",
        "coordinates": [
          -74.4,
          44.6167
        ]
      },
      "type": "Feature",
      "properties": {
        "hierarchy": [
          "tgn:2128354",
          "tgn:1000001",
          "tgn:7012149",
          "tgn:7013941",
          "tgn:7007568",
          "tgn:7029392"
        ],
        "placetype": [
          "aat:300008699"
        ],
        "id": 2128354,
        "name:xx": "Alder Brook"
      }
    },
    {
      "geometry": {
        "type": "Point",
        "coordinates": [
          -74.65,
          43.35
        ]
      },
      "type": "Feature",
      "properties": {
        "hierarchy": [
          "tgn:2128355",
          "tgn:1000001",
          "tgn:7012149",
          "tgn:1002440",
          "tgn:7007568",
          "tgn:7029392"
        ],
        "placetype": [
          "aat:300008699"
        ],
        "id": 2128355,
        "name:xx": "Alder Brook"
      }
    },
    {
      "geometry": {
        "type": "Point",
        "coordinates": [
          -73.6667,
          43.6667
        ]
      },
      "type": "Feature",
      "properties": {
        "hierarchy": [
          "tgn:2128356",
          "tgn:1000001",
          "tgn:7012149",
          "tgn:1002986",
          "tgn:7007568",
          "tgn:7029392"
        ],
        "placetype": [
          "aat:300008699"
        ],
        "id": 2128356,
        "name:xx": "Alder Brook"
      }
    },
    {
      "geometry": {
        "type": "Point",
        "coordinates": [
          -73.8,
          43.8
        ]
      },
      "type": "Feature",
      "properties": {
        "hierarchy": [
          "tgn:2128357",
          "tgn:1000001",
          "tgn:7012149",
          "tgn:7007568",
          "tgn:7029392"
        ],
        "placetype": [
          "aat:300008699"
        ],
        "id": 2128357,
        "name:xx": "Alder Brook"
      }
    },
    {
      "geometry": {
        "type": "Point",
        "coordinates": [
          -74,
          44.2333
        ]
      },
      "type": "Feature",
      "properties": {
        "hierarchy": [
          "tgn:2128358",
          "tgn:1000001",
          "tgn:7012149",
          "tgn:2001461",
          "tgn:7007568",
          "tgn:7029392"
        ],
        "placetype": [
          "aat:300008699"
        ],
        "id": 2128358,
        "name:xx": "Alder Brook"
      }
    },
    {
      "geometry": {
        "type": "Point",
        "coordinates": [
          -74.9667,
          44.4
        ]
      },
      "type": "Feature",
      "properties": {
        "hierarchy": [
          "tgn:2128359",
          "tgn:1000001",
          "tgn:7012149",
          "tgn:7016021",
          "tgn:7007568",
          "tgn:7029392"
        ],
        "placetype": [
          "aat:300008699"
        ],
        "id": 2128359,
        "name:xx": "Alder Brook"
      }
    }
  ]
}
