{
  "geometry": {
    "type": "Point",
    "coordinates": [
      -121.0667,
      47.3333
    ]
  },
  "type": "Feature",
  "properties": {
    "hierarchy": [
      "tgn:2387513",
      "tgn:1000001",
      "tgn:7012149",
      "tgn:1002553",
      "tgn:7007920",
      "tgn:7029392"
    ],
    "placetype": [
      "aat:300008706"
    ],
    "id": 2387513,
    "name:xx": "Hex Creek"
  }
}
