{
  "geometry": {
    "type": "Point",
    "coordinates": [
      -4.325,
      35.152
    ]
  },
  "type": "Feature",
  "properties": {
    "hierarchy": [
      "tgn:1091465",
      "tgn:7001242",
      "tgn:1000179",
      "tgn:7593698",
      "tgn:7029392"
    ],
    "placetype": [
      "aat:300008347"
    ],
    "id": 1091465,
    "name:xx": "Torres de Alcala"
  }
}
