{
  "type": "FeatureCollection",
  "features": [
    {
      "geometry": {
        "type": "Point",
        "coordinates": [
          -106.994722,
          24.665833
        ]
      },
      "type": "Feature",
      "properties": {
        "hierarchy": [
          "tgn:7439110",
          "tgn:1000001",
          "tgn:7005595",
          "tgn:7005560",
          "tgn:7029392"
        ],
        "placetype": [
          "aat:300008347"
        ],
        "id": 7439110,
        "name:xx": "Tecomate"
      }
    },
    {
      "geometry": {
        "type": "Point",
        "coordinates": [
          -107.182222,
          24.608056
        ]
      },
      "type": "Feature",
      "properties": {
        "hierarchy": [
          "tgn:7439111",
          "tgn:1000001",
          "tgn:7005595",
          "tgn:7005560",
          "tgn:7029392"
        ],
        "placetype": [
          "aat:300008347"
        ],
        "id": 7439111,
        "name:xx": "Tecomate"
      }
    },
    {
      "geometry": {
        "type": "Point",
        "coordinates": [
          -106.216667,
          24.166667
        ]
      },
      "type": "Feature",
      "properties": {
        "hierarchy": [
          "tgn:7439112",
          "tgn:1000001",
          "tgn:7005595",
          "tgn:7005560",
          "tgn:7029392"
        ],
        "placetype": [
          "aat:300008347"
        ],
        "id": 7439112,
        "name:xx": "Tecomate"
      }
    },
    {
      "geometry": {
        "type": "Point",
        "coordinates": [
          -106.25,
          23.283333
        ]
      },
      "type": "Feature",
      "properties": {
        "hierarchy": [
          "tgn:7439113",
          "tgn:1000001",
          "tgn:7005595",
          "tgn:7005560",
          "tgn:7029392"
        ],
        "placetype": [
          "aat:300008347"
        ],
        "id": 7439113,
        "name:xx": "Tecomate"
      }
    },
    {
      "geometry": {
        "type": "Point",
        "coordinates": [
          -101.616667,
          22.55
        ]
      },
      "type": "Feature",
      "properties": {
        "hierarchy": [
          "tgn:7439114",
          "tgn:1000001",
          "tgn:7005594",
          "tgn:7005560",
          "tgn:7029392"
        ],
        "placetype": [
          "aat:300008347"
        ],
        "id": 7439114,
        "name:xx": "Tecomate"
      }
    },
    {
      "geometry": {
        "type": "Point",
        "coordinates": [
          -105.4,
          21.983333
        ]
      },
      "type": "Feature",
      "properties": {
        "hierarchy": [
          "tgn:7439115",
          "tgn:1000001",
          "tgn:1001906",
          "tgn:7005560",
          "tgn:7029392"
        ],
        "placetype": [
          "aat:300008347"
        ],
        "id": 7439115,
        "name:xx": "Tecomate"
      }
    },
    {
      "geometry": {
        "type": "Point",
        "coordinates": [
          -97.55,
          20.783333
        ]
      },
      "type": "Feature",
      "properties": {
        "hierarchy": [
          "tgn:7439116",
          "tgn:1000001",
          "tgn:7005599",
          "tgn:7005560",
          "tgn:7029392"
        ],
        "placetype": [
          "aat:300008347"
        ],
        "id": 7439116,
        "name:xx": "Tecomate"
      }
    },
    {
      "geometry": {
        "type": "Point",
        "coordinates": [
          -104.466667,
          19.55
        ]
      },
      "type": "Feature",
      "properties": {
        "hierarchy": [
          "tgn:7439117",
          "tgn:7005586",
          "tgn:1000001",
          "tgn:7005560",
          "tgn:7029392"
        ],
        "placetype": [
          "aat:300008347"
        ],
        "id": 7439117,
        "name:xx": "Tecomate"
      }
    },
    {
      "geometry": {
        "type": "Point",
        "coordinates": [
          -95.516667,
          18.466667
        ]
      },
      "type": "Feature",
      "properties": {
        "hierarchy": [
          "tgn:7439118",
          "tgn:1000001",
          "tgn:7005599",
          "tgn:7005560",
          "tgn:7029392"
        ],
        "placetype": [
          "aat:300008347"
        ],
        "id": 7439118,
        "name:xx": "Tecomate"
      }
    },
    {
      "geometry": {
        "type": "Point",
        "coordinates": [
          -102.483333,
          20.1
        ]
      },
      "type": "Feature",
      "properties": {
        "hierarchy": [
          "tgn:7439119",
          "tgn:1000001",
          "tgn:7005590",
          "tgn:7005560",
          "tgn:7029392"
        ],
        "placetype": [
          "aat:300008347"
        ],
        "id": 7439119,
        "name:xx": "Tecomatán"
      }
    }
  ]
}
