{
  "geometry": {
    "type": "Point",
    "coordinates": [
      -108.0833,
      37.8833
    ]
  },
  "type": "Feature",
  "properties": {
    "hierarchy": [
      "tgn:2639393",
      "tgn:1000001",
      "tgn:7012149",
      "tgn:7007158",
      "tgn:2000248",
      "tgn:7029392"
    ],
    "placetype": [
      "aat:300008706"
    ],
    "id": 2639393,
    "name:xx": "Saltado Creek"
  }
}
