{
  "type": "FeatureCollection",
  "features": [
    {
      "geometry": {
        "type": "Point",
        "coordinates": [
          -92.3667,
          47.8833
        ]
      },
      "type": "Feature",
      "properties": {
        "hierarchy": [
          "tgn:1118570",
          "tgn:1000001",
          "tgn:7012149",
          "tgn:2001067",
          "tgn:7007521",
          "tgn:7029392"
        ],
        "placetype": [
          "aat:300008680"
        ],
        "id": 1118570,
        "name:xx": "Vermilion Lake"
      }
    },
    {
      "geometry": {
        "type": "Point",
        "coordinates": [
          -92.1667,
          50.0333
        ]
      },
      "type": "Feature",
      "properties": {
        "hierarchy": [
          "tgn:1118571",
          "tgn:7005685",
          "tgn:1000001",
          "tgn:7013154",
          "tgn:7029392"
        ],
        "placetype": [
          "aat:300008680"
        ],
        "id": 1118571,
        "name:xx": "Vermilion Lake"
      }
    },
    {
      "geometry": {
        "type": "Point",
        "coordinates": [
          -79.2833,
          45.3333
        ]
      },
      "type": "Feature",
      "properties": {
        "hierarchy": [
          "tgn:1118572",
          "tgn:7005685",
          "tgn:1000001",
          "tgn:7013154",
          "tgn:7029392"
        ],
        "placetype": [
          "aat:300008680"
        ],
        "id": 1118572,
        "name:xx": "Vernon, Lake"
      }
    },
    {
      "geometry": {
        "type": "Point",
        "coordinates": [
          12.166667,
          42.316667
        ]
      },
      "type": "Feature",
      "properties": {
        "hierarchy": [
          "tgn:1118574",
          "tgn:7003139",
          "tgn:1000003",
          "tgn:7003080",
          "tgn:1000080",
          "tgn:7029392"
        ],
        "placetype": [
          "aat:300008680"
        ],
        "id": 1118574,
        "name:xx": "Vico, Lago di"
      }
    },
    {
      "geometry": {
        "type": "Point",
        "coordinates": [
          33,
          -1
        ]
      },
      "type": "Feature",
      "properties": {
        "hierarchy": [
          "tgn:1118577",
          "tgn:7001242",
          "tgn:7029392"
        ],
        "placetype": [
          "aat:300008680"
        ],
        "id": 1118577,
        "name:xx": "Victoria, Lake"
      }
    }
  ]
}
