{
  "geometry": {
    "type": "Point",
    "coordinates": [
      -83.2667,
      36.1833
    ]
  },
  "type": "Feature",
  "properties": {
    "hierarchy": [
      "tgn:2341933",
      "tgn:1000001",
      "tgn:7012149",
      "tgn:2001868",
      "tgn:7007825",
      "tgn:7029392"
    ],
    "placetype": [
      "aat:300008746"
    ],
    "id": 2341933,
    "name:xx": "Fry Cave"
  }
}
