{
  "geometry": {
    "type": "Point",
    "coordinates": [
      -80.3833,
      39.4833
    ]
  },
  "type": "Feature",
  "properties": {
    "hierarchy": [
      "tgn:2245940",
      "tgn:1000001",
      "tgn:7012149",
      "tgn:2002275",
      "tgn:7013961",
      "tgn:7029392"
    ],
    "placetype": [
      "aat:300008699"
    ],
    "id": 2245940,
    "name:xx": "Coal Lick Run"
  }
}
