{
  "geometry": {
    "type": "Point",
    "coordinates": [
      -85.7333,
      40.1833
    ]
  },
  "type": "Feature",
  "properties": {
    "hierarchy": [
      "tgn:2410727",
      "tgn:1000001",
      "tgn:7012149",
      "tgn:1002623",
      "tgn:7007252",
      "tgn:7029392"
    ],
    "placetype": [
      "aat:300008706"
    ],
    "id": 2410727,
    "name:xx": "Indian Creek"
  }
}
