{
  "geometry": {
    "type": "Point",
    "coordinates": [
      -86.3333,
      30.55
    ]
  },
  "type": "Feature",
  "properties": {
    "hierarchy": [
      "tgn:2150372",
      "tgn:1000001",
      "tgn:7012149",
      "tgn:2000290",
      "tgn:7007240",
      "tgn:7029392"
    ],
    "placetype": [
      "aat:300008706"
    ],
    "id": 2150372,
    "name:xx": "Basin Creek"
  }
}
