{
  "geometry": {
    "type": "Point",
    "coordinates": [
      120.3739,
      22.6834
    ]
  },
  "type": "Feature",
  "properties": {
    "hierarchy": [
      "tgn:7489987",
      "tgn:7001004",
      "tgn:1000004",
      "tgn:1000141",
      "tgn:7029392"
    ],
    "placetype": [
      "aat:300008347"
    ],
    "id": 7489987,
    "name:xx": "Dajiuwan"
  }
}
