{
  "geometry": {
    "type": "Point",
    "coordinates": [
      -107.1333,
      32.4833
    ]
  },
  "type": "Feature",
  "properties": {
    "hierarchy": [
      "tgn:2742308",
      "tgn:1000001",
      "tgn:2001435",
      "tgn:7012149",
      "tgn:7007566",
      "tgn:7029392"
    ],
    "placetype": [
      "aat:300008761"
    ],
    "id": 2742308,
    "name:xx": "Valles Canyon"
  }
}
