{
  "type": "FeatureCollection",
  "features": [
    {
      "geometry": {
        "type": "Point",
        "coordinates": [
          -104.9167,
          34.6
        ]
      },
      "type": "Feature",
      "properties": {
        "hierarchy": [
          "tgn:2637890",
          "tgn:1000001",
          "tgn:7012149",
          "tgn:7007566",
          "tgn:7029392"
        ],
        "placetype": [
          "aat:300008706"
        ],
        "id": 2637890,
        "name:xx": "Salado Creek"
      }
    },
    {
      "geometry": {
        "type": "Point",
        "coordinates": [
          -107.25,
          35.3167
        ]
      },
      "type": "Feature",
      "properties": {
        "hierarchy": [
          "tgn:2637891",
          "tgn:1000001",
          "tgn:7012149",
          "tgn:2001451",
          "tgn:7007566",
          "tgn:7029392"
        ],
        "placetype": [
          "aat:300008706"
        ],
        "id": 2637891,
        "name:xx": "Salado Creek"
      }
    },
    {
      "geometry": {
        "type": "Point",
        "coordinates": [
          -103.5667,
          36.0667
        ]
      },
      "type": "Feature",
      "properties": {
        "hierarchy": [
          "tgn:2637892",
          "tgn:1000001",
          "tgn:7012149",
          "tgn:2001439",
          "tgn:7007566",
          "tgn:7029392"
        ],
        "placetype": [
          "aat:300008706"
        ],
        "id": 2637892,
        "name:xx": "Salado Creek"
      }
    },
    {
      "geometry": {
        "type": "Point",
        "coordinates": [
          -104.85,
          36.3167
        ]
      },
      "type": "Feature",
      "properties": {
        "hierarchy": [
          "tgn:2637893",
          "tgn:1000001",
          "tgn:2001432",
          "tgn:7012149",
          "tgn:7007566",
          "tgn:7029392"
        ],
        "placetype": [
          "aat:300008706"
        ],
        "id": 2637893,
        "name:xx": "Salado Creek"
      }
    },
    {
      "geometry": {
        "type": "Point",
        "coordinates": [
          -98.6,
          26.3167
        ]
      },
      "type": "Feature",
      "properties": {
        "hierarchy": [
          "tgn:2637894",
          "tgn:1000001",
          "tgn:7012149",
          "tgn:2002075",
          "tgn:7007826",
          "tgn:7029392"
        ],
        "placetype": [
          "aat:300008706"
        ],
        "id": 2637894,
        "name:xx": "Salado Creek"
      }
    },
    {
      "geometry": {
        "type": "Point",
        "coordinates": [
          -97.9667,
          27.3
        ]
      },
      "type": "Feature",
      "properties": {
        "hierarchy": [
          "tgn:2637895",
          "tgn:1000001",
          "tgn:7012149",
          "tgn:2002022",
          "tgn:7007826",
          "tgn:7029392"
        ],
        "placetype": [
          "aat:300008706"
        ],
        "id": 2637895,
        "name:xx": "Salado Creek"
      }
    },
    {
      "geometry": {
        "type": "Point",
        "coordinates": [
          -100.35,
          28.95
        ]
      },
      "type": "Feature",
      "properties": {
        "hierarchy": [
          "tgn:2637896",
          "tgn:1000001",
          "tgn:7012149",
          "tgn:2002038",
          "tgn:7007826",
          "tgn:7029392"
        ],
        "placetype": [
          "aat:300008706"
        ],
        "id": 2637896,
        "name:xx": "Salado Creek"
      }
    },
    {
      "geometry": {
        "type": "Point",
        "coordinates": [
          -100.4667,
          29.2333
        ]
      },
      "type": "Feature",
      "properties": {
        "hierarchy": [
          "tgn:2637897",
          "tgn:1000001",
          "tgn:7012149",
          "tgn:2002021",
          "tgn:7007826",
          "tgn:7029392"
        ],
        "placetype": [
          "aat:300008706"
        ],
        "id": 2637897,
        "name:xx": "Salado Creek"
      }
    },
    {
      "geometry": {
        "type": "Point",
        "coordinates": [
          -98.2167,
          27.5
        ]
      },
      "type": "Feature",
      "properties": {
        "hierarchy": [
          "tgn:2637898",
          "tgn:1000001",
          "tgn:7012149",
          "tgn:2002013",
          "tgn:7007826",
          "tgn:7029392"
        ],
        "placetype": [
          "aat:300008706"
        ],
        "id": 2637898,
        "name:xx": "Salado Creek"
      }
    },
    {
      "geometry": {
        "type": "Point",
        "coordinates": [
          -98.6333,
          29.7167
        ]
      },
      "type": "Feature",
      "properties": {
        "hierarchy": [
          "tgn:2637899",
          "tgn:1000001",
          "tgn:2001941",
          "tgn:7012149",
          "tgn:7007826",
          "tgn:7029392"
        ],
        "placetype": [
          "aat:300008706"
        ],
        "id": 2637899,
        "name:xx": "Salado Creek"
      }
    }
  ]
}
