{
  "geometry": {
    "type": "Point",
    "coordinates": [
      -117.3167,
      44.2167
    ]
  },
  "type": "Feature",
  "properties": {
    "hierarchy": [
      "tgn:2500733",
      "tgn:1000001",
      "tgn:7012149",
      "tgn:2001718",
      "tgn:7007708",
      "tgn:7029392"
    ],
    "placetype": [
      "aat:300008697"
    ],
    "id": 2500733,
    "name:xx": "McDowell Spring"
  }
}
