{
  "type": "FeatureCollection",
  "features": [
    {
      "geometry": {
        "type": "Point",
        "coordinates": [
          -119.3,
          37.9833
        ]
      },
      "type": "Feature",
      "properties": {
        "hierarchy": [
          "tgn:2224370",
          "tgn:1000001",
          "tgn:7012149",
          "tgn:7007157",
          "tgn:1002675",
          "tgn:7029392"
        ],
        "placetype": [
          "aat:300008680"
        ],
        "id": 2224370,
        "name:xx": "Cascade Lake"
      }
    },
    {
      "geometry": {
        "type": "Point",
        "coordinates": [
          -120.0833,
          38.9333
        ]
      },
      "type": "Feature",
      "properties": {
        "hierarchy": [
          "tgn:2224371",
          "tgn:1000001",
          "tgn:7012149",
          "tgn:1002350",
          "tgn:7007157",
          "tgn:7029392"
        ],
        "placetype": [
          "aat:300008680"
        ],
        "id": 2224371,
        "name:xx": "Cascade Lake"
      }
    },
    {
      "geometry": {
        "type": "Point",
        "coordinates": [
          -105.6,
          40.4
        ]
      },
      "type": "Feature",
      "properties": {
        "hierarchy": [
          "tgn:2224372",
          "tgn:1000001",
          "tgn:7012149",
          "tgn:2000226",
          "tgn:7007158",
          "tgn:7029392"
        ],
        "placetype": [
          "aat:300006191"
        ],
        "id": 2224372,
        "name:xx": "Cascade Lake"
      }
    },
    {
      "geometry": {
        "type": "Point",
        "coordinates": [
          -84.35,
          30.4167
        ]
      },
      "type": "Feature",
      "properties": {
        "hierarchy": [
          "tgn:2224373",
          "tgn:1000001",
          "tgn:7012149",
          "tgn:2000276",
          "tgn:7007240",
          "tgn:7029392"
        ],
        "placetype": [
          "aat:300008680"
        ],
        "id": 2224373,
        "name:xx": "Cascade Lake"
      }
    },
    {
      "geometry": {
        "type": "Point",
        "coordinates": [
          -76.8833,
          39.6
        ]
      },
      "type": "Feature",
      "properties": {
        "hierarchy": [
          "tgn:2224374",
          "tgn:1002238",
          "tgn:1000001",
          "tgn:7012149",
          "tgn:7007516",
          "tgn:7029392"
        ],
        "placetype": [
          "aat:300006191"
        ],
        "id": 2224374,
        "name:xx": "Cascade Lake"
      }
    },
    {
      "geometry": {
        "type": "Point",
        "coordinates": [
          -82.95,
          42.7833
        ]
      },
      "type": "Feature",
      "properties": {
        "hierarchy": [
          "tgn:2224375",
          "tgn:1000001",
          "tgn:7012149",
          "tgn:1002617",
          "tgn:7007520",
          "tgn:7029392"
        ],
        "placetype": [
          "aat:300008680"
        ],
        "id": 2224375,
        "name:xx": "Cascade Lake"
      }
    },
    {
      "geometry": {
        "type": "Point",
        "coordinates": [
          -93.9,
          46.4833
        ]
      },
      "type": "Feature",
      "properties": {
        "hierarchy": [
          "tgn:2224376",
          "tgn:1000001",
          "tgn:2001016",
          "tgn:7012149",
          "tgn:7007521",
          "tgn:7029392"
        ],
        "placetype": [
          "aat:300008680"
        ],
        "id": 2224376,
        "name:xx": "Cascade Lake"
      }
    },
    {
      "geometry": {
        "type": "Point",
        "coordinates": [
          -90.6333,
          47.8667
        ]
      },
      "type": "Feature",
      "properties": {
        "hierarchy": [
          "tgn:2224377",
          "tgn:1000001",
          "tgn:2001014",
          "tgn:7012149",
          "tgn:7007521",
          "tgn:7029392"
        ],
        "placetype": [
          "aat:300008680"
        ],
        "id": 2224377,
        "name:xx": "Cascade Lake"
      }
    },
    {
      "geometry": {
        "type": "Point",
        "coordinates": [
          -110.25,
          46.05
        ]
      },
      "type": "Feature",
      "properties": {
        "hierarchy": [
          "tgn:2224378",
          "tgn:1000001",
          "tgn:7012149",
          "tgn:2001308",
          "tgn:7007524",
          "tgn:7029392"
        ],
        "placetype": [
          "aat:300008680"
        ],
        "id": 2224378,
        "name:xx": "Cascade Lake"
      }
    },
    {
      "geometry": {
        "type": "Point",
        "coordinates": [
          -74.2,
          40.1333
        ]
      },
      "type": "Feature",
      "properties": {
        "hierarchy": [
          "tgn:2224379",
          "tgn:1000001",
          "tgn:7014090",
          "tgn:7012149",
          "tgn:7007565",
          "tgn:7029392"
        ],
        "placetype": [
          "aat:300006191"
        ],
        "id": 2224379,
        "name:xx": "Cascade Lake"
      }
    }
  ]
}
