{
  "geometry": {
    "type": "Point",
    "coordinates": [
      -98.7667,
      36.5833
    ]
  },
  "type": "Feature",
  "properties": {
    "hierarchy": [
      "tgn:2770837",
      "tgn:1000001",
      "tgn:7012149",
      "tgn:2001698",
      "tgn:7007707",
      "tgn:7029392"
    ],
    "placetype": [
      "aat:300008706"
    ],
    "id": 2770837,
    "name:xx": "Wildcat Creek"
  }
}
