{
  "geometry": {
    "type": "Point",
    "coordinates": [
      -75.6833,
      39.1667
    ]
  },
  "type": "Feature",
  "properties": {
    "hierarchy": [
      "tgn:2361425",
      "tgn:1000001",
      "tgn:7012149",
      "tgn:7029392"
    ],
    "placetype": [
      "aat:300008699"
    ],
    "id": 2361425,
    "name:xx": "Gravelly Run"
  }
}
