{
  "geometry": {
    "type": "Point",
    "coordinates": [
      -121.2333,
      46.75
    ]
  },
  "type": "Feature",
  "properties": {
    "hierarchy": [
      "tgn:2456160",
      "tgn:1000001",
      "tgn:7012149",
      "tgn:1003042",
      "tgn:7007920",
      "tgn:7029392"
    ],
    "placetype": [
      "aat:300008706"
    ],
    "id": 2456160,
    "name:xx": "Little Hindoo Creek"
  }
}
