{
  "geometry": {
    "type": "Point",
    "coordinates": [
      81.87877,
      26.32945
    ]
  },
  "type": "Feature",
  "properties": {
    "hierarchy": [
      "tgn:7552267",
      "tgn:1000004",
      "tgn:7000198",
      "tgn:7016722",
      "tgn:7029392"
    ],
    "placetype": [
      "aat:300008347"
    ],
    "name:en": "Maniāri Alīganj",
    "id": 7552267
  }
}
