{
  "geometry": {
    "type": "Point",
    "coordinates": [
      -106.6333,
      40.8667
    ]
  },
  "type": "Feature",
  "properties": {
    "hierarchy": [
      "tgn:2610774",
      "tgn:1000001",
      "tgn:7012149",
      "tgn:2000220",
      "tgn:7007158",
      "tgn:7029392"
    ],
    "placetype": [
      "aat:300008798"
    ],
    "id": 2610774,
    "name:xx": "Red Elephant Mountain"
  }
}
