{
  "geometry": {
    "type": "Point",
    "coordinates": [
      -86.2833,
      33.4833
    ]
  },
  "type": "Feature",
  "properties": {
    "hierarchy": [
      "tgn:2626907",
      "tgn:7002659",
      "tgn:1000001",
      "tgn:7012149",
      "tgn:2000060",
      "tgn:7029392"
    ],
    "placetype": [
      "aat:300008347"
    ],
    "id": 2626907,
    "name:xx": "Rocky Ridge"
  }
}
