{
  "type": "FeatureCollection",
  "features": [
    {
      "geometry": {
        "type": "Point",
        "coordinates": [
          -84.25,
          41.8167
        ]
      },
      "type": "Feature",
      "properties": {
        "hierarchy": [
          "tgn:2155060",
          "tgn:1000001",
          "tgn:7012149",
          "tgn:1002588",
          "tgn:7007520",
          "tgn:7029392"
        ],
        "placetype": [
          "aat:300008680"
        ],
        "id": 2155060,
        "name:xx": "Bear Lake"
      }
    },
    {
      "geometry": {
        "type": "Point",
        "coordinates": [
          -84.6667,
          41.8667
        ]
      },
      "type": "Feature",
      "properties": {
        "hierarchy": [
          "tgn:2155061",
          "tgn:1000001",
          "tgn:7012149",
          "tgn:1002481",
          "tgn:7007520",
          "tgn:7029392"
        ],
        "placetype": [
          "aat:300008680"
        ],
        "id": 2155061,
        "name:xx": "Bear Lake"
      }
    },
    {
      "geometry": {
        "type": "Point",
        "coordinates": [
          -84.9833,
          42.2667
        ]
      },
      "type": "Feature",
      "properties": {
        "hierarchy": [
          "tgn:2155062",
          "tgn:1000001",
          "tgn:1002222",
          "tgn:7012149",
          "tgn:7007520",
          "tgn:7029392"
        ],
        "placetype": [
          "aat:300008680"
        ],
        "id": 2155062,
        "name:xx": "Bear Lake"
      }
    },
    {
      "geometry": {
        "type": "Point",
        "coordinates": [
          -83.2333,
          43.1167
        ]
      },
      "type": "Feature",
      "properties": {
        "hierarchy": [
          "tgn:2155063",
          "tgn:1000001",
          "tgn:7012149",
          "tgn:1002576",
          "tgn:7007520",
          "tgn:7029392"
        ],
        "placetype": [
          "aat:300008680"
        ],
        "id": 2155063,
        "name:xx": "Bear Lake"
      }
    },
    {
      "geometry": {
        "type": "Point",
        "coordinates": [
          -84.95,
          43.8833
        ]
      },
      "type": "Feature",
      "properties": {
        "hierarchy": [
          "tgn:2155064",
          "tgn:1000001",
          "tgn:2000953",
          "tgn:7012149",
          "tgn:7007520",
          "tgn:7029392"
        ],
        "placetype": [
          "aat:300008680"
        ],
        "id": 2155064,
        "name:xx": "Bear Lake"
      }
    },
    {
      "geometry": {
        "type": "Point",
        "coordinates": [
          -85.35,
          44.0167
        ]
      },
      "type": "Feature",
      "properties": {
        "hierarchy": [
          "tgn:2155065",
          "tgn:1000001",
          "tgn:7012149",
          "tgn:2000987",
          "tgn:7007520",
          "tgn:7029392"
        ],
        "placetype": [
          "aat:300008680"
        ],
        "id": 2155065,
        "name:xx": "Bear Lake"
      }
    },
    {
      "geometry": {
        "type": "Point",
        "coordinates": [
          -84.2667,
          44.4
        ]
      },
      "type": "Feature",
      "properties": {
        "hierarchy": [
          "tgn:2155066",
          "tgn:1000001",
          "tgn:7012149",
          "tgn:2000985",
          "tgn:7007520",
          "tgn:7029392"
        ],
        "placetype": [
          "aat:300008680"
        ],
        "id": 2155066,
        "name:xx": "Bear Lake"
      }
    },
    {
      "geometry": {
        "type": "Point",
        "coordinates": [
          -84.8833,
          44.4167
        ]
      },
      "type": "Feature",
      "properties": {
        "hierarchy": [
          "tgn:2155067",
          "tgn:1000001",
          "tgn:7012149",
          "tgn:2000980",
          "tgn:7007520",
          "tgn:7029392"
        ],
        "placetype": [
          "aat:300008680"
        ],
        "id": 2155067,
        "name:xx": "Bear Lake"
      }
    },
    {
      "geometry": {
        "type": "Point",
        "coordinates": [
          -86.15,
          44.4333
        ]
      },
      "type": "Feature",
      "properties": {
        "hierarchy": [
          "tgn:2155068",
          "tgn:1000001",
          "tgn:7012149",
          "tgn:2000974",
          "tgn:7007520",
          "tgn:7029392"
        ],
        "placetype": [
          "aat:300008680"
        ],
        "id": 2155068,
        "name:xx": "Bear Lake"
      }
    },
    {
      "geometry": {
        "type": "Point",
        "coordinates": [
          -84.3833,
          44.4333
        ]
      },
      "type": "Feature",
      "properties": {
        "hierarchy": [
          "tgn:2155069",
          "tgn:1000001",
          "tgn:7012149",
          "tgn:2000991",
          "tgn:7007520",
          "tgn:7029392"
        ],
        "placetype": [
          "aat:300008680"
        ],
        "id": 2155069,
        "name:xx": "Bear Lake"
      }
    }
  ]
}
