{
  "type": "FeatureCollection",
  "features": [
    {
      "geometry": {
        "type": "Point",
        "coordinates": [
          39.7333,
          52.3167
        ]
      },
      "type": "Feature",
      "properties": {
        "hierarchy": [
          "tgn:1138100",
          "tgn:1000004",
          "tgn:7011575",
          "tgn:7018214",
          "tgn:7002435",
          "tgn:7029392"
        ],
        "placetype": [
          "aat:300008347"
        ],
        "id": 1138100,
        "name:xx": "Oktyabrskoye"
      }
    },
    {
      "geometry": {
        "type": "Point",
        "coordinates": [
          55.5167,
          52.3667
        ]
      },
      "type": "Feature",
      "properties": {
        "hierarchy": [
          "tgn:1138101",
          "tgn:1000004",
          "tgn:1003398",
          "tgn:7018214",
          "tgn:7002435",
          "tgn:7029392"
        ],
        "placetype": [
          "aat:300008347"
        ],
        "id": 1138101,
        "name:xx": "Oktyabrskoye"
      }
    },
    {
      "geometry": {
        "type": "Point",
        "coordinates": [
          46.5,
          52.9
        ]
      },
      "type": "Feature",
      "properties": {
        "hierarchy": [
          "tgn:1138102",
          "tgn:1000004",
          "tgn:1003399",
          "tgn:7018214",
          "tgn:7002435",
          "tgn:7029392"
        ],
        "placetype": [
          "aat:300008347"
        ],
        "id": 1138102,
        "name:xx": "Oktyabr'skoye"
      }
    },
    {
      "geometry": {
        "type": "Point",
        "coordinates": [
          62.7667,
          54.4333
        ]
      },
      "type": "Feature",
      "properties": {
        "hierarchy": [
          "tgn:1138103",
          "tgn:6001314",
          "tgn:1000004",
          "tgn:7018214",
          "tgn:7002435",
          "tgn:7029392"
        ],
        "placetype": [
          "aat:300008347"
        ],
        "id": 1138103,
        "name:xx": "Oktyabrskoye"
      }
    },
    {
      "geometry": {
        "type": "Point",
        "coordinates": [
          66.05,
          62.4667
        ]
      },
      "type": "Feature",
      "properties": {
        "hierarchy": [
          "tgn:1138104",
          "tgn:1000004",
          "tgn:7011606",
          "tgn:7018214",
          "tgn:7002435",
          "tgn:7029392"
        ],
        "placetype": [
          "aat:300008347"
        ],
        "id": 1138104,
        "name:xx": "Oktyabr'skoye"
      }
    },
    {
      "geometry": {
        "type": "Point",
        "coordinates": [
          37.9167,
          49.7167
        ]
      },
      "type": "Feature",
      "properties": {
        "hierarchy": [
          "tgn:1138105",
          "tgn:1003361",
          "tgn:1000003",
          "tgn:7006660",
          "tgn:7029392"
        ],
        "placetype": [
          "aat:300008347"
        ],
        "id": 1138105,
        "name:xx": "Olshana"
      }
    },
    {
      "geometry": {
        "type": "Point",
        "coordinates": [
          34,
          50.8333
        ]
      },
      "type": "Feature",
      "properties": {
        "hierarchy": [
          "tgn:1138106",
          "tgn:1000003",
          "tgn:1003410",
          "tgn:7006660",
          "tgn:7029392"
        ],
        "placetype": [
          "aat:300008347"
        ],
        "id": 1138106,
        "name:xx": "Olshana"
      }
    },
    {
      "geometry": {
        "type": "Point",
        "coordinates": [
          35.4167,
          51.7667
        ]
      },
      "type": "Feature",
      "properties": {
        "hierarchy": [
          "tgn:1138107",
          "tgn:1000004",
          "tgn:1003382",
          "tgn:7018214",
          "tgn:7002435",
          "tgn:7029392"
        ],
        "placetype": [
          "aat:300008347"
        ],
        "id": 1138107,
        "name:xx": "Ol'shanka"
      }
    },
    {
      "geometry": {
        "type": "Point",
        "coordinates": [
          27.3333,
          52.0833
        ]
      },
      "type": "Feature",
      "properties": {
        "hierarchy": [
          "tgn:1138108",
          "tgn:1003357",
          "tgn:1000003",
          "tgn:7006657",
          "tgn:7029392"
        ],
        "placetype": [
          "aat:300008347"
        ],
        "id": 1138108,
        "name:xx": "Ol'šany"
      }
    },
    {
      "geometry": {
        "type": "Point",
        "coordinates": [
          39.3167,
          50.3167
        ]
      },
      "type": "Feature",
      "properties": {
        "hierarchy": [
          "tgn:1138109",
          "tgn:1000004",
          "tgn:1003424",
          "tgn:7018214",
          "tgn:7002435",
          "tgn:7029392"
        ],
        "placetype": [
          "aat:300008347"
        ],
        "id": 1138109,
        "name:xx": "Olkhovatka"
      }
    }
  ]
}
