{
  "geometry": {
    "type": "Point",
    "coordinates": [
      6.9833,
      47.9667
    ]
  },
  "type": "Feature",
  "properties": {
    "hierarchy": [
      "tgn:1036279",
      "tgn:7002870",
      "tgn:1000003",
      "tgn:1000070",
      "tgn:7029392"
    ],
    "placetype": [
      "aat:300008347"
    ],
    "id": 1036279,
    "name:xx": "Wildenstein"
  }
}
