{
  "geometry": {
    "type": "Point",
    "coordinates": [
      31.18968,
      29.999076
    ]
  },
  "type": "Feature",
  "properties": {
    "hierarchy": [
      "tgn:7530678",
      "tgn:7001242",
      "tgn:7016833",
      "tgn:1001083",
      "tgn:7029392"
    ],
    "placetype": [
      "aat:300004792"
    ],
    "id": 7530678,
    "name:xx": "Ash Shirkah ash Sharqīyah lil Dukhān"
  }
}
