{
  "geometry": {
    "type": "Point",
    "coordinates": [
      -88.9333,
      34.6833
    ]
  },
  "type": "Feature",
  "properties": {
    "hierarchy": [
      "tgn:2126241",
      "tgn:1000001",
      "tgn:7012149",
      "tgn:2001155",
      "tgn:7007522",
      "tgn:7029392"
    ],
    "placetype": [
      "aat:300008761"
    ],
    "id": 2126241,
    "name:xx": "Adkins Bottom"
  }
}
