{
  "geometry": {
    "type": "Point",
    "coordinates": [
      -91.0667,
      34.0167
    ]
  },
  "type": "Feature",
  "properties": {
    "hierarchy": [
      "tgn:2649877",
      "tgn:1000001",
      "tgn:7016172",
      "tgn:7012149",
      "tgn:7029392"
    ],
    "placetype": [
      "aat:300008699"
    ],
    "id": 2649877,
    "name:xx": "Scrubgrass Bayou"
  }
}
