{
  "geometry": {
    "type": "Point",
    "coordinates": [
      -85.5667,
      42.15
    ]
  },
  "type": "Feature",
  "properties": {
    "hierarchy": [
      "tgn:2357290",
      "tgn:1000001",
      "tgn:7012149",
      "tgn:1002529",
      "tgn:7007520",
      "tgn:7029392"
    ],
    "placetype": [
      "aat:300008680"
    ],
    "id": 2357290,
    "name:xx": "Gourdneck Lake"
  }
}
