{
  "geometry": {
    "type": "Point",
    "coordinates": [
      -81.0833,
      39.4167
    ]
  },
  "type": "Feature",
  "properties": {
    "hierarchy": [
      "tgn:2120104",
      "tgn:1000001",
      "tgn:7012149",
      "tgn:2002286",
      "tgn:7013961",
      "tgn:7029392"
    ],
    "placetype": [
      "aat:300008347"
    ],
    "id": 2120104,
    "name:xx": "Sugar Valley"
  }
}
