{
  "geometry": {
    "type": "Point",
    "coordinates": [
      86.632198,
      20.986724
    ]
  },
  "type": "Feature",
  "properties": {
    "hierarchy": [
      "tgn:7575889",
      "tgn:1000004",
      "tgn:7000198",
      "tgn:7016694",
      "tgn:7029392"
    ],
    "placetype": [
      "aat:300008347"
    ],
    "name:en": "Khāki Hāt",
    "id": 7575889
  }
}
