{
  "geometry": {
    "type": "Point",
    "coordinates": [
      32.884747,
      24.186109
    ]
  },
  "type": "Feature",
  "properties": {
    "hierarchy": [
      "tgn:7520980",
      "tgn:7001242",
      "tgn:7016833",
      "tgn:7000122",
      "tgn:7029392"
    ],
    "placetype": [
      "aat:300008347"
    ],
    "name:en": "Abū ar Rīsh Baḩrī",
    "id": 7520980
  }
}
