{
  "type": "FeatureCollection",
  "features": [
    {
      "geometry": {
        "type": "Point",
        "coordinates": [
          -103.45,
          23.65
        ]
      },
      "type": "Feature",
      "properties": {
        "hierarchy": [
          "tgn:7363230",
          "tgn:1000001",
          "tgn:7005601",
          "tgn:7005560",
          "tgn:7029392"
        ],
        "placetype": [
          "aat:300007783"
        ],
        "id": 7363230,
        "name:xx": "El Arenal"
      }
    },
    {
      "geometry": {
        "type": "Point",
        "coordinates": [
          -99.15,
          19.466667
        ]
      },
      "type": "Feature",
      "properties": {
        "hierarchy": [
          "tgn:7363231",
          "tgn:7005575",
          "tgn:1000001",
          "tgn:7005560",
          "tgn:7029392"
        ],
        "placetype": [
          "aat:300000745"
        ],
        "id": 7363231,
        "name:xx": "El Arenal"
      }
    },
    {
      "geometry": {
        "type": "Point",
        "coordinates": [
          -99.05,
          25.65
        ]
      },
      "type": "Feature",
      "properties": {
        "hierarchy": [
          "tgn:7363233",
          "tgn:1000001",
          "tgn:7005589",
          "tgn:7005560",
          "tgn:7029392"
        ],
        "placetype": [
          "aat:300008347"
        ],
        "id": 7363233,
        "name:xx": "El Arenal"
      }
    },
    {
      "geometry": {
        "type": "Point",
        "coordinates": [
          -98.383333,
          24.916667
        ]
      },
      "type": "Feature",
      "properties": {
        "hierarchy": [
          "tgn:7363234",
          "tgn:1000001",
          "tgn:7005597",
          "tgn:7005560",
          "tgn:7029392"
        ],
        "placetype": [
          "aat:300008347"
        ],
        "id": 7363234,
        "name:xx": "El Arenal"
      }
    },
    {
      "geometry": {
        "type": "Point",
        "coordinates": [
          -104.283333,
          24
        ]
      },
      "type": "Feature",
      "properties": {
        "hierarchy": [
          "tgn:7363235",
          "tgn:7005583",
          "tgn:1000001",
          "tgn:7005560",
          "tgn:7029392"
        ],
        "placetype": [
          "aat:300008347"
        ],
        "id": 7363235,
        "name:xx": "El Arenal"
      }
    },
    {
      "geometry": {
        "type": "Point",
        "coordinates": [
          -103.45,
          23.65
        ]
      },
      "type": "Feature",
      "properties": {
        "hierarchy": [
          "tgn:7363236",
          "tgn:1000001",
          "tgn:7005601",
          "tgn:7005560",
          "tgn:7029392"
        ],
        "placetype": [
          "aat:300008347"
        ],
        "id": 7363236,
        "name:xx": "El Arenal"
      }
    },
    {
      "geometry": {
        "type": "Point",
        "coordinates": [
          -97.783333,
          21.983333
        ]
      },
      "type": "Feature",
      "properties": {
        "hierarchy": [
          "tgn:7363237",
          "tgn:1000001",
          "tgn:7005599",
          "tgn:7005560",
          "tgn:7029392"
        ],
        "placetype": [
          "aat:300008347"
        ],
        "id": 7363237,
        "name:xx": "El Arenal"
      }
    },
    {
      "geometry": {
        "type": "Point",
        "coordinates": [
          -98.383333,
          20.916667
        ]
      },
      "type": "Feature",
      "properties": {
        "hierarchy": [
          "tgn:7363238",
          "tgn:7005587",
          "tgn:1000001",
          "tgn:7005560",
          "tgn:7029392"
        ],
        "placetype": [
          "aat:300008347"
        ],
        "id": 7363238,
        "name:xx": "El Arenal"
      }
    }
  ]
}
