{
  "geometry": {
    "type": "Point",
    "coordinates": [
      -77.4833,
      37.9333
    ]
  },
  "type": "Feature",
  "properties": {
    "hierarchy": [
      "tgn:2467172",
      "tgn:1000001",
      "tgn:1002235",
      "tgn:7012149",
      "tgn:7007919",
      "tgn:7029392"
    ],
    "placetype": [
      "aat:300008706"
    ],
    "id": 2467172,
    "name:xx": "Long Creek"
  }
}
