{
  "geometry": {
    "type": "Point",
    "coordinates": [
      15.9333,
      44.95
    ]
  },
  "type": "Feature",
  "properties": {
    "hierarchy": [
      "tgn:1064960",
      "tgn:7018774",
      "tgn:1000003",
      "tgn:7006664",
      "tgn:7029392"
    ],
    "placetype": [
      "aat:300008347"
    ],
    "id": 1064960,
    "name:xx": "Cazin"
  }
}
