{
  "geometry": {
    "type": "Point",
    "coordinates": [
      53.2667,
      47.6333
    ]
  },
  "type": "Feature",
  "properties": {
    "hierarchy": [
      "tgn:1056691",
      "tgn:7012908",
      "tgn:1000004",
      "tgn:7014786",
      "tgn:7029392"
    ],
    "placetype": [
      "aat:300008347"
    ],
    "id": 1056691,
    "name:xx": "Makat"
  }
}
