{
  "geometry": {
    "type": "Point",
    "coordinates": [
      -46.45,
      -23.4833
    ]
  },
  "type": "Feature",
  "properties": {
    "hierarchy": [
      "tgn:1125083",
      "tgn:1001945",
      "tgn:1000047",
      "tgn:7002457",
      "tgn:1000002",
      "tgn:7029392"
    ],
    "placetype": [
      "aat:300008707"
    ],
    "id": 1125083,
    "name:xx": "Jacu, Rio do"
  }
}
