{
  "geometry": {
    "type": "Point",
    "coordinates": [
      -121.7333,
      48.8667
    ]
  },
  "type": "Feature",
  "properties": {
    "hierarchy": [
      "tgn:2149083",
      "tgn:1000001",
      "tgn:7012149",
      "tgn:1003020",
      "tgn:7007920",
      "tgn:7029392"
    ],
    "placetype": [
      "aat:300008798"
    ],
    "id": 2149083,
    "name:xx": "Barometer Mountain"
  }
}
