{
  "geometry": {
    "type": "Point",
    "coordinates": [
      -93.1333,
      30.2833
    ]
  },
  "type": "Feature",
  "properties": {
    "hierarchy": [
      "tgn:2191874",
      "tgn:1000001",
      "tgn:2000863",
      "tgn:7012149",
      "tgn:7007256",
      "tgn:7029392"
    ],
    "placetype": [
      "aat:300132316"
    ],
    "id": 2191874,
    "name:xx": "Brady Bay"
  }
}
