{
  "geometry": {
    "type": "Point",
    "coordinates": [
      -91.7333,
      42.1833
    ]
  },
  "type": "Feature",
  "properties": {
    "hierarchy": [
      "tgn:2135847",
      "tgn:1000001",
      "tgn:7012149",
      "tgn:2000617",
      "tgn:7007253",
      "tgn:7029392"
    ],
    "placetype": [
      "aat:300008706"
    ],
    "id": 2135847,
    "name:xx": "Apple Creek"
  }
}
