{
  "geometry": {
    "type": "Point",
    "coordinates": [
      -110.55,
      42.2833
    ]
  },
  "type": "Feature",
  "properties": {
    "hierarchy": [
      "tgn:2591455",
      "tgn:1000001",
      "tgn:7012149",
      "tgn:2002376",
      "tgn:7007923",
      "tgn:7029392"
    ],
    "placetype": [
      "aat:300386845"
    ],
    "id": 2591455,
    "name:xx": "Pomeroy Basin"
  }
}
