{
  "type": "FeatureCollection",
  "features": [
    {
      "geometry": {
        "type": "Point",
        "coordinates": [
          -122.5667,
          38.6833
        ]
      },
      "type": "Feature",
      "properties": {
        "hierarchy": [
          "tgn:2719710",
          "tgn:1000001",
          "tgn:7012149",
          "tgn:7007157",
          "tgn:1002566",
          "tgn:7029392"
        ],
        "placetype": [
          "aat:300008798"
        ],
        "id": 2719710,
        "name:xx": "Three Peaks"
      }
    },
    {
      "geometry": {
        "type": "Point",
        "coordinates": [
          -120.1667,
          35.8
        ]
      },
      "type": "Feature",
      "properties": {
        "hierarchy": [
          "tgn:2719711",
          "tgn:1000001",
          "tgn:7012149",
          "tgn:1002550",
          "tgn:7007157",
          "tgn:7029392"
        ],
        "placetype": [
          "aat:300008798"
        ],
        "id": 2719711,
        "name:xx": "Three Peaks"
      }
    },
    {
      "geometry": {
        "type": "Point",
        "coordinates": [
          -121.3,
          35.8333
        ]
      },
      "type": "Feature",
      "properties": {
        "hierarchy": [
          "tgn:2719712",
          "tgn:1000001",
          "tgn:7012149",
          "tgn:7007157",
          "tgn:1002684",
          "tgn:7029392"
        ],
        "placetype": [
          "aat:300008798"
        ],
        "id": 2719712,
        "name:xx": "Three Peaks"
      }
    },
    {
      "geometry": {
        "type": "Point",
        "coordinates": [
          -104.0833,
          45.4
        ]
      },
      "type": "Feature",
      "properties": {
        "hierarchy": [
          "tgn:2719713",
          "tgn:1000001",
          "tgn:2001265",
          "tgn:7012149",
          "tgn:7007524",
          "tgn:7029392"
        ],
        "placetype": [
          "aat:300008798"
        ],
        "id": 2719713,
        "name:xx": "Three Peaks"
      }
    },
    {
      "geometry": {
        "type": "Point",
        "coordinates": [
          -74.0667,
          44.1833
        ]
      },
      "type": "Feature",
      "properties": {
        "hierarchy": [
          "tgn:2719714",
          "tgn:1000001",
          "tgn:7012149",
          "tgn:2001461",
          "tgn:7007568",
          "tgn:7029392"
        ],
        "placetype": [
          "aat:300008798"
        ],
        "id": 2719714,
        "name:xx": "Three Peaks"
      }
    },
    {
      "geometry": {
        "type": "Point",
        "coordinates": [
          -113.3667,
          37.7667
        ]
      },
      "type": "Feature",
      "properties": {
        "hierarchy": [
          "tgn:2719715",
          "tgn:1000001",
          "tgn:7012149",
          "tgn:2002111",
          "tgn:7007827",
          "tgn:7029392"
        ],
        "placetype": [
          "aat:300008798"
        ],
        "id": 2719715,
        "name:xx": "Three Peaks"
      }
    },
    {
      "geometry": {
        "type": "Point",
        "coordinates": [
          -121.7333,
          47.0333
        ]
      },
      "type": "Feature",
      "properties": {
        "hierarchy": [
          "tgn:2719716",
          "tgn:1000001",
          "tgn:7012149",
          "tgn:1002785",
          "tgn:7007920",
          "tgn:7029392"
        ],
        "placetype": [
          "aat:300008798"
        ],
        "id": 2719716,
        "name:xx": "Three Peaks"
      }
    },
    {
      "geometry": {
        "type": "Point",
        "coordinates": [
          -123.55,
          47.4833
        ]
      },
      "type": "Feature",
      "properties": {
        "hierarchy": [
          "tgn:2719717",
          "tgn:1000001",
          "tgn:7012149",
          "tgn:1002418",
          "tgn:7007920",
          "tgn:7029392"
        ],
        "placetype": [
          "aat:300008798"
        ],
        "id": 2719717,
        "name:xx": "Three Peaks"
      }
    },
    {
      "geometry": {
        "type": "Point",
        "coordinates": [
          -113.2,
          37.75
        ]
      },
      "type": "Feature",
      "properties": {
        "hierarchy": [
          "tgn:2719718",
          "tgn:1000001",
          "tgn:7012149",
          "tgn:2002111",
          "tgn:7007827",
          "tgn:7029392"
        ],
        "placetype": [
          "aat:300008798"
        ],
        "id": 2719718,
        "name:xx": "Three Peaks, The"
      }
    },
    {
      "geometry": {
        "type": "Point",
        "coordinates": [
          -109.6167,
          38.6167
        ]
      },
      "type": "Feature",
      "properties": {
        "hierarchy": [
          "tgn:2719719",
          "tgn:1000001",
          "tgn:7012149",
          "tgn:2002110",
          "tgn:7007827",
          "tgn:7029392"
        ],
        "placetype": [
          "aat:300008798"
        ],
        "id": 2719719,
        "name:xx": "Three Penguins"
      }
    }
  ]
}
