{
  "type": "FeatureCollection",
  "features": [
    {
      "geometry": {
        "type": "Point",
        "coordinates": [
          32.516667,
          30.233333
        ]
      },
      "type": "Feature",
      "properties": {
        "hierarchy": [
          "tgn:7521700",
          "tgn:7001242",
          "tgn:7016833",
          "tgn:1001110",
          "tgn:7029392"
        ],
        "placetype": [
          "aat:300008791"
        ],
        "name:en": "'Alāwī al Būghāz, Jazīrat",
        "id": 7521700
      }
    },
    {
      "geometry": {
        "type": "Point",
        "coordinates": [
          30.683333,
          29.25
        ]
      },
      "type": "Feature",
      "properties": {
        "hierarchy": [
          "tgn:7521701",
          "tgn:7001242",
          "tgn:7001105",
          "tgn:7016833",
          "tgn:7029392"
        ],
        "placetype": [
          "aat:300008347"
        ],
        "name:en": "Al 'Awfī",
        "id": 7521701
      }
    },
    {
      "geometry": {
        "type": "Point",
        "coordinates": [
          30.935561,
          29.122235
        ]
      },
      "type": "Feature",
      "properties": {
        "hierarchy": [
          "tgn:7521702",
          "tgn:7001242",
          "tgn:7016833",
          "tgn:1001142",
          "tgn:7029392"
        ],
        "placetype": [
          "aat:300008347"
        ],
        "name:en": "Al 'Awāwinah",
        "id": 7521702
      }
    },
    {
      "geometry": {
        "type": "Point",
        "coordinates": [
          31.592538,
          30.620042
        ]
      },
      "type": "Feature",
      "properties": {
        "hierarchy": [
          "tgn:7521703",
          "tgn:7001242",
          "tgn:7016833",
          "tgn:1001113",
          "tgn:7029392"
        ],
        "placetype": [
          "aat:300008347"
        ],
        "id": 7521703,
        "name:xx": "Al 'Awāsijah"
      }
    },
    {
      "geometry": {
        "type": "Point",
        "coordinates": [
          31.338863,
          27.085824
        ]
      },
      "type": "Feature",
      "properties": {
        "hierarchy": [
          "tgn:7521704",
          "tgn:7001242",
          "tgn:7016833",
          "tgn:1001114",
          "tgn:7029392"
        ],
        "placetype": [
          "aat:300008347"
        ],
        "name:en": "Al 'Awānah",
        "id": 7521704
      }
    },
    {
      "geometry": {
        "type": "Point",
        "coordinates": [
          31.85,
          26.3
        ]
      },
      "type": "Feature",
      "properties": {
        "hierarchy": [
          "tgn:7521705",
          "tgn:7001242",
          "tgn:7016833",
          "tgn:7000124",
          "tgn:7029392"
        ],
        "placetype": [
          "aat:300008347"
        ],
        "name:en": "Al 'Awāmir Qiblī",
        "id": 7521705
      }
    },
    {
      "geometry": {
        "type": "Point",
        "coordinates": [
          31.854806,
          26.314309
        ]
      },
      "type": "Feature",
      "properties": {
        "hierarchy": [
          "tgn:7521706",
          "tgn:7001242",
          "tgn:7016833",
          "tgn:7000124",
          "tgn:7029392"
        ],
        "placetype": [
          "aat:300008347"
        ],
        "name:en": "Al 'Awāmir Baḩrī",
        "id": 7521706
      }
    },
    {
      "geometry": {
        "type": "Point",
        "coordinates": [
          30.660833,
          30.810278
        ]
      },
      "type": "Feature",
      "properties": {
        "hierarchy": [
          "tgn:7521707",
          "tgn:7001242",
          "tgn:1001075",
          "tgn:7016833",
          "tgn:7029392"
        ],
        "placetype": [
          "aat:300008347"
        ],
        "name:en": "Al 'Awāmir",
        "id": 7521707
      }
    },
    {
      "geometry": {
        "type": "Point",
        "coordinates": [
          32.583333,
          25.683333
        ]
      },
      "type": "Feature",
      "properties": {
        "hierarchy": [
          "tgn:7521708",
          "tgn:7001242",
          "tgn:7016833",
          "tgn:7000123",
          "tgn:7029392"
        ],
        "placetype": [
          "aat:300343519"
        ],
        "name:en": "Abū Kalb, Ḩawshat",
        "id": 7521708
      }
    }
  ]
}
