{
  "geometry": {
    "type": "Point",
    "coordinates": [
      -78.5333,
      35.7667
    ]
  },
  "type": "Feature",
  "properties": {
    "hierarchy": [
      "tgn:2147604",
      "tgn:1000001",
      "tgn:7012149",
      "tgn:2001548",
      "tgn:7007709",
      "tgn:7029392"
    ],
    "placetype": [
      "aat:300008347"
    ],
    "id": 2147604,
    "name:xx": "Barclay Downs"
  }
}
