{
  "geometry": {
    "type": "Point",
    "coordinates": [
      -75.1667,
      42.4833
    ]
  },
  "type": "Feature",
  "properties": {
    "hierarchy": [
      "tgn:2561866",
      "tgn:1000001",
      "tgn:7012149",
      "tgn:7014318",
      "tgn:7007568",
      "tgn:7029392"
    ],
    "placetype": [
      "aat:300008347"
    ],
    "id": 2561866,
    "name:xx": "Otsdawa"
  }
}
