{
  "geometry": {
    "type": "Point",
    "coordinates": [
      -8.513,
      41.859
    ]
  },
  "type": "Feature",
  "properties": {
    "hierarchy": [
      "tgn:7030483",
      "tgn:1000003",
      "tgn:7003830",
      "tgn:1000090",
      "tgn:7029392"
    ],
    "placetype": [
      "aat:300008347"
    ],
    "name:pt": "Grijó",
    "id": 7030483
  }
}
