{
  "geometry": {
    "type": "Point",
    "coordinates": [
      -91.35,
      47.8667
    ]
  },
  "type": "Feature",
  "properties": {
    "hierarchy": [
      "tgn:2194201",
      "tgn:1000001",
      "tgn:7012149",
      "tgn:2001036",
      "tgn:7007521",
      "tgn:7029392"
    ],
    "placetype": [
      "aat:300008680"
    ],
    "id": 2194201,
    "name:xx": "Briddle Lake"
  }
}
