{
  "geometry": {
    "type": "Point",
    "coordinates": [
      77.629906,
      20.994784
    ]
  },
  "type": "Feature",
  "properties": {
    "hierarchy": [
      "tgn:7577038",
      "tgn:1000004",
      "tgn:7000198",
      "tgn:1001895",
      "tgn:7029392"
    ],
    "placetype": [
      "aat:300008347"
    ],
    "name:en": "Khār Tālegaon",
    "id": 7577038
  }
}
