{
  "geometry": {
    "type": "Point",
    "coordinates": [
      129.1833,
      40.6667
    ]
  },
  "type": "Feature",
  "properties": {
    "hierarchy": [
      "tgn:1082031",
      "tgn:1001285",
      "tgn:1000004",
      "tgn:1000122",
      "tgn:7029392"
    ],
    "placetype": [
      "aat:300008347",
      "aat:300008375",
      "aat:300120599"
    ],
    "id": 1082031,
    "name:xx": "Kimch'aek"
  }
}
