{
  "geometry": {
    "type": "Point",
    "coordinates": [
      31.2309,
      30.996474
    ]
  },
  "type": "Feature",
  "properties": {
    "hierarchy": [
      "tgn:7536436",
      "tgn:7001242",
      "tgn:7016833",
      "tgn:7001312",
      "tgn:7029392"
    ],
    "placetype": [
      "aat:300008347"
    ],
    "name:en": "Kafr aş Şārim al Baḩrī",
    "id": 7536436
  }
}
