{
  "geometry": {
    "type": "Point",
    "coordinates": [
      -106.85,
      30.15
    ]
  },
  "type": "Feature",
  "properties": {
    "hierarchy": [
      "tgn:7386388",
      "tgn:7005581",
      "tgn:1000001",
      "tgn:7005560",
      "tgn:7029392"
    ],
    "placetype": [
      "aat:300008699"
    ],
    "id": 7386388,
    "name:xx": "Plan de Álamos, Arroyo del"
  }
}
