{
  "type": "FeatureCollection",
  "features": [
    {
      "geometry": {
        "type": "Point",
        "coordinates": [
          -94.15,
          16.416667
        ]
      },
      "type": "Feature",
      "properties": {
        "hierarchy": [
          "tgn:7349360",
          "tgn:1000001",
          "tgn:7005591",
          "tgn:7005560",
          "tgn:7029392"
        ],
        "placetype": [
          "aat:300008347"
        ],
        "id": 7349360,
        "name:xx": "Agua Fría"
      }
    },
    {
      "geometry": {
        "type": "Point",
        "coordinates": [
          -96.833333,
          15.833333
        ]
      },
      "type": "Feature",
      "properties": {
        "hierarchy": [
          "tgn:7349361",
          "tgn:7005581",
          "tgn:1000001",
          "tgn:7005560",
          "tgn:7029392"
        ],
        "placetype": [
          "aat:300008347"
        ],
        "id": 7349361,
        "name:xx": "Agua Fría"
      }
    },
    {
      "geometry": {
        "type": "Point",
        "coordinates": [
          -106.75,
          26.233333
        ]
      },
      "type": "Feature",
      "properties": {
        "hierarchy": [
          "tgn:7349362",
          "tgn:7005581",
          "tgn:1000001",
          "tgn:7005560",
          "tgn:7029392"
        ],
        "placetype": [
          "aat:300387007"
        ],
        "id": 7349362,
        "name:xx": "Agua Fría"
      }
    },
    {
      "geometry": {
        "type": "Point",
        "coordinates": [
          -99.833333,
          25.8
        ]
      },
      "type": "Feature",
      "properties": {
        "hierarchy": [
          "tgn:7349363",
          "tgn:1000001",
          "tgn:7005589",
          "tgn:7005560",
          "tgn:7029392"
        ],
        "placetype": [
          "aat:300008347"
        ],
        "id": 7349363,
        "name:xx": "Agua Fresca"
      }
    },
    {
      "geometry": {
        "type": "Point",
        "coordinates": [
          -110.833333,
          23.933333
        ]
      },
      "type": "Feature",
      "properties": {
        "hierarchy": [
          "tgn:7349364",
          "tgn:1001836",
          "tgn:1000001",
          "tgn:7005560",
          "tgn:7029392"
        ],
        "placetype": [
          "aat:300008347"
        ],
        "id": 7349364,
        "name:xx": "Agua Fresca"
      }
    },
    {
      "geometry": {
        "type": "Point",
        "coordinates": [
          -116.64,
          32.138889
        ]
      },
      "type": "Feature",
      "properties": {
        "hierarchy": [
          "tgn:7349365",
          "tgn:1001835",
          "tgn:1000001",
          "tgn:7005560",
          "tgn:7029392"
        ],
        "placetype": [
          "aat:300008347"
        ],
        "id": 7349365,
        "name:xx": "Agua Escondida"
      }
    },
    {
      "geometry": {
        "type": "Point",
        "coordinates": [
          -107.1,
          26.883333
        ]
      },
      "type": "Feature",
      "properties": {
        "hierarchy": [
          "tgn:7349366",
          "tgn:7005581",
          "tgn:1000001",
          "tgn:7005560",
          "tgn:7029392"
        ],
        "placetype": [
          "aat:300000241"
        ],
        "id": 7349366,
        "name:xx": "Rancho Agua Escondida"
      }
    },
    {
      "geometry": {
        "type": "Point",
        "coordinates": [
          -106.083333,
          26.35
        ]
      },
      "type": "Feature",
      "properties": {
        "hierarchy": [
          "tgn:7349367",
          "tgn:7005583",
          "tgn:1000001",
          "tgn:7005560",
          "tgn:7029392"
        ],
        "placetype": [
          "aat:300000241"
        ],
        "id": 7349367,
        "name:xx": "Rancho Agua Escondida"
      }
    },
    {
      "geometry": {
        "type": "Point",
        "coordinates": [
          -91.45,
          16.683333
        ]
      },
      "type": "Feature",
      "properties": {
        "hierarchy": [
          "tgn:7349368",
          "tgn:7005580",
          "tgn:1000001",
          "tgn:7005560",
          "tgn:7029392"
        ],
        "placetype": [
          "aat:300132339"
        ],
        "id": 7349368,
        "name:xx": "Agua Escondida, Meseta"
      }
    },
    {
      "geometry": {
        "type": "Point",
        "coordinates": [
          -116.788333,
          32.098333
        ]
      },
      "type": "Feature",
      "properties": {
        "hierarchy": [
          "tgn:7349369",
          "tgn:1001835",
          "tgn:1000001",
          "tgn:7005560",
          "tgn:7029392"
        ],
        "placetype": [
          "aat:300266554",
          "aat:300008699"
        ],
        "id": 7349369,
        "name:xx": "Agua Escondida, Cañón"
      }
    }
  ]
}
