{
  "type": "FeatureCollection",
  "features": [
    {
      "geometry": {
        "type": "Point",
        "coordinates": [
          -80.45,
          39.2667
        ]
      },
      "type": "Feature",
      "properties": {
        "hierarchy": [
          "tgn:2120530",
          "tgn:1000001",
          "tgn:7012149",
          "tgn:2002267",
          "tgn:7013961",
          "tgn:7029392"
        ],
        "placetype": [
          "aat:300008347"
        ],
        "id": 2120530,
        "name:xx": "Wolf Summit"
      }
    },
    {
      "geometry": {
        "type": "Point",
        "coordinates": [
          -80.6,
          38.2833
        ]
      },
      "type": "Feature",
      "properties": {
        "hierarchy": [
          "tgn:2120533",
          "tgn:1000001",
          "tgn:7012149",
          "tgn:2002284",
          "tgn:7013961",
          "tgn:7029392"
        ],
        "placetype": [
          "aat:300387016"
        ],
        "id": 2120533,
        "name:xx": "Woodbine"
      }
    },
    {
      "geometry": {
        "type": "Point",
        "coordinates": [
          -80.8167,
          39.8
        ]
      },
      "type": "Feature",
      "properties": {
        "hierarchy": [
          "tgn:2120534",
          "tgn:1000001",
          "tgn:7012149",
          "tgn:2002276",
          "tgn:7013961",
          "tgn:7029392"
        ],
        "placetype": [
          "aat:300008347",
          "aat:300387210"
        ],
        "id": 2120534,
        "name:xx": "Woodlands"
      }
    },
    {
      "geometry": {
        "type": "Point",
        "coordinates": [
          -80.15,
          38.2667
        ]
      },
      "type": "Feature",
      "properties": {
        "hierarchy": [
          "tgn:2120535",
          "tgn:1000001",
          "tgn:7012149",
          "tgn:2002287",
          "tgn:7013961",
          "tgn:7029392"
        ],
        "placetype": [
          "aat:300008347",
          "aat:300387210"
        ],
        "id": 2120535,
        "name:xx": "Woodrow"
      }
    },
    {
      "geometry": {
        "type": "Point",
        "coordinates": [
          -80.5333,
          39.7667
        ]
      },
      "type": "Feature",
      "properties": {
        "hierarchy": [
          "tgn:2120536",
          "tgn:1000001",
          "tgn:7012149",
          "tgn:2002276",
          "tgn:7013961",
          "tgn:7029392"
        ],
        "placetype": [
          "aat:300008347",
          "aat:300387210"
        ],
        "id": 2120536,
        "name:xx": "Woodruff"
      }
    },
    {
      "geometry": {
        "type": "Point",
        "coordinates": [
          -81.8833,
          38.15
        ]
      },
      "type": "Feature",
      "properties": {
        "hierarchy": [
          "tgn:2120538",
          "tgn:1000001",
          "tgn:7012149",
          "tgn:2002272",
          "tgn:7013961",
          "tgn:7029392"
        ],
        "placetype": [
          "aat:300008347"
        ],
        "id": 2120538,
        "name:xx": "Woodville"
      }
    },
    {
      "geometry": {
        "type": "Point",
        "coordinates": [
          -81.3833,
          37.4
        ]
      },
      "type": "Feature",
      "properties": {
        "hierarchy": [
          "tgn:2120539",
          "tgn:1000001",
          "tgn:7012149",
          "tgn:2002274",
          "tgn:7013961",
          "tgn:7029392"
        ],
        "placetype": [
          "aat:300008347"
        ],
        "id": 2120539,
        "name:xx": "Worth"
      }
    }
  ]
}
