{
  "geometry": {
    "type": "Point",
    "coordinates": [
      -106.4167,
      45.7167
    ]
  },
  "type": "Feature",
  "properties": {
    "hierarchy": [
      "tgn:2780717",
      "tgn:1000001",
      "tgn:7012149",
      "tgn:2001303",
      "tgn:7007524",
      "tgn:7029392"
    ],
    "placetype": [
      "aat:300008347"
    ],
    "id": 2780717,
    "name:xx": "Wood Place"
  }
}
