{
  "geometry": {
    "type": "Point",
    "coordinates": [
      -76.6333,
      3.0333
    ]
  },
  "type": "Feature",
  "properties": {
    "hierarchy": [
      "tgn:1023732",
      "tgn:1000554",
      "tgn:1000050",
      "tgn:1000002",
      "tgn:7029392"
    ],
    "placetype": [
      "aat:300008347"
    ],
    "id": 1023732,
    "name:xx": "Buenos Aires"
  }
}
