{
  "type": "FeatureCollection",
  "features": [
    {
      "geometry": {
        "type": "Point",
        "coordinates": [
          4.04443,
          50.987356
        ]
      },
      "type": "Feature",
      "properties": {
        "hierarchy": [
          "tgn:7252431",
          "tgn:7003457",
          "tgn:1000003",
          "tgn:1000063",
          "tgn:7018236",
          "tgn:7029392"
        ],
        "placetype": [
          "aat:300008347"
        ],
        "id": 7252431,
        "name:xx": "Molenhoek"
      }
    },
    {
      "geometry": {
        "type": "Point",
        "coordinates": [
          4.333333,
          51.016667
        ]
      },
      "type": "Feature",
      "properties": {
        "hierarchy": [
          "tgn:7252433",
          "tgn:7003456",
          "tgn:1000003",
          "tgn:1000063",
          "tgn:7018236",
          "tgn:7029392"
        ],
        "placetype": [
          "aat:300008347"
        ],
        "id": 7252433,
        "name:xx": "Molenhoek"
      }
    },
    {
      "geometry": {
        "type": "Point",
        "coordinates": [
          2.785952,
          50.934607
        ]
      },
      "type": "Feature",
      "properties": {
        "hierarchy": [
          "tgn:7252439",
          "tgn:7003458",
          "tgn:1000003",
          "tgn:1000063",
          "tgn:7018236",
          "tgn:7029392"
        ],
        "placetype": [
          "aat:300008347"
        ],
        "id": 7252439,
        "name:xx": "Molenhoek"
      }
    }
  ]
}
