{
  "geometry": {
    "type": "Point",
    "coordinates": [
      -115.7833,
      39.5333
    ]
  },
  "type": "Feature",
  "properties": {
    "hierarchy": [
      "tgn:2539938",
      "tgn:1000001",
      "tgn:7012149",
      "tgn:2001420",
      "tgn:7007526",
      "tgn:7029392"
    ],
    "placetype": [
      "aat:300008347"
    ],
    "id": 2539938,
    "name:xx": "Newark"
  }
}
