{
  "type": "FeatureCollection",
  "features": [
    {
      "geometry": {
        "type": "Point",
        "coordinates": [
          23.283333,
          40.816667
        ]
      },
      "type": "Feature",
      "properties": {
        "hierarchy": [
          "tgn:7230460",
          "tgn:7002715",
          "tgn:7002731",
          "tgn:1000003",
          "tgn:1000074",
          "tgn:7029392"
        ],
        "placetype": [
          "aat:300008347"
        ],
        "id": 7230460,
        "name:xx": "Krionérion"
      }
    },
    {
      "geometry": {
        "type": "Point",
        "coordinates": [
          23.083333,
          40.383333
        ]
      },
      "type": "Feature",
      "properties": {
        "hierarchy": [
          "tgn:7230461",
          "tgn:7002715",
          "tgn:7002731",
          "tgn:1000003",
          "tgn:1000074",
          "tgn:7029392"
        ],
        "placetype": [
          "aat:300008347"
        ],
        "id": 7230461,
        "name:xx": "Krionérion"
      }
    },
    {
      "geometry": {
        "type": "Point",
        "coordinates": [
          20.501111,
          39.885556
        ]
      },
      "type": "Feature",
      "properties": {
        "hierarchy": [
          "tgn:7230462",
          "tgn:7002707",
          "tgn:7002705",
          "tgn:1000003",
          "tgn:1000074",
          "tgn:7029392"
        ],
        "placetype": [
          "aat:300008347"
        ],
        "id": 7230462,
        "name:xx": "Kryonérion"
      }
    },
    {
      "geometry": {
        "type": "Point",
        "coordinates": [
          21.047222,
          39.36
        ]
      },
      "type": "Feature",
      "properties": {
        "hierarchy": [
          "tgn:7230463",
          "tgn:7002706",
          "tgn:7002705",
          "tgn:1000003",
          "tgn:1000074",
          "tgn:7029392"
        ],
        "placetype": [
          "aat:300008347"
        ],
        "id": 7230463,
        "name:xx": "Kryonérion"
      }
    },
    {
      "geometry": {
        "type": "Point",
        "coordinates": [
          21.6875,
          39.333056
        ]
      },
      "type": "Feature",
      "properties": {
        "hierarchy": [
          "tgn:7230464",
          "tgn:7002748",
          "tgn:7001399",
          "tgn:1000003",
          "tgn:1000074",
          "tgn:7029392"
        ],
        "placetype": [
          "aat:300008347"
        ],
        "id": 7230464,
        "name:xx": "Kryonérion"
      }
    },
    {
      "geometry": {
        "type": "Point",
        "coordinates": [
          21.6,
          38.35
        ]
      },
      "type": "Feature",
      "properties": {
        "hierarchy": [
          "tgn:7230465",
          "tgn:7002680",
          "tgn:7001395",
          "tgn:1000003",
          "tgn:1000074",
          "tgn:7029392"
        ],
        "placetype": [
          "aat:300008347"
        ],
        "id": 7230465,
        "name:xx": "Kryonéri"
      }
    },
    {
      "geometry": {
        "type": "Point",
        "coordinates": [
          23.833333,
          38.15
        ]
      },
      "type": "Feature",
      "properties": {
        "hierarchy": [
          "tgn:7230466",
          "tgn:7002681",
          "tgn:7001395",
          "tgn:1000003",
          "tgn:1000074",
          "tgn:7029392"
        ],
        "placetype": [
          "aat:300008347"
        ],
        "id": 7230466,
        "name:xx": "Krionérion"
      }
    },
    {
      "geometry": {
        "type": "Point",
        "coordinates": [
          21.983333,
          38.016667
        ]
      },
      "type": "Feature",
      "properties": {
        "hierarchy": [
          "tgn:7230467",
          "tgn:7002743",
          "tgn:7017076",
          "tgn:1000003",
          "tgn:1000074",
          "tgn:7029392"
        ],
        "placetype": [
          "aat:300008347"
        ],
        "id": 7230467,
        "name:xx": "Krionérion"
      }
    },
    {
      "geometry": {
        "type": "Point",
        "coordinates": [
          22.633333,
          37.966667
        ]
      },
      "type": "Feature",
      "properties": {
        "hierarchy": [
          "tgn:7230468",
          "tgn:7002741",
          "tgn:7017076",
          "tgn:1000003",
          "tgn:1000074",
          "tgn:7029392"
        ],
        "placetype": [
          "aat:300008347"
        ],
        "id": 7230468,
        "name:xx": "Krionérion"
      }
    },
    {
      "geometry": {
        "type": "Point",
        "coordinates": [
          22.533333,
          37.583333
        ]
      },
      "type": "Feature",
      "properties": {
        "hierarchy": [
          "tgn:7230469",
          "tgn:7002739",
          "tgn:7017076",
          "tgn:1000003",
          "tgn:1000074",
          "tgn:7029392"
        ],
        "placetype": [
          "aat:300008347"
        ],
        "id": 7230469,
        "name:xx": "Krionérion"
      }
    }
  ]
}
