{
  "geometry": {
    "type": "Point",
    "coordinates": [
      -77.25,
      37.35
    ]
  },
  "type": "Feature",
  "properties": {
    "hierarchy": [
      "tgn:2733032",
      "tgn:1000001",
      "tgn:1002267",
      "tgn:7012149",
      "tgn:7007919",
      "tgn:7029392"
    ],
    "placetype": [
      "aat:300008791"
    ],
    "id": 2733032,
    "name:xx": "Turkey Island"
  }
}
