{
  "geometry": {
    "type": "Point",
    "coordinates": [
      -86.5167,
      34.95
    ]
  },
  "type": "Feature",
  "properties": {
    "hierarchy": [
      "tgn:2005310",
      "tgn:7002659",
      "tgn:1000001",
      "tgn:7012149",
      "tgn:2000044",
      "tgn:7029392"
    ],
    "placetype": [
      "aat:300008347",
      "aat:300387210"
    ],
    "id": 2005310,
    "name:xx": "Skinem"
  }
}
