{
  "geometry": {
    "type": "Point",
    "coordinates": [
      -72.2667,
      41.0667
    ]
  },
  "type": "Feature",
  "properties": {
    "hierarchy": [
      "tgn:2613943",
      "tgn:1000001",
      "tgn:7012149",
      "tgn:1002924",
      "tgn:7007568",
      "tgn:7029392"
    ],
    "placetype": [
      "aat:300008850"
    ],
    "id": 2613943,
    "name:xx": "Reel Point"
  }
}
