{
  "geometry": {
    "type": "Point",
    "coordinates": [
      -71.85,
      41.4833
    ]
  },
  "type": "Feature",
  "properties": {
    "hierarchy": [
      "tgn:2387350",
      "tgn:1000001",
      "tgn:1002714",
      "tgn:7012149",
      "tgn:7007159",
      "tgn:7029392"
    ],
    "placetype": [
      "aat:300008905"
    ],
    "id": 2387350,
    "name:xx": "Hetchel Swamp"
  }
}
