{
  "geometry": {
    "type": "Point",
    "coordinates": [
      -81.3333,
      24.8333
    ]
  },
  "type": "Feature",
  "properties": {
    "hierarchy": [
      "tgn:2206378",
      "tgn:1000001",
      "tgn:7012149",
      "tgn:1002676",
      "tgn:7007240",
      "tgn:7029392"
    ],
    "placetype": [
      "aat:300132348"
    ],
    "id": 2206378,
    "name:xx": "Bullfrog Banks"
  }
}
