{
  "geometry": {
    "type": "Point",
    "coordinates": [
      -113.15,
      44.6333
    ]
  },
  "type": "Feature",
  "properties": {
    "hierarchy": [
      "tgn:2205417",
      "tgn:1000001",
      "tgn:7012149",
      "tgn:2000481",
      "tgn:7007250",
      "tgn:7029392"
    ],
    "placetype": [
      "aat:300008706"
    ],
    "id": 2205417,
    "name:xx": "Bull Creek"
  }
}
