{
  "geometry": {
    "type": "Point",
    "coordinates": [
      116.0667,
      25.9833
    ]
  },
  "type": "Feature",
  "properties": {
    "hierarchy": [
      "tgn:1072482",
      "tgn:1000004",
      "tgn:7002082",
      "tgn:1000111",
      "tgn:7029392"
    ],
    "placetype": [
      "aat:300008347"
    ],
    "id": 1072482,
    "name:xx": "Wangtian"
  }
}
