{
  "type": "FeatureCollection",
  "features": [
    {
      "geometry": {
        "type": "Point",
        "coordinates": [
          -121.4833,
          48.15
        ]
      },
      "type": "Feature",
      "properties": {
        "hierarchy": [
          "tgn:2302140",
          "tgn:1000001",
          "tgn:7012149",
          "tgn:1002899",
          "tgn:7007920",
          "tgn:7029392"
        ],
        "placetype": [
          "aat:300008706"
        ],
        "id": 2302140,
        "name:xx": "Dutch Creek"
      }
    },
    {
      "geometry": {
        "type": "Point",
        "coordinates": [
          -91.1667,
          44.9667
        ]
      },
      "type": "Feature",
      "properties": {
        "hierarchy": [
          "tgn:2302141",
          "tgn:1000001",
          "tgn:2002313",
          "tgn:7012149",
          "tgn:7007922",
          "tgn:7029392"
        ],
        "placetype": [
          "aat:300008706"
        ],
        "id": 2302141,
        "name:xx": "Dutch Creek"
      }
    },
    {
      "geometry": {
        "type": "Point",
        "coordinates": [
          -90.8833,
          43.8167
        ]
      },
      "type": "Feature",
      "properties": {
        "hierarchy": [
          "tgn:2302142",
          "tgn:1000001",
          "tgn:7012149",
          "tgn:7007922",
          "tgn:7029392"
        ],
        "placetype": [
          "aat:300008706"
        ],
        "id": 2302142,
        "name:xx": "Dutch Creek"
      }
    },
    {
      "geometry": {
        "type": "Point",
        "coordinates": [
          -91.2667,
          44.1167
        ]
      },
      "type": "Feature",
      "properties": {
        "hierarchy": [
          "tgn:2302143",
          "tgn:1000001",
          "tgn:7012149",
          "tgn:2002357",
          "tgn:7007922",
          "tgn:7029392"
        ],
        "placetype": [
          "aat:300008706"
        ],
        "id": 2302143,
        "name:xx": "Dutch Creek"
      }
    },
    {
      "geometry": {
        "type": "Point",
        "coordinates": [
          -106.7167,
          44.7833
        ]
      },
      "type": "Feature",
      "properties": {
        "hierarchy": [
          "tgn:2302144",
          "tgn:1000001",
          "tgn:7012149",
          "tgn:2002381",
          "tgn:7007923",
          "tgn:7029392"
        ],
        "placetype": [
          "aat:300008706"
        ],
        "id": 2302144,
        "name:xx": "Dutch Creek"
      }
    },
    {
      "geometry": {
        "type": "Point",
        "coordinates": [
          -104.8167,
          44.4833
        ]
      },
      "type": "Feature",
      "properties": {
        "hierarchy": [
          "tgn:2302145",
          "tgn:1000001",
          "tgn:2002370",
          "tgn:7012149",
          "tgn:7007923",
          "tgn:7029392"
        ],
        "placetype": [
          "aat:300008706"
        ],
        "id": 2302145,
        "name:xx": "Dutch Creek"
      }
    },
    {
      "geometry": {
        "type": "Point",
        "coordinates": [
          -85.45,
          36.8333
        ]
      },
      "type": "Feature",
      "properties": {
        "hierarchy": [
          "tgn:2302146",
          "tgn:1000001",
          "tgn:7012149",
          "tgn:2000785",
          "tgn:7007255",
          "tgn:7029392"
        ],
        "placetype": [
          "aat:300008746"
        ],
        "id": 2302146,
        "name:xx": "Dutch Creek Cave"
      }
    },
    {
      "geometry": {
        "type": "Point",
        "coordinates": [
          -107.3333,
          39.1833
        ]
      },
      "type": "Feature",
      "properties": {
        "hierarchy": [
          "tgn:2302147",
          "tgn:1000001",
          "tgn:7012149",
          "tgn:7007158",
          "tgn:2000240",
          "tgn:7029392"
        ],
        "placetype": [
          "aat:300000390"
        ],
        "id": 2302147,
        "name:xx": "Dutch Creek Mine"
      }
    }
  ]
}
