{
  "type": "FeatureCollection",
  "features": [
    {
      "geometry": {
        "type": "Point",
        "coordinates": [
          -2.033333,
          39.566667
        ]
      },
      "type": "Feature",
      "properties": {
        "hierarchy": [
          "tgn:7294770",
          "tgn:7002818",
          "tgn:1001647",
          "tgn:1000003",
          "tgn:1000095",
          "tgn:7029392"
        ],
        "placetype": [
          "aat:300266554",
          "aat:300008699"
        ],
        "id": 7294770,
        "name:xx": "Vallejo, Arroyo del"
      }
    },
    {
      "geometry": {
        "type": "Point",
        "coordinates": [
          -4.433333,
          39.016667
        ]
      },
      "type": "Feature",
      "properties": {
        "hierarchy": [
          "tgn:7294771",
          "tgn:7002816",
          "tgn:1001647",
          "tgn:1000003",
          "tgn:1000095",
          "tgn:7029392"
        ],
        "placetype": [
          "aat:300008699"
        ],
        "id": 7294771,
        "name:xx": "Vallejo, Arroyo del"
      }
    },
    {
      "geometry": {
        "type": "Point",
        "coordinates": [
          -4.733333,
          43.133333
        ]
      },
      "type": "Feature",
      "properties": {
        "hierarchy": [
          "tgn:7294772",
          "tgn:7002760",
          "tgn:1000003",
          "tgn:1000095",
          "tgn:7029392"
        ],
        "placetype": [
          "aat:300008347"
        ],
        "id": 7294772,
        "name:xx": "Vallejo"
      }
    },
    {
      "geometry": {
        "type": "Point",
        "coordinates": [
          -4.033333,
          43.133333
        ]
      },
      "type": "Feature",
      "properties": {
        "hierarchy": [
          "tgn:7294773",
          "tgn:7002760",
          "tgn:1000003",
          "tgn:1000095",
          "tgn:7029392"
        ],
        "placetype": [
          "aat:300008347"
        ],
        "id": 7294773,
        "name:xx": "Vallejo"
      }
    },
    {
      "geometry": {
        "type": "Point",
        "coordinates": [
          -3.683333,
          43.05
        ]
      },
      "type": "Feature",
      "properties": {
        "hierarchy": [
          "tgn:7294774",
          "tgn:7002810",
          "tgn:7001158",
          "tgn:1000003",
          "tgn:1000095",
          "tgn:7029392"
        ],
        "placetype": [
          "aat:300008347"
        ],
        "id": 7294774,
        "name:xx": "Vallejo"
      }
    },
    {
      "geometry": {
        "type": "Point",
        "coordinates": [
          -3.716667,
          42.883333
        ]
      },
      "type": "Feature",
      "properties": {
        "hierarchy": [
          "tgn:7294775",
          "tgn:7002810",
          "tgn:7001158",
          "tgn:1000003",
          "tgn:1000095",
          "tgn:7029392"
        ],
        "placetype": [
          "aat:300008347"
        ],
        "id": 7294775,
        "name:xx": "Vallejo"
      }
    },
    {
      "geometry": {
        "type": "Point",
        "coordinates": [
          -5.633333,
          42.4
        ]
      },
      "type": "Feature",
      "properties": {
        "hierarchy": [
          "tgn:7294776",
          "tgn:7002826",
          "tgn:7001158",
          "tgn:1000003",
          "tgn:1000095",
          "tgn:7029392"
        ],
        "placetype": [
          "aat:300008347"
        ],
        "id": 7294776,
        "name:xx": "Vallejo"
      }
    },
    {
      "geometry": {
        "type": "Point",
        "coordinates": [
          -3.183333,
          42.116667
        ]
      },
      "type": "Feature",
      "properties": {
        "hierarchy": [
          "tgn:7294777",
          "tgn:7002810",
          "tgn:7001158",
          "tgn:1000003",
          "tgn:1000095",
          "tgn:7029392"
        ],
        "placetype": [
          "aat:300008347"
        ],
        "id": 7294777,
        "name:xx": "Vallejimeno"
      }
    },
    {
      "geometry": {
        "type": "Point",
        "coordinates": [
          -5.716667,
          40.4
        ]
      },
      "type": "Feature",
      "properties": {
        "hierarchy": [
          "tgn:7294778",
          "tgn:7002835",
          "tgn:7001158",
          "tgn:1000003",
          "tgn:1000095",
          "tgn:7029392"
        ],
        "placetype": [
          "aat:300008347"
        ],
        "id": 7294778,
        "name:xx": "Vallejera de Riofrío"
      }
    },
    {
      "geometry": {
        "type": "Point",
        "coordinates": [
          -5.75,
          36.7
        ]
      },
      "type": "Feature",
      "properties": {
        "hierarchy": [
          "tgn:7294779",
          "tgn:7002813",
          "tgn:7002758",
          "tgn:1000003",
          "tgn:1000095",
          "tgn:7029392"
        ],
        "placetype": [
          "aat:300008347"
        ],
        "id": 7294779,
        "name:xx": "Vallejas"
      }
    }
  ]
}
