{
  "geometry": {
    "type": "Point",
    "coordinates": [
      -176.8667,
      51.75
    ]
  },
  "type": "Feature",
  "properties": {
    "hierarchy": [
      "tgn:2719323",
      "tgn:7030516",
      "tgn:7006450",
      "tgn:1000001",
      "tgn:7012149",
      "tgn:7029392"
    ],
    "placetype": [
      "aat:300132316"
    ],
    "id": 2719323,
    "name:xx": "Three Arm Bay"
  }
}
