{
  "type": "FeatureCollection",
  "features": [
    {
      "geometry": {
        "type": "Point",
        "coordinates": [
          10.133333,
          47.983333
        ]
      },
      "type": "Feature",
      "properties": {
        "hierarchy": [
          "tgn:7104770",
          "tgn:7003669",
          "tgn:1000003",
          "tgn:7000084",
          "tgn:7029392"
        ],
        "placetype": [
          "aat:300008795"
        ],
        "id": 7104770,
        "name:xx": "Schloßberg"
      }
    },
    {
      "geometry": {
        "type": "Point",
        "coordinates": [
          13.65,
          54.533333
        ]
      },
      "type": "Feature",
      "properties": {
        "hierarchy": [
          "tgn:7104771",
          "tgn:1000003",
          "tgn:7000094",
          "tgn:7000084",
          "tgn:7029392"
        ],
        "placetype": [
          "aat:300008777"
        ],
        "id": 7104771,
        "name:xx": "Schloß Berg"
      }
    },
    {
      "geometry": {
        "type": "Point",
        "coordinates": [
          12.816667,
          54.15
        ]
      },
      "type": "Feature",
      "properties": {
        "hierarchy": [
          "tgn:7104772",
          "tgn:1000003",
          "tgn:7000094",
          "tgn:7000084",
          "tgn:7029392"
        ],
        "placetype": [
          "aat:300008777"
        ],
        "id": 7104772,
        "name:xx": "Schloß-Berg"
      }
    },
    {
      "geometry": {
        "type": "Point",
        "coordinates": [
          11.466667,
          53.833333
        ]
      },
      "type": "Feature",
      "properties": {
        "hierarchy": [
          "tgn:7104773",
          "tgn:1000003",
          "tgn:7000094",
          "tgn:7000084",
          "tgn:7029392"
        ],
        "placetype": [
          "aat:300008777"
        ],
        "id": 7104773,
        "name:xx": "Schloß-Berg"
      }
    },
    {
      "geometry": {
        "type": "Point",
        "coordinates": [
          11.383333,
          53.7
        ]
      },
      "type": "Feature",
      "properties": {
        "hierarchy": [
          "tgn:7104774",
          "tgn:1000003",
          "tgn:7000094",
          "tgn:7000084",
          "tgn:7029392"
        ],
        "placetype": [
          "aat:300008777"
        ],
        "id": 7104774,
        "name:xx": "Schloß Berg"
      }
    },
    {
      "geometry": {
        "type": "Point",
        "coordinates": [
          13.916667,
          53.516667
        ]
      },
      "type": "Feature",
      "properties": {
        "hierarchy": [
          "tgn:7104775",
          "tgn:1000003",
          "tgn:7000094",
          "tgn:7000084",
          "tgn:7029392"
        ],
        "placetype": [
          "aat:300008777"
        ],
        "id": 7104775,
        "name:xx": "Schloß-Berg"
      }
    },
    {
      "geometry": {
        "type": "Point",
        "coordinates": [
          12.55,
          52.7
        ]
      },
      "type": "Feature",
      "properties": {
        "hierarchy": [
          "tgn:7104777",
          "tgn:7000096",
          "tgn:1000003",
          "tgn:7000084",
          "tgn:7029392"
        ],
        "placetype": [
          "aat:300008777"
        ],
        "id": 7104777,
        "name:xx": "Schloß-Berg"
      }
    },
    {
      "geometry": {
        "type": "Point",
        "coordinates": [
          13.183333,
          51.983333
        ]
      },
      "type": "Feature",
      "properties": {
        "hierarchy": [
          "tgn:7104778",
          "tgn:7000096",
          "tgn:1000003",
          "tgn:7000084",
          "tgn:7029392"
        ],
        "placetype": [
          "aat:300008777"
        ],
        "id": 7104778,
        "name:xx": "Schloß-Berg"
      }
    },
    {
      "geometry": {
        "type": "Point",
        "coordinates": [
          12.183333,
          51.933333
        ]
      },
      "type": "Feature",
      "properties": {
        "hierarchy": [
          "tgn:7104779",
          "tgn:1000003",
          "tgn:7003687",
          "tgn:7000084",
          "tgn:7029392"
        ],
        "placetype": [
          "aat:300008777"
        ],
        "id": 7104779,
        "name:xx": "Schloß-Berg"
      }
    }
  ]
}
