{
  "geometry": {
    "type": "Point",
    "coordinates": [
      114.85,
      28.9667
    ]
  },
  "type": "Feature",
  "properties": {
    "hierarchy": [
      "tgn:1071711",
      "tgn:1000004",
      "tgn:7002082",
      "tgn:1000111",
      "tgn:7029392"
    ],
    "placetype": [
      "aat:300008347"
    ],
    "id": 1071711,
    "name:xx": "Shimenlou"
  }
}
