{
  "geometry": {
    "type": "Point",
    "coordinates": [
      -97.85,
      32.8833
    ]
  },
  "type": "Feature",
  "properties": {
    "hierarchy": [
      "tgn:2732774",
      "tgn:1000001",
      "tgn:7012149",
      "tgn:1002771",
      "tgn:7007826",
      "tgn:7029392"
    ],
    "placetype": [
      "aat:300008706"
    ],
    "id": 2732774,
    "name:xx": "Turkey Creek"
  }
}
