{
  "geometry": {
    "type": "Point",
    "coordinates": [
      -87.9667,
      42.4167
    ]
  },
  "type": "Feature",
  "properties": {
    "hierarchy": [
      "tgn:2029461",
      "tgn:1000001",
      "tgn:7012149",
      "tgn:7013855",
      "tgn:7007251",
      "tgn:7029392"
    ],
    "placetype": [
      "aat:300008347"
    ],
    "id": 2029461,
    "name:xx": "Old Mill Creek"
  }
}
