{
  "geometry": {
    "type": "Point",
    "coordinates": [
      -78.35,
      40.4833
    ]
  },
  "type": "Feature",
  "properties": {
    "hierarchy": [
      "tgn:2435812",
      "tgn:1000001",
      "tgn:1002185",
      "tgn:7012149",
      "tgn:7007710",
      "tgn:7029392"
    ],
    "placetype": [
      "aat:300008706"
    ],
    "id": 2435812,
    "name:xx": "Kettle Creek"
  }
}
