{
  "geometry": {
    "type": "Point",
    "coordinates": [
      -75.2333,
      44.2333
    ]
  },
  "type": "Feature",
  "properties": {
    "hierarchy": [
      "tgn:2248541",
      "tgn:1000001",
      "tgn:7012149",
      "tgn:7016021",
      "tgn:7007568",
      "tgn:7029392"
    ],
    "placetype": [
      "aat:300008863"
    ],
    "id": 2248541,
    "name:xx": "Cold Spring Brook State Forest"
  }
}
