{
  "geometry": {
    "type": "Point",
    "coordinates": [
      11.2167,
      50.3667
    ]
  },
  "type": "Feature",
  "properties": {
    "hierarchy": [
      "tgn:1040535",
      "tgn:7003669",
      "tgn:1000003",
      "tgn:7000084",
      "tgn:7029392"
    ],
    "placetype": [
      "aat:300008347"
    ],
    "id": 1040535,
    "name:xx": "Nordhalben"
  }
}
