{
  "geometry": {
    "type": "Point",
    "coordinates": [
      -69.75,
      -27.35
    ]
  },
  "type": "Feature",
  "properties": {
    "hierarchy": [
      "tgn:7308153",
      "tgn:1001630",
      "tgn:1000049",
      "tgn:1000002",
      "tgn:7029392"
    ],
    "placetype": [
      "aat:300008697"
    ],
    "id": 7308153,
    "name:xx": "Medio, Agua del"
  }
}
