{
  "geometry": {
    "type": "Point",
    "coordinates": [
      -78.888,
      -2.714
    ]
  },
  "type": "Feature",
  "properties": {
    "hierarchy": [
      "tgn:1024087",
      "tgn:1001170",
      "tgn:7002561",
      "tgn:1000051",
      "tgn:1000002",
      "tgn:7029392"
    ],
    "placetype": [
      "aat:300008347"
    ],
    "id": 1024087,
    "name:xx": "Biblián"
  }
}
