{
  "type": "FeatureCollection",
  "features": [
    {
      "geometry": {
        "type": "Point",
        "coordinates": [
          0,
          52.816667
        ]
      },
      "type": "Feature",
      "properties": {
        "hierarchy": [
          "tgn:7461080",
          "tgn:7002445",
          "tgn:1000003",
          "tgn:7008157",
          "tgn:7008591",
          "tgn:7029392"
        ],
        "placetype": [
          "aat:300008347"
        ],
        "name:en": "Holbeach Clough",
        "id": 7461080
      }
    },
    {
      "geometry": {
        "type": "Point",
        "coordinates": [
          -3.95,
          56.55
        ]
      },
      "type": "Feature",
      "properties": {
        "hierarchy": [
          "tgn:7461082",
          "tgn:7002444",
          "tgn:1000003",
          "tgn:7019152",
          "tgn:7008591",
          "tgn:7029392"
        ],
        "placetype": [
          "aat:300008680"
        ],
        "name:en": "Hoil, Loch",
        "id": 7461082
      }
    },
    {
      "geometry": {
        "type": "Point",
        "coordinates": [
          -1.066667,
          60.3
        ]
      },
      "type": "Feature",
      "properties": {
        "hierarchy": [
          "tgn:7461085",
          "tgn:7002444",
          "tgn:1000003",
          "tgn:7029508",
          "tgn:7008591",
          "tgn:7029392"
        ],
        "placetype": [
          "aat:300008791"
        ],
        "name:en": "Hog Island",
        "id": 7461085
      }
    },
    {
      "geometry": {
        "type": "Point",
        "coordinates": [
          -6.616667,
          56.616667
        ]
      },
      "type": "Feature",
      "properties": {
        "hierarchy": [
          "tgn:7461087",
          "tgn:7019094",
          "tgn:7002444",
          "tgn:1000003",
          "tgn:7008591",
          "tgn:7029392"
        ],
        "placetype": [
          "aat:300132316"
        ],
        "name:en": "Hogh Bay",
        "id": 7461087
      }
    },
    {
      "geometry": {
        "type": "Point",
        "coordinates": [
          -4.166667,
          55.883333
        ]
      },
      "type": "Feature",
      "properties": {
        "hierarchy": [
          "tgn:7461089",
          "tgn:7002444",
          "tgn:1000003",
          "tgn:7019097",
          "tgn:7008591",
          "tgn:7029392"
        ],
        "placetype": [
          "aat:300008347"
        ],
        "name:en": "Hogganfield",
        "id": 7461089
      }
    }
  ]
}
