{
  "type": "FeatureCollection",
  "features": [
    {
      "geometry": {
        "type": "Point",
        "coordinates": [
          -76.4667,
          41.1667
        ]
      },
      "type": "Feature",
      "properties": {
        "hierarchy": [
          "tgn:2277230",
          "tgn:1000001",
          "tgn:1002294",
          "tgn:7012149",
          "tgn:7007710",
          "tgn:7029392"
        ],
        "placetype": [
          "aat:300008798"
        ],
        "id": 2277230,
        "name:xx": "Davis Hill"
      }
    },
    {
      "geometry": {
        "type": "Point",
        "coordinates": [
          -80.5333,
          32.9167
        ]
      },
      "type": "Feature",
      "properties": {
        "hierarchy": [
          "tgn:2277231",
          "tgn:1000001",
          "tgn:2001739",
          "tgn:7012149",
          "tgn:7007712",
          "tgn:7029392"
        ],
        "placetype": [
          "aat:300008347"
        ],
        "id": 2277231,
        "name:xx": "Davis Hill"
      }
    },
    {
      "geometry": {
        "type": "Point",
        "coordinates": [
          -85.0667,
          35.2833
        ]
      },
      "type": "Feature",
      "properties": {
        "hierarchy": [
          "tgn:2277232",
          "tgn:1000001",
          "tgn:7012149",
          "tgn:2001869",
          "tgn:7007825",
          "tgn:7029392"
        ],
        "placetype": [
          "aat:300008798"
        ],
        "id": 2277232,
        "name:xx": "Davis Hill"
      }
    },
    {
      "geometry": {
        "type": "Point",
        "coordinates": [
          -87.9167,
          35.2667
        ]
      },
      "type": "Feature",
      "properties": {
        "hierarchy": [
          "tgn:2277233",
          "tgn:1000001",
          "tgn:7012149",
          "tgn:2001927",
          "tgn:7007825",
          "tgn:7029392"
        ],
        "placetype": [
          "aat:300008798"
        ],
        "id": 2277233,
        "name:xx": "Davis Hill"
      }
    },
    {
      "geometry": {
        "type": "Point",
        "coordinates": [
          -94.8333,
          30.3
        ]
      },
      "type": "Feature",
      "properties": {
        "hierarchy": [
          "tgn:2277234",
          "tgn:1000001",
          "tgn:7012149",
          "tgn:1002595",
          "tgn:7007826",
          "tgn:7029392"
        ],
        "placetype": [
          "aat:300008798"
        ],
        "id": 2277234,
        "name:xx": "Davis Hill"
      }
    },
    {
      "geometry": {
        "type": "Point",
        "coordinates": [
          -97.8333,
          30.1833
        ]
      },
      "type": "Feature",
      "properties": {
        "hierarchy": [
          "tgn:2277235",
          "tgn:1000001",
          "tgn:7012149",
          "tgn:1002952",
          "tgn:7007826",
          "tgn:7029392"
        ],
        "placetype": [
          "aat:300008798"
        ],
        "id": 2277235,
        "name:xx": "Davis Hill"
      }
    },
    {
      "geometry": {
        "type": "Point",
        "coordinates": [
          -111.2833,
          39.9333
        ]
      },
      "type": "Feature",
      "properties": {
        "hierarchy": [
          "tgn:2277236",
          "tgn:1000001",
          "tgn:7012149",
          "tgn:2002125",
          "tgn:7007827",
          "tgn:7029392"
        ],
        "placetype": [
          "aat:300008798"
        ],
        "id": 2277236,
        "name:xx": "Davis Hill"
      }
    },
    {
      "geometry": {
        "type": "Point",
        "coordinates": [
          -72.5333,
          44.6167
        ]
      },
      "type": "Feature",
      "properties": {
        "hierarchy": [
          "tgn:2277237",
          "tgn:1000001",
          "tgn:2002133",
          "tgn:7012149",
          "tgn:7007828",
          "tgn:7029392"
        ],
        "placetype": [
          "aat:300008798"
        ],
        "id": 2277237,
        "name:xx": "Davis Hill"
      }
    },
    {
      "geometry": {
        "type": "Point",
        "coordinates": [
          -122.5833,
          47.0833
        ]
      },
      "type": "Feature",
      "properties": {
        "hierarchy": [
          "tgn:2277238",
          "tgn:1000001",
          "tgn:7012149",
          "tgn:1002785",
          "tgn:7007920",
          "tgn:7029392"
        ],
        "placetype": [
          "aat:300008798"
        ],
        "id": 2277238,
        "name:xx": "Davis Hill"
      }
    },
    {
      "geometry": {
        "type": "Point",
        "coordinates": [
          -122.9667,
          46.75
        ]
      },
      "type": "Feature",
      "properties": {
        "hierarchy": [
          "tgn:2277239",
          "tgn:1000001",
          "tgn:7012149",
          "tgn:1002594",
          "tgn:7007920",
          "tgn:7029392"
        ],
        "placetype": [
          "aat:300008798"
        ],
        "id": 2277239,
        "name:xx": "Davis Hill"
      }
    }
  ]
}
