{
  "geometry": {
    "type": "Point",
    "coordinates": [
      -109.5833,
      34.0333
    ]
  },
  "type": "Feature",
  "properties": {
    "hierarchy": [
      "tgn:2570275",
      "tgn:2000090",
      "tgn:1000001",
      "tgn:7006451",
      "tgn:7012149",
      "tgn:7029392"
    ],
    "placetype": [
      "aat:300006191"
    ],
    "id": 2570275,
    "name:xx": "Pasture Tank"
  }
}
