{
  "type": "FeatureCollection",
  "features": [
    {
      "geometry": {
        "type": "Point",
        "coordinates": [
          26.05,
          35.166667
        ]
      },
      "type": "Feature",
      "properties": {
        "hierarchy": [
          "tgn:5004221",
          "tgn:7002692",
          "tgn:7012056",
          "tgn:1000003",
          "tgn:1000074",
          "tgn:7029392"
        ],
        "placetype": [
          "aat:300008347",
          "aat:300008372"
        ],
        "id": 5004221,
        "name:xx": "Akhládhia"
      }
    },
    {
      "geometry": {
        "type": "Point",
        "coordinates": [
          25.628,
          35.256
        ]
      },
      "type": "Feature",
      "properties": {
        "hierarchy": [
          "tgn:5004223",
          "tgn:7002692",
          "tgn:7012056",
          "tgn:1000003",
          "tgn:1000074",
          "tgn:7029392"
        ],
        "placetype": [
          "aat:300106738",
          "aat:300008347",
          "aat:300000810",
          "aat:300167671"
        ],
        "id": 5004223,
        "name:xx": "Dreros"
      }
    },
    {
      "geometry": {
        "type": "Point",
        "coordinates": [
          26.1,
          35.183333
        ]
      },
      "type": "Feature",
      "properties": {
        "hierarchy": [
          "tgn:5004227",
          "tgn:7002692",
          "tgn:7012056",
          "tgn:1000003",
          "tgn:1000074",
          "tgn:7029392"
        ],
        "placetype": [
          "aat:300008347"
        ],
        "id": 5004227,
        "name:xx": "Piskokephalo"
      }
    }
  ]
}
