{
  "geometry": {
    "type": "Point",
    "coordinates": [
      -148.2167,
      60.3333
    ]
  },
  "type": "Feature",
  "properties": {
    "hierarchy": [
      "tgn:2417106",
      "tgn:7006450",
      "tgn:1000001",
      "tgn:7012149",
      "tgn:2000086",
      "tgn:7029392"
    ],
    "placetype": [
      "aat:300132316"
    ],
    "id": 2417106,
    "name:xx": "Jackpot Bay"
  }
}
