{
  "geometry": {
    "type": "Point",
    "coordinates": [
      -86.4667,
      43.6667
    ]
  },
  "type": "Feature",
  "properties": {
    "hierarchy": [
      "tgn:2740939",
      "tgn:1000001",
      "tgn:7012149",
      "tgn:2000984",
      "tgn:7007520",
      "tgn:7029392"
    ],
    "placetype": [
      "aat:300008680"
    ],
    "id": 2740939,
    "name:xx": "Upper Silver Lake"
  }
}
