{
  "geometry": {
    "type": "Point",
    "coordinates": [
      -85.8667,
      37.9833
    ]
  },
  "type": "Feature",
  "properties": {
    "hierarchy": [
      "tgn:2698248",
      "tgn:1000001",
      "tgn:2000774",
      "tgn:7012149",
      "tgn:7007255",
      "tgn:7029392"
    ],
    "placetype": [
      "aat:300008699"
    ],
    "id": 2698248,
    "name:xx": "Stowers Branch"
  }
}
