{
  "geometry": {
    "type": "Point",
    "coordinates": [
      1.731334,
      42.47095
    ]
  },
  "type": "Feature",
  "properties": {
    "hierarchy": [
      "tgn:7342651",
      "tgn:7008912",
      "tgn:7030216",
      "tgn:1000003",
      "tgn:1000095",
      "tgn:7029392"
    ],
    "placetype": [
      "aat:300266640"
    ],
    "id": 7342651,
    "name:xx": "Can Colomé, Sierra de"
  }
}
