{
  "geometry": {
    "type": "Point",
    "coordinates": [
      9.75,
      49.45
    ]
  },
  "type": "Feature",
  "properties": {
    "hierarchy": [
      "tgn:7158291",
      "tgn:7003692",
      "tgn:1000003",
      "tgn:7000084",
      "tgn:7029392"
    ],
    "placetype": [
      "aat:300132356"
    ],
    "id": 7158291,
    "name:xx": "Höheäcker"
  }
}
