{
  "type": "FeatureCollection",
  "features": [
    {
      "geometry": {
        "type": "Point",
        "coordinates": [
          -95.05,
          39.3667
        ]
      },
      "type": "Feature",
      "properties": {
        "hierarchy": [
          "tgn:2036730",
          "tgn:1000001",
          "tgn:7012149",
          "tgn:2000711",
          "tgn:7007254",
          "tgn:7029392"
        ],
        "placetype": [
          "aat:300008347",
          "aat:300387210"
        ],
        "id": 2036730,
        "name:xx": "Lowemont"
      }
    },
    {
      "geometry": {
        "type": "Point",
        "coordinates": [
          -98.5333,
          39.05
        ]
      },
      "type": "Feature",
      "properties": {
        "hierarchy": [
          "tgn:2036731",
          "tgn:1000001",
          "tgn:7012149",
          "tgn:2000743",
          "tgn:7007254",
          "tgn:7029392"
        ],
        "placetype": [
          "aat:300008347"
        ],
        "id": 2036731,
        "name:xx": "Lucas"
      }
    },
    {
      "geometry": {
        "type": "Point",
        "coordinates": [
          -100.95,
          39.85
        ]
      },
      "type": "Feature",
      "properties": {
        "hierarchy": [
          "tgn:2036732",
          "tgn:1000001",
          "tgn:7012149",
          "tgn:2000736",
          "tgn:7007254",
          "tgn:7029392"
        ],
        "placetype": [
          "aat:300008347"
        ],
        "id": 2036732,
        "name:xx": "Ludell"
      }
    },
    {
      "geometry": {
        "type": "Point",
        "coordinates": [
          -98.6833,
          39.1
        ]
      },
      "type": "Feature",
      "properties": {
        "hierarchy": [
          "tgn:2036733",
          "tgn:1000001",
          "tgn:7012149",
          "tgn:2000743",
          "tgn:7007254",
          "tgn:7029392"
        ],
        "placetype": [
          "aat:300008347"
        ],
        "id": 2036733,
        "name:xx": "Luray"
      }
    },
    {
      "geometry": {
        "type": "Point",
        "coordinates": [
          -101.2833,
          38.2667
        ]
      },
      "type": "Feature",
      "properties": {
        "hierarchy": [
          "tgn:2036734",
          "tgn:1000001",
          "tgn:7012149",
          "tgn:2000761",
          "tgn:7007254",
          "tgn:7029392"
        ],
        "placetype": [
          "aat:300008347",
          "aat:300387210"
        ],
        "id": 2036734,
        "name:xx": "Lydia"
      }
    },
    {
      "geometry": {
        "type": "Point",
        "coordinates": [
          -98.2,
          38.3333
        ]
      },
      "type": "Feature",
      "properties": {
        "hierarchy": [
          "tgn:2036737",
          "tgn:1000001",
          "tgn:7012149",
          "tgn:2000739",
          "tgn:7007254",
          "tgn:7029392"
        ],
        "placetype": [
          "aat:300008347"
        ],
        "id": 2036737,
        "name:xx": "Lyons"
      }
    },
    {
      "geometry": {
        "type": "Point",
        "coordinates": [
          -101.3833,
          39
        ]
      },
      "type": "Feature",
      "properties": {
        "hierarchy": [
          "tgn:2036738",
          "tgn:1000001",
          "tgn:7012149",
          "tgn:2000714",
          "tgn:7007254",
          "tgn:7029392"
        ],
        "placetype": [
          "aat:300387016"
        ],
        "id": 2036738,
        "name:xx": "McAllaster"
      }
    }
  ]
}
