{
  "geometry": {
    "type": "Point",
    "coordinates": [
      -100.35,
      17.45
    ]
  },
  "type": "Feature",
  "properties": {
    "hierarchy": [
      "tgn:7406876",
      "tgn:7005585",
      "tgn:1000001",
      "tgn:7005560",
      "tgn:7029392"
    ],
    "placetype": [
      "aat:300008347"
    ],
    "id": 7406876,
    "name:xx": "Santo Domingo"
  }
}
