{
  "geometry": {
    "type": "Point",
    "coordinates": [
      -77.8833,
      41.3667
    ]
  },
  "type": "Feature",
  "properties": {
    "hierarchy": [
      "tgn:2684386",
      "tgn:1000001",
      "tgn:1002286",
      "tgn:7012149",
      "tgn:7007710",
      "tgn:7029392"
    ],
    "placetype": [
      "aat:300008699"
    ],
    "id": 2684386,
    "name:xx": "Spicewood Run"
  }
}
