{
  "geometry": {
    "type": "Point",
    "coordinates": [
      76.175383,
      30.615226
    ]
  },
  "type": "Feature",
  "properties": {
    "hierarchy": [
      "tgn:7583527",
      "tgn:1000004",
      "tgn:7000198",
      "tgn:7016883",
      "tgn:7029392"
    ],
    "placetype": [
      "aat:300008347"
    ],
    "name:en": "Nawān Kālgarh",
    "id": 7583527
  }
}
