{
  "geometry": {
    "type": "Point",
    "coordinates": [
      -111.3833,
      42.8667
    ]
  },
  "type": "Feature",
  "properties": {
    "hierarchy": [
      "tgn:2607734",
      "tgn:1000001",
      "tgn:2000466",
      "tgn:7012149",
      "tgn:7007250",
      "tgn:7029392"
    ],
    "placetype": [
      "aat:300008761"
    ],
    "id": 2607734,
    "name:xx": "Rasmussen Valley"
  }
}
