{
  "geometry": {
    "type": "Point",
    "coordinates": [
      -78.5667,
      37.5833
    ]
  },
  "type": "Feature",
  "properties": {
    "hierarchy": [
      "tgn:2267140",
      "tgn:1000001",
      "tgn:2002149",
      "tgn:7012149",
      "tgn:7007919",
      "tgn:7029392"
    ],
    "placetype": [
      "aat:300008699"
    ],
    "id": 2267140,
    "name:xx": "Crews Branch"
  }
}
