{
  "geometry": {
    "type": "Point",
    "coordinates": [
      -105.3333,
      36.6667
    ]
  },
  "type": "Feature",
  "properties": {
    "hierarchy": [
      "tgn:2438126",
      "tgn:1000001",
      "tgn:2001432",
      "tgn:7012149",
      "tgn:7007566",
      "tgn:7029392"
    ],
    "placetype": [
      "aat:300000390"
    ],
    "id": 2438126,
    "name:xx": "King Yellow Jacket"
  }
}
