{
  "geometry": {
    "type": "Point",
    "coordinates": [
      73.083333,
      17.833333
    ]
  },
  "type": "Feature",
  "properties": {
    "hierarchy": [
      "tgn:7571231",
      "tgn:1000004",
      "tgn:7000198",
      "tgn:1001895",
      "tgn:7029392"
    ],
    "placetype": [
      "aat:300006909"
    ],
    "name:en": "Janjīra Fort",
    "id": 7571231
  }
}
