{
  "geometry": {
    "type": "Point",
    "coordinates": [
      81.541358,
      26.801272
    ]
  },
  "type": "Feature",
  "properties": {
    "hierarchy": [
      "tgn:7557344",
      "tgn:1000004",
      "tgn:7000198",
      "tgn:7016722",
      "tgn:7029392"
    ],
    "placetype": [
      "aat:300008347"
    ],
    "name:en": "Rāmsanehīghāt",
    "id": 7557344
  }
}
