{
  "geometry": {
    "type": "Point",
    "coordinates": [
      -114.8833,
      35.4667
    ]
  },
  "type": "Feature",
  "properties": {
    "hierarchy": [
      "tgn:2554530",
      "tgn:1000001",
      "tgn:2001410",
      "tgn:7012149",
      "tgn:7007526",
      "tgn:7029392"
    ],
    "placetype": [
      "aat:300000390"
    ],
    "id": 2554530,
    "name:xx": "Oakland Mine"
  }
}
