{
  "geometry": {
    "type": "Point",
    "coordinates": [
      -135.8667,
      -76.05
    ]
  },
  "type": "Feature",
  "properties": {
    "hierarchy": [
      "tgn:1103925",
      "tgn:1000007",
      "tgn:7029392"
    ],
    "placetype": [
      "aat:300008795"
    ],
    "id": 1103925,
    "name:xx": "Berlin, Mount"
  }
}
