{
  "geometry": {
    "type": "Point",
    "coordinates": [
      -131.6667,
      55.8667
    ]
  },
  "type": "Feature",
  "properties": {
    "hierarchy": [
      "tgn:2253275",
      "tgn:7006450",
      "tgn:1000001",
      "tgn:2124076",
      "tgn:7012149",
      "tgn:7029392"
    ],
    "placetype": [
      "aat:300132316"
    ],
    "id": 2253275,
    "name:xx": "Convenient Cove"
  }
}
