{
  "geometry": {
    "type": "Point",
    "coordinates": [
      -115.1167,
      35.35
    ]
  },
  "type": "Feature",
  "properties": {
    "hierarchy": [
      "tgn:2246379",
      "tgn:1000001",
      "tgn:7012149",
      "tgn:7007157",
      "tgn:1002857",
      "tgn:7029392"
    ],
    "placetype": [
      "aat:300008697"
    ],
    "id": 2246379,
    "name:xx": "Coats Spring"
  }
}
