{
  "type": "FeatureCollection",
  "features": [
    {
      "geometry": {
        "type": "Point",
        "coordinates": [
          9.766667,
          48.7
        ]
      },
      "type": "Feature",
      "properties": {
        "hierarchy": [
          "tgn:7154530",
          "tgn:7003692",
          "tgn:1000003",
          "tgn:7000084",
          "tgn:7029392"
        ],
        "placetype": [
          "aat:300000206"
        ],
        "id": 7154530,
        "name:xx": "Kapfhof"
      }
    },
    {
      "geometry": {
        "type": "Point",
        "coordinates": [
          13.2,
          48.966667
        ]
      },
      "type": "Feature",
      "properties": {
        "hierarchy": [
          "tgn:7154531",
          "tgn:7003669",
          "tgn:1000003",
          "tgn:7000084",
          "tgn:7029392"
        ],
        "placetype": [
          "aat:300008347"
        ],
        "id": 7154531,
        "name:xx": "Kapfham"
      }
    },
    {
      "geometry": {
        "type": "Point",
        "coordinates": [
          13.466667,
          48.85
        ]
      },
      "type": "Feature",
      "properties": {
        "hierarchy": [
          "tgn:7154532",
          "tgn:7003669",
          "tgn:1000003",
          "tgn:7000084",
          "tgn:7029392"
        ],
        "placetype": [
          "aat:300008347"
        ],
        "id": 7154532,
        "name:xx": "Kapfham"
      }
    },
    {
      "geometry": {
        "type": "Point",
        "coordinates": [
          13.35,
          48.7
        ]
      },
      "type": "Feature",
      "properties": {
        "hierarchy": [
          "tgn:7154533",
          "tgn:7003669",
          "tgn:1000003",
          "tgn:7000084",
          "tgn:7029392"
        ],
        "placetype": [
          "aat:300008347"
        ],
        "id": 7154533,
        "name:xx": "Kapfham"
      }
    },
    {
      "geometry": {
        "type": "Point",
        "coordinates": [
          13.2,
          48.7
        ]
      },
      "type": "Feature",
      "properties": {
        "hierarchy": [
          "tgn:7154534",
          "tgn:7003669",
          "tgn:1000003",
          "tgn:7000084",
          "tgn:7029392"
        ],
        "placetype": [
          "aat:300008347"
        ],
        "id": 7154534,
        "name:xx": "Kapfham"
      }
    },
    {
      "geometry": {
        "type": "Point",
        "coordinates": [
          13.566667,
          48.583333
        ]
      },
      "type": "Feature",
      "properties": {
        "hierarchy": [
          "tgn:7154535",
          "tgn:7003669",
          "tgn:1000003",
          "tgn:7000084",
          "tgn:7029392"
        ],
        "placetype": [
          "aat:300008347"
        ],
        "id": 7154535,
        "name:xx": "Kapfham"
      }
    },
    {
      "geometry": {
        "type": "Point",
        "coordinates": [
          13.183333,
          48.616667
        ]
      },
      "type": "Feature",
      "properties": {
        "hierarchy": [
          "tgn:7154536",
          "tgn:7003669",
          "tgn:1000003",
          "tgn:7000084",
          "tgn:7029392"
        ],
        "placetype": [
          "aat:300000206"
        ],
        "id": 7154536,
        "name:xx": "Kapfham"
      }
    },
    {
      "geometry": {
        "type": "Point",
        "coordinates": [
          13.4,
          48.383333
        ]
      },
      "type": "Feature",
      "properties": {
        "hierarchy": [
          "tgn:7154537",
          "tgn:7003669",
          "tgn:1000003",
          "tgn:7000084",
          "tgn:7029392"
        ],
        "placetype": [
          "aat:300000206"
        ],
        "id": 7154537,
        "name:xx": "Kapfham"
      }
    },
    {
      "geometry": {
        "type": "Point",
        "coordinates": [
          8.683333,
          48.8
        ]
      },
      "type": "Feature",
      "properties": {
        "hierarchy": [
          "tgn:7154538",
          "tgn:7003692",
          "tgn:1000003",
          "tgn:7000084",
          "tgn:7029392"
        ],
        "placetype": [
          "aat:300008347"
        ],
        "id": 7154538,
        "name:xx": "Kapfenhardt"
      }
    },
    {
      "geometry": {
        "type": "Point",
        "coordinates": [
          10.216667,
          48.866667
        ]
      },
      "type": "Feature",
      "properties": {
        "hierarchy": [
          "tgn:7154539",
          "tgn:7003692",
          "tgn:1000003",
          "tgn:7000084",
          "tgn:7029392"
        ],
        "placetype": [
          "aat:300008347"
        ],
        "id": 7154539,
        "name:xx": "Kapfenburg"
      }
    }
  ]
}
