{
  "geometry": {
    "type": "Point",
    "coordinates": [
      -121.7833,
      46.7833
    ]
  },
  "type": "Feature",
  "properties": {
    "hierarchy": [
      "tgn:2743019",
      "tgn:1000001",
      "tgn:7012149",
      "tgn:1002785",
      "tgn:7007920",
      "tgn:7029392"
    ],
    "placetype": [
      "aat:300008761"
    ],
    "id": 2743019,
    "name:xx": "Van Trump Canyon"
  }
}
