{
  "type": "FeatureCollection",
  "features": [
    {
      "geometry": {
        "type": "Point",
        "coordinates": [
          -84.4333,
          37.1333
        ]
      },
      "type": "Feature",
      "properties": {
        "hierarchy": [
          "tgn:2660940",
          "tgn:1000001",
          "tgn:7012149",
          "tgn:2000839",
          "tgn:7007255",
          "tgn:7029392"
        ],
        "placetype": [
          "aat:300008706"
        ],
        "id": 2660940,
        "name:xx": "Short Creek"
      }
    },
    {
      "geometry": {
        "type": "Point",
        "coordinates": [
          -85.3167,
          37.7
        ]
      },
      "type": "Feature",
      "properties": {
        "hierarchy": [
          "tgn:2660941",
          "tgn:1000001",
          "tgn:7012149",
          "tgn:2000849",
          "tgn:7007255",
          "tgn:7029392"
        ],
        "placetype": [
          "aat:300008706"
        ],
        "id": 2660941,
        "name:xx": "Short Creek"
      }
    },
    {
      "geometry": {
        "type": "Point",
        "coordinates": [
          -84.4667,
          38.6333
        ]
      },
      "type": "Feature",
      "properties": {
        "hierarchy": [
          "tgn:2660942",
          "tgn:1000001",
          "tgn:7012149",
          "tgn:1002778",
          "tgn:7007255",
          "tgn:7029392"
        ],
        "placetype": [
          "aat:300008706"
        ],
        "id": 2660942,
        "name:xx": "Short Creek"
      }
    },
    {
      "geometry": {
        "type": "Point",
        "coordinates": [
          -83.4,
          37.1167
        ]
      },
      "type": "Feature",
      "properties": {
        "hierarchy": [
          "tgn:2660943",
          "tgn:1000001",
          "tgn:7012149",
          "tgn:2000811",
          "tgn:7007255",
          "tgn:7029392"
        ],
        "placetype": [
          "aat:300008706"
        ],
        "id": 2660943,
        "name:xx": "Short Creek"
      }
    },
    {
      "geometry": {
        "type": "Point",
        "coordinates": [
          -86.45,
          37.5167
        ]
      },
      "type": "Feature",
      "properties": {
        "hierarchy": [
          "tgn:2660944",
          "tgn:1000001",
          "tgn:7012149",
          "tgn:2000793",
          "tgn:7007255",
          "tgn:7029392"
        ],
        "placetype": [
          "aat:300008706"
        ],
        "id": 2660944,
        "name:xx": "Short Creek"
      }
    },
    {
      "geometry": {
        "type": "Point",
        "coordinates": [
          -83.7167,
          37.9
        ]
      },
      "type": "Feature",
      "properties": {
        "hierarchy": [
          "tgn:2660945",
          "tgn:1000001",
          "tgn:7012149",
          "tgn:7007255",
          "tgn:7029392"
        ],
        "placetype": [
          "aat:300008706"
        ],
        "id": 2660945,
        "name:xx": "Short Creek"
      }
    },
    {
      "geometry": {
        "type": "Point",
        "coordinates": [
          -85.1167,
          37.95
        ]
      },
      "type": "Feature",
      "properties": {
        "hierarchy": [
          "tgn:2660946",
          "tgn:1002147",
          "tgn:1000001",
          "tgn:7012149",
          "tgn:7007255",
          "tgn:7029392"
        ],
        "placetype": [
          "aat:300008706"
        ],
        "id": 2660946,
        "name:xx": "Short Creek"
      }
    },
    {
      "geometry": {
        "type": "Point",
        "coordinates": [
          -88.95,
          34.8667
        ]
      },
      "type": "Feature",
      "properties": {
        "hierarchy": [
          "tgn:2660947",
          "tgn:1000001",
          "tgn:7012149",
          "tgn:2001155",
          "tgn:7007522",
          "tgn:7029392"
        ],
        "placetype": [
          "aat:300008706"
        ],
        "id": 2660947,
        "name:xx": "Short Creek"
      }
    },
    {
      "geometry": {
        "type": "Point",
        "coordinates": [
          -88.1833,
          34.9167
        ]
      },
      "type": "Feature",
      "properties": {
        "hierarchy": [
          "tgn:2660948",
          "tgn:1000001",
          "tgn:7012149",
          "tgn:2001156",
          "tgn:7007522",
          "tgn:7029392"
        ],
        "placetype": [
          "aat:300008706"
        ],
        "id": 2660948,
        "name:xx": "Short Creek"
      }
    },
    {
      "geometry": {
        "type": "Point",
        "coordinates": [
          -90.3167,
          32.8
        ]
      },
      "type": "Feature",
      "properties": {
        "hierarchy": [
          "tgn:2660949",
          "tgn:1000001",
          "tgn:7012149",
          "tgn:2001167",
          "tgn:7007522",
          "tgn:7029392"
        ],
        "placetype": [
          "aat:300008706"
        ],
        "id": 2660949,
        "name:xx": "Short Creek"
      }
    }
  ]
}
