{
  "geometry": {
    "type": "Point",
    "coordinates": [
      -76.25,
      42.35
    ]
  },
  "type": "Feature",
  "properties": {
    "hierarchy": [
      "tgn:2609258",
      "tgn:1000001",
      "tgn:7012149",
      "tgn:1002950",
      "tgn:7007568",
      "tgn:7029392"
    ],
    "placetype": [
      "aat:300008761"
    ],
    "id": 2609258,
    "name:xx": "Rawson Hollow"
  }
}
