{
  "geometry": {
    "type": "Point",
    "coordinates": [
      -90.5833,
      29.8667
    ]
  },
  "type": "Feature",
  "properties": {
    "hierarchy": [
      "tgn:2152677",
      "tgn:1000001",
      "tgn:7012149",
      "tgn:2000882",
      "tgn:7007256",
      "tgn:7029392"
    ],
    "placetype": [
      "aat:300008347"
    ],
    "id": 2152677,
    "name:xx": "Bayou Boeuf"
  }
}
