{
  "type": "FeatureCollection",
  "features": [
    {
      "geometry": {
        "type": "Point",
        "coordinates": [
          13.5,
          51.5
        ]
      },
      "type": "Feature",
      "properties": {
        "hierarchy": [
          "tgn:7150080",
          "tgn:7000096",
          "tgn:1000003",
          "tgn:7000084",
          "tgn:7029392"
        ],
        "placetype": [
          "aat:300008347"
        ],
        "id": 7150080,
        "name:xx": "Kraupa"
      }
    },
    {
      "geometry": {
        "type": "Point",
        "coordinates": [
          13.283333,
          54.1
        ]
      },
      "type": "Feature",
      "properties": {
        "hierarchy": [
          "tgn:7150081",
          "tgn:1000003",
          "tgn:7000094",
          "tgn:7000084",
          "tgn:7029392"
        ],
        "placetype": [
          "aat:300008347"
        ],
        "id": 7150081,
        "name:xx": "Krauelshorst"
      }
    },
    {
      "geometry": {
        "type": "Point",
        "coordinates": [
          6.15,
          51
        ]
      },
      "type": "Feature",
      "properties": {
        "hierarchy": [
          "tgn:7150082",
          "tgn:1000003",
          "tgn:7003677",
          "tgn:7000084",
          "tgn:7029392"
        ],
        "placetype": [
          "aat:300008347"
        ],
        "id": 7150082,
        "name:xx": "Kraudorf"
      }
    },
    {
      "geometry": {
        "type": "Point",
        "coordinates": [
          9.4,
          47.8
        ]
      },
      "type": "Feature",
      "properties": {
        "hierarchy": [
          "tgn:7150084",
          "tgn:7003692",
          "tgn:1000003",
          "tgn:7000084",
          "tgn:7029392"
        ],
        "placetype": [
          "aat:300000206"
        ],
        "id": 7150084,
        "name:xx": "Krauchen"
      }
    },
    {
      "geometry": {
        "type": "Point",
        "coordinates": [
          9.333333,
          54.533333
        ]
      },
      "type": "Feature",
      "properties": {
        "hierarchy": [
          "tgn:7150085",
          "tgn:1000003",
          "tgn:7003688",
          "tgn:7000084",
          "tgn:7029392"
        ],
        "placetype": [
          "aat:300000206"
        ],
        "id": 7150085,
        "name:xx": "Krau"
      }
    },
    {
      "geometry": {
        "type": "Point",
        "coordinates": [
          10.716667,
          48.8
        ]
      },
      "type": "Feature",
      "properties": {
        "hierarchy": [
          "tgn:7150086",
          "tgn:7003669",
          "tgn:1000003",
          "tgn:7000084",
          "tgn:7029392"
        ],
        "placetype": [
          "aat:300008347"
        ],
        "id": 7150086,
        "name:xx": "Kratzhof"
      }
    },
    {
      "geometry": {
        "type": "Point",
        "coordinates": [
          7.616667,
          50.75
        ]
      },
      "type": "Feature",
      "properties": {
        "hierarchy": [
          "tgn:7150087",
          "tgn:1000003",
          "tgn:7003682",
          "tgn:7000084",
          "tgn:7029392"
        ],
        "placetype": [
          "aat:300000206"
        ],
        "id": 7150087,
        "name:xx": "Kratzhahn"
      }
    },
    {
      "geometry": {
        "type": "Point",
        "coordinates": [
          10.1,
          50.966667
        ]
      },
      "type": "Feature",
      "properties": {
        "hierarchy": [
          "tgn:7150088",
          "tgn:1000003",
          "tgn:7003689",
          "tgn:7000084",
          "tgn:7029392"
        ],
        "placetype": [
          "aat:300000206"
        ],
        "id": 7150088,
        "name:xx": "Vorwerk Kratzeroda"
      }
    },
    {
      "geometry": {
        "type": "Point",
        "coordinates": [
          11.766667,
          48.466667
        ]
      },
      "type": "Feature",
      "properties": {
        "hierarchy": [
          "tgn:7150089",
          "tgn:7003669",
          "tgn:1000003",
          "tgn:7000084",
          "tgn:7029392"
        ],
        "placetype": [
          "aat:300008347"
        ],
        "id": 7150089,
        "name:xx": "Kratzerimbach"
      }
    }
  ]
}
