{
  "geometry": {
    "type": "Point",
    "coordinates": [
      -107.4167,
      45.8667
    ]
  },
  "type": "Feature",
  "properties": {
    "hierarchy": [
      "tgn:2544815",
      "tgn:1000001",
      "tgn:2001261",
      "tgn:7012149",
      "tgn:7007524",
      "tgn:7029392"
    ],
    "placetype": [
      "aat:300008706"
    ],
    "id": 2544815,
    "name:xx": "North Cottonwood Creek"
  }
}
