{
  "type": "FeatureCollection",
  "features": [
    {
      "geometry": {
        "type": "Point",
        "coordinates": [
          -104.6333,
          35.5333
        ]
      },
      "type": "Feature",
      "properties": {
        "hierarchy": [
          "tgn:2271180",
          "tgn:1000001",
          "tgn:7012149",
          "tgn:2001453",
          "tgn:7007566",
          "tgn:7029392"
        ],
        "placetype": [
          "aat:300008761"
        ],
        "id": 2271180,
        "name:xx": "Cuevas, Cañon"
      }
    },
    {
      "geometry": {
        "type": "Point",
        "coordinates": [
          -104.9167,
          35.4667
        ]
      },
      "type": "Feature",
      "properties": {
        "hierarchy": [
          "tgn:2271181",
          "tgn:1000001",
          "tgn:7012149",
          "tgn:2001453",
          "tgn:7007566",
          "tgn:7029392"
        ],
        "placetype": [
          "aat:300008761"
        ],
        "id": 2271181,
        "name:xx": "Cuevas, Cañon de las"
      }
    },
    {
      "geometry": {
        "type": "Point",
        "coordinates": [
          -104.45,
          35.9333
        ]
      },
      "type": "Feature",
      "properties": {
        "hierarchy": [
          "tgn:2271182",
          "tgn:1000001",
          "tgn:7012149",
          "tgn:2001446",
          "tgn:7007566",
          "tgn:7029392"
        ],
        "placetype": [
          "aat:300008761"
        ],
        "id": 2271182,
        "name:xx": "Cuevas, Cañon las"
      }
    },
    {
      "geometry": {
        "type": "Point",
        "coordinates": [
          -100.2167,
          28.5333
        ]
      },
      "type": "Feature",
      "properties": {
        "hierarchy": [
          "tgn:2271183",
          "tgn:1000001",
          "tgn:7012149",
          "tgn:2002038",
          "tgn:7007826",
          "tgn:7029392"
        ],
        "placetype": [
          "aat:300008706"
        ],
        "id": 2271183,
        "name:xx": "Cuevas Creek"
      }
    },
    {
      "geometry": {
        "type": "Point",
        "coordinates": [
          -98.85,
          26.8167
        ]
      },
      "type": "Feature",
      "properties": {
        "hierarchy": [
          "tgn:2271184",
          "tgn:1000001",
          "tgn:7012149",
          "tgn:2002012",
          "tgn:7007826",
          "tgn:7029392"
        ],
        "placetype": [
          "aat:300008347"
        ],
        "id": 2271184,
        "name:xx": "Cuevitas"
      }
    },
    {
      "geometry": {
        "type": "Point",
        "coordinates": [
          -98.5667,
          26.25
        ]
      },
      "type": "Feature",
      "properties": {
        "hierarchy": [
          "tgn:2271185",
          "tgn:1000001",
          "tgn:7012149",
          "tgn:2002002",
          "tgn:7007826",
          "tgn:7029392"
        ],
        "placetype": [
          "aat:300008347"
        ],
        "id": 2271185,
        "name:xx": "Cuevitas"
      }
    },
    {
      "geometry": {
        "type": "Point",
        "coordinates": [
          -104.5167,
          35.8833
        ]
      },
      "type": "Feature",
      "properties": {
        "hierarchy": [
          "tgn:2271186",
          "tgn:1000001",
          "tgn:7012149",
          "tgn:2001446",
          "tgn:7007566",
          "tgn:7029392"
        ],
        "placetype": [
          "aat:300008761"
        ],
        "id": 2271186,
        "name:xx": "Cuevitas, Cañon"
      }
    },
    {
      "geometry": {
        "type": "Point",
        "coordinates": [
          -104.45,
          35.9667
        ]
      },
      "type": "Feature",
      "properties": {
        "hierarchy": [
          "tgn:2271187",
          "tgn:1000001",
          "tgn:7012149",
          "tgn:2001446",
          "tgn:7007566",
          "tgn:7029392"
        ],
        "placetype": [
          "aat:300008761"
        ],
        "id": 2271187,
        "name:xx": "Cuevitas, Cañon las"
      }
    },
    {
      "geometry": {
        "type": "Point",
        "coordinates": [
          -107.0333,
          35.7167
        ]
      },
      "type": "Feature",
      "properties": {
        "hierarchy": [
          "tgn:2271188",
          "tgn:1000001",
          "tgn:7012149",
          "tgn:2001451",
          "tgn:7007566",
          "tgn:7029392"
        ],
        "placetype": [
          "aat:300008699"
        ],
        "id": 2271188,
        "name:xx": "Cuevitas, Arroyo"
      }
    },
    {
      "geometry": {
        "type": "Point",
        "coordinates": [
          -105.4333,
          32.75
        ]
      },
      "type": "Feature",
      "properties": {
        "hierarchy": [
          "tgn:2271189",
          "tgn:1000001",
          "tgn:7012149",
          "tgn:7007566",
          "tgn:7029392"
        ],
        "placetype": [
          "aat:300008761"
        ],
        "id": 2271189,
        "name:xx": "Cuevo Canyon"
      }
    }
  ]
}
