{
  "type": "FeatureCollection",
  "features": [
    {
      "geometry": {
        "type": "Point",
        "coordinates": [
          -2.033333,
          52.7
        ]
      },
      "type": "Feature",
      "properties": {
        "hierarchy": [
          "tgn:7463343",
          "tgn:7002445",
          "tgn:1000003",
          "tgn:7008174",
          "tgn:7008591",
          "tgn:7029392"
        ],
        "placetype": [
          "aat:300008347"
        ],
        "name:en": "Huntington",
        "id": 7463343
      }
    },
    {
      "geometry": {
        "type": "Point",
        "coordinates": [
          1.45,
          52.316667
        ]
      },
      "type": "Feature",
      "properties": {
        "hierarchy": [
          "tgn:7463345",
          "tgn:7002445",
          "tgn:1000003",
          "tgn:7008185",
          "tgn:7008591",
          "tgn:7029392"
        ],
        "placetype": [
          "aat:300008347"
        ],
        "name:en": "Huntingfield",
        "id": 7463345
      }
    },
    {
      "geometry": {
        "type": "Point",
        "coordinates": [
          -0.166667,
          52.333333
        ]
      },
      "type": "Feature",
      "properties": {
        "hierarchy": [
          "tgn:7463348",
          "tgn:7002445",
          "tgn:7011980",
          "tgn:1000003",
          "tgn:7008591",
          "tgn:7029392"
        ],
        "placetype": [
          "aat:300000745"
        ],
        "name:en": "Huntingdon and Peterborough",
        "id": 7463348
      }
    }
  ]
}
