{
  "geometry": {
    "type": "Point",
    "coordinates": [
      -70.7333,
      41.7667
    ]
  },
  "type": "Feature",
  "properties": {
    "hierarchy": [
      "tgn:2449591",
      "tgn:1000001",
      "tgn:7014423",
      "tgn:7012149",
      "tgn:7007517",
      "tgn:7029392"
    ],
    "placetype": [
      "aat:300008798"
    ],
    "id": 2449591,
    "name:xx": "Lincoln Hill"
  }
}
