{
  "type": "FeatureCollection",
  "features": [
    {
      "geometry": {
        "type": "Point",
        "coordinates": [
          -113.2333,
          45.3167
        ]
      },
      "type": "Feature",
      "properties": {
        "hierarchy": [
          "tgn:2223110",
          "tgn:1000001",
          "tgn:2001260",
          "tgn:7012149",
          "tgn:7007524",
          "tgn:7029392"
        ],
        "placetype": [
          "aat:300008798"
        ],
        "id": 2223110,
        "name:xx": "Carroll Hill"
      }
    },
    {
      "geometry": {
        "type": "Point",
        "coordinates": [
          -75.2833,
          42.1833
        ]
      },
      "type": "Feature",
      "properties": {
        "hierarchy": [
          "tgn:2223111",
          "tgn:1000001",
          "tgn:1002328",
          "tgn:7012149",
          "tgn:7007568",
          "tgn:7029392"
        ],
        "placetype": [
          "aat:300008798"
        ],
        "id": 2223111,
        "name:xx": "Carroll Hill"
      }
    },
    {
      "geometry": {
        "type": "Point",
        "coordinates": [
          -78.8333,
          42.2667
        ]
      },
      "type": "Feature",
      "properties": {
        "hierarchy": [
          "tgn:2223112",
          "tgn:1000001",
          "tgn:1002245",
          "tgn:7012149",
          "tgn:7007568",
          "tgn:7029392"
        ],
        "placetype": [
          "aat:300008798"
        ],
        "id": 2223112,
        "name:xx": "Carroll Hill"
      }
    },
    {
      "geometry": {
        "type": "Point",
        "coordinates": [
          -80.4167,
          37.9
        ]
      },
      "type": "Feature",
      "properties": {
        "hierarchy": [
          "tgn:2223113",
          "tgn:1000001",
          "tgn:7012149",
          "tgn:2002264",
          "tgn:7013961",
          "tgn:7029392"
        ],
        "placetype": [
          "aat:300008798"
        ],
        "id": 2223113,
        "name:xx": "Carroll Hill"
      }
    },
    {
      "geometry": {
        "type": "Point",
        "coordinates": [
          -75.3,
          42.2
        ]
      },
      "type": "Feature",
      "properties": {
        "hierarchy": [
          "tgn:2223114",
          "tgn:1000001",
          "tgn:1002328",
          "tgn:7012149",
          "tgn:7007568",
          "tgn:7029392"
        ],
        "placetype": [
          "aat:300008761"
        ],
        "id": 2223114,
        "name:xx": "Carroll Hollow"
      }
    },
    {
      "geometry": {
        "type": "Point",
        "coordinates": [
          -87.8833,
          35.05
        ]
      },
      "type": "Feature",
      "properties": {
        "hierarchy": [
          "tgn:2223115",
          "tgn:1000001",
          "tgn:7012149",
          "tgn:2001927",
          "tgn:7007825",
          "tgn:7029392"
        ],
        "placetype": [
          "aat:300008761"
        ],
        "id": 2223115,
        "name:xx": "Carroll Hollow"
      }
    },
    {
      "geometry": {
        "type": "Point",
        "coordinates": [
          -87.8833,
          35.9333
        ]
      },
      "type": "Feature",
      "properties": {
        "hierarchy": [
          "tgn:2223116",
          "tgn:1000001",
          "tgn:7012149",
          "tgn:2001879",
          "tgn:7007825",
          "tgn:7029392"
        ],
        "placetype": [
          "aat:300008761"
        ],
        "id": 2223116,
        "name:xx": "Carroll Hollow"
      }
    },
    {
      "geometry": {
        "type": "Point",
        "coordinates": [
          -84.15,
          36.1
        ]
      },
      "type": "Feature",
      "properties": {
        "hierarchy": [
          "tgn:2223117",
          "tgn:2001837",
          "tgn:1000001",
          "tgn:7012149",
          "tgn:7007825",
          "tgn:7029392"
        ],
        "placetype": [
          "aat:300008761"
        ],
        "id": 2223117,
        "name:xx": "Carroll Hollow"
      }
    },
    {
      "geometry": {
        "type": "Point",
        "coordinates": [
          -87.6667,
          36.2333
        ]
      },
      "type": "Feature",
      "properties": {
        "hierarchy": [
          "tgn:2223118",
          "tgn:1000001",
          "tgn:7012149",
          "tgn:2001878",
          "tgn:7007825",
          "tgn:7029392"
        ],
        "placetype": [
          "aat:300008761"
        ],
        "id": 2223118,
        "name:xx": "Carroll Hollow"
      }
    },
    {
      "geometry": {
        "type": "Point",
        "coordinates": [
          -86.2,
          35.3833
        ]
      },
      "type": "Feature",
      "properties": {
        "hierarchy": [
          "tgn:2223119",
          "tgn:1000001",
          "tgn:7012149",
          "tgn:2001852",
          "tgn:7007825",
          "tgn:7029392"
        ],
        "placetype": [
          "aat:300008761"
        ],
        "id": 2223119,
        "name:xx": "Carroll Hollow"
      }
    }
  ]
}
