{
  "geometry": {
    "type": "Point",
    "coordinates": [
      31.816667,
      26.566667
    ]
  },
  "type": "Feature",
  "properties": {
    "hierarchy": [
      "tgn:7527476",
      "tgn:7001242",
      "tgn:7001311",
      "tgn:7016833",
      "tgn:7029392"
    ],
    "placetype": [
      "aat:300005926"
    ],
    "name:en": "S카d카 Ab큰 Jilb훮nah",
    "id": 7527476
  }
}
