{
  "geometry": {
    "type": "Point",
    "coordinates": [
      -106.6667,
      37.9167
    ]
  },
  "type": "Feature",
  "properties": {
    "hierarchy": [
      "tgn:2667983",
      "tgn:1000001",
      "tgn:7012149",
      "tgn:7007158",
      "tgn:2000246",
      "tgn:7029392"
    ],
    "placetype": [
      "aat:300000390"
    ],
    "id": 2667983,
    "name:xx": "Sky City Mine"
  }
}
