{
  "geometry": {
    "type": "Point",
    "coordinates": [
      14.45,
      14.3333
    ]
  },
  "type": "Feature",
  "properties": {
    "hierarchy": [
      "tgn:1088572",
      "tgn:7001242",
      "tgn:1000995",
      "tgn:1000156",
      "tgn:7029392"
    ],
    "placetype": [
      "aat:300008347"
    ],
    "id": 1088572,
    "name:xx": "Rig-Rig"
  }
}
