{
  "geometry": {
    "type": "Point",
    "coordinates": [
      -103.3333,
      37.4333
    ]
  },
  "type": "Feature",
  "properties": {
    "hierarchy": [
      "tgn:2288051",
      "tgn:1000001",
      "tgn:7012149",
      "tgn:2000227",
      "tgn:7007158",
      "tgn:7029392"
    ],
    "placetype": [
      "aat:300008699"
    ],
    "id": 2288051,
    "name:xx": "Dinner Branch"
  }
}
