{
  "geometry": {
    "type": "Point",
    "coordinates": [
      79.7795,
      27.1314
    ]
  },
  "type": "Feature",
  "properties": {
    "hierarchy": [
      "tgn:7562577",
      "tgn:1000004",
      "tgn:7000198",
      "tgn:7016722",
      "tgn:7029392"
    ],
    "placetype": [
      "aat:300008347"
    ],
    "name:en": "Chhabile Purwa",
    "id": 7562577
  }
}
