{
  "geometry": {
    "type": "Point",
    "coordinates": [
      -106.95,
      43.8667
    ]
  },
  "type": "Feature",
  "properties": {
    "hierarchy": [
      "tgn:2673707",
      "tgn:1000001",
      "tgn:7012149",
      "tgn:2002374",
      "tgn:7007923",
      "tgn:7029392"
    ],
    "placetype": [
      "aat:300266640"
    ],
    "id": 2673707,
    "name:xx": "Snow Cave Ridge"
  }
}
