{
  "type": "FeatureCollection",
  "features": [
    {
      "geometry": {
        "type": "Point",
        "coordinates": [
          75.2833,
          40.6333
        ]
      },
      "type": "Feature",
      "properties": {
        "hierarchy": [
          "tgn:1115321",
          "tgn:1000004",
          "tgn:1003394",
          "tgn:7006655",
          "tgn:7029392"
        ],
        "placetype": [
          "aat:300008680"
        ],
        "id": 1115321,
        "name:xx": "Chatyr-Kël', Ozero"
      }
    },
    {
      "geometry": {
        "type": "Point",
        "coordinates": [
          27.9333,
          52.3833
        ]
      },
      "type": "Feature",
      "properties": {
        "hierarchy": [
          "tgn:1115322",
          "tgn:7012187",
          "tgn:1000003",
          "tgn:7006657",
          "tgn:7029392"
        ],
        "placetype": [
          "aat:300008680"
        ],
        "id": 1115322,
        "name:xx": "Chervonnoye, Ozero"
      }
    },
    {
      "geometry": {
        "type": "Point",
        "coordinates": [
          140.1,
          53.4167
        ]
      },
      "type": "Feature",
      "properties": {
        "hierarchy": [
          "tgn:1115323",
          "tgn:1000004",
          "tgn:7014474",
          "tgn:7018214",
          "tgn:7002435",
          "tgn:7029392"
        ],
        "placetype": [
          "aat:300008680"
        ],
        "id": 1115323,
        "name:xx": "Chlya Ozero"
      }
    },
    {
      "geometry": {
        "type": "Point",
        "coordinates": [
          42.5833,
          58.7667
        ]
      },
      "type": "Feature",
      "properties": {
        "hierarchy": [
          "tgn:1115324",
          "tgn:1000004",
          "tgn:4005827",
          "tgn:7018214",
          "tgn:7002435",
          "tgn:7029392"
        ],
        "placetype": [
          "aat:300008680"
        ],
        "id": 1115324,
        "name:xx": "Chukhlomskoye, Ozero"
      }
    },
    {
      "geometry": {
        "type": "Point",
        "coordinates": [
          136.6,
          52
        ]
      },
      "type": "Feature",
      "properties": {
        "hierarchy": [
          "tgn:1115326",
          "tgn:1000004",
          "tgn:7014474",
          "tgn:7018214",
          "tgn:7002435",
          "tgn:7029392"
        ],
        "placetype": [
          "aat:300008680"
        ],
        "id": 1115326,
        "name:xx": "Chukchagirskoye, Ozero"
      }
    },
    {
      "geometry": {
        "type": "Point",
        "coordinates": [
          69.8333,
          54.1667
        ]
      },
      "type": "Feature",
      "properties": {
        "hierarchy": [
          "tgn:1115328",
          "tgn:1000004",
          "tgn:7014786",
          "tgn:7029392"
        ],
        "placetype": [
          "aat:300008680"
        ],
        "id": 1115328,
        "name:xx": "Shaglyteniz, Ozero"
      }
    }
  ]
}
