{
  "geometry": {
    "type": "Point",
    "coordinates": [
      15.75,
      50.9167
    ]
  },
  "type": "Feature",
  "properties": {
    "hierarchy": [
      "tgn:1049105",
      "tgn:7024123",
      "tgn:1000003",
      "tgn:7006366",
      "tgn:7029392"
    ],
    "placetype": [
      "aat:300008347",
      "aat:300008389",
      "aat:300387223",
      "aat:300387302"
    ],
    "id": 1049105,
    "name:xx": "Jelenia Góra"
  }
}
