{
  "geometry": {
    "type": "Point",
    "coordinates": [
      -81.4833,
      30.3667
    ]
  },
  "type": "Feature",
  "properties": {
    "hierarchy": [
      "tgn:2529133",
      "tgn:1000001",
      "tgn:2000264",
      "tgn:7012149",
      "tgn:7007240",
      "tgn:7029392"
    ],
    "placetype": [
      "aat:300008706"
    ],
    "id": 2529133,
    "name:xx": "Mud Flats Creek"
  }
}
