{
  "geometry": {
    "type": "Point",
    "coordinates": [
      -160.1833,
      61.8833
    ]
  },
  "type": "Feature",
  "properties": {
    "hierarchy": [
      "tgn:2710015",
      "tgn:7006450",
      "tgn:1000001",
      "tgn:7012149",
      "tgn:2000087",
      "tgn:7029392"
    ],
    "placetype": [
      "aat:300008707"
    ],
    "id": 2710015,
    "name:xx": "Talbiksok River"
  }
}
