{
  "geometry": {
    "type": "Point",
    "coordinates": [
      123.8667,
      13.3167
    ]
  },
  "type": "Feature",
  "properties": {
    "hierarchy": [
      "tgn:1006676",
      "tgn:1001094",
      "tgn:1000004",
      "tgn:1000135",
      "tgn:7029392"
    ],
    "placetype": [
      "aat:300008791"
    ],
    "id": 1006676,
    "name:xx": "Cagraray Island"
  }
}
