{
  "geometry": {
    "type": "Point",
    "coordinates": [
      24.983333,
      41.35
    ]
  },
  "type": "Feature",
  "properties": {
    "hierarchy": [
      "tgn:7227833",
      "tgn:7011170",
      "tgn:7002715",
      "tgn:1000003",
      "tgn:1000074",
      "tgn:7029392"
    ],
    "placetype": [
      "aat:300008699"
    ],
    "id": 7227833,
    "name:xx": "Lítza Réma"
  }
}
