{
  "geometry": {
    "type": "Point",
    "coordinates": [
      -15.1833,
      15.3667
    ]
  },
  "type": "Feature",
  "properties": {
    "hierarchy": [
      "tgn:1092521",
      "tgn:7001242",
      "tgn:1001700",
      "tgn:1000189",
      "tgn:7029392"
    ],
    "placetype": [
      "aat:300008347"
    ],
    "id": 1092521,
    "name:xx": "Linguère"
  }
}
