{
  "geometry": {
    "type": "Point",
    "coordinates": [
      -39.75,
      -7.2333
    ]
  },
  "type": "Feature",
  "properties": {
    "hierarchy": [
      "tgn:1023001",
      "tgn:7006064",
      "tgn:1000047",
      "tgn:7002455",
      "tgn:1000002",
      "tgn:7029392"
    ],
    "placetype": [
      "aat:300008347"
    ],
    "id": 1023001,
    "name:xx": "Santana do Cariri"
  }
}
