{
  "geometry": {
    "type": "Point",
    "coordinates": [
      72.916667,
      22.15
    ]
  },
  "type": "Feature",
  "properties": {
    "hierarchy": [
      "tgn:7574714",
      "tgn:1000004",
      "tgn:1001869",
      "tgn:7000198",
      "tgn:7029392"
    ],
    "placetype": [
      "aat:300008347"
    ],
    "name:en": "Kurāl",
    "id": 7574714
  }
}
