{
  "geometry": {
    "type": "Point",
    "coordinates": [
      -72.1167,
      9.05
    ]
  },
  "type": "Feature",
  "properties": {
    "hierarchy": [
      "tgn:1130648",
      "tgn:1000002",
      "tgn:7029392"
    ],
    "placetype": [
      "aat:300008707"
    ],
    "id": 1130648,
    "name:xx": "Tarra"
  }
}
