{
  "geometry": {
    "type": "Point",
    "coordinates": [
      -100.2167,
      46.2667
    ]
  },
  "type": "Feature",
  "properties": {
    "hierarchy": [
      "tgn:2077789",
      "tgn:1000001",
      "tgn:2001571",
      "tgn:7012149",
      "tgn:7007705",
      "tgn:7029392"
    ],
    "placetype": [
      "aat:300008347"
    ],
    "id": 2077789,
    "name:xx": "Linton"
  }
}
