{
  "type": "FeatureCollection",
  "features": [
    {
      "geometry": {
        "type": "Point",
        "coordinates": [
          -84.05,
          31.65
        ]
      },
      "type": "Feature",
      "properties": {
        "hierarchy": [
          "tgn:2350170",
          "tgn:1000001",
          "tgn:7012149",
          "tgn:2000379",
          "tgn:7007248",
          "tgn:7029392"
        ],
        "placetype": [
          "aat:300008699"
        ],
        "id": 2350170,
        "name:xx": "Gin Branch"
      }
    },
    {
      "geometry": {
        "type": "Point",
        "coordinates": [
          -93.2333,
          31.5
        ]
      },
      "type": "Feature",
      "properties": {
        "hierarchy": [
          "tgn:2350171",
          "tgn:1000001",
          "tgn:7012149",
          "tgn:7007256",
          "tgn:7029392"
        ],
        "placetype": [
          "aat:300008699"
        ],
        "id": 2350171,
        "name:xx": "Gin Branch"
      }
    },
    {
      "geometry": {
        "type": "Point",
        "coordinates": [
          -90.8833,
          31.65
        ]
      },
      "type": "Feature",
      "properties": {
        "hierarchy": [
          "tgn:2350172",
          "tgn:1000001",
          "tgn:7012149",
          "tgn:2001117",
          "tgn:7007522",
          "tgn:7029392"
        ],
        "placetype": [
          "aat:300008699"
        ],
        "id": 2350172,
        "name:xx": "Gin Branch"
      }
    },
    {
      "geometry": {
        "type": "Point",
        "coordinates": [
          -89.4667,
          31.6
        ]
      },
      "type": "Feature",
      "properties": {
        "hierarchy": [
          "tgn:2350173",
          "tgn:1000001",
          "tgn:2001101",
          "tgn:7012149",
          "tgn:7007522",
          "tgn:7029392"
        ],
        "placetype": [
          "aat:300008699"
        ],
        "id": 2350173,
        "name:xx": "Gin Branch"
      }
    },
    {
      "geometry": {
        "type": "Point",
        "coordinates": [
          -79.1167,
          34.4667
        ]
      },
      "type": "Feature",
      "properties": {
        "hierarchy": [
          "tgn:2350174",
          "tgn:1000001",
          "tgn:7012149",
          "tgn:2001534",
          "tgn:7007709",
          "tgn:7029392"
        ],
        "placetype": [
          "aat:300008699"
        ],
        "id": 2350174,
        "name:xx": "Gin Branch"
      }
    },
    {
      "geometry": {
        "type": "Point",
        "coordinates": [
          -80.7167,
          33.5167
        ]
      },
      "type": "Feature",
      "properties": {
        "hierarchy": [
          "tgn:2350175",
          "tgn:1000001",
          "tgn:7012149",
          "tgn:7007712",
          "tgn:7029392"
        ],
        "placetype": [
          "aat:300008699"
        ],
        "id": 2350175,
        "name:xx": "Gin Branch"
      }
    },
    {
      "geometry": {
        "type": "Point",
        "coordinates": [
          -81.3167,
          35.1
        ]
      },
      "type": "Feature",
      "properties": {
        "hierarchy": [
          "tgn:2350176",
          "tgn:1000001",
          "tgn:7012149",
          "tgn:2001770",
          "tgn:7007712",
          "tgn:7029392"
        ],
        "placetype": [
          "aat:300008699"
        ],
        "id": 2350176,
        "name:xx": "Gin Branch"
      }
    },
    {
      "geometry": {
        "type": "Point",
        "coordinates": [
          -81.2333,
          33.5833
        ]
      },
      "type": "Feature",
      "properties": {
        "hierarchy": [
          "tgn:2350177",
          "tgn:1000001",
          "tgn:7012149",
          "tgn:2001762",
          "tgn:7007712",
          "tgn:7029392"
        ],
        "placetype": [
          "aat:300008699"
        ],
        "id": 2350177,
        "name:xx": "Gin Branch"
      }
    },
    {
      "geometry": {
        "type": "Point",
        "coordinates": [
          -80.2833,
          34.2
        ]
      },
      "type": "Feature",
      "properties": {
        "hierarchy": [
          "tgn:2350178",
          "tgn:1000001",
          "tgn:7012149",
          "tgn:2001755",
          "tgn:7007712",
          "tgn:7029392"
        ],
        "placetype": [
          "aat:300008699"
        ],
        "id": 2350178,
        "name:xx": "Gin Branch"
      }
    },
    {
      "geometry": {
        "type": "Point",
        "coordinates": [
          -87.2667,
          35.6667
        ]
      },
      "type": "Feature",
      "properties": {
        "hierarchy": [
          "tgn:2350179",
          "tgn:1000001",
          "tgn:7012149",
          "tgn:7007825",
          "tgn:7029392"
        ],
        "placetype": [
          "aat:300008699"
        ],
        "id": 2350179,
        "name:xx": "Gin Branch"
      }
    }
  ]
}
