{
  "geometry": {
    "type": "Point",
    "coordinates": [
      -99.733333,
      17.35
    ]
  },
  "type": "Feature",
  "properties": {
    "hierarchy": [
      "tgn:7406111",
      "tgn:7005585",
      "tgn:1000001",
      "tgn:7005560",
      "tgn:7029392"
    ],
    "placetype": [
      "aat:300008699"
    ],
    "id": 7406111,
    "name:xx": "Papagayo, Río"
  }
}
