{
  "geometry": {
    "type": "Point",
    "coordinates": [
      -80.9667,
      39.8667
    ]
  },
  "type": "Feature",
  "properties": {
    "hierarchy": [
      "tgn:2600514",
      "tgn:1002175",
      "tgn:1000001",
      "tgn:7012149",
      "tgn:7007706",
      "tgn:7029392"
    ],
    "placetype": [
      "aat:300266640"
    ],
    "id": 2600514,
    "name:xx": "Pugh Ridge"
  }
}
