{
  "geometry": {
    "type": "Point",
    "coordinates": [
      35.7167,
      32.0333
    ]
  },
  "type": "Feature",
  "properties": {
    "hierarchy": [
      "tgn:1081875",
      "tgn:1002057",
      "tgn:1000004",
      "tgn:1000121",
      "tgn:7029392"
    ],
    "placetype": [
      "aat:300008347",
      "aat:300387220",
      "aat:300008375"
    ],
    "id": 1081875,
    "name:xx": "As-Salṭ"
  }
}
