{
  "geometry": {
    "type": "Point",
    "coordinates": [
      -93.1667,
      38.1333
    ]
  },
  "type": "Feature",
  "properties": {
    "hierarchy": [
      "tgn:2058644",
      "tgn:1000001",
      "tgn:2001173",
      "tgn:7012149",
      "tgn:7007523",
      "tgn:7029392"
    ],
    "placetype": [
      "aat:300008347"
    ],
    "id": 2058644,
    "name:xx": "Edwards"
  }
}
