{
  "type": "FeatureCollection",
  "features": [
    {
      "geometry": {
        "type": "Point",
        "coordinates": [
          10.366667,
          50.5
        ]
      },
      "type": "Feature",
      "properties": {
        "hierarchy": [
          "tgn:7104970",
          "tgn:1000003",
          "tgn:7003689",
          "tgn:7000084",
          "tgn:7029392"
        ],
        "placetype": [
          "aat:300008777"
        ],
        "id": 7104970,
        "name:xx": "Schloß-Berg"
      }
    },
    {
      "geometry": {
        "type": "Point",
        "coordinates": [
          10.116667,
          50.483333
        ]
      },
      "type": "Feature",
      "properties": {
        "hierarchy": [
          "tgn:7104971",
          "tgn:7003669",
          "tgn:1000003",
          "tgn:7000084",
          "tgn:7029392"
        ],
        "placetype": [
          "aat:300008777"
        ],
        "id": 7104971,
        "name:xx": "Schloßberg"
      }
    },
    {
      "geometry": {
        "type": "Point",
        "coordinates": [
          10.233333,
          50.466667
        ]
      },
      "type": "Feature",
      "properties": {
        "hierarchy": [
          "tgn:7104972",
          "tgn:7003669",
          "tgn:1000003",
          "tgn:7000084",
          "tgn:7029392"
        ],
        "placetype": [
          "aat:300008777"
        ],
        "id": 7104972,
        "name:xx": "Schloß-Berg"
      }
    },
    {
      "geometry": {
        "type": "Point",
        "coordinates": [
          11.716667,
          49.983333
        ]
      },
      "type": "Feature",
      "properties": {
        "hierarchy": [
          "tgn:7104973",
          "tgn:7003669",
          "tgn:1000003",
          "tgn:7000084",
          "tgn:7029392"
        ],
        "placetype": [
          "aat:300008777"
        ],
        "id": 7104973,
        "name:xx": "Schloßberg"
      }
    },
    {
      "geometry": {
        "type": "Point",
        "coordinates": [
          11.016667,
          49.883333
        ]
      },
      "type": "Feature",
      "properties": {
        "hierarchy": [
          "tgn:7104974",
          "tgn:7003669",
          "tgn:1000003",
          "tgn:7000084",
          "tgn:7029392"
        ],
        "placetype": [
          "aat:300008777"
        ],
        "id": 7104974,
        "name:xx": "Schloßberg"
      }
    },
    {
      "geometry": {
        "type": "Point",
        "coordinates": [
          8.316667,
          49.866667
        ]
      },
      "type": "Feature",
      "properties": {
        "hierarchy": [
          "tgn:7104975",
          "tgn:1000003",
          "tgn:7003682",
          "tgn:7000084",
          "tgn:7029392"
        ],
        "placetype": [
          "aat:300008777"
        ],
        "id": 7104975,
        "name:xx": "Schloß Berg"
      }
    },
    {
      "geometry": {
        "type": "Point",
        "coordinates": [
          10.416667,
          49.816667
        ]
      },
      "type": "Feature",
      "properties": {
        "hierarchy": [
          "tgn:7104976",
          "tgn:7003669",
          "tgn:1000003",
          "tgn:7000084",
          "tgn:7029392"
        ],
        "placetype": [
          "aat:300008777"
        ],
        "id": 7104976,
        "name:xx": "Schloßberg"
      }
    },
    {
      "geometry": {
        "type": "Point",
        "coordinates": [
          6.883333,
          49.816667
        ]
      },
      "type": "Feature",
      "properties": {
        "hierarchy": [
          "tgn:7104977",
          "tgn:1000003",
          "tgn:7003682",
          "tgn:7000084",
          "tgn:7029392"
        ],
        "placetype": [
          "aat:300008777"
        ],
        "id": 7104977,
        "name:xx": "Schloß Berg"
      }
    },
    {
      "geometry": {
        "type": "Point",
        "coordinates": [
          11.116667,
          49.8
        ]
      },
      "type": "Feature",
      "properties": {
        "hierarchy": [
          "tgn:7104978",
          "tgn:7003669",
          "tgn:1000003",
          "tgn:7000084",
          "tgn:7029392"
        ],
        "placetype": [
          "aat:300008777"
        ],
        "id": 7104978,
        "name:xx": "Schloßberg"
      }
    },
    {
      "geometry": {
        "type": "Point",
        "coordinates": [
          8.666667,
          49.8
        ]
      },
      "type": "Feature",
      "properties": {
        "hierarchy": [
          "tgn:7104979",
          "tgn:1000003",
          "tgn:7003678",
          "tgn:7000084",
          "tgn:7029392"
        ],
        "placetype": [
          "aat:300008777"
        ],
        "id": 7104979,
        "name:xx": "Schloßberg"
      }
    }
  ]
}
