{
  "geometry": {
    "type": "Point",
    "coordinates": [
      87.27878,
      23.310182
    ]
  },
  "type": "Feature",
  "properties": {
    "hierarchy": [
      "tgn:7548358",
      "tgn:1000004",
      "tgn:7000198",
      "tgn:1001977",
      "tgn:7029392"
    ],
    "placetype": [
      "aat:300008347"
    ],
    "name:en": "Brindābanpur",
    "id": 7548358
  }
}
