{
  "geometry": {
    "type": "Point",
    "coordinates": [
      -109.4167,
      45.7167
    ]
  },
  "type": "Feature",
  "properties": {
    "hierarchy": [
      "tgn:2259861",
      "tgn:1000001",
      "tgn:7012149",
      "tgn:2001307",
      "tgn:7007524",
      "tgn:7029392"
    ],
    "placetype": [
      "aat:300008706"
    ],
    "id": 2259861,
    "name:xx": "Coulee Creek"
  }
}
