{
  "geometry": {
    "type": "Point",
    "coordinates": [
      -83.8833,
      32.2667
    ]
  },
  "type": "Feature",
  "properties": {
    "hierarchy": [
      "tgn:2627539",
      "tgn:1000001",
      "tgn:7012149",
      "tgn:2000337",
      "tgn:7007248",
      "tgn:7029392"
    ],
    "placetype": [
      "aat:300008699"
    ],
    "id": 2627539,
    "name:xx": "Rogers Branch"
  }
}
