{
  "geometry": {
    "type": "Point",
    "coordinates": [
      -81.85,
      38.1667
    ]
  },
  "type": "Feature",
  "properties": {
    "hierarchy": [
      "tgn:2125639",
      "tgn:1000001",
      "tgn:2002255",
      "tgn:7012149",
      "tgn:7013961",
      "tgn:7029392"
    ],
    "placetype": [
      "aat:300008347"
    ],
    "id": 2125639,
    "name:xx": "Adams"
  }
}
