{
  "geometry": {
    "type": "Point",
    "coordinates": [
      10.1833,
      55.5167
    ]
  },
  "type": "Feature",
  "properties": {
    "hierarchy": [
      "tgn:1028105",
      "tgn:1000003",
      "tgn:7594009",
      "tgn:1000066",
      "tgn:7029392"
    ],
    "placetype": [
      "aat:300008347"
    ],
    "id": 1028105,
    "name:xx": "Særslev"
  }
}
