{
  "geometry": {
    "type": "Point",
    "coordinates": [
      90.626,
      23.65
    ]
  },
  "type": "Feature",
  "properties": {
    "hierarchy": [
      "tgn:7031478",
      "tgn:7000189",
      "tgn:1000004",
      "tgn:1000105",
      "tgn:7029392"
    ],
    "placetype": [
      "aat:300008347"
    ],
    "name:en": "Sonārgaon",
    "id": 7031478
  }
}
