{
  "geometry": {
    "type": "Point",
    "coordinates": [
      -90.9833,
      42.4833
    ]
  },
  "type": "Feature",
  "properties": {
    "hierarchy": [
      "tgn:2457606",
      "tgn:1000001",
      "tgn:2000591",
      "tgn:7012149",
      "tgn:7007253",
      "tgn:7029392"
    ],
    "placetype": [
      "aat:300008707"
    ],
    "id": 2457606,
    "name:xx": "Little Maquoketa River"
  }
}
