{
  "type": "FeatureCollection",
  "features": [
    {
      "geometry": {
        "type": "Point",
        "coordinates": [
          -102.066667,
          18.116667
        ]
      },
      "type": "Feature",
      "properties": {
        "hierarchy": [
          "tgn:7440680",
          "tgn:7005585",
          "tgn:1000001",
          "tgn:7005560",
          "tgn:7029392"
        ],
        "placetype": [
          "aat:300008347"
        ],
        "id": 7440680,
        "name:xx": "Santa María"
      }
    },
    {
      "geometry": {
        "type": "Point",
        "coordinates": [
          -101.833333,
          18.083333
        ]
      },
      "type": "Feature",
      "properties": {
        "hierarchy": [
          "tgn:7440681",
          "tgn:7005585",
          "tgn:1000001",
          "tgn:7005560",
          "tgn:7029392"
        ],
        "placetype": [
          "aat:300008347"
        ],
        "id": 7440681,
        "name:xx": "Santa María"
      }
    },
    {
      "geometry": {
        "type": "Point",
        "coordinates": [
          -94.433333,
          18
        ]
      },
      "type": "Feature",
      "properties": {
        "hierarchy": [
          "tgn:7440682",
          "tgn:1000001",
          "tgn:7005599",
          "tgn:7005560",
          "tgn:7029392"
        ],
        "placetype": [
          "aat:300008347"
        ],
        "id": 7440682,
        "name:xx": "Santa María"
      }
    },
    {
      "geometry": {
        "type": "Point",
        "coordinates": [
          -93.283333,
          17.666667
        ]
      },
      "type": "Feature",
      "properties": {
        "hierarchy": [
          "tgn:7440683",
          "tgn:7005580",
          "tgn:1000001",
          "tgn:7005560",
          "tgn:7029392"
        ],
        "placetype": [
          "aat:300008347"
        ],
        "id": 7440683,
        "name:xx": "Santa María"
      }
    },
    {
      "geometry": {
        "type": "Point",
        "coordinates": [
          -97.783333,
          17.583333
        ]
      },
      "type": "Feature",
      "properties": {
        "hierarchy": [
          "tgn:7440684",
          "tgn:1000001",
          "tgn:7005591",
          "tgn:7005560",
          "tgn:7029392"
        ],
        "placetype": [
          "aat:300008347"
        ],
        "id": 7440684,
        "name:xx": "Santa María"
      }
    },
    {
      "geometry": {
        "type": "Point",
        "coordinates": [
          -93.316667,
          17.566667
        ]
      },
      "type": "Feature",
      "properties": {
        "hierarchy": [
          "tgn:7440685",
          "tgn:7005580",
          "tgn:1000001",
          "tgn:7005560",
          "tgn:7029392"
        ],
        "placetype": [
          "aat:300008347"
        ],
        "id": 7440685,
        "name:xx": "Santa María"
      }
    },
    {
      "geometry": {
        "type": "Point",
        "coordinates": [
          -98.433333,
          16.833333
        ]
      },
      "type": "Feature",
      "properties": {
        "hierarchy": [
          "tgn:7440686",
          "tgn:7005585",
          "tgn:1000001",
          "tgn:7005560",
          "tgn:7029392"
        ],
        "placetype": [
          "aat:300008347"
        ],
        "id": 7440686,
        "name:xx": "Santa María"
      }
    },
    {
      "geometry": {
        "type": "Point",
        "coordinates": [
          -95.233333,
          16.316667
        ]
      },
      "type": "Feature",
      "properties": {
        "hierarchy": [
          "tgn:7440687",
          "tgn:1000001",
          "tgn:7005591",
          "tgn:7005560",
          "tgn:7029392"
        ],
        "placetype": [
          "aat:300008347"
        ],
        "id": 7440687,
        "name:xx": "Santa María"
      }
    },
    {
      "geometry": {
        "type": "Point",
        "coordinates": [
          -93.366667,
          16.216667
        ]
      },
      "type": "Feature",
      "properties": {
        "hierarchy": [
          "tgn:7440688",
          "tgn:7005580",
          "tgn:1000001",
          "tgn:7005560",
          "tgn:7029392"
        ],
        "placetype": [
          "aat:300008347"
        ],
        "id": 7440688,
        "name:xx": "Santa María"
      }
    },
    {
      "geometry": {
        "type": "Point",
        "coordinates": [
          -91.95,
          16.166667
        ]
      },
      "type": "Feature",
      "properties": {
        "hierarchy": [
          "tgn:7440689",
          "tgn:7005580",
          "tgn:1000001",
          "tgn:7005560",
          "tgn:7029392"
        ],
        "placetype": [
          "aat:300008347"
        ],
        "id": 7440689,
        "name:xx": "Santa María"
      }
    }
  ]
}
