{
  "geometry": {
    "type": "Point",
    "coordinates": [
      -91.3167,
      34.5167
    ]
  },
  "type": "Feature",
  "properties": {
    "hierarchy": [
      "tgn:2007915",
      "tgn:2000105",
      "tgn:1000001",
      "tgn:7016172",
      "tgn:7012149",
      "tgn:7029392"
    ],
    "placetype": [
      "aat:300008347"
    ],
    "id": 2007915,
    "name:xx": "Casscoe"
  }
}
