{
  "type": "FeatureCollection",
  "features": [
    {
      "geometry": {
        "type": "Point",
        "coordinates": [
          41.8833,
          50.5833
        ]
      },
      "type": "Feature",
      "properties": {
        "hierarchy": [
          "tgn:1056590",
          "tgn:1000004",
          "tgn:7013207",
          "tgn:7018214",
          "tgn:7002435",
          "tgn:7029392"
        ],
        "placetype": [
          "aat:300008347"
        ],
        "id": 1056590,
        "name:xx": "Lukovskaya"
      }
    },
    {
      "geometry": {
        "type": "Point",
        "coordinates": [
          40.5833,
          67.7
        ]
      },
      "type": "Feature",
      "properties": {
        "hierarchy": [
          "tgn:1056591",
          "tgn:1000004",
          "tgn:7011584",
          "tgn:7018214",
          "tgn:7002435",
          "tgn:7029392"
        ],
        "placetype": [
          "aat:300008347"
        ],
        "id": 1056591,
        "name:xx": "Lumbovka"
      }
    },
    {
      "geometry": {
        "type": "Point",
        "coordinates": [
          26.6333,
          52.3
        ]
      },
      "type": "Feature",
      "properties": {
        "hierarchy": [
          "tgn:1056592",
          "tgn:1003357",
          "tgn:1000003",
          "tgn:7006657",
          "tgn:7029392"
        ],
        "placetype": [
          "aat:300008347"
        ],
        "id": 1056592,
        "name:xx": "Lunin"
      }
    },
    {
      "geometry": {
        "type": "Point",
        "coordinates": [
          26.8333,
          52.3
        ]
      },
      "type": "Feature",
      "properties": {
        "hierarchy": [
          "tgn:1056593",
          "tgn:1003357",
          "tgn:1000003",
          "tgn:7006657",
          "tgn:7029392"
        ],
        "placetype": [
          "aat:300008347"
        ],
        "id": 1056593,
        "name:xx": "Luninets"
      }
    },
    {
      "geometry": {
        "type": "Point",
        "coordinates": [
          45.25,
          53.6167
        ]
      },
      "type": "Feature",
      "properties": {
        "hierarchy": [
          "tgn:1056594",
          "tgn:1000004",
          "tgn:1003399",
          "tgn:7018214",
          "tgn:7002435",
          "tgn:7029392"
        ],
        "placetype": [
          "aat:300008347"
        ],
        "id": 1056594,
        "name:xx": "Lunino"
      }
    },
    {
      "geometry": {
        "type": "Point",
        "coordinates": [
          24.2667,
          53.45
        ]
      },
      "type": "Feature",
      "properties": {
        "hierarchy": [
          "tgn:1056595",
          "tgn:7012158",
          "tgn:1000003",
          "tgn:7006657",
          "tgn:7029392"
        ],
        "placetype": [
          "aat:300008347"
        ],
        "id": 1056595,
        "name:xx": "Lunno"
      }
    },
    {
      "geometry": {
        "type": "Point",
        "coordinates": [
          44.593,
          40.379
        ]
      },
      "type": "Feature",
      "properties": {
        "hierarchy": [
          "tgn:1056596",
          "tgn:1000004",
          "tgn:7024037",
          "tgn:7006651",
          "tgn:7029392"
        ],
        "placetype": [
          "aat:300008347"
        ],
        "name:en": "Argel",
        "id": 1056596,
        "name:xx": "Lusakert"
      }
    },
    {
      "geometry": {
        "type": "Point",
        "coordinates": [
          39.2167,
          48.4
        ]
      },
      "type": "Feature",
      "properties": {
        "hierarchy": [
          "tgn:1056597",
          "tgn:1000003",
          "tgn:7012067",
          "tgn:7006660",
          "tgn:7029392"
        ],
        "placetype": [
          "aat:300008347"
        ],
        "id": 1056597,
        "name:xx": "Lutuhyne"
      }
    },
    {
      "geometry": {
        "type": "Point",
        "coordinates": [
          47.2,
          60.6833
        ]
      },
      "type": "Feature",
      "properties": {
        "hierarchy": [
          "tgn:1056598",
          "tgn:1000004",
          "tgn:1003379",
          "tgn:7018214",
          "tgn:7002435",
          "tgn:7029392"
        ],
        "placetype": [
          "aat:300008347"
        ],
        "id": 1056598,
        "name:xx": "Luza"
      }
    },
    {
      "geometry": {
        "type": "Point",
        "coordinates": [
          35.2,
          49.1
        ]
      },
      "type": "Feature",
      "properties": {
        "hierarchy": [
          "tgn:1056599",
          "tgn:7011648",
          "tgn:1000003",
          "tgn:7006660",
          "tgn:7029392"
        ],
        "placetype": [
          "aat:300008347"
        ],
        "id": 1056599,
        "name:xx": "Lychkove"
      }
    }
  ]
}
