{
  "geometry": {
    "type": "Point",
    "coordinates": [
      -81.1667,
      37.3667
    ]
  },
  "type": "Feature",
  "properties": {
    "hierarchy": [
      "tgn:2515878",
      "tgn:1000001",
      "tgn:7012149",
      "tgn:2002278",
      "tgn:7013961",
      "tgn:7029392"
    ],
    "placetype": [
      "aat:300008699"
    ],
    "id": 2515878,
    "name:xx": "Milton Branch"
  }
}
