{
  "geometry": {
    "type": "Point",
    "coordinates": [
      -106.2833,
      35.85
    ]
  },
  "type": "Feature",
  "properties": {
    "hierarchy": [
      "tgn:2204236",
      "tgn:1000001",
      "tgn:7012149",
      "tgn:7007566",
      "tgn:7029392"
    ],
    "placetype": [
      "aat:300008699"
    ],
    "id": 2204236,
    "name:xx": "Buey, Cañada del"
  }
}
