{
  "geometry": {
    "type": "Point",
    "coordinates": [
      -107.9167,
      34.1333
    ]
  },
  "type": "Feature",
  "properties": {
    "hierarchy": [
      "tgn:2389084",
      "tgn:1000001",
      "tgn:2001429",
      "tgn:7012149",
      "tgn:7007566",
      "tgn:7029392"
    ],
    "placetype": [
      "aat:300006191"
    ],
    "id": 2389084,
    "name:xx": "Hidden Tank"
  }
}
