{
  "geometry": {
    "type": "Point",
    "coordinates": [
      -90.6333,
      43.6167
    ]
  },
  "type": "Feature",
  "properties": {
    "hierarchy": [
      "tgn:2122172",
      "tgn:1000001",
      "tgn:7012149",
      "tgn:2002358",
      "tgn:7007922",
      "tgn:7029392"
    ],
    "placetype": [
      "aat:300008347",
      "aat:300387210"
    ],
    "id": 2122172,
    "name:xx": "Potts Corners"
  }
}
