{
  "geometry": {
    "type": "Point",
    "coordinates": [
      112.1667,
      39.0833
    ]
  },
  "type": "Feature",
  "properties": {
    "hierarchy": [
      "tgn:1071583",
      "tgn:1000004",
      "tgn:7002086",
      "tgn:1000111",
      "tgn:7029392"
    ],
    "placetype": [
      "aat:300008347"
    ],
    "id": 1071583,
    "name:xx": "Shenchi"
  }
}
