{
  "type": "FeatureCollection",
  "features": [
    {
      "geometry": {
        "type": "Point",
        "coordinates": [
          12.235,
          45.565
        ]
      },
      "type": "Feature",
      "properties": {
        "hierarchy": [
          "tgn:4007292",
          "tgn:7002996",
          "tgn:1000003",
          "tgn:7002997",
          "tgn:1000080",
          "tgn:7029392"
        ],
        "placetype": [
          "aat:300008347"
        ],
        "id": 4007292,
        "name:xx": "Mogliano Veneto"
      }
    },
    {
      "geometry": {
        "type": "Point",
        "coordinates": [
          26,
          44.5333
        ]
      },
      "type": "Feature",
      "properties": {
        "hierarchy": [
          "tgn:4007294",
          "tgn:1000003",
          "tgn:7593858",
          "tgn:1000091",
          "tgn:7029392"
        ],
        "placetype": [
          "aat:300008347"
        ],
        "id": 4007294,
        "name:xx": "Mogoșoaia"
      }
    },
    {
      "geometry": {
        "type": "Point",
        "coordinates": [
          24.55,
          47.65
        ]
      },
      "type": "Feature",
      "properties": {
        "hierarchy": [
          "tgn:4007298",
          "tgn:1000003",
          "tgn:7002696",
          "tgn:1000091",
          "tgn:7029392"
        ],
        "placetype": [
          "aat:300008347"
        ],
        "id": 4007298,
        "name:xx": "Moiseiu"
      }
    }
  ]
}
