{
  "geometry": {
    "type": "Point",
    "coordinates": [
      -76.3333,
      37.3667
    ]
  },
  "type": "Feature",
  "properties": {
    "hierarchy": [
      "tgn:2113049",
      "tgn:1000001",
      "tgn:7012149",
      "tgn:1002647",
      "tgn:7007919",
      "tgn:7029392"
    ],
    "placetype": [
      "aat:300008347"
    ],
    "id": 2113049,
    "name:xx": "Mobjack"
  }
}
