{
  "geometry": {
    "type": "Point",
    "coordinates": [
      -76.9167,
      42.4833
    ]
  },
  "type": "Feature",
  "properties": {
    "hierarchy": [
      "tgn:2069409",
      "tgn:1000001",
      "tgn:7012149",
      "tgn:1003045",
      "tgn:7007568",
      "tgn:7029392"
    ],
    "placetype": [
      "aat:300008347"
    ],
    "id": 2069409,
    "name:xx": "Glenora"
  }
}
