{
  "type": "FeatureCollection",
  "features": [
    {
      "geometry": {
        "type": "Point",
        "coordinates": [
          -70.966667,
          -29.5
        ]
      },
      "type": "Feature",
      "properties": {
        "hierarchy": [
          "tgn:7279900",
          "tgn:1001657",
          "tgn:1000049",
          "tgn:1000002",
          "tgn:7029392"
        ],
        "placetype": [
          "aat:300008699"
        ],
        "id": 7279900,
        "name:xx": "Rajos, Quebrada de los"
      }
    },
    {
      "geometry": {
        "type": "Point",
        "coordinates": [
          -70.95,
          -29.533333
        ]
      },
      "type": "Feature",
      "properties": {
        "hierarchy": [
          "tgn:7279901",
          "tgn:1001657",
          "tgn:1000049",
          "tgn:1000002",
          "tgn:7029392"
        ],
        "placetype": [
          "aat:300008699"
        ],
        "id": 7279901,
        "name:xx": "Rajos, Quebrada"
      }
    },
    {
      "geometry": {
        "type": "Point",
        "coordinates": [
          -70.733333,
          -35.55
        ]
      },
      "type": "Feature",
      "properties": {
        "hierarchy": [
          "tgn:7279902",
          "tgn:1001705",
          "tgn:1000049",
          "tgn:1000002",
          "tgn:7029392"
        ],
        "placetype": [
          "aat:300008795"
        ],
        "id": 7279902,
        "name:xx": "Rajaduras, Cerro"
      }
    },
    {
      "geometry": {
        "type": "Point",
        "coordinates": [
          -69.733333,
          -20.6
        ]
      },
      "type": "Feature",
      "properties": {
        "hierarchy": [
          "tgn:7279903",
          "tgn:7002464",
          "tgn:1000049",
          "tgn:1000002",
          "tgn:7029392"
        ],
        "placetype": [
          "aat:300008795"
        ],
        "id": 7279903,
        "name:xx": "Rincón, Cerro del"
      }
    },
    {
      "geometry": {
        "type": "Point",
        "coordinates": [
          -71.9,
          -34.4
        ]
      },
      "type": "Feature",
      "properties": {
        "hierarchy": [
          "tgn:7279904",
          "tgn:1001695",
          "tgn:1000049",
          "tgn:1000002",
          "tgn:7029392"
        ],
        "placetype": [
          "aat:300008777"
        ],
        "id": 7279904,
        "name:xx": "Rincón, Cerro"
      }
    },
    {
      "geometry": {
        "type": "Point",
        "coordinates": [
          -70.533333,
          -24.933333
        ]
      },
      "type": "Feature",
      "properties": {
        "hierarchy": [
          "tgn:7279905",
          "tgn:7016598",
          "tgn:1000049",
          "tgn:1000002",
          "tgn:7029392"
        ],
        "placetype": [
          "aat:300132317"
        ],
        "id": 7279905,
        "name:xx": "Rincón, Caleta"
      }
    },
    {
      "geometry": {
        "type": "Point",
        "coordinates": [
          -69.733333,
          -20.583333
        ]
      },
      "type": "Feature",
      "properties": {
        "hierarchy": [
          "tgn:7279906",
          "tgn:7002464",
          "tgn:1000049",
          "tgn:1000002",
          "tgn:7029392"
        ],
        "placetype": [
          "aat:300387033"
        ],
        "id": 7279906,
        "name:xx": "Rincón"
      }
    },
    {
      "geometry": {
        "type": "Point",
        "coordinates": [
          -72.366667,
          -36.466667
        ]
      },
      "type": "Feature",
      "properties": {
        "hierarchy": [
          "tgn:7279907",
          "tgn:1001637",
          "tgn:1000049",
          "tgn:1000002",
          "tgn:7029392"
        ],
        "placetype": [
          "aat:300008347"
        ],
        "id": 7279907,
        "name:xx": "Rincón"
      }
    },
    {
      "geometry": {
        "type": "Point",
        "coordinates": [
          -72.4,
          -36.316667
        ]
      },
      "type": "Feature",
      "properties": {
        "hierarchy": [
          "tgn:7279908",
          "tgn:1001637",
          "tgn:1000049",
          "tgn:1000002",
          "tgn:7029392"
        ],
        "placetype": [
          "aat:300008347"
        ],
        "id": 7279908,
        "name:xx": "Rincón"
      }
    },
    {
      "geometry": {
        "type": "Point",
        "coordinates": [
          -70.75,
          -28.9
        ]
      },
      "type": "Feature",
      "properties": {
        "hierarchy": [
          "tgn:7279909",
          "tgn:1001630",
          "tgn:1000049",
          "tgn:1000002",
          "tgn:7029392"
        ],
        "placetype": [
          "aat:300008347"
        ],
        "id": 7279909,
        "name:xx": "Rincón"
      }
    }
  ]
}
