{
  "type": "FeatureCollection",
  "features": [
    {
      "geometry": {
        "type": "Point",
        "coordinates": [
          13.483333,
          52.183333
        ]
      },
      "type": "Feature",
      "properties": {
        "hierarchy": [
          "tgn:7152860",
          "tgn:7000096",
          "tgn:1000003",
          "tgn:7000084",
          "tgn:7029392"
        ],
        "placetype": [
          "aat:300008777"
        ],
        "id": 7152860,
        "name:xx": "Jägersberg"
      }
    },
    {
      "geometry": {
        "type": "Point",
        "coordinates": [
          11.016667,
          51.483333
        ]
      },
      "type": "Feature",
      "properties": {
        "hierarchy": [
          "tgn:7152861",
          "tgn:1000003",
          "tgn:7003687",
          "tgn:7000084",
          "tgn:7029392"
        ],
        "placetype": [
          "aat:300008777"
        ],
        "id": 7152861,
        "name:xx": "Jägers-Berg"
      }
    },
    {
      "geometry": {
        "type": "Point",
        "coordinates": [
          11.466667,
          50.85
        ]
      },
      "type": "Feature",
      "properties": {
        "hierarchy": [
          "tgn:7152862",
          "tgn:1000003",
          "tgn:7003689",
          "tgn:7000084",
          "tgn:7029392"
        ],
        "placetype": [
          "aat:300008777"
        ],
        "id": 7152862,
        "name:xx": "Jägers-Berg"
      }
    },
    {
      "geometry": {
        "type": "Point",
        "coordinates": [
          11.35,
          50.85
        ]
      },
      "type": "Feature",
      "properties": {
        "hierarchy": [
          "tgn:7152863",
          "tgn:1000003",
          "tgn:7003689",
          "tgn:7000084",
          "tgn:7029392"
        ],
        "placetype": [
          "aat:300008777"
        ],
        "id": 7152863,
        "name:xx": "Jägers-Berg"
      }
    },
    {
      "geometry": {
        "type": "Point",
        "coordinates": [
          10.95,
          50.35
        ]
      },
      "type": "Feature",
      "properties": {
        "hierarchy": [
          "tgn:7152864",
          "tgn:7003669",
          "tgn:1000003",
          "tgn:7000084",
          "tgn:7029392"
        ],
        "placetype": [
          "aat:300008777"
        ],
        "id": 7152864,
        "name:xx": "Jägers-Berg"
      }
    },
    {
      "geometry": {
        "type": "Point",
        "coordinates": [
          11.5,
          49.95
        ]
      },
      "type": "Feature",
      "properties": {
        "hierarchy": [
          "tgn:7152865",
          "tgn:7003669",
          "tgn:1000003",
          "tgn:7000084",
          "tgn:7029392"
        ],
        "placetype": [
          "aat:300008777"
        ],
        "id": 7152865,
        "name:xx": "Jägers-Berg"
      }
    },
    {
      "geometry": {
        "type": "Point",
        "coordinates": [
          10.483333,
          49.65
        ]
      },
      "type": "Feature",
      "properties": {
        "hierarchy": [
          "tgn:7152866",
          "tgn:7003669",
          "tgn:1000003",
          "tgn:7000084",
          "tgn:7029392"
        ],
        "placetype": [
          "aat:300008777"
        ],
        "id": 7152866,
        "name:xx": "Jägersberg"
      }
    },
    {
      "geometry": {
        "type": "Point",
        "coordinates": [
          11.6,
          50.966667
        ]
      },
      "type": "Feature",
      "properties": {
        "hierarchy": [
          "tgn:7152867",
          "tgn:1000003",
          "tgn:7003689",
          "tgn:7000084",
          "tgn:7029392"
        ],
        "placetype": [
          "aat:300000206"
        ],
        "id": 7152867,
        "name:xx": "Jägersberg"
      }
    },
    {
      "geometry": {
        "type": "Point",
        "coordinates": [
          10.266667,
          47.433333
        ]
      },
      "type": "Feature",
      "properties": {
        "hierarchy": [
          "tgn:7152868",
          "tgn:7003669",
          "tgn:1000003",
          "tgn:7000084",
          "tgn:7029392"
        ],
        "placetype": [
          "aat:300000206"
        ],
        "id": 7152868,
        "name:xx": "Jägersberg"
      }
    },
    {
      "geometry": {
        "type": "Point",
        "coordinates": [
          10.266667,
          48.316667
        ]
      },
      "type": "Feature",
      "properties": {
        "hierarchy": [
          "tgn:7152869",
          "tgn:7003669",
          "tgn:1000003",
          "tgn:7000084",
          "tgn:7029392"
        ],
        "placetype": [
          "aat:300008863"
        ],
        "id": 7152869,
        "name:xx": "Jägersäule"
      }
    }
  ]
}
