{
  "geometry": {
    "type": "Point",
    "coordinates": [
      -106.8333,
      35.5167
    ]
  },
  "type": "Feature",
  "properties": {
    "hierarchy": [
      "tgn:2182555",
      "tgn:1000001",
      "tgn:7012149",
      "tgn:2001451",
      "tgn:7007566",
      "tgn:7029392"
    ],
    "placetype": [
      "aat:300000390"
    ],
    "id": 2182555,
    "name:xx": "Blue Sky"
  }
}
