{
  "geometry": {
    "type": "Point",
    "coordinates": [
      -115.9833,
      42.2333
    ]
  },
  "type": "Feature",
  "properties": {
    "hierarchy": [
      "tgn:2729941",
      "tgn:1000001",
      "tgn:7012149",
      "tgn:2000488",
      "tgn:7007250",
      "tgn:7029392"
    ],
    "placetype": [
      "aat:300008706"
    ],
    "id": 2729941,
    "name:xx": "Trout Creek"
  }
}
