{
  "geometry": {
    "type": "Point",
    "coordinates": [
      -70.2667,
      -37.3833
    ]
  },
  "type": "Feature",
  "properties": {
    "hierarchy": [
      "tgn:1019312",
      "tgn:7006477",
      "tgn:1001450",
      "tgn:1000002",
      "tgn:7029392"
    ],
    "placetype": [
      "aat:300008347"
    ],
    "id": 1019312,
    "name:xx": "Chos Malal"
  }
}
