{
  "geometry": {
    "type": "Point",
    "coordinates": [
      -104.3167,
      44.1833
    ]
  },
  "type": "Feature",
  "properties": {
    "hierarchy": [
      "tgn:2495800",
      "tgn:1000001",
      "tgn:7012149",
      "tgn:7007923",
      "tgn:7029392"
    ],
    "placetype": [
      "aat:300008706"
    ],
    "id": 2495800,
    "name:xx": "Mason Creek"
  }
}
