{
  "geometry": {
    "type": "Point",
    "coordinates": [
      -109.2667,
      32.9333
    ]
  },
  "type": "Feature",
  "properties": {
    "hierarchy": [
      "tgn:2369997",
      "tgn:1000001",
      "tgn:7006451",
      "tgn:2000095",
      "tgn:7012149",
      "tgn:7029392"
    ],
    "placetype": [
      "aat:300008798"
    ],
    "id": 2369997,
    "name:xx": "Guthrie Mountain"
  }
}
