{
  "geometry": {
    "type": "Point",
    "coordinates": [
      26.305,
      58.341
    ]
  },
  "type": "Feature",
  "properties": {
    "hierarchy": [
      "tgn:1058746",
      "tgn:7006642",
      "tgn:1000003",
      "tgn:7006540",
      "tgn:7029392"
    ],
    "placetype": [
      "aat:300008347"
    ],
    "name:en": "Puhja",
    "id": 1058746
  }
}
