{
  "geometry": {
    "type": "Point",
    "coordinates": [
      -108.6333,
      48.4667
    ]
  },
  "type": "Feature",
  "properties": {
    "hierarchy": [
      "tgn:2544576",
      "tgn:1000001",
      "tgn:2001262",
      "tgn:7012149",
      "tgn:7007524",
      "tgn:7029392"
    ],
    "placetype": [
      "aat:300006075"
    ],
    "id": 2544576,
    "name:xx": "North Canal"
  }
}
