{
  "geometry": {
    "type": "Point",
    "coordinates": [
      9.3167,
      45.55
    ]
  },
  "type": "Feature",
  "properties": {
    "hierarchy": [
      "tgn:1136121",
      "tgn:1000003",
      "tgn:7003237",
      "tgn:1000080",
      "tgn:7029392"
    ],
    "placetype": [
      "aat:300006075"
    ],
    "id": 1136121,
    "name:xx": "Villoresi, Canale"
  }
}
