{
  "geometry": {
    "type": "Point",
    "coordinates": [
      76.50424,
      30.21454
    ]
  },
  "type": "Feature",
  "properties": {
    "hierarchy": [
      "tgn:7584265",
      "tgn:1000004",
      "tgn:7000198",
      "tgn:7016883",
      "tgn:7029392"
    ],
    "placetype": [
      "aat:300008347"
    ],
    "name:en": "Nizāmpur",
    "id": 7584265
  }
}
