{
  "geometry": {
    "type": "Point",
    "coordinates": [
      32.340241,
      26.123438
    ]
  },
  "type": "Feature",
  "properties": {
    "hierarchy": [
      "tgn:7521583",
      "tgn:7001242",
      "tgn:7016833",
      "tgn:7000123",
      "tgn:7029392"
    ],
    "placetype": [
      "aat:300008347"
    ],
    "name:en": "Abū Ḩizām",
    "id": 7521583
  }
}
