{
  "type": "FeatureCollection",
  "features": [
    {
      "geometry": {
        "type": "Point",
        "coordinates": [
          -96.65,
          16.483333
        ]
      },
      "type": "Feature",
      "properties": {
        "hierarchy": [
          "tgn:7355820",
          "tgn:1000001",
          "tgn:7005591",
          "tgn:7005560",
          "tgn:7029392"
        ],
        "placetype": [
          "aat:300008347"
        ],
        "id": 7355820,
        "name:xx": "Cerrito Blanco"
      }
    },
    {
      "geometry": {
        "type": "Point",
        "coordinates": [
          -99.866667,
          26.7
        ]
      },
      "type": "Feature",
      "properties": {
        "hierarchy": [
          "tgn:7355821",
          "tgn:1000001",
          "tgn:7005589",
          "tgn:7005560",
          "tgn:7029392"
        ],
        "placetype": [
          "aat:300387007"
        ],
        "id": 7355821,
        "name:xx": "Cerrito Blanco"
      }
    },
    {
      "geometry": {
        "type": "Point",
        "coordinates": [
          -107.816667,
          28.95
        ]
      },
      "type": "Feature",
      "properties": {
        "hierarchy": [
          "tgn:7355822",
          "tgn:7005581",
          "tgn:1000001",
          "tgn:7005560",
          "tgn:7029392"
        ],
        "placetype": [
          "aat:300266554",
          "aat:300008699"
        ],
        "id": 7355822,
        "name:xx": "Cerrito, Arroyo del"
      }
    },
    {
      "geometry": {
        "type": "Point",
        "coordinates": [
          -99.683333,
          25.166667
        ]
      },
      "type": "Feature",
      "properties": {
        "hierarchy": [
          "tgn:7355823",
          "tgn:1000001",
          "tgn:7005589",
          "tgn:7005560",
          "tgn:7029392"
        ],
        "placetype": [
          "aat:300008347"
        ],
        "id": 7355823,
        "name:xx": "Cerrito"
      }
    },
    {
      "geometry": {
        "type": "Point",
        "coordinates": [
          -101.15,
          22.916667
        ]
      },
      "type": "Feature",
      "properties": {
        "hierarchy": [
          "tgn:7355824",
          "tgn:1000001",
          "tgn:7005594",
          "tgn:7005560",
          "tgn:7029392"
        ],
        "placetype": [
          "aat:300008347"
        ],
        "id": 7355824,
        "name:xx": "Cerrito"
      }
    },
    {
      "geometry": {
        "type": "Point",
        "coordinates": [
          -100.683333,
          21.75
        ]
      },
      "type": "Feature",
      "properties": {
        "hierarchy": [
          "tgn:7355825",
          "tgn:1000001",
          "tgn:7005594",
          "tgn:7005560",
          "tgn:7029392"
        ],
        "placetype": [
          "aat:300008347"
        ],
        "id": 7355825,
        "name:xx": "Cerrito"
      }
    },
    {
      "geometry": {
        "type": "Point",
        "coordinates": [
          -99.933333,
          20.683333
        ]
      },
      "type": "Feature",
      "properties": {
        "hierarchy": [
          "tgn:7355826",
          "tgn:1000001",
          "tgn:7005593",
          "tgn:7005560",
          "tgn:7029392"
        ],
        "placetype": [
          "aat:300008347"
        ],
        "id": 7355826,
        "name:xx": "Cerrito"
      }
    },
    {
      "geometry": {
        "type": "Point",
        "coordinates": [
          -104.1,
          19.75
        ]
      },
      "type": "Feature",
      "properties": {
        "hierarchy": [
          "tgn:7355827",
          "tgn:7005586",
          "tgn:1000001",
          "tgn:7005560",
          "tgn:7029392"
        ],
        "placetype": [
          "aat:300008347"
        ],
        "id": 7355827,
        "name:xx": "Cerrito"
      }
    },
    {
      "geometry": {
        "type": "Point",
        "coordinates": [
          -96.7,
          19.633333
        ]
      },
      "type": "Feature",
      "properties": {
        "hierarchy": [
          "tgn:7355828",
          "tgn:1000001",
          "tgn:7005599",
          "tgn:7005560",
          "tgn:7029392"
        ],
        "placetype": [
          "aat:300008347"
        ],
        "id": 7355828,
        "name:xx": "Cerrillos de Díaz"
      }
    },
    {
      "geometry": {
        "type": "Point",
        "coordinates": [
          -107.166667,
          25.15
        ]
      },
      "type": "Feature",
      "properties": {
        "hierarchy": [
          "tgn:7355829",
          "tgn:1000001",
          "tgn:7005595",
          "tgn:7005560",
          "tgn:7029392"
        ],
        "placetype": [
          "aat:300008347"
        ],
        "id": 7355829,
        "name:xx": "Cerricillo"
      }
    }
  ]
}
