{
  "geometry": {
    "type": "Point",
    "coordinates": [
      -95.6333,
      29.7667
    ]
  },
  "type": "Feature",
  "properties": {
    "hierarchy": [
      "tgn:2148082",
      "tgn:1000001",
      "tgn:7012149",
      "tgn:7007826",
      "tgn:7029392"
    ],
    "placetype": [
      "aat:300006191"
    ],
    "id": 2148082,
    "name:xx": "Barker Reservoir"
  }
}
