{
  "geometry": {
    "type": "Point",
    "coordinates": [
      -91.45,
      36.4667
    ]
  },
  "type": "Feature",
  "properties": {
    "hierarchy": [
      "tgn:2529952",
      "tgn:1000001",
      "tgn:7016172",
      "tgn:7012149",
      "tgn:2000172",
      "tgn:7029392"
    ],
    "placetype": [
      "aat:300008697"
    ],
    "id": 2529952,
    "name:xx": "Mud Spring"
  }
}
