{
  "geometry": {
    "type": "Point",
    "coordinates": [
      -77.3167,
      40.3833
    ]
  },
  "type": "Feature",
  "properties": {
    "hierarchy": [
      "tgn:2530776",
      "tgn:1000001",
      "tgn:7012149",
      "tgn:1002779",
      "tgn:7007710",
      "tgn:7029392"
    ],
    "placetype": [
      "aat:300008699"
    ],
    "id": 2530776,
    "name:xx": "Muddy Run"
  }
}
