{
  "geometry": {
    "type": "Point",
    "coordinates": [
      -92.9167,
      36.05
    ]
  },
  "type": "Feature",
  "properties": {
    "hierarchy": [
      "tgn:2408113",
      "tgn:1000001",
      "tgn:7016172",
      "tgn:7012149",
      "tgn:2000169",
      "tgn:7029392"
    ],
    "placetype": [
      "aat:300000390"
    ],
    "id": 2408113,
    "name:xx": "Hurricane Mine"
  }
}
