{
  "geometry": {
    "type": "Point",
    "coordinates": [
      -83.0167,
      33.0667
    ]
  },
  "type": "Feature",
  "properties": {
    "hierarchy": [
      "tgn:2341027",
      "tgn:1000001",
      "tgn:7012149",
      "tgn:2000361",
      "tgn:7007248",
      "tgn:7029392"
    ],
    "placetype": [
      "aat:300008347"
    ],
    "id": 2341027,
    "name:xx": "Friendship"
  }
}
