{
  "type": "FeatureCollection",
  "features": [
    {
      "geometry": {
        "type": "Point",
        "coordinates": [
          151.1,
          -33.9167
        ]
      },
      "type": "Feature",
      "properties": {
        "hierarchy": [
          "tgn:1096480",
          "tgn:7000490",
          "tgn:1000006",
          "tgn:7001828",
          "tgn:7029392"
        ],
        "placetype": [
          "aat:300008347"
        ],
        "id": 1096480,
        "name:xx": "Campsie"
      }
    },
    {
      "geometry": {
        "type": "Point",
        "coordinates": [
          146.35,
          -31.5833
        ]
      },
      "type": "Feature",
      "properties": {
        "hierarchy": [
          "tgn:1096481",
          "tgn:7000490",
          "tgn:1000006",
          "tgn:7001828",
          "tgn:7029392"
        ],
        "placetype": [
          "aat:300008347"
        ],
        "id": 1096481,
        "name:xx": "Canbelego"
      }
    },
    {
      "geometry": {
        "type": "Point",
        "coordinates": [
          149.7,
          -36.8333
        ]
      },
      "type": "Feature",
      "properties": {
        "hierarchy": [
          "tgn:1096483",
          "tgn:7000490",
          "tgn:1000006",
          "tgn:7001828",
          "tgn:7029392"
        ],
        "placetype": [
          "aat:300008347"
        ],
        "id": 1096483,
        "name:xx": "Candelo"
      }
    },
    {
      "geometry": {
        "type": "Point",
        "coordinates": [
          150.95,
          -33.8833
        ]
      },
      "type": "Feature",
      "properties": {
        "hierarchy": [
          "tgn:1096484",
          "tgn:7000490",
          "tgn:1000006",
          "tgn:7001828",
          "tgn:7029392"
        ],
        "placetype": [
          "aat:300008347"
        ],
        "id": 1096484,
        "name:xx": "Canley Vale"
      }
    },
    {
      "geometry": {
        "type": "Point",
        "coordinates": [
          149.1,
          -37.5833
        ]
      },
      "type": "Feature",
      "properties": {
        "hierarchy": [
          "tgn:1096485",
          "tgn:7000490",
          "tgn:1000006",
          "tgn:7006238",
          "tgn:7029392"
        ],
        "placetype": [
          "aat:300008347"
        ],
        "id": 1096485,
        "name:xx": "Cann River"
      }
    },
    {
      "geometry": {
        "type": "Point",
        "coordinates": [
          115.9333,
          -32.0333
        ]
      },
      "type": "Feature",
      "properties": {
        "hierarchy": [
          "tgn:1096486",
          "tgn:7000490",
          "tgn:1000006",
          "tgn:7001834",
          "tgn:7029392"
        ],
        "placetype": [
          "aat:300008347"
        ],
        "id": 1096486,
        "name:xx": "Canning"
      }
    },
    {
      "geometry": {
        "type": "Point",
        "coordinates": [
          148.7,
          -20.2833
        ]
      },
      "type": "Feature",
      "properties": {
        "hierarchy": [
          "tgn:1096487",
          "tgn:7000490",
          "tgn:1000006",
          "tgn:7001830",
          "tgn:7029392"
        ],
        "placetype": [
          "aat:300008347"
        ],
        "id": 1096487,
        "name:xx": "Cannonvale"
      }
    },
    {
      "geometry": {
        "type": "Point",
        "coordinates": [
          148.5,
          -33.5667
        ]
      },
      "type": "Feature",
      "properties": {
        "hierarchy": [
          "tgn:1096488",
          "tgn:7000490",
          "tgn:1000006",
          "tgn:7001828",
          "tgn:7029392"
        ],
        "placetype": [
          "aat:300008347"
        ],
        "id": 1096488,
        "name:xx": "Canowindra"
      }
    },
    {
      "geometry": {
        "type": "Point",
        "coordinates": [
          151.1167,
          -33.9167
        ]
      },
      "type": "Feature",
      "properties": {
        "hierarchy": [
          "tgn:1096489",
          "tgn:7000490",
          "tgn:1000006",
          "tgn:7001828",
          "tgn:7029392"
        ],
        "placetype": [
          "aat:300008347",
          "aat:300265612"
        ],
        "id": 1096489,
        "name:xx": "Canterbury"
      }
    }
  ]
}
