{
  "geometry": {
    "type": "Point",
    "coordinates": [
      -88.2833,
      41.3833
    ]
  },
  "type": "Feature",
  "properties": {
    "hierarchy": [
      "tgn:2295181",
      "tgn:1000001",
      "tgn:7012149",
      "tgn:1002430",
      "tgn:7007251",
      "tgn:7029392"
    ],
    "placetype": [
      "aat:300008791"
    ],
    "id": 2295181,
    "name:xx": "Dresden Island"
  }
}
