{
  "geometry": {
    "type": "Point",
    "coordinates": [
      -90.2167,
      29.3833
    ]
  },
  "type": "Feature",
  "properties": {
    "hierarchy": [
      "tgn:2784233",
      "tgn:1000001",
      "tgn:7012149",
      "tgn:7007256",
      "tgn:7029392"
    ],
    "placetype": [
      "aat:300006075"
    ],
    "id": 2784233,
    "name:xx": "Yankee Canal"
  }
}
