{
  "type": "FeatureCollection",
  "features": [
    {
      "geometry": {
        "type": "Point",
        "coordinates": [
          -106.4667,
          46.4
        ]
      },
      "type": "Feature",
      "properties": {
        "hierarchy": [
          "tgn:2416510",
          "tgn:1000001",
          "tgn:7012149",
          "tgn:2001303",
          "tgn:7007524",
          "tgn:7029392"
        ],
        "placetype": [
          "aat:300008706"
        ],
        "id": 2416510,
        "name:xx": "Jack Creek"
      }
    },
    {
      "geometry": {
        "type": "Point",
        "coordinates": [
          -112.5833,
          46.3167
        ]
      },
      "type": "Feature",
      "properties": {
        "hierarchy": [
          "tgn:2416511",
          "tgn:1000001",
          "tgn:7012149",
          "tgn:2001298",
          "tgn:7007524",
          "tgn:7029392"
        ],
        "placetype": [
          "aat:300008706"
        ],
        "id": 2416511,
        "name:xx": "Jack Creek"
      }
    },
    {
      "geometry": {
        "type": "Point",
        "coordinates": [
          -107.1667,
          48.7833
        ]
      },
      "type": "Feature",
      "properties": {
        "hierarchy": [
          "tgn:2416512",
          "tgn:1000001",
          "tgn:7012149",
          "tgn:2001312",
          "tgn:7007524",
          "tgn:7029392"
        ],
        "placetype": [
          "aat:300008706"
        ],
        "id": 2416512,
        "name:xx": "Jack Creek"
      }
    },
    {
      "geometry": {
        "type": "Point",
        "coordinates": [
          -116.2333,
          40.95
        ]
      },
      "type": "Feature",
      "properties": {
        "hierarchy": [
          "tgn:2416513",
          "tgn:1000001",
          "tgn:2001413",
          "tgn:7012149",
          "tgn:7007526",
          "tgn:7029392"
        ],
        "placetype": [
          "aat:300008706"
        ],
        "id": 2416513,
        "name:xx": "Jack Creek"
      }
    },
    {
      "geometry": {
        "type": "Point",
        "coordinates": [
          -116,
          41.5667
        ]
      },
      "type": "Feature",
      "properties": {
        "hierarchy": [
          "tgn:2416514",
          "tgn:1000001",
          "tgn:2001411",
          "tgn:7012149",
          "tgn:7007526",
          "tgn:7029392"
        ],
        "placetype": [
          "aat:300008706"
        ],
        "id": 2416514,
        "name:xx": "Jack Creek"
      }
    },
    {
      "geometry": {
        "type": "Point",
        "coordinates": [
          -116.0833,
          41.4833
        ]
      },
      "type": "Feature",
      "properties": {
        "hierarchy": [
          "tgn:2416515",
          "tgn:1000001",
          "tgn:2001411",
          "tgn:7012149",
          "tgn:7007526",
          "tgn:7029392"
        ],
        "placetype": [
          "aat:300008347"
        ],
        "id": 2416515,
        "name:xx": "Jack Creek"
      }
    },
    {
      "geometry": {
        "type": "Point",
        "coordinates": [
          -80.85,
          35.8667
        ]
      },
      "type": "Feature",
      "properties": {
        "hierarchy": [
          "tgn:2416517",
          "tgn:1000001",
          "tgn:7012149",
          "tgn:2001507",
          "tgn:7007709",
          "tgn:7029392"
        ],
        "placetype": [
          "aat:300008706"
        ],
        "id": 2416517,
        "name:xx": "Jack Creek"
      }
    },
    {
      "geometry": {
        "type": "Point",
        "coordinates": [
          -98.8,
          34.55
        ]
      },
      "type": "Feature",
      "properties": {
        "hierarchy": [
          "tgn:2416518",
          "tgn:1000001",
          "tgn:7012149",
          "tgn:7007707",
          "tgn:7029392"
        ],
        "placetype": [
          "aat:300008706"
        ],
        "id": 2416518,
        "name:xx": "Jack Creek"
      }
    },
    {
      "geometry": {
        "type": "Point",
        "coordinates": [
          -96.9833,
          34.3667
        ]
      },
      "type": "Feature",
      "properties": {
        "hierarchy": [
          "tgn:2416519",
          "tgn:1000001",
          "tgn:7012149",
          "tgn:2001672",
          "tgn:7007707",
          "tgn:7029392"
        ],
        "placetype": [
          "aat:300008706"
        ],
        "id": 2416519,
        "name:xx": "Jack Creek"
      }
    }
  ]
}
