{
  "geometry": {
    "type": "Point",
    "coordinates": [
      -80.3667,
      38.4833
    ]
  },
  "type": "Feature",
  "properties": {
    "hierarchy": [
      "tgn:2425946",
      "tgn:1000001",
      "tgn:7012149",
      "tgn:2002300",
      "tgn:7013961",
      "tgn:7029392"
    ],
    "placetype": [
      "aat:300008798"
    ],
    "id": 2425946,
    "name:xx": "Jonathan Knob"
  }
}
