{
  "geometry": {
    "type": "Point",
    "coordinates": [
      -82.6333,
      30.1833
    ]
  },
  "type": "Feature",
  "properties": {
    "hierarchy": [
      "tgn:2414838",
      "tgn:1000001",
      "tgn:2000262",
      "tgn:7012149",
      "tgn:7007240",
      "tgn:7029392"
    ],
    "placetype": [
      "aat:300006191"
    ],
    "id": 2414838,
    "name:xx": "Isabella, Lake"
  }
}
