{
  "type": "FeatureCollection",
  "features": [
    {
      "geometry": {
        "type": "Point",
        "coordinates": [
          -69.4167,
          45.4667
        ]
      },
      "type": "Feature",
      "properties": {
        "hierarchy": [
          "tgn:2197860",
          "tgn:1000001",
          "tgn:7012149",
          "tgn:2000928",
          "tgn:7007515",
          "tgn:7029392"
        ],
        "placetype": [
          "aat:300008680"
        ],
        "id": 2197860,
        "name:xx": "Brown Pond"
      }
    },
    {
      "geometry": {
        "type": "Point",
        "coordinates": [
          -72.1667,
          42.4833
        ]
      },
      "type": "Feature",
      "properties": {
        "hierarchy": [
          "tgn:2197861",
          "tgn:1000001",
          "tgn:7012149",
          "tgn:1003038",
          "tgn:7007517",
          "tgn:7029392"
        ],
        "placetype": [
          "aat:300006191"
        ],
        "id": 2197861,
        "name:xx": "Brown Pond"
      }
    },
    {
      "geometry": {
        "type": "Point",
        "coordinates": [
          -73.5667,
          43.65
        ]
      },
      "type": "Feature",
      "properties": {
        "hierarchy": [
          "tgn:2197862",
          "tgn:1000001",
          "tgn:7012149",
          "tgn:1002986",
          "tgn:7007568",
          "tgn:7029392"
        ],
        "placetype": [
          "aat:300008680"
        ],
        "id": 2197862,
        "name:xx": "Brown Pond"
      }
    },
    {
      "geometry": {
        "type": "Point",
        "coordinates": [
          -74.1,
          43.7333
        ]
      },
      "type": "Feature",
      "properties": {
        "hierarchy": [
          "tgn:2197863",
          "tgn:1000001",
          "tgn:7012149",
          "tgn:1002440",
          "tgn:7007568",
          "tgn:7029392"
        ],
        "placetype": [
          "aat:300008680"
        ],
        "id": 2197863,
        "name:xx": "Brown Pond"
      }
    },
    {
      "geometry": {
        "type": "Point",
        "coordinates": [
          -76.1833,
          41.65
        ]
      },
      "type": "Feature",
      "properties": {
        "hierarchy": [
          "tgn:2197864",
          "tgn:1000001",
          "tgn:7012149",
          "tgn:1003041",
          "tgn:7007710",
          "tgn:7029392"
        ],
        "placetype": [
          "aat:300008680"
        ],
        "id": 2197864,
        "name:xx": "Brown Pond"
      }
    },
    {
      "geometry": {
        "type": "Point",
        "coordinates": [
          -79.9667,
          32.9333
        ]
      },
      "type": "Feature",
      "properties": {
        "hierarchy": [
          "tgn:2197865",
          "tgn:2001732",
          "tgn:1000001",
          "tgn:7012149",
          "tgn:7007712",
          "tgn:7029392"
        ],
        "placetype": [
          "aat:300006191"
        ],
        "id": 2197865,
        "name:xx": "Brown Pond"
      }
    },
    {
      "geometry": {
        "type": "Point",
        "coordinates": [
          -84.5,
          36.5333
        ]
      },
      "type": "Feature",
      "properties": {
        "hierarchy": [
          "tgn:2197866",
          "tgn:1000001",
          "tgn:7012149",
          "tgn:2001912",
          "tgn:7007825",
          "tgn:7029392"
        ],
        "placetype": [
          "aat:300008680"
        ],
        "id": 2197866,
        "name:xx": "Brown Pond"
      }
    },
    {
      "geometry": {
        "type": "Point",
        "coordinates": [
          -71.9667,
          44.7167
        ]
      },
      "type": "Feature",
      "properties": {
        "hierarchy": [
          "tgn:2197867",
          "tgn:1000001",
          "tgn:1002753",
          "tgn:7012149",
          "tgn:7007828",
          "tgn:7029392"
        ],
        "placetype": [
          "aat:300008680"
        ],
        "id": 2197867,
        "name:xx": "Brown Pond"
      }
    },
    {
      "geometry": {
        "type": "Point",
        "coordinates": [
          -85.7833,
          33.3833
        ]
      },
      "type": "Feature",
      "properties": {
        "hierarchy": [
          "tgn:2197868",
          "tgn:7002659",
          "tgn:1000001",
          "tgn:2000013",
          "tgn:7012149",
          "tgn:7029392"
        ],
        "placetype": [
          "aat:300000390"
        ],
        "id": 2197868,
        "name:xx": "Brown Prospect"
      }
    },
    {
      "geometry": {
        "type": "Point",
        "coordinates": [
          -82.9333,
          36.2167
        ]
      },
      "type": "Feature",
      "properties": {
        "hierarchy": [
          "tgn:2197869",
          "tgn:1000001",
          "tgn:7012149",
          "tgn:2001866",
          "tgn:7007825",
          "tgn:7029392"
        ],
        "placetype": [
          "aat:300000390"
        ],
        "id": 2197869,
        "name:xx": "Brown Prospect"
      }
    }
  ]
}
