{
  "type": "FeatureCollection",
  "features": [
    {
      "geometry": {
        "type": "Point",
        "coordinates": [
          146.3333,
          -38.6667
        ]
      },
      "type": "Feature",
      "properties": {
        "hierarchy": [
          "tgn:1098350",
          "tgn:7000490",
          "tgn:1000006",
          "tgn:7006238",
          "tgn:7029392"
        ],
        "placetype": [
          "aat:300008347"
        ],
        "id": 1098350,
        "name:xx": "Toora"
      }
    },
    {
      "geometry": {
        "type": "Point",
        "coordinates": [
          131.8,
          -16.5333
        ]
      },
      "type": "Feature",
      "properties": {
        "hierarchy": [
          "tgn:1098352",
          "tgn:7000490",
          "tgn:1000006",
          "tgn:7001829",
          "tgn:7029392"
        ],
        "placetype": [
          "aat:300008347"
        ],
        "id": 1098352,
        "name:xx": "Top Springs"
      }
    },
    {
      "geometry": {
        "type": "Point",
        "coordinates": [
          151.55,
          -33.0167
        ]
      },
      "type": "Feature",
      "properties": {
        "hierarchy": [
          "tgn:1098353",
          "tgn:7000490",
          "tgn:1000006",
          "tgn:7001828",
          "tgn:7029392"
        ],
        "placetype": [
          "aat:300008347"
        ],
        "id": 1098353,
        "name:xx": "Toronto"
      }
    },
    {
      "geometry": {
        "type": "Point",
        "coordinates": [
          144.3167,
          -38.5
        ]
      },
      "type": "Feature",
      "properties": {
        "hierarchy": [
          "tgn:1098354",
          "tgn:7000490",
          "tgn:1000006",
          "tgn:7006238",
          "tgn:7029392"
        ],
        "placetype": [
          "aat:300008347"
        ],
        "id": 1098354,
        "name:xx": "Torquay"
      }
    },
    {
      "geometry": {
        "type": "Point",
        "coordinates": [
          145,
          -20.8333
        ]
      },
      "type": "Feature",
      "properties": {
        "hierarchy": [
          "tgn:1098355",
          "tgn:7000490",
          "tgn:1000006",
          "tgn:7001830",
          "tgn:7029392"
        ],
        "placetype": [
          "aat:300008347"
        ],
        "id": 1098355,
        "name:xx": "Torrens Creek"
      }
    },
    {
      "geometry": {
        "type": "Point",
        "coordinates": [
          147.4,
          -32.2333
        ]
      },
      "type": "Feature",
      "properties": {
        "hierarchy": [
          "tgn:1098356",
          "tgn:7000490",
          "tgn:1000006",
          "tgn:7001828",
          "tgn:7029392"
        ],
        "placetype": [
          "aat:300008347"
        ],
        "id": 1098356,
        "name:xx": "Tottenham"
      }
    },
    {
      "geometry": {
        "type": "Point",
        "coordinates": [
          151.5333,
          -33.2667
        ]
      },
      "type": "Feature",
      "properties": {
        "hierarchy": [
          "tgn:1098357",
          "tgn:7000490",
          "tgn:1000006",
          "tgn:7001828",
          "tgn:7029392"
        ],
        "placetype": [
          "aat:300008347"
        ],
        "id": 1098357,
        "name:xx": "Toukley"
      }
    },
    {
      "geometry": {
        "type": "Point",
        "coordinates": [
          144.6,
          -22.05
        ]
      },
      "type": "Feature",
      "properties": {
        "hierarchy": [
          "tgn:1098358",
          "tgn:7000490",
          "tgn:1000006",
          "tgn:7001830",
          "tgn:7029392"
        ],
        "placetype": [
          "aat:300008347"
        ],
        "id": 1098358,
        "name:xx": "Tower Hill"
      }
    }
  ]
}
