{
  "geometry": {
    "type": "Point",
    "coordinates": [
      -75.4833,
      41.15
    ]
  },
  "type": "Feature",
  "properties": {
    "hierarchy": [
      "tgn:2693362",
      "tgn:1000001",
      "tgn:7012149",
      "tgn:1002682",
      "tgn:7007710",
      "tgn:7029392"
    ],
    "placetype": [
      "aat:300008905"
    ],
    "id": 2693362,
    "name:xx": "Stein Swamp"
  }
}
