{
  "geometry": {
    "type": "Point",
    "coordinates": [
      -85.95,
      34.8167
    ]
  },
  "type": "Feature",
  "properties": {
    "hierarchy": [
      "tgn:2293442",
      "tgn:7002659",
      "tgn:1000001",
      "tgn:7012149",
      "tgn:2000035",
      "tgn:7029392"
    ],
    "placetype": [
      "aat:300008746"
    ],
    "id": 2293442,
    "name:xx": "Double Natural Bridge Cave"
  }
}
