{
  "type": "FeatureCollection",
  "features": [
    {
      "geometry": {
        "type": "Point",
        "coordinates": [
          10.316667,
          44.916667
        ]
      },
      "type": "Feature",
      "properties": {
        "hierarchy": [
          "tgn:7038210",
          "tgn:7003131",
          "tgn:1000003",
          "tgn:7008516",
          "tgn:1000080",
          "tgn:7029392"
        ],
        "placetype": [
          "aat:300008347"
        ],
        "id": 7038210,
        "name:xx": "Torrile"
      }
    },
    {
      "geometry": {
        "type": "Point",
        "coordinates": [
          8.7,
          40.2
        ]
      },
      "type": "Feature",
      "properties": {
        "hierarchy": [
          "tgn:7038213",
          "tgn:1001730",
          "tgn:1000003",
          "tgn:7003121",
          "tgn:1000080",
          "tgn:7029392"
        ],
        "placetype": [
          "aat:300008795"
        ],
        "id": 7038213,
        "name:xx": "Torrigas, Punta"
      }
    },
    {
      "geometry": {
        "type": "Point",
        "coordinates": [
          11.616667,
          45.516667
        ]
      },
      "type": "Feature",
      "properties": {
        "hierarchy": [
          "tgn:7038214",
          "tgn:7003008",
          "tgn:1000003",
          "tgn:7002997",
          "tgn:1000080",
          "tgn:7029392"
        ],
        "placetype": [
          "aat:300008347"
        ],
        "id": 7038214,
        "name:xx": "Torri di Quartesolo"
      }
    },
    {
      "geometry": {
        "type": "Point",
        "coordinates": [
          10.683333,
          45.6
        ]
      },
      "type": "Feature",
      "properties": {
        "hierarchy": [
          "tgn:7038215",
          "tgn:7003007",
          "tgn:1000003",
          "tgn:7002997",
          "tgn:1000080",
          "tgn:7029392"
        ],
        "placetype": [
          "aat:300008347"
        ],
        "id": 7038215,
        "name:xx": "Torri del Benaco"
      }
    },
    {
      "geometry": {
        "type": "Point",
        "coordinates": [
          10.283333,
          45.016667
        ]
      },
      "type": "Feature",
      "properties": {
        "hierarchy": [
          "tgn:7038219",
          "tgn:7003131",
          "tgn:1000003",
          "tgn:7008516",
          "tgn:1000080",
          "tgn:7029392"
        ],
        "placetype": [
          "aat:300008347"
        ],
        "id": 7038219,
        "name:xx": "Torricella del Pizzo"
      }
    }
  ]
}
