{
  "type": "FeatureCollection",
  "features": [
    {
      "geometry": {
        "type": "Point",
        "coordinates": [
          13.066667,
          42.616667
        ]
      },
      "type": "Feature",
      "properties": {
        "hierarchy": [
          "tgn:7041180",
          "tgn:7003137",
          "tgn:1000003",
          "tgn:7003080",
          "tgn:1000080",
          "tgn:7029392"
        ],
        "placetype": [
          "aat:300008347"
        ],
        "id": 7041180,
        "name:xx": "San Pietro"
      }
    },
    {
      "geometry": {
        "type": "Point",
        "coordinates": [
          13.633333,
          42.483333
        ]
      },
      "type": "Feature",
      "properties": {
        "hierarchy": [
          "tgn:7041181",
          "tgn:7009084",
          "tgn:7003001",
          "tgn:1000003",
          "tgn:1000080",
          "tgn:7029392"
        ],
        "placetype": [
          "aat:300008347"
        ],
        "id": 7041181,
        "name:xx": "San Pietro"
      }
    },
    {
      "geometry": {
        "type": "Point",
        "coordinates": [
          13.3,
          42.416667
        ]
      },
      "type": "Feature",
      "properties": {
        "hierarchy": [
          "tgn:7041182",
          "tgn:7009084",
          "tgn:7004154",
          "tgn:1000003",
          "tgn:1000080",
          "tgn:7029392"
        ],
        "placetype": [
          "aat:300008347"
        ],
        "id": 7041182,
        "name:xx": "San Pietro"
      }
    },
    {
      "geometry": {
        "type": "Point",
        "coordinates": [
          13.15,
          42.233333
        ]
      },
      "type": "Feature",
      "properties": {
        "hierarchy": [
          "tgn:7041183",
          "tgn:7003137",
          "tgn:1000003",
          "tgn:7003080",
          "tgn:1000080",
          "tgn:7029392"
        ],
        "placetype": [
          "aat:300008347"
        ],
        "id": 7041183,
        "name:xx": "San Pietro"
      }
    },
    {
      "geometry": {
        "type": "Point",
        "coordinates": [
          13.85,
          41.633333
        ]
      },
      "type": "Feature",
      "properties": {
        "hierarchy": [
          "tgn:7041184",
          "tgn:7003135",
          "tgn:1000003",
          "tgn:7003080",
          "tgn:1000080",
          "tgn:7029392"
        ],
        "placetype": [
          "aat:300008347"
        ],
        "id": 7041184,
        "name:xx": "San Pietro"
      }
    },
    {
      "geometry": {
        "type": "Point",
        "coordinates": [
          14.716667,
          40.7
        ]
      },
      "type": "Feature",
      "properties": {
        "hierarchy": [
          "tgn:7041185",
          "tgn:7003005",
          "tgn:7003014",
          "tgn:1000003",
          "tgn:1000080",
          "tgn:7029392"
        ],
        "placetype": [
          "aat:300008347"
        ],
        "id": 7041185,
        "name:xx": "San Pietro"
      }
    },
    {
      "geometry": {
        "type": "Point",
        "coordinates": [
          16.033333,
          39.4
        ]
      },
      "type": "Feature",
      "properties": {
        "hierarchy": [
          "tgn:7041187",
          "tgn:1003450",
          "tgn:7007850",
          "tgn:1000003",
          "tgn:1000080",
          "tgn:7029392"
        ],
        "placetype": [
          "aat:300008347"
        ],
        "id": 7041187,
        "name:xx": "San Pietro"
      }
    },
    {
      "geometry": {
        "type": "Point",
        "coordinates": [
          17.066667,
          38.983333
        ]
      },
      "type": "Feature",
      "properties": {
        "hierarchy": [
          "tgn:7041189",
          "tgn:7024841",
          "tgn:7007850",
          "tgn:1000003",
          "tgn:1000080",
          "tgn:7029392"
        ],
        "placetype": [
          "aat:300008347"
        ],
        "id": 7041189,
        "name:xx": "Casa San Pietro"
      }
    }
  ]
}
