{
  "geometry": {
    "type": "Point",
    "coordinates": [
      -112.3167,
      37.5333
    ]
  },
  "type": "Feature",
  "properties": {
    "hierarchy": [
      "tgn:2180990",
      "tgn:1000001",
      "tgn:7012149",
      "tgn:7007827",
      "tgn:7029392"
    ],
    "placetype": [
      "aat:300008706"
    ],
    "id": 2180990,
    "name:xx": "Blubber Creek"
  }
}
