{
  "geometry": {
    "type": "Point",
    "coordinates": [
      -90.5833,
      29.2167
    ]
  },
  "type": "Feature",
  "properties": {
    "hierarchy": [
      "tgn:2443643",
      "tgn:1000001",
      "tgn:7012149",
      "tgn:2000908",
      "tgn:7007256",
      "tgn:7029392"
    ],
    "placetype": [
      "aat:300008680"
    ],
    "id": 2443643,
    "name:xx": "La Graisse, Lake"
  }
}
