{
  "geometry": {
    "type": "Point",
    "coordinates": [
      -109.0667,
      47.2333
    ]
  },
  "type": "Feature",
  "properties": {
    "hierarchy": [
      "tgn:2737000",
      "tgn:1000001",
      "tgn:7012149",
      "tgn:2001273",
      "tgn:7007524",
      "tgn:7029392"
    ],
    "placetype": [
      "aat:300000390"
    ],
    "id": 2737000,
    "name:xx": "Two Lady Number 5 Mine"
  }
}
