{
  "geometry": {
    "type": "Point",
    "coordinates": [
      -2.0167,
      53.65
    ]
  },
  "type": "Feature",
  "properties": {
    "hierarchy": [
      "tgn:1103524",
      "tgn:1003573",
      "tgn:7002445",
      "tgn:1000003",
      "tgn:7029507",
      "tgn:7008591",
      "tgn:7029392"
    ],
    "placetype": [
      "aat:300386886"
    ],
    "id": 1103524,
    "name:xx": "Rishworth Moor"
  }
}
