{
  "geometry": {
    "type": "Point",
    "coordinates": [
      -89.2833,
      32.45
    ]
  },
  "type": "Feature",
  "properties": {
    "hierarchy": [
      "tgn:2056213",
      "tgn:1000001",
      "tgn:7012149",
      "tgn:2001136",
      "tgn:7007522",
      "tgn:7029392"
    ],
    "placetype": [
      "aat:300008347"
    ],
    "id": 2056213,
    "name:xx": "Conehatta"
  }
}
