{
  "geometry": {
    "type": "Point",
    "coordinates": [
      -72.15,
      42.5667
    ]
  },
  "type": "Feature",
  "properties": {
    "hierarchy": [
      "tgn:2512260",
      "tgn:1000001",
      "tgn:7012149",
      "tgn:1003038",
      "tgn:7007517",
      "tgn:7029392"
    ],
    "placetype": [
      "aat:300008699"
    ],
    "id": 2512260,
    "name:xx": "Mill Brook"
  }
}
