{
  "geometry": {
    "type": "Point",
    "coordinates": [
      -93.7333,
      40.7333
    ]
  },
  "type": "Feature",
  "properties": {
    "hierarchy": [
      "tgn:2035103",
      "tgn:1000001",
      "tgn:7019179",
      "tgn:7012149",
      "tgn:7007253",
      "tgn:7029392"
    ],
    "placetype": [
      "aat:300008347"
    ],
    "id": 2035103,
    "name:xx": "Leon"
  }
}
