{
  "geometry": {
    "type": "Point",
    "coordinates": [
      -87.9833,
      37.2667
    ]
  },
  "type": "Feature",
  "properties": {
    "hierarchy": [
      "tgn:2205032",
      "tgn:1000001",
      "tgn:7012149",
      "tgn:7007255",
      "tgn:7029392"
    ],
    "placetype": [
      "aat:300008699"
    ],
    "id": 2205032,
    "name:xx": "Buggs Branch"
  }
}
