{
  "geometry": {
    "type": "Point",
    "coordinates": [
      -80.1833,
      33.9667
    ]
  },
  "type": "Feature",
  "properties": {
    "hierarchy": [
      "tgn:2497797",
      "tgn:1000001",
      "tgn:7012149",
      "tgn:2001767",
      "tgn:7007712",
      "tgn:7029392"
    ],
    "placetype": [
      "aat:300008347"
    ],
    "id": 2497797,
    "name:xx": "Mayesville East Subdivision"
  }
}
