{
  "geometry": {
    "type": "Point",
    "coordinates": [
      -80.75,
      36.5167
    ]
  },
  "type": "Feature",
  "properties": {
    "hierarchy": [
      "tgn:2523191",
      "tgn:1000001",
      "tgn:7012149",
      "tgn:7029392"
    ],
    "placetype": [
      "aat:300008699"
    ],
    "id": 2523191,
    "name:xx": "Moores Fork"
  }
}
