{
  "geometry": {
    "type": "Point",
    "coordinates": [
      17.35,
      4.3333
    ]
  },
  "type": "Feature",
  "properties": {
    "hierarchy": [
      "tgn:1088343",
      "tgn:7001242",
      "tgn:1001002",
      "tgn:1000155",
      "tgn:7029392"
    ],
    "placetype": [
      "aat:300008347"
    ],
    "id": 1088343,
    "name:xx": "Bolay I"
  }
}
