{
  "geometry": {
    "type": "Point",
    "coordinates": [
      -83.5333,
      37.65
    ]
  },
  "type": "Feature",
  "properties": {
    "hierarchy": [
      "tgn:2226991",
      "tgn:1000001",
      "tgn:7012149",
      "tgn:7007255",
      "tgn:7029392"
    ],
    "placetype": [
      "aat:300008699"
    ],
    "id": 2226991,
    "name:xx": "Cave Branch"
  }
}
