{
  "geometry": {
    "type": "Point",
    "coordinates": [
      -95.6833,
      35.1833
    ]
  },
  "type": "Feature",
  "properties": {
    "hierarchy": [
      "tgn:2083953",
      "tgn:1000001",
      "tgn:7012149",
      "tgn:2001683",
      "tgn:7007707",
      "tgn:7029392"
    ],
    "placetype": [
      "aat:300008347"
    ],
    "id": 2083953,
    "name:xx": "Sams Point"
  }
}
