{
  "geometry": {
    "type": "Point",
    "coordinates": [
      -118.5833,
      42.7833
    ]
  },
  "type": "Feature",
  "properties": {
    "hierarchy": [
      "tgn:2402342",
      "tgn:1000001",
      "tgn:7012149",
      "tgn:2001709",
      "tgn:7007708",
      "tgn:7029392"
    ],
    "placetype": [
      "aat:300008706"
    ],
    "id": 2402342,
    "name:xx": "Horton Creek"
  }
}
