{
  "geometry": {
    "type": "Point",
    "coordinates": [
      20.0833,
      60.2667
    ]
  },
  "type": "Feature",
  "properties": {
    "hierarchy": [
      "tgn:4009864",
      "tgn:7594378",
      "tgn:1000003",
      "tgn:1000069",
      "tgn:7029392"
    ],
    "placetype": [
      "aat:300008347"
    ],
    "id": 4009864,
    "name:xx": "Saltvik"
  }
}
