{
  "geometry": {
    "type": "Point",
    "coordinates": [
      -72.3333,
      8.6167
    ]
  },
  "type": "Feature",
  "properties": {
    "hierarchy": [
      "tgn:1025108",
      "tgn:1001985",
      "tgn:1000002",
      "tgn:1000059",
      "tgn:7029392"
    ],
    "placetype": [
      "aat:300008347"
    ],
    "id": 1025108,
    "name:xx": "El Guayabo"
  }
}
