{
  "geometry": {
    "type": "Point",
    "coordinates": [
      -86.25,
      40.9833
    ]
  },
  "type": "Feature",
  "properties": {
    "hierarchy": [
      "tgn:2757098",
      "tgn:1000001",
      "tgn:7012149",
      "tgn:1002396",
      "tgn:7007252",
      "tgn:7029392"
    ],
    "placetype": [
      "aat:300006075"
    ],
    "id": 2757098,
    "name:xx": "Werner Ditch"
  }
}
