{
  "type": "FeatureCollection",
  "features": [
    {
      "geometry": {
        "type": "Point",
        "coordinates": [
          -109.65,
          45.8167
        ]
      },
      "type": "Feature",
      "properties": {
        "hierarchy": [
          "tgn:2279660",
          "tgn:1000001",
          "tgn:7012149",
          "tgn:2001308",
          "tgn:7007524",
          "tgn:7029392"
        ],
        "placetype": [
          "aat:300008706"
        ],
        "id": 2279660,
        "name:xx": "Deadmans Creek"
      }
    },
    {
      "geometry": {
        "type": "Point",
        "coordinates": [
          -101.95,
          44.2333
        ]
      },
      "type": "Feature",
      "properties": {
        "hierarchy": [
          "tgn:2279661",
          "tgn:1000001",
          "tgn:2001797",
          "tgn:7012149",
          "tgn:7007713",
          "tgn:7029392"
        ],
        "placetype": [
          "aat:300008706"
        ],
        "id": 2279661,
        "name:xx": "Deadmans Creek"
      }
    },
    {
      "geometry": {
        "type": "Point",
        "coordinates": [
          -116.1833,
          47.6167
        ]
      },
      "type": "Feature",
      "properties": {
        "hierarchy": [
          "tgn:2279662",
          "tgn:1000001",
          "tgn:7012149",
          "tgn:2000491",
          "tgn:7007250",
          "tgn:7029392"
        ],
        "placetype": [
          "aat:300132316"
        ],
        "id": 2279662,
        "name:xx": "Deadmans Eddy"
      }
    },
    {
      "geometry": {
        "type": "Point",
        "coordinates": [
          -117.7167,
          48.9333
        ]
      },
      "type": "Feature",
      "properties": {
        "hierarchy": [
          "tgn:2279663",
          "tgn:1000001",
          "tgn:7012149",
          "tgn:2002250",
          "tgn:7007920",
          "tgn:7029392"
        ],
        "placetype": [
          "aat:300132316"
        ],
        "id": 2279663,
        "name:xx": "Deadmans Eddy"
      }
    },
    {
      "geometry": {
        "type": "Point",
        "coordinates": [
          -117.35,
          48.8667
        ]
      },
      "type": "Feature",
      "properties": {
        "hierarchy": [
          "tgn:2279664",
          "tgn:1000001",
          "tgn:7012149",
          "tgn:2002248",
          "tgn:7007920",
          "tgn:7029392"
        ],
        "placetype": [
          "aat:300132316"
        ],
        "id": 2279664,
        "name:xx": "Deadmans Eddy"
      }
    },
    {
      "geometry": {
        "type": "Point",
        "coordinates": [
          -122.7167,
          38.0167
        ]
      },
      "type": "Feature",
      "properties": {
        "hierarchy": [
          "tgn:2279665",
          "tgn:1000001",
          "tgn:7012149",
          "tgn:7007157",
          "tgn:7014005",
          "tgn:7029392"
        ],
        "placetype": [
          "aat:300008761"
        ],
        "id": 2279665,
        "name:xx": "Deadmans Gulch"
      }
    },
    {
      "geometry": {
        "type": "Point",
        "coordinates": [
          -107.2,
          39.5333
        ]
      },
      "type": "Feature",
      "properties": {
        "hierarchy": [
          "tgn:2279666",
          "tgn:1000001",
          "tgn:7012149",
          "tgn:2000214",
          "tgn:7007158",
          "tgn:7029392"
        ],
        "placetype": [
          "aat:300008761"
        ],
        "id": 2279666,
        "name:xx": "Deadmans Gulch"
      }
    },
    {
      "geometry": {
        "type": "Point",
        "coordinates": [
          -107.9833,
          38.5167
        ]
      },
      "type": "Feature",
      "properties": {
        "hierarchy": [
          "tgn:2279667",
          "tgn:1000001",
          "tgn:7012149",
          "tgn:2000234",
          "tgn:7007158",
          "tgn:7029392"
        ],
        "placetype": [
          "aat:300008761"
        ],
        "id": 2279667,
        "name:xx": "Deadmans Gulch"
      }
    },
    {
      "geometry": {
        "type": "Point",
        "coordinates": [
          -74.8333,
          43.65
        ]
      },
      "type": "Feature",
      "properties": {
        "hierarchy": [
          "tgn:2279669",
          "tgn:1000001",
          "tgn:7012149",
          "tgn:1002472",
          "tgn:7007568",
          "tgn:7029392"
        ],
        "placetype": [
          "aat:300008761"
        ],
        "id": 2279669,
        "name:xx": "Deadmans Gulch"
      }
    }
  ]
}
