{
  "geometry": {
    "type": "Point",
    "coordinates": [
      -104.6167,
      36.9833
    ]
  },
  "type": "Feature",
  "properties": {
    "hierarchy": [
      "tgn:2179982",
      "tgn:1000001",
      "tgn:7012149",
      "tgn:7029392"
    ],
    "placetype": [
      "aat:300008761"
    ],
    "id": 2179982,
    "name:xx": "Blind Canyon"
  }
}
