{
  "geometry": {
    "type": "Point",
    "coordinates": [
      -84.0167,
      44.3167
    ]
  },
  "type": "Feature",
  "properties": {
    "hierarchy": [
      "tgn:2280491",
      "tgn:1000001",
      "tgn:7012149",
      "tgn:2000985",
      "tgn:7007520",
      "tgn:7029392"
    ],
    "placetype": [
      "aat:300008706"
    ],
    "id": 2280491,
    "name:xx": "Dedrich Creek"
  }
}
