{
  "geometry": {
    "type": "Point",
    "coordinates": [
      -119.7333,
      39.4333
    ]
  },
  "type": "Feature",
  "properties": {
    "hierarchy": [
      "tgn:2293308",
      "tgn:1000001",
      "tgn:7012149",
      "tgn:1002999",
      "tgn:7007526",
      "tgn:7029392"
    ],
    "placetype": [
      "aat:300008697"
    ],
    "id": 2293308,
    "name:xx": "Double Diamond Spring"
  }
}
