{
  "geometry": {
    "type": "Point",
    "coordinates": [
      -115.4833,
      47.6333
    ]
  },
  "type": "Feature",
  "properties": {
    "hierarchy": [
      "tgn:2526065",
      "tgn:1000001",
      "tgn:7012149",
      "tgn:2001304",
      "tgn:7007524",
      "tgn:7029392"
    ],
    "placetype": [
      "aat:300008706"
    ],
    "id": 2526065,
    "name:xx": "Mosquito Creek"
  }
}
