{
  "type": "FeatureCollection",
  "features": [
    {
      "geometry": {
        "type": "Point",
        "coordinates": [
          -103.533333,
          27.533333
        ]
      },
      "type": "Feature",
      "properties": {
        "hierarchy": [
          "tgn:7386340",
          "tgn:1001853",
          "tgn:1000001",
          "tgn:7005560",
          "tgn:7029392"
        ],
        "placetype": [
          "aat:300008795"
        ],
        "id": 7386340,
        "name:xx": "Prietos, Cerros"
      }
    },
    {
      "geometry": {
        "type": "Point",
        "coordinates": [
          -104.25,
          26.866667
        ]
      },
      "type": "Feature",
      "properties": {
        "hierarchy": [
          "tgn:7386341",
          "tgn:7005581",
          "tgn:1000001",
          "tgn:7005560",
          "tgn:7029392"
        ],
        "placetype": [
          "aat:300008795"
        ],
        "id": 7386341,
        "name:xx": "Prietos, Cerros"
      }
    },
    {
      "geometry": {
        "type": "Point",
        "coordinates": [
          -103.166667,
          26.066667
        ]
      },
      "type": "Feature",
      "properties": {
        "hierarchy": [
          "tgn:7386342",
          "tgn:1001853",
          "tgn:1000001",
          "tgn:7005560",
          "tgn:7029392"
        ],
        "placetype": [
          "aat:300008777"
        ],
        "id": 7386342,
        "name:xx": "Prietos, Cerros"
      }
    },
    {
      "geometry": {
        "type": "Point",
        "coordinates": [
          -104.35,
          29.05
        ]
      },
      "type": "Feature",
      "properties": {
        "hierarchy": [
          "tgn:7386343",
          "tgn:7005581",
          "tgn:1000001",
          "tgn:7005560",
          "tgn:7029392"
        ],
        "placetype": [
          "aat:300008777"
        ],
        "id": 7386343,
        "name:xx": "Prieto, Cerros"
      }
    },
    {
      "geometry": {
        "type": "Point",
        "coordinates": [
          -115.308056,
          32.413889
        ]
      },
      "type": "Feature",
      "properties": {
        "hierarchy": [
          "tgn:7386344",
          "tgn:1001835",
          "tgn:1000001",
          "tgn:7005560",
          "tgn:7029392"
        ],
        "placetype": [
          "aat:300008795"
        ],
        "id": 7386344,
        "name:xx": "Prieto, Cerro"
      }
    },
    {
      "geometry": {
        "type": "Point",
        "coordinates": [
          -117.066667,
          32.4
        ]
      },
      "type": "Feature",
      "properties": {
        "hierarchy": [
          "tgn:7386345",
          "tgn:1001835",
          "tgn:1000001",
          "tgn:7005560",
          "tgn:7029392"
        ],
        "placetype": [
          "aat:300008795"
        ],
        "id": 7386345,
        "name:xx": "Prieto, Cerro"
      }
    },
    {
      "geometry": {
        "type": "Point",
        "coordinates": [
          -115.883333,
          32.25
        ]
      },
      "type": "Feature",
      "properties": {
        "hierarchy": [
          "tgn:7386346",
          "tgn:1001835",
          "tgn:1000001",
          "tgn:7005560",
          "tgn:7029392"
        ],
        "placetype": [
          "aat:300008795"
        ],
        "id": 7386346,
        "name:xx": "Prieto, Cerro"
      }
    },
    {
      "geometry": {
        "type": "Point",
        "coordinates": [
          -112.966667,
          31.883333
        ]
      },
      "type": "Feature",
      "properties": {
        "hierarchy": [
          "tgn:7386347",
          "tgn:1000001",
          "tgn:1001960",
          "tgn:7005560",
          "tgn:7029392"
        ],
        "placetype": [
          "aat:300008795"
        ],
        "id": 7386347,
        "name:xx": "Prieto, Cerro"
      }
    },
    {
      "geometry": {
        "type": "Point",
        "coordinates": [
          -115.916667,
          31.216667
        ]
      },
      "type": "Feature",
      "properties": {
        "hierarchy": [
          "tgn:7386348",
          "tgn:1001835",
          "tgn:1000001",
          "tgn:7005560",
          "tgn:7029392"
        ],
        "placetype": [
          "aat:300008795"
        ],
        "id": 7386348,
        "name:xx": "Prieto, Cerro"
      }
    },
    {
      "geometry": {
        "type": "Point",
        "coordinates": [
          -110.8,
          31.15
        ]
      },
      "type": "Feature",
      "properties": {
        "hierarchy": [
          "tgn:7386349",
          "tgn:1000001",
          "tgn:1001960",
          "tgn:7005560",
          "tgn:7029392"
        ],
        "placetype": [
          "aat:300008795"
        ],
        "id": 7386349,
        "name:xx": "Prieto, Cerro"
      }
    }
  ]
}
