{
  "geometry": {
    "type": "Point",
    "coordinates": [
      -119.9833,
      47.55
    ]
  },
  "type": "Feature",
  "properties": {
    "hierarchy": [
      "tgn:2131235",
      "tgn:1000001",
      "tgn:2002242",
      "tgn:7012149",
      "tgn:7007920",
      "tgn:7029392"
    ],
    "placetype": [
      "aat:300008347"
    ],
    "id": 2131235,
    "name:xx": "Alstown"
  }
}
