{
  "geometry": {
    "type": "Point",
    "coordinates": [
      -81.2167,
      36.9167
    ]
  },
  "type": "Feature",
  "properties": {
    "hierarchy": [
      "tgn:2775276",
      "tgn:1000001",
      "tgn:7012149",
      "tgn:2002196",
      "tgn:7007919",
      "tgn:7029392"
    ],
    "placetype": [
      "aat:300008347"
    ],
    "id": 2775276,
    "name:xx": "Wilson"
  }
}
