{
  "geometry": {
    "type": "Point",
    "coordinates": [
      -94.7833,
      45.7333
    ]
  },
  "type": "Feature",
  "properties": {
    "hierarchy": [
      "tgn:2708823",
      "tgn:1000001",
      "tgn:7012149",
      "tgn:2001071",
      "tgn:7007521",
      "tgn:7029392"
    ],
    "placetype": [
      "aat:300006191"
    ],
    "id": 2708823,
    "name:xx": "Sylvia Lake"
  }
}
