{
  "geometry": {
    "type": "Point",
    "coordinates": [
      -104.8167,
      44.05
    ]
  },
  "type": "Feature",
  "properties": {
    "hierarchy": [
      "tgn:2756593",
      "tgn:1000001",
      "tgn:7012149",
      "tgn:2002387",
      "tgn:7007923",
      "tgn:7029392"
    ],
    "placetype": [
      "aat:300006191"
    ],
    "id": 2756593,
    "name:xx": "Wellman Reservoir"
  }
}
