{
  "type": "FeatureCollection",
  "features": [
    {
      "geometry": {
        "type": "Point",
        "coordinates": [
          -75.3667,
          37.8667
        ]
      },
      "type": "Feature",
      "properties": {
        "hierarchy": [
          "tgn:1120760",
          "tgn:1002132",
          "tgn:1000001",
          "tgn:7012149",
          "tgn:7007919",
          "tgn:7029392"
        ],
        "placetype": [
          "aat:300132317"
        ],
        "id": 1120760,
        "name:xx": "Toms Cove"
      }
    },
    {
      "geometry": {
        "type": "Point",
        "coordinates": [
          -73.5167,
          41.0333
        ]
      },
      "type": "Feature",
      "properties": {
        "hierarchy": [
          "tgn:1120762",
          "tgn:1002366",
          "tgn:1000001",
          "tgn:7012149",
          "tgn:7007159",
          "tgn:7029392"
        ],
        "placetype": [
          "aat:300132317"
        ],
        "id": 1120762,
        "name:xx": "Westcott Cove"
      }
    },
    {
      "geometry": {
        "type": "Point",
        "coordinates": [
          -79.0667,
          43.1167
        ]
      },
      "type": "Feature",
      "properties": {
        "hierarchy": [
          "tgn:1120764",
          "tgn:1000001",
          "tgn:7029392"
        ],
        "placetype": [
          "aat:300008699"
        ],
        "id": 1120764,
        "name:xx": "The Whirlpool"
      }
    },
    {
      "geometry": {
        "type": "Point",
        "coordinates": [
          -63.8,
          -1.6833
        ]
      },
      "type": "Feature",
      "properties": {
        "hierarchy": [
          "tgn:1120765",
          "tgn:1001826",
          "tgn:1000047",
          "tgn:7002456",
          "tgn:1000002",
          "tgn:7029392"
        ],
        "placetype": [
          "aat:300008707"
        ],
        "id": 1120765,
        "name:xx": "Água Preta, Igarapé"
      }
    },
    {
      "geometry": {
        "type": "Point",
        "coordinates": [
          -56.7167,
          -13.7
        ]
      },
      "type": "Feature",
      "properties": {
        "hierarchy": [
          "tgn:1120766",
          "tgn:7006260",
          "tgn:7002454",
          "tgn:1000047",
          "tgn:1000002",
          "tgn:7029392"
        ],
        "placetype": [
          "aat:300008707"
        ],
        "id": 1120766,
        "name:xx": "Água Verde"
      }
    },
    {
      "geometry": {
        "type": "Point",
        "coordinates": [
          -6.9333,
          41.0333
        ]
      },
      "type": "Feature",
      "properties": {
        "hierarchy": [
          "tgn:1120767",
          "tgn:1000003",
          "tgn:7029392"
        ],
        "placetype": [
          "aat:300008707"
        ],
        "id": 1120767,
        "name:es": "Águeda"
      }
    },
    {
      "geometry": {
        "type": "Point",
        "coordinates": [
          -101.2,
          27.883333
        ]
      },
      "type": "Feature",
      "properties": {
        "hierarchy": [
          "tgn:1120768",
          "tgn:1001853",
          "tgn:1000001",
          "tgn:7005560",
          "tgn:7029392"
        ],
        "placetype": [
          "aat:300008707",
          "aat:300008699"
        ],
        "id": 1120768,
        "name:xx": "Álamos, Río de los"
      }
    }
  ]
}
