{
  "geometry": {
    "type": "Point",
    "coordinates": [
      -153.1333,
      70.9167
    ]
  },
  "type": "Feature",
  "properties": {
    "hierarchy": [
      "tgn:2586467",
      "tgn:7006450",
      "tgn:1000001",
      "tgn:7012149",
      "tgn:2124005",
      "tgn:7029392"
    ],
    "placetype": [
      "aat:300008850"
    ],
    "id": 2586467,
    "name:xx": "Pitt Point"
  }
}
