{
  "geometry": {
    "type": "Point",
    "coordinates": [
      0.4667,
      48.2667
    ]
  },
  "type": "Feature",
  "properties": {
    "hierarchy": [
      "tgn:1035295",
      "tgn:1000003",
      "tgn:7002893",
      "tgn:1000070",
      "tgn:7029392"
    ],
    "placetype": [
      "aat:300008347"
    ],
    "id": 1035295,
    "name:xx": "Saint Cosme-de-Vair"
  }
}
