{
  "geometry": {
    "type": "Point",
    "coordinates": [
      97.8667,
      16.55
    ]
  },
  "type": "Feature",
  "properties": {
    "hierarchy": [
      "tgn:1066066",
      "tgn:1000004",
      "tgn:7002188",
      "tgn:1000108",
      "tgn:7029392"
    ],
    "placetype": [
      "aat:300008347"
    ],
    "id": 1066066,
    "name:xx": "Kawbein"
  }
}
