{
  "geometry": {
    "type": "Point",
    "coordinates": [
      78.32313,
      27.910547
    ]
  },
  "type": "Feature",
  "properties": {
    "hierarchy": [
      "tgn:7545461",
      "tgn:1000004",
      "tgn:7000198",
      "tgn:7016722",
      "tgn:7029392"
    ],
    "placetype": [
      "aat:300008347"
    ],
    "name:en": "Barla",
    "id": 7545461
  }
}
