{
  "geometry": {
    "type": "Point",
    "coordinates": [
      -93.9333,
      45.8333
    ]
  },
  "type": "Feature",
  "properties": {
    "hierarchy": [
      "tgn:2055291",
      "tgn:1000001",
      "tgn:7012149",
      "tgn:2001047",
      "tgn:7007521",
      "tgn:7029392"
    ],
    "placetype": [
      "aat:300008347"
    ],
    "id": 2055291,
    "name:xx": "Ramey"
  }
}
