{
  "geometry": {
    "type": "Point",
    "coordinates": [
      -82.3333,
      36.7333
    ]
  },
  "type": "Feature",
  "properties": {
    "hierarchy": [
      "tgn:2503607",
      "tgn:1000001",
      "tgn:7012149",
      "tgn:2002188",
      "tgn:7007919",
      "tgn:7029392"
    ],
    "placetype": [
      "aat:300008699"
    ],
    "id": 2503607,
    "name:xx": "Meade Branch"
  }
}
