{
  "geometry": {
    "type": "Point",
    "coordinates": [
      -74.0333,
      40.4833
    ]
  },
  "type": "Feature",
  "properties": {
    "hierarchy": [
      "tgn:2333213",
      "tgn:1000001",
      "tgn:1002963",
      "tgn:7012149",
      "tgn:7007565",
      "tgn:7029392"
    ],
    "placetype": [
      "aat:300132348"
    ],
    "id": 2333213,
    "name:xx": "Flynns Knoll"
  }
}
