{
  "geometry": {
    "type": "Point",
    "coordinates": [
      -90.0667,
      35.4333
    ]
  },
  "type": "Feature",
  "properties": {
    "hierarchy": [
      "tgn:2098635",
      "tgn:1000001",
      "tgn:7012149",
      "tgn:2001920",
      "tgn:7007825",
      "tgn:7029392"
    ],
    "placetype": [
      "aat:300008347",
      "aat:300387210"
    ],
    "id": 2098635,
    "name:xx": "Corona"
  }
}
