{
  "geometry": {
    "type": "Point",
    "coordinates": [
      -73.3667,
      40.9167
    ]
  },
  "type": "Feature",
  "properties": {
    "hierarchy": [
      "tgn:2299246",
      "tgn:1000001",
      "tgn:7012149",
      "tgn:1002924",
      "tgn:7007568",
      "tgn:7029392"
    ],
    "placetype": [
      "aat:300008791"
    ],
    "id": 2299246,
    "name:xx": "Duck Island"
  }
}
