{
  "geometry": {
    "type": "Point",
    "coordinates": [
      -86.8667,
      35.6833
    ]
  },
  "type": "Feature",
  "properties": {
    "hierarchy": [
      "tgn:2267549",
      "tgn:1000001",
      "tgn:7012149",
      "tgn:2001896",
      "tgn:7007825",
      "tgn:7029392"
    ],
    "placetype": [
      "aat:300008699"
    ],
    "id": 2267549,
    "name:xx": "Crockett Branch"
  }
}
