{
  "geometry": {
    "type": "Point",
    "coordinates": [
      -81.6833,
      39.1167
    ]
  },
  "type": "Feature",
  "properties": {
    "hierarchy": [
      "tgn:2661222",
      "tgn:1000001",
      "tgn:7012149",
      "tgn:2002303",
      "tgn:7013961",
      "tgn:7029392"
    ],
    "placetype": [
      "aat:300008699"
    ],
    "id": 2661222,
    "name:xx": "Short Run"
  }
}
