{
  "geometry": {
    "type": "Point",
    "coordinates": [
      31.75,
      31.35
    ]
  },
  "type": "Feature",
  "properties": {
    "hierarchy": [
      "tgn:1001225",
      "tgn:7001242",
      "tgn:7016833",
      "tgn:7029392"
    ],
    "placetype": [
      "aat:300387064",
      "aat:300235093"
    ],
    "id": 1001225,
    "name:xx": "Muḩāfaz̧at Dumyāţ"
  }
}
