{
  "geometry": {
    "type": "Point",
    "coordinates": [
      -76.9667,
      38.2333
    ]
  },
  "type": "Feature",
  "properties": {
    "hierarchy": [
      "tgn:2393942",
      "tgn:1000001",
      "tgn:7012149",
      "tgn:1003018",
      "tgn:7007919",
      "tgn:7029392"
    ],
    "placetype": [
      "aat:300008850"
    ],
    "id": 2393942,
    "name:xx": "Hog Point"
  }
}
