{
  "geometry": {
    "type": "Point",
    "coordinates": [
      -117.5167,
      33.4667
    ]
  },
  "type": "Feature",
  "properties": {
    "hierarchy": [
      "tgn:2179974",
      "tgn:1000001",
      "tgn:7012149",
      "tgn:7007157",
      "tgn:1002748",
      "tgn:7029392"
    ],
    "placetype": [
      "aat:300008761"
    ],
    "id": 2179974,
    "name:xx": "Blind Canyon"
  }
}
