{
  "geometry": {
    "type": "Point",
    "coordinates": [
      -71.5333,
      44.0667
    ]
  },
  "type": "Feature",
  "properties": {
    "hierarchy": [
      "tgn:2392445",
      "tgn:1000001",
      "tgn:2001424",
      "tgn:7012149",
      "tgn:7007564",
      "tgn:7029392"
    ],
    "placetype": [
      "aat:300008798"
    ],
    "id": 2392445,
    "name:xx": "Hitchcock, Mount"
  }
}
