{
  "geometry": {
    "type": "Point",
    "coordinates": [
      -65.7833,
      45.9167
    ]
  },
  "type": "Feature",
  "properties": {
    "hierarchy": [
      "tgn:1122454",
      "tgn:7005685",
      "tgn:1000001",
      "tgn:7005799",
      "tgn:7029392"
    ],
    "placetype": [
      "aat:300008707"
    ],
    "id": 1122454,
    "name:xx": "Canaan River"
  }
}
