{
  "geometry": {
    "type": "Point",
    "coordinates": [
      -81.7167,
      31.0667
    ]
  },
  "type": "Feature",
  "properties": {
    "hierarchy": [
      "tgn:2241651",
      "tgn:1000001",
      "tgn:2000311",
      "tgn:7012149",
      "tgn:7007248",
      "tgn:7029392"
    ],
    "placetype": [
      "aat:300008791"
    ],
    "id": 2241651,
    "name:xx": "Clarks Island"
  }
}
