{
  "geometry": {
    "type": "Point",
    "coordinates": [
      -87.1167,
      34.3833
    ]
  },
  "type": "Feature",
  "properties": {
    "hierarchy": [
      "tgn:2698153",
      "tgn:7002659",
      "tgn:1000001",
      "tgn:7012149",
      "tgn:2000039",
      "tgn:7029392"
    ],
    "placetype": [
      "aat:300008699"
    ],
    "id": 2698153,
    "name:xx": "Stover Branch"
  }
}
