{
  "geometry": {
    "type": "Point",
    "coordinates": [
      -81.4667,
      38.1667
    ]
  },
  "type": "Feature",
  "properties": {
    "hierarchy": [
      "tgn:2513416",
      "tgn:1000001",
      "tgn:7012149",
      "tgn:2002270",
      "tgn:7013961",
      "tgn:7029392"
    ],
    "placetype": [
      "aat:300008761"
    ],
    "id": 2513416,
    "name:xx": "Mill Hollow"
  }
}
