{
  "geometry": {
    "type": "Point",
    "coordinates": [
      -106.7333,
      41.0333
    ]
  },
  "type": "Feature",
  "properties": {
    "hierarchy": [
      "tgn:2195954",
      "tgn:1000001",
      "tgn:2002368",
      "tgn:7012149",
      "tgn:7007923",
      "tgn:7029392"
    ],
    "placetype": [
      "aat:300000390"
    ],
    "id": 2195954,
    "name:xx": "Broadway Mine"
  }
}
