{
  "geometry": {
    "type": "Point",
    "coordinates": [
      -113.65,
      47.8667
    ]
  },
  "type": "Feature",
  "properties": {
    "hierarchy": [
      "tgn:2267123",
      "tgn:1000001",
      "tgn:7012149",
      "tgn:2001274",
      "tgn:7007524",
      "tgn:7029392"
    ],
    "placetype": [
      "aat:300008680"
    ],
    "id": 2267123,
    "name:xx": "Crevice Lake"
  }
}
