{
  "geometry": {
    "type": "Point",
    "coordinates": [
      -104.4167,
      35.8333
    ]
  },
  "type": "Feature",
  "properties": {
    "hierarchy": [
      "tgn:2127676",
      "tgn:1000001",
      "tgn:7012149",
      "tgn:2001446",
      "tgn:7007566",
      "tgn:7029392"
    ],
    "placetype": [
      "aat:300008761"
    ],
    "id": 2127676,
    "name:xx": "Alamito, Cañon"
  }
}
