{
  "geometry": {
    "type": "Point",
    "coordinates": [
      30.5833,
      -3.1333
    ]
  },
  "type": "Feature",
  "properties": {
    "hierarchy": [
      "tgn:7014956",
      "tgn:7001242",
      "tgn:7001630",
      "tgn:7029392"
    ],
    "placetype": [
      "aat:300387064",
      "aat:300000774"
    ],
    "id": 7014956,
    "name:xx": "Cankuzo"
  }
}
