{
  "geometry": {
    "type": "Point",
    "coordinates": [
      -119.2667,
      45.8667
    ]
  },
  "type": "Feature",
  "properties": {
    "hierarchy": [
      "tgn:2786565",
      "tgn:1000001",
      "tgn:7012149",
      "tgn:2001720",
      "tgn:7007708",
      "tgn:7029392"
    ],
    "placetype": [
      "aat:300006075"
    ],
    "id": 2786565,
    "name:xx": "Z Canal"
  }
}
