{
  "geometry": {
    "type": "Point",
    "coordinates": [
      -81.5333,
      28.4667
    ]
  },
  "type": "Feature",
  "properties": {
    "hierarchy": [
      "tgn:2472321",
      "tgn:1000001",
      "tgn:7012149",
      "tgn:1002749",
      "tgn:7007240",
      "tgn:7029392"
    ],
    "placetype": [
      "aat:300008680"
    ],
    "id": 2472321,
    "name:xx": "Louise, Lake"
  }
}
