{
  "geometry": {
    "type": "Point",
    "coordinates": [
      -95.9333,
      28.6167
    ]
  },
  "type": "Feature",
  "properties": {
    "hierarchy": [
      "tgn:2685619",
      "tgn:1000001",
      "tgn:7012149",
      "tgn:1002646",
      "tgn:7007826",
      "tgn:7029392"
    ],
    "placetype": [
      "aat:300132316"
    ],
    "id": 2685619,
    "name:xx": "Spring Bayou Cove"
  }
}
