{
  "geometry": {
    "type": "Point",
    "coordinates": [
      -93.5667,
      36.4833
    ]
  },
  "type": "Feature",
  "properties": {
    "hierarchy": [
      "tgn:7021298",
      "tgn:1000001",
      "tgn:7012149",
      "tgn:7029392"
    ],
    "placetype": [
      "aat:300008680",
      "aat:300006191"
    ],
    "id": 7021298,
    "name:xx": "Table Rock Lake"
  }
}
