{
  "type": "FeatureCollection",
  "features": [
    {
      "geometry": {
        "type": "Point",
        "coordinates": [
          -78.7333,
          44.6667
        ]
      },
      "type": "Feature",
      "properties": {
        "hierarchy": [
          "tgn:1116321",
          "tgn:7005685",
          "tgn:1000001",
          "tgn:7013154",
          "tgn:7029392"
        ],
        "placetype": [
          "aat:300008680"
        ],
        "id": 1116321,
        "name:xx": "Four Mile Lake"
      }
    },
    {
      "geometry": {
        "type": "Point",
        "coordinates": [
          -74.65,
          41.0333
        ]
      },
      "type": "Feature",
      "properties": {
        "hierarchy": [
          "tgn:1116324",
          "tgn:1000001",
          "tgn:1002934",
          "tgn:7012149",
          "tgn:7007565",
          "tgn:7029392"
        ],
        "placetype": [
          "aat:300008680"
        ],
        "id": 1116324,
        "name:xx": "Fox Hollow Lake"
      }
    },
    {
      "geometry": {
        "type": "Point",
        "coordinates": [
          -88.15,
          42.4
        ]
      },
      "type": "Feature",
      "properties": {
        "hierarchy": [
          "tgn:1116325",
          "tgn:1000001",
          "tgn:7012149",
          "tgn:7013855",
          "tgn:7007251",
          "tgn:7029392"
        ],
        "placetype": [
          "aat:300008680"
        ],
        "id": 1116325,
        "name:xx": "Fox Lake"
      }
    },
    {
      "geometry": {
        "type": "Point",
        "coordinates": [
          -125.8333,
          54.0333
        ]
      },
      "type": "Feature",
      "properties": {
        "hierarchy": [
          "tgn:1116328",
          "tgn:7005735",
          "tgn:7005685",
          "tgn:1000001",
          "tgn:7029392"
        ],
        "placetype": [
          "aat:300008680"
        ],
        "id": 1116328,
        "name:xx": "François Lake"
      }
    },
    {
      "geometry": {
        "type": "Point",
        "coordinates": [
          -129.2,
          61.25
        ]
      },
      "type": "Feature",
      "properties": {
        "hierarchy": [
          "tgn:1116329",
          "tgn:7005685",
          "tgn:1000001",
          "tgn:7005806",
          "tgn:7029392"
        ],
        "placetype": [
          "aat:300008680"
        ],
        "id": 1116329,
        "name:xx": "Frances Lake"
      }
    }
  ]
}
