{
  "geometry": {
    "type": "Point",
    "coordinates": [
      17.0667,
      -2.7167
    ]
  },
  "type": "Feature",
  "properties": {
    "hierarchy": [
      "tgn:1089110",
      "tgn:1001143",
      "tgn:7001242",
      "tgn:1000159",
      "tgn:7029392"
    ],
    "placetype": [
      "aat:300008347"
    ],
    "id": 1089110,
    "name:xx": "Kenia"
  }
}
