{
  "geometry": {
    "type": "Point",
    "coordinates": [
      -88.9375,
      20.3125
    ]
  },
  "type": "Feature",
  "properties": {
    "hierarchy": [
      "tgn:7402089",
      "tgn:1000001",
      "tgn:7005600",
      "tgn:7005560",
      "tgn:7029392"
    ],
    "placetype": [
      "aat:300008347"
    ],
    "id": 7402089,
    "name:xx": "Sisbic"
  }
}
