{
  "geometry": {
    "type": "Point",
    "coordinates": [
      -151.6333,
      61.2833
    ]
  },
  "type": "Feature",
  "properties": {
    "hierarchy": [
      "tgn:2236165",
      "tgn:7006450",
      "tgn:1000001",
      "tgn:7019698",
      "tgn:7012149",
      "tgn:7029392"
    ],
    "placetype": [
      "aat:300008706"
    ],
    "id": 2236165,
    "name:xx": "Chichantna Creek"
  }
}
