{
  "type": "FeatureCollection",
  "features": [
    {
      "geometry": {
        "type": "Point",
        "coordinates": [
          -91.6833,
          33.3
        ]
      },
      "type": "Feature",
      "properties": {
        "hierarchy": [
          "tgn:2696470",
          "tgn:2000106",
          "tgn:1000001",
          "tgn:7016172",
          "tgn:7012149",
          "tgn:7029392"
        ],
        "placetype": [
          "aat:300006191"
        ],
        "id": 2696470,
        "name:xx": "Stone Lake"
      }
    },
    {
      "geometry": {
        "type": "Point",
        "coordinates": [
          -121.4833,
          38.3333
        ]
      },
      "type": "Feature",
      "properties": {
        "hierarchy": [
          "tgn:2696471",
          "tgn:1000001",
          "tgn:7012149",
          "tgn:7007157",
          "tgn:1002841",
          "tgn:7029392"
        ],
        "placetype": [
          "aat:300008680"
        ],
        "id": 2696471,
        "name:xx": "Stone Lake"
      }
    },
    {
      "geometry": {
        "type": "Point",
        "coordinates": [
          -105.6833,
          40.15
        ]
      },
      "type": "Feature",
      "properties": {
        "hierarchy": [
          "tgn:2696472",
          "tgn:1000001",
          "tgn:7012149",
          "tgn:2000216",
          "tgn:7007158",
          "tgn:7029392"
        ],
        "placetype": [
          "aat:300008680"
        ],
        "id": 2696472,
        "name:xx": "Stone Lake"
      }
    },
    {
      "geometry": {
        "type": "Point",
        "coordinates": [
          -83.5667,
          32.7833
        ]
      },
      "type": "Feature",
      "properties": {
        "hierarchy": [
          "tgn:2696473",
          "tgn:1000001",
          "tgn:2000302",
          "tgn:7012149",
          "tgn:7007248",
          "tgn:7029392"
        ],
        "placetype": [
          "aat:300006191"
        ],
        "id": 2696473,
        "name:xx": "Stone Lake"
      }
    },
    {
      "geometry": {
        "type": "Point",
        "coordinates": [
          -83.3833,
          32.6833
        ]
      },
      "type": "Feature",
      "properties": {
        "hierarchy": [
          "tgn:2696474",
          "tgn:1000001",
          "tgn:7012149",
          "tgn:2000434",
          "tgn:7007248",
          "tgn:7029392"
        ],
        "placetype": [
          "aat:300006191"
        ],
        "id": 2696474,
        "name:xx": "Stone Lake"
      }
    },
    {
      "geometry": {
        "type": "Point",
        "coordinates": [
          -83.4,
          31.4
        ]
      },
      "type": "Feature",
      "properties": {
        "hierarchy": [
          "tgn:2696475",
          "tgn:1000001",
          "tgn:7012149",
          "tgn:2000428",
          "tgn:7007248",
          "tgn:7029392"
        ],
        "placetype": [
          "aat:300006191"
        ],
        "id": 2696475,
        "name:xx": "Stone Lake"
      }
    },
    {
      "geometry": {
        "type": "Point",
        "coordinates": [
          -89.95,
          38.25
        ]
      },
      "type": "Feature",
      "properties": {
        "hierarchy": [
          "tgn:2696476",
          "tgn:1000001",
          "tgn:7012149",
          "tgn:1002677",
          "tgn:7007251",
          "tgn:7029392"
        ],
        "placetype": [
          "aat:300006191"
        ],
        "id": 2696476,
        "name:xx": "Stone Lake"
      }
    },
    {
      "geometry": {
        "type": "Point",
        "coordinates": [
          -85.65,
          41.7333
        ]
      },
      "type": "Feature",
      "properties": {
        "hierarchy": [
          "tgn:2696477",
          "tgn:1000001",
          "tgn:7012149",
          "tgn:1002565",
          "tgn:7007252",
          "tgn:7029392"
        ],
        "placetype": [
          "aat:300008680"
        ],
        "id": 2696477,
        "name:xx": "Stone Lake"
      }
    },
    {
      "geometry": {
        "type": "Point",
        "coordinates": [
          -91.1167,
          41.15
        ]
      },
      "type": "Feature",
      "properties": {
        "hierarchy": [
          "tgn:2696478",
          "tgn:1000001",
          "tgn:7012149",
          "tgn:2000618",
          "tgn:7007253",
          "tgn:7029392"
        ],
        "placetype": [
          "aat:300008680"
        ],
        "id": 2696478,
        "name:xx": "Stone Lake"
      }
    },
    {
      "geometry": {
        "type": "Point",
        "coordinates": [
          -77.0833,
          39
        ]
      },
      "type": "Feature",
      "properties": {
        "hierarchy": [
          "tgn:2696479",
          "tgn:1000001",
          "tgn:7016104",
          "tgn:7012149",
          "tgn:7007516",
          "tgn:7029392"
        ],
        "placetype": [
          "aat:300006191"
        ],
        "id": 2696479,
        "name:xx": "Stone Lake"
      }
    }
  ]
}
