{
  "geometry": {
    "type": "Point",
    "coordinates": [
      -74.4333,
      42.3167
    ]
  },
  "type": "Feature",
  "properties": {
    "hierarchy": [
      "tgn:2242044",
      "tgn:1000001",
      "tgn:1002328",
      "tgn:7012149",
      "tgn:7007568",
      "tgn:7029392"
    ],
    "placetype": [
      "aat:300008798"
    ],
    "id": 2242044,
    "name:xx": "Clay Hill"
  }
}
