{
  "type": "FeatureCollection",
  "features": [
    {
      "geometry": {
        "type": "Point",
        "coordinates": [
          -112.25,
          29.15
        ]
      },
      "type": "Feature",
      "properties": {
        "hierarchy": [
          "tgn:1114160",
          "tgn:1000001",
          "tgn:1001960",
          "tgn:7005560",
          "tgn:7029392"
        ],
        "placetype": [
          "aat:300387026",
          "aat:300008713"
        ],
        "id": 1114160,
        "name:xx": "Infiernillo, Canal del"
      }
    },
    {
      "geometry": {
        "type": "Point",
        "coordinates": [
          137,
          34.5833
        ]
      },
      "type": "Feature",
      "properties": {
        "hierarchy": [
          "tgn:1114161",
          "tgn:7016674",
          "tgn:1000004",
          "tgn:1000120",
          "tgn:7029392"
        ],
        "placetype": [
          "aat:300008713"
        ],
        "id": 1114161,
        "name:xx": "Irago-suidō"
      }
    },
    {
      "geometry": {
        "type": "Point",
        "coordinates": [
          -90.84,
          -0.439
        ]
      },
      "type": "Feature",
      "properties": {
        "hierarchy": [
          "tgn:1114162",
          "tgn:1001259",
          "tgn:1009942",
          "tgn:7002563",
          "tgn:1000051",
          "tgn:1000002",
          "tgn:7029392"
        ],
        "placetype": [
          "aat:300008713"
        ],
        "id": 1114162,
        "name:xx": "Canal Isabela"
      }
    },
    {
      "geometry": {
        "type": "Point",
        "coordinates": [
          -75,
          18
        ]
      },
      "type": "Feature",
      "properties": {
        "hierarchy": [
          "tgn:1114163",
          "tgn:1000001",
          "tgn:7029392"
        ],
        "placetype": [
          "aat:300008713"
        ],
        "id": 1114163,
        "name:xx": "Jamaica Channel"
      }
    },
    {
      "geometry": {
        "type": "Point",
        "coordinates": [
          -80.006,
          -3.25
        ]
      },
      "type": "Feature",
      "properties": {
        "hierarchy": [
          "tgn:1114164",
          "tgn:1001277",
          "tgn:7002560",
          "tgn:1000051",
          "tgn:1000002",
          "tgn:7029392"
        ],
        "placetype": [
          "aat:300008713"
        ],
        "id": 1114164,
        "name:xx": "Jambelí, Canal de"
      }
    },
    {
      "geometry": {
        "type": "Point",
        "coordinates": [
          123.0833,
          11.8
        ]
      },
      "type": "Feature",
      "properties": {
        "hierarchy": [
          "tgn:1114165",
          "tgn:1000004",
          "tgn:1000135",
          "tgn:7029392"
        ],
        "placetype": [
          "aat:300008713"
        ],
        "id": 1114165,
        "name:xx": "Jintotolo Channel"
      }
    },
    {
      "geometry": {
        "type": "Point",
        "coordinates": [
          12.25,
          54.5
        ]
      },
      "type": "Feature",
      "properties": {
        "hierarchy": [
          "tgn:1114166",
          "tgn:1000003",
          "tgn:7029392"
        ],
        "placetype": [
          "aat:300008713"
        ],
        "name:da": "Kadet Rinne",
        "id": 1114166,
        "name:de": "Kadetrenden"
      }
    },
    {
      "geometry": {
        "type": "Point",
        "coordinates": [
          -157.5,
          21.2167
        ]
      },
      "type": "Feature",
      "properties": {
        "hierarchy": [
          "tgn:1114167",
          "tgn:1002648",
          "tgn:1000001",
          "tgn:7012149",
          "tgn:7007249",
          "tgn:7029392"
        ],
        "placetype": [
          "aat:300008713"
        ],
        "id": 1114167,
        "name:xx": "Kaiwi Channel"
      }
    },
    {
      "geometry": {
        "type": "Point",
        "coordinates": [
          -158.8333,
          21.8
        ]
      },
      "type": "Feature",
      "properties": {
        "hierarchy": [
          "tgn:1114169",
          "tgn:1002534",
          "tgn:1000001",
          "tgn:7012149",
          "tgn:7007249",
          "tgn:7029392"
        ],
        "placetype": [
          "aat:300008713"
        ],
        "id": 1114169,
        "name:xx": "Kauai Channel"
      }
    }
  ]
}
