{
  "geometry": {
    "type": "Point",
    "coordinates": [
      -97.2333,
      38.5833
    ]
  },
  "type": "Feature",
  "properties": {
    "hierarchy": [
      "tgn:2762377",
      "tgn:1000001",
      "tgn:7012149",
      "tgn:7007254",
      "tgn:7029392"
    ],
    "placetype": [
      "aat:300008706"
    ],
    "id": 2762377,
    "name:xx": "West Turkey Creek"
  }
}
