{
  "geometry": {
    "type": "Point",
    "coordinates": [
      31.75,
      1.6833
    ]
  },
  "type": "Feature",
  "properties": {
    "hierarchy": [
      "tgn:1095076",
      "tgn:7001242",
      "tgn:1000948",
      "tgn:1000206",
      "tgn:7029392"
    ],
    "placetype": [
      "aat:300008347"
    ],
    "id": 1095076,
    "name:xx": "Masindi"
  }
}
