{
  "geometry": {
    "type": "Point",
    "coordinates": [
      -86.35,
      39.1167
    ]
  },
  "type": "Feature",
  "properties": {
    "hierarchy": [
      "tgn:2354962",
      "tgn:1000001",
      "tgn:7012149",
      "tgn:7007252",
      "tgn:7029392"
    ],
    "placetype": [
      "aat:300008699"
    ],
    "id": 2354962,
    "name:xx": "Goodley Branch"
  }
}
