{
  "geometry": {
    "type": "Point",
    "coordinates": [
      41.4833,
      4.5667
    ]
  },
  "type": "Feature",
  "properties": {
    "hierarchy": [
      "tgn:1089747",
      "tgn:7001242",
      "tgn:1001537",
      "tgn:7000489",
      "tgn:7029392"
    ],
    "placetype": [
      "aat:300008347"
    ],
    "id": 1089747,
    "name:xx": "Bogol Manya"
  }
}
