{
  "type": "FeatureCollection",
  "features": [
    {
      "geometry": {
        "type": "Point",
        "coordinates": [
          -75.7667,
          38.4667
        ]
      },
      "type": "Feature",
      "properties": {
        "hierarchy": [
          "tgn:2366520",
          "tgn:1000001",
          "tgn:1003023",
          "tgn:7012149",
          "tgn:7007516",
          "tgn:7029392"
        ],
        "placetype": [
          "aat:300008706"
        ],
        "id": 2366520,
        "name:xx": "Grimes Creek"
      }
    },
    {
      "geometry": {
        "type": "Point",
        "coordinates": [
          -113.35,
          45.05
        ]
      },
      "type": "Feature",
      "properties": {
        "hierarchy": [
          "tgn:2366521",
          "tgn:1000001",
          "tgn:2001260",
          "tgn:7012149",
          "tgn:7007524",
          "tgn:7029392"
        ],
        "placetype": [
          "aat:300008706"
        ],
        "id": 2366521,
        "name:xx": "Grimes Creek"
      }
    },
    {
      "geometry": {
        "type": "Point",
        "coordinates": [
          -105.5833,
          46.4333
        ]
      },
      "type": "Feature",
      "properties": {
        "hierarchy": [
          "tgn:2366522",
          "tgn:1000001",
          "tgn:2001268",
          "tgn:7012149",
          "tgn:7007524",
          "tgn:7029392"
        ],
        "placetype": [
          "aat:300008706"
        ],
        "id": 2366522,
        "name:xx": "Grimes Creek"
      }
    },
    {
      "geometry": {
        "type": "Point",
        "coordinates": [
          -77.4167,
          42.6833
        ]
      },
      "type": "Feature",
      "properties": {
        "hierarchy": [
          "tgn:2366523",
          "tgn:1000001",
          "tgn:7012149",
          "tgn:1002747",
          "tgn:7007568",
          "tgn:7029392"
        ],
        "placetype": [
          "aat:300008706"
        ],
        "id": 2366523,
        "name:xx": "Grimes Creek"
      }
    },
    {
      "geometry": {
        "type": "Point",
        "coordinates": [
          -116.6,
          45.5333
        ]
      },
      "type": "Feature",
      "properties": {
        "hierarchy": [
          "tgn:2366524",
          "tgn:1000001",
          "tgn:7012149",
          "tgn:2001722",
          "tgn:7007708",
          "tgn:7029392"
        ],
        "placetype": [
          "aat:300008706"
        ],
        "id": 2366524,
        "name:xx": "Grimes Creek"
      }
    },
    {
      "geometry": {
        "type": "Point",
        "coordinates": [
          -80.2333,
          33.5167
        ]
      },
      "type": "Feature",
      "properties": {
        "hierarchy": [
          "tgn:2366525",
          "tgn:1000001",
          "tgn:2001738",
          "tgn:7012149",
          "tgn:7007712",
          "tgn:7029392"
        ],
        "placetype": [
          "aat:300008706"
        ],
        "id": 2366525,
        "name:xx": "Grimes Creek"
      }
    },
    {
      "geometry": {
        "type": "Point",
        "coordinates": [
          -94.5,
          31.1
        ]
      },
      "type": "Feature",
      "properties": {
        "hierarchy": [
          "tgn:2366526",
          "tgn:1002149",
          "tgn:1000001",
          "tgn:7012149",
          "tgn:7007826",
          "tgn:7029392"
        ],
        "placetype": [
          "aat:300008706"
        ],
        "id": 2366526,
        "name:xx": "Grimes Creek"
      }
    },
    {
      "geometry": {
        "type": "Point",
        "coordinates": [
          -111.55,
          37.9833
        ]
      },
      "type": "Feature",
      "properties": {
        "hierarchy": [
          "tgn:2366527",
          "tgn:1000001",
          "tgn:2002109",
          "tgn:7012149",
          "tgn:7007827",
          "tgn:7029392"
        ],
        "placetype": [
          "aat:300008706"
        ],
        "id": 2366527,
        "name:xx": "Grimes Creek"
      }
    },
    {
      "geometry": {
        "type": "Point",
        "coordinates": [
          -79.75,
          37.15
        ]
      },
      "type": "Feature",
      "properties": {
        "hierarchy": [
          "tgn:2366528",
          "tgn:1000001",
          "tgn:7012149",
          "tgn:2002160",
          "tgn:7007919",
          "tgn:7029392"
        ],
        "placetype": [
          "aat:300008706"
        ],
        "id": 2366528,
        "name:xx": "Grimes Creek"
      }
    },
    {
      "geometry": {
        "type": "Point",
        "coordinates": [
          -124.5833,
          48.2833
        ]
      },
      "type": "Feature",
      "properties": {
        "hierarchy": [
          "tgn:2366529",
          "tgn:1000001",
          "tgn:1002271",
          "tgn:7012149",
          "tgn:7007920",
          "tgn:7029392"
        ],
        "placetype": [
          "aat:300008706"
        ],
        "id": 2366529,
        "name:xx": "Grimes Creek"
      }
    }
  ]
}
