{
  "geometry": {
    "type": "Point",
    "coordinates": [
      -106.3167,
      44.85
    ]
  },
  "type": "Feature",
  "properties": {
    "hierarchy": [
      "tgn:2763918",
      "tgn:1000001",
      "tgn:7012149",
      "tgn:2002381",
      "tgn:7007923",
      "tgn:7029392"
    ],
    "placetype": [
      "aat:300008761"
    ],
    "id": 2763918,
    "name:xx": "Whedon Draw"
  }
}
