{
  "geometry": {
    "type": "Point",
    "coordinates": [
      -122.5667,
      42.9167
    ]
  },
  "type": "Feature",
  "properties": {
    "hierarchy": [
      "tgn:2758941",
      "tgn:1000001",
      "tgn:7012149",
      "tgn:2001711",
      "tgn:7007708",
      "tgn:7029392"
    ],
    "placetype": [
      "aat:300008706"
    ],
    "id": 2758941,
    "name:xx": "West Fork Abbott Creek"
  }
}
