{
  "geometry": {
    "type": "Point",
    "coordinates": [
      -83.55,
      38.05
    ]
  },
  "type": "Feature",
  "properties": {
    "hierarchy": [
      "tgn:2167139",
      "tgn:1002169",
      "tgn:1000001",
      "tgn:7012149",
      "tgn:7007255",
      "tgn:7029392"
    ],
    "placetype": [
      "aat:300008699"
    ],
    "id": 2167139,
    "name:xx": "Big Cave Run"
  }
}
