{
  "type": "FeatureCollection",
  "features": [
    {
      "geometry": {
        "type": "Point",
        "coordinates": [
          -80.9333,
          37.2
        ]
      },
      "type": "Feature",
      "properties": {
        "hierarchy": [
          "tgn:2690920",
          "tgn:1000001",
          "tgn:2002145",
          "tgn:7012149",
          "tgn:7007919",
          "tgn:7029392"
        ],
        "placetype": [
          "aat:300008347"
        ],
        "id": 2690920,
        "name:xx": "Stange Mines"
      }
    },
    {
      "geometry": {
        "type": "Point",
        "coordinates": [
          -97.6,
          45.5167
        ]
      },
      "type": "Feature",
      "properties": {
        "hierarchy": [
          "tgn:2690921",
          "tgn:1000001",
          "tgn:2001788",
          "tgn:7012149",
          "tgn:7007713",
          "tgn:7029392"
        ],
        "placetype": [
          "aat:300008680"
        ],
        "id": 2690921,
        "name:xx": "Stangland Slough"
      }
    },
    {
      "geometry": {
        "type": "Point",
        "coordinates": [
          -80.6,
          41.4833
        ]
      },
      "type": "Feature",
      "properties": {
        "hierarchy": [
          "tgn:2690922",
          "tgn:1000001",
          "tgn:7012149",
          "tgn:1002955",
          "tgn:7007706",
          "tgn:7029392"
        ],
        "placetype": [
          "aat:300008347"
        ],
        "id": 2690922,
        "name:xx": "Stanhope"
      }
    },
    {
      "geometry": {
        "type": "Point",
        "coordinates": [
          -72.5333,
          44.95
        ]
      },
      "type": "Feature",
      "properties": {
        "hierarchy": [
          "tgn:2690923",
          "tgn:1000001",
          "tgn:1002753",
          "tgn:7012149",
          "tgn:7007828",
          "tgn:7029392"
        ],
        "placetype": [
          "aat:300008699"
        ],
        "id": 2690923,
        "name:xx": "Stanhope Brook"
      }
    },
    {
      "geometry": {
        "type": "Point",
        "coordinates": [
          -73.3333,
          44.9
        ]
      },
      "type": "Feature",
      "properties": {
        "hierarchy": [
          "tgn:2690924",
          "tgn:1000001",
          "tgn:1002415",
          "tgn:7012149",
          "tgn:7007828",
          "tgn:7029392"
        ],
        "placetype": [
          "aat:300008798"
        ],
        "id": 2690924,
        "name:xx": "Stanhope Hill"
      }
    },
    {
      "geometry": {
        "type": "Point",
        "coordinates": [
          -132.6,
          56.0167
        ]
      },
      "type": "Feature",
      "properties": {
        "hierarchy": [
          "tgn:2690925",
          "tgn:7006450",
          "tgn:1000001",
          "tgn:7012149",
          "tgn:2000088",
          "tgn:7029392"
        ],
        "placetype": [
          "aat:300008791"
        ],
        "id": 2690925,
        "name:xx": "Stanhope Island"
      }
    },
    {
      "geometry": {
        "type": "Point",
        "coordinates": [
          -67.7,
          45.2
        ]
      },
      "type": "Feature",
      "properties": {
        "hierarchy": [
          "tgn:2690926",
          "tgn:1000001",
          "tgn:7012149",
          "tgn:7014589",
          "tgn:7007515",
          "tgn:7029392"
        ],
        "placetype": [
          "aat:300008905"
        ],
        "id": 2690926,
        "name:xx": "Stanhope Meadow"
      }
    },
    {
      "geometry": {
        "type": "Point",
        "coordinates": [
          -97.5833,
          31.9167
        ]
      },
      "type": "Feature",
      "properties": {
        "hierarchy": [
          "tgn:2690927",
          "tgn:1000001",
          "tgn:1002191",
          "tgn:7012149",
          "tgn:7007826",
          "tgn:7029392"
        ],
        "placetype": [
          "aat:300008699"
        ],
        "id": 2690927,
        "name:xx": "Stanifer Branch"
      }
    },
    {
      "geometry": {
        "type": "Point",
        "coordinates": [
          -83.1667,
          36.25
        ]
      },
      "type": "Feature",
      "properties": {
        "hierarchy": [
          "tgn:2690928",
          "tgn:1000001",
          "tgn:7012149",
          "tgn:2001868",
          "tgn:7007825",
          "tgn:7029392"
        ],
        "placetype": [
          "aat:300008680"
        ],
        "id": 2690928,
        "name:xx": "Stanifer Pond"
      }
    },
    {
      "geometry": {
        "type": "Point",
        "coordinates": [
          -95.1667,
          35.4
        ]
      },
      "type": "Feature",
      "properties": {
        "hierarchy": [
          "tgn:2690929",
          "tgn:1000001",
          "tgn:7012149",
          "tgn:2001673",
          "tgn:7007707",
          "tgn:7029392"
        ],
        "placetype": [
          "aat:300008798"
        ],
        "id": 2690929,
        "name:xx": "Stanifird Mountain"
      }
    }
  ]
}
