{
  "geometry": {
    "type": "Point",
    "coordinates": [
      79.33834,
      23.990101
    ]
  },
  "type": "Feature",
  "properties": {
    "hierarchy": [
      "tgn:7547387",
      "tgn:1000004",
      "tgn:7000198",
      "tgn:1001894",
      "tgn:7029392"
    ],
    "placetype": [
      "aat:300008699"
    ],
    "name:en": "Bewās River",
    "id": 7547387
  }
}
