{
  "geometry": {
    "type": "Point",
    "coordinates": [
      122.1167,
      41.2167
    ]
  },
  "type": "Feature",
  "properties": {
    "hierarchy": [
      "tgn:1068813",
      "tgn:1000004",
      "tgn:1001390",
      "tgn:1000111",
      "tgn:7029392"
    ],
    "placetype": [
      "aat:300008347"
    ],
    "id": 1068813,
    "name:xx": "Houguangzhengtai"
  }
}
