{
  "geometry": {
    "type": "Point",
    "coordinates": [
      -76.85,
      38.8167
    ]
  },
  "type": "Feature",
  "properties": {
    "hierarchy": [
      "tgn:1133394",
      "tgn:1000001",
      "tgn:2124001",
      "tgn:7012149",
      "tgn:7007516",
      "tgn:7029392"
    ],
    "placetype": [
      "aat:300008706"
    ],
    "id": 1133394,
    "name:xx": "Henson Creek"
  }
}
