{
  "geometry": {
    "type": "Point",
    "coordinates": [
      -57.4333,
      -34.3333
    ]
  },
  "type": "Feature",
  "properties": {
    "hierarchy": [
      "tgn:1024967",
      "tgn:1000574",
      "tgn:1000002",
      "tgn:1000058",
      "tgn:7029392"
    ],
    "placetype": [
      "aat:300008347"
    ],
    "id": 1024967,
    "name:xx": "Rosario"
  }
}
