{
  "geometry": {
    "type": "Point",
    "coordinates": [
      -71.2667,
      42.3667
    ]
  },
  "type": "Feature",
  "properties": {
    "hierarchy": [
      "tgn:2050918",
      "tgn:1000001",
      "tgn:1002665",
      "tgn:7012149",
      "tgn:7014617",
      "tgn:7007517",
      "tgn:7029392"
    ],
    "placetype": [
      "aat:300000745"
    ],
    "id": 2050918,
    "name:xx": "Kendal Green"
  }
}
