{
  "geometry": {
    "type": "Point",
    "coordinates": [
      -119.05,
      34.0833
    ]
  },
  "type": "Feature",
  "properties": {
    "hierarchy": [
      "tgn:2589620",
      "tgn:1000001",
      "tgn:7012149",
      "tgn:7007157",
      "tgn:1002972",
      "tgn:7029392"
    ],
    "placetype": [
      "aat:300008850"
    ],
    "id": 2589620,
    "name:xx": "Point Mugu"
  }
}
