{
  "geometry": {
    "type": "Point",
    "coordinates": [
      -67.866667,
      -23.05
    ]
  },
  "type": "Feature",
  "properties": {
    "hierarchy": [
      "tgn:7308961",
      "tgn:7016598",
      "tgn:1000049",
      "tgn:1000002",
      "tgn:7029392"
    ],
    "placetype": [
      "aat:300008795"
    ],
    "id": 7308961,
    "name:xx": "Macón, Cerros de"
  }
}
