{
  "type": "FeatureCollection",
  "features": [
    {
      "geometry": {
        "type": "Point",
        "coordinates": [
          11.65,
          50.483333
        ]
      },
      "type": "Feature",
      "properties": {
        "hierarchy": [
          "tgn:7095420",
          "tgn:1000003",
          "tgn:7003689",
          "tgn:7000084",
          "tgn:7029392"
        ],
        "placetype": [
          "aat:300008347"
        ],
        "id": 7095420,
        "name:xx": "Schönbrunn"
      }
    },
    {
      "geometry": {
        "type": "Point",
        "coordinates": [
          12.116667,
          50.4
        ]
      },
      "type": "Feature",
      "properties": {
        "hierarchy": [
          "tgn:7095421",
          "tgn:1000003",
          "tgn:7003685",
          "tgn:7000084",
          "tgn:7029392"
        ],
        "placetype": [
          "aat:300008347"
        ],
        "id": 7095421,
        "name:xx": "Schönbrunn"
      }
    },
    {
      "geometry": {
        "type": "Point",
        "coordinates": [
          11.583333,
          50.266667
        ]
      },
      "type": "Feature",
      "properties": {
        "hierarchy": [
          "tgn:7095422",
          "tgn:7003669",
          "tgn:1000003",
          "tgn:7000084",
          "tgn:7029392"
        ],
        "placetype": [
          "aat:300008347"
        ],
        "id": 7095422,
        "name:xx": "Schönbrunn"
      }
    },
    {
      "geometry": {
        "type": "Point",
        "coordinates": [
          11.016667,
          50.116667
        ]
      },
      "type": "Feature",
      "properties": {
        "hierarchy": [
          "tgn:7095423",
          "tgn:7003669",
          "tgn:1000003",
          "tgn:7000084",
          "tgn:7029392"
        ],
        "placetype": [
          "aat:300008347"
        ],
        "id": 7095423,
        "name:xx": "Schönbrunn"
      }
    },
    {
      "geometry": {
        "type": "Point",
        "coordinates": [
          11.966667,
          50.033333
        ]
      },
      "type": "Feature",
      "properties": {
        "hierarchy": [
          "tgn:7095424",
          "tgn:7003669",
          "tgn:1000003",
          "tgn:7000084",
          "tgn:7029392"
        ],
        "placetype": [
          "aat:300008347"
        ],
        "id": 7095424,
        "name:xx": "Schönbrunn"
      }
    },
    {
      "geometry": {
        "type": "Point",
        "coordinates": [
          10.716667,
          50
        ]
      },
      "type": "Feature",
      "properties": {
        "hierarchy": [
          "tgn:7095425",
          "tgn:7003669",
          "tgn:1000003",
          "tgn:7000084",
          "tgn:7029392"
        ],
        "placetype": [
          "aat:300008347"
        ],
        "id": 7095425,
        "name:xx": "Schönbrunn"
      }
    },
    {
      "geometry": {
        "type": "Point",
        "coordinates": [
          10.7,
          49.866667
        ]
      },
      "type": "Feature",
      "properties": {
        "hierarchy": [
          "tgn:7095426",
          "tgn:7003669",
          "tgn:1000003",
          "tgn:7000084",
          "tgn:7029392"
        ],
        "placetype": [
          "aat:300008347"
        ],
        "id": 7095426,
        "name:xx": "Schönbrunn"
      }
    },
    {
      "geometry": {
        "type": "Point",
        "coordinates": [
          12.3,
          49.716667
        ]
      },
      "type": "Feature",
      "properties": {
        "hierarchy": [
          "tgn:7095427",
          "tgn:7003669",
          "tgn:1000003",
          "tgn:7000084",
          "tgn:7029392"
        ],
        "placetype": [
          "aat:300008347"
        ],
        "id": 7095427,
        "name:xx": "Schönbrunn"
      }
    },
    {
      "geometry": {
        "type": "Point",
        "coordinates": [
          8.833333,
          49.516667
        ]
      },
      "type": "Feature",
      "properties": {
        "hierarchy": [
          "tgn:7095428",
          "tgn:1000003",
          "tgn:7003678",
          "tgn:7000084",
          "tgn:7029392"
        ],
        "placetype": [
          "aat:300008347"
        ],
        "id": 7095428,
        "name:xx": "Schönbrunn"
      }
    },
    {
      "geometry": {
        "type": "Point",
        "coordinates": [
          11.25,
          49.233333
        ]
      },
      "type": "Feature",
      "properties": {
        "hierarchy": [
          "tgn:7095429",
          "tgn:7003669",
          "tgn:1000003",
          "tgn:7000084",
          "tgn:7029392"
        ],
        "placetype": [
          "aat:300008347"
        ],
        "id": 7095429,
        "name:xx": "Schönbrunn"
      }
    }
  ]
}
