{
  "geometry": {
    "type": "Point",
    "coordinates": [
      -98.7667,
      26.5667
    ]
  },
  "type": "Feature",
  "properties": {
    "hierarchy": [
      "tgn:2312750",
      "tgn:1000001",
      "tgn:7012149",
      "tgn:2002075",
      "tgn:7007826",
      "tgn:7029392"
    ],
    "placetype": [
      "aat:300006191"
    ],
    "id": 2312750,
    "name:xx": "El Leoncito Tank"
  }
}
