{
  "geometry": {
    "type": "Point",
    "coordinates": [
      -152.1333,
      58.9667
    ]
  },
  "type": "Feature",
  "properties": {
    "hierarchy": [
      "tgn:2543206",
      "tgn:7006450",
      "tgn:1000001",
      "tgn:2124012",
      "tgn:7012149",
      "tgn:7029392"
    ],
    "placetype": [
      "aat:300008791"
    ],
    "id": 2543206,
    "name:xx": "Nord Island"
  }
}
