{
  "geometry": {
    "type": "Point",
    "coordinates": [
      70.30217,
      27.038316
    ]
  },
  "type": "Feature",
  "properties": {
    "hierarchy": [
      "tgn:7581059",
      "tgn:1000004",
      "tgn:7000198",
      "tgn:7016788",
      "tgn:7029392"
    ],
    "placetype": [
      "aat:300008347"
    ],
    "name:en": "Shyāmbhar ki Dhani",
    "id": 7581059
  }
}
