{
  "geometry": {
    "type": "Point",
    "coordinates": [
      -132.75,
      55.95
    ]
  },
  "type": "Feature",
  "properties": {
    "hierarchy": [
      "tgn:2303315",
      "tgn:7006450",
      "tgn:1000001",
      "tgn:7012149",
      "tgn:7019760",
      "tgn:7029392"
    ],
    "placetype": [
      "aat:300008706"
    ],
    "id": 2303315,
    "name:xx": "Eagle Creek"
  }
}
