{
  "geometry": {
    "type": "Point",
    "coordinates": [
      -112.7167,
      39.9667
    ]
  },
  "type": "Feature",
  "properties": {
    "hierarchy": [
      "tgn:2665049",
      "tgn:1000001",
      "tgn:7012149",
      "tgn:2002123",
      "tgn:7007827",
      "tgn:7029392"
    ],
    "placetype": [
      "aat:300386831"
    ],
    "id": 2665049,
    "name:xx": "Simpson Mountains"
  }
}
