{
  "geometry": {
    "type": "Point",
    "coordinates": [
      -101.0833,
      26.1333
    ]
  },
  "type": "Feature",
  "properties": {
    "hierarchy": [
      "tgn:1018107",
      "tgn:1001853",
      "tgn:1000001",
      "tgn:7005560",
      "tgn:7029392"
    ],
    "placetype": [
      "aat:300008347"
    ],
    "id": 1018107,
    "name:xx": "Reata"
  }
}
