{
  "geometry": {
    "type": "Point",
    "coordinates": [
      -44.9833,
      -21.7167
    ]
  },
  "type": "Feature",
  "properties": {
    "hierarchy": [
      "tgn:1022910",
      "tgn:7006237",
      "tgn:1000047",
      "tgn:7002457",
      "tgn:1000002",
      "tgn:7029392"
    ],
    "placetype": [
      "aat:300008347"
    ],
    "id": 1022910,
    "name:xx": "São Tomé das Letras"
  }
}
