{
  "geometry": {
    "type": "Point",
    "coordinates": [
      -93.55,
      38.7667
    ]
  },
  "type": "Feature",
  "properties": {
    "hierarchy": [
      "tgn:2059406",
      "tgn:1000001",
      "tgn:7012149",
      "tgn:2001210",
      "tgn:7007523",
      "tgn:7029392"
    ],
    "placetype": [
      "aat:300008347"
    ],
    "id": 2059406,
    "name:xx": "Knob Noster"
  }
}
