{
  "geometry": {
    "type": "Point",
    "coordinates": [
      -104.05,
      44.2333
    ]
  },
  "type": "Feature",
  "properties": {
    "hierarchy": [
      "tgn:2314709",
      "tgn:1000001",
      "tgn:2002370",
      "tgn:7012149",
      "tgn:7007923",
      "tgn:7029392"
    ],
    "placetype": [
      "aat:300008697"
    ],
    "id": 2314709,
    "name:xx": "Elk Spring"
  }
}
