{
  "geometry": {
    "type": "Point",
    "coordinates": [
      -111.35,
      31.6333
    ]
  },
  "type": "Feature",
  "properties": {
    "hierarchy": [
      "tgn:2498748",
      "tgn:1000001",
      "tgn:7006451",
      "tgn:7012149",
      "tgn:2000100",
      "tgn:7029392"
    ],
    "placetype": [
      "aat:300008761"
    ],
    "id": 2498748,
    "name:xx": "McCafferty Canyon"
  }
}
