{
  "geometry": {
    "type": "Point",
    "coordinates": [
      -75.95,
      38.1667
    ]
  },
  "type": "Feature",
  "properties": {
    "hierarchy": [
      "tgn:2371451",
      "tgn:1000001",
      "tgn:1002902",
      "tgn:7012149",
      "tgn:7007516",
      "tgn:7029392"
    ],
    "placetype": [
      "aat:300008850"
    ],
    "id": 2371451,
    "name:xx": "Haines Point"
  }
}
