{
  "geometry": {
    "type": "Point",
    "coordinates": [
      -106.1667,
      53.9333
    ]
  },
  "type": "Feature",
  "properties": {
    "hierarchy": [
      "tgn:1118660",
      "tgn:7005685",
      "tgn:1000001",
      "tgn:7005805",
      "tgn:1101797",
      "tgn:7029392"
    ],
    "placetype": [
      "aat:300008680"
    ],
    "id": 1118660,
    "name:xx": "Waskesiu Lake"
  }
}
