{
  "geometry": {
    "type": "Point",
    "coordinates": [
      -80.9667,
      22.3833
    ]
  },
  "type": "Feature",
  "properties": {
    "hierarchy": [
      "tgn:1124549",
      "tgn:1000001",
      "tgn:7004624",
      "tgn:7029392"
    ],
    "placetype": [
      "aat:300008707"
    ],
    "id": 1124549,
    "name:xx": "Hanábana"
  }
}
