{
  "geometry": {
    "type": "Point",
    "coordinates": [
      -86.0167,
      44.65
    ]
  },
  "type": "Feature",
  "properties": {
    "hierarchy": [
      "tgn:2052210",
      "tgn:1000001",
      "tgn:2000949",
      "tgn:7012149",
      "tgn:7007520",
      "tgn:7029392"
    ],
    "placetype": [
      "aat:300008347"
    ],
    "id": 2052210,
    "name:xx": "Honor"
  }
}
