{
  "type": "FeatureCollection",
  "features": [
    {
      "geometry": {
        "type": "Point",
        "coordinates": [
          12.15,
          -15.1667
        ]
      },
      "type": "Feature",
      "properties": {
        "hierarchy": [
          "tgn:7001601",
          "tgn:7001242",
          "tgn:1000149",
          "tgn:7000392",
          "tgn:7029392"
        ],
        "placetype": [
          "aat:300008347",
          "aat:300387223",
          "aat:300008375",
          "aat:300120599"
        ],
        "id": 7001601,
        "name:xx": "Namibe"
      }
    },
    {
      "geometry": {
        "type": "Point",
        "coordinates": [
          82.216667,
          16.733333
        ]
      },
      "type": "Feature",
      "properties": {
        "hierarchy": [
          "tgn:7001602",
          "tgn:1000004",
          "tgn:7000198",
          "tgn:1002000",
          "tgn:7029392"
        ],
        "placetype": [
          "aat:300008347",
          "aat:300008375",
          "aat:300120599"
        ],
        "name:en": "Yanam",
        "id": 7001602
      }
    },
    {
      "geometry": {
        "type": "Point",
        "coordinates": [
          20,
          17
        ]
      },
      "type": "Feature",
      "properties": {
        "hierarchy": [
          "tgn:7001604",
          "tgn:7001242",
          "tgn:7029392"
        ],
        "placetype": [
          "aat:300387346"
        ],
        "name:en": "Sudan",
        "id": 7001604
      }
    }
  ]
}
