{
  "geometry": {
    "type": "Point",
    "coordinates": [
      -78.2833,
      37.55
    ]
  },
  "type": "Feature",
  "properties": {
    "hierarchy": [
      "tgn:2114643",
      "tgn:1000001",
      "tgn:7012149",
      "tgn:2002156",
      "tgn:7007919",
      "tgn:7029392"
    ],
    "placetype": [
      "aat:300008347",
      "aat:300387210"
    ],
    "id": 2114643,
    "name:xx": "Trents Mill"
  }
}
