{
  "geometry": {
    "type": "Point",
    "coordinates": [
      71.21421,
      26.235621
    ]
  },
  "type": "Feature",
  "properties": {
    "hierarchy": [
      "tgn:7573485",
      "tgn:1000004",
      "tgn:7000198",
      "tgn:7016788",
      "tgn:7029392"
    ],
    "placetype": [
      "aat:300008347"
    ],
    "name:en": "Gūnga",
    "id": 7573485
  }
}
