{
  "geometry": {
    "type": "Point",
    "coordinates": [
      120.2269,
      23.3684
    ]
  },
  "type": "Feature",
  "properties": {
    "hierarchy": [
      "tgn:7480671",
      "tgn:7468018",
      "tgn:1000004",
      "tgn:1000141",
      "tgn:7029392"
    ],
    "placetype": [
      "aat:300006495"
    ],
    "id": 7480671,
    "name:xx": "Guangrong Guoxiao Longjiao Fenxiao"
  }
}
