{
  "type": "FeatureCollection",
  "features": [
    {
      "geometry": {
        "type": "Point",
        "coordinates": [
          31.283333,
          29.633333
        ]
      },
      "type": "Feature",
      "properties": {
        "hierarchy": [
          "tgn:7522380",
          "tgn:7001242",
          "tgn:7016833",
          "tgn:1001083",
          "tgn:7029392"
        ],
        "placetype": [
          "aat:300008057"
        ],
        "name:en": "Ezbet Ibrâhîm Shidid",
        "id": 7522380
      }
    },
    {
      "geometry": {
        "type": "Point",
        "coordinates": [
          31.816197,
          31.034302
        ]
      },
      "type": "Feature",
      "properties": {
        "hierarchy": [
          "tgn:7522381",
          "tgn:7001242",
          "tgn:7016833",
          "tgn:1001113",
          "tgn:7029392"
        ],
        "placetype": [
          "aat:300008347"
        ],
        "name:en": "'Ezbet Ibrâhîm Sa'd",
        "id": 7522381
      }
    },
    {
      "geometry": {
        "type": "Point",
        "coordinates": [
          31.016667,
          29.416667
        ]
      },
      "type": "Feature",
      "properties": {
        "hierarchy": [
          "tgn:7522382",
          "tgn:7001242",
          "tgn:7001105",
          "tgn:7016833",
          "tgn:7029392"
        ],
        "placetype": [
          "aat:300008057"
        ],
        "name:en": "Ezbet Ibrâhim Muḥammnad",
        "id": 7522382
      }
    },
    {
      "geometry": {
        "type": "Point",
        "coordinates": [
          30.565622,
          31.245691
        ]
      },
      "type": "Feature",
      "properties": {
        "hierarchy": [
          "tgn:7522383",
          "tgn:7001242",
          "tgn:1001075",
          "tgn:7016833",
          "tgn:7029392"
        ],
        "placetype": [
          "aat:300008347"
        ],
        "name:en": "'Izbat al 'Iryān",
        "id": 7522383
      }
    },
    {
      "geometry": {
        "type": "Point",
        "coordinates": [
          32,
          30.883333
        ]
      },
      "type": "Feature",
      "properties": {
        "hierarchy": [
          "tgn:7522384",
          "tgn:7001242",
          "tgn:7016833",
          "tgn:1001113",
          "tgn:7029392"
        ],
        "placetype": [
          "aat:300008347"
        ],
        "name:en": "'Ezbet Ibrâhîm Ḥusayn 'Omar",
        "id": 7522384
      }
    },
    {
      "geometry": {
        "type": "Point",
        "coordinates": [
          32.081461,
          30.555379
        ]
      },
      "type": "Feature",
      "properties": {
        "hierarchy": [
          "tgn:7522385",
          "tgn:7001242",
          "tgn:7016833",
          "tgn:1001113",
          "tgn:7029392"
        ],
        "placetype": [
          "aat:300008347"
        ],
        "name:en": "'Ezbet Ibrâhîm Gurîsh",
        "id": 7522385
      }
    },
    {
      "geometry": {
        "type": "Point",
        "coordinates": [
          30.616667,
          31.35
        ]
      },
      "type": "Feature",
      "properties": {
        "hierarchy": [
          "tgn:7522386",
          "tgn:7001242",
          "tgn:7016833",
          "tgn:1001335",
          "tgn:7029392"
        ],
        "placetype": [
          "aat:300008347"
        ],
        "name:en": "'Ezbet Ibrâhîm el-Fâr",
        "id": 7522386
      }
    },
    {
      "geometry": {
        "type": "Point",
        "coordinates": [
          31.605556,
          30.602222
        ]
      },
      "type": "Feature",
      "properties": {
        "hierarchy": [
          "tgn:7522387",
          "tgn:7001242",
          "tgn:7016833",
          "tgn:1001113",
          "tgn:7029392"
        ],
        "placetype": [
          "aat:300008347"
        ],
        "name:en": "'Ezbet Ibrâhîm Bey",
        "id": 7522387
      }
    },
    {
      "geometry": {
        "type": "Point",
        "coordinates": [
          31.1,
          31.133333
        ]
      },
      "type": "Feature",
      "properties": {
        "hierarchy": [
          "tgn:7522388",
          "tgn:7001242",
          "tgn:7016833",
          "tgn:7001312",
          "tgn:7029392"
        ],
        "placetype": [
          "aat:300008347"
        ],
        "name:en": "'Ezbet Ibrâhîm Barakat",
        "id": 7522388
      }
    },
    {
      "geometry": {
        "type": "Point",
        "coordinates": [
          31.811667,
          30.8425
        ]
      },
      "type": "Feature",
      "properties": {
        "hierarchy": [
          "tgn:7522389",
          "tgn:7001242",
          "tgn:7016833",
          "tgn:1001113",
          "tgn:7029392"
        ],
        "placetype": [
          "aat:300008347"
        ],
        "name:en": "'Ezbet Ibrâhîm Abu Nigm",
        "id": 7522389
      }
    }
  ]
}
