{
  "geometry": {
    "type": "Point",
    "coordinates": [
      -83.2667,
      36.0167
    ]
  },
  "type": "Feature",
  "properties": {
    "hierarchy": [
      "tgn:2412501",
      "tgn:1000001",
      "tgn:7012149",
      "tgn:2001881",
      "tgn:7007825",
      "tgn:7029392"
    ],
    "placetype": [
      "aat:300132348"
    ],
    "id": 2412501,
    "name:xx": "Indian Walk Shoals"
  }
}
