{
  "geometry": {
    "type": "Point",
    "coordinates": [
      -96.45,
      41.7333
    ]
  },
  "type": "Feature",
  "properties": {
    "hierarchy": [
      "tgn:2241092",
      "tgn:1000001",
      "tgn:7012149",
      "tgn:7007525",
      "tgn:7029392"
    ],
    "placetype": [
      "aat:300008706"
    ],
    "id": 2241092,
    "name:xx": "Clark Creek"
  }
}
