{
  "geometry": {
    "type": "Point",
    "coordinates": [
      -117.25,
      44.35
    ]
  },
  "type": "Feature",
  "properties": {
    "hierarchy": [
      "tgn:2084911",
      "tgn:7013349",
      "tgn:1000001",
      "tgn:7012149",
      "tgn:7007708",
      "tgn:7029392"
    ],
    "placetype": [
      "aat:300008347"
    ],
    "id": 2084911,
    "name:xx": "Huntington"
  }
}
