{
  "geometry": {
    "type": "Point",
    "coordinates": [
      -84.1167,
      33.7833
    ]
  },
  "type": "Feature",
  "properties": {
    "hierarchy": [
      "tgn:2606721",
      "tgn:1000001",
      "tgn:7012149",
      "tgn:2124023",
      "tgn:7007248",
      "tgn:7029392"
    ],
    "placetype": [
      "aat:300006191"
    ],
    "id": 2606721,
    "name:xx": "Ramsden Lake"
  }
}
