{
  "type": "FeatureCollection",
  "features": [
    {
      "geometry": {
        "type": "Point",
        "coordinates": [
          7.2833,
          51.3
        ]
      },
      "type": "Feature",
      "properties": {
        "hierarchy": [
          "tgn:7017051",
          "tgn:1000003",
          "tgn:7003677",
          "tgn:7000084",
          "tgn:7029392"
        ],
        "placetype": [
          "aat:300008347",
          "aat:300008375"
        ],
        "id": 7017051,
        "name:xx": "Berghausen"
      }
    },
    {
      "geometry": {
        "type": "Point",
        "coordinates": [
          8.816667,
          50.4
        ]
      },
      "type": "Feature",
      "properties": {
        "hierarchy": [
          "tgn:7017052",
          "tgn:1000003",
          "tgn:7003684",
          "tgn:7000084",
          "tgn:7029392"
        ],
        "placetype": [
          "aat:300008347"
        ],
        "id": 7017052,
        "name:xx": "Wolfersheim"
      }
    },
    {
      "geometry": {
        "type": "Point",
        "coordinates": [
          3.0167,
          47.1833
        ]
      },
      "type": "Feature",
      "properties": {
        "hierarchy": [
          "tgn:7017054",
          "tgn:1000003",
          "tgn:7002875",
          "tgn:1000070",
          "tgn:7029392"
        ],
        "placetype": [
          "aat:300008347"
        ],
        "id": 7017054,
        "name:xx": "Charité-sur-Loire, La"
      }
    },
    {
      "geometry": {
        "type": "Point",
        "coordinates": [
          8.25,
          50.433333
        ]
      },
      "type": "Feature",
      "properties": {
        "hierarchy": [
          "tgn:7017056",
          "tgn:1000003",
          "tgn:7003678",
          "tgn:7000084",
          "tgn:7029392"
        ],
        "placetype": [
          "aat:300008347"
        ],
        "id": 7017056,
        "name:xx": "Fürfurt"
      }
    },
    {
      "geometry": {
        "type": "Point",
        "coordinates": [
          8.3,
          50.433333
        ]
      },
      "type": "Feature",
      "properties": {
        "hierarchy": [
          "tgn:7017057",
          "tgn:1000003",
          "tgn:7003678",
          "tgn:7000084",
          "tgn:7029392"
        ],
        "placetype": [
          "aat:300008347"
        ],
        "id": 7017057,
        "name:xx": "Weinbach"
      }
    }
  ]
}
