{
  "geometry": {
    "type": "Point",
    "coordinates": [
      -92.3833,
      31.9667
    ]
  },
  "type": "Feature",
  "properties": {
    "hierarchy": [
      "tgn:2042772",
      "tgn:1000001",
      "tgn:7012149",
      "tgn:2000917",
      "tgn:7007256",
      "tgn:7029392"
    ],
    "placetype": [
      "aat:300008347",
      "aat:300387210"
    ],
    "id": 2042772,
    "name:xx": "Flat Creek"
  }
}
