{
  "geometry": {
    "type": "Point",
    "coordinates": [
      -75.35,
      39.4333
    ]
  },
  "type": "Feature",
  "properties": {
    "hierarchy": [
      "tgn:2283876",
      "tgn:1002309",
      "tgn:1000001",
      "tgn:7012149",
      "tgn:7007565",
      "tgn:7029392"
    ],
    "placetype": [
      "aat:300008699"
    ],
    "id": 2283876,
    "name:xx": "Denn Branch"
  }
}
