{
  "geometry": {
    "type": "Point",
    "coordinates": [
      98.6667,
      27.9833
    ]
  },
  "type": "Feature",
  "properties": {
    "hierarchy": [
      "tgn:1066731",
      "tgn:1000004",
      "tgn:7018118",
      "tgn:1000111",
      "tgn:7029392"
    ],
    "placetype": [
      "aat:300008347"
    ],
    "id": 1066731,
    "name:xx": "Bangda"
  }
}
