{
  "geometry": {
    "type": "Point",
    "coordinates": [
      -97.4833,
      39.7333
    ]
  },
  "type": "Feature",
  "properties": {
    "hierarchy": [
      "tgn:2732617",
      "tgn:1000001",
      "tgn:7012149",
      "tgn:2000738",
      "tgn:7007254",
      "tgn:7029392"
    ],
    "placetype": [
      "aat:300008706"
    ],
    "id": 2732617,
    "name:xx": "Turkey Creek"
  }
}
