{
  "geometry": {
    "type": "Point",
    "coordinates": [
      -97.3667,
      32.8667
    ]
  },
  "type": "Feature",
  "properties": {
    "hierarchy": [
      "tgn:2455391",
      "tgn:1000001",
      "tgn:7012149",
      "tgn:1002939",
      "tgn:7007826",
      "tgn:7029392"
    ],
    "placetype": [
      "aat:300008706"
    ],
    "id": 2455391,
    "name:xx": "Little Fossil Creek"
  }
}
