{
  "geometry": {
    "type": "Point",
    "coordinates": [
      -85.3667,
      12.8667
    ]
  },
  "type": "Feature",
  "properties": {
    "hierarchy": [
      "tgn:1018750",
      "tgn:1000691",
      "tgn:1000001",
      "tgn:7005562",
      "tgn:7029392"
    ],
    "placetype": [
      "aat:300008347"
    ],
    "id": 1018750,
    "name:xx": "Matiguás"
  }
}
