{
  "geometry": {
    "type": "Point",
    "coordinates": [
      23.9167,
      -6.2833
    ]
  },
  "type": "Feature",
  "properties": {
    "hierarchy": [
      "tgn:1088816",
      "tgn:7001242",
      "tgn:1001346",
      "tgn:1000159",
      "tgn:7029392"
    ],
    "placetype": [
      "aat:300008347"
    ],
    "id": 1088816,
    "name:xx": "Bibanga"
  }
}
