{
  "geometry": {
    "type": "Point",
    "coordinates": [
      -107.0333,
      43.55
    ]
  },
  "type": "Feature",
  "properties": {
    "hierarchy": [
      "tgn:2548890",
      "tgn:1000001",
      "tgn:7012149",
      "tgn:2002374",
      "tgn:7007923",
      "tgn:7029392"
    ],
    "placetype": [
      "aat:300008706"
    ],
    "id": 2548890,
    "name:xx": "North Poker Creek"
  }
}
