{
  "geometry": {
    "type": "Point",
    "coordinates": [
      -72.6167,
      43.45
    ]
  },
  "type": "Feature",
  "properties": {
    "hierarchy": [
      "tgn:2727187",
      "tgn:1000001",
      "tgn:2002136",
      "tgn:7012149",
      "tgn:7007828",
      "tgn:7029392"
    ],
    "placetype": [
      "aat:300008699"
    ],
    "id": 2727187,
    "name:xx": "Tracer Brook"
  }
}
