{
  "type": "FeatureCollection",
  "features": [
    {
      "geometry": {
        "type": "Point",
        "coordinates": [
          -67,
          -25
        ]
      },
      "type": "Feature",
      "properties": {
        "hierarchy": [
          "tgn:1110260",
          "tgn:1000002",
          "tgn:7029392"
        ],
        "placetype": [
          "aat:300132339"
        ],
        "id": 1110260,
        "name:xx": "Atacama, Puna de"
      }
    },
    {
      "geometry": {
        "type": "Point",
        "coordinates": [
          3,
          44.6833
        ]
      },
      "type": "Feature",
      "properties": {
        "hierarchy": [
          "tgn:1110261",
          "tgn:1000003",
          "tgn:1000070",
          "tgn:7029392"
        ],
        "placetype": [
          "aat:300132339"
        ],
        "id": 1110261,
        "name:xx": "Aubrac"
      }
    },
    {
      "geometry": {
        "type": "Point",
        "coordinates": [
          82,
          24
        ]
      },
      "type": "Feature",
      "properties": {
        "hierarchy": [
          "tgn:1110262",
          "tgn:1000004",
          "tgn:7000198",
          "tgn:1001894",
          "tgn:7029392"
        ],
        "placetype": [
          "aat:300387346"
        ],
        "name:en": "Baghelkhand",
        "id": 1110262
      }
    },
    {
      "geometry": {
        "type": "Point",
        "coordinates": [
          13.7167,
          46.0833
        ]
      },
      "type": "Feature",
      "properties": {
        "hierarchy": [
          "tgn:1110263",
          "tgn:1000003",
          "tgn:7015085",
          "tgn:7006670",
          "tgn:7029392"
        ],
        "placetype": [
          "aat:300132339"
        ],
        "id": 1110263,
        "name:xx": "Banjšice"
      }
    },
    {
      "geometry": {
        "type": "Point",
        "coordinates": [
          15.75,
          3.5
        ]
      },
      "type": "Feature",
      "properties": {
        "hierarchy": [
          "tgn:1110265",
          "tgn:7001242",
          "tgn:1000158",
          "tgn:7029392"
        ],
        "placetype": [
          "aat:300132339"
        ],
        "id": 1110265,
        "name:xx": "Batéké, Plateau"
      }
    },
    {
      "geometry": {
        "type": "Point",
        "coordinates": [
          80.3333,
          24.1667
        ]
      },
      "type": "Feature",
      "properties": {
        "hierarchy": [
          "tgn:1110267",
          "tgn:1000004",
          "tgn:7000198",
          "tgn:1001894",
          "tgn:7029392"
        ],
        "placetype": [
          "aat:300132339"
        ],
        "id": 1110267,
        "name:xx": "Bhander Plateau"
      }
    },
    {
      "geometry": {
        "type": "Point",
        "coordinates": [
          2.9167,
          45.3333
        ]
      },
      "type": "Feature",
      "properties": {
        "hierarchy": [
          "tgn:1110269",
          "tgn:7002871",
          "tgn:1000003",
          "tgn:1000070",
          "tgn:7029392"
        ],
        "placetype": [
          "aat:300132339"
        ],
        "id": 1110269,
        "name:xx": "Cézallier, Monts du"
      }
    }
  ]
}
