{
  "geometry": {
    "type": "Point",
    "coordinates": [
      -121.35,
      47.5833
    ]
  },
  "type": "Feature",
  "properties": {
    "hierarchy": [
      "tgn:2233412",
      "tgn:1000001",
      "tgn:7012149",
      "tgn:7018871",
      "tgn:7007920",
      "tgn:7029392"
    ],
    "placetype": [
      "aat:300008680"
    ],
    "id": 2233412,
    "name:xx": "Charlie Lakes"
  }
}
