{
  "geometry": {
    "type": "Point",
    "coordinates": [
      -96.1167,
      37.5833
    ]
  },
  "type": "Feature",
  "properties": {
    "hierarchy": [
      "tgn:2460351",
      "tgn:1000001",
      "tgn:7012149",
      "tgn:7007254",
      "tgn:7029392"
    ],
    "placetype": [
      "aat:300008706"
    ],
    "id": 2460351,
    "name:xx": "Little Salt Creek"
  }
}
