{
  "geometry": {
    "type": "Point",
    "coordinates": [
      -119.6667,
      48.75
    ]
  },
  "type": "Feature",
  "properties": {
    "hierarchy": [
      "tgn:2421890",
      "tgn:1000001",
      "tgn:7012149",
      "tgn:1002742",
      "tgn:7007920",
      "tgn:7029392"
    ],
    "placetype": [
      "aat:300008680"
    ],
    "id": 2421890,
    "name:xx": "Jim Black Lake"
  }
}
