{
  "geometry": {
    "type": "Point",
    "coordinates": [
      -105.55,
      45.2167
    ]
  },
  "type": "Feature",
  "properties": {
    "hierarchy": [
      "tgn:2130751",
      "tgn:1000001",
      "tgn:7012149",
      "tgn:2001297",
      "tgn:7007524",
      "tgn:7029392"
    ],
    "placetype": [
      "aat:300008761"
    ],
    "id": 2130751,
    "name:xx": "Allison Draw"
  }
}
