{
  "geometry": {
    "type": "Point",
    "coordinates": [
      -80.9833,
      35.2333
    ]
  },
  "type": "Feature",
  "properties": {
    "hierarchy": [
      "tgn:2762977",
      "tgn:1000001",
      "tgn:7012149",
      "tgn:7014021",
      "tgn:7007709",
      "tgn:7029392"
    ],
    "placetype": [
      "aat:300008347"
    ],
    "id": 2762977,
    "name:xx": "Westmoreland"
  }
}
