{
  "geometry": {
    "type": "Point",
    "coordinates": [
      103.35,
      21.9167
    ]
  },
  "type": "Feature",
  "properties": {
    "hierarchy": [
      "tgn:1087267",
      "tgn:1000004",
      "tgn:7001048",
      "tgn:1000145",
      "tgn:7029392"
    ],
    "placetype": [
      "aat:300008347"
    ],
    "id": 1087267,
    "name:xx": "Tủa Chùa"
  }
}
