{
  "geometry": {
    "type": "Point",
    "coordinates": [
      75.365319,
      28.251349
    ]
  },
  "type": "Feature",
  "properties": {
    "hierarchy": [
      "tgn:7583709",
      "tgn:1000004",
      "tgn:7000198",
      "tgn:7016788",
      "tgn:7029392"
    ],
    "placetype": [
      "aat:300008347"
    ],
    "name:en": "Farāns Ka Bās",
    "id": 7583709
  }
}
