{
  "geometry": {
    "type": "Point",
    "coordinates": [
      -118.3833,
      37.15
    ]
  },
  "type": "Feature",
  "properties": {
    "hierarchy": [
      "tgn:2585889",
      "tgn:1000001",
      "tgn:7012149",
      "tgn:2000183",
      "tgn:7007157",
      "tgn:7029392"
    ],
    "placetype": [
      "aat:300008798"
    ],
    "id": 2585889,
    "name:xx": "Piper Peak"
  }
}
