{
  "type": "FeatureCollection",
  "features": [
    {
      "geometry": {
        "type": "Point",
        "coordinates": [
          -103.9667,
          32.8167
        ]
      },
      "type": "Feature",
      "properties": {
        "hierarchy": [
          "tgn:2067140",
          "tgn:1000001",
          "tgn:2001436",
          "tgn:7012149",
          "tgn:7007566",
          "tgn:7029392"
        ],
        "placetype": [
          "aat:300008347"
        ],
        "id": 2067140,
        "name:xx": "Loco Hills"
      }
    },
    {
      "geometry": {
        "type": "Point",
        "coordinates": [
          -103.4,
          35.35
        ]
      },
      "type": "Feature",
      "properties": {
        "hierarchy": [
          "tgn:2067141",
          "tgn:1000001",
          "tgn:7012149",
          "tgn:2001448",
          "tgn:7007566",
          "tgn:7029392"
        ],
        "placetype": [
          "aat:300008347"
        ],
        "id": 2067141,
        "name:xx": "Logan"
      }
    },
    {
      "geometry": {
        "type": "Point",
        "coordinates": [
          -108.7,
          32.35
        ]
      },
      "type": "Feature",
      "properties": {
        "hierarchy": [
          "tgn:2067142",
          "tgn:1000001",
          "tgn:7012149",
          "tgn:2001440",
          "tgn:7007566",
          "tgn:7029392"
        ],
        "placetype": [
          "aat:300008347",
          "aat:300008416"
        ],
        "id": 2067142,
        "name:xx": "Lordsburg"
      }
    },
    {
      "geometry": {
        "type": "Point",
        "coordinates": [
          -105.15,
          35.7167
        ]
      },
      "type": "Feature",
      "properties": {
        "hierarchy": [
          "tgn:2067143",
          "tgn:1000001",
          "tgn:7012149",
          "tgn:2001453",
          "tgn:7007566",
          "tgn:7029392"
        ],
        "placetype": [
          "aat:300008347",
          "aat:300387210"
        ],
        "id": 2067143,
        "name:xx": "Los Alamos"
      }
    },
    {
      "geometry": {
        "type": "Point",
        "coordinates": [
          -106.75,
          34.7167
        ]
      },
      "type": "Feature",
      "properties": {
        "hierarchy": [
          "tgn:2067145",
          "tgn:1000001",
          "tgn:7012149",
          "tgn:2001460",
          "tgn:7007566",
          "tgn:7029392"
        ],
        "placetype": [
          "aat:300008347"
        ],
        "id": 2067145,
        "name:xx": "Los Chavez"
      }
    },
    {
      "geometry": {
        "type": "Point",
        "coordinates": [
          -105.6333,
          36.3833
        ]
      },
      "type": "Feature",
      "properties": {
        "hierarchy": [
          "tgn:2067146",
          "tgn:1000001",
          "tgn:7012149",
          "tgn:2001457",
          "tgn:7007566",
          "tgn:7029392"
        ],
        "placetype": [
          "aat:300008347",
          "aat:300387210"
        ],
        "id": 2067146,
        "name:xx": "Los Cordovas"
      }
    },
    {
      "geometry": {
        "type": "Point",
        "coordinates": [
          -106.0333,
          36.1
        ]
      },
      "type": "Feature",
      "properties": {
        "hierarchy": [
          "tgn:2067149",
          "tgn:1000001",
          "tgn:7012149",
          "tgn:2001449",
          "tgn:7007566",
          "tgn:7029392"
        ],
        "placetype": [
          "aat:300008347",
          "aat:300387210"
        ],
        "id": 2067149,
        "name:xx": "Los Luceros"
      }
    }
  ]
}
