{
  "geometry": {
    "type": "Point",
    "coordinates": [
      74.879167,
      32.848611
    ]
  },
  "type": "Feature",
  "properties": {
    "hierarchy": [
      "tgn:7592517",
      "tgn:1000004",
      "tgn:7000198",
      "tgn:7000799",
      "tgn:7029392"
    ],
    "placetype": [
      "aat:300008863"
    ],
    "name:en": "Pungālīwāli Rakh",
    "id": 7592517
  }
}
