{
  "geometry": {
    "type": "Point",
    "coordinates": [
      -80.2167,
      34.8833
    ]
  },
  "type": "Feature",
  "properties": {
    "hierarchy": [
      "tgn:2767429",
      "tgn:2001466",
      "tgn:1000001",
      "tgn:7012149",
      "tgn:7007709",
      "tgn:7029392"
    ],
    "placetype": [
      "aat:300006191"
    ],
    "id": 2767429,
    "name:xx": "White Store Lake"
  }
}
