{
  "geometry": {
    "type": "Point",
    "coordinates": [
      -85.2333,
      36.9333
    ]
  },
  "type": "Feature",
  "properties": {
    "hierarchy": [
      "tgn:2197594",
      "tgn:2000765",
      "tgn:1000001",
      "tgn:7012149",
      "tgn:7007255",
      "tgn:7029392"
    ],
    "placetype": [
      "aat:300008761"
    ],
    "id": 2197594,
    "name:xx": "Brown Hollow"
  }
}
