{
  "geometry": {
    "type": "Point",
    "coordinates": [
      -81.3667,
      38.5333
    ]
  },
  "type": "Feature",
  "properties": {
    "hierarchy": [
      "tgn:2671429",
      "tgn:1000001",
      "tgn:7012149",
      "tgn:7013961",
      "tgn:7029392"
    ],
    "placetype": [
      "aat:300008761"
    ],
    "id": 2671429,
    "name:xx": "Smith Hollow"
  }
}
