{
  "geometry": {
    "type": "Point",
    "coordinates": [
      -122.35,
      47.9667
    ]
  },
  "type": "Feature",
  "properties": {
    "hierarchy": [
      "tgn:7020069",
      "tgn:1000001",
      "tgn:7012149",
      "tgn:1002505",
      "tgn:7007920",
      "tgn:7029392"
    ],
    "placetype": [
      "aat:300006191"
    ],
    "id": 7020069,
    "name:xx": "Orrs Pond"
  }
}
