{
  "geometry": {
    "type": "Point",
    "coordinates": [
      -84.9333,
      37.2333
    ]
  },
  "type": "Feature",
  "properties": {
    "hierarchy": [
      "tgn:2370736",
      "tgn:1000001",
      "tgn:2000779",
      "tgn:7012149",
      "tgn:7007255",
      "tgn:7029392"
    ],
    "placetype": [
      "aat:300266640"
    ],
    "id": 2370736,
    "name:xx": "Hacker Ridge"
  }
}
