{
  "geometry": {
    "type": "Point",
    "coordinates": [
      -97.2333,
      32.55
    ]
  },
  "type": "Feature",
  "properties": {
    "hierarchy": [
      "tgn:2742330",
      "tgn:1000001",
      "tgn:7012149",
      "tgn:7007826",
      "tgn:7029392"
    ],
    "placetype": [
      "aat:300008699"
    ],
    "id": 2742330,
    "name:xx": "Valley Branch"
  }
}
