{
  "geometry": {
    "type": "Point",
    "coordinates": [
      -99.7167,
      27.7333
    ]
  },
  "type": "Feature",
  "properties": {
    "hierarchy": [
      "tgn:2743943",
      "tgn:1000001",
      "tgn:7012149",
      "tgn:2002090",
      "tgn:7007826",
      "tgn:7029392"
    ],
    "placetype": [
      "aat:300006191"
    ],
    "id": 2743943,
    "name:xx": "Venancio Tank"
  }
}
