{
  "geometry": {
    "type": "Point",
    "coordinates": [
      -90.0167,
      35.1667
    ]
  },
  "type": "Feature",
  "properties": {
    "hierarchy": [
      "tgn:2708713",
      "tgn:1000001",
      "tgn:7012149",
      "tgn:2001915",
      "tgn:7007825",
      "tgn:7029392"
    ],
    "placetype": [
      "aat:300008347"
    ],
    "id": 2708713,
    "name:xx": "Sylvan Heights"
  }
}
