{
  "geometry": {
    "type": "Point",
    "coordinates": [
      121.44032,
      24.97759
    ]
  },
  "type": "Feature",
  "properties": {
    "hierarchy": [
      "tgn:7496104",
      "tgn:1000004",
      "tgn:1000454",
      "tgn:1000141",
      "tgn:7029392"
    ],
    "placetype": [
      "aat:300000498"
    ],
    "id": 7496104,
    "name:xx": "Changfeng Sancun"
  }
}
