{
  "geometry": {
    "type": "Point",
    "coordinates": [
      31.833333,
      31.35
    ]
  },
  "type": "Feature",
  "properties": {
    "hierarchy": [
      "tgn:7534294",
      "tgn:7001242",
      "tgn:7016833",
      "tgn:1001225",
      "tgn:7029392"
    ],
    "placetype": [
      "aat:300008791"
    ],
    "name:en": "Ḩaţab, Jazīrat al",
    "id": 7534294
  }
}
