{
  "geometry": {
    "type": "Point",
    "coordinates": [
      -75.2833,
      40.5167
    ]
  },
  "type": "Feature",
  "properties": {
    "hierarchy": [
      "tgn:2092080",
      "tgn:1000001",
      "tgn:1002213",
      "tgn:7012149",
      "tgn:7007710",
      "tgn:7029392"
    ],
    "placetype": [
      "aat:300008347"
    ],
    "id": 2092080,
    "name:xx": "Pleasant Valley"
  }
}
