{
  "type": "FeatureCollection",
  "features": [
    {
      "geometry": {
        "type": "Point",
        "coordinates": [
          -120.1333,
          44.8
        ]
      },
      "type": "Feature",
      "properties": {
        "hierarchy": [
          "tgn:2623340",
          "tgn:1000001",
          "tgn:7012149",
          "tgn:2001723",
          "tgn:7007708",
          "tgn:7029392"
        ],
        "placetype": [
          "aat:300008761"
        ],
        "id": 2623340,
        "name:xx": "Rock Canyon"
      }
    },
    {
      "geometry": {
        "type": "Point",
        "coordinates": [
          -122.2333,
          45.0333
        ]
      },
      "type": "Feature",
      "properties": {
        "hierarchy": [
          "tgn:2623341",
          "tgn:1000001",
          "tgn:1002270",
          "tgn:7012149",
          "tgn:7007708",
          "tgn:7029392"
        ],
        "placetype": [
          "aat:300008761"
        ],
        "id": 2623341,
        "name:xx": "Rock Canyon"
      }
    },
    {
      "geometry": {
        "type": "Point",
        "coordinates": [
          -121.1333,
          42.15
        ]
      },
      "type": "Feature",
      "properties": {
        "hierarchy": [
          "tgn:2623342",
          "tgn:1000001",
          "tgn:7012149",
          "tgn:2001714",
          "tgn:7007708",
          "tgn:7029392"
        ],
        "placetype": [
          "aat:300008761"
        ],
        "id": 2623342,
        "name:xx": "Rock Canyon"
      }
    },
    {
      "geometry": {
        "type": "Point",
        "coordinates": [
          -117.9333,
          42.1667
        ]
      },
      "type": "Feature",
      "properties": {
        "hierarchy": [
          "tgn:2623343",
          "tgn:1000001",
          "tgn:7012149",
          "tgn:2001718",
          "tgn:7007708",
          "tgn:7029392"
        ],
        "placetype": [
          "aat:300008761"
        ],
        "id": 2623343,
        "name:xx": "Rock Canyon"
      }
    },
    {
      "geometry": {
        "type": "Point",
        "coordinates": [
          -123.4833,
          44.2167
        ]
      },
      "type": "Feature",
      "properties": {
        "hierarchy": [
          "tgn:2623344",
          "tgn:1000001",
          "tgn:7012149",
          "tgn:2001716",
          "tgn:7007708",
          "tgn:7029392"
        ],
        "placetype": [
          "aat:300008761"
        ],
        "id": 2623344,
        "name:xx": "Rock Canyon"
      }
    },
    {
      "geometry": {
        "type": "Point",
        "coordinates": [
          -101.8,
          32.8333
        ]
      },
      "type": "Feature",
      "properties": {
        "hierarchy": [
          "tgn:2623345",
          "tgn:1000001",
          "tgn:7012149",
          "tgn:2001971",
          "tgn:7007826",
          "tgn:7029392"
        ],
        "placetype": [
          "aat:300008761"
        ],
        "id": 2623345,
        "name:xx": "Rock Canyon"
      }
    },
    {
      "geometry": {
        "type": "Point",
        "coordinates": [
          -101.5167,
          32.8333
        ]
      },
      "type": "Feature",
      "properties": {
        "hierarchy": [
          "tgn:2623346",
          "tgn:1000001",
          "tgn:2001943",
          "tgn:7012149",
          "tgn:7007826",
          "tgn:7029392"
        ],
        "placetype": [
          "aat:300008761"
        ],
        "id": 2623346,
        "name:xx": "Rock Canyon"
      }
    },
    {
      "geometry": {
        "type": "Point",
        "coordinates": [
          -99.1833,
          33.4167
        ]
      },
      "type": "Feature",
      "properties": {
        "hierarchy": [
          "tgn:2623347",
          "tgn:1000001",
          "tgn:2001939",
          "tgn:7012149",
          "tgn:7007826",
          "tgn:7029392"
        ],
        "placetype": [
          "aat:300008761"
        ],
        "id": 2623347,
        "name:xx": "Rock Canyon"
      }
    },
    {
      "geometry": {
        "type": "Point",
        "coordinates": [
          -102.2167,
          35.4
        ]
      },
      "type": "Feature",
      "properties": {
        "hierarchy": [
          "tgn:2623348",
          "tgn:1000001",
          "tgn:7012149",
          "tgn:2002051",
          "tgn:7007826",
          "tgn:7029392"
        ],
        "placetype": [
          "aat:300008761"
        ],
        "id": 2623348,
        "name:xx": "Rock Canyon"
      }
    },
    {
      "geometry": {
        "type": "Point",
        "coordinates": [
          -113.95,
          37.5333
        ]
      },
      "type": "Feature",
      "properties": {
        "hierarchy": [
          "tgn:2623349",
          "tgn:1000001",
          "tgn:7012149",
          "tgn:2002127",
          "tgn:7007827",
          "tgn:7029392"
        ],
        "placetype": [
          "aat:300008761"
        ],
        "id": 2623349,
        "name:xx": "Rock Canyon"
      }
    }
  ]
}
