{
  "geometry": {
    "type": "Point",
    "coordinates": [
      -108.8333,
      38.5833
    ]
  },
  "type": "Feature",
  "properties": {
    "hierarchy": [
      "tgn:2244171",
      "tgn:1000001",
      "tgn:7012149",
      "tgn:2000230",
      "tgn:7007158",
      "tgn:7029392"
    ],
    "placetype": [
      "aat:300000390"
    ],
    "id": 2244171,
    "name:xx": "Cliffdweller Mines"
  }
}
