{
  "geometry": {
    "type": "Point",
    "coordinates": [
      26.869722,
      37.708056
    ]
  },
  "type": "Feature",
  "properties": {
    "hierarchy": [
      "tgn:7220950",
      "tgn:7011164",
      "tgn:7002674",
      "tgn:1000003",
      "tgn:1000074",
      "tgn:7029392"
    ],
    "placetype": [
      "aat:300000641"
    ],
    "id": 7220950,
    "name:xx": "Moní Timíou Stavroú"
  }
}
