{
  "geometry": {
    "type": "Point",
    "coordinates": [
      31.63035,
      31.250692
    ]
  },
  "type": "Feature",
  "properties": {
    "hierarchy": [
      "tgn:7536736",
      "tgn:7001242",
      "tgn:1001059",
      "tgn:7016833",
      "tgn:7029392"
    ],
    "placetype": [
      "aat:300008347"
    ],
    "id": 7536736,
    "name:xx": "Kafr at Tur'ah al Jadīd"
  }
}
