{
  "geometry": {
    "type": "Point",
    "coordinates": [
      -106.5667,
      32.3333
    ]
  },
  "type": "Feature",
  "properties": {
    "hierarchy": [
      "tgn:2519429",
      "tgn:1000001",
      "tgn:2001435",
      "tgn:7012149",
      "tgn:7007566",
      "tgn:7029392"
    ],
    "placetype": [
      "aat:300008347",
      "aat:300167671",
      "aat:300387243"
    ],
    "id": 2519429,
    "name:xx": "Modoc"
  }
}
