{
  "geometry": {
    "type": "Point",
    "coordinates": [
      -76.9167,
      42.2833
    ]
  },
  "type": "Feature",
  "properties": {
    "hierarchy": [
      "tgn:2305760",
      "tgn:1000001",
      "tgn:7012149",
      "tgn:7007568",
      "tgn:7029392"
    ],
    "placetype": [
      "aat:300008706"
    ],
    "id": 2305760,
    "name:xx": "East Creek"
  }
}
