{
  "geometry": {
    "type": "Point",
    "coordinates": [
      -87.05,
      39.3667
    ]
  },
  "type": "Feature",
  "properties": {
    "hierarchy": [
      "tgn:2657735",
      "tgn:1000001",
      "tgn:7012149",
      "tgn:2000544",
      "tgn:7007252",
      "tgn:7029392"
    ],
    "placetype": [
      "aat:300006075"
    ],
    "id": 2657735,
    "name:xx": "Shelkett Ditch"
  }
}
