{
  "geometry": {
    "type": "Point",
    "coordinates": [
      31.666667,
      26.55
    ]
  },
  "type": "Feature",
  "properties": {
    "hierarchy": [
      "tgn:7536363",
      "tgn:7001242",
      "tgn:7016833",
      "tgn:7000124",
      "tgn:7029392"
    ],
    "placetype": [
      "aat:300008347"
    ],
    "name:en": "Khuşş al Būşah",
    "id": 7536363
  }
}
