{
  "geometry": {
    "type": "Point",
    "coordinates": [
      77.733057,
      26.339861
    ]
  },
  "type": "Feature",
  "properties": {
    "hierarchy": [
      "tgn:7581293",
      "tgn:1000004",
      "tgn:7000198",
      "tgn:1001894",
      "tgn:7029392"
    ],
    "placetype": [
      "aat:300007783"
    ],
    "name:en": "Sikrodā",
    "id": 7581293
  }
}
