{
  "geometry": {
    "type": "Point",
    "coordinates": [
      -155.2167,
      66.1833
    ]
  },
  "type": "Feature",
  "properties": {
    "hierarchy": [
      "tgn:2141639",
      "tgn:7006450",
      "tgn:1000001",
      "tgn:7012149",
      "tgn:2000089",
      "tgn:7029392"
    ],
    "placetype": [
      "aat:300008706"
    ],
    "id": 2141639,
    "name:xx": "Babantaltlin Creek"
  }
}
