{
  "type": "FeatureCollection",
  "features": [
    {
      "geometry": {
        "type": "Point",
        "coordinates": [
          -115.4667,
          33.0167
        ]
      },
      "type": "Feature",
      "properties": {
        "hierarchy": [
          "tgn:2523300",
          "tgn:1000001",
          "tgn:7012149",
          "tgn:2000182",
          "tgn:7007157",
          "tgn:7029392"
        ],
        "placetype": [
          "aat:300006075"
        ],
        "id": 2523300,
        "name:xx": "Moorhead Canal"
      }
    },
    {
      "geometry": {
        "type": "Point",
        "coordinates": [
          -95.6833,
          42.3833
        ]
      },
      "type": "Feature",
      "properties": {
        "hierarchy": [
          "tgn:2523301",
          "tgn:1000001",
          "tgn:7012149",
          "tgn:7007253",
          "tgn:7029392"
        ],
        "placetype": [
          "aat:300008706"
        ],
        "id": 2523301,
        "name:xx": "Moorhead Creek"
      }
    },
    {
      "geometry": {
        "type": "Point",
        "coordinates": [
          -115.4667,
          33.0167
        ]
      },
      "type": "Feature",
      "properties": {
        "hierarchy": [
          "tgn:2523302",
          "tgn:1000001",
          "tgn:7012149",
          "tgn:2000182",
          "tgn:7007157",
          "tgn:7029392"
        ],
        "placetype": [
          "aat:300006075"
        ],
        "id": 2523302,
        "name:xx": "Moorhead Drain"
      }
    },
    {
      "geometry": {
        "type": "Point",
        "coordinates": [
          -105.4,
          40.1167
        ]
      },
      "type": "Feature",
      "properties": {
        "hierarchy": [
          "tgn:2523303",
          "tgn:1000001",
          "tgn:2000198",
          "tgn:7012149",
          "tgn:7007158",
          "tgn:7029392"
        ],
        "placetype": [
          "aat:300008761"
        ],
        "id": 2523303,
        "name:xx": "Moorhead Gulch"
      }
    },
    {
      "geometry": {
        "type": "Point",
        "coordinates": [
          -86.4,
          35.1667
        ]
      },
      "type": "Feature",
      "properties": {
        "hierarchy": [
          "tgn:2523304",
          "tgn:1000001",
          "tgn:7012149",
          "tgn:2001888",
          "tgn:7007825",
          "tgn:7029392"
        ],
        "placetype": [
          "aat:300008761"
        ],
        "id": 2523304,
        "name:xx": "Moorhead Hollow"
      }
    },
    {
      "geometry": {
        "type": "Point",
        "coordinates": [
          -119.15,
          45.8167
        ]
      },
      "type": "Feature",
      "properties": {
        "hierarchy": [
          "tgn:2523305",
          "tgn:1000001",
          "tgn:7012149",
          "tgn:2001720",
          "tgn:7007708",
          "tgn:7029392"
        ],
        "placetype": [
          "aat:300008347"
        ],
        "id": 2523305,
        "name:xx": "Moorhouse"
      }
    },
    {
      "geometry": {
        "type": "Point",
        "coordinates": [
          -76.85,
          37.0833
        ]
      },
      "type": "Feature",
      "properties": {
        "hierarchy": [
          "tgn:2523306",
          "tgn:1000001",
          "tgn:7012149",
          "tgn:1002931",
          "tgn:7007919",
          "tgn:7029392"
        ],
        "placetype": [
          "aat:300008347"
        ],
        "id": 2523306,
        "name:xx": "Mooring"
      }
    },
    {
      "geometry": {
        "type": "Point",
        "coordinates": [
          -95.9,
          30.65
        ]
      },
      "type": "Feature",
      "properties": {
        "hierarchy": [
          "tgn:2523307",
          "tgn:1000001",
          "tgn:7012149",
          "tgn:1002429",
          "tgn:7007826",
          "tgn:7029392"
        ],
        "placetype": [
          "aat:300008706"
        ],
        "id": 2523307,
        "name:xx": "Mooring Creek"
      }
    },
    {
      "geometry": {
        "type": "Point",
        "coordinates": [
          -81.8,
          26.1667
        ]
      },
      "type": "Feature",
      "properties": {
        "hierarchy": [
          "tgn:2523308",
          "tgn:1000001",
          "tgn:1002289",
          "tgn:7012149",
          "tgn:7007240",
          "tgn:7029392"
        ],
        "placetype": [
          "aat:300132316"
        ],
        "id": 2523308,
        "name:xx": "Moorings Bay"
      }
    },
    {
      "geometry": {
        "type": "Point",
        "coordinates": [
          -122.2,
          47.6
        ]
      },
      "type": "Feature",
      "properties": {
        "hierarchy": [
          "tgn:2523309",
          "tgn:1000001",
          "tgn:7012149",
          "tgn:7018871",
          "tgn:7007920",
          "tgn:7029392"
        ],
        "placetype": [
          "aat:300008347"
        ],
        "id": 2523309,
        "name:xx": "Moorland"
      }
    }
  ]
}
