{
  "geometry": {
    "type": "Point",
    "coordinates": [
      -105.0833,
      36.85
    ]
  },
  "type": "Feature",
  "properties": {
    "hierarchy": [
      "tgn:2495508",
      "tgn:1000001",
      "tgn:2001432",
      "tgn:7012149",
      "tgn:7007566",
      "tgn:7029392"
    ],
    "placetype": [
      "aat:300008680"
    ],
    "id": 2495508,
    "name:xx": "Marys Lake"
  }
}
