{
  "type": "FeatureCollection",
  "features": [
    {
      "geometry": {
        "type": "Point",
        "coordinates": [
          -76.8833,
          40.9333
        ]
      },
      "type": "Feature",
      "properties": {
        "hierarchy": [
          "tgn:2514910",
          "tgn:1000001",
          "tgn:7012149",
          "tgn:1002965",
          "tgn:7007710",
          "tgn:7029392"
        ],
        "placetype": [
          "aat:300008699"
        ],
        "id": 2514910,
        "name:xx": "Miller Run"
      }
    },
    {
      "geometry": {
        "type": "Point",
        "coordinates": [
          -72.1,
          44.6333
        ]
      },
      "type": "Feature",
      "properties": {
        "hierarchy": [
          "tgn:2514911",
          "tgn:2002131",
          "tgn:1000001",
          "tgn:7012149",
          "tgn:7007828",
          "tgn:7029392"
        ],
        "placetype": [
          "aat:300008699"
        ],
        "id": 2514911,
        "name:xx": "Miller Run"
      }
    },
    {
      "geometry": {
        "type": "Point",
        "coordinates": [
          -78.3333,
          39.3333
        ]
      },
      "type": "Feature",
      "properties": {
        "hierarchy": [
          "tgn:2514912",
          "tgn:1000001",
          "tgn:7012149",
          "tgn:2002161",
          "tgn:7007919",
          "tgn:7029392"
        ],
        "placetype": [
          "aat:300008699"
        ],
        "id": 2514912,
        "name:xx": "Miller Run"
      }
    },
    {
      "geometry": {
        "type": "Point",
        "coordinates": [
          -78.75,
          38.2167
        ]
      },
      "type": "Feature",
      "properties": {
        "hierarchy": [
          "tgn:2514913",
          "tgn:1000001",
          "tgn:7012149",
          "tgn:2002187",
          "tgn:7007919",
          "tgn:7029392"
        ],
        "placetype": [
          "aat:300008699"
        ],
        "id": 2514913,
        "name:xx": "Miller Run"
      }
    },
    {
      "geometry": {
        "type": "Point",
        "coordinates": [
          -81.3167,
          38.8333
        ]
      },
      "type": "Feature",
      "properties": {
        "hierarchy": [
          "tgn:2514914",
          "tgn:1000001",
          "tgn:7012149",
          "tgn:2002293",
          "tgn:7013961",
          "tgn:7029392"
        ],
        "placetype": [
          "aat:300008699"
        ],
        "id": 2514914,
        "name:xx": "Miller Run"
      }
    },
    {
      "geometry": {
        "type": "Point",
        "coordinates": [
          -80.3667,
          39.6833
        ]
      },
      "type": "Feature",
      "properties": {
        "hierarchy": [
          "tgn:2514917",
          "tgn:1000001",
          "tgn:7012149",
          "tgn:2002281",
          "tgn:7013961",
          "tgn:7029392"
        ],
        "placetype": [
          "aat:300008699"
        ],
        "id": 2514917,
        "name:xx": "Miller Run"
      }
    },
    {
      "geometry": {
        "type": "Point",
        "coordinates": [
          -77.45,
          41.3667
        ]
      },
      "type": "Feature",
      "properties": {
        "hierarchy": [
          "tgn:2514918",
          "tgn:1000001",
          "tgn:7012149",
          "tgn:1002613",
          "tgn:7007710",
          "tgn:7029392"
        ],
        "placetype": [
          "aat:300055621"
        ],
        "id": 2514918,
        "name:xx": "Miller Run Natural Area"
      }
    },
    {
      "geometry": {
        "type": "Point",
        "coordinates": [
          -123.65,
          46.2333
        ]
      },
      "type": "Feature",
      "properties": {
        "hierarchy": [
          "tgn:2514919",
          "tgn:1000001",
          "tgn:1002276",
          "tgn:7012149",
          "tgn:7007708",
          "tgn:7029392"
        ],
        "placetype": [
          "aat:300386848"
        ],
        "id": 2514919,
        "name:xx": "Miller Sands"
      }
    }
  ]
}
