{
  "geometry": {
    "type": "Point",
    "coordinates": [
      34.575968,
      24.76783
    ]
  },
  "type": "Feature",
  "properties": {
    "hierarchy": [
      "tgn:7536862",
      "tgn:7001242",
      "tgn:7001311",
      "tgn:7016833",
      "tgn:7029392"
    ],
    "placetype": [
      "aat:300008795"
    ],
    "name:en": "Ḩafāfīt, Jabal",
    "id": 7536862
  }
}
