{
  "geometry": {
    "type": "Point",
    "coordinates": [
      -85.3333,
      38.2667
    ]
  },
  "type": "Feature",
  "properties": {
    "hierarchy": [
      "tgn:2482159",
      "tgn:1000001",
      "tgn:7012149",
      "tgn:7007255",
      "tgn:7029392"
    ],
    "placetype": [
      "aat:300008699"
    ],
    "id": 2482159,
    "name:xx": "Lang Run"
  }
}
