{
  "geometry": {
    "type": "Point",
    "coordinates": [
      -91.5167,
      36.45
    ]
  },
  "type": "Feature",
  "properties": {
    "hierarchy": [
      "tgn:2325724",
      "tgn:1000001",
      "tgn:7012149",
      "tgn:7029392"
    ],
    "placetype": [
      "aat:300008706"
    ],
    "id": 2325724,
    "name:xx": "Field Creek"
  }
}
