{
  "geometry": {
    "type": "Point",
    "coordinates": [
      -114.9333,
      42.9167
    ]
  },
  "type": "Feature",
  "properties": {
    "hierarchy": [
      "tgn:2025397",
      "tgn:1000001",
      "tgn:7012149",
      "tgn:2000475",
      "tgn:7007250",
      "tgn:7029392"
    ],
    "placetype": [
      "aat:300008347"
    ],
    "id": 2025397,
    "name:xx": "Bliss"
  }
}
