{
  "type": "FeatureCollection",
  "features": [
    {
      "geometry": {
        "type": "Point",
        "coordinates": [
          -82.8833,
          35.1833
        ]
      },
      "type": "Feature",
      "properties": {
        "hierarchy": [
          "tgn:2421200",
          "tgn:1000001",
          "tgn:7012149",
          "tgn:2001544",
          "tgn:7007709",
          "tgn:7029392"
        ],
        "placetype": [
          "aat:300008699"
        ],
        "id": 2421200,
        "name:xx": "Jerry Branch"
      }
    },
    {
      "geometry": {
        "type": "Point",
        "coordinates": [
          -97.1167,
          33.95
        ]
      },
      "type": "Feature",
      "properties": {
        "hierarchy": [
          "tgn:2421201",
          "tgn:1000001",
          "tgn:7012149",
          "tgn:2001665",
          "tgn:7007707",
          "tgn:7029392"
        ],
        "placetype": [
          "aat:300008699"
        ],
        "id": 2421201,
        "name:xx": "Jerry Branch"
      }
    },
    {
      "geometry": {
        "type": "Point",
        "coordinates": [
          -84.7,
          36.2167
        ]
      },
      "type": "Feature",
      "properties": {
        "hierarchy": [
          "tgn:2421202",
          "tgn:1000001",
          "tgn:7012149",
          "tgn:2001901",
          "tgn:7007825",
          "tgn:7029392"
        ],
        "placetype": [
          "aat:300008699"
        ],
        "id": 2421202,
        "name:xx": "Jerry Branch"
      }
    },
    {
      "geometry": {
        "type": "Point",
        "coordinates": [
          -84.9,
          35.0333
        ]
      },
      "type": "Feature",
      "properties": {
        "hierarchy": [
          "tgn:2421203",
          "tgn:1000001",
          "tgn:2001842",
          "tgn:7012149",
          "tgn:7007825",
          "tgn:7029392"
        ],
        "placetype": [
          "aat:300008699"
        ],
        "id": 2421203,
        "name:xx": "Jerry Branch"
      }
    },
    {
      "geometry": {
        "type": "Point",
        "coordinates": [
          -82.4333,
          37.1667
        ]
      },
      "type": "Feature",
      "properties": {
        "hierarchy": [
          "tgn:2421204",
          "tgn:1000001",
          "tgn:7012149",
          "tgn:2002157",
          "tgn:7007919",
          "tgn:7029392"
        ],
        "placetype": [
          "aat:300008699"
        ],
        "id": 2421204,
        "name:xx": "Jerry Branch"
      }
    },
    {
      "geometry": {
        "type": "Point",
        "coordinates": [
          -79.75,
          37.8667
        ]
      },
      "type": "Feature",
      "properties": {
        "hierarchy": [
          "tgn:2421205",
          "tgn:2002138",
          "tgn:1000001",
          "tgn:7012149",
          "tgn:7007919",
          "tgn:7029392"
        ],
        "placetype": [
          "aat:300008699"
        ],
        "id": 2421205,
        "name:xx": "Jerry Branch"
      }
    },
    {
      "geometry": {
        "type": "Point",
        "coordinates": [
          -68.6667,
          45.65
        ]
      },
      "type": "Feature",
      "properties": {
        "hierarchy": [
          "tgn:2421206",
          "tgn:1000001",
          "tgn:7012149",
          "tgn:2000927",
          "tgn:7007515",
          "tgn:7029392"
        ],
        "placetype": [
          "aat:300008699"
        ],
        "id": 2421206,
        "name:xx": "Jerry Brook"
      }
    },
    {
      "geometry": {
        "type": "Point",
        "coordinates": [
          -70.5,
          44.05
        ]
      },
      "type": "Feature",
      "properties": {
        "hierarchy": [
          "tgn:2421207",
          "tgn:1000001",
          "tgn:2000920",
          "tgn:7012149",
          "tgn:7007515",
          "tgn:7029392"
        ],
        "placetype": [
          "aat:300008699"
        ],
        "id": 2421207,
        "name:xx": "Jerry Brook"
      }
    },
    {
      "geometry": {
        "type": "Point",
        "coordinates": [
          -120.5333,
          39.0167
        ]
      },
      "type": "Feature",
      "properties": {
        "hierarchy": [
          "tgn:2421208",
          "tgn:1000001",
          "tgn:7012149",
          "tgn:7007157",
          "tgn:1002791",
          "tgn:7029392"
        ],
        "placetype": [
          "aat:300008761"
        ],
        "id": 2421208,
        "name:xx": "Jerry Canyon"
      }
    },
    {
      "geometry": {
        "type": "Point",
        "coordinates": [
          -105.6833,
          35.35
        ]
      },
      "type": "Feature",
      "properties": {
        "hierarchy": [
          "tgn:2421209",
          "tgn:1000001",
          "tgn:7012149",
          "tgn:7007566",
          "tgn:7029392"
        ],
        "placetype": [
          "aat:300008761"
        ],
        "id": 2421209,
        "name:xx": "Jerry Canyon"
      }
    }
  ]
}
