{
  "type": "FeatureCollection",
  "features": [
    {
      "geometry": {
        "type": "Point",
        "coordinates": [
          -77.1833,
          39.2333
        ]
      },
      "type": "Feature",
      "properties": {
        "hierarchy": [
          "tgn:2049260",
          "tgn:1000001",
          "tgn:7016104",
          "tgn:7012149",
          "tgn:7007516",
          "tgn:7029392"
        ],
        "placetype": [
          "aat:300008347"
        ],
        "id": 2049260,
        "name:xx": "Woodfield"
      }
    },
    {
      "geometry": {
        "type": "Point",
        "coordinates": [
          -78.95,
          39.6
        ]
      },
      "type": "Feature",
      "properties": {
        "hierarchy": [
          "tgn:2049262",
          "tgn:2000934",
          "tgn:1000001",
          "tgn:7012149",
          "tgn:7007516",
          "tgn:7029392"
        ],
        "placetype": [
          "aat:300008347"
        ],
        "id": 2049262,
        "name:xx": "Woodland"
      }
    },
    {
      "geometry": {
        "type": "Point",
        "coordinates": [
          -76.8667,
          38.2667
        ]
      },
      "type": "Feature",
      "properties": {
        "hierarchy": [
          "tgn:2049264",
          "tgn:7016100",
          "tgn:1000001",
          "tgn:7012149",
          "tgn:7007516",
          "tgn:7029392"
        ],
        "placetype": [
          "aat:300008347"
        ],
        "id": 2049264,
        "name:xx": "Woodland Point"
      }
    },
    {
      "geometry": {
        "type": "Point",
        "coordinates": [
          -76.7167,
          39.3167
        ]
      },
      "type": "Feature",
      "properties": {
        "hierarchy": [
          "tgn:2049267",
          "tgn:7016099",
          "tgn:1000001",
          "tgn:7012149",
          "tgn:7007516",
          "tgn:7029392"
        ],
        "placetype": [
          "aat:300008347"
        ],
        "id": 2049267,
        "name:xx": "Woodlawn"
      }
    },
    {
      "geometry": {
        "type": "Point",
        "coordinates": [
          -76.8833,
          38.9333
        ]
      },
      "type": "Feature",
      "properties": {
        "hierarchy": [
          "tgn:2049268",
          "tgn:1000001",
          "tgn:2124001",
          "tgn:7012149",
          "tgn:7007516",
          "tgn:7029392"
        ],
        "placetype": [
          "aat:300008347"
        ],
        "id": 2049268,
        "name:xx": "Woodlawn"
      }
    },
    {
      "geometry": {
        "type": "Point",
        "coordinates": [
          -76.0667,
          39.6333
        ]
      },
      "type": "Feature",
      "properties": {
        "hierarchy": [
          "tgn:2049269",
          "tgn:1002247",
          "tgn:1000001",
          "tgn:7012149",
          "tgn:7007516",
          "tgn:7029392"
        ],
        "placetype": [
          "aat:300008347",
          "aat:300387210"
        ],
        "id": 2049269,
        "name:xx": "Woodlawn"
      }
    }
  ]
}
