{
  "geometry": {
    "type": "Point",
    "coordinates": [
      -75.0833,
      38.4667
    ]
  },
  "type": "Feature",
  "properties": {
    "hierarchy": [
      "tgn:2152859",
      "tgn:1000001",
      "tgn:7012149",
      "tgn:7029392"
    ],
    "placetype": [
      "aat:300132316"
    ],
    "id": 2152859,
    "name:xx": "Bayville Gut"
  }
}
