{
  "geometry": {
    "type": "Point",
    "coordinates": [
      -75.9833,
      36.6667
    ]
  },
  "type": "Feature",
  "properties": {
    "hierarchy": [
      "tgn:2233072",
      "tgn:1000001",
      "tgn:7012149",
      "tgn:7022218",
      "tgn:7007919",
      "tgn:7029392"
    ],
    "placetype": [
      "aat:300008850"
    ],
    "id": 2233072,
    "name:xx": "Charity Neck"
  }
}
