{
  "geometry": {
    "type": "Point",
    "coordinates": [
      -99.35,
      28.0333
    ]
  },
  "type": "Feature",
  "properties": {
    "hierarchy": [
      "tgn:2104068",
      "tgn:1000001",
      "tgn:7012149",
      "tgn:2002027",
      "tgn:7007826",
      "tgn:7029392"
    ],
    "placetype": [
      "aat:300008347"
    ],
    "id": 2104068,
    "name:xx": "Encinal"
  }
}
