{
  "geometry": {
    "type": "Point",
    "coordinates": [
      -80.5667,
      37.9833
    ]
  },
  "type": "Feature",
  "properties": {
    "hierarchy": [
      "tgn:2444047",
      "tgn:1000001",
      "tgn:7012149",
      "tgn:2002264",
      "tgn:7013961",
      "tgn:7029392"
    ],
    "placetype": [
      "aat:300386845"
    ],
    "id": 2444047,
    "name:xx": "LaFayette Bottom"
  }
}
