{
  "geometry": {
    "type": "Point",
    "coordinates": [
      148.0167,
      -35.8167
    ]
  },
  "type": "Feature",
  "properties": {
    "hierarchy": [
      "tgn:1098378",
      "tgn:7000490",
      "tgn:1000006",
      "tgn:7001828",
      "tgn:7029392"
    ],
    "placetype": [
      "aat:300008347"
    ],
    "id": 1098378,
    "name:xx": "Tumbarumba"
  }
}
