{
  "geometry": {
    "type": "Point",
    "coordinates": [
      -89.5167,
      37.6667
    ]
  },
  "type": "Feature",
  "properties": {
    "hierarchy": [
      "tgn:2192973",
      "tgn:1000001",
      "tgn:7012149",
      "tgn:2001228",
      "tgn:7007523",
      "tgn:7029392"
    ],
    "placetype": [
      "aat:300055621"
    ],
    "id": 2192973,
    "name:xx": "Brazeau Bottoms"
  }
}
