{
  "geometry": {
    "type": "Point",
    "coordinates": [
      -84.7167,
      41.7833
    ]
  },
  "type": "Feature",
  "properties": {
    "hierarchy": [
      "tgn:2422888",
      "tgn:1000001",
      "tgn:7012149",
      "tgn:1002481",
      "tgn:7007520",
      "tgn:7029392"
    ],
    "placetype": [
      "aat:300008699"
    ],
    "id": 2422888,
    "name:xx": "Joe Drain"
  }
}
