{
  "geometry": {
    "type": "Point",
    "coordinates": [
      -77.95,
      36.6667
    ]
  },
  "type": "Feature",
  "properties": {
    "hierarchy": [
      "tgn:2505912",
      "tgn:1000001",
      "tgn:2002147",
      "tgn:7012149",
      "tgn:7007919",
      "tgn:7029392"
    ],
    "placetype": [
      "aat:300008347"
    ],
    "id": 2505912,
    "name:xx": "Merchant"
  }
}
