{
  "geometry": {
    "type": "Point",
    "coordinates": [
      -75.0667,
      44.8333
    ]
  },
  "type": "Feature",
  "properties": {
    "hierarchy": [
      "tgn:2068452",
      "tgn:1000001",
      "tgn:7012149",
      "tgn:7016021",
      "tgn:7007568",
      "tgn:7029392"
    ],
    "placetype": [
      "aat:300008347"
    ],
    "id": 2068452,
    "name:xx": "Chase Mills"
  }
}
