{
  "geometry": {
    "type": "Point",
    "coordinates": [
      -94.3833,
      35.5167
    ]
  },
  "type": "Feature",
  "properties": {
    "hierarchy": [
      "tgn:2295486",
      "tgn:1000001",
      "tgn:7016172",
      "tgn:2000121",
      "tgn:7012149",
      "tgn:7029392"
    ],
    "placetype": [
      "aat:300008697"
    ],
    "id": 2295486,
    "name:xx": "Dripping Spring"
  }
}
