{
  "geometry": {
    "type": "Point",
    "coordinates": [
      79.8782,
      27.0689
    ]
  },
  "type": "Feature",
  "properties": {
    "hierarchy": [
      "tgn:7563014",
      "tgn:1000004",
      "tgn:7000198",
      "tgn:7016722",
      "tgn:7029392"
    ],
    "placetype": [
      "aat:300008347"
    ],
    "name:en": "Panwāra",
    "id": 7563014
  }
}
