{
  "geometry": {
    "type": "Point",
    "coordinates": [
      -95.05,
      39.9667
    ]
  },
  "type": "Feature",
  "properties": {
    "hierarchy": [
      "tgn:2623612",
      "tgn:1000001",
      "tgn:7012149",
      "tgn:2001204",
      "tgn:7007523",
      "tgn:7029392"
    ],
    "placetype": [
      "aat:300008706"
    ],
    "id": 2623612,
    "name:xx": "Rock Creek"
  }
}
