{
  "type": "FeatureCollection",
  "features": [
    {
      "geometry": {
        "type": "Point",
        "coordinates": [
          -85.8167,
          33.25
        ]
      },
      "type": "Feature",
      "properties": {
        "hierarchy": [
          "tgn:2507090",
          "tgn:7002659",
          "tgn:1000001",
          "tgn:2000013",
          "tgn:7012149",
          "tgn:7029392"
        ],
        "placetype": [
          "aat:300008706"
        ],
        "id": 2507090,
        "name:xx": "Metcalf Creek"
      }
    },
    {
      "geometry": {
        "type": "Point",
        "coordinates": [
          -116.9333,
          34.2167
        ]
      },
      "type": "Feature",
      "properties": {
        "hierarchy": [
          "tgn:2507091",
          "tgn:1000001",
          "tgn:7012149",
          "tgn:7007157",
          "tgn:1002857",
          "tgn:7029392"
        ],
        "placetype": [
          "aat:300008706"
        ],
        "id": 2507091,
        "name:xx": "Metcalf Creek"
      }
    },
    {
      "geometry": {
        "type": "Point",
        "coordinates": [
          -106.5,
          39.6833
        ]
      },
      "type": "Feature",
      "properties": {
        "hierarchy": [
          "tgn:2507092",
          "tgn:1000001",
          "tgn:7012149",
          "tgn:2000210",
          "tgn:7007158",
          "tgn:7029392"
        ],
        "placetype": [
          "aat:300008706"
        ],
        "id": 2507092,
        "name:xx": "Metcalf Creek"
      }
    },
    {
      "geometry": {
        "type": "Point",
        "coordinates": [
          -83.25,
          34.95
        ]
      },
      "type": "Feature",
      "properties": {
        "hierarchy": [
          "tgn:2507093",
          "tgn:1000001",
          "tgn:7012149",
          "tgn:2000410",
          "tgn:7007248",
          "tgn:7029392"
        ],
        "placetype": [
          "aat:300008706"
        ],
        "id": 2507093,
        "name:xx": "Metcalf Creek"
      }
    },
    {
      "geometry": {
        "type": "Point",
        "coordinates": [
          -70.8333,
          42.7167
        ]
      },
      "type": "Feature",
      "properties": {
        "hierarchy": [
          "tgn:2507094",
          "tgn:1000001",
          "tgn:1002359",
          "tgn:7012149",
          "tgn:7007517",
          "tgn:7029392"
        ],
        "placetype": [
          "aat:300008706"
        ],
        "id": 2507094,
        "name:xx": "Metcalf Creek"
      }
    },
    {
      "geometry": {
        "type": "Point",
        "coordinates": [
          -106.5167,
          39.6333
        ]
      },
      "type": "Feature",
      "properties": {
        "hierarchy": [
          "tgn:2507095",
          "tgn:1000001",
          "tgn:7012149",
          "tgn:2000210",
          "tgn:7007158",
          "tgn:7029392"
        ],
        "placetype": [
          "aat:300006075"
        ],
        "id": 2507095,
        "name:xx": "Metcalf Ditch"
      }
    },
    {
      "geometry": {
        "type": "Point",
        "coordinates": [
          -84.9667,
          41.25
        ]
      },
      "type": "Feature",
      "properties": {
        "hierarchy": [
          "tgn:2507096",
          "tgn:1000001",
          "tgn:7012149",
          "tgn:7007252",
          "tgn:7029392"
        ],
        "placetype": [
          "aat:300006075"
        ],
        "id": 2507096,
        "name:xx": "Metcalf Ditch"
      }
    },
    {
      "geometry": {
        "type": "Point",
        "coordinates": [
          -84.9,
          41.3833
        ]
      },
      "type": "Feature",
      "properties": {
        "hierarchy": [
          "tgn:2507097",
          "tgn:1000001",
          "tgn:1002320",
          "tgn:7012149",
          "tgn:7007252",
          "tgn:7029392"
        ],
        "placetype": [
          "aat:300006075"
        ],
        "id": 2507097,
        "name:xx": "Metcalf Ditch"
      }
    },
    {
      "geometry": {
        "type": "Point",
        "coordinates": [
          -111.8833,
          39.15
        ]
      },
      "type": "Feature",
      "properties": {
        "hierarchy": [
          "tgn:2507098",
          "tgn:1000001",
          "tgn:7012149",
          "tgn:2002120",
          "tgn:7007827",
          "tgn:7029392"
        ],
        "placetype": [
          "aat:300006075"
        ],
        "id": 2507098,
        "name:xx": "Metcalf Ditch"
      }
    },
    {
      "geometry": {
        "type": "Point",
        "coordinates": [
          -124.1167,
          41.75
        ]
      },
      "type": "Feature",
      "properties": {
        "hierarchy": [
          "tgn:2507099",
          "tgn:1000001",
          "tgn:7012149",
          "tgn:2000180",
          "tgn:7007157",
          "tgn:7029392"
        ],
        "placetype": [
          "aat:300132451"
        ],
        "id": 2507099,
        "name:xx": "Metcalf Grove"
      }
    }
  ]
}
