{
  "geometry": {
    "type": "Point",
    "coordinates": [
      -113.5167,
      44.5333
    ]
  },
  "type": "Feature",
  "properties": {
    "hierarchy": [
      "tgn:2568400",
      "tgn:1000001",
      "tgn:7012149",
      "tgn:2000481",
      "tgn:7007250",
      "tgn:7029392"
    ],
    "placetype": [
      "aat:300008699"
    ],
    "id": 2568400,
    "name:xx": "Park Fork"
  }
}
