{
  "geometry": {
    "type": "Point",
    "coordinates": [
      -111.35,
      31.6333
    ]
  },
  "type": "Feature",
  "properties": {
    "hierarchy": [
      "tgn:2354684",
      "tgn:1000001",
      "tgn:7006451",
      "tgn:7012149",
      "tgn:2000100",
      "tgn:7029392"
    ],
    "placetype": [
      "aat:300000390"
    ],
    "id": 2354684,
    "name:xx": "Good Enough Mine"
  }
}
