{
  "geometry": {
    "type": "Point",
    "coordinates": [
      -84.3333,
      36.55
    ]
  },
  "type": "Feature",
  "properties": {
    "hierarchy": [
      "tgn:2648910",
      "tgn:1000001",
      "tgn:7012149",
      "tgn:2001912",
      "tgn:7007825",
      "tgn:7029392"
    ],
    "placetype": [
      "aat:300008699"
    ],
    "id": 2648910,
    "name:xx": "Scott Branch"
  }
}
