{
  "geometry": {
    "type": "Point",
    "coordinates": [
      -115.0167,
      43.1667
    ]
  },
  "type": "Feature",
  "properties": {
    "hierarchy": [
      "tgn:2214722",
      "tgn:1000001",
      "tgn:7012149",
      "tgn:2000475",
      "tgn:7007250",
      "tgn:7029392"
    ],
    "placetype": [
      "aat:300008706"
    ],
    "id": 2214722,
    "name:xx": "Calf Creek"
  }
}
