{
  "geometry": {
    "type": "Point",
    "coordinates": [
      -87.7667,
      38.75
    ]
  },
  "type": "Feature",
  "properties": {
    "hierarchy": [
      "tgn:2029646",
      "tgn:1000001",
      "tgn:7012149",
      "tgn:2000517",
      "tgn:7007251",
      "tgn:7029392"
    ],
    "placetype": [
      "aat:300008347"
    ],
    "id": 2029646,
    "name:xx": "Petrolia"
  }
}
