{
  "geometry": {
    "type": "Point",
    "coordinates": [
      -96.0167,
      29.3333
    ]
  },
  "type": "Feature",
  "properties": {
    "hierarchy": [
      "tgn:2490922",
      "tgn:1000001",
      "tgn:7012149",
      "tgn:1003019",
      "tgn:7007826",
      "tgn:7029392"
    ],
    "placetype": [
      "aat:300008680"
    ],
    "id": 2490922,
    "name:xx": "Manso Lake"
  }
}
