{
  "type": "FeatureCollection",
  "features": [
    {
      "geometry": {
        "type": "Point",
        "coordinates": [
          2.2667,
          48.8833
        ]
      },
      "type": "Feature",
      "properties": {
        "hierarchy": [
          "tgn:7009402",
          "tgn:1000003",
          "tgn:7002883",
          "tgn:1000070",
          "tgn:7029392"
        ],
        "placetype": [
          "aat:300008347",
          "aat:300387330",
          "aat:300000874",
          "aat:300008375",
          "aat:300387302"
        ],
        "id": 7009402,
        "name:xx": "Neuilly-sur-Seine"
      }
    },
    {
      "geometry": {
        "type": "Point",
        "coordinates": [
          2.7833,
          50.5833
        ]
      },
      "type": "Feature",
      "properties": {
        "hierarchy": [
          "tgn:7009403",
          "tgn:1000003",
          "tgn:7001097",
          "tgn:1000070",
          "tgn:7029392"
        ],
        "placetype": [
          "aat:300008347"
        ],
        "id": 7009403,
        "name:xx": "Neuve-Chapelle"
      }
    },
    {
      "geometry": {
        "type": "Point",
        "coordinates": [
          4.8,
          45.8833
        ]
      },
      "type": "Feature",
      "properties": {
        "hierarchy": [
          "tgn:7009404",
          "tgn:1000003",
          "tgn:1000070",
          "tgn:7002897",
          "tgn:7029392"
        ],
        "placetype": [
          "aat:300008347"
        ],
        "id": 7009404,
        "name:xx": "Neuville-sur-Saône"
      }
    },
    {
      "geometry": {
        "type": "Point",
        "coordinates": [
          1.2,
          45.6667
        ]
      },
      "type": "Feature",
      "properties": {
        "hierarchy": [
          "tgn:7009405",
          "tgn:1000003",
          "tgn:7001095",
          "tgn:1000070",
          "tgn:7029392"
        ],
        "placetype": [
          "aat:300008347"
        ],
        "id": 7009405,
        "name:xx": "Nexon"
      }
    },
    {
      "geometry": {
        "type": "Point",
        "coordinates": [
          -0.45,
          46.3167
        ]
      },
      "type": "Feature",
      "properties": {
        "hierarchy": [
          "tgn:7009406",
          "tgn:1000003",
          "tgn:7002892",
          "tgn:1000070",
          "tgn:7029392"
        ],
        "placetype": [
          "aat:300008347",
          "aat:300387225",
          "aat:300008389",
          "aat:300387330",
          "aat:300387512",
          "aat:300387285"
        ],
        "id": 7009406,
        "name:xx": "Niort"
      }
    },
    {
      "geometry": {
        "type": "Point",
        "coordinates": [
          2.5,
          48.8333
        ]
      },
      "type": "Feature",
      "properties": {
        "hierarchy": [
          "tgn:7009408",
          "tgn:1000003",
          "tgn:7002883",
          "tgn:1000070",
          "tgn:7029392"
        ],
        "placetype": [
          "aat:300008347"
        ],
        "id": 7009408,
        "name:xx": "Nogent-sur-Marne"
      }
    },
    {
      "geometry": {
        "type": "Point",
        "coordinates": [
          3.5167,
          48.5
        ]
      },
      "type": "Feature",
      "properties": {
        "hierarchy": [
          "tgn:7009409",
          "tgn:1000003",
          "tgn:7002880",
          "tgn:1000070",
          "tgn:7029392"
        ],
        "placetype": [
          "aat:300008347"
        ],
        "id": 7009409,
        "name:xx": "Nogent-sur-Seine"
      }
    }
  ]
}
