{
  "type": "FeatureCollection",
  "features": [
    {
      "geometry": {
        "type": "Point",
        "coordinates": [
          -84.35,
          10.4667
        ]
      },
      "type": "Feature",
      "properties": {
        "hierarchy": [
          "tgn:1016210",
          "tgn:1001093",
          "tgn:1000001",
          "tgn:7005364",
          "tgn:7029392"
        ],
        "placetype": [
          "aat:300008347"
        ],
        "id": 1016210,
        "name:xx": "Altamira"
      }
    },
    {
      "geometry": {
        "type": "Point",
        "coordinates": [
          -82.9667,
          9.5167
        ]
      },
      "type": "Feature",
      "properties": {
        "hierarchy": [
          "tgn:1016211",
          "tgn:1001391",
          "tgn:1000001",
          "tgn:7005364",
          "tgn:7029392"
        ],
        "placetype": [
          "aat:300008347"
        ],
        "id": 1016211,
        "name:xx": "Amubri"
      }
    },
    {
      "geometry": {
        "type": "Point",
        "coordinates": [
          -84.9,
          10.55
        ]
      },
      "type": "Feature",
      "properties": {
        "hierarchy": [
          "tgn:1016212",
          "tgn:1001274",
          "tgn:1000001",
          "tgn:7005364",
          "tgn:7029392"
        ],
        "placetype": [
          "aat:300008347"
        ],
        "id": 1016212,
        "name:xx": "Arenal"
      }
    },
    {
      "geometry": {
        "type": "Point",
        "coordinates": [
          -84.3833,
          9.9833
        ]
      },
      "type": "Feature",
      "properties": {
        "hierarchy": [
          "tgn:1016213",
          "tgn:1001093",
          "tgn:1000001",
          "tgn:7005364",
          "tgn:7029392"
        ],
        "placetype": [
          "aat:300008347"
        ],
        "id": 1016213,
        "name:xx": "Atenas"
      }
    },
    {
      "geometry": {
        "type": "Point",
        "coordinates": [
          -85.3,
          10.5167
        ]
      },
      "type": "Feature",
      "properties": {
        "hierarchy": [
          "tgn:1016214",
          "tgn:1001274",
          "tgn:1000001",
          "tgn:7005364",
          "tgn:7029392"
        ],
        "placetype": [
          "aat:300008347"
        ],
        "id": 1016214,
        "name:xx": "Bagaces"
      }
    },
    {
      "geometry": {
        "type": "Point",
        "coordinates": [
          -83.3167,
          9
        ]
      },
      "type": "Feature",
      "properties": {
        "hierarchy": [
          "tgn:1016215",
          "tgn:1001491",
          "tgn:1000001",
          "tgn:7005364",
          "tgn:7029392"
        ],
        "placetype": [
          "aat:300008347"
        ],
        "id": 1016215,
        "name:xx": "Boruca"
      }
    },
    {
      "geometry": {
        "type": "Point",
        "coordinates": [
          -83.3833,
          9.1667
        ]
      },
      "type": "Feature",
      "properties": {
        "hierarchy": [
          "tgn:1016216",
          "tgn:1001491",
          "tgn:1000001",
          "tgn:7005364",
          "tgn:7029392"
        ],
        "placetype": [
          "aat:300008347"
        ],
        "id": 1016216,
        "name:xx": "Buenos Aires"
      }
    },
    {
      "geometry": {
        "type": "Point",
        "coordinates": [
          -85.1,
          10.4333
        ]
      },
      "type": "Feature",
      "properties": {
        "hierarchy": [
          "tgn:1016217",
          "tgn:1001274",
          "tgn:1000001",
          "tgn:7005364",
          "tgn:7029392"
        ],
        "placetype": [
          "aat:300008347"
        ],
        "id": 1016217,
        "name:xx": "Cañas"
      }
    },
    {
      "geometry": {
        "type": "Point",
        "coordinates": [
          -84.7833,
          10.9
        ]
      },
      "type": "Feature",
      "properties": {
        "hierarchy": [
          "tgn:1016218",
          "tgn:1001093",
          "tgn:1000001",
          "tgn:7005364",
          "tgn:7029392"
        ],
        "placetype": [
          "aat:300008347"
        ],
        "id": 1016218,
        "name:xx": "Caño Negro"
      }
    },
    {
      "geometry": {
        "type": "Point",
        "coordinates": [
          -85.0833,
          9.6
        ]
      },
      "type": "Feature",
      "properties": {
        "hierarchy": [
          "tgn:1016219",
          "tgn:1001491",
          "tgn:1000001",
          "tgn:7005364",
          "tgn:7029392"
        ],
        "placetype": [
          "aat:300008347"
        ],
        "id": 1016219,
        "name:xx": "Cabuya"
      }
    }
  ]
}
