{
  "geometry": {
    "type": "Point",
    "coordinates": [
      -114.5667,
      32.75
    ]
  },
  "type": "Feature",
  "properties": {
    "hierarchy": [
      "tgn:2716479",
      "tgn:1000001",
      "tgn:7012149",
      "tgn:7029392"
    ],
    "placetype": [
      "aat:300055621"
    ],
    "id": 2716479,
    "name:xx": "The Island"
  }
}
