{
  "geometry": {
    "type": "Point",
    "coordinates": [
      -113.9333,
      48.5667
    ]
  },
  "type": "Feature",
  "properties": {
    "hierarchy": [
      "tgn:1117261",
      "tgn:1000001",
      "tgn:7012149",
      "tgn:2001274",
      "tgn:7007524",
      "tgn:7029392"
    ],
    "placetype": [
      "aat:300008680"
    ],
    "id": 1117261,
    "name:xx": "McDonald, Lake"
  }
}
