{
  "geometry": {
    "type": "Point",
    "coordinates": [
      -94.3667,
      38.8833
    ]
  },
  "type": "Feature",
  "properties": {
    "hierarchy": [
      "tgn:2228381",
      "tgn:1000001",
      "tgn:7012149",
      "tgn:2001208",
      "tgn:7007523",
      "tgn:7029392"
    ],
    "placetype": [
      "aat:300008706"
    ],
    "id": 2228381,
    "name:xx": "Cedar Creek"
  }
}
