{
  "geometry": {
    "type": "Point",
    "coordinates": [
      -77.8833,
      41.85
    ]
  },
  "type": "Feature",
  "properties": {
    "hierarchy": [
      "tgn:2580564",
      "tgn:1000001",
      "tgn:7012149",
      "tgn:1002800",
      "tgn:7007710",
      "tgn:7029392"
    ],
    "placetype": [
      "aat:300008761"
    ],
    "id": 2580564,
    "name:xx": "Pigeon Hollow"
  }
}
