{
  "geometry": {
    "type": "Point",
    "coordinates": [
      47.8333,
      30.5667
    ]
  },
  "type": "Feature",
  "properties": {
    "hierarchy": [
      "tgn:1079426",
      "tgn:1001072",
      "tgn:1000004",
      "tgn:1000118",
      "tgn:7029392"
    ],
    "placetype": [
      "aat:300008347"
    ],
    "id": 1079426,
    "name:xx": "Kibāsī"
  }
}
