{
  "type": "FeatureCollection",
  "features": [
    {
      "geometry": {
        "type": "Point",
        "coordinates": [
          -6.133333,
          55.316667
        ]
      },
      "type": "Feature",
      "properties": {
        "hierarchy": [
          "tgn:7457730",
          "tgn:7002448",
          "tgn:7019157",
          "tgn:1000003",
          "tgn:7008591",
          "tgn:7029392"
        ],
        "placetype": [
          "aat:300386114"
        ],
        "name:en": "Mac Donnell Race",
        "id": 7457730
      }
    },
    {
      "geometry": {
        "type": "Point",
        "coordinates": [
          0.133333,
          52.933333
        ]
      },
      "type": "Feature",
      "properties": {
        "hierarchy": [
          "tgn:7457734",
          "tgn:7002445",
          "tgn:1000003",
          "tgn:7008157",
          "tgn:7008591",
          "tgn:7029392"
        ],
        "placetype": [
          "aat:300008713"
        ],
        "name:en": "Maccaroni Channel",
        "id": 7457734
      }
    },
    {
      "geometry": {
        "type": "Point",
        "coordinates": [
          -6.716667,
          57.95
        ]
      },
      "type": "Feature",
      "properties": {
        "hierarchy": [
          "tgn:7457738",
          "tgn:7002444",
          "tgn:1000003",
          "tgn:7008094",
          "tgn:7008591",
          "tgn:7029392"
        ],
        "placetype": [
          "aat:300132316"
        ],
        "name:en": "Maaruig, Loch",
        "id": 7457738
      }
    },
    {
      "geometry": {
        "type": "Point",
        "coordinates": [
          -0.683333,
          54.5
        ]
      },
      "type": "Feature",
      "properties": {
        "hierarchy": [
          "tgn:7457739",
          "tgn:7002445",
          "tgn:1000003",
          "tgn:7008166",
          "tgn:7008591",
          "tgn:7029392"
        ],
        "placetype": [
          "aat:300008347"
        ],
        "name:en": "Lythe",
        "id": 7457739
      }
    }
  ]
}
