{
  "geometry": {
    "type": "Point",
    "coordinates": [
      -121.2333,
      38.05
    ]
  },
  "type": "Feature",
  "properties": {
    "hierarchy": [
      "tgn:2176631",
      "tgn:1000001",
      "tgn:7012149",
      "tgn:7007157",
      "tgn:1002861",
      "tgn:7029392"
    ],
    "placetype": [
      "aat:300008347"
    ],
    "id": 2176631,
    "name:xx": "Black Lands"
  }
}
