{
  "geometry": {
    "type": "Point",
    "coordinates": [
      -119.6333,
      44.1833
    ]
  },
  "type": "Feature",
  "properties": {
    "hierarchy": [
      "tgn:2699971",
      "tgn:1000001",
      "tgn:7012149",
      "tgn:2001708",
      "tgn:7007708",
      "tgn:7029392"
    ],
    "placetype": [
      "aat:300006191"
    ],
    "id": 2699971,
    "name:xx": "Stump Creek Reservoir"
  }
}
