{
  "geometry": {
    "type": "Point",
    "coordinates": [
      -86.3333,
      37.4667
    ]
  },
  "type": "Feature",
  "properties": {
    "hierarchy": [
      "tgn:2499473",
      "tgn:1000001",
      "tgn:7012149",
      "tgn:2000793",
      "tgn:7007255",
      "tgn:7029392"
    ],
    "placetype": [
      "aat:300008699"
    ],
    "id": 2499473,
    "name:xx": "McClure Fork"
  }
}
