{
  "geometry": {
    "type": "Point",
    "coordinates": [
      -76.2333,
      37.8833
    ]
  },
  "type": "Feature",
  "properties": {
    "hierarchy": [
      "tgn:2671777",
      "tgn:1000001",
      "tgn:7016098",
      "tgn:7012149",
      "tgn:7007516",
      "tgn:7029392"
    ],
    "placetype": [
      "aat:300008850"
    ],
    "id": 2671777,
    "name:xx": "Smith Point"
  }
}
