{
  "geometry": {
    "type": "Point",
    "coordinates": [
      -119.7167,
      39.1167
    ]
  },
  "type": "Feature",
  "properties": {
    "hierarchy": [
      "tgn:2599124",
      "tgn:1000001",
      "tgn:7022245",
      "tgn:7012149",
      "tgn:7007526",
      "tgn:7029392"
    ],
    "placetype": [
      "aat:300266640"
    ],
    "id": 2599124,
    "name:xx": "Prison Hill"
  }
}
