{
  "geometry": {
    "type": "Point",
    "coordinates": [
      -70.9167,
      43.75
    ]
  },
  "type": "Feature",
  "properties": {
    "hierarchy": [
      "tgn:2548726",
      "tgn:1000001",
      "tgn:7012149",
      "tgn:2000933",
      "tgn:7007515",
      "tgn:7029392"
    ],
    "placetype": [
      "aat:300008347"
    ],
    "id": 2548726,
    "name:xx": "North Parsonsfield"
  }
}
