{
  "geometry": {
    "type": "Point",
    "coordinates": [
      -114.9167,
      41.1833
    ]
  },
  "type": "Feature",
  "properties": {
    "hierarchy": [
      "tgn:2563906",
      "tgn:1000001",
      "tgn:2001411",
      "tgn:7012149",
      "tgn:7007526",
      "tgn:7029392"
    ],
    "placetype": [
      "aat:300008798"
    ],
    "id": 2563906,
    "name:xx": "Oxley Peak"
  }
}
