{
  "geometry": {
    "type": "Point",
    "coordinates": [
      -124.2167,
      43.2167
    ]
  },
  "type": "Feature",
  "properties": {
    "hierarchy": [
      "tgn:2084561",
      "tgn:1000001",
      "tgn:2001702",
      "tgn:7012149",
      "tgn:7007708",
      "tgn:7029392"
    ],
    "placetype": [
      "aat:300008347",
      "aat:300387210"
    ],
    "id": 2084561,
    "name:xx": "Coaledo"
  }
}
