{
  "geometry": {
    "type": "Point",
    "coordinates": [
      -109.3833,
      33.85
    ]
  },
  "type": "Feature",
  "properties": {
    "hierarchy": [
      "tgn:2564183",
      "tgn:2000090",
      "tgn:1000001",
      "tgn:7006451",
      "tgn:7012149",
      "tgn:7029392"
    ],
    "placetype": [
      "aat:300008697"
    ],
    "id": 2564183,
    "name:xx": "PN Spring"
  }
}
