{
  "geometry": {
    "type": "Point",
    "coordinates": [
      -122.1833,
      47.2333
    ]
  },
  "type": "Feature",
  "properties": {
    "hierarchy": [
      "tgn:1118339",
      "tgn:1000001",
      "tgn:7012149",
      "tgn:1002785",
      "tgn:7007920",
      "tgn:7029392"
    ],
    "placetype": [
      "aat:300008680"
    ],
    "id": 1118339,
    "name:xx": "Tapps, Lake"
  }
}
