{
  "geometry": {
    "type": "Point",
    "coordinates": [
      20.0667,
      60.2333
    ]
  },
  "type": "Feature",
  "properties": {
    "hierarchy": [
      "tgn:1031355",
      "tgn:7594378",
      "tgn:1000003",
      "tgn:1000069",
      "tgn:7029392"
    ],
    "placetype": [
      "aat:300008347"
    ],
    "id": 1031355,
    "name:xx": "Kastelholm"
  }
}
