{
  "geometry": {
    "type": "Point",
    "coordinates": [
      -88.0667,
      46.6833
    ]
  },
  "type": "Feature",
  "properties": {
    "hierarchy": [
      "tgn:2129324",
      "tgn:2000947",
      "tgn:1000001",
      "tgn:7012149",
      "tgn:7007520",
      "tgn:7029392"
    ],
    "placetype": [
      "aat:300008680"
    ],
    "id": 2129324,
    "name:xx": "Alice, Lake"
  }
}
