{
  "geometry": {
    "type": "Point",
    "coordinates": [
      -81.9167,
      33.6833
    ]
  },
  "type": "Feature",
  "properties": {
    "hierarchy": [
      "tgn:2778148",
      "tgn:1000001",
      "tgn:7013677",
      "tgn:7012149",
      "tgn:7007712",
      "tgn:7029392"
    ],
    "placetype": [
      "aat:300008347"
    ],
    "id": 2778148,
    "name:xx": "Wise"
  }
}
