{
  "type": "FeatureCollection",
  "features": [
    {
      "geometry": {
        "type": "Point",
        "coordinates": [
          8.75,
          40.666667
        ]
      },
      "type": "Feature",
      "properties": {
        "hierarchy": [
          "tgn:7003631",
          "tgn:7015163",
          "tgn:1000003",
          "tgn:7003121",
          "tgn:1000080",
          "tgn:7029392"
        ],
        "placetype": [
          "aat:300008347"
        ],
        "id": 7003631,
        "name:xx": "Ploaghe"
      }
    },
    {
      "geometry": {
        "type": "Point",
        "coordinates": [
          4.666,
          52
        ]
      },
      "type": "Feature",
      "properties": {
        "hierarchy": [
          "tgn:7003632",
          "tgn:1000003",
          "tgn:7016845",
          "tgn:7029392"
        ],
        "placetype": [
          "aat:300387064",
          "aat:300000774"
        ],
        "name:en": "South Holland",
        "id": 7003632
      }
    },
    {
      "geometry": {
        "type": "Point",
        "coordinates": [
          8.3333,
          40.6333
        ]
      },
      "type": "Feature",
      "properties": {
        "hierarchy": [
          "tgn:7003633",
          "tgn:7015163",
          "tgn:1000003",
          "tgn:7003121",
          "tgn:1000080",
          "tgn:7029392"
        ],
        "placetype": [
          "aat:300000372",
          "aat:300008057"
        ],
        "id": 7003633,
        "name:xx": "Anghelu Ruju"
      }
    },
    {
      "geometry": {
        "type": "Point",
        "coordinates": [
          8.883333,
          40.833333
        ]
      },
      "type": "Feature",
      "properties": {
        "hierarchy": [
          "tgn:7003634",
          "tgn:7015163",
          "tgn:1000003",
          "tgn:7003121",
          "tgn:1000080",
          "tgn:7029392"
        ],
        "placetype": [
          "aat:300008347"
        ],
        "id": 7003634,
        "name:xx": "Perfugas"
      }
    },
    {
      "geometry": {
        "type": "Point",
        "coordinates": [
          3.75,
          51.4167
        ]
      },
      "type": "Feature",
      "properties": {
        "hierarchy": [
          "tgn:7003635",
          "tgn:1000003",
          "tgn:7016845",
          "tgn:7029392"
        ],
        "placetype": [
          "aat:300387064",
          "aat:300000774"
        ],
        "id": 7003635,
        "name:xx": "Zeeland"
      }
    }
  ]
}
