{
  "type": "FeatureCollection",
  "features": [
    {
      "geometry": {
        "type": "Point",
        "coordinates": [
          -111.483333,
          24.933333
        ]
      },
      "type": "Feature",
      "properties": {
        "hierarchy": [
          "tgn:7366830",
          "tgn:1001836",
          "tgn:1000001",
          "tgn:7005560",
          "tgn:7029392"
        ],
        "placetype": [
          "aat:300008347"
        ],
        "id": 7366830,
        "name:xx": "El Toro"
      }
    },
    {
      "geometry": {
        "type": "Point",
        "coordinates": [
          -107.243611,
          24.758889
        ]
      },
      "type": "Feature",
      "properties": {
        "hierarchy": [
          "tgn:7366831",
          "tgn:1000001",
          "tgn:7005595",
          "tgn:7005560",
          "tgn:7029392"
        ],
        "placetype": [
          "aat:300008347"
        ],
        "id": 7366831,
        "name:xx": "El Toro"
      }
    },
    {
      "geometry": {
        "type": "Point",
        "coordinates": [
          -98.166667,
          24.75
        ]
      },
      "type": "Feature",
      "properties": {
        "hierarchy": [
          "tgn:7366832",
          "tgn:1000001",
          "tgn:7005597",
          "tgn:7005560",
          "tgn:7029392"
        ],
        "placetype": [
          "aat:300008347"
        ],
        "id": 7366832,
        "name:xx": "El Toro"
      }
    },
    {
      "geometry": {
        "type": "Point",
        "coordinates": [
          -104.266667,
          21
        ]
      },
      "type": "Feature",
      "properties": {
        "hierarchy": [
          "tgn:7366833",
          "tgn:1000001",
          "tgn:1001906",
          "tgn:7005560",
          "tgn:7029392"
        ],
        "placetype": [
          "aat:300008347"
        ],
        "id": 7366833,
        "name:xx": "El Toro"
      }
    },
    {
      "geometry": {
        "type": "Point",
        "coordinates": [
          -104.016667,
          21.916667
        ]
      },
      "type": "Feature",
      "properties": {
        "hierarchy": [
          "tgn:7366834",
          "tgn:7005586",
          "tgn:1000001",
          "tgn:7005560",
          "tgn:7029392"
        ],
        "placetype": [
          "aat:300266554",
          "aat:300008699"
        ],
        "id": 7366834,
        "name:xx": "El Roble"
      }
    },
    {
      "geometry": {
        "type": "Point",
        "coordinates": [
          -99.6,
          27.15
        ]
      },
      "type": "Feature",
      "properties": {
        "hierarchy": [
          "tgn:7366835",
          "tgn:1000001",
          "tgn:7005597",
          "tgn:7005560",
          "tgn:7029392"
        ],
        "placetype": [
          "aat:300008347"
        ],
        "id": 7366835,
        "name:xx": "El Roble"
      }
    },
    {
      "geometry": {
        "type": "Point",
        "coordinates": [
          -98.85,
          25.616667
        ]
      },
      "type": "Feature",
      "properties": {
        "hierarchy": [
          "tgn:7366836",
          "tgn:1000001",
          "tgn:7005589",
          "tgn:7005560",
          "tgn:7029392"
        ],
        "placetype": [
          "aat:300008347"
        ],
        "id": 7366836,
        "name:xx": "El Roble"
      }
    },
    {
      "geometry": {
        "type": "Point",
        "coordinates": [
          -99.95,
          25.2
        ]
      },
      "type": "Feature",
      "properties": {
        "hierarchy": [
          "tgn:7366837",
          "tgn:1000001",
          "tgn:7005589",
          "tgn:7005560",
          "tgn:7029392"
        ],
        "placetype": [
          "aat:300008347"
        ],
        "id": 7366837,
        "name:xx": "El Roble"
      }
    },
    {
      "geometry": {
        "type": "Point",
        "coordinates": [
          -107.45,
          25.183333
        ]
      },
      "type": "Feature",
      "properties": {
        "hierarchy": [
          "tgn:7366838",
          "tgn:1000001",
          "tgn:7005595",
          "tgn:7005560",
          "tgn:7029392"
        ],
        "placetype": [
          "aat:300008347"
        ],
        "id": 7366838,
        "name:xx": "El Roble"
      }
    },
    {
      "geometry": {
        "type": "Point",
        "coordinates": [
          -107.244722,
          24.406667
        ]
      },
      "type": "Feature",
      "properties": {
        "hierarchy": [
          "tgn:7366839",
          "tgn:1000001",
          "tgn:7005595",
          "tgn:7005560",
          "tgn:7029392"
        ],
        "placetype": [
          "aat:300008347"
        ],
        "id": 7366839,
        "name:xx": "El Roble"
      }
    }
  ]
}
