{
  "geometry": {
    "type": "Point",
    "coordinates": [
      78.978121,
      24.703732
    ]
  },
  "type": "Feature",
  "properties": {
    "hierarchy": [
      "tgn:7584818",
      "tgn:1000004",
      "tgn:7000198",
      "tgn:1001894",
      "tgn:7029392"
    ],
    "placetype": [
      "aat:300008347"
    ],
    "name:en": "Nārāyanpur",
    "id": 7584818
  }
}
