{
  "geometry": {
    "type": "Point",
    "coordinates": [
      -87.5333,
      44.7667
    ]
  },
  "type": "Feature",
  "properties": {
    "hierarchy": [
      "tgn:2127050",
      "tgn:1000001",
      "tgn:7012149",
      "tgn:7007922",
      "tgn:7029392"
    ],
    "placetype": [
      "aat:300008707"
    ],
    "id": 2127050,
    "name:xx": "Ahnapee River"
  }
}
