{
  "type": "FeatureCollection",
  "features": [
    {
      "geometry": {
        "type": "Point",
        "coordinates": [
          9.05,
          54.65
        ]
      },
      "type": "Feature",
      "properties": {
        "hierarchy": [
          "tgn:7199200",
          "tgn:1000003",
          "tgn:7003688",
          "tgn:7000084",
          "tgn:7029392"
        ],
        "placetype": [
          "aat:300008347"
        ],
        "id": 7199200,
        "name:xx": "Drelsdorf"
      }
    },
    {
      "geometry": {
        "type": "Point",
        "coordinates": [
          11.583333,
          53.433333
        ]
      },
      "type": "Feature",
      "properties": {
        "hierarchy": [
          "tgn:7199201",
          "tgn:1000003",
          "tgn:7000094",
          "tgn:7000084",
          "tgn:7029392"
        ],
        "placetype": [
          "aat:300008699"
        ],
        "id": 7199201,
        "name:xx": "Drellen-Graben"
      }
    },
    {
      "geometry": {
        "type": "Point",
        "coordinates": [
          11.516667,
          51.833333
        ]
      },
      "type": "Feature",
      "properties": {
        "hierarchy": [
          "tgn:7199202",
          "tgn:1000003",
          "tgn:7003687",
          "tgn:7000084",
          "tgn:7029392"
        ],
        "placetype": [
          "aat:300008777"
        ],
        "id": 7199202,
        "name:xx": "Drell-Berg"
      }
    },
    {
      "geometry": {
        "type": "Point",
        "coordinates": [
          14.433333,
          51.366667
        ]
      },
      "type": "Feature",
      "properties": {
        "hierarchy": [
          "tgn:7199203",
          "tgn:1000003",
          "tgn:7003685",
          "tgn:7000084",
          "tgn:7029392"
        ],
        "placetype": [
          "aat:300008347"
        ],
        "id": 7199203,
        "name:xx": "Driewitz"
      }
    },
    {
      "geometry": {
        "type": "Point",
        "coordinates": [
          7.8,
          49.75
        ]
      },
      "type": "Feature",
      "properties": {
        "hierarchy": [
          "tgn:7199204",
          "tgn:1000003",
          "tgn:7003682",
          "tgn:7000084",
          "tgn:7029392"
        ],
        "placetype": [
          "aat:300008347"
        ],
        "id": 7199204,
        "name:xx": "Dreiweiherhof"
      }
    },
    {
      "geometry": {
        "type": "Point",
        "coordinates": [
          14.416667,
          51.4
        ]
      },
      "type": "Feature",
      "properties": {
        "hierarchy": [
          "tgn:7199205",
          "tgn:1000003",
          "tgn:7003685",
          "tgn:7000084",
          "tgn:7029392"
        ],
        "placetype": [
          "aat:300008347"
        ],
        "id": 7199205,
        "name:xx": "Dreiweibern"
      }
    },
    {
      "geometry": {
        "type": "Point",
        "coordinates": [
          11.8,
          50.733333
        ]
      },
      "type": "Feature",
      "properties": {
        "hierarchy": [
          "tgn:7199207",
          "tgn:1000003",
          "tgn:7003689",
          "tgn:7000084",
          "tgn:7029392"
        ],
        "placetype": [
          "aat:300008347"
        ],
        "id": 7199207,
        "name:xx": "Dreitzsch"
      }
    },
    {
      "geometry": {
        "type": "Point",
        "coordinates": [
          7.4,
          50.333333
        ]
      },
      "type": "Feature",
      "properties": {
        "hierarchy": [
          "tgn:7199209",
          "tgn:1000003",
          "tgn:7003682",
          "tgn:7000084",
          "tgn:7029392"
        ],
        "placetype": [
          "aat:300008777"
        ],
        "id": 7199209,
        "name:xx": "Drei Tonnen Kuppe"
      }
    }
  ]
}
