{
  "geometry": {
    "type": "Point",
    "coordinates": [
      -116.2833,
      42.55
    ]
  },
  "type": "Feature",
  "properties": {
    "hierarchy": [
      "tgn:2264403",
      "tgn:1000001",
      "tgn:7012149",
      "tgn:2000488",
      "tgn:7007250",
      "tgn:7029392"
    ],
    "placetype": [
      "aat:300008697"
    ],
    "id": 2264403,
    "name:xx": "Crab Spring"
  }
}
