{
  "geometry": {
    "type": "Point",
    "coordinates": [
      -104.05,
      47.3667
    ]
  },
  "type": "Feature",
  "properties": {
    "hierarchy": [
      "tgn:2590163",
      "tgn:1000001",
      "tgn:7012149",
      "tgn:7029392"
    ],
    "placetype": [
      "aat:300008706"
    ],
    "id": 2590163,
    "name:xx": "Poison Spring Creek"
  }
}
