{
  "geometry": {
    "type": "Point",
    "coordinates": [
      -82.4167,
      35.1667
    ]
  },
  "type": "Feature",
  "properties": {
    "hierarchy": [
      "tgn:7021145",
      "tgn:1000001",
      "tgn:7012149",
      "tgn:7029392"
    ],
    "placetype": [
      "aat:300386831",
      "aat:300266640"
    ],
    "id": 7021145,
    "name:xx": "Saluda Mountains"
  }
}
