{
  "type": "FeatureCollection",
  "features": [
    {
      "geometry": {
        "type": "Point",
        "coordinates": [
          -85.2833,
          42.6833
        ]
      },
      "type": "Feature",
      "properties": {
        "hierarchy": [
          "tgn:2756300",
          "tgn:1002166",
          "tgn:1000001",
          "tgn:7012149",
          "tgn:7007520",
          "tgn:7029392"
        ],
        "placetype": [
          "aat:300008347"
        ],
        "id": 2756300,
        "name:xx": "Welcome Corner"
      }
    },
    {
      "geometry": {
        "type": "Point",
        "coordinates": [
          -133.15,
          54.9667
        ]
      },
      "type": "Feature",
      "properties": {
        "hierarchy": [
          "tgn:2756301",
          "tgn:7006450",
          "tgn:1000001",
          "tgn:7012149",
          "tgn:2000082",
          "tgn:7029392"
        ],
        "placetype": [
          "aat:300132316"
        ],
        "id": 2756301,
        "name:xx": "Welcome Cove"
      }
    },
    {
      "geometry": {
        "type": "Point",
        "coordinates": [
          -71.4833,
          41.3833
        ]
      },
      "type": "Feature",
      "properties": {
        "hierarchy": [
          "tgn:2756302",
          "tgn:1002996",
          "tgn:1000001",
          "tgn:7012149",
          "tgn:7007711",
          "tgn:7029392"
        ],
        "placetype": [
          "aat:300132316"
        ],
        "id": 2756302,
        "name:xx": "Welcome Cove"
      }
    },
    {
      "geometry": {
        "type": "Point",
        "coordinates": [
          -150.7167,
          68.3
        ]
      },
      "type": "Feature",
      "properties": {
        "hierarchy": [
          "tgn:2756303",
          "tgn:7006450",
          "tgn:1000001",
          "tgn:7012149",
          "tgn:2124005",
          "tgn:7029392"
        ],
        "placetype": [
          "aat:300008706"
        ],
        "id": 2756303,
        "name:xx": "Welcome Creek"
      }
    },
    {
      "geometry": {
        "type": "Point",
        "coordinates": [
          -93.05,
          47.4
        ]
      },
      "type": "Feature",
      "properties": {
        "hierarchy": [
          "tgn:2756304",
          "tgn:1000001",
          "tgn:7012149",
          "tgn:7007521",
          "tgn:7029392"
        ],
        "placetype": [
          "aat:300008706"
        ],
        "id": 2756304,
        "name:xx": "Welcome Creek"
      }
    },
    {
      "geometry": {
        "type": "Point",
        "coordinates": [
          -112.7333,
          47.35
        ]
      },
      "type": "Feature",
      "properties": {
        "hierarchy": [
          "tgn:2756305",
          "tgn:1000001",
          "tgn:7012149",
          "tgn:2001284",
          "tgn:7007524",
          "tgn:7029392"
        ],
        "placetype": [
          "aat:300008706"
        ],
        "id": 2756305,
        "name:xx": "Welcome Creek"
      }
    },
    {
      "geometry": {
        "type": "Point",
        "coordinates": [
          -113.8,
          46.6
        ]
      },
      "type": "Feature",
      "properties": {
        "hierarchy": [
          "tgn:2756306",
          "tgn:1000001",
          "tgn:7012149",
          "tgn:2001279",
          "tgn:7007524",
          "tgn:7029392"
        ],
        "placetype": [
          "aat:300008706"
        ],
        "id": 2756306,
        "name:xx": "Welcome Creek"
      }
    },
    {
      "geometry": {
        "type": "Point",
        "coordinates": [
          -122.0667,
          44.8833
        ]
      },
      "type": "Feature",
      "properties": {
        "hierarchy": [
          "tgn:2756307",
          "tgn:1000001",
          "tgn:7012149",
          "tgn:1002636",
          "tgn:7007708",
          "tgn:7029392"
        ],
        "placetype": [
          "aat:300008706"
        ],
        "id": 2756307,
        "name:xx": "Welcome Creek"
      }
    },
    {
      "geometry": {
        "type": "Point",
        "coordinates": [
          -113.9,
          37.1
        ]
      },
      "type": "Feature",
      "properties": {
        "hierarchy": [
          "tgn:2756308",
          "tgn:1000001",
          "tgn:7012149",
          "tgn:7029392"
        ],
        "placetype": [
          "aat:300008706"
        ],
        "id": 2756308,
        "name:xx": "Welcome Creek"
      }
    },
    {
      "geometry": {
        "type": "Point",
        "coordinates": [
          -91.0667,
          30.55
        ]
      },
      "type": "Feature",
      "properties": {
        "hierarchy": [
          "tgn:2756309",
          "tgn:1000001",
          "tgn:2000870",
          "tgn:7012149",
          "tgn:7007256",
          "tgn:7029392"
        ],
        "placetype": [
          "aat:300008347"
        ],
        "id": 2756309,
        "name:xx": "Welcome Heights"
      }
    }
  ]
}
