{
  "geometry": {
    "type": "Point",
    "coordinates": [
      -108.4667,
      35.3333
    ]
  },
  "type": "Feature",
  "properties": {
    "hierarchy": [
      "tgn:2474624",
      "tgn:1000001",
      "tgn:7012149",
      "tgn:7019676",
      "tgn:7007566",
      "tgn:7029392"
    ],
    "placetype": [
      "aat:300006191"
    ],
    "id": 2474624,
    "name:xx": "Lower Section Nineteen Tank"
  }
}
