{
  "geometry": {
    "type": "Point",
    "coordinates": [
      -115.8833,
      47.5667
    ]
  },
  "type": "Feature",
  "properties": {
    "hierarchy": [
      "tgn:2739187",
      "tgn:1000001",
      "tgn:7012149",
      "tgn:2000491",
      "tgn:7007250",
      "tgn:7029392"
    ],
    "placetype": [
      "aat:300008761"
    ],
    "id": 2739187,
    "name:xx": "Unknown Gulch"
  }
}
