{
  "geometry": {
    "type": "Point",
    "coordinates": [
      -84.5667,
      34.6833
    ]
  },
  "type": "Feature",
  "properties": {
    "hierarchy": [
      "tgn:2313350",
      "tgn:1000001",
      "tgn:7012149",
      "tgn:2000352",
      "tgn:7007248",
      "tgn:7029392"
    ],
    "placetype": [
      "aat:300008347"
    ],
    "id": 2313350,
    "name:xx": "Elders"
  }
}
