{
  "type": "FeatureCollection",
  "features": [
    {
      "geometry": {
        "type": "Point",
        "coordinates": [
          -79.6333,
          40.2167
        ]
      },
      "type": "Feature",
      "properties": {
        "hierarchy": [
          "tgn:2144790",
          "tgn:1000001",
          "tgn:7012149",
          "tgn:1003017",
          "tgn:7007710",
          "tgn:7029392"
        ],
        "placetype": [
          "aat:300008798"
        ],
        "id": 2144790,
        "name:xx": "Bald Hill"
      }
    },
    {
      "geometry": {
        "type": "Point",
        "coordinates": [
          -76.4667,
          41.1667
        ]
      },
      "type": "Feature",
      "properties": {
        "hierarchy": [
          "tgn:2144791",
          "tgn:1000001",
          "tgn:1002294",
          "tgn:7012149",
          "tgn:7007710",
          "tgn:7029392"
        ],
        "placetype": [
          "aat:300008798"
        ],
        "id": 2144791,
        "name:xx": "Bald Hill"
      }
    },
    {
      "geometry": {
        "type": "Point",
        "coordinates": [
          -74.95,
          41.3333
        ]
      },
      "type": "Feature",
      "properties": {
        "hierarchy": [
          "tgn:2144792",
          "tgn:1000001",
          "tgn:7012149",
          "tgn:1002789",
          "tgn:7007710",
          "tgn:7029392"
        ],
        "placetype": [
          "aat:300008798"
        ],
        "id": 2144792,
        "name:xx": "Bald Hill"
      }
    },
    {
      "geometry": {
        "type": "Point",
        "coordinates": [
          -79.0333,
          41.6
        ]
      },
      "type": "Feature",
      "properties": {
        "hierarchy": [
          "tgn:2144793",
          "tgn:1000001",
          "tgn:7012149",
          "tgn:1002378",
          "tgn:7007710",
          "tgn:7029392"
        ],
        "placetype": [
          "aat:300008798"
        ],
        "id": 2144793,
        "name:xx": "Bald Hill"
      }
    },
    {
      "geometry": {
        "type": "Point",
        "coordinates": [
          -77.2833,
          41.6
        ]
      },
      "type": "Feature",
      "properties": {
        "hierarchy": [
          "tgn:2144794",
          "tgn:1000001",
          "tgn:7012149",
          "tgn:1002945",
          "tgn:7007710",
          "tgn:7029392"
        ],
        "placetype": [
          "aat:300008798"
        ],
        "id": 2144794,
        "name:xx": "Bald Hill"
      }
    },
    {
      "geometry": {
        "type": "Point",
        "coordinates": [
          -71.7,
          41.55
        ]
      },
      "type": "Feature",
      "properties": {
        "hierarchy": [
          "tgn:2144795",
          "tgn:1002996",
          "tgn:1000001",
          "tgn:7012149",
          "tgn:7007711",
          "tgn:7029392"
        ],
        "placetype": [
          "aat:300008798"
        ],
        "id": 2144795,
        "name:xx": "Bald Hill"
      }
    },
    {
      "geometry": {
        "type": "Point",
        "coordinates": [
          -71.7,
          41.6333
        ]
      },
      "type": "Feature",
      "properties": {
        "hierarchy": [
          "tgn:2144796",
          "tgn:1002541",
          "tgn:1000001",
          "tgn:7012149",
          "tgn:7007711",
          "tgn:7029392"
        ],
        "placetype": [
          "aat:300008798"
        ],
        "id": 2144796,
        "name:xx": "Bald Hill"
      }
    },
    {
      "geometry": {
        "type": "Point",
        "coordinates": [
          -71.55,
          41.7667
        ]
      },
      "type": "Feature",
      "properties": {
        "hierarchy": [
          "tgn:2144797",
          "tgn:1002808",
          "tgn:1000001",
          "tgn:7012149",
          "tgn:7007711",
          "tgn:7029392"
        ],
        "placetype": [
          "aat:300008798"
        ],
        "id": 2144797,
        "name:xx": "Bald Hill"
      }
    },
    {
      "geometry": {
        "type": "Point",
        "coordinates": [
          -103.3,
          43.6833
        ]
      },
      "type": "Feature",
      "properties": {
        "hierarchy": [
          "tgn:2144798",
          "tgn:1000001",
          "tgn:2001786",
          "tgn:7012149",
          "tgn:7007713",
          "tgn:7029392"
        ],
        "placetype": [
          "aat:300008798"
        ],
        "id": 2144798,
        "name:xx": "Bald Hill"
      }
    },
    {
      "geometry": {
        "type": "Point",
        "coordinates": [
          -85.1667,
          35.1667
        ]
      },
      "type": "Feature",
      "properties": {
        "hierarchy": [
          "tgn:2144799",
          "tgn:1000001",
          "tgn:7012149",
          "tgn:2001869",
          "tgn:7007825",
          "tgn:7029392"
        ],
        "placetype": [
          "aat:300008798"
        ],
        "id": 2144799,
        "name:xx": "Bald Hill"
      }
    }
  ]
}
