{
  "type": "FeatureCollection",
  "features": [
    {
      "geometry": {
        "type": "Point",
        "coordinates": [
          8.166667,
          48.45
        ]
      },
      "type": "Feature",
      "properties": {
        "hierarchy": [
          "tgn:7158320",
          "tgn:7003692",
          "tgn:1000003",
          "tgn:7000084",
          "tgn:7029392"
        ],
        "placetype": [
          "aat:300008347"
        ],
        "id": 7158320,
        "name:xx": "Hohbruck"
      }
    },
    {
      "geometry": {
        "type": "Point",
        "coordinates": [
          10.05,
          47.866667
        ]
      },
      "type": "Feature",
      "properties": {
        "hierarchy": [
          "tgn:7158321",
          "tgn:7003692",
          "tgn:1000003",
          "tgn:7000084",
          "tgn:7029392"
        ],
        "placetype": [
          "aat:300266640"
        ],
        "id": 7158321,
        "name:xx": "Hohberg"
      }
    },
    {
      "geometry": {
        "type": "Point",
        "coordinates": [
          7.9,
          48.316667
        ]
      },
      "type": "Feature",
      "properties": {
        "hierarchy": [
          "tgn:7158322",
          "tgn:7003692",
          "tgn:1000003",
          "tgn:7000084",
          "tgn:7029392"
        ],
        "placetype": [
          "aat:300387200"
        ],
        "id": 7158322,
        "name:xx": "Hohberg"
      }
    },
    {
      "geometry": {
        "type": "Point",
        "coordinates": [
          7.983333,
          51.533333
        ]
      },
      "type": "Feature",
      "properties": {
        "hierarchy": [
          "tgn:7158323",
          "tgn:1000003",
          "tgn:7003677",
          "tgn:7000084",
          "tgn:7029392"
        ],
        "placetype": [
          "aat:300008347"
        ],
        "id": 7158323,
        "name:xx": "Höhberg"
      }
    },
    {
      "geometry": {
        "type": "Point",
        "coordinates": [
          11.666667,
          50.2
        ]
      },
      "type": "Feature",
      "properties": {
        "hierarchy": [
          "tgn:7158324",
          "tgn:7003669",
          "tgn:1000003",
          "tgn:7000084",
          "tgn:7029392"
        ],
        "placetype": [
          "aat:300008347"
        ],
        "id": 7158324,
        "name:xx": "Hohberg"
      }
    },
    {
      "geometry": {
        "type": "Point",
        "coordinates": [
          10.783333,
          49.2
        ]
      },
      "type": "Feature",
      "properties": {
        "hierarchy": [
          "tgn:7158325",
          "tgn:7003669",
          "tgn:1000003",
          "tgn:7000084",
          "tgn:7029392"
        ],
        "placetype": [
          "aat:300008347"
        ],
        "id": 7158325,
        "name:xx": "Höhberg"
      }
    },
    {
      "geometry": {
        "type": "Point",
        "coordinates": [
          10.683333,
          49.133333
        ]
      },
      "type": "Feature",
      "properties": {
        "hierarchy": [
          "tgn:7158326",
          "tgn:7003669",
          "tgn:1000003",
          "tgn:7000084",
          "tgn:7029392"
        ],
        "placetype": [
          "aat:300008347"
        ],
        "id": 7158326,
        "name:xx": "Höhberg"
      }
    },
    {
      "geometry": {
        "type": "Point",
        "coordinates": [
          10.816667,
          52.166667
        ]
      },
      "type": "Feature",
      "properties": {
        "hierarchy": [
          "tgn:7158327",
          "tgn:1000003",
          "tgn:7003676",
          "tgn:7000084",
          "tgn:7029392"
        ],
        "placetype": [
          "aat:300008777"
        ],
        "id": 7158327,
        "name:xx": "Hohberg"
      }
    },
    {
      "geometry": {
        "type": "Point",
        "coordinates": [
          10.683333,
          52.116667
        ]
      },
      "type": "Feature",
      "properties": {
        "hierarchy": [
          "tgn:7158328",
          "tgn:1000003",
          "tgn:7003676",
          "tgn:7000084",
          "tgn:7029392"
        ],
        "placetype": [
          "aat:300008777"
        ],
        "id": 7158328,
        "name:xx": "Hoh-Berg"
      }
    }
  ]
}
