{
  "type": "FeatureCollection",
  "features": [
    {
      "geometry": {
        "type": "Point",
        "coordinates": [
          -123.1667,
          42.6167
        ]
      },
      "type": "Feature",
      "properties": {
        "hierarchy": [
          "tgn:2378120",
          "tgn:1000001",
          "tgn:7012149",
          "tgn:2001711",
          "tgn:7007708",
          "tgn:7029392"
        ],
        "placetype": [
          "aat:300008761"
        ],
        "id": 2378120,
        "name:xx": "Harris Gulch"
      }
    },
    {
      "geometry": {
        "type": "Point",
        "coordinates": [
          -74.2,
          39.6
        ]
      },
      "type": "Feature",
      "properties": {
        "hierarchy": [
          "tgn:2378121",
          "tgn:1000001",
          "tgn:1002738",
          "tgn:7012149",
          "tgn:7007565",
          "tgn:7029392"
        ],
        "placetype": [
          "aat:300132316"
        ],
        "id": 2378121,
        "name:xx": "Harris Harbor"
      }
    },
    {
      "geometry": {
        "type": "Point",
        "coordinates": [
          -117.4333,
          36.5833
        ]
      },
      "type": "Feature",
      "properties": {
        "hierarchy": [
          "tgn:2378122",
          "tgn:1000001",
          "tgn:7012149",
          "tgn:2000183",
          "tgn:7007157",
          "tgn:7029392"
        ],
        "placetype": [
          "aat:300008798"
        ],
        "id": 2378122,
        "name:xx": "Harris Hill"
      }
    },
    {
      "geometry": {
        "type": "Point",
        "coordinates": [
          -88.3,
          37.15
        ]
      },
      "type": "Feature",
      "properties": {
        "hierarchy": [
          "tgn:2378123",
          "tgn:1000001",
          "tgn:7012149",
          "tgn:2000814",
          "tgn:7007255",
          "tgn:7029392"
        ],
        "placetype": [
          "aat:300008798"
        ],
        "id": 2378123,
        "name:xx": "Harris Hill"
      }
    },
    {
      "geometry": {
        "type": "Point",
        "coordinates": [
          -70.35,
          44.0833
        ]
      },
      "type": "Feature",
      "properties": {
        "hierarchy": [
          "tgn:2378124",
          "tgn:2000918",
          "tgn:1000001",
          "tgn:7012149",
          "tgn:7007515",
          "tgn:7029392"
        ],
        "placetype": [
          "aat:300008798"
        ],
        "id": 2378124,
        "name:xx": "Harris Hill"
      }
    },
    {
      "geometry": {
        "type": "Point",
        "coordinates": [
          -76.6333,
          39.7167
        ]
      },
      "type": "Feature",
      "properties": {
        "hierarchy": [
          "tgn:2378125",
          "tgn:7016099",
          "tgn:1000001",
          "tgn:7012149",
          "tgn:7007516",
          "tgn:7029392"
        ],
        "placetype": [
          "aat:300008347"
        ],
        "id": 2378125,
        "name:xx": "Harris Hill"
      }
    },
    {
      "geometry": {
        "type": "Point",
        "coordinates": [
          -72.3167,
          42.5167
        ]
      },
      "type": "Feature",
      "properties": {
        "hierarchy": [
          "tgn:2378126",
          "tgn:1000001",
          "tgn:7013942",
          "tgn:7012149",
          "tgn:7007517",
          "tgn:7029392"
        ],
        "placetype": [
          "aat:300008798"
        ],
        "id": 2378126,
        "name:xx": "Harris Hill"
      }
    },
    {
      "geometry": {
        "type": "Point",
        "coordinates": [
          -108.9167,
          45.5333
        ]
      },
      "type": "Feature",
      "properties": {
        "hierarchy": [
          "tgn:2378127",
          "tgn:1000001",
          "tgn:2001264",
          "tgn:7012149",
          "tgn:7007524",
          "tgn:7029392"
        ],
        "placetype": [
          "aat:300008798"
        ],
        "id": 2378127,
        "name:xx": "Harris Hill"
      }
    },
    {
      "geometry": {
        "type": "Point",
        "coordinates": [
          -75.2667,
          42.5333
        ]
      },
      "type": "Feature",
      "properties": {
        "hierarchy": [
          "tgn:2378128",
          "tgn:1000001",
          "tgn:7012149",
          "tgn:7014318",
          "tgn:7007568",
          "tgn:7029392"
        ],
        "placetype": [
          "aat:300008798"
        ],
        "id": 2378128,
        "name:xx": "Harris Hill"
      }
    },
    {
      "geometry": {
        "type": "Point",
        "coordinates": [
          -79.1833,
          42.1667
        ]
      },
      "type": "Feature",
      "properties": {
        "hierarchy": [
          "tgn:2378129",
          "tgn:1000001",
          "tgn:1002259",
          "tgn:7012149",
          "tgn:7007568",
          "tgn:7029392"
        ],
        "placetype": [
          "aat:300008798"
        ],
        "id": 2378129,
        "name:xx": "Harris Hill"
      }
    }
  ]
}
