{
  "geometry": {
    "type": "Point",
    "coordinates": [
      -123.0833,
      39.4667
    ]
  },
  "type": "Feature",
  "properties": {
    "hierarchy": [
      "tgn:2626758",
      "tgn:1000001",
      "tgn:7012149",
      "tgn:7007157",
      "tgn:2000185",
      "tgn:7029392"
    ],
    "placetype": [
      "aat:300008798"
    ],
    "id": 2626758,
    "name:xx": "Rocky Point"
  }
}
