{
  "type": "FeatureCollection",
  "features": [
    {
      "geometry": {
        "type": "Point",
        "coordinates": [
          10.516667,
          48.816667
        ]
      },
      "type": "Feature",
      "properties": {
        "hierarchy": [
          "tgn:7109990",
          "tgn:7003669",
          "tgn:1000003",
          "tgn:7000084",
          "tgn:7029392"
        ],
        "placetype": [
          "aat:300008347"
        ],
        "id": 7109990,
        "name:xx": "Reimlingen"
      }
    },
    {
      "geometry": {
        "type": "Point",
        "coordinates": [
          10.616667,
          48.75
        ]
      },
      "type": "Feature",
      "properties": {
        "hierarchy": [
          "tgn:7109991",
          "tgn:7003669",
          "tgn:1000003",
          "tgn:7000084",
          "tgn:7029392"
        ],
        "placetype": [
          "aat:300008347"
        ],
        "id": 7109991,
        "name:xx": "Reimertshof"
      }
    },
    {
      "geometry": {
        "type": "Point",
        "coordinates": [
          8.633333,
          50.7
        ]
      },
      "type": "Feature",
      "properties": {
        "hierarchy": [
          "tgn:7109992",
          "tgn:1000003",
          "tgn:7003678",
          "tgn:7000084",
          "tgn:7029392"
        ],
        "placetype": [
          "aat:300008347"
        ],
        "id": 7109992,
        "name:xx": "Reimershausen"
      }
    },
    {
      "geometry": {
        "type": "Point",
        "coordinates": [
          12.183333,
          53.666667
        ]
      },
      "type": "Feature",
      "properties": {
        "hierarchy": [
          "tgn:7109993",
          "tgn:1000003",
          "tgn:7000094",
          "tgn:7000084",
          "tgn:7029392"
        ],
        "placetype": [
          "aat:300008680"
        ],
        "id": 7109993,
        "name:xx": "Reimershagener See"
      }
    },
    {
      "geometry": {
        "type": "Point",
        "coordinates": [
          12.183333,
          53.666667
        ]
      },
      "type": "Feature",
      "properties": {
        "hierarchy": [
          "tgn:7109994",
          "tgn:1000003",
          "tgn:7000094",
          "tgn:7000084",
          "tgn:7029392"
        ],
        "placetype": [
          "aat:300008347"
        ],
        "id": 7109994,
        "name:xx": "Reimershagen"
      }
    },
    {
      "geometry": {
        "type": "Point",
        "coordinates": [
          12.216667,
          50.6
        ]
      },
      "type": "Feature",
      "properties": {
        "hierarchy": [
          "tgn:7109995",
          "tgn:1000003",
          "tgn:7003685",
          "tgn:7000084",
          "tgn:7029392"
        ],
        "placetype": [
          "aat:300008347"
        ],
        "id": 7109995,
        "name:xx": "Reimersgrün"
      }
    },
    {
      "geometry": {
        "type": "Point",
        "coordinates": [
          9.016667,
          54.383333
        ]
      },
      "type": "Feature",
      "properties": {
        "hierarchy": [
          "tgn:7109996",
          "tgn:1000003",
          "tgn:7003688",
          "tgn:7000084",
          "tgn:7029392"
        ],
        "placetype": [
          "aat:300008347"
        ],
        "id": 7109996,
        "name:xx": "Reimersbude"
      }
    },
    {
      "geometry": {
        "type": "Point",
        "coordinates": [
          11.65,
          47.7
        ]
      },
      "type": "Feature",
      "properties": {
        "hierarchy": [
          "tgn:7109997",
          "tgn:7003669",
          "tgn:1000003",
          "tgn:7000084",
          "tgn:7029392"
        ],
        "placetype": [
          "aat:300008795"
        ],
        "id": 7109997,
        "name:xx": "Reimers Berg"
      }
    },
    {
      "geometry": {
        "type": "Point",
        "coordinates": [
          12.1,
          48.35
        ]
      },
      "type": "Feature",
      "properties": {
        "hierarchy": [
          "tgn:7109998",
          "tgn:7003669",
          "tgn:1000003",
          "tgn:7000084",
          "tgn:7029392"
        ],
        "placetype": [
          "aat:300008347"
        ],
        "id": 7109998,
        "name:xx": "Reimering"
      }
    },
    {
      "geometry": {
        "type": "Point",
        "coordinates": [
          9.8,
          53.05
        ]
      },
      "type": "Feature",
      "properties": {
        "hierarchy": [
          "tgn:7109999",
          "tgn:1000003",
          "tgn:7003676",
          "tgn:7000084",
          "tgn:7029392"
        ],
        "placetype": [
          "aat:300008347"
        ],
        "id": 7109999,
        "name:xx": "Reimerdingen"
      }
    }
  ]
}
