{
  "type": "FeatureCollection",
  "features": [
    {
      "geometry": {
        "type": "Point",
        "coordinates": [
          -84.4833,
          36.7833
        ]
      },
      "type": "Feature",
      "properties": {
        "hierarchy": [
          "tgn:2038860",
          "tgn:1000001",
          "tgn:7012149",
          "tgn:2000818",
          "tgn:7007255",
          "tgn:7029392"
        ],
        "placetype": [
          "aat:300008347"
        ],
        "id": 2038860,
        "name:xx": "Flat Rock"
      }
    },
    {
      "geometry": {
        "type": "Point",
        "coordinates": [
          -84.2667,
          37.35
        ]
      },
      "type": "Feature",
      "properties": {
        "hierarchy": [
          "tgn:2038861",
          "tgn:1000001",
          "tgn:7012149",
          "tgn:2000840",
          "tgn:7007255",
          "tgn:7029392"
        ],
        "placetype": [
          "aat:300008347",
          "aat:300387210"
        ],
        "id": 2038861,
        "name:xx": "Flat Rock"
      }
    },
    {
      "geometry": {
        "type": "Point",
        "coordinates": [
          -86.55,
          36.6667
        ]
      },
      "type": "Feature",
      "properties": {
        "hierarchy": [
          "tgn:2038862",
          "tgn:1000001",
          "tgn:7012149",
          "tgn:2000842",
          "tgn:7007255",
          "tgn:7029392"
        ],
        "placetype": [
          "aat:300008347",
          "aat:300387210"
        ],
        "id": 2038862,
        "name:xx": "Flat Rock"
      }
    },
    {
      "geometry": {
        "type": "Point",
        "coordinates": [
          -82.7167,
          38.5167
        ]
      },
      "type": "Feature",
      "properties": {
        "hierarchy": [
          "tgn:2038863",
          "tgn:1000001",
          "tgn:7012149",
          "tgn:1002426",
          "tgn:7007255",
          "tgn:7029392"
        ],
        "placetype": [
          "aat:300008347"
        ],
        "id": 2038863,
        "name:xx": "Flatwoods"
      }
    },
    {
      "geometry": {
        "type": "Point",
        "coordinates": [
          -86.2833,
          36.65
        ]
      },
      "type": "Feature",
      "properties": {
        "hierarchy": [
          "tgn:2038867",
          "tgn:2000766",
          "tgn:1000001",
          "tgn:7012149",
          "tgn:7007255",
          "tgn:7029392"
        ],
        "placetype": [
          "aat:300008347"
        ],
        "id": 2038867,
        "name:xx": "Fleet"
      }
    }
  ]
}
