{
  "geometry": {
    "type": "Point",
    "coordinates": [
      -108.3667,
      42.0167
    ]
  },
  "type": "Feature",
  "properties": {
    "hierarchy": [
      "tgn:2476141",
      "tgn:1000001",
      "tgn:7012149",
      "tgn:2002383",
      "tgn:7007923",
      "tgn:7029392"
    ],
    "placetype": [
      "aat:300008798"
    ],
    "id": 2476141,
    "name:xx": "Luman Butte"
  }
}
