{
  "geometry": {
    "type": "Point",
    "coordinates": [
      -72.55,
      41.3333
    ]
  },
  "type": "Feature",
  "properties": {
    "hierarchy": [
      "tgn:2621614",
      "tgn:1000001",
      "tgn:1002664",
      "tgn:7012149",
      "tgn:7007159",
      "tgn:7029392"
    ],
    "placetype": [
      "aat:300008798"
    ],
    "id": 2621614,
    "name:xx": "Roast Meat Hill"
  }
}
