{
  "geometry": {
    "type": "Point",
    "coordinates": [
      -81.0167,
      37.4167
    ]
  },
  "type": "Feature",
  "properties": {
    "hierarchy": [
      "tgn:2563904",
      "tgn:1000001",
      "tgn:7012149",
      "tgn:2002278",
      "tgn:7013961",
      "tgn:7029392"
    ],
    "placetype": [
      "aat:300008761"
    ],
    "id": 2563904,
    "name:xx": "Oxley Hollow"
  }
}
