{
  "geometry": {
    "type": "Point",
    "coordinates": [
      -94.25,
      35.1833
    ]
  },
  "type": "Feature",
  "properties": {
    "hierarchy": [
      "tgn:2365535",
      "tgn:1000001",
      "tgn:7016172",
      "tgn:7012149",
      "tgn:2000170",
      "tgn:7029392"
    ],
    "placetype": [
      "aat:300006191"
    ],
    "id": 2365535,
    "name:xx": "Greenwood Reservoir"
  }
}
