{
  "geometry": {
    "type": "Point",
    "coordinates": [
      -81.4833,
      25.8667
    ]
  },
  "type": "Feature",
  "properties": {
    "hierarchy": [
      "tgn:2321839",
      "tgn:1000001",
      "tgn:1002289",
      "tgn:7012149",
      "tgn:7007240",
      "tgn:7029392"
    ],
    "placetype": [
      "aat:300008347"
    ],
    "id": 2321839,
    "name:xx": "Fakahatchee"
  }
}
