{
  "type": "FeatureCollection",
  "features": [
    {
      "geometry": {
        "type": "Point",
        "coordinates": [
          -80.5833,
          37
        ]
      },
      "type": "Feature",
      "properties": {
        "hierarchy": [
          "tgn:2701440",
          "tgn:1000001",
          "tgn:7012149",
          "tgn:7007919",
          "tgn:7029392"
        ],
        "placetype": [
          "aat:300008699"
        ],
        "id": 2701440,
        "name:xx": "Sugar Run"
      }
    },
    {
      "geometry": {
        "type": "Point",
        "coordinates": [
          -80.1667,
          37.1
        ]
      },
      "type": "Feature",
      "properties": {
        "hierarchy": [
          "tgn:2701441",
          "tgn:1000001",
          "tgn:7012149",
          "tgn:2002158",
          "tgn:7007919",
          "tgn:7029392"
        ],
        "placetype": [
          "aat:300008699"
        ],
        "id": 2701441,
        "name:xx": "Sugar Run"
      }
    },
    {
      "geometry": {
        "type": "Point",
        "coordinates": [
          -80.1,
          37.65
        ]
      },
      "type": "Feature",
      "properties": {
        "hierarchy": [
          "tgn:2701442",
          "tgn:2002138",
          "tgn:1000001",
          "tgn:7012149",
          "tgn:7007919",
          "tgn:7029392"
        ],
        "placetype": [
          "aat:300008699"
        ],
        "id": 2701442,
        "name:xx": "Sugar Run"
      }
    },
    {
      "geometry": {
        "type": "Point",
        "coordinates": [
          -79.0667,
          38.6167
        ]
      },
      "type": "Feature",
      "properties": {
        "hierarchy": [
          "tgn:2701443",
          "tgn:1000001",
          "tgn:7012149",
          "tgn:2002187",
          "tgn:7007919",
          "tgn:7029392"
        ],
        "placetype": [
          "aat:300008699"
        ],
        "id": 2701443,
        "name:xx": "Sugar Run"
      }
    },
    {
      "geometry": {
        "type": "Point",
        "coordinates": [
          -80.85,
          37.25
        ]
      },
      "type": "Feature",
      "properties": {
        "hierarchy": [
          "tgn:2701444",
          "tgn:1000001",
          "tgn:7012149",
          "tgn:2002162",
          "tgn:7007919",
          "tgn:7029392"
        ],
        "placetype": [
          "aat:300008699"
        ],
        "id": 2701444,
        "name:xx": "Sugar Run"
      }
    },
    {
      "geometry": {
        "type": "Point",
        "coordinates": [
          -83.1,
          36.7167
        ]
      },
      "type": "Feature",
      "properties": {
        "hierarchy": [
          "tgn:2701445",
          "tgn:1000001",
          "tgn:7012149",
          "tgn:2002169",
          "tgn:7007919",
          "tgn:7029392"
        ],
        "placetype": [
          "aat:300008699"
        ],
        "id": 2701445,
        "name:xx": "Sugar Run"
      }
    },
    {
      "geometry": {
        "type": "Point",
        "coordinates": [
          -80.0667,
          38.0333
        ]
      },
      "type": "Feature",
      "properties": {
        "hierarchy": [
          "tgn:2701446",
          "tgn:1000001",
          "tgn:7012149",
          "tgn:2002264",
          "tgn:7013961",
          "tgn:7029392"
        ],
        "placetype": [
          "aat:300008699"
        ],
        "id": 2701446,
        "name:xx": "Sugar Run"
      }
    },
    {
      "geometry": {
        "type": "Point",
        "coordinates": [
          -79.7833,
          38.3833
        ]
      },
      "type": "Feature",
      "properties": {
        "hierarchy": [
          "tgn:2701447",
          "tgn:1000001",
          "tgn:7012149",
          "tgn:2002287",
          "tgn:7013961",
          "tgn:7029392"
        ],
        "placetype": [
          "aat:300008699"
        ],
        "id": 2701447,
        "name:xx": "Sugar Run"
      }
    },
    {
      "geometry": {
        "type": "Point",
        "coordinates": [
          -80.2833,
          38.5833
        ]
      },
      "type": "Feature",
      "properties": {
        "hierarchy": [
          "tgn:2701448",
          "tgn:1000001",
          "tgn:7012149",
          "tgn:2002300",
          "tgn:7013961",
          "tgn:7029392"
        ],
        "placetype": [
          "aat:300008699"
        ],
        "id": 2701448,
        "name:xx": "Sugar Run"
      }
    },
    {
      "geometry": {
        "type": "Point",
        "coordinates": [
          -81.3833,
          38.7333
        ]
      },
      "type": "Feature",
      "properties": {
        "hierarchy": [
          "tgn:2701449",
          "tgn:1000001",
          "tgn:7012149",
          "tgn:2002293",
          "tgn:7013961",
          "tgn:7029392"
        ],
        "placetype": [
          "aat:300008699"
        ],
        "id": 2701449,
        "name:xx": "Sugar Run"
      }
    }
  ]
}
