{
  "geometry": {
    "type": "Point",
    "coordinates": [
      -91.0667,
      33.9333
    ]
  },
  "type": "Feature",
  "properties": {
    "hierarchy": [
      "tgn:2521467",
      "tgn:1000001",
      "tgn:7016172",
      "tgn:7012149",
      "tgn:2000125",
      "tgn:7029392"
    ],
    "placetype": [
      "aat:300008850"
    ],
    "id": 2521467,
    "name:xx": "Montgomery Point"
  }
}
