{
  "type": "FeatureCollection",
  "features": [
    {
      "geometry": {
        "type": "Point",
        "coordinates": [
          -93.2167,
          30.2833
        ]
      },
      "type": "Feature",
      "properties": {
        "hierarchy": [
          "tgn:2154950",
          "tgn:1000001",
          "tgn:2000863",
          "tgn:7012149",
          "tgn:7007256",
          "tgn:7029392"
        ],
        "placetype": [
          "aat:300008791"
        ],
        "id": 2154950,
        "name:xx": "Bear Island"
      }
    },
    {
      "geometry": {
        "type": "Point",
        "coordinates": [
          -93.45,
          32.2833
        ]
      },
      "type": "Feature",
      "properties": {
        "hierarchy": [
          "tgn:2154951",
          "tgn:1000001",
          "tgn:2000861",
          "tgn:7012149",
          "tgn:7007256",
          "tgn:7029392"
        ],
        "placetype": [
          "aat:300008791"
        ],
        "id": 2154951,
        "name:xx": "Bear Island"
      }
    },
    {
      "geometry": {
        "type": "Point",
        "coordinates": [
          -90.6167,
          30.2667
        ]
      },
      "type": "Feature",
      "properties": {
        "hierarchy": [
          "tgn:2154952",
          "tgn:1000001",
          "tgn:7012149",
          "tgn:2000885",
          "tgn:7007256",
          "tgn:7029392"
        ],
        "placetype": [
          "aat:300055621"
        ],
        "id": 2154952,
        "name:xx": "Bear Island"
      }
    },
    {
      "geometry": {
        "type": "Point",
        "coordinates": [
          -89.8,
          30.4833
        ]
      },
      "type": "Feature",
      "properties": {
        "hierarchy": [
          "tgn:2154953",
          "tgn:1000001",
          "tgn:7012149",
          "tgn:2000905",
          "tgn:7007256",
          "tgn:7029392"
        ],
        "placetype": [
          "aat:300008791"
        ],
        "id": 2154953,
        "name:xx": "Bear Island"
      }
    },
    {
      "geometry": {
        "type": "Point",
        "coordinates": [
          -93.4,
          31.3667
        ]
      },
      "type": "Feature",
      "properties": {
        "hierarchy": [
          "tgn:2154954",
          "tgn:1000001",
          "tgn:7012149",
          "tgn:2000896",
          "tgn:7007256",
          "tgn:7029392"
        ],
        "placetype": [
          "aat:300008791"
        ],
        "id": 2154954,
        "name:xx": "Bear Island"
      }
    },
    {
      "geometry": {
        "type": "Point",
        "coordinates": [
          -69.8667,
          43.7667
        ]
      },
      "type": "Feature",
      "properties": {
        "hierarchy": [
          "tgn:2154955",
          "tgn:1000001",
          "tgn:7012149",
          "tgn:2000929",
          "tgn:7007515",
          "tgn:7029392"
        ],
        "placetype": [
          "aat:300008791"
        ],
        "id": 2154955,
        "name:xx": "Bear Island"
      }
    },
    {
      "geometry": {
        "type": "Point",
        "coordinates": [
          -68.5833,
          44.2167
        ]
      },
      "type": "Feature",
      "properties": {
        "hierarchy": [
          "tgn:2154956",
          "tgn:1000001",
          "tgn:2000922",
          "tgn:7012149",
          "tgn:7007515",
          "tgn:7029392"
        ],
        "placetype": [
          "aat:300008791"
        ],
        "id": 2154956,
        "name:xx": "Bear Island"
      }
    },
    {
      "geometry": {
        "type": "Point",
        "coordinates": [
          -67.8,
          45.7667
        ]
      },
      "type": "Feature",
      "properties": {
        "hierarchy": [
          "tgn:2154957",
          "tgn:2000919",
          "tgn:1000001",
          "tgn:7012149",
          "tgn:7007515",
          "tgn:7029392"
        ],
        "placetype": [
          "aat:300008791"
        ],
        "id": 2154957,
        "name:xx": "Bear Island"
      }
    },
    {
      "geometry": {
        "type": "Point",
        "coordinates": [
          -67.9333,
          45.2333
        ]
      },
      "type": "Feature",
      "properties": {
        "hierarchy": [
          "tgn:2154958",
          "tgn:1000001",
          "tgn:7012149",
          "tgn:7014589",
          "tgn:7007515",
          "tgn:7029392"
        ],
        "placetype": [
          "aat:300008791"
        ],
        "id": 2154958,
        "name:xx": "Bear Island"
      }
    },
    {
      "geometry": {
        "type": "Point",
        "coordinates": [
          -71.2333,
          42.0833
        ]
      },
      "type": "Feature",
      "properties": {
        "hierarchy": [
          "tgn:2154959",
          "tgn:1000001",
          "tgn:1002724",
          "tgn:7012149",
          "tgn:7007517",
          "tgn:7029392"
        ],
        "placetype": [
          "aat:300008791"
        ],
        "id": 2154959,
        "name:xx": "Bear Island"
      }
    }
  ]
}
