{
  "geometry": {
    "type": "Point",
    "coordinates": [
      -84.35,
      38.45
    ]
  },
  "type": "Feature",
  "properties": {
    "hierarchy": [
      "tgn:1002458",
      "tgn:1000001",
      "tgn:7012149",
      "tgn:7007255",
      "tgn:7029392"
    ],
    "placetype": [
      "aat:300387145",
      "aat:300000771"
    ],
    "id": 1002458,
    "name:xx": "Harrison"
  }
}
