{
  "type": "FeatureCollection",
  "features": [
    {
      "geometry": {
        "type": "Point",
        "coordinates": [
          -120.9,
          47.8
        ]
      },
      "type": "Feature",
      "properties": {
        "hierarchy": [
          "tgn:2471070",
          "tgn:1000001",
          "tgn:1002260",
          "tgn:7012149",
          "tgn:7007920",
          "tgn:7029392"
        ],
        "placetype": [
          "aat:300008706"
        ],
        "id": 2471070,
        "name:xx": "Lost Creek"
      }
    },
    {
      "geometry": {
        "type": "Point",
        "coordinates": [
          -119.1,
          48.2167
        ]
      },
      "type": "Feature",
      "properties": {
        "hierarchy": [
          "tgn:2471071",
          "tgn:1000001",
          "tgn:7012149",
          "tgn:1002742",
          "tgn:7007920",
          "tgn:7029392"
        ],
        "placetype": [
          "aat:300008706"
        ],
        "id": 2471071,
        "name:xx": "Lost Creek"
      }
    },
    {
      "geometry": {
        "type": "Point",
        "coordinates": [
          -122.7833,
          47.5667
        ]
      },
      "type": "Feature",
      "properties": {
        "hierarchy": [
          "tgn:2471072",
          "tgn:1000001",
          "tgn:7012149",
          "tgn:1002552",
          "tgn:7007920",
          "tgn:7029392"
        ],
        "placetype": [
          "aat:300008706"
        ],
        "id": 2471072,
        "name:xx": "Lost Creek"
      }
    },
    {
      "geometry": {
        "type": "Point",
        "coordinates": [
          -124.2167,
          47.7667
        ]
      },
      "type": "Feature",
      "properties": {
        "hierarchy": [
          "tgn:2471073",
          "tgn:1000001",
          "tgn:7012149",
          "tgn:1002521",
          "tgn:7007920",
          "tgn:7029392"
        ],
        "placetype": [
          "aat:300008706"
        ],
        "id": 2471073,
        "name:xx": "Lost Creek"
      }
    },
    {
      "geometry": {
        "type": "Point",
        "coordinates": [
          -121.4167,
          47.85
        ]
      },
      "type": "Feature",
      "properties": {
        "hierarchy": [
          "tgn:2471074",
          "tgn:1000001",
          "tgn:7012149",
          "tgn:1002899",
          "tgn:7007920",
          "tgn:7029392"
        ],
        "placetype": [
          "aat:300008706"
        ],
        "id": 2471074,
        "name:xx": "Lost Creek"
      }
    },
    {
      "geometry": {
        "type": "Point",
        "coordinates": [
          -82.4333,
          38.0333
        ]
      },
      "type": "Feature",
      "properties": {
        "hierarchy": [
          "tgn:2471075",
          "tgn:1000001",
          "tgn:7012149",
          "tgn:2002299",
          "tgn:7013961",
          "tgn:7029392"
        ],
        "placetype": [
          "aat:300008706"
        ],
        "id": 2471075,
        "name:xx": "Lost Creek"
      }
    },
    {
      "geometry": {
        "type": "Point",
        "coordinates": [
          -80.3167,
          39.1
        ]
      },
      "type": "Feature",
      "properties": {
        "hierarchy": [
          "tgn:2471076",
          "tgn:1000001",
          "tgn:7012149",
          "tgn:7013961",
          "tgn:7029392"
        ],
        "placetype": [
          "aat:300008706"
        ],
        "id": 2471076,
        "name:xx": "Lost Creek"
      }
    },
    {
      "geometry": {
        "type": "Point",
        "coordinates": [
          -89.0333,
          45.4
        ]
      },
      "type": "Feature",
      "properties": {
        "hierarchy": [
          "tgn:2471077",
          "tgn:1000001",
          "tgn:7012149",
          "tgn:2002333",
          "tgn:7007922",
          "tgn:7029392"
        ],
        "placetype": [
          "aat:300008706"
        ],
        "id": 2471077,
        "name:xx": "Lost Creek"
      }
    },
    {
      "geometry": {
        "type": "Point",
        "coordinates": [
          -89.9,
          46.1
        ]
      },
      "type": "Feature",
      "properties": {
        "hierarchy": [
          "tgn:2471078",
          "tgn:1000001",
          "tgn:7012149",
          "tgn:7007922",
          "tgn:7029392"
        ],
        "placetype": [
          "aat:300008706"
        ],
        "id": 2471078,
        "name:xx": "Lost Creek"
      }
    },
    {
      "geometry": {
        "type": "Point",
        "coordinates": [
          -92.15,
          44.5
        ]
      },
      "type": "Feature",
      "properties": {
        "hierarchy": [
          "tgn:2471079",
          "tgn:1000001",
          "tgn:7012149",
          "tgn:2002344",
          "tgn:7007922",
          "tgn:7029392"
        ],
        "placetype": [
          "aat:300008706"
        ],
        "id": 2471079,
        "name:xx": "Lost Creek"
      }
    }
  ]
}
