{
  "geometry": {
    "type": "Point",
    "coordinates": [
      25.393038,
      30.882216
    ]
  },
  "type": "Feature",
  "properties": {
    "hierarchy": [
      "tgn:7536062",
      "tgn:7001242",
      "tgn:7016833",
      "tgn:1001418",
      "tgn:7029392"
    ],
    "placetype": [
      "aat:300008777"
    ],
    "name:en": "Gawâmi, Qâret el-",
    "id": 7536062
  }
}
