{
  "geometry": {
    "type": "Point",
    "coordinates": [
      -120.6167,
      46.3833
    ]
  },
  "type": "Feature",
  "properties": {
    "hierarchy": [
      "tgn:2586650",
      "tgn:1000001",
      "tgn:7012149",
      "tgn:1003042",
      "tgn:7007920",
      "tgn:7029392"
    ],
    "placetype": [
      "aat:300006075"
    ],
    "id": 2586650,
    "name:xx": "Piute Lateral"
  }
}
