{
  "type": "FeatureCollection",
  "features": [
    {
      "geometry": {
        "type": "Point",
        "coordinates": [
          -107.116667,
          24.85
        ]
      },
      "type": "Feature",
      "properties": {
        "hierarchy": [
          "tgn:7360880",
          "tgn:1000001",
          "tgn:7005595",
          "tgn:7005560",
          "tgn:7029392"
        ],
        "placetype": [
          "aat:300008699"
        ],
        "id": 7360880,
        "name:xx": "Cofradía, Arroyo"
      }
    },
    {
      "geometry": {
        "type": "Point",
        "coordinates": [
          -104.133333,
          19.883333
        ]
      },
      "type": "Feature",
      "properties": {
        "hierarchy": [
          "tgn:7360881",
          "tgn:7005586",
          "tgn:1000001",
          "tgn:7005560",
          "tgn:7029392"
        ],
        "placetype": [
          "aat:300006191"
        ],
        "id": 7360881,
        "name:xx": "Cofradía"
      }
    },
    {
      "geometry": {
        "type": "Point",
        "coordinates": [
          -105.416667,
          25.866667
        ]
      },
      "type": "Feature",
      "properties": {
        "hierarchy": [
          "tgn:7360882",
          "tgn:7005583",
          "tgn:1000001",
          "tgn:7005560",
          "tgn:7029392"
        ],
        "placetype": [
          "aat:300008347"
        ],
        "id": 7360882,
        "name:xx": "Cofradía"
      }
    },
    {
      "geometry": {
        "type": "Point",
        "coordinates": [
          -108.45,
          25.5
        ]
      },
      "type": "Feature",
      "properties": {
        "hierarchy": [
          "tgn:7360883",
          "tgn:1000001",
          "tgn:7005595",
          "tgn:7005560",
          "tgn:7029392"
        ],
        "placetype": [
          "aat:300008347"
        ],
        "id": 7360883,
        "name:xx": "Cofradía"
      }
    },
    {
      "geometry": {
        "type": "Point",
        "coordinates": [
          -107.169167,
          24.897222
        ]
      },
      "type": "Feature",
      "properties": {
        "hierarchy": [
          "tgn:7360884",
          "tgn:1000001",
          "tgn:7005595",
          "tgn:7005560",
          "tgn:7029392"
        ],
        "placetype": [
          "aat:300008347"
        ],
        "id": 7360884,
        "name:xx": "Cofradía"
      }
    },
    {
      "geometry": {
        "type": "Point",
        "coordinates": [
          -107.646111,
          24.7675
        ]
      },
      "type": "Feature",
      "properties": {
        "hierarchy": [
          "tgn:7360885",
          "tgn:1000001",
          "tgn:7005595",
          "tgn:7005560",
          "tgn:7029392"
        ],
        "placetype": [
          "aat:300008347"
        ],
        "id": 7360885,
        "name:xx": "Cofradía"
      }
    },
    {
      "geometry": {
        "type": "Point",
        "coordinates": [
          -107.056389,
          24.376389
        ]
      },
      "type": "Feature",
      "properties": {
        "hierarchy": [
          "tgn:7360886",
          "tgn:1000001",
          "tgn:7005595",
          "tgn:7005560",
          "tgn:7029392"
        ],
        "placetype": [
          "aat:300008347"
        ],
        "id": 7360886,
        "name:xx": "Cofradía"
      }
    },
    {
      "geometry": {
        "type": "Point",
        "coordinates": [
          -105.183333,
          22.483333
        ]
      },
      "type": "Feature",
      "properties": {
        "hierarchy": [
          "tgn:7360887",
          "tgn:1000001",
          "tgn:1001906",
          "tgn:7005560",
          "tgn:7029392"
        ],
        "placetype": [
          "aat:300008347"
        ],
        "id": 7360887,
        "name:xx": "Cofradía"
      }
    },
    {
      "geometry": {
        "type": "Point",
        "coordinates": [
          -105.114444,
          22.054444
        ]
      },
      "type": "Feature",
      "properties": {
        "hierarchy": [
          "tgn:7360888",
          "tgn:1000001",
          "tgn:1001906",
          "tgn:7005560",
          "tgn:7029392"
        ],
        "placetype": [
          "aat:300008347"
        ],
        "id": 7360888,
        "name:xx": "Cofradía de Cuyutlán"
      }
    },
    {
      "geometry": {
        "type": "Point",
        "coordinates": [
          -103.633333,
          22.05
        ]
      },
      "type": "Feature",
      "properties": {
        "hierarchy": [
          "tgn:7360889",
          "tgn:7005586",
          "tgn:1000001",
          "tgn:7005560",
          "tgn:7029392"
        ],
        "placetype": [
          "aat:300008347"
        ],
        "id": 7360889,
        "name:xx": "Cofradía"
      }
    }
  ]
}
