{
  "geometry": {
    "type": "Point",
    "coordinates": [
      -90.9833,
      40.0833
    ]
  },
  "type": "Feature",
  "properties": {
    "hierarchy": [
      "tgn:2678023",
      "tgn:1002134",
      "tgn:1000001",
      "tgn:7012149",
      "tgn:7007251",
      "tgn:7029392"
    ],
    "placetype": [
      "aat:300008706"
    ],
    "id": 2678023,
    "name:xx": "South Fork Bear Creek"
  }
}
