{
  "geometry": {
    "type": "Point",
    "coordinates": [
      -81.7833,
      38.15
    ]
  },
  "type": "Feature",
  "properties": {
    "hierarchy": [
      "tgn:2645107",
      "tgn:1000001",
      "tgn:2002255",
      "tgn:7012149",
      "tgn:7013961",
      "tgn:7029392"
    ],
    "placetype": [
      "aat:300008761"
    ],
    "id": 2645107,
    "name:xx": "Sauls Camp Hollow"
  }
}
