{
  "geometry": {
    "type": "Point",
    "coordinates": [
      -81.5667,
      31.8333
    ]
  },
  "type": "Feature",
  "properties": {
    "hierarchy": [
      "tgn:2505549",
      "tgn:1000001",
      "tgn:7012149",
      "tgn:2000380",
      "tgn:7007248",
      "tgn:7029392"
    ],
    "placetype": [
      "aat:300008905"
    ],
    "id": 2505549,
    "name:xx": "Melvin Swamp"
  }
}
