{
  "geometry": {
    "type": "Point",
    "coordinates": [
      -100.8667,
      44.7333
    ]
  },
  "type": "Feature",
  "properties": {
    "hierarchy": [
      "tgn:2767934",
      "tgn:1000001",
      "tgn:7012149",
      "tgn:2001828",
      "tgn:7007713",
      "tgn:7029392"
    ],
    "placetype": [
      "aat:300008761"
    ],
    "id": 2767934,
    "name:xx": "Whiteman Draw"
  }
}
