{
  "geometry": {
    "type": "Point",
    "coordinates": [
      -42.6333,
      -5.8833
    ]
  },
  "type": "Feature",
  "properties": {
    "hierarchy": [
      "tgn:1020480",
      "tgn:7006252",
      "tgn:1000047",
      "tgn:7002455",
      "tgn:1000002",
      "tgn:7029392"
    ],
    "placetype": [
      "aat:300008347"
    ],
    "id": 1020480,
    "name:xx": "Água Branca"
  }
}
