{
  "geometry": {
    "type": "Point",
    "coordinates": [
      -90.6667,
      33.2833
    ]
  },
  "type": "Feature",
  "properties": {
    "hierarchy": [
      "tgn:2302055",
      "tgn:1000001",
      "tgn:7012149",
      "tgn:2001152",
      "tgn:7007522",
      "tgn:7029392"
    ],
    "placetype": [
      "aat:300008905"
    ],
    "id": 2302055,
    "name:xx": "Dutch Brake"
  }
}
