{
  "geometry": {
    "type": "Point",
    "coordinates": [
      126.1833,
      37.9167
    ]
  },
  "type": "Feature",
  "properties": {
    "hierarchy": [
      "tgn:1082159",
      "tgn:1001301",
      "tgn:1000004",
      "tgn:1000122",
      "tgn:7029392"
    ],
    "placetype": [
      "aat:300008347"
    ],
    "id": 1082159,
    "name:xx": "Yŏnan"
  }
}
