{
  "geometry": {
    "type": "Point",
    "coordinates": [
      -90.2333,
      44.9667
    ]
  },
  "type": "Feature",
  "properties": {
    "hierarchy": [
      "tgn:1121891",
      "tgn:1000001",
      "tgn:7012149",
      "tgn:2002336",
      "tgn:7007922",
      "tgn:7029392"
    ],
    "placetype": [
      "aat:300008707"
    ],
    "id": 1121891,
    "name:xx": "Big Eau Pleine"
  }
}
