{
  "geometry": {
    "type": "Point",
    "coordinates": [
      -123.0833,
      41.3167
    ]
  },
  "type": "Feature",
  "properties": {
    "hierarchy": [
      "tgn:2439622",
      "tgn:1000001",
      "tgn:7012149",
      "tgn:7007157",
      "tgn:2000189",
      "tgn:7029392"
    ],
    "placetype": [
      "aat:300000390"
    ],
    "id": 2439622,
    "name:xx": "Kismet Mine"
  }
}
