{
  "type": "FeatureCollection",
  "features": [
    {
      "geometry": {
        "type": "Point",
        "coordinates": [
          -86.2,
          39.1833
        ]
      },
      "type": "Feature",
      "properties": {
        "hierarchy": [
          "tgn:2277840",
          "tgn:1000001",
          "tgn:1002209",
          "tgn:7012149",
          "tgn:7007252",
          "tgn:7029392"
        ],
        "placetype": [
          "aat:300006191"
        ],
        "id": 2277840,
        "name:xx": "Dawson Lake"
      }
    },
    {
      "geometry": {
        "type": "Point",
        "coordinates": [
          -95.0833,
          37.9833
        ]
      },
      "type": "Feature",
      "properties": {
        "hierarchy": [
          "tgn:2277841",
          "tgn:2000660",
          "tgn:1000001",
          "tgn:7012149",
          "tgn:7007254",
          "tgn:7029392"
        ],
        "placetype": [
          "aat:300006191"
        ],
        "id": 2277841,
        "name:xx": "Dawson Lake"
      }
    },
    {
      "geometry": {
        "type": "Point",
        "coordinates": [
          -88.1833,
          46.0667
        ]
      },
      "type": "Feature",
      "properties": {
        "hierarchy": [
          "tgn:2277842",
          "tgn:1000001",
          "tgn:7012149",
          "tgn:2000966",
          "tgn:7007520",
          "tgn:7029392"
        ],
        "placetype": [
          "aat:300008680"
        ],
        "id": 2277842,
        "name:xx": "Dawson Lake"
      }
    },
    {
      "geometry": {
        "type": "Point",
        "coordinates": [
          -83.6333,
          46.0833
        ]
      },
      "type": "Feature",
      "properties": {
        "hierarchy": [
          "tgn:2277843",
          "tgn:1000001",
          "tgn:2000952",
          "tgn:7012149",
          "tgn:7007520",
          "tgn:7029392"
        ],
        "placetype": [
          "aat:300008680"
        ],
        "id": 2277843,
        "name:xx": "Dawson Lake"
      }
    },
    {
      "geometry": {
        "type": "Point",
        "coordinates": [
          -95.25,
          33.3667
        ]
      },
      "type": "Feature",
      "properties": {
        "hierarchy": [
          "tgn:2277844",
          "tgn:1000001",
          "tgn:7012149",
          "tgn:2002061",
          "tgn:7007826",
          "tgn:7029392"
        ],
        "placetype": [
          "aat:300008680"
        ],
        "id": 2277844,
        "name:xx": "Dawson Lake"
      }
    },
    {
      "geometry": {
        "type": "Point",
        "coordinates": [
          -88.7667,
          45.5667
        ]
      },
      "type": "Feature",
      "properties": {
        "hierarchy": [
          "tgn:2277845",
          "tgn:1000001",
          "tgn:2002323",
          "tgn:7012149",
          "tgn:7007922",
          "tgn:7029392"
        ],
        "placetype": [
          "aat:300008680"
        ],
        "id": 2277845,
        "name:xx": "Dawson Lake"
      }
    },
    {
      "geometry": {
        "type": "Point",
        "coordinates": [
          -132.7,
          55.4667
        ]
      },
      "type": "Feature",
      "properties": {
        "hierarchy": [
          "tgn:2277846",
          "tgn:7006450",
          "tgn:1000001",
          "tgn:7012149",
          "tgn:2000082",
          "tgn:7029392"
        ],
        "placetype": [
          "aat:300000390"
        ],
        "id": 2277846,
        "name:xx": "Dawson Mine"
      }
    },
    {
      "geometry": {
        "type": "Point",
        "coordinates": [
          -120.2333,
          35.9
        ]
      },
      "type": "Feature",
      "properties": {
        "hierarchy": [
          "tgn:2277847",
          "tgn:1000001",
          "tgn:7012149",
          "tgn:1002550",
          "tgn:7007157",
          "tgn:7029392"
        ],
        "placetype": [
          "aat:300000390"
        ],
        "id": 2277847,
        "name:xx": "Dawson Mine"
      }
    },
    {
      "geometry": {
        "type": "Point",
        "coordinates": [
          -118.4833,
          44.6833
        ]
      },
      "type": "Feature",
      "properties": {
        "hierarchy": [
          "tgn:2277848",
          "tgn:7013349",
          "tgn:1000001",
          "tgn:7012149",
          "tgn:7007708",
          "tgn:7029392"
        ],
        "placetype": [
          "aat:300000390"
        ],
        "id": 2277848,
        "name:xx": "Dawson Mine"
      }
    },
    {
      "geometry": {
        "type": "Point",
        "coordinates": [
          -105.3,
          38.3833
        ]
      },
      "type": "Feature",
      "properties": {
        "hierarchy": [
          "tgn:2277849",
          "tgn:1000001",
          "tgn:7012149",
          "tgn:2000213",
          "tgn:7007158",
          "tgn:7029392"
        ],
        "placetype": [
          "aat:300008798"
        ],
        "id": 2277849,
        "name:xx": "Dawson Mountain"
      }
    }
  ]
}
