{
  "geometry": {
    "type": "Point",
    "coordinates": [
      -85.3667,
      44.9333
    ]
  },
  "type": "Feature",
  "properties": {
    "hierarchy": [
      "tgn:2173506",
      "tgn:2000945",
      "tgn:1000001",
      "tgn:7012149",
      "tgn:7007520",
      "tgn:7029392"
    ],
    "placetype": [
      "aat:300008680"
    ],
    "id": 2173506,
    "name:xx": "Birch Lake"
  }
}
