{
  "geometry": {
    "type": "Point",
    "coordinates": [
      -80.6667,
      39.75
    ]
  },
  "type": "Feature",
  "properties": {
    "hierarchy": [
      "tgn:2696431",
      "tgn:1000001",
      "tgn:7012149",
      "tgn:2002276",
      "tgn:7013961",
      "tgn:7029392"
    ],
    "placetype": [
      "aat:300008761"
    ],
    "id": 2696431,
    "name:xx": "Stone Hollow"
  }
}
