{
  "geometry": {
    "type": "Point",
    "coordinates": [
      -114.2667,
      39.0167
    ]
  },
  "type": "Feature",
  "properties": {
    "hierarchy": [
      "tgn:2512782",
      "tgn:1000001",
      "tgn:7012149",
      "tgn:2001420",
      "tgn:7007526",
      "tgn:7029392"
    ],
    "placetype": [
      "aat:300008706"
    ],
    "id": 2512782,
    "name:xx": "Mill Creek"
  }
}
