{
  "geometry": {
    "type": "Point",
    "coordinates": [
      107.2667,
      34.3833
    ]
  },
  "type": "Feature",
  "properties": {
    "hierarchy": [
      "tgn:7001898",
      "tgn:1000004",
      "tgn:7002084",
      "tgn:1000111",
      "tgn:7029392"
    ],
    "placetype": [
      "aat:300008347"
    ],
    "id": 7001898,
    "name:xx": "Baoji"
  }
}
