{
  "geometry": {
    "type": "Point",
    "coordinates": [
      -99.4667,
      40.4167
    ]
  },
  "type": "Feature",
  "properties": {
    "hierarchy": [
      "tgn:2635919",
      "tgn:1000001",
      "tgn:7012149",
      "tgn:2001384",
      "tgn:7007525",
      "tgn:7029392"
    ],
    "placetype": [
      "aat:300008706"
    ],
    "id": 2635919,
    "name:xx": "Sacramento Creek"
  }
}
