{
  "geometry": {
    "type": "Point",
    "coordinates": [
      -131.4667,
      55.2167
    ]
  },
  "type": "Feature",
  "properties": {
    "hierarchy": [
      "tgn:2534747",
      "tgn:7006450",
      "tgn:1000001",
      "tgn:7012149",
      "tgn:2000082",
      "tgn:7029392"
    ],
    "placetype": [
      "aat:300132316"
    ],
    "id": 2534747,
    "name:xx": "Nadzaheer Cove"
  }
}
