{
  "geometry": {
    "type": "Point",
    "coordinates": [
      -76.6167,
      34.9333
    ]
  },
  "type": "Feature",
  "properties": {
    "hierarchy": [
      "tgn:2425913",
      "tgn:1000001",
      "tgn:2001477",
      "tgn:7012149",
      "tgn:7007709",
      "tgn:7029392"
    ],
    "placetype": [
      "aat:300008706"
    ],
    "id": 2425913,
    "name:xx": "Jonaquin Creek"
  }
}
