{
  "geometry": {
    "type": "Point",
    "coordinates": [
      -106.45,
      35.0833
    ]
  },
  "type": "Feature",
  "properties": {
    "hierarchy": [
      "tgn:2316700",
      "tgn:1000001",
      "tgn:2001428",
      "tgn:7012149",
      "tgn:7007566",
      "tgn:7029392"
    ],
    "placetype": [
      "aat:300008697"
    ],
    "id": 2316700,
    "name:xx": "Embudo Spring"
  }
}
