{
  "geometry": {
    "type": "Point",
    "coordinates": [
      14.2333,
      -14.8667
    ]
  },
  "type": "Feature",
  "properties": {
    "hierarchy": [
      "tgn:1087922",
      "tgn:7001242",
      "tgn:1000149",
      "tgn:1000867",
      "tgn:7029392"
    ],
    "placetype": [
      "aat:300008347"
    ],
    "id": 1087922,
    "name:xx": "Muquequete"
  }
}
