{
  "geometry": {
    "type": "Point",
    "coordinates": [
      -83.4667,
      43.4333
    ]
  },
  "type": "Feature",
  "properties": {
    "hierarchy": [
      "tgn:2232934",
      "tgn:1000001",
      "tgn:7012149",
      "tgn:2000997",
      "tgn:7007520",
      "tgn:7029392"
    ],
    "placetype": [
      "aat:300006075"
    ],
    "id": 2232934,
    "name:xx": "Chapple Drain"
  }
}
