{
  "geometry": {
    "type": "Point",
    "coordinates": [
      -159.8667,
      9.3167
    ]
  },
  "type": "Feature",
  "properties": {
    "hierarchy": [
      "tgn:2550095",
      "tgn:7030515",
      "tgn:7006450",
      "tgn:1000001",
      "tgn:7012149",
      "tgn:7029392"
    ],
    "placetype": [
      "aat:300132316"
    ],
    "id": 2550095,
    "name:xx": "Northeast Bight"
  }
}
