{
  "geometry": {
    "type": "Point",
    "coordinates": [
      102.3167,
      20.3667
    ]
  },
  "type": "Feature",
  "properties": {
    "hierarchy": [
      "tgn:1082456",
      "tgn:1000004",
      "tgn:7000852",
      "tgn:1000125",
      "tgn:7029392"
    ],
    "placetype": [
      "aat:300008347"
    ],
    "id": 1082456,
    "name:xx": "Ban Namnga"
  }
}
