{
  "type": "FeatureCollection",
  "features": [
    {
      "geometry": {
        "type": "Point",
        "coordinates": [
          122.6667,
          7.5
        ]
      },
      "type": "Feature",
      "properties": {
        "hierarchy": [
          "tgn:1113821",
          "tgn:1000004",
          "tgn:1001611",
          "tgn:1000135",
          "tgn:7029392"
        ],
        "placetype": [
          "aat:300132316"
        ],
        "id": 1113821,
        "name:xx": "Sibuguey Bay"
      }
    },
    {
      "geometry": {
        "type": "Point",
        "coordinates": [
          -83.0833,
          21.6333
        ]
      },
      "type": "Feature",
      "properties": {
        "hierarchy": [
          "tgn:1113823",
          "tgn:7006369",
          "tgn:1000001",
          "tgn:7004624",
          "tgn:7029392"
        ],
        "placetype": [
          "aat:300132316"
        ],
        "id": 1113823,
        "name:xx": "Siguanea, Ensenada de la"
      }
    },
    {
      "geometry": {
        "type": "Point",
        "coordinates": [
          114,
          22.2667
        ]
      },
      "type": "Feature",
      "properties": {
        "hierarchy": [
          "tgn:1113824",
          "tgn:7018487",
          "tgn:1007810",
          "tgn:1000004",
          "tgn:7004542",
          "tgn:1000111",
          "tgn:7029392"
        ],
        "placetype": [
          "aat:300132316"
        ],
        "id": 1113824,
        "name:xx": "Ngan Kwong Wan"
      }
    },
    {
      "geometry": {
        "type": "Point",
        "coordinates": [
          -3.116667,
          58.5
        ]
      },
      "type": "Feature",
      "properties": {
        "hierarchy": [
          "tgn:1113825",
          "tgn:7002444",
          "tgn:1000003",
          "tgn:7008082",
          "tgn:7008591",
          "tgn:7029392"
        ],
        "placetype": [
          "aat:300132316"
        ],
        "id": 1113825,
        "name:xx": "Sinclair's Bay"
      }
    },
    {
      "geometry": {
        "type": "Point",
        "coordinates": [
          122.8333,
          8.1833
        ]
      },
      "type": "Feature",
      "properties": {
        "hierarchy": [
          "tgn:1113826",
          "tgn:1000004",
          "tgn:1001610",
          "tgn:1000135",
          "tgn:7029392"
        ],
        "placetype": [
          "aat:300132316"
        ],
        "id": 1113826,
        "name:xx": "Sindangan Bay"
      }
    },
    {
      "geometry": {
        "type": "Point",
        "coordinates": [
          -75.1333,
          38.25
        ]
      },
      "type": "Feature",
      "properties": {
        "hierarchy": [
          "tgn:1113827",
          "tgn:1000001",
          "tgn:1003037",
          "tgn:7012149",
          "tgn:7007516",
          "tgn:7029392"
        ],
        "placetype": [
          "aat:300132316"
        ],
        "id": 1113827,
        "name:xx": "Sinepuxent Bay"
      }
    },
    {
      "geometry": {
        "type": "Point",
        "coordinates": [
          12.8333,
          56.2833
        ]
      },
      "type": "Feature",
      "properties": {
        "hierarchy": [
          "tgn:1113829",
          "tgn:1000003",
          "tgn:7024622",
          "tgn:1000097",
          "tgn:7029392"
        ],
        "placetype": [
          "aat:300132316"
        ],
        "id": 1113829,
        "name:xx": "Skälderviken"
      }
    }
  ]
}
