{
  "geometry": {
    "type": "Point",
    "coordinates": [
      -95.9333,
      44.2667
    ]
  },
  "type": "Feature",
  "properties": {
    "hierarchy": [
      "tgn:2624300",
      "tgn:1000001",
      "tgn:7012149",
      "tgn:2001040",
      "tgn:7007521",
      "tgn:7029392"
    ],
    "placetype": [
      "aat:300008680"
    ],
    "id": 2624300,
    "name:xx": "Rock Lake"
  }
}
