{
  "geometry": {
    "type": "Point",
    "coordinates": [
      -71.4667,
      41.9667
    ]
  },
  "type": "Feature",
  "properties": {
    "hierarchy": [
      "tgn:2094995",
      "tgn:1002808",
      "tgn:1000001",
      "tgn:7012149",
      "tgn:7007711",
      "tgn:7029392"
    ],
    "placetype": [
      "aat:300008347"
    ],
    "id": 2094995,
    "name:xx": "Manville"
  }
}
