{
  "geometry": {
    "type": "Point",
    "coordinates": [
      5.8333,
      48.1167
    ]
  },
  "type": "Feature",
  "properties": {
    "hierarchy": [
      "tgn:1034303",
      "tgn:1000003",
      "tgn:7002888",
      "tgn:1000070",
      "tgn:7029392"
    ],
    "placetype": [
      "aat:300008347"
    ],
    "id": 1034303,
    "name:xx": "Martigny-les-Bains"
  }
}
