{
  "geometry": {
    "type": "Point",
    "coordinates": [
      30.543484,
      30.99042
    ]
  },
  "type": "Feature",
  "properties": {
    "hierarchy": [
      "tgn:7526044",
      "tgn:7001242",
      "tgn:1001075",
      "tgn:7016833",
      "tgn:7029392"
    ],
    "placetype": [
      "aat:300008347"
    ],
    "name:en": "Ţarābanbā",
    "id": 7526044
  }
}
