{
  "geometry": {
    "type": "Point",
    "coordinates": [
      -79.65,
      38.85
    ]
  },
  "type": "Feature",
  "properties": {
    "hierarchy": [
      "tgn:2500042",
      "tgn:1000001",
      "tgn:7012149",
      "tgn:2002291",
      "tgn:7013961",
      "tgn:7029392"
    ],
    "placetype": [
      "aat:300266640"
    ],
    "id": 2500042,
    "name:xx": "McCray Ridge"
  }
}
