{
  "geometry": {
    "type": "Point",
    "coordinates": [
      -107.9167,
      33.2333
    ]
  },
  "type": "Feature",
  "properties": {
    "hierarchy": [
      "tgn:2687576",
      "tgn:1000001",
      "tgn:7012149",
      "tgn:2001455",
      "tgn:7007566",
      "tgn:7029392"
    ],
    "placetype": [
      "aat:300008697"
    ],
    "id": 2687576,
    "name:xx": "Spring Mountain Spring"
  }
}
