{
  "geometry": {
    "type": "Point",
    "coordinates": [
      -113.2333,
      46.7333
    ]
  },
  "type": "Feature",
  "properties": {
    "hierarchy": [
      "tgn:2344782",
      "tgn:1000001",
      "tgn:7012149",
      "tgn:2001279",
      "tgn:7007524",
      "tgn:7029392"
    ],
    "placetype": [
      "aat:300008761"
    ],
    "id": 2344782,
    "name:xx": "Garden Gulch"
  }
}
