{
  "type": "FeatureCollection",
  "features": [
    {
      "geometry": {
        "type": "Point",
        "coordinates": [
          -71.2325,
          -28.483333
        ]
      },
      "type": "Feature",
      "properties": {
        "hierarchy": [
          "tgn:7318140",
          "tgn:1001630",
          "tgn:1000049",
          "tgn:1000002",
          "tgn:7029392"
        ],
        "placetype": [
          "aat:300008777"
        ],
        "id": 7318140,
        "name:xx": "Colorado, Cerro"
      }
    },
    {
      "geometry": {
        "type": "Point",
        "coordinates": [
          -70.4,
          -25.266667
        ]
      },
      "type": "Feature",
      "properties": {
        "hierarchy": [
          "tgn:7318141",
          "tgn:7016598",
          "tgn:1000049",
          "tgn:1000002",
          "tgn:7029392"
        ],
        "placetype": [
          "aat:300008777"
        ],
        "id": 7318141,
        "name:xx": "Colorado, Cerro"
      }
    },
    {
      "geometry": {
        "type": "Point",
        "coordinates": [
          -70.666667,
          -35.533333
        ]
      },
      "type": "Feature",
      "properties": {
        "hierarchy": [
          "tgn:7318142",
          "tgn:1001705",
          "tgn:1000049",
          "tgn:1000002",
          "tgn:7029392"
        ],
        "placetype": [
          "aat:300386986"
        ],
        "id": 7318142,
        "name:xx": "Colorado, Cerro"
      }
    },
    {
      "geometry": {
        "type": "Point",
        "coordinates": [
          -71.233333,
          -37.216667
        ]
      },
      "type": "Feature",
      "properties": {
        "hierarchy": [
          "tgn:7318143",
          "tgn:1001637",
          "tgn:1000049",
          "tgn:1000002",
          "tgn:7029392"
        ],
        "placetype": [
          "aat:300008699"
        ],
        "id": 7318143,
        "name:xx": "Colorado, Cajón"
      }
    },
    {
      "geometry": {
        "type": "Point",
        "coordinates": [
          -74.233333,
          -49.533333
        ]
      },
      "type": "Feature",
      "properties": {
        "hierarchy": [
          "tgn:7318144",
          "tgn:1001702",
          "tgn:1000049",
          "tgn:1000002",
          "tgn:7029392"
        ],
        "placetype": [
          "aat:300386846"
        ],
        "id": 7318144,
        "name:xx": "Colorado, Cabo"
      }
    },
    {
      "geometry": {
        "type": "Point",
        "coordinates": [
          -71.916667,
          -46.616667
        ]
      },
      "type": "Feature",
      "properties": {
        "hierarchy": [
          "tgn:7318145",
          "tgn:1001623",
          "tgn:1000049",
          "tgn:1000002",
          "tgn:7029392"
        ],
        "placetype": [
          "aat:300008699"
        ],
        "id": 7318145,
        "name:xx": "Colorado, Arroyo"
      }
    },
    {
      "geometry": {
        "type": "Point",
        "coordinates": [
          -71.85,
          -34.616667
        ]
      },
      "type": "Feature",
      "properties": {
        "hierarchy": [
          "tgn:7318146",
          "tgn:1001695",
          "tgn:1000049",
          "tgn:1000002",
          "tgn:7029392"
        ],
        "placetype": [
          "aat:300008795"
        ],
        "id": 7318146,
        "name:xx": "Colorado, Alto"
      }
    },
    {
      "geometry": {
        "type": "Point",
        "coordinates": [
          -71.883333,
          -34.333333
        ]
      },
      "type": "Feature",
      "properties": {
        "hierarchy": [
          "tgn:7318147",
          "tgn:1001695",
          "tgn:1000049",
          "tgn:1000002",
          "tgn:7029392"
        ],
        "placetype": [
          "aat:300008795"
        ],
        "id": 7318147,
        "name:xx": "Colorado, Alto"
      }
    },
    {
      "geometry": {
        "type": "Point",
        "coordinates": [
          -71.05,
          -32.033333
        ]
      },
      "type": "Feature",
      "properties": {
        "hierarchy": [
          "tgn:7318148",
          "tgn:1001657",
          "tgn:1000049",
          "tgn:1000002",
          "tgn:7029392"
        ],
        "placetype": [
          "aat:300008795"
        ],
        "id": 7318148,
        "name:xx": "Colorado, Alto"
      }
    },
    {
      "geometry": {
        "type": "Point",
        "coordinates": [
          -68.55,
          -24.1
        ]
      },
      "type": "Feature",
      "properties": {
        "hierarchy": [
          "tgn:7318149",
          "tgn:7016598",
          "tgn:1000049",
          "tgn:1000002",
          "tgn:7029392"
        ],
        "placetype": [
          "aat:300008795"
        ],
        "id": 7318149,
        "name:xx": "Colorado, Alto"
      }
    }
  ]
}
