{
  "geometry": {
    "type": "Point",
    "coordinates": [
      -120.8833,
      44.6833
    ]
  },
  "type": "Feature",
  "properties": {
    "hierarchy": [
      "tgn:2765084",
      "tgn:1000001",
      "tgn:7012149",
      "tgn:2001712",
      "tgn:7007708",
      "tgn:7029392"
    ],
    "placetype": [
      "aat:300008697"
    ],
    "id": 2765084,
    "name:xx": "Whisky Spring"
  }
}
