{
  "geometry": {
    "type": "Point",
    "coordinates": [
      -91.0167,
      41.0167
    ]
  },
  "type": "Feature",
  "properties": {
    "hierarchy": [
      "tgn:2380969",
      "tgn:1000001",
      "tgn:2000589",
      "tgn:7012149",
      "tgn:7007253",
      "tgn:7029392"
    ],
    "placetype": [
      "aat:300006075"
    ],
    "id": 2380969,
    "name:xx": "Hawkeye-Dolbee Diversion Channel"
  }
}
