{
  "geometry": {
    "type": "Point",
    "coordinates": [
      -82.55,
      39.3333
    ]
  },
  "type": "Feature",
  "properties": {
    "hierarchy": [
      "tgn:2509364",
      "tgn:1000001",
      "tgn:7012149",
      "tgn:7007706",
      "tgn:7029392"
    ],
    "placetype": [
      "aat:300008706"
    ],
    "id": 2509364,
    "name:xx": "Middle Fork Salt Creek"
  }
}
