{
  "geometry": {
    "type": "Point",
    "coordinates": [
      -115.5167,
      40.2667
    ]
  },
  "type": "Feature",
  "properties": {
    "hierarchy": [
      "tgn:2410866",
      "tgn:1000001",
      "tgn:2001411",
      "tgn:7012149",
      "tgn:7007526",
      "tgn:7029392"
    ],
    "placetype": [
      "aat:300008706"
    ],
    "id": 2410866,
    "name:xx": "Indian Creek"
  }
}
