{
  "geometry": {
    "type": "Point",
    "coordinates": [
      23.7333,
      49.85
    ]
  },
  "type": "Feature",
  "properties": {
    "hierarchy": [
      "tgn:4010825",
      "tgn:1000003",
      "tgn:7011664",
      "tgn:7006660",
      "tgn:7029392"
    ],
    "placetype": [
      "aat:300008347",
      "aat:300008375"
    ],
    "id": 4010825,
    "name:xx": "Storonna"
  }
}
