{
  "geometry": {
    "type": "Point",
    "coordinates": [
      -119.5167,
      44.8667
    ]
  },
  "type": "Feature",
  "properties": {
    "hierarchy": [
      "tgn:2605456",
      "tgn:1000001",
      "tgn:7012149",
      "tgn:2001708",
      "tgn:7007708",
      "tgn:7029392"
    ],
    "placetype": [
      "aat:300008761"
    ],
    "id": 2605456,
    "name:xx": "Rail Canyon"
  }
}
