{
  "geometry": {
    "type": "Point",
    "coordinates": [
      23.8167,
      11.55
    ]
  },
  "type": "Feature",
  "properties": {
    "hierarchy": [
      "tgn:1094354",
      "tgn:7001242",
      "tgn:1001212",
      "tgn:1000201",
      "tgn:7029392"
    ],
    "placetype": [
      "aat:300008347"
    ],
    "id": 1094354,
    "name:xx": "Markundi"
  }
}
