{
  "geometry": {
    "type": "Point",
    "coordinates": [
      -76.6167,
      41.95
    ]
  },
  "type": "Feature",
  "properties": {
    "hierarchy": [
      "tgn:2560438",
      "tgn:1000001",
      "tgn:1002194",
      "tgn:7012149",
      "tgn:7007710",
      "tgn:7029392"
    ],
    "placetype": [
      "aat:300008706"
    ],
    "id": 2560438,
    "name:xx": "Orcutt Creek"
  }
}
