{
  "geometry": {
    "type": "Point",
    "coordinates": [
      -119.2833,
      48.35
    ]
  },
  "type": "Feature",
  "properties": {
    "hierarchy": [
      "tgn:2340532",
      "tgn:1000001",
      "tgn:7012149",
      "tgn:1002742",
      "tgn:7007920",
      "tgn:7029392"
    ],
    "placetype": [
      "aat:300008761"
    ],
    "id": 2340532,
    "name:xx": "French Valley"
  }
}
