{
  "geometry": {
    "type": "Point",
    "coordinates": [
      -95.7667,
      30.65
    ]
  },
  "type": "Feature",
  "properties": {
    "hierarchy": [
      "tgn:2486769",
      "tgn:1000001",
      "tgn:7012149",
      "tgn:1002980",
      "tgn:7007826",
      "tgn:7029392"
    ],
    "placetype": [
      "aat:300008699"
    ],
    "id": 2486769,
    "name:xx": "Lee Branch"
  }
}
