{
  "geometry": {
    "type": "Point",
    "coordinates": [
      -86.3167,
      34.8833
    ]
  },
  "type": "Feature",
  "properties": {
    "hierarchy": [
      "tgn:2165081",
      "tgn:7002659",
      "tgn:1000001",
      "tgn:7012149",
      "tgn:2000035",
      "tgn:7029392"
    ],
    "placetype": [
      "aat:300008746"
    ],
    "id": 2165081,
    "name:xx": "Bethel Cave"
  }
}
