{
  "geometry": {
    "type": "Point",
    "coordinates": [
      24.433333,
      37.166667
    ]
  },
  "type": "Feature",
  "properties": {
    "hierarchy": [
      "tgn:7234249",
      "tgn:7011270",
      "tgn:7002674",
      "tgn:1000003",
      "tgn:1000074",
      "tgn:7029392"
    ],
    "placetype": [
      "aat:300132316"
    ],
    "id": 7234249,
    "name:xx": "Avesalós, Órmos"
  }
}
