{
  "geometry": {
    "type": "Point",
    "coordinates": [
      -82.5167,
      37.0333
    ]
  },
  "type": "Feature",
  "properties": {
    "hierarchy": [
      "tgn:2375822",
      "tgn:1000001",
      "tgn:7012149",
      "tgn:2002195",
      "tgn:7007919",
      "tgn:7029392"
    ],
    "placetype": [
      "aat:300008761"
    ],
    "id": 2375822,
    "name:xx": "Happy Hollow"
  }
}
