{
  "geometry": {
    "type": "Point",
    "coordinates": [
      -74.4833,
      41.9167
    ]
  },
  "type": "Feature",
  "properties": {
    "hierarchy": [
      "tgn:2389585",
      "tgn:1000001",
      "tgn:7012149",
      "tgn:1002961",
      "tgn:7007568",
      "tgn:7029392"
    ],
    "placetype": [
      "aat:300008699"
    ],
    "id": 2389585,
    "name:xx": "High Falls Brook"
  }
}
