{
  "type": "FeatureCollection",
  "features": [
    {
      "geometry": {
        "type": "Point",
        "coordinates": [
          -71.05,
          -34.5
        ]
      },
      "type": "Feature",
      "properties": {
        "hierarchy": [
          "tgn:7290860",
          "tgn:1001695",
          "tgn:1000049",
          "tgn:1000002",
          "tgn:7029392"
        ],
        "placetype": [
          "aat:300266554",
          "aat:300008699"
        ],
        "id": 7290860,
        "name:xx": "Culenes, Quebrada los"
      }
    },
    {
      "geometry": {
        "type": "Point",
        "coordinates": [
          -71.216667,
          -34.166667
        ]
      },
      "type": "Feature",
      "properties": {
        "hierarchy": [
          "tgn:7290861",
          "tgn:1001708",
          "tgn:1000049",
          "tgn:1000002",
          "tgn:7029392"
        ],
        "placetype": [
          "aat:300008699"
        ],
        "id": 7290861,
        "name:xx": "Culenes, Quebrada de los"
      }
    },
    {
      "geometry": {
        "type": "Point",
        "coordinates": [
          -71.533333,
          -33.2
        ]
      },
      "type": "Feature",
      "properties": {
        "hierarchy": [
          "tgn:7290862",
          "tgn:1001768",
          "tgn:1000049",
          "tgn:1000002",
          "tgn:7029392"
        ],
        "placetype": [
          "aat:300008699"
        ],
        "id": 7290862,
        "name:xx": "Culenes, Quebrada"
      }
    },
    {
      "geometry": {
        "type": "Point",
        "coordinates": [
          -70.016667,
          -33.15
        ]
      },
      "type": "Feature",
      "properties": {
        "hierarchy": [
          "tgn:7290863",
          "tgn:1001708",
          "tgn:1000049",
          "tgn:1000002",
          "tgn:7029392"
        ],
        "placetype": [
          "aat:300008795"
        ],
        "id": 7290863,
        "name:xx": "Culenes, Cerro"
      }
    },
    {
      "geometry": {
        "type": "Point",
        "coordinates": [
          -72.166667,
          -35.3
        ]
      },
      "type": "Feature",
      "properties": {
        "hierarchy": [
          "tgn:7290864",
          "tgn:1001705",
          "tgn:1000049",
          "tgn:1000002",
          "tgn:7029392"
        ],
        "placetype": [
          "aat:300387200"
        ],
        "id": 7290864,
        "name:xx": "Culenes"
      }
    },
    {
      "geometry": {
        "type": "Point",
        "coordinates": [
          -71.4,
          -33.9
        ]
      },
      "type": "Feature",
      "properties": {
        "hierarchy": [
          "tgn:7290865",
          "tgn:1001708",
          "tgn:1000049",
          "tgn:1000002",
          "tgn:7029392"
        ],
        "placetype": [
          "aat:300008777"
        ],
        "id": 7290865,
        "name:xx": "Culenes"
      }
    },
    {
      "geometry": {
        "type": "Point",
        "coordinates": [
          -72.75,
          -37.466667
        ]
      },
      "type": "Feature",
      "properties": {
        "hierarchy": [
          "tgn:7290866",
          "tgn:1001637",
          "tgn:1000049",
          "tgn:1000002",
          "tgn:7029392"
        ],
        "placetype": [
          "aat:300008699"
        ],
        "id": 7290866,
        "name:xx": "Culenco, Río"
      }
    },
    {
      "geometry": {
        "type": "Point",
        "coordinates": [
          -72.25,
          -36.983333
        ]
      },
      "type": "Feature",
      "properties": {
        "hierarchy": [
          "tgn:7290867",
          "tgn:1001637",
          "tgn:1000049",
          "tgn:1000002",
          "tgn:7029392"
        ],
        "placetype": [
          "aat:300008699"
        ],
        "id": 7290867,
        "name:xx": "Culenco, Estero"
      }
    },
    {
      "geometry": {
        "type": "Point",
        "coordinates": [
          -71.683333,
          -34.816667
        ]
      },
      "type": "Feature",
      "properties": {
        "hierarchy": [
          "tgn:7290868",
          "tgn:1001695",
          "tgn:1000049",
          "tgn:1000002",
          "tgn:7029392"
        ],
        "placetype": [
          "aat:300008795"
        ],
        "id": 7290868,
        "name:xx": "Culenco, Cerro"
      }
    },
    {
      "geometry": {
        "type": "Point",
        "coordinates": [
          -70.716667,
          -31.933333
        ]
      },
      "type": "Feature",
      "properties": {
        "hierarchy": [
          "tgn:7290869",
          "tgn:1001657",
          "tgn:1000049",
          "tgn:1000002",
          "tgn:7029392"
        ],
        "placetype": [
          "aat:300008795"
        ],
        "id": 7290869,
        "name:xx": "Culenco, Cerro"
      }
    }
  ]
}
