{
  "geometry": {
    "type": "Point",
    "coordinates": [
      -152.7333,
      68.7167
    ]
  },
  "type": "Feature",
  "properties": {
    "hierarchy": [
      "tgn:2379927",
      "tgn:7006450",
      "tgn:1000001",
      "tgn:7012149",
      "tgn:2124005",
      "tgn:7029392"
    ],
    "placetype": [
      "aat:300008798"
    ],
    "id": 2379927,
    "name:xx": "Hatbox Mesa"
  }
}
