{
  "geometry": {
    "type": "Point",
    "coordinates": [
      -81.35,
      36.95
    ]
  },
  "type": "Feature",
  "properties": {
    "hierarchy": [
      "tgn:2613334",
      "tgn:1000001",
      "tgn:7012149",
      "tgn:2002196",
      "tgn:7007919",
      "tgn:7029392"
    ],
    "placetype": [
      "aat:300008706"
    ],
    "id": 2613334,
    "name:xx": "Reed Creek"
  }
}
