{
  "type": "FeatureCollection",
  "features": [
    {
      "geometry": {
        "type": "Point",
        "coordinates": [
          -107.5,
          43.3667
        ]
      },
      "type": "Feature",
      "properties": {
        "hierarchy": [
          "tgn:2706050",
          "tgn:1000001",
          "tgn:7012149",
          "tgn:2002377",
          "tgn:7007923",
          "tgn:7029392"
        ],
        "placetype": [
          "aat:300008697"
        ],
        "id": 2706050,
        "name:xx": "Swaim Spring"
      }
    },
    {
      "geometry": {
        "type": "Point",
        "coordinates": [
          -80.2667,
          36.0167
        ]
      },
      "type": "Feature",
      "properties": {
        "hierarchy": [
          "tgn:2706051",
          "tgn:1000001",
          "tgn:7012149",
          "tgn:2001494",
          "tgn:7007709",
          "tgn:7029392"
        ],
        "placetype": [
          "aat:300008347"
        ],
        "id": 2706051,
        "name:xx": "Swaimtown"
      }
    },
    {
      "geometry": {
        "type": "Point",
        "coordinates": [
          -74.8,
          39.1167
        ]
      },
      "type": "Feature",
      "properties": {
        "hierarchy": [
          "tgn:2706052",
          "tgn:1002232",
          "tgn:1000001",
          "tgn:7012149",
          "tgn:7007565",
          "tgn:7029392"
        ],
        "placetype": [
          "aat:300008347"
        ],
        "id": 2706052,
        "name:xx": "Swain"
      }
    },
    {
      "geometry": {
        "type": "Point",
        "coordinates": [
          -75.4,
          38.6833
        ]
      },
      "type": "Feature",
      "properties": {
        "hierarchy": [
          "tgn:2706053",
          "tgn:1002933",
          "tgn:1000001",
          "tgn:7012149",
          "tgn:7007239",
          "tgn:7029392"
        ],
        "placetype": [
          "aat:300008347"
        ],
        "id": 2706053,
        "name:xx": "Swain Acres"
      }
    },
    {
      "geometry": {
        "type": "Point",
        "coordinates": [
          -86.2667,
          39.0833
        ]
      },
      "type": "Feature",
      "properties": {
        "hierarchy": [
          "tgn:2706054",
          "tgn:1000001",
          "tgn:1002209",
          "tgn:7012149",
          "tgn:7007252",
          "tgn:7029392"
        ],
        "placetype": [
          "aat:300008699"
        ],
        "id": 2706054,
        "name:xx": "Swain Branch"
      }
    },
    {
      "geometry": {
        "type": "Point",
        "coordinates": [
          -78.0333,
          34.0667
        ]
      },
      "type": "Feature",
      "properties": {
        "hierarchy": [
          "tgn:2706055",
          "tgn:1000001",
          "tgn:2001472",
          "tgn:7012149",
          "tgn:7007709",
          "tgn:7029392"
        ],
        "placetype": [
          "aat:300008699"
        ],
        "id": 2706055,
        "name:xx": "Swain Branch"
      }
    },
    {
      "geometry": {
        "type": "Point",
        "coordinates": [
          -106.1167,
          45.7833
        ]
      },
      "type": "Feature",
      "properties": {
        "hierarchy": [
          "tgn:2706056",
          "tgn:1000001",
          "tgn:2001268",
          "tgn:7012149",
          "tgn:7007524",
          "tgn:7029392"
        ],
        "placetype": [
          "aat:300008761"
        ],
        "id": 2706056,
        "name:xx": "Swain Coulee"
      }
    },
    {
      "geometry": {
        "type": "Point",
        "coordinates": [
          -82.5,
          32.8
        ]
      },
      "type": "Feature",
      "properties": {
        "hierarchy": [
          "tgn:2706057",
          "tgn:1000001",
          "tgn:7012149",
          "tgn:7007248",
          "tgn:7029392"
        ],
        "placetype": [
          "aat:300008706"
        ],
        "id": 2706057,
        "name:xx": "Swain Creek"
      }
    },
    {
      "geometry": {
        "type": "Point",
        "coordinates": [
          -115.2,
          43.6167
        ]
      },
      "type": "Feature",
      "properties": {
        "hierarchy": [
          "tgn:2706058",
          "tgn:1000001",
          "tgn:7012149",
          "tgn:2000471",
          "tgn:7007250",
          "tgn:7029392"
        ],
        "placetype": [
          "aat:300008761"
        ],
        "id": 2706058,
        "name:xx": "Swain Gulch"
      }
    },
    {
      "geometry": {
        "type": "Point",
        "coordinates": [
          -121.4,
          39.35
        ]
      },
      "type": "Feature",
      "properties": {
        "hierarchy": [
          "tgn:2706059",
          "tgn:1000001",
          "tgn:1002218",
          "tgn:7012149",
          "tgn:7007157",
          "tgn:7029392"
        ],
        "placetype": [
          "aat:300008798"
        ],
        "id": 2706059,
        "name:xx": "Swain Hill"
      }
    }
  ]
}
