{
  "geometry": {
    "type": "Point",
    "coordinates": [
      34.1167,
      58.2667
    ]
  },
  "type": "Feature",
  "properties": {
    "hierarchy": [
      "tgn:1058000",
      "tgn:1000004",
      "tgn:4008031",
      "tgn:7018214",
      "tgn:7002435",
      "tgn:7029392"
    ],
    "placetype": [
      "aat:300008347"
    ],
    "id": 1058000,
    "name:xx": "Opechenskiy Posad"
  }
}
