{
  "geometry": {
    "type": "Point",
    "coordinates": [
      -76.7833,
      43.0167
    ]
  },
  "type": "Feature",
  "properties": {
    "hierarchy": [
      "tgn:2244618",
      "tgn:1000001",
      "tgn:7012149",
      "tgn:7014600",
      "tgn:7007568",
      "tgn:7029392"
    ],
    "placetype": [
      "aat:300006075"
    ],
    "id": 2244618,
    "name:xx": "Clintons Ditch"
  }
}
