{
  "type": "FeatureCollection",
  "features": [
    {
      "geometry": {
        "type": "Point",
        "coordinates": [
          -76.6167,
          37.8833
        ]
      },
      "type": "Feature",
      "properties": {
        "hierarchy": [
          "tgn:2111741",
          "tgn:1000001",
          "tgn:7012149",
          "tgn:7014334",
          "tgn:7007919",
          "tgn:7029392"
        ],
        "placetype": [
          "aat:300008347"
        ],
        "id": 2111741,
        "name:xx": "Farnham"
      }
    },
    {
      "geometry": {
        "type": "Point",
        "coordinates": [
          -81.1833,
          36.9667
        ]
      },
      "type": "Feature",
      "properties": {
        "hierarchy": [
          "tgn:2111743",
          "tgn:1000001",
          "tgn:7012149",
          "tgn:2002196",
          "tgn:7007919",
          "tgn:7029392"
        ],
        "placetype": [
          "aat:300008347"
        ],
        "id": 2111743,
        "name:xx": "Favonia"
      }
    },
    {
      "geometry": {
        "type": "Point",
        "coordinates": [
          -78.3,
          39.1167
        ]
      },
      "type": "Feature",
      "properties": {
        "hierarchy": [
          "tgn:2111744",
          "tgn:1000001",
          "tgn:7012149",
          "tgn:2002161",
          "tgn:7007919",
          "tgn:7029392"
        ],
        "placetype": [
          "aat:300387210",
          "aat:300386834"
        ],
        "id": 2111744,
        "name:xx": "Fawcett Gap"
      }
    },
    {
      "geometry": {
        "type": "Point",
        "coordinates": [
          -77.4167,
          37.5833
        ]
      },
      "type": "Feature",
      "properties": {
        "hierarchy": [
          "tgn:2111745",
          "tgn:1000001",
          "tgn:7012149",
          "tgn:1002467",
          "tgn:7007919",
          "tgn:7029392"
        ],
        "placetype": [
          "aat:300008347"
        ],
        "id": 2111745,
        "name:xx": "Fayette Park"
      }
    },
    {
      "geometry": {
        "type": "Point",
        "coordinates": [
          -78.0667,
          37.2167
        ]
      },
      "type": "Feature",
      "properties": {
        "hierarchy": [
          "tgn:2111749",
          "tgn:1000001",
          "tgn:7012149",
          "tgn:2002176",
          "tgn:7007919",
          "tgn:7029392"
        ],
        "placetype": [
          "aat:300008347",
          "aat:300387210"
        ],
        "id": 2111749,
        "name:xx": "Fergusonville"
      }
    }
  ]
}
