{
  "geometry": {
    "type": "Point",
    "coordinates": [
      -82.05,
      30.1833
    ]
  },
  "type": "Feature",
  "properties": {
    "hierarchy": [
      "tgn:2727675",
      "tgn:1000001",
      "tgn:7012149",
      "tgn:7007240",
      "tgn:7029392"
    ],
    "placetype": [
      "aat:300266640"
    ],
    "id": 2727675,
    "name:xx": "Trail Ridge"
  }
}
