{
  "geometry": {
    "type": "Point",
    "coordinates": [
      112.7333,
      36.6667
    ]
  },
  "type": "Feature",
  "properties": {
    "hierarchy": [
      "tgn:1071121",
      "tgn:1000004",
      "tgn:7002086",
      "tgn:1000111",
      "tgn:7029392"
    ],
    "placetype": [
      "aat:300008347"
    ],
    "id": 1071121,
    "name:xx": "Qin Xian"
  }
}
