{
  "geometry": {
    "type": "Point",
    "coordinates": [
      -87.15,
      33.5167
    ]
  },
  "type": "Feature",
  "properties": {
    "hierarchy": [
      "tgn:2351172",
      "tgn:7002659",
      "tgn:1000001",
      "tgn:7012149",
      "tgn:2000036",
      "tgn:7029392"
    ],
    "placetype": [
      "aat:300008706"
    ],
    "id": 2351172,
    "name:xx": "Glaze Creek"
  }
}
