{
  "geometry": {
    "type": "Point",
    "coordinates": [
      79.061942,
      24.203785
    ]
  },
  "type": "Feature",
  "properties": {
    "hierarchy": [
      "tgn:7566793",
      "tgn:1000004",
      "tgn:7000198",
      "tgn:1001894",
      "tgn:7029392"
    ],
    "placetype": [
      "aat:300008347"
    ],
    "name:en": "Semarāshekh",
    "id": 7566793
  }
}
