{
  "geometry": {
    "type": "Point",
    "coordinates": [
      11.6667,
      54.3333
    ]
  },
  "type": "Feature",
  "properties": {
    "hierarchy": [
      "tgn:1113424",
      "tgn:1000003",
      "tgn:7029392"
    ],
    "placetype": [
      "aat:300132316"
    ],
    "id": 1113424,
    "name:de": "Mecklenburger Bucht"
  }
}
