{
  "type": "FeatureCollection",
  "features": [
    {
      "geometry": {
        "type": "Point",
        "coordinates": [
          -121.7833,
          44.8167
        ]
      },
      "type": "Feature",
      "properties": {
        "hierarchy": [
          "tgn:2457140",
          "tgn:1000001",
          "tgn:7012149",
          "tgn:1002636",
          "tgn:7007708",
          "tgn:7029392"
        ],
        "placetype": [
          "aat:300008680"
        ],
        "id": 2457140,
        "name:xx": "Little Lake"
      }
    },
    {
      "geometry": {
        "type": "Point",
        "coordinates": [
          -117.0833,
          42.2167
        ]
      },
      "type": "Feature",
      "properties": {
        "hierarchy": [
          "tgn:2457141",
          "tgn:1000001",
          "tgn:7012149",
          "tgn:2001718",
          "tgn:7007708",
          "tgn:7029392"
        ],
        "placetype": [
          "aat:300006191"
        ],
        "id": 2457141,
        "name:xx": "Little Lake"
      }
    },
    {
      "geometry": {
        "type": "Point",
        "coordinates": [
          -75.5833,
          41.0167
        ]
      },
      "type": "Feature",
      "properties": {
        "hierarchy": [
          "tgn:2457142",
          "tgn:1000001",
          "tgn:1002233",
          "tgn:7012149",
          "tgn:7007710",
          "tgn:7029392"
        ],
        "placetype": [
          "aat:300008680"
        ],
        "id": 2457142,
        "name:xx": "Little Lake"
      }
    },
    {
      "geometry": {
        "type": "Point",
        "coordinates": [
          -80,
          33.5167
        ]
      },
      "type": "Feature",
      "properties": {
        "hierarchy": [
          "tgn:2457143",
          "tgn:1000001",
          "tgn:7012149",
          "tgn:2001769",
          "tgn:7007712",
          "tgn:7029392"
        ],
        "placetype": [
          "aat:300008680"
        ],
        "id": 2457143,
        "name:xx": "Little Lake"
      }
    },
    {
      "geometry": {
        "type": "Point",
        "coordinates": [
          -80.65,
          33.7833
        ]
      },
      "type": "Feature",
      "properties": {
        "hierarchy": [
          "tgn:2457144",
          "tgn:1000001",
          "tgn:7012149",
          "tgn:2001764",
          "tgn:7007712",
          "tgn:7029392"
        ],
        "placetype": [
          "aat:300008680"
        ],
        "id": 2457144,
        "name:xx": "Little Lake"
      }
    },
    {
      "geometry": {
        "type": "Point",
        "coordinates": [
          -80.5833,
          33.9667
        ]
      },
      "type": "Feature",
      "properties": {
        "hierarchy": [
          "tgn:2457145",
          "tgn:1000001",
          "tgn:7012149",
          "tgn:2001767",
          "tgn:7007712",
          "tgn:7029392"
        ],
        "placetype": [
          "aat:300008680"
        ],
        "id": 2457145,
        "name:xx": "Little Lake"
      }
    },
    {
      "geometry": {
        "type": "Point",
        "coordinates": [
          -89.15,
          35.4667
        ]
      },
      "type": "Feature",
      "properties": {
        "hierarchy": [
          "tgn:2457146",
          "tgn:1000001",
          "tgn:7012149",
          "tgn:2001874",
          "tgn:7007825",
          "tgn:7029392"
        ],
        "placetype": [
          "aat:300006191"
        ],
        "id": 2457146,
        "name:xx": "Little Lake"
      }
    },
    {
      "geometry": {
        "type": "Point",
        "coordinates": [
          -94.2333,
          29.7
        ]
      },
      "type": "Feature",
      "properties": {
        "hierarchy": [
          "tgn:2457147",
          "tgn:1000001",
          "tgn:7012149",
          "tgn:2002011",
          "tgn:7007826",
          "tgn:7029392"
        ],
        "placetype": [
          "aat:300008680"
        ],
        "id": 2457147,
        "name:xx": "Little Lake"
      }
    },
    {
      "geometry": {
        "type": "Point",
        "coordinates": [
          -97,
          30.3667
        ]
      },
      "type": "Feature",
      "properties": {
        "hierarchy": [
          "tgn:2457148",
          "tgn:1000001",
          "tgn:7012149",
          "tgn:1002584",
          "tgn:7007826",
          "tgn:7029392"
        ],
        "placetype": [
          "aat:300008680"
        ],
        "id": 2457148,
        "name:xx": "Little Lake"
      }
    },
    {
      "geometry": {
        "type": "Point",
        "coordinates": [
          -98.4167,
          32.5
        ]
      },
      "type": "Feature",
      "properties": {
        "hierarchy": [
          "tgn:2457149",
          "tgn:1000001",
          "tgn:7012149",
          "tgn:2001982",
          "tgn:7007826",
          "tgn:7029392"
        ],
        "placetype": [
          "aat:300008680"
        ],
        "id": 2457149,
        "name:xx": "Little Lake"
      }
    }
  ]
}
