{
  "geometry": {
    "type": "Point",
    "coordinates": [
      -78.8167,
      40.5167
    ]
  },
  "type": "Feature",
  "properties": {
    "hierarchy": [
      "tgn:2455037",
      "tgn:1000001",
      "tgn:1002225",
      "tgn:7012149",
      "tgn:7007710",
      "tgn:7029392"
    ],
    "placetype": [
      "aat:300008706"
    ],
    "id": 2455037,
    "name:xx": "Little Elk Creek"
  }
}
