{
  "geometry": {
    "type": "Point",
    "coordinates": [
      -104.3667,
      30.8833
    ]
  },
  "type": "Feature",
  "properties": {
    "hierarchy": [
      "tgn:2185145",
      "tgn:1000001",
      "tgn:7012149",
      "tgn:2002010",
      "tgn:7007826",
      "tgn:7029392"
    ],
    "placetype": [
      "aat:300008761"
    ],
    "id": 2185145,
    "name:xx": "Boggy Canyon"
  }
}
