{
  "geometry": {
    "type": "Point",
    "coordinates": [
      -110.0333,
      40.65
    ]
  },
  "type": "Feature",
  "properties": {
    "hierarchy": [
      "tgn:2323165",
      "tgn:1000001",
      "tgn:7012149",
      "tgn:7007827",
      "tgn:7029392"
    ],
    "placetype": [
      "aat:300008706"
    ],
    "id": 2323165,
    "name:xx": "Farm Creek"
  }
}
