{
  "geometry": {
    "type": "Point",
    "coordinates": [
      -92.25,
      37.2167
    ]
  },
  "type": "Feature",
  "properties": {
    "hierarchy": [
      "tgn:2594295",
      "tgn:1000001",
      "tgn:7012149",
      "tgn:2001258",
      "tgn:7007523",
      "tgn:7029392"
    ],
    "placetype": [
      "aat:300006191"
    ],
    "id": 2594295,
    "name:xx": "Porter Lake"
  }
}
