{
  "geometry": {
    "type": "Point",
    "coordinates": [
      -54.5667,
      -28.1333
    ]
  },
  "type": "Feature",
  "properties": {
    "hierarchy": [
      "tgn:1021540",
      "tgn:1001941",
      "tgn:1000047",
      "tgn:7002458",
      "tgn:1000002",
      "tgn:7029392"
    ],
    "placetype": [
      "aat:300008347"
    ],
    "id": 1021540,
    "name:xx": "Guarani das Missões"
  }
}
