{
  "geometry": {
    "type": "Point",
    "coordinates": [
      -89.7833,
      35.9333
    ]
  },
  "type": "Feature",
  "properties": {
    "hierarchy": [
      "tgn:2551825",
      "tgn:1000001",
      "tgn:7016172",
      "tgn:7012149",
      "tgn:2000151",
      "tgn:7029392"
    ],
    "placetype": [
      "aat:300006075"
    ],
    "id": 2551825,
    "name:xx": "Number 76, Ditch"
  }
}
