{
  "geometry": {
    "type": "Point",
    "coordinates": [
      25.15,
      37.633333
    ]
  },
  "type": "Feature",
  "properties": {
    "hierarchy": [
      "tgn:7228285",
      "tgn:7011270",
      "tgn:7002674",
      "tgn:1000003",
      "tgn:1000074",
      "tgn:7029392"
    ],
    "placetype": [
      "aat:300132316"
    ],
    "id": 7228285,
    "name:xx": "Kolimvíthra, Órmos"
  }
}
