{
  "type": "FeatureCollection",
  "features": [
    {
      "geometry": {
        "type": "Point",
        "coordinates": [
          -76.2833,
          42.4333
        ]
      },
      "type": "Feature",
      "properties": {
        "hierarchy": [
          "tgn:2691510",
          "tgn:1000001",
          "tgn:7012149",
          "tgn:1002950",
          "tgn:7007568",
          "tgn:7029392"
        ],
        "placetype": [
          "aat:300008798"
        ],
        "id": 2691510,
        "name:xx": "Star Stanton Hill"
      }
    },
    {
      "geometry": {
        "type": "Point",
        "coordinates": [
          -120.6,
          39.1167
        ]
      },
      "type": "Feature",
      "properties": {
        "hierarchy": [
          "tgn:2691511",
          "tgn:1000001",
          "tgn:7012149",
          "tgn:7007157",
          "tgn:1002791",
          "tgn:7029392"
        ],
        "placetype": [
          "aat:300000390"
        ],
        "id": 2691511,
        "name:xx": "Star Town Mine"
      }
    },
    {
      "geometry": {
        "type": "Point",
        "coordinates": [
          -105.55,
          39.7167
        ]
      },
      "type": "Feature",
      "properties": {
        "hierarchy": [
          "tgn:2691512",
          "tgn:1000001",
          "tgn:2000201",
          "tgn:7012149",
          "tgn:7007158",
          "tgn:7029392"
        ],
        "placetype": [
          "aat:300000390"
        ],
        "id": 2691512,
        "name:xx": "Star Tunnel"
      }
    },
    {
      "geometry": {
        "type": "Point",
        "coordinates": [
          -111.45,
          40.6
        ]
      },
      "type": "Feature",
      "properties": {
        "hierarchy": [
          "tgn:2691513",
          "tgn:1000001",
          "tgn:7012149",
          "tgn:2002126",
          "tgn:7007827",
          "tgn:7029392"
        ],
        "placetype": [
          "aat:300000390"
        ],
        "id": 2691513,
        "name:xx": "Star Tunnel"
      }
    },
    {
      "geometry": {
        "type": "Point",
        "coordinates": [
          -111.2333,
          34.2333
        ]
      },
      "type": "Feature",
      "properties": {
        "hierarchy": [
          "tgn:2691514",
          "tgn:1000001",
          "tgn:7006451",
          "tgn:2000093",
          "tgn:7012149",
          "tgn:7029392"
        ],
        "placetype": [
          "aat:300008761"
        ],
        "id": 2691514,
        "name:xx": "Star Valley"
      }
    },
    {
      "geometry": {
        "type": "Point",
        "coordinates": [
          -122.5167,
          39.2333
        ]
      },
      "type": "Feature",
      "properties": {
        "hierarchy": [
          "tgn:2691515",
          "tgn:1000001",
          "tgn:7012149",
          "tgn:1002296",
          "tgn:7007157",
          "tgn:7029392"
        ],
        "placetype": [
          "aat:300386845"
        ],
        "id": 2691515,
        "name:xx": "Star Valley"
      }
    },
    {
      "geometry": {
        "type": "Point",
        "coordinates": [
          -116.95,
          42.0333
        ]
      },
      "type": "Feature",
      "properties": {
        "hierarchy": [
          "tgn:2691516",
          "tgn:1000001",
          "tgn:7012149",
          "tgn:2000488",
          "tgn:7007250",
          "tgn:7029392"
        ],
        "placetype": [
          "aat:300008761"
        ],
        "id": 2691516,
        "name:xx": "Star Valley"
      }
    },
    {
      "geometry": {
        "type": "Point",
        "coordinates": [
          -99.8833,
          34.6
        ]
      },
      "type": "Feature",
      "properties": {
        "hierarchy": [
          "tgn:2691517",
          "tgn:1000001",
          "tgn:2001651",
          "tgn:7012149",
          "tgn:7007707",
          "tgn:7029392"
        ],
        "placetype": [
          "aat:300008761"
        ],
        "id": 2691517,
        "name:xx": "Star Valley"
      }
    },
    {
      "geometry": {
        "type": "Point",
        "coordinates": [
          -89.9167,
          42.9333
        ]
      },
      "type": "Feature",
      "properties": {
        "hierarchy": [
          "tgn:2691518",
          "tgn:1000001",
          "tgn:7012149",
          "tgn:2002326",
          "tgn:7007922",
          "tgn:7029392"
        ],
        "placetype": [
          "aat:300008761"
        ],
        "id": 2691518,
        "name:xx": "Star Valley"
      }
    },
    {
      "geometry": {
        "type": "Point",
        "coordinates": [
          -110.9,
          42.5833
        ]
      },
      "type": "Feature",
      "properties": {
        "hierarchy": [
          "tgn:2691519",
          "tgn:1000001",
          "tgn:7012149",
          "tgn:2002376",
          "tgn:7007923",
          "tgn:7029392"
        ],
        "placetype": [
          "aat:300008761"
        ],
        "id": 2691519,
        "name:xx": "Star Valley"
      }
    }
  ]
}
