{
  "geometry": {
    "type": "Point",
    "coordinates": [
      -108.1667,
      31.7833
    ]
  },
  "type": "Feature",
  "properties": {
    "hierarchy": [
      "tgn:2413300",
      "tgn:1000001",
      "tgn:7012149",
      "tgn:2001444",
      "tgn:7007566",
      "tgn:7029392"
    ],
    "placetype": [
      "aat:300006191"
    ],
    "id": 2413300,
    "name:xx": "International Tank"
  }
}
