{
  "geometry": {
    "type": "Point",
    "coordinates": [
      -120.15,
      38.5333
    ]
  },
  "type": "Feature",
  "properties": {
    "hierarchy": [
      "tgn:2661631",
      "tgn:1002146",
      "tgn:1000001",
      "tgn:7012149",
      "tgn:7007157",
      "tgn:7029392"
    ],
    "placetype": [
      "aat:300008680"
    ],
    "id": 2661631,
    "name:xx": "Shriner Lake"
  }
}
