{
  "geometry": {
    "type": "Point",
    "coordinates": [
      -76.9333,
      37.0333
    ]
  },
  "type": "Feature",
  "properties": {
    "hierarchy": [
      "tgn:2111462",
      "tgn:1000001",
      "tgn:7012149",
      "tgn:1002931",
      "tgn:7007919",
      "tgn:7029392"
    ],
    "placetype": [
      "aat:300008347"
    ],
    "id": 2111462,
    "name:xx": "Dendron"
  }
}
