{
  "geometry": {
    "type": "Point",
    "coordinates": [
      -79.85,
      34.2833
    ]
  },
  "type": "Feature",
  "properties": {
    "hierarchy": [
      "tgn:2189702",
      "tgn:1000001",
      "tgn:2001740",
      "tgn:7012149",
      "tgn:7007712",
      "tgn:7029392"
    ],
    "placetype": [
      "aat:300008347"
    ],
    "id": 2189702,
    "name:xx": "Bowens Manor"
  }
}
