{
  "type": "FeatureCollection",
  "features": [
    {
      "geometry": {
        "type": "Point",
        "coordinates": [
          9.8,
          44.066667
        ]
      },
      "type": "Feature",
      "properties": {
        "hierarchy": [
          "tgn:7046090",
          "tgn:1000003",
          "tgn:7003143",
          "tgn:7003236",
          "tgn:1000080",
          "tgn:7029392"
        ],
        "placetype": [
          "aat:300008347"
        ],
        "id": 7046090,
        "name:xx": "Campiglia"
      }
    },
    {
      "geometry": {
        "type": "Point",
        "coordinates": [
          9.566667,
          46.116667
        ]
      },
      "type": "Feature",
      "properties": {
        "hierarchy": [
          "tgn:7046094",
          "tgn:1000003",
          "tgn:7003152",
          "tgn:7003237",
          "tgn:1000080",
          "tgn:7029392"
        ],
        "placetype": [
          "aat:300008347"
        ],
        "id": 7046094,
        "name:xx": "Campiano"
      }
    },
    {
      "geometry": {
        "type": "Point",
        "coordinates": [
          16.2,
          41.816667
        ]
      },
      "type": "Feature",
      "properties": {
        "hierarchy": [
          "tgn:7046096",
          "tgn:1003455",
          "tgn:1000003",
          "tgn:7010380",
          "tgn:1000080",
          "tgn:7029392"
        ],
        "placetype": [
          "aat:300004847"
        ],
        "id": 7046096,
        "name:xx": "Torre di Campi"
      }
    },
    {
      "geometry": {
        "type": "Point",
        "coordinates": [
          16.2,
          41.816667
        ]
      },
      "type": "Feature",
      "properties": {
        "hierarchy": [
          "tgn:7046097",
          "tgn:1003455",
          "tgn:1000003",
          "tgn:7010380",
          "tgn:1000080",
          "tgn:7029392"
        ],
        "placetype": [
          "aat:300008791"
        ],
        "id": 7046097,
        "name:xx": "Campi, Isola di"
      }
    },
    {
      "geometry": {
        "type": "Point",
        "coordinates": [
          11.183333,
          45.866667
        ]
      },
      "type": "Feature",
      "properties": {
        "hierarchy": [
          "tgn:7046098",
          "tgn:7003158",
          "tgn:1000003",
          "tgn:7003124",
          "tgn:1000080",
          "tgn:7029392"
        ],
        "placetype": [
          "aat:300008347"
        ],
        "id": 7046098,
        "name:xx": "Campi"
      }
    },
    {
      "geometry": {
        "type": "Point",
        "coordinates": [
          9.716667,
          44.466667
        ]
      },
      "type": "Feature",
      "properties": {
        "hierarchy": [
          "tgn:7046099",
          "tgn:7003131",
          "tgn:1000003",
          "tgn:7008516",
          "tgn:1000080",
          "tgn:7029392"
        ],
        "placetype": [
          "aat:300008347"
        ],
        "id": 7046099,
        "name:xx": "Campi"
      }
    }
  ]
}
