{
  "geometry": {
    "type": "Point",
    "coordinates": [
      -78.4667,
      34.75
    ]
  },
  "type": "Feature",
  "properties": {
    "hierarchy": [
      "tgn:2410417",
      "tgn:1000001",
      "tgn:2001471",
      "tgn:7012149",
      "tgn:7007709",
      "tgn:7029392"
    ],
    "placetype": [
      "aat:300008905"
    ],
    "id": 2410417,
    "name:xx": "Indian Camp Bay"
  }
}
