{
  "geometry": {
    "type": "Point",
    "coordinates": [
      -72.1167,
      42.75
    ]
  },
  "type": "Feature",
  "properties": {
    "hierarchy": [
      "tgn:2696592",
      "tgn:7019618",
      "tgn:1000001",
      "tgn:7012149",
      "tgn:7007564",
      "tgn:7029392"
    ],
    "placetype": [
      "aat:300008680"
    ],
    "id": 2696592,
    "name:xx": "Stone Pond"
  }
}
