{
  "geometry": {
    "type": "Point",
    "coordinates": [
      -97.6333,
      32.7833
    ]
  },
  "type": "Feature",
  "properties": {
    "hierarchy": [
      "tgn:2495479",
      "tgn:1000001",
      "tgn:7012149",
      "tgn:7007826",
      "tgn:7029392"
    ],
    "placetype": [
      "aat:300008706"
    ],
    "id": 2495479,
    "name:xx": "Marys Creek"
  }
}
