{
  "geometry": {
    "type": "Point",
    "coordinates": [
      -74.9333,
      40.65
    ]
  },
  "type": "Feature",
  "properties": {
    "hierarchy": [
      "tgn:1102485",
      "tgn:1000001",
      "tgn:1002493",
      "tgn:7012149",
      "tgn:7007565",
      "tgn:7029392"
    ],
    "placetype": [
      "aat:300008192"
    ],
    "id": 1102485,
    "name:xx": "Spruce Run State Park"
  }
}
