{
  "type": "FeatureCollection",
  "features": [
    {
      "geometry": {
        "type": "Point",
        "coordinates": [
          2.558458,
          41.747716
        ]
      },
      "type": "Feature",
      "properties": {
        "hierarchy": [
          "tgn:7341231",
          "tgn:7002820",
          "tgn:7030216",
          "tgn:1000003",
          "tgn:1000095",
          "tgn:7029392"
        ],
        "placetype": [
          "aat:300008347"
        ],
        "id": 7341231,
        "name:xx": "Breda"
      }
    },
    {
      "geometry": {
        "type": "Point",
        "coordinates": [
          -5.8,
          36.433333
        ]
      },
      "type": "Feature",
      "properties": {
        "hierarchy": [
          "tgn:7341232",
          "tgn:7002813",
          "tgn:7002758",
          "tgn:1000003",
          "tgn:1000095",
          "tgn:7029392"
        ],
        "placetype": [
          "aat:300008699"
        ],
        "id": 7341232,
        "name:xx": "Brecial, Arroyo del"
      }
    },
    {
      "geometry": {
        "type": "Point",
        "coordinates": [
          -5.383333,
          43.45
        ]
      },
      "type": "Feature",
      "properties": {
        "hierarchy": [
          "tgn:7341233",
          "tgn:7008911",
          "tgn:1000003",
          "tgn:7002763",
          "tgn:1000095",
          "tgn:7029392"
        ],
        "placetype": [
          "aat:300008347"
        ],
        "id": 7341233,
        "name:xx": "Breceña"
      }
    },
    {
      "geometry": {
        "type": "Point",
        "coordinates": [
          -8.183333,
          43.4
        ]
      },
      "type": "Feature",
      "properties": {
        "hierarchy": [
          "tgn:7341234",
          "tgn:7002824",
          "tgn:1000003",
          "tgn:7002786",
          "tgn:1000095",
          "tgn:7029392"
        ],
        "placetype": [
          "aat:300008347"
        ],
        "id": 7341234,
        "name:xx": "Breamo"
      }
    },
    {
      "geometry": {
        "type": "Point",
        "coordinates": [
          -3.1,
          40.233333
        ]
      },
      "type": "Feature",
      "properties": {
        "hierarchy": [
          "tgn:7341235",
          "tgn:7010420",
          "tgn:1000003",
          "tgn:7002795",
          "tgn:1000095",
          "tgn:7029392"
        ],
        "placetype": [
          "aat:300008347"
        ],
        "id": 7341235,
        "name:xx": "Brea de Tajo"
      }
    },
    {
      "geometry": {
        "type": "Point",
        "coordinates": [
          -1.6,
          41.533333
        ]
      },
      "type": "Feature",
      "properties": {
        "hierarchy": [
          "tgn:7341236",
          "tgn:7002759",
          "tgn:7002845",
          "tgn:1000003",
          "tgn:1000095",
          "tgn:7029392"
        ],
        "placetype": [
          "aat:300008347"
        ],
        "id": 7341236,
        "name:xx": "Brea de Aragón"
      }
    },
    {
      "geometry": {
        "type": "Point",
        "coordinates": [
          -3.066667,
          40.183333
        ]
      },
      "type": "Feature",
      "properties": {
        "hierarchy": [
          "tgn:7341237",
          "tgn:7002822",
          "tgn:1001647",
          "tgn:1000003",
          "tgn:1000095",
          "tgn:7029392"
        ],
        "placetype": [
          "aat:300008699"
        ],
        "id": 7341237,
        "name:xx": "Brea, Arroyo de"
      }
    },
    {
      "geometry": {
        "type": "Point",
        "coordinates": [
          -9.133333,
          43.15
        ]
      },
      "type": "Feature",
      "properties": {
        "hierarchy": [
          "tgn:7341238",
          "tgn:7002824",
          "tgn:1000003",
          "tgn:7002786",
          "tgn:1000095",
          "tgn:7029392"
        ],
        "placetype": [
          "aat:300008347"
        ],
        "id": 7341238,
        "name:xx": "Brea"
      }
    },
    {
      "geometry": {
        "type": "Point",
        "coordinates": [
          -6.15,
          42.5
        ]
      },
      "type": "Feature",
      "properties": {
        "hierarchy": [
          "tgn:7341239",
          "tgn:7002826",
          "tgn:7001158",
          "tgn:1000003",
          "tgn:1000095",
          "tgn:7029392"
        ],
        "placetype": [
          "aat:300008347"
        ],
        "id": 7341239,
        "name:xx": "Brazuelo"
      }
    }
  ]
}
