{
  "geometry": {
    "type": "Point",
    "coordinates": [
      5.7333,
      46.3667
    ]
  },
  "type": "Feature",
  "properties": {
    "hierarchy": [
      "tgn:1036034",
      "tgn:1000003",
      "tgn:7002881",
      "tgn:1000070",
      "tgn:7029392"
    ],
    "placetype": [
      "aat:300008347"
    ],
    "id": 1036034,
    "name:xx": "Vaux-lès-Saint-Claude"
  }
}
