{
  "geometry": {
    "type": "Point",
    "coordinates": [
      -76.7333,
      38.0833
    ]
  },
  "type": "Feature",
  "properties": {
    "hierarchy": [
      "tgn:2542986",
      "tgn:1000001",
      "tgn:7012149",
      "tgn:1003018",
      "tgn:7007919",
      "tgn:7029392"
    ],
    "placetype": [
      "aat:300008347"
    ],
    "id": 2542986,
    "name:xx": "Nomini"
  }
}
