{
  "geometry": {
    "type": "Point",
    "coordinates": [
      -120.0167,
      44.1333
    ]
  },
  "type": "Feature",
  "properties": {
    "hierarchy": [
      "tgn:2590990",
      "tgn:1000001",
      "tgn:2001703",
      "tgn:7012149",
      "tgn:7007708",
      "tgn:7029392"
    ],
    "placetype": [
      "aat:300006191"
    ],
    "id": 2590990,
    "name:xx": "Poley Reservoir"
  }
}
