{
  "geometry": {
    "type": "Point",
    "coordinates": [
      -72.4667,
      43.7167
    ]
  },
  "type": "Feature",
  "properties": {
    "hierarchy": [
      "tgn:2109880",
      "tgn:1000001",
      "tgn:2002136",
      "tgn:7012149",
      "tgn:7007828",
      "tgn:7029392"
    ],
    "placetype": [
      "aat:300008347"
    ],
    "id": 2109880,
    "name:xx": "North Pomfret"
  }
}
