{
  "geometry": {
    "type": "Point",
    "coordinates": [
      -121.45,
      47.6333
    ]
  },
  "type": "Feature",
  "properties": {
    "hierarchy": [
      "tgn:2243762",
      "tgn:1000001",
      "tgn:7012149",
      "tgn:7018871",
      "tgn:7007920",
      "tgn:7029392"
    ],
    "placetype": [
      "aat:300000390"
    ],
    "id": 2243762,
    "name:xx": "Cleopatra Mine"
  }
}
