{
  "geometry": {
    "type": "Point",
    "coordinates": [
      -72.0833,
      41.9833
    ]
  },
  "type": "Feature",
  "properties": {
    "hierarchy": [
      "tgn:2486477",
      "tgn:1000001",
      "tgn:7012149",
      "tgn:7029392"
    ],
    "placetype": [
      "aat:300008699"
    ],
    "id": 2486477,
    "name:xx": "Lebanon Brook"
  }
}
