{
  "geometry": {
    "type": "Point",
    "coordinates": [
      104.45,
      20.55
    ]
  },
  "type": "Feature",
  "properties": {
    "hierarchy": [
      "tgn:1082551",
      "tgn:7000843",
      "tgn:1000004",
      "tgn:1000125",
      "tgn:7029392"
    ],
    "placetype": [
      "aat:300008347"
    ],
    "id": 1082551,
    "name:xx": "Sop Hao"
  }
}
