{
  "geometry": {
    "type": "Point",
    "coordinates": [
      -83.45,
      37.1667
    ]
  },
  "type": "Feature",
  "properties": {
    "hierarchy": [
      "tgn:2259599",
      "tgn:1000001",
      "tgn:7012149",
      "tgn:2000811",
      "tgn:7007255",
      "tgn:7029392"
    ],
    "placetype": [
      "aat:300008699"
    ],
    "id": 2259599,
    "name:xx": "Couch Branch"
  }
}
