{
  "geometry": {
    "type": "Point",
    "coordinates": [
      -109.7333,
      36.8833
    ]
  },
  "type": "Feature",
  "properties": {
    "hierarchy": [
      "tgn:1132804",
      "tgn:1000001",
      "tgn:7012149",
      "tgn:7029392"
    ],
    "placetype": [
      "aat:300008706"
    ],
    "id": 1132804,
    "name:xx": "Chinle Creek"
  }
}
