{
  "type": "FeatureCollection",
  "features": [
    {
      "geometry": {
        "type": "Point",
        "coordinates": [
          -84.5,
          34.3
        ]
      },
      "type": "Feature",
      "properties": {
        "hierarchy": [
          "tgn:2212550",
          "tgn:1000001",
          "tgn:2000319",
          "tgn:7012149",
          "tgn:7007248",
          "tgn:7029392"
        ],
        "placetype": [
          "aat:300008706"
        ],
        "id": 2212550,
        "name:xx": "Byrd Creek"
      }
    },
    {
      "geometry": {
        "type": "Point",
        "coordinates": [
          -88.6667,
          36.8
        ]
      },
      "type": "Feature",
      "properties": {
        "hierarchy": [
          "tgn:2212551",
          "tgn:1000001",
          "tgn:7012149",
          "tgn:2000792",
          "tgn:7007255",
          "tgn:7029392"
        ],
        "placetype": [
          "aat:300008706"
        ],
        "id": 2212551,
        "name:xx": "Byrd Creek"
      }
    },
    {
      "geometry": {
        "type": "Point",
        "coordinates": [
          -88.4333,
          31.2667
        ]
      },
      "type": "Feature",
      "properties": {
        "hierarchy": [
          "tgn:2212552",
          "tgn:1000001",
          "tgn:7012149",
          "tgn:7029392"
        ],
        "placetype": [
          "aat:300008706"
        ],
        "id": 2212552,
        "name:xx": "Byrd Creek"
      }
    },
    {
      "geometry": {
        "type": "Point",
        "coordinates": [
          -89.7167,
          37.5
        ]
      },
      "type": "Feature",
      "properties": {
        "hierarchy": [
          "tgn:2212553",
          "tgn:1000001",
          "tgn:2001179",
          "tgn:7012149",
          "tgn:7007523",
          "tgn:7029392"
        ],
        "placetype": [
          "aat:300008706"
        ],
        "id": 2212553,
        "name:xx": "Byrd Creek"
      }
    },
    {
      "geometry": {
        "type": "Point",
        "coordinates": [
          -82.1333,
          33.9
        ]
      },
      "type": "Feature",
      "properties": {
        "hierarchy": [
          "tgn:2212554",
          "tgn:1000001",
          "tgn:7012149",
          "tgn:7007712",
          "tgn:7029392"
        ],
        "placetype": [
          "aat:300008706"
        ],
        "id": 2212554,
        "name:xx": "Byrd Creek"
      }
    },
    {
      "geometry": {
        "type": "Point",
        "coordinates": [
          -83.0833,
          36.4667
        ]
      },
      "type": "Feature",
      "properties": {
        "hierarchy": [
          "tgn:2212555",
          "tgn:1000001",
          "tgn:7012149",
          "tgn:2001873",
          "tgn:7007825",
          "tgn:7029392"
        ],
        "placetype": [
          "aat:300008706"
        ],
        "id": 2212555,
        "name:xx": "Byrd Creek"
      }
    },
    {
      "geometry": {
        "type": "Point",
        "coordinates": [
          -85.0667,
          35.9
        ]
      },
      "type": "Feature",
      "properties": {
        "hierarchy": [
          "tgn:2212556",
          "tgn:1000001",
          "tgn:7012149",
          "tgn:2001854",
          "tgn:7007825",
          "tgn:7029392"
        ],
        "placetype": [
          "aat:300008706"
        ],
        "id": 2212556,
        "name:xx": "Byrd Creek"
      }
    },
    {
      "geometry": {
        "type": "Point",
        "coordinates": [
          -87.9833,
          36.6
        ]
      },
      "type": "Feature",
      "properties": {
        "hierarchy": [
          "tgn:2212557",
          "tgn:1000001",
          "tgn:7012149",
          "tgn:2001917",
          "tgn:7007825",
          "tgn:7029392"
        ],
        "placetype": [
          "aat:300008706"
        ],
        "id": 2212557,
        "name:xx": "Byrd Creek"
      }
    },
    {
      "geometry": {
        "type": "Point",
        "coordinates": [
          -78.15,
          37.85
        ]
      },
      "type": "Feature",
      "properties": {
        "hierarchy": [
          "tgn:2212558",
          "tgn:1000001",
          "tgn:7012149",
          "tgn:7007919",
          "tgn:7029392"
        ],
        "placetype": [
          "aat:300008706"
        ],
        "id": 2212558,
        "name:xx": "Byrd Creek"
      }
    },
    {
      "geometry": {
        "type": "Point",
        "coordinates": [
          -85.0333,
          35.8833
        ]
      },
      "type": "Feature",
      "properties": {
        "hierarchy": [
          "tgn:2212559",
          "tgn:1000001",
          "tgn:7012149",
          "tgn:2001854",
          "tgn:7007825",
          "tgn:7029392"
        ],
        "placetype": [
          "aat:300006191"
        ],
        "id": 2212559,
        "name:xx": "Byrd Creek Lake"
      }
    }
  ]
}
