{
  "geometry": {
    "type": "Point",
    "coordinates": [
      -122.35,
      43.7833
    ]
  },
  "type": "Feature",
  "properties": {
    "hierarchy": [
      "tgn:2590307",
      "tgn:1000001",
      "tgn:7012149",
      "tgn:2001716",
      "tgn:7007708",
      "tgn:7029392"
    ],
    "placetype": [
      "aat:300008706"
    ],
    "id": 2590307,
    "name:xx": "Polallie Creek"
  }
}
