{
  "geometry": {
    "type": "Point",
    "coordinates": [
      -114.1333,
      39.2667
    ]
  },
  "type": "Feature",
  "properties": {
    "hierarchy": [
      "tgn:2374332",
      "tgn:1000001",
      "tgn:7012149",
      "tgn:7029392"
    ],
    "placetype": [
      "aat:300008706"
    ],
    "id": 2374332,
    "name:xx": "Hampton Creek"
  }
}
