{
  "geometry": {
    "type": "Point",
    "coordinates": [
      55.2833,
      49.4167
    ]
  },
  "type": "Feature",
  "properties": {
    "hierarchy": [
      "tgn:1059109",
      "tgn:7011450",
      "tgn:1000004",
      "tgn:7014786",
      "tgn:7029392"
    ],
    "placetype": [
      "aat:300008347"
    ],
    "id": 1059109,
    "name:xx": "Saga"
  }
}
