{
  "geometry": {
    "type": "Point",
    "coordinates": [
      -119.45,
      38.0167
    ]
  },
  "type": "Feature",
  "properties": {
    "hierarchy": [
      "tgn:2654969",
      "tgn:1000001",
      "tgn:7012149",
      "tgn:7007157",
      "tgn:1002957",
      "tgn:7029392"
    ],
    "placetype": [
      "aat:300008680"
    ],
    "id": 2654969,
    "name:xx": "Shamrock Lake"
  }
}
