{
  "geometry": {
    "type": "Point",
    "coordinates": [
      -72.25,
      41.0333
    ]
  },
  "type": "Feature",
  "properties": {
    "hierarchy": [
      "tgn:2147585",
      "tgn:1000001",
      "tgn:7012149",
      "tgn:1002924",
      "tgn:7007568",
      "tgn:7029392"
    ],
    "placetype": [
      "aat:300132348"
    ],
    "id": 2147585,
    "name:xx": "Barcelona Bank"
  }
}
