{
  "geometry": {
    "type": "Point",
    "coordinates": [
      -79.2167,
      39.2667
    ]
  },
  "type": "Feature",
  "properties": {
    "hierarchy": [
      "tgn:2423937",
      "tgn:1000001",
      "tgn:2002263",
      "tgn:7012149",
      "tgn:7013961",
      "tgn:7029392"
    ],
    "placetype": [
      "aat:300008699"
    ],
    "id": 2423937,
    "name:xx": "Johnnycake Run"
  }
}
