{
  "geometry": {
    "type": "Point",
    "coordinates": [
      -70.1167,
      41.85
    ]
  },
  "type": "Feature",
  "properties": {
    "hierarchy": [
      "tgn:2172643",
      "tgn:1002165",
      "tgn:1000001",
      "tgn:7012149",
      "tgn:7007517",
      "tgn:7029392"
    ],
    "placetype": [
      "aat:300132348"
    ],
    "id": 2172643,
    "name:xx": "Billingsgate Shoal"
  }
}
