{
  "type": "FeatureCollection",
  "features": [
    {
      "geometry": {
        "type": "Point",
        "coordinates": [
          151.1,
          -34.0333
        ]
      },
      "type": "Feature",
      "properties": {
        "hierarchy": [
          "tgn:1097570",
          "tgn:7000490",
          "tgn:1000006",
          "tgn:7001828",
          "tgn:7029392"
        ],
        "placetype": [
          "aat:300008347"
        ],
        "id": 1097570,
        "name:xx": "Miranda"
      }
    },
    {
      "geometry": {
        "type": "Point",
        "coordinates": [
          146.15,
          -38.4
        ]
      },
      "type": "Feature",
      "properties": {
        "hierarchy": [
          "tgn:1097571",
          "tgn:7000490",
          "tgn:1000006",
          "tgn:7006238",
          "tgn:7029392"
        ],
        "placetype": [
          "aat:300008347"
        ],
        "id": 1097571,
        "name:xx": "Mirboo North"
      }
    },
    {
      "geometry": {
        "type": "Point",
        "coordinates": [
          151.5667,
          -24.2833
        ]
      },
      "type": "Feature",
      "properties": {
        "hierarchy": [
          "tgn:1097572",
          "tgn:7000490",
          "tgn:1000006",
          "tgn:7001830",
          "tgn:7029392"
        ],
        "placetype": [
          "aat:300008347"
        ],
        "id": 1097572,
        "name:xx": "Miriam Vale"
      }
    },
    {
      "geometry": {
        "type": "Point",
        "coordinates": [
          129.0667,
          -17.1333
        ]
      },
      "type": "Feature",
      "properties": {
        "hierarchy": [
          "tgn:1097573",
          "tgn:7000490",
          "tgn:1000006",
          "tgn:7001829",
          "tgn:7029392"
        ],
        "placetype": [
          "aat:300008347"
        ],
        "id": 1097573,
        "name:xx": "Mistake Creek"
      }
    },
    {
      "geometry": {
        "type": "Point",
        "coordinates": [
          138.6,
          -34.9833
        ]
      },
      "type": "Feature",
      "properties": {
        "hierarchy": [
          "tgn:1097574",
          "tgn:7000490",
          "tgn:1000006",
          "tgn:7001831",
          "tgn:7029392"
        ],
        "placetype": [
          "aat:300008347",
          "aat:300000874"
        ],
        "id": 1097574,
        "name:xx": "Mitcham"
      }
    },
    {
      "geometry": {
        "type": "Point",
        "coordinates": [
          147.9333,
          -26.5
        ]
      },
      "type": "Feature",
      "properties": {
        "hierarchy": [
          "tgn:1097575",
          "tgn:7000490",
          "tgn:1000006",
          "tgn:7001830",
          "tgn:7029392"
        ],
        "placetype": [
          "aat:300008347"
        ],
        "id": 1097575,
        "name:xx": "Mitchell"
      }
    },
    {
      "geometry": {
        "type": "Point",
        "coordinates": [
          141.6667,
          -15.5
        ]
      },
      "type": "Feature",
      "properties": {
        "hierarchy": [
          "tgn:1097576",
          "tgn:7000490",
          "tgn:1000006",
          "tgn:7001830",
          "tgn:7029392"
        ],
        "placetype": [
          "aat:300008347"
        ],
        "id": 1097576,
        "name:xx": "Mitchell River Mission"
      }
    },
    {
      "geometry": {
        "type": "Point",
        "coordinates": [
          150.4167,
          -34.45
        ]
      },
      "type": "Feature",
      "properties": {
        "hierarchy": [
          "tgn:1097577",
          "tgn:7000490",
          "tgn:1000006",
          "tgn:7001828",
          "tgn:7029392"
        ],
        "placetype": [
          "aat:300008347"
        ],
        "id": 1097577,
        "name:xx": "Mittagong"
      }
    },
    {
      "geometry": {
        "type": "Point",
        "coordinates": [
          144.8333,
          -36.1333
        ]
      },
      "type": "Feature",
      "properties": {
        "hierarchy": [
          "tgn:1097578",
          "tgn:7000490",
          "tgn:1000006",
          "tgn:7001828",
          "tgn:7029392"
        ],
        "placetype": [
          "aat:300008347"
        ],
        "id": 1097578,
        "name:xx": "Moama"
      }
    },
    {
      "geometry": {
        "type": "Point",
        "coordinates": [
          138.4833,
          -35.2
        ]
      },
      "type": "Feature",
      "properties": {
        "hierarchy": [
          "tgn:1097579",
          "tgn:7000490",
          "tgn:1000006",
          "tgn:7001831",
          "tgn:7029392"
        ],
        "placetype": [
          "aat:300008347"
        ],
        "id": 1097579,
        "name:xx": "Moana"
      }
    }
  ]
}
