{
  "geometry": {
    "type": "Point",
    "coordinates": [
      -121.8833,
      36.2833
    ]
  },
  "type": "Feature",
  "properties": {
    "hierarchy": [
      "tgn:2705301",
      "tgn:1000001",
      "tgn:7012149",
      "tgn:7007157",
      "tgn:1002684",
      "tgn:7029392"
    ],
    "placetype": [
      "aat:300055621"
    ],
    "id": 2705301,
    "name:xx": "Sur Breakers"
  }
}
