{
  "geometry": {
    "type": "Point",
    "coordinates": [
      30.65,
      -28.35
    ]
  },
  "type": "Feature",
  "properties": {
    "hierarchy": [
      "tgn:7000806",
      "tgn:7001242",
      "tgn:7016749",
      "tgn:1000193",
      "tgn:7029392"
    ],
    "placetype": [
      "aat:300000833"
    ],
    "id": 7000806,
    "name:xx": "Isandhlwana"
  }
}
