{
  "geometry": {
    "type": "Point",
    "coordinates": [
      9.4667,
      54.85
    ]
  },
  "type": "Feature",
  "properties": {
    "hierarchy": [
      "tgn:1027980",
      "tgn:1000003",
      "tgn:7594009",
      "tgn:1000066",
      "tgn:7029392"
    ],
    "placetype": [
      "aat:300008347"
    ],
    "id": 1027980,
    "name:xx": "Kruså"
  }
}
