{
  "type": "FeatureCollection",
  "features": [
    {
      "geometry": {
        "type": "Point",
        "coordinates": [
          -94.65,
          35.5333
        ]
      },
      "type": "Feature",
      "properties": {
        "hierarchy": [
          "tgn:2228470",
          "tgn:1000001",
          "tgn:7012149",
          "tgn:2001690",
          "tgn:7007707",
          "tgn:7029392"
        ],
        "placetype": [
          "aat:300008706"
        ],
        "id": 2228470,
        "name:xx": "Cedar Creek"
      }
    },
    {
      "geometry": {
        "type": "Point",
        "coordinates": [
          -98.3167,
          35.8833
        ]
      },
      "type": "Feature",
      "properties": {
        "hierarchy": [
          "tgn:2228471",
          "tgn:2001628",
          "tgn:1000001",
          "tgn:7012149",
          "tgn:7007707",
          "tgn:7029392"
        ],
        "placetype": [
          "aat:300008706"
        ],
        "id": 2228471,
        "name:xx": "Cedar Creek"
      }
    },
    {
      "geometry": {
        "type": "Point",
        "coordinates": [
          -96.5,
          36.2333
        ]
      },
      "type": "Feature",
      "properties": {
        "hierarchy": [
          "tgn:2228472",
          "tgn:1000001",
          "tgn:7012149",
          "tgn:2001681",
          "tgn:7007707",
          "tgn:7029392"
        ],
        "placetype": [
          "aat:300008706"
        ],
        "id": 2228472,
        "name:xx": "Cedar Creek"
      }
    },
    {
      "geometry": {
        "type": "Point",
        "coordinates": [
          -95.45,
          36.9167
        ]
      },
      "type": "Feature",
      "properties": {
        "hierarchy": [
          "tgn:2228473",
          "tgn:1000001",
          "tgn:7012149",
          "tgn:2001675",
          "tgn:7007707",
          "tgn:7029392"
        ],
        "placetype": [
          "aat:300008706"
        ],
        "id": 2228473,
        "name:xx": "Cedar Creek"
      }
    },
    {
      "geometry": {
        "type": "Point",
        "coordinates": [
          -124.1333,
          42.3167
        ]
      },
      "type": "Feature",
      "properties": {
        "hierarchy": [
          "tgn:2228474",
          "tgn:1000001",
          "tgn:2001704",
          "tgn:7012149",
          "tgn:7007708",
          "tgn:7029392"
        ],
        "placetype": [
          "aat:300008706"
        ],
        "id": 2228474,
        "name:xx": "Cedar Creek"
      }
    },
    {
      "geometry": {
        "type": "Point",
        "coordinates": [
          -122.6167,
          43.45
        ]
      },
      "type": "Feature",
      "properties": {
        "hierarchy": [
          "tgn:2228475",
          "tgn:1000001",
          "tgn:7012149",
          "tgn:2001716",
          "tgn:7007708",
          "tgn:7029392"
        ],
        "placetype": [
          "aat:300008706"
        ],
        "id": 2228475,
        "name:xx": "Cedar Creek"
      }
    },
    {
      "geometry": {
        "type": "Point",
        "coordinates": [
          -123.8667,
          43.5333
        ]
      },
      "type": "Feature",
      "properties": {
        "hierarchy": [
          "tgn:2228476",
          "tgn:1000001",
          "tgn:2001702",
          "tgn:7012149",
          "tgn:7007708",
          "tgn:7029392"
        ],
        "placetype": [
          "aat:300008706"
        ],
        "id": 2228476,
        "name:xx": "Cedar Creek"
      }
    },
    {
      "geometry": {
        "type": "Point",
        "coordinates": [
          -123.7667,
          44.2833
        ]
      },
      "type": "Feature",
      "properties": {
        "hierarchy": [
          "tgn:2228477",
          "tgn:1000001",
          "tgn:7012149",
          "tgn:7007708",
          "tgn:7029392"
        ],
        "placetype": [
          "aat:300008706"
        ],
        "id": 2228477,
        "name:xx": "Cedar Creek"
      }
    },
    {
      "geometry": {
        "type": "Point",
        "coordinates": [
          -122.6833,
          44.3167
        ]
      },
      "type": "Feature",
      "properties": {
        "hierarchy": [
          "tgn:2228478",
          "tgn:1000001",
          "tgn:7012149",
          "tgn:2001717",
          "tgn:7007708",
          "tgn:7029392"
        ],
        "placetype": [
          "aat:300008706"
        ],
        "id": 2228478,
        "name:xx": "Cedar Creek"
      }
    },
    {
      "geometry": {
        "type": "Point",
        "coordinates": [
          -123.7833,
          44.3833
        ]
      },
      "type": "Feature",
      "properties": {
        "hierarchy": [
          "tgn:2228479",
          "tgn:1000001",
          "tgn:7012149",
          "tgn:1002599",
          "tgn:7007708",
          "tgn:7029392"
        ],
        "placetype": [
          "aat:300008706"
        ],
        "id": 2228479,
        "name:xx": "Cedar Creek"
      }
    }
  ]
}
