{
  "geometry": {
    "type": "Point",
    "coordinates": [
      -58.0833,
      -34.8667
    ]
  },
  "type": "Feature",
  "properties": {
    "hierarchy": [
      "tgn:1004289",
      "tgn:1001160",
      "tgn:7006477",
      "tgn:1000002",
      "tgn:7006289",
      "tgn:7029392"
    ],
    "placetype": [
      "aat:300000745"
    ],
    "id": 1004289,
    "name:xx": "City Bell"
  }
}
