{
  "type": "FeatureCollection",
  "features": [
    {
      "geometry": {
        "type": "Point",
        "coordinates": [
          -70.7,
          42.0333
        ]
      },
      "type": "Feature",
      "properties": {
        "hierarchy": [
          "tgn:2758270",
          "tgn:1000001",
          "tgn:7014423",
          "tgn:7012149",
          "tgn:7007517",
          "tgn:7029392"
        ],
        "placetype": [
          "aat:300008699"
        ],
        "id": 2758270,
        "name:xx": "West Brook"
      }
    },
    {
      "geometry": {
        "type": "Point",
        "coordinates": [
          -72.5833,
          42.75
        ]
      },
      "type": "Feature",
      "properties": {
        "hierarchy": [
          "tgn:2758271",
          "tgn:1000001",
          "tgn:7012149",
          "tgn:7029392"
        ],
        "placetype": [
          "aat:300008699"
        ],
        "id": 2758271,
        "name:xx": "West Brook"
      }
    },
    {
      "geometry": {
        "type": "Point",
        "coordinates": [
          -71.55,
          43.7667
        ]
      },
      "type": "Feature",
      "properties": {
        "hierarchy": [
          "tgn:2758272",
          "tgn:1000001",
          "tgn:2001424",
          "tgn:7012149",
          "tgn:7007564",
          "tgn:7029392"
        ],
        "placetype": [
          "aat:300008699"
        ],
        "id": 2758272,
        "name:xx": "West Brook"
      }
    },
    {
      "geometry": {
        "type": "Point",
        "coordinates": [
          -74.4167,
          40.8167
        ]
      },
      "type": "Feature",
      "properties": {
        "hierarchy": [
          "tgn:2758273",
          "tgn:1000001",
          "tgn:1002695",
          "tgn:7012149",
          "tgn:7007565",
          "tgn:7029392"
        ],
        "placetype": [
          "aat:300008699"
        ],
        "id": 2758273,
        "name:xx": "West Brook"
      }
    },
    {
      "geometry": {
        "type": "Point",
        "coordinates": [
          -73.1333,
          40.75
        ]
      },
      "type": "Feature",
      "properties": {
        "hierarchy": [
          "tgn:2758274",
          "tgn:1000001",
          "tgn:7012149",
          "tgn:1002924",
          "tgn:7007568",
          "tgn:7029392"
        ],
        "placetype": [
          "aat:300008699"
        ],
        "id": 2758274,
        "name:xx": "West Brook"
      }
    },
    {
      "geometry": {
        "type": "Point",
        "coordinates": [
          -73.6,
          44.75
        ]
      },
      "type": "Feature",
      "properties": {
        "hierarchy": [
          "tgn:2758275",
          "tgn:1000001",
          "tgn:1002284",
          "tgn:7012149",
          "tgn:7007568",
          "tgn:7029392"
        ],
        "placetype": [
          "aat:300008699"
        ],
        "id": 2758275,
        "name:xx": "West Brook"
      }
    },
    {
      "geometry": {
        "type": "Point",
        "coordinates": [
          -75.15,
          42.2667
        ]
      },
      "type": "Feature",
      "properties": {
        "hierarchy": [
          "tgn:2758276",
          "tgn:1000001",
          "tgn:1002328",
          "tgn:7012149",
          "tgn:7007568",
          "tgn:7029392"
        ],
        "placetype": [
          "aat:300008699"
        ],
        "id": 2758276,
        "name:xx": "West Brook"
      }
    },
    {
      "geometry": {
        "type": "Point",
        "coordinates": [
          -73.3833,
          42.6167
        ]
      },
      "type": "Feature",
      "properties": {
        "hierarchy": [
          "tgn:2758277",
          "tgn:1000001",
          "tgn:7012149",
          "tgn:1002821",
          "tgn:7007568",
          "tgn:7029392"
        ],
        "placetype": [
          "aat:300008699"
        ],
        "id": 2758277,
        "name:xx": "West Brook"
      }
    },
    {
      "geometry": {
        "type": "Point",
        "coordinates": [
          -75.45,
          42.6167
        ]
      },
      "type": "Feature",
      "properties": {
        "hierarchy": [
          "tgn:2758278",
          "tgn:1000001",
          "tgn:1002262",
          "tgn:7012149",
          "tgn:7007568",
          "tgn:7029392"
        ],
        "placetype": [
          "aat:300008699"
        ],
        "id": 2758278,
        "name:xx": "West Brook"
      }
    },
    {
      "geometry": {
        "type": "Point",
        "coordinates": [
          -73.7667,
          43.4
        ]
      },
      "type": "Feature",
      "properties": {
        "hierarchy": [
          "tgn:2758279",
          "tgn:1000001",
          "tgn:7012149",
          "tgn:1002986",
          "tgn:7007568",
          "tgn:7029392"
        ],
        "placetype": [
          "aat:300008699"
        ],
        "id": 2758279,
        "name:xx": "West Brook"
      }
    }
  ]
}
