{
  "geometry": {
    "type": "Point",
    "coordinates": [
      -91.6167,
      46.3333
    ]
  },
  "type": "Feature",
  "properties": {
    "hierarchy": [
      "tgn:2187592",
      "tgn:1000001",
      "tgn:2002318",
      "tgn:7012149",
      "tgn:7007922",
      "tgn:7029392"
    ],
    "placetype": [
      "aat:300008680"
    ],
    "id": 2187592,
    "name:xx": "Boot Lake"
  }
}
