{
  "geometry": {
    "type": "Point",
    "coordinates": [
      -124.1167,
      43.0167
    ]
  },
  "type": "Feature",
  "properties": {
    "hierarchy": [
      "tgn:2234343",
      "tgn:1000001",
      "tgn:2001702",
      "tgn:7012149",
      "tgn:7007708",
      "tgn:7029392"
    ],
    "placetype": [
      "aat:300008347"
    ],
    "id": 2234343,
    "name:xx": "Cheney"
  }
}
