{
  "geometry": {
    "type": "Point",
    "coordinates": [
      25.838333,
      40.4725
    ]
  },
  "type": "Feature",
  "properties": {
    "hierarchy": [
      "tgn:7221568",
      "tgn:7002753",
      "tgn:7002756",
      "tgn:1000003",
      "tgn:1000074",
      "tgn:7029392"
    ],
    "placetype": [
      "aat:300008791"
    ],
    "id": 7221568,
    "name:xx": "Zouráfa, Vrachonisída"
  }
}
