{
  "type": "FeatureCollection",
  "features": [
    {
      "geometry": {
        "type": "Point",
        "coordinates": [
          -95.5167,
          41.2667
        ]
      },
      "type": "Feature",
      "properties": {
        "hierarchy": [
          "tgn:2712470",
          "tgn:1000001",
          "tgn:7012149",
          "tgn:2000638",
          "tgn:7007253",
          "tgn:7029392"
        ],
        "placetype": [
          "aat:300008347"
        ],
        "id": 2712470,
        "name:xx": "Taylor"
      }
    },
    {
      "geometry": {
        "type": "Point",
        "coordinates": [
          -76.5167,
          39.5667
        ]
      },
      "type": "Feature",
      "properties": {
        "hierarchy": [
          "tgn:2712471",
          "tgn:1000001",
          "tgn:7016102",
          "tgn:7012149",
          "tgn:7007516",
          "tgn:7029392"
        ],
        "placetype": [
          "aat:300008347"
        ],
        "id": 2712471,
        "name:xx": "Taylor"
      }
    },
    {
      "geometry": {
        "type": "Point",
        "coordinates": [
          -114.6833,
          39.0667
        ]
      },
      "type": "Feature",
      "properties": {
        "hierarchy": [
          "tgn:2712472",
          "tgn:1000001",
          "tgn:7012149",
          "tgn:2001420",
          "tgn:7007526",
          "tgn:7029392"
        ],
        "placetype": [
          "aat:300008347"
        ],
        "id": 2712472,
        "name:xx": "Taylor"
      }
    },
    {
      "geometry": {
        "type": "Point",
        "coordinates": [
          -107.1167,
          36.0167
        ]
      },
      "type": "Feature",
      "properties": {
        "hierarchy": [
          "tgn:2712473",
          "tgn:1000001",
          "tgn:7012149",
          "tgn:2001451",
          "tgn:7007566",
          "tgn:7029392"
        ],
        "placetype": [
          "aat:300000390"
        ],
        "id": 2712473,
        "name:xx": "Taylor"
      }
    },
    {
      "geometry": {
        "type": "Point",
        "coordinates": [
          -107.5667,
          33.5333
        ]
      },
      "type": "Feature",
      "properties": {
        "hierarchy": [
          "tgn:2712474",
          "tgn:1000001",
          "tgn:7012149",
          "tgn:2001456",
          "tgn:7007566",
          "tgn:7029392"
        ],
        "placetype": [
          "aat:300000390"
        ],
        "id": 2712474,
        "name:xx": "Taylor"
      }
    },
    {
      "geometry": {
        "type": "Point",
        "coordinates": [
          -99.3667,
          35.2333
        ]
      },
      "type": "Feature",
      "properties": {
        "hierarchy": [
          "tgn:2712475",
          "tgn:2001627",
          "tgn:1000001",
          "tgn:7012149",
          "tgn:7007707",
          "tgn:7029392"
        ],
        "placetype": [
          "aat:300008347"
        ],
        "id": 2712475,
        "name:xx": "Taylor"
      }
    },
    {
      "geometry": {
        "type": "Point",
        "coordinates": [
          -79.7833,
          40.3833
        ]
      },
      "type": "Feature",
      "properties": {
        "hierarchy": [
          "tgn:2712476",
          "tgn:7013272",
          "tgn:1000001",
          "tgn:7012149",
          "tgn:7007710",
          "tgn:7029392"
        ],
        "placetype": [
          "aat:300008347"
        ],
        "id": 2712476,
        "name:xx": "Taylor"
      }
    },
    {
      "geometry": {
        "type": "Point",
        "coordinates": [
          -84.7833,
          35.1167
        ]
      },
      "type": "Feature",
      "properties": {
        "hierarchy": [
          "tgn:2712477",
          "tgn:1000001",
          "tgn:2001842",
          "tgn:7012149",
          "tgn:7007825",
          "tgn:7029392"
        ],
        "placetype": [
          "aat:300008347"
        ],
        "id": 2712477,
        "name:xx": "Taylor"
      }
    },
    {
      "geometry": {
        "type": "Point",
        "coordinates": [
          -79.9,
          37.0833
        ]
      },
      "type": "Feature",
      "properties": {
        "hierarchy": [
          "tgn:2712478",
          "tgn:1000001",
          "tgn:7012149",
          "tgn:2002160",
          "tgn:7007919",
          "tgn:7029392"
        ],
        "placetype": [
          "aat:300008347"
        ],
        "id": 2712478,
        "name:xx": "Taylor"
      }
    },
    {
      "geometry": {
        "type": "Point",
        "coordinates": [
          -78.9667,
          39.0333
        ]
      },
      "type": "Feature",
      "properties": {
        "hierarchy": [
          "tgn:2712479",
          "tgn:1000001",
          "tgn:7012149",
          "tgn:2002266",
          "tgn:7013961",
          "tgn:7029392"
        ],
        "placetype": [
          "aat:300008347"
        ],
        "id": 2712479,
        "name:xx": "Taylor"
      }
    }
  ]
}
