{
  "geometry": {
    "type": "Point",
    "coordinates": [
      -114.7667,
      45.8833
    ]
  },
  "type": "Feature",
  "properties": {
    "hierarchy": [
      "tgn:2748001",
      "tgn:1000001",
      "tgn:7012149",
      "tgn:2000476",
      "tgn:7007250",
      "tgn:7029392"
    ],
    "placetype": [
      "aat:300132348"
    ],
    "id": 2748001,
    "name:xx": "Waldo Bar"
  }
}
