{
  "geometry": {
    "type": "Point",
    "coordinates": [
      -70.75,
      43.0833
    ]
  },
  "type": "Feature",
  "properties": {
    "hierarchy": [
      "tgn:2542651",
      "tgn:1000001",
      "tgn:7012149",
      "tgn:7029392"
    ],
    "placetype": [
      "aat:300132348"
    ],
    "id": 2542651,
    "name:xx": "Nobles Island"
  }
}
