{
  "geometry": {
    "type": "Point",
    "coordinates": [
      -87.3167,
      35.8167
    ]
  },
  "type": "Feature",
  "properties": {
    "hierarchy": [
      "tgn:2217588",
      "tgn:1000001",
      "tgn:7012149",
      "tgn:7015666",
      "tgn:7007825",
      "tgn:7029392"
    ],
    "placetype": [
      "aat:300008798"
    ],
    "id": 2217588,
    "name:xx": "Campbell Hill"
  }
}
