{
  "geometry": {
    "type": "Point",
    "coordinates": [
      -7.0167,
      39.6667
    ]
  },
  "type": "Feature",
  "properties": {
    "hierarchy": [
      "tgn:7010408",
      "tgn:1000003",
      "tgn:7029392"
    ],
    "placetype": [
      "aat:300008707"
    ],
    "name:pt": "Erges",
    "id": 7010408,
    "name:es": "Erjas"
  }
}
