{
  "geometry": {
    "type": "Point",
    "coordinates": [
      -76.4667,
      42.7667
    ]
  },
  "type": "Feature",
  "properties": {
    "hierarchy": [
      "tgn:2311222",
      "tgn:1000001",
      "tgn:1002246",
      "tgn:7012149",
      "tgn:7007568",
      "tgn:7029392"
    ],
    "placetype": [
      "aat:300008347"
    ],
    "id": 2311222,
    "name:xx": "Edgewater"
  }
}
