{
  "geometry": {
    "type": "Point",
    "coordinates": [
      -76.2833,
      42.7333
    ]
  },
  "type": "Feature",
  "properties": {
    "hierarchy": [
      "tgn:2649068",
      "tgn:1000001",
      "tgn:7012149",
      "tgn:7007568",
      "tgn:7029392"
    ],
    "placetype": [
      "aat:300008761"
    ],
    "id": 2649068,
    "name:xx": "Scott Gulf"
  }
}
