{
  "geometry": {
    "type": "Point",
    "coordinates": [
      -83.75,
      39.8333
    ]
  },
  "type": "Feature",
  "properties": {
    "hierarchy": [
      "tgn:2081404",
      "tgn:1000001",
      "tgn:1002274",
      "tgn:7012149",
      "tgn:7007706",
      "tgn:7029392"
    ],
    "placetype": [
      "aat:300008347"
    ],
    "id": 2081404,
    "name:xx": "Pitchin"
  }
}
