{
  "geometry": {
    "type": "Point",
    "coordinates": [
      -107.8667,
      47.55
    ]
  },
  "type": "Feature",
  "properties": {
    "hierarchy": [
      "tgn:2422255",
      "tgn:1000001",
      "tgn:7012149",
      "tgn:2001295",
      "tgn:7007524",
      "tgn:7029392"
    ],
    "placetype": [
      "aat:300008706"
    ],
    "id": 2422255,
    "name:xx": "Jim Wells Creek"
  }
}
