{
  "geometry": {
    "type": "Point",
    "coordinates": [
      -92.5667,
      32.9167
    ]
  },
  "type": "Feature",
  "properties": {
    "hierarchy": [
      "tgn:2216498",
      "tgn:1000001",
      "tgn:7012149",
      "tgn:2000909",
      "tgn:7007256",
      "tgn:7029392"
    ],
    "placetype": [
      "aat:300008706"
    ],
    "id": 2216498,
    "name:xx": "Camp Creek"
  }
}
