{
  "type": "FeatureCollection",
  "features": [
    {
      "geometry": {
        "type": "Point",
        "coordinates": [
          -116.8,
          32.1
        ]
      },
      "type": "Feature",
      "properties": {
        "hierarchy": [
          "tgn:7375090",
          "tgn:1001835",
          "tgn:1000001",
          "tgn:7005560",
          "tgn:7029392"
        ],
        "placetype": [
          "aat:300266554",
          "aat:300008699"
        ],
        "id": 7375090,
        "name:xx": "La Zorra, Arroyo"
      }
    },
    {
      "geometry": {
        "type": "Point",
        "coordinates": [
          -108.183333,
          27.8
        ]
      },
      "type": "Feature",
      "properties": {
        "hierarchy": [
          "tgn:7375091",
          "tgn:7005581",
          "tgn:1000001",
          "tgn:7005560",
          "tgn:7029392"
        ],
        "placetype": [
          "aat:300008347"
        ],
        "id": 7375091,
        "name:xx": "La Cueva"
      }
    },
    {
      "geometry": {
        "type": "Point",
        "coordinates": [
          -106.366667,
          27.25
        ]
      },
      "type": "Feature",
      "properties": {
        "hierarchy": [
          "tgn:7375092",
          "tgn:7005581",
          "tgn:1000001",
          "tgn:7005560",
          "tgn:7029392"
        ],
        "placetype": [
          "aat:300008347"
        ],
        "id": 7375092,
        "name:xx": "La Cueva"
      }
    },
    {
      "geometry": {
        "type": "Point",
        "coordinates": [
          -108.816667,
          27.15
        ]
      },
      "type": "Feature",
      "properties": {
        "hierarchy": [
          "tgn:7375093",
          "tgn:1000001",
          "tgn:1001960",
          "tgn:7005560",
          "tgn:7029392"
        ],
        "placetype": [
          "aat:300008347"
        ],
        "id": 7375093,
        "name:xx": "La Cueva"
      }
    },
    {
      "geometry": {
        "type": "Point",
        "coordinates": [
          -107.366667,
          26.5
        ]
      },
      "type": "Feature",
      "properties": {
        "hierarchy": [
          "tgn:7375094",
          "tgn:7005581",
          "tgn:1000001",
          "tgn:7005560",
          "tgn:7029392"
        ],
        "placetype": [
          "aat:300008347"
        ],
        "id": 7375094,
        "name:xx": "La Cueva"
      }
    },
    {
      "geometry": {
        "type": "Point",
        "coordinates": [
          -107.716667,
          25.583333
        ]
      },
      "type": "Feature",
      "properties": {
        "hierarchy": [
          "tgn:7375095",
          "tgn:1000001",
          "tgn:7005595",
          "tgn:7005560",
          "tgn:7029392"
        ],
        "placetype": [
          "aat:300008347"
        ],
        "id": 7375095,
        "name:xx": "La Cueva"
      }
    },
    {
      "geometry": {
        "type": "Point",
        "coordinates": [
          -107.596389,
          24.723889
        ]
      },
      "type": "Feature",
      "properties": {
        "hierarchy": [
          "tgn:7375096",
          "tgn:1000001",
          "tgn:7005595",
          "tgn:7005560",
          "tgn:7029392"
        ],
        "placetype": [
          "aat:300008347"
        ],
        "id": 7375096,
        "name:xx": "La Curva"
      }
    },
    {
      "geometry": {
        "type": "Point",
        "coordinates": [
          -105.416667,
          23.616667
        ]
      },
      "type": "Feature",
      "properties": {
        "hierarchy": [
          "tgn:7375097",
          "tgn:7005583",
          "tgn:1000001",
          "tgn:7005560",
          "tgn:7029392"
        ],
        "placetype": [
          "aat:300008347"
        ],
        "id": 7375097,
        "name:xx": "La Cueva"
      }
    },
    {
      "geometry": {
        "type": "Point",
        "coordinates": [
          -100.2,
          21.433333
        ]
      },
      "type": "Feature",
      "properties": {
        "hierarchy": [
          "tgn:7375098",
          "tgn:7005584",
          "tgn:1000001",
          "tgn:7005560",
          "tgn:7029392"
        ],
        "placetype": [
          "aat:300008347"
        ],
        "id": 7375098,
        "name:xx": "La Cueva"
      }
    },
    {
      "geometry": {
        "type": "Point",
        "coordinates": [
          -100.683333,
          20.45
        ]
      },
      "type": "Feature",
      "properties": {
        "hierarchy": [
          "tgn:7375099",
          "tgn:7005584",
          "tgn:1000001",
          "tgn:7005560",
          "tgn:7029392"
        ],
        "placetype": [
          "aat:300008347"
        ],
        "id": 7375099,
        "name:xx": "La Cueva"
      }
    }
  ]
}
