{
  "geometry": {
    "type": "Point",
    "coordinates": [
      62.45,
      29.0167
    ]
  },
  "type": "Feature",
  "properties": {
    "hierarchy": [
      "tgn:1083644",
      "tgn:7000360",
      "tgn:1000004",
      "tgn:1000133",
      "tgn:7029392"
    ],
    "placetype": [
      "aat:300008347"
    ],
    "id": 1083644,
    "name:xx": "Mashki, Chah"
  }
}
