{
  "geometry": {
    "type": "Point",
    "coordinates": [
      -81.4833,
      34.6167
    ]
  },
  "type": "Feature",
  "properties": {
    "hierarchy": [
      "tgn:2263575",
      "tgn:1000001",
      "tgn:7012149",
      "tgn:7007712",
      "tgn:7029392"
    ],
    "placetype": [
      "aat:300008706"
    ],
    "id": 2263575,
    "name:xx": "Coxs Creek"
  }
}
