{
  "geometry": {
    "type": "Point",
    "coordinates": [
      -87.0667,
      38.6833
    ]
  },
  "type": "Feature",
  "properties": {
    "hierarchy": [
      "tgn:2135301",
      "tgn:1000001",
      "tgn:2000541",
      "tgn:7012149",
      "tgn:7007252",
      "tgn:7029392"
    ],
    "placetype": [
      "aat:300008706"
    ],
    "id": 2135301,
    "name:xx": "Antioch Creek"
  }
}
