{
  "geometry": {
    "type": "Point",
    "coordinates": [
      -88.5333,
      41.75
    ]
  },
  "type": "Feature",
  "properties": {
    "hierarchy": [
      "tgn:2026595",
      "tgn:1000001",
      "tgn:7012149",
      "tgn:1002531",
      "tgn:7007251",
      "tgn:7029392"
    ],
    "placetype": [
      "aat:300008347"
    ],
    "id": 2026595,
    "name:xx": "Big Rock"
  }
}
