{
  "geometry": {
    "type": "Point",
    "coordinates": [
      87.598789,
      22.17768
    ]
  },
  "type": "Feature",
  "properties": {
    "hierarchy": [
      "tgn:1076785",
      "tgn:1000004",
      "tgn:7000198",
      "tgn:1001977",
      "tgn:7029392"
    ],
    "placetype": [
      "aat:300008347"
    ],
    "name:en": "Sābang",
    "id": 1076785
  }
}
