{
  "geometry": {
    "type": "Point",
    "coordinates": [
      -86.3833,
      35.5333
    ]
  },
  "type": "Feature",
  "properties": {
    "hierarchy": [
      "tgn:2255384",
      "tgn:1000001",
      "tgn:7012149",
      "tgn:2001911",
      "tgn:7007825",
      "tgn:7029392"
    ],
    "placetype": [
      "aat:300008699"
    ],
    "id": 2255384,
    "name:xx": "Coops Branch"
  }
}
