{
  "geometry": {
    "type": "Point",
    "coordinates": [
      -88.4333,
      35.05
    ]
  },
  "type": "Feature",
  "properties": {
    "hierarchy": [
      "tgn:7021391",
      "tgn:1000001",
      "tgn:7012149",
      "tgn:7029392"
    ],
    "placetype": [
      "aat:300008706"
    ],
    "id": 7021391,
    "name:xx": "Wardlow Creek"
  }
}
