{
  "geometry": {
    "type": "Point",
    "coordinates": [
      39.3167,
      47.0333
    ]
  },
  "type": "Feature",
  "properties": {
    "hierarchy": [
      "tgn:1061500",
      "tgn:1000004",
      "tgn:1003405",
      "tgn:7018214",
      "tgn:7002435",
      "tgn:7029392"
    ],
    "placetype": [
      "aat:300008347"
    ],
    "id": 1061500,
    "name:xx": "Zajmo-Obryv"
  }
}
