{
  "geometry": {
    "type": "Point",
    "coordinates": [
      28.74436,
      30.816505
    ]
  },
  "type": "Feature",
  "properties": {
    "hierarchy": [
      "tgn:7524908",
      "tgn:7001242",
      "tgn:7016833",
      "tgn:1001418",
      "tgn:7029392"
    ],
    "placetype": [
      "aat:300008777"
    ],
    "name:en": "Burt Sabâi el-Gharbi, 'Alam",
    "id": 7524908
  }
}
