{
  "geometry": {
    "type": "Point",
    "coordinates": [
      -73.4167,
      42.1167
    ]
  },
  "type": "Feature",
  "properties": {
    "hierarchy": [
      "tgn:2210474",
      "tgn:7013388",
      "tgn:1000001",
      "tgn:7012149",
      "tgn:7007517",
      "tgn:7029392"
    ],
    "placetype": [
      "aat:300008798"
    ],
    "id": 2210474,
    "name:xx": "Bushnell, Mount"
  }
}
