{
  "type": "FeatureCollection",
  "features": [
    {
      "geometry": {
        "type": "Point",
        "coordinates": [
          8.983333,
          52.266667
        ]
      },
      "type": "Feature",
      "properties": {
        "hierarchy": [
          "tgn:7061032",
          "tgn:1000003",
          "tgn:7003677",
          "tgn:7000084",
          "tgn:7029392"
        ],
        "placetype": [
          "aat:300008347"
        ],
        "id": 7061032,
        "name:xx": "Bad Nammen"
      }
    },
    {
      "geometry": {
        "type": "Point",
        "coordinates": [
          9.468056,
          52.1775
        ]
      },
      "type": "Feature",
      "properties": {
        "hierarchy": [
          "tgn:7061037",
          "tgn:1000003",
          "tgn:7003676",
          "tgn:7000084",
          "tgn:7029392"
        ],
        "placetype": [
          "aat:300007783"
        ],
        "id": 7061037,
        "name:xx": "Bahnhof Bad Münder (Deister)"
      }
    },
    {
      "geometry": {
        "type": "Point",
        "coordinates": [
          8.983333,
          51.9
        ]
      },
      "type": "Feature",
      "properties": {
        "hierarchy": [
          "tgn:7061039",
          "tgn:1000003",
          "tgn:7003677",
          "tgn:7000084",
          "tgn:7029392"
        ],
        "placetype": [
          "aat:300000745"
        ],
        "id": 7061039,
        "name:xx": "Bad Meinberg"
      }
    }
  ]
}
