{
  "geometry": {
    "type": "Point",
    "coordinates": [
      74.54055,
      32.830959
    ]
  },
  "type": "Feature",
  "properties": {
    "hierarchy": [
      "tgn:7592173",
      "tgn:1000004",
      "tgn:7000198",
      "tgn:7000799",
      "tgn:7029392"
    ],
    "placetype": [
      "aat:300008347"
    ],
    "name:en": "Khalka Malāl",
    "id": 7592173
  }
}
