{
  "type": "FeatureCollection",
  "features": [
    {
      "geometry": {
        "type": "Point",
        "coordinates": [
          -83.0333,
          32.6333
        ]
      },
      "type": "Feature",
      "properties": {
        "hierarchy": [
          "tgn:2296740",
          "tgn:1000001",
          "tgn:7012149",
          "tgn:2000378",
          "tgn:7007248",
          "tgn:7029392"
        ],
        "placetype": [
          "aat:300008706"
        ],
        "id": 2296740,
        "name:xx": "Dry Creek"
      }
    },
    {
      "geometry": {
        "type": "Point",
        "coordinates": [
          -82.8833,
          33.3
        ]
      },
      "type": "Feature",
      "properties": {
        "hierarchy": [
          "tgn:2296741",
          "tgn:1000001",
          "tgn:7012149",
          "tgn:2000361",
          "tgn:7007248",
          "tgn:7029392"
        ],
        "placetype": [
          "aat:300008706"
        ],
        "id": 2296741,
        "name:xx": "Dry Creek"
      }
    },
    {
      "geometry": {
        "type": "Point",
        "coordinates": [
          -84.65,
          33.7167
        ]
      },
      "type": "Feature",
      "properties": {
        "hierarchy": [
          "tgn:2296742",
          "tgn:1000001",
          "tgn:7012149",
          "tgn:2000339",
          "tgn:7007248",
          "tgn:7029392"
        ],
        "placetype": [
          "aat:300008706"
        ],
        "id": 2296742,
        "name:xx": "Dry Creek"
      }
    },
    {
      "geometry": {
        "type": "Point",
        "coordinates": [
          -85.3833,
          33.9833
        ]
      },
      "type": "Feature",
      "properties": {
        "hierarchy": [
          "tgn:2296743",
          "tgn:1000001",
          "tgn:7012149",
          "tgn:2000406",
          "tgn:7007248",
          "tgn:7029392"
        ],
        "placetype": [
          "aat:300008706"
        ],
        "id": 2296743,
        "name:xx": "Dry Creek"
      }
    },
    {
      "geometry": {
        "type": "Point",
        "coordinates": [
          -85.0667,
          34.5167
        ]
      },
      "type": "Feature",
      "properties": {
        "hierarchy": [
          "tgn:2296744",
          "tgn:1000001",
          "tgn:7012149",
          "tgn:2000355",
          "tgn:7007248",
          "tgn:7029392"
        ],
        "placetype": [
          "aat:300008706"
        ],
        "id": 2296744,
        "name:xx": "Dry Creek"
      }
    },
    {
      "geometry": {
        "type": "Point",
        "coordinates": [
          -84.3167,
          34.8667
        ]
      },
      "type": "Feature",
      "properties": {
        "hierarchy": [
          "tgn:2296745",
          "tgn:1000001",
          "tgn:7012149",
          "tgn:2000346",
          "tgn:7007248",
          "tgn:7029392"
        ],
        "placetype": [
          "aat:300008706"
        ],
        "id": 2296745,
        "name:xx": "Dry Creek"
      }
    },
    {
      "geometry": {
        "type": "Point",
        "coordinates": [
          -111.1,
          42.4833
        ]
      },
      "type": "Feature",
      "properties": {
        "hierarchy": [
          "tgn:2296746",
          "tgn:2000455",
          "tgn:1000001",
          "tgn:7012149",
          "tgn:7007250",
          "tgn:7029392"
        ],
        "placetype": [
          "aat:300008706"
        ],
        "id": 2296746,
        "name:xx": "Dry Creek"
      }
    },
    {
      "geometry": {
        "type": "Point",
        "coordinates": [
          -114.1667,
          43.4333
        ]
      },
      "type": "Feature",
      "properties": {
        "hierarchy": [
          "tgn:2296747",
          "tgn:1000001",
          "tgn:2000458",
          "tgn:7012149",
          "tgn:7007250",
          "tgn:7029392"
        ],
        "placetype": [
          "aat:300008706"
        ],
        "id": 2296747,
        "name:xx": "Dry Creek"
      }
    },
    {
      "geometry": {
        "type": "Point",
        "coordinates": [
          -115.8167,
          43.7667
        ]
      },
      "type": "Feature",
      "properties": {
        "hierarchy": [
          "tgn:2296748",
          "tgn:1000001",
          "tgn:2000459",
          "tgn:7012149",
          "tgn:7007250",
          "tgn:7029392"
        ],
        "placetype": [
          "aat:300008706"
        ],
        "id": 2296748,
        "name:xx": "Dry Creek"
      }
    },
    {
      "geometry": {
        "type": "Point",
        "coordinates": [
          -115.0667,
          44.25
        ]
      },
      "type": "Feature",
      "properties": {
        "hierarchy": [
          "tgn:2296749",
          "tgn:1000001",
          "tgn:2000470",
          "tgn:7012149",
          "tgn:7007250",
          "tgn:7029392"
        ],
        "placetype": [
          "aat:300008706"
        ],
        "id": 2296749,
        "name:xx": "Dry Creek"
      }
    }
  ]
}
