{
  "geometry": {
    "type": "Point",
    "coordinates": [
      -90.2167,
      31.0167
    ]
  },
  "type": "Feature",
  "properties": {
    "hierarchy": [
      "tgn:2287756",
      "tgn:1000001",
      "tgn:7012149",
      "tgn:2001159",
      "tgn:7007522",
      "tgn:7029392"
    ],
    "placetype": [
      "aat:300008347"
    ],
    "id": 2287756,
    "name:xx": "Dillon"
  }
}
