{
  "geometry": {
    "type": "Point",
    "coordinates": [
      71.421271,
      24.035934
    ]
  },
  "type": "Feature",
  "properties": {
    "hierarchy": [
      "tgn:7580210",
      "tgn:1000004",
      "tgn:1001869",
      "tgn:7000198",
      "tgn:7029392"
    ],
    "placetype": [
      "aat:300008347"
    ],
    "name:en": "Tharād",
    "id": 7580210
  }
}
