{
  "geometry": {
    "type": "Point",
    "coordinates": [
      -85.2833,
      45.1833
    ]
  },
  "type": "Feature",
  "properties": {
    "hierarchy": [
      "tgn:2667340",
      "tgn:2000945",
      "tgn:1000001",
      "tgn:7012149",
      "tgn:7007520",
      "tgn:7029392"
    ],
    "placetype": [
      "aat:300008680"
    ],
    "id": 2667340,
    "name:xx": "Skinner Lake"
  }
}
