{
  "geometry": {
    "type": "Point",
    "coordinates": [
      -95.6167,
      28.7667
    ]
  },
  "type": "Feature",
  "properties": {
    "hierarchy": [
      "tgn:2278548",
      "tgn:1000001",
      "tgn:7012149",
      "tgn:1002646",
      "tgn:7007826",
      "tgn:7029392"
    ],
    "placetype": [
      "aat:300008680"
    ],
    "id": 2278548,
    "name:xx": "Dead Caney Lake"
  }
}
