{
  "geometry": {
    "type": "Point",
    "coordinates": [
      -79.3167,
      42.35
    ]
  },
  "type": "Feature",
  "properties": {
    "hierarchy": [
      "tgn:2070212",
      "tgn:1000001",
      "tgn:1002259",
      "tgn:7012149",
      "tgn:7007568",
      "tgn:7029392"
    ],
    "placetype": [
      "aat:300008347"
    ],
    "id": 2070212,
    "name:xx": "Lily Dale"
  }
}
