{
  "geometry": {
    "type": "Point",
    "coordinates": [
      123.4167,
      -10.6333
    ]
  },
  "type": "Feature",
  "properties": {
    "hierarchy": [
      "tgn:1077457",
      "tgn:1000004",
      "tgn:1008813",
      "tgn:1001467",
      "tgn:1000116",
      "tgn:7029392"
    ],
    "placetype": [
      "aat:300008347"
    ],
    "id": 1077457,
    "name:xx": "Batuidu"
  }
}
