{
  "geometry": {
    "type": "Point",
    "coordinates": [
      8.266667,
      53.25
    ]
  },
  "type": "Feature",
  "properties": {
    "hierarchy": [
      "tgn:7143632",
      "tgn:1000003",
      "tgn:7003676",
      "tgn:7000084",
      "tgn:7029392"
    ],
    "placetype": [
      "aat:300008699"
    ],
    "id": 7143632,
    "name:xx": "Loyer Bäke"
  }
}
