{
  "geometry": {
    "type": "Point",
    "coordinates": [
      -92.7167,
      39.7167
    ]
  },
  "type": "Feature",
  "properties": {
    "hierarchy": [
      "tgn:2373934",
      "tgn:1000001",
      "tgn:7012149",
      "tgn:1002619",
      "tgn:7007523",
      "tgn:7029392"
    ],
    "placetype": [
      "aat:300008347"
    ],
    "id": 2373934,
    "name:xx": "Hammack"
  }
}
