{
  "geometry": {
    "type": "Point",
    "coordinates": [
      -85.4667,
      32.7833
    ]
  },
  "type": "Feature",
  "properties": {
    "hierarchy": [
      "tgn:2005398",
      "tgn:7002659",
      "tgn:1000001",
      "tgn:2000008",
      "tgn:7012149",
      "tgn:7029392"
    ],
    "placetype": [
      "aat:300008347",
      "aat:300387210"
    ],
    "id": 2005398,
    "name:xx": "Sturkie"
  }
}
