{
  "type": "FeatureCollection",
  "features": [
    {
      "geometry": {
        "type": "Point",
        "coordinates": [
          -4.583333,
          55.166667
        ]
      },
      "type": "Feature",
      "properties": {
        "hierarchy": [
          "tgn:7448540",
          "tgn:7002444",
          "tgn:1000003",
          "tgn:7019085",
          "tgn:7008591",
          "tgn:7029392"
        ],
        "placetype": [
          "aat:300008347"
        ],
        "name:en": "Rowantree",
        "id": 7448540
      }
    },
    {
      "geometry": {
        "type": "Point",
        "coordinates": [
          -7.15,
          54.716667
        ]
      },
      "type": "Feature",
      "properties": {
        "hierarchy": [
          "tgn:7448543",
          "tgn:7002448",
          "tgn:1000003",
          "tgn:7019206",
          "tgn:7008591",
          "tgn:7029392"
        ],
        "placetype": [
          "aat:300008347"
        ],
        "name:en": "Rousky",
        "id": 7448543
      }
    },
    {
      "geometry": {
        "type": "Point",
        "coordinates": [
          -2.95,
          59.15
        ]
      },
      "type": "Feature",
      "properties": {
        "hierarchy": [
          "tgn:7448546",
          "tgn:7002444",
          "tgn:1000003",
          "tgn:7009907",
          "tgn:7008591",
          "tgn:7029392"
        ],
        "placetype": [
          "aat:300266558"
        ],
        "name:en": "Rousay Sound",
        "id": 7448546
      }
    },
    {
      "geometry": {
        "type": "Point",
        "coordinates": [
          -6.322902,
          49.97868
        ]
      },
      "type": "Feature",
      "properties": {
        "hierarchy": [
          "tgn:7448549",
          "tgn:7002445",
          "tgn:7008116",
          "tgn:1000003",
          "tgn:7008591",
          "tgn:7029392"
        ],
        "placetype": [
          "aat:300008791"
        ],
        "name:en": "Round Island",
        "id": 7448549
      }
    }
  ]
}
