{
  "geometry": {
    "type": "Point",
    "coordinates": [
      -121.9833,
      37.1333
    ]
  },
  "type": "Feature",
  "properties": {
    "hierarchy": [
      "tgn:2208636",
      "tgn:1000001",
      "tgn:7012149",
      "tgn:7007157",
      "tgn:1002869",
      "tgn:7029392"
    ],
    "placetype": [
      "aat:300008706"
    ],
    "id": 2208636,
    "name:xx": "Burns Creek"
  }
}
