{
  "geometry": {
    "type": "Point",
    "coordinates": [
      136.25,
      36.3333
    ]
  },
  "type": "Feature",
  "properties": {
    "hierarchy": [
      "tgn:1080345",
      "tgn:7000895",
      "tgn:1000004",
      "tgn:1000988",
      "tgn:1000120",
      "tgn:7029392"
    ],
    "placetype": [
      "aat:300008347"
    ],
    "id": 1080345,
    "name:xx": "Kaga"
  }
}
