{
  "type": "FeatureCollection",
  "features": [
    {
      "geometry": {
        "type": "Point",
        "coordinates": [
          15.2167,
          57.05
        ]
      },
      "type": "Feature",
      "properties": {
        "hierarchy": [
          "tgn:4004512",
          "tgn:1000003",
          "tgn:1000405",
          "tgn:1000097",
          "tgn:7029392"
        ],
        "placetype": [
          "aat:300008347"
        ],
        "id": 4004512,
        "name:xx": "Granhult"
      }
    },
    {
      "geometry": {
        "type": "Point",
        "coordinates": [
          11.283333,
          43.716667
        ]
      },
      "type": "Feature",
      "properties": {
        "hierarchy": [
          "tgn:4004519",
          "tgn:7003163",
          "tgn:1000003",
          "tgn:7009760",
          "tgn:1000080",
          "tgn:7029392"
        ],
        "placetype": [
          "aat:300008347"
        ],
        "id": 4004519,
        "name:xx": "Grassina"
      }
    }
  ]
}
