{
  "geometry": {
    "type": "Point",
    "coordinates": [
      -77.1333,
      43.2833
    ]
  },
  "type": "Feature",
  "properties": {
    "hierarchy": [
      "tgn:2069742",
      "tgn:1000001",
      "tgn:7012149",
      "tgn:7014600",
      "tgn:7007568",
      "tgn:7029392"
    ],
    "placetype": [
      "aat:300008347",
      "aat:300387210"
    ],
    "id": 2069742,
    "name:xx": "Holland Cove"
  }
}
