{
  "geometry": {
    "type": "Point",
    "coordinates": [
      -4.7167,
      54.0833
    ]
  },
  "type": "Feature",
  "properties": {
    "hierarchy": [
      "tgn:1043071",
      "tgn:1000003",
      "tgn:7005258",
      "tgn:7029392"
    ],
    "placetype": [
      "aat:300008347"
    ],
    "id": 1043071,
    "name:xx": "Port Saint Mary"
  }
}
