{
  "geometry": {
    "type": "Point",
    "coordinates": [
      -91.0333,
      41.2167
    ]
  },
  "type": "Feature",
  "properties": {
    "hierarchy": [
      "tgn:2706637",
      "tgn:1000001",
      "tgn:7012149",
      "tgn:2000520",
      "tgn:7007251",
      "tgn:7029392"
    ],
    "placetype": [
      "aat:300006075"
    ],
    "id": 2706637,
    "name:xx": "Swan Lake Ditch"
  }
}
