{
  "geometry": {
    "type": "Point",
    "coordinates": [
      -122.3667,
      45.6667
    ]
  },
  "type": "Feature",
  "properties": {
    "hierarchy": [
      "tgn:2276566",
      "tgn:1000001",
      "tgn:1002275",
      "tgn:7012149",
      "tgn:7007920",
      "tgn:7029392"
    ],
    "placetype": [
      "aat:300008706"
    ],
    "id": 2276566,
    "name:xx": "David Creek"
  }
}
