{
  "geometry": {
    "type": "Point",
    "coordinates": [
      -77.05,
      -12.05
    ]
  },
  "type": "Feature",
  "properties": {
    "hierarchy": [
      "tgn:1024561",
      "tgn:1000670",
      "tgn:1000002",
      "tgn:1000056",
      "tgn:7029392"
    ],
    "placetype": [
      "aat:300008347",
      "aat:300008389",
      "aat:300000874"
    ],
    "id": 1024561,
    "name:xx": "Jesús María"
  }
}
