{
  "geometry": {
    "type": "Point",
    "coordinates": [
      -85.4833,
      31.4167
    ]
  },
  "type": "Feature",
  "properties": {
    "hierarchy": [
      "tgn:2683556",
      "tgn:7002659",
      "tgn:1000001",
      "tgn:7012149",
      "tgn:2000022",
      "tgn:7029392"
    ],
    "placetype": [
      "aat:300008699"
    ],
    "id": 2683556,
    "name:xx": "Spear Branch"
  }
}
