{
  "geometry": {
    "type": "Point",
    "coordinates": [
      -121.05,
      39.0333
    ]
  },
  "type": "Feature",
  "properties": {
    "hierarchy": [
      "tgn:2576102",
      "tgn:1000001",
      "tgn:7012149",
      "tgn:7007157",
      "tgn:1002710",
      "tgn:7029392"
    ],
    "placetype": [
      "aat:300008697"
    ],
    "id": 2576102,
    "name:xx": "Perkins Spring"
  }
}
