{
  "type": "FeatureCollection",
  "features": [
    {
      "geometry": {
        "type": "Point",
        "coordinates": [
          11.266667,
          49.6
        ]
      },
      "type": "Feature",
      "properties": {
        "hierarchy": [
          "tgn:7117600",
          "tgn:7003669",
          "tgn:1000003",
          "tgn:7000084",
          "tgn:7029392"
        ],
        "placetype": [
          "aat:300008347"
        ],
        "id": 7117600,
        "name:xx": "Ödhof"
      }
    },
    {
      "geometry": {
        "type": "Point",
        "coordinates": [
          12.8,
          49.066667
        ]
      },
      "type": "Feature",
      "properties": {
        "hierarchy": [
          "tgn:7117601",
          "tgn:7003669",
          "tgn:1000003",
          "tgn:7000084",
          "tgn:7029392"
        ],
        "placetype": [
          "aat:300008347"
        ],
        "id": 7117601,
        "name:xx": "Ödhof"
      }
    },
    {
      "geometry": {
        "type": "Point",
        "coordinates": [
          13.583333,
          48.716667
        ]
      },
      "type": "Feature",
      "properties": {
        "hierarchy": [
          "tgn:7117602",
          "tgn:7003669",
          "tgn:1000003",
          "tgn:7000084",
          "tgn:7029392"
        ],
        "placetype": [
          "aat:300008347"
        ],
        "id": 7117602,
        "name:xx": "Ödhof"
      }
    },
    {
      "geometry": {
        "type": "Point",
        "coordinates": [
          12.45,
          49.883333
        ]
      },
      "type": "Feature",
      "properties": {
        "hierarchy": [
          "tgn:7117603",
          "tgn:7003669",
          "tgn:1000003",
          "tgn:7000084",
          "tgn:7029392"
        ],
        "placetype": [
          "aat:300000206"
        ],
        "id": 7117603,
        "name:xx": "Ödhof"
      }
    },
    {
      "geometry": {
        "type": "Point",
        "coordinates": [
          12.45,
          49.6
        ]
      },
      "type": "Feature",
      "properties": {
        "hierarchy": [
          "tgn:7117604",
          "tgn:7003669",
          "tgn:1000003",
          "tgn:7000084",
          "tgn:7029392"
        ],
        "placetype": [
          "aat:300000206"
        ],
        "id": 7117604,
        "name:xx": "Ödhof"
      }
    },
    {
      "geometry": {
        "type": "Point",
        "coordinates": [
          12.083333,
          49.583333
        ]
      },
      "type": "Feature",
      "properties": {
        "hierarchy": [
          "tgn:7117605",
          "tgn:7003669",
          "tgn:1000003",
          "tgn:7000084",
          "tgn:7029392"
        ],
        "placetype": [
          "aat:300000206"
        ],
        "id": 7117605,
        "name:xx": "Ödhof"
      }
    },
    {
      "geometry": {
        "type": "Point",
        "coordinates": [
          11.85,
          49.583333
        ]
      },
      "type": "Feature",
      "properties": {
        "hierarchy": [
          "tgn:7117606",
          "tgn:7003669",
          "tgn:1000003",
          "tgn:7000084",
          "tgn:7029392"
        ],
        "placetype": [
          "aat:300000206"
        ],
        "id": 7117606,
        "name:xx": "Ödhof"
      }
    },
    {
      "geometry": {
        "type": "Point",
        "coordinates": [
          12.2,
          49.366667
        ]
      },
      "type": "Feature",
      "properties": {
        "hierarchy": [
          "tgn:7117607",
          "tgn:7003669",
          "tgn:1000003",
          "tgn:7000084",
          "tgn:7029392"
        ],
        "placetype": [
          "aat:300000206"
        ],
        "id": 7117607,
        "name:xx": "Ödhof"
      }
    },
    {
      "geometry": {
        "type": "Point",
        "coordinates": [
          12.433333,
          49.116667
        ]
      },
      "type": "Feature",
      "properties": {
        "hierarchy": [
          "tgn:7117608",
          "tgn:7003669",
          "tgn:1000003",
          "tgn:7000084",
          "tgn:7029392"
        ],
        "placetype": [
          "aat:300000206"
        ],
        "id": 7117608,
        "name:xx": "Ödhof"
      }
    },
    {
      "geometry": {
        "type": "Point",
        "coordinates": [
          11.666667,
          49.033333
        ]
      },
      "type": "Feature",
      "properties": {
        "hierarchy": [
          "tgn:7117609",
          "tgn:7003669",
          "tgn:1000003",
          "tgn:7000084",
          "tgn:7029392"
        ],
        "placetype": [
          "aat:300000206"
        ],
        "id": 7117609,
        "name:xx": "Ödhof"
      }
    }
  ]
}
