{
  "geometry": {
    "type": "Point",
    "coordinates": [
      -70.8333,
      43.1333
    ]
  },
  "type": "Feature",
  "properties": {
    "hierarchy": [
      "tgn:2243672",
      "tgn:1000001",
      "tgn:2001426",
      "tgn:7012149",
      "tgn:7007564",
      "tgn:7029392"
    ],
    "placetype": [
      "aat:300008850"
    ],
    "id": 2243672,
    "name:xx": "Clements Point"
  }
}
