{
  "geometry": {
    "type": "Point",
    "coordinates": [
      -85.35,
      35.9333
    ]
  },
  "type": "Feature",
  "properties": {
    "hierarchy": [
      "tgn:2098048",
      "tgn:1000001",
      "tgn:7012149",
      "tgn:2001929",
      "tgn:7007825",
      "tgn:7029392"
    ],
    "placetype": [
      "aat:300008347"
    ],
    "id": 2098048,
    "name:xx": "Bon Air"
  }
}
