{
  "type": "FeatureCollection",
  "features": [
    {
      "geometry": {
        "type": "Point",
        "coordinates": [
          -106.2667,
          39.9333
        ]
      },
      "type": "Feature",
      "properties": {
        "hierarchy": [
          "tgn:2205930",
          "tgn:1000001",
          "tgn:7012149",
          "tgn:2000216",
          "tgn:7007158",
          "tgn:7029392"
        ],
        "placetype": [
          "aat:300008699"
        ],
        "id": 2205930,
        "name:xx": "Bull Run"
      }
    },
    {
      "geometry": {
        "type": "Point",
        "coordinates": [
          -88.8333,
          42.0333
        ]
      },
      "type": "Feature",
      "properties": {
        "hierarchy": [
          "tgn:2205931",
          "tgn:1000001",
          "tgn:7019012",
          "tgn:7012149",
          "tgn:7007251",
          "tgn:7029392"
        ],
        "placetype": [
          "aat:300008699"
        ],
        "id": 2205931,
        "name:xx": "Bull Run"
      }
    },
    {
      "geometry": {
        "type": "Point",
        "coordinates": [
          -89.4,
          40.6333
        ]
      },
      "type": "Feature",
      "properties": {
        "hierarchy": [
          "tgn:2205932",
          "tgn:1000001",
          "tgn:7012149",
          "tgn:2000533",
          "tgn:7007251",
          "tgn:7029392"
        ],
        "placetype": [
          "aat:300008699"
        ],
        "id": 2205932,
        "name:xx": "Bull Run"
      }
    },
    {
      "geometry": {
        "type": "Point",
        "coordinates": [
          -90.95,
          39.6167
        ]
      },
      "type": "Feature",
      "properties": {
        "hierarchy": [
          "tgn:2205933",
          "tgn:1000001",
          "tgn:7012149",
          "tgn:1002786",
          "tgn:7007251",
          "tgn:7029392"
        ],
        "placetype": [
          "aat:300008699"
        ],
        "id": 2205933,
        "name:xx": "Bull Run"
      }
    },
    {
      "geometry": {
        "type": "Point",
        "coordinates": [
          -87.5167,
          41.4333
        ]
      },
      "type": "Feature",
      "properties": {
        "hierarchy": [
          "tgn:2205934",
          "tgn:1000001",
          "tgn:7012149",
          "tgn:1002569",
          "tgn:7007252",
          "tgn:7029392"
        ],
        "placetype": [
          "aat:300008699"
        ],
        "id": 2205934,
        "name:xx": "Bull Run"
      }
    },
    {
      "geometry": {
        "type": "Point",
        "coordinates": [
          -85.8,
          38.55
        ]
      },
      "type": "Feature",
      "properties": {
        "hierarchy": [
          "tgn:2205935",
          "tgn:1000001",
          "tgn:1002273",
          "tgn:7012149",
          "tgn:7007252",
          "tgn:7029392"
        ],
        "placetype": [
          "aat:300008699"
        ],
        "id": 2205935,
        "name:xx": "Bull Run"
      }
    },
    {
      "geometry": {
        "type": "Point",
        "coordinates": [
          -84.8833,
          39.25
        ]
      },
      "type": "Feature",
      "properties": {
        "hierarchy": [
          "tgn:2205936",
          "tgn:1000001",
          "tgn:1002324",
          "tgn:7012149",
          "tgn:7007252",
          "tgn:7029392"
        ],
        "placetype": [
          "aat:300008699"
        ],
        "id": 2205936,
        "name:xx": "Bull Run"
      }
    },
    {
      "geometry": {
        "type": "Point",
        "coordinates": [
          -93.6667,
          41.4167
        ]
      },
      "type": "Feature",
      "properties": {
        "hierarchy": [
          "tgn:2205937",
          "tgn:1000001",
          "tgn:7012149",
          "tgn:2000651",
          "tgn:7007253",
          "tgn:7029392"
        ],
        "placetype": [
          "aat:300008699"
        ],
        "id": 2205937,
        "name:xx": "Bull Run"
      }
    },
    {
      "geometry": {
        "type": "Point",
        "coordinates": [
          -96.35,
          42.8
        ]
      },
      "type": "Feature",
      "properties": {
        "hierarchy": [
          "tgn:2205938",
          "tgn:1000001",
          "tgn:7012149",
          "tgn:2000635",
          "tgn:7007253",
          "tgn:7029392"
        ],
        "placetype": [
          "aat:300008699"
        ],
        "id": 2205938,
        "name:xx": "Bull Run"
      }
    },
    {
      "geometry": {
        "type": "Point",
        "coordinates": [
          -95.05,
          41.6833
        ]
      },
      "type": "Feature",
      "properties": {
        "hierarchy": [
          "tgn:2205939",
          "tgn:2000565",
          "tgn:1000001",
          "tgn:7012149",
          "tgn:7007253",
          "tgn:7029392"
        ],
        "placetype": [
          "aat:300008699"
        ],
        "id": 2205939,
        "name:xx": "Bull Run"
      }
    }
  ]
}
