{
  "geometry": {
    "type": "Point",
    "coordinates": [
      -106.65,
      38.8833
    ]
  },
  "type": "Feature",
  "properties": {
    "hierarchy": [
      "tgn:2402216",
      "tgn:1000001",
      "tgn:7012149",
      "tgn:2000217",
      "tgn:7007158",
      "tgn:7029392"
    ],
    "placetype": [
      "aat:300008680"
    ],
    "id": 2402216,
    "name:xx": "Horsethief Lake"
  }
}
