{
  "geometry": {
    "type": "Point",
    "coordinates": [
      -92.3667,
      45.9167
    ]
  },
  "type": "Feature",
  "properties": {
    "hierarchy": [
      "tgn:2465847",
      "tgn:1000001",
      "tgn:2002311",
      "tgn:7012149",
      "tgn:7007922",
      "tgn:7029392"
    ],
    "placetype": [
      "aat:300008680"
    ],
    "id": 2465847,
    "name:xx": "Lone Star Lake"
  }
}
