{
  "geometry": {
    "type": "Point",
    "coordinates": [
      12.2833,
      59.8833
    ]
  },
  "type": "Feature",
  "properties": {
    "hierarchy": [
      "tgn:1062890",
      "tgn:1000003",
      "tgn:7010031",
      "tgn:1000097",
      "tgn:7029392"
    ],
    "placetype": [
      "aat:300008347"
    ],
    "id": 1062890,
    "name:xx": "Charlottenberg"
  }
}
