{
  "geometry": {
    "type": "Point",
    "coordinates": [
      15.9833,
      20.0667
    ]
  },
  "type": "Feature",
  "properties": {
    "hierarchy": [
      "tgn:7000521",
      "tgn:7001242",
      "tgn:7029392"
    ],
    "placetype": [
      "aat:300387091"
    ],
    "id": 7000521,
    "name:xx": "Atoui"
  }
}
