{
  "geometry": {
    "type": "Point",
    "coordinates": [
      -153.4167,
      59.35
    ]
  },
  "type": "Feature",
  "properties": {
    "hierarchy": [
      "tgn:2140317",
      "tgn:7006450",
      "tgn:1000001",
      "tgn:7019698",
      "tgn:7012149",
      "tgn:7029392"
    ],
    "placetype": [
      "aat:300008798"
    ],
    "id": 2140317,
    "name:xx": "Augustine Volcano"
  }
}
