{
  "geometry": {
    "type": "Point",
    "coordinates": [
      -80.8833,
      39.3167
    ]
  },
  "type": "Feature",
  "properties": {
    "hierarchy": [
      "tgn:2493730",
      "tgn:1000001",
      "tgn:7012149",
      "tgn:2002292",
      "tgn:7013961",
      "tgn:7029392"
    ],
    "placetype": [
      "aat:300008699"
    ],
    "id": 2493730,
    "name:xx": "Marsh Run"
  }
}
