{
  "geometry": {
    "type": "Point",
    "coordinates": [
      -84.0667,
      34.4333
    ]
  },
  "type": "Feature",
  "properties": {
    "hierarchy": [
      "tgn:2242595",
      "tgn:1000001",
      "tgn:7012149",
      "tgn:7007248",
      "tgn:7029392"
    ],
    "placetype": [
      "aat:300008706"
    ],
    "id": 2242595,
    "name:xx": "Clear Creek"
  }
}
