{
  "geometry": {
    "type": "Point",
    "coordinates": [
      -84.35,
      38.0333
    ]
  },
  "type": "Feature",
  "properties": {
    "hierarchy": [
      "tgn:2276575",
      "tgn:1000001",
      "tgn:7012149",
      "tgn:1002371",
      "tgn:7007255",
      "tgn:7029392"
    ],
    "placetype": [
      "aat:300008699"
    ],
    "id": 2276575,
    "name:xx": "David Fork"
  }
}
