{
  "geometry": {
    "type": "Point",
    "coordinates": [
      21.55,
      44.0833
    ]
  },
  "type": "Feature",
  "properties": {
    "hierarchy": [
      "tgn:1064975",
      "tgn:1000003",
      "tgn:7006669",
      "tgn:7029392"
    ],
    "placetype": [
      "aat:300008347"
    ],
    "id": 1064975,
    "name:xx": "Despotovac"
  }
}
