{
  "geometry": {
    "type": "Point",
    "coordinates": [
      -80.0667,
      36.9167
    ]
  },
  "type": "Feature",
  "properties": {
    "hierarchy": [
      "tgn:2540866",
      "tgn:1000001",
      "tgn:7012149",
      "tgn:2002160",
      "tgn:7007919",
      "tgn:7029392"
    ],
    "placetype": [
      "aat:300008706"
    ],
    "id": 2540866,
    "name:xx": "Nicholas Creek"
  }
}
