{
  "geometry": {
    "type": "Point",
    "coordinates": [
      -92.3333,
      35.15
    ]
  },
  "type": "Feature",
  "properties": {
    "hierarchy": [
      "tgn:2200571",
      "tgn:1000001",
      "tgn:7016172",
      "tgn:7012149",
      "tgn:2000127",
      "tgn:7029392"
    ],
    "placetype": [
      "aat:300008905"
    ],
    "id": 2200571,
    "name:xx": "Brushy Pond"
  }
}
