{
  "geometry": {
    "type": "Point",
    "coordinates": [
      23.3333,
      44.0167
    ]
  },
  "type": "Feature",
  "properties": {
    "hierarchy": [
      "tgn:1050016",
      "tgn:1000003",
      "tgn:1000364",
      "tgn:1000091",
      "tgn:7029392"
    ],
    "placetype": [
      "aat:300008347"
    ],
    "id": 1050016,
    "name:xx": "Băilești"
  }
}
