{
  "geometry": {
    "type": "Point",
    "coordinates": [
      -78.4667,
      36.0167
    ]
  },
  "type": "Feature",
  "properties": {
    "hierarchy": [
      "tgn:2077368",
      "tgn:1000001",
      "tgn:7012149",
      "tgn:7013940",
      "tgn:7007709",
      "tgn:7029392"
    ],
    "placetype": [
      "aat:300008347"
    ],
    "id": 2077368,
    "name:xx": "Youngsville"
  }
}
