{
  "geometry": {
    "type": "Point",
    "coordinates": [
      -98.3333,
      49.9667
    ]
  },
  "type": "Feature",
  "properties": {
    "hierarchy": [
      "tgn:7013036",
      "tgn:7005685",
      "tgn:1000001",
      "tgn:7005734",
      "tgn:7029392"
    ],
    "placetype": [
      "aat:300008347",
      "aat:300008389",
      "aat:300387270",
      "aat:300387285"
    ],
    "id": 7013036,
    "name:xx": "Portage la Prairie"
  }
}
