{
  "geometry": {
    "type": "Point",
    "coordinates": [
      77.220905,
      29.881485
    ]
  },
  "type": "Feature",
  "properties": {
    "hierarchy": [
      "tgn:7589913",
      "tgn:1000004",
      "tgn:7000198",
      "tgn:7016722",
      "tgn:7029392"
    ],
    "placetype": [
      "aat:300008347"
    ],
    "name:en": "Dāla Mājra",
    "id": 7589913
  }
}
