{
  "geometry": {
    "type": "Point",
    "coordinates": [
      -1.3833,
      12.9667
    ]
  },
  "type": "Feature",
  "properties": {
    "hierarchy": [
      "tgn:1095830",
      "tgn:7024160",
      "tgn:7001242",
      "tgn:1000558",
      "tgn:1000208",
      "tgn:7029392"
    ],
    "placetype": [
      "aat:300008347"
    ],
    "id": 1095830,
    "name:xx": "Mané"
  }
}
