{
  "geometry": {
    "type": "Point",
    "coordinates": [
      -74.9167,
      42.2333
    ]
  },
  "type": "Feature",
  "properties": {
    "hierarchy": [
      "tgn:2648773",
      "tgn:1000001",
      "tgn:1002328",
      "tgn:7012149",
      "tgn:7007568",
      "tgn:7029392"
    ],
    "placetype": [
      "aat:300008798"
    ],
    "id": 2648773,
    "name:xx": "Scotch Mountain"
  }
}
