{
  "geometry": {
    "type": "Point",
    "coordinates": [
      78.5375,
      17.1775
    ]
  },
  "type": "Feature",
  "properties": {
    "hierarchy": [
      "tgn:7569792",
      "tgn:1001828",
      "tgn:1000004",
      "tgn:7000198",
      "tgn:7029392"
    ],
    "placetype": [
      "aat:300007595"
    ],
    "name:en": "Bālāji Temple",
    "id": 7569792
  }
}
