{
  "geometry": {
    "type": "Point",
    "coordinates": [
      -87.2333,
      37.75
    ]
  },
  "type": "Feature",
  "properties": {
    "hierarchy": [
      "tgn:2041361",
      "tgn:1000001",
      "tgn:7012149",
      "tgn:2000786",
      "tgn:7007255",
      "tgn:7029392"
    ],
    "placetype": [
      "aat:300008347"
    ],
    "id": 2041361,
    "name:xx": "Sorgho"
  }
}
