{
  "geometry": {
    "type": "Point",
    "coordinates": [
      -87.1833,
      34.8833
    ]
  },
  "type": "Feature",
  "properties": {
    "hierarchy": [
      "tgn:2501365",
      "tgn:7002659",
      "tgn:1000001",
      "tgn:7012149",
      "tgn:2000041",
      "tgn:7029392"
    ],
    "placetype": [
      "aat:300008699"
    ],
    "id": 2501365,
    "name:xx": "McGowan Branch"
  }
}
