{
  "type": "FeatureCollection",
  "features": [
    {
      "geometry": {
        "type": "Point",
        "coordinates": [
          -109.1,
          40.1833
        ]
      },
      "type": "Feature",
      "properties": {
        "hierarchy": [
          "tgn:2279250",
          "tgn:1000001",
          "tgn:7012149",
          "tgn:2002124",
          "tgn:7007827",
          "tgn:7029392"
        ],
        "placetype": [
          "aat:300266640"
        ],
        "id": 2279250,
        "name:xx": "Deadman Bench Divide"
      }
    },
    {
      "geometry": {
        "type": "Point",
        "coordinates": [
          -67.75,
          45.3833
        ]
      },
      "type": "Feature",
      "properties": {
        "hierarchy": [
          "tgn:2279251",
          "tgn:1000001",
          "tgn:7012149",
          "tgn:7014589",
          "tgn:7007515",
          "tgn:7029392"
        ],
        "placetype": [
          "aat:300008905"
        ],
        "id": 2279251,
        "name:xx": "Deadman Bog"
      }
    },
    {
      "geometry": {
        "type": "Point",
        "coordinates": [
          -88.1,
          34.3833
        ]
      },
      "type": "Feature",
      "properties": {
        "hierarchy": [
          "tgn:2279252",
          "tgn:7002659",
          "tgn:1000001",
          "tgn:7012149",
          "tgn:2000029",
          "tgn:7029392"
        ],
        "placetype": [
          "aat:300008699"
        ],
        "id": 2279252,
        "name:xx": "Deadman Branch"
      }
    },
    {
      "geometry": {
        "type": "Point",
        "coordinates": [
          -82.9167,
          37.2667
        ]
      },
      "type": "Feature",
      "properties": {
        "hierarchy": [
          "tgn:2279253",
          "tgn:1000001",
          "tgn:7012149",
          "tgn:2000805",
          "tgn:7007255",
          "tgn:7029392"
        ],
        "placetype": [
          "aat:300008699"
        ],
        "id": 2279253,
        "name:xx": "Deadman Branch"
      }
    },
    {
      "geometry": {
        "type": "Point",
        "coordinates": [
          -89.2667,
          31.7
        ]
      },
      "type": "Feature",
      "properties": {
        "hierarchy": [
          "tgn:2279254",
          "tgn:1000001",
          "tgn:7012149",
          "tgn:2001119",
          "tgn:7007522",
          "tgn:7029392"
        ],
        "placetype": [
          "aat:300008699"
        ],
        "id": 2279254,
        "name:xx": "Deadman Branch"
      }
    },
    {
      "geometry": {
        "type": "Point",
        "coordinates": [
          -97.0833,
          34.3
        ]
      },
      "type": "Feature",
      "properties": {
        "hierarchy": [
          "tgn:2279255",
          "tgn:1000001",
          "tgn:2001632",
          "tgn:7012149",
          "tgn:7007707",
          "tgn:7029392"
        ],
        "placetype": [
          "aat:300008699"
        ],
        "id": 2279255,
        "name:xx": "Deadman Branch"
      }
    },
    {
      "geometry": {
        "type": "Point",
        "coordinates": [
          -94.95,
          33.75
        ]
      },
      "type": "Feature",
      "properties": {
        "hierarchy": [
          "tgn:2279256",
          "tgn:1000001",
          "tgn:7012149",
          "tgn:7029392"
        ],
        "placetype": [
          "aat:300008699"
        ],
        "id": 2279256,
        "name:xx": "Deadman Branch"
      }
    },
    {
      "geometry": {
        "type": "Point",
        "coordinates": [
          -80.1,
          34.5333
        ]
      },
      "type": "Feature",
      "properties": {
        "hierarchy": [
          "tgn:2279257",
          "tgn:1000001",
          "tgn:2001737",
          "tgn:7012149",
          "tgn:7007712",
          "tgn:7029392"
        ],
        "placetype": [
          "aat:300008699"
        ],
        "id": 2279257,
        "name:xx": "Deadman Branch"
      }
    },
    {
      "geometry": {
        "type": "Point",
        "coordinates": [
          -88.95,
          35.1667
        ]
      },
      "type": "Feature",
      "properties": {
        "hierarchy": [
          "tgn:2279258",
          "tgn:1000001",
          "tgn:7012149",
          "tgn:2001871",
          "tgn:7007825",
          "tgn:7029392"
        ],
        "placetype": [
          "aat:300008699"
        ],
        "id": 2279258,
        "name:xx": "Deadman Branch"
      }
    },
    {
      "geometry": {
        "type": "Point",
        "coordinates": [
          -100,
          33.0333
        ]
      },
      "type": "Feature",
      "properties": {
        "hierarchy": [
          "tgn:2279259",
          "tgn:1000001",
          "tgn:7012149",
          "tgn:7007826",
          "tgn:7029392"
        ],
        "placetype": [
          "aat:300008699"
        ],
        "id": 2279259,
        "name:xx": "Deadman Branch"
      }
    }
  ]
}
