{
  "geometry": {
    "type": "Point",
    "coordinates": [
      -73.65,
      43.8333
    ]
  },
  "type": "Feature",
  "properties": {
    "hierarchy": [
      "tgn:2351933",
      "tgn:1000001",
      "tgn:7012149",
      "tgn:2001461",
      "tgn:7007568",
      "tgn:7029392"
    ],
    "placetype": [
      "aat:300008905"
    ],
    "id": 2351933,
    "name:xx": "Glidden Marsh"
  }
}
