{
  "type": "FeatureCollection",
  "features": [
    {
      "geometry": {
        "type": "Point",
        "coordinates": [
          -86.4,
          30.75
        ]
      },
      "type": "Feature",
      "properties": {
        "hierarchy": [
          "tgn:2375180",
          "tgn:1000001",
          "tgn:7012149",
          "tgn:2000281",
          "tgn:7007240",
          "tgn:7029392"
        ],
        "placetype": [
          "aat:300008699"
        ],
        "id": 2375180,
        "name:xx": "Hannah Branch"
      }
    },
    {
      "geometry": {
        "type": "Point",
        "coordinates": [
          -82.3,
          33.1167
        ]
      },
      "type": "Feature",
      "properties": {
        "hierarchy": [
          "tgn:2375181",
          "tgn:1000001",
          "tgn:7012149",
          "tgn:2000372",
          "tgn:7007248",
          "tgn:7029392"
        ],
        "placetype": [
          "aat:300008699"
        ],
        "id": 2375181,
        "name:xx": "Hannah Branch"
      }
    },
    {
      "geometry": {
        "type": "Point",
        "coordinates": [
          -83.5833,
          34.9
        ]
      },
      "type": "Feature",
      "properties": {
        "hierarchy": [
          "tgn:2375182",
          "tgn:1000001",
          "tgn:7012149",
          "tgn:2000410",
          "tgn:7007248",
          "tgn:7029392"
        ],
        "placetype": [
          "aat:300008699"
        ],
        "id": 2375182,
        "name:xx": "Hannah Branch"
      }
    },
    {
      "geometry": {
        "type": "Point",
        "coordinates": [
          -92.85,
          37.2833
        ]
      },
      "type": "Feature",
      "properties": {
        "hierarchy": [
          "tgn:2375183",
          "tgn:1000001",
          "tgn:7012149",
          "tgn:2001256",
          "tgn:7007523",
          "tgn:7029392"
        ],
        "placetype": [
          "aat:300008699"
        ],
        "id": 2375183,
        "name:xx": "Hannah Branch"
      }
    },
    {
      "geometry": {
        "type": "Point",
        "coordinates": [
          -76.9667,
          34.7167
        ]
      },
      "type": "Feature",
      "properties": {
        "hierarchy": [
          "tgn:2375184",
          "tgn:1000001",
          "tgn:2001477",
          "tgn:7012149",
          "tgn:7007709",
          "tgn:7029392"
        ],
        "placetype": [
          "aat:300008699"
        ],
        "id": 2375184,
        "name:xx": "Hannah Branch"
      }
    },
    {
      "geometry": {
        "type": "Point",
        "coordinates": [
          -82.1667,
          35.8167
        ]
      },
      "type": "Feature",
      "properties": {
        "hierarchy": [
          "tgn:2375185",
          "tgn:1000001",
          "tgn:7012149",
          "tgn:2001556",
          "tgn:7007709",
          "tgn:7029392"
        ],
        "placetype": [
          "aat:300008699"
        ],
        "id": 2375185,
        "name:xx": "Hannah Branch"
      }
    },
    {
      "geometry": {
        "type": "Point",
        "coordinates": [
          -83.9167,
          35.55
        ]
      },
      "type": "Feature",
      "properties": {
        "hierarchy": [
          "tgn:2375186",
          "tgn:1000001",
          "tgn:2001841",
          "tgn:7012149",
          "tgn:7007825",
          "tgn:7029392"
        ],
        "placetype": [
          "aat:300008699"
        ],
        "id": 2375186,
        "name:xx": "Hannah Branch"
      }
    },
    {
      "geometry": {
        "type": "Point",
        "coordinates": [
          -85.8667,
          36.0333
        ]
      },
      "type": "Feature",
      "properties": {
        "hierarchy": [
          "tgn:2375187",
          "tgn:1000001",
          "tgn:7012149",
          "tgn:7022246",
          "tgn:7007825",
          "tgn:7029392"
        ],
        "placetype": [
          "aat:300008699"
        ],
        "id": 2375187,
        "name:xx": "Hannah Branch"
      }
    },
    {
      "geometry": {
        "type": "Point",
        "coordinates": [
          -87.0333,
          36.1167
        ]
      },
      "type": "Feature",
      "properties": {
        "hierarchy": [
          "tgn:2375188",
          "tgn:1000001",
          "tgn:7012149",
          "tgn:2001847",
          "tgn:7007825",
          "tgn:7029392"
        ],
        "placetype": [
          "aat:300008699"
        ],
        "id": 2375188,
        "name:xx": "Hannah Branch"
      }
    },
    {
      "geometry": {
        "type": "Point",
        "coordinates": [
          -81.9667,
          36.4333
        ]
      },
      "type": "Feature",
      "properties": {
        "hierarchy": [
          "tgn:2375189",
          "tgn:1000001",
          "tgn:7012149",
          "tgn:2001846",
          "tgn:7007825",
          "tgn:7029392"
        ],
        "placetype": [
          "aat:300008699"
        ],
        "id": 2375189,
        "name:xx": "Hannah Branch"
      }
    }
  ]
}
