{
  "type": "FeatureCollection",
  "features": [
    {
      "geometry": {
        "type": "Point",
        "coordinates": [
          4.236498,
          51.097123
        ]
      },
      "type": "Feature",
      "properties": {
        "hierarchy": [
          "tgn:4001700",
          "tgn:7003456",
          "tgn:1000003",
          "tgn:1000063",
          "tgn:7018236",
          "tgn:7029392"
        ],
        "placetype": [
          "aat:300008347"
        ],
        "id": 4001700,
        "name:xx": "Bornem"
      }
    },
    {
      "geometry": {
        "type": "Point",
        "coordinates": [
          5.966667,
          53.333333
        ]
      },
      "type": "Feature",
      "properties": {
        "hierarchy": [
          "tgn:4001703",
          "tgn:7003616",
          "tgn:1000003",
          "tgn:7016845",
          "tgn:7029392"
        ],
        "placetype": [
          "aat:300008347"
        ],
        "name:nl": "Bornwird",
        "id": 4001703
      }
    },
    {
      "geometry": {
        "type": "Point",
        "coordinates": [
          11.8,
          45.816667
        ]
      },
      "type": "Feature",
      "properties": {
        "hierarchy": [
          "tgn:4001706",
          "tgn:7002996",
          "tgn:1000003",
          "tgn:7002997",
          "tgn:1000080",
          "tgn:7029392"
        ],
        "placetype": [
          "aat:300008347"
        ],
        "id": 4001706,
        "name:xx": "Borso del Grappa"
      }
    }
  ]
}
