{
  "geometry": {
    "type": "Point",
    "coordinates": [
      -95.9833,
      37.2333
    ]
  },
  "type": "Feature",
  "properties": {
    "hierarchy": [
      "tgn:2159398",
      "tgn:1000001",
      "tgn:7012149",
      "tgn:7007254",
      "tgn:7029392"
    ],
    "placetype": [
      "aat:300008706"
    ],
    "id": 2159398,
    "name:xx": "Bee Creek"
  }
}
