{
  "geometry": {
    "type": "Point",
    "coordinates": [
      31.223755,
      30.056473
    ]
  },
  "type": "Feature",
  "properties": {
    "hierarchy": [
      "tgn:7530091",
      "tgn:7001242",
      "tgn:7016833",
      "tgn:1001083",
      "tgn:7029392"
    ],
    "placetype": [
      "aat:300005768"
    ],
    "id": 7530091,
    "name:xx": "Mutḩaf Maḩmūd Khalīl"
  }
}
