{
  "type": "FeatureCollection",
  "features": [
    {
      "geometry": {
        "type": "Point",
        "coordinates": [
          125.95,
          10.7667
        ]
      },
      "type": "Feature",
      "properties": {
        "hierarchy": [
          "tgn:1009291",
          "tgn:1000004",
          "tgn:1001231",
          "tgn:1000135",
          "tgn:7029392"
        ],
        "placetype": [
          "aat:300008791"
        ],
        "id": 1009291,
        "name:xx": "Suluan Island"
      }
    },
    {
      "geometry": {
        "type": "Point",
        "coordinates": [
          140.0833,
          31.45
        ]
      },
      "type": "Feature",
      "properties": {
        "hierarchy": [
          "tgn:1009296",
          "tgn:7000895",
          "tgn:1000004",
          "tgn:1001031",
          "tgn:1010054",
          "tgn:1000120",
          "tgn:7029392"
        ],
        "placetype": [
          "aat:300008791"
        ],
        "id": 1009296,
        "name:xx": "Sumisu-jima"
      }
    },
    {
      "geometry": {
        "type": "Point",
        "coordinates": [
          -86.6333,
          45.55
        ]
      },
      "type": "Feature",
      "properties": {
        "hierarchy": [
          "tgn:1009297",
          "tgn:1000001",
          "tgn:2000955",
          "tgn:7012149",
          "tgn:7007520",
          "tgn:7029392"
        ],
        "placetype": [
          "aat:300008791"
        ],
        "id": 1009297,
        "name:xx": "Summer Island"
      }
    }
  ]
}
