{
  "geometry": {
    "type": "Point",
    "coordinates": [
      -92.3333,
      35.6833
    ]
  },
  "type": "Feature",
  "properties": {
    "hierarchy": [
      "tgn:2153584",
      "tgn:1000001",
      "tgn:7016172",
      "tgn:7012149",
      "tgn:2000175",
      "tgn:7029392"
    ],
    "placetype": [
      "aat:300008699"
    ],
    "id": 2153584,
    "name:xx": "Bear Branch"
  }
}
