{
  "geometry": {
    "type": "Point",
    "coordinates": [
      -84.9667,
      36.6667
    ]
  },
  "type": "Feature",
  "properties": {
    "hierarchy": [
      "tgn:2518646",
      "tgn:1000001",
      "tgn:7012149",
      "tgn:2000850",
      "tgn:7007255",
      "tgn:7029392"
    ],
    "placetype": [
      "aat:300008798"
    ],
    "id": 2518646,
    "name:xx": "Mitchell Knob"
  }
}
