{
  "geometry": {
    "type": "Point",
    "coordinates": [
      -108.0833,
      37.4167
    ]
  },
  "type": "Feature",
  "properties": {
    "hierarchy": [
      "tgn:2210173",
      "tgn:1000001",
      "tgn:7012149",
      "tgn:7007158",
      "tgn:7029392"
    ],
    "placetype": [
      "aat:300008798"
    ],
    "id": 2210173,
    "name:xx": "Burwell Peak"
  }
}
