{
  "geometry": {
    "type": "Point",
    "coordinates": [
      -81.2833,
      29.8667
    ]
  },
  "type": "Feature",
  "properties": {
    "hierarchy": [
      "tgn:2603024",
      "tgn:1000001",
      "tgn:7012149",
      "tgn:2000283",
      "tgn:7007240",
      "tgn:7029392"
    ],
    "placetype": [
      "aat:300008706"
    ],
    "id": 2603024,
    "name:xx": "Quarry Creek"
  }
}
