{
  "geometry": {
    "type": "Point",
    "coordinates": [
      121.8107,
      25.1302
    ]
  },
  "type": "Feature",
  "properties": {
    "hierarchy": [
      "tgn:7493042",
      "tgn:1000004",
      "tgn:1000454",
      "tgn:1000141",
      "tgn:7029392"
    ],
    "placetype": [
      "aat:300387173"
    ],
    "id": 7493042,
    "name:xx": "Shen'ao Li"
  }
}
