{
  "type": "FeatureCollection",
  "features": [
    {
      "geometry": {
        "type": "Point",
        "coordinates": [
          -82.3,
          37.0167
        ]
      },
      "type": "Feature",
      "properties": {
        "hierarchy": [
          "tgn:2154910",
          "tgn:1000001",
          "tgn:7012149",
          "tgn:2002157",
          "tgn:7007919",
          "tgn:7029392"
        ],
        "placetype": [
          "aat:300008761"
        ],
        "id": 2154910,
        "name:xx": "Bear Hollow"
      }
    },
    {
      "geometry": {
        "type": "Point",
        "coordinates": [
          -82.2,
          37.3333
        ]
      },
      "type": "Feature",
      "properties": {
        "hierarchy": [
          "tgn:2154911",
          "tgn:1000001",
          "tgn:2002148",
          "tgn:7012149",
          "tgn:7007919",
          "tgn:7029392"
        ],
        "placetype": [
          "aat:300008761"
        ],
        "id": 2154911,
        "name:xx": "Bear Hollow"
      }
    },
    {
      "geometry": {
        "type": "Point",
        "coordinates": [
          -79.5333,
          37.5333
        ]
      },
      "type": "Feature",
      "properties": {
        "hierarchy": [
          "tgn:2154912",
          "tgn:1000001",
          "tgn:2002146",
          "tgn:7012149",
          "tgn:7007919",
          "tgn:7029392"
        ],
        "placetype": [
          "aat:300008761"
        ],
        "id": 2154912,
        "name:xx": "Bear Hollow"
      }
    },
    {
      "geometry": {
        "type": "Point",
        "coordinates": [
          -80.0667,
          37.8667
        ]
      },
      "type": "Feature",
      "properties": {
        "hierarchy": [
          "tgn:2154913",
          "tgn:2002138",
          "tgn:1000001",
          "tgn:7012149",
          "tgn:7007919",
          "tgn:7029392"
        ],
        "placetype": [
          "aat:300008761"
        ],
        "id": 2154913,
        "name:xx": "Bear Hollow"
      }
    },
    {
      "geometry": {
        "type": "Point",
        "coordinates": [
          -79.7667,
          38.2667
        ]
      },
      "type": "Feature",
      "properties": {
        "hierarchy": [
          "tgn:2154914",
          "tgn:1000001",
          "tgn:7012149",
          "tgn:2002168",
          "tgn:7007919",
          "tgn:7029392"
        ],
        "placetype": [
          "aat:300008761"
        ],
        "id": 2154914,
        "name:xx": "Bear Hollow"
      }
    },
    {
      "geometry": {
        "type": "Point",
        "coordinates": [
          -78.1167,
          38.8833
        ]
      },
      "type": "Feature",
      "properties": {
        "hierarchy": [
          "tgn:2154915",
          "tgn:1000001",
          "tgn:7012149",
          "tgn:2002193",
          "tgn:7007919",
          "tgn:7029392"
        ],
        "placetype": [
          "aat:300008761"
        ],
        "id": 2154915,
        "name:xx": "Bear Hollow"
      }
    },
    {
      "geometry": {
        "type": "Point",
        "coordinates": [
          -81.9167,
          37.5667
        ]
      },
      "type": "Feature",
      "properties": {
        "hierarchy": [
          "tgn:2154916",
          "tgn:1000001",
          "tgn:7012149",
          "tgn:2002280",
          "tgn:7013961",
          "tgn:7029392"
        ],
        "placetype": [
          "aat:300008761"
        ],
        "id": 2154916,
        "name:xx": "Bear Hollow"
      }
    },
    {
      "geometry": {
        "type": "Point",
        "coordinates": [
          -81.35,
          37.95
        ]
      },
      "type": "Feature",
      "properties": {
        "hierarchy": [
          "tgn:2154917",
          "tgn:1000001",
          "tgn:7012149",
          "tgn:2002290",
          "tgn:7013961",
          "tgn:7029392"
        ],
        "placetype": [
          "aat:300008761"
        ],
        "id": 2154917,
        "name:xx": "Bear Hollow"
      }
    },
    {
      "geometry": {
        "type": "Point",
        "coordinates": [
          -81.5167,
          37.9833
        ]
      },
      "type": "Feature",
      "properties": {
        "hierarchy": [
          "tgn:2154918",
          "tgn:1000001",
          "tgn:2002255",
          "tgn:7012149",
          "tgn:7013961",
          "tgn:7029392"
        ],
        "placetype": [
          "aat:300008761"
        ],
        "id": 2154918,
        "name:xx": "Bear Hollow"
      }
    },
    {
      "geometry": {
        "type": "Point",
        "coordinates": [
          -81.4167,
          38.0833
        ]
      },
      "type": "Feature",
      "properties": {
        "hierarchy": [
          "tgn:2154919",
          "tgn:1000001",
          "tgn:7012149",
          "tgn:2002270",
          "tgn:7013961",
          "tgn:7029392"
        ],
        "placetype": [
          "aat:300008761"
        ],
        "id": 2154919,
        "name:xx": "Bear Hollow"
      }
    }
  ]
}
