{
  "type": "FeatureCollection",
  "features": [
    {
      "geometry": {
        "type": "Point",
        "coordinates": [
          97.6667,
          54.5
        ]
      },
      "type": "Feature",
      "properties": {
        "hierarchy": [
          "tgn:1109994",
          "tgn:1003373",
          "tgn:1000004",
          "tgn:7018214",
          "tgn:7002435",
          "tgn:7029392"
        ],
        "placetype": [
          "aat:300386831"
        ],
        "id": 1109994,
        "name:xx": "Gutarskiy Khrebet"
      }
    },
    {
      "geometry": {
        "type": "Point",
        "coordinates": [
          73.5,
          19.5
        ]
      },
      "type": "Feature",
      "properties": {
        "hierarchy": [
          "tgn:1109997",
          "tgn:1000004",
          "tgn:7000198",
          "tgn:1001895",
          "tgn:7029392"
        ],
        "placetype": [
          "aat:300386831",
          "aat:300008795"
        ],
        "name:en": "Harischandra Range",
        "id": 1109997
      }
    },
    {
      "geometry": {
        "type": "Point",
        "coordinates": [
          175.566667,
          -38.683333
        ]
      },
      "type": "Feature",
      "properties": {
        "hierarchy": [
          "tgn:1109998",
          "tgn:1008380",
          "tgn:1000226",
          "tgn:7018426",
          "tgn:1000006",
          "tgn:7029392"
        ],
        "placetype": [
          "aat:300386831",
          "aat:300008795"
        ],
        "name:en": "Hauhungaroa Range",
        "id": 1109998
      }
    },
    {
      "geometry": {
        "type": "Point",
        "coordinates": [
          170,
          -44.766667
        ]
      },
      "type": "Feature",
      "properties": {
        "hierarchy": [
          "tgn:1109999",
          "tgn:1009227",
          "tgn:1000226",
          "tgn:1000006",
          "tgn:7029392"
        ],
        "placetype": [
          "aat:300386831",
          "aat:300008795"
        ],
        "name:en": "Hawkdun Range",
        "id": 1109999
      }
    }
  ]
}
