{
  "geometry": {
    "type": "Point",
    "coordinates": [
      -84.4833,
      38.9833
    ]
  },
  "type": "Feature",
  "properties": {
    "hierarchy": [
      "tgn:2041584",
      "tgn:1000001",
      "tgn:7012149",
      "tgn:1002544",
      "tgn:7007255",
      "tgn:7029392"
    ],
    "placetype": [
      "aat:300008347"
    ],
    "id": 2041584,
    "name:xx": "Taylor Mill"
  }
}
