{
  "type": "FeatureCollection",
  "features": [
    {
      "geometry": {
        "type": "Point",
        "coordinates": [
          -107.5167,
          40.2
        ]
      },
      "type": "Feature",
      "properties": {
        "hierarchy": [
          "tgn:2775890",
          "tgn:1000001",
          "tgn:7012149",
          "tgn:7007158",
          "tgn:2000243",
          "tgn:7029392"
        ],
        "placetype": [
          "aat:300008798"
        ],
        "id": 2775890,
        "name:xx": "Wilson Mesa"
      }
    },
    {
      "geometry": {
        "type": "Point",
        "coordinates": [
          -107.95,
          37.9
        ]
      },
      "type": "Feature",
      "properties": {
        "hierarchy": [
          "tgn:2775891",
          "tgn:1000001",
          "tgn:7012149",
          "tgn:7007158",
          "tgn:2000248",
          "tgn:7029392"
        ],
        "placetype": [
          "aat:300008798"
        ],
        "id": 2775891,
        "name:xx": "Wilson Mesa"
      }
    },
    {
      "geometry": {
        "type": "Point",
        "coordinates": [
          -105.1,
          36.6333
        ]
      },
      "type": "Feature",
      "properties": {
        "hierarchy": [
          "tgn:2775892",
          "tgn:1000001",
          "tgn:2001432",
          "tgn:7012149",
          "tgn:7007566",
          "tgn:7029392"
        ],
        "placetype": [
          "aat:300008798"
        ],
        "id": 2775892,
        "name:xx": "Wilson Mesa"
      }
    },
    {
      "geometry": {
        "type": "Point",
        "coordinates": [
          -110.7667,
          37.2667
        ]
      },
      "type": "Feature",
      "properties": {
        "hierarchy": [
          "tgn:2775893",
          "tgn:1000001",
          "tgn:7012149",
          "tgn:2002119",
          "tgn:7007827",
          "tgn:7029392"
        ],
        "placetype": [
          "aat:300008798"
        ],
        "id": 2775893,
        "name:xx": "Wilson Mesa"
      }
    },
    {
      "geometry": {
        "type": "Point",
        "coordinates": [
          -109.3667,
          38.5333
        ]
      },
      "type": "Feature",
      "properties": {
        "hierarchy": [
          "tgn:2775894",
          "tgn:1000001",
          "tgn:7012149",
          "tgn:2002110",
          "tgn:7007827",
          "tgn:7029392"
        ],
        "placetype": [
          "aat:300008798"
        ],
        "id": 2775894,
        "name:xx": "Wilson Mesa"
      }
    },
    {
      "geometry": {
        "type": "Point",
        "coordinates": [
          -84.2333,
          34.7167
        ]
      },
      "type": "Feature",
      "properties": {
        "hierarchy": [
          "tgn:2775895",
          "tgn:1000001",
          "tgn:7012149",
          "tgn:2000346",
          "tgn:7007248",
          "tgn:7029392"
        ],
        "placetype": [
          "aat:300008347"
        ],
        "id": 2775895,
        "name:xx": "Wilson Mill"
      }
    },
    {
      "geometry": {
        "type": "Point",
        "coordinates": [
          -76.2,
          39.6167
        ]
      },
      "type": "Feature",
      "properties": {
        "hierarchy": [
          "tgn:2775896",
          "tgn:1000001",
          "tgn:7016102",
          "tgn:7012149",
          "tgn:7007516",
          "tgn:7029392"
        ],
        "placetype": [
          "aat:300008347"
        ],
        "id": 2775896,
        "name:xx": "Wilson Mill"
      }
    },
    {
      "geometry": {
        "type": "Point",
        "coordinates": [
          -88.1167,
          34.5333
        ]
      },
      "type": "Feature",
      "properties": {
        "hierarchy": [
          "tgn:2775897",
          "tgn:7002659",
          "tgn:1000001",
          "tgn:7012149",
          "tgn:2000029",
          "tgn:7029392"
        ],
        "placetype": [
          "aat:300008699"
        ],
        "id": 2775897,
        "name:xx": "Wilson Mill Branch"
      }
    },
    {
      "geometry": {
        "type": "Point",
        "coordinates": [
          -85.0833,
          30.6167
        ]
      },
      "type": "Feature",
      "properties": {
        "hierarchy": [
          "tgn:2775898",
          "tgn:1000001",
          "tgn:7012149",
          "tgn:7007240",
          "tgn:7029392"
        ],
        "placetype": [
          "aat:300008706"
        ],
        "id": 2775898,
        "name:xx": "Wilson Mill Creek"
      }
    },
    {
      "geometry": {
        "type": "Point",
        "coordinates": [
          -82.7833,
          35.2
        ]
      },
      "type": "Feature",
      "properties": {
        "hierarchy": [
          "tgn:2775899",
          "tgn:1000001",
          "tgn:7012149",
          "tgn:2001544",
          "tgn:7007709",
          "tgn:7029392"
        ],
        "placetype": [
          "aat:300008706"
        ],
        "id": 2775899,
        "name:xx": "Wilson Mill Creek"
      }
    }
  ]
}
