{
  "geometry": {
    "type": "Point",
    "coordinates": [
      -86.2667,
      31.15
    ]
  },
  "type": "Feature",
  "properties": {
    "hierarchy": [
      "tgn:2598600",
      "tgn:7002659",
      "tgn:1000001",
      "tgn:2000019",
      "tgn:7012149",
      "tgn:7029392"
    ],
    "placetype": [
      "aat:300008706"
    ],
    "id": 2598600,
    "name:xx": "Prices Creek"
  }
}
