{
  "geometry": {
    "type": "Point",
    "coordinates": [
      17.15,
      20.7667
    ]
  },
  "type": "Feature",
  "properties": {
    "hierarchy": [
      "tgn:1088507",
      "tgn:7001242",
      "tgn:1000968",
      "tgn:1000156",
      "tgn:7029392"
    ],
    "placetype": [
      "aat:300008347"
    ],
    "id": 1088507,
    "name:xx": "Goubon"
  }
}
