{
  "geometry": {
    "type": "Point",
    "coordinates": [
      -91.0833,
      46.0667
    ]
  },
  "type": "Feature",
  "properties": {
    "hierarchy": [
      "tgn:2713619",
      "tgn:1000001",
      "tgn:7012149",
      "tgn:2002353",
      "tgn:7007922",
      "tgn:7029392"
    ],
    "placetype": [
      "aat:300008707"
    ],
    "id": 2713619,
    "name:xx": "Teal River"
  }
}
