{
  "geometry": {
    "type": "Point",
    "coordinates": [
      40.1167,
      45.8667
    ]
  },
  "type": "Feature",
  "properties": {
    "hierarchy": [
      "tgn:1060293",
      "tgn:1000004",
      "tgn:7011531",
      "tgn:7018214",
      "tgn:7002435",
      "tgn:7029392"
    ],
    "placetype": [
      "aat:300008347"
    ],
    "id": 1060293,
    "name:xx": "Tikhoretsk"
  }
}
