{
  "geometry": {
    "type": "Point",
    "coordinates": [
      -71.3333,
      42.6333
    ]
  },
  "type": "Feature",
  "properties": {
    "hierarchy": [
      "tgn:2510683",
      "tgn:1000001",
      "tgn:1002665",
      "tgn:7012149",
      "tgn:7007517",
      "tgn:7029392"
    ],
    "placetype": [
      "aat:300008347"
    ],
    "id": 2510683,
    "name:xx": "Middlesex Village"
  }
}
