{
  "geometry": {
    "type": "Point",
    "coordinates": [
      -121.65,
      46.8167
    ]
  },
  "type": "Feature",
  "properties": {
    "hierarchy": [
      "tgn:2150197",
      "tgn:1000001",
      "tgn:7012149",
      "tgn:1002785",
      "tgn:7007920",
      "tgn:7029392"
    ],
    "placetype": [
      "aat:300008706"
    ],
    "id": 2150197,
    "name:xx": "Basalt Creek"
  }
}
