{
  "geometry": {
    "type": "Point",
    "coordinates": [
      -77.7667,
      39.45
    ]
  },
  "type": "Feature",
  "properties": {
    "hierarchy": [
      "tgn:2674607",
      "tgn:1000001",
      "tgn:7016106",
      "tgn:7012149",
      "tgn:7007516",
      "tgn:7029392"
    ],
    "placetype": [
      "aat:300008347"
    ],
    "id": 2674607,
    "name:xx": "Snyders Landing"
  }
}
