{
  "geometry": {
    "type": "Point",
    "coordinates": [
      -69.55,
      43.8333
    ]
  },
  "type": "Feature",
  "properties": {
    "hierarchy": [
      "tgn:2381615",
      "tgn:1000001",
      "tgn:2000925",
      "tgn:7012149",
      "tgn:7007515",
      "tgn:7029392"
    ],
    "placetype": [
      "aat:300008791"
    ],
    "id": 2381615,
    "name:xx": "Hay Island"
  }
}
