{
  "geometry": {
    "type": "Point",
    "coordinates": [
      -97.9333,
      31.7667
    ]
  },
  "type": "Feature",
  "properties": {
    "hierarchy": [
      "tgn:2681573",
      "tgn:1000001",
      "tgn:7012149",
      "tgn:7007826",
      "tgn:7029392"
    ],
    "placetype": [
      "aat:300008706"
    ],
    "id": 2681573,
    "name:xx": "South Prong Meridan Creek"
  }
}
