{
  "geometry": {
    "type": "Point",
    "coordinates": [
      -88.5333,
      37.45
    ]
  },
  "type": "Feature",
  "properties": {
    "hierarchy": [
      "tgn:2607229",
      "tgn:1000001",
      "tgn:7012149",
      "tgn:2000523",
      "tgn:7007251",
      "tgn:7029392"
    ],
    "placetype": [
      "aat:300008699"
    ],
    "id": 2607229,
    "name:xx": "Randolph Branch"
  }
}
