{
  "geometry": {
    "type": "Point",
    "coordinates": [
      -82.9833,
      38.4333
    ]
  },
  "type": "Feature",
  "properties": {
    "hierarchy": [
      "tgn:2300815",
      "tgn:1000001",
      "tgn:7012149",
      "tgn:1002426",
      "tgn:7007255",
      "tgn:7029392"
    ],
    "placetype": [
      "aat:300008699"
    ],
    "id": 2300815,
    "name:xx": "Duncan Fork"
  }
}
