{
  "geometry": {
    "type": "Point",
    "coordinates": [
      -81.9333,
      39.5667
    ]
  },
  "type": "Feature",
  "properties": {
    "hierarchy": [
      "tgn:2629976",
      "tgn:1000001",
      "tgn:7012149",
      "tgn:2001618",
      "tgn:7007706",
      "tgn:7029392"
    ],
    "placetype": [
      "aat:300008347"
    ],
    "id": 2629976,
    "name:xx": "Rosseau"
  }
}
