{
  "geometry": {
    "type": "Point",
    "coordinates": [
      -86.0833,
      34.05
    ]
  },
  "type": "Feature",
  "properties": {
    "hierarchy": [
      "tgn:2361488",
      "tgn:7002659",
      "tgn:1000001",
      "tgn:2000004",
      "tgn:7012149",
      "tgn:7029392"
    ],
    "placetype": [
      "aat:300008746"
    ],
    "id": 2361488,
    "name:xx": "Graves Cave"
  }
}
