{
  "geometry": {
    "type": "Point",
    "coordinates": [
      -2.85,
      53.2833
    ]
  },
  "type": "Feature",
  "properties": {
    "hierarchy": [
      "tgn:1124275",
      "tgn:7002445",
      "tgn:7008114",
      "tgn:1000003",
      "tgn:7008591",
      "tgn:7029392"
    ],
    "placetype": [
      "aat:300008707"
    ],
    "id": 1124275,
    "name:xx": "Gowy"
  }
}
