{
  "geometry": {
    "type": "Point",
    "coordinates": [
      -107.0333,
      41.4333
    ]
  },
  "type": "Feature",
  "properties": {
    "hierarchy": [
      "tgn:2468692",
      "tgn:1000001",
      "tgn:2002368",
      "tgn:7012149",
      "tgn:7007923",
      "tgn:7029392"
    ],
    "placetype": [
      "aat:300006191"
    ],
    "id": 2468692,
    "name:xx": "Long Pond Reservoir"
  }
}
