{
  "geometry": {
    "type": "Point",
    "coordinates": [
      -48.2333,
      -18.3167
    ]
  },
  "type": "Feature",
  "properties": {
    "hierarchy": [
      "tgn:1020620",
      "tgn:7012827",
      "tgn:7002454",
      "tgn:1000047",
      "tgn:1000002",
      "tgn:7029392"
    ],
    "placetype": [
      "aat:300008347"
    ],
    "id": 1020620,
    "name:xx": "Anhanguera"
  }
}
