{
  "geometry": {
    "type": "Point",
    "coordinates": [
      78.05,
      12.516667
    ]
  },
  "type": "Feature",
  "properties": {
    "hierarchy": [
      "tgn:7558399",
      "tgn:1000004",
      "tgn:7000198",
      "tgn:7001797",
      "tgn:7029392"
    ],
    "placetype": [
      "aat:300008347"
    ],
    "name:en": "Rāyakottai",
    "id": 7558399
  }
}
