{
  "geometry": {
    "type": "Point",
    "coordinates": [
      149.3833,
      -36.8667
    ]
  },
  "type": "Feature",
  "properties": {
    "hierarchy": [
      "tgn:1096317",
      "tgn:7000490",
      "tgn:1000006",
      "tgn:7001828",
      "tgn:7029392"
    ],
    "placetype": [
      "aat:300008347"
    ],
    "id": 1096317,
    "name:xx": "Bombala"
  }
}
