{
  "type": "FeatureCollection",
  "features": [
    {
      "geometry": {
        "type": "Point",
        "coordinates": [
          -83.1833,
          34.9333
        ]
      },
      "type": "Feature",
      "properties": {
        "hierarchy": [
          "tgn:2023920",
          "tgn:1000001",
          "tgn:7012149",
          "tgn:2000410",
          "tgn:7007248",
          "tgn:7029392"
        ],
        "placetype": [
          "aat:300008347",
          "aat:300387210"
        ],
        "id": 2023920,
        "name:xx": "Pine Mountain"
      }
    },
    {
      "geometry": {
        "type": "Point",
        "coordinates": [
          -84.85,
          32.85
        ]
      },
      "type": "Feature",
      "properties": {
        "hierarchy": [
          "tgn:2023921",
          "tgn:1000001",
          "tgn:7012149",
          "tgn:2000363",
          "tgn:7007248",
          "tgn:7029392"
        ],
        "placetype": [
          "aat:300008347"
        ],
        "id": 2023921,
        "name:xx": "Pine Mountain"
      }
    },
    {
      "geometry": {
        "type": "Point",
        "coordinates": [
          -84.8167,
          32.7833
        ]
      },
      "type": "Feature",
      "properties": {
        "hierarchy": [
          "tgn:2023924",
          "tgn:1000001",
          "tgn:7012149",
          "tgn:2000363",
          "tgn:7007248",
          "tgn:7029392"
        ],
        "placetype": [
          "aat:300008347"
        ],
        "id": 2023924,
        "name:xx": "Pine Mountain Valley"
      }
    },
    {
      "geometry": {
        "type": "Point",
        "coordinates": [
          -81.3833,
          32.2833
        ]
      },
      "type": "Feature",
      "properties": {
        "hierarchy": [
          "tgn:2023925",
          "tgn:1000001",
          "tgn:7012149",
          "tgn:2000342",
          "tgn:7007248",
          "tgn:7029392"
        ],
        "placetype": [
          "aat:300008347"
        ],
        "id": 2023925,
        "name:xx": "Pineora"
      }
    },
    {
      "geometry": {
        "type": "Point",
        "coordinates": [
          -84.1,
          30.85
        ]
      },
      "type": "Feature",
      "properties": {
        "hierarchy": [
          "tgn:2023926",
          "tgn:1000001",
          "tgn:7012149",
          "tgn:2000356",
          "tgn:7007248",
          "tgn:7029392"
        ],
        "placetype": [
          "aat:300008347"
        ],
        "id": 2023926,
        "name:xx": "Pine Park"
      }
    },
    {
      "geometry": {
        "type": "Point",
        "coordinates": [
          -83.5,
          32.1
        ]
      },
      "type": "Feature",
      "properties": {
        "hierarchy": [
          "tgn:2023928",
          "tgn:1000001",
          "tgn:7012149",
          "tgn:2000447",
          "tgn:7007248",
          "tgn:7029392"
        ],
        "placetype": [
          "aat:300008347"
        ],
        "id": 2023928,
        "name:xx": "Pineview"
      }
    }
  ]
}
