{
  "geometry": {
    "type": "Point",
    "coordinates": [
      -96.35,
      33.4333
    ]
  },
  "type": "Feature",
  "properties": {
    "hierarchy": [
      "tgn:2290791",
      "tgn:1000001",
      "tgn:7012149",
      "tgn:2001983",
      "tgn:7007826",
      "tgn:7029392"
    ],
    "placetype": [
      "aat:300008706"
    ],
    "id": 2290791,
    "name:xx": "Dog Creek"
  }
}
