{
  "geometry": {
    "type": "Point",
    "coordinates": [
      33.860278,
      29.795556
    ]
  },
  "type": "Feature",
  "properties": {
    "hierarchy": [
      "tgn:7543679",
      "tgn:7001242",
      "tgn:7016833",
      "tgn:7001336",
      "tgn:7029392"
    ],
    "placetype": [
      "aat:300379998"
    ],
    "id": 7543679,
    "name:xx": "Khādim, Rawḑ al"
  }
}
