{
  "type": "FeatureCollection",
  "features": [
    {
      "geometry": {
        "type": "Point",
        "coordinates": [
          -69.0667,
          46.05
        ]
      },
      "type": "Feature",
      "properties": {
        "hierarchy": [
          "tgn:2177660",
          "tgn:1000001",
          "tgn:7012149",
          "tgn:2000928",
          "tgn:7007515",
          "tgn:7029392"
        ],
        "placetype": [
          "aat:300008905"
        ],
        "id": 2177660,
        "name:xx": "Black Spruce Bog"
      }
    },
    {
      "geometry": {
        "type": "Point",
        "coordinates": [
          -73.7667,
          43.4167
        ]
      },
      "type": "Feature",
      "properties": {
        "hierarchy": [
          "tgn:2177661",
          "tgn:1000001",
          "tgn:7012149",
          "tgn:1002986",
          "tgn:7007568",
          "tgn:7029392"
        ],
        "placetype": [
          "aat:300008798"
        ],
        "id": 2177661,
        "name:xx": "Black Spruce Mountain"
      }
    },
    {
      "geometry": {
        "type": "Point",
        "coordinates": [
          -70.6667,
          45.1
        ]
      },
      "type": "Feature",
      "properties": {
        "hierarchy": [
          "tgn:2177663",
          "tgn:1000001",
          "tgn:2000921",
          "tgn:7012149",
          "tgn:7007515",
          "tgn:7029392"
        ],
        "placetype": [
          "aat:300008798"
        ],
        "id": 2177663,
        "name:xx": "Black Spur"
      }
    },
    {
      "geometry": {
        "type": "Point",
        "coordinates": [
          -83.45,
          38.3667
        ]
      },
      "type": "Feature",
      "properties": {
        "hierarchy": [
          "tgn:2177666",
          "tgn:1000001",
          "tgn:7012149",
          "tgn:1002375",
          "tgn:7007255",
          "tgn:7029392"
        ],
        "placetype": [
          "aat:300008699"
        ],
        "id": 2177666,
        "name:xx": "Black Stairs Branch"
      }
    },
    {
      "geometry": {
        "type": "Point",
        "coordinates": [
          -75.7,
          39.3167
        ]
      },
      "type": "Feature",
      "properties": {
        "hierarchy": [
          "tgn:2177667",
          "tgn:7014201",
          "tgn:1000001",
          "tgn:7012149",
          "tgn:7007239",
          "tgn:7029392"
        ],
        "placetype": [
          "aat:300008699"
        ],
        "id": 2177667,
        "name:xx": "Black Stallion Ditch"
      }
    },
    {
      "geometry": {
        "type": "Point",
        "coordinates": [
          -117.6667,
          33.7667
        ]
      },
      "type": "Feature",
      "properties": {
        "hierarchy": [
          "tgn:2177668",
          "tgn:1000001",
          "tgn:7012149",
          "tgn:7007157",
          "tgn:1002748",
          "tgn:7029392"
        ],
        "placetype": [
          "aat:300000390"
        ],
        "id": 2177668,
        "name:xx": "Black Star Coal Mine"
      }
    },
    {
      "geometry": {
        "type": "Point",
        "coordinates": [
          -117.6167,
          33.8
        ]
      },
      "type": "Feature",
      "properties": {
        "hierarchy": [
          "tgn:2177669",
          "tgn:1000001",
          "tgn:7012149",
          "tgn:7007157",
          "tgn:1002748",
          "tgn:7029392"
        ],
        "placetype": [
          "aat:300008706"
        ],
        "id": 2177669,
        "name:xx": "Black Star Creek"
      }
    }
  ]
}
