{
  "type": "FeatureCollection",
  "features": [
    {
      "geometry": {
        "type": "Point",
        "coordinates": [
          -87.9,
          46.8833
        ]
      },
      "type": "Feature",
      "properties": {
        "hierarchy": [
          "tgn:2633810",
          "tgn:1000001",
          "tgn:7012149",
          "tgn:2000975",
          "tgn:7007520",
          "tgn:7029392"
        ],
        "placetype": [
          "aat:300008680"
        ],
        "id": 2633810,
        "name:xx": "Rush Lake"
      }
    },
    {
      "geometry": {
        "type": "Point",
        "coordinates": [
          -84.0833,
          45.1167
        ]
      },
      "type": "Feature",
      "properties": {
        "hierarchy": [
          "tgn:2633811",
          "tgn:1000001",
          "tgn:7012149",
          "tgn:2000982",
          "tgn:7007520",
          "tgn:7029392"
        ],
        "placetype": [
          "aat:300008680"
        ],
        "id": 2633811,
        "name:xx": "Rush Lake"
      }
    },
    {
      "geometry": {
        "type": "Point",
        "coordinates": [
          -93.1833,
          45.0667
        ]
      },
      "type": "Feature",
      "properties": {
        "hierarchy": [
          "tgn:2633812",
          "tgn:1000001",
          "tgn:7012149",
          "tgn:2001060",
          "tgn:7007521",
          "tgn:7029392"
        ],
        "placetype": [
          "aat:300008680"
        ],
        "id": 2633812,
        "name:xx": "Rush Lake"
      }
    },
    {
      "geometry": {
        "type": "Point",
        "coordinates": [
          -93.9333,
          45.4833
        ]
      },
      "type": "Feature",
      "properties": {
        "hierarchy": [
          "tgn:2633813",
          "tgn:1000001",
          "tgn:7012149",
          "tgn:2001069",
          "tgn:7007521",
          "tgn:7029392"
        ],
        "placetype": [
          "aat:300008680"
        ],
        "id": 2633813,
        "name:xx": "Rush Lake"
      }
    },
    {
      "geometry": {
        "type": "Point",
        "coordinates": [
          -93.05,
          45.6833
        ]
      },
      "type": "Feature",
      "properties": {
        "hierarchy": [
          "tgn:2633814",
          "tgn:1000001",
          "tgn:2001011",
          "tgn:7012149",
          "tgn:7007521",
          "tgn:7029392"
        ],
        "placetype": [
          "aat:300008680"
        ],
        "id": 2633814,
        "name:xx": "Rush Lake"
      }
    },
    {
      "geometry": {
        "type": "Point",
        "coordinates": [
          -96.1333,
          46.25
        ]
      },
      "type": "Feature",
      "properties": {
        "hierarchy": [
          "tgn:2633815",
          "tgn:1000001",
          "tgn:7012149",
          "tgn:2001054",
          "tgn:7007521",
          "tgn:7029392"
        ],
        "placetype": [
          "aat:300008680"
        ],
        "id": 2633815,
        "name:xx": "Rush Lake"
      }
    },
    {
      "geometry": {
        "type": "Point",
        "coordinates": [
          -94.2667,
          46.3333
        ]
      },
      "type": "Feature",
      "properties": {
        "hierarchy": [
          "tgn:2633816",
          "tgn:1000001",
          "tgn:2001016",
          "tgn:7012149",
          "tgn:7007521",
          "tgn:7029392"
        ],
        "placetype": [
          "aat:300008680"
        ],
        "id": 2633816,
        "name:xx": "Rush Lake"
      }
    },
    {
      "geometry": {
        "type": "Point",
        "coordinates": [
          -92.75,
          46.35
        ]
      },
      "type": "Feature",
      "properties": {
        "hierarchy": [
          "tgn:2633817",
          "tgn:1000001",
          "tgn:7012149",
          "tgn:2001056",
          "tgn:7007521",
          "tgn:7029392"
        ],
        "placetype": [
          "aat:300008680"
        ],
        "id": 2633817,
        "name:xx": "Rush Lake"
      }
    },
    {
      "geometry": {
        "type": "Point",
        "coordinates": [
          -95.6,
          47.0167
        ]
      },
      "type": "Feature",
      "properties": {
        "hierarchy": [
          "tgn:2633818",
          "tgn:2001001",
          "tgn:1000001",
          "tgn:7012149",
          "tgn:7007521",
          "tgn:7029392"
        ],
        "placetype": [
          "aat:300008680"
        ],
        "id": 2633818,
        "name:xx": "Rush Lake"
      }
    },
    {
      "geometry": {
        "type": "Point",
        "coordinates": [
          -92.1667,
          47.15
        ]
      },
      "type": "Feature",
      "properties": {
        "hierarchy": [
          "tgn:2633819",
          "tgn:1000001",
          "tgn:7012149",
          "tgn:2001067",
          "tgn:7007521",
          "tgn:7029392"
        ],
        "placetype": [
          "aat:300008680"
        ],
        "id": 2633819,
        "name:xx": "Rush Lake"
      }
    }
  ]
}
