{
  "geometry": {
    "type": "Point",
    "coordinates": [
      -83.5167,
      35.3667
    ]
  },
  "type": "Feature",
  "properties": {
    "hierarchy": [
      "tgn:2592942",
      "tgn:1000001",
      "tgn:7012149",
      "tgn:2001543",
      "tgn:7007709",
      "tgn:7029392"
    ],
    "placetype": [
      "aat:300008761"
    ],
    "id": 2592942,
    "name:xx": "Poplar Cove"
  }
}
