{
  "geometry": {
    "type": "Point",
    "coordinates": [
      -95.7333,
      38.25
    ]
  },
  "type": "Feature",
  "properties": {
    "hierarchy": [
      "tgn:2037183",
      "tgn:1000001",
      "tgn:2000675",
      "tgn:7012149",
      "tgn:7007254",
      "tgn:7029392"
    ],
    "placetype": [
      "aat:300008347"
    ],
    "id": 2037183,
    "name:xx": "New Strawn"
  }
}
