{
  "geometry": {
    "type": "Point",
    "coordinates": [
      -94.05,
      31.95
    ]
  },
  "type": "Feature",
  "properties": {
    "hierarchy": [
      "tgn:2578066",
      "tgn:1000001",
      "tgn:7012149",
      "tgn:7029392"
    ],
    "placetype": [
      "aat:300008706"
    ],
    "id": 2578066,
    "name:xx": "Petty Creek"
  }
}
