{
  "geometry": {
    "type": "Point",
    "coordinates": [
      -118.7667,
      48.1833
    ]
  },
  "type": "Feature",
  "properties": {
    "hierarchy": [
      "tgn:2213695",
      "tgn:1000001",
      "tgn:2002243",
      "tgn:7012149",
      "tgn:7007920",
      "tgn:7029392"
    ],
    "placetype": [
      "aat:300008706"
    ],
    "id": 2213695,
    "name:xx": "Cache Creek"
  }
}
