{
  "geometry": {
    "type": "Point",
    "coordinates": [
      -82.55,
      35.9167
    ]
  },
  "type": "Feature",
  "properties": {
    "hierarchy": [
      "tgn:2613459",
      "tgn:1000001",
      "tgn:7012149",
      "tgn:2001516",
      "tgn:7007709",
      "tgn:7029392"
    ],
    "placetype": [
      "aat:300008798"
    ],
    "id": 2613459,
    "name:xx": "Reed Mountain"
  }
}
