{
  "geometry": {
    "type": "Point",
    "coordinates": [
      -79.1167,
      37.5833
    ]
  },
  "type": "Feature",
  "properties": {
    "hierarchy": [
      "tgn:2322344",
      "tgn:2002140",
      "tgn:1000001",
      "tgn:7012149",
      "tgn:7007919",
      "tgn:7029392"
    ],
    "placetype": [
      "aat:300008706"
    ],
    "id": 2322344,
    "name:xx": "Falling Rock Creek"
  }
}
