{
  "geometry": {
    "type": "Point",
    "coordinates": [
      26.2875,
      35.316111
    ]
  },
  "type": "Feature",
  "properties": {
    "hierarchy": [
      "tgn:7224455",
      "tgn:7002692",
      "tgn:7012056",
      "tgn:1000003",
      "tgn:1000074",
      "tgn:7029392"
    ],
    "placetype": [
      "aat:300011692"
    ],
    "id": 7224455,
    "name:xx": "Pinákl, Vráchoi"
  }
}
