{
  "geometry": {
    "type": "Point",
    "coordinates": [
      -87.8667,
      43.1667
    ]
  },
  "type": "Feature",
  "properties": {
    "hierarchy": [
      "tgn:2338173",
      "tgn:1000001",
      "tgn:7012149",
      "tgn:1002672",
      "tgn:7007922",
      "tgn:7029392"
    ],
    "placetype": [
      "aat:300008850"
    ],
    "id": 2338173,
    "name:xx": "Fox Point"
  }
}
