{
  "geometry": {
    "type": "Point",
    "coordinates": [
      -113.5667,
      35.2167
    ]
  },
  "type": "Feature",
  "properties": {
    "hierarchy": [
      "tgn:2602459",
      "tgn:1000001",
      "tgn:7006451",
      "tgn:7012149",
      "tgn:2000098",
      "tgn:7029392"
    ],
    "placetype": [
      "aat:300008791"
    ],
    "id": 2602459,
    "name:xx": "Pyramid Rock"
  }
}
