{
  "geometry": {
    "type": "Point",
    "coordinates": [
      -93.45,
      30.7667
    ]
  },
  "type": "Feature",
  "properties": {
    "hierarchy": [
      "tgn:2043555",
      "tgn:1000001",
      "tgn:2000859",
      "tgn:7012149",
      "tgn:7007256",
      "tgn:7029392"
    ],
    "placetype": [
      "aat:300387016"
    ],
    "id": 2043555,
    "name:xx": "Neale"
  }
}
