{
  "geometry": {
    "type": "Point",
    "coordinates": [
      -83.3833,
      31.7167
    ]
  },
  "type": "Feature",
  "properties": {
    "hierarchy": [
      "tgn:2481866",
      "tgn:1000001",
      "tgn:7012149",
      "tgn:2000368",
      "tgn:7007248",
      "tgn:7029392"
    ],
    "placetype": [
      "aat:300008347"
    ],
    "id": 2481866,
    "name:xx": "Lands Crossroads"
  }
}
