{
  "geometry": {
    "type": "Point",
    "coordinates": [
      -79.9833,
      41.0833
    ]
  },
  "type": "Feature",
  "properties": {
    "hierarchy": [
      "tgn:2094549",
      "tgn:1000001",
      "tgn:1002217",
      "tgn:7012149",
      "tgn:7007710",
      "tgn:7029392"
    ],
    "placetype": [
      "aat:300008347"
    ],
    "id": 2094549,
    "name:xx": "Wick"
  }
}
