{
  "geometry": {
    "type": "Point",
    "coordinates": [
      -86.4333,
      39.4333
    ]
  },
  "type": "Feature",
  "properties": {
    "hierarchy": [
      "tgn:2311298",
      "tgn:1000001",
      "tgn:7012149",
      "tgn:1002694",
      "tgn:7007252",
      "tgn:7029392"
    ],
    "placetype": [
      "aat:300006191"
    ],
    "id": 2311298,
    "name:xx": "Edgewood, Lake"
  }
}
