{
  "geometry": {
    "type": "Point",
    "coordinates": [
      125.4167,
      6.6333
    ]
  },
  "type": "Feature",
  "properties": {
    "hierarchy": [
      "tgn:1128310",
      "tgn:1000004",
      "tgn:7016744",
      "tgn:1000135",
      "tgn:7029392"
    ],
    "placetype": [
      "aat:300008707"
    ],
    "id": 1128310,
    "name:xx": "Padada"
  }
}
