{
  "geometry": {
    "type": "Point",
    "coordinates": [
      -86.0167,
      15.6667
    ]
  },
  "type": "Feature",
  "properties": {
    "hierarchy": [
      "tgn:1016848",
      "tgn:1000573",
      "tgn:1000001",
      "tgn:7005554",
      "tgn:7029392"
    ],
    "placetype": [
      "aat:300008347"
    ],
    "id": 1016848,
    "name:xx": "Tocoa"
  }
}
