{
  "geometry": {
    "type": "Point",
    "coordinates": [
      -87.2167,
      36.85
    ]
  },
  "type": "Feature",
  "properties": {
    "hierarchy": [
      "tgn:2314326",
      "tgn:1000001",
      "tgn:7012149",
      "tgn:7029392"
    ],
    "placetype": [
      "aat:300008699"
    ],
    "id": 2314326,
    "name:xx": "Elk Fork"
  }
}
