{
  "geometry": {
    "type": "Point",
    "coordinates": [
      -104.2333,
      35.4667
    ]
  },
  "type": "Feature",
  "properties": {
    "hierarchy": [
      "tgn:2229478",
      "tgn:1000001",
      "tgn:7012149",
      "tgn:2001453",
      "tgn:7007566",
      "tgn:7029392"
    ],
    "placetype": [
      "aat:300008850"
    ],
    "id": 2229478,
    "name:xx": "Cedar Point"
  }
}
