{
  "geometry": {
    "type": "Point",
    "coordinates": [
      -7.05,
      37.85
    ]
  },
  "type": "Feature",
  "properties": {
    "hierarchy": [
      "tgn:7307544",
      "tgn:7002758",
      "tgn:7002823",
      "tgn:1000003",
      "tgn:1000095",
      "tgn:7029392"
    ],
    "placetype": [
      "aat:300008798"
    ],
    "id": 7307544,
    "name:xx": "Mármol, Cumbre del"
  }
}
