{
  "geometry": {
    "type": "Point",
    "coordinates": [
      2.963875,
      51.15612
    ]
  },
  "type": "Feature",
  "properties": {
    "hierarchy": [
      "tgn:1026450",
      "tgn:7003458",
      "tgn:1000003",
      "tgn:1000063",
      "tgn:7018236",
      "tgn:7029392"
    ],
    "placetype": [
      "aat:300008347"
    ],
    "id": 1026450,
    "name:xx": "Gistel"
  }
}
