{
  "type": "FeatureCollection",
  "features": [
    {
      "geometry": {
        "type": "Point",
        "coordinates": [
          10.809722,
          51.305278
        ]
      },
      "type": "Feature",
      "properties": {
        "hierarchy": [
          "tgn:7160330",
          "tgn:1000003",
          "tgn:7003689",
          "tgn:7000084",
          "tgn:7029392"
        ],
        "placetype": [
          "aat:300007783"
        ],
        "id": 7160330,
        "name:xx": "Bahnhof Hohenebra"
      }
    },
    {
      "geometry": {
        "type": "Point",
        "coordinates": [
          13.75,
          54.033333
        ]
      },
      "type": "Feature",
      "properties": {
        "hierarchy": [
          "tgn:7160332",
          "tgn:1000003",
          "tgn:7000094",
          "tgn:7000084",
          "tgn:7029392"
        ],
        "placetype": [
          "aat:300132317"
        ],
        "id": 7160332,
        "name:xx": "Hohendorfer See"
      }
    },
    {
      "geometry": {
        "type": "Point",
        "coordinates": [
          11.266667,
          51.766667
        ]
      },
      "type": "Feature",
      "properties": {
        "hierarchy": [
          "tgn:7160333",
          "tgn:1000003",
          "tgn:7003687",
          "tgn:7000084",
          "tgn:7029392"
        ],
        "placetype": [
          "aat:300000206"
        ],
        "id": 7160333,
        "name:xx": "Vorwerk Hohendorf"
      }
    },
    {
      "geometry": {
        "type": "Point",
        "coordinates": [
          12.983333,
          54.4
        ]
      },
      "type": "Feature",
      "properties": {
        "hierarchy": [
          "tgn:7160334",
          "tgn:1000003",
          "tgn:7000094",
          "tgn:7000084",
          "tgn:7029392"
        ],
        "placetype": [
          "aat:300008347"
        ],
        "id": 7160334,
        "name:xx": "Hohendorf"
      }
    },
    {
      "geometry": {
        "type": "Point",
        "coordinates": [
          13.55,
          51.95
        ]
      },
      "type": "Feature",
      "properties": {
        "hierarchy": [
          "tgn:7160336",
          "tgn:7000096",
          "tgn:1000003",
          "tgn:7000084",
          "tgn:7029392"
        ],
        "placetype": [
          "aat:300008347"
        ],
        "id": 7160336,
        "name:xx": "Hohendorf"
      }
    },
    {
      "geometry": {
        "type": "Point",
        "coordinates": [
          12.333333,
          51.116667
        ]
      },
      "type": "Feature",
      "properties": {
        "hierarchy": [
          "tgn:7160337",
          "tgn:1000003",
          "tgn:7003685",
          "tgn:7000084",
          "tgn:7029392"
        ],
        "placetype": [
          "aat:300008347"
        ],
        "id": 7160337,
        "name:xx": "Hohendorf"
      }
    },
    {
      "geometry": {
        "type": "Point",
        "coordinates": [
          11.783333,
          50.966667
        ]
      },
      "type": "Feature",
      "properties": {
        "hierarchy": [
          "tgn:7160338",
          "tgn:1000003",
          "tgn:7003689",
          "tgn:7000084",
          "tgn:7029392"
        ],
        "placetype": [
          "aat:300008347"
        ],
        "id": 7160338,
        "name:xx": "Hohendorf"
      }
    },
    {
      "geometry": {
        "type": "Point",
        "coordinates": [
          12.3,
          50.216667
        ]
      },
      "type": "Feature",
      "properties": {
        "hierarchy": [
          "tgn:7160339",
          "tgn:1000003",
          "tgn:7003685",
          "tgn:7000084",
          "tgn:7029392"
        ],
        "placetype": [
          "aat:300008347"
        ],
        "id": 7160339,
        "name:xx": "Hohendorf"
      }
    }
  ]
}
