{
  "geometry": {
    "type": "Point",
    "coordinates": [
      -121.8333,
      47.7833
    ]
  },
  "type": "Feature",
  "properties": {
    "hierarchy": [
      "tgn:2316532",
      "tgn:1000001",
      "tgn:7012149",
      "tgn:1002899",
      "tgn:7007920",
      "tgn:7029392"
    ],
    "placetype": [
      "aat:300008706"
    ],
    "id": 2316532,
    "name:xx": "Elwell Creek"
  }
}
