{
  "geometry": {
    "type": "Point",
    "coordinates": [
      -75.0833,
      41.3333
    ]
  },
  "type": "Feature",
  "properties": {
    "hierarchy": [
      "tgn:2208174",
      "tgn:1000001",
      "tgn:7012149",
      "tgn:1002789",
      "tgn:7007710",
      "tgn:7029392"
    ],
    "placetype": [
      "aat:300266640"
    ],
    "id": 2208174,
    "name:xx": "Burleigh Ridge"
  }
}
