{
  "geometry": {
    "type": "Point",
    "coordinates": [
      -123.0167,
      42.1667
    ]
  },
  "type": "Feature",
  "properties": {
    "hierarchy": [
      "tgn:2237456",
      "tgn:1000001",
      "tgn:7012149",
      "tgn:2001711",
      "tgn:7007708",
      "tgn:7029392"
    ],
    "placetype": [
      "aat:300006075"
    ],
    "id": 2237456,
    "name:xx": "China Ditch"
  }
}
