{
  "geometry": {
    "type": "Point",
    "coordinates": [
      -88.25,
      34.9167
    ]
  },
  "type": "Feature",
  "properties": {
    "hierarchy": [
      "tgn:2268895",
      "tgn:1000001",
      "tgn:7012149",
      "tgn:2001156",
      "tgn:7007522",
      "tgn:7029392"
    ],
    "placetype": [
      "aat:300008347"
    ],
    "id": 2268895,
    "name:xx": "Cross Roads"
  }
}
