{
  "geometry": {
    "type": "Point",
    "coordinates": [
      -71.0667,
      41.9333
    ]
  },
  "type": "Feature",
  "properties": {
    "hierarchy": [
      "tgn:2597797",
      "tgn:1002201",
      "tgn:1000001",
      "tgn:7012149",
      "tgn:7007517",
      "tgn:7029392"
    ],
    "placetype": [
      "aat:300008347"
    ],
    "id": 2597797,
    "name:xx": "Prattville"
  }
}
