{
  "type": "FeatureCollection",
  "features": [
    {
      "geometry": {
        "type": "Point",
        "coordinates": [
          -105.1833,
          40.7833
        ]
      },
      "type": "Feature",
      "properties": {
        "hierarchy": [
          "tgn:2563280",
          "tgn:1000001",
          "tgn:7012149",
          "tgn:2000226",
          "tgn:7007158",
          "tgn:7029392"
        ],
        "placetype": [
          "aat:300008706"
        ],
        "id": 2563280,
        "name:xx": "Owl Creek"
      }
    },
    {
      "geometry": {
        "type": "Point",
        "coordinates": [
          -106.0667,
          40.4667
        ]
      },
      "type": "Feature",
      "properties": {
        "hierarchy": [
          "tgn:2563281",
          "tgn:1000001",
          "tgn:7012149",
          "tgn:2000220",
          "tgn:7007158",
          "tgn:7029392"
        ],
        "placetype": [
          "aat:300008706"
        ],
        "id": 2563281,
        "name:xx": "Owl Creek"
      }
    },
    {
      "geometry": {
        "type": "Point",
        "coordinates": [
          -106.8833,
          39.1667
        ]
      },
      "type": "Feature",
      "properties": {
        "hierarchy": [
          "tgn:2563282",
          "tgn:1000001",
          "tgn:7012149",
          "tgn:7007158",
          "tgn:2000240",
          "tgn:7029392"
        ],
        "placetype": [
          "aat:300008706"
        ],
        "id": 2563282,
        "name:xx": "Owl Creek"
      }
    },
    {
      "geometry": {
        "type": "Point",
        "coordinates": [
          -104.7833,
          40.9833
        ]
      },
      "type": "Feature",
      "properties": {
        "hierarchy": [
          "tgn:2563283",
          "tgn:1000001",
          "tgn:7012149",
          "tgn:7007158",
          "tgn:2000253",
          "tgn:7029392"
        ],
        "placetype": [
          "aat:300008706"
        ],
        "id": 2563283,
        "name:xx": "Owl Creek"
      }
    },
    {
      "geometry": {
        "type": "Point",
        "coordinates": [
          -107.55,
          38.15
        ]
      },
      "type": "Feature",
      "properties": {
        "hierarchy": [
          "tgn:2563284",
          "tgn:1000001",
          "tgn:7012149",
          "tgn:2000237",
          "tgn:7007158",
          "tgn:7029392"
        ],
        "placetype": [
          "aat:300008706"
        ],
        "id": 2563284,
        "name:xx": "Owl Creek"
      }
    },
    {
      "geometry": {
        "type": "Point",
        "coordinates": [
          -83.25,
          29.9333
        ]
      },
      "type": "Feature",
      "properties": {
        "hierarchy": [
          "tgn:2563285",
          "tgn:1000001",
          "tgn:2000275",
          "tgn:7012149",
          "tgn:7007240",
          "tgn:7029392"
        ],
        "placetype": [
          "aat:300008706"
        ],
        "id": 2563285,
        "name:xx": "Owl Creek"
      }
    },
    {
      "geometry": {
        "type": "Point",
        "coordinates": [
          -81.7667,
          26.75
        ]
      },
      "type": "Feature",
      "properties": {
        "hierarchy": [
          "tgn:2563286",
          "tgn:1000001",
          "tgn:7012149",
          "tgn:1002582",
          "tgn:7007240",
          "tgn:7029392"
        ],
        "placetype": [
          "aat:300008706"
        ],
        "id": 2563286,
        "name:xx": "Owl Creek"
      }
    },
    {
      "geometry": {
        "type": "Point",
        "coordinates": [
          -85,
          30
        ]
      },
      "type": "Feature",
      "properties": {
        "hierarchy": [
          "tgn:2563287",
          "tgn:1000001",
          "tgn:7012149",
          "tgn:7007240",
          "tgn:7029392"
        ],
        "placetype": [
          "aat:300008706"
        ],
        "id": 2563287,
        "name:xx": "Owl Creek"
      }
    },
    {
      "geometry": {
        "type": "Point",
        "coordinates": [
          -84.5833,
          34.0833
        ]
      },
      "type": "Feature",
      "properties": {
        "hierarchy": [
          "tgn:2563288",
          "tgn:1000001",
          "tgn:2000319",
          "tgn:7012149",
          "tgn:7007248",
          "tgn:7029392"
        ],
        "placetype": [
          "aat:300008706"
        ],
        "id": 2563288,
        "name:xx": "Owl Creek"
      }
    },
    {
      "geometry": {
        "type": "Point",
        "coordinates": [
          -83.7667,
          34.85
        ]
      },
      "type": "Feature",
      "properties": {
        "hierarchy": [
          "tgn:2563289",
          "tgn:1000001",
          "tgn:7012149",
          "tgn:2000430",
          "tgn:7007248",
          "tgn:7029392"
        ],
        "placetype": [
          "aat:300008706"
        ],
        "id": 2563289,
        "name:xx": "Owl Creek"
      }
    }
  ]
}
