{
  "geometry": {
    "type": "Point",
    "coordinates": [
      -105.8333,
      33.4667
    ]
  },
  "type": "Feature",
  "properties": {
    "hierarchy": [
      "tgn:2313252",
      "tgn:1000001",
      "tgn:7012149",
      "tgn:2001442",
      "tgn:7007566",
      "tgn:7029392"
    ],
    "placetype": [
      "aat:300008761"
    ],
    "id": 2313252,
    "name:xx": "Elder Canyon"
  }
}
