{
  "geometry": {
    "type": "Point",
    "coordinates": [
      -95.7167,
      34.1833
    ]
  },
  "type": "Feature",
  "properties": {
    "hierarchy": [
      "tgn:2300569",
      "tgn:1000001",
      "tgn:7012149",
      "tgn:2001686",
      "tgn:7007707",
      "tgn:7029392"
    ],
    "placetype": [
      "aat:300008706"
    ],
    "id": 2300569,
    "name:xx": "Dumpling Creek"
  }
}
