{
  "geometry": {
    "type": "Point",
    "coordinates": [
      117.0333,
      23.45
    ]
  },
  "type": "Feature",
  "properties": {
    "hierarchy": [
      "tgn:1070574",
      "tgn:1000004",
      "tgn:7005232",
      "tgn:1008286",
      "tgn:1000111",
      "tgn:7029392"
    ],
    "placetype": [
      "aat:300008347"
    ],
    "id": 1070574,
    "name:xx": "Nan'ao Dao"
  }
}
