{
  "geometry": {
    "type": "Point",
    "coordinates": [
      -91.0667,
      40.75
    ]
  },
  "type": "Feature",
  "properties": {
    "hierarchy": [
      "tgn:2448554",
      "tgn:1000001",
      "tgn:7012149",
      "tgn:2000510",
      "tgn:7007251",
      "tgn:7029392"
    ],
    "placetype": [
      "aat:300008680"
    ],
    "id": 2448554,
    "name:xx": "Lily Lake"
  }
}
