{
  "geometry": {
    "type": "Point",
    "coordinates": [
      9.75,
      2.25
    ]
  },
  "type": "Feature",
  "properties": {
    "hierarchy": [
      "tgn:1127942",
      "tgn:7001242",
      "tgn:7029392"
    ],
    "placetype": [
      "aat:300008707"
    ],
    "id": 1127942,
    "name:xx": "Ntem"
  }
}
