{
  "geometry": {
    "type": "Point",
    "coordinates": [
      -82.0833,
      39.2333
    ]
  },
  "type": "Feature",
  "properties": {
    "hierarchy": [
      "tgn:2597785",
      "tgn:2001610",
      "tgn:1000001",
      "tgn:7012149",
      "tgn:7007706",
      "tgn:7029392"
    ],
    "placetype": [
      "aat:300008699"
    ],
    "id": 2597785,
    "name:xx": "Pratts Fork"
  }
}
