{
  "type": "FeatureCollection",
  "features": [
    {
      "geometry": {
        "type": "Point",
        "coordinates": [
          -83.1,
          41.6
        ]
      },
      "type": "Feature",
      "properties": {
        "hierarchy": [
          "tgn:2080440",
          "tgn:1000001",
          "tgn:7012149",
          "tgn:1002761",
          "tgn:7007706",
          "tgn:7029392"
        ],
        "placetype": [
          "aat:300008347"
        ],
        "id": 2080440,
        "name:xx": "Long Beach"
      }
    },
    {
      "geometry": {
        "type": "Point",
        "coordinates": [
          -81.8,
          39.0833
        ]
      },
      "type": "Feature",
      "properties": {
        "hierarchy": [
          "tgn:2080441",
          "tgn:1000001",
          "tgn:7012149",
          "tgn:2001616",
          "tgn:7007706",
          "tgn:7029392"
        ],
        "placetype": [
          "aat:300008347"
        ],
        "id": 2080441,
        "name:xx": "Long Bottom"
      }
    },
    {
      "geometry": {
        "type": "Point",
        "coordinates": [
          -80.8,
          40.1833
        ]
      },
      "type": "Feature",
      "properties": {
        "hierarchy": [
          "tgn:2080443",
          "tgn:1000001",
          "tgn:7012149",
          "tgn:1002519",
          "tgn:7007706",
          "tgn:7029392"
        ],
        "placetype": [
          "aat:300008347",
          "aat:300387210"
        ],
        "id": 2080443,
        "name:xx": "Long Run"
      }
    },
    {
      "geometry": {
        "type": "Point",
        "coordinates": [
          -80.8,
          40.8333
        ]
      },
      "type": "Feature",
      "properties": {
        "hierarchy": [
          "tgn:2080444",
          "tgn:1000001",
          "tgn:1002295",
          "tgn:7012149",
          "tgn:7007706",
          "tgn:7029392"
        ],
        "placetype": [
          "aat:300008347",
          "aat:300387210"
        ],
        "id": 2080444,
        "name:xx": "Longs Crossing"
      }
    },
    {
      "geometry": {
        "type": "Point",
        "coordinates": [
          -82.2167,
          39.4833
        ]
      },
      "type": "Feature",
      "properties": {
        "hierarchy": [
          "tgn:2080445",
          "tgn:1000001",
          "tgn:7012149",
          "tgn:2001613",
          "tgn:7007706",
          "tgn:7029392"
        ],
        "placetype": [
          "aat:300008347"
        ],
        "id": 2080445,
        "name:xx": "Longstreth"
      }
    },
    {
      "geometry": {
        "type": "Point",
        "coordinates": [
          -81,
          40.0167
        ]
      },
      "type": "Feature",
      "properties": {
        "hierarchy": [
          "tgn:2080446",
          "tgn:1002175",
          "tgn:1000001",
          "tgn:7012149",
          "tgn:7007706",
          "tgn:7029392"
        ],
        "placetype": [
          "aat:300008347"
        ],
        "id": 2080446,
        "name:xx": "Loomis"
      }
    }
  ]
}
