{
  "geometry": {
    "type": "Point",
    "coordinates": [
      -73.65,
      43.55
    ]
  },
  "type": "Feature",
  "properties": {
    "hierarchy": [
      "tgn:2068126",
      "tgn:1000001",
      "tgn:7012149",
      "tgn:1002986",
      "tgn:7007568",
      "tgn:7029392"
    ],
    "placetype": [
      "aat:300008347"
    ],
    "id": 2068126,
    "name:xx": "Bolton Landing"
  }
}
