{
  "geometry": {
    "type": "Point",
    "coordinates": [
      -112.0625,
      26.8125
    ]
  },
  "type": "Feature",
  "properties": {
    "hierarchy": [
      "tgn:7418112",
      "tgn:1001836",
      "tgn:1000001",
      "tgn:7005560",
      "tgn:7029392"
    ],
    "placetype": [
      "aat:300008699"
    ],
    "id": 7418112,
    "name:xx": "Mulegé, Río"
  }
}
