{
  "geometry": {
    "type": "Point",
    "coordinates": [
      -105.35,
      41.1667
    ]
  },
  "type": "Feature",
  "properties": {
    "hierarchy": [
      "tgn:2311935",
      "tgn:2002365",
      "tgn:1000001",
      "tgn:7012149",
      "tgn:7007923",
      "tgn:7029392"
    ],
    "placetype": [
      "aat:300008798"
    ],
    "id": 2311935,
    "name:xx": "Egbert Hill"
  }
}
