{
  "geometry": {
    "type": "Point",
    "coordinates": [
      -100.3333,
      37.1667
    ]
  },
  "type": "Feature",
  "properties": {
    "hierarchy": [
      "tgn:2614717",
      "tgn:1000001",
      "tgn:7012149",
      "tgn:2000719",
      "tgn:7007254",
      "tgn:7029392"
    ],
    "placetype": [
      "aat:300008706"
    ],
    "id": 2614717,
    "name:xx": "Remuda Creek"
  }
}
