{
  "geometry": {
    "type": "Point",
    "coordinates": [
      32.834101,
      25.078845
    ]
  },
  "type": "Feature",
  "properties": {
    "hierarchy": [
      "tgn:7543246",
      "tgn:7001242",
      "tgn:7016833",
      "tgn:7000122",
      "tgn:7029392"
    ],
    "placetype": [
      "aat:300008791"
    ],
    "name:en": "Ḑabḩah, Jazīrat aḑ",
    "id": 7543246
  }
}
