{
  "geometry": {
    "type": "Point",
    "coordinates": [
      -155.6333,
      20.0167
    ]
  },
  "type": "Feature",
  "properties": {
    "hierarchy": [
      "tgn:2565190",
      "tgn:7023902",
      "tgn:1000001",
      "tgn:7012149",
      "tgn:7007249",
      "tgn:7029392"
    ],
    "placetype": [
      "aat:300006191"
    ],
    "id": 2565190,
    "name:xx": "Paiakuli Reservoir"
  }
}
