{
  "geometry": {
    "type": "Point",
    "coordinates": [
      12.118,
      45.641
    ]
  },
  "type": "Feature",
  "properties": {
    "hierarchy": [
      "tgn:5003180",
      "tgn:7002996",
      "tgn:1000003",
      "tgn:7002997",
      "tgn:1000080",
      "tgn:7029392"
    ],
    "placetype": [
      "aat:300008347"
    ],
    "id": 5003180,
    "name:xx": "Santa Cristina di Quinto di Treviso"
  }
}
