{
  "geometry": {
    "type": "Point",
    "coordinates": [
      -84.7667,
      45.9333
    ]
  },
  "type": "Feature",
  "properties": {
    "hierarchy": [
      "tgn:2604296",
      "tgn:1000001",
      "tgn:7012149",
      "tgn:2000973",
      "tgn:7007520",
      "tgn:7029392"
    ],
    "placetype": [
      "aat:300008706"
    ],
    "id": 2604296,
    "name:xx": "Rabbit Back Creek"
  }
}
