{
  "geometry": {
    "type": "Point",
    "coordinates": [
      94.690237,
      27.673128
    ]
  },
  "type": "Feature",
  "properties": {
    "hierarchy": [
      "tgn:7546272",
      "tgn:1000004",
      "tgn:1001832",
      "tgn:7000198",
      "tgn:7029392"
    ],
    "placetype": [
      "aat:300008347"
    ],
    "name:en": "Bātelegaon",
    "id": 7546272
  }
}
