{
  "geometry": {
    "type": "Point",
    "coordinates": [
      -85.6667,
      33.1167
    ]
  },
  "type": "Feature",
  "properties": {
    "hierarchy": [
      "tgn:2005294",
      "tgn:7002659",
      "tgn:1000001",
      "tgn:2000013",
      "tgn:7012149",
      "tgn:7029392"
    ],
    "placetype": [
      "aat:300008347",
      "aat:300387210"
    ],
    "id": 2005294,
    "name:xx": "Sikesville"
  }
}
