{
  "geometry": {
    "type": "Point",
    "coordinates": [
      21.6333,
      51.9167
    ]
  },
  "type": "Feature",
  "properties": {
    "hierarchy": [
      "tgn:1049045",
      "tgn:1000003",
      "tgn:7024122",
      "tgn:7006366",
      "tgn:7029392"
    ],
    "placetype": [
      "aat:300008347"
    ],
    "id": 1049045,
    "name:xx": "Garwolin"
  }
}
