{
  "geometry": {
    "type": "Point",
    "coordinates": [
      -105.55,
      44.45
    ]
  },
  "type": "Feature",
  "properties": {
    "hierarchy": [
      "tgn:2686874",
      "tgn:1000001",
      "tgn:2002367",
      "tgn:7012149",
      "tgn:7007923",
      "tgn:7029392"
    ],
    "placetype": [
      "aat:300008761"
    ],
    "id": 2686874,
    "name:xx": "Spring Draw"
  }
}
