{
  "geometry": {
    "type": "Point",
    "coordinates": [
      8.8333,
      47.2333
    ]
  },
  "type": "Feature",
  "properties": {
    "hierarchy": [
      "tgn:7007668",
      "tgn:1000003",
      "tgn:7003755",
      "tgn:7011731",
      "tgn:7029392"
    ],
    "placetype": [
      "aat:300008347"
    ],
    "id": 7007668,
    "name:xx": "Rapperswil"
  }
}
