{
  "geometry": {
    "type": "Point",
    "coordinates": [
      -111.9167,
      40.7833
    ]
  },
  "type": "Feature",
  "properties": {
    "hierarchy": [
      "tgn:2132408",
      "tgn:1000001",
      "tgn:7012149",
      "tgn:2002118",
      "tgn:7007827",
      "tgn:7029392"
    ],
    "placetype": [
      "aat:300008347"
    ],
    "id": 2132408,
    "name:xx": "Amos Addition"
  }
}
