{
  "geometry": {
    "type": "Point",
    "coordinates": [
      79.8667,
      27.1989
    ]
  },
  "type": "Feature",
  "properties": {
    "hierarchy": [
      "tgn:7561683",
      "tgn:1000004",
      "tgn:7000198",
      "tgn:7016722",
      "tgn:7029392"
    ],
    "placetype": [
      "aat:300008347"
    ],
    "name:en": "Deokali",
    "id": 7561683
  }
}
