{
  "geometry": {
    "type": "Point",
    "coordinates": [
      -100.35,
      44.85
    ]
  },
  "type": "Feature",
  "properties": {
    "hierarchy": [
      "tgn:2138267",
      "tgn:1000001",
      "tgn:7012149",
      "tgn:2001829",
      "tgn:7007713",
      "tgn:7029392"
    ],
    "placetype": [
      "aat:300008798"
    ],
    "id": 2138267,
    "name:xx": "Artichoke Butte"
  }
}
