{
  "geometry": {
    "type": "Point",
    "coordinates": [
      120.75,
      16.4833
    ]
  },
  "type": "Feature",
  "properties": {
    "hierarchy": [
      "tgn:1101067",
      "tgn:1000004",
      "tgn:1001151",
      "tgn:1000135",
      "tgn:7029392"
    ],
    "placetype": [
      "aat:300006084"
    ],
    "id": 1101067,
    "name:xx": "Ambuklao Dam"
  }
}
