{
  "geometry": {
    "type": "Point",
    "coordinates": [
      -90.8833,
      45.9333
    ]
  },
  "type": "Feature",
  "properties": {
    "hierarchy": [
      "tgn:2179189",
      "tgn:1000001",
      "tgn:7012149",
      "tgn:2002353",
      "tgn:7007922",
      "tgn:7029392"
    ],
    "placetype": [
      "aat:300008680"
    ],
    "id": 2179189,
    "name:xx": "Blaisdell Lake"
  }
}
