{
  "geometry": {
    "type": "Point",
    "coordinates": [
      -91.8167,
      46.1667
    ]
  },
  "type": "Feature",
  "properties": {
    "hierarchy": [
      "tgn:2752102",
      "tgn:1000001",
      "tgn:2002318",
      "tgn:7012149",
      "tgn:7007922",
      "tgn:7029392"
    ],
    "placetype": [
      "aat:300008680"
    ],
    "id": 2752102,
    "name:xx": "Wascott Lake"
  }
}
