{
  "geometry": {
    "type": "Point",
    "coordinates": [
      -8.6667,
      5.3333
    ]
  },
  "type": "Feature",
  "properties": {
    "hierarchy": [
      "tgn:1000444",
      "tgn:7001242",
      "tgn:1000171",
      "tgn:7029392"
    ],
    "placetype": [
      "aat:300387064",
      "aat:300000771"
    ],
    "id": 1000444,
    "name:xx": "Sinoe"
  }
}
