{
  "geometry": {
    "type": "Point",
    "coordinates": [
      77.45,
      11.983333
    ]
  },
  "type": "Feature",
  "properties": {
    "hierarchy": [
      "tgn:7552231",
      "tgn:1000004",
      "tgn:7000198",
      "tgn:1001882",
      "tgn:7029392"
    ],
    "placetype": [
      "aat:300008347"
    ],
    "name:en": "Moranūr",
    "id": 7552231
  }
}
