{
  "geometry": {
    "type": "Point",
    "coordinates": [
      -110.45,
      45.1833
    ]
  },
  "type": "Feature",
  "properties": {
    "hierarchy": [
      "tgn:2244959",
      "tgn:1000001",
      "tgn:7012149",
      "tgn:2001293",
      "tgn:7007524",
      "tgn:7029392"
    ],
    "placetype": [
      "aat:300008706"
    ],
    "id": 2244959,
    "name:xx": "Clover Creek"
  }
}
