{
  "geometry": {
    "type": "Point",
    "coordinates": [
      -91.4667,
      43.95
    ]
  },
  "type": "Feature",
  "properties": {
    "hierarchy": [
      "tgn:2408308",
      "tgn:1000001",
      "tgn:7012149",
      "tgn:2001083",
      "tgn:7007521",
      "tgn:7029392"
    ],
    "placetype": [
      "aat:300266640"
    ],
    "id": 2408308,
    "name:xx": "Husman Ridge"
  }
}
