{
  "geometry": {
    "type": "Point",
    "coordinates": [
      -79.9833,
      37.75
    ]
  },
  "type": "Feature",
  "properties": {
    "hierarchy": [
      "tgn:1134276",
      "tgn:1000001",
      "tgn:7012149",
      "tgn:7029392"
    ],
    "placetype": [
      "aat:300008706"
    ],
    "id": 1134276,
    "name:xx": "Potts Creek"
  }
}
