{
  "geometry": {
    "type": "Point",
    "coordinates": [
      38.95,
      36.6833
    ]
  },
  "type": "Feature",
  "properties": {
    "hierarchy": [
      "tgn:1085255",
      "tgn:1002064",
      "tgn:1000004",
      "tgn:1000140",
      "tgn:7029392"
    ],
    "placetype": [
      "aat:300008347"
    ],
    "id": 1085255,
    "name:xx": "Tall al-Abyaḍ"
  }
}
