{
  "geometry": {
    "type": "Point",
    "coordinates": [
      -132.4667,
      56.2833
    ]
  },
  "type": "Feature",
  "properties": {
    "hierarchy": [
      "tgn:2319480",
      "tgn:7006450",
      "tgn:1000001",
      "tgn:7012149",
      "tgn:2000088",
      "tgn:7029392"
    ],
    "placetype": [
      "aat:300008791"
    ],
    "id": 2319480,
    "name:xx": "Etolin Island"
  }
}
