{
  "geometry": {
    "type": "Point",
    "coordinates": [
      -104.4667,
      35.75
    ]
  },
  "type": "Feature",
  "properties": {
    "hierarchy": [
      "tgn:2597174",
      "tgn:1000001",
      "tgn:7012149",
      "tgn:2001453",
      "tgn:7007566",
      "tgn:7029392"
    ],
    "placetype": [
      "aat:300008697"
    ],
    "id": 2597174,
    "name:xx": "Pozo Azul"
  }
}
