{
  "type": "FeatureCollection",
  "features": [
    {
      "geometry": {
        "type": "Point",
        "coordinates": [
          175.466667,
          -39.5
        ]
      },
      "type": "Feature",
      "properties": {
        "hierarchy": [
          "tgn:7505820",
          "tgn:1008380",
          "tgn:7520093",
          "tgn:1000226",
          "tgn:1000006",
          "tgn:7029392"
        ],
        "placetype": [
          "aat:300008699"
        ],
        "name:en": "Tokiahuru Stream",
        "id": 7505820
      }
    },
    {
      "geometry": {
        "type": "Point",
        "coordinates": [
          174.4,
          -36.383333
        ]
      },
      "type": "Feature",
      "properties": {
        "hierarchy": [
          "tgn:7505821",
          "tgn:1008380",
          "tgn:7000507",
          "tgn:1000226",
          "tgn:1000006",
          "tgn:7029392"
        ],
        "placetype": [
          "aat:300008699"
        ],
        "name:en": "Tokenui Creek",
        "id": 7505821
      }
    },
    {
      "geometry": {
        "type": "Point",
        "coordinates": [
          175.816667,
          -40.233333
        ]
      },
      "type": "Feature",
      "properties": {
        "hierarchy": [
          "tgn:7505822",
          "tgn:1008380",
          "tgn:7520093",
          "tgn:1000226",
          "tgn:1000006",
          "tgn:7029392"
        ],
        "placetype": [
          "aat:300008699"
        ],
        "name:en": "Tokeawa",
        "id": 7505822
      }
    },
    {
      "geometry": {
        "type": "Point",
        "coordinates": [
          173.966667,
          -36.05
        ]
      },
      "type": "Feature",
      "properties": {
        "hierarchy": [
          "tgn:7505823",
          "tgn:1008380",
          "tgn:7000507",
          "tgn:1000226",
          "tgn:1000006",
          "tgn:7029392"
        ],
        "placetype": [
          "aat:300008347"
        ],
        "name:en": "Tokatoka",
        "id": 7505823
      }
    },
    {
      "geometry": {
        "type": "Point",
        "coordinates": [
          169.8,
          -46.416667
        ]
      },
      "type": "Feature",
      "properties": {
        "hierarchy": [
          "tgn:7505824",
          "tgn:1009227",
          "tgn:1000226",
          "tgn:7018437",
          "tgn:1000006",
          "tgn:7029392"
        ],
        "placetype": [
          "aat:300008347"
        ],
        "name:en": "Tokata",
        "id": 7505824
      }
    },
    {
      "geometry": {
        "type": "Point",
        "coordinates": [
          170.65,
          -44.95
        ]
      },
      "type": "Feature",
      "properties": {
        "hierarchy": [
          "tgn:7505825",
          "tgn:1009227",
          "tgn:1000226",
          "tgn:7018437",
          "tgn:1000006",
          "tgn:7029392"
        ],
        "placetype": [
          "aat:300008347"
        ],
        "name:en": "Tokarahi",
        "id": 7505825
      }
    },
    {
      "geometry": {
        "type": "Point",
        "coordinates": [
          175.2,
          -38.4
        ]
      },
      "type": "Feature",
      "properties": {
        "hierarchy": [
          "tgn:7505826",
          "tgn:1008380",
          "tgn:1000226",
          "tgn:7018426",
          "tgn:1000006",
          "tgn:7029392"
        ],
        "placetype": [
          "aat:300008795"
        ],
        "name:en": "Tokapiko",
        "id": 7505826
      }
    },
    {
      "geometry": {
        "type": "Point",
        "coordinates": [
          168.833333,
          -46.6
        ]
      },
      "type": "Feature",
      "properties": {
        "hierarchy": [
          "tgn:7505827",
          "tgn:1009227",
          "tgn:1000226",
          "tgn:7016822",
          "tgn:1000006",
          "tgn:7029392"
        ],
        "placetype": [
          "aat:300008699"
        ],
        "name:en": "Tokanui Stream",
        "id": 7505827
      }
    },
    {
      "geometry": {
        "type": "Point",
        "coordinates": [
          176.35,
          -39.5
        ]
      },
      "type": "Feature",
      "properties": {
        "hierarchy": [
          "tgn:7505828",
          "tgn:7016670",
          "tgn:1008380",
          "tgn:1000226",
          "tgn:1000006",
          "tgn:7029392"
        ],
        "placetype": [
          "aat:300008699"
        ],
        "name:en": "Taruarau River",
        "id": 7505828
      }
    },
    {
      "geometry": {
        "type": "Point",
        "coordinates": [
          169.35,
          -44.883333
        ]
      },
      "type": "Feature",
      "properties": {
        "hierarchy": [
          "tgn:7505829",
          "tgn:1009227",
          "tgn:1000226",
          "tgn:7018437",
          "tgn:1000006",
          "tgn:7029392"
        ],
        "placetype": [
          "aat:300008699"
        ],
        "name:en": "Tarras Creek",
        "id": 7505829
      }
    }
  ]
}
