{
  "geometry": {
    "type": "Point",
    "coordinates": [
      -86.6667,
      34.45
    ]
  },
  "type": "Feature",
  "properties": {
    "hierarchy": [
      "tgn:2514928",
      "tgn:7002659",
      "tgn:1000001",
      "tgn:7012149",
      "tgn:2000051",
      "tgn:7029392"
    ],
    "placetype": [
      "aat:300008697"
    ],
    "id": 2514928,
    "name:xx": "Miller Spring"
  }
}
