{
  "geometry": {
    "type": "Point",
    "coordinates": [
      -101.4167,
      41.9667
    ]
  },
  "type": "Feature",
  "properties": {
    "hierarchy": [
      "tgn:2222761",
      "tgn:1000001",
      "tgn:7012149",
      "tgn:7007525",
      "tgn:7029392"
    ],
    "placetype": [
      "aat:300008680"
    ],
    "id": 2222761,
    "name:xx": "Carr Lake"
  }
}
