{
  "geometry": {
    "type": "Point",
    "coordinates": [
      -82.7833,
      36.2333
    ]
  },
  "type": "Feature",
  "properties": {
    "hierarchy": [
      "tgn:2426928",
      "tgn:1000001",
      "tgn:7012149",
      "tgn:2001866",
      "tgn:7007825",
      "tgn:7029392"
    ],
    "placetype": [
      "aat:300266640"
    ],
    "id": 2426928,
    "name:xx": "Jones Ridge"
  }
}
