{
  "geometry": {
    "type": "Point",
    "coordinates": [
      -122.9167,
      40.35
    ]
  },
  "type": "Feature",
  "properties": {
    "hierarchy": [
      "tgn:2460158",
      "tgn:1000001",
      "tgn:7012149",
      "tgn:7007157",
      "tgn:2000188",
      "tgn:7029392"
    ],
    "placetype": [
      "aat:300008798"
    ],
    "id": 2460158,
    "name:xx": "Little Round Mountain"
  }
}
