{
  "geometry": {
    "type": "Point",
    "coordinates": [
      -88.6333,
      40.2333
    ]
  },
  "type": "Feature",
  "properties": {
    "hierarchy": [
      "tgn:2027822",
      "tgn:1000001",
      "tgn:1002322",
      "tgn:7012149",
      "tgn:7007251",
      "tgn:7029392"
    ],
    "placetype": [
      "aat:300008347"
    ],
    "id": 2027822,
    "name:xx": "Farmer City"
  }
}
