{
  "geometry": {
    "type": "Point",
    "coordinates": [
      -66.95,
      10.4667
    ]
  },
  "type": "Feature",
  "properties": {
    "hierarchy": [
      "tgn:1004932",
      "tgn:7005022",
      "tgn:1000842",
      "tgn:1000002",
      "tgn:1000059",
      "tgn:7029392"
    ],
    "placetype": [
      "aat:300000745"
    ],
    "id": 1004932,
    "name:xx": "La Vega"
  }
}
