{
  "geometry": {
    "type": "Point",
    "coordinates": [
      -73.4667,
      43.0167
    ]
  },
  "type": "Feature",
  "properties": {
    "hierarchy": [
      "tgn:2067836",
      "tgn:1000001",
      "tgn:7012149",
      "tgn:1002993",
      "tgn:7007568",
      "tgn:7029392"
    ],
    "placetype": [
      "aat:300008347",
      "aat:300387210"
    ],
    "id": 2067836,
    "name:xx": "Archdale"
  }
}
