{
  "geometry": {
    "type": "Point",
    "coordinates": [
      -97.5833,
      33.8333
    ]
  },
  "type": "Feature",
  "properties": {
    "hierarchy": [
      "tgn:2624940",
      "tgn:1000001",
      "tgn:7012149",
      "tgn:2002044",
      "tgn:7007826",
      "tgn:7029392"
    ],
    "placetype": [
      "aat:300008706"
    ],
    "id": 2624940,
    "name:xx": "Rock Springs Creek"
  }
}
