{
  "geometry": {
    "type": "Point",
    "coordinates": [
      -90.6167,
      31.4333
    ]
  },
  "type": "Feature",
  "properties": {
    "hierarchy": [
      "tgn:2400084",
      "tgn:1000001",
      "tgn:7012149",
      "tgn:7007522",
      "tgn:7029392"
    ],
    "placetype": [
      "aat:300008706"
    ],
    "id": 2400084,
    "name:xx": "Horse Creek"
  }
}
