{
  "geometry": {
    "type": "Point",
    "coordinates": [
      -77.45,
      39.8667
    ]
  },
  "type": "Feature",
  "properties": {
    "hierarchy": [
      "tgn:2221037",
      "tgn:1002137",
      "tgn:1000001",
      "tgn:7012149",
      "tgn:7007710",
      "tgn:7029392"
    ],
    "placetype": [
      "aat:300006191"
    ],
    "id": 2221037,
    "name:xx": "Carbaugh Reservoir"
  }
}
