{
  "geometry": {
    "type": "Point",
    "coordinates": [
      -86.9833,
      30.6667
    ]
  },
  "type": "Feature",
  "properties": {
    "hierarchy": [
      "tgn:2627462",
      "tgn:1000001",
      "tgn:7012149",
      "tgn:2000285",
      "tgn:7007240",
      "tgn:7029392"
    ],
    "placetype": [
      "aat:300008347"
    ],
    "id": 2627462,
    "name:xx": "Roeville"
  }
}
