{
  "geometry": {
    "type": "Point",
    "coordinates": [
      134.1667,
      34.8333
    ]
  },
  "type": "Feature",
  "properties": {
    "hierarchy": [
      "tgn:1081705",
      "tgn:1001015",
      "tgn:7000897",
      "tgn:1000004",
      "tgn:1000120",
      "tgn:7029392"
    ],
    "placetype": [
      "aat:300008347"
    ],
    "id": 1081705,
    "name:xx": "Wake"
  }
}
