{
  "geometry": {
    "type": "Point",
    "coordinates": [
      -105.1833,
      40.75
    ]
  },
  "type": "Feature",
  "properties": {
    "hierarchy": [
      "tgn:2186936",
      "tgn:1000001",
      "tgn:7012149",
      "tgn:2000226",
      "tgn:7007158",
      "tgn:7029392"
    ],
    "placetype": [
      "aat:300008697"
    ],
    "id": 2186936,
    "name:xx": "Bonner Spring"
  }
}
