{
  "geometry": {
    "type": "Point",
    "coordinates": [
      9.05,
      51.65
    ]
  },
  "type": "Feature",
  "properties": {
    "hierarchy": [
      "tgn:7060120",
      "tgn:1000003",
      "tgn:7003677",
      "tgn:7000084",
      "tgn:7029392"
    ],
    "placetype": [
      "aat:300008347"
    ],
    "id": 7060120,
    "name:xx": "Altenheerse"
  }
}
