{
  "type": "FeatureCollection",
  "features": [
    {
      "geometry": {
        "type": "Point",
        "coordinates": [
          35.3333,
          31.9167
        ]
      },
      "type": "Feature",
      "properties": {
        "hierarchy": [
          "tgn:7033030",
          "tgn:1000004",
          "tgn:7029392"
        ],
        "placetype": [
          "aat:300387178"
        ],
        "id": 7033030,
        "name:xx": "Canaan"
      }
    },
    {
      "geometry": {
        "type": "Point",
        "coordinates": [
          5,
          47.316
        ]
      },
      "type": "Feature",
      "properties": {
        "hierarchy": [
          "tgn:7033031",
          "tgn:1000003",
          "tgn:7002875",
          "tgn:1000070",
          "tgn:7029392"
        ],
        "placetype": [
          "aat:300000641"
        ],
        "id": 7033031,
        "name:xx": "Chartreuse de Champmol"
      }
    },
    {
      "geometry": {
        "type": "Point",
        "coordinates": [
          6.533,
          48.566
        ]
      },
      "type": "Feature",
      "properties": {
        "hierarchy": [
          "tgn:7033032",
          "tgn:1000003",
          "tgn:7002888",
          "tgn:1000070",
          "tgn:7029392"
        ],
        "placetype": [
          "aat:300008347"
        ],
        "id": 7033032,
        "name:xx": "Moncel-lès-Lunéville"
      }
    }
  ]
}
