{
  "geometry": {
    "type": "Point",
    "coordinates": [
      -107.2833,
      35.3333
    ]
  },
  "type": "Feature",
  "properties": {
    "hierarchy": [
      "tgn:2126935",
      "tgn:1000001",
      "tgn:7012149",
      "tgn:2001451",
      "tgn:7007566",
      "tgn:7029392"
    ],
    "placetype": [
      "aat:300008697"
    ],
    "id": 2126935,
    "name:xx": "Agua del Cañoncito"
  }
}
