{
  "geometry": {
    "type": "Point",
    "coordinates": [
      -7.0833,
      53.45
    ]
  },
  "type": "Feature",
  "properties": {
    "hierarchy": [
      "tgn:1042887",
      "tgn:7001199",
      "tgn:7003491",
      "tgn:1000003",
      "tgn:1000078",
      "tgn:7029392"
    ],
    "placetype": [
      "aat:300008347"
    ],
    "id": 1042887,
    "name:xx": "Kinnegad"
  }
}
