{
  "geometry": {
    "type": "Point",
    "coordinates": [
      -122.5167,
      41.8667
    ]
  },
  "type": "Feature",
  "properties": {
    "hierarchy": [
      "tgn:2440077",
      "tgn:1000001",
      "tgn:7012149",
      "tgn:7007157",
      "tgn:2000189",
      "tgn:7029392"
    ],
    "placetype": [
      "aat:300008697"
    ],
    "id": 2440077,
    "name:xx": "Klamathon Spring"
  }
}
