{
  "geometry": {
    "type": "Point",
    "coordinates": [
      -122.8333,
      51.6667
    ]
  },
  "type": "Feature",
  "properties": {
    "hierarchy": [
      "tgn:1132437",
      "tgn:7005735",
      "tgn:7005685",
      "tgn:1000001",
      "tgn:7029392"
    ],
    "placetype": [
      "aat:300008706"
    ],
    "id": 1132437,
    "name:xx": "Big Creek"
  }
}
