{
  "geometry": {
    "type": "Point",
    "coordinates": [
      -88.4667,
      37.0667
    ]
  },
  "type": "Feature",
  "properties": {
    "hierarchy": [
      "tgn:2140955",
      "tgn:1000001",
      "tgn:7012149",
      "tgn:2000523",
      "tgn:7007251",
      "tgn:7029392"
    ],
    "placetype": [
      "aat:300008680"
    ],
    "id": 2140955,
    "name:xx": "Avery Lake"
  }
}
