{
  "type": "FeatureCollection",
  "features": [
    {
      "geometry": {
        "type": "Point",
        "coordinates": [
          -117.0167,
          34.1833
        ]
      },
      "type": "Feature",
      "properties": {
        "hierarchy": [
          "tgn:2424530",
          "tgn:1000001",
          "tgn:7012149",
          "tgn:7007157",
          "tgn:1002857",
          "tgn:7029392"
        ],
        "placetype": [
          "aat:300008706"
        ],
        "id": 2424530,
        "name:xx": "Johnson Creek"
      }
    },
    {
      "geometry": {
        "type": "Point",
        "coordinates": [
          -121.35,
          36.5667
        ]
      },
      "type": "Feature",
      "properties": {
        "hierarchy": [
          "tgn:2424531",
          "tgn:1000001",
          "tgn:7012149",
          "tgn:7007157",
          "tgn:1002684",
          "tgn:7029392"
        ],
        "placetype": [
          "aat:300008706"
        ],
        "id": 2424531,
        "name:xx": "Johnson Creek"
      }
    },
    {
      "geometry": {
        "type": "Point",
        "coordinates": [
          -118.3333,
          36.4167
        ]
      },
      "type": "Feature",
      "properties": {
        "hierarchy": [
          "tgn:2424532",
          "tgn:1000001",
          "tgn:7012149",
          "tgn:7007157",
          "tgn:1002956",
          "tgn:7029392"
        ],
        "placetype": [
          "aat:300008706"
        ],
        "id": 2424532,
        "name:xx": "Johnson Creek"
      }
    },
    {
      "geometry": {
        "type": "Point",
        "coordinates": [
          -107.0333,
          40.8833
        ]
      },
      "type": "Feature",
      "properties": {
        "hierarchy": [
          "tgn:2424533",
          "tgn:1000001",
          "tgn:7012149",
          "tgn:7007158",
          "tgn:2000245",
          "tgn:7029392"
        ],
        "placetype": [
          "aat:300008706"
        ],
        "id": 2424533,
        "name:xx": "Johnson Creek"
      }
    },
    {
      "geometry": {
        "type": "Point",
        "coordinates": [
          -107.35,
          39.7167
        ]
      },
      "type": "Feature",
      "properties": {
        "hierarchy": [
          "tgn:2424534",
          "tgn:1000001",
          "tgn:7012149",
          "tgn:2000214",
          "tgn:7007158",
          "tgn:7029392"
        ],
        "placetype": [
          "aat:300008706"
        ],
        "id": 2424534,
        "name:xx": "Johnson Creek"
      }
    },
    {
      "geometry": {
        "type": "Point",
        "coordinates": [
          -106.7333,
          39.2667
        ]
      },
      "type": "Feature",
      "properties": {
        "hierarchy": [
          "tgn:2424535",
          "tgn:1000001",
          "tgn:7012149",
          "tgn:7007158",
          "tgn:2000240",
          "tgn:7029392"
        ],
        "placetype": [
          "aat:300008706"
        ],
        "id": 2424535,
        "name:xx": "Johnson Creek"
      }
    },
    {
      "geometry": {
        "type": "Point",
        "coordinates": [
          -108.7333,
          38.8333
        ]
      },
      "type": "Feature",
      "properties": {
        "hierarchy": [
          "tgn:2424536",
          "tgn:1000001",
          "tgn:7012149",
          "tgn:2000230",
          "tgn:7007158",
          "tgn:7029392"
        ],
        "placetype": [
          "aat:300008706"
        ],
        "id": 2424536,
        "name:xx": "Johnson Creek"
      }
    },
    {
      "geometry": {
        "type": "Point",
        "coordinates": [
          -108,
          38.2167
        ]
      },
      "type": "Feature",
      "properties": {
        "hierarchy": [
          "tgn:2424537",
          "tgn:1000001",
          "tgn:7012149",
          "tgn:2000234",
          "tgn:7007158",
          "tgn:7029392"
        ],
        "placetype": [
          "aat:300008706"
        ],
        "id": 2424537,
        "name:xx": "Johnson Creek"
      }
    },
    {
      "geometry": {
        "type": "Point",
        "coordinates": [
          -107.5833,
          37.5833
        ]
      },
      "type": "Feature",
      "properties": {
        "hierarchy": [
          "tgn:2424538",
          "tgn:1000001",
          "tgn:7012149",
          "tgn:2000225",
          "tgn:7007158",
          "tgn:7029392"
        ],
        "placetype": [
          "aat:300008706"
        ],
        "id": 2424538,
        "name:xx": "Johnson Creek"
      }
    },
    {
      "geometry": {
        "type": "Point",
        "coordinates": [
          -105.2,
          37.0833
        ]
      },
      "type": "Feature",
      "properties": {
        "hierarchy": [
          "tgn:2424539",
          "tgn:1000001",
          "tgn:7012149",
          "tgn:7007158",
          "tgn:7029392"
        ],
        "placetype": [
          "aat:300008706"
        ],
        "id": 2424539,
        "name:xx": "Johnson Creek"
      }
    }
  ]
}
