{
  "geometry": {
    "type": "Point",
    "coordinates": [
      -81.15,
      22.1333
    ]
  },
  "type": "Feature",
  "properties": {
    "hierarchy": [
      "tgn:7006414",
      "tgn:1001424",
      "tgn:1000001",
      "tgn:7004624",
      "tgn:7029392"
    ],
    "placetype": [
      "aat:300132316"
    ],
    "id": 7006414,
    "name:xx": "Cochinos, Bahía de"
  }
}
