{
  "geometry": {
    "type": "Point",
    "coordinates": [
      -121.8667,
      37.1833
    ]
  },
  "type": "Feature",
  "properties": {
    "hierarchy": [
      "tgn:2318132",
      "tgn:1000001",
      "tgn:7012149",
      "tgn:7007157",
      "tgn:7014475",
      "tgn:7029392"
    ],
    "placetype": [
      "aat:300000390"
    ],
    "id": 2318132,
    "name:xx": "Enriquita Mine"
  }
}
