{
  "geometry": {
    "type": "Point",
    "coordinates": [
      -116.7167,
      47.35
    ]
  },
  "type": "Feature",
  "properties": {
    "hierarchy": [
      "tgn:2630779",
      "tgn:1000001",
      "tgn:7012149",
      "tgn:7007250",
      "tgn:7029392"
    ],
    "placetype": [
      "aat:300008680"
    ],
    "id": 2630779,
    "name:xx": "Round Lake"
  }
}
