{
  "type": "FeatureCollection",
  "features": [
    {
      "geometry": {
        "type": "Point",
        "coordinates": [
          -84.0333,
          36.9
        ]
      },
      "type": "Feature",
      "properties": {
        "hierarchy": [
          "tgn:2694750",
          "tgn:1000001",
          "tgn:7012149",
          "tgn:2000806",
          "tgn:7007255",
          "tgn:7029392"
        ],
        "placetype": [
          "aat:300008706"
        ],
        "id": 2694750,
        "name:xx": "Stewarts Creek"
      }
    },
    {
      "geometry": {
        "type": "Point",
        "coordinates": [
          -85.35,
          37.5833
        ]
      },
      "type": "Feature",
      "properties": {
        "hierarchy": [
          "tgn:2694751",
          "tgn:1000001",
          "tgn:7012149",
          "tgn:2000822",
          "tgn:7007255",
          "tgn:7029392"
        ],
        "placetype": [
          "aat:300008706"
        ],
        "id": 2694751,
        "name:xx": "Stewarts Creek"
      }
    },
    {
      "geometry": {
        "type": "Point",
        "coordinates": [
          -78.0833,
          34.9667
        ]
      },
      "type": "Feature",
      "properties": {
        "hierarchy": [
          "tgn:2694754",
          "tgn:1000001",
          "tgn:7012149",
          "tgn:7007709",
          "tgn:7029392"
        ],
        "placetype": [
          "aat:300008706"
        ],
        "id": 2694754,
        "name:xx": "Stewarts Creek"
      }
    },
    {
      "geometry": {
        "type": "Point",
        "coordinates": [
          -80.6167,
          35.0333
        ]
      },
      "type": "Feature",
      "properties": {
        "hierarchy": [
          "tgn:2694755",
          "tgn:1000001",
          "tgn:7012149",
          "tgn:2001546",
          "tgn:7007709",
          "tgn:7029392"
        ],
        "placetype": [
          "aat:300008706"
        ],
        "id": 2694755,
        "name:xx": "Stewarts Creek"
      }
    },
    {
      "geometry": {
        "type": "Point",
        "coordinates": [
          -78,
          35.05
        ]
      },
      "type": "Feature",
      "properties": {
        "hierarchy": [
          "tgn:2694756",
          "tgn:1000001",
          "tgn:7012149",
          "tgn:2001491",
          "tgn:7007709",
          "tgn:7029392"
        ],
        "placetype": [
          "aat:300008706"
        ],
        "id": 2694756,
        "name:xx": "Stewarts Creek"
      }
    },
    {
      "geometry": {
        "type": "Point",
        "coordinates": [
          -80.7833,
          36.5833
        ]
      },
      "type": "Feature",
      "properties": {
        "hierarchy": [
          "tgn:2694757",
          "tgn:1000001",
          "tgn:7012149",
          "tgn:7029392"
        ],
        "placetype": [
          "aat:300008706"
        ],
        "id": 2694757,
        "name:xx": "Stewarts Creek"
      }
    },
    {
      "geometry": {
        "type": "Point",
        "coordinates": [
          -95.5,
          30.4
        ]
      },
      "type": "Feature",
      "properties": {
        "hierarchy": [
          "tgn:2694758",
          "tgn:1000001",
          "tgn:7012149",
          "tgn:1002691",
          "tgn:7007826",
          "tgn:7029392"
        ],
        "placetype": [
          "aat:300008706"
        ],
        "id": 2694758,
        "name:xx": "Stewarts Creek"
      }
    },
    {
      "geometry": {
        "type": "Point",
        "coordinates": [
          -119.4667,
          44.45
        ]
      },
      "type": "Feature",
      "properties": {
        "hierarchy": [
          "tgn:2694759",
          "tgn:1000001",
          "tgn:7012149",
          "tgn:2001708",
          "tgn:7007708",
          "tgn:7029392"
        ],
        "placetype": [
          "aat:300008347"
        ],
        "id": 2694759,
        "name:xx": "Stewarts Crossing"
      }
    }
  ]
}
