{
  "geometry": {
    "type": "Point",
    "coordinates": [
      -116.8167,
      43.0167
    ]
  },
  "type": "Feature",
  "properties": {
    "hierarchy": [
      "tgn:2131281",
      "tgn:1000001",
      "tgn:7012149",
      "tgn:2000488",
      "tgn:7007250",
      "tgn:7029392"
    ],
    "placetype": [
      "aat:300000390"
    ],
    "id": 2131281,
    "name:xx": "Alta Mine"
  }
}
