{
  "geometry": {
    "type": "Point",
    "coordinates": [
      -75.1333,
      44.3167
    ]
  },
  "type": "Feature",
  "properties": {
    "hierarchy": [
      "tgn:2173287",
      "tgn:1000001",
      "tgn:7012149",
      "tgn:7016021",
      "tgn:7007568",
      "tgn:7029392"
    ],
    "placetype": [
      "aat:300008699"
    ],
    "id": 2173287,
    "name:xx": "Birch Brook"
  }
}
