{
  "geometry": {
    "type": "Point",
    "coordinates": [
      78.286684,
      24.132663
    ]
  },
  "type": "Feature",
  "properties": {
    "hierarchy": [
      "tgn:7582970",
      "tgn:1000004",
      "tgn:7000198",
      "tgn:1001894",
      "tgn:7029392"
    ],
    "placetype": [
      "aat:300008347"
    ],
    "name:en": "Mohalīmokam",
    "id": 7582970
  }
}
