{
  "geometry": {
    "type": "Point",
    "coordinates": [
      -111.55,
      42.0333
    ]
  },
  "type": "Feature",
  "properties": {
    "hierarchy": [
      "tgn:2665480",
      "tgn:1000001",
      "tgn:7012149",
      "tgn:7029392"
    ],
    "placetype": [
      "aat:300008761"
    ],
    "id": 2665480,
    "name:xx": "Sink Hollow"
  }
}
