{
  "geometry": {
    "type": "Point",
    "coordinates": [
      29.05,
      52.4167
    ]
  },
  "type": "Feature",
  "properties": {
    "hierarchy": [
      "tgn:1138354",
      "tgn:7012187",
      "tgn:1000003",
      "tgn:7006657",
      "tgn:7029392"
    ],
    "placetype": [
      "aat:300008347",
      "aat:300008375"
    ],
    "id": 1138354,
    "name:xx": "Saviči"
  }
}
