{
  "geometry": {
    "type": "Point",
    "coordinates": [
      31.066,
      29.483
    ]
  },
  "type": "Feature",
  "properties": {
    "hierarchy": [
      "tgn:6004675",
      "tgn:7001242",
      "tgn:7001105",
      "tgn:7016833",
      "tgn:7029392"
    ],
    "placetype": [
      "aat:300008024",
      "aat:300000833"
    ],
    "id": 6004675,
    "name:xx": "Kawm al Ḩamām"
  }
}
