{
  "type": "FeatureCollection",
  "features": [
    {
      "geometry": {
        "type": "Point",
        "coordinates": [
          0.28234,
          42.257791
        ]
      },
      "type": "Feature",
      "properties": {
        "hierarchy": [
          "tgn:5003430",
          "tgn:7002759",
          "tgn:7008909",
          "tgn:1000003",
          "tgn:1000095",
          "tgn:7029392"
        ],
        "placetype": [
          "aat:300008347"
        ],
        "id": 5003430,
        "name:xx": "Pano"
      }
    },
    {
      "geometry": {
        "type": "Point",
        "coordinates": [
          0.119065,
          41.929736
        ]
      },
      "type": "Feature",
      "properties": {
        "hierarchy": [
          "tgn:5003433",
          "tgn:7002759",
          "tgn:7008909",
          "tgn:1000003",
          "tgn:1000095",
          "tgn:7029392"
        ],
        "placetype": [
          "aat:300008347"
        ],
        "id": 5003433,
        "name:xx": "Selgua"
      }
    },
    {
      "geometry": {
        "type": "Point",
        "coordinates": [
          0.564834,
          42.114529
        ]
      },
      "type": "Feature",
      "properties": {
        "hierarchy": [
          "tgn:5003436",
          "tgn:7002759",
          "tgn:7008909",
          "tgn:1000003",
          "tgn:1000095",
          "tgn:7029392"
        ],
        "placetype": [
          "aat:300008347"
        ],
        "id": 5003436,
        "name:xx": "Tolva"
      }
    },
    {
      "geometry": {
        "type": "Point",
        "coordinates": [
          -81.1667,
          43.4
        ]
      },
      "type": "Feature",
      "properties": {
        "hierarchy": [
          "tgn:5003439",
          "tgn:7002824",
          "tgn:1000003",
          "tgn:7002786",
          "tgn:1000095",
          "tgn:7029392"
        ],
        "placetype": [
          "aat:300008347"
        ],
        "id": 5003439,
        "name:xx": "Breamo"
      }
    }
  ]
}
