{
  "geometry": {
    "type": "Point",
    "coordinates": [
      -70.45,
      -33.75
    ]
  },
  "type": "Feature",
  "properties": {
    "hierarchy": [
      "tgn:7313058",
      "tgn:1001708",
      "tgn:1000049",
      "tgn:1000002",
      "tgn:7029392"
    ],
    "placetype": [
      "aat:300008699"
    ],
    "id": 7313058,
    "name:xx": "Los Cipreses, Cajón de"
  }
}
