{
  "geometry": {
    "type": "Point",
    "coordinates": [
      76.202433,
      30.608397
    ]
  },
  "type": "Feature",
  "properties": {
    "hierarchy": [
      "tgn:7583529",
      "tgn:1000004",
      "tgn:7000198",
      "tgn:7016883",
      "tgn:7029392"
    ],
    "placetype": [
      "aat:300008347"
    ],
    "name:en": "Chāhilān",
    "id": 7583529
  }
}
