{
  "geometry": {
    "type": "Point",
    "coordinates": [
      -74.35,
      41.75
    ]
  },
  "type": "Feature",
  "properties": {
    "hierarchy": [
      "tgn:2073007",
      "tgn:1000001",
      "tgn:7012149",
      "tgn:1002961",
      "tgn:7007568",
      "tgn:7029392"
    ],
    "placetype": [
      "aat:300008347"
    ],
    "id": 2073007,
    "name:xx": "Wawarsing"
  }
}
