{
  "type": "FeatureCollection",
  "features": [
    {
      "geometry": {
        "type": "Point",
        "coordinates": [
          6.383333,
          50.75
        ]
      },
      "type": "Feature",
      "properties": {
        "hierarchy": [
          "tgn:7161070",
          "tgn:1000003",
          "tgn:7003677",
          "tgn:7000084",
          "tgn:7029392"
        ],
        "placetype": [
          "aat:300008863"
        ],
        "id": 7161070,
        "name:xx": "Der Hochwald"
      }
    },
    {
      "geometry": {
        "type": "Point",
        "coordinates": [
          7.633333,
          50.1
        ]
      },
      "type": "Feature",
      "properties": {
        "hierarchy": [
          "tgn:7161071",
          "tgn:1000003",
          "tgn:7003682",
          "tgn:7000084",
          "tgn:7029392"
        ],
        "placetype": [
          "aat:300008863"
        ],
        "id": 7161071,
        "name:xx": "Hochwald"
      }
    },
    {
      "geometry": {
        "type": "Point",
        "coordinates": [
          12.416667,
          49.95
        ]
      },
      "type": "Feature",
      "properties": {
        "hierarchy": [
          "tgn:7161072",
          "tgn:7003669",
          "tgn:1000003",
          "tgn:7000084",
          "tgn:7029392"
        ],
        "placetype": [
          "aat:300008863"
        ],
        "id": 7161072,
        "name:xx": "Hoch-Wald"
      }
    },
    {
      "geometry": {
        "type": "Point",
        "coordinates": [
          7.166667,
          49.95
        ]
      },
      "type": "Feature",
      "properties": {
        "hierarchy": [
          "tgn:7161073",
          "tgn:1000003",
          "tgn:7003682",
          "tgn:7000084",
          "tgn:7029392"
        ],
        "placetype": [
          "aat:300008863"
        ],
        "id": 7161073,
        "name:xx": "Hochwald"
      }
    },
    {
      "geometry": {
        "type": "Point",
        "coordinates": [
          10.483333,
          49.883333
        ]
      },
      "type": "Feature",
      "properties": {
        "hierarchy": [
          "tgn:7161074",
          "tgn:7003669",
          "tgn:1000003",
          "tgn:7000084",
          "tgn:7029392"
        ],
        "placetype": [
          "aat:300008863"
        ],
        "id": 7161074,
        "name:xx": "Hochwald"
      }
    },
    {
      "geometry": {
        "type": "Point",
        "coordinates": [
          7.1,
          49.233333
        ]
      },
      "type": "Feature",
      "properties": {
        "hierarchy": [
          "tgn:7161075",
          "tgn:1000003",
          "tgn:7003684",
          "tgn:7000084",
          "tgn:7029392"
        ],
        "placetype": [
          "aat:300008863"
        ],
        "id": 7161075,
        "name:xx": "Hochwald"
      }
    },
    {
      "geometry": {
        "type": "Point",
        "coordinates": [
          7.283333,
          49.183333
        ]
      },
      "type": "Feature",
      "properties": {
        "hierarchy": [
          "tgn:7161076",
          "tgn:1000003",
          "tgn:7003684",
          "tgn:7000084",
          "tgn:7029392"
        ],
        "placetype": [
          "aat:300008863"
        ],
        "id": 7161076,
        "name:xx": "Hochwald"
      }
    },
    {
      "geometry": {
        "type": "Point",
        "coordinates": [
          8.766667,
          49.066667
        ]
      },
      "type": "Feature",
      "properties": {
        "hierarchy": [
          "tgn:7161077",
          "tgn:7003692",
          "tgn:1000003",
          "tgn:7000084",
          "tgn:7029392"
        ],
        "placetype": [
          "aat:300008863"
        ],
        "id": 7161077,
        "name:xx": "Hochwald"
      }
    },
    {
      "geometry": {
        "type": "Point",
        "coordinates": [
          8.483333,
          48.166667
        ]
      },
      "type": "Feature",
      "properties": {
        "hierarchy": [
          "tgn:7161078",
          "tgn:7003692",
          "tgn:1000003",
          "tgn:7000084",
          "tgn:7029392"
        ],
        "placetype": [
          "aat:300008863"
        ],
        "id": 7161078,
        "name:xx": "Hochwald"
      }
    }
  ]
}
