{
  "geometry": {
    "type": "Point",
    "coordinates": [
      -110.7333,
      46.9333
    ]
  },
  "type": "Feature",
  "properties": {
    "hierarchy": [
      "tgn:2534597",
      "tgn:1000001",
      "tgn:2001266",
      "tgn:7012149",
      "tgn:7007524",
      "tgn:7029392"
    ],
    "placetype": [
      "aat:300000390"
    ],
    "id": 2534597,
    "name:xx": "NW SW Section 29 Mine"
  }
}
