{
  "geometry": {
    "type": "Point",
    "coordinates": [
      -99.9833,
      30.0833
    ]
  },
  "type": "Feature",
  "properties": {
    "hierarchy": [
      "tgn:2253240",
      "tgn:1000001",
      "tgn:7012149",
      "tgn:2001980",
      "tgn:7007826",
      "tgn:7029392"
    ],
    "placetype": [
      "aat:300008706"
    ],
    "id": 2253240,
    "name:xx": "Contrary Creek"
  }
}
