{
  "geometry": {
    "type": "Point",
    "coordinates": [
      -111.6167,
      43.2833
    ]
  },
  "type": "Feature",
  "properties": {
    "hierarchy": [
      "tgn:2223586",
      "tgn:1000001",
      "tgn:7012149",
      "tgn:7007250",
      "tgn:7029392"
    ],
    "placetype": [
      "aat:300008706"
    ],
    "id": 2223586,
    "name:xx": "Carter Creek"
  }
}
