{
  "geometry": {
    "type": "Point",
    "coordinates": [
      11.166667,
      51.55
    ]
  },
  "type": "Feature",
  "properties": {
    "hierarchy": [
      "tgn:7212105",
      "tgn:1000003",
      "tgn:7003687",
      "tgn:7000084",
      "tgn:7029392"
    ],
    "placetype": [
      "aat:300004792"
    ],
    "id": 7212105,
    "name:xx": "Försterei Bodenschwende"
  }
}
