{
  "geometry": {
    "type": "Point",
    "coordinates": [
      -94.6667,
      47.0333
    ]
  },
  "type": "Feature",
  "properties": {
    "hierarchy": [
      "tgn:2451406",
      "tgn:1000001",
      "tgn:7012149",
      "tgn:2001027",
      "tgn:7007521",
      "tgn:7029392"
    ],
    "placetype": [
      "aat:300008680"
    ],
    "id": 2451406,
    "name:xx": "Little Bass Lake"
  }
}
