{
  "geometry": {
    "type": "Point",
    "coordinates": [
      34.3333,
      54.0833
    ]
  },
  "type": "Feature",
  "properties": {
    "hierarchy": [
      "tgn:1055317",
      "tgn:1000004",
      "tgn:1003377",
      "tgn:7018214",
      "tgn:7002435",
      "tgn:7029392"
    ],
    "placetype": [
      "aat:300008347"
    ],
    "id": 1055317,
    "name:xx": "Kirov"
  }
}
