{
  "geometry": {
    "type": "Point",
    "coordinates": [
      -107.4333,
      44.9667
    ]
  },
  "type": "Feature",
  "properties": {
    "hierarchy": [
      "tgn:2239415",
      "tgn:1000001",
      "tgn:7012149",
      "tgn:2002381",
      "tgn:7007923",
      "tgn:7029392"
    ],
    "placetype": [
      "aat:300006075"
    ],
    "id": 2239415,
    "name:xx": "Church Ditch"
  }
}
