{
  "geometry": {
    "type": "Point",
    "coordinates": [
      -71.8667,
      41.6333
    ]
  },
  "type": "Feature",
  "properties": {
    "hierarchy": [
      "tgn:2384563",
      "tgn:1000001",
      "tgn:7012149",
      "tgn:7007159",
      "tgn:7029392"
    ],
    "placetype": [
      "aat:300008761"
    ],
    "id": 2384563,
    "name:xx": "Hell Hollow"
  }
}
