{
  "geometry": {
    "type": "Point",
    "coordinates": [
      121.4562,
      25.0453
    ]
  },
  "type": "Feature",
  "properties": {
    "hierarchy": [
      "tgn:7469301",
      "tgn:1000004",
      "tgn:1000454",
      "tgn:1000141",
      "tgn:7029392"
    ],
    "placetype": [
      "aat:300387173"
    ],
    "id": 7469301,
    "name:xx": "Zhonggang Li"
  }
}
