{
  "geometry": {
    "type": "Point",
    "coordinates": [
      -97.4167,
      32.1833
    ]
  },
  "type": "Feature",
  "properties": {
    "hierarchy": [
      "tgn:2162197",
      "tgn:1000001",
      "tgn:7012149",
      "tgn:7007826",
      "tgn:7029392"
    ],
    "placetype": [
      "aat:300008706"
    ],
    "id": 2162197,
    "name:xx": "Belnap Creek"
  }
}
