{
  "geometry": {
    "type": "Point",
    "coordinates": [
      -102.2167,
      41.8667
    ]
  },
  "type": "Feature",
  "properties": {
    "hierarchy": [
      "tgn:2751516",
      "tgn:1000001",
      "tgn:2001350",
      "tgn:7012149",
      "tgn:7007525",
      "tgn:7029392"
    ],
    "placetype": [
      "aat:300386845"
    ],
    "id": 2751516,
    "name:xx": "Warneke Valley"
  }
}
