{
  "geometry": {
    "type": "Point",
    "coordinates": [
      -74.3333,
      41.8833
    ]
  },
  "type": "Feature",
  "properties": {
    "hierarchy": [
      "tgn:2170488",
      "tgn:1000001",
      "tgn:7012149",
      "tgn:1002961",
      "tgn:7007568",
      "tgn:7029392"
    ],
    "placetype": [
      "aat:300008798"
    ],
    "id": 2170488,
    "name:xx": "Big Rosy Bone Knob"
  }
}
