{
  "geometry": {
    "type": "Point",
    "coordinates": [
      -75.2833,
      38.05
    ]
  },
  "type": "Feature",
  "properties": {
    "hierarchy": [
      "tgn:2767074",
      "tgn:1000001",
      "tgn:1003037",
      "tgn:7012149",
      "tgn:7007516",
      "tgn:7029392"
    ],
    "placetype": [
      "aat:300132348"
    ],
    "id": 2767074,
    "name:xx": "White Rock"
  }
}
