{
  "geometry": {
    "type": "Point",
    "coordinates": [
      -88.0167,
      32.75
    ]
  },
  "type": "Feature",
  "properties": {
    "hierarchy": [
      "tgn:2002842",
      "tgn:7002659",
      "tgn:1000001",
      "tgn:7012149",
      "tgn:2000031",
      "tgn:7029392"
    ],
    "placetype": [
      "aat:300008347"
    ],
    "id": 2002842,
    "name:xx": "Boligee"
  }
}
