{
  "type": "FeatureCollection",
  "features": [
    {
      "geometry": {
        "type": "Point",
        "coordinates": [
          -50.6833,
          -2.5833
        ]
      },
      "type": "Feature",
      "properties": {
        "hierarchy": [
          "tgn:1121320",
          "tgn:7006247",
          "tgn:1000047",
          "tgn:7002456",
          "tgn:1000002",
          "tgn:7029392"
        ],
        "placetype": [
          "aat:300008707"
        ],
        "id": 1121320,
        "name:xx": "Arataú"
      }
    },
    {
      "geometry": {
        "type": "Point",
        "coordinates": [
          -49.85,
          -1.9167
        ]
      },
      "type": "Feature",
      "properties": {
        "hierarchy": [
          "tgn:1121321",
          "tgn:7006247",
          "tgn:1000047",
          "tgn:7002456",
          "tgn:1000002",
          "tgn:7029392"
        ],
        "placetype": [
          "aat:300008707"
        ],
        "id": 1121321,
        "name:xx": "Araticu"
      }
    },
    {
      "geometry": {
        "type": "Point",
        "coordinates": [
          -63.6,
          -4.1
        ]
      },
      "type": "Feature",
      "properties": {
        "hierarchy": [
          "tgn:1121322",
          "tgn:1001826",
          "tgn:1000047",
          "tgn:7002456",
          "tgn:1000002",
          "tgn:7029392"
        ],
        "placetype": [
          "aat:300008707"
        ],
        "id": 1121322,
        "name:xx": "Arauá"
      }
    },
    {
      "geometry": {
        "type": "Point",
        "coordinates": [
          -65.2333,
          -7.9833
        ]
      },
      "type": "Feature",
      "properties": {
        "hierarchy": [
          "tgn:1121323",
          "tgn:1001826",
          "tgn:1000047",
          "tgn:7002456",
          "tgn:1000002",
          "tgn:7029392"
        ],
        "placetype": [
          "aat:300008707"
        ],
        "id": 1121323,
        "name:xx": "Arauã"
      }
    },
    {
      "geometry": {
        "type": "Point",
        "coordinates": [
          -66.5833,
          7.4
        ]
      },
      "type": "Feature",
      "properties": {
        "hierarchy": [
          "tgn:1121324",
          "tgn:1000002",
          "tgn:1000059",
          "tgn:7029392"
        ],
        "placetype": [
          "aat:300008707"
        ],
        "id": 1121324,
        "name:xx": "Arauca, Río"
      }
    },
    {
      "geometry": {
        "type": "Point",
        "coordinates": [
          168.683333,
          -44
        ]
      },
      "type": "Feature",
      "properties": {
        "hierarchy": [
          "tgn:1121326",
          "tgn:1009227",
          "tgn:1000226",
          "tgn:1000006",
          "tgn:7029392"
        ],
        "placetype": [
          "aat:300008707",
          "aat:300008699"
        ],
        "id": 1121326,
        "name:xx": "Arawata"
      }
    }
  ]
}
