{
  "type": "FeatureCollection",
  "features": [
    {
      "geometry": {
        "type": "Point",
        "coordinates": [
          -89.6667,
          40.85
        ]
      },
      "type": "Feature",
      "properties": {
        "hierarchy": [
          "tgn:2027560",
          "tgn:1000001",
          "tgn:7012149",
          "tgn:2000521",
          "tgn:7007251",
          "tgn:7029392"
        ],
        "placetype": [
          "aat:300008347"
        ],
        "id": 2027560,
        "name:xx": "Dunlap"
      }
    },
    {
      "geometry": {
        "type": "Point",
        "coordinates": [
          -90.2,
          38.5
        ]
      },
      "type": "Feature",
      "properties": {
        "hierarchy": [
          "tgn:2027561",
          "tgn:1000001",
          "tgn:7012149",
          "tgn:7016022",
          "tgn:7007251",
          "tgn:7029392"
        ],
        "placetype": [
          "aat:300008347"
        ],
        "id": 2027561,
        "name:xx": "Dupo"
      }
    },
    {
      "geometry": {
        "type": "Point",
        "coordinates": [
          -89.25,
          37.9833
        ]
      },
      "type": "Feature",
      "properties": {
        "hierarchy": [
          "tgn:2027565",
          "tgn:1000001",
          "tgn:7012149",
          "tgn:2000522",
          "tgn:7007251",
          "tgn:7029392"
        ],
        "placetype": [
          "aat:300008347"
        ],
        "id": 2027565,
        "name:xx": "Du Quoin"
      }
    },
    {
      "geometry": {
        "type": "Point",
        "coordinates": [
          -89.3167,
          42.4333
        ]
      },
      "type": "Feature",
      "properties": {
        "hierarchy": [
          "tgn:2027566",
          "tgn:1000001",
          "tgn:7012149",
          "tgn:1003030",
          "tgn:7007251",
          "tgn:7029392"
        ],
        "placetype": [
          "aat:300008347"
        ],
        "id": 2027566,
        "name:xx": "Durand"
      }
    },
    {
      "geometry": {
        "type": "Point",
        "coordinates": [
          -90.0167,
          38.5667
        ]
      },
      "type": "Feature",
      "properties": {
        "hierarchy": [
          "tgn:2027568",
          "tgn:1000001",
          "tgn:7012149",
          "tgn:7016022",
          "tgn:7007251",
          "tgn:7029392"
        ],
        "placetype": [
          "aat:300008347"
        ],
        "id": 2027568,
        "name:xx": "Dutch Hollow"
      }
    }
  ]
}
