{
  "geometry": {
    "type": "Point",
    "coordinates": [
      -83.2667,
      38.2833
    ]
  },
  "type": "Feature",
  "properties": {
    "hierarchy": [
      "tgn:1134930",
      "tgn:1000001",
      "tgn:7012149",
      "tgn:7007255",
      "tgn:7029392"
    ],
    "placetype": [
      "aat:300008706"
    ],
    "id": 1134930,
    "name:xx": "Tygarts Creek"
  }
}
