{
  "geometry": {
    "type": "Point",
    "coordinates": [
      79.14791,
      25.512178
    ]
  },
  "type": "Feature",
  "properties": {
    "hierarchy": [
      "tgn:7566674",
      "tgn:1000004",
      "tgn:7000198",
      "tgn:7016722",
      "tgn:7029392"
    ],
    "placetype": [
      "aat:300006075"
    ],
    "name:en": "Barwār Main Canal",
    "id": 7566674
  }
}
