{
  "geometry": {
    "type": "Point",
    "coordinates": [
      -40.5333,
      -16.3833
    ]
  },
  "type": "Feature",
  "properties": {
    "hierarchy": [
      "tgn:1022743",
      "tgn:7006237",
      "tgn:1000047",
      "tgn:7002457",
      "tgn:1000002",
      "tgn:7029392"
    ],
    "placetype": [
      "aat:300008347"
    ],
    "id": 1022743,
    "name:xx": "Rubim"
  }
}
