{
  "geometry": {
    "type": "Point",
    "coordinates": [
      -114.4833,
      42.0667
    ]
  },
  "type": "Feature",
  "properties": {
    "hierarchy": [
      "tgn:2206089",
      "tgn:1000001",
      "tgn:7012149",
      "tgn:2000493",
      "tgn:7007250",
      "tgn:7029392"
    ],
    "placetype": [
      "aat:300008697"
    ],
    "id": 2206089,
    "name:xx": "Bull Spring"
  }
}
