{
  "geometry": {
    "type": "Point",
    "coordinates": [
      123.3667,
      42.35
    ]
  },
  "type": "Feature",
  "properties": {
    "hierarchy": [
      "tgn:1068814",
      "tgn:1000004",
      "tgn:1001390",
      "tgn:1000111",
      "tgn:7029392"
    ],
    "placetype": [
      "aat:300008347"
    ],
    "id": 1068814,
    "name:xx": "Hougujiazi"
  }
}
