{
  "geometry": {
    "type": "Point",
    "coordinates": [
      11.1667,
      61.7667
    ]
  },
  "type": "Feature",
  "properties": {
    "hierarchy": [
      "tgn:1048697",
      "tgn:7003643",
      "tgn:1000003",
      "tgn:1000088",
      "tgn:7029392"
    ],
    "placetype": [
      "aat:300008347"
    ],
    "id": 1048697,
    "name:xx": "Otnes"
  }
}
