{
  "type": "FeatureCollection",
  "features": [
    {
      "geometry": {
        "type": "Point",
        "coordinates": [
          11.183333,
          42.5
        ]
      },
      "type": "Feature",
      "properties": {
        "hierarchy": [
          "tgn:7009080",
          "tgn:1003460",
          "tgn:1000003",
          "tgn:7009760",
          "tgn:1000080",
          "tgn:7029392"
        ],
        "placetype": [
          "aat:300008707",
          "aat:300008699"
        ],
        "id": 7009080,
        "name:xx": "Albegna"
      }
    },
    {
      "geometry": {
        "type": "Point",
        "coordinates": [
          13.3,
          42.383
        ]
      },
      "type": "Feature",
      "properties": {
        "hierarchy": [
          "tgn:7009082",
          "tgn:7009084",
          "tgn:7004154",
          "tgn:1000003",
          "tgn:1000080",
          "tgn:7029392"
        ],
        "placetype": [
          "aat:300008347",
          "aat:300000810",
          "aat:300008372",
          "aat:300308016"
        ],
        "id": 7009082,
        "name:xx": "San Vittorino"
      }
    },
    {
      "geometry": {
        "type": "Point",
        "coordinates": [
          -6.416667,
          56.316667
        ]
      },
      "type": "Feature",
      "properties": {
        "hierarchy": [
          "tgn:7009083",
          "tgn:7019094",
          "tgn:7002444",
          "tgn:1000003",
          "tgn:7008591",
          "tgn:7029392"
        ],
        "placetype": [
          "aat:300008791"
        ],
        "name:en": "Iona",
        "id": 7009083
      }
    },
    {
      "geometry": {
        "type": "Point",
        "coordinates": [
          13.75,
          42.25
        ]
      },
      "type": "Feature",
      "properties": {
        "hierarchy": [
          "tgn:7009084",
          "tgn:1000003",
          "tgn:1000080",
          "tgn:7029392"
        ],
        "placetype": [
          "aat:300019258",
          "aat:300387064",
          "aat:300019267",
          "aat:300019508",
          "aat:300020533",
          "aat:300236112"
        ],
        "id": 7009084,
        "name:it": "Abruzzi"
      }
    },
    {
      "geometry": {
        "type": "Point",
        "coordinates": [
          -6.266667,
          56.016667
        ]
      },
      "type": "Feature",
      "properties": {
        "hierarchy": [
          "tgn:7009087",
          "tgn:7019094",
          "tgn:7002444",
          "tgn:1000003",
          "tgn:7008591",
          "tgn:7029392"
        ],
        "placetype": [
          "aat:300008791"
        ],
        "name:en": "Oronsay",
        "id": 7009087
      }
    },
    {
      "geometry": {
        "type": "Point",
        "coordinates": [
          14.333333,
          41.333333
        ]
      },
      "type": "Feature",
      "properties": {
        "hierarchy": [
          "tgn:7009088",
          "tgn:7003011",
          "tgn:7003005",
          "tgn:1000003",
          "tgn:1000080",
          "tgn:7029392"
        ],
        "placetype": [
          "aat:300008347",
          "aat:300000810",
          "aat:300008375"
        ],
        "id": 7009088,
        "name:xx": "Alife"
      }
    }
  ]
}
