{
  "geometry": {
    "type": "Point",
    "coordinates": [
      -82.8167,
      27.9167
    ]
  },
  "type": "Feature",
  "properties": {
    "hierarchy": [
      "tgn:2589679",
      "tgn:1000001",
      "tgn:7012149",
      "tgn:1002790",
      "tgn:7007240",
      "tgn:7029392"
    ],
    "placetype": [
      "aat:300008850"
    ],
    "id": 2589679,
    "name:xx": "Point Pleasant"
  }
}
