{
  "geometry": {
    "type": "Point",
    "coordinates": [
      -78.0667,
      38.0333
    ]
  },
  "type": "Feature",
  "properties": {
    "hierarchy": [
      "tgn:2483326",
      "tgn:1000001",
      "tgn:7012149",
      "tgn:2002170",
      "tgn:7007919",
      "tgn:7029392"
    ],
    "placetype": [
      "aat:300008706"
    ],
    "id": 2483326,
    "name:xx": "Lasley Creek"
  }
}
