{
  "geometry": {
    "type": "Point",
    "coordinates": [
      99.6667,
      17.25
    ]
  },
  "type": "Feature",
  "properties": {
    "hierarchy": [
      "tgn:7000965",
      "tgn:7005194",
      "tgn:1000004",
      "tgn:1000142",
      "tgn:7029392"
    ],
    "placetype": [
      "aat:300387145",
      "aat:300000774"
    ],
    "id": 7000965,
    "name:xx": "Sukhothai, Changwat"
  }
}
