{
  "geometry": {
    "type": "Point",
    "coordinates": [
      -76.45,
      35.0667
    ]
  },
  "type": "Feature",
  "properties": {
    "hierarchy": [
      "tgn:2589842",
      "tgn:1000001",
      "tgn:2001477",
      "tgn:7012149",
      "tgn:7007709",
      "tgn:7029392"
    ],
    "placetype": [
      "aat:300008850"
    ],
    "id": 2589842,
    "name:xx": "Point of Marsh"
  }
}
