{
  "geometry": {
    "type": "Point",
    "coordinates": [
      -82.2833,
      30.4333
    ]
  },
  "type": "Feature",
  "properties": {
    "hierarchy": [
      "tgn:2021532",
      "tgn:2000257",
      "tgn:1000001",
      "tgn:7012149",
      "tgn:7007240",
      "tgn:7029392"
    ],
    "placetype": [
      "aat:300008347"
    ],
    "id": 2021532,
    "name:xx": "Taylor"
  }
}
