{
  "geometry": {
    "type": "Point",
    "coordinates": [
      31.855607,
      30.114164
    ]
  },
  "type": "Feature",
  "properties": {
    "hierarchy": [
      "tgn:7535353",
      "tgn:7001242",
      "tgn:7016833",
      "tgn:7029392"
    ],
    "placetype": [
      "aat:300379998"
    ],
    "name:en": "Fūl, Wādī al",
    "id": 7535353
  }
}
