{
  "geometry": {
    "type": "Point",
    "coordinates": [
      -83.85,
      38.1167
    ]
  },
  "type": "Feature",
  "properties": {
    "hierarchy": [
      "tgn:2639376",
      "tgn:1000001",
      "tgn:7012149",
      "tgn:2000799",
      "tgn:7007255",
      "tgn:7029392"
    ],
    "placetype": [
      "aat:300008706"
    ],
    "id": 2639376,
    "name:xx": "Salt Well Creek"
  }
}
