{
  "geometry": {
    "type": "Point",
    "coordinates": [
      -67.8333,
      51.15
    ]
  },
  "type": "Feature",
  "properties": {
    "hierarchy": [
      "tgn:1115528",
      "tgn:7005685",
      "tgn:1000001",
      "tgn:7005804",
      "tgn:7029392"
    ],
    "placetype": [
      "aat:300008680"
    ],
    "id": 1115528,
    "name:xx": "Bardoux, Lac"
  }
}
