{
  "geometry": {
    "type": "Point",
    "coordinates": [
      -72.3167,
      43.3167
    ]
  },
  "type": "Feature",
  "properties": {
    "hierarchy": [
      "tgn:2233613",
      "tgn:1000001",
      "tgn:2001427",
      "tgn:7012149",
      "tgn:7007564",
      "tgn:7029392"
    ],
    "placetype": [
      "aat:300008699"
    ],
    "id": 2233613,
    "name:xx": "Chase Brook"
  }
}
