{
  "geometry": {
    "type": "Point",
    "coordinates": [
      31.692021,
      31.239463
    ]
  },
  "type": "Feature",
  "properties": {
    "hierarchy": [
      "tgn:7543473",
      "tgn:7001242",
      "tgn:7016833",
      "tgn:1001225",
      "tgn:7029392"
    ],
    "placetype": [
      "aat:300006075"
    ],
    "name:en": "Tir'at al Baḩarīyah",
    "id": 7543473
  }
}
