{
  "geometry": {
    "type": "Point",
    "coordinates": [
      -81.2667,
      38.3667
    ]
  },
  "type": "Feature",
  "properties": {
    "hierarchy": [
      "tgn:2153727",
      "tgn:1000001",
      "tgn:7012149",
      "tgn:2002270",
      "tgn:7013961",
      "tgn:7029392"
    ],
    "placetype": [
      "aat:300008699"
    ],
    "id": 2153727,
    "name:xx": "Bear Branch"
  }
}
