{
  "geometry": {
    "type": "Point",
    "coordinates": [
      -72.0167,
      41.25
    ]
  },
  "type": "Feature",
  "properties": {
    "hierarchy": [
      "tgn:2069194",
      "tgn:1000001",
      "tgn:7012149",
      "tgn:1002924",
      "tgn:7007568",
      "tgn:7029392"
    ],
    "placetype": [
      "aat:300008347"
    ],
    "id": 2069194,
    "name:xx": "Fishers Island"
  }
}
