{
  "type": "FeatureCollection",
  "features": [
    {
      "geometry": {
        "type": "Point",
        "coordinates": [
          -85.6167,
          40.3833
        ]
      },
      "type": "Feature",
      "properties": {
        "hierarchy": [
          "tgn:2149350",
          "tgn:1000001",
          "tgn:7012149",
          "tgn:1002416",
          "tgn:7007252",
          "tgn:7029392"
        ],
        "placetype": [
          "aat:300008706"
        ],
        "id": 2149350,
        "name:xx": "Barren Creek"
      }
    },
    {
      "geometry": {
        "type": "Point",
        "coordinates": [
          -75.6333,
          38.45
        ]
      },
      "type": "Feature",
      "properties": {
        "hierarchy": [
          "tgn:2149351",
          "tgn:1000001",
          "tgn:1003023",
          "tgn:7012149",
          "tgn:7007516",
          "tgn:7029392"
        ],
        "placetype": [
          "aat:300008706"
        ],
        "id": 2149351,
        "name:xx": "Barren Creek"
      }
    },
    {
      "geometry": {
        "type": "Point",
        "coordinates": [
          -93.4667,
          37.6167
        ]
      },
      "type": "Feature",
      "properties": {
        "hierarchy": [
          "tgn:2149352",
          "tgn:1000001",
          "tgn:7012149",
          "tgn:2001232",
          "tgn:7007523",
          "tgn:7029392"
        ],
        "placetype": [
          "aat:300008706"
        ],
        "id": 2149352,
        "name:xx": "Barren Creek"
      }
    },
    {
      "geometry": {
        "type": "Point",
        "coordinates": [
          -82.3,
          38.9333
        ]
      },
      "type": "Feature",
      "properties": {
        "hierarchy": [
          "tgn:2149353",
          "tgn:1000001",
          "tgn:7012149",
          "tgn:2001612",
          "tgn:7007706",
          "tgn:7029392"
        ],
        "placetype": [
          "aat:300008706"
        ],
        "id": 2149353,
        "name:xx": "Barren Creek"
      }
    },
    {
      "geometry": {
        "type": "Point",
        "coordinates": [
          -85.75,
          35.8167
        ]
      },
      "type": "Feature",
      "properties": {
        "hierarchy": [
          "tgn:2149354",
          "tgn:1000001",
          "tgn:7012149",
          "tgn:7007825",
          "tgn:7029392"
        ],
        "placetype": [
          "aat:300008706"
        ],
        "id": 2149354,
        "name:xx": "Barren Creek"
      }
    },
    {
      "geometry": {
        "type": "Point",
        "coordinates": [
          -81.2833,
          38.4667
        ]
      },
      "type": "Feature",
      "properties": {
        "hierarchy": [
          "tgn:2149355",
          "tgn:1000001",
          "tgn:7012149",
          "tgn:2002270",
          "tgn:7013961",
          "tgn:7029392"
        ],
        "placetype": [
          "aat:300008347"
        ],
        "id": 2149355,
        "name:xx": "Barren Creek"
      }
    },
    {
      "geometry": {
        "type": "Point",
        "coordinates": [
          -81.2833,
          38.4833
        ]
      },
      "type": "Feature",
      "properties": {
        "hierarchy": [
          "tgn:2149356",
          "tgn:1000001",
          "tgn:7012149",
          "tgn:2002270",
          "tgn:7013961",
          "tgn:7029392"
        ],
        "placetype": [
          "aat:300008706"
        ],
        "id": 2149356,
        "name:xx": "Barren Creek"
      }
    },
    {
      "geometry": {
        "type": "Point",
        "coordinates": [
          -75.8167,
          38.4667
        ]
      },
      "type": "Feature",
      "properties": {
        "hierarchy": [
          "tgn:2149357",
          "tgn:1000001",
          "tgn:1003023",
          "tgn:7012149",
          "tgn:7007516",
          "tgn:7029392"
        ],
        "placetype": [
          "aat:300008850"
        ],
        "id": 2149357,
        "name:xx": "Barren Creek Point"
      }
    },
    {
      "geometry": {
        "type": "Point",
        "coordinates": [
          -87.25,
          38.3667
        ]
      },
      "type": "Feature",
      "properties": {
        "hierarchy": [
          "tgn:2149358",
          "tgn:1000001",
          "tgn:7012149",
          "tgn:2000551",
          "tgn:7007252",
          "tgn:7029392"
        ],
        "placetype": [
          "aat:300006075"
        ],
        "id": 2149358,
        "name:xx": "Barren Ditch"
      }
    },
    {
      "geometry": {
        "type": "Point",
        "coordinates": [
          -91.7667,
          35.9833
        ]
      },
      "type": "Feature",
      "properties": {
        "hierarchy": [
          "tgn:2149359",
          "tgn:1000001",
          "tgn:7016172",
          "tgn:7012149",
          "tgn:7029392"
        ],
        "placetype": [
          "aat:300008699"
        ],
        "id": 2149359,
        "name:xx": "Barren Fork"
      }
    }
  ]
}
