{
  "geometry": {
    "type": "Point",
    "coordinates": [
      75.481111,
      25.555
    ]
  },
  "type": "Feature",
  "properties": {
    "hierarchy": [
      "tgn:7568220",
      "tgn:1000004",
      "tgn:7000198",
      "tgn:7016788",
      "tgn:7029392"
    ],
    "placetype": [
      "aat:300008347"
    ],
    "name:en": "Pīthāpura",
    "id": 7568220
  }
}
