{
  "geometry": {
    "type": "Point",
    "coordinates": [
      -3.3333,
      50.85
    ]
  },
  "type": "Feature",
  "properties": {
    "hierarchy": [
      "tgn:7025362",
      "tgn:7002445",
      "tgn:1000003",
      "tgn:7012077",
      "tgn:7008591",
      "tgn:7029392"
    ],
    "placetype": [
      "aat:300008347"
    ],
    "id": 7025362,
    "name:xx": "Aller"
  }
}
