{
  "geometry": {
    "type": "Point",
    "coordinates": [
      -87.7833,
      34.25
    ]
  },
  "type": "Feature",
  "properties": {
    "hierarchy": [
      "tgn:2003475",
      "tgn:7002659",
      "tgn:1000001",
      "tgn:7012149",
      "tgn:2000046",
      "tgn:7029392"
    ],
    "placetype": [
      "aat:300008347",
      "aat:300387210"
    ],
    "id": 2003475,
    "name:xx": "Fairview"
  }
}
