{
  "geometry": {
    "type": "Point",
    "coordinates": [
      9.55,
      53.15
    ]
  },
  "type": "Feature",
  "properties": {
    "hierarchy": [
      "tgn:7079372",
      "tgn:1000003",
      "tgn:7003676",
      "tgn:7000084",
      "tgn:7029392"
    ],
    "placetype": [
      "aat:300055621"
    ],
    "id": 7079372,
    "name:xx": "Wümmeniederung"
  }
}
