{
  "geometry": {
    "type": "Point",
    "coordinates": [
      -85.6333,
      30.5667
    ]
  },
  "type": "Feature",
  "properties": {
    "hierarchy": [
      "tgn:2223489",
      "tgn:1000001",
      "tgn:7012149",
      "tgn:2000291",
      "tgn:7007240",
      "tgn:7029392"
    ],
    "placetype": [
      "aat:300008699"
    ],
    "id": 2223489,
    "name:xx": "Carter Branch"
  }
}
