{
  "geometry": {
    "type": "Point",
    "coordinates": [
      -96.8833,
      31.0333
    ]
  },
  "type": "Feature",
  "properties": {
    "hierarchy": [
      "tgn:2102894",
      "tgn:1000001",
      "tgn:7012149",
      "tgn:1002670",
      "tgn:7007826",
      "tgn:7029392"
    ],
    "placetype": [
      "aat:300008347",
      "aat:300387210"
    ],
    "id": 2102894,
    "name:xx": "Briary"
  }
}
