{
  "geometry": {
    "type": "Point",
    "coordinates": [
      -70.7167,
      -16.8167
    ]
  },
  "type": "Feature",
  "properties": {
    "hierarchy": [
      "tgn:1024418",
      "tgn:1000700",
      "tgn:1000002",
      "tgn:1000056",
      "tgn:7029392"
    ],
    "placetype": [
      "aat:300008347"
    ],
    "id": 1024418,
    "name:xx": "Carumas"
  }
}
