{
  "type": "FeatureCollection",
  "features": [
    {
      "geometry": {
        "type": "Point",
        "coordinates": [
          -74.1,
          40.8667
        ]
      },
      "type": "Feature",
      "properties": {
        "hierarchy": [
          "tgn:2064800",
          "tgn:1002178",
          "tgn:1000001",
          "tgn:7012149",
          "tgn:7007565",
          "tgn:7029392"
        ],
        "placetype": [
          "aat:300008347"
        ],
        "id": 2064800,
        "name:xx": "Garfield"
      }
    },
    {
      "geometry": {
        "type": "Point",
        "coordinates": [
          -74.3167,
          40.65
        ]
      },
      "type": "Feature",
      "properties": {
        "hierarchy": [
          "tgn:2064805",
          "tgn:1000001",
          "tgn:1002963",
          "tgn:7012149",
          "tgn:7007565",
          "tgn:7029392"
        ],
        "placetype": [
          "aat:300008347"
        ],
        "id": 2064805,
        "name:xx": "Garwood"
      }
    },
    {
      "geometry": {
        "type": "Point",
        "coordinates": [
          -74.65,
          40.0667
        ]
      },
      "type": "Feature",
      "properties": {
        "hierarchy": [
          "tgn:2064806",
          "tgn:1002215",
          "tgn:1000001",
          "tgn:7012149",
          "tgn:7007565",
          "tgn:7029392"
        ],
        "placetype": [
          "aat:300008347"
        ],
        "id": 2064806,
        "name:xx": "Georgetown"
      }
    },
    {
      "geometry": {
        "type": "Point",
        "coordinates": [
          -74.2833,
          40.1833
        ]
      },
      "type": "Feature",
      "properties": {
        "hierarchy": [
          "tgn:2064807",
          "tgn:1000001",
          "tgn:7014090",
          "tgn:7012149",
          "tgn:7007565",
          "tgn:7029392"
        ],
        "placetype": [
          "aat:300008347",
          "aat:300387210"
        ],
        "id": 2064807,
        "name:xx": "Georgia"
      }
    },
    {
      "geometry": {
        "type": "Point",
        "coordinates": [
          -74.5833,
          39.5
        ]
      },
      "type": "Feature",
      "properties": {
        "hierarchy": [
          "tgn:2064808",
          "tgn:1002157",
          "tgn:1000001",
          "tgn:7012149",
          "tgn:7007565",
          "tgn:7029392"
        ],
        "placetype": [
          "aat:300008347"
        ],
        "id": 2064808,
        "name:xx": "Germania"
      }
    },
    {
      "geometry": {
        "type": "Point",
        "coordinates": [
          -74.95,
          39.8333
        ]
      },
      "type": "Feature",
      "properties": {
        "hierarchy": [
          "tgn:2064809",
          "tgn:1002227",
          "tgn:1000001",
          "tgn:7012149",
          "tgn:7007565",
          "tgn:7029392"
        ],
        "placetype": [
          "aat:300008347"
        ],
        "id": 2064809,
        "name:xx": "Gibbsboro"
      }
    }
  ]
}
