{
  "geometry": {
    "type": "Point",
    "coordinates": [
      132.3667,
      43.45
    ]
  },
  "type": "Feature",
  "properties": {
    "hierarchy": [
      "tgn:1052305",
      "tgn:1000004",
      "tgn:7011539",
      "tgn:7018214",
      "tgn:7002435",
      "tgn:7029392"
    ],
    "placetype": [
      "aat:300008347"
    ],
    "id": 1052305,
    "name:xx": "Art'omovskij"
  }
}
