{
  "geometry": {
    "type": "Point",
    "coordinates": [
      -90.5833,
      37.8167
    ]
  },
  "type": "Feature",
  "properties": {
    "hierarchy": [
      "tgn:2310115",
      "tgn:1000001",
      "tgn:7012149",
      "tgn:2001241",
      "tgn:7007523",
      "tgn:7029392"
    ],
    "placetype": [
      "aat:300008699"
    ],
    "id": 2310115,
    "name:xx": "Eaton Branch"
  }
}
