{
  "geometry": {
    "type": "Point",
    "coordinates": [
      -64.8167,
      18.3333
    ]
  },
  "type": "Feature",
  "properties": {
    "hierarchy": [
      "tgn:1115021",
      "tgn:1000001",
      "tgn:7005118",
      "tgn:7029392"
    ],
    "placetype": [
      "aat:300266558"
    ],
    "id": 1115021,
    "name:xx": "Pillsbury Sound"
  }
}
