{
  "geometry": {
    "type": "Point",
    "coordinates": [
      -99.0333,
      40.65
    ]
  },
  "type": "Feature",
  "properties": {
    "hierarchy": [
      "tgn:2508385",
      "tgn:1000001",
      "tgn:7012149",
      "tgn:7007525",
      "tgn:7029392"
    ],
    "placetype": [
      "aat:300008707"
    ],
    "id": 2508385,
    "name:xx": "Middle Channel Platte River"
  }
}
