{
  "geometry": {
    "type": "Point",
    "coordinates": [
      -87.3333,
      36.6667
    ]
  },
  "type": "Feature",
  "properties": {
    "hierarchy": [
      "tgn:2148120",
      "tgn:1000001",
      "tgn:2000780",
      "tgn:7012149",
      "tgn:7007255",
      "tgn:7029392"
    ],
    "placetype": [
      "aat:300008347"
    ],
    "id": 2148120,
    "name:xx": "Barkers Mill"
  }
}
