{
  "geometry": {
    "type": "Point",
    "coordinates": [
      -91.2833,
      34.8833
    ]
  },
  "type": "Feature",
  "properties": {
    "hierarchy": [
      "tgn:2388671",
      "tgn:1000001",
      "tgn:7016172",
      "tgn:7012149",
      "tgn:2000152",
      "tgn:7029392"
    ],
    "placetype": [
      "aat:300008680"
    ],
    "id": 2388671,
    "name:xx": "Hickson Lake"
  }
}
