{
  "geometry": {
    "type": "Point",
    "coordinates": [
      -106.2167,
      36.8667
    ]
  },
  "type": "Feature",
  "properties": {
    "hierarchy": [
      "tgn:2146596",
      "tgn:1000001",
      "tgn:7012149",
      "tgn:2001449",
      "tgn:7007566",
      "tgn:7029392"
    ],
    "placetype": [
      "aat:300008798"
    ],
    "id": 2146596,
    "name:xx": "Banco Julian"
  }
}
