{
  "type": "FeatureCollection",
  "features": [
    {
      "geometry": {
        "type": "Point",
        "coordinates": [
          -104.6,
          36.9667
        ]
      },
      "type": "Feature",
      "properties": {
        "hierarchy": [
          "tgn:2287770",
          "tgn:1000001",
          "tgn:2001432",
          "tgn:7012149",
          "tgn:7007566",
          "tgn:7029392"
        ],
        "placetype": [
          "aat:300008761"
        ],
        "id": 2287770,
        "name:xx": "Dillon Canyon"
      }
    },
    {
      "geometry": {
        "type": "Point",
        "coordinates": [
          -123.4,
          40.3333
        ]
      },
      "type": "Feature",
      "properties": {
        "hierarchy": [
          "tgn:2287771",
          "tgn:1000001",
          "tgn:7012149",
          "tgn:7007157",
          "tgn:2000191",
          "tgn:7029392"
        ],
        "placetype": [
          "aat:300132316"
        ],
        "id": 2287771,
        "name:xx": "Dillon Cove"
      }
    },
    {
      "geometry": {
        "type": "Point",
        "coordinates": [
          -163.8167,
          65.2167
        ]
      },
      "type": "Feature",
      "properties": {
        "hierarchy": [
          "tgn:2287772",
          "tgn:7006450",
          "tgn:1000001",
          "tgn:7012149",
          "tgn:2000079",
          "tgn:7029392"
        ],
        "placetype": [
          "aat:300008706"
        ],
        "id": 2287772,
        "name:xx": "Dillon Creek"
      }
    },
    {
      "geometry": {
        "type": "Point",
        "coordinates": [
          -121.2167,
          40.4167
        ]
      },
      "type": "Feature",
      "properties": {
        "hierarchy": [
          "tgn:2287773",
          "tgn:1000001",
          "tgn:7012149",
          "tgn:7007157",
          "tgn:2000187",
          "tgn:7029392"
        ],
        "placetype": [
          "aat:300008706"
        ],
        "id": 2287773,
        "name:xx": "Dillon Creek"
      }
    },
    {
      "geometry": {
        "type": "Point",
        "coordinates": [
          -123.7,
          41.5833
        ]
      },
      "type": "Feature",
      "properties": {
        "hierarchy": [
          "tgn:2287774",
          "tgn:1000001",
          "tgn:7012149",
          "tgn:7007157",
          "tgn:2000189",
          "tgn:7029392"
        ],
        "placetype": [
          "aat:300008706"
        ],
        "id": 2287774,
        "name:xx": "Dillon Creek"
      }
    },
    {
      "geometry": {
        "type": "Point",
        "coordinates": [
          -89.5167,
          40.6167
        ]
      },
      "type": "Feature",
      "properties": {
        "hierarchy": [
          "tgn:2287775",
          "tgn:1000001",
          "tgn:7012149",
          "tgn:2000533",
          "tgn:7007251",
          "tgn:7029392"
        ],
        "placetype": [
          "aat:300008706"
        ],
        "id": 2287775,
        "name:xx": "Dillon Creek"
      }
    },
    {
      "geometry": {
        "type": "Point",
        "coordinates": [
          -86.6333,
          38.5
        ]
      },
      "type": "Feature",
      "properties": {
        "hierarchy": [
          "tgn:2287776",
          "tgn:1000001",
          "tgn:7012149",
          "tgn:7007252",
          "tgn:7029392"
        ],
        "placetype": [
          "aat:300008706"
        ],
        "id": 2287776,
        "name:xx": "Dillon Creek"
      }
    },
    {
      "geometry": {
        "type": "Point",
        "coordinates": [
          -89.7167,
          31.2
        ]
      },
      "type": "Feature",
      "properties": {
        "hierarchy": [
          "tgn:2287777",
          "tgn:1000001",
          "tgn:7012149",
          "tgn:2001131",
          "tgn:7007522",
          "tgn:7029392"
        ],
        "placetype": [
          "aat:300008706"
        ],
        "id": 2287777,
        "name:xx": "Dillon Creek"
      }
    },
    {
      "geometry": {
        "type": "Point",
        "coordinates": [
          -94.8167,
          39.9333
        ]
      },
      "type": "Feature",
      "properties": {
        "hierarchy": [
          "tgn:2287778",
          "tgn:2001168",
          "tgn:1000001",
          "tgn:7012149",
          "tgn:7007523",
          "tgn:7029392"
        ],
        "placetype": [
          "aat:300008706"
        ],
        "id": 2287778,
        "name:xx": "Dillon Creek"
      }
    },
    {
      "geometry": {
        "type": "Point",
        "coordinates": [
          -74.1333,
          39.9333
        ]
      },
      "type": "Feature",
      "properties": {
        "hierarchy": [
          "tgn:2287779",
          "tgn:1000001",
          "tgn:1002738",
          "tgn:7012149",
          "tgn:7007565",
          "tgn:7029392"
        ],
        "placetype": [
          "aat:300008706"
        ],
        "id": 2287779,
        "name:xx": "Dillon Creek"
      }
    }
  ]
}
