{
  "type": "FeatureCollection",
  "features": [
    {
      "geometry": {
        "type": "Point",
        "coordinates": [
          -130.0167,
          55.9
        ]
      },
      "type": "Feature",
      "properties": {
        "hierarchy": [
          "tgn:2638580",
          "tgn:7006450",
          "tgn:1000001",
          "tgn:7012149",
          "tgn:2000082",
          "tgn:7029392"
        ],
        "placetype": [
          "aat:300008707"
        ],
        "id": 2638580,
        "name:xx": "Salmon River"
      }
    },
    {
      "geometry": {
        "type": "Point",
        "coordinates": [
          -135.7667,
          58.55
        ]
      },
      "type": "Feature",
      "properties": {
        "hierarchy": [
          "tgn:2638581",
          "tgn:7006450",
          "tgn:1000001",
          "tgn:7012149",
          "tgn:7019760",
          "tgn:7029392"
        ],
        "placetype": [
          "aat:300008707"
        ],
        "id": 2638581,
        "name:xx": "Salmon River"
      }
    },
    {
      "geometry": {
        "type": "Point",
        "coordinates": [
          -153.9,
          62.7333
        ]
      },
      "type": "Feature",
      "properties": {
        "hierarchy": [
          "tgn:2638582",
          "tgn:7006450",
          "tgn:1000001",
          "tgn:7012149",
          "tgn:2000089",
          "tgn:7029392"
        ],
        "placetype": [
          "aat:300008707"
        ],
        "id": 2638582,
        "name:xx": "Salmon River"
      }
    },
    {
      "geometry": {
        "type": "Point",
        "coordinates": [
          -159.3667,
          67.7167
        ]
      },
      "type": "Feature",
      "properties": {
        "hierarchy": [
          "tgn:2638583",
          "tgn:7006450",
          "tgn:1000001",
          "tgn:7012149",
          "tgn:2124014",
          "tgn:7029392"
        ],
        "placetype": [
          "aat:300008707"
        ],
        "id": 2638583,
        "name:xx": "Salmon River"
      }
    },
    {
      "geometry": {
        "type": "Point",
        "coordinates": [
          -123.3167,
          41.25
        ]
      },
      "type": "Feature",
      "properties": {
        "hierarchy": [
          "tgn:2638584",
          "tgn:1000001",
          "tgn:7012149",
          "tgn:7007157",
          "tgn:7029392"
        ],
        "placetype": [
          "aat:300008707"
        ],
        "id": 2638584,
        "name:xx": "Salmon River"
      }
    },
    {
      "geometry": {
        "type": "Point",
        "coordinates": [
          -121.7,
          45.3333
        ]
      },
      "type": "Feature",
      "properties": {
        "hierarchy": [
          "tgn:2638585",
          "tgn:1000001",
          "tgn:1002270",
          "tgn:7012149",
          "tgn:7007708",
          "tgn:7029392"
        ],
        "placetype": [
          "aat:300008707"
        ],
        "id": 2638585,
        "name:xx": "Salmon River"
      }
    },
    {
      "geometry": {
        "type": "Point",
        "coordinates": [
          -124.0333,
          47.5167
        ]
      },
      "type": "Feature",
      "properties": {
        "hierarchy": [
          "tgn:2638586",
          "tgn:1000001",
          "tgn:7012149",
          "tgn:7007920",
          "tgn:7029392"
        ],
        "placetype": [
          "aat:300008707"
        ],
        "id": 2638586,
        "name:xx": "Salmon River"
      }
    },
    {
      "geometry": {
        "type": "Point",
        "coordinates": [
          -121.7,
          45.2333
        ]
      },
      "type": "Feature",
      "properties": {
        "hierarchy": [
          "tgn:2638587",
          "tgn:1000001",
          "tgn:1002270",
          "tgn:7012149",
          "tgn:7007708",
          "tgn:7029392"
        ],
        "placetype": [
          "aat:300008905"
        ],
        "id": 2638587,
        "name:xx": "Salmon River Meadows"
      }
    },
    {
      "geometry": {
        "type": "Point",
        "coordinates": [
          -123.05,
          41.3167
        ]
      },
      "type": "Feature",
      "properties": {
        "hierarchy": [
          "tgn:2638588",
          "tgn:1000001",
          "tgn:7012149",
          "tgn:7007157",
          "tgn:2000189",
          "tgn:7029392"
        ],
        "placetype": [
          "aat:300000390"
        ],
        "id": 2638588,
        "name:xx": "Salmon River Mine"
      }
    },
    {
      "geometry": {
        "type": "Point",
        "coordinates": [
          -114.9167,
          45.4167
        ]
      },
      "type": "Feature",
      "properties": {
        "hierarchy": [
          "tgn:2638589",
          "tgn:1000001",
          "tgn:7012149",
          "tgn:2000476",
          "tgn:7007250",
          "tgn:7029392"
        ],
        "placetype": [
          "aat:300386831"
        ],
        "id": 2638589,
        "name:xx": "Salmon River Mountains"
      }
    }
  ]
}
