{
  "geometry": {
    "type": "Point",
    "coordinates": [
      -82.9667,
      39.1833
    ]
  },
  "type": "Feature",
  "properties": {
    "hierarchy": [
      "tgn:2130882",
      "tgn:1000001",
      "tgn:7012149",
      "tgn:1002470",
      "tgn:7007706",
      "tgn:7029392"
    ],
    "placetype": [
      "aat:300008347",
      "aat:300167671"
    ],
    "id": 2130882,
    "name:xx": "Alma"
  }
}
