{
  "geometry": {
    "type": "Point",
    "coordinates": [
      -105.1333,
      35.7333
    ]
  },
  "type": "Feature",
  "properties": {
    "hierarchy": [
      "tgn:2292024",
      "tgn:1000001",
      "tgn:7012149",
      "tgn:2001453",
      "tgn:7007566",
      "tgn:7029392"
    ],
    "placetype": [
      "aat:300006191"
    ],
    "id": 2292024,
    "name:xx": "Don Santiago Reservoir"
  }
}
