{
  "geometry": {
    "type": "Point",
    "coordinates": [
      -95.0167,
      31.8833
    ]
  },
  "type": "Feature",
  "properties": {
    "hierarchy": [
      "tgn:2699630",
      "tgn:1000001",
      "tgn:7012149",
      "tgn:1002263",
      "tgn:7007826",
      "tgn:7029392"
    ],
    "placetype": [
      "aat:300008347"
    ],
    "id": 2699630,
    "name:xx": "Stryker Creek Junction"
  }
}
