{
  "geometry": {
    "type": "Point",
    "coordinates": [
      71.5167,
      38.55
    ]
  },
  "type": "Feature",
  "properties": {
    "hierarchy": [
      "tgn:1103766",
      "tgn:7011627",
      "tgn:1000004",
      "tgn:7014835",
      "tgn:7029392"
    ],
    "placetype": [
      "aat:300008795"
    ],
    "id": 1103766,
    "name:xx": "Arnavad, Pik"
  }
}
