{
  "geometry": {
    "type": "Point",
    "coordinates": [
      107.6333,
      -3.15
    ]
  },
  "type": "Feature",
  "properties": {
    "hierarchy": [
      "tgn:1078119",
      "tgn:1006479",
      "tgn:1000004",
      "tgn:1001554",
      "tgn:1000116",
      "tgn:7029392"
    ],
    "placetype": [
      "aat:300008347"
    ],
    "id": 1078119,
    "name:xx": "Membalong"
  }
}
