{
  "geometry": {
    "type": "Point",
    "coordinates": [
      -122.1667,
      43.1833
    ]
  },
  "type": "Feature",
  "properties": {
    "hierarchy": [
      "tgn:2479784",
      "tgn:1000001",
      "tgn:7012149",
      "tgn:2001706",
      "tgn:7007708",
      "tgn:7029392"
    ],
    "placetype": [
      "aat:300008706"
    ],
    "id": 2479784,
    "name:xx": "Lake Creek"
  }
}
