{
  "geometry": {
    "type": "Point",
    "coordinates": [
      30.66764,
      28.173537
    ]
  },
  "type": "Feature",
  "properties": {
    "hierarchy": [
      "tgn:7534317",
      "tgn:7001242",
      "tgn:7016833",
      "tgn:1001088",
      "tgn:7029392"
    ],
    "placetype": [
      "aat:300008347"
    ],
    "name:en": "Mahdīyah",
    "id": 7534317
  }
}
