{
  "geometry": {
    "type": "Point",
    "coordinates": [
      -83.95,
      31.9167
    ]
  },
  "type": "Feature",
  "properties": {
    "hierarchy": [
      "tgn:2250021",
      "tgn:1000001",
      "tgn:7012149",
      "tgn:7007248",
      "tgn:7029392"
    ],
    "placetype": [
      "aat:300008699"
    ],
    "id": 2250021,
    "name:xx": "Collins Branch"
  }
}
