{
  "geometry": {
    "type": "Point",
    "coordinates": [
      -104.8667,
      54.9833
    ]
  },
  "type": "Feature",
  "properties": {
    "hierarchy": [
      "tgn:1117501",
      "tgn:7005685",
      "tgn:1000001",
      "tgn:7005805",
      "tgn:7029392"
    ],
    "placetype": [
      "aat:300008680"
    ],
    "id": 1117501,
    "name:xx": "Nipekamew Lake"
  }
}
