{
  "geometry": {
    "type": "Point",
    "coordinates": [
      -117.4167,
      47.65
    ]
  },
  "type": "Feature",
  "properties": {
    "hierarchy": [
      "tgn:2218108",
      "tgn:1000001",
      "tgn:7012149",
      "tgn:2002249",
      "tgn:7007920",
      "tgn:7029392"
    ],
    "placetype": [
      "aat:300008791"
    ],
    "id": 2218108,
    "name:xx": "Canada Island"
  }
}
