{
  "geometry": {
    "type": "Point",
    "coordinates": [
      -111.8667,
      32.5333
    ]
  },
  "type": "Feature",
  "properties": {
    "hierarchy": [
      "tgn:2668617",
      "tgn:1000001",
      "tgn:7006451",
      "tgn:7012149",
      "tgn:7029392"
    ],
    "placetype": [
      "aat:300386831"
    ],
    "id": 2668617,
    "name:xx": "Slate Mountains"
  }
}
