{
  "geometry": {
    "type": "Point",
    "coordinates": [
      -81.5167,
      34.0167
    ]
  },
  "type": "Feature",
  "properties": {
    "hierarchy": [
      "tgn:2095655",
      "tgn:1000001",
      "tgn:7012149",
      "tgn:2001765",
      "tgn:7007712",
      "tgn:7029392"
    ],
    "placetype": [
      "aat:300008347",
      "aat:300387210"
    ],
    "id": 2095655,
    "name:xx": "Delmar"
  }
}
