{
  "type": "FeatureCollection",
  "features": [
    {
      "geometry": {
        "type": "Point",
        "coordinates": [
          31.65,
          30.05
        ]
      },
      "type": "Feature",
      "properties": {
        "hierarchy": [
          "tgn:1001091",
          "tgn:7001242",
          "tgn:7016833",
          "tgn:7029392"
        ],
        "placetype": [
          "aat:300387064",
          "aat:300235093"
        ],
        "name:en": "Cairo",
        "id": 1001091
      }
    },
    {
      "geometry": {
        "type": "Point",
        "coordinates": [
          31.25,
          30.3
        ]
      },
      "type": "Feature",
      "properties": {
        "hierarchy": [
          "tgn:1001092",
          "tgn:7001242",
          "tgn:7016833",
          "tgn:7029392"
        ],
        "placetype": [
          "aat:300387064",
          "aat:300235093"
        ],
        "id": 1001092,
        "name:xx": "Muḩāfaz̧at al Qalyūbīyah"
      }
    },
    {
      "geometry": {
        "type": "Point",
        "coordinates": [
          -84.5,
          10.5
        ]
      },
      "type": "Feature",
      "properties": {
        "hierarchy": [
          "tgn:1001093",
          "tgn:1000001",
          "tgn:7005364",
          "tgn:7029392"
        ],
        "placetype": [
          "aat:300387064",
          "aat:300000774"
        ],
        "id": 1001093,
        "name:xx": "Alajuela"
      }
    },
    {
      "geometry": {
        "type": "Point",
        "coordinates": [
          123.55,
          13.2167
        ]
      },
      "type": "Feature",
      "properties": {
        "hierarchy": [
          "tgn:1001094",
          "tgn:1000004",
          "tgn:1000135",
          "tgn:7029392"
        ],
        "placetype": [
          "aat:300387064",
          "aat:300000774"
        ],
        "id": 1001094,
        "name:xx": "Albay"
      }
    },
    {
      "geometry": {
        "type": "Point",
        "coordinates": [
          33.2,
          19
        ]
      },
      "type": "Feature",
      "properties": {
        "hierarchy": [
          "tgn:1001097",
          "tgn:7001242",
          "tgn:1000201",
          "tgn:7029392"
        ],
        "placetype": [
          "aat:300387064",
          "aat:300387145",
          "aat:300000774",
          "aat:300000776"
        ],
        "name:en": "Nile",
        "id": 1001097
      }
    },
    {
      "geometry": {
        "type": "Point",
        "coordinates": [
          34.1,
          11.15
        ]
      },
      "type": "Feature",
      "properties": {
        "hierarchy": [
          "tgn:1001098",
          "tgn:7001242",
          "tgn:1000201",
          "tgn:7029392"
        ],
        "placetype": [
          "aat:300387064",
          "aat:300387145",
          "aat:300000774",
          "aat:300000776"
        ],
        "name:en": "Blue Nile",
        "id": 1001098
      }
    },
    {
      "geometry": {
        "type": "Point",
        "coordinates": [
          44.3333,
          31.9833
        ]
      },
      "type": "Feature",
      "properties": {
        "hierarchy": [
          "tgn:1001099",
          "tgn:1000004",
          "tgn:1000118",
          "tgn:7029392"
        ],
        "placetype": [
          "aat:300387064",
          "aat:300235093"
        ],
        "id": 1001099,
        "name:xx": "An-Najaf"
      }
    }
  ]
}
