{
  "geometry": {
    "type": "Point",
    "coordinates": [
      2.8333,
      50.4333
    ]
  },
  "type": "Feature",
  "properties": {
    "hierarchy": [
      "tgn:7009278",
      "tgn:1000003",
      "tgn:7001097",
      "tgn:1000070",
      "tgn:7029392"
    ],
    "placetype": [
      "aat:300008347",
      "aat:300008389",
      "aat:300387305",
      "aat:300387302",
      "aat:300387286"
    ],
    "id": 7009278,
    "name:xx": "Lens"
  }
}
