{
  "type": "FeatureCollection",
  "features": [
    {
      "geometry": {
        "type": "Point",
        "coordinates": [
          21,
          55.5
        ]
      },
      "type": "Feature",
      "properties": {
        "hierarchy": [
          "tgn:4007870",
          "tgn:1000003",
          "tgn:7594052",
          "tgn:7006542",
          "tgn:7029392"
        ],
        "placetype": [
          "aat:300008347",
          "aat:300000547",
          "aat:300008375"
        ],
        "id": 4007870,
        "name:xx": "Neringa"
      }
    },
    {
      "geometry": {
        "type": "Point",
        "coordinates": [
          8.483333,
          54.7
        ]
      },
      "type": "Feature",
      "properties": {
        "hierarchy": [
          "tgn:4007873",
          "tgn:1000003",
          "tgn:7003688",
          "tgn:7000084",
          "tgn:7029392"
        ],
        "placetype": [
          "aat:300008347"
        ],
        "id": 4007873,
        "name:xx": "Nieblum"
      }
    },
    {
      "geometry": {
        "type": "Point",
        "coordinates": [
          20.0833,
          52.0667
        ]
      },
      "type": "Feature",
      "properties": {
        "hierarchy": [
          "tgn:4007874",
          "tgn:1000003",
          "tgn:7024121",
          "tgn:7006366",
          "tgn:7029392"
        ],
        "placetype": [
          "aat:300008347"
        ],
        "id": 4007874,
        "name:xx": "Nieborów"
      }
    },
    {
      "geometry": {
        "type": "Point",
        "coordinates": [
          10.083333,
          48.9
        ]
      },
      "type": "Feature",
      "properties": {
        "hierarchy": [
          "tgn:4007876",
          "tgn:7003692",
          "tgn:1000003",
          "tgn:7000084",
          "tgn:7029392"
        ],
        "placetype": [
          "aat:300008347"
        ],
        "id": 4007876,
        "name:xx": "Niederalfingen"
      }
    },
    {
      "geometry": {
        "type": "Point",
        "coordinates": [
          7.633333,
          50.383333
        ]
      },
      "type": "Feature",
      "properties": {
        "hierarchy": [
          "tgn:4007878",
          "tgn:1000003",
          "tgn:7003682",
          "tgn:7004448",
          "tgn:7000084",
          "tgn:7029392"
        ],
        "placetype": [
          "aat:300000745",
          "aat:300000874"
        ],
        "id": 4007878,
        "name:xx": "Niederberg"
      }
    }
  ]
}
