{
  "geometry": {
    "type": "Point",
    "coordinates": [
      -82.2833,
      35.5333
    ]
  },
  "type": "Feature",
  "properties": {
    "hierarchy": [
      "tgn:2633631",
      "tgn:1000001",
      "tgn:2001473",
      "tgn:7012149",
      "tgn:7007709",
      "tgn:7029392"
    ],
    "placetype": [
      "aat:300008699"
    ],
    "id": 2633631,
    "name:xx": "Rush Branch"
  }
}
