{
  "geometry": {
    "type": "Point",
    "coordinates": [
      -73.85,
      45.1833
    ]
  },
  "type": "Feature",
  "properties": {
    "hierarchy": [
      "tgn:1015416",
      "tgn:7005685",
      "tgn:1000001",
      "tgn:7005804",
      "tgn:7029392"
    ],
    "placetype": [
      "aat:300008347"
    ],
    "id": 1015416,
    "name:xx": "Howick"
  }
}
