{
  "geometry": {
    "type": "Point",
    "coordinates": [
      15.3833,
      51.1833
    ]
  },
  "type": "Feature",
  "properties": {
    "hierarchy": [
      "tgn:1049297",
      "tgn:7024123",
      "tgn:1000003",
      "tgn:7006366",
      "tgn:7029392"
    ],
    "placetype": [
      "aat:300008347"
    ],
    "id": 1049297,
    "name:xx": "Nowogrodziec"
  }
}
