{
  "geometry": {
    "type": "Point",
    "coordinates": [
      14.45,
      51.85
    ]
  },
  "type": "Feature",
  "properties": {
    "hierarchy": [
      "tgn:7154979",
      "tgn:7000096",
      "tgn:1000003",
      "tgn:7000084",
      "tgn:7029392"
    ],
    "placetype": [
      "aat:300004792"
    ],
    "id": 7154979,
    "name:xx": "Försterei Kleine Heide"
  }
}
