{
  "geometry": {
    "type": "Point",
    "coordinates": [
      -87.05,
      39.9333
    ]
  },
  "type": "Feature",
  "properties": {
    "hierarchy": [
      "tgn:2282313",
      "tgn:1000001",
      "tgn:7012149",
      "tgn:2000547",
      "tgn:7007252",
      "tgn:7029392"
    ],
    "placetype": [
      "aat:300008347"
    ],
    "id": 2282313,
    "name:xx": "Deer Mill"
  }
}
