{
  "geometry": {
    "type": "Point",
    "coordinates": [
      87.962778,
      21.893889
    ]
  },
  "type": "Feature",
  "properties": {
    "hierarchy": [
      "tgn:7585565",
      "tgn:1000004",
      "tgn:7000198",
      "tgn:1001977",
      "tgn:7029392"
    ],
    "placetype": [
      "aat:300008347"
    ],
    "name:en": "Tālpāti",
    "id": 7585565
  }
}
