{
  "type": "FeatureCollection",
  "features": [
    {
      "geometry": {
        "type": "Point",
        "coordinates": [
          -94.0333,
          31.8167
        ]
      },
      "type": "Feature",
      "properties": {
        "hierarchy": [
          "tgn:2103060",
          "tgn:1000001",
          "tgn:7012149",
          "tgn:2002073",
          "tgn:7007826",
          "tgn:7029392"
        ],
        "placetype": [
          "aat:300008347",
          "aat:300387210"
        ],
        "id": 2103060,
        "name:xx": "Campti"
      }
    },
    {
      "geometry": {
        "type": "Point",
        "coordinates": [
          -99.1,
          29.8833
        ]
      },
      "type": "Feature",
      "properties": {
        "hierarchy": [
          "tgn:2103062",
          "tgn:1000001",
          "tgn:7012149",
          "tgn:2002018",
          "tgn:7007826",
          "tgn:7029392"
        ],
        "placetype": [
          "aat:300008347",
          "aat:300387210"
        ],
        "id": 2103062,
        "name:xx": "Camp Verde"
      }
    },
    {
      "geometry": {
        "type": "Point",
        "coordinates": [
          -100,
          29.6667
        ]
      },
      "type": "Feature",
      "properties": {
        "hierarchy": [
          "tgn:2103063",
          "tgn:1000001",
          "tgn:7012149",
          "tgn:2002060",
          "tgn:7007826",
          "tgn:7029392"
        ],
        "placetype": [
          "aat:300008347"
        ],
        "id": 2103063,
        "name:xx": "Camp Wood"
      }
    },
    {
      "geometry": {
        "type": "Point",
        "coordinates": [
          -96,
          32.5667
        ]
      },
      "type": "Feature",
      "properties": {
        "hierarchy": [
          "tgn:2103065",
          "tgn:1000001",
          "tgn:7012149",
          "tgn:1002969",
          "tgn:7007826",
          "tgn:7029392"
        ],
        "placetype": [
          "aat:300008347",
          "aat:300387210"
        ],
        "id": 2103065,
        "name:xx": "Cana"
      }
    },
    {
      "geometry": {
        "type": "Point",
        "coordinates": [
          -100.3667,
          35.9
        ]
      },
      "type": "Feature",
      "properties": {
        "hierarchy": [
          "tgn:2103067",
          "tgn:1000001",
          "tgn:7012149",
          "tgn:2002001",
          "tgn:7007826",
          "tgn:7029392"
        ],
        "placetype": [
          "aat:300008347"
        ],
        "id": 2103067,
        "name:xx": "Canadian"
      }
    },
    {
      "geometry": {
        "type": "Point",
        "coordinates": [
          -104.6833,
          30.1333
        ]
      },
      "type": "Feature",
      "properties": {
        "hierarchy": [
          "tgn:2103069",
          "tgn:1000001",
          "tgn:7012149",
          "tgn:2002057",
          "tgn:7007826",
          "tgn:7029392"
        ],
        "placetype": [
          "aat:300008347"
        ],
        "id": 2103069,
        "name:xx": "Candelaria"
      }
    }
  ]
}
