{
  "geometry": {
    "type": "Point",
    "coordinates": [
      -118.45,
      48.65
    ]
  },
  "type": "Feature",
  "properties": {
    "hierarchy": [
      "tgn:2750500",
      "tgn:1000001",
      "tgn:2002243",
      "tgn:7012149",
      "tgn:7007920",
      "tgn:7029392"
    ],
    "placetype": [
      "aat:300008798"
    ],
    "id": 2750500,
    "name:xx": "Wapaloosie Mountain"
  }
}
