{
  "geometry": {
    "type": "Point",
    "coordinates": [
      33.261944,
      29.8275
    ]
  },
  "type": "Feature",
  "properties": {
    "hierarchy": [
      "tgn:7543671",
      "tgn:7001242",
      "tgn:7016833",
      "tgn:7001336",
      "tgn:7029392"
    ],
    "placetype": [
      "aat:300000626"
    ],
    "id": 7543671,
    "name:xx": "Darb ash Sh'wī"
  }
}
