{
  "geometry": {
    "type": "Point",
    "coordinates": [
      -85.0667,
      36.7833
    ]
  },
  "type": "Feature",
  "properties": {
    "hierarchy": [
      "tgn:2563055",
      "tgn:1000001",
      "tgn:2000783",
      "tgn:7012149",
      "tgn:7007255",
      "tgn:7029392"
    ],
    "placetype": [
      "aat:300008699"
    ],
    "id": 2563055,
    "name:xx": "Owens Branch"
  }
}
