{
  "type": "FeatureCollection",
  "features": [
    {
      "geometry": {
        "type": "Point",
        "coordinates": [
          12,
          46.433333
        ]
      },
      "type": "Feature",
      "properties": {
        "hierarchy": [
          "tgn:4002212",
          "tgn:1003510",
          "tgn:1000003",
          "tgn:7003120",
          "tgn:1000080",
          "tgn:7029392"
        ],
        "placetype": [
          "aat:300008347"
        ],
        "id": 4002212,
        "name:xx": "Caprile"
      }
    },
    {
      "geometry": {
        "type": "Point",
        "coordinates": [
          -69.0667,
          -15.8167
        ]
      },
      "type": "Feature",
      "properties": {
        "hierarchy": [
          "tgn:4002218",
          "tgn:1000662",
          "tgn:1000046",
          "tgn:1000002",
          "tgn:7029392"
        ],
        "placetype": [
          "aat:300008347",
          "aat:300008375"
        ],
        "id": 4002218,
        "name:xx": "Carabuco"
      }
    }
  ]
}
