{
  "geometry": {
    "type": "Point",
    "coordinates": [
      -82.45,
      36.0167
    ]
  },
  "type": "Feature",
  "properties": {
    "hierarchy": [
      "tgn:2170284",
      "tgn:1000001",
      "tgn:7012149",
      "tgn:7029392"
    ],
    "placetype": [
      "aat:300266640"
    ],
    "id": 2170284,
    "name:xx": "Big Ridge"
  }
}
