{
  "geometry": {
    "type": "Point",
    "coordinates": [
      -76.35,
      39.9167
    ]
  },
  "type": "Feature",
  "properties": {
    "hierarchy": [
      "tgn:2367974",
      "tgn:1000001",
      "tgn:7012149",
      "tgn:7013867",
      "tgn:7007710",
      "tgn:7029392"
    ],
    "placetype": [
      "aat:300008761"
    ],
    "id": 2367974,
    "name:xx": "Grubb Hollow"
  }
}
