{
  "geometry": {
    "type": "Point",
    "coordinates": [
      151.45,
      7.35
    ]
  },
  "type": "Feature",
  "properties": {
    "hierarchy": [
      "tgn:1114231",
      "tgn:7018508",
      "tgn:1010363",
      "tgn:1000220",
      "tgn:1000006",
      "tgn:7029392"
    ],
    "placetype": [
      "aat:300008713"
    ],
    "id": 1114231,
    "name:xx": "Piaanu Pass"
  }
}
