{
  "geometry": {
    "type": "Point",
    "coordinates": [
      -85.5833,
      34.5833
    ]
  },
  "type": "Feature",
  "properties": {
    "hierarchy": [
      "tgn:2307027",
      "tgn:1000001",
      "tgn:7012149",
      "tgn:7029392"
    ],
    "placetype": [
      "aat:300008706"
    ],
    "id": 2307027,
    "name:xx": "East Fork Lookout Creek"
  }
}
