{
  "geometry": {
    "type": "Point",
    "coordinates": [
      31.39317,
      30.137898
    ]
  },
  "type": "Feature",
  "properties": {
    "hierarchy": [
      "tgn:7531476",
      "tgn:7001242",
      "tgn:7016833",
      "tgn:1001091",
      "tgn:7029392"
    ],
    "placetype": [
      "aat:300004792"
    ],
    "id": 7531476,
    "name:xx": "Mişr li Khidmāt al Bī'ah"
  }
}
