{
  "geometry": {
    "type": "Point",
    "coordinates": [
      -121.05,
      40.05
    ]
  },
  "type": "Feature",
  "properties": {
    "hierarchy": [
      "tgn:2758107",
      "tgn:1000001",
      "tgn:7012149",
      "tgn:7007157",
      "tgn:2000187",
      "tgn:7029392"
    ],
    "placetype": [
      "aat:300008706"
    ],
    "id": 2758107,
    "name:xx": "West Branch Soda Creek"
  }
}
