{
  "geometry": {
    "type": "Point",
    "coordinates": [
      22.8667,
      53.3333
    ]
  },
  "type": "Feature",
  "properties": {
    "hierarchy": [
      "tgn:1049144",
      "tgn:1000003",
      "tgn:7024117",
      "tgn:7006366",
      "tgn:7029392"
    ],
    "placetype": [
      "aat:300008347"
    ],
    "id": 1049144,
    "name:xx": "Knyszyn"
  }
}
