{
  "geometry": {
    "type": "Point",
    "coordinates": [
      -82.3667,
      34.0667
    ]
  },
  "type": "Feature",
  "properties": {
    "hierarchy": [
      "tgn:2185762",
      "tgn:1000001",
      "tgn:7012149",
      "tgn:7007712",
      "tgn:7029392"
    ],
    "placetype": [
      "aat:300008699"
    ],
    "id": 2185762,
    "name:xx": "Bold Branch"
  }
}
