{
  "geometry": {
    "type": "Point",
    "coordinates": [
      -117.3167,
      46.65
    ]
  },
  "type": "Feature",
  "properties": {
    "hierarchy": [
      "tgn:2477848",
      "tgn:1000001",
      "tgn:7012149",
      "tgn:2002252",
      "tgn:7007920",
      "tgn:7029392"
    ],
    "placetype": [
      "aat:300008761"
    ],
    "id": 2477848,
    "name:xx": "MacMurry Canyon"
  }
}
