{
  "geometry": {
    "type": "Point",
    "coordinates": [
      -83.1167,
      36.3333
    ]
  },
  "type": "Feature",
  "properties": {
    "hierarchy": [
      "tgn:2538340",
      "tgn:1000001",
      "tgn:7012149",
      "tgn:2001873",
      "tgn:7007825",
      "tgn:7029392"
    ],
    "placetype": [
      "aat:300266640"
    ],
    "id": 2538340,
    "name:xx": "Nenny Ridge"
  }
}
