{
  "geometry": {
    "type": "Point",
    "coordinates": [
      -80.6833,
      40.0167
    ]
  },
  "type": "Feature",
  "properties": {
    "hierarchy": [
      "tgn:2275881",
      "tgn:1000001",
      "tgn:7012149",
      "tgn:7013961",
      "tgn:7029392"
    ],
    "placetype": [
      "aat:300008761"
    ],
    "id": 2275881,
    "name:xx": "Dark Hollow"
  }
}
