{
  "geometry": {
    "type": "Point",
    "coordinates": [
      -79.0833,
      36.0333
    ]
  },
  "type": "Feature",
  "properties": {
    "hierarchy": [
      "tgn:2771609",
      "tgn:1000001",
      "tgn:7012149",
      "tgn:2001525",
      "tgn:7007709",
      "tgn:7029392"
    ],
    "placetype": [
      "aat:300008347"
    ],
    "id": 2771609,
    "name:xx": "Wildwood"
  }
}
