{
  "geometry": {
    "type": "Point",
    "coordinates": [
      95.6833,
      23.9167
    ]
  },
  "type": "Feature",
  "properties": {
    "hierarchy": [
      "tgn:7002192",
      "tgn:1000004",
      "tgn:1002109",
      "tgn:1000108",
      "tgn:7029392"
    ],
    "placetype": [
      "aat:300008347"
    ],
    "id": 7002192,
    "name:xx": "Wuntho"
  }
}
