{
  "geometry": {
    "type": "Point",
    "coordinates": [
      120.6798,
      24.1732
    ]
  },
  "type": "Feature",
  "properties": {
    "hierarchy": [
      "tgn:7497620",
      "tgn:1000004",
      "tgn:7001009",
      "tgn:1000141",
      "tgn:7029392"
    ],
    "placetype": [
      "aat:300007836"
    ],
    "id": 7497620,
    "name:xx": "Wenxinmei Qiao"
  }
}
