{
  "geometry": {
    "type": "Point",
    "coordinates": [
      -82.85,
      41.2667
    ]
  },
  "type": "Feature",
  "properties": {
    "hierarchy": [
      "tgn:2080897",
      "tgn:1000001",
      "tgn:7012149",
      "tgn:1002865",
      "tgn:7007706",
      "tgn:7029392"
    ],
    "placetype": [
      "aat:300008347"
    ],
    "id": 2080897,
    "name:xx": "Mount Pleasant"
  }
}
