{
  "geometry": {
    "type": "Point",
    "coordinates": [
      26.1667,
      -20.1833
    ]
  },
  "type": "Feature",
  "properties": {
    "hierarchy": [
      "tgn:1088089",
      "tgn:1000824",
      "tgn:7001242",
      "tgn:1000150",
      "tgn:7029392"
    ],
    "placetype": [
      "aat:300008347"
    ],
    "id": 1088089,
    "name:xx": "Nata"
  }
}
