{
  "type": "FeatureCollection",
  "features": [
    {
      "geometry": {
        "type": "Point",
        "coordinates": [
          -61.1833,
          14.7333
        ]
      },
      "type": "Feature",
      "properties": {
        "hierarchy": [
          "tgn:1120741",
          "tgn:7015035",
          "tgn:1000001",
          "tgn:7005870",
          "tgn:7029392"
        ],
        "placetype": [
          "aat:300386968"
        ],
        "id": 1120741,
        "name:xx": "Saint-Pierre, Rade de"
      }
    },
    {
      "geometry": {
        "type": "Point",
        "coordinates": [
          -118.4,
          33.7833
        ]
      },
      "type": "Feature",
      "properties": {
        "hierarchy": [
          "tgn:1120744",
          "tgn:1000001",
          "tgn:7012149",
          "tgn:7007157",
          "tgn:1002608",
          "tgn:7029392"
        ],
        "placetype": [
          "aat:300132317"
        ],
        "id": 1120744,
        "name:xx": "Bluff Cove"
      }
    },
    {
      "geometry": {
        "type": "Point",
        "coordinates": [
          -73.3333,
          41.1
        ]
      },
      "type": "Feature",
      "properties": {
        "hierarchy": [
          "tgn:1120745",
          "tgn:1002366",
          "tgn:1000001",
          "tgn:7012149",
          "tgn:7007159",
          "tgn:7029392"
        ],
        "placetype": [
          "aat:300132317"
        ],
        "id": 1120745,
        "name:xx": "Compo Cove"
      }
    },
    {
      "geometry": {
        "type": "Point",
        "coordinates": [
          -82.5,
          23.0833
        ]
      },
      "type": "Feature",
      "properties": {
        "hierarchy": [
          "tgn:1120747",
          "tgn:7006453",
          "tgn:1001206",
          "tgn:1000001",
          "tgn:7004624",
          "tgn:7029392"
        ],
        "placetype": [
          "aat:300132317"
        ],
        "id": 1120747,
        "name:xx": "Grande, Laguna"
      }
    },
    {
      "geometry": {
        "type": "Point",
        "coordinates": [
          -73.2333,
          40.7
        ]
      },
      "type": "Feature",
      "properties": {
        "hierarchy": [
          "tgn:1120748",
          "tgn:1000001",
          "tgn:7012149",
          "tgn:1002924",
          "tgn:7007568",
          "tgn:7029392"
        ],
        "placetype": [
          "aat:300132317"
        ],
        "id": 1120748,
        "name:xx": "Great Cove"
      }
    },
    {
      "geometry": {
        "type": "Point",
        "coordinates": [
          -73.5667,
          41.0167
        ]
      },
      "type": "Feature",
      "properties": {
        "hierarchy": [
          "tgn:1120749",
          "tgn:1002366",
          "tgn:1000001",
          "tgn:7012149",
          "tgn:7007159",
          "tgn:7029392"
        ],
        "placetype": [
          "aat:300132317"
        ],
        "id": 1120749,
        "name:xx": "Greenwich Cove"
      }
    }
  ]
}
