{
  "geometry": {
    "type": "Point",
    "coordinates": [
      -70.8333,
      41.5833
    ]
  },
  "type": "Feature",
  "properties": {
    "hierarchy": [
      "tgn:2467700",
      "tgn:1002201",
      "tgn:1000001",
      "tgn:7012149",
      "tgn:7007517",
      "tgn:7029392"
    ],
    "placetype": [
      "aat:300008791"
    ],
    "id": 2467700,
    "name:xx": "Long Island"
  }
}
