{
  "type": "FeatureCollection",
  "features": [
    {
      "geometry": {
        "type": "Point",
        "coordinates": [
          -8.816667,
          43.033333
        ]
      },
      "type": "Feature",
      "properties": {
        "hierarchy": [
          "tgn:4010051",
          "tgn:7002824",
          "tgn:1000003",
          "tgn:7002786",
          "tgn:1000095",
          "tgn:7029392"
        ],
        "placetype": [
          "aat:300008347"
        ],
        "id": 4010051,
        "name:xx": "Santa Comba"
      }
    },
    {
      "geometry": {
        "type": "Point",
        "coordinates": [
          12.119167,
          45.641944
        ]
      },
      "type": "Feature",
      "properties": {
        "hierarchy": [
          "tgn:4010053",
          "tgn:1003478",
          "tgn:1000003",
          "tgn:7003120",
          "tgn:1000080",
          "tgn:7029392"
        ],
        "placetype": [
          "aat:300008347"
        ],
        "id": 4010053,
        "name:xx": "Santa Cristina"
      }
    },
    {
      "geometry": {
        "type": "Point",
        "coordinates": [
          11.716667,
          45.65
        ]
      },
      "type": "Feature",
      "properties": {
        "hierarchy": [
          "tgn:4010054",
          "tgn:7003008",
          "tgn:1000003",
          "tgn:7002997",
          "tgn:1000080",
          "tgn:7029392"
        ],
        "placetype": [
          "aat:300008347"
        ],
        "id": 4010054,
        "name:xx": "Santa Croce Bigolina"
      }
    },
    {
      "geometry": {
        "type": "Point",
        "coordinates": [
          -4.233333,
          40.116667
        ]
      },
      "type": "Feature",
      "properties": {
        "hierarchy": [
          "tgn:4010059",
          "tgn:7002847",
          "tgn:1001647",
          "tgn:1000003",
          "tgn:1000095",
          "tgn:7029392"
        ],
        "placetype": [
          "aat:300008347"
        ],
        "id": 4010059,
        "name:xx": "Santa Cruz del Retamar"
      }
    }
  ]
}
