{
  "type": "FeatureCollection",
  "features": [
    {
      "geometry": {
        "type": "Point",
        "coordinates": [
          -111.3667,
          32.6
        ]
      },
      "type": "Feature",
      "properties": {
        "hierarchy": [
          "tgn:2775190",
          "tgn:1000001",
          "tgn:7006451",
          "tgn:7012149",
          "tgn:2000101",
          "tgn:7029392"
        ],
        "placetype": [
          "aat:300006191"
        ],
        "id": 2775190,
        "name:xx": "Wilmonts Pond"
      }
    },
    {
      "geometry": {
        "type": "Point",
        "coordinates": [
          -88.8,
          43.8833
        ]
      },
      "type": "Feature",
      "properties": {
        "hierarchy": [
          "tgn:2775191",
          "tgn:1000001",
          "tgn:7020939",
          "tgn:7012149",
          "tgn:7007922",
          "tgn:7029392"
        ],
        "placetype": [
          "aat:300008347"
        ],
        "id": 2775191,
        "name:xx": "Wilmoore Heights"
      }
    },
    {
      "geometry": {
        "type": "Point",
        "coordinates": [
          -106.6167,
          39.65
        ]
      },
      "type": "Feature",
      "properties": {
        "hierarchy": [
          "tgn:2775192",
          "tgn:1000001",
          "tgn:7012149",
          "tgn:2000210",
          "tgn:7007158",
          "tgn:7029392"
        ],
        "placetype": [
          "aat:300008347"
        ],
        "id": 2775192,
        "name:xx": "Wilmor"
      }
    },
    {
      "geometry": {
        "type": "Point",
        "coordinates": [
          -106.6167,
          39.65
        ]
      },
      "type": "Feature",
      "properties": {
        "hierarchy": [
          "tgn:2775193",
          "tgn:1000001",
          "tgn:7012149",
          "tgn:2000210",
          "tgn:7007158",
          "tgn:7029392"
        ],
        "placetype": [
          "aat:300008680"
        ],
        "id": 2775193,
        "name:xx": "Wilmor Lake"
      }
    },
    {
      "geometry": {
        "type": "Point",
        "coordinates": [
          -90.3833,
          37.2667
        ]
      },
      "type": "Feature",
      "properties": {
        "hierarchy": [
          "tgn:2775194",
          "tgn:1000001",
          "tgn:7012149",
          "tgn:2001255",
          "tgn:7007523",
          "tgn:7029392"
        ],
        "placetype": [
          "aat:300008706"
        ],
        "id": 2775194,
        "name:xx": "Wilmore Creek"
      }
    },
    {
      "geometry": {
        "type": "Point",
        "coordinates": [
          -84.6167,
          40.9167
        ]
      },
      "type": "Feature",
      "properties": {
        "hierarchy": [
          "tgn:2775195",
          "tgn:1000001",
          "tgn:7012149",
          "tgn:1002968",
          "tgn:7007706",
          "tgn:7029392"
        ],
        "placetype": [
          "aat:300006075"
        ],
        "id": 2775195,
        "name:xx": "Wilmore Ditch"
      }
    },
    {
      "geometry": {
        "type": "Point",
        "coordinates": [
          -85.4667,
          32.55
        ]
      },
      "type": "Feature",
      "properties": {
        "hierarchy": [
          "tgn:2775198",
          "tgn:7002659",
          "tgn:1000001",
          "tgn:7012149",
          "tgn:2000040",
          "tgn:7029392"
        ],
        "placetype": [
          "aat:300006191"
        ],
        "id": 2775198,
        "name:xx": "Wilmore, Lake"
      }
    },
    {
      "geometry": {
        "type": "Point",
        "coordinates": [
          -90.8833,
          33.3
        ]
      },
      "type": "Feature",
      "properties": {
        "hierarchy": [
          "tgn:2775199",
          "tgn:1000001",
          "tgn:7012149",
          "tgn:2001161",
          "tgn:7007522",
          "tgn:7029392"
        ],
        "placetype": [
          "aat:300008347"
        ],
        "id": 2775199,
        "name:xx": "Wilmot"
      }
    }
  ]
}
