{
  "geometry": {
    "type": "Point",
    "coordinates": [
      -66.8333,
      -36.2833
    ]
  },
  "type": "Feature",
  "properties": {
    "hierarchy": [
      "tgn:1121482",
      "tgn:7006477",
      "tgn:1000002",
      "tgn:7029392"
    ],
    "placetype": [
      "aat:300008707"
    ],
    "id": 1121482,
    "name:xx": "Atuel, Río"
  }
}
