{
  "geometry": {
    "type": "Point",
    "coordinates": [
      29.316667,
      30.816667
    ]
  },
  "type": "Feature",
  "properties": {
    "hierarchy": [
      "tgn:7522608",
      "tgn:7001242",
      "tgn:7016833",
      "tgn:1001418",
      "tgn:7029392"
    ],
    "placetype": [
      "aat:300007783"
    ],
    "name:en": "Maḩaţţat ar Ru'aysāt",
    "id": 7522608
  }
}
