{
  "geometry": {
    "type": "Point",
    "coordinates": [
      -74.8833,
      42.9667
    ]
  },
  "type": "Feature",
  "properties": {
    "hierarchy": [
      "tgn:2551070",
      "tgn:1000001",
      "tgn:7012149",
      "tgn:1002472",
      "tgn:7007568",
      "tgn:7029392"
    ],
    "placetype": [
      "aat:300008706"
    ],
    "id": 2551070,
    "name:xx": "Nowadaga Creek"
  }
}
