{
  "type": "FeatureCollection",
  "features": [
    {
      "geometry": {
        "type": "Point",
        "coordinates": [
          5.916667,
          51.166667
        ]
      },
      "type": "Feature",
      "properties": {
        "hierarchy": [
          "tgn:7273880",
          "tgn:1000003",
          "tgn:7003622",
          "tgn:7016845",
          "tgn:7029392"
        ],
        "placetype": [
          "aat:300008347"
        ],
        "name:nl": "Weerd",
        "id": 7273880
      }
    },
    {
      "geometry": {
        "type": "Point",
        "coordinates": [
          6.433333,
          52.033333
        ]
      },
      "type": "Feature",
      "properties": {
        "hierarchy": [
          "tgn:7273881",
          "tgn:7003619",
          "tgn:1000003",
          "tgn:7016845",
          "tgn:7029392"
        ],
        "placetype": [
          "aat:300007836"
        ],
        "name:nl": "Weenksbrug",
        "id": 7273881
      }
    },
    {
      "geometry": {
        "type": "Point",
        "coordinates": [
          7.1,
          52.983333
        ]
      },
      "type": "Feature",
      "properties": {
        "hierarchy": [
          "tgn:7273882",
          "tgn:1000003",
          "tgn:7003613",
          "tgn:7016845",
          "tgn:7029392"
        ],
        "placetype": [
          "aat:300387200"
        ],
        "name:nl": "Weenderveld",
        "id": 7273882
      }
    },
    {
      "geometry": {
        "type": "Point",
        "coordinates": [
          7.1,
          52.966667
        ]
      },
      "type": "Feature",
      "properties": {
        "hierarchy": [
          "tgn:7273883",
          "tgn:1000003",
          "tgn:7003613",
          "tgn:7016845",
          "tgn:7029392"
        ],
        "placetype": [
          "aat:300006075"
        ],
        "name:nl": "Weende-Jipsinghuizenkanaal",
        "id": 7273883
      }
    },
    {
      "geometry": {
        "type": "Point",
        "coordinates": [
          7.133333,
          53
        ]
      },
      "type": "Feature",
      "properties": {
        "hierarchy": [
          "tgn:7273884",
          "tgn:1000003",
          "tgn:7003613",
          "tgn:7016845",
          "tgn:7029392"
        ],
        "placetype": [
          "aat:300008347"
        ],
        "name:nl": "Weende",
        "id": 7273884
      }
    },
    {
      "geometry": {
        "type": "Point",
        "coordinates": [
          4.383333,
          51.633333
        ]
      },
      "type": "Feature",
      "properties": {
        "hierarchy": [
          "tgn:7273885",
          "tgn:1000003",
          "tgn:7003624",
          "tgn:7016845",
          "tgn:7029392"
        ],
        "placetype": [
          "aat:300006075"
        ],
        "name:nl": "Weelkreek",
        "id": 7273885
      }
    },
    {
      "geometry": {
        "type": "Point",
        "coordinates": [
          6.716667,
          53.1
        ]
      },
      "type": "Feature",
      "properties": {
        "hierarchy": [
          "tgn:7273886",
          "tgn:7003614",
          "tgn:1000003",
          "tgn:7016845",
          "tgn:7029392"
        ],
        "placetype": [
          "aat:300387200"
        ],
        "name:nl": "Weelings",
        "id": 7273886
      }
    },
    {
      "geometry": {
        "type": "Point",
        "coordinates": [
          5.633333,
          51.633333
        ]
      },
      "type": "Feature",
      "properties": {
        "hierarchy": [
          "tgn:7273887",
          "tgn:1000003",
          "tgn:7003624",
          "tgn:7016845",
          "tgn:7029392"
        ],
        "placetype": [
          "aat:300008347"
        ],
        "name:nl": "Weeg",
        "id": 7273887
      }
    },
    {
      "geometry": {
        "type": "Point",
        "coordinates": [
          5.3,
          51.316667
        ]
      },
      "type": "Feature",
      "properties": {
        "hierarchy": [
          "tgn:7273888",
          "tgn:1000003",
          "tgn:7003624",
          "tgn:7016845",
          "tgn:7029392"
        ],
        "placetype": [
          "aat:300008347"
        ],
        "name:nl": "Weebosch",
        "id": 7273888
      }
    },
    {
      "geometry": {
        "type": "Point",
        "coordinates": [
          6.1,
          53.233333
        ]
      },
      "type": "Feature",
      "properties": {
        "hierarchy": [
          "tgn:7273889",
          "tgn:7003616",
          "tgn:1000003",
          "tgn:7016845",
          "tgn:7029392"
        ],
        "placetype": [
          "aat:300008347"
        ],
        "name:nl": "Wedzeburen",
        "id": 7273889
      }
    }
  ]
}
