{
  "geometry": {
    "type": "Point",
    "coordinates": [
      -77.4833,
      42.6167
    ]
  },
  "type": "Feature",
  "properties": {
    "hierarchy": [
      "tgn:2311861",
      "tgn:1000001",
      "tgn:7012149",
      "tgn:1002747",
      "tgn:7007568",
      "tgn:7029392"
    ],
    "placetype": [
      "aat:300008706"
    ],
    "id": 2311861,
    "name:xx": "Eelpot Creek"
  }
}
