{
  "geometry": {
    "type": "Point",
    "coordinates": [
      -116.8333,
      43.1167
    ]
  },
  "type": "Feature",
  "properties": {
    "hierarchy": [
      "tgn:2265336",
      "tgn:1000001",
      "tgn:7012149",
      "tgn:2000488",
      "tgn:7007250",
      "tgn:7029392"
    ],
    "placetype": [
      "aat:300008706"
    ],
    "id": 2265336,
    "name:xx": "Crane Creek"
  }
}
