{
  "geometry": {
    "type": "Point",
    "coordinates": [
      -83.9833,
      36.0833
    ]
  },
  "type": "Feature",
  "properties": {
    "hierarchy": [
      "tgn:2491735",
      "tgn:1000001",
      "tgn:7012149",
      "tgn:2001883",
      "tgn:7007825",
      "tgn:7029392"
    ],
    "placetype": [
      "aat:300008347"
    ],
    "id": 2491735,
    "name:xx": "Mapleview"
  }
}
