{
  "geometry": {
    "type": "Point",
    "coordinates": [
      -93.8833,
      39.7667
    ]
  },
  "type": "Feature",
  "properties": {
    "hierarchy": [
      "tgn:2466585",
      "tgn:1000001",
      "tgn:7012149",
      "tgn:7007523",
      "tgn:7029392"
    ],
    "placetype": [
      "aat:300008699"
    ],
    "id": 2466585,
    "name:xx": "Long Branch"
  }
}
