{
  "type": "FeatureCollection",
  "features": [
    {
      "geometry": {
        "type": "Point",
        "coordinates": [
          -93.0333,
          36.1667
        ]
      },
      "type": "Feature",
      "properties": {
        "hierarchy": [
          "tgn:2527340",
          "tgn:1000001",
          "tgn:7016172",
          "tgn:2000109",
          "tgn:7012149",
          "tgn:7029392"
        ],
        "placetype": [
          "aat:300008347"
        ],
        "id": 2527340,
        "name:xx": "Mount Pleasant"
      }
    },
    {
      "geometry": {
        "type": "Point",
        "coordinates": [
          -84.3833,
          30.1333
        ]
      },
      "type": "Feature",
      "properties": {
        "hierarchy": [
          "tgn:2527341",
          "tgn:1000001",
          "tgn:7012149",
          "tgn:2000289",
          "tgn:7007240",
          "tgn:7029392"
        ],
        "placetype": [
          "aat:300008347"
        ],
        "id": 2527341,
        "name:xx": "Mount Pleasant"
      }
    },
    {
      "geometry": {
        "type": "Point",
        "coordinates": [
          -84.5,
          30.9667
        ]
      },
      "type": "Feature",
      "properties": {
        "hierarchy": [
          "tgn:2527342",
          "tgn:1000001",
          "tgn:7012149",
          "tgn:7013517",
          "tgn:7007248",
          "tgn:7029392"
        ],
        "placetype": [
          "aat:300008347"
        ],
        "id": 2527342,
        "name:xx": "Mount Pleasant"
      }
    },
    {
      "geometry": {
        "type": "Point",
        "coordinates": [
          -81.1333,
          31.9333
        ]
      },
      "type": "Feature",
      "properties": {
        "hierarchy": [
          "tgn:2527343",
          "tgn:1000001",
          "tgn:2000316",
          "tgn:7012149",
          "tgn:7007248",
          "tgn:7029392"
        ],
        "placetype": [
          "aat:300008347"
        ],
        "id": 2527343,
        "name:xx": "Mount Pleasant"
      }
    },
    {
      "geometry": {
        "type": "Point",
        "coordinates": [
          -83.2333,
          32.9667
        ]
      },
      "type": "Feature",
      "properties": {
        "hierarchy": [
          "tgn:2527344",
          "tgn:2000296",
          "tgn:1000001",
          "tgn:7012149",
          "tgn:7007248",
          "tgn:7029392"
        ],
        "placetype": [
          "aat:300008347"
        ],
        "id": 2527344,
        "name:xx": "Mount Pleasant"
      }
    },
    {
      "geometry": {
        "type": "Point",
        "coordinates": [
          -81.85,
          32.1833
        ]
      },
      "type": "Feature",
      "properties": {
        "hierarchy": [
          "tgn:2527345",
          "tgn:1000001",
          "tgn:7012149",
          "tgn:2000345",
          "tgn:7007248",
          "tgn:7029392"
        ],
        "placetype": [
          "aat:300008347"
        ],
        "id": 2527345,
        "name:xx": "Mount Pleasant"
      }
    },
    {
      "geometry": {
        "type": "Point",
        "coordinates": [
          -86.3167,
          40.8333
        ]
      },
      "type": "Feature",
      "properties": {
        "hierarchy": [
          "tgn:2527347",
          "tgn:1000001",
          "tgn:1002242",
          "tgn:7012149",
          "tgn:7007252",
          "tgn:7029392"
        ],
        "placetype": [
          "aat:300008347"
        ],
        "id": 2527347,
        "name:xx": "Mount Pleasant"
      }
    },
    {
      "geometry": {
        "type": "Point",
        "coordinates": [
          -91.2833,
          30.6333
        ]
      },
      "type": "Feature",
      "properties": {
        "hierarchy": [
          "tgn:2527348",
          "tgn:1000001",
          "tgn:2000870",
          "tgn:7012149",
          "tgn:7007256",
          "tgn:7029392"
        ],
        "placetype": [
          "aat:300008347"
        ],
        "id": 2527348,
        "name:xx": "Mount Pleasant"
      }
    },
    {
      "geometry": {
        "type": "Point",
        "coordinates": [
          -92.1667,
          32.1333
        ]
      },
      "type": "Feature",
      "properties": {
        "hierarchy": [
          "tgn:2527349",
          "tgn:1000001",
          "tgn:7012149",
          "tgn:2000917",
          "tgn:7007256",
          "tgn:7029392"
        ],
        "placetype": [
          "aat:300008347"
        ],
        "id": 2527349,
        "name:xx": "Mount Pleasant"
      }
    }
  ]
}
