{
  "type": "FeatureCollection",
  "features": [
    {
      "geometry": {
        "type": "Point",
        "coordinates": [
          -86.4833,
          42.05
        ]
      },
      "type": "Feature",
      "properties": {
        "hierarchy": [
          "tgn:2053320",
          "tgn:1000001",
          "tgn:1002182",
          "tgn:7012149",
          "tgn:7007520",
          "tgn:7029392"
        ],
        "placetype": [
          "aat:300008347"
        ],
        "id": 2053320,
        "name:xx": "Shoreham"
      }
    },
    {
      "geometry": {
        "type": "Point",
        "coordinates": [
          -86.6,
          41.8833
        ]
      },
      "type": "Feature",
      "properties": {
        "hierarchy": [
          "tgn:2053321",
          "tgn:1000001",
          "tgn:1002182",
          "tgn:7012149",
          "tgn:7007520",
          "tgn:7029392"
        ],
        "placetype": [
          "aat:300008347"
        ],
        "id": 2053321,
        "name:xx": "Shorewood Hills"
      }
    },
    {
      "geometry": {
        "type": "Point",
        "coordinates": [
          -88.7,
          46.5
        ]
      },
      "type": "Feature",
      "properties": {
        "hierarchy": [
          "tgn:2053323",
          "tgn:1000001",
          "tgn:7012149",
          "tgn:2000963",
          "tgn:7007520",
          "tgn:7029392"
        ],
        "placetype": [
          "aat:300008347"
        ],
        "id": 2053323,
        "name:xx": "Sidnaw"
      }
    },
    {
      "geometry": {
        "type": "Point",
        "coordinates": [
          -85.1167,
          43.25
        ]
      },
      "type": "Feature",
      "properties": {
        "hierarchy": [
          "tgn:2053324",
          "tgn:1000001",
          "tgn:7012149",
          "tgn:2000981",
          "tgn:7007520",
          "tgn:7029392"
        ],
        "placetype": [
          "aat:300008347"
        ],
        "id": 2053324,
        "name:xx": "Sidney"
      }
    },
    {
      "geometry": {
        "type": "Point",
        "coordinates": [
          -83.6,
          44.45
        ]
      },
      "type": "Feature",
      "properties": {
        "hierarchy": [
          "tgn:2053325",
          "tgn:1000001",
          "tgn:7012149",
          "tgn:2000965",
          "tgn:7007520",
          "tgn:7029392"
        ],
        "placetype": [
          "aat:300008347",
          "aat:300387210"
        ],
        "id": 2053325,
        "name:xx": "Sid Town"
      }
    },
    {
      "geometry": {
        "type": "Point",
        "coordinates": [
          -90.1,
          46.4667
        ]
      },
      "type": "Feature",
      "properties": {
        "hierarchy": [
          "tgn:2053326",
          "tgn:1000001",
          "tgn:7012149",
          "tgn:2000960",
          "tgn:7007520",
          "tgn:7029392"
        ],
        "placetype": [
          "aat:300387016"
        ],
        "id": 2053326,
        "name:xx": "Siemens"
      }
    },
    {
      "geometry": {
        "type": "Point",
        "coordinates": [
          -89.5667,
          46.8167
        ]
      },
      "type": "Feature",
      "properties": {
        "hierarchy": [
          "tgn:2053327",
          "tgn:1000001",
          "tgn:7012149",
          "tgn:2000986",
          "tgn:7007520",
          "tgn:7029392"
        ],
        "placetype": [
          "aat:300008347"
        ],
        "id": 2053327,
        "name:xx": "Silver City"
      }
    },
    {
      "geometry": {
        "type": "Point",
        "coordinates": [
          -83.2333,
          43.3167
        ]
      },
      "type": "Feature",
      "properties": {
        "hierarchy": [
          "tgn:2053328",
          "tgn:1000001",
          "tgn:7012149",
          "tgn:2000997",
          "tgn:7007520",
          "tgn:7029392"
        ],
        "placetype": [
          "aat:300008347"
        ],
        "id": 2053328,
        "name:xx": "Silverwood"
      }
    }
  ]
}
