{
  "geometry": {
    "type": "Point",
    "coordinates": [
      29.2333,
      55.1667
    ]
  },
  "type": "Feature",
  "properties": {
    "hierarchy": [
      "tgn:1060658",
      "tgn:7011701",
      "tgn:1000003",
      "tgn:7006657",
      "tgn:7029392"
    ],
    "placetype": [
      "aat:300008347"
    ],
    "id": 1060658,
    "name:xx": "Ulla"
  }
}
