{
  "geometry": {
    "type": "Point",
    "coordinates": [
      19.6667,
      48.3333
    ]
  },
  "type": "Feature",
  "properties": {
    "hierarchy": [
      "tgn:1027353",
      "tgn:7027131",
      "tgn:1000003",
      "tgn:7011765",
      "tgn:7029392"
    ],
    "placetype": [
      "aat:300008347"
    ],
    "id": 1027353,
    "name:xx": "Lučenec"
  }
}
