{
  "geometry": {
    "type": "Point",
    "coordinates": [
      -69.4833,
      46.4833
    ]
  },
  "type": "Feature",
  "properties": {
    "hierarchy": [
      "tgn:2758158",
      "tgn:1000001",
      "tgn:7012149",
      "tgn:2000928",
      "tgn:7007515",
      "tgn:7029392"
    ],
    "placetype": [
      "aat:300008699"
    ],
    "id": 2758158,
    "name:xx": "West Branch Thoroughfare Brook"
  }
}
