{
  "geometry": {
    "type": "Point",
    "coordinates": [
      -88.8167,
      36.1167
    ]
  },
  "type": "Feature",
  "properties": {
    "hierarchy": [
      "tgn:2097877",
      "tgn:1000001",
      "tgn:7012149",
      "tgn:2001928",
      "tgn:7007825",
      "tgn:7029392"
    ],
    "placetype": [
      "aat:300008347",
      "aat:300387210"
    ],
    "id": 2097877,
    "name:xx": "Beech Grove"
  }
}
