{
  "geometry": {
    "type": "Point",
    "coordinates": [
      -106.9667,
      34.6833
    ]
  },
  "type": "Feature",
  "properties": {
    "hierarchy": [
      "tgn:2507071",
      "tgn:1000001",
      "tgn:7012149",
      "tgn:2001460",
      "tgn:7007566",
      "tgn:7029392"
    ],
    "placetype": [
      "aat:300006191"
    ],
    "id": 2507071,
    "name:xx": "Metate Reservoir"
  }
}
