{
  "geometry": {
    "type": "Point",
    "coordinates": [
      -58.0167,
      -34.9333
    ]
  },
  "type": "Feature",
  "properties": {
    "hierarchy": [
      "tgn:1133290",
      "tgn:1001160",
      "tgn:7006477",
      "tgn:1000002",
      "tgn:7029392"
    ],
    "placetype": [
      "aat:300008706"
    ],
    "id": 1133290,
    "name:xx": "Gato, Arroyo del"
  }
}
