{
  "geometry": {
    "type": "Point",
    "coordinates": [
      -109.8167,
      38.4333
    ]
  },
  "type": "Feature",
  "properties": {
    "hierarchy": [
      "tgn:2712647",
      "tgn:1000001",
      "tgn:7012149",
      "tgn:2002119",
      "tgn:7007827",
      "tgn:7029392"
    ],
    "placetype": [
      "aat:300008761"
    ],
    "id": 2712647,
    "name:xx": "Taylor Canyon"
  }
}
