{
  "geometry": {
    "type": "Point",
    "coordinates": [
      -105.1833,
      37.6667
    ]
  },
  "type": "Feature",
  "properties": {
    "hierarchy": [
      "tgn:2657014",
      "tgn:1000001",
      "tgn:7012149",
      "tgn:2000219",
      "tgn:7007158",
      "tgn:7029392"
    ],
    "placetype": [
      "aat:300008798"
    ],
    "id": 2657014,
    "name:xx": "Sheep Mountain"
  }
}
