{
  "geometry": {
    "type": "Point",
    "coordinates": [
      53.5167,
      54.8333
    ]
  },
  "type": "Feature",
  "properties": {
    "hierarchy": [
      "tgn:1051243",
      "tgn:1000004",
      "tgn:7002435",
      "tgn:7011524",
      "tgn:7029392"
    ],
    "placetype": [
      "aat:300008347"
    ],
    "id": 1051243,
    "name:xx": "Chekan"
  }
}
