{
  "geometry": {
    "type": "Point",
    "coordinates": [
      4.9667,
      49.5667
    ]
  },
  "type": "Feature",
  "properties": {
    "hierarchy": [
      "tgn:1033596",
      "tgn:1000003",
      "tgn:7002880",
      "tgn:1000070",
      "tgn:7029392"
    ],
    "placetype": [
      "aat:300008347"
    ],
    "id": 1033596,
    "name:xx": "La Besace"
  }
}
