{
  "geometry": {
    "type": "Point",
    "coordinates": [
      -80.8167,
      40.7667
    ]
  },
  "type": "Feature",
  "properties": {
    "hierarchy": [
      "tgn:2511066",
      "tgn:1000001",
      "tgn:1002295",
      "tgn:7012149",
      "tgn:7007706",
      "tgn:7029392"
    ],
    "placetype": [
      "aat:300006191"
    ],
    "id": 2511066,
    "name:xx": "Midway Lake"
  }
}
