{
  "geometry": {
    "type": "Point",
    "coordinates": [
      -101.45,
      44.3667
    ]
  },
  "type": "Feature",
  "properties": {
    "hierarchy": [
      "tgn:2655283",
      "tgn:1000001",
      "tgn:2001797",
      "tgn:7012149",
      "tgn:7007713",
      "tgn:7029392"
    ],
    "placetype": [
      "aat:300008706"
    ],
    "id": 2655283,
    "name:xx": "Shanty Creek"
  }
}
