{
  "geometry": {
    "type": "Point",
    "coordinates": [
      -78.5333,
      36.65
    ]
  },
  "type": "Feature",
  "properties": {
    "hierarchy": [
      "tgn:2112440",
      "tgn:1000001",
      "tgn:7012149",
      "tgn:2002173",
      "tgn:7007919",
      "tgn:7029392"
    ],
    "placetype": [
      "aat:300008347"
    ],
    "id": 2112440,
    "name:xx": "Jeffress"
  }
}
