{
  "geometry": {
    "type": "Point",
    "coordinates": [
      29.966667,
      30.95
    ]
  },
  "type": "Feature",
  "properties": {
    "hierarchy": [
      "tgn:7527647",
      "tgn:7001242",
      "tgn:1001075",
      "tgn:7016833",
      "tgn:7029392"
    ],
    "placetype": [
      "aat:300007544"
    ],
    "name:en": "Sīdī 'Umar Abū Luţay'ah",
    "id": 7527647
  }
}
