{
  "geometry": {
    "type": "Point",
    "coordinates": [
      99.3333,
      17.9167
    ]
  },
  "type": "Feature",
  "properties": {
    "hierarchy": [
      "tgn:1085694",
      "tgn:7000923",
      "tgn:7005194",
      "tgn:1000004",
      "tgn:1000142",
      "tgn:7029392"
    ],
    "placetype": [
      "aat:300008347"
    ],
    "id": 1085694,
    "name:xx": "Sop Prap"
  }
}
