{
  "geometry": {
    "type": "Point",
    "coordinates": [
      -108.15,
      37.9167
    ]
  },
  "type": "Feature",
  "properties": {
    "hierarchy": [
      "tgn:2733767",
      "tgn:1000001",
      "tgn:7012149",
      "tgn:7007158",
      "tgn:2000248",
      "tgn:7029392"
    ],
    "placetype": [
      "aat:300008706"
    ],
    "id": 2733767,
    "name:xx": "Turner Creek"
  }
}
