{
  "geometry": {
    "type": "Point",
    "coordinates": [
      -95.1833,
      40.9667
    ]
  },
  "type": "Feature",
  "properties": {
    "hierarchy": [
      "tgn:2138859",
      "tgn:1000001",
      "tgn:7012149",
      "tgn:2000625",
      "tgn:7007253",
      "tgn:7029392"
    ],
    "placetype": [
      "aat:300008706"
    ],
    "id": 2138859,
    "name:xx": "Ashby Creek"
  }
}
