{
  "type": "FeatureCollection",
  "features": [
    {
      "geometry": {
        "type": "Point",
        "coordinates": [
          16.8,
          39.066667
        ]
      },
      "type": "Feature",
      "properties": {
        "hierarchy": [
          "tgn:7047110",
          "tgn:7024841",
          "tgn:7007850",
          "tgn:1000003",
          "tgn:1000080",
          "tgn:7029392"
        ],
        "placetype": [
          "aat:300008347"
        ],
        "id": 7047110,
        "name:xx": "Fatighella"
      }
    },
    {
      "geometry": {
        "type": "Point",
        "coordinates": [
          13.3,
          41.4
        ]
      },
      "type": "Feature",
      "properties": {
        "hierarchy": [
          "tgn:7047111",
          "tgn:7003136",
          "tgn:1000003",
          "tgn:7003080",
          "tgn:1000080",
          "tgn:7029392"
        ],
        "placetype": [
          "aat:300008795"
        ],
        "id": 7047111,
        "name:xx": "Fate, Monte delle"
      }
    },
    {
      "geometry": {
        "type": "Point",
        "coordinates": [
          10.866667,
          43.333333
        ]
      },
      "type": "Feature",
      "properties": {
        "hierarchy": [
          "tgn:7047112",
          "tgn:7003166",
          "tgn:1000003",
          "tgn:7009760",
          "tgn:1000080",
          "tgn:7029392"
        ],
        "placetype": [
          "aat:300008347"
        ],
        "id": 7047112,
        "name:xx": "Fatagliano"
      }
    },
    {
      "geometry": {
        "type": "Point",
        "coordinates": [
          12.1,
          42.55
        ]
      },
      "type": "Feature",
      "properties": {
        "hierarchy": [
          "tgn:7047113",
          "tgn:7003139",
          "tgn:1000003",
          "tgn:7003080",
          "tgn:1000080",
          "tgn:7029392"
        ],
        "placetype": [
          "aat:300008347"
        ],
        "id": 7047113,
        "name:xx": "Fastello"
      }
    },
    {
      "geometry": {
        "type": "Point",
        "coordinates": [
          12.933333,
          42.333333
        ]
      },
      "type": "Feature",
      "properties": {
        "hierarchy": [
          "tgn:7047114",
          "tgn:7003171",
          "tgn:1000003",
          "tgn:7003125",
          "tgn:1000080",
          "tgn:7029392"
        ],
        "placetype": [
          "aat:300008347"
        ],
        "id": 7047114,
        "name:xx": "Fassinoro"
      }
    },
    {
      "geometry": {
        "type": "Point",
        "coordinates": [
          11.7,
          46.433333
        ]
      },
      "type": "Feature",
      "properties": {
        "hierarchy": [
          "tgn:7047115",
          "tgn:1003440",
          "tgn:1000003",
          "tgn:7003124",
          "tgn:1000080",
          "tgn:7029392"
        ],
        "placetype": [
          "aat:300008761"
        ],
        "id": 7047115,
        "name:xx": "Fassa, Val di"
      }
    },
    {
      "geometry": {
        "type": "Point",
        "coordinates": [
          10.166667,
          44.666667
        ]
      },
      "type": "Feature",
      "properties": {
        "hierarchy": [
          "tgn:7047116",
          "tgn:7003131",
          "tgn:1000003",
          "tgn:7008516",
          "tgn:1000080",
          "tgn:7029392"
        ],
        "placetype": [
          "aat:300008347"
        ],
        "id": 7047116,
        "name:xx": "Faseto"
      }
    },
    {
      "geometry": {
        "type": "Point",
        "coordinates": [
          9.216667,
          44.583333
        ]
      },
      "type": "Feature",
      "properties": {
        "hierarchy": [
          "tgn:7047117",
          "tgn:1000003",
          "tgn:7003142",
          "tgn:7003236",
          "tgn:1000080",
          "tgn:7029392"
        ],
        "placetype": [
          "aat:300008347"
        ],
        "id": 7047117,
        "name:xx": "Fascia"
      }
    }
  ]
}
