{
  "geometry": {
    "type": "Point",
    "coordinates": [
      -93.75,
      44.5333
    ]
  },
  "type": "Feature",
  "properties": {
    "hierarchy": [
      "tgn:2334510",
      "tgn:1000001",
      "tgn:7012149",
      "tgn:2001038",
      "tgn:7007521",
      "tgn:7029392"
    ],
    "placetype": [
      "aat:300008706"
    ],
    "id": 2334510,
    "name:xx": "Forest Prairie Creek"
  }
}
