{
  "geometry": {
    "type": "Point",
    "coordinates": [
      -102.2833,
      35.2167
    ]
  },
  "type": "Feature",
  "properties": {
    "hierarchy": [
      "tgn:2548708",
      "tgn:1000001",
      "tgn:7012149",
      "tgn:7007826",
      "tgn:7029392"
    ],
    "placetype": [
      "aat:300008706"
    ],
    "id": 2548708,
    "name:xx": "North Palo Duro Creek"
  }
}
