{
  "geometry": {
    "type": "Point",
    "coordinates": [
      2.65,
      48.8333
    ]
  },
  "type": "Feature",
  "properties": {
    "hierarchy": [
      "tgn:4006956",
      "tgn:1000003",
      "tgn:7002883",
      "tgn:1000070",
      "tgn:7029392"
    ],
    "placetype": [
      "aat:300008347"
    ],
    "id": 4006956,
    "name:xx": "Marne-la-Vallée"
  }
}
