{
  "geometry": {
    "type": "Point",
    "coordinates": [
      -87.1667,
      34.8667
    ]
  },
  "type": "Feature",
  "properties": {
    "hierarchy": [
      "tgn:2695660",
      "tgn:7002659",
      "tgn:1000001",
      "tgn:7012149",
      "tgn:2000041",
      "tgn:7029392"
    ],
    "placetype": [
      "aat:300008761"
    ],
    "id": 2695660,
    "name:xx": "Stinnett Hollow"
  }
}
