{
  "geometry": {
    "type": "Point",
    "coordinates": [
      -123.7167,
      47.6333
    ]
  },
  "type": "Feature",
  "properties": {
    "hierarchy": [
      "tgn:2719760",
      "tgn:1000001",
      "tgn:7012149",
      "tgn:1002521",
      "tgn:7007920",
      "tgn:7029392"
    ],
    "placetype": [
      "aat:300008680"
    ],
    "id": 2719760,
    "name:xx": "Three Prune Lakes"
  }
}
