{
  "geometry": {
    "type": "Point",
    "coordinates": [
      121.4317,
      25.1984
    ]
  },
  "type": "Feature",
  "properties": {
    "hierarchy": [
      "tgn:7468978",
      "tgn:1000004",
      "tgn:1000454",
      "tgn:1000141",
      "tgn:7029392"
    ],
    "placetype": [
      "aat:300387173"
    ],
    "id": 7468978,
    "name:xx": "Kanding Li"
  }
}
