{
  "geometry": {
    "type": "Point",
    "coordinates": [
      -92.05,
      37.6167
    ]
  },
  "type": "Feature",
  "properties": {
    "hierarchy": [
      "tgn:2588888",
      "tgn:1000001",
      "tgn:7012149",
      "tgn:2001233",
      "tgn:7007523",
      "tgn:7029392"
    ],
    "placetype": [
      "aat:300386845"
    ],
    "id": 2588888,
    "name:xx": "Pocket Eddy"
  }
}
