{
  "geometry": {
    "type": "Point",
    "coordinates": [
      -82.7167,
      40.3667
    ]
  },
  "type": "Feature",
  "properties": {
    "hierarchy": [
      "tgn:2615958",
      "tgn:1000001",
      "tgn:7012149",
      "tgn:1002697",
      "tgn:7007706",
      "tgn:7029392"
    ],
    "placetype": [
      "aat:300008699"
    ],
    "id": 2615958,
    "name:xx": "Reynolds Run"
  }
}
