{
  "geometry": {
    "type": "Point",
    "coordinates": [
      34.194451,
      24.615579
    ]
  },
  "type": "Feature",
  "properties": {
    "hierarchy": [
      "tgn:7521917",
      "tgn:7001242",
      "tgn:7001311",
      "tgn:7016833",
      "tgn:7029392"
    ],
    "placetype": [
      "aat:300379998"
    ],
    "name:en": "Ab큰 Mur훮d, W훮d카",
    "id": 7521917
  }
}
