{
  "geometry": {
    "type": "Point",
    "coordinates": [
      -87.9833,
      43.4667
    ]
  },
  "type": "Feature",
  "properties": {
    "hierarchy": [
      "tgn:2122638",
      "tgn:1000001",
      "tgn:7012149",
      "tgn:1002766",
      "tgn:7007922",
      "tgn:7029392"
    ],
    "placetype": [
      "aat:300008347"
    ],
    "id": 2122638,
    "name:xx": "Waubeka"
  }
}
