{
  "geometry": {
    "type": "Point",
    "coordinates": [
      -111.9667,
      35.55
    ]
  },
  "type": "Feature",
  "properties": {
    "hierarchy": [
      "tgn:2587223",
      "tgn:1000001",
      "tgn:7006451",
      "tgn:2000092",
      "tgn:7012149",
      "tgn:7029392"
    ],
    "placetype": [
      "aat:300006191"
    ],
    "id": 2587223,
    "name:xx": "Platten Tank"
  }
}
