{
  "geometry": {
    "type": "Point",
    "coordinates": [
      -81.4167,
      31.3667
    ]
  },
  "type": "Feature",
  "properties": {
    "hierarchy": [
      "tgn:2275655",
      "tgn:1000001",
      "tgn:7012149",
      "tgn:2000386",
      "tgn:7007248",
      "tgn:7029392"
    ],
    "placetype": [
      "aat:300008707"
    ],
    "id": 2275655,
    "name:xx": "Darien River"
  }
}
