{
  "type": "FeatureCollection",
  "features": [
    {
      "geometry": {
        "type": "Point",
        "coordinates": [
          -92.8,
          40.55
        ]
      },
      "type": "Feature",
      "properties": {
        "hierarchy": [
          "tgn:2732690",
          "tgn:1000001",
          "tgn:7012149",
          "tgn:2001234",
          "tgn:7007523",
          "tgn:7029392"
        ],
        "placetype": [
          "aat:300008706"
        ],
        "id": 2732690,
        "name:xx": "Turkey Creek"
      }
    },
    {
      "geometry": {
        "type": "Point",
        "coordinates": [
          -110.3333,
          46.15
        ]
      },
      "type": "Feature",
      "properties": {
        "hierarchy": [
          "tgn:2732692",
          "tgn:1000001",
          "tgn:7012149",
          "tgn:2001293",
          "tgn:7007524",
          "tgn:7029392"
        ],
        "placetype": [
          "aat:300008706"
        ],
        "id": 2732692,
        "name:xx": "Turkey Creek"
      }
    },
    {
      "geometry": {
        "type": "Point",
        "coordinates": [
          -97.0667,
          40.0167
        ]
      },
      "type": "Feature",
      "properties": {
        "hierarchy": [
          "tgn:2732693",
          "tgn:1000001",
          "tgn:2001363",
          "tgn:7012149",
          "tgn:7007525",
          "tgn:7029392"
        ],
        "placetype": [
          "aat:300008706"
        ],
        "id": 2732693,
        "name:xx": "Turkey Creek"
      }
    },
    {
      "geometry": {
        "type": "Point",
        "coordinates": [
          -96.0167,
          41.4
        ]
      },
      "type": "Feature",
      "properties": {
        "hierarchy": [
          "tgn:2732694",
          "tgn:1000001",
          "tgn:7012149",
          "tgn:2001404",
          "tgn:7007525",
          "tgn:7029392"
        ],
        "placetype": [
          "aat:300008706"
        ],
        "id": 2732694,
        "name:xx": "Turkey Creek"
      }
    },
    {
      "geometry": {
        "type": "Point",
        "coordinates": [
          -96.8833,
          42.65
        ]
      },
      "type": "Feature",
      "properties": {
        "hierarchy": [
          "tgn:2732695",
          "tgn:1000001",
          "tgn:2001341",
          "tgn:7012149",
          "tgn:7007525",
          "tgn:7029392"
        ],
        "placetype": [
          "aat:300008706"
        ],
        "id": 2732695,
        "name:xx": "Turkey Creek"
      }
    },
    {
      "geometry": {
        "type": "Point",
        "coordinates": [
          -98.8333,
          42.6833
        ]
      },
      "type": "Feature",
      "properties": {
        "hierarchy": [
          "tgn:2732696",
          "tgn:1000001",
          "tgn:2001360",
          "tgn:7012149",
          "tgn:7007525",
          "tgn:7029392"
        ],
        "placetype": [
          "aat:300008706"
        ],
        "id": 2732696,
        "name:xx": "Turkey Creek"
      }
    },
    {
      "geometry": {
        "type": "Point",
        "coordinates": [
          -99.4,
          40.8167
        ]
      },
      "type": "Feature",
      "properties": {
        "hierarchy": [
          "tgn:2732697",
          "tgn:1000001",
          "tgn:2001325",
          "tgn:7012149",
          "tgn:7007525",
          "tgn:7029392"
        ],
        "placetype": [
          "aat:300008706"
        ],
        "id": 2732697,
        "name:xx": "Turkey Creek"
      }
    },
    {
      "geometry": {
        "type": "Point",
        "coordinates": [
          -106.4333,
          35.9833
        ]
      },
      "type": "Feature",
      "properties": {
        "hierarchy": [
          "tgn:2732698",
          "tgn:1000001",
          "tgn:7012149",
          "tgn:2001451",
          "tgn:7007566",
          "tgn:7029392"
        ],
        "placetype": [
          "aat:300008706"
        ],
        "id": 2732698,
        "name:xx": "Turkey Creek"
      }
    },
    {
      "geometry": {
        "type": "Point",
        "coordinates": [
          -107.5833,
          33.8167
        ]
      },
      "type": "Feature",
      "properties": {
        "hierarchy": [
          "tgn:2732699",
          "tgn:1000001",
          "tgn:7012149",
          "tgn:2001456",
          "tgn:7007566",
          "tgn:7029392"
        ],
        "placetype": [
          "aat:300008706"
        ],
        "id": 2732699,
        "name:xx": "Turkey Creek"
      }
    }
  ]
}
