{
  "geometry": {
    "type": "Point",
    "coordinates": [
      -113.2833,
      38.45
    ]
  },
  "type": "Feature",
  "properties": {
    "hierarchy": [
      "tgn:2409977",
      "tgn:2002101",
      "tgn:1000001",
      "tgn:7012149",
      "tgn:7007827",
      "tgn:7029392"
    ],
    "placetype": [
      "aat:300000390"
    ],
    "id": 2409977,
    "name:xx": "Imperial Mine"
  }
}
