{
  "geometry": {
    "type": "Point",
    "coordinates": [
      34.709582,
      24.497602
    ]
  },
  "type": "Feature",
  "properties": {
    "hierarchy": [
      "tgn:7523276",
      "tgn:7001242",
      "tgn:7001311",
      "tgn:7016833",
      "tgn:7029392"
    ],
    "placetype": [
      "aat:300379998"
    ],
    "name:en": "Durunkāt, Wādī",
    "id": 7523276
  }
}
