{
  "geometry": {
    "type": "Point",
    "coordinates": [
      -110.2833,
      40.8833
    ]
  },
  "type": "Feature",
  "properties": {
    "hierarchy": [
      "tgn:2322417",
      "tgn:1000001",
      "tgn:7012149",
      "tgn:2002122",
      "tgn:7007827",
      "tgn:7029392"
    ],
    "placetype": [
      "aat:300008706"
    ],
    "id": 2322417,
    "name:xx": "Fallon Creek"
  }
}
