{
  "geometry": {
    "type": "Point",
    "coordinates": [
      -96.8167,
      29.3333
    ]
  },
  "type": "Feature",
  "properties": {
    "hierarchy": [
      "tgn:2376821",
      "tgn:1000001",
      "tgn:7012149",
      "tgn:1002578",
      "tgn:7007826",
      "tgn:7029392"
    ],
    "placetype": [
      "aat:300008706"
    ],
    "id": 2376821,
    "name:xx": "Hardys Sandy Creek"
  }
}
