{
  "geometry": {
    "type": "Point",
    "coordinates": [
      -101.4333,
      36.9167
    ]
  },
  "type": "Feature",
  "properties": {
    "hierarchy": [
      "tgn:2770395",
      "tgn:1000001",
      "tgn:7012149",
      "tgn:2001692",
      "tgn:7007707",
      "tgn:7029392"
    ],
    "placetype": [
      "aat:300008680"
    ],
    "id": 2770395,
    "name:xx": "Wild Horse Lake"
  }
}
