{
  "geometry": {
    "type": "Point",
    "coordinates": [
      -104.233333,
      19.25
    ]
  },
  "type": "Feature",
  "properties": {
    "hierarchy": [
      "tgn:7394767",
      "tgn:7016644",
      "tgn:1000001",
      "tgn:7005560",
      "tgn:7029392"
    ],
    "placetype": [
      "aat:300008347"
    ],
    "id": 7394767,
    "name:xx": "San José de Camotlán"
  }
}
