{
  "geometry": {
    "type": "Point",
    "coordinates": [
      -103.5333,
      35.1167
    ]
  },
  "type": "Feature",
  "properties": {
    "hierarchy": [
      "tgn:2717788",
      "tgn:1000001",
      "tgn:7012149",
      "tgn:2001448",
      "tgn:7007566",
      "tgn:7029392"
    ],
    "placetype": [
      "aat:300006075"
    ],
    "id": 2717788,
    "name:xx": "Thomas Lateral"
  }
}
