{
  "type": "FeatureCollection",
  "features": [
    {
      "geometry": {
        "type": "Point",
        "coordinates": [
          -85.5833,
          37.9833
        ]
      },
      "type": "Feature",
      "properties": {
        "hierarchy": [
          "tgn:2228340",
          "tgn:1000001",
          "tgn:2000774",
          "tgn:7012149",
          "tgn:7007255",
          "tgn:7029392"
        ],
        "placetype": [
          "aat:300008706"
        ],
        "id": 2228340,
        "name:xx": "Cedar Creek"
      }
    },
    {
      "geometry": {
        "type": "Point",
        "coordinates": [
          -84.05,
          38.5167
        ]
      },
      "type": "Feature",
      "properties": {
        "hierarchy": [
          "tgn:2228341",
          "tgn:1000001",
          "tgn:7012149",
          "tgn:1002829",
          "tgn:7007255",
          "tgn:7029392"
        ],
        "placetype": [
          "aat:300008706"
        ],
        "id": 2228341,
        "name:xx": "Cedar Creek"
      }
    },
    {
      "geometry": {
        "type": "Point",
        "coordinates": [
          -92.6167,
          31.8167
        ]
      },
      "type": "Feature",
      "properties": {
        "hierarchy": [
          "tgn:2228342",
          "tgn:1000001",
          "tgn:7012149",
          "tgn:2000917",
          "tgn:7007256",
          "tgn:7029392"
        ],
        "placetype": [
          "aat:300008706"
        ],
        "id": 2228342,
        "name:xx": "Cedar Creek"
      }
    },
    {
      "geometry": {
        "type": "Point",
        "coordinates": [
          -75.8667,
          37.9333
        ]
      },
      "type": "Feature",
      "properties": {
        "hierarchy": [
          "tgn:2228343",
          "tgn:1000001",
          "tgn:1002902",
          "tgn:7012149",
          "tgn:7007516",
          "tgn:7029392"
        ],
        "placetype": [
          "aat:300132316"
        ],
        "id": 2228343,
        "name:xx": "Cedar Creek"
      }
    },
    {
      "geometry": {
        "type": "Point",
        "coordinates": [
          -76.0333,
          38.3167
        ]
      },
      "type": "Feature",
      "properties": {
        "hierarchy": [
          "tgn:2228344",
          "tgn:1002338",
          "tgn:1000001",
          "tgn:7012149",
          "tgn:7007516",
          "tgn:7029392"
        ],
        "placetype": [
          "aat:300008706"
        ],
        "id": 2228344,
        "name:xx": "Cedar Creek"
      }
    },
    {
      "geometry": {
        "type": "Point",
        "coordinates": [
          -75.8833,
          38.25
        ]
      },
      "type": "Feature",
      "properties": {
        "hierarchy": [
          "tgn:2228345",
          "tgn:1000001",
          "tgn:1003023",
          "tgn:7012149",
          "tgn:7007516",
          "tgn:7029392"
        ],
        "placetype": [
          "aat:300008706"
        ],
        "id": 2228345,
        "name:xx": "Cedar Creek"
      }
    },
    {
      "geometry": {
        "type": "Point",
        "coordinates": [
          -86.2333,
          42.2667
        ]
      },
      "type": "Feature",
      "properties": {
        "hierarchy": [
          "tgn:2228346",
          "tgn:1000001",
          "tgn:7012149",
          "tgn:1002967",
          "tgn:7007520",
          "tgn:7029392"
        ],
        "placetype": [
          "aat:300008706"
        ],
        "id": 2228346,
        "name:xx": "Cedar Creek"
      }
    },
    {
      "geometry": {
        "type": "Point",
        "coordinates": [
          -83.55,
          42.65
        ]
      },
      "type": "Feature",
      "properties": {
        "hierarchy": [
          "tgn:2228347",
          "tgn:1000001",
          "tgn:7012149",
          "tgn:1002737",
          "tgn:7007520",
          "tgn:7029392"
        ],
        "placetype": [
          "aat:300008706"
        ],
        "id": 2228347,
        "name:xx": "Cedar Creek"
      }
    },
    {
      "geometry": {
        "type": "Point",
        "coordinates": [
          -85.5167,
          43.2333
        ]
      },
      "type": "Feature",
      "properties": {
        "hierarchy": [
          "tgn:2228348",
          "tgn:1000001",
          "tgn:7012149",
          "tgn:1002540",
          "tgn:7007520",
          "tgn:7029392"
        ],
        "placetype": [
          "aat:300008706"
        ],
        "id": 2228348,
        "name:xx": "Cedar Creek"
      }
    },
    {
      "geometry": {
        "type": "Point",
        "coordinates": [
          -85.3167,
          43.5833
        ]
      },
      "type": "Feature",
      "properties": {
        "hierarchy": [
          "tgn:2228349",
          "tgn:1000001",
          "tgn:7012149",
          "tgn:2000977",
          "tgn:7007520",
          "tgn:7029392"
        ],
        "placetype": [
          "aat:300008706"
        ],
        "id": 2228349,
        "name:xx": "Cedar Creek"
      }
    }
  ]
}
