{
  "geometry": {
    "type": "Point",
    "coordinates": [
      -93.4667,
      38.5167
    ]
  },
  "type": "Feature",
  "properties": {
    "hierarchy": [
      "tgn:2148015",
      "tgn:1000001",
      "tgn:7012149",
      "tgn:7007523",
      "tgn:7029392"
    ],
    "placetype": [
      "aat:300008706"
    ],
    "id": 2148015,
    "name:xx": "Barker Creek"
  }
}
