{
  "type": "FeatureCollection",
  "features": [
    {
      "geometry": {
        "type": "Point",
        "coordinates": [
          3.951736,
          50.883908
        ]
      },
      "type": "Feature",
      "properties": {
        "hierarchy": [
          "tgn:7250963",
          "tgn:7003457",
          "tgn:1000003",
          "tgn:1000063",
          "tgn:7018236",
          "tgn:7029392"
        ],
        "placetype": [
          "aat:300008347"
        ],
        "id": 7250963,
        "name:xx": "Oostdorp"
      }
    },
    {
      "geometry": {
        "type": "Point",
        "coordinates": [
          4.7,
          51.366667
        ]
      },
      "type": "Feature",
      "properties": {
        "hierarchy": [
          "tgn:7250964",
          "tgn:7003456",
          "tgn:1000003",
          "tgn:1000063",
          "tgn:7018236",
          "tgn:7029392"
        ],
        "placetype": [
          "aat:300008347"
        ],
        "id": 7250964,
        "name:xx": "Oostbrecht"
      }
    },
    {
      "geometry": {
        "type": "Point",
        "coordinates": [
          4.232973,
          51.125996
        ]
      },
      "type": "Feature",
      "properties": {
        "hierarchy": [
          "tgn:7250965",
          "tgn:7003457",
          "tgn:1000003",
          "tgn:1000063",
          "tgn:7018236",
          "tgn:7029392"
        ],
        "placetype": [
          "aat:300008347"
        ],
        "id": 7250965,
        "name:xx": "Oostbarm"
      }
    },
    {
      "geometry": {
        "type": "Point",
        "coordinates": [
          4.798382,
          51.194469
        ]
      },
      "type": "Feature",
      "properties": {
        "hierarchy": [
          "tgn:7250968",
          "tgn:7003456",
          "tgn:1000003",
          "tgn:1000063",
          "tgn:7018236",
          "tgn:7029392"
        ],
        "placetype": [
          "aat:300008347"
        ],
        "id": 7250968,
        "name:xx": "Oorlandseheide"
      }
    },
    {
      "geometry": {
        "type": "Point",
        "coordinates": [
          4.35,
          51.283333
        ]
      },
      "type": "Feature",
      "properties": {
        "hierarchy": [
          "tgn:7250969",
          "tgn:7003456",
          "tgn:1000003",
          "tgn:1000063",
          "tgn:7018236",
          "tgn:7029392"
        ],
        "placetype": [
          "aat:300006163"
        ],
        "id": 7250969,
        "name:xx": "Oorderen, Polder d'"
      }
    }
  ]
}
