{
  "geometry": {
    "type": "Point",
    "coordinates": [
      -98.2333,
      32.65
    ]
  },
  "type": "Feature",
  "properties": {
    "hierarchy": [
      "tgn:2623756",
      "tgn:1000001",
      "tgn:7012149",
      "tgn:2002053",
      "tgn:7007826",
      "tgn:7029392"
    ],
    "placetype": [
      "aat:300008706"
    ],
    "id": 2623756,
    "name:xx": "Rock Creek"
  }
}
