{
  "geometry": {
    "type": "Point",
    "coordinates": [
      -83.4167,
      39.75
    ]
  },
  "type": "Feature",
  "properties": {
    "hierarchy": [
      "tgn:2301172",
      "tgn:1000001",
      "tgn:7012149",
      "tgn:1002625",
      "tgn:7007706",
      "tgn:7029392"
    ],
    "placetype": [
      "aat:300006075"
    ],
    "id": 2301172,
    "name:xx": "Dunkin Ditch"
  }
}
