{
  "geometry": {
    "type": "Point",
    "coordinates": [
      140.2833,
      -6.3833
    ]
  },
  "type": "Feature",
  "properties": {
    "hierarchy": [
      "tgn:1078455",
      "tgn:1000004",
      "tgn:7003970",
      "tgn:1000116",
      "tgn:7029392"
    ],
    "placetype": [
      "aat:300008347"
    ],
    "id": 1078455,
    "name:xx": "Rumahtinggih"
  }
}
