{
  "geometry": {
    "type": "Point",
    "coordinates": [
      -92.7667,
      37.8167
    ]
  },
  "type": "Feature",
  "properties": {
    "hierarchy": [
      "tgn:2617241",
      "tgn:1000001",
      "tgn:7012149",
      "tgn:2001211",
      "tgn:7007523",
      "tgn:7029392"
    ],
    "placetype": [
      "aat:300008761"
    ],
    "id": 2617241,
    "name:xx": "Richey Hollow"
  }
}
