{
  "geometry": {
    "type": "Point",
    "coordinates": [
      -112.3167,
      45.0167
    ]
  },
  "type": "Feature",
  "properties": {
    "hierarchy": [
      "tgn:2266360",
      "tgn:1000001",
      "tgn:7012149",
      "tgn:7007524",
      "tgn:7029392"
    ],
    "placetype": [
      "aat:300008706"
    ],
    "id": 2266360,
    "name:xx": "Crazy Springs Creek"
  }
}
