{
  "geometry": {
    "type": "Point",
    "coordinates": [
      -108.7167,
      33.2333
    ]
  },
  "type": "Feature",
  "properties": {
    "hierarchy": [
      "tgn:2582205",
      "tgn:1000001",
      "tgn:7012149",
      "tgn:7007566",
      "tgn:7029392"
    ],
    "placetype": [
      "aat:300008706"
    ],
    "id": 2582205,
    "name:xx": "Pine Creek"
  }
}
