{
  "type": "FeatureCollection",
  "features": [
    {
      "geometry": {
        "type": "Point",
        "coordinates": [
          -88.1833,
          33.9667
        ]
      },
      "type": "Feature",
      "properties": {
        "hierarchy": [
          "tgn:2470870",
          "tgn:1000001",
          "tgn:7012149",
          "tgn:7029392"
        ],
        "placetype": [
          "aat:300008706"
        ],
        "id": 2470870,
        "name:xx": "Lost Creek"
      }
    },
    {
      "geometry": {
        "type": "Point",
        "coordinates": [
          -165.2667,
          64.55
        ]
      },
      "type": "Feature",
      "properties": {
        "hierarchy": [
          "tgn:2470871",
          "tgn:7006450",
          "tgn:1000001",
          "tgn:7012149",
          "tgn:2000079",
          "tgn:7029392"
        ],
        "placetype": [
          "aat:300008706"
        ],
        "id": 2470871,
        "name:xx": "Lost Creek"
      }
    },
    {
      "geometry": {
        "type": "Point",
        "coordinates": [
          -141.25,
          64.8333
        ]
      },
      "type": "Feature",
      "properties": {
        "hierarchy": [
          "tgn:2470872",
          "tgn:7006450",
          "tgn:1000001",
          "tgn:7012149",
          "tgn:2000085",
          "tgn:7029392"
        ],
        "placetype": [
          "aat:300008706"
        ],
        "id": 2470872,
        "name:xx": "Lost Creek"
      }
    },
    {
      "geometry": {
        "type": "Point",
        "coordinates": [
          -146.7,
          65.2833
        ]
      },
      "type": "Feature",
      "properties": {
        "hierarchy": [
          "tgn:2470873",
          "tgn:7006450",
          "tgn:1000001",
          "tgn:7019674",
          "tgn:7012149",
          "tgn:7029392"
        ],
        "placetype": [
          "aat:300008706"
        ],
        "id": 2470873,
        "name:xx": "Lost Creek"
      }
    },
    {
      "geometry": {
        "type": "Point",
        "coordinates": [
          -150.05,
          65.2833
        ]
      },
      "type": "Feature",
      "properties": {
        "hierarchy": [
          "tgn:2470874",
          "tgn:7006450",
          "tgn:1000001",
          "tgn:7012149",
          "tgn:2000089",
          "tgn:7029392"
        ],
        "placetype": [
          "aat:300008706"
        ],
        "id": 2470874,
        "name:xx": "Lost Creek"
      }
    },
    {
      "geometry": {
        "type": "Point",
        "coordinates": [
          -143.7833,
          61.05
        ]
      },
      "type": "Feature",
      "properties": {
        "hierarchy": [
          "tgn:2470875",
          "tgn:7006450",
          "tgn:1000001",
          "tgn:7012149",
          "tgn:2000086",
          "tgn:7029392"
        ],
        "placetype": [
          "aat:300008706"
        ],
        "id": 2470875,
        "name:xx": "Lost Creek"
      }
    },
    {
      "geometry": {
        "type": "Point",
        "coordinates": [
          -149.4,
          60.25
        ]
      },
      "type": "Feature",
      "properties": {
        "hierarchy": [
          "tgn:2470876",
          "tgn:7006450",
          "tgn:1000001",
          "tgn:7019698",
          "tgn:7012149",
          "tgn:7029392"
        ],
        "placetype": [
          "aat:300008706"
        ],
        "id": 2470876,
        "name:xx": "Lost Creek"
      }
    },
    {
      "geometry": {
        "type": "Point",
        "coordinates": [
          -113.9167,
          35.75
        ]
      },
      "type": "Feature",
      "properties": {
        "hierarchy": [
          "tgn:2470877",
          "tgn:1000001",
          "tgn:7006451",
          "tgn:7012149",
          "tgn:2000098",
          "tgn:7029392"
        ],
        "placetype": [
          "aat:300008706"
        ],
        "id": 2470877,
        "name:xx": "Lost Creek"
      }
    },
    {
      "geometry": {
        "type": "Point",
        "coordinates": [
          -91.7333,
          33.5
        ]
      },
      "type": "Feature",
      "properties": {
        "hierarchy": [
          "tgn:2470878",
          "tgn:1000001",
          "tgn:7016172",
          "tgn:7012149",
          "tgn:2000126",
          "tgn:7029392"
        ],
        "placetype": [
          "aat:300008706"
        ],
        "id": 2470878,
        "name:xx": "Lost Creek"
      }
    },
    {
      "geometry": {
        "type": "Point",
        "coordinates": [
          -92.4667,
          33.7667
        ]
      },
      "type": "Feature",
      "properties": {
        "hierarchy": [
          "tgn:2470879",
          "tgn:1000001",
          "tgn:7016172",
          "tgn:2000111",
          "tgn:7012149",
          "tgn:7029392"
        ],
        "placetype": [
          "aat:300008706"
        ],
        "id": 2470879,
        "name:xx": "Lost Creek"
      }
    }
  ]
}
