{
  "geometry": {
    "type": "Point",
    "coordinates": [
      -91.8833,
      46.35
    ]
  },
  "type": "Feature",
  "properties": {
    "hierarchy": [
      "tgn:2202792",
      "tgn:1000001",
      "tgn:2002318",
      "tgn:7012149",
      "tgn:7007922",
      "tgn:7029392"
    ],
    "placetype": [
      "aat:300008706"
    ],
    "id": 2202792,
    "name:xx": "Buckety Creek"
  }
}
