{
  "geometry": {
    "type": "Point",
    "coordinates": [
      -1.75,
      37.883333
    ]
  },
  "type": "Feature",
  "properties": {
    "hierarchy": [
      "tgn:7307154",
      "tgn:1001439",
      "tgn:1000003",
      "tgn:7002797",
      "tgn:1000095",
      "tgn:7029392"
    ],
    "placetype": [
      "aat:300266640"
    ],
    "id": 7307154,
    "name:xx": "Madroño, Sierra del"
  }
}
