{
  "type": "FeatureCollection",
  "features": [
    {
      "geometry": {
        "type": "Point",
        "coordinates": [
          -109.0667,
          47.25
        ]
      },
      "type": "Feature",
      "properties": {
        "hierarchy": [
          "tgn:2252110",
          "tgn:1000001",
          "tgn:7012149",
          "tgn:2001273",
          "tgn:7007524",
          "tgn:7029392"
        ],
        "placetype": [
          "aat:300008798"
        ],
        "id": 2252110,
        "name:xx": "Cone Butte"
      }
    },
    {
      "geometry": {
        "type": "Point",
        "coordinates": [
          -104.5333,
          32.3833
        ]
      },
      "type": "Feature",
      "properties": {
        "hierarchy": [
          "tgn:2252111",
          "tgn:1000001",
          "tgn:2001436",
          "tgn:7012149",
          "tgn:7007566",
          "tgn:7029392"
        ],
        "placetype": [
          "aat:300008798"
        ],
        "id": 2252111,
        "name:xx": "Cone Butte"
      }
    },
    {
      "geometry": {
        "type": "Point",
        "coordinates": [
          -110.1833,
          33.7667
        ]
      },
      "type": "Feature",
      "properties": {
        "hierarchy": [
          "tgn:2252112",
          "tgn:1000001",
          "tgn:7006451",
          "tgn:2000093",
          "tgn:7012149",
          "tgn:7029392"
        ],
        "placetype": [
          "aat:300006191"
        ],
        "id": 2252112,
        "name:xx": "Cone Butte Tank"
      }
    },
    {
      "geometry": {
        "type": "Point",
        "coordinates": [
          -112.9833,
          42.4
        ]
      },
      "type": "Feature",
      "properties": {
        "hierarchy": [
          "tgn:2252113",
          "tgn:1000001",
          "tgn:7012149",
          "tgn:2000490",
          "tgn:7007250",
          "tgn:7029392"
        ],
        "placetype": [
          "aat:300008761"
        ],
        "id": 2252113,
        "name:xx": "Cone Canyon"
      }
    },
    {
      "geometry": {
        "type": "Point",
        "coordinates": [
          -116.2667,
          48.5333
        ]
      },
      "type": "Feature",
      "properties": {
        "hierarchy": [
          "tgn:2252115",
          "tgn:1000001",
          "tgn:2000462",
          "tgn:7012149",
          "tgn:7007250",
          "tgn:7029392"
        ],
        "placetype": [
          "aat:300008706"
        ],
        "id": 2252115,
        "name:xx": "Cone Creek"
      }
    },
    {
      "geometry": {
        "type": "Point",
        "coordinates": [
          -83.6,
          41.8
        ]
      },
      "type": "Feature",
      "properties": {
        "hierarchy": [
          "tgn:2252116",
          "tgn:1000001",
          "tgn:7012149",
          "tgn:1002679",
          "tgn:7007520",
          "tgn:7029392"
        ],
        "placetype": [
          "aat:300008706"
        ],
        "id": 2252116,
        "name:xx": "Cone Creek"
      }
    },
    {
      "geometry": {
        "type": "Point",
        "coordinates": [
          -114.4,
          45.7167
        ]
      },
      "type": "Feature",
      "properties": {
        "hierarchy": [
          "tgn:2252117",
          "tgn:1000001",
          "tgn:7012149",
          "tgn:2001300",
          "tgn:7007524",
          "tgn:7029392"
        ],
        "placetype": [
          "aat:300008706"
        ],
        "id": 2252117,
        "name:xx": "Cone Creek"
      }
    },
    {
      "geometry": {
        "type": "Point",
        "coordinates": [
          -122.4167,
          43.5667
        ]
      },
      "type": "Feature",
      "properties": {
        "hierarchy": [
          "tgn:2252118",
          "tgn:1000001",
          "tgn:7012149",
          "tgn:2001716",
          "tgn:7007708",
          "tgn:7029392"
        ],
        "placetype": [
          "aat:300008706"
        ],
        "id": 2252118,
        "name:xx": "Cone Creek"
      }
    },
    {
      "geometry": {
        "type": "Point",
        "coordinates": [
          -77.0833,
          38.15
        ]
      },
      "type": "Feature",
      "properties": {
        "hierarchy": [
          "tgn:2252119",
          "tgn:1000001",
          "tgn:7012149",
          "tgn:1002362",
          "tgn:7007919",
          "tgn:7029392"
        ],
        "placetype": [
          "aat:300008706"
        ],
        "id": 2252119,
        "name:xx": "Cone Creek"
      }
    }
  ]
}
