{
  "geometry": {
    "type": "Point",
    "coordinates": [
      -109.55,
      33.4167
    ]
  },
  "type": "Feature",
  "properties": {
    "hierarchy": [
      "tgn:2776925",
      "tgn:1000001",
      "tgn:7006451",
      "tgn:2000094",
      "tgn:7012149",
      "tgn:7029392"
    ],
    "placetype": [
      "aat:300006191"
    ],
    "id": 2776925,
    "name:xx": "Windy Bob Tank"
  }
}
