{
  "geometry": {
    "type": "Point",
    "coordinates": [
      -87.85,
      33.2833
    ]
  },
  "type": "Feature",
  "properties": {
    "hierarchy": [
      "tgn:2464734",
      "tgn:7002659",
      "tgn:1000001",
      "tgn:7012149",
      "tgn:7029392"
    ],
    "placetype": [
      "aat:300008706"
    ],
    "id": 2464734,
    "name:xx": "Logan Creek"
  }
}
