{
  "geometry": {
    "type": "Point",
    "coordinates": [
      -76.2167,
      42.75
    ]
  },
  "type": "Feature",
  "properties": {
    "hierarchy": [
      "tgn:2215297",
      "tgn:1000001",
      "tgn:1002302",
      "tgn:7012149",
      "tgn:7007568",
      "tgn:7029392"
    ],
    "placetype": [
      "aat:300008706"
    ],
    "id": 2215297,
    "name:xx": "Callan Creek"
  }
}
