{
  "geometry": {
    "type": "Point",
    "coordinates": [
      -113.0333,
      34.9167
    ]
  },
  "type": "Feature",
  "properties": {
    "hierarchy": [
      "tgn:2324963",
      "tgn:1000001",
      "tgn:7006451",
      "tgn:7012149",
      "tgn:2000103",
      "tgn:7029392"
    ],
    "placetype": [
      "aat:300266640"
    ],
    "id": 2324963,
    "name:xx": "Ferguson Ridge"
  }
}
