{
  "geometry": {
    "type": "Point",
    "coordinates": [
      -83.7333,
      44.55
    ]
  },
  "type": "Feature",
  "properties": {
    "hierarchy": [
      "tgn:2718446",
      "tgn:2000942",
      "tgn:1000001",
      "tgn:7012149",
      "tgn:7007520",
      "tgn:7029392"
    ],
    "placetype": [
      "aat:300008680"
    ],
    "id": 2718446,
    "name:xx": "Thompson Lake"
  }
}
