{
  "geometry": {
    "type": "Point",
    "coordinates": [
      -71.7667,
      43.0667
    ]
  },
  "type": "Feature",
  "properties": {
    "hierarchy": [
      "tgn:2688999",
      "tgn:1000001",
      "tgn:1002480",
      "tgn:7012149",
      "tgn:7007564",
      "tgn:7029392"
    ],
    "placetype": [
      "aat:300008905"
    ],
    "id": 2688999,
    "name:xx": "Squamscot Bog"
  }
}
