{
  "geometry": {
    "type": "Point",
    "coordinates": [
      -81.3333,
      37.4333
    ]
  },
  "type": "Feature",
  "properties": {
    "hierarchy": [
      "tgn:2270004",
      "tgn:1000001",
      "tgn:7012149",
      "tgn:2002304",
      "tgn:7013961",
      "tgn:7029392"
    ],
    "placetype": [
      "aat:300006191"
    ],
    "id": 2270004,
    "name:xx": "Crumpler Impoundment Number Two"
  }
}
