{
  "geometry": {
    "type": "Point",
    "coordinates": [
      -87.6833,
      37.2667
    ]
  },
  "type": "Feature",
  "properties": {
    "hierarchy": [
      "tgn:2037736",
      "tgn:1000001",
      "tgn:7012149",
      "tgn:2000801",
      "tgn:7007255",
      "tgn:7029392"
    ],
    "placetype": [
      "aat:300008347"
    ],
    "id": 2037736,
    "name:xx": "Beulah"
  }
}
