{
  "type": "FeatureCollection",
  "features": [
    {
      "geometry": {
        "type": "Point",
        "coordinates": [
          7.3833,
          51.5333
        ]
      },
      "type": "Feature",
      "properties": {
        "hierarchy": [
          "tgn:1141181",
          "tgn:1000003",
          "tgn:7003677",
          "tgn:7000084",
          "tgn:7004982",
          "tgn:7029392"
        ],
        "placetype": [
          "aat:300000745",
          "aat:300387332"
        ],
        "id": 1141181,
        "name:xx": "Rahm"
      }
    },
    {
      "geometry": {
        "type": "Point",
        "coordinates": [
          7.3667,
          51.4667
        ]
      },
      "type": "Feature",
      "properties": {
        "hierarchy": [
          "tgn:1141182",
          "tgn:1000003",
          "tgn:7003677",
          "tgn:7000084",
          "tgn:7029392"
        ],
        "placetype": [
          "aat:300000745"
        ],
        "id": 1141182,
        "name:de": "Stockum"
      }
    }
  ]
}
