{
  "geometry": {
    "type": "Point",
    "coordinates": [
      75.475553,
      25.052587
    ]
  },
  "type": "Feature",
  "properties": {
    "hierarchy": [
      "tgn:7576182",
      "tgn:1000004",
      "tgn:7000198",
      "tgn:7016788",
      "tgn:7029392"
    ],
    "placetype": [
      "aat:300008347"
    ],
    "name:en": "Lāmākho",
    "id": 7576182
  }
}
