{
  "type": "FeatureCollection",
  "features": [
    {
      "geometry": {
        "type": "Point",
        "coordinates": [
          -74.283333,
          -49.8
        ]
      },
      "type": "Feature",
      "properties": {
        "hierarchy": [
          "tgn:7309690",
          "tgn:1001702",
          "tgn:1000049",
          "tgn:1000002",
          "tgn:7029392"
        ],
        "placetype": [
          "aat:300008791"
        ],
        "id": 7309690,
        "name:xx": "Nueva, Isla"
      }
    },
    {
      "geometry": {
        "type": "Point",
        "coordinates": [
          -74.6,
          -46.833333
        ]
      },
      "type": "Feature",
      "properties": {
        "hierarchy": [
          "tgn:7309691",
          "tgn:1001623",
          "tgn:1000049",
          "tgn:1000002",
          "tgn:7029392"
        ],
        "placetype": [
          "aat:300008791"
        ],
        "id": 7309691,
        "name:xx": "Nueva, Isla"
      }
    },
    {
      "geometry": {
        "type": "Point",
        "coordinates": [
          -70.933333,
          -29.066667
        ]
      },
      "type": "Feature",
      "properties": {
        "hierarchy": [
          "tgn:7309692",
          "tgn:1001630",
          "tgn:1000049",
          "tgn:1000002",
          "tgn:7029392"
        ],
        "placetype": [
          "aat:300008697"
        ],
        "id": 7309692,
        "name:xx": "Nueva, Aguada"
      }
    },
    {
      "geometry": {
        "type": "Point",
        "coordinates": [
          -74.883333,
          -51.65
        ]
      },
      "type": "Feature",
      "properties": {
        "hierarchy": [
          "tgn:7309693",
          "tgn:1001702",
          "tgn:1000049",
          "tgn:1000002",
          "tgn:7029392"
        ],
        "placetype": [
          "aat:300008795"
        ],
        "id": 7309693,
        "name:xx": "Nuestra Señora de la Victoria, Monte"
      }
    },
    {
      "geometry": {
        "type": "Point",
        "coordinates": [
          -74.75,
          -49.966667
        ]
      },
      "type": "Feature",
      "properties": {
        "hierarchy": [
          "tgn:7309694",
          "tgn:1001702",
          "tgn:1000049",
          "tgn:1000002",
          "tgn:7029392"
        ],
        "placetype": [
          "aat:300008795"
        ],
        "id": 7309694,
        "name:xx": "Nuestra Señora, Monte"
      }
    },
    {
      "geometry": {
        "type": "Point",
        "coordinates": [
          -74.783333,
          -50.016667
        ]
      },
      "type": "Feature",
      "properties": {
        "hierarchy": [
          "tgn:7309695",
          "tgn:1001702",
          "tgn:1000049",
          "tgn:1000002",
          "tgn:7029392"
        ],
        "placetype": [
          "aat:300008676"
        ],
        "id": 7309695,
        "name:xx": "Nuestra Señora, Fiordo"
      }
    },
    {
      "geometry": {
        "type": "Point",
        "coordinates": [
          -75.183333,
          -48.033333
        ]
      },
      "type": "Feature",
      "properties": {
        "hierarchy": [
          "tgn:7309696",
          "tgn:1001623",
          "tgn:1000049",
          "tgn:1000002",
          "tgn:7029392"
        ],
        "placetype": [
          "aat:300008676"
        ],
        "id": 7309696,
        "name:xx": "Nuestra Señora, Fiordo"
      }
    },
    {
      "geometry": {
        "type": "Point",
        "coordinates": [
          -70.466667,
          -25.25
        ]
      },
      "type": "Feature",
      "properties": {
        "hierarchy": [
          "tgn:7309697",
          "tgn:7016598",
          "tgn:1000049",
          "tgn:1000002",
          "tgn:7029392"
        ],
        "placetype": [
          "aat:300132316"
        ],
        "id": 7309697,
        "name:xx": "Nuestra Señora, Bahía"
      }
    },
    {
      "geometry": {
        "type": "Point",
        "coordinates": [
          -72,
          -46.283333
        ]
      },
      "type": "Feature",
      "properties": {
        "hierarchy": [
          "tgn:7309698",
          "tgn:1001623",
          "tgn:1000049",
          "tgn:1000002",
          "tgn:7029392"
        ],
        "placetype": [
          "aat:300008795"
        ],
        "id": 7309698,
        "name:xx": "Nudo, Cerro"
      }
    }
  ]
}
