{
  "geometry": {
    "type": "Point",
    "coordinates": [
      -114.45,
      36.9167
    ]
  },
  "type": "Feature",
  "properties": {
    "hierarchy": [
      "tgn:2778084",
      "tgn:1000001",
      "tgn:2001416",
      "tgn:7012149",
      "tgn:7007526",
      "tgn:7029392"
    ],
    "placetype": [
      "aat:300008697"
    ],
    "id": 2778084,
    "name:xx": "Wiregrass Spring"
  }
}
