{
  "geometry": {
    "type": "Point",
    "coordinates": [
      -109.6333,
      45.0667
    ]
  },
  "type": "Feature",
  "properties": {
    "hierarchy": [
      "tgn:1108778",
      "tgn:1000001",
      "tgn:7012149",
      "tgn:7029392"
    ],
    "placetype": [
      "aat:300008795"
    ],
    "id": 1108778,
    "name:xx": "Beartooth Mountains"
  }
}
