{
  "type": "FeatureCollection",
  "features": [
    {
      "geometry": {
        "type": "Point",
        "coordinates": [
          9.4375,
          39.1225
        ]
      },
      "type": "Feature",
      "properties": {
        "hierarchy": [
          "tgn:7058920",
          "tgn:1001641",
          "tgn:1000003",
          "tgn:7003121",
          "tgn:1000080",
          "tgn:7029392"
        ],
        "placetype": [
          "aat:300008850"
        ],
        "id": 7058920,
        "name:xx": "Boi, Capo"
      }
    },
    {
      "geometry": {
        "type": "Point",
        "coordinates": [
          9.216667,
          44.35
        ]
      },
      "type": "Feature",
      "properties": {
        "hierarchy": [
          "tgn:7058921",
          "tgn:1000003",
          "tgn:7003236",
          "tgn:1000080",
          "tgn:7029392"
        ],
        "placetype": [
          "aat:300008699"
        ],
        "id": 7058921,
        "name:xx": "Bogo, Rio"
      }
    },
    {
      "geometry": {
        "type": "Point",
        "coordinates": [
          8.2,
          46.116667
        ]
      },
      "type": "Feature",
      "properties": {
        "hierarchy": [
          "tgn:7058922",
          "tgn:1003478",
          "tgn:1000003",
          "tgn:7003120",
          "tgn:1000080",
          "tgn:7029392"
        ],
        "placetype": [
          "aat:300387198"
        ],
        "id": 7058922,
        "name:xx": "Bognanco"
      }
    },
    {
      "geometry": {
        "type": "Point",
        "coordinates": [
          8.3,
          46.133333
        ]
      },
      "type": "Feature",
      "properties": {
        "hierarchy": [
          "tgn:7058923",
          "tgn:1003478",
          "tgn:1000003",
          "tgn:7003120",
          "tgn:1000080",
          "tgn:7029392"
        ],
        "placetype": [
          "aat:300008699"
        ],
        "id": 7058923,
        "name:xx": "Bogna, Torrente"
      }
    },
    {
      "geometry": {
        "type": "Point",
        "coordinates": [
          11.8,
          45.916667
        ]
      },
      "type": "Feature",
      "properties": {
        "hierarchy": [
          "tgn:7058925",
          "tgn:7002991",
          "tgn:1000003",
          "tgn:7002997",
          "tgn:1000080",
          "tgn:7029392"
        ],
        "placetype": [
          "aat:300008347"
        ],
        "id": 7058925,
        "name:xx": "Boffat"
      }
    },
    {
      "geometry": {
        "type": "Point",
        "coordinates": [
          9.483333,
          45.35
        ]
      },
      "type": "Feature",
      "properties": {
        "hierarchy": [
          "tgn:7058927",
          "tgn:7003150",
          "tgn:1000003",
          "tgn:7003237",
          "tgn:1000080",
          "tgn:7029392"
        ],
        "placetype": [
          "aat:300008347"
        ],
        "id": 7058927,
        "name:xx": "Boffalora d'Adda"
      }
    },
    {
      "geometry": {
        "type": "Point",
        "coordinates": [
          9.166667,
          45.433333
        ]
      },
      "type": "Feature",
      "properties": {
        "hierarchy": [
          "tgn:7058928",
          "tgn:7003150",
          "tgn:1000003",
          "tgn:7003237",
          "tgn:1000080",
          "tgn:7029392"
        ],
        "placetype": [
          "aat:300008347"
        ],
        "id": 7058928,
        "name:xx": "Boffalora"
      }
    }
  ]
}
