{
  "geometry": {
    "type": "Point",
    "coordinates": [
      -90.3333,
      37.8833
    ]
  },
  "type": "Feature",
  "properties": {
    "hierarchy": [
      "tgn:2511957",
      "tgn:1000001",
      "tgn:7012149",
      "tgn:2001240",
      "tgn:7007523",
      "tgn:7029392"
    ],
    "placetype": [
      "aat:300008347"
    ],
    "id": 2511957,
    "name:xx": "Mill"
  }
}
