{
  "geometry": {
    "type": "Point",
    "coordinates": [
      -93.75,
      37.8333
    ]
  },
  "type": "Feature",
  "properties": {
    "hierarchy": [
      "tgn:2628460",
      "tgn:1000001",
      "tgn:7012149",
      "tgn:2001239",
      "tgn:7007523",
      "tgn:7029392"
    ],
    "placetype": [
      "aat:300008347"
    ],
    "id": 2628460,
    "name:xx": "Rookins"
  }
}
