{
  "geometry": {
    "type": "Point",
    "coordinates": [
      -54.75,
      48.95
    ]
  },
  "type": "Feature",
  "properties": {
    "hierarchy": [
      "tgn:1116366",
      "tgn:7005685",
      "tgn:7005807",
      "tgn:1000001",
      "tgn:7005801",
      "tgn:7029392"
    ],
    "placetype": [
      "aat:300008680"
    ],
    "id": 1116366,
    "name:xx": "Gander Lake"
  }
}
