{
  "type": "FeatureCollection",
  "features": [
    {
      "geometry": {
        "type": "Point",
        "coordinates": [
          -133.05,
          55.15
        ]
      },
      "type": "Feature",
      "properties": {
        "hierarchy": [
          "tgn:2193320",
          "tgn:7006450",
          "tgn:1000001",
          "tgn:7012149",
          "tgn:2000082",
          "tgn:7029392"
        ],
        "placetype": [
          "aat:300132316"
        ],
        "id": 2193320,
        "name:xx": "Breezy Bay"
      }
    },
    {
      "geometry": {
        "type": "Point",
        "coordinates": [
          -123.7667,
          42.55
        ]
      },
      "type": "Feature",
      "properties": {
        "hierarchy": [
          "tgn:2193321",
          "tgn:1000001",
          "tgn:7012149",
          "tgn:2001713",
          "tgn:7007708",
          "tgn:7029392"
        ],
        "placetype": [
          "aat:300008706"
        ],
        "id": 2193321,
        "name:xx": "Breezy Creek"
      }
    },
    {
      "geometry": {
        "type": "Point",
        "coordinates": [
          -72.9333,
          41.8667
        ]
      },
      "type": "Feature",
      "properties": {
        "hierarchy": [
          "tgn:2193323",
          "tgn:1000001",
          "tgn:1002461",
          "tgn:7012149",
          "tgn:7007159",
          "tgn:7029392"
        ],
        "placetype": [
          "aat:300008798"
        ],
        "id": 2193323,
        "name:xx": "Breezy Hill"
      }
    },
    {
      "geometry": {
        "type": "Point",
        "coordinates": [
          -94.65,
          37.5333
        ]
      },
      "type": "Feature",
      "properties": {
        "hierarchy": [
          "tgn:2193324",
          "tgn:1000001",
          "tgn:2000678",
          "tgn:7012149",
          "tgn:7007254",
          "tgn:7029392"
        ],
        "placetype": [
          "aat:300008798"
        ],
        "id": 2193324,
        "name:xx": "Breezy Hill"
      }
    },
    {
      "geometry": {
        "type": "Point",
        "coordinates": [
          -70.8333,
          42.0167
        ]
      },
      "type": "Feature",
      "properties": {
        "hierarchy": [
          "tgn:2193325",
          "tgn:1000001",
          "tgn:7014423",
          "tgn:7012149",
          "tgn:7007517",
          "tgn:7029392"
        ],
        "placetype": [
          "aat:300008347"
        ],
        "id": 2193325,
        "name:xx": "Breezy Hill"
      }
    },
    {
      "geometry": {
        "type": "Point",
        "coordinates": [
          -86.8667,
          35.8833
        ]
      },
      "type": "Feature",
      "properties": {
        "hierarchy": [
          "tgn:2193326",
          "tgn:1000001",
          "tgn:7012149",
          "tgn:2001930",
          "tgn:7007825",
          "tgn:7029392"
        ],
        "placetype": [
          "aat:300008798"
        ],
        "id": 2193326,
        "name:xx": "Breezy Hill"
      }
    },
    {
      "geometry": {
        "type": "Point",
        "coordinates": [
          -96.2833,
          32.7167
        ]
      },
      "type": "Feature",
      "properties": {
        "hierarchy": [
          "tgn:2193327",
          "tgn:1000001",
          "tgn:7012149",
          "tgn:1002535",
          "tgn:7007826",
          "tgn:7029392"
        ],
        "placetype": [
          "aat:300008798"
        ],
        "id": 2193327,
        "name:xx": "Breezy Hill"
      }
    },
    {
      "geometry": {
        "type": "Point",
        "coordinates": [
          -72.1667,
          44.8833
        ]
      },
      "type": "Feature",
      "properties": {
        "hierarchy": [
          "tgn:2193328",
          "tgn:1000001",
          "tgn:1002753",
          "tgn:7012149",
          "tgn:7007828",
          "tgn:7029392"
        ],
        "placetype": [
          "aat:300008798"
        ],
        "id": 2193328,
        "name:xx": "Breezy Hill"
      }
    },
    {
      "geometry": {
        "type": "Point",
        "coordinates": [
          -76.8,
          39.6667
        ]
      },
      "type": "Feature",
      "properties": {
        "hierarchy": [
          "tgn:2193329",
          "tgn:7016099",
          "tgn:1000001",
          "tgn:7012149",
          "tgn:7007516",
          "tgn:7029392"
        ],
        "placetype": [
          "aat:300008347"
        ],
        "id": 2193329,
        "name:xx": "Breezy Hill Estates"
      }
    }
  ]
}
