{
  "geometry": {
    "type": "Point",
    "coordinates": [
      -102.2333,
      39.7667
    ]
  },
  "type": "Feature",
  "properties": {
    "hierarchy": [
      "tgn:2417329",
      "tgn:1000001",
      "tgn:7012149",
      "tgn:7007158",
      "tgn:2000254",
      "tgn:7029392"
    ],
    "placetype": [
      "aat:300008761"
    ],
    "id": 2417329,
    "name:xx": "Jacks Gulch"
  }
}
