{
  "geometry": {
    "type": "Point",
    "coordinates": [
      -114.3167,
      62.5167
    ]
  },
  "type": "Feature",
  "properties": {
    "hierarchy": [
      "tgn:1132046",
      "tgn:7005685",
      "tgn:1000001",
      "tgn:1000296",
      "tgn:7029392"
    ],
    "placetype": [
      "aat:300008707"
    ],
    "id": 1132046,
    "name:xx": "Yellowknife"
  }
}
