{
  "geometry": {
    "type": "Point",
    "coordinates": [
      -91.8333,
      37.1833
    ]
  },
  "type": "Feature",
  "properties": {
    "hierarchy": [
      "tgn:2635981",
      "tgn:1000001",
      "tgn:7012149",
      "tgn:2001252",
      "tgn:7007523",
      "tgn:7029392"
    ],
    "placetype": [
      "aat:300008699"
    ],
    "id": 2635981,
    "name:xx": "Saddle Branch"
  }
}
