{
  "geometry": {
    "type": "Point",
    "coordinates": [
      -72.5167,
      44.5333
    ]
  },
  "type": "Feature",
  "properties": {
    "hierarchy": [
      "tgn:2109751",
      "tgn:1000001",
      "tgn:2002133",
      "tgn:7012149",
      "tgn:7007828",
      "tgn:7029392"
    ],
    "placetype": [
      "aat:300008347"
    ],
    "id": 2109751,
    "name:xx": "Lake Elmore"
  }
}
