{
  "type": "FeatureCollection",
  "features": [
    {
      "geometry": {
        "type": "Point",
        "coordinates": [
          31.678428,
          30.580653
        ]
      },
      "type": "Feature",
      "properties": {
        "hierarchy": [
          "tgn:7525300",
          "tgn:7001242",
          "tgn:7016833",
          "tgn:1001113",
          "tgn:7029392"
        ],
        "placetype": [
          "aat:300008347"
        ],
        "id": 7525300,
        "name:xx": "'Izbat al Jamāyilah"
      }
    },
    {
      "geometry": {
        "type": "Point",
        "coordinates": [
          30.424444,
          31.047778
        ]
      },
      "type": "Feature",
      "properties": {
        "hierarchy": [
          "tgn:7525301",
          "tgn:7001242",
          "tgn:1001075",
          "tgn:7016833",
          "tgn:7029392"
        ],
        "placetype": [
          "aat:300008347"
        ],
        "name:en": "'Ezbet el-Gamâmîza",
        "id": 7525301
      }
    },
    {
      "geometry": {
        "type": "Point",
        "coordinates": [
          31.192412,
          31.151944
        ]
      },
      "type": "Feature",
      "properties": {
        "hierarchy": [
          "tgn:7525302",
          "tgn:7001242",
          "tgn:7016833",
          "tgn:1001335",
          "tgn:7029392"
        ],
        "placetype": [
          "aat:300008347"
        ],
        "name:en": "'Ezbet el-Gamal",
        "id": 7525302
      }
    },
    {
      "geometry": {
        "type": "Point",
        "coordinates": [
          31.316667,
          31.266667
        ]
      },
      "type": "Feature",
      "properties": {
        "hierarchy": [
          "tgn:7525303",
          "tgn:7001242",
          "tgn:1001059",
          "tgn:7016833",
          "tgn:7029392"
        ],
        "placetype": [
          "aat:300008347"
        ],
        "name:en": "'Ezbet el-Gâhari",
        "id": 7525303
      }
    },
    {
      "geometry": {
        "type": "Point",
        "coordinates": [
          30.852659,
          30.343208
        ]
      },
      "type": "Feature",
      "properties": {
        "hierarchy": [
          "tgn:7525306",
          "tgn:7001242",
          "tgn:7016833",
          "tgn:1001087",
          "tgn:7029392"
        ],
        "placetype": [
          "aat:300008347"
        ],
        "name:en": "Dalhamū",
        "id": 7525306
      }
    },
    {
      "geometry": {
        "type": "Point",
        "coordinates": [
          33.087222,
          29.710556
        ]
      },
      "type": "Feature",
      "properties": {
        "hierarchy": [
          "tgn:7525307",
          "tgn:7001242",
          "tgn:7016833",
          "tgn:7001336",
          "tgn:7029392"
        ],
        "placetype": [
          "aat:300008697"
        ],
        "id": 7525307,
        "name:xx": "Dalbahīyah, 'Ayn ad"
      }
    },
    {
      "geometry": {
        "type": "Point",
        "coordinates": [
          31.134322,
          29.185874
        ]
      },
      "type": "Feature",
      "properties": {
        "hierarchy": [
          "tgn:7525308",
          "tgn:7001242",
          "tgn:7001105",
          "tgn:7016833",
          "tgn:7029392"
        ],
        "placetype": [
          "aat:300008347"
        ],
        "name:en": "Dalāş",
        "id": 7525308
      }
    },
    {
      "geometry": {
        "type": "Point",
        "coordinates": [
          34.034266,
          24.878445
        ]
      },
      "type": "Feature",
      "properties": {
        "hierarchy": [
          "tgn:7525309",
          "tgn:7001242",
          "tgn:7001311",
          "tgn:7016833",
          "tgn:7029392"
        ],
        "placetype": [
          "aat:300379998"
        ],
        "name:en": "Dalâlîl, Wâdî",
        "id": 7525309
      }
    }
  ]
}
