{
  "geometry": {
    "type": "Point",
    "coordinates": [
      -47.4667,
      -21.85
    ]
  },
  "type": "Feature",
  "properties": {
    "hierarchy": [
      "tgn:1022562",
      "tgn:1001945",
      "tgn:1000047",
      "tgn:7002457",
      "tgn:1000002",
      "tgn:7029392"
    ],
    "placetype": [
      "aat:300008347"
    ],
    "id": 1022562,
    "name:xx": "Porto Ferreira"
  }
}
