{
  "geometry": {
    "type": "Point",
    "coordinates": [
      17.3333,
      48.15
    ]
  },
  "type": "Feature",
  "properties": {
    "hierarchy": [
      "tgn:1027593",
      "tgn:7027126",
      "tgn:1000003",
      "tgn:7011765",
      "tgn:7029392"
    ],
    "placetype": [
      "aat:300008347"
    ],
    "id": 1027593,
    "name:xx": "Tomášov"
  }
}
