{
  "geometry": {
    "type": "Point",
    "coordinates": [
      -83.7167,
      35.4167
    ]
  },
  "type": "Feature",
  "properties": {
    "hierarchy": [
      "tgn:2784799",
      "tgn:1000001",
      "tgn:7012149",
      "tgn:2001497",
      "tgn:7007709",
      "tgn:7029392"
    ],
    "placetype": [
      "aat:300008699"
    ],
    "id": 2784799,
    "name:xx": "Yellow Branch"
  }
}
