{
  "geometry": {
    "type": "Point",
    "coordinates": [
      -107.1833,
      41.0167
    ]
  },
  "type": "Feature",
  "properties": {
    "hierarchy": [
      "tgn:2621072",
      "tgn:1000001",
      "tgn:2002368",
      "tgn:7012149",
      "tgn:7007923",
      "tgn:7029392"
    ],
    "placetype": [
      "aat:300008761"
    ],
    "id": 2621072,
    "name:xx": "Road Gulch"
  }
}
