{
  "geometry": {
    "type": "Point",
    "coordinates": [
      14.35,
      53.433333
    ]
  },
  "type": "Feature",
  "properties": {
    "hierarchy": [
      "tgn:7193329",
      "tgn:1000003",
      "tgn:7000094",
      "tgn:7000084",
      "tgn:7029392"
    ],
    "placetype": [
      "aat:300004792"
    ],
    "id": 7193329,
    "name:xx": "Försterei Flattenwerder"
  }
}
