{
  "geometry": {
    "type": "Point",
    "coordinates": [
      -146.8667,
      60.8333
    ]
  },
  "type": "Feature",
  "properties": {
    "hierarchy": [
      "tgn:2179940",
      "tgn:7006450",
      "tgn:1000001",
      "tgn:7012149",
      "tgn:2000086",
      "tgn:7029392"
    ],
    "placetype": [
      "aat:300132348"
    ],
    "id": 2179940,
    "name:xx": "Bligh Reef"
  }
}
