{
  "geometry": {
    "type": "Point",
    "coordinates": [
      -87.9833,
      31.9667
    ]
  },
  "type": "Feature",
  "properties": {
    "hierarchy": [
      "tgn:2784787",
      "tgn:7002659",
      "tgn:1000001",
      "tgn:2000012",
      "tgn:7012149",
      "tgn:7029392"
    ],
    "placetype": [
      "aat:300008699"
    ],
    "id": 2784787,
    "name:xx": "Yellow Branch"
  }
}
