{
  "geometry": {
    "type": "Point",
    "coordinates": [
      -77.8833,
      40.5333
    ]
  },
  "type": "Feature",
  "properties": {
    "hierarchy": [
      "tgn:2142157",
      "tgn:1000001",
      "tgn:7012149",
      "tgn:1002494",
      "tgn:7007710",
      "tgn:7029392"
    ],
    "placetype": [
      "aat:300008761"
    ],
    "id": 2142157,
    "name:xx": "Back Hollow"
  }
}
