{
  "geometry": {
    "type": "Point",
    "coordinates": [
      -99.3833,
      43.8833
    ]
  },
  "type": "Feature",
  "properties": {
    "hierarchy": [
      "tgn:2592139",
      "tgn:1000001",
      "tgn:2001812",
      "tgn:7012149",
      "tgn:7007713",
      "tgn:7029392"
    ],
    "placetype": [
      "aat:300008706"
    ],
    "id": 2592139,
    "name:xx": "Pontoon Creek"
  }
}
