{
  "geometry": {
    "type": "Point",
    "coordinates": [
      -85.8667,
      44.7667
    ]
  },
  "type": "Feature",
  "properties": {
    "hierarchy": [
      "tgn:2401733",
      "tgn:1000001",
      "tgn:2000949",
      "tgn:7012149",
      "tgn:7007520",
      "tgn:7029392"
    ],
    "placetype": [
      "aat:300008680"
    ],
    "id": 2401733,
    "name:xx": "Horseshoe Lake"
  }
}
