{
  "geometry": {
    "type": "Point",
    "coordinates": [
      79.9411,
      27.0646
    ]
  },
  "type": "Feature",
  "properties": {
    "hierarchy": [
      "tgn:7563283",
      "tgn:1000004",
      "tgn:7000198",
      "tgn:7016722",
      "tgn:7029392"
    ],
    "placetype": [
      "aat:300008347"
    ],
    "name:en": "Daryāpur Chandai",
    "id": 7563283
  }
}
