{
  "geometry": {
    "type": "Point",
    "coordinates": [
      -108.8667,
      38.25
    ]
  },
  "type": "Feature",
  "properties": {
    "hierarchy": [
      "tgn:2666948",
      "tgn:1000001",
      "tgn:7012149",
      "tgn:2000234",
      "tgn:7007158",
      "tgn:7029392"
    ],
    "placetype": [
      "aat:300008798"
    ],
    "id": 2666948,
    "name:xx": "Skein Mesa"
  }
}
