{
  "geometry": {
    "type": "Point",
    "coordinates": [
      -123.5833,
      44.5167
    ]
  },
  "type": "Feature",
  "properties": {
    "hierarchy": [
      "tgn:2701520",
      "tgn:1000001",
      "tgn:7012149",
      "tgn:7007708",
      "tgn:7029392"
    ],
    "placetype": [
      "aat:300008706"
    ],
    "id": 2701520,
    "name:xx": "Sugarbowl Creek"
  }
}
