{
  "type": "FeatureCollection",
  "features": [
    {
      "geometry": {
        "type": "Point",
        "coordinates": [
          4.85,
          52.766667
        ]
      },
      "type": "Feature",
      "properties": {
        "hierarchy": [
          "tgn:7269930",
          "tgn:1000003",
          "tgn:7006951",
          "tgn:7016845",
          "tgn:7029392"
        ],
        "placetype": [
          "aat:300006163"
        ],
        "name:nl": "Moerbeekerpolder",
        "id": 7269930
      }
    },
    {
      "geometry": {
        "type": "Point",
        "coordinates": [
          4.85,
          52.766667
        ]
      },
      "type": "Feature",
      "properties": {
        "hierarchy": [
          "tgn:7269931",
          "tgn:1000003",
          "tgn:7006951",
          "tgn:7016845",
          "tgn:7029392"
        ],
        "placetype": [
          "aat:300008347"
        ],
        "name:nl": "Moerbeek",
        "id": 7269931
      }
    },
    {
      "geometry": {
        "type": "Point",
        "coordinates": [
          5.866667,
          53.166667
        ]
      },
      "type": "Feature",
      "properties": {
        "hierarchy": [
          "tgn:7269932",
          "tgn:7003616",
          "tgn:1000003",
          "tgn:7016845",
          "tgn:7029392"
        ],
        "placetype": [
          "aat:300387200"
        ],
        "name:nl": "Moenslanden",
        "id": 7269932
      }
    },
    {
      "geometry": {
        "type": "Point",
        "coordinates": [
          5.116667,
          52.45
        ]
      },
      "type": "Feature",
      "properties": {
        "hierarchy": [
          "tgn:7269933",
          "tgn:1000003",
          "tgn:7006951",
          "tgn:7016845",
          "tgn:7029392"
        ],
        "placetype": [
          "aat:300008347"
        ],
        "name:nl": "Moeniswerf",
        "id": 7269933
      }
    },
    {
      "geometry": {
        "type": "Point",
        "coordinates": [
          7.116667,
          53.2
        ]
      },
      "type": "Feature",
      "properties": {
        "hierarchy": [
          "tgn:7269934",
          "tgn:1000003",
          "tgn:7003613",
          "tgn:7016845",
          "tgn:7029392"
        ],
        "placetype": [
          "aat:300387200"
        ],
        "name:nl": "Modderland",
        "id": 7269934
      }
    },
    {
      "geometry": {
        "type": "Point",
        "coordinates": [
          6.15,
          53.1
        ]
      },
      "type": "Feature",
      "properties": {
        "hierarchy": [
          "tgn:7269935",
          "tgn:7003616",
          "tgn:1000003",
          "tgn:7016845",
          "tgn:7029392"
        ],
        "placetype": [
          "aat:300006075"
        ],
        "name:nl": "Modderikswijk",
        "id": 7269935
      }
    },
    {
      "geometry": {
        "type": "Point",
        "coordinates": [
          6,
          52.733333
        ]
      },
      "type": "Feature",
      "properties": {
        "hierarchy": [
          "tgn:7269936",
          "tgn:1000003",
          "tgn:7003626",
          "tgn:7016845",
          "tgn:7029392"
        ],
        "placetype": [
          "aat:300387055"
        ],
        "name:nl": "Moddergat",
        "id": 7269936
      }
    },
    {
      "geometry": {
        "type": "Point",
        "coordinates": [
          6.083333,
          53.4
        ]
      },
      "type": "Feature",
      "properties": {
        "hierarchy": [
          "tgn:7269937",
          "tgn:7003616",
          "tgn:1000003",
          "tgn:7016845",
          "tgn:7029392"
        ],
        "placetype": [
          "aat:300008347"
        ],
        "name:nl": "Moddergat",
        "id": 7269937
      }
    },
    {
      "geometry": {
        "type": "Point",
        "coordinates": [
          6.45,
          52.8
        ]
      },
      "type": "Feature",
      "properties": {
        "hierarchy": [
          "tgn:7269938",
          "tgn:7003614",
          "tgn:1000003",
          "tgn:7016845",
          "tgn:7029392"
        ],
        "placetype": [
          "aat:300008688"
        ],
        "name:nl": "Moddergat",
        "id": 7269938
      }
    },
    {
      "geometry": {
        "type": "Point",
        "coordinates": [
          5.633333,
          53.233333
        ]
      },
      "type": "Feature",
      "properties": {
        "hierarchy": [
          "tgn:7269939",
          "tgn:7003616",
          "tgn:1000003",
          "tgn:7016845",
          "tgn:7029392"
        ],
        "placetype": [
          "aat:300006075"
        ],
        "name:nl": "Moddergat",
        "id": 7269939
      }
    }
  ]
}
