{
  "type": "FeatureCollection",
  "features": [
    {
      "geometry": {
        "type": "Point",
        "coordinates": [
          -75.0667,
          40.45
        ]
      },
      "type": "Feature",
      "properties": {
        "hierarchy": [
          "tgn:2672260",
          "tgn:1000001",
          "tgn:1002213",
          "tgn:7012149",
          "tgn:7007710",
          "tgn:7029392"
        ],
        "placetype": [
          "aat:300008706"
        ],
        "id": 2672260,
        "name:xx": "Smithtown Creek"
      }
    },
    {
      "geometry": {
        "type": "Point",
        "coordinates": [
          -93.8667,
          33.05
        ]
      },
      "type": "Feature",
      "properties": {
        "hierarchy": [
          "tgn:2672261",
          "tgn:1000001",
          "tgn:7016172",
          "tgn:7012149",
          "tgn:2000150",
          "tgn:7029392"
        ],
        "placetype": [
          "aat:300008347"
        ],
        "id": 2672261,
        "name:xx": "Smithville"
      }
    },
    {
      "geometry": {
        "type": "Point",
        "coordinates": [
          -92.5667,
          33.2167
        ]
      },
      "type": "Feature",
      "properties": {
        "hierarchy": [
          "tgn:2672262",
          "tgn:1000001",
          "tgn:7016172",
          "tgn:7012149",
          "tgn:2000174",
          "tgn:7029392"
        ],
        "placetype": [
          "aat:300008347"
        ],
        "id": 2672262,
        "name:xx": "Smithville"
      }
    },
    {
      "geometry": {
        "type": "Point",
        "coordinates": [
          -90.55,
          35.9167
        ]
      },
      "type": "Feature",
      "properties": {
        "hierarchy": [
          "tgn:2672263",
          "tgn:1000001",
          "tgn:7016172",
          "tgn:2000120",
          "tgn:7012149",
          "tgn:7029392"
        ],
        "placetype": [
          "aat:300008347"
        ],
        "id": 2672263,
        "name:xx": "Smithville"
      }
    },
    {
      "geometry": {
        "type": "Point",
        "coordinates": [
          -87.0167,
          39.3167
        ]
      },
      "type": "Feature",
      "properties": {
        "hierarchy": [
          "tgn:2672264",
          "tgn:1000001",
          "tgn:7012149",
          "tgn:2000548",
          "tgn:7007252",
          "tgn:7029392"
        ],
        "placetype": [
          "aat:300008347"
        ],
        "id": 2672264,
        "name:xx": "Smithville"
      }
    },
    {
      "geometry": {
        "type": "Point",
        "coordinates": [
          -85.5,
          38
        ]
      },
      "type": "Feature",
      "properties": {
        "hierarchy": [
          "tgn:2672265",
          "tgn:1000001",
          "tgn:2000774",
          "tgn:7012149",
          "tgn:7007255",
          "tgn:7029392"
        ],
        "placetype": [
          "aat:300008347"
        ],
        "id": 2672265,
        "name:xx": "Smithville"
      }
    },
    {
      "geometry": {
        "type": "Point",
        "coordinates": [
          -76.1,
          39.2833
        ]
      },
      "type": "Feature",
      "properties": {
        "hierarchy": [
          "tgn:2672266",
          "tgn:1000001",
          "tgn:1002539",
          "tgn:7012149",
          "tgn:7007516",
          "tgn:7029392"
        ],
        "placetype": [
          "aat:300008347"
        ],
        "id": 2672266,
        "name:xx": "Smithville"
      }
    },
    {
      "geometry": {
        "type": "Point",
        "coordinates": [
          -72.05,
          42.3833
        ]
      },
      "type": "Feature",
      "properties": {
        "hierarchy": [
          "tgn:2672267",
          "tgn:1000001",
          "tgn:7012149",
          "tgn:1003038",
          "tgn:7007517",
          "tgn:7029392"
        ],
        "placetype": [
          "aat:300008347"
        ],
        "id": 2672267,
        "name:xx": "Smithville"
      }
    },
    {
      "geometry": {
        "type": "Point",
        "coordinates": [
          -85.1667,
          44.5167
        ]
      },
      "type": "Feature",
      "properties": {
        "hierarchy": [
          "tgn:2672268",
          "tgn:1000001",
          "tgn:7012149",
          "tgn:2000968",
          "tgn:7007520",
          "tgn:7029392"
        ],
        "placetype": [
          "aat:300008347"
        ],
        "id": 2672268,
        "name:xx": "Smithville"
      }
    },
    {
      "geometry": {
        "type": "Point",
        "coordinates": [
          -80.8667,
          35.4833
        ]
      },
      "type": "Feature",
      "properties": {
        "hierarchy": [
          "tgn:2672269",
          "tgn:1000001",
          "tgn:7012149",
          "tgn:7014021",
          "tgn:7007709",
          "tgn:7029392"
        ],
        "placetype": [
          "aat:300008347"
        ],
        "id": 2672269,
        "name:xx": "Smithville"
      }
    }
  ]
}
