{
  "geometry": {
    "type": "Point",
    "coordinates": [
      -81.0667,
      28.75
    ]
  },
  "type": "Feature",
  "properties": {
    "hierarchy": [
      "tgn:2346391",
      "tgn:1000001",
      "tgn:7012149",
      "tgn:1002881",
      "tgn:7007240",
      "tgn:7029392"
    ],
    "placetype": [
      "aat:300008850"
    ],
    "id": 2346391,
    "name:xx": "Gator Point"
  }
}
