{
  "geometry": {
    "type": "Point",
    "coordinates": [
      -121.05,
      47.3167
    ]
  },
  "type": "Feature",
  "properties": {
    "hierarchy": [
      "tgn:2257676",
      "tgn:1000001",
      "tgn:7012149",
      "tgn:1002553",
      "tgn:7007920",
      "tgn:7029392"
    ],
    "placetype": [
      "aat:300008706"
    ],
    "id": 2257676,
    "name:xx": "Corral Creek"
  }
}
