{
  "geometry": {
    "type": "Point",
    "coordinates": [
      -90.2333,
      37.9833
    ]
  },
  "type": "Feature",
  "properties": {
    "hierarchy": [
      "tgn:2581096",
      "tgn:1000001",
      "tgn:7012149",
      "tgn:2001240",
      "tgn:7007523",
      "tgn:7029392"
    ],
    "placetype": [
      "aat:300008798"
    ],
    "id": 2581096,
    "name:xx": "Pikes Peak"
  }
}
