{
  "geometry": {
    "type": "Point",
    "coordinates": [
      3.55,
      50.35
    ]
  },
  "type": "Feature",
  "properties": {
    "hierarchy": [
      "tgn:1034277",
      "tgn:1000003",
      "tgn:7001097",
      "tgn:1000070",
      "tgn:7029392"
    ],
    "placetype": [
      "aat:300008347"
    ],
    "id": 1034277,
    "name:xx": "Marly"
  }
}
