{
  "geometry": {
    "type": "Point",
    "coordinates": [
      -98.5167,
      31.1667
    ]
  },
  "type": "Feature",
  "properties": {
    "hierarchy": [
      "tgn:2733439",
      "tgn:1000001",
      "tgn:7012149",
      "tgn:2002069",
      "tgn:7007826",
      "tgn:7029392"
    ],
    "placetype": [
      "aat:300386845"
    ],
    "id": 2733439,
    "name:xx": "Turkey Valley"
  }
}
