{
  "geometry": {
    "type": "Point",
    "coordinates": [
      -147.65,
      60.4833
    ]
  },
  "type": "Feature",
  "properties": {
    "hierarchy": [
      "tgn:2288508",
      "tgn:7006450",
      "tgn:1000001",
      "tgn:7012149",
      "tgn:2000086",
      "tgn:7029392"
    ],
    "placetype": [
      "aat:300008791"
    ],
    "id": 2288508,
    "name:xx": "Disk Island"
  }
}
