{
  "type": "FeatureCollection",
  "features": [
    {
      "geometry": {
        "type": "Point",
        "coordinates": [
          -118.05,
          45.8667
        ]
      },
      "type": "Feature",
      "properties": {
        "hierarchy": [
          "tgn:2709410",
          "tgn:1000001",
          "tgn:7012149",
          "tgn:2001720",
          "tgn:7007708",
          "tgn:7029392"
        ],
        "placetype": [
          "aat:300008697"
        ],
        "id": 2709410,
        "name:xx": "Table Spring"
      }
    },
    {
      "geometry": {
        "type": "Point",
        "coordinates": [
          -118.35,
          48.9333
        ]
      },
      "type": "Feature",
      "properties": {
        "hierarchy": [
          "tgn:2709411",
          "tgn:1000001",
          "tgn:2002243",
          "tgn:7012149",
          "tgn:7007920",
          "tgn:7029392"
        ],
        "placetype": [
          "aat:300008697"
        ],
        "id": 2709411,
        "name:xx": "Table Spring"
      }
    },
    {
      "geometry": {
        "type": "Point",
        "coordinates": [
          -151.0333,
          68.6167
        ]
      },
      "type": "Feature",
      "properties": {
        "hierarchy": [
          "tgn:2709412",
          "tgn:7006450",
          "tgn:1000001",
          "tgn:7012149",
          "tgn:2124005",
          "tgn:7029392"
        ],
        "placetype": [
          "aat:300008798"
        ],
        "id": 2709412,
        "name:xx": "Table Top"
      }
    },
    {
      "geometry": {
        "type": "Point",
        "coordinates": [
          -109.1667,
          33.2167
        ]
      },
      "type": "Feature",
      "properties": {
        "hierarchy": [
          "tgn:2709413",
          "tgn:1000001",
          "tgn:7006451",
          "tgn:2000095",
          "tgn:7012149",
          "tgn:7029392"
        ],
        "placetype": [
          "aat:300008798"
        ],
        "id": 2709413,
        "name:xx": "Table Top"
      }
    },
    {
      "geometry": {
        "type": "Point",
        "coordinates": [
          -111.3,
          34.15
        ]
      },
      "type": "Feature",
      "properties": {
        "hierarchy": [
          "tgn:2709414",
          "tgn:1000001",
          "tgn:7006451",
          "tgn:2000093",
          "tgn:7012149",
          "tgn:7029392"
        ],
        "placetype": [
          "aat:300008798"
        ],
        "id": 2709414,
        "name:xx": "Table Top"
      }
    },
    {
      "geometry": {
        "type": "Point",
        "coordinates": [
          -106.6833,
          38.3833
        ]
      },
      "type": "Feature",
      "properties": {
        "hierarchy": [
          "tgn:2709415",
          "tgn:1000001",
          "tgn:7012149",
          "tgn:7007158",
          "tgn:2000246",
          "tgn:7029392"
        ],
        "placetype": [
          "aat:300008798"
        ],
        "id": 2709415,
        "name:xx": "Table Top"
      }
    },
    {
      "geometry": {
        "type": "Point",
        "coordinates": [
          -107.5833,
          47.5833
        ]
      },
      "type": "Feature",
      "properties": {
        "hierarchy": [
          "tgn:2709416",
          "tgn:1000001",
          "tgn:7012149",
          "tgn:2001276",
          "tgn:7007524",
          "tgn:7029392"
        ],
        "placetype": [
          "aat:300008798"
        ],
        "id": 2709416,
        "name:xx": "Table Top"
      }
    },
    {
      "geometry": {
        "type": "Point",
        "coordinates": [
          -108.95,
          33.2167
        ]
      },
      "type": "Feature",
      "properties": {
        "hierarchy": [
          "tgn:2709417",
          "tgn:1000001",
          "tgn:2001429",
          "tgn:7012149",
          "tgn:7007566",
          "tgn:7029392"
        ],
        "placetype": [
          "aat:300008798"
        ],
        "id": 2709417,
        "name:xx": "Table Top"
      }
    },
    {
      "geometry": {
        "type": "Point",
        "coordinates": [
          -105.8333,
          32.65
        ]
      },
      "type": "Feature",
      "properties": {
        "hierarchy": [
          "tgn:2709418",
          "tgn:1000001",
          "tgn:7012149",
          "tgn:2001447",
          "tgn:7007566",
          "tgn:7029392"
        ],
        "placetype": [
          "aat:300008798"
        ],
        "id": 2709418,
        "name:xx": "Table Top"
      }
    },
    {
      "geometry": {
        "type": "Point",
        "coordinates": [
          -118.0167,
          43.6667
        ]
      },
      "type": "Feature",
      "properties": {
        "hierarchy": [
          "tgn:2709419",
          "tgn:1000001",
          "tgn:7012149",
          "tgn:2001718",
          "tgn:7007708",
          "tgn:7029392"
        ],
        "placetype": [
          "aat:300008798"
        ],
        "id": 2709419,
        "name:xx": "Table Top"
      }
    }
  ]
}
