{
  "type": "FeatureCollection",
  "features": [
    {
      "geometry": {
        "type": "Point",
        "coordinates": [
          -114.1,
          47.7
        ]
      },
      "type": "Feature",
      "properties": {
        "hierarchy": [
          "tgn:2173990",
          "tgn:1000001",
          "tgn:7012149",
          "tgn:2001283",
          "tgn:7007524",
          "tgn:7029392"
        ],
        "placetype": [
          "aat:300008850"
        ],
        "id": 2173990,
        "name:xx": "Bird Point"
      }
    },
    {
      "geometry": {
        "type": "Point",
        "coordinates": [
          -123.9833,
          45.9333
        ]
      },
      "type": "Feature",
      "properties": {
        "hierarchy": [
          "tgn:2173991",
          "tgn:1000001",
          "tgn:1002276",
          "tgn:7012149",
          "tgn:7007708",
          "tgn:7029392"
        ],
        "placetype": [
          "aat:300008850"
        ],
        "id": 2173991,
        "name:xx": "Bird Point"
      }
    },
    {
      "geometry": {
        "type": "Point",
        "coordinates": [
          -96.95,
          28.1167
        ]
      },
      "type": "Feature",
      "properties": {
        "hierarchy": [
          "tgn:2173992",
          "tgn:7013313",
          "tgn:1000001",
          "tgn:7012149",
          "tgn:7007826",
          "tgn:7029392"
        ],
        "placetype": [
          "aat:300008850"
        ],
        "id": 2173992,
        "name:xx": "Bird Point"
      }
    },
    {
      "geometry": {
        "type": "Point",
        "coordinates": [
          -73.2167,
          41.6333
        ]
      },
      "type": "Feature",
      "properties": {
        "hierarchy": [
          "tgn:2173993",
          "tgn:1000001",
          "tgn:1002601",
          "tgn:7012149",
          "tgn:7007159",
          "tgn:7029392"
        ],
        "placetype": [
          "aat:300006191"
        ],
        "id": 2173993,
        "name:xx": "Bird Pond"
      }
    },
    {
      "geometry": {
        "type": "Point",
        "coordinates": [
          -82.3333,
          29.1833
        ]
      },
      "type": "Feature",
      "properties": {
        "hierarchy": [
          "tgn:2173994",
          "tgn:1000001",
          "tgn:7012149",
          "tgn:1002631",
          "tgn:7007240",
          "tgn:7029392"
        ],
        "placetype": [
          "aat:300008680"
        ],
        "id": 2173994,
        "name:xx": "Bird Pond"
      }
    },
    {
      "geometry": {
        "type": "Point",
        "coordinates": [
          -82.75,
          29.7167
        ]
      },
      "type": "Feature",
      "properties": {
        "hierarchy": [
          "tgn:2173995",
          "tgn:1000001",
          "tgn:2000269",
          "tgn:7012149",
          "tgn:7007240",
          "tgn:7029392"
        ],
        "placetype": [
          "aat:300008680"
        ],
        "id": 2173995,
        "name:xx": "Bird Pond"
      }
    },
    {
      "geometry": {
        "type": "Point",
        "coordinates": [
          -83.15,
          29.9333
        ]
      },
      "type": "Feature",
      "properties": {
        "hierarchy": [
          "tgn:2173996",
          "tgn:1000001",
          "tgn:2000275",
          "tgn:7012149",
          "tgn:7007240",
          "tgn:7029392"
        ],
        "placetype": [
          "aat:300008680"
        ],
        "id": 2173996,
        "name:xx": "Bird Pond"
      }
    },
    {
      "geometry": {
        "type": "Point",
        "coordinates": [
          -83.6167,
          29.9667
        ]
      },
      "type": "Feature",
      "properties": {
        "hierarchy": [
          "tgn:2173997",
          "tgn:1000001",
          "tgn:7012149",
          "tgn:2000287",
          "tgn:7007240",
          "tgn:7029392"
        ],
        "placetype": [
          "aat:300008680"
        ],
        "id": 2173997,
        "name:xx": "Bird Pond"
      }
    },
    {
      "geometry": {
        "type": "Point",
        "coordinates": [
          -85.1,
          30.5667
        ]
      },
      "type": "Feature",
      "properties": {
        "hierarchy": [
          "tgn:2173998",
          "tgn:1000001",
          "tgn:2000260",
          "tgn:7012149",
          "tgn:7007240",
          "tgn:7029392"
        ],
        "placetype": [
          "aat:300008680"
        ],
        "id": 2173998,
        "name:xx": "Bird Pond"
      }
    },
    {
      "geometry": {
        "type": "Point",
        "coordinates": [
          -82.65,
          30.3333
        ]
      },
      "type": "Feature",
      "properties": {
        "hierarchy": [
          "tgn:2173999",
          "tgn:1000001",
          "tgn:2000262",
          "tgn:7012149",
          "tgn:7007240",
          "tgn:7029392"
        ],
        "placetype": [
          "aat:300008905"
        ],
        "id": 2173999,
        "name:xx": "Bird Pond"
      }
    }
  ]
}
