{
  "geometry": {
    "type": "Point",
    "coordinates": [
      -157.8167,
      56.2833
    ]
  },
  "type": "Feature",
  "properties": {
    "hierarchy": [
      "tgn:2430419",
      "tgn:7006450",
      "tgn:1000001",
      "tgn:7030517",
      "tgn:7012149",
      "tgn:7029392"
    ],
    "placetype": [
      "aat:300008791"
    ],
    "id": 2430419,
    "name:xx": "Kak Island"
  }
}
