{
  "geometry": {
    "type": "Point",
    "coordinates": [
      -121.4333,
      45.6333
    ]
  },
  "type": "Feature",
  "properties": {
    "hierarchy": [
      "tgn:2411694",
      "tgn:1000001",
      "tgn:7012149",
      "tgn:2001710",
      "tgn:7007708",
      "tgn:7029392"
    ],
    "placetype": [
      "aat:300008680"
    ],
    "id": 2411694,
    "name:xx": "Indian Lake"
  }
}
