{
  "geometry": {
    "type": "Point",
    "coordinates": [
      -123.2833,
      45.8333
    ]
  },
  "type": "Feature",
  "properties": {
    "hierarchy": [
      "tgn:2755722",
      "tgn:1000001",
      "tgn:1002293",
      "tgn:7012149",
      "tgn:7007708",
      "tgn:7029392"
    ],
    "placetype": [
      "aat:300008706"
    ],
    "id": 2755722,
    "name:xx": "Weed Creek"
  }
}
