{
  "geometry": {
    "type": "Point",
    "coordinates": [
      -85.95,
      30.3667
    ]
  },
  "type": "Feature",
  "properties": {
    "hierarchy": [
      "tgn:2189444",
      "tgn:2000258",
      "tgn:1000001",
      "tgn:7012149",
      "tgn:7007240",
      "tgn:7029392"
    ],
    "placetype": [
      "aat:300008699"
    ],
    "id": 2189444,
    "name:xx": "Boutwell Branch"
  }
}
