{
  "geometry": {
    "type": "Point",
    "coordinates": [
      -91.4167,
      17.75
    ]
  },
  "type": "Feature",
  "properties": {
    "hierarchy": [
      "tgn:1129591",
      "tgn:1000001",
      "tgn:7029392"
    ],
    "placetype": [
      "aat:300008707"
    ],
    "id": 1129591,
    "name:xx": "San Pedro"
  }
}
