{
  "geometry": {
    "type": "Point",
    "coordinates": [
      -103.5667,
      32.2333
    ]
  },
  "type": "Feature",
  "properties": {
    "hierarchy": [
      "tgn:2161298",
      "tgn:1000001",
      "tgn:7012149",
      "tgn:2001441",
      "tgn:7007566",
      "tgn:7029392"
    ],
    "placetype": [
      "aat:300008680"
    ],
    "id": 2161298,
    "name:xx": "Bell Lake"
  }
}
