{
  "type": "FeatureCollection",
  "features": [
    {
      "geometry": {
        "type": "Point",
        "coordinates": [
          -113.3333,
          48.4
        ]
      },
      "type": "Feature",
      "properties": {
        "hierarchy": [
          "tgn:2510910",
          "tgn:1000001",
          "tgn:7012149",
          "tgn:2001277",
          "tgn:7007524",
          "tgn:7029392"
        ],
        "placetype": [
          "aat:300008706"
        ],
        "id": 2510910,
        "name:xx": "Midvale Creek"
      }
    },
    {
      "geometry": {
        "type": "Point",
        "coordinates": [
          -116.8,
          44.4333
        ]
      },
      "type": "Feature",
      "properties": {
        "hierarchy": [
          "tgn:2510911",
          "tgn:1000001",
          "tgn:7012149",
          "tgn:2000495",
          "tgn:7007250",
          "tgn:7029392"
        ],
        "placetype": [
          "aat:300008798"
        ],
        "id": 2510911,
        "name:xx": "Midvale Hill"
      }
    },
    {
      "geometry": {
        "type": "Point",
        "coordinates": [
          -111.85,
          40.6
        ]
      },
      "type": "Feature",
      "properties": {
        "hierarchy": [
          "tgn:2510912",
          "tgn:1000001",
          "tgn:7012149",
          "tgn:2002118",
          "tgn:7007827",
          "tgn:7029392"
        ],
        "placetype": [
          "aat:300008347"
        ],
        "id": 2510912,
        "name:xx": "Midvale Terrace"
      }
    },
    {
      "geometry": {
        "type": "Point",
        "coordinates": [
          -75.6,
          39.65
        ]
      },
      "type": "Feature",
      "properties": {
        "hierarchy": [
          "tgn:2510913",
          "tgn:7014201",
          "tgn:1000001",
          "tgn:7012149",
          "tgn:7007239",
          "tgn:7029392"
        ],
        "placetype": [
          "aat:300008347"
        ],
        "id": 2510913,
        "name:xx": "Midvalf"
      }
    },
    {
      "geometry": {
        "type": "Point",
        "coordinates": [
          -119.3833,
          36.2833
        ]
      },
      "type": "Feature",
      "properties": {
        "hierarchy": [
          "tgn:2510914",
          "tgn:1000001",
          "tgn:7012149",
          "tgn:7007157",
          "tgn:1002956",
          "tgn:7029392"
        ],
        "placetype": [
          "aat:300008347"
        ],
        "id": 2510914,
        "name:xx": "Midvalley"
      }
    },
    {
      "geometry": {
        "type": "Point",
        "coordinates": [
          -111.8833,
          40.6
        ]
      },
      "type": "Feature",
      "properties": {
        "hierarchy": [
          "tgn:2510915",
          "tgn:1000001",
          "tgn:7012149",
          "tgn:2002118",
          "tgn:7007827",
          "tgn:7029392"
        ],
        "placetype": [
          "aat:300008347"
        ],
        "id": 2510915,
        "name:xx": "Midvalley"
      }
    },
    {
      "geometry": {
        "type": "Point",
        "coordinates": [
          -111.8667,
          40.6
        ]
      },
      "type": "Feature",
      "properties": {
        "hierarchy": [
          "tgn:2510916",
          "tgn:1000001",
          "tgn:7012149",
          "tgn:2002118",
          "tgn:7007827",
          "tgn:7029392"
        ],
        "placetype": [
          "aat:300008347"
        ],
        "id": 2510916,
        "name:xx": "Midvalley Estates"
      }
    },
    {
      "geometry": {
        "type": "Point",
        "coordinates": [
          -111.8833,
          40.5833
        ]
      },
      "type": "Feature",
      "properties": {
        "hierarchy": [
          "tgn:2510917",
          "tgn:1000001",
          "tgn:7012149",
          "tgn:2002118",
          "tgn:7007827",
          "tgn:7029392"
        ],
        "placetype": [
          "aat:300008347"
        ],
        "id": 2510917,
        "name:xx": "Midvalley Manors"
      }
    },
    {
      "geometry": {
        "type": "Point",
        "coordinates": [
          -111.9167,
          40.5833
        ]
      },
      "type": "Feature",
      "properties": {
        "hierarchy": [
          "tgn:2510918",
          "tgn:1000001",
          "tgn:7012149",
          "tgn:2002118",
          "tgn:7007827",
          "tgn:7029392"
        ],
        "placetype": [
          "aat:300008347"
        ],
        "id": 2510918,
        "name:xx": "Midvalley Terrace"
      }
    },
    {
      "geometry": {
        "type": "Point",
        "coordinates": [
          -110.1833,
          40.1833
        ]
      },
      "type": "Feature",
      "properties": {
        "hierarchy": [
          "tgn:2510919",
          "tgn:1000001",
          "tgn:2002107",
          "tgn:7012149",
          "tgn:7007827",
          "tgn:7029392"
        ],
        "placetype": [
          "aat:300006075"
        ],
        "id": 2510919,
        "name:xx": "Midview Ditch"
      }
    }
  ]
}
