{
  "geometry": {
    "type": "Point",
    "coordinates": [
      -122.8167,
      45.9167
    ]
  },
  "type": "Feature",
  "properties": {
    "hierarchy": [
      "tgn:2528604",
      "tgn:1000001",
      "tgn:1002293",
      "tgn:7012149",
      "tgn:7007708",
      "tgn:7029392"
    ],
    "placetype": [
      "aat:300008680"
    ],
    "id": 2528604,
    "name:xx": "Muckle Lake"
  }
}
