{
  "geometry": {
    "type": "Point",
    "coordinates": [
      -81.75,
      31.0833
    ]
  },
  "type": "Feature",
  "properties": {
    "hierarchy": [
      "tgn:2754459",
      "tgn:1000001",
      "tgn:2000311",
      "tgn:7012149",
      "tgn:7007248",
      "tgn:7029392"
    ],
    "placetype": [
      "aat:300008905"
    ],
    "id": 2754459,
    "name:xx": "Waverly Swamp"
  }
}
