{
  "geometry": {
    "type": "Point",
    "coordinates": [
      32.75,
      52.2167
    ]
  },
  "type": "Feature",
  "properties": {
    "hierarchy": [
      "tgn:7012002",
      "tgn:1000003",
      "tgn:7006660",
      "tgn:7029392"
    ],
    "placetype": [
      "aat:300387064",
      "aat:300235107"
    ],
    "id": 7012002,
    "name:xx": "Černigov"
  }
}
