{
  "type": "FeatureCollection",
  "features": [
    {
      "geometry": {
        "type": "Point",
        "coordinates": [
          23.516667,
          35.3
        ]
      },
      "type": "Feature",
      "properties": {
        "hierarchy": [
          "tgn:7236500",
          "tgn:7002690",
          "tgn:7012056",
          "tgn:1000003",
          "tgn:1000074",
          "tgn:7029392"
        ],
        "placetype": [
          "aat:300008347"
        ],
        "id": 7236500,
        "name:xx": "Áyios Nikólaos"
      }
    },
    {
      "geometry": {
        "type": "Point",
        "coordinates": [
          25.416667,
          35.016667
        ]
      },
      "type": "Feature",
      "properties": {
        "hierarchy": [
          "tgn:7236502",
          "tgn:7002692",
          "tgn:7012056",
          "tgn:1000003",
          "tgn:1000074",
          "tgn:7029392"
        ],
        "placetype": [
          "aat:300008347"
        ],
        "id": 7236502,
        "name:xx": "Áyios Nikólaos"
      }
    },
    {
      "geometry": {
        "type": "Point",
        "coordinates": [
          20.366667,
          39.9
        ]
      },
      "type": "Feature",
      "properties": {
        "hierarchy": [
          "tgn:7236503",
          "tgn:7002707",
          "tgn:7002705",
          "tgn:1000003",
          "tgn:1000074",
          "tgn:7029392"
        ],
        "placetype": [
          "aat:300008798"
        ],
        "id": 7236503,
        "name:xx": "Áyios Nikólaos"
      }
    },
    {
      "geometry": {
        "type": "Point",
        "coordinates": [
          22.25,
          38.116667
        ]
      },
      "type": "Feature",
      "properties": {
        "hierarchy": [
          "tgn:7236504",
          "tgn:7002741",
          "tgn:7017076",
          "tgn:1000003",
          "tgn:1000074",
          "tgn:7029392"
        ],
        "placetype": [
          "aat:300008795"
        ],
        "id": 7236504,
        "name:xx": "Áyios Nikólaos"
      }
    },
    {
      "geometry": {
        "type": "Point",
        "coordinates": [
          21.7,
          36.883333
        ]
      },
      "type": "Feature",
      "properties": {
        "hierarchy": [
          "tgn:7236505",
          "tgn:7011369",
          "tgn:7017076",
          "tgn:1000003",
          "tgn:1000074",
          "tgn:7029392"
        ],
        "placetype": [
          "aat:300008795"
        ],
        "id": 7236505,
        "name:xx": "Áyios Nikólaos"
      }
    },
    {
      "geometry": {
        "type": "Point",
        "coordinates": [
          25.696667,
          37.084444
        ]
      },
      "type": "Feature",
      "properties": {
        "hierarchy": [
          "tgn:7236506",
          "tgn:7011270",
          "tgn:7002674",
          "tgn:1000003",
          "tgn:1000074",
          "tgn:7029392"
        ],
        "placetype": [
          "aat:300008791"
        ],
        "id": 7236506,
        "name:xx": "Ágios Nikólaos, Nisída"
      }
    },
    {
      "geometry": {
        "type": "Point",
        "coordinates": [
          22.383333,
          36.566667
        ]
      },
      "type": "Feature",
      "properties": {
        "hierarchy": [
          "tgn:7236507",
          "tgn:7002745",
          "tgn:7017076",
          "tgn:1000003",
          "tgn:1000074",
          "tgn:7029392"
        ],
        "placetype": [
          "aat:300008777"
        ],
        "id": 7236507,
        "name:xx": "Áyios Nikólaos"
      }
    },
    {
      "geometry": {
        "type": "Point",
        "coordinates": [
          22.35,
          36.75
        ]
      },
      "type": "Feature",
      "properties": {
        "hierarchy": [
          "tgn:7236508",
          "tgn:7002745",
          "tgn:7017076",
          "tgn:1000003",
          "tgn:1000074",
          "tgn:7029392"
        ],
        "placetype": [
          "aat:300008795"
        ],
        "id": 7236508,
        "name:xx": "Áyios Níko"
      }
    },
    {
      "geometry": {
        "type": "Point",
        "coordinates": [
          20.616667,
          38.8
        ]
      },
      "type": "Feature",
      "properties": {
        "hierarchy": [
          "tgn:7236509",
          "tgn:7011168",
          "tgn:7001338",
          "tgn:1000003",
          "tgn:1000074",
          "tgn:7029392"
        ],
        "placetype": [
          "aat:300008850"
        ],
        "id": 7236509,
        "name:xx": "Ágios Nikítas, Ákra"
      }
    }
  ]
}
