{
  "geometry": {
    "type": "Point",
    "coordinates": [
      -117.0667,
      39.4833
    ]
  },
  "type": "Feature",
  "properties": {
    "hierarchy": [
      "tgn:2335664",
      "tgn:1000001",
      "tgn:2001415",
      "tgn:7012149",
      "tgn:7007526",
      "tgn:7029392"
    ],
    "placetype": [
      "aat:300000390"
    ],
    "id": 2335664,
    "name:xx": "Fortuna Mine"
  }
}
