{
  "geometry": {
    "type": "Point",
    "coordinates": [
      -76.7333,
      38.7667
    ]
  },
  "type": "Feature",
  "properties": {
    "hierarchy": [
      "tgn:2706685",
      "tgn:1000001",
      "tgn:2124001",
      "tgn:7012149",
      "tgn:7007516",
      "tgn:7029392"
    ],
    "placetype": [
      "aat:300008706"
    ],
    "id": 2706685,
    "name:xx": "Swan Point Creek"
  }
}
