{
  "geometry": {
    "type": "Point",
    "coordinates": [
      -87.35,
      35.55
    ]
  },
  "type": "Feature",
  "properties": {
    "hierarchy": [
      "tgn:2755508",
      "tgn:1000001",
      "tgn:7012149",
      "tgn:2001887",
      "tgn:7007825",
      "tgn:7029392"
    ],
    "placetype": [
      "aat:300008761"
    ],
    "id": 2755508,
    "name:xx": "Webster Hollow"
  }
}
