{
  "geometry": {
    "type": "Point",
    "coordinates": [
      -82.2167,
      36.95
    ]
  },
  "type": "Feature",
  "properties": {
    "hierarchy": [
      "tgn:2361262",
      "tgn:1000001",
      "tgn:7012149",
      "tgn:2002188",
      "tgn:7007919",
      "tgn:7029392"
    ],
    "placetype": [
      "aat:300008706"
    ],
    "id": 2361262,
    "name:xx": "Gravel Lick Creek"
  }
}
