{
  "type": "FeatureCollection",
  "features": [
    {
      "geometry": {
        "type": "Point",
        "coordinates": [
          -5.3,
          50.266667
        ]
      },
      "type": "Feature",
      "properties": {
        "hierarchy": [
          "tgn:7459590",
          "tgn:7002445",
          "tgn:7008116",
          "tgn:1000003",
          "tgn:7008591",
          "tgn:7029392"
        ],
        "placetype": [
          "aat:300008347"
        ],
        "name:en": "Portreath",
        "id": 7459590
      }
    },
    {
      "geometry": {
        "type": "Point",
        "coordinates": [
          -4.883333,
          50.6
        ]
      },
      "type": "Feature",
      "properties": {
        "hierarchy": [
          "tgn:7459591",
          "tgn:7002445",
          "tgn:7008116",
          "tgn:1000003",
          "tgn:7008591",
          "tgn:7029392"
        ],
        "placetype": [
          "aat:300132316"
        ],
        "name:en": "Portquin Bay",
        "id": 7459591
      }
    },
    {
      "geometry": {
        "type": "Point",
        "coordinates": [
          -1.7,
          51.116667
        ]
      },
      "type": "Feature",
      "properties": {
        "hierarchy": [
          "tgn:7459593",
          "tgn:7002445",
          "tgn:1000003",
          "tgn:7008180",
          "tgn:7008591",
          "tgn:7029392"
        ],
        "placetype": [
          "aat:300008777"
        ],
        "name:en": "Porton Down",
        "id": 7459593
      }
    },
    {
      "geometry": {
        "type": "Point",
        "coordinates": [
          -1.733333,
          51.116667
        ]
      },
      "type": "Feature",
      "properties": {
        "hierarchy": [
          "tgn:7459594",
          "tgn:7002445",
          "tgn:1000003",
          "tgn:7008180",
          "tgn:7008591",
          "tgn:7029392"
        ],
        "placetype": [
          "aat:300008347"
        ],
        "name:en": "Porton",
        "id": 7459594
      }
    },
    {
      "geometry": {
        "type": "Point",
        "coordinates": [
          -5.083333,
          54.816667
        ]
      },
      "type": "Feature",
      "properties": {
        "hierarchy": [
          "tgn:7459595",
          "tgn:7002444",
          "tgn:7008074",
          "tgn:1000003",
          "tgn:7008591",
          "tgn:7029392"
        ],
        "placetype": [
          "aat:300132316"
        ],
        "name:en": "Port of Spittal Bay",
        "id": 7459595
      }
    },
    {
      "geometry": {
        "type": "Point",
        "coordinates": [
          -4.25,
          56.133333
        ]
      },
      "type": "Feature",
      "properties": {
        "hierarchy": [
          "tgn:7459597",
          "tgn:7002444",
          "tgn:1000003",
          "tgn:5000460",
          "tgn:7008591",
          "tgn:7029392"
        ],
        "placetype": [
          "aat:300007783"
        ],
        "name:en": "Port of Menteith Station",
        "id": 7459597
      }
    },
    {
      "geometry": {
        "type": "Point",
        "coordinates": [
          -4.266667,
          56.183333
        ]
      },
      "type": "Feature",
      "properties": {
        "hierarchy": [
          "tgn:7459598",
          "tgn:7002444",
          "tgn:1000003",
          "tgn:5000460",
          "tgn:7008591",
          "tgn:7029392"
        ],
        "placetype": [
          "aat:300008347"
        ],
        "name:en": "Port of Menteith",
        "id": 7459598
      }
    }
  ]
}
