{
  "geometry": {
    "type": "Point",
    "coordinates": [
      30.683333,
      29.233333
    ]
  },
  "type": "Feature",
  "properties": {
    "hierarchy": [
      "tgn:7527538",
      "tgn:7001242",
      "tgn:7001105",
      "tgn:7016833",
      "tgn:7029392"
    ],
    "placetype": [
      "aat:300005926"
    ],
    "name:en": "S카d카 T훮j ad D카n",
    "id": 7527538
  }
}
