{
  "geometry": {
    "type": "Point",
    "coordinates": [
      -111.7333,
      38.5167
    ]
  },
  "type": "Feature",
  "properties": {
    "hierarchy": [
      "tgn:2671756",
      "tgn:1000001",
      "tgn:7012149",
      "tgn:2002121",
      "tgn:7007827",
      "tgn:7029392"
    ],
    "placetype": [
      "aat:300055621"
    ],
    "id": 2671756,
    "name:xx": "Smith Overflow"
  }
}
