{
  "geometry": {
    "type": "Point",
    "coordinates": [
      -91.8333,
      48.1833
    ]
  },
  "type": "Feature",
  "properties": {
    "hierarchy": [
      "tgn:2644964",
      "tgn:1000001",
      "tgn:7012149",
      "tgn:2001067",
      "tgn:7007521",
      "tgn:7029392"
    ],
    "placetype": [
      "aat:300132316"
    ],
    "id": 2644964,
    "name:xx": "Saturday Bay"
  }
}
