{
  "geometry": {
    "type": "Point",
    "coordinates": [
      -29.3167,
      -20.5167
    ]
  },
  "type": "Feature",
  "properties": {
    "hierarchy": [
      "tgn:1009508",
      "tgn:7006389",
      "tgn:1000047",
      "tgn:7002457",
      "tgn:1000002",
      "tgn:7029392"
    ],
    "placetype": [
      "aat:300008791"
    ],
    "id": 1009508,
    "name:xx": "Trindade"
  }
}
