{
  "geometry": {
    "type": "Point",
    "coordinates": [
      -101.0833,
      32.7167
    ]
  },
  "type": "Feature",
  "properties": {
    "hierarchy": [
      "tgn:2237122",
      "tgn:1000001",
      "tgn:7012149",
      "tgn:2002071",
      "tgn:7007826",
      "tgn:7029392"
    ],
    "placetype": [
      "aat:300008706"
    ],
    "id": 2237122,
    "name:xx": "Chimney Creek"
  }
}
