{
  "geometry": {
    "type": "Point",
    "coordinates": [
      -74.1167,
      44.9333
    ]
  },
  "type": "Feature",
  "properties": {
    "hierarchy": [
      "tgn:2192966",
      "tgn:1000001",
      "tgn:7012149",
      "tgn:7013941",
      "tgn:7007568",
      "tgn:7029392"
    ],
    "placetype": [
      "aat:300008761"
    ],
    "id": 2192966,
    "name:xx": "Brayton Hollow"
  }
}
