{
  "geometry": {
    "type": "Point",
    "coordinates": [
      -91.3167,
      43.25
    ]
  },
  "type": "Feature",
  "properties": {
    "hierarchy": [
      "tgn:2318515",
      "tgn:2000563",
      "tgn:1000001",
      "tgn:7012149",
      "tgn:7007253",
      "tgn:7029392"
    ],
    "placetype": [
      "aat:300008699"
    ],
    "id": 2318515,
    "name:xx": "Erickson Spring Branch"
  }
}
