{
  "geometry": {
    "type": "Point",
    "coordinates": [
      -96.55,
      46.3833
    ]
  },
  "type": "Feature",
  "properties": {
    "hierarchy": [
      "tgn:2261173",
      "tgn:1000001",
      "tgn:7012149",
      "tgn:2001082",
      "tgn:7007521",
      "tgn:7029392"
    ],
    "placetype": [
      "aat:300006075"
    ],
    "id": 2261173,
    "name:xx": "County Ditch Number Twentythree"
  }
}
