{
  "geometry": {
    "type": "Point",
    "coordinates": [
      -70.85,
      41.4333
    ]
  },
  "type": "Feature",
  "properties": {
    "hierarchy": [
      "tgn:2324455",
      "tgn:1000001",
      "tgn:1002344",
      "tgn:7012149",
      "tgn:7007517",
      "tgn:7029392"
    ],
    "placetype": [
      "aat:300132348"
    ],
    "id": 2324455,
    "name:xx": "Felix Ledge"
  }
}
