{
  "geometry": {
    "type": "Point",
    "coordinates": [
      -116.75,
      48.8833
    ]
  },
  "type": "Feature",
  "properties": {
    "hierarchy": [
      "tgn:2157259",
      "tgn:1000001",
      "tgn:2000462",
      "tgn:7012149",
      "tgn:7007250",
      "tgn:7029392"
    ],
    "placetype": [
      "aat:300008706"
    ],
    "id": 2157259,
    "name:xx": "Beaver Creek"
  }
}
