{
  "geometry": {
    "type": "Point",
    "coordinates": [
      -85.8167,
      38.3667
    ]
  },
  "type": "Feature",
  "properties": {
    "hierarchy": [
      "tgn:2738150",
      "tgn:1000001",
      "tgn:7012149",
      "tgn:1002376",
      "tgn:7007252",
      "tgn:7029392"
    ],
    "placetype": [
      "aat:300006191"
    ],
    "id": 2738150,
    "name:xx": "Ulrich Lake"
  }
}
