{
  "type": "FeatureCollection",
  "features": [
    {
      "geometry": {
        "type": "Point",
        "coordinates": [
          -85.25,
          33.9
        ]
      },
      "type": "Feature",
      "properties": {
        "hierarchy": [
          "tgn:2022740",
          "tgn:1000001",
          "tgn:7012149",
          "tgn:2000362",
          "tgn:7007248",
          "tgn:7029392"
        ],
        "placetype": [
          "aat:300008347",
          "aat:300387210"
        ],
        "id": 2022740,
        "name:xx": "Dugdown"
      }
    },
    {
      "geometry": {
        "type": "Point",
        "coordinates": [
          -84.1333,
          34
        ]
      },
      "type": "Feature",
      "properties": {
        "hierarchy": [
          "tgn:2022741",
          "tgn:1000001",
          "tgn:7012149",
          "tgn:2000358",
          "tgn:7007248",
          "tgn:7029392"
        ],
        "placetype": [
          "aat:300008347"
        ],
        "id": 2022741,
        "name:xx": "Duluth"
      }
    },
    {
      "geometry": {
        "type": "Point",
        "coordinates": [
          -84.4833,
          32.0333
        ]
      },
      "type": "Feature",
      "properties": {
        "hierarchy": [
          "tgn:2022742",
          "tgn:1000001",
          "tgn:7012149",
          "tgn:2000443",
          "tgn:7007248",
          "tgn:7029392"
        ],
        "placetype": [
          "aat:300008347",
          "aat:300387210"
        ],
        "id": 2022742,
        "name:xx": "Dumas"
      }
    },
    {
      "geometry": {
        "type": "Point",
        "coordinates": [
          -85.2167,
          34.9667
        ]
      },
      "type": "Feature",
      "properties": {
        "hierarchy": [
          "tgn:2022744",
          "tgn:1000001",
          "tgn:2000314",
          "tgn:7012149",
          "tgn:7007248",
          "tgn:7029392"
        ],
        "placetype": [
          "aat:300008347"
        ],
        "id": 2022744,
        "name:xx": "Duncan Park"
      }
    },
    {
      "geometry": {
        "type": "Point",
        "coordinates": [
          -84.3333,
          33.9333
        ]
      },
      "type": "Feature",
      "properties": {
        "hierarchy": [
          "tgn:2022746",
          "tgn:1000001",
          "tgn:7012149",
          "tgn:2124023",
          "tgn:7007248",
          "tgn:7029392"
        ],
        "placetype": [
          "aat:300008347"
        ],
        "id": 2022746,
        "name:xx": "Dunwoody"
      }
    },
    {
      "geometry": {
        "type": "Point",
        "coordinates": [
          -84.7667,
          32.9167
        ]
      },
      "type": "Feature",
      "properties": {
        "hierarchy": [
          "tgn:2022748",
          "tgn:1000001",
          "tgn:7012149",
          "tgn:2000390",
          "tgn:7007248",
          "tgn:7029392"
        ],
        "placetype": [
          "aat:300008347"
        ],
        "id": 2022748,
        "name:xx": "Durand"
      }
    }
  ]
}
