{
  "geometry": {
    "type": "Point",
    "coordinates": [
      -90.9667,
      47.7667
    ]
  },
  "type": "Feature",
  "properties": {
    "hierarchy": [
      "tgn:2615508",
      "tgn:1000001",
      "tgn:2001014",
      "tgn:7012149",
      "tgn:7007521",
      "tgn:7029392"
    ],
    "placetype": [
      "aat:300008680"
    ],
    "id": 2615508,
    "name:xx": "Retreat Lake"
  }
}
