{
  "geometry": {
    "type": "Point",
    "coordinates": [
      8.05,
      50.75
    ]
  },
  "type": "Feature",
  "properties": {
    "hierarchy": [
      "tgn:7207403",
      "tgn:1000003",
      "tgn:7003677",
      "tgn:7000084",
      "tgn:7029392"
    ],
    "placetype": [
      "aat:300008699"
    ],
    "id": 7207403,
    "name:xx": "Buchheller"
  }
}
