{
  "geometry": {
    "type": "Point",
    "coordinates": [
      -105.1667,
      46.55
    ]
  },
  "type": "Feature",
  "properties": {
    "hierarchy": [
      "tgn:2330555",
      "tgn:1000001",
      "tgn:7012149",
      "tgn:2001299",
      "tgn:7007524",
      "tgn:7029392"
    ],
    "placetype": [
      "aat:300008706"
    ],
    "id": 2330555,
    "name:xx": "Flat Creek"
  }
}
