{
  "geometry": {
    "type": "Point",
    "coordinates": [
      120.5803,
      23.7581
    ]
  },
  "type": "Feature",
  "properties": {
    "hierarchy": [
      "tgn:7475473",
      "tgn:1000004",
      "tgn:7001014",
      "tgn:1000141",
      "tgn:7029392"
    ],
    "placetype": [
      "aat:300387033"
    ],
    "id": 7475473,
    "name:xx": "Jiuxionglin"
  }
}
