{
  "geometry": {
    "type": "Point",
    "coordinates": [
      -88.85,
      33.7333
    ]
  },
  "type": "Feature",
  "properties": {
    "hierarchy": [
      "tgn:2738511",
      "tgn:1000001",
      "tgn:2001098",
      "tgn:7012149",
      "tgn:7007522",
      "tgn:7029392"
    ],
    "placetype": [
      "aat:300008706"
    ],
    "id": 2738511,
    "name:xx": "Underwood Creek"
  }
}
