{
  "geometry": {
    "type": "Point",
    "coordinates": [
      -87.0167,
      32.5667
    ]
  },
  "type": "Feature",
  "properties": {
    "hierarchy": [
      "tgn:2184956",
      "tgn:7002659",
      "tgn:1000001",
      "tgn:7012149",
      "tgn:2000023",
      "tgn:7029392"
    ],
    "placetype": [
      "aat:300008699"
    ],
    "id": 2184956,
    "name:xx": "Bogg Branch"
  }
}
