{
  "geometry": {
    "type": "Point",
    "coordinates": [
      -110.6833,
      32.2333
    ]
  },
  "type": "Feature",
  "properties": {
    "hierarchy": [
      "tgn:2344133",
      "tgn:1000001",
      "tgn:7006451",
      "tgn:7012149",
      "tgn:2000100",
      "tgn:7029392"
    ],
    "placetype": [
      "aat:300006191"
    ],
    "id": 2344133,
    "name:xx": "Gambusi Lake"
  }
}
