{
  "geometry": {
    "type": "Point",
    "coordinates": [
      105.6667,
      37.4333
    ]
  },
  "type": "Feature",
  "properties": {
    "hierarchy": [
      "tgn:1074058",
      "tgn:1000004",
      "tgn:7018053",
      "tgn:1000111",
      "tgn:7029392"
    ],
    "placetype": [
      "aat:300008347"
    ],
    "id": 1074058,
    "name:xx": "Zhongning"
  }
}
