{
  "geometry": {
    "type": "Point",
    "coordinates": [
      29.489198,
      28.603925
    ]
  },
  "type": "Feature",
  "properties": {
    "hierarchy": [
      "tgn:7539273",
      "tgn:7001242",
      "tgn:7016833",
      "tgn:7029392"
    ],
    "placetype": [
      "aat:300008777"
    ],
    "name:en": "Maţrūd, Qārat",
    "id": 7539273
  }
}
