{
  "geometry": {
    "type": "Point",
    "coordinates": [
      20.3333,
      46.4167
    ]
  },
  "type": "Feature",
  "properties": {
    "hierarchy": [
      "tgn:7010476",
      "tgn:1000362",
      "tgn:1000003",
      "tgn:7006278",
      "tgn:7029392"
    ],
    "placetype": [
      "aat:300008347",
      "aat:300008375"
    ],
    "id": 7010476,
    "name:xx": "Hódmezővásárhely"
  }
}
