{
  "geometry": {
    "type": "Point",
    "coordinates": [
      27.394562,
      31.239501
    ]
  },
  "type": "Feature",
  "properties": {
    "hierarchy": [
      "tgn:7520502",
      "tgn:7001242",
      "tgn:7016833",
      "tgn:1001418",
      "tgn:7029392"
    ],
    "placetype": [
      "aat:300007783"
    ],
    "name:en": "Maḩaţţat al Jarāwilah",
    "id": 7520502
  }
}
