{
  "geometry": {
    "type": "Point",
    "coordinates": [
      81.75,
      46.1667
    ]
  },
  "type": "Feature",
  "properties": {
    "hierarchy": [
      "tgn:1118904",
      "tgn:1000004",
      "tgn:7014786",
      "tgn:7029392"
    ],
    "placetype": [
      "aat:300266556"
    ],
    "id": 1118904,
    "name:xx": "Alakol, Ozero"
  }
}
