{
  "geometry": {
    "type": "Point",
    "coordinates": [
      -123.3333,
      47.55
    ]
  },
  "type": "Feature",
  "properties": {
    "hierarchy": [
      "tgn:2292077",
      "tgn:1000001",
      "tgn:7012149",
      "tgn:1002645",
      "tgn:7007920",
      "tgn:7029392"
    ],
    "placetype": [
      "aat:300008706"
    ],
    "id": 2292077,
    "name:xx": "Donahue Creek"
  }
}
