{
  "geometry": {
    "type": "Point",
    "coordinates": [
      -73.45,
      43.25
    ]
  },
  "type": "Feature",
  "properties": {
    "hierarchy": [
      "tgn:2349769",
      "tgn:1000001",
      "tgn:7012149",
      "tgn:1002993",
      "tgn:7007568",
      "tgn:7029392"
    ],
    "placetype": [
      "aat:300008699"
    ],
    "id": 2349769,
    "name:xx": "Gillis Brook"
  }
}
