{
  "geometry": {
    "type": "Point",
    "coordinates": [
      -108.1667,
      32.8833
    ]
  },
  "type": "Feature",
  "properties": {
    "hierarchy": [
      "tgn:2736510",
      "tgn:1000001",
      "tgn:7012149",
      "tgn:2001437",
      "tgn:7007566",
      "tgn:7029392"
    ],
    "placetype": [
      "aat:300008798"
    ],
    "id": 2736510,
    "name:xx": "Twin Sisters"
  }
}
