{
  "geometry": {
    "type": "Point",
    "coordinates": [
      31.300183,
      30.109972
    ]
  },
  "type": "Feature",
  "properties": {
    "hierarchy": [
      "tgn:7526589",
      "tgn:7001242",
      "tgn:7016833",
      "tgn:1001091",
      "tgn:7029392"
    ],
    "placetype": [
      "aat:300004792"
    ],
    "id": 7526589,
    "name:xx": "Al Hay'ah al 'Āmmah lil Tawḩīd al Qiyāsī"
  }
}
