{
  "geometry": {
    "type": "Point",
    "coordinates": [
      -78.25,
      34.3333
    ]
  },
  "type": "Feature",
  "properties": {
    "hierarchy": [
      "tgn:2073484",
      "tgn:1000001",
      "tgn:2001485",
      "tgn:7012149",
      "tgn:7007709",
      "tgn:7029392"
    ],
    "placetype": [
      "aat:300008347",
      "aat:300387210"
    ],
    "id": 2073484,
    "name:xx": "Armour"
  }
}
