{
  "geometry": {
    "type": "Point",
    "coordinates": [
      -107.15,
      42.7167
    ]
  },
  "type": "Feature",
  "properties": {
    "hierarchy": [
      "tgn:2636768",
      "tgn:1000001",
      "tgn:7012149",
      "tgn:2002377",
      "tgn:7007923",
      "tgn:7029392"
    ],
    "placetype": [
      "aat:300008798"
    ],
    "id": 2636768,
    "name:xx": "Sagehen Hill"
  }
}
