{
  "geometry": {
    "type": "Point",
    "coordinates": [
      -141.8167,
      62.1167
    ]
  },
  "type": "Feature",
  "properties": {
    "hierarchy": [
      "tgn:2204957",
      "tgn:7006450",
      "tgn:1000001",
      "tgn:7012149",
      "tgn:2000086",
      "tgn:7029392"
    ],
    "placetype": [
      "aat:300008761"
    ],
    "id": 2204957,
    "name:xx": "Bug Gulch"
  }
}
