{
  "geometry": {
    "type": "Point",
    "coordinates": [
      -99.1667,
      35.3333
    ]
  },
  "type": "Feature",
  "properties": {
    "hierarchy": [
      "tgn:2082930",
      "tgn:1000001",
      "tgn:7012149",
      "tgn:2001697",
      "tgn:7007707",
      "tgn:7029392"
    ],
    "placetype": [
      "aat:300008347"
    ],
    "id": 2082930,
    "name:xx": "Burns Flat"
  }
}
