{
  "geometry": {
    "type": "Point",
    "coordinates": [
      -120.55,
      44.7833
    ]
  },
  "type": "Feature",
  "properties": {
    "hierarchy": [
      "tgn:2477496",
      "tgn:1000001",
      "tgn:7012149",
      "tgn:2001712",
      "tgn:7007708",
      "tgn:7029392"
    ],
    "placetype": [
      "aat:300266640"
    ],
    "id": 2477496,
    "name:xx": "Lyons Ridge"
  }
}
