{
  "type": "FeatureCollection",
  "features": [
    {
      "geometry": {
        "type": "Point",
        "coordinates": [
          7.45,
          51.366667
        ]
      },
      "type": "Feature",
      "properties": {
        "hierarchy": [
          "tgn:7179730",
          "tgn:1000003",
          "tgn:7003677",
          "tgn:7000084",
          "tgn:7029392"
        ],
        "placetype": [
          "aat:300008347"
        ],
        "id": 7179730,
        "name:xx": "Grünthal"
      }
    },
    {
      "geometry": {
        "type": "Point",
        "coordinates": [
          12.166667,
          49.05
        ]
      },
      "type": "Feature",
      "properties": {
        "hierarchy": [
          "tgn:7179731",
          "tgn:7003669",
          "tgn:1000003",
          "tgn:7000084",
          "tgn:7029392"
        ],
        "placetype": [
          "aat:300008347"
        ],
        "id": 7179731,
        "name:xx": "Grünthal"
      }
    },
    {
      "geometry": {
        "type": "Point",
        "coordinates": [
          12.4,
          48.133333
        ]
      },
      "type": "Feature",
      "properties": {
        "hierarchy": [
          "tgn:7179732",
          "tgn:7003669",
          "tgn:1000003",
          "tgn:7000084",
          "tgn:7029392"
        ],
        "placetype": [
          "aat:300008347"
        ],
        "id": 7179732,
        "name:xx": "Grünthal"
      }
    },
    {
      "geometry": {
        "type": "Point",
        "coordinates": [
          12.1,
          47.8
        ]
      },
      "type": "Feature",
      "properties": {
        "hierarchy": [
          "tgn:7179733",
          "tgn:7003669",
          "tgn:1000003",
          "tgn:7000084",
          "tgn:7029392"
        ],
        "placetype": [
          "aat:300008347"
        ],
        "id": 7179733,
        "name:xx": "Grünthal"
      }
    },
    {
      "geometry": {
        "type": "Point",
        "coordinates": [
          9.9,
          54.533333
        ]
      },
      "type": "Feature",
      "properties": {
        "hierarchy": [
          "tgn:7179734",
          "tgn:1000003",
          "tgn:7003688",
          "tgn:7000084",
          "tgn:7029392"
        ],
        "placetype": [
          "aat:300000206"
        ],
        "id": 7179734,
        "name:xx": "Grünthal"
      }
    },
    {
      "geometry": {
        "type": "Point",
        "coordinates": [
          9.2,
          54.45
        ]
      },
      "type": "Feature",
      "properties": {
        "hierarchy": [
          "tgn:7179736",
          "tgn:1000003",
          "tgn:7003688",
          "tgn:7000084",
          "tgn:7029392"
        ],
        "placetype": [
          "aat:300000206"
        ],
        "id": 7179736,
        "name:xx": "Grünthal"
      }
    },
    {
      "geometry": {
        "type": "Point",
        "coordinates": [
          9.033333,
          54.433333
        ]
      },
      "type": "Feature",
      "properties": {
        "hierarchy": [
          "tgn:7179737",
          "tgn:1000003",
          "tgn:7003688",
          "tgn:7000084",
          "tgn:7029392"
        ],
        "placetype": [
          "aat:300000206"
        ],
        "id": 7179737,
        "name:xx": "Grünthal"
      }
    },
    {
      "geometry": {
        "type": "Point",
        "coordinates": [
          6.533333,
          51.6
        ]
      },
      "type": "Feature",
      "properties": {
        "hierarchy": [
          "tgn:7179738",
          "tgn:1000003",
          "tgn:7003677",
          "tgn:7000084",
          "tgn:7029392"
        ],
        "placetype": [
          "aat:300000206"
        ],
        "id": 7179738,
        "name:xx": "Grünthal"
      }
    },
    {
      "geometry": {
        "type": "Point",
        "coordinates": [
          7.783333,
          51.366667
        ]
      },
      "type": "Feature",
      "properties": {
        "hierarchy": [
          "tgn:7179739",
          "tgn:1000003",
          "tgn:7003677",
          "tgn:7000084",
          "tgn:7029392"
        ],
        "placetype": [
          "aat:300000206"
        ],
        "id": 7179739,
        "name:xx": "Grünthal"
      }
    }
  ]
}
