{
  "geometry": {
    "type": "Point",
    "coordinates": [
      -81.1333,
      36.7833
    ]
  },
  "type": "Feature",
  "properties": {
    "hierarchy": [
      "tgn:2417845",
      "tgn:1000001",
      "tgn:7012149",
      "tgn:2002196",
      "tgn:7007919",
      "tgn:7029392"
    ],
    "placetype": [
      "aat:300008761"
    ],
    "id": 2417845,
    "name:xx": "Jackson Hollow"
  }
}
