{
  "geometry": {
    "type": "Point",
    "coordinates": [
      -119.4667,
      35.3667
    ]
  },
  "type": "Feature",
  "properties": {
    "hierarchy": [
      "tgn:2517689",
      "tgn:1000001",
      "tgn:7012149",
      "tgn:1002545",
      "tgn:7007157",
      "tgn:7029392"
    ],
    "placetype": [
      "aat:300006075"
    ],
    "id": 2517689,
    "name:xx": "Mirasol Ditch"
  }
}
