{
  "geometry": {
    "type": "Point",
    "coordinates": [
      -84.7167,
      38.9333
    ]
  },
  "type": "Feature",
  "properties": {
    "hierarchy": [
      "tgn:2039471",
      "tgn:1000001",
      "tgn:1002189",
      "tgn:7012149",
      "tgn:7007255",
      "tgn:7029392"
    ],
    "placetype": [
      "aat:300008347",
      "aat:300387210"
    ],
    "id": 2039471,
    "name:xx": "Hueys Corners"
  }
}
