{
  "geometry": {
    "type": "Point",
    "coordinates": [
      -88.2667,
      32.0333
    ]
  },
  "type": "Feature",
  "properties": {
    "hierarchy": [
      "tgn:2391162",
      "tgn:7002659",
      "tgn:1000001",
      "tgn:2000011",
      "tgn:7012149",
      "tgn:7029392"
    ],
    "placetype": [
      "aat:300008798"
    ],
    "id": 2391162,
    "name:xx": "Hill Mountain"
  }
}
