{
  "type": "FeatureCollection",
  "features": [
    {
      "geometry": {
        "type": "Point",
        "coordinates": [
          2.67689,
          41.740043
        ]
      },
      "type": "Feature",
      "properties": {
        "hierarchy": [
          "tgn:7325632",
          "tgn:7002820",
          "tgn:7030216",
          "tgn:1000003",
          "tgn:1000095",
          "tgn:7029392"
        ],
        "placetype": [
          "aat:300008699"
        ],
        "id": 7325632,
        "name:xx": "Santa Coloma, Riera de"
      }
    },
    {
      "geometry": {
        "type": "Point",
        "coordinates": [
          -6.716667,
          43.3
        ]
      },
      "type": "Feature",
      "properties": {
        "hierarchy": [
          "tgn:7325633",
          "tgn:7008911",
          "tgn:1000003",
          "tgn:7002763",
          "tgn:1000095",
          "tgn:7029392"
        ],
        "placetype": [
          "aat:300008347"
        ],
        "id": 7325633,
        "name:xx": "Santa Coloma"
      }
    },
    {
      "geometry": {
        "type": "Point",
        "coordinates": [
          -3.158612,
          43.138968
        ]
      },
      "type": "Feature",
      "properties": {
        "hierarchy": [
          "tgn:7325634",
          "tgn:7002810",
          "tgn:7001158",
          "tgn:1000003",
          "tgn:1000095",
          "tgn:7029392"
        ],
        "placetype": [
          "aat:300008347"
        ],
        "id": 7325634,
        "name:xx": "Santa Coloma"
      }
    },
    {
      "geometry": {
        "type": "Point",
        "coordinates": [
          -3.283333,
          42.833333
        ]
      },
      "type": "Feature",
      "properties": {
        "hierarchy": [
          "tgn:7325635",
          "tgn:7002810",
          "tgn:7001158",
          "tgn:1000003",
          "tgn:1000095",
          "tgn:7029392"
        ],
        "placetype": [
          "aat:300008347"
        ],
        "id": 7325635,
        "name:xx": "Santa Coloma"
      }
    },
    {
      "geometry": {
        "type": "Point",
        "coordinates": [
          -2.633333,
          42.366667
        ]
      },
      "type": "Feature",
      "properties": {
        "hierarchy": [
          "tgn:7325636",
          "tgn:7002827",
          "tgn:1000003",
          "tgn:7002789",
          "tgn:1000095",
          "tgn:7029392"
        ],
        "placetype": [
          "aat:300008347"
        ],
        "id": 7325636,
        "name:xx": "Santa Coloma"
      }
    },
    {
      "geometry": {
        "type": "Point",
        "coordinates": [
          -5.666667,
          41.333333
        ]
      },
      "type": "Feature",
      "properties": {
        "hierarchy": [
          "tgn:7325637",
          "tgn:7001158",
          "tgn:7002850",
          "tgn:1000003",
          "tgn:1000095",
          "tgn:7029392"
        ],
        "placetype": [
          "aat:300008347"
        ],
        "id": 7325637,
        "name:xx": "Santa Clara de Avedillo"
      }
    },
    {
      "geometry": {
        "type": "Point",
        "coordinates": [
          -2.416667,
          43.333333
        ]
      },
      "type": "Feature",
      "properties": {
        "hierarchy": [
          "tgn:7325638",
          "tgn:7002849",
          "tgn:1000003",
          "tgn:7009604",
          "tgn:1000095",
          "tgn:7029392"
        ],
        "placetype": [
          "aat:300386846"
        ],
        "id": 7325638,
        "name:xx": "Santa Clara, Punta de"
      }
    },
    {
      "geometry": {
        "type": "Point",
        "coordinates": [
          -4.616667,
          43.4
        ]
      },
      "type": "Feature",
      "properties": {
        "hierarchy": [
          "tgn:7325639",
          "tgn:7008911",
          "tgn:1000003",
          "tgn:7002763",
          "tgn:1000095",
          "tgn:7029392"
        ],
        "placetype": [
          "aat:300386846"
        ],
        "id": 7325639,
        "name:xx": "Santa Clara, Punta"
      }
    }
  ]
}
