{
  "geometry": {
    "type": "Point",
    "coordinates": [
      -90.5167,
      36.4833
    ]
  },
  "type": "Feature",
  "properties": {
    "hierarchy": [
      "tgn:2008942",
      "tgn:1000001",
      "tgn:7016172",
      "tgn:2000115",
      "tgn:7012149",
      "tgn:7029392"
    ],
    "placetype": [
      "aat:300008347"
    ],
    "id": 2008942,
    "name:xx": "Moark"
  }
}
