{
  "geometry": {
    "type": "Point",
    "coordinates": [
      -75.3833,
      41.8833
    ]
  },
  "type": "Feature",
  "properties": {
    "hierarchy": [
      "tgn:2092995",
      "tgn:1000001",
      "tgn:7012149",
      "tgn:1003008",
      "tgn:7007710",
      "tgn:7029392"
    ],
    "placetype": [
      "aat:300008347"
    ],
    "id": 2092995,
    "name:xx": "Shehawken"
  }
}
