{
  "geometry": {
    "type": "Point",
    "coordinates": [
      -111.2833,
      31.95
    ]
  },
  "type": "Feature",
  "properties": {
    "hierarchy": [
      "tgn:2372854",
      "tgn:1000001",
      "tgn:7006451",
      "tgn:7012149",
      "tgn:2000100",
      "tgn:7029392"
    ],
    "placetype": [
      "aat:300006191"
    ],
    "id": 2372854,
    "name:xx": "Hall Tank"
  }
}
