{
  "geometry": {
    "type": "Point",
    "coordinates": [
      9.35,
      51.333333
    ]
  },
  "type": "Feature",
  "properties": {
    "hierarchy": [
      "tgn:7166608",
      "tgn:1000003",
      "tgn:7003678",
      "tgn:7000084",
      "tgn:7029392"
    ],
    "placetype": [
      "aat:300004792"
    ],
    "id": 7166608,
    "name:xx": "Försterei Heide"
  }
}
