{
  "geometry": {
    "type": "Point",
    "coordinates": [
      -121.6167,
      38.2833
    ]
  },
  "type": "Feature",
  "properties": {
    "hierarchy": [
      "tgn:2314929",
      "tgn:1000001",
      "tgn:7012149",
      "tgn:7007157",
      "tgn:1002901",
      "tgn:7029392"
    ],
    "placetype": [
      "aat:300008699"
    ],
    "id": 2314929,
    "name:xx": "Elkhorn Slough"
  }
}
