{
  "type": "FeatureCollection",
  "features": [
    {
      "geometry": {
        "type": "Point",
        "coordinates": [
          -149.7167,
          60.6
        ]
      },
      "type": "Feature",
      "properties": {
        "hierarchy": [
          "tgn:2285790",
          "tgn:7006450",
          "tgn:1000001",
          "tgn:7019698",
          "tgn:7012149",
          "tgn:7029392"
        ],
        "placetype": [
          "aat:300008680"
        ],
        "id": 2285790,
        "name:xx": "Devils Pass Lake"
      }
    },
    {
      "geometry": {
        "type": "Point",
        "coordinates": [
          -133.8333,
          58.7167
        ]
      },
      "type": "Feature",
      "properties": {
        "hierarchy": [
          "tgn:2285791",
          "tgn:7006450",
          "tgn:1000001",
          "tgn:7012149",
          "tgn:7029392"
        ],
        "placetype": [
          "aat:300008798"
        ],
        "id": 2285791,
        "name:xx": "Devils Paw"
      }
    },
    {
      "geometry": {
        "type": "Point",
        "coordinates": [
          -120.2833,
          39.0167
        ]
      },
      "type": "Feature",
      "properties": {
        "hierarchy": [
          "tgn:2285792",
          "tgn:1000001",
          "tgn:7012149",
          "tgn:7007157",
          "tgn:1002791",
          "tgn:7029392"
        ],
        "placetype": [
          "aat:300008798"
        ],
        "id": 2285792,
        "name:xx": "Devils Peak"
      }
    },
    {
      "geometry": {
        "type": "Point",
        "coordinates": [
          -121.7833,
          36.3667
        ]
      },
      "type": "Feature",
      "properties": {
        "hierarchy": [
          "tgn:2285793",
          "tgn:1000001",
          "tgn:7012149",
          "tgn:7007157",
          "tgn:1002684",
          "tgn:7029392"
        ],
        "placetype": [
          "aat:300008798"
        ],
        "id": 2285793,
        "name:xx": "Devils Peak"
      }
    },
    {
      "geometry": {
        "type": "Point",
        "coordinates": [
          -72.25,
          42.2
        ]
      },
      "type": "Feature",
      "properties": {
        "hierarchy": [
          "tgn:2285794",
          "tgn:1000001",
          "tgn:7012149",
          "tgn:1003038",
          "tgn:7007517",
          "tgn:7029392"
        ],
        "placetype": [
          "aat:300008798"
        ],
        "id": 2285794,
        "name:xx": "Devils Peak"
      }
    },
    {
      "geometry": {
        "type": "Point",
        "coordinates": [
          -95.2333,
          35.7333
        ]
      },
      "type": "Feature",
      "properties": {
        "hierarchy": [
          "tgn:2285795",
          "tgn:1000001",
          "tgn:7012149",
          "tgn:2001673",
          "tgn:7007707",
          "tgn:7029392"
        ],
        "placetype": [
          "aat:300008798"
        ],
        "id": 2285795,
        "name:xx": "Devils Peak"
      }
    },
    {
      "geometry": {
        "type": "Point",
        "coordinates": [
          -122.2,
          42.6333
        ]
      },
      "type": "Feature",
      "properties": {
        "hierarchy": [
          "tgn:2285796",
          "tgn:1000001",
          "tgn:7012149",
          "tgn:2001714",
          "tgn:7007708",
          "tgn:7029392"
        ],
        "placetype": [
          "aat:300008798"
        ],
        "id": 2285796,
        "name:xx": "Devils Peak"
      }
    },
    {
      "geometry": {
        "type": "Point",
        "coordinates": [
          -121.9333,
          44.75
        ]
      },
      "type": "Feature",
      "properties": {
        "hierarchy": [
          "tgn:2285797",
          "tgn:1000001",
          "tgn:7012149",
          "tgn:1002636",
          "tgn:7007708",
          "tgn:7029392"
        ],
        "placetype": [
          "aat:300008798"
        ],
        "id": 2285797,
        "name:xx": "Devils Peak"
      }
    },
    {
      "geometry": {
        "type": "Point",
        "coordinates": [
          -121.8667,
          45.25
        ]
      },
      "type": "Feature",
      "properties": {
        "hierarchy": [
          "tgn:2285798",
          "tgn:1000001",
          "tgn:1002270",
          "tgn:7012149",
          "tgn:7007708",
          "tgn:7029392"
        ],
        "placetype": [
          "aat:300008798"
        ],
        "id": 2285798,
        "name:xx": "Devils Peak"
      }
    },
    {
      "geometry": {
        "type": "Point",
        "coordinates": [
          -111.5833,
          39.6167
        ]
      },
      "type": "Feature",
      "properties": {
        "hierarchy": [
          "tgn:2285799",
          "tgn:1000001",
          "tgn:7012149",
          "tgn:2002120",
          "tgn:7007827",
          "tgn:7029392"
        ],
        "placetype": [
          "aat:300008798"
        ],
        "id": 2285799,
        "name:xx": "Devils Peak"
      }
    }
  ]
}
