{
  "geometry": {
    "type": "Point",
    "coordinates": [
      31.2667,
      53.7667
    ]
  },
  "type": "Feature",
  "properties": {
    "hierarchy": [
      "tgn:1061167",
      "tgn:7011700",
      "tgn:1000003",
      "tgn:7006657",
      "tgn:7029392"
    ],
    "placetype": [
      "aat:300008347"
    ],
    "id": 1061167,
    "name:xx": "Veremeyki"
  }
}
