{
  "geometry": {
    "type": "Point",
    "coordinates": [
      -107.4667,
      33.4833
    ]
  },
  "type": "Feature",
  "properties": {
    "hierarchy": [
      "tgn:2745880",
      "tgn:1000001",
      "tgn:7012149",
      "tgn:7007566",
      "tgn:7029392"
    ],
    "placetype": [
      "aat:300008699"
    ],
    "id": 2745880,
    "name:xx": "Vivian, Cañada"
  }
}
