{
  "geometry": {
    "type": "Point",
    "coordinates": [
      73.366667,
      18.816667
    ]
  },
  "type": "Feature",
  "properties": {
    "hierarchy": [
      "tgn:1077153",
      "tgn:1000004",
      "tgn:7000198",
      "tgn:1001895",
      "tgn:7029392"
    ],
    "placetype": [
      "aat:300008347"
    ],
    "name:en": "Thākurvādi",
    "id": 1077153
  }
}
