{
  "geometry": {
    "type": "Point",
    "coordinates": [
      -94.2667,
      31.05
    ]
  },
  "type": "Feature",
  "properties": {
    "hierarchy": [
      "tgn:2191124",
      "tgn:1000001",
      "tgn:7012149",
      "tgn:2002009",
      "tgn:7007826",
      "tgn:7029392"
    ],
    "placetype": [
      "aat:300008697"
    ],
    "id": 2191124,
    "name:xx": "Boykin Spring"
  }
}
