{
  "geometry": {
    "type": "Point",
    "coordinates": [
      -90.4667,
      36.95
    ]
  },
  "type": "Feature",
  "properties": {
    "hierarchy": [
      "tgn:2382208",
      "tgn:1000001",
      "tgn:7012149",
      "tgn:7007523",
      "tgn:7029392"
    ],
    "placetype": [
      "aat:300008761"
    ],
    "id": 2382208,
    "name:xx": "Haynes Hollow"
  }
}
