{
  "geometry": {
    "type": "Point",
    "coordinates": [
      -64.35,
      -6.5667
    ]
  },
  "type": "Feature",
  "properties": {
    "hierarchy": [
      "tgn:1021057",
      "tgn:1001826",
      "tgn:1000047",
      "tgn:7002456",
      "tgn:1000002",
      "tgn:7029392"
    ],
    "placetype": [
      "aat:300008347"
    ],
    "id": 1021057,
    "name:xx": "Canutama"
  }
}
