{
  "geometry": {
    "type": "Point",
    "coordinates": [
      -79.3167,
      36.6667
    ]
  },
  "type": "Feature",
  "properties": {
    "hierarchy": [
      "tgn:2173389",
      "tgn:1000001",
      "tgn:7012149",
      "tgn:7007919",
      "tgn:7029392"
    ],
    "placetype": [
      "aat:300008706"
    ],
    "id": 2173389,
    "name:xx": "Birch Creek"
  }
}
