{
  "geometry": {
    "type": "Point",
    "coordinates": [
      -97.6167,
      31.5333
    ]
  },
  "type": "Feature",
  "properties": {
    "hierarchy": [
      "tgn:2103474",
      "tgn:1000001",
      "tgn:7012149",
      "tgn:1002303",
      "tgn:7007826",
      "tgn:7029392"
    ],
    "placetype": [
      "aat:300008347"
    ],
    "id": 2103474,
    "name:xx": "Coryell"
  }
}
