{
  "geometry": {
    "type": "Point",
    "coordinates": [
      31.106667,
      31.570556
    ]
  },
  "type": "Feature",
  "properties": {
    "hierarchy": [
      "tgn:7532243",
      "tgn:7001242",
      "tgn:7016833",
      "tgn:1001335",
      "tgn:7029392"
    ],
    "placetype": [
      "aat:300005433"
    ],
    "name:en": "Sakn Muḥammad Ḥilu",
    "id": 7532243
  }
}
