{
  "geometry": {
    "type": "Point",
    "coordinates": [
      -69.9667,
      43.8833
    ]
  },
  "type": "Feature",
  "properties": {
    "hierarchy": [
      "tgn:2492208",
      "tgn:1000001",
      "tgn:2000920",
      "tgn:7012149",
      "tgn:7007515",
      "tgn:7029392"
    ],
    "placetype": [
      "aat:300008699"
    ],
    "id": 2492208,
    "name:xx": "Mare Brook"
  }
}
