{
  "geometry": {
    "type": "Point",
    "coordinates": [
      -83.05,
      37.3667
    ]
  },
  "type": "Feature",
  "properties": {
    "hierarchy": [
      "tgn:2167741",
      "tgn:1000001",
      "tgn:7012149",
      "tgn:2000805",
      "tgn:7007255",
      "tgn:7029392"
    ],
    "placetype": [
      "aat:300008699"
    ],
    "id": 2167741,
    "name:xx": "Big Cutoff Branch"
  }
}
