{
  "geometry": {
    "type": "Point",
    "coordinates": [
      18.0167,
      52.8167
    ]
  },
  "type": "Feature",
  "properties": {
    "hierarchy": [
      "tgn:1049348",
      "tgn:7024116",
      "tgn:1000003",
      "tgn:7006366",
      "tgn:7029392"
    ],
    "placetype": [
      "aat:300008347"
    ],
    "id": 1049348,
    "name:xx": "Pakośó"
  }
}
