{
  "geometry": {
    "type": "Point",
    "coordinates": [
      -83.8333,
      38.0167
    ]
  },
  "type": "Feature",
  "properties": {
    "hierarchy": [
      "tgn:2474701",
      "tgn:1000001",
      "tgn:7012149",
      "tgn:2000830",
      "tgn:7007255",
      "tgn:7029392"
    ],
    "placetype": [
      "aat:300008347"
    ],
    "id": 2474701,
    "name:xx": "Lower Spencer"
  }
}
