{
  "geometry": {
    "type": "Point",
    "coordinates": [
      125.6167,
      10.35
    ]
  },
  "type": "Feature",
  "properties": {
    "hierarchy": [
      "tgn:1084369",
      "tgn:1001065",
      "tgn:1000004",
      "tgn:1000135",
      "tgn:7029392"
    ],
    "placetype": [
      "aat:300008347"
    ],
    "id": 1084369,
    "name:xx": "Loreto"
  }
}
