{
  "geometry": {
    "type": "Point",
    "coordinates": [
      148.1667,
      -36.3667
    ]
  },
  "type": "Feature",
  "properties": {
    "hierarchy": [
      "tgn:1096936",
      "tgn:7000490",
      "tgn:1000006",
      "tgn:7001828",
      "tgn:7029392"
    ],
    "placetype": [
      "aat:300008347"
    ],
    "id": 1096936,
    "name:xx": "Geehi"
  }
}
