{
  "type": "FeatureCollection",
  "features": [
    {
      "geometry": {
        "type": "Point",
        "coordinates": [
          -71.2,
          43.1167
        ]
      },
      "type": "Feature",
      "properties": {
        "hierarchy": [
          "tgn:2125830",
          "tgn:1000001",
          "tgn:7014352",
          "tgn:7012149",
          "tgn:7007564",
          "tgn:7029392"
        ],
        "placetype": [
          "aat:300008798"
        ],
        "id": 2125830,
        "name:xx": "Adams Hill"
      }
    },
    {
      "geometry": {
        "type": "Point",
        "coordinates": [
          -98.3333,
          34.6333
        ]
      },
      "type": "Feature",
      "properties": {
        "hierarchy": [
          "tgn:2125831",
          "tgn:1000001",
          "tgn:2001638",
          "tgn:7012149",
          "tgn:7007707",
          "tgn:7029392"
        ],
        "placetype": [
          "aat:300008798"
        ],
        "id": 2125831,
        "name:xx": "Adams Hill"
      }
    },
    {
      "geometry": {
        "type": "Point",
        "coordinates": [
          -87.0667,
          35.0167
        ]
      },
      "type": "Feature",
      "properties": {
        "hierarchy": [
          "tgn:2125832",
          "tgn:1000001",
          "tgn:7012149",
          "tgn:2001864",
          "tgn:7007825",
          "tgn:7029392"
        ],
        "placetype": [
          "aat:300008798"
        ],
        "id": 2125832,
        "name:xx": "Adams Hill"
      }
    },
    {
      "geometry": {
        "type": "Point",
        "coordinates": [
          -94.45,
          33.3833
        ]
      },
      "type": "Feature",
      "properties": {
        "hierarchy": [
          "tgn:2125833",
          "tgn:1000001",
          "tgn:2001944",
          "tgn:7012149",
          "tgn:7007826",
          "tgn:7029392"
        ],
        "placetype": [
          "aat:300008798"
        ],
        "id": 2125833,
        "name:xx": "Adams Hill"
      }
    },
    {
      "geometry": {
        "type": "Point",
        "coordinates": [
          -72.3,
          42.5167
        ]
      },
      "type": "Feature",
      "properties": {
        "hierarchy": [
          "tgn:2125834",
          "tgn:1000001",
          "tgn:7013942",
          "tgn:7012149",
          "tgn:7007517",
          "tgn:7029392"
        ],
        "placetype": [
          "aat:300008798"
        ],
        "id": 2125834,
        "name:xx": "Adams Hills"
      }
    },
    {
      "geometry": {
        "type": "Point",
        "coordinates": [
          -92.3667,
          35.7667
        ]
      },
      "type": "Feature",
      "properties": {
        "hierarchy": [
          "tgn:2125835",
          "tgn:1000001",
          "tgn:7016172",
          "tgn:7012149",
          "tgn:2000173",
          "tgn:7029392"
        ],
        "placetype": [
          "aat:300008761"
        ],
        "id": 2125835,
        "name:xx": "Adams Hollow"
      }
    },
    {
      "geometry": {
        "type": "Point",
        "coordinates": [
          -90.9,
          37.3833
        ]
      },
      "type": "Feature",
      "properties": {
        "hierarchy": [
          "tgn:2125836",
          "tgn:1000001",
          "tgn:7012149",
          "tgn:2001236",
          "tgn:7007523",
          "tgn:7029392"
        ],
        "placetype": [
          "aat:300008761"
        ],
        "id": 2125836,
        "name:xx": "Adams Hollow"
      }
    },
    {
      "geometry": {
        "type": "Point",
        "coordinates": [
          -92.9667,
          37.8667
        ]
      },
      "type": "Feature",
      "properties": {
        "hierarchy": [
          "tgn:2125837",
          "tgn:1000001",
          "tgn:7012149",
          "tgn:2001192",
          "tgn:7007523",
          "tgn:7029392"
        ],
        "placetype": [
          "aat:300008761"
        ],
        "id": 2125837,
        "name:xx": "Adams Hollow"
      }
    },
    {
      "geometry": {
        "type": "Point",
        "coordinates": [
          -90.35,
          37.3
        ]
      },
      "type": "Feature",
      "properties": {
        "hierarchy": [
          "tgn:2125838",
          "tgn:1000001",
          "tgn:7012149",
          "tgn:7007523",
          "tgn:7029392"
        ],
        "placetype": [
          "aat:300008761"
        ],
        "id": 2125838,
        "name:xx": "Adams Hollow"
      }
    },
    {
      "geometry": {
        "type": "Point",
        "coordinates": [
          -83.7833,
          35.5333
        ]
      },
      "type": "Feature",
      "properties": {
        "hierarchy": [
          "tgn:2125839",
          "tgn:1000001",
          "tgn:7012149",
          "tgn:2001543",
          "tgn:7007709",
          "tgn:7029392"
        ],
        "placetype": [
          "aat:300008761"
        ],
        "id": 2125839,
        "name:xx": "Adams Hollow"
      }
    }
  ]
}
