{
  "geometry": {
    "type": "Point",
    "coordinates": [
      2.45,
      49.0833
    ]
  },
  "type": "Feature",
  "properties": {
    "hierarchy": [
      "tgn:1033502",
      "tgn:1000003",
      "tgn:7002883",
      "tgn:1000070",
      "tgn:7029392"
    ],
    "placetype": [
      "aat:300008347"
    ],
    "id": 1033502,
    "name:xx": "Jagny-sous-Bois"
  }
}
