{
  "geometry": {
    "type": "Point",
    "coordinates": [
      120.8248,
      24.6725
    ]
  },
  "type": "Feature",
  "properties": {
    "hierarchy": [
      "tgn:7476161",
      "tgn:7487020",
      "tgn:1000004",
      "tgn:1000141",
      "tgn:7029392"
    ],
    "placetype": [
      "aat:300387057"
    ],
    "id": 7476161,
    "name:xx": "Zhonggang Xikou"
  }
}
