{
  "geometry": {
    "type": "Point",
    "coordinates": [
      25.5667,
      47.5333
    ]
  },
  "type": "Feature",
  "properties": {
    "hierarchy": [
      "tgn:1050058",
      "tgn:1000003",
      "tgn:7002700",
      "tgn:1000091",
      "tgn:7029392"
    ],
    "placetype": [
      "aat:300008347"
    ],
    "id": 1050058,
    "name:xx": "Cîmpulung Moldovenesc"
  }
}
