{
  "geometry": {
    "type": "Point",
    "coordinates": [
      -87.95,
      41.9333
    ]
  },
  "type": "Feature",
  "properties": {
    "hierarchy": [
      "tgn:2027171",
      "tgn:1000001",
      "tgn:7019013",
      "tgn:7012149",
      "tgn:7007251",
      "tgn:7029392"
    ],
    "placetype": [
      "aat:300008347"
    ],
    "id": 2027171,
    "name:xx": "Churchville"
  }
}
