{
  "geometry": {
    "type": "Point",
    "coordinates": [
      -106.55,
      32.55
    ]
  },
  "type": "Feature",
  "properties": {
    "hierarchy": [
      "tgn:2208054",
      "tgn:1000001",
      "tgn:2001435",
      "tgn:7012149",
      "tgn:7007566",
      "tgn:7029392"
    ],
    "placetype": [
      "aat:300008697"
    ],
    "id": 2208054,
    "name:xx": "Burke Spring"
  }
}
