{
  "geometry": {
    "type": "Point",
    "coordinates": [
      -87.8167,
      36.5333
    ]
  },
  "type": "Feature",
  "properties": {
    "hierarchy": [
      "tgn:2181337",
      "tgn:1000001",
      "tgn:7012149",
      "tgn:2001917",
      "tgn:7007825",
      "tgn:7029392"
    ],
    "placetype": [
      "aat:300008706"
    ],
    "id": 2181337,
    "name:xx": "Blue Creek"
  }
}
