{
  "geometry": {
    "type": "Point",
    "coordinates": [
      -12.6667,
      12.5833
    ]
  },
  "type": "Feature",
  "properties": {
    "hierarchy": [
      "tgn:1092550",
      "tgn:7001242",
      "tgn:1001742",
      "tgn:1000189",
      "tgn:7029392"
    ],
    "placetype": [
      "aat:300008347"
    ],
    "id": 1092550,
    "name:xx": "Tiankoye"
  }
}
