{
  "geometry": {
    "type": "Point",
    "coordinates": [
      119.3167,
      31.45
    ]
  },
  "type": "Feature",
  "properties": {
    "hierarchy": [
      "tgn:1070589",
      "tgn:1000004",
      "tgn:7002081",
      "tgn:1000111",
      "tgn:7029392"
    ],
    "placetype": [
      "aat:300008347"
    ],
    "id": 1070589,
    "name:xx": "Nandu"
  }
}
