{
  "geometry": {
    "type": "Point",
    "coordinates": [
      108.5333,
      58.6667
    ]
  },
  "type": "Feature",
  "properties": {
    "hierarchy": [
      "tgn:1051287",
      "tgn:1003373",
      "tgn:1000004",
      "tgn:7018214",
      "tgn:7002435",
      "tgn:7029392"
    ],
    "placetype": [
      "aat:300008347"
    ],
    "id": 1051287,
    "name:xx": "Cherkashina"
  }
}
