{
  "geometry": {
    "type": "Point",
    "coordinates": [
      -107.2167,
      36.5333
    ]
  },
  "type": "Feature",
  "properties": {
    "hierarchy": [
      "tgn:2240278",
      "tgn:1000001",
      "tgn:7012149",
      "tgn:2001449",
      "tgn:7007566",
      "tgn:7029392"
    ],
    "placetype": [
      "aat:300008697"
    ],
    "id": 2240278,
    "name:xx": "Ciruelas Spring"
  }
}
