{
  "geometry": {
    "type": "Point",
    "coordinates": [
      30.92758,
      30.636245
    ]
  },
  "type": "Feature",
  "properties": {
    "hierarchy": [
      "tgn:7533685",
      "tgn:7001242",
      "tgn:7016833",
      "tgn:1001087",
      "tgn:7029392"
    ],
    "placetype": [
      "aat:300008347"
    ],
    "name:en": "Kafr Mīt Abū al Kawm",
    "id": 7533685
  }
}
