{
  "geometry": {
    "type": "Point",
    "coordinates": [
      -95.3333,
      41.8167
    ]
  },
  "type": "Feature",
  "properties": {
    "hierarchy": [
      "tgn:2034630",
      "tgn:1000001",
      "tgn:7012149",
      "tgn:2000643",
      "tgn:7007253",
      "tgn:7029392"
    ],
    "placetype": [
      "aat:300008347"
    ],
    "id": 2034630,
    "name:xx": "Defiance"
  }
}
