{
  "geometry": {
    "type": "Point",
    "coordinates": [
      -80.0333,
      32.9667
    ]
  },
  "type": "Feature",
  "properties": {
    "hierarchy": [
      "tgn:2355616",
      "tgn:2001732",
      "tgn:1000001",
      "tgn:7012149",
      "tgn:7007712",
      "tgn:7029392"
    ],
    "placetype": [
      "aat:300008347"
    ],
    "id": 2355616,
    "name:xx": "Goose Creek Heights"
  }
}
