{
  "geometry": {
    "type": "Point",
    "coordinates": [
      -85.9333,
      46.3333
    ]
  },
  "type": "Feature",
  "properties": {
    "hierarchy": [
      "tgn:2053290",
      "tgn:1000001",
      "tgn:7012149",
      "tgn:2000996",
      "tgn:7007520",
      "tgn:7029392"
    ],
    "placetype": [
      "aat:300008347"
    ],
    "id": 2053290,
    "name:xx": "Seney"
  }
}
