{
  "type": "FeatureCollection",
  "features": [
    {
      "geometry": {
        "type": "Point",
        "coordinates": [
          -81.8,
          36.2
        ]
      },
      "type": "Feature",
      "properties": {
        "hierarchy": [
          "tgn:2166670",
          "tgn:1000001",
          "tgn:7012149",
          "tgn:2001551",
          "tgn:7007709",
          "tgn:7029392"
        ],
        "placetype": [
          "aat:300008699"
        ],
        "id": 2166670,
        "name:xx": "Big Branch"
      }
    },
    {
      "geometry": {
        "type": "Point",
        "coordinates": [
          -78.0167,
          36.4167
        ]
      },
      "type": "Feature",
      "properties": {
        "hierarchy": [
          "tgn:2166671",
          "tgn:1000001",
          "tgn:7012149",
          "tgn:2001549",
          "tgn:7007709",
          "tgn:7029392"
        ],
        "placetype": [
          "aat:300008699"
        ],
        "id": 2166671,
        "name:xx": "Big Branch"
      }
    },
    {
      "geometry": {
        "type": "Point",
        "coordinates": [
          -81.6333,
          36.4833
        ]
      },
      "type": "Feature",
      "properties": {
        "hierarchy": [
          "tgn:2166672",
          "tgn:2001467",
          "tgn:1000001",
          "tgn:7012149",
          "tgn:7007709",
          "tgn:7029392"
        ],
        "placetype": [
          "aat:300008699"
        ],
        "id": 2166672,
        "name:xx": "Big Branch"
      }
    },
    {
      "geometry": {
        "type": "Point",
        "coordinates": [
          -78.8667,
          34.2333
        ]
      },
      "type": "Feature",
      "properties": {
        "hierarchy": [
          "tgn:2166673",
          "tgn:1000001",
          "tgn:2001485",
          "tgn:7012149",
          "tgn:7007709",
          "tgn:7029392"
        ],
        "placetype": [
          "aat:300008699"
        ],
        "id": 2166673,
        "name:xx": "Big Branch"
      }
    },
    {
      "geometry": {
        "type": "Point",
        "coordinates": [
          -78.1333,
          34.4333
        ]
      },
      "type": "Feature",
      "properties": {
        "hierarchy": [
          "tgn:2166674",
          "tgn:1000001",
          "tgn:7012149",
          "tgn:2001527",
          "tgn:7007709",
          "tgn:7029392"
        ],
        "placetype": [
          "aat:300008699"
        ],
        "id": 2166674,
        "name:xx": "Big Branch"
      }
    },
    {
      "geometry": {
        "type": "Point",
        "coordinates": [
          -79.4667,
          34.75
        ]
      },
      "type": "Feature",
      "properties": {
        "hierarchy": [
          "tgn:2166675",
          "tgn:1000001",
          "tgn:7012149",
          "tgn:2001539",
          "tgn:7007709",
          "tgn:7029392"
        ],
        "placetype": [
          "aat:300008699"
        ],
        "id": 2166675,
        "name:xx": "Big Branch"
      }
    },
    {
      "geometry": {
        "type": "Point",
        "coordinates": [
          -78.25,
          34.75
        ]
      },
      "type": "Feature",
      "properties": {
        "hierarchy": [
          "tgn:2166676",
          "tgn:1000001",
          "tgn:7012149",
          "tgn:2001538",
          "tgn:7007709",
          "tgn:7029392"
        ],
        "placetype": [
          "aat:300008699"
        ],
        "id": 2166676,
        "name:xx": "Big Branch"
      }
    },
    {
      "geometry": {
        "type": "Point",
        "coordinates": [
          -79,
          35.1167
        ]
      },
      "type": "Feature",
      "properties": {
        "hierarchy": [
          "tgn:2166677",
          "tgn:1000001",
          "tgn:7012149",
          "tgn:2001487",
          "tgn:7007709",
          "tgn:7029392"
        ],
        "placetype": [
          "aat:300008699"
        ],
        "id": 2166677,
        "name:xx": "Big Branch"
      }
    },
    {
      "geometry": {
        "type": "Point",
        "coordinates": [
          -79.2333,
          35.3
        ]
      },
      "type": "Feature",
      "properties": {
        "hierarchy": [
          "tgn:2166678",
          "tgn:1000001",
          "tgn:7012149",
          "tgn:2001521",
          "tgn:7007709",
          "tgn:7029392"
        ],
        "placetype": [
          "aat:300008699"
        ],
        "id": 2166678,
        "name:xx": "Big Branch"
      }
    },
    {
      "geometry": {
        "type": "Point",
        "coordinates": [
          -79.8333,
          35.6167
        ]
      },
      "type": "Feature",
      "properties": {
        "hierarchy": [
          "tgn:2166679",
          "tgn:1000001",
          "tgn:7012149",
          "tgn:2001532",
          "tgn:7007709",
          "tgn:7029392"
        ],
        "placetype": [
          "aat:300008699"
        ],
        "id": 2166679,
        "name:xx": "Big Branch"
      }
    }
  ]
}
