{
  "geometry": {
    "type": "Point",
    "coordinates": [
      -78.75,
      37.55
    ]
  },
  "type": "Feature",
  "properties": {
    "hierarchy": [
      "tgn:2683661",
      "tgn:1000001",
      "tgn:2002149",
      "tgn:7012149",
      "tgn:7007919",
      "tgn:7029392"
    ],
    "placetype": [
      "aat:300008798"
    ],
    "id": 2683661,
    "name:xx": "Spears Mountain"
  }
}
