{
  "type": "FeatureCollection",
  "features": [
    {
      "geometry": {
        "type": "Point",
        "coordinates": [
          -96.75,
          20.066667
        ]
      },
      "type": "Feature",
      "properties": {
        "hierarchy": [
          "tgn:7435560",
          "tgn:1000001",
          "tgn:7005599",
          "tgn:7005560",
          "tgn:7029392"
        ],
        "placetype": [
          "aat:300008347"
        ],
        "id": 7435560,
        "name:xx": "Zapotal"
      }
    },
    {
      "geometry": {
        "type": "Point",
        "coordinates": [
          -92.2,
          18.116667
        ]
      },
      "type": "Feature",
      "properties": {
        "hierarchy": [
          "tgn:7435561",
          "tgn:1000001",
          "tgn:7005596",
          "tgn:7005560",
          "tgn:7029392"
        ],
        "placetype": [
          "aat:300008347"
        ],
        "id": 7435561,
        "name:xx": "Zapotal"
      }
    },
    {
      "geometry": {
        "type": "Point",
        "coordinates": [
          -93.5,
          18.083333
        ]
      },
      "type": "Feature",
      "properties": {
        "hierarchy": [
          "tgn:7435562",
          "tgn:1000001",
          "tgn:7005599",
          "tgn:7005560",
          "tgn:7029392"
        ],
        "placetype": [
          "aat:300008347"
        ],
        "id": 7435562,
        "name:xx": "Zapotal"
      }
    },
    {
      "geometry": {
        "type": "Point",
        "coordinates": [
          -94.433333,
          17.966667
        ]
      },
      "type": "Feature",
      "properties": {
        "hierarchy": [
          "tgn:7435563",
          "tgn:1000001",
          "tgn:7005599",
          "tgn:7005560",
          "tgn:7029392"
        ],
        "placetype": [
          "aat:300008347"
        ],
        "id": 7435563,
        "name:xx": "Zapotal"
      }
    },
    {
      "geometry": {
        "type": "Point",
        "coordinates": [
          -95.833333,
          17.75
        ]
      },
      "type": "Feature",
      "properties": {
        "hierarchy": [
          "tgn:7435564",
          "tgn:1000001",
          "tgn:7005599",
          "tgn:7005560",
          "tgn:7029392"
        ],
        "placetype": [
          "aat:300008347"
        ],
        "id": 7435564,
        "name:xx": "Zapotal"
      }
    },
    {
      "geometry": {
        "type": "Point",
        "coordinates": [
          -95.033333,
          16.766667
        ]
      },
      "type": "Feature",
      "properties": {
        "hierarchy": [
          "tgn:7435565",
          "tgn:1000001",
          "tgn:7005591",
          "tgn:7005560",
          "tgn:7029392"
        ],
        "placetype": [
          "aat:300008347"
        ],
        "id": 7435565,
        "name:xx": "Zapotal"
      }
    },
    {
      "geometry": {
        "type": "Point",
        "coordinates": [
          -91.433333,
          16.75
        ]
      },
      "type": "Feature",
      "properties": {
        "hierarchy": [
          "tgn:7435566",
          "tgn:7005580",
          "tgn:1000001",
          "tgn:7005560",
          "tgn:7029392"
        ],
        "placetype": [
          "aat:300008347"
        ],
        "id": 7435566,
        "name:xx": "Zapotal"
      }
    },
    {
      "geometry": {
        "type": "Point",
        "coordinates": [
          -96.566667,
          15.666667
        ]
      },
      "type": "Feature",
      "properties": {
        "hierarchy": [
          "tgn:7435567",
          "tgn:1000001",
          "tgn:7005591",
          "tgn:7005560",
          "tgn:7029392"
        ],
        "placetype": [
          "aat:300008347"
        ],
        "id": 7435567,
        "name:xx": "Zapotal"
      }
    },
    {
      "geometry": {
        "type": "Point",
        "coordinates": [
          -92.433333,
          14.783333
        ]
      },
      "type": "Feature",
      "properties": {
        "hierarchy": [
          "tgn:7435569",
          "tgn:7005580",
          "tgn:1000001",
          "tgn:7005560",
          "tgn:7029392"
        ],
        "placetype": [
          "aat:300008347"
        ],
        "id": 7435569,
        "name:xx": "Zapotal"
      }
    }
  ]
}
