{
  "type": "FeatureCollection",
  "features": [
    {
      "geometry": {
        "type": "Point",
        "coordinates": [
          -76.0167,
          38.85
        ]
      },
      "type": "Feature",
      "properties": {
        "hierarchy": [
          "tgn:2524500",
          "tgn:1000001",
          "tgn:2000939",
          "tgn:7012149",
          "tgn:7007516",
          "tgn:7029392"
        ],
        "placetype": [
          "aat:300008347"
        ],
        "id": 2524500,
        "name:xx": "Morgans Neglect"
      }
    },
    {
      "geometry": {
        "type": "Point",
        "coordinates": [
          -94.9833,
          29.6667
        ]
      },
      "type": "Feature",
      "properties": {
        "hierarchy": [
          "tgn:2524501",
          "tgn:1000001",
          "tgn:7012149",
          "tgn:1002456",
          "tgn:7007826",
          "tgn:7029392"
        ],
        "placetype": [
          "aat:300008850"
        ],
        "id": 2524501,
        "name:xx": "Morgans Point"
      }
    },
    {
      "geometry": {
        "type": "Point",
        "coordinates": [
          -97.4667,
          31.1333
        ]
      },
      "type": "Feature",
      "properties": {
        "hierarchy": [
          "tgn:2524502",
          "tgn:1000001",
          "tgn:1002174",
          "tgn:7012149",
          "tgn:7007826",
          "tgn:7029392"
        ],
        "placetype": [
          "aat:300008850"
        ],
        "id": 2524502,
        "name:xx": "Morgans Point"
      }
    },
    {
      "geometry": {
        "type": "Point",
        "coordinates": [
          -85.95,
          31.85
        ]
      },
      "type": "Feature",
      "properties": {
        "hierarchy": [
          "tgn:2524503",
          "tgn:7002659",
          "tgn:1000001",
          "tgn:7012149",
          "tgn:2000054",
          "tgn:7029392"
        ],
        "placetype": [
          "aat:300006191"
        ],
        "id": 2524503,
        "name:xx": "Morgans Pond"
      }
    },
    {
      "geometry": {
        "type": "Point",
        "coordinates": [
          -86.95,
          31.4333
        ]
      },
      "type": "Feature",
      "properties": {
        "hierarchy": [
          "tgn:2524504",
          "tgn:7002659",
          "tgn:1000001",
          "tgn:2000017",
          "tgn:7012149",
          "tgn:7029392"
        ],
        "placetype": [
          "aat:300006191"
        ],
        "id": 2524504,
        "name:xx": "Morgans Pond"
      }
    },
    {
      "geometry": {
        "type": "Point",
        "coordinates": [
          -81.3333,
          32.1833
        ]
      },
      "type": "Feature",
      "properties": {
        "hierarchy": [
          "tgn:2524505",
          "tgn:1000001",
          "tgn:7012149",
          "tgn:2000342",
          "tgn:7007248",
          "tgn:7029392"
        ],
        "placetype": [
          "aat:300008680"
        ],
        "id": 2524505,
        "name:xx": "Morgans Pond"
      }
    },
    {
      "geometry": {
        "type": "Point",
        "coordinates": [
          -82.7667,
          32.85
        ]
      },
      "type": "Feature",
      "properties": {
        "hierarchy": [
          "tgn:2524506",
          "tgn:1000001",
          "tgn:7012149",
          "tgn:2000441",
          "tgn:7007248",
          "tgn:7029392"
        ],
        "placetype": [
          "aat:300008680"
        ],
        "id": 2524506,
        "name:xx": "Morgans Pond"
      }
    },
    {
      "geometry": {
        "type": "Point",
        "coordinates": [
          -81.3333,
          32.1833
        ]
      },
      "type": "Feature",
      "properties": {
        "hierarchy": [
          "tgn:2524507",
          "tgn:1000001",
          "tgn:7012149",
          "tgn:2000342",
          "tgn:7007248",
          "tgn:7029392"
        ],
        "placetype": [
          "aat:300006191"
        ],
        "id": 2524507,
        "name:xx": "Morgans Pond"
      }
    },
    {
      "geometry": {
        "type": "Point",
        "coordinates": [
          -72.1667,
          42.1333
        ]
      },
      "type": "Feature",
      "properties": {
        "hierarchy": [
          "tgn:2524508",
          "tgn:1000001",
          "tgn:7019982",
          "tgn:7012149",
          "tgn:7007517",
          "tgn:7029392"
        ],
        "placetype": [
          "aat:300008905"
        ],
        "id": 2524508,
        "name:xx": "Morgans Pond"
      }
    },
    {
      "geometry": {
        "type": "Point",
        "coordinates": [
          -79.6833,
          34.95
        ]
      },
      "type": "Feature",
      "properties": {
        "hierarchy": [
          "tgn:2524509",
          "tgn:1000001",
          "tgn:7012149",
          "tgn:2001533",
          "tgn:7007709",
          "tgn:7029392"
        ],
        "placetype": [
          "aat:300006191"
        ],
        "id": 2524509,
        "name:xx": "Morgans Pond"
      }
    }
  ]
}
