{
  "geometry": {
    "type": "Point",
    "coordinates": [
      -112.9333,
      31.95
    ]
  },
  "type": "Feature",
  "properties": {
    "hierarchy": [
      "tgn:2124981",
      "tgn:1000001",
      "tgn:7006451",
      "tgn:7012149",
      "tgn:2000100",
      "tgn:7029392"
    ],
    "placetype": [
      "aat:300008805"
    ],
    "id": 2124981,
    "name:xx": "Abra Plain, La"
  }
}
