{
  "geometry": {
    "type": "Point",
    "coordinates": [
      -117.35,
      43.2667
    ]
  },
  "type": "Feature",
  "properties": {
    "hierarchy": [
      "tgn:2350138",
      "tgn:1000001",
      "tgn:7012149",
      "tgn:2001718",
      "tgn:7007708",
      "tgn:7029392"
    ],
    "placetype": [
      "aat:300386845"
    ],
    "id": 2350138,
    "name:xx": "Gin Basin"
  }
}
