{
  "geometry": {
    "type": "Point",
    "coordinates": [
      34.664167,
      30.026389
    ]
  },
  "type": "Feature",
  "properties": {
    "hierarchy": [
      "tgn:7529936",
      "tgn:7001242",
      "tgn:7016833",
      "tgn:7001335",
      "tgn:7029392"
    ],
    "placetype": [
      "aat:300379998"
    ],
    "name:en": "Abū Juway', Wādī",
    "id": 7529936
  }
}
