{
  "geometry": {
    "type": "Point",
    "coordinates": [
      -70.833333,
      -33.25
    ]
  },
  "type": "Feature",
  "properties": {
    "hierarchy": [
      "tgn:7292685",
      "tgn:1001708",
      "tgn:1000049",
      "tgn:1000002",
      "tgn:7029392"
    ],
    "placetype": [
      "aat:300000206"
    ],
    "id": 7292685,
    "name:xx": "El Desengaño"
  }
}
