{
  "geometry": {
    "type": "Point",
    "coordinates": [
      -176.8333,
      51.8167
    ]
  },
  "type": "Feature",
  "properties": {
    "hierarchy": [
      "tgn:2152539",
      "tgn:7030516",
      "tgn:7006450",
      "tgn:1000001",
      "tgn:7012149",
      "tgn:7029392"
    ],
    "placetype": [
      "aat:300386853"
    ],
    "id": 2152539,
    "name:xx": "Bay of Islands"
  }
}
