{
  "geometry": {
    "type": "Point",
    "coordinates": [
      -92.9333,
      40.2333
    ]
  },
  "type": "Feature",
  "properties": {
    "hierarchy": [
      "tgn:1133118",
      "tgn:1000001",
      "tgn:7012149",
      "tgn:7007523",
      "tgn:7029392"
    ],
    "placetype": [
      "aat:300008706"
    ],
    "id": 1133118,
    "name:xx": "East Yellow Creek"
  }
}
