{
  "geometry": {
    "type": "Point",
    "coordinates": [
      -116.1333,
      45.7667
    ]
  },
  "type": "Feature",
  "properties": {
    "hierarchy": [
      "tgn:2585064",
      "tgn:1000001",
      "tgn:7012149",
      "tgn:2000476",
      "tgn:7007250",
      "tgn:7029392"
    ],
    "placetype": [
      "aat:300266640"
    ],
    "id": 2585064,
    "name:xx": "Pinnacle Ridge"
  }
}
