{
  "geometry": {
    "type": "Point",
    "coordinates": [
      23.2167,
      4.5833
    ]
  },
  "type": "Feature",
  "properties": {
    "hierarchy": [
      "tgn:1088935",
      "tgn:7001242",
      "tgn:7016755",
      "tgn:1000159",
      "tgn:7029392"
    ],
    "placetype": [
      "aat:300008347"
    ],
    "id": 1088935,
    "name:xx": "Dongobe"
  }
}
