{
  "geometry": {
    "type": "Point",
    "coordinates": [
      -2.75,
      8.05
    ]
  },
  "type": "Feature",
  "properties": {
    "hierarchy": [
      "tgn:1090319",
      "tgn:7001242",
      "tgn:1000530",
      "tgn:1000168",
      "tgn:7029392"
    ],
    "placetype": [
      "aat:300008347"
    ],
    "id": 1090319,
    "name:xx": "Bondoukou"
  }
}
