{
  "geometry": {
    "type": "Point",
    "coordinates": [
      11.75,
      53.716667
    ]
  },
  "type": "Feature",
  "properties": {
    "hierarchy": [
      "tgn:7203989",
      "tgn:1000003",
      "tgn:7000094",
      "tgn:7000084",
      "tgn:7029392"
    ],
    "placetype": [
      "aat:300008699"
    ],
    "id": 7203989,
    "name:xx": "Brüeler-Berg"
  }
}
