{
  "type": "FeatureCollection",
  "features": [
    {
      "geometry": {
        "type": "Point",
        "coordinates": [
          30.75,
          27.75
        ]
      },
      "type": "Feature",
      "properties": {
        "hierarchy": [
          "tgn:7521541",
          "tgn:7001242",
          "tgn:7016833",
          "tgn:1001088",
          "tgn:7029392"
        ],
        "placetype": [
          "aat:300008347"
        ],
        "name:en": "Al 'Arīn Qiblī",
        "id": 7521541
      }
    },
    {
      "geometry": {
        "type": "Point",
        "coordinates": [
          30.75,
          27.783333
        ]
      },
      "type": "Feature",
      "properties": {
        "hierarchy": [
          "tgn:7521542",
          "tgn:7001242",
          "tgn:7016833",
          "tgn:1001088",
          "tgn:7029392"
        ],
        "placetype": [
          "aat:300008347"
        ],
        "name:en": "Al 'Arīn al Baḩrī",
        "id": 7521542
      }
    },
    {
      "geometry": {
        "type": "Point",
        "coordinates": [
          31.747973,
          30.753391
        ]
      },
      "type": "Feature",
      "properties": {
        "hierarchy": [
          "tgn:7521543",
          "tgn:7001242",
          "tgn:7016833",
          "tgn:1001113",
          "tgn:7029392"
        ],
        "placetype": [
          "aat:300008347"
        ],
        "id": 7521543,
        "name:xx": "Al 'Ārīn"
      }
    },
    {
      "geometry": {
        "type": "Point",
        "coordinates": [
          30.766667,
          27.383333
        ]
      },
      "type": "Feature",
      "properties": {
        "hierarchy": [
          "tgn:7521544",
          "tgn:7001242",
          "tgn:7016833",
          "tgn:1001114",
          "tgn:7029392"
        ],
        "placetype": [
          "aat:300008347"
        ],
        "name:en": "Al 'Arīḑah",
        "id": 7521544
      }
    },
    {
      "geometry": {
        "type": "Point",
        "coordinates": [
          33.95,
          28.533333
        ]
      },
      "type": "Feature",
      "properties": {
        "hierarchy": [
          "tgn:7521545",
          "tgn:7001242",
          "tgn:7016833",
          "tgn:7001336",
          "tgn:7029392"
        ],
        "placetype": [
          "aat:300008057"
        ],
        "name:en": "Al Arba'īn",
        "id": 7521545
      }
    },
    {
      "geometry": {
        "type": "Point",
        "coordinates": [
          32.55,
          29.966667
        ]
      },
      "type": "Feature",
      "properties": {
        "hierarchy": [
          "tgn:7521546",
          "tgn:7001242",
          "tgn:7016833",
          "tgn:1001110",
          "tgn:7029392"
        ],
        "placetype": [
          "aat:300007783"
        ],
        "name:en": "Al Arba'īn",
        "id": 7521546
      }
    },
    {
      "geometry": {
        "type": "Point",
        "coordinates": [
          32.533333,
          29.966667
        ]
      },
      "type": "Feature",
      "properties": {
        "hierarchy": [
          "tgn:7521547",
          "tgn:7001242",
          "tgn:7016833",
          "tgn:1001110",
          "tgn:7029392"
        ],
        "placetype": [
          "aat:300000745"
        ],
        "name:en": "Al Arba'īn",
        "id": 7521547
      }
    },
    {
      "geometry": {
        "type": "Point",
        "coordinates": [
          31.433333,
          26.883333
        ]
      },
      "type": "Feature",
      "properties": {
        "hierarchy": [
          "tgn:7521548",
          "tgn:7001242",
          "tgn:7016833",
          "tgn:7000124",
          "tgn:7029392"
        ],
        "placetype": [
          "aat:300008347"
        ],
        "name:en": "Al Arba'īn",
        "id": 7521548
      }
    },
    {
      "geometry": {
        "type": "Point",
        "coordinates": [
          31.387838,
          30.472405
        ]
      },
      "type": "Feature",
      "properties": {
        "hierarchy": [
          "tgn:7521549",
          "tgn:7001242",
          "tgn:7016833",
          "tgn:1001113",
          "tgn:7029392"
        ],
        "placetype": [
          "aat:300008347"
        ],
        "name:en": "Al A'rās",
        "id": 7521549
      }
    }
  ]
}
