{
  "geometry": {
    "type": "Point",
    "coordinates": [
      27.25,
      -16.7667
    ]
  },
  "type": "Feature",
  "properties": {
    "hierarchy": [
      "tgn:1095891",
      "tgn:7001242",
      "tgn:1001544",
      "tgn:1000209",
      "tgn:7029392"
    ],
    "placetype": [
      "aat:300008347"
    ],
    "id": 1095891,
    "name:xx": "Batoka"
  }
}
