{
  "geometry": {
    "type": "Point",
    "coordinates": [
      -72.4667,
      41.3167
    ]
  },
  "type": "Feature",
  "properties": {
    "hierarchy": [
      "tgn:2783340",
      "tgn:1000001",
      "tgn:1002664",
      "tgn:7012149",
      "tgn:7007159",
      "tgn:7029392"
    ],
    "placetype": [
      "aat:300006191"
    ],
    "id": 2783340,
    "name:xx": "Wrights Pond"
  }
}
