{
  "geometry": {
    "type": "Point",
    "coordinates": [
      -93.8167,
      33.7667
    ]
  },
  "type": "Feature",
  "properties": {
    "hierarchy": [
      "tgn:2348691",
      "tgn:1000001",
      "tgn:7016172",
      "tgn:7012149",
      "tgn:7029392"
    ],
    "placetype": [
      "aat:300008706"
    ],
    "id": 2348691,
    "name:xx": "Gibson Creek"
  }
}
