{
  "type": "FeatureCollection",
  "features": [
    {
      "geometry": {
        "type": "Point",
        "coordinates": [
          -5.6,
          54.55
        ]
      },
      "type": "Feature",
      "properties": {
        "hierarchy": [
          "tgn:7457200",
          "tgn:7019182",
          "tgn:7002448",
          "tgn:1000003",
          "tgn:7008591",
          "tgn:7029392"
        ],
        "placetype": [
          "aat:300387502"
        ],
        "name:en": "Mount Stewart House",
        "id": 7457200
      }
    },
    {
      "geometry": {
        "type": "Point",
        "coordinates": [
          -6.633333,
          55.1
        ]
      },
      "type": "Feature",
      "properties": {
        "hierarchy": [
          "tgn:7457203",
          "tgn:7002448",
          "tgn:7019216",
          "tgn:1000003",
          "tgn:7008591",
          "tgn:7029392"
        ],
        "placetype": [
          "aat:300004792"
        ],
        "name:en": "Mountsandel Cottage",
        "id": 7457203
      }
    },
    {
      "geometry": {
        "type": "Point",
        "coordinates": [
          -1.7,
          51.166667
        ]
      },
      "type": "Feature",
      "properties": {
        "hierarchy": [
          "tgn:7457204",
          "tgn:7002445",
          "tgn:1000003",
          "tgn:7008180",
          "tgn:7008591",
          "tgn:7029392"
        ],
        "placetype": [
          "aat:300000206"
        ],
        "name:en": "Mount Pleasant Farm",
        "id": 7457204
      }
    },
    {
      "geometry": {
        "type": "Point",
        "coordinates": [
          -7.333333,
          54.616667
        ]
      },
      "type": "Feature",
      "properties": {
        "hierarchy": [
          "tgn:7457205",
          "tgn:7002448",
          "tgn:1000003",
          "tgn:7019206",
          "tgn:7008591",
          "tgn:7029392"
        ],
        "placetype": [
          "aat:300008347"
        ],
        "name:en": "Mount Pleasant",
        "id": 7457205
      }
    },
    {
      "geometry": {
        "type": "Point",
        "coordinates": [
          -6.466667,
          54.233333
        ]
      },
      "type": "Feature",
      "properties": {
        "hierarchy": [
          "tgn:7457206",
          "tgn:7002448",
          "tgn:1000003",
          "tgn:7019199",
          "tgn:7008591",
          "tgn:7029392"
        ],
        "placetype": [
          "aat:300008347"
        ],
        "name:en": "Mount Norris",
        "id": 7457206
      }
    },
    {
      "geometry": {
        "type": "Point",
        "coordinates": [
          -2.833333,
          56.316667
        ]
      },
      "type": "Feature",
      "properties": {
        "hierarchy": [
          "tgn:7457208",
          "tgn:7002444",
          "tgn:1000003",
          "tgn:7008076",
          "tgn:7008591",
          "tgn:7029392"
        ],
        "placetype": [
          "aat:300387502"
        ],
        "name:en": "Mount Melville",
        "id": 7457208
      }
    },
    {
      "geometry": {
        "type": "Point",
        "coordinates": [
          -7.35,
          54.65
        ]
      },
      "type": "Feature",
      "properties": {
        "hierarchy": [
          "tgn:7457209",
          "tgn:7002448",
          "tgn:1000003",
          "tgn:7019206",
          "tgn:7008591",
          "tgn:7029392"
        ],
        "placetype": [
          "aat:300008347"
        ],
        "name:en": "Mountjoy",
        "id": 7457209
      }
    }
  ]
}
