{
  "geometry": {
    "type": "Point",
    "coordinates": [
      127.0667,
      37.7667
    ]
  },
  "type": "Feature",
  "properties": {
    "hierarchy": [
      "tgn:1082293",
      "tgn:1000004",
      "tgn:1001370",
      "tgn:7000299",
      "tgn:7029392"
    ],
    "placetype": [
      "aat:300008347"
    ],
    "id": 1082293,
    "name:xx": "Majŏn-ni"
  }
}
