{
  "geometry": {
    "type": "Point",
    "coordinates": [
      -122.5833,
      37.9167
    ]
  },
  "type": "Feature",
  "properties": {
    "hierarchy": [
      "tgn:2509105",
      "tgn:1000001",
      "tgn:7012149",
      "tgn:7007157",
      "tgn:7014005",
      "tgn:7029392"
    ],
    "placetype": [
      "aat:300008706"
    ],
    "id": 2509105,
    "name:xx": "Middle Fork Lagunitas Creek"
  }
}
