{
  "geometry": {
    "type": "Point",
    "coordinates": [
      -84.3667,
      39.7667
    ]
  },
  "type": "Feature",
  "properties": {
    "hierarchy": [
      "tgn:2344594",
      "tgn:1000001",
      "tgn:7012149",
      "tgn:1002689",
      "tgn:7007706",
      "tgn:7029392"
    ],
    "placetype": [
      "aat:300008699"
    ],
    "id": 2344594,
    "name:xx": "Garber Run"
  }
}
