{
  "type": "FeatureCollection",
  "features": [
    {
      "geometry": {
        "type": "Point",
        "coordinates": [
          -2.566667,
          56.2
        ]
      },
      "type": "Feature",
      "properties": {
        "hierarchy": [
          "tgn:7458063",
          "tgn:7002444",
          "tgn:1000003",
          "tgn:7008076",
          "tgn:7008591",
          "tgn:7029392"
        ],
        "placetype": [
          "aat:300011692"
        ],
        "name:en": "Norman Rock",
        "id": 7458063
      }
    },
    {
      "geometry": {
        "type": "Point",
        "coordinates": [
          -0.65,
          51.25
        ]
      },
      "type": "Feature",
      "properties": {
        "hierarchy": [
          "tgn:7458064",
          "tgn:7002445",
          "tgn:1000003",
          "tgn:7008175",
          "tgn:7008591",
          "tgn:7029392"
        ],
        "placetype": [
          "aat:300008347"
        ],
        "name:en": "Normandy",
        "id": 7458064
      }
    },
    {
      "geometry": {
        "type": "Point",
        "coordinates": [
          -1.616667,
          51.066667
        ]
      },
      "type": "Feature",
      "properties": {
        "hierarchy": [
          "tgn:7458065",
          "tgn:7002445",
          "tgn:1000003",
          "tgn:7008139",
          "tgn:7008591",
          "tgn:7029392"
        ],
        "placetype": [
          "aat:300387502"
        ],
        "name:en": "Norman Court",
        "id": 7458065
      }
    },
    {
      "geometry": {
        "type": "Point",
        "coordinates": [
          -0.866667,
          54.216667
        ]
      },
      "type": "Feature",
      "properties": {
        "hierarchy": [
          "tgn:7458067",
          "tgn:7002445",
          "tgn:1000003",
          "tgn:7008166",
          "tgn:7008591",
          "tgn:7029392"
        ],
        "placetype": [
          "aat:300008347"
        ],
        "name:en": "Normanby",
        "id": 7458067
      }
    },
    {
      "geometry": {
        "type": "Point",
        "coordinates": [
          -0.5,
          53.366667
        ]
      },
      "type": "Feature",
      "properties": {
        "hierarchy": [
          "tgn:7458068",
          "tgn:7002445",
          "tgn:1000003",
          "tgn:7008157",
          "tgn:7008591",
          "tgn:7029392"
        ],
        "placetype": [
          "aat:300008347"
        ],
        "name:en": "Normanby",
        "id": 7458068
      }
    },
    {
      "geometry": {
        "type": "Point",
        "coordinates": [
          -1.483333,
          50.766667
        ]
      },
      "type": "Feature",
      "properties": {
        "hierarchy": [
          "tgn:7458069",
          "tgn:7002445",
          "tgn:1000003",
          "tgn:7008139",
          "tgn:7008591",
          "tgn:7029392"
        ],
        "placetype": [
          "aat:300008347"
        ],
        "name:en": "Norleywood",
        "id": 7458069
      }
    }
  ]
}
