{
  "geometry": {
    "type": "Point",
    "coordinates": [
      -118.3333,
      35.7667
    ]
  },
  "type": "Feature",
  "properties": {
    "hierarchy": [
      "tgn:2214523",
      "tgn:1000001",
      "tgn:7012149",
      "tgn:1002545",
      "tgn:7007157",
      "tgn:7029392"
    ],
    "placetype": [
      "aat:300008706"
    ],
    "id": 2214523,
    "name:xx": "Caldwell Creek"
  }
}
