{
  "geometry": {
    "type": "Point",
    "coordinates": [
      124.75,
      9.1667
    ]
  },
  "type": "Feature",
  "properties": {
    "hierarchy": [
      "tgn:7005901",
      "tgn:1000004",
      "tgn:1000135",
      "tgn:7029392"
    ],
    "placetype": [
      "aat:300387064",
      "aat:300000774"
    ],
    "id": 7005901,
    "name:xx": "Camiguin"
  }
}
