{
  "geometry": {
    "type": "Point",
    "coordinates": [
      -113.1333,
      37.4833
    ]
  },
  "type": "Feature",
  "properties": {
    "hierarchy": [
      "tgn:2216627",
      "tgn:1000001",
      "tgn:7012149",
      "tgn:7007827",
      "tgn:7029392"
    ],
    "placetype": [
      "aat:300008706"
    ],
    "id": 2216627,
    "name:xx": "Camp Creek"
  }
}
