{
  "geometry": {
    "type": "Point",
    "coordinates": [
      -112.9833,
      35.65
    ]
  },
  "type": "Feature",
  "properties": {
    "hierarchy": [
      "tgn:2265735",
      "tgn:1000001",
      "tgn:7006451",
      "tgn:2000092",
      "tgn:7012149",
      "tgn:7029392"
    ],
    "placetype": [
      "aat:300008761"
    ],
    "id": 2265735,
    "name:xx": "Crater Canyon"
  }
}
