{
  "geometry": {
    "type": "Point",
    "coordinates": [
      -80.0667,
      34.9167
    ]
  },
  "type": "Feature",
  "properties": {
    "hierarchy": [
      "tgn:2240481",
      "tgn:2001466",
      "tgn:1000001",
      "tgn:7012149",
      "tgn:7007709",
      "tgn:7029392"
    ],
    "placetype": [
      "aat:300006191"
    ],
    "id": 2240481,
    "name:xx": "City Pond"
  }
}
