{
  "type": "FeatureCollection",
  "features": [
    {
      "geometry": {
        "type": "Point",
        "coordinates": [
          5.833333,
          52.083333
        ]
      },
      "type": "Feature",
      "properties": {
        "hierarchy": [
          "tgn:7018782",
          "tgn:7003619",
          "tgn:1000003",
          "tgn:7016845",
          "tgn:7029392"
        ],
        "placetype": [
          "aat:300008189",
          "aat:300008187"
        ],
        "id": 7018782,
        "name:xx": "Hoge Veluwe, Nationale Park de"
      }
    },
    {
      "geometry": {
        "type": "Point",
        "coordinates": [
          11.516667,
          42.816667
        ]
      },
      "type": "Feature",
      "properties": {
        "hierarchy": [
          "tgn:7018786",
          "tgn:7003168",
          "tgn:1000003",
          "tgn:7009760",
          "tgn:1000080",
          "tgn:7029392"
        ],
        "placetype": [
          "aat:300008795"
        ],
        "id": 7018786,
        "name:xx": "Monte Labbro"
      }
    },
    {
      "geometry": {
        "type": "Point",
        "coordinates": [
          -88.95,
          16.2667
        ]
      },
      "type": "Feature",
      "properties": {
        "hierarchy": [
          "tgn:7018787",
          "tgn:1000941",
          "tgn:7005346",
          "tgn:1000001",
          "tgn:7029392"
        ],
        "placetype": [
          "aat:300017826",
          "aat:300008347",
          "aat:300000810",
          "aat:300167671"
        ],
        "id": 7018787,
        "name:xx": "Lubaantún"
      }
    },
    {
      "geometry": {
        "type": "Point",
        "coordinates": [
          14.083,
          40.833
        ]
      },
      "type": "Feature",
      "properties": {
        "hierarchy": [
          "tgn:7018789",
          "tgn:7003013",
          "tgn:7003005",
          "tgn:1000003",
          "tgn:1000080",
          "tgn:7029392"
        ],
        "placetype": [
          "aat:300008347",
          "aat:300000810",
          "aat:300167671"
        ],
        "id": 7018789,
        "name:xx": "Arco Felice-Lucrino"
      }
    }
  ]
}
