{
  "geometry": {
    "type": "Point",
    "coordinates": [
      -89.0833,
      35.4167
    ]
  },
  "type": "Feature",
  "properties": {
    "hierarchy": [
      "tgn:2232860",
      "tgn:1000001",
      "tgn:7012149",
      "tgn:2001871",
      "tgn:7007825",
      "tgn:7029392"
    ],
    "placetype": [
      "aat:300008905"
    ],
    "id": 2232860,
    "name:xx": "Chapman Swamp"
  }
}
