{
  "geometry": {
    "type": "Point",
    "coordinates": [
      -82.3333,
      39.2167
    ]
  },
  "type": "Feature",
  "properties": {
    "hierarchy": [
      "tgn:2468891",
      "tgn:1000001",
      "tgn:7012149",
      "tgn:7007706",
      "tgn:7029392"
    ],
    "placetype": [
      "aat:300008699"
    ],
    "id": 2468891,
    "name:xx": "Long Run"
  }
}
