{
  "geometry": {
    "type": "Point",
    "coordinates": [
      -87.4167,
      34.6333
    ]
  },
  "type": "Feature",
  "properties": {
    "hierarchy": [
      "tgn:2441071",
      "tgn:7002659",
      "tgn:1000001",
      "tgn:7012149",
      "tgn:2000039",
      "tgn:7029392"
    ],
    "placetype": [
      "aat:300006191"
    ],
    "id": 2441071,
    "name:xx": "Knoff Lake"
  }
}
