{
  "geometry": {
    "type": "Point",
    "coordinates": [
      -81.2167,
      36.7333
    ]
  },
  "type": "Feature",
  "properties": {
    "hierarchy": [
      "tgn:2743619",
      "tgn:1000001",
      "tgn:7012149",
      "tgn:2002164",
      "tgn:7007919",
      "tgn:7029392"
    ],
    "placetype": [
      "aat:300008699"
    ],
    "id": 2743619,
    "name:xx": "Vaughn Branch"
  }
}
