{
  "geometry": {
    "type": "Point",
    "coordinates": [
      -149.6667,
      61.25
    ]
  },
  "type": "Feature",
  "properties": {
    "hierarchy": [
      "tgn:2547346",
      "tgn:2124017",
      "tgn:7006450",
      "tgn:1000001",
      "tgn:7012149",
      "tgn:7029392"
    ],
    "placetype": [
      "aat:300008706"
    ],
    "id": 2547346,
    "name:xx": "North Fork Ship Creek"
  }
}
