{
  "geometry": {
    "type": "Point",
    "coordinates": [
      13.45,
      51.55
    ]
  },
  "type": "Feature",
  "properties": {
    "hierarchy": [
      "tgn:7072845",
      "tgn:7000096",
      "tgn:1000003",
      "tgn:7000084",
      "tgn:7029392"
    ],
    "placetype": [
      "aat:300008347"
    ],
    "id": 7072845,
    "name:xx": "Thalberg"
  }
}
