{
  "geometry": {
    "type": "Point",
    "coordinates": [
      -69.5167,
      44.0167
    ]
  },
  "type": "Feature",
  "properties": {
    "hierarchy": [
      "tgn:7017809",
      "tgn:1000001",
      "tgn:2000925",
      "tgn:7012149",
      "tgn:7007515",
      "tgn:7029392"
    ],
    "placetype": [
      "aat:300008347"
    ],
    "id": 7017809,
    "name:xx": "Damariscotta"
  }
}
