{
  "geometry": {
    "type": "Point",
    "coordinates": [
      -97.2167,
      45.7333
    ]
  },
  "type": "Feature",
  "properties": {
    "hierarchy": [
      "tgn:2690773",
      "tgn:1000001",
      "tgn:7012149",
      "tgn:7007713",
      "tgn:7029392"
    ],
    "placetype": [
      "aat:300008706"
    ],
    "id": 2690773,
    "name:xx": "Standfast Creek"
  }
}
