{
  "geometry": {
    "type": "Point",
    "coordinates": [
      31.4667,
      -28.45
    ]
  },
  "type": "Feature",
  "properties": {
    "hierarchy": [
      "tgn:1100675",
      "tgn:7001242",
      "tgn:7016749",
      "tgn:1000193",
      "tgn:7029392"
    ],
    "placetype": [
      "aat:300000833"
    ],
    "id": 1100675,
    "name:xx": "Umgungundhlovu"
  }
}
