{
  "geometry": {
    "type": "Point",
    "coordinates": [
      -108.8833,
      45.4667
    ]
  },
  "type": "Feature",
  "properties": {
    "hierarchy": [
      "tgn:2305928",
      "tgn:1000001",
      "tgn:2001264",
      "tgn:7012149",
      "tgn:7007524",
      "tgn:7029392"
    ],
    "placetype": [
      "aat:300006075"
    ],
    "id": 2305928,
    "name:xx": "East Elbow Ditch"
  }
}
