{
  "geometry": {
    "type": "Point",
    "coordinates": [
      -111.75,
      39.8167
    ]
  },
  "type": "Feature",
  "properties": {
    "hierarchy": [
      "tgn:2543692",
      "tgn:1000001",
      "tgn:7012149",
      "tgn:7007827",
      "tgn:7029392"
    ],
    "placetype": [
      "aat:300386845"
    ],
    "id": 2543692,
    "name:xx": "North Basin"
  }
}
