{
  "geometry": {
    "type": "Point",
    "coordinates": [
      -75.8667,
      43.0667
    ]
  },
  "type": "Feature",
  "properties": {
    "hierarchy": [
      "tgn:2071272",
      "tgn:1000001",
      "tgn:7012149",
      "tgn:1002624",
      "tgn:7007568",
      "tgn:7029392"
    ],
    "placetype": [
      "aat:300008347"
    ],
    "id": 2071272,
    "name:xx": "North Chittenango"
  }
}
