{
  "geometry": {
    "type": "Point",
    "coordinates": [
      -84.6167,
      36.2667
    ]
  },
  "type": "Feature",
  "properties": {
    "hierarchy": [
      "tgn:2277110",
      "tgn:1000001",
      "tgn:7012149",
      "tgn:7007825",
      "tgn:7029392"
    ],
    "placetype": [
      "aat:300008706"
    ],
    "id": 2277110,
    "name:xx": "Davis Creek"
  }
}
