{
  "geometry": {
    "type": "Point",
    "coordinates": [
      -135.4167,
      59.15
    ]
  },
  "type": "Feature",
  "properties": {
    "hierarchy": [
      "tgn:2236942",
      "tgn:7006450",
      "tgn:1000001",
      "tgn:2124077",
      "tgn:7012149",
      "tgn:7029392"
    ],
    "placetype": [
      "aat:300132316"
    ],
    "id": 2236942,
    "name:xx": "Chilkat Inlet"
  }
}
