{
  "geometry": {
    "type": "Point",
    "coordinates": [
      38.3667,
      25.6167
    ]
  },
  "type": "Feature",
  "properties": {
    "hierarchy": [
      "tgn:1111194",
      "tgn:1000004",
      "tgn:1000137",
      "tgn:7029392"
    ],
    "placetype": [
      "aat:300387091"
    ],
    "id": 1111194,
    "name:xx": "Jizl, Wādī al-"
  }
}
