{
  "type": "FeatureCollection",
  "features": [
    {
      "geometry": {
        "type": "Point",
        "coordinates": [
          10.2,
          47.7
        ]
      },
      "type": "Feature",
      "properties": {
        "hierarchy": [
          "tgn:7190050",
          "tgn:7003669",
          "tgn:1000003",
          "tgn:7000084",
          "tgn:7029392"
        ],
        "placetype": [
          "aat:300008347"
        ],
        "id": 7190050,
        "name:xx": "Eschach"
      }
    },
    {
      "geometry": {
        "type": "Point",
        "coordinates": [
          10.7,
          47.6
        ]
      },
      "type": "Feature",
      "properties": {
        "hierarchy": [
          "tgn:7190051",
          "tgn:7003669",
          "tgn:1000003",
          "tgn:7000084",
          "tgn:7029392"
        ],
        "placetype": [
          "aat:300008347"
        ],
        "id": 7190051,
        "name:xx": "Eschach"
      }
    },
    {
      "geometry": {
        "type": "Point",
        "coordinates": [
          10.75,
          47.733333
        ]
      },
      "type": "Feature",
      "properties": {
        "hierarchy": [
          "tgn:7190052",
          "tgn:7003669",
          "tgn:1000003",
          "tgn:7000084",
          "tgn:7029392"
        ],
        "placetype": [
          "aat:300000206"
        ],
        "id": 7190052,
        "name:xx": "Eschach"
      }
    },
    {
      "geometry": {
        "type": "Point",
        "coordinates": [
          9.25,
          53.816667
        ]
      },
      "type": "Feature",
      "properties": {
        "hierarchy": [
          "tgn:7190053",
          "tgn:1000003",
          "tgn:7003676",
          "tgn:7000084",
          "tgn:7029392"
        ],
        "placetype": [
          "aat:300008347"
        ],
        "id": 7190053,
        "name:xx": "Esch"
      }
    },
    {
      "geometry": {
        "type": "Point",
        "coordinates": [
          9.566667,
          53.683333
        ]
      },
      "type": "Feature",
      "properties": {
        "hierarchy": [
          "tgn:7190054",
          "tgn:1000003",
          "tgn:7003688",
          "tgn:7000084",
          "tgn:7029392"
        ],
        "placetype": [
          "aat:300008347"
        ],
        "id": 7190054,
        "name:xx": "Im Esch"
      }
    },
    {
      "geometry": {
        "type": "Point",
        "coordinates": [
          6.85,
          51.016667
        ]
      },
      "type": "Feature",
      "properties": {
        "hierarchy": [
          "tgn:7190055",
          "tgn:1000003",
          "tgn:7003677",
          "tgn:7000084",
          "tgn:7029392"
        ],
        "placetype": [
          "aat:300008347"
        ],
        "id": 7190055,
        "name:xx": "Esch"
      }
    },
    {
      "geometry": {
        "type": "Point",
        "coordinates": [
          6.55,
          50.933333
        ]
      },
      "type": "Feature",
      "properties": {
        "hierarchy": [
          "tgn:7190056",
          "tgn:1000003",
          "tgn:7003677",
          "tgn:7000084",
          "tgn:7029392"
        ],
        "placetype": [
          "aat:300008347"
        ],
        "id": 7190056,
        "name:xx": "Esch"
      }
    },
    {
      "geometry": {
        "type": "Point",
        "coordinates": [
          6.833333,
          50.5
        ]
      },
      "type": "Feature",
      "properties": {
        "hierarchy": [
          "tgn:7190057",
          "tgn:1000003",
          "tgn:7003677",
          "tgn:7000084",
          "tgn:7029392"
        ],
        "placetype": [
          "aat:300008347"
        ],
        "id": 7190057,
        "name:xx": "Esch"
      }
    },
    {
      "geometry": {
        "type": "Point",
        "coordinates": [
          6.616667,
          50.366667
        ]
      },
      "type": "Feature",
      "properties": {
        "hierarchy": [
          "tgn:7190058",
          "tgn:1000003",
          "tgn:7003682",
          "tgn:7000084",
          "tgn:7029392"
        ],
        "placetype": [
          "aat:300008347"
        ],
        "id": 7190058,
        "name:xx": "Esch"
      }
    },
    {
      "geometry": {
        "type": "Point",
        "coordinates": [
          8.316667,
          50.25
        ]
      },
      "type": "Feature",
      "properties": {
        "hierarchy": [
          "tgn:7190059",
          "tgn:1000003",
          "tgn:7003678",
          "tgn:7000084",
          "tgn:7029392"
        ],
        "placetype": [
          "aat:300008347"
        ],
        "id": 7190059,
        "name:xx": "Esch"
      }
    }
  ]
}
