{
  "geometry": {
    "type": "Point",
    "coordinates": [
      -102.8167,
      32.95
    ]
  },
  "type": "Feature",
  "properties": {
    "hierarchy": [
      "tgn:2103767",
      "tgn:1000001",
      "tgn:7012149",
      "tgn:2002097",
      "tgn:7007826",
      "tgn:7029392"
    ],
    "placetype": [
      "aat:300008347"
    ],
    "id": 2103767,
    "name:xx": "Denver City"
  }
}
