{
  "geometry": {
    "type": "Point",
    "coordinates": [
      -92.7167,
      34.9167
    ]
  },
  "type": "Feature",
  "properties": {
    "hierarchy": [
      "tgn:2219019",
      "tgn:1000001",
      "tgn:7016172",
      "tgn:7012149",
      "tgn:2000157",
      "tgn:7029392"
    ],
    "placetype": [
      "aat:300008761"
    ],
    "id": 2219019,
    "name:xx": "Caney Creek"
  }
}
