{
  "geometry": {
    "type": "Point",
    "coordinates": [
      -107.9333,
      39.5333
    ]
  },
  "type": "Feature",
  "properties": {
    "hierarchy": [
      "tgn:2327066",
      "tgn:1000001",
      "tgn:7012149",
      "tgn:2000214",
      "tgn:7007158",
      "tgn:7029392"
    ],
    "placetype": [
      "aat:300008706"
    ],
    "id": 2327066,
    "name:xx": "First Anvil Creek"
  }
}
