{
  "type": "FeatureCollection",
  "features": [
    {
      "geometry": {
        "type": "Point",
        "coordinates": [
          -141.1,
          64.1
        ]
      },
      "type": "Feature",
      "properties": {
        "hierarchy": [
          "tgn:2219950",
          "tgn:7006450",
          "tgn:1000001",
          "tgn:7012149",
          "tgn:2000085",
          "tgn:7029392"
        ],
        "placetype": [
          "aat:300008706"
        ],
        "id": 2219950,
        "name:xx": "Canyon Creek"
      }
    },
    {
      "geometry": {
        "type": "Point",
        "coordinates": [
          -165.35,
          64.65
        ]
      },
      "type": "Feature",
      "properties": {
        "hierarchy": [
          "tgn:2219951",
          "tgn:7006450",
          "tgn:1000001",
          "tgn:7012149",
          "tgn:2000079",
          "tgn:7029392"
        ],
        "placetype": [
          "aat:300008706"
        ],
        "id": 2219951,
        "name:xx": "Canyon Creek"
      }
    },
    {
      "geometry": {
        "type": "Point",
        "coordinates": [
          -154.0667,
          59.9167
        ]
      },
      "type": "Feature",
      "properties": {
        "hierarchy": [
          "tgn:2219952",
          "tgn:7006450",
          "tgn:1000001",
          "tgn:7030517",
          "tgn:7012149",
          "tgn:7029392"
        ],
        "placetype": [
          "aat:300008706"
        ],
        "id": 2219952,
        "name:xx": "Canyon Creek"
      }
    },
    {
      "geometry": {
        "type": "Point",
        "coordinates": [
          -149.4333,
          60.5667
        ]
      },
      "type": "Feature",
      "properties": {
        "hierarchy": [
          "tgn:2219953",
          "tgn:7006450",
          "tgn:1000001",
          "tgn:7019698",
          "tgn:7012149",
          "tgn:7029392"
        ],
        "placetype": [
          "aat:300008706"
        ],
        "id": 2219953,
        "name:xx": "Canyon Creek"
      }
    },
    {
      "geometry": {
        "type": "Point",
        "coordinates": [
          -146.5333,
          64.3167
        ]
      },
      "type": "Feature",
      "properties": {
        "hierarchy": [
          "tgn:2219954",
          "tgn:7006450",
          "tgn:1000001",
          "tgn:7019674",
          "tgn:7012149",
          "tgn:7029392"
        ],
        "placetype": [
          "aat:300008706"
        ],
        "id": 2219954,
        "name:xx": "Canyon Creek"
      }
    },
    {
      "geometry": {
        "type": "Point",
        "coordinates": [
          -160.8167,
          65.9667
        ]
      },
      "type": "Feature",
      "properties": {
        "hierarchy": [
          "tgn:2219955",
          "tgn:7006450",
          "tgn:1000001",
          "tgn:7012149",
          "tgn:2124014",
          "tgn:7029392"
        ],
        "placetype": [
          "aat:300008706"
        ],
        "id": 2219955,
        "name:xx": "Canyon Creek"
      }
    },
    {
      "geometry": {
        "type": "Point",
        "coordinates": [
          -109.1167,
          33.7667
        ]
      },
      "type": "Feature",
      "properties": {
        "hierarchy": [
          "tgn:2219957",
          "tgn:1000001",
          "tgn:7006451",
          "tgn:7012149",
          "tgn:7029392"
        ],
        "placetype": [
          "aat:300008706"
        ],
        "id": 2219957,
        "name:xx": "Canyon Creek"
      }
    },
    {
      "geometry": {
        "type": "Point",
        "coordinates": [
          -111.6,
          34.2167
        ]
      },
      "type": "Feature",
      "properties": {
        "hierarchy": [
          "tgn:2219958",
          "tgn:1000001",
          "tgn:7006451",
          "tgn:2000093",
          "tgn:7012149",
          "tgn:7029392"
        ],
        "placetype": [
          "aat:300008706"
        ],
        "id": 2219958,
        "name:xx": "Canyon Creek"
      }
    },
    {
      "geometry": {
        "type": "Point",
        "coordinates": [
          -109.1167,
          33.7667
        ]
      },
      "type": "Feature",
      "properties": {
        "hierarchy": [
          "tgn:2219959",
          "tgn:1000001",
          "tgn:7006451",
          "tgn:2000095",
          "tgn:7012149",
          "tgn:7029392"
        ],
        "placetype": [
          "aat:300008706"
        ],
        "id": 2219959,
        "name:xx": "Canyon Creek"
      }
    }
  ]
}
