{
  "type": "FeatureCollection",
  "features": [
    {
      "geometry": {
        "type": "Point",
        "coordinates": [
          72.6,
          37
        ]
      },
      "type": "Feature",
      "properties": {
        "hierarchy": [
          "tgn:1065500",
          "tgn:7016612",
          "tgn:7011625",
          "tgn:1000004",
          "tgn:7029392"
        ],
        "placetype": [
          "aat:300008347"
        ],
        "id": 1065500,
        "name:xx": "Qalʻeh-ye Panjeh"
      }
    },
    {
      "geometry": {
        "type": "Point",
        "coordinates": [
          69.0167,
          34.0333
        ]
      },
      "type": "Feature",
      "properties": {
        "hierarchy": [
          "tgn:1065501",
          "tgn:7016612",
          "tgn:1000004",
          "tgn:1001398",
          "tgn:7029392"
        ],
        "placetype": [
          "aat:300008347"
        ],
        "id": 1065501,
        "name:xx": "Qaleh-ye Saber"
      }
    },
    {
      "geometry": {
        "type": "Point",
        "coordinates": [
          67.2833,
          35.9
        ]
      },
      "type": "Feature",
      "properties": {
        "hierarchy": [
          "tgn:1065502",
          "tgn:7016612",
          "tgn:1000004",
          "tgn:1001515",
          "tgn:7029392"
        ],
        "placetype": [
          "aat:300008347"
        ],
        "id": 1065502,
        "name:xx": "Qaleh-ye Sarkari"
      }
    },
    {
      "geometry": {
        "type": "Point",
        "coordinates": [
          68.7667,
          37.2167
        ]
      },
      "type": "Feature",
      "properties": {
        "hierarchy": [
          "tgn:1065504",
          "tgn:7016612",
          "tgn:1000004",
          "tgn:1001495",
          "tgn:7029392"
        ],
        "placetype": [
          "aat:300008347"
        ],
        "id": 1065504,
        "name:xx": "Qaravol"
      }
    },
    {
      "geometry": {
        "type": "Point",
        "coordinates": [
          61.7667,
          34.9333
        ]
      },
      "type": "Feature",
      "properties": {
        "hierarchy": [
          "tgn:1065505",
          "tgn:7016612",
          "tgn:1000004",
          "tgn:1001293",
          "tgn:7029392"
        ],
        "placetype": [
          "aat:300008347"
        ],
        "name:en": "Karabagh",
        "id": 1065505
      }
    },
    {
      "geometry": {
        "type": "Point",
        "coordinates": [
          66.0667,
          37.4
        ]
      },
      "type": "Feature",
      "properties": {
        "hierarchy": [
          "tgn:1065506",
          "tgn:7016612",
          "tgn:1000004",
          "tgn:1001327",
          "tgn:7029392"
        ],
        "placetype": [
          "aat:300008347"
        ],
        "id": 1065506,
        "name:xx": "Qarqin"
      }
    },
    {
      "geometry": {
        "type": "Point",
        "coordinates": [
          64.2833,
          35.6833
        ]
      },
      "type": "Feature",
      "properties": {
        "hierarchy": [
          "tgn:1065507",
          "tgn:7016612",
          "tgn:1000004",
          "tgn:1001248",
          "tgn:7029392"
        ],
        "placetype": [
          "aat:300008347"
        ],
        "id": 1065507,
        "name:xx": "Qeysar"
      }
    },
    {
      "geometry": {
        "type": "Point",
        "coordinates": [
          62.6,
          30.15
        ]
      },
      "type": "Feature",
      "properties": {
        "hierarchy": [
          "tgn:1065509",
          "tgn:7016612",
          "tgn:1000004",
          "tgn:1001440",
          "tgn:7029392"
        ],
        "placetype": [
          "aat:300008347"
        ],
        "id": 1065509,
        "name:xx": "Rudbar"
      }
    }
  ]
}
