{
  "geometry": {
    "type": "Point",
    "coordinates": [
      79.483333,
      10.85
    ]
  },
  "type": "Feature",
  "properties": {
    "hierarchy": [
      "tgn:7577340",
      "tgn:1000004",
      "tgn:7000198",
      "tgn:7001797",
      "tgn:7029392"
    ],
    "placetype": [
      "aat:300008347"
    ],
    "name:en": "Kudavāsa",
    "id": 7577340
  }
}
