{
  "geometry": {
    "type": "Point",
    "coordinates": [
      -91.6167,
      35.75
    ]
  },
  "type": "Feature",
  "properties": {
    "hierarchy": [
      "tgn:2310053",
      "tgn:1000001",
      "tgn:7016172",
      "tgn:7012149",
      "tgn:2000136",
      "tgn:7029392"
    ],
    "placetype": [
      "aat:300008347"
    ],
    "id": 2310053,
    "name:xx": "Eastwood Addition"
  }
}
