{
  "geometry": {
    "type": "Point",
    "coordinates": [
      21.25,
      41.3667
    ]
  },
  "type": "Feature",
  "properties": {
    "hierarchy": [
      "tgn:1065086",
      "tgn:1000003",
      "tgn:7015189",
      "tgn:7006667",
      "tgn:7029392"
    ],
    "placetype": [
      "aat:300008347"
    ],
    "id": 1065086,
    "name:xx": "Krusevo"
  }
}
