{
  "geometry": {
    "type": "Point",
    "coordinates": [
      -76.7667,
      37.2833
    ]
  },
  "type": "Feature",
  "properties": {
    "hierarchy": [
      "tgn:2597121",
      "tgn:1000001",
      "tgn:7012149",
      "tgn:1002511",
      "tgn:7007919",
      "tgn:7029392"
    ],
    "placetype": [
      "aat:300008706"
    ],
    "id": 2597121,
    "name:xx": "Powhatan Creek"
  }
}
