{
  "geometry": {
    "type": "Point",
    "coordinates": [
      -80.2333,
      40.1833
    ]
  },
  "type": "Feature",
  "properties": {
    "hierarchy": [
      "tgn:2094201",
      "tgn:1000001",
      "tgn:7012149",
      "tgn:1002995",
      "tgn:7007710",
      "tgn:7029392"
    ],
    "placetype": [
      "aat:300247594"
    ],
    "id": 2094201,
    "name:xx": "Washington Mall"
  }
}
