{
  "geometry": {
    "type": "Point",
    "coordinates": [
      -95.4167,
      34.1167
    ]
  },
  "type": "Feature",
  "properties": {
    "hierarchy": [
      "tgn:2082795",
      "tgn:1000001",
      "tgn:2001634",
      "tgn:7012149",
      "tgn:7007707",
      "tgn:7029392"
    ],
    "placetype": [
      "aat:300008347",
      "aat:300387210"
    ],
    "id": 2082795,
    "name:xx": "Apple"
  }
}
