{
  "geometry": {
    "type": "Point",
    "coordinates": [
      -81.65,
      36.35
    ]
  },
  "type": "Feature",
  "properties": {
    "hierarchy": [
      "tgn:2467643",
      "tgn:2001467",
      "tgn:1000001",
      "tgn:7012149",
      "tgn:7007709",
      "tgn:7029392"
    ],
    "placetype": [
      "aat:300008798"
    ],
    "id": 2467643,
    "name:xx": "Long Hope Mountain"
  }
}
