{
  "geometry": {
    "type": "Point",
    "coordinates": [
      -74.0167,
      40.75
    ]
  },
  "type": "Feature",
  "properties": {
    "hierarchy": [
      "tgn:2438236",
      "tgn:1000001",
      "tgn:1002489",
      "tgn:7012149",
      "tgn:7007565",
      "tgn:7029392"
    ],
    "placetype": [
      "aat:300008798"
    ],
    "id": 2438236,
    "name:xx": "Kings Bluff"
  }
}
