{
  "geometry": {
    "type": "Point",
    "coordinates": [
      -83.5667,
      34.8167
    ]
  },
  "type": "Feature",
  "properties": {
    "hierarchy": [
      "tgn:2770900",
      "tgn:1000001",
      "tgn:7012149",
      "tgn:2000410",
      "tgn:7007248",
      "tgn:7029392"
    ],
    "placetype": [
      "aat:300132316"
    ],
    "id": 2770900,
    "name:xx": "Wildcat Creek Cove"
  }
}
