{
  "geometry": {
    "type": "Point",
    "coordinates": [
      -176.3333,
      51.7167
    ]
  },
  "type": "Feature",
  "properties": {
    "hierarchy": [
      "tgn:2655460",
      "tgn:7030516",
      "tgn:7006450",
      "tgn:1000001",
      "tgn:7012149",
      "tgn:7029392"
    ],
    "placetype": [
      "aat:300008850"
    ],
    "id": 2655460,
    "name:xx": "Sharp Cape"
  }
}
