{
  "geometry": {
    "type": "Point",
    "coordinates": [
      -71.3167,
      41.6667
    ]
  },
  "type": "Feature",
  "properties": {
    "hierarchy": [
      "tgn:2555779",
      "tgn:1002202",
      "tgn:1000001",
      "tgn:7012149",
      "tgn:7007711",
      "tgn:7029392"
    ],
    "placetype": [
      "aat:300132348"
    ],
    "id": 2555779,
    "name:xx": "Ohio Ledge"
  }
}
