{
  "geometry": {
    "type": "Point",
    "coordinates": [
      -85.5167,
      45.6667
    ]
  },
  "type": "Feature",
  "properties": {
    "hierarchy": [
      "tgn:2427449",
      "tgn:1000001",
      "tgn:2000950",
      "tgn:7012149",
      "tgn:7007520",
      "tgn:7029392"
    ],
    "placetype": [
      "aat:300008707"
    ],
    "id": 2427449,
    "name:xx": "Jordan River"
  }
}
