{
  "geometry": {
    "type": "Point",
    "coordinates": [
      117.5167,
      -32.3667
    ]
  },
  "type": "Feature",
  "properties": {
    "hierarchy": [
      "tgn:1096413",
      "tgn:7000490",
      "tgn:1000006",
      "tgn:7001834",
      "tgn:7029392"
    ],
    "placetype": [
      "aat:300008347"
    ],
    "id": 1096413,
    "name:xx": "Bulyee"
  }
}
