{
  "geometry": {
    "type": "Point",
    "coordinates": [
      -106.85,
      44.35
    ]
  },
  "type": "Feature",
  "properties": {
    "hierarchy": [
      "tgn:2303446",
      "tgn:1000001",
      "tgn:7012149",
      "tgn:2002374",
      "tgn:7007923",
      "tgn:7029392"
    ],
    "placetype": [
      "aat:300006075"
    ],
    "id": 2303446,
    "name:xx": "Eagle Ditch"
  }
}
