{
  "geometry": {
    "type": "Point",
    "coordinates": [
      -89.4167,
      30.1833
    ]
  },
  "type": "Feature",
  "properties": {
    "hierarchy": [
      "tgn:2637431",
      "tgn:1000001",
      "tgn:7012149",
      "tgn:2001108",
      "tgn:7007522",
      "tgn:7029392"
    ],
    "placetype": [
      "aat:300008791"
    ],
    "id": 2637431,
    "name:xx": "Saint Josephs Island"
  }
}
