{
  "geometry": {
    "type": "Point",
    "coordinates": [
      -68.05,
      44.7333
    ]
  },
  "type": "Feature",
  "properties": {
    "hierarchy": [
      "tgn:2283791",
      "tgn:1000001",
      "tgn:7012149",
      "tgn:7007515",
      "tgn:7029392"
    ],
    "placetype": [
      "aat:300008905"
    ],
    "id": 2283791,
    "name:xx": "Denbow Heath"
  }
}
