{
  "geometry": {
    "type": "Point",
    "coordinates": [
      -87.05,
      32.3333
    ]
  },
  "type": "Feature",
  "properties": {
    "hierarchy": [
      "tgn:2754207",
      "tgn:7002659",
      "tgn:1000001",
      "tgn:7012149",
      "tgn:2000023",
      "tgn:7029392"
    ],
    "placetype": [
      "aat:300132348"
    ],
    "id": 2754207,
    "name:xx": "Watts Bar"
  }
}
