{
  "geometry": {
    "type": "Point",
    "coordinates": [
      -93.3167,
      29.7833
    ]
  },
  "type": "Feature",
  "properties": {
    "hierarchy": [
      "tgn:2042440",
      "tgn:1000001",
      "tgn:7020676",
      "tgn:7012149",
      "tgn:7007256",
      "tgn:7029392"
    ],
    "placetype": [
      "aat:300008347"
    ],
    "id": 2042440,
    "name:xx": "Cameron"
  }
}
