{
  "geometry": {
    "type": "Point",
    "coordinates": [
      20.8333,
      -33.8333
    ]
  },
  "type": "Feature",
  "properties": {
    "hierarchy": [
      "tgn:1093307",
      "tgn:7001242",
      "tgn:7017584",
      "tgn:1000193",
      "tgn:7029392"
    ],
    "placetype": [
      "aat:300008347"
    ],
    "id": 1093307,
    "name:xx": "Lemoenshoek"
  }
}
