{
  "geometry": {
    "type": "Point",
    "coordinates": [
      16.4333,
      60.4167
    ]
  },
  "type": "Feature",
  "properties": {
    "hierarchy": [
      "tgn:1062838",
      "tgn:1000374",
      "tgn:1000003",
      "tgn:1000097",
      "tgn:7029392"
    ],
    "placetype": [
      "aat:300008347"
    ],
    "id": 1062838,
    "name:xx": "Bodåsgruvan"
  }
}
