{
  "geometry": {
    "type": "Point",
    "coordinates": [
      -94.3333,
      35.9333
    ]
  },
  "type": "Feature",
  "properties": {
    "hierarchy": [
      "tgn:2597450",
      "tgn:1000001",
      "tgn:7016172",
      "tgn:7012149",
      "tgn:2000176",
      "tgn:7029392"
    ],
    "placetype": [
      "aat:300006191"
    ],
    "id": 2597450,
    "name:xx": "Prairie Grove, Lake"
  }
}
