{
  "geometry": {
    "type": "Point",
    "coordinates": [
      -104.9167,
      43.8333
    ]
  },
  "type": "Feature",
  "properties": {
    "hierarchy": [
      "tgn:2723564",
      "tgn:1000001",
      "tgn:7012149",
      "tgn:2002387",
      "tgn:7007923",
      "tgn:7029392"
    ],
    "placetype": [
      "aat:300006191"
    ],
    "id": 2723564,
    "name:xx": "Todd Detention Dam Reservoir"
  }
}
