{
  "geometry": {
    "type": "Point",
    "coordinates": [
      -122.8333,
      45.65
    ]
  },
  "type": "Feature",
  "properties": {
    "hierarchy": [
      "tgn:2745714",
      "tgn:1000001",
      "tgn:7012149",
      "tgn:1002699",
      "tgn:7007708",
      "tgn:7029392"
    ],
    "placetype": [
      "aat:300008905"
    ],
    "id": 2745714,
    "name:xx": "Virginia Lake"
  }
}
