{
  "geometry": {
    "type": "Point",
    "coordinates": [
      -97.4167,
      26.5333
    ]
  },
  "type": "Feature",
  "properties": {
    "hierarchy": [
      "tgn:2312886",
      "tgn:1000001",
      "tgn:7012149",
      "tgn:2002094",
      "tgn:7007826",
      "tgn:7029392"
    ],
    "placetype": [
      "aat:300008791"
    ],
    "id": 2312886,
    "name:xx": "El Sauz Island"
  }
}
