{
  "geometry": {
    "type": "Point",
    "coordinates": [
      -105.5667,
      36.1833
    ]
  },
  "type": "Feature",
  "properties": {
    "hierarchy": [
      "tgn:2132384",
      "tgn:1000001",
      "tgn:7012149",
      "tgn:2001457",
      "tgn:7007566",
      "tgn:7029392"
    ],
    "placetype": [
      "aat:300008761"
    ],
    "id": 2132384,
    "name:xx": "Amole Canyon"
  }
}
