{
  "geometry": {
    "type": "Point",
    "coordinates": [
      -45.3833,
      -23.8667
    ]
  },
  "type": "Feature",
  "properties": {
    "hierarchy": [
      "tgn:1107510",
      "tgn:1001945",
      "tgn:1000047",
      "tgn:7002457",
      "tgn:1000002",
      "tgn:1008853",
      "tgn:7029392"
    ],
    "placetype": [
      "aat:300008798"
    ],
    "id": 1107510,
    "name:xx": "São Sebastião, Pico de"
  }
}
