{
  "geometry": {
    "type": "Point",
    "coordinates": [
      -47.1667,
      -0.7667
    ]
  },
  "type": "Feature",
  "properties": {
    "hierarchy": [
      "tgn:1022810",
      "tgn:7006247",
      "tgn:1000047",
      "tgn:7002456",
      "tgn:1000002",
      "tgn:7029392"
    ],
    "placetype": [
      "aat:300008347"
    ],
    "id": 1022810,
    "name:xx": "São João de Pirabas"
  }
}
