{
  "geometry": {
    "type": "Point",
    "coordinates": [
      -88.15,
      42.4333
    ]
  },
  "type": "Feature",
  "properties": {
    "hierarchy": [
      "tgn:2765055",
      "tgn:1000001",
      "tgn:7012149",
      "tgn:7013855",
      "tgn:7007251",
      "tgn:7029392"
    ],
    "placetype": [
      "aat:300008850"
    ],
    "id": 2765055,
    "name:xx": "Whisky Point"
  }
}
