{
  "geometry": {
    "type": "Point",
    "coordinates": [
      -95.1833,
      45.55
    ]
  },
  "type": "Feature",
  "properties": {
    "hierarchy": [
      "tgn:2651463",
      "tgn:1000001",
      "tgn:7012149",
      "tgn:7007521",
      "tgn:7029392"
    ],
    "placetype": [
      "aat:300008699"
    ],
    "id": 2651463,
    "name:xx": "Sedan Brook"
  }
}
