{
  "geometry": {
    "type": "Point",
    "coordinates": [
      -71.714,
      -13.616
    ]
  },
  "type": "Feature",
  "properties": {
    "hierarchy": [
      "tgn:7032409",
      "tgn:1000584",
      "tgn:1000002",
      "tgn:1000056",
      "tgn:7029392"
    ],
    "placetype": [
      "aat:300008347",
      "aat:300000810",
      "aat:300167671",
      "aat:300017283",
      "aat:300008372"
    ],
    "id": 7032409,
    "name:xx": "Pikillacta"
  }
}
