{
  "geometry": {
    "type": "Point",
    "coordinates": [
      -75.9333,
      43.2333
    ]
  },
  "type": "Feature",
  "properties": {
    "hierarchy": [
      "tgn:2068057",
      "tgn:1000001",
      "tgn:7012149",
      "tgn:1002758",
      "tgn:7007568",
      "tgn:7029392"
    ],
    "placetype": [
      "aat:300008347"
    ],
    "id": 2068057,
    "name:xx": "Bernhards Bay"
  }
}
