{
  "type": "FeatureCollection",
  "features": [
    {
      "geometry": {
        "type": "Point",
        "coordinates": [
          131.25,
          57.3333
        ]
      },
      "type": "Feature",
      "properties": {
        "hierarchy": [
          "tgn:1124240",
          "tgn:1000004",
          "tgn:7011528",
          "tgn:7002435",
          "tgn:7029392"
        ],
        "placetype": [
          "aat:300008707"
        ],
        "id": 1124240,
        "name:xx": "Gonam"
      }
    },
    {
      "geometry": {
        "type": "Point",
        "coordinates": [
          115.3667,
          26
        ]
      },
      "type": "Feature",
      "properties": {
        "hierarchy": [
          "tgn:1124241",
          "tgn:1000004",
          "tgn:7002082",
          "tgn:1000111",
          "tgn:7029392"
        ],
        "placetype": [
          "aat:300008707"
        ],
        "id": 1124241,
        "name:xx": "Gong"
      }
    },
    {
      "geometry": {
        "type": "Point",
        "coordinates": [
          12.0833,
          9.4833
        ]
      },
      "type": "Feature",
      "properties": {
        "hierarchy": [
          "tgn:1124242",
          "tgn:7001242",
          "tgn:1000182",
          "tgn:7029392"
        ],
        "placetype": [
          "aat:300008707"
        ],
        "id": 1124242,
        "name:xx": "Gongola"
      }
    },
    {
      "geometry": {
        "type": "Point",
        "coordinates": [
          -57.9,
          -22.8
        ]
      },
      "type": "Feature",
      "properties": {
        "hierarchy": [
          "tgn:1124244",
          "tgn:7002636",
          "tgn:1000730",
          "tgn:1000002",
          "tgn:1000055",
          "tgn:7029392"
        ],
        "placetype": [
          "aat:300008707"
        ],
        "id": 1124244,
        "name:xx": "González, Riacho"
      }
    },
    {
      "geometry": {
        "type": "Point",
        "coordinates": [
          -73.4667,
          41.1
        ]
      },
      "type": "Feature",
      "properties": {
        "hierarchy": [
          "tgn:1124247",
          "tgn:1002366",
          "tgn:1000001",
          "tgn:7012149",
          "tgn:7007159",
          "tgn:7029392"
        ],
        "placetype": [
          "aat:300008707"
        ],
        "id": 1124247,
        "name:xx": "Goodwives"
      }
    },
    {
      "geometry": {
        "type": "Point",
        "coordinates": [
          -98,
          47.9333
        ]
      },
      "type": "Feature",
      "properties": {
        "hierarchy": [
          "tgn:1124249",
          "tgn:1000001",
          "tgn:7012149",
          "tgn:7007705",
          "tgn:7029392"
        ],
        "placetype": [
          "aat:300008707"
        ],
        "id": 1124249,
        "name:xx": "Goose"
      }
    }
  ]
}
