{
  "geometry": {
    "type": "Point",
    "coordinates": [
      -72.65,
      41.8333
    ]
  },
  "type": "Feature",
  "properties": {
    "hierarchy": [
      "tgn:2280447",
      "tgn:1000001",
      "tgn:1002461",
      "tgn:7012149",
      "tgn:7007159",
      "tgn:7029392"
    ],
    "placetype": [
      "aat:300008699"
    ],
    "id": 2280447,
    "name:xx": "Deckers Brook"
  }
}
