{
  "type": "FeatureCollection",
  "features": [
    {
      "geometry": {
        "type": "Point",
        "coordinates": [
          -5.266667,
          40.25
        ]
      },
      "type": "Feature",
      "properties": {
        "hierarchy": [
          "tgn:7331040",
          "tgn:7002806",
          "tgn:7001158",
          "tgn:1000003",
          "tgn:1000095",
          "tgn:7029392"
        ],
        "placetype": [
          "aat:300008680"
        ],
        "id": 7331040,
        "name:xx": "Grande de Gredos, Laguna"
      }
    },
    {
      "geometry": {
        "type": "Point",
        "coordinates": [
          -13.466667,
          29.2
        ]
      },
      "type": "Feature",
      "properties": {
        "hierarchy": [
          "tgn:7331041",
          "tgn:7002825",
          "tgn:7016622",
          "tgn:1000003",
          "tgn:1000095",
          "tgn:7029392"
        ],
        "placetype": [
          "aat:300008805"
        ],
        "id": 7331041,
        "name:xx": "Grande, Vega"
      }
    },
    {
      "geometry": {
        "type": "Point",
        "coordinates": [
          -6.55,
          39.833333
        ]
      },
      "type": "Feature",
      "properties": {
        "hierarchy": [
          "tgn:7331042",
          "tgn:7002811",
          "tgn:1000003",
          "tgn:7003837",
          "tgn:1000095",
          "tgn:7029392"
        ],
        "placetype": [
          "aat:300266640"
        ],
        "id": 7331042,
        "name:xx": "Grande, Sierra"
      }
    },
    {
      "geometry": {
        "type": "Point",
        "coordinates": [
          -5.6,
          41.833333
        ]
      },
      "type": "Feature",
      "properties": {
        "hierarchy": [
          "tgn:7331043",
          "tgn:7001158",
          "tgn:7002850",
          "tgn:1000003",
          "tgn:1000095",
          "tgn:7029392"
        ],
        "placetype": [
          "aat:300008688"
        ],
        "id": 7331043,
        "name:xx": "Grande, Salina"
      }
    },
    {
      "geometry": {
        "type": "Point",
        "coordinates": [
          -0.2,
          41.05
        ]
      },
      "type": "Feature",
      "properties": {
        "hierarchy": [
          "tgn:7331044",
          "tgn:7002759",
          "tgn:7002843",
          "tgn:1000003",
          "tgn:1000095",
          "tgn:7029392"
        ],
        "placetype": [
          "aat:300387086"
        ],
        "id": 7331044,
        "name:xx": "Grande, Salada"
      }
    },
    {
      "geometry": {
        "type": "Point",
        "coordinates": [
          -8.7,
          43.183333
        ]
      },
      "type": "Feature",
      "properties": {
        "hierarchy": [
          "tgn:7331046",
          "tgn:7002824",
          "tgn:1000003",
          "tgn:7002786",
          "tgn:1000095",
          "tgn:7029392"
        ],
        "placetype": [
          "aat:300008699"
        ],
        "id": 7331046,
        "name:xx": "Grande, Río"
      }
    },
    {
      "geometry": {
        "type": "Point",
        "coordinates": [
          -9.15,
          43.133333
        ]
      },
      "type": "Feature",
      "properties": {
        "hierarchy": [
          "tgn:7331047",
          "tgn:7002824",
          "tgn:1000003",
          "tgn:7002786",
          "tgn:1000095",
          "tgn:7029392"
        ],
        "placetype": [
          "aat:300008699"
        ],
        "id": 7331047,
        "name:xx": "Grande, Río"
      }
    },
    {
      "geometry": {
        "type": "Point",
        "coordinates": [
          -7.383333,
          42.266667
        ]
      },
      "type": "Feature",
      "properties": {
        "hierarchy": [
          "tgn:7331048",
          "tgn:7002831",
          "tgn:1000003",
          "tgn:7002786",
          "tgn:1000095",
          "tgn:7029392"
        ],
        "placetype": [
          "aat:300008699"
        ],
        "id": 7331048,
        "name:xx": "Grande, Río"
      }
    },
    {
      "geometry": {
        "type": "Point",
        "coordinates": [
          -8.116667,
          42.15
        ]
      },
      "type": "Feature",
      "properties": {
        "hierarchy": [
          "tgn:7331049",
          "tgn:7002831",
          "tgn:1000003",
          "tgn:7002786",
          "tgn:1000095",
          "tgn:7029392"
        ],
        "placetype": [
          "aat:300008699"
        ],
        "id": 7331049,
        "name:xx": "Grande, Río"
      }
    }
  ]
}
