{
  "geometry": {
    "type": "Point",
    "coordinates": [
      -119.7833,
      44.3167
    ]
  },
  "type": "Feature",
  "properties": {
    "hierarchy": [
      "tgn:2613487",
      "tgn:1000001",
      "tgn:7012149",
      "tgn:2001723",
      "tgn:7007708",
      "tgn:7029392"
    ],
    "placetype": [
      "aat:300006191"
    ],
    "id": 2613487,
    "name:xx": "Reed Reservoir"
  }
}
