{
  "geometry": {
    "type": "Point",
    "coordinates": [
      -119.4167,
      36.8167
    ]
  },
  "type": "Feature",
  "properties": {
    "hierarchy": [
      "tgn:2446295",
      "tgn:1000001",
      "tgn:7012149",
      "tgn:1002392",
      "tgn:7007157",
      "tgn:7029392"
    ],
    "placetype": [
      "aat:300008706"
    ],
    "id": 2446295,
    "name:xx": "Lewis Creek"
  }
}
