{
  "type": "FeatureCollection",
  "features": [
    {
      "geometry": {
        "type": "Point",
        "coordinates": [
          12.133333,
          49.133333
        ]
      },
      "type": "Feature",
      "properties": {
        "hierarchy": [
          "tgn:7105000",
          "tgn:7003669",
          "tgn:1000003",
          "tgn:7000084",
          "tgn:7029392"
        ],
        "placetype": [
          "aat:300008777"
        ],
        "id": 7105000,
        "name:xx": "Schlossberg"
      }
    },
    {
      "geometry": {
        "type": "Point",
        "coordinates": [
          8.283333,
          48.783333
        ]
      },
      "type": "Feature",
      "properties": {
        "hierarchy": [
          "tgn:7105002",
          "tgn:7003692",
          "tgn:1000003",
          "tgn:7000084",
          "tgn:7029392"
        ],
        "placetype": [
          "aat:300008777"
        ],
        "id": 7105002,
        "name:xx": "Schloßberg"
      }
    },
    {
      "geometry": {
        "type": "Point",
        "coordinates": [
          8.933333,
          48.616667
        ]
      },
      "type": "Feature",
      "properties": {
        "hierarchy": [
          "tgn:7105003",
          "tgn:7003692",
          "tgn:1000003",
          "tgn:7000084",
          "tgn:7029392"
        ],
        "placetype": [
          "aat:300008777"
        ],
        "id": 7105003,
        "name:xx": "Schlossberg"
      }
    },
    {
      "geometry": {
        "type": "Point",
        "coordinates": [
          10.25,
          48.6
        ]
      },
      "type": "Feature",
      "properties": {
        "hierarchy": [
          "tgn:7105004",
          "tgn:7003692",
          "tgn:1000003",
          "tgn:7000084",
          "tgn:7029392"
        ],
        "placetype": [
          "aat:300008777"
        ],
        "id": 7105004,
        "name:xx": "Schloßberg"
      }
    },
    {
      "geometry": {
        "type": "Point",
        "coordinates": [
          8.883333,
          48.6
        ]
      },
      "type": "Feature",
      "properties": {
        "hierarchy": [
          "tgn:7105005",
          "tgn:7003692",
          "tgn:1000003",
          "tgn:7000084",
          "tgn:7029392"
        ],
        "placetype": [
          "aat:300008777"
        ],
        "id": 7105005,
        "name:xx": "Schloßberg"
      }
    },
    {
      "geometry": {
        "type": "Point",
        "coordinates": [
          9.7,
          48.583333
        ]
      },
      "type": "Feature",
      "properties": {
        "hierarchy": [
          "tgn:7105006",
          "tgn:7003692",
          "tgn:1000003",
          "tgn:7000084",
          "tgn:7029392"
        ],
        "placetype": [
          "aat:300008777"
        ],
        "id": 7105006,
        "name:xx": "Schloß-Berg"
      }
    },
    {
      "geometry": {
        "type": "Point",
        "coordinates": [
          12.683333,
          48.466667
        ]
      },
      "type": "Feature",
      "properties": {
        "hierarchy": [
          "tgn:7105007",
          "tgn:7003669",
          "tgn:1000003",
          "tgn:7000084",
          "tgn:7029392"
        ],
        "placetype": [
          "aat:300008777"
        ],
        "id": 7105007,
        "name:xx": "Schloss Berg"
      }
    },
    {
      "geometry": {
        "type": "Point",
        "coordinates": [
          9.9,
          48.45
        ]
      },
      "type": "Feature",
      "properties": {
        "hierarchy": [
          "tgn:7105009",
          "tgn:7003692",
          "tgn:1000003",
          "tgn:7000084",
          "tgn:7029392"
        ],
        "placetype": [
          "aat:300008777"
        ],
        "id": 7105009,
        "name:xx": "Schloß-Berg"
      }
    }
  ]
}
