{
  "geometry": {
    "type": "Point",
    "coordinates": [
      -106.3167,
      41.3667
    ]
  },
  "type": "Feature",
  "properties": {
    "hierarchy": [
      "tgn:2383379",
      "tgn:2002365",
      "tgn:1000001",
      "tgn:7012149",
      "tgn:7007923",
      "tgn:7029392"
    ],
    "placetype": [
      "aat:300008680"
    ],
    "id": 2383379,
    "name:xx": "Heart Lake"
  }
}
