{
  "geometry": {
    "type": "Point",
    "coordinates": [
      -83.3833,
      43.0833
    ]
  },
  "type": "Feature",
  "properties": {
    "hierarchy": [
      "tgn:2667339",
      "tgn:1000001",
      "tgn:7012149",
      "tgn:1002576",
      "tgn:7007520",
      "tgn:7029392"
    ],
    "placetype": [
      "aat:300008680"
    ],
    "id": 2667339,
    "name:xx": "Skinner Lake"
  }
}
