{
  "geometry": {
    "type": "Point",
    "coordinates": [
      -81.1667,
      8.4167
    ]
  },
  "type": "Feature",
  "properties": {
    "hierarchy": [
      "tgn:1018817",
      "tgn:1001593",
      "tgn:1000001",
      "tgn:7005565",
      "tgn:7029392"
    ],
    "placetype": [
      "aat:300008347"
    ],
    "id": 1018817,
    "name:xx": "Cañazas"
  }
}
