{
  "geometry": {
    "type": "Point",
    "coordinates": [
      -116.5167,
      45.8667
    ]
  },
  "type": "Feature",
  "properties": {
    "hierarchy": [
      "tgn:2389505",
      "tgn:1000001",
      "tgn:7012149",
      "tgn:2000476",
      "tgn:7007250",
      "tgn:7029392"
    ],
    "placetype": [
      "aat:300386831"
    ],
    "id": 2389505,
    "name:xx": "High Breaks"
  }
}
