{
  "geometry": {
    "type": "Point",
    "coordinates": [
      121.2025,
      24.1525
    ]
  },
  "type": "Feature",
  "properties": {
    "hierarchy": [
      "tgn:7484840",
      "tgn:7488858",
      "tgn:1000004",
      "tgn:1000141",
      "tgn:7029392"
    ],
    "placetype": [
      "aat:300008798"
    ],
    "id": 7484840,
    "name:xx": "Zhenlieba Shan"
  }
}
