{
  "geometry": {
    "type": "Point",
    "coordinates": [
      16.595,
      38.809
    ]
  },
  "type": "Feature",
  "properties": {
    "hierarchy": [
      "tgn:6005307",
      "tgn:1003447",
      "tgn:7007850",
      "tgn:1000003",
      "tgn:1000080",
      "tgn:7029392"
    ],
    "placetype": [
      "aat:300008347",
      "aat:300167671"
    ],
    "id": 6005307,
    "name:xx": "Scolacium"
  }
}
