{
  "type": "FeatureCollection",
  "features": [
    {
      "geometry": {
        "type": "Point",
        "coordinates": [
          23.966,
          54.016
        ]
      },
      "type": "Feature",
      "properties": {
        "hierarchy": [
          "tgn:7594031",
          "tgn:1000003",
          "tgn:7006542",
          "tgn:7029392"
        ],
        "placetype": [
          "aat:300387064",
          "aat:300265612"
        ],
        "id": 7594031,
        "name:xx": "Druskininkai"
      }
    },
    {
      "geometry": {
        "type": "Point",
        "coordinates": [
          24.666667,
          54.733333
        ]
      },
      "type": "Feature",
      "properties": {
        "hierarchy": [
          "tgn:7594032",
          "tgn:1000003",
          "tgn:7006542",
          "tgn:7029392"
        ],
        "placetype": [
          "aat:300387064",
          "aat:300265612"
        ],
        "id": 7594032,
        "name:xx": "Elektrénai"
      }
    },
    {
      "geometry": {
        "type": "Point",
        "coordinates": [
          23.2,
          54.366667
        ]
      },
      "type": "Feature",
      "properties": {
        "hierarchy": [
          "tgn:7594038",
          "tgn:1000003",
          "tgn:7006542",
          "tgn:7029392"
        ],
        "placetype": [
          "aat:300387064",
          "aat:300265612"
        ],
        "id": 7594038,
        "name:xx": "Kalvarijos"
      }
    },
    {
      "geometry": {
        "type": "Point",
        "coordinates": [
          23.9,
          54.9
        ]
      },
      "type": "Feature",
      "properties": {
        "hierarchy": [
          "tgn:7594039",
          "tgn:1000003",
          "tgn:7006542",
          "tgn:7029392"
        ],
        "placetype": [
          "aat:300387064",
          "aat:300265612"
        ],
        "id": 7594039,
        "name:xx": "Kauno Miestas"
      }
    }
  ]
}
