{
  "geometry": {
    "type": "Point",
    "coordinates": [
      -87.4333,
      36.65
    ]
  },
  "type": "Feature",
  "properties": {
    "hierarchy": [
      "tgn:2040560",
      "tgn:1000001",
      "tgn:2000780",
      "tgn:7012149",
      "tgn:7007255",
      "tgn:7029392"
    ],
    "placetype": [
      "aat:300008347"
    ],
    "id": 2040560,
    "name:xx": "Oak Grove"
  }
}
