{
  "geometry": {
    "type": "Point",
    "coordinates": [
      39.6333,
      49.4667
    ]
  },
  "type": "Feature",
  "properties": {
    "hierarchy": [
      "tgn:1055935",
      "tgn:1000003",
      "tgn:7012067",
      "tgn:7006660",
      "tgn:7029392"
    ],
    "placetype": [
      "aat:300008347"
    ],
    "id": 1055935,
    "name:xx": "Kryzs'ke"
  }
}
