{
  "geometry": {
    "type": "Point",
    "coordinates": [
      15.333,
      40.2167
    ]
  },
  "type": "Feature",
  "properties": {
    "hierarchy": [
      "tgn:1106265",
      "tgn:7003005",
      "tgn:7003014",
      "tgn:1000003",
      "tgn:1000080",
      "tgn:7029392"
    ],
    "placetype": [
      "aat:300008795"
    ],
    "id": 1106265,
    "name:xx": "Sacro, Monte"
  }
}
