{
  "geometry": {
    "type": "Point",
    "coordinates": [
      79.408291,
      27.07728
    ]
  },
  "type": "Feature",
  "properties": {
    "hierarchy": [
      "tgn:7562687",
      "tgn:1000004",
      "tgn:7000198",
      "tgn:7016722",
      "tgn:7029392"
    ],
    "placetype": [
      "aat:300008347"
    ],
    "name:en": "Harīpur",
    "id": 7562687
  }
}
