{
  "geometry": {
    "type": "Point",
    "coordinates": [
      -82.75,
      32.85
    ]
  },
  "type": "Feature",
  "properties": {
    "hierarchy": [
      "tgn:2425053",
      "tgn:1000001",
      "tgn:7012149",
      "tgn:2000441",
      "tgn:7007248",
      "tgn:7029392"
    ],
    "placetype": [
      "aat:300006191"
    ],
    "id": 2425053,
    "name:xx": "Johnson Lake"
  }
}
