{
  "geometry": {
    "type": "Point",
    "coordinates": [
      -98.2333,
      42.3333
    ]
  },
  "type": "Feature",
  "properties": {
    "hierarchy": [
      "tgn:2062515",
      "tgn:2001317",
      "tgn:1000001",
      "tgn:7012149",
      "tgn:7007525",
      "tgn:7029392"
    ],
    "placetype": [
      "aat:300008347"
    ],
    "id": 2062515,
    "name:xx": "Orchard"
  }
}
