{
  "geometry": {
    "type": "Point",
    "coordinates": [
      -70.9667,
      41.5167
    ]
  },
  "type": "Feature",
  "properties": {
    "hierarchy": [
      "tgn:2049636",
      "tgn:1002201",
      "tgn:1000001",
      "tgn:7012149",
      "tgn:7007517",
      "tgn:7029392"
    ],
    "placetype": [
      "aat:300008347"
    ],
    "id": 2049636,
    "name:xx": "Cow Yard"
  }
}
