{
  "geometry": {
    "type": "Point",
    "coordinates": [
      -116.7167,
      44.8167
    ]
  },
  "type": "Feature",
  "properties": {
    "hierarchy": [
      "tgn:2271099",
      "tgn:1000001",
      "tgn:7012149",
      "tgn:2000495",
      "tgn:7007250",
      "tgn:7029392"
    ],
    "placetype": [
      "aat:300386831"
    ],
    "id": 2271099,
    "name:xx": "Cuddy Mountains"
  }
}
