{
  "geometry": {
    "type": "Point",
    "coordinates": [
      32.660126,
      31.04468
    ]
  },
  "type": "Feature",
  "properties": {
    "hierarchy": [
      "tgn:7531808",
      "tgn:7001242",
      "tgn:7016833",
      "tgn:7001335",
      "tgn:7029392"
    ],
    "placetype": [
      "aat:300008777"
    ],
    "id": 7531808,
    "name:xx": "Al Maḩamdīyah"
  }
}
