{
  "type": "FeatureCollection",
  "features": [
    {
      "geometry": {
        "type": "Point",
        "coordinates": [
          -71.666667,
          -34.216667
        ]
      },
      "type": "Feature",
      "properties": {
        "hierarchy": [
          "tgn:7313230",
          "tgn:1001695",
          "tgn:1000049",
          "tgn:1000002",
          "tgn:7029392"
        ],
        "placetype": [
          "aat:300387200"
        ],
        "id": 7313230,
        "name:xx": "Los Perales"
      }
    },
    {
      "geometry": {
        "type": "Point",
        "coordinates": [
          -71.633333,
          -33.383333
        ]
      },
      "type": "Feature",
      "properties": {
        "hierarchy": [
          "tgn:7313231",
          "tgn:1001768",
          "tgn:1000049",
          "tgn:1000002",
          "tgn:7029392"
        ],
        "placetype": [
          "aat:300387200"
        ],
        "id": 7313231,
        "name:xx": "Los Perales"
      }
    },
    {
      "geometry": {
        "type": "Point",
        "coordinates": [
          -71.25,
          -33.25
        ]
      },
      "type": "Feature",
      "properties": {
        "hierarchy": [
          "tgn:7313232",
          "tgn:1001768",
          "tgn:1000049",
          "tgn:1000002",
          "tgn:7029392"
        ],
        "placetype": [
          "aat:300387200"
        ],
        "id": 7313232,
        "name:xx": "Los Perales"
      }
    },
    {
      "geometry": {
        "type": "Point",
        "coordinates": [
          -71.333333,
          -32.45
        ]
      },
      "type": "Feature",
      "properties": {
        "hierarchy": [
          "tgn:7313234",
          "tgn:1001768",
          "tgn:1000049",
          "tgn:1000002",
          "tgn:7029392"
        ],
        "placetype": [
          "aat:300387200"
        ],
        "id": 7313234,
        "name:xx": "Los Perales"
      }
    },
    {
      "geometry": {
        "type": "Point",
        "coordinates": [
          -71.95,
          -34.283333
        ]
      },
      "type": "Feature",
      "properties": {
        "hierarchy": [
          "tgn:7313235",
          "tgn:1001695",
          "tgn:1000049",
          "tgn:1000002",
          "tgn:7029392"
        ],
        "placetype": [
          "aat:300008777"
        ],
        "id": 7313235,
        "name:xx": "Los Perales"
      }
    },
    {
      "geometry": {
        "type": "Point",
        "coordinates": [
          -70.833333,
          -34.3
        ]
      },
      "type": "Feature",
      "properties": {
        "hierarchy": [
          "tgn:7313236",
          "tgn:1001695",
          "tgn:1000049",
          "tgn:1000002",
          "tgn:7029392"
        ],
        "placetype": [
          "aat:300000206"
        ],
        "id": 7313236,
        "name:xx": "Los Perales"
      }
    },
    {
      "geometry": {
        "type": "Point",
        "coordinates": [
          -71.316667,
          -33.15
        ]
      },
      "type": "Feature",
      "properties": {
        "hierarchy": [
          "tgn:7313237",
          "tgn:1001768",
          "tgn:1000049",
          "tgn:1000002",
          "tgn:7029392"
        ],
        "placetype": [
          "aat:300000206"
        ],
        "id": 7313237,
        "name:xx": "Los Perales"
      }
    },
    {
      "geometry": {
        "type": "Point",
        "coordinates": [
          -71.533333,
          -33.116667
        ]
      },
      "type": "Feature",
      "properties": {
        "hierarchy": [
          "tgn:7313238",
          "tgn:1001768",
          "tgn:1000049",
          "tgn:1000002",
          "tgn:7029392"
        ],
        "placetype": [
          "aat:300000206"
        ],
        "id": 7313238,
        "name:xx": "Los Perales"
      }
    },
    {
      "geometry": {
        "type": "Point",
        "coordinates": [
          -71.266667,
          -32.55
        ]
      },
      "type": "Feature",
      "properties": {
        "hierarchy": [
          "tgn:7313239",
          "tgn:1001768",
          "tgn:1000049",
          "tgn:1000002",
          "tgn:7029392"
        ],
        "placetype": [
          "aat:300000206"
        ],
        "id": 7313239,
        "name:xx": "Los Perales"
      }
    }
  ]
}
