{
  "type": "FeatureCollection",
  "features": [
    {
      "geometry": {
        "type": "Point",
        "coordinates": [
          -101.9167,
          41.6333
        ]
      },
      "type": "Feature",
      "properties": {
        "hierarchy": [
          "tgn:2224640",
          "tgn:2001318",
          "tgn:1000001",
          "tgn:7012149",
          "tgn:7007525",
          "tgn:7029392"
        ],
        "placetype": [
          "aat:300386845"
        ],
        "id": 2224640,
        "name:xx": "Casey Valley"
      }
    },
    {
      "geometry": {
        "type": "Point",
        "coordinates": [
          -75.0333,
          40.1833
        ]
      },
      "type": "Feature",
      "properties": {
        "hierarchy": [
          "tgn:2224641",
          "tgn:1000001",
          "tgn:1002213",
          "tgn:7012149",
          "tgn:7007710",
          "tgn:7029392"
        ],
        "placetype": [
          "aat:300008347"
        ],
        "id": 2224641,
        "name:xx": "Casey Village"
      }
    },
    {
      "geometry": {
        "type": "Point",
        "coordinates": [
          -74.25,
          40.5833
        ]
      },
      "type": "Feature",
      "properties": {
        "hierarchy": [
          "tgn:2224643",
          "tgn:1000001",
          "tgn:1002666",
          "tgn:7012149",
          "tgn:7007565",
          "tgn:7029392"
        ],
        "placetype": [
          "aat:300008706"
        ],
        "id": 2224643,
        "name:xx": "Caseys Creek"
      }
    },
    {
      "geometry": {
        "type": "Point",
        "coordinates": [
          -83.8,
          41.4167
        ]
      },
      "type": "Feature",
      "properties": {
        "hierarchy": [
          "tgn:2224644",
          "tgn:1000001",
          "tgn:7012149",
          "tgn:1003033",
          "tgn:7007706",
          "tgn:7029392"
        ],
        "placetype": [
          "aat:300008791"
        ],
        "id": 2224644,
        "name:xx": "Caseys Island"
      }
    },
    {
      "geometry": {
        "type": "Point",
        "coordinates": [
          -84.9,
          34.3333
        ]
      },
      "type": "Feature",
      "properties": {
        "hierarchy": [
          "tgn:2224645",
          "tgn:1000001",
          "tgn:2000299",
          "tgn:7012149",
          "tgn:7007248",
          "tgn:7029392"
        ],
        "placetype": [
          "aat:300006191"
        ],
        "id": 2224645,
        "name:xx": "Caseys Lakes"
      }
    },
    {
      "geometry": {
        "type": "Point",
        "coordinates": [
          -84.9,
          34.3333
        ]
      },
      "type": "Feature",
      "properties": {
        "hierarchy": [
          "tgn:2224647",
          "tgn:1000001",
          "tgn:2000299",
          "tgn:7012149",
          "tgn:7007248",
          "tgn:7029392"
        ],
        "placetype": [
          "aat:300006191"
        ],
        "id": 2224647,
        "name:xx": "Caseys North Lake"
      }
    },
    {
      "geometry": {
        "type": "Point",
        "coordinates": [
          -97.6167,
          44.8667
        ]
      },
      "type": "Feature",
      "properties": {
        "hierarchy": [
          "tgn:2224648",
          "tgn:1000001",
          "tgn:2001782",
          "tgn:7012149",
          "tgn:7007713",
          "tgn:7029392"
        ],
        "placetype": [
          "aat:300008905"
        ],
        "id": 2224648,
        "name:xx": "Caseys Slough"
      }
    },
    {
      "geometry": {
        "type": "Point",
        "coordinates": [
          -84.9,
          34.3333
        ]
      },
      "type": "Feature",
      "properties": {
        "hierarchy": [
          "tgn:2224649",
          "tgn:1000001",
          "tgn:2000299",
          "tgn:7012149",
          "tgn:7007248",
          "tgn:7029392"
        ],
        "placetype": [
          "aat:300006191"
        ],
        "id": 2224649,
        "name:xx": "Caseys South Lake"
      }
    }
  ]
}
