{
  "geometry": {
    "type": "Point",
    "coordinates": [
      -78.45,
      41.8833
    ]
  },
  "type": "Feature",
  "properties": {
    "hierarchy": [
      "tgn:2287441",
      "tgn:1000001",
      "tgn:7012149",
      "tgn:7016020",
      "tgn:7007710",
      "tgn:7029392"
    ],
    "placetype": [
      "aat:300008761"
    ],
    "id": 2287441,
    "name:xx": "Diegel Hollow"
  }
}
