{
  "geometry": {
    "type": "Point",
    "coordinates": [
      -102.7333,
      30.1833
    ]
  },
  "type": "Feature",
  "properties": {
    "hierarchy": [
      "tgn:2567250",
      "tgn:1000001",
      "tgn:7012149",
      "tgn:2002055",
      "tgn:7007826",
      "tgn:7029392"
    ],
    "placetype": [
      "aat:300008798"
    ],
    "id": 2567250,
    "name:xx": "Panther Peak"
  }
}
