{
  "type": "FeatureCollection",
  "features": [
    {
      "geometry": {
        "type": "Point",
        "coordinates": [
          9.233333,
          45.416667
        ]
      },
      "type": "Feature",
      "properties": {
        "hierarchy": [
          "tgn:7042180",
          "tgn:7003150",
          "tgn:1000003",
          "tgn:7003237",
          "tgn:1000080",
          "tgn:7029392"
        ],
        "placetype": [
          "aat:300008347"
        ],
        "id": 7042180,
        "name:xx": "Rogeredo"
      }
    },
    {
      "geometry": {
        "type": "Point",
        "coordinates": [
          11.033333,
          44.283333
        ]
      },
      "type": "Feature",
      "properties": {
        "hierarchy": [
          "tgn:7042182",
          "tgn:7003127",
          "tgn:1000003",
          "tgn:7008516",
          "tgn:1000080",
          "tgn:7029392"
        ],
        "placetype": [
          "aat:300008347"
        ],
        "id": 7042182,
        "name:xx": "Roffeno Musiolo"
      }
    },
    {
      "geometry": {
        "type": "Point",
        "coordinates": [
          12.166667,
          43.75
        ]
      },
      "type": "Feature",
      "properties": {
        "hierarchy": [
          "tgn:7042183",
          "tgn:1003483",
          "tgn:1000003",
          "tgn:7003240",
          "tgn:1000080",
          "tgn:7029392"
        ],
        "placetype": [
          "aat:300008347"
        ],
        "id": 7042183,
        "name:xx": "Rofelle"
      }
    },
    {
      "geometry": {
        "type": "Point",
        "coordinates": [
          15.233333,
          40.133333
        ]
      },
      "type": "Feature",
      "properties": {
        "hierarchy": [
          "tgn:7042184",
          "tgn:7003005",
          "tgn:7003014",
          "tgn:1000003",
          "tgn:1000080",
          "tgn:7029392"
        ],
        "placetype": [
          "aat:300008347"
        ],
        "id": 7042184,
        "name:xx": "Rodio"
      }
    },
    {
      "geometry": {
        "type": "Point",
        "coordinates": [
          10.616667,
          45.2
        ]
      },
      "type": "Feature",
      "properties": {
        "hierarchy": [
          "tgn:7042185",
          "tgn:7005880",
          "tgn:1000003",
          "tgn:7003237",
          "tgn:1000080",
          "tgn:7029392"
        ],
        "placetype": [
          "aat:300008347"
        ],
        "id": 7042185,
        "name:xx": "Rodigo"
      }
    },
    {
      "geometry": {
        "type": "Point",
        "coordinates": [
          11.1,
          44.316667
        ]
      },
      "type": "Feature",
      "properties": {
        "hierarchy": [
          "tgn:7042187",
          "tgn:7003127",
          "tgn:1000003",
          "tgn:7008516",
          "tgn:1000080",
          "tgn:7029392"
        ],
        "placetype": [
          "aat:300008347"
        ],
        "id": 7042187,
        "name:xx": "Rodiano"
      }
    },
    {
      "geometry": {
        "type": "Point",
        "coordinates": [
          15.166667,
          38.1
        ]
      },
      "type": "Feature",
      "properties": {
        "hierarchy": [
          "tgn:7042188",
          "tgn:1000003",
          "tgn:7003122",
          "tgn:7003157",
          "tgn:1000080",
          "tgn:7029392"
        ],
        "placetype": [
          "aat:300008347"
        ],
        "id": 7042188,
        "name:xx": "Rodi"
      }
    }
  ]
}
