{
  "geometry": {
    "type": "Point",
    "coordinates": [
      -94.3667,
      35.0667
    ]
  },
  "type": "Feature",
  "properties": {
    "hierarchy": [
      "tgn:2617708",
      "tgn:1000001",
      "tgn:7012149",
      "tgn:7029392"
    ],
    "placetype": [
      "aat:300008706"
    ],
    "id": 2617708,
    "name:xx": "Riddle Creek"
  }
}
