{
  "geometry": {
    "type": "Point",
    "coordinates": [
      -83.2167,
      37.0167
    ]
  },
  "type": "Feature",
  "properties": {
    "hierarchy": [
      "tgn:2616225",
      "tgn:1000001",
      "tgn:7012149",
      "tgn:2000811",
      "tgn:7007255",
      "tgn:7029392"
    ],
    "placetype": [
      "aat:300008699"
    ],
    "id": 2616225,
    "name:xx": "Rhone Fork"
  }
}
