{
  "geometry": {
    "type": "Point",
    "coordinates": [
      -120.65,
      38.9333
    ]
  },
  "type": "Feature",
  "properties": {
    "hierarchy": [
      "tgn:2573336",
      "tgn:1000001",
      "tgn:7012149",
      "tgn:1002350",
      "tgn:7007157",
      "tgn:7029392"
    ],
    "placetype": [
      "aat:300266640"
    ],
    "id": 2573336,
    "name:xx": "Peavine Point"
  }
}
