{
  "geometry": {
    "type": "Point",
    "coordinates": [
      -80.5333,
      27.6167
    ]
  },
  "type": "Feature",
  "properties": {
    "hierarchy": [
      "tgn:2386144",
      "tgn:1000001",
      "tgn:1002500",
      "tgn:7012149",
      "tgn:7007240",
      "tgn:7029392"
    ],
    "placetype": [
      "aat:300008680"
    ],
    "id": 2386144,
    "name:xx": "Henry Schacht Lake"
  }
}
