{
  "geometry": {
    "type": "Point",
    "coordinates": [
      -82.8833,
      37.7333
    ]
  },
  "type": "Feature",
  "properties": {
    "hierarchy": [
      "tgn:2289856",
      "tgn:1000001",
      "tgn:7012149",
      "tgn:2000804",
      "tgn:7007255",
      "tgn:7029392"
    ],
    "placetype": [
      "aat:300008347"
    ],
    "id": 2289856,
    "name:xx": "Dobson"
  }
}
