{
  "type": "FeatureCollection",
  "features": [
    {
      "geometry": {
        "type": "Point",
        "coordinates": [
          -101.9,
          44.5333
        ]
      },
      "type": "Feature",
      "properties": {
        "hierarchy": [
          "tgn:2097060",
          "tgn:1000001",
          "tgn:7012149",
          "tgn:2001836",
          "tgn:7007713",
          "tgn:7029392"
        ],
        "placetype": [
          "aat:300008347"
        ],
        "id": 2097060,
        "name:xx": "Bridger"
      }
    },
    {
      "geometry": {
        "type": "Point",
        "coordinates": [
          -97.5,
          43.55
        ]
      },
      "type": "Feature",
      "properties": {
        "hierarchy": [
          "tgn:2097061",
          "tgn:1000001",
          "tgn:2001813",
          "tgn:7012149",
          "tgn:7007713",
          "tgn:7029392"
        ],
        "placetype": [
          "aat:300008347"
        ],
        "id": 2097061,
        "name:xx": "Bridgewater"
      }
    },
    {
      "geometry": {
        "type": "Point",
        "coordinates": [
          -97.7333,
          45.3333
        ]
      },
      "type": "Feature",
      "properties": {
        "hierarchy": [
          "tgn:2097062",
          "tgn:1000001",
          "tgn:2001788",
          "tgn:7012149",
          "tgn:7007713",
          "tgn:7029392"
        ],
        "placetype": [
          "aat:300008347"
        ],
        "id": 2097062,
        "name:xx": "Bristol"
      }
    },
    {
      "geometry": {
        "type": "Point",
        "coordinates": [
          -97.75,
          45.7833
        ]
      },
      "type": "Feature",
      "properties": {
        "hierarchy": [
          "tgn:2097063",
          "tgn:1000001",
          "tgn:2001815",
          "tgn:7012149",
          "tgn:7007713",
          "tgn:7029392"
        ],
        "placetype": [
          "aat:300008347"
        ],
        "id": 2097063,
        "name:xx": "Britton"
      }
    },
    {
      "geometry": {
        "type": "Point",
        "coordinates": [
          -98.3333,
          44.4833
        ]
      },
      "type": "Feature",
      "properties": {
        "hierarchy": [
          "tgn:2097065",
          "tgn:2001772",
          "tgn:1000001",
          "tgn:7012149",
          "tgn:7007713",
          "tgn:7029392"
        ],
        "placetype": [
          "aat:300008347"
        ],
        "id": 2097065,
        "name:xx": "Broadland"
      }
    },
    {
      "geometry": {
        "type": "Point",
        "coordinates": [
          -96.8833,
          44.4333
        ]
      },
      "type": "Feature",
      "properties": {
        "hierarchy": [
          "tgn:2097069",
          "tgn:1000001",
          "tgn:2001775",
          "tgn:7012149",
          "tgn:7007713",
          "tgn:7029392"
        ],
        "placetype": [
          "aat:300008347"
        ],
        "id": 2097069,
        "name:xx": "Bruce"
      }
    }
  ]
}
