{
  "geometry": {
    "type": "Point",
    "coordinates": [
      -109.0667,
      33.55
    ]
  },
  "type": "Feature",
  "properties": {
    "hierarchy": [
      "tgn:2224730",
      "tgn:1000001",
      "tgn:7006451",
      "tgn:2000095",
      "tgn:7012149",
      "tgn:7029392"
    ],
    "placetype": [
      "aat:300008697"
    ],
    "id": 2224730,
    "name:xx": "Cashier Spring"
  }
}
