{
  "type": "FeatureCollection",
  "features": [
    {
      "geometry": {
        "type": "Point",
        "coordinates": [
          30.280224,
          30.899879
        ]
      },
      "type": "Feature",
      "properties": {
        "hierarchy": [
          "tgn:7544060",
          "tgn:7001242",
          "tgn:1001075",
          "tgn:7016833",
          "tgn:7029392"
        ],
        "placetype": [
          "aat:300006075"
        ],
        "name:en": "Tir'at Ḩawsh 'Īsá",
        "id": 7544060
      }
    },
    {
      "geometry": {
        "type": "Point",
        "coordinates": [
          30.482065,
          30.924133
        ]
      },
      "type": "Feature",
      "properties": {
        "hierarchy": [
          "tgn:7544061",
          "tgn:7001242",
          "tgn:1001075",
          "tgn:7016833",
          "tgn:7029392"
        ],
        "placetype": [
          "aat:300008347"
        ],
        "name:en": "Naj' Muḩammad Fāḑīl",
        "id": 7544061
      }
    },
    {
      "geometry": {
        "type": "Point",
        "coordinates": [
          30.352525,
          30.917411
        ]
      },
      "type": "Feature",
      "properties": {
        "hierarchy": [
          "tgn:7544062",
          "tgn:7001242",
          "tgn:1001075",
          "tgn:7016833",
          "tgn:7029392"
        ],
        "placetype": [
          "aat:300008347"
        ],
        "name:en": "Farhāsh",
        "id": 7544062
      }
    },
    {
      "geometry": {
        "type": "Point",
        "coordinates": [
          30.49776,
          30.915372
        ]
      },
      "type": "Feature",
      "properties": {
        "hierarchy": [
          "tgn:7544063",
          "tgn:7001242",
          "tgn:1001075",
          "tgn:7016833",
          "tgn:7029392"
        ],
        "placetype": [
          "aat:300008347"
        ],
        "name:en": "Naj' Rashīd Mihannā",
        "id": 7544063
      }
    },
    {
      "geometry": {
        "type": "Point",
        "coordinates": [
          30.478186,
          30.910224
        ]
      },
      "type": "Feature",
      "properties": {
        "hierarchy": [
          "tgn:7544064",
          "tgn:7001242",
          "tgn:1001075",
          "tgn:7016833",
          "tgn:7029392"
        ],
        "placetype": [
          "aat:300008347"
        ],
        "name:en": "Naj' ad Dūktūr",
        "id": 7544064
      }
    },
    {
      "geometry": {
        "type": "Point",
        "coordinates": [
          30.491909,
          30.908693
        ]
      },
      "type": "Feature",
      "properties": {
        "hierarchy": [
          "tgn:7544065",
          "tgn:7001242",
          "tgn:1001075",
          "tgn:7016833",
          "tgn:7029392"
        ],
        "placetype": [
          "aat:300008347"
        ],
        "name:en": "Naj' Bīr al 'Asal",
        "id": 7544065
      }
    },
    {
      "geometry": {
        "type": "Point",
        "coordinates": [
          30.49223,
          30.899686
        ]
      },
      "type": "Feature",
      "properties": {
        "hierarchy": [
          "tgn:7544066",
          "tgn:7001242",
          "tgn:1001075",
          "tgn:7016833",
          "tgn:7029392"
        ],
        "placetype": [
          "aat:300008347"
        ],
        "name:en": "Naj' al Gharbāwī",
        "id": 7544066
      }
    },
    {
      "geometry": {
        "type": "Point",
        "coordinates": [
          30.476727,
          30.895711
        ]
      },
      "type": "Feature",
      "properties": {
        "hierarchy": [
          "tgn:7544067",
          "tgn:7001242",
          "tgn:1001075",
          "tgn:7016833",
          "tgn:7029392"
        ],
        "placetype": [
          "aat:300008347"
        ],
        "name:en": "Naj' al 'Aţfī",
        "id": 7544067
      }
    },
    {
      "geometry": {
        "type": "Point",
        "coordinates": [
          30.278396,
          30.810485
        ]
      },
      "type": "Feature",
      "properties": {
        "hierarchy": [
          "tgn:7544068",
          "tgn:7001242",
          "tgn:1001075",
          "tgn:7016833",
          "tgn:7029392"
        ],
        "placetype": [
          "aat:300006075"
        ],
        "name:en": "Tir'at 'Abd al Qādir",
        "id": 7544068
      }
    },
    {
      "geometry": {
        "type": "Point",
        "coordinates": [
          31.711623,
          31.254496
        ]
      },
      "type": "Feature",
      "properties": {
        "hierarchy": [
          "tgn:7544069",
          "tgn:7001242",
          "tgn:7016833",
          "tgn:1001225",
          "tgn:7029392"
        ],
        "placetype": [
          "aat:300008347"
        ],
        "id": 7544069,
        "name:xx": "'Izbat al Mākīnah"
      }
    }
  ]
}
