{
  "type": "FeatureCollection",
  "features": [
    {
      "geometry": {
        "type": "Point",
        "coordinates": [
          14.216667,
          41.583333
        ]
      },
      "type": "Feature",
      "properties": {
        "hierarchy": [
          "tgn:7049400",
          "tgn:1003464",
          "tgn:1000003",
          "tgn:7003241",
          "tgn:1000080",
          "tgn:7029392"
        ],
        "placetype": [
          "aat:300008699"
        ],
        "id": 7049400,
        "name:xx": "Carpino, Fiume"
      }
    },
    {
      "geometry": {
        "type": "Point",
        "coordinates": [
          12.383333,
          43.383333
        ]
      },
      "type": "Feature",
      "properties": {
        "hierarchy": [
          "tgn:7049402",
          "tgn:7003170",
          "tgn:1000003",
          "tgn:7003125",
          "tgn:1000080",
          "tgn:7029392"
        ],
        "placetype": [
          "aat:300008347"
        ],
        "id": 7049402,
        "name:xx": "Carpini"
      }
    },
    {
      "geometry": {
        "type": "Point",
        "coordinates": [
          14.5,
          42
        ]
      },
      "type": "Feature",
      "properties": {
        "hierarchy": [
          "tgn:7049403",
          "tgn:7009084",
          "tgn:7003000",
          "tgn:1000003",
          "tgn:1000080",
          "tgn:7029392"
        ],
        "placetype": [
          "aat:300008347"
        ],
        "id": 7049403,
        "name:xx": "Carpineto Sinello"
      }
    },
    {
      "geometry": {
        "type": "Point",
        "coordinates": [
          11.033333,
          44.1
        ]
      },
      "type": "Feature",
      "properties": {
        "hierarchy": [
          "tgn:7049407",
          "tgn:7003127",
          "tgn:1000003",
          "tgn:7008516",
          "tgn:1000080",
          "tgn:7029392"
        ],
        "placetype": [
          "aat:300008347"
        ],
        "id": 7049407,
        "name:xx": "Carpineta"
      }
    },
    {
      "geometry": {
        "type": "Point",
        "coordinates": [
          12.138889,
          44.239167
        ]
      },
      "type": "Feature",
      "properties": {
        "hierarchy": [
          "tgn:7049409",
          "tgn:7003129",
          "tgn:1000003",
          "tgn:7008516",
          "tgn:1000080",
          "tgn:7029392"
        ],
        "placetype": [
          "aat:300008347"
        ],
        "id": 7049409,
        "name:xx": "Carpinello"
      }
    }
  ]
}
