{
  "geometry": {
    "type": "Point",
    "coordinates": [
      -72.0833,
      43.7667
    ]
  },
  "type": "Feature",
  "properties": {
    "hierarchy": [
      "tgn:2215208",
      "tgn:1000001",
      "tgn:2001424",
      "tgn:7012149",
      "tgn:7007564",
      "tgn:7029392"
    ],
    "placetype": [
      "aat:300008699"
    ],
    "id": 2215208,
    "name:xx": "Call Brook"
  }
}
