{
  "geometry": {
    "type": "Point",
    "coordinates": [
      -76.45,
      37.3667
    ]
  },
  "type": "Feature",
  "properties": {
    "hierarchy": [
      "tgn:2419607",
      "tgn:1000001",
      "tgn:7012149",
      "tgn:1002411",
      "tgn:7007919",
      "tgn:7029392"
    ],
    "placetype": [
      "aat:300008850"
    ],
    "id": 2419607,
    "name:xx": "Jarvis Point"
  }
}
