{
  "geometry": {
    "type": "Point",
    "coordinates": [
      44.85,
      10.1667
    ]
  },
  "type": "Feature",
  "properties": {
    "hierarchy": [
      "tgn:1092673",
      "tgn:7001242",
      "tgn:1001774",
      "tgn:1000192",
      "tgn:7029392"
    ],
    "placetype": [
      "aat:300008347"
    ],
    "id": 1092673,
    "name:xx": "Daragodleh"
  }
}
