{
  "geometry": {
    "type": "Point",
    "coordinates": [
      -159.0833,
      56.25
    ]
  },
  "type": "Feature",
  "properties": {
    "hierarchy": [
      "tgn:2440651",
      "tgn:7006450",
      "tgn:1000001",
      "tgn:7030517",
      "tgn:7012149",
      "tgn:7029392"
    ],
    "placetype": [
      "aat:300008798"
    ],
    "id": 2440651,
    "name:xx": "Knife Peak"
  }
}
