{
  "geometry": {
    "type": "Point",
    "coordinates": [
      -114.0167,
      45.9333
    ]
  },
  "type": "Feature",
  "properties": {
    "hierarchy": [
      "tgn:2154706",
      "tgn:1000001",
      "tgn:7012149",
      "tgn:2001300",
      "tgn:7007524",
      "tgn:7029392"
    ],
    "placetype": [
      "aat:300008761"
    ],
    "id": 2154706,
    "name:xx": "Bear Gulch"
  }
}
