{
  "geometry": {
    "type": "Point",
    "coordinates": [
      -72.7667,
      42.7167
    ]
  },
  "type": "Feature",
  "properties": {
    "hierarchy": [
      "tgn:2607132",
      "tgn:1000001",
      "tgn:7012149",
      "tgn:7029392"
    ],
    "placetype": [
      "aat:300008699"
    ],
    "id": 2607132,
    "name:xx": "Randall Brook"
  }
}
