{
  "geometry": {
    "type": "Point",
    "coordinates": [
      -97.8167,
      29.05
    ]
  },
  "type": "Feature",
  "properties": {
    "hierarchy": [
      "tgn:2377279",
      "tgn:1000001",
      "tgn:7012149",
      "tgn:1002533",
      "tgn:7007826",
      "tgn:7029392"
    ],
    "placetype": [
      "aat:300008347"
    ],
    "id": 2377279,
    "name:xx": "Harmony"
  }
}
