{
  "geometry": {
    "type": "Point",
    "coordinates": [
      1.55,
      48.6167
    ]
  },
  "type": "Feature",
  "properties": {
    "hierarchy": [
      "tgn:1123531",
      "tgn:1000003",
      "tgn:1000070",
      "tgn:7029392"
    ],
    "placetype": [
      "aat:300008707"
    ],
    "id": 1123531,
    "name:xx": "Drouette"
  }
}
