{
  "geometry": {
    "type": "Point",
    "coordinates": [
      -94.8333,
      39.3333
    ]
  },
  "type": "Feature",
  "properties": {
    "hierarchy": [
      "tgn:2523693",
      "tgn:1000001",
      "tgn:7012149",
      "tgn:2001231",
      "tgn:7007523",
      "tgn:7029392"
    ],
    "placetype": [
      "aat:300008699"
    ],
    "id": 2523693,
    "name:xx": "Moppin Branch"
  }
}
