{
  "geometry": {
    "type": "Point",
    "coordinates": [
      -75.8333,
      41.2167
    ]
  },
  "type": "Feature",
  "properties": {
    "hierarchy": [
      "tgn:2558596",
      "tgn:1000001",
      "tgn:7012149",
      "tgn:1002612",
      "tgn:7007710",
      "tgn:7029392"
    ],
    "placetype": [
      "aat:300008347"
    ],
    "id": 2558596,
    "name:xx": "Oliver Mills"
  }
}
