{
  "geometry": {
    "type": "Point",
    "coordinates": [
      22.65,
      39.433333
    ]
  },
  "type": "Feature",
  "properties": {
    "hierarchy": [
      "tgn:7223820",
      "tgn:7002750",
      "tgn:7001399",
      "tgn:1000003",
      "tgn:1000074",
      "tgn:7029392"
    ],
    "placetype": [
      "aat:300008699"
    ],
    "id": 7223820,
    "name:xx": "Onkhistós Réa"
  }
}
