{
  "geometry": {
    "type": "Point",
    "coordinates": [
      46.9167,
      39.9833
    ]
  },
  "type": "Feature",
  "properties": {
    "hierarchy": [
      "tgn:1051968",
      "tgn:7011438",
      "tgn:1000004",
      "tgn:7006646",
      "tgn:7029392"
    ],
    "placetype": [
      "aat:300008347",
      "aat:300008375"
    ],
    "id": 1051968,
    "name:xx": "Agdam"
  }
}
