{
  "geometry": {
    "type": "Point",
    "coordinates": [
      -81.5333,
      29.2833
    ]
  },
  "type": "Feature",
  "properties": {
    "hierarchy": [
      "tgn:2773843",
      "tgn:1000001",
      "tgn:7012149",
      "tgn:1002977",
      "tgn:7007240",
      "tgn:7029392"
    ],
    "placetype": [
      "aat:300132316"
    ],
    "id": 2773843,
    "name:xx": "Willow Cove"
  }
}
