{
  "geometry": {
    "type": "Point",
    "coordinates": [
      -83.3667,
      35.6333
    ]
  },
  "type": "Feature",
  "properties": {
    "hierarchy": [
      "tgn:2495573",
      "tgn:1000001",
      "tgn:7012149",
      "tgn:7029392"
    ],
    "placetype": [
      "aat:300008798"
    ],
    "id": 2495573,
    "name:xx": "Masa Knob"
  }
}
