{
  "type": "FeatureCollection",
  "features": [
    {
      "geometry": {
        "type": "Point",
        "coordinates": [
          120.882295,
          24.681921
        ]
      },
      "type": "Feature",
      "properties": {
        "hierarchy": [
          "tgn:7473800",
          "tgn:7487020",
          "tgn:1000004",
          "tgn:1000141",
          "tgn:7029392"
        ],
        "placetype": [
          "aat:300008347"
        ],
        "id": 7473800,
        "name:xx": "Tianliao"
      }
    },
    {
      "geometry": {
        "type": "Point",
        "coordinates": [
          120.5775,
          24.291667
        ]
      },
      "type": "Feature",
      "properties": {
        "hierarchy": [
          "tgn:7473801",
          "tgn:1000004",
          "tgn:7001009",
          "tgn:1000141",
          "tgn:7029392"
        ],
        "placetype": [
          "aat:300008347"
        ],
        "id": 7473801,
        "name:xx": "Tianliao"
      }
    },
    {
      "geometry": {
        "type": "Point",
        "coordinates": [
          120.5254,
          24.0439
        ]
      },
      "type": "Feature",
      "properties": {
        "hierarchy": [
          "tgn:7473802",
          "tgn:1000004",
          "tgn:7467799",
          "tgn:1000141",
          "tgn:7029392"
        ],
        "placetype": [
          "aat:300008347"
        ],
        "id": 7473802,
        "name:xx": "Tianliao"
      }
    },
    {
      "geometry": {
        "type": "Point",
        "coordinates": [
          120.500827,
          23.960533
        ]
      },
      "type": "Feature",
      "properties": {
        "hierarchy": [
          "tgn:7473803",
          "tgn:1000004",
          "tgn:7467799",
          "tgn:1000141",
          "tgn:7029392"
        ],
        "placetype": [
          "aat:300008347"
        ],
        "id": 7473803,
        "name:xx": "Tianliao"
      }
    },
    {
      "geometry": {
        "type": "Point",
        "coordinates": [
          120.350359,
          23.768806
        ]
      },
      "type": "Feature",
      "properties": {
        "hierarchy": [
          "tgn:7473805",
          "tgn:1000004",
          "tgn:7001014",
          "tgn:1000141",
          "tgn:7029392"
        ],
        "placetype": [
          "aat:300008347"
        ],
        "id": 7473805,
        "name:xx": "Tianliao"
      }
    },
    {
      "geometry": {
        "type": "Point",
        "coordinates": [
          120.574457,
          23.419237
        ]
      },
      "type": "Feature",
      "properties": {
        "hierarchy": [
          "tgn:7473808",
          "tgn:7468018",
          "tgn:1000004",
          "tgn:1000141",
          "tgn:7029392"
        ],
        "placetype": [
          "aat:300008347"
        ],
        "id": 7473808,
        "name:xx": "Tianliao"
      }
    },
    {
      "geometry": {
        "type": "Point",
        "coordinates": [
          120.258991,
          23.517975
        ]
      },
      "type": "Feature",
      "properties": {
        "hierarchy": [
          "tgn:7473809",
          "tgn:7468018",
          "tgn:1000004",
          "tgn:1000141",
          "tgn:7029392"
        ],
        "placetype": [
          "aat:300008347"
        ],
        "id": 7473809,
        "name:xx": "Tianliao"
      }
    }
  ]
}
