{
  "geometry": {
    "type": "Point",
    "coordinates": [
      -107.3333,
      35.4667
    ]
  },
  "type": "Feature",
  "properties": {
    "hierarchy": [
      "tgn:2521555",
      "tgn:1000001",
      "tgn:7012149",
      "tgn:7019676",
      "tgn:7007566",
      "tgn:7029392"
    ],
    "placetype": [
      "aat:300008798"
    ],
    "id": 2521555,
    "name:xx": "Montoso, Cerro"
  }
}
