{
  "geometry": {
    "type": "Point",
    "coordinates": [
      -85.0167,
      42.6667
    ]
  },
  "type": "Feature",
  "properties": {
    "hierarchy": [
      "tgn:2648581",
      "tgn:1000001",
      "tgn:2000957",
      "tgn:7012149",
      "tgn:7007520",
      "tgn:7029392"
    ],
    "placetype": [
      "aat:300008706"
    ],
    "id": 2648581,
    "name:xx": "Scipio Creek"
  }
}
