{
  "type": "FeatureCollection",
  "features": [
    {
      "geometry": {
        "type": "Point",
        "coordinates": [
          -70.7667,
          43.2667
        ]
      },
      "type": "Feature",
      "properties": {
        "hierarchy": [
          "tgn:2372690",
          "tgn:1000001",
          "tgn:7012149",
          "tgn:2000933",
          "tgn:7007515",
          "tgn:7029392"
        ],
        "placetype": [
          "aat:300008798"
        ],
        "id": 2372690,
        "name:xx": "Hall Hill"
      }
    },
    {
      "geometry": {
        "type": "Point",
        "coordinates": [
          -67.65,
          44.5833
        ]
      },
      "type": "Feature",
      "properties": {
        "hierarchy": [
          "tgn:2372691",
          "tgn:1000001",
          "tgn:7012149",
          "tgn:7014589",
          "tgn:7007515",
          "tgn:7029392"
        ],
        "placetype": [
          "aat:300008798"
        ],
        "id": 2372691,
        "name:xx": "Hall Hill"
      }
    },
    {
      "geometry": {
        "type": "Point",
        "coordinates": [
          -68.4167,
          45
        ]
      },
      "type": "Feature",
      "properties": {
        "hierarchy": [
          "tgn:2372692",
          "tgn:1000001",
          "tgn:7012149",
          "tgn:2000927",
          "tgn:7007515",
          "tgn:7029392"
        ],
        "placetype": [
          "aat:300008798"
        ],
        "id": 2372692,
        "name:xx": "Hall Hill"
      }
    },
    {
      "geometry": {
        "type": "Point",
        "coordinates": [
          -73.55,
          44.35
        ]
      },
      "type": "Feature",
      "properties": {
        "hierarchy": [
          "tgn:2372693",
          "tgn:1000001",
          "tgn:7012149",
          "tgn:2001461",
          "tgn:7007568",
          "tgn:7029392"
        ],
        "placetype": [
          "aat:300008798"
        ],
        "id": 2372693,
        "name:xx": "Hall Hill"
      }
    },
    {
      "geometry": {
        "type": "Point",
        "coordinates": [
          -100.45,
          46.05
        ]
      },
      "type": "Feature",
      "properties": {
        "hierarchy": [
          "tgn:2372694",
          "tgn:1000001",
          "tgn:2001571",
          "tgn:7012149",
          "tgn:7007705",
          "tgn:7029392"
        ],
        "placetype": [
          "aat:300008798"
        ],
        "id": 2372694,
        "name:xx": "Hall Hill"
      }
    },
    {
      "geometry": {
        "type": "Point",
        "coordinates": [
          -118.7667,
          44.4333
        ]
      },
      "type": "Feature",
      "properties": {
        "hierarchy": [
          "tgn:2372695",
          "tgn:1000001",
          "tgn:7012149",
          "tgn:2001708",
          "tgn:7007708",
          "tgn:7029392"
        ],
        "placetype": [
          "aat:300008798"
        ],
        "id": 2372695,
        "name:xx": "Hall Hill"
      }
    },
    {
      "geometry": {
        "type": "Point",
        "coordinates": [
          -72.4667,
          43.55
        ]
      },
      "type": "Feature",
      "properties": {
        "hierarchy": [
          "tgn:2372696",
          "tgn:1000001",
          "tgn:2002136",
          "tgn:7012149",
          "tgn:7007828",
          "tgn:7029392"
        ],
        "placetype": [
          "aat:300008798"
        ],
        "id": 2372696,
        "name:xx": "Hall Hill"
      }
    },
    {
      "geometry": {
        "type": "Point",
        "coordinates": [
          -72.4667,
          42
        ]
      },
      "type": "Feature",
      "properties": {
        "hierarchy": [
          "tgn:2372697",
          "tgn:1000001",
          "tgn:1002949",
          "tgn:7012149",
          "tgn:7007159",
          "tgn:7029392"
        ],
        "placetype": [
          "aat:300008699"
        ],
        "id": 2372697,
        "name:xx": "Hall Hill Brook"
      }
    },
    {
      "geometry": {
        "type": "Point",
        "coordinates": [
          -86.15,
          34.7
        ]
      },
      "type": "Feature",
      "properties": {
        "hierarchy": [
          "tgn:2372698",
          "tgn:7002659",
          "tgn:1000001",
          "tgn:7012149",
          "tgn:2000035",
          "tgn:7029392"
        ],
        "placetype": [
          "aat:300008761"
        ],
        "id": 2372698,
        "name:xx": "Hall Hollow"
      }
    },
    {
      "geometry": {
        "type": "Point",
        "coordinates": [
          -85.2,
          34.65
        ]
      },
      "type": "Feature",
      "properties": {
        "hierarchy": [
          "tgn:2372699",
          "tgn:1000001",
          "tgn:7012149",
          "tgn:2000437",
          "tgn:7007248",
          "tgn:7029392"
        ],
        "placetype": [
          "aat:300008761"
        ],
        "id": 2372699,
        "name:xx": "Hall Hollow"
      }
    }
  ]
}
