{
  "geometry": {
    "type": "Point",
    "coordinates": [
      -110.4333,
      34.4167
    ]
  },
  "type": "Feature",
  "properties": {
    "hierarchy": [
      "tgn:2761228",
      "tgn:1000001",
      "tgn:7006451",
      "tgn:7012149",
      "tgn:2000099",
      "tgn:7029392"
    ],
    "placetype": [
      "aat:300006191"
    ],
    "id": 2761228,
    "name:xx": "West Long Hollow Tank"
  }
}
