{
  "geometry": {
    "type": "Point",
    "coordinates": [
      -111.3167,
      43.3333
    ]
  },
  "type": "Feature",
  "properties": {
    "hierarchy": [
      "tgn:2467379",
      "tgn:1000001",
      "tgn:2000461",
      "tgn:7012149",
      "tgn:7007250",
      "tgn:7029392"
    ],
    "placetype": [
      "aat:300008761"
    ],
    "id": 2467379,
    "name:xx": "Long Gulch"
  }
}
