{
  "geometry": {
    "type": "Point",
    "coordinates": [
      -90.6167,
      33.2833
    ]
  },
  "type": "Feature",
  "properties": {
    "hierarchy": [
      "tgn:2597978",
      "tgn:1000001",
      "tgn:7012149",
      "tgn:2001152",
      "tgn:7007522",
      "tgn:7029392"
    ],
    "placetype": [
      "aat:300008798"
    ],
    "id": 2597978,
    "name:xx": "Prentiss Mound"
  }
}
