{
  "geometry": {
    "type": "Point",
    "coordinates": [
      40.8833,
      44.2833
    ]
  },
  "type": "Feature",
  "properties": {
    "hierarchy": [
      "tgn:1122076",
      "tgn:1000004",
      "tgn:7002435",
      "tgn:7029392"
    ],
    "placetype": [
      "aat:300008707"
    ],
    "id": 1122076,
    "name:xx": "Bol'shaya Laba"
  }
}
