{
  "geometry": {
    "type": "Point",
    "coordinates": [
      -107.6167,
      42.8167
    ]
  },
  "type": "Feature",
  "properties": {
    "hierarchy": [
      "tgn:2644551",
      "tgn:1000001",
      "tgn:7012149",
      "tgn:2002371",
      "tgn:7007923",
      "tgn:7029392"
    ],
    "placetype": [
      "aat:300008798"
    ],
    "id": 2644551,
    "name:xx": "Sarcophagus Butte"
  }
}
