{
  "geometry": {
    "type": "Point",
    "coordinates": [
      91.51,
      23.807474
    ]
  },
  "type": "Feature",
  "properties": {
    "hierarchy": [
      "tgn:7550263",
      "tgn:1000004",
      "tgn:7000198",
      "tgn:1001578",
      "tgn:7029392"
    ],
    "placetype": [
      "aat:300008347"
    ],
    "name:en": "Chandrasādhubāri",
    "id": 7550263
  }
}
