{
  "geometry": {
    "type": "Point",
    "coordinates": [
      -74.2833,
      43.1833
    ]
  },
  "type": "Feature",
  "properties": {
    "hierarchy": [
      "tgn:2519056",
      "tgn:1000001",
      "tgn:7012149",
      "tgn:1002397",
      "tgn:7007568",
      "tgn:7029392"
    ],
    "placetype": [
      "aat:300008905"
    ],
    "id": 2519056,
    "name:xx": "Moat Vly"
  }
}
