{
  "geometry": {
    "type": "Point",
    "coordinates": [
      117.2333,
      35.1667
    ]
  },
  "type": "Feature",
  "properties": {
    "hierarchy": [
      "tgn:1139701",
      "tgn:1000004",
      "tgn:7002085",
      "tgn:1000111",
      "tgn:7029392"
    ],
    "placetype": [
      "aat:300008347"
    ],
    "id": 1139701,
    "name:xx": "Teng Xian"
  }
}
