{
  "geometry": {
    "type": "Point",
    "coordinates": [
      -116.2833,
      46.7833
    ]
  },
  "type": "Feature",
  "properties": {
    "hierarchy": [
      "tgn:2562919",
      "tgn:1000001",
      "tgn:2000469",
      "tgn:7012149",
      "tgn:7007250",
      "tgn:7029392"
    ],
    "placetype": [
      "aat:300008706"
    ],
    "id": 2562919,
    "name:xx": "Oviatt Creek"
  }
}
