{
  "type": "FeatureCollection",
  "features": [
    {
      "geometry": {
        "type": "Point",
        "coordinates": [
          10.816667,
          51.433333
        ]
      },
      "type": "Feature",
      "properties": {
        "hierarchy": [
          "tgn:7108100",
          "tgn:1000003",
          "tgn:7003689",
          "tgn:7000084",
          "tgn:7029392"
        ],
        "placetype": [
          "aat:300008777"
        ],
        "id": 7108100,
        "name:xx": "Rade-Berg"
      }
    },
    {
      "geometry": {
        "type": "Point",
        "coordinates": [
          7.9,
          51.366667
        ]
      },
      "type": "Feature",
      "properties": {
        "hierarchy": [
          "tgn:7108101",
          "tgn:1000003",
          "tgn:7003677",
          "tgn:7000084",
          "tgn:7029392"
        ],
        "placetype": [
          "aat:300008777"
        ],
        "id": 7108101,
        "name:xx": "Rade-Berg"
      }
    },
    {
      "geometry": {
        "type": "Point",
        "coordinates": [
          7.3,
          49.683333
        ]
      },
      "type": "Feature",
      "properties": {
        "hierarchy": [
          "tgn:7108102",
          "tgn:1000003",
          "tgn:7003682",
          "tgn:7000084",
          "tgn:7029392"
        ],
        "placetype": [
          "aat:300008777"
        ],
        "id": 7108102,
        "name:xx": "Rade-Berg"
      }
    },
    {
      "geometry": {
        "type": "Point",
        "coordinates": [
          11.716667,
          53.766667
        ]
      },
      "type": "Feature",
      "properties": {
        "hierarchy": [
          "tgn:7108103",
          "tgn:1000003",
          "tgn:7000094",
          "tgn:7000084",
          "tgn:7029392"
        ],
        "placetype": [
          "aat:300008699"
        ],
        "id": 7108103,
        "name:xx": "Rade-Bach"
      }
    },
    {
      "geometry": {
        "type": "Point",
        "coordinates": [
          8.3,
          51.066667
        ]
      },
      "type": "Feature",
      "properties": {
        "hierarchy": [
          "tgn:7108104",
          "tgn:1000003",
          "tgn:7003677",
          "tgn:7000084",
          "tgn:7029392"
        ],
        "placetype": [
          "aat:300000206"
        ],
        "id": 7108104,
        "name:xx": "Radebach"
      }
    },
    {
      "geometry": {
        "type": "Point",
        "coordinates": [
          9.75,
          54.333333
        ]
      },
      "type": "Feature",
      "properties": {
        "hierarchy": [
          "tgn:7108105",
          "tgn:1000003",
          "tgn:7003688",
          "tgn:7000084",
          "tgn:7029392"
        ],
        "placetype": [
          "aat:300008347"
        ],
        "id": 7108105,
        "name:xx": "Rade"
      }
    },
    {
      "geometry": {
        "type": "Point",
        "coordinates": [
          9.716667,
          54.1
        ]
      },
      "type": "Feature",
      "properties": {
        "hierarchy": [
          "tgn:7108106",
          "tgn:1000003",
          "tgn:7003688",
          "tgn:7000084",
          "tgn:7029392"
        ],
        "placetype": [
          "aat:300008347"
        ],
        "id": 7108106,
        "name:xx": "Rade"
      }
    },
    {
      "geometry": {
        "type": "Point",
        "coordinates": [
          9.75,
          54
        ]
      },
      "type": "Feature",
      "properties": {
        "hierarchy": [
          "tgn:7108107",
          "tgn:1000003",
          "tgn:7003688",
          "tgn:7000084",
          "tgn:7029392"
        ],
        "placetype": [
          "aat:300008347"
        ],
        "id": 7108107,
        "name:xx": "Rade"
      }
    },
    {
      "geometry": {
        "type": "Point",
        "coordinates": [
          10.133333,
          53.733333
        ]
      },
      "type": "Feature",
      "properties": {
        "hierarchy": [
          "tgn:7108108",
          "tgn:1000003",
          "tgn:7003688",
          "tgn:7000084",
          "tgn:7029392"
        ],
        "placetype": [
          "aat:300008347"
        ],
        "id": 7108108,
        "name:xx": "Rade"
      }
    },
    {
      "geometry": {
        "type": "Point",
        "coordinates": [
          9.8,
          53.383333
        ]
      },
      "type": "Feature",
      "properties": {
        "hierarchy": [
          "tgn:7108109",
          "tgn:1000003",
          "tgn:7003676",
          "tgn:7000084",
          "tgn:7029392"
        ],
        "placetype": [
          "aat:300008347"
        ],
        "id": 7108109,
        "name:xx": "Rade"
      }
    }
  ]
}
