{
  "geometry": {
    "type": "Point",
    "coordinates": [
      29.8833,
      6.0333
    ]
  },
  "type": "Feature",
  "properties": {
    "hierarchy": [
      "tgn:1094381",
      "tgn:7001242",
      "tgn:1001081",
      "tgn:7441551",
      "tgn:7029392"
    ],
    "placetype": [
      "aat:300008347"
    ],
    "id": 1094381,
    "name:xx": "Mvolo"
  }
}
