{
  "type": "FeatureCollection",
  "features": [
    {
      "geometry": {
        "type": "Point",
        "coordinates": [
          -105.533333,
          29.816667
        ]
      },
      "type": "Feature",
      "properties": {
        "hierarchy": [
          "tgn:7363040",
          "tgn:7005581",
          "tgn:1000001",
          "tgn:7005560",
          "tgn:7029392"
        ],
        "placetype": [
          "aat:300000241"
        ],
        "id": 7363040,
        "name:xx": "Rancho El Castillo"
      }
    },
    {
      "geometry": {
        "type": "Point",
        "coordinates": [
          -111.15,
          29
        ]
      },
      "type": "Feature",
      "properties": {
        "hierarchy": [
          "tgn:7363041",
          "tgn:1000001",
          "tgn:1001960",
          "tgn:7005560",
          "tgn:7029392"
        ],
        "placetype": [
          "aat:300000241"
        ],
        "id": 7363041,
        "name:xx": "Rancho El Castillo"
      }
    },
    {
      "geometry": {
        "type": "Point",
        "coordinates": [
          -104.25,
          19.933333
        ]
      },
      "type": "Feature",
      "properties": {
        "hierarchy": [
          "tgn:7363042",
          "tgn:7005586",
          "tgn:1000001",
          "tgn:7005560",
          "tgn:7029392"
        ],
        "placetype": [
          "aat:300006191"
        ],
        "id": 7363042,
        "name:xx": "El Castillo"
      }
    },
    {
      "geometry": {
        "type": "Point",
        "coordinates": [
          -103.233333,
          20.5
        ]
      },
      "type": "Feature",
      "properties": {
        "hierarchy": [
          "tgn:7363043",
          "tgn:7005586",
          "tgn:1000001",
          "tgn:7005560",
          "tgn:7029392"
        ],
        "placetype": [
          "aat:300007783"
        ],
        "id": 7363043,
        "name:xx": "El Castillo"
      }
    },
    {
      "geometry": {
        "type": "Point",
        "coordinates": [
          -110.183333,
          27.516667
        ]
      },
      "type": "Feature",
      "properties": {
        "hierarchy": [
          "tgn:7363044",
          "tgn:1000001",
          "tgn:1001960",
          "tgn:7005560",
          "tgn:7029392"
        ],
        "placetype": [
          "aat:300008347"
        ],
        "id": 7363044,
        "name:xx": "El Castillo"
      }
    },
    {
      "geometry": {
        "type": "Point",
        "coordinates": [
          -103.416667,
          25.65
        ]
      },
      "type": "Feature",
      "properties": {
        "hierarchy": [
          "tgn:7363045",
          "tgn:7005583",
          "tgn:1000001",
          "tgn:7005560",
          "tgn:7029392"
        ],
        "placetype": [
          "aat:300008347"
        ],
        "id": 7363045,
        "name:xx": "El Castillo"
      }
    },
    {
      "geometry": {
        "type": "Point",
        "coordinates": [
          -100,
          25.533333
        ]
      },
      "type": "Feature",
      "properties": {
        "hierarchy": [
          "tgn:7363046",
          "tgn:1000001",
          "tgn:7005589",
          "tgn:7005560",
          "tgn:7029392"
        ],
        "placetype": [
          "aat:300008347"
        ],
        "id": 7363046,
        "name:xx": "El Castillo"
      }
    },
    {
      "geometry": {
        "type": "Point",
        "coordinates": [
          -100.633333,
          25.183333
        ]
      },
      "type": "Feature",
      "properties": {
        "hierarchy": [
          "tgn:7363047",
          "tgn:1000001",
          "tgn:7005589",
          "tgn:7005560",
          "tgn:7029392"
        ],
        "placetype": [
          "aat:300008347"
        ],
        "id": 7363047,
        "name:xx": "El Castillo"
      }
    },
    {
      "geometry": {
        "type": "Point",
        "coordinates": [
          -107.720278,
          24.495556
        ]
      },
      "type": "Feature",
      "properties": {
        "hierarchy": [
          "tgn:7363048",
          "tgn:1000001",
          "tgn:7005595",
          "tgn:7005560",
          "tgn:7029392"
        ],
        "placetype": [
          "aat:300008347"
        ],
        "id": 7363048,
        "name:xx": "El Castillo"
      }
    },
    {
      "geometry": {
        "type": "Point",
        "coordinates": [
          -106.333333,
          23.183333
        ]
      },
      "type": "Feature",
      "properties": {
        "hierarchy": [
          "tgn:7363049",
          "tgn:1000001",
          "tgn:7005595",
          "tgn:7005560",
          "tgn:7029392"
        ],
        "placetype": [
          "aat:300008347"
        ],
        "id": 7363049,
        "name:xx": "El Castillo"
      }
    }
  ]
}
