{
  "geometry": {
    "type": "Point",
    "coordinates": [
      -92.1667,
      38.4833
    ]
  },
  "type": "Feature",
  "properties": {
    "hierarchy": [
      "tgn:2060827",
      "tgn:1000001",
      "tgn:7012149",
      "tgn:1002288",
      "tgn:7007523",
      "tgn:7029392"
    ],
    "placetype": [
      "aat:300008347"
    ],
    "id": 2060827,
    "name:xx": "Wardsville"
  }
}
