{
  "geometry": {
    "type": "Point",
    "coordinates": [
      79.322287,
      26.21393
    ]
  },
  "type": "Feature",
  "properties": {
    "hierarchy": [
      "tgn:7565078",
      "tgn:1000004",
      "tgn:7000198",
      "tgn:7016722",
      "tgn:7029392"
    ],
    "placetype": [
      "aat:300008347"
    ],
    "name:en": "Sahāo",
    "id": 7565078
  }
}
