{
  "geometry": {
    "type": "Point",
    "coordinates": [
      -155.15,
      58.0833
    ]
  },
  "type": "Feature",
  "properties": {
    "hierarchy": [
      "tgn:2725618",
      "tgn:7006450",
      "tgn:1000001",
      "tgn:2124012",
      "tgn:7012149",
      "tgn:7029392"
    ],
    "placetype": [
      "aat:300008798"
    ],
    "id": 2725618,
    "name:xx": "Topographers Peak"
  }
}
