{
  "geometry": {
    "type": "Point",
    "coordinates": [
      -104.2333,
      47.55
    ]
  },
  "type": "Feature",
  "properties": {
    "hierarchy": [
      "tgn:2653166",
      "tgn:1000001",
      "tgn:7012149",
      "tgn:2001301",
      "tgn:7007524",
      "tgn:7029392"
    ],
    "placetype": [
      "aat:300008791"
    ],
    "id": 2653166,
    "name:xx": "Seven Sisters Island"
  }
}
