{
  "geometry": {
    "type": "Point",
    "coordinates": [
      -97.8833,
      39.7167
    ]
  },
  "type": "Feature",
  "properties": {
    "hierarchy": [
      "tgn:2637365",
      "tgn:1000001",
      "tgn:7012149",
      "tgn:2000738",
      "tgn:7007254",
      "tgn:7029392"
    ],
    "placetype": [
      "aat:300008706"
    ],
    "id": 2637365,
    "name:xx": "Saint Johns Creek"
  }
}
