{
  "geometry": {
    "type": "Point",
    "coordinates": [
      30.15,
      38.0833
    ]
  },
  "type": "Feature",
  "properties": {
    "hierarchy": [
      "tgn:7017535",
      "tgn:7002513",
      "tgn:1000004",
      "tgn:7018451",
      "tgn:1000144",
      "tgn:7029392"
    ],
    "placetype": [
      "aat:300008347",
      "aat:300008375"
    ],
    "id": 7017535,
    "name:xx": "Dinar"
  }
}
