{
  "geometry": {
    "type": "Point",
    "coordinates": [
      54.1667,
      54.9833
    ]
  },
  "type": "Feature",
  "properties": {
    "hierarchy": [
      "tgn:1051557",
      "tgn:1000004",
      "tgn:7011498",
      "tgn:7002435",
      "tgn:7029392"
    ],
    "placetype": [
      "aat:300008347"
    ],
    "id": 1051557,
    "name:xx": "Sharanbashknyazevo"
  }
}
