{
  "geometry": {
    "type": "Point",
    "coordinates": [
      -83.2333,
      38.3167
    ]
  },
  "type": "Feature",
  "properties": {
    "hierarchy": [
      "tgn:2671948",
      "tgn:1000001",
      "tgn:1002240",
      "tgn:7012149",
      "tgn:7007255",
      "tgn:7029392"
    ],
    "placetype": [
      "aat:300008699"
    ],
    "id": 2671948,
    "name:xx": "Smith Run"
  }
}
