{
  "geometry": {
    "type": "Point",
    "coordinates": [
      -77.1167,
      35.4667
    ]
  },
  "type": "Feature",
  "properties": {
    "hierarchy": [
      "tgn:2429597",
      "tgn:1000001",
      "tgn:7013368",
      "tgn:7012149",
      "tgn:7007709",
      "tgn:7029392"
    ],
    "placetype": [
      "aat:300008699"
    ],
    "id": 2429597,
    "name:xx": "Juniper Swamp"
  }
}
