{
  "geometry": {
    "type": "Point",
    "coordinates": [
      17.3667,
      59.6167
    ]
  },
  "type": "Feature",
  "properties": {
    "hierarchy": [
      "tgn:7009810",
      "tgn:1000003",
      "tgn:1000462",
      "tgn:1000097",
      "tgn:7029392"
    ],
    "placetype": [
      "aat:300008347"
    ],
    "id": 7009810,
    "name:xx": "Ekolsund"
  }
}
