{
  "geometry": {
    "type": "Point",
    "coordinates": [
      -96.0667,
      35.9167
    ]
  },
  "type": "Feature",
  "properties": {
    "hierarchy": [
      "tgn:2667630",
      "tgn:1000001",
      "tgn:2001641",
      "tgn:7012149",
      "tgn:7007707",
      "tgn:7029392"
    ],
    "placetype": [
      "aat:300008706"
    ],
    "id": 2667630,
    "name:xx": "Skull Creek"
  }
}
