{
  "geometry": {
    "type": "Point",
    "coordinates": [
      -71.4167,
      42.7667
    ]
  },
  "type": "Feature",
  "properties": {
    "hierarchy": [
      "tgn:2613612",
      "tgn:1000001",
      "tgn:1002480",
      "tgn:7012149",
      "tgn:7007564",
      "tgn:7029392"
    ],
    "placetype": [
      "aat:300008699"
    ],
    "id": 2613612,
    "name:xx": "Reeds Brook"
  }
}
