{
  "type": "FeatureCollection",
  "features": [
    {
      "geometry": {
        "type": "Point",
        "coordinates": [
          -0.25,
          53.566667
        ]
      },
      "type": "Feature",
      "properties": {
        "hierarchy": [
          "tgn:1029690",
          "tgn:7002445",
          "tgn:1000003",
          "tgn:7008157",
          "tgn:7008591",
          "tgn:7029392"
        ],
        "placetype": [
          "aat:300008347",
          "aat:300008372"
        ],
        "name:en": "Keelby",
        "id": 1029690
      }
    },
    {
      "geometry": {
        "type": "Point",
        "coordinates": [
          -1.266667,
          52.816667
        ]
      },
      "type": "Feature",
      "properties": {
        "hierarchy": [
          "tgn:1029692",
          "tgn:7002445",
          "tgn:1000003",
          "tgn:7008155",
          "tgn:7008591",
          "tgn:7029392"
        ],
        "placetype": [
          "aat:300008347",
          "aat:300008375"
        ],
        "name:en": "Kegworth",
        "id": 1029692
      }
    },
    {
      "geometry": {
        "type": "Point",
        "coordinates": [
          -1.4667,
          54.7167
        ]
      },
      "type": "Feature",
      "properties": {
        "hierarchy": [
          "tgn:1029694",
          "tgn:7002445",
          "tgn:1000003",
          "tgn:7008127",
          "tgn:7008591",
          "tgn:7029392"
        ],
        "placetype": [
          "aat:300008347"
        ],
        "id": 1029694,
        "name:xx": "Kelloe"
      }
    },
    {
      "geometry": {
        "type": "Point",
        "coordinates": [
          -2.716667,
          53.2
        ]
      },
      "type": "Feature",
      "properties": {
        "hierarchy": [
          "tgn:1029695",
          "tgn:7002445",
          "tgn:7008114",
          "tgn:1000003",
          "tgn:7008591",
          "tgn:7029392"
        ],
        "placetype": [
          "aat:300008347"
        ],
        "name:en": "Kelsall",
        "id": 1029695
      }
    },
    {
      "geometry": {
        "type": "Point",
        "coordinates": [
          0.283333,
          51.666667
        ]
      },
      "type": "Feature",
      "properties": {
        "hierarchy": [
          "tgn:1029697",
          "tgn:7002445",
          "tgn:1000003",
          "tgn:7008131",
          "tgn:7008591",
          "tgn:7029392"
        ],
        "placetype": [
          "aat:300008347"
        ],
        "name:en": "Kelvedon Hatch",
        "id": 1029697
      }
    },
    {
      "geometry": {
        "type": "Point",
        "coordinates": [
          -2.2,
          52.133333
        ]
      },
      "type": "Feature",
      "properties": {
        "hierarchy": [
          "tgn:1029698",
          "tgn:7002445",
          "tgn:1000003",
          "tgn:5000227",
          "tgn:7008591",
          "tgn:7029392"
        ],
        "placetype": [
          "aat:300008347"
        ],
        "name:en": "Kempsey",
        "id": 1029698
      }
    },
    {
      "geometry": {
        "type": "Point",
        "coordinates": [
          -0.483333,
          52.1
        ]
      },
      "type": "Feature",
      "properties": {
        "hierarchy": [
          "tgn:1029699",
          "tgn:7002445",
          "tgn:7008103",
          "tgn:1000003",
          "tgn:7008591",
          "tgn:7029392"
        ],
        "placetype": [
          "aat:300008347"
        ],
        "id": 1029699,
        "name:xx": "Kempston"
      }
    }
  ]
}
