{
  "geometry": {
    "type": "Point",
    "coordinates": [
      -121.2667,
      38.0833
    ]
  },
  "type": "Feature",
  "properties": {
    "hierarchy": [
      "tgn:2010053",
      "tgn:1000001",
      "tgn:7012149",
      "tgn:7007157",
      "tgn:1002861",
      "tgn:7029392"
    ],
    "placetype": [
      "aat:300387016"
    ],
    "id": 2010053,
    "name:xx": "Armstrong"
  }
}
