{
  "geometry": {
    "type": "Point",
    "coordinates": [
      -79.8167,
      34.6167
    ]
  },
  "type": "Feature",
  "properties": {
    "hierarchy": [
      "tgn:2405415",
      "tgn:1000001",
      "tgn:2001737",
      "tgn:7012149",
      "tgn:7007712",
      "tgn:7029392"
    ],
    "placetype": [
      "aat:300008706"
    ],
    "id": 2405415,
    "name:xx": "Hugh Creek"
  }
}
