{
  "geometry": {
    "type": "Point",
    "coordinates": [
      -112.0167,
      43.7667
    ]
  },
  "type": "Feature",
  "properties": {
    "hierarchy": [
      "tgn:2433277",
      "tgn:1000001",
      "tgn:7012149",
      "tgn:2000477",
      "tgn:7007250",
      "tgn:7029392"
    ],
    "placetype": [
      "aat:300008791"
    ],
    "id": 2433277,
    "name:xx": "Kellers Island"
  }
}
