{
  "geometry": {
    "type": "Point",
    "coordinates": [
      32.566667,
      22.75
    ]
  },
  "type": "Feature",
  "properties": {
    "hierarchy": [
      "tgn:1099700",
      "tgn:7001242",
      "tgn:7016833",
      "tgn:7000122",
      "tgn:7029392"
    ],
    "placetype": [
      "aat:300008347",
      "aat:300167671"
    ],
    "name:en": "As Subū'",
    "id": 1099700
  }
}
