{
  "geometry": {
    "type": "Point",
    "coordinates": [
      26.7167,
      52.8333
    ]
  },
  "type": "Feature",
  "properties": {
    "hierarchy": [
      "tgn:1056520",
      "tgn:1003357",
      "tgn:1000003",
      "tgn:7006657",
      "tgn:7029392"
    ],
    "placetype": [
      "aat:300008347"
    ],
    "id": 1056520,
    "name:xx": "Loktyši"
  }
}
