{
  "type": "FeatureCollection",
  "features": [
    {
      "geometry": {
        "type": "Point",
        "coordinates": [
          -108.5,
          38.7167
        ]
      },
      "type": "Feature",
      "properties": {
        "hierarchy": [
          "tgn:2509850",
          "tgn:1000001",
          "tgn:7012149",
          "tgn:2000230",
          "tgn:7007158",
          "tgn:7029392"
        ],
        "placetype": [
          "aat:300008798"
        ],
        "id": 2509850,
        "name:xx": "Middle Mesa"
      }
    },
    {
      "geometry": {
        "type": "Point",
        "coordinates": [
          -103.4,
          37.1
        ]
      },
      "type": "Feature",
      "properties": {
        "hierarchy": [
          "tgn:2509851",
          "tgn:1000001",
          "tgn:7012149",
          "tgn:2000227",
          "tgn:7007158",
          "tgn:7029392"
        ],
        "placetype": [
          "aat:300008798"
        ],
        "id": 2509851,
        "name:xx": "Middle Mesa"
      }
    },
    {
      "geometry": {
        "type": "Point",
        "coordinates": [
          -107.55,
          37
        ]
      },
      "type": "Feature",
      "properties": {
        "hierarchy": [
          "tgn:2509852",
          "tgn:1000001",
          "tgn:7012149",
          "tgn:7029392"
        ],
        "placetype": [
          "aat:300008798"
        ],
        "id": 2509852,
        "name:xx": "Middle Mesa"
      }
    },
    {
      "geometry": {
        "type": "Point",
        "coordinates": [
          -108.0333,
          33.1833
        ]
      },
      "type": "Feature",
      "properties": {
        "hierarchy": [
          "tgn:2509853",
          "tgn:1000001",
          "tgn:7012149",
          "tgn:2001437",
          "tgn:7007566",
          "tgn:7029392"
        ],
        "placetype": [
          "aat:300008798"
        ],
        "id": 2509853,
        "name:xx": "Middle Mesa"
      }
    },
    {
      "geometry": {
        "type": "Point",
        "coordinates": [
          -107.7167,
          34.5333
        ]
      },
      "type": "Feature",
      "properties": {
        "hierarchy": [
          "tgn:2509854",
          "tgn:1000001",
          "tgn:7012149",
          "tgn:7007566",
          "tgn:7029392"
        ],
        "placetype": [
          "aat:300008798"
        ],
        "id": 2509854,
        "name:xx": "Middle Mesa"
      }
    },
    {
      "geometry": {
        "type": "Point",
        "coordinates": [
          -105.1833,
          35.35
        ]
      },
      "type": "Feature",
      "properties": {
        "hierarchy": [
          "tgn:2509855",
          "tgn:1000001",
          "tgn:7012149",
          "tgn:2001453",
          "tgn:7007566",
          "tgn:7029392"
        ],
        "placetype": [
          "aat:300008798"
        ],
        "id": 2509855,
        "name:xx": "Middle Mesa"
      }
    },
    {
      "geometry": {
        "type": "Point",
        "coordinates": [
          -107.3167,
          36.9667
        ]
      },
      "type": "Feature",
      "properties": {
        "hierarchy": [
          "tgn:2509856",
          "tgn:1000001",
          "tgn:7012149",
          "tgn:2001449",
          "tgn:7007566",
          "tgn:7029392"
        ],
        "placetype": [
          "aat:300008798"
        ],
        "id": 2509856,
        "name:xx": "Middle Mesa"
      }
    },
    {
      "geometry": {
        "type": "Point",
        "coordinates": [
          -103.05,
          36.9667
        ]
      },
      "type": "Feature",
      "properties": {
        "hierarchy": [
          "tgn:2509857",
          "tgn:1000001",
          "tgn:7012149",
          "tgn:2001459",
          "tgn:7007566",
          "tgn:7029392"
        ],
        "placetype": [
          "aat:300008798"
        ],
        "id": 2509857,
        "name:xx": "Middle Mesa"
      }
    },
    {
      "geometry": {
        "type": "Point",
        "coordinates": [
          -109.1333,
          38.1833
        ]
      },
      "type": "Feature",
      "properties": {
        "hierarchy": [
          "tgn:2509858",
          "tgn:1000001",
          "tgn:7012149",
          "tgn:2002119",
          "tgn:7007827",
          "tgn:7029392"
        ],
        "placetype": [
          "aat:300008798"
        ],
        "id": 2509858,
        "name:xx": "Middle Mesa"
      }
    },
    {
      "geometry": {
        "type": "Point",
        "coordinates": [
          -107.7333,
          34.55
        ]
      },
      "type": "Feature",
      "properties": {
        "hierarchy": [
          "tgn:2509859",
          "tgn:1000001",
          "tgn:7012149",
          "tgn:7007566",
          "tgn:7029392"
        ],
        "placetype": [
          "aat:300008761"
        ],
        "id": 2509859,
        "name:xx": "Middle Mesa Canyon"
      }
    }
  ]
}
