{
  "geometry": {
    "type": "Point",
    "coordinates": [
      120.85,
      30.6833
    ]
  },
  "type": "Feature",
  "properties": {
    "hierarchy": [
      "tgn:1068033",
      "tgn:1000004",
      "tgn:7002076",
      "tgn:1000111",
      "tgn:7029392"
    ],
    "placetype": [
      "aat:300008347"
    ],
    "id": 1068033,
    "name:xx": "Fengjianjiao"
  }
}
