{
  "geometry": {
    "type": "Point",
    "coordinates": [
      -121.0167,
      46.3667
    ]
  },
  "type": "Feature",
  "properties": {
    "hierarchy": [
      "tgn:2126699",
      "tgn:1000001",
      "tgn:7012149",
      "tgn:1003042",
      "tgn:7007920",
      "tgn:7029392"
    ],
    "placetype": [
      "aat:300008706"
    ],
    "id": 2126699,
    "name:xx": "Agency Creek"
  }
}
