{
  "geometry": {
    "type": "Point",
    "coordinates": [
      -82.0333,
      26.4833
    ]
  },
  "type": "Feature",
  "properties": {
    "hierarchy": [
      "tgn:2579741",
      "tgn:1000001",
      "tgn:1002289",
      "tgn:7012149",
      "tgn:7007240",
      "tgn:7029392"
    ],
    "placetype": [
      "aat:300008791"
    ],
    "id": 2579741,
    "name:xx": "Picnic Island"
  }
}
