{
  "type": "FeatureCollection",
  "features": [
    {
      "geometry": {
        "type": "Point",
        "coordinates": [
          -82.8833,
          34.6667
        ]
      },
      "type": "Feature",
      "properties": {
        "hierarchy": [
          "tgn:2659300",
          "tgn:1000001",
          "tgn:7012149",
          "tgn:2001761",
          "tgn:7007712",
          "tgn:7029392"
        ],
        "placetype": [
          "aat:300008699"
        ],
        "id": 2659300,
        "name:xx": "Shiloh Branch"
      }
    },
    {
      "geometry": {
        "type": "Point",
        "coordinates": [
          -85.4833,
          35.1167
        ]
      },
      "type": "Feature",
      "properties": {
        "hierarchy": [
          "tgn:2659301",
          "tgn:1000001",
          "tgn:7012149",
          "tgn:2001894",
          "tgn:7007825",
          "tgn:7029392"
        ],
        "placetype": [
          "aat:300008699"
        ],
        "id": 2659301,
        "name:xx": "Shiloh Branch"
      }
    },
    {
      "geometry": {
        "type": "Point",
        "coordinates": [
          -88.3333,
          35.1
        ]
      },
      "type": "Feature",
      "properties": {
        "hierarchy": [
          "tgn:2659302",
          "tgn:1000001",
          "tgn:7012149",
          "tgn:2001872",
          "tgn:7007825",
          "tgn:7029392"
        ],
        "placetype": [
          "aat:300008699"
        ],
        "id": 2659302,
        "name:xx": "Shiloh Branch"
      }
    },
    {
      "geometry": {
        "type": "Point",
        "coordinates": [
          -87.7333,
          36.2333
        ]
      },
      "type": "Feature",
      "properties": {
        "hierarchy": [
          "tgn:2659303",
          "tgn:1000001",
          "tgn:7012149",
          "tgn:7007825",
          "tgn:7029392"
        ],
        "placetype": [
          "aat:300008699"
        ],
        "id": 2659303,
        "name:xx": "Shiloh Branch"
      }
    },
    {
      "geometry": {
        "type": "Point",
        "coordinates": [
          -96.8833,
          32.4833
        ]
      },
      "type": "Feature",
      "properties": {
        "hierarchy": [
          "tgn:2659304",
          "tgn:1000001",
          "tgn:7012149",
          "tgn:1002355",
          "tgn:7007826",
          "tgn:7029392"
        ],
        "placetype": [
          "aat:300008699"
        ],
        "id": 2659304,
        "name:xx": "Shiloh Branch"
      }
    },
    {
      "geometry": {
        "type": "Point",
        "coordinates": [
          -94.6333,
          31.9833
        ]
      },
      "type": "Feature",
      "properties": {
        "hierarchy": [
          "tgn:2659305",
          "tgn:1000001",
          "tgn:7012149",
          "tgn:1002839",
          "tgn:7007826",
          "tgn:7029392"
        ],
        "placetype": [
          "aat:300008699"
        ],
        "id": 2659305,
        "name:xx": "Shiloh Branch"
      }
    },
    {
      "geometry": {
        "type": "Point",
        "coordinates": [
          -95.4167,
          32.7833
        ]
      },
      "type": "Feature",
      "properties": {
        "hierarchy": [
          "tgn:2659306",
          "tgn:1000001",
          "tgn:7012149",
          "tgn:1003034",
          "tgn:7007826",
          "tgn:7029392"
        ],
        "placetype": [
          "aat:300008699"
        ],
        "id": 2659306,
        "name:xx": "Shiloh Branch"
      }
    },
    {
      "geometry": {
        "type": "Point",
        "coordinates": [
          -96.9833,
          30.0167
        ]
      },
      "type": "Feature",
      "properties": {
        "hierarchy": [
          "tgn:2659307",
          "tgn:1000001",
          "tgn:7012149",
          "tgn:1002374",
          "tgn:7007826",
          "tgn:7029392"
        ],
        "placetype": [
          "aat:300008699"
        ],
        "id": 2659307,
        "name:xx": "Shiloh Branch"
      }
    },
    {
      "geometry": {
        "type": "Point",
        "coordinates": [
          -87.75,
          36.2333
        ]
      },
      "type": "Feature",
      "properties": {
        "hierarchy": [
          "tgn:2659308",
          "tgn:1000001",
          "tgn:7012149",
          "tgn:2001879",
          "tgn:7007825",
          "tgn:7029392"
        ],
        "placetype": [
          "aat:300008746"
        ],
        "id": 2659308,
        "name:xx": "Shiloh Branch Cave"
      }
    },
    {
      "geometry": {
        "type": "Point",
        "coordinates": [
          -77.3333,
          35.3667
        ]
      },
      "type": "Feature",
      "properties": {
        "hierarchy": [
          "tgn:2659309",
          "tgn:1000001",
          "tgn:7012149",
          "tgn:2001530",
          "tgn:7007709",
          "tgn:7029392"
        ],
        "placetype": [
          "aat:300006075"
        ],
        "id": 2659309,
        "name:xx": "Shiloh Canal"
      }
    }
  ]
}
