{
  "geometry": {
    "type": "Point",
    "coordinates": [
      -46.7667,
      -1.0333
    ]
  },
  "type": "Feature",
  "properties": {
    "hierarchy": [
      "tgn:1020892",
      "tgn:7006247",
      "tgn:1000047",
      "tgn:7002456",
      "tgn:1000002",
      "tgn:7029392"
    ],
    "placetype": [
      "aat:300008347"
    ],
    "id": 1020892,
    "name:xx": "Bragança"
  }
}
