{
  "geometry": {
    "type": "Point",
    "coordinates": [
      -91.2833,
      38.8333
    ]
  },
  "type": "Feature",
  "properties": {
    "hierarchy": [
      "tgn:2423708",
      "tgn:1000001",
      "tgn:7012149",
      "tgn:1002984",
      "tgn:7007523",
      "tgn:7029392"
    ],
    "placetype": [
      "aat:300006191"
    ],
    "id": 2423708,
    "name:xx": "John Scofield Lake"
  }
}
