{
  "geometry": {
    "type": "Point",
    "coordinates": [
      31.35,
      -12.0167
    ]
  },
  "type": "Feature",
  "properties": {
    "hierarchy": [
      "tgn:1095903",
      "tgn:7001242",
      "tgn:1001461",
      "tgn:1000209",
      "tgn:7029392"
    ],
    "placetype": [
      "aat:300008347"
    ],
    "id": 1095903,
    "name:xx": "Chilonga"
  }
}
