{
  "geometry": {
    "type": "Point",
    "coordinates": [
      62.2833,
      27.35
    ]
  },
  "type": "Feature",
  "properties": {
    "hierarchy": [
      "tgn:1079304",
      "tgn:1000004",
      "tgn:7002176",
      "tgn:7000231",
      "tgn:7029392"
    ],
    "placetype": [
      "aat:300008347"
    ],
    "id": 1079304,
    "name:xx": "Sarāvān"
  }
}
