{
  "geometry": {
    "type": "Point",
    "coordinates": [
      -76.3667,
      37.15
    ]
  },
  "type": "Feature",
  "properties": {
    "hierarchy": [
      "tgn:2152428",
      "tgn:1000001",
      "tgn:7012149",
      "tgn:1003048",
      "tgn:7007919",
      "tgn:7029392"
    ],
    "placetype": [
      "aat:300008850"
    ],
    "id": 2152428,
    "name:xx": "Bay Point"
  }
}
