{
  "geometry": {
    "type": "Point",
    "coordinates": [
      -123.8667,
      45.2833
    ]
  },
  "type": "Feature",
  "properties": {
    "hierarchy": [
      "tgn:2757442",
      "tgn:1000001",
      "tgn:7012149",
      "tgn:1002943",
      "tgn:7007708",
      "tgn:7029392"
    ],
    "placetype": [
      "aat:300008706"
    ],
    "id": 2757442,
    "name:xx": "West Beaver Creek"
  }
}
