{
  "type": "FeatureCollection",
  "features": [
    {
      "geometry": {
        "type": "Point",
        "coordinates": [
          -84.6833,
          43.75
        ]
      },
      "type": "Feature",
      "properties": {
        "hierarchy": [
          "tgn:2505740",
          "tgn:1000001",
          "tgn:7012149",
          "tgn:2000967",
          "tgn:7007520",
          "tgn:7029392"
        ],
        "placetype": [
          "aat:300008699"
        ],
        "id": 2505740,
        "name:xx": "Menery Drain"
      }
    },
    {
      "geometry": {
        "type": "Point",
        "coordinates": [
          -90.2,
          35.4167
        ]
      },
      "type": "Feature",
      "properties": {
        "hierarchy": [
          "tgn:2505741",
          "tgn:1000001",
          "tgn:7016172",
          "tgn:2000122",
          "tgn:7012149",
          "tgn:7029392"
        ],
        "placetype": [
          "aat:300008347"
        ],
        "id": 2505741,
        "name:xx": "Meneshea"
      }
    },
    {
      "geometry": {
        "type": "Point",
        "coordinates": [
          -90.2,
          35.4167
        ]
      },
      "type": "Feature",
      "properties": {
        "hierarchy": [
          "tgn:2505742",
          "tgn:1000001",
          "tgn:7016172",
          "tgn:2000122",
          "tgn:7012149",
          "tgn:7029392"
        ],
        "placetype": [
          "aat:300008680"
        ],
        "id": 2505742,
        "name:xx": "Meneshea Lake"
      }
    },
    {
      "geometry": {
        "type": "Point",
        "coordinates": [
          -91.4833,
          34.6
        ]
      },
      "type": "Feature",
      "properties": {
        "hierarchy": [
          "tgn:2505743",
          "tgn:1000001",
          "tgn:7016172",
          "tgn:7012149",
          "tgn:2000163",
          "tgn:7029392"
        ],
        "placetype": [
          "aat:300006191"
        ],
        "id": 2505743,
        "name:xx": "Menett Reservoir"
      }
    },
    {
      "geometry": {
        "type": "Point",
        "coordinates": [
          -107.05,
          36.1667
        ]
      },
      "type": "Feature",
      "properties": {
        "hierarchy": [
          "tgn:2505744",
          "tgn:1000001",
          "tgn:7012149",
          "tgn:2001451",
          "tgn:7007566",
          "tgn:7029392"
        ],
        "placetype": [
          "aat:300008761"
        ],
        "id": 2505744,
        "name:xx": "Menfee Canyon"
      }
    },
    {
      "geometry": {
        "type": "Point",
        "coordinates": [
          -81.6167,
          34.75
        ]
      },
      "type": "Feature",
      "properties": {
        "hierarchy": [
          "tgn:2505745",
          "tgn:1000001",
          "tgn:7012149",
          "tgn:2001768",
          "tgn:7007712",
          "tgn:7029392"
        ],
        "placetype": [
          "aat:300008706"
        ],
        "id": 2505745,
        "name:xx": "Meng Creek"
      }
    },
    {
      "geometry": {
        "type": "Point",
        "coordinates": [
          -103.5,
          42.95
        ]
      },
      "type": "Feature",
      "properties": {
        "hierarchy": [
          "tgn:2505746",
          "tgn:1000001",
          "tgn:7012149",
          "tgn:2001398",
          "tgn:7007525",
          "tgn:7029392"
        ],
        "placetype": [
          "aat:300006191"
        ],
        "id": 2505746,
        "name:xx": "Meng Reservoir"
      }
    },
    {
      "geometry": {
        "type": "Point",
        "coordinates": [
          -88.5333,
          46.7
        ]
      },
      "type": "Feature",
      "properties": {
        "hierarchy": [
          "tgn:2505747",
          "tgn:2000947",
          "tgn:1000001",
          "tgn:7012149",
          "tgn:7007520",
          "tgn:7029392"
        ],
        "placetype": [
          "aat:300008706"
        ],
        "id": 2505747,
        "name:xx": "Menge Creek"
      }
    },
    {
      "geometry": {
        "type": "Point",
        "coordinates": [
          -85.8667,
          30.5833
        ]
      },
      "type": "Feature",
      "properties": {
        "hierarchy": [
          "tgn:2505748",
          "tgn:1000001",
          "tgn:7012149",
          "tgn:2000291",
          "tgn:7007240",
          "tgn:7029392"
        ],
        "placetype": [
          "aat:300008680"
        ],
        "id": 2505748,
        "name:xx": "Menge Pond"
      }
    },
    {
      "geometry": {
        "type": "Point",
        "coordinates": [
          -91.1833,
          30.5
        ]
      },
      "type": "Feature",
      "properties": {
        "hierarchy": [
          "tgn:2505749",
          "tgn:1000001",
          "tgn:2000870",
          "tgn:7012149",
          "tgn:7007256",
          "tgn:7029392"
        ],
        "placetype": [
          "aat:300008347"
        ],
        "id": 2505749,
        "name:xx": "Mengel Landing"
      }
    }
  ]
}
