{
  "geometry": {
    "type": "Point",
    "coordinates": [
      11.4167,
      55.6667
    ]
  },
  "type": "Feature",
  "properties": {
    "hierarchy": [
      "tgn:1027946",
      "tgn:7594008",
      "tgn:1000003",
      "tgn:1000066",
      "tgn:7029392"
    ],
    "placetype": [
      "aat:300008347"
    ],
    "id": 1027946,
    "name:xx": "Jyderup"
  }
}
