{
  "geometry": {
    "type": "Point",
    "coordinates": [
      -116.0333,
      48.0833
    ]
  },
  "type": "Feature",
  "properties": {
    "hierarchy": [
      "tgn:2213529",
      "tgn:1000001",
      "tgn:7012149",
      "tgn:7029392"
    ],
    "placetype": [
      "aat:300008761"
    ],
    "id": 2213529,
    "name:xx": "Cabinet Gorge"
  }
}
