{
  "geometry": {
    "type": "Point",
    "coordinates": [
      35.5833,
      33.7333
    ]
  },
  "type": "Feature",
  "properties": {
    "hierarchy": [
      "tgn:1082646",
      "tgn:1001317",
      "tgn:1000004",
      "tgn:1000126",
      "tgn:7029392"
    ],
    "placetype": [
      "aat:300008347"
    ],
    "id": 1082646,
    "name:xx": "Rishmayyā"
  }
}
