{
  "geometry": {
    "type": "Point",
    "coordinates": [
      -89.7833,
      32.35
    ]
  },
  "type": "Feature",
  "properties": {
    "hierarchy": [
      "tgn:2516594",
      "tgn:1000001",
      "tgn:7012149",
      "tgn:2001146",
      "tgn:7007522",
      "tgn:7029392"
    ],
    "placetype": [
      "aat:300008697"
    ],
    "id": 2516594,
    "name:xx": "Mineral Spring"
  }
}
