{
  "geometry": {
    "type": "Point",
    "coordinates": [
      -122.3667,
      37.4833
    ]
  },
  "type": "Feature",
  "properties": {
    "hierarchy": [
      "tgn:2126358",
      "tgn:1000001",
      "tgn:7012149",
      "tgn:7007157",
      "tgn:1002864",
      "tgn:7029392"
    ],
    "placetype": [
      "aat:300008761"
    ],
    "id": 2126358,
    "name:xx": "Adobe Gulch"
  }
}
