{
  "geometry": {
    "type": "Point",
    "coordinates": [
      -89.1333,
      37.1667
    ]
  },
  "type": "Feature",
  "properties": {
    "hierarchy": [
      "tgn:2387211",
      "tgn:1000001",
      "tgn:7012149",
      "tgn:2000524",
      "tgn:7007251",
      "tgn:7029392"
    ],
    "placetype": [
      "aat:300008699"
    ],
    "id": 2387211,
    "name:xx": "Hess Bayou"
  }
}
