{
  "type": "FeatureCollection",
  "features": [
    {
      "geometry": {
        "type": "Point",
        "coordinates": [
          -111.6,
          43
        ]
      },
      "type": "Feature",
      "properties": {
        "hierarchy": [
          "tgn:2449180",
          "tgn:1000001",
          "tgn:2000466",
          "tgn:7012149",
          "tgn:7007250",
          "tgn:7029392"
        ],
        "placetype": [
          "aat:300008798"
        ],
        "id": 2449180,
        "name:xx": "Limerock Mountain"
      }
    },
    {
      "geometry": {
        "type": "Point",
        "coordinates": [
          -118.35,
          34.3167
        ]
      },
      "type": "Feature",
      "properties": {
        "hierarchy": [
          "tgn:2449181",
          "tgn:1000001",
          "tgn:7012149",
          "tgn:7007157",
          "tgn:1002608",
          "tgn:7029392"
        ],
        "placetype": [
          "aat:300008798"
        ],
        "id": 2449181,
        "name:xx": "Limerock Peak"
      }
    },
    {
      "geometry": {
        "type": "Point",
        "coordinates": [
          -115.4667,
          38.9667
        ]
      },
      "type": "Feature",
      "properties": {
        "hierarchy": [
          "tgn:2449182",
          "tgn:1000001",
          "tgn:7012149",
          "tgn:2001420",
          "tgn:7007526",
          "tgn:7029392"
        ],
        "placetype": [
          "aat:300008697"
        ],
        "id": 2449182,
        "name:xx": "Limerock Spring"
      }
    },
    {
      "geometry": {
        "type": "Point",
        "coordinates": [
          -112.5,
          37.6667
        ]
      },
      "type": "Feature",
      "properties": {
        "hierarchy": [
          "tgn:2449183",
          "tgn:1000001",
          "tgn:2002109",
          "tgn:7012149",
          "tgn:7007827",
          "tgn:7029392"
        ],
        "placetype": [
          "aat:300008697"
        ],
        "id": 2449183,
        "name:xx": "Limerock Spring"
      }
    },
    {
      "geometry": {
        "type": "Point",
        "coordinates": [
          -91.1,
          43.0833
        ]
      },
      "type": "Feature",
      "properties": {
        "hierarchy": [
          "tgn:2449184",
          "tgn:1000001",
          "tgn:2002316",
          "tgn:7012149",
          "tgn:7007922",
          "tgn:7029392"
        ],
        "placetype": [
          "aat:300008761"
        ],
        "id": 2449184,
        "name:xx": "Limery Coulee"
      }
    },
    {
      "geometry": {
        "type": "Point",
        "coordinates": [
          -91.1,
          43.0833
        ]
      },
      "type": "Feature",
      "properties": {
        "hierarchy": [
          "tgn:2449185",
          "tgn:1000001",
          "tgn:2002316",
          "tgn:7012149",
          "tgn:7007922",
          "tgn:7029392"
        ],
        "placetype": [
          "aat:300266640"
        ],
        "id": 2449185,
        "name:xx": "Limery Ridge"
      }
    },
    {
      "geometry": {
        "type": "Point",
        "coordinates": [
          -86.2333,
          31.6833
        ]
      },
      "type": "Feature",
      "properties": {
        "hierarchy": [
          "tgn:2449186",
          "tgn:7002659",
          "tgn:1000001",
          "tgn:2000020",
          "tgn:7012149",
          "tgn:7029392"
        ],
        "placetype": [
          "aat:300008680"
        ],
        "id": 2449186,
        "name:xx": "Limesink Pond"
      }
    },
    {
      "geometry": {
        "type": "Point",
        "coordinates": [
          -150.7667,
          68.1
        ]
      },
      "type": "Feature",
      "properties": {
        "hierarchy": [
          "tgn:2449187",
          "tgn:7006450",
          "tgn:1000001",
          "tgn:7012149",
          "tgn:2124005",
          "tgn:7029392"
        ],
        "placetype": [
          "aat:300008798"
        ],
        "id": 2449187,
        "name:xx": "Limestack Mountain"
      }
    },
    {
      "geometry": {
        "type": "Point",
        "coordinates": [
          -82.5167,
          38.95
        ]
      },
      "type": "Feature",
      "properties": {
        "hierarchy": [
          "tgn:2449188",
          "tgn:1000001",
          "tgn:7012149",
          "tgn:2001614",
          "tgn:7007706",
          "tgn:7029392"
        ],
        "placetype": [
          "aat:300008347"
        ],
        "id": 2449188,
        "name:xx": "Limestone"
      }
    }
  ]
}
