{
  "geometry": {
    "type": "Point",
    "coordinates": [
      14.4167,
      48.0667
    ]
  },
  "type": "Feature",
  "properties": {
    "hierarchy": [
      "tgn:7003303",
      "tgn:7003026",
      "tgn:1000003",
      "tgn:1000062",
      "tgn:7029392"
    ],
    "placetype": [
      "aat:300008347"
    ],
    "id": 7003303,
    "name:xx": "Steyr"
  }
}
