{
  "geometry": {
    "type": "Point",
    "coordinates": [
      -82.9167,
      35.65
    ]
  },
  "type": "Feature",
  "properties": {
    "hierarchy": [
      "tgn:2640103",
      "tgn:1000001",
      "tgn:7012149",
      "tgn:2001503",
      "tgn:7007709",
      "tgn:7029392"
    ],
    "placetype": [
      "aat:300266640"
    ],
    "id": 2640103,
    "name:xx": "Sams Land"
  }
}
