{
  "geometry": {
    "type": "Point",
    "coordinates": [
      -99.25,
      41.6333
    ]
  },
  "type": "Feature",
  "properties": {
    "hierarchy": [
      "tgn:2458619",
      "tgn:1000001",
      "tgn:2001336",
      "tgn:7012149",
      "tgn:7007525",
      "tgn:7029392"
    ],
    "placetype": [
      "aat:300008761"
    ],
    "id": 2458619,
    "name:xx": "Little Oak Canyon"
  }
}
