{
  "geometry": {
    "type": "Point",
    "coordinates": [
      -100.6025,
      20.625
    ]
  },
  "type": "Feature",
  "properties": {
    "hierarchy": [
      "tgn:7417644",
      "tgn:7005584",
      "tgn:1000001",
      "tgn:7005560",
      "tgn:7029392"
    ],
    "placetype": [
      "aat:300008347"
    ],
    "id": 7417644,
    "name:xx": "Ojo Zarco"
  }
}
