{
  "type": "FeatureCollection",
  "features": [
    {
      "geometry": {
        "type": "Point",
        "coordinates": [
          -82.25,
          35.6667
        ]
      },
      "type": "Feature",
      "properties": {
        "hierarchy": [
          "tgn:2595200",
          "tgn:1000001",
          "tgn:7012149",
          "tgn:2001514",
          "tgn:7007709",
          "tgn:7029392"
        ],
        "placetype": [
          "aat:300008761"
        ],
        "id": 2595200,
        "name:xx": "Pot Cove"
      }
    },
    {
      "geometry": {
        "type": "Point",
        "coordinates": [
          -163.8,
          65.9167
        ]
      },
      "type": "Feature",
      "properties": {
        "hierarchy": [
          "tgn:2595201",
          "tgn:7006450",
          "tgn:1000001",
          "tgn:7012149",
          "tgn:2124014",
          "tgn:7029392"
        ],
        "placetype": [
          "aat:300008706"
        ],
        "id": 2595201,
        "name:xx": "Pot Creek"
      }
    },
    {
      "geometry": {
        "type": "Point",
        "coordinates": [
          -108.9333,
          40.6167
        ]
      },
      "type": "Feature",
      "properties": {
        "hierarchy": [
          "tgn:2595202",
          "tgn:1000001",
          "tgn:7012149",
          "tgn:7029392"
        ],
        "placetype": [
          "aat:300008706"
        ],
        "id": 2595202,
        "name:xx": "Pot Creek"
      }
    },
    {
      "geometry": {
        "type": "Point",
        "coordinates": [
          -116.7167,
          45.8667
        ]
      },
      "type": "Feature",
      "properties": {
        "hierarchy": [
          "tgn:2595203",
          "tgn:1000001",
          "tgn:7012149",
          "tgn:2000476",
          "tgn:7007250",
          "tgn:7029392"
        ],
        "placetype": [
          "aat:300008706"
        ],
        "id": 2595203,
        "name:xx": "Pot Creek"
      }
    },
    {
      "geometry": {
        "type": "Point",
        "coordinates": [
          -113.9833,
          43.7333
        ]
      },
      "type": "Feature",
      "properties": {
        "hierarchy": [
          "tgn:2595204",
          "tgn:1000001",
          "tgn:7012149",
          "tgn:7007250",
          "tgn:7029392"
        ],
        "placetype": [
          "aat:300008706"
        ],
        "id": 2595204,
        "name:xx": "Pot Creek"
      }
    },
    {
      "geometry": {
        "type": "Point",
        "coordinates": [
          -115.4167,
          46.7333
        ]
      },
      "type": "Feature",
      "properties": {
        "hierarchy": [
          "tgn:2595205",
          "tgn:1000001",
          "tgn:2000469",
          "tgn:7012149",
          "tgn:7007250",
          "tgn:7029392"
        ],
        "placetype": [
          "aat:300008706"
        ],
        "id": 2595205,
        "name:xx": "Pot Creek"
      }
    },
    {
      "geometry": {
        "type": "Point",
        "coordinates": [
          -121.9,
          45.0333
        ]
      },
      "type": "Feature",
      "properties": {
        "hierarchy": [
          "tgn:2595206",
          "tgn:1000001",
          "tgn:1002270",
          "tgn:7012149",
          "tgn:7007708",
          "tgn:7029392"
        ],
        "placetype": [
          "aat:300008706"
        ],
        "id": 2595206,
        "name:xx": "Pot Creek"
      }
    },
    {
      "geometry": {
        "type": "Point",
        "coordinates": [
          -117.5667,
          45.2333
        ]
      },
      "type": "Feature",
      "properties": {
        "hierarchy": [
          "tgn:2595207",
          "tgn:1000001",
          "tgn:7012149",
          "tgn:2001721",
          "tgn:7007708",
          "tgn:7029392"
        ],
        "placetype": [
          "aat:300008706"
        ],
        "id": 2595207,
        "name:xx": "Pot Creek"
      }
    },
    {
      "geometry": {
        "type": "Point",
        "coordinates": [
          -118.1,
          45.5
        ]
      },
      "type": "Feature",
      "properties": {
        "hierarchy": [
          "tgn:2595208",
          "tgn:1000001",
          "tgn:7012149",
          "tgn:2001720",
          "tgn:7007708",
          "tgn:7029392"
        ],
        "placetype": [
          "aat:300008706"
        ],
        "id": 2595208,
        "name:xx": "Pot Creek"
      }
    },
    {
      "geometry": {
        "type": "Point",
        "coordinates": [
          -100.5833,
          31.45
        ]
      },
      "type": "Feature",
      "properties": {
        "hierarchy": [
          "tgn:2595209",
          "tgn:1000001",
          "tgn:7012149",
          "tgn:2002085",
          "tgn:7007826",
          "tgn:7029392"
        ],
        "placetype": [
          "aat:300008706"
        ],
        "id": 2595209,
        "name:xx": "Pot Creek"
      }
    }
  ]
}
