{
  "geometry": {
    "type": "Point",
    "coordinates": [
      -79.35,
      36.7167
    ]
  },
  "type": "Feature",
  "properties": {
    "hierarchy": [
      "tgn:2111169",
      "tgn:1000001",
      "tgn:7012149",
      "tgn:2002172",
      "tgn:7007919",
      "tgn:7029392"
    ],
    "placetype": [
      "aat:300008347",
      "aat:300387210"
    ],
    "id": 2111169,
    "name:xx": "Chestnut Level"
  }
}
