{
  "geometry": {
    "type": "Point",
    "coordinates": [
      -86.3167,
      39.85
    ]
  },
  "type": "Feature",
  "properties": {
    "hierarchy": [
      "tgn:2490816",
      "tgn:1000001",
      "tgn:7012149",
      "tgn:1002465",
      "tgn:7007252",
      "tgn:7029392"
    ],
    "placetype": [
      "aat:300006191"
    ],
    "id": 2490816,
    "name:xx": "Manor Lake"
  }
}
