{
  "geometry": {
    "type": "Point",
    "coordinates": [
      -115.7167,
      45.5167
    ]
  },
  "type": "Feature",
  "properties": {
    "hierarchy": [
      "tgn:2401679",
      "tgn:1000001",
      "tgn:7012149",
      "tgn:2000476",
      "tgn:7007250",
      "tgn:7029392"
    ],
    "placetype": [
      "aat:300008680"
    ],
    "id": 2401679,
    "name:xx": "Horseshoe Lake"
  }
}
