{
  "geometry": {
    "type": "Point",
    "coordinates": [
      -85.5667,
      40.3333
    ]
  },
  "type": "Feature",
  "properties": {
    "hierarchy": [
      "tgn:2616955",
      "tgn:1000001",
      "tgn:7012149",
      "tgn:7007252",
      "tgn:7029392"
    ],
    "placetype": [
      "aat:300006075"
    ],
    "id": 2616955,
    "name:xx": "Richard Ditch"
  }
}
