{
  "geometry": {
    "type": "Point",
    "coordinates": [
      121.3484,
      25.0486
    ]
  },
  "type": "Feature",
  "properties": {
    "hierarchy": [
      "tgn:7491400",
      "tgn:1000004",
      "tgn:7001013",
      "tgn:1000141",
      "tgn:7029392"
    ],
    "placetype": [
      "aat:300387173"
    ],
    "id": 7491400,
    "name:xx": "Dagang Cun"
  }
}
