{
  "type": "FeatureCollection",
  "features": [
    {
      "geometry": {
        "type": "Point",
        "coordinates": [
          5.75,
          43.9333
        ]
      },
      "type": "Feature",
      "properties": {
        "hierarchy": [
          "tgn:4006851",
          "tgn:1000003",
          "tgn:1000070",
          "tgn:7002895",
          "tgn:7029392"
        ],
        "placetype": [
          "aat:300008347"
        ],
        "id": 4006851,
        "name:xx": "Mane"
      }
    },
    {
      "geometry": {
        "type": "Point",
        "coordinates": [
          -0.45,
          39.483333
        ]
      },
      "type": "Feature",
      "properties": {
        "hierarchy": [
          "tgn:4006859",
          "tgn:7001165",
          "tgn:1000003",
          "tgn:7002793",
          "tgn:1000095",
          "tgn:7029392"
        ],
        "placetype": [
          "aat:300008347"
        ],
        "id": 4006859,
        "name:xx": "Manises"
      }
    }
  ]
}
