{
  "geometry": {
    "type": "Point",
    "coordinates": [
      -119.9333,
      37.6833
    ]
  },
  "type": "Feature",
  "properties": {
    "hierarchy": [
      "tgn:2546338",
      "tgn:1000001",
      "tgn:7012149",
      "tgn:7007157",
      "tgn:7014004",
      "tgn:7029392"
    ],
    "placetype": [
      "aat:300008761"
    ],
    "id": 2546338,
    "name:xx": "North Fork Halls Gulch"
  }
}
