{
  "type": "FeatureCollection",
  "features": [
    {
      "geometry": {
        "type": "Point",
        "coordinates": [
          -90.9833,
          30.1167
        ]
      },
      "type": "Feature",
      "properties": {
        "hierarchy": [
          "tgn:2042620",
          "tgn:2000856",
          "tgn:1000001",
          "tgn:7012149",
          "tgn:7007256",
          "tgn:7029392"
        ],
        "placetype": [
          "aat:300008347"
        ],
        "id": 2042620,
        "name:xx": "Darrow"
      }
    },
    {
      "geometry": {
        "type": "Point",
        "coordinates": [
          -91.8,
          30.0333
        ]
      },
      "type": "Feature",
      "properties": {
        "hierarchy": [
          "tgn:2042621",
          "tgn:1000001",
          "tgn:7012149",
          "tgn:2000876",
          "tgn:7007256",
          "tgn:7029392"
        ],
        "placetype": [
          "aat:300008347",
          "aat:300387210"
        ],
        "id": 2042621,
        "name:xx": "Daspit"
      }
    },
    {
      "geometry": {
        "type": "Point",
        "coordinates": [
          -89.8333,
          29.6
        ]
      },
      "type": "Feature",
      "properties": {
        "hierarchy": [
          "tgn:2042622",
          "tgn:1000001",
          "tgn:7012149",
          "tgn:2000891",
          "tgn:7007256",
          "tgn:7029392"
        ],
        "placetype": [
          "aat:300008347"
        ],
        "id": 2042622,
        "name:xx": "Davant"
      }
    },
    {
      "geometry": {
        "type": "Point",
        "coordinates": [
          -89.8833,
          30.5667
        ]
      },
      "type": "Feature",
      "properties": {
        "hierarchy": [
          "tgn:2042623",
          "tgn:1000001",
          "tgn:7012149",
          "tgn:2000905",
          "tgn:7007256",
          "tgn:7029392"
        ],
        "placetype": [
          "aat:300387016"
        ],
        "id": 2042623,
        "name:xx": "Dave"
      }
    },
    {
      "geometry": {
        "type": "Point",
        "coordinates": [
          -91.8667,
          29.95
        ]
      },
      "type": "Feature",
      "properties": {
        "hierarchy": [
          "tgn:2042624",
          "tgn:1000001",
          "tgn:7012149",
          "tgn:2000876",
          "tgn:7007256",
          "tgn:7029392"
        ],
        "placetype": [
          "aat:300387016"
        ],
        "id": 2042624,
        "name:xx": "Davids"
      }
    },
    {
      "geometry": {
        "type": "Point",
        "coordinates": [
          -90.5,
          30.85
        ]
      },
      "type": "Feature",
      "properties": {
        "hierarchy": [
          "tgn:2042625",
          "tgn:1000001",
          "tgn:7012149",
          "tgn:2000906",
          "tgn:7007256",
          "tgn:7029392"
        ],
        "placetype": [
          "aat:300387016"
        ],
        "id": 2042625,
        "name:xx": "Day"
      }
    },
    {
      "geometry": {
        "type": "Point",
        "coordinates": [
          -92.15,
          32.9
        ]
      },
      "type": "Feature",
      "properties": {
        "hierarchy": [
          "tgn:2042626",
          "tgn:1000001",
          "tgn:7012149",
          "tgn:2000909",
          "tgn:7007256",
          "tgn:7029392"
        ],
        "placetype": [
          "aat:300008347",
          "aat:300387210"
        ],
        "id": 2042626,
        "name:xx": "Dean"
      }
    },
    {
      "geometry": {
        "type": "Point",
        "coordinates": [
          -93.7,
          32.3167
        ]
      },
      "type": "Feature",
      "properties": {
        "hierarchy": [
          "tgn:2042628",
          "tgn:1000001",
          "tgn:2000862",
          "tgn:7012149",
          "tgn:7007256",
          "tgn:7029392"
        ],
        "placetype": [
          "aat:300008347",
          "aat:300387210"
        ],
        "id": 2042628,
        "name:xx": "De Broeck Landing"
      }
    },
    {
      "geometry": {
        "type": "Point",
        "coordinates": [
          -91.0667,
          30.6333
        ]
      },
      "type": "Feature",
      "properties": {
        "hierarchy": [
          "tgn:2042629",
          "tgn:1000001",
          "tgn:2000870",
          "tgn:7012149",
          "tgn:7007256",
          "tgn:7029392"
        ],
        "placetype": [
          "aat:300008347",
          "aat:300387210"
        ],
        "id": 2042629,
        "name:xx": "Deerford"
      }
    }
  ]
}
