{
  "geometry": {
    "type": "Point",
    "coordinates": [
      -108.9833,
      32.1667
    ]
  },
  "type": "Feature",
  "properties": {
    "hierarchy": [
      "tgn:2501196",
      "tgn:1000001",
      "tgn:7012149",
      "tgn:2001440",
      "tgn:7007566",
      "tgn:7029392"
    ],
    "placetype": [
      "aat:300008798"
    ],
    "id": 2501196,
    "name:xx": "McGhee Peak"
  }
}
