{
  "geometry": {
    "type": "Point",
    "coordinates": [
      22.7833,
      -8.25
    ]
  },
  "type": "Feature",
  "properties": {
    "hierarchy": [
      "tgn:1089099",
      "tgn:7001242",
      "tgn:7016706",
      "tgn:1000159",
      "tgn:7029392"
    ],
    "placetype": [
      "aat:300008347"
    ],
    "id": 1089099,
    "name:xx": "Katapakishi"
  }
}
