{
  "type": "FeatureCollection",
  "features": [
    {
      "geometry": {
        "type": "Point",
        "coordinates": [
          -111.9333,
          41.3667
        ]
      },
      "type": "Feature",
      "properties": {
        "hierarchy": [
          "tgn:2248150",
          "tgn:1000001",
          "tgn:7012149",
          "tgn:2002129",
          "tgn:7007827",
          "tgn:7029392"
        ],
        "placetype": [
          "aat:300008761"
        ],
        "id": 2248150,
        "name:xx": "Cold Canyon"
      }
    },
    {
      "geometry": {
        "type": "Point",
        "coordinates": [
          -122.6333,
          45.6667
        ]
      },
      "type": "Feature",
      "properties": {
        "hierarchy": [
          "tgn:2248151",
          "tgn:1000001",
          "tgn:1002275",
          "tgn:7012149",
          "tgn:7007920",
          "tgn:7029392"
        ],
        "placetype": [
          "aat:300008761"
        ],
        "id": 2248151,
        "name:xx": "Cold Canyon"
      }
    },
    {
      "geometry": {
        "type": "Point",
        "coordinates": [
          -92.1167,
          36.6667
        ]
      },
      "type": "Feature",
      "properties": {
        "hierarchy": [
          "tgn:2248152",
          "tgn:1000001",
          "tgn:7012149",
          "tgn:2001226",
          "tgn:7007523",
          "tgn:7029392"
        ],
        "placetype": [
          "aat:300008746"
        ],
        "id": 2248152,
        "name:xx": "Cold Cave"
      }
    },
    {
      "geometry": {
        "type": "Point",
        "coordinates": [
          -80.65,
          37.1167
        ]
      },
      "type": "Feature",
      "properties": {
        "hierarchy": [
          "tgn:2248153",
          "tgn:1000001",
          "tgn:7012149",
          "tgn:2002183",
          "tgn:7007919",
          "tgn:7029392"
        ],
        "placetype": [
          "aat:300008746"
        ],
        "id": 2248153,
        "name:xx": "Cold Cave"
      }
    },
    {
      "geometry": {
        "type": "Point",
        "coordinates": [
          -83.4667,
          37.9333
        ]
      },
      "type": "Feature",
      "properties": {
        "hierarchy": [
          "tgn:2248154",
          "tgn:1000001",
          "tgn:7012149",
          "tgn:2000826",
          "tgn:7007255",
          "tgn:7029392"
        ],
        "placetype": [
          "aat:300008706"
        ],
        "id": 2248154,
        "name:xx": "Cold Cave Creek"
      }
    },
    {
      "geometry": {
        "type": "Point",
        "coordinates": [
          -88.1167,
          30.9667
        ]
      },
      "type": "Feature",
      "properties": {
        "hierarchy": [
          "tgn:2248155",
          "tgn:7002659",
          "tgn:1000001",
          "tgn:7012149",
          "tgn:2000048",
          "tgn:7029392"
        ],
        "placetype": [
          "aat:300008706"
        ],
        "id": 2248155,
        "name:xx": "Cold Creek"
      }
    },
    {
      "geometry": {
        "type": "Point",
        "coordinates": [
          -164.65,
          64.9167
        ]
      },
      "type": "Feature",
      "properties": {
        "hierarchy": [
          "tgn:2248156",
          "tgn:7006450",
          "tgn:1000001",
          "tgn:7012149",
          "tgn:2000079",
          "tgn:7029392"
        ],
        "placetype": [
          "aat:300008706"
        ],
        "id": 2248156,
        "name:xx": "Cold Creek"
      }
    },
    {
      "geometry": {
        "type": "Point",
        "coordinates": [
          -150.6833,
          65.0167
        ]
      },
      "type": "Feature",
      "properties": {
        "hierarchy": [
          "tgn:2248157",
          "tgn:7006450",
          "tgn:1000001",
          "tgn:7012149",
          "tgn:2000089",
          "tgn:7029392"
        ],
        "placetype": [
          "aat:300008706"
        ],
        "id": 2248157,
        "name:xx": "Cold Creek"
      }
    },
    {
      "geometry": {
        "type": "Point",
        "coordinates": [
          -109.1,
          33.05
        ]
      },
      "type": "Feature",
      "properties": {
        "hierarchy": [
          "tgn:2248158",
          "tgn:1000001",
          "tgn:7006451",
          "tgn:2000095",
          "tgn:7012149",
          "tgn:7029392"
        ],
        "placetype": [
          "aat:300008706"
        ],
        "id": 2248158,
        "name:xx": "Cold Creek"
      }
    },
    {
      "geometry": {
        "type": "Point",
        "coordinates": [
          -119.0667,
          37.5333
        ]
      },
      "type": "Feature",
      "properties": {
        "hierarchy": [
          "tgn:2248159",
          "tgn:1000001",
          "tgn:7012149",
          "tgn:7007157",
          "tgn:1002621",
          "tgn:7029392"
        ],
        "placetype": [
          "aat:300008706"
        ],
        "id": 2248159,
        "name:xx": "Cold Creek"
      }
    }
  ]
}
