{
  "geometry": {
    "type": "Point",
    "coordinates": [
      132.9333,
      34.0167
    ]
  },
  "type": "Feature",
  "properties": {
    "hierarchy": [
      "tgn:1081492",
      "tgn:7004473",
      "tgn:1000004",
      "tgn:7000903",
      "tgn:1000120",
      "tgn:7029392"
    ],
    "placetype": [
      "aat:300008347"
    ],
    "id": 1081492,
    "name:xx": "Tamagawa"
  }
}
