{
  "type": "FeatureCollection",
  "features": [
    {
      "geometry": {
        "type": "Point",
        "coordinates": [
          9.483333,
          40.466667
        ]
      },
      "type": "Feature",
      "properties": {
        "hierarchy": [
          "tgn:1045152",
          "tgn:1001724",
          "tgn:1000003",
          "tgn:7003121",
          "tgn:1000080",
          "tgn:7029392"
        ],
        "placetype": [
          "aat:300008347"
        ],
        "id": 1045152,
        "name:xx": "Lula"
      }
    },
    {
      "geometry": {
        "type": "Point",
        "coordinates": [
          8.9,
          39.648889
        ]
      },
      "type": "Feature",
      "properties": {
        "hierarchy": [
          "tgn:1045153",
          "tgn:1001641",
          "tgn:1000003",
          "tgn:7003121",
          "tgn:1000080",
          "tgn:7029392"
        ],
        "placetype": [
          "aat:300008347"
        ],
        "id": 1045153,
        "name:xx": "Lunamatrona"
      }
    },
    {
      "geometry": {
        "type": "Point",
        "coordinates": [
          12.433333,
          43.733333
        ]
      },
      "type": "Feature",
      "properties": {
        "hierarchy": [
          "tgn:1045154",
          "tgn:1003483",
          "tgn:1000003",
          "tgn:7003240",
          "tgn:1000080",
          "tgn:7029392"
        ],
        "placetype": [
          "aat:300008347"
        ],
        "id": 1045154,
        "name:xx": "Lunano"
      }
    },
    {
      "geometry": {
        "type": "Point",
        "coordinates": [
          9.066667,
          45.033333
        ]
      },
      "type": "Feature",
      "properties": {
        "hierarchy": [
          "tgn:1045155",
          "tgn:1000003",
          "tgn:7003151",
          "tgn:7003237",
          "tgn:1000080",
          "tgn:7029392"
        ],
        "placetype": [
          "aat:300008347"
        ],
        "id": 1045155,
        "name:xx": "Lungavilla"
      }
    },
    {
      "geometry": {
        "type": "Point",
        "coordinates": [
          16.116667,
          39.733333
        ]
      },
      "type": "Feature",
      "properties": {
        "hierarchy": [
          "tgn:1045156",
          "tgn:1003450",
          "tgn:7007850",
          "tgn:1000003",
          "tgn:1000080",
          "tgn:7029392"
        ],
        "placetype": [
          "aat:300008347"
        ],
        "id": 1045156,
        "name:xx": "Lungro"
      }
    },
    {
      "geometry": {
        "type": "Point",
        "coordinates": [
          9.2,
          41.05
        ]
      },
      "type": "Feature",
      "properties": {
        "hierarchy": [
          "tgn:1045157",
          "tgn:7015163",
          "tgn:1000003",
          "tgn:7003121",
          "tgn:1000080",
          "tgn:7029392"
        ],
        "placetype": [
          "aat:300008347"
        ],
        "id": 1045157,
        "name:xx": "Luogosanto"
      }
    },
    {
      "geometry": {
        "type": "Point",
        "coordinates": [
          7.7,
          44.3
        ]
      },
      "type": "Feature",
      "properties": {
        "hierarchy": [
          "tgn:1045158",
          "tgn:7005126",
          "tgn:1000003",
          "tgn:7003120",
          "tgn:1000080",
          "tgn:7029392"
        ],
        "placetype": [
          "aat:300008347"
        ],
        "id": 1045158,
        "name:xx": "Lurisia"
      }
    },
    {
      "geometry": {
        "type": "Point",
        "coordinates": [
          7.25,
          44.8
        ]
      },
      "type": "Feature",
      "properties": {
        "hierarchy": [
          "tgn:1045159",
          "tgn:7003154",
          "tgn:1000003",
          "tgn:7003120",
          "tgn:1000080",
          "tgn:7029392"
        ],
        "placetype": [
          "aat:300008347"
        ],
        "id": 1045159,
        "name:xx": "Luserna San Giovanni"
      }
    }
  ]
}
