{
  "geometry": {
    "type": "Point",
    "coordinates": [
      -106.3833,
      36.0167
    ]
  },
  "type": "Feature",
  "properties": {
    "hierarchy": [
      "tgn:2239828",
      "tgn:1000001",
      "tgn:7012149",
      "tgn:2001449",
      "tgn:7007566",
      "tgn:7029392"
    ],
    "placetype": [
      "aat:300008905"
    ],
    "id": 2239828,
    "name:xx": "Cienega del Oso"
  }
}
