{
  "geometry": {
    "type": "Point",
    "coordinates": [
      24.8333,
      64.2833
    ]
  },
  "type": "Feature",
  "properties": {
    "hierarchy": [
      "tgn:1031484",
      "tgn:1001475",
      "tgn:1000003",
      "tgn:1000069",
      "tgn:7029392"
    ],
    "placetype": [
      "aat:300008347"
    ],
    "id": 1031484,
    "name:xx": "Oulainen"
  }
}
