{
  "geometry": {
    "type": "Point",
    "coordinates": [
      21.4667,
      48.5833
    ]
  },
  "type": "Feature",
  "properties": {
    "hierarchy": [
      "tgn:1105787",
      "tgn:1000003",
      "tgn:7029392"
    ],
    "placetype": [
      "aat:300008795"
    ],
    "name:hu": "Nagy-Milic",
    "id": 1105787
  }
}
