{
  "geometry": {
    "type": "Point",
    "coordinates": [
      -84.95,
      35.4167
    ]
  },
  "type": "Feature",
  "properties": {
    "hierarchy": [
      "tgn:2233925",
      "tgn:1000001",
      "tgn:7012149",
      "tgn:2001897",
      "tgn:7007825",
      "tgn:7029392"
    ],
    "placetype": [
      "aat:300008699"
    ],
    "id": 2233925,
    "name:xx": "Chatton Spring Branch"
  }
}
