{
  "geometry": {
    "type": "Point",
    "coordinates": [
      -93.4167,
      34.4833
    ]
  },
  "type": "Feature",
  "properties": {
    "hierarchy": [
      "tgn:2507474",
      "tgn:1000001",
      "tgn:7016172",
      "tgn:7012149",
      "tgn:7029392"
    ],
    "placetype": [
      "aat:300008706"
    ],
    "id": 2507474,
    "name:xx": "Meyers Creek"
  }
}
