{
  "geometry": {
    "type": "Point",
    "coordinates": [
      11.95,
      49.116667
    ]
  },
  "type": "Feature",
  "properties": {
    "hierarchy": [
      "tgn:7186663",
      "tgn:7003669",
      "tgn:1000003",
      "tgn:7000084",
      "tgn:7029392"
    ],
    "placetype": [
      "aat:300000206"
    ],
    "id": 7186663,
    "name:xx": "Grabenhäuser"
  }
}
