{
  "geometry": {
    "type": "Point",
    "coordinates": [
      -112.35,
      45.8167
    ]
  },
  "type": "Feature",
  "properties": {
    "hierarchy": [
      "tgn:2628626",
      "tgn:1000001",
      "tgn:7012149",
      "tgn:7007524",
      "tgn:7029392"
    ],
    "placetype": [
      "aat:300008706"
    ],
    "id": 2628626,
    "name:xx": "Root Creek"
  }
}
