{
  "geometry": {
    "type": "Point",
    "coordinates": [
      -103.2167,
      40.5667
    ]
  },
  "type": "Feature",
  "properties": {
    "hierarchy": [
      "tgn:2151538",
      "tgn:1000001",
      "tgn:7012149",
      "tgn:2000229",
      "tgn:7007158",
      "tgn:7029392"
    ],
    "placetype": [
      "aat:300006075"
    ],
    "id": 2151538,
    "name:xx": "Batten Ditch"
  }
}
