{
  "geometry": {
    "type": "Point",
    "coordinates": [
      -109.05,
      40.5333
    ]
  },
  "type": "Feature",
  "properties": {
    "hierarchy": [
      "tgn:2426539",
      "tgn:1000001",
      "tgn:7012149",
      "tgn:7029392"
    ],
    "placetype": [
      "aat:300008706"
    ],
    "id": 2426539,
    "name:xx": "Jones Hole Creek"
  }
}
