{
  "geometry": {
    "type": "Point",
    "coordinates": [
      -84.4833,
      35.45
    ]
  },
  "type": "Feature",
  "properties": {
    "hierarchy": [
      "tgn:2388666",
      "tgn:1000001",
      "tgn:7012149",
      "tgn:7022542",
      "tgn:7007825",
      "tgn:7029392"
    ],
    "placetype": [
      "aat:300008697"
    ],
    "id": 2388666,
    "name:xx": "Hicks-Brown Spring"
  }
}
