{
  "geometry": {
    "type": "Point",
    "coordinates": [
      -83.1667,
      36.3667
    ]
  },
  "type": "Feature",
  "properties": {
    "hierarchy": [
      "tgn:2099232",
      "tgn:1000001",
      "tgn:7012149",
      "tgn:2001873",
      "tgn:7007825",
      "tgn:7029392"
    ],
    "placetype": [
      "aat:300008347",
      "aat:300387210"
    ],
    "id": 2099232,
    "name:xx": "Galbraith Springs"
  }
}
