{
  "geometry": {
    "type": "Point",
    "coordinates": [
      -110.5667,
      45.45
    ]
  },
  "type": "Feature",
  "properties": {
    "hierarchy": [
      "tgn:2500471",
      "tgn:1000001",
      "tgn:7012149",
      "tgn:2001293",
      "tgn:7007524",
      "tgn:7029392"
    ],
    "placetype": [
      "aat:300008706"
    ],
    "id": 2500471,
    "name:xx": "McDonald Creek"
  }
}
