{
  "geometry": {
    "type": "Point",
    "coordinates": [
      -104.35,
      40.4833
    ]
  },
  "type": "Feature",
  "properties": {
    "hierarchy": [
      "tgn:2589864",
      "tgn:1000001",
      "tgn:7012149",
      "tgn:7007158",
      "tgn:2000253",
      "tgn:7029392"
    ],
    "placetype": [
      "aat:300008798"
    ],
    "id": 2589864,
    "name:xx": "Point of Rocks"
  }
}
