{
  "geometry": {
    "type": "Point",
    "coordinates": [
      9.35,
      53.55
    ]
  },
  "type": "Feature",
  "properties": {
    "hierarchy": [
      "tgn:7095475",
      "tgn:1000003",
      "tgn:7003676",
      "tgn:7000084",
      "tgn:7029392"
    ],
    "placetype": [
      "aat:300000206"
    ],
    "id": 7095475,
    "name:xx": "Schwingerbaum"
  }
}
