{
  "type": "FeatureCollection",
  "features": [
    {
      "geometry": {
        "type": "Point",
        "coordinates": [
          -71,
          -39.25
        ]
      },
      "type": "Feature",
      "properties": {
        "hierarchy": [
          "tgn:1121150",
          "tgn:7006477",
          "tgn:1001450",
          "tgn:1000002",
          "tgn:7029392"
        ],
        "placetype": [
          "aat:300008707"
        ],
        "id": 1121150,
        "name:xx": "Aluminé"
      }
    },
    {
      "geometry": {
        "type": "Point",
        "coordinates": [
          -8.25,
          40.3
        ]
      },
      "type": "Feature",
      "properties": {
        "hierarchy": [
          "tgn:1121151",
          "tgn:1000003",
          "tgn:1000090",
          "tgn:7029392"
        ],
        "placetype": [
          "aat:300008707"
        ],
        "id": 1121151,
        "name:xx": "Alva, Rio"
      }
    },
    {
      "geometry": {
        "type": "Point",
        "coordinates": [
          -46.6167,
          -23.75
        ]
      },
      "type": "Feature",
      "properties": {
        "hierarchy": [
          "tgn:1121152",
          "tgn:1001945",
          "tgn:1000047",
          "tgn:7002457",
          "tgn:1000002",
          "tgn:7029392"
        ],
        "placetype": [
          "aat:300008707"
        ],
        "id": 1121152,
        "name:xx": "Alvarengas, Ribeirão"
      }
    },
    {
      "geometry": {
        "type": "Point",
        "coordinates": [
          -3.4,
          52.966667
        ]
      },
      "type": "Feature",
      "properties": {
        "hierarchy": [
          "tgn:1121153",
          "tgn:7002443",
          "tgn:1000003",
          "tgn:7008591",
          "tgn:7029392"
        ],
        "placetype": [
          "aat:300008707",
          "aat:300008699"
        ],
        "name:en": "Alwen",
        "id": 1121153
      }
    },
    {
      "geometry": {
        "type": "Point",
        "coordinates": [
          6.15,
          49.3667
        ]
      },
      "type": "Feature",
      "properties": {
        "hierarchy": [
          "tgn:1121154",
          "tgn:1000003",
          "tgn:7029392"
        ],
        "placetype": [
          "aat:300008707"
        ],
        "id": 1121154,
        "name:xx": "Alzette"
      }
    },
    {
      "geometry": {
        "type": "Point",
        "coordinates": [
          60,
          8
        ]
      },
      "type": "Feature",
      "properties": {
        "hierarchy": [
          "tgn:1121155",
          "tgn:1000002",
          "tgn:7029392"
        ],
        "placetype": [
          "aat:300008707"
        ],
        "id": 1121155,
        "name:xx": "Amacuro"
      }
    },
    {
      "geometry": {
        "type": "Point",
        "coordinates": [
          -99.2,
          17.883333
        ]
      },
      "type": "Feature",
      "properties": {
        "hierarchy": [
          "tgn:1121156",
          "tgn:1000001",
          "tgn:7005560",
          "tgn:7029392"
        ],
        "placetype": [
          "aat:300008707",
          "aat:300008699"
        ],
        "id": 1121156,
        "name:xx": "Amacuzac, Río"
      }
    },
    {
      "geometry": {
        "type": "Point",
        "coordinates": [
          -98.766667,
          21.25
        ]
      },
      "type": "Feature",
      "properties": {
        "hierarchy": [
          "tgn:1121157",
          "tgn:7005587",
          "tgn:1000001",
          "tgn:7005560",
          "tgn:7029392"
        ],
        "placetype": [
          "aat:300008707",
          "aat:300008699"
        ],
        "id": 1121157,
        "name:xx": "Amajac, Río"
      }
    },
    {
      "geometry": {
        "type": "Point",
        "coordinates": [
          -85.151,
          14.237
        ]
      },
      "type": "Feature",
      "properties": {
        "hierarchy": [
          "tgn:1121158",
          "tgn:1000653",
          "tgn:1000001",
          "tgn:7005562",
          "tgn:7029392"
        ],
        "placetype": [
          "aat:300008707"
        ],
        "id": 1121158,
        "name:xx": "Amaka, Río"
      }
    },
    {
      "geometry": {
        "type": "Point",
        "coordinates": [
          115.2,
          54.8333
        ]
      },
      "type": "Feature",
      "properties": {
        "hierarchy": [
          "tgn:1121159",
          "tgn:1000004",
          "tgn:7011500",
          "tgn:7002435",
          "tgn:7029392"
        ],
        "placetype": [
          "aat:300008707"
        ],
        "id": 1121159,
        "name:xx": "Amalat"
      }
    }
  ]
}
