{
  "geometry": {
    "type": "Point",
    "coordinates": [
      -100.5333,
      47.3167
    ]
  },
  "type": "Feature",
  "properties": {
    "hierarchy": [
      "tgn:2565445",
      "tgn:1000001",
      "tgn:7012149",
      "tgn:7007705",
      "tgn:7029392"
    ],
    "placetype": [
      "aat:300008706"
    ],
    "id": 2565445,
    "name:xx": "Painted Woods Creek"
  }
}
