{
  "type": "FeatureCollection",
  "features": [
    {
      "geometry": {
        "type": "Point",
        "coordinates": [
          -81.6333,
          36.6333
        ]
      },
      "type": "Feature",
      "properties": {
        "hierarchy": [
          "tgn:2691360",
          "tgn:1000001",
          "tgn:7012149",
          "tgn:2002194",
          "tgn:7007919",
          "tgn:7029392"
        ],
        "placetype": [
          "aat:300008699"
        ],
        "id": 2691360,
        "name:xx": "Star Hill Branch"
      }
    },
    {
      "geometry": {
        "type": "Point",
        "coordinates": [
          -75.5333,
          39.1
        ]
      },
      "type": "Feature",
      "properties": {
        "hierarchy": [
          "tgn:2691361",
          "tgn:1002538",
          "tgn:1000001",
          "tgn:7012149",
          "tgn:7007239",
          "tgn:7029392"
        ],
        "placetype": [
          "aat:300008347"
        ],
        "id": 2691361,
        "name:xx": "Star Hill Village"
      }
    },
    {
      "geometry": {
        "type": "Point",
        "coordinates": [
          -87.7,
          34.6667
        ]
      },
      "type": "Feature",
      "properties": {
        "hierarchy": [
          "tgn:2691362",
          "tgn:7002659",
          "tgn:1000001",
          "tgn:2000016",
          "tgn:7012149",
          "tgn:7029392"
        ],
        "placetype": [
          "aat:300008761"
        ],
        "id": 2691362,
        "name:xx": "Star Hollow"
      }
    },
    {
      "geometry": {
        "type": "Point",
        "coordinates": [
          -83.0167,
          38.6333
        ]
      },
      "type": "Feature",
      "properties": {
        "hierarchy": [
          "tgn:2691363",
          "tgn:1000001",
          "tgn:7012149",
          "tgn:1002426",
          "tgn:7007255",
          "tgn:7029392"
        ],
        "placetype": [
          "aat:300008761"
        ],
        "id": 2691363,
        "name:xx": "Star Hollow"
      }
    },
    {
      "geometry": {
        "type": "Point",
        "coordinates": [
          -94,
          36.6167
        ]
      },
      "type": "Feature",
      "properties": {
        "hierarchy": [
          "tgn:2691364",
          "tgn:1000001",
          "tgn:7012149",
          "tgn:7007523",
          "tgn:7029392"
        ],
        "placetype": [
          "aat:300008761"
        ],
        "id": 2691364,
        "name:xx": "Star Hollow"
      }
    },
    {
      "geometry": {
        "type": "Point",
        "coordinates": [
          -97.95,
          32.4167
        ]
      },
      "type": "Feature",
      "properties": {
        "hierarchy": [
          "tgn:2691366",
          "tgn:1000001",
          "tgn:7012149",
          "tgn:1002484",
          "tgn:7007826",
          "tgn:7029392"
        ],
        "placetype": [
          "aat:300008706"
        ],
        "id": 2691366,
        "name:xx": "Star Hollow Creek"
      }
    },
    {
      "geometry": {
        "type": "Point",
        "coordinates": [
          -113.9,
          43.6667
        ]
      },
      "type": "Feature",
      "properties": {
        "hierarchy": [
          "tgn:2691367",
          "tgn:1000001",
          "tgn:2000470",
          "tgn:7012149",
          "tgn:7007250",
          "tgn:7029392"
        ],
        "placetype": [
          "aat:300008706"
        ],
        "id": 2691367,
        "name:xx": "Star Hope Creek"
      }
    },
    {
      "geometry": {
        "type": "Point",
        "coordinates": [
          -113.9167,
          43.6833
        ]
      },
      "type": "Feature",
      "properties": {
        "hierarchy": [
          "tgn:2691368",
          "tgn:1000001",
          "tgn:2000470",
          "tgn:7012149",
          "tgn:7007250",
          "tgn:7029392"
        ],
        "placetype": [
          "aat:300008761"
        ],
        "id": 2691368,
        "name:xx": "Star Hope Gulch"
      }
    },
    {
      "geometry": {
        "type": "Point",
        "coordinates": [
          -113.9167,
          43.6833
        ]
      },
      "type": "Feature",
      "properties": {
        "hierarchy": [
          "tgn:2691369",
          "tgn:1000001",
          "tgn:2000470",
          "tgn:7012149",
          "tgn:7007250",
          "tgn:7029392"
        ],
        "placetype": [
          "aat:300000390"
        ],
        "id": 2691369,
        "name:xx": "Star Hope Mine"
      }
    }
  ]
}
