{
  "type": "FeatureCollection",
  "features": [
    {
      "geometry": {
        "type": "Point",
        "coordinates": [
          -83.0833,
          35.3833
        ]
      },
      "type": "Feature",
      "properties": {
        "hierarchy": [
          "tgn:2194740",
          "tgn:1000001",
          "tgn:7012149",
          "tgn:2001508",
          "tgn:7007709",
          "tgn:7029392"
        ],
        "placetype": [
          "aat:300266640"
        ],
        "id": 2194740,
        "name:xx": "Brier Ridge"
      }
    },
    {
      "geometry": {
        "type": "Point",
        "coordinates": [
          -82.4,
          36
        ]
      },
      "type": "Feature",
      "properties": {
        "hierarchy": [
          "tgn:2194741",
          "tgn:1000001",
          "tgn:7012149",
          "tgn:2001556",
          "tgn:7007709",
          "tgn:7029392"
        ],
        "placetype": [
          "aat:300266640"
        ],
        "id": 2194741,
        "name:xx": "Brier Ridge"
      }
    },
    {
      "geometry": {
        "type": "Point",
        "coordinates": [
          -80.8,
          40.2167
        ]
      },
      "type": "Feature",
      "properties": {
        "hierarchy": [
          "tgn:2194742",
          "tgn:1000001",
          "tgn:7012149",
          "tgn:1002519",
          "tgn:7007706",
          "tgn:7029392"
        ],
        "placetype": [
          "aat:300266640"
        ],
        "id": 2194742,
        "name:xx": "Brier Ridge"
      }
    },
    {
      "geometry": {
        "type": "Point",
        "coordinates": [
          -83.65,
          38.7667
        ]
      },
      "type": "Feature",
      "properties": {
        "hierarchy": [
          "tgn:2194743",
          "tgn:1002136",
          "tgn:1000001",
          "tgn:7012149",
          "tgn:7007706",
          "tgn:7029392"
        ],
        "placetype": [
          "aat:300266640"
        ],
        "id": 2194743,
        "name:xx": "Brier Ridge"
      }
    },
    {
      "geometry": {
        "type": "Point",
        "coordinates": [
          -78,
          40.2
        ]
      },
      "type": "Feature",
      "properties": {
        "hierarchy": [
          "tgn:2194744",
          "tgn:1000001",
          "tgn:7012149",
          "tgn:1002494",
          "tgn:7007710",
          "tgn:7029392"
        ],
        "placetype": [
          "aat:300266640"
        ],
        "id": 2194744,
        "name:xx": "Brier Ridge"
      }
    },
    {
      "geometry": {
        "type": "Point",
        "coordinates": [
          -83.6667,
          35.5833
        ]
      },
      "type": "Feature",
      "properties": {
        "hierarchy": [
          "tgn:2194745",
          "tgn:1000001",
          "tgn:2001841",
          "tgn:7012149",
          "tgn:7007825",
          "tgn:7029392"
        ],
        "placetype": [
          "aat:300266640"
        ],
        "id": 2194745,
        "name:xx": "Brier Ridge"
      }
    },
    {
      "geometry": {
        "type": "Point",
        "coordinates": [
          -81.6667,
          36.5833
        ]
      },
      "type": "Feature",
      "properties": {
        "hierarchy": [
          "tgn:2194746",
          "tgn:1000001",
          "tgn:7012149",
          "tgn:2001882",
          "tgn:7007825",
          "tgn:7029392"
        ],
        "placetype": [
          "aat:300266640"
        ],
        "id": 2194746,
        "name:xx": "Brier Ridge"
      }
    },
    {
      "geometry": {
        "type": "Point",
        "coordinates": [
          -81.55,
          36.6167
        ]
      },
      "type": "Feature",
      "properties": {
        "hierarchy": [
          "tgn:2194747",
          "tgn:1000001",
          "tgn:7012149",
          "tgn:2002164",
          "tgn:7007919",
          "tgn:7029392"
        ],
        "placetype": [
          "aat:300266640"
        ],
        "id": 2194747,
        "name:xx": "Brier Ridge"
      }
    },
    {
      "geometry": {
        "type": "Point",
        "coordinates": [
          -81.45,
          36.6333
        ]
      },
      "type": "Feature",
      "properties": {
        "hierarchy": [
          "tgn:2194748",
          "tgn:1000001",
          "tgn:7012149",
          "tgn:2002164",
          "tgn:7007919",
          "tgn:7029392"
        ],
        "placetype": [
          "aat:300008699"
        ],
        "id": 2194748,
        "name:xx": "Brier Run"
      }
    },
    {
      "geometry": {
        "type": "Point",
        "coordinates": [
          -80.6667,
          38.5167
        ]
      },
      "type": "Feature",
      "properties": {
        "hierarchy": [
          "tgn:2194749",
          "tgn:1000001",
          "tgn:7012149",
          "tgn:2002284",
          "tgn:7013961",
          "tgn:7029392"
        ],
        "placetype": [
          "aat:300008699"
        ],
        "id": 2194749,
        "name:xx": "Brier Run"
      }
    }
  ]
}
