{
  "type": "FeatureCollection",
  "features": [
    {
      "geometry": {
        "type": "Point",
        "coordinates": [
          -72.266667,
          -36.616667
        ]
      },
      "type": "Feature",
      "properties": {
        "hierarchy": [
          "tgn:7282850",
          "tgn:1001637",
          "tgn:1000049",
          "tgn:1000002",
          "tgn:7029392"
        ],
        "placetype": [
          "aat:300387200"
        ],
        "id": 7282850,
        "name:xx": "Pelehuito"
      }
    },
    {
      "geometry": {
        "type": "Point",
        "coordinates": [
          -72.783333,
          -38.033333
        ]
      },
      "type": "Feature",
      "properties": {
        "hierarchy": [
          "tgn:7282851",
          "tgn:1001692",
          "tgn:1000049",
          "tgn:1000002",
          "tgn:7029392"
        ],
        "placetype": [
          "aat:300008699"
        ],
        "id": 7282851,
        "name:xx": "Pelehue, Estero"
      }
    },
    {
      "geometry": {
        "type": "Point",
        "coordinates": [
          -72.45,
          -37.6
        ]
      },
      "type": "Feature",
      "properties": {
        "hierarchy": [
          "tgn:7282852",
          "tgn:1001637",
          "tgn:1000049",
          "tgn:1000002",
          "tgn:7029392"
        ],
        "placetype": [
          "aat:300008699"
        ],
        "id": 7282852,
        "name:xx": "Pelehue, Estero"
      }
    },
    {
      "geometry": {
        "type": "Point",
        "coordinates": [
          -72.283333,
          -36.616667
        ]
      },
      "type": "Feature",
      "properties": {
        "hierarchy": [
          "tgn:7282853",
          "tgn:1001637",
          "tgn:1000049",
          "tgn:1000002",
          "tgn:7029392"
        ],
        "placetype": [
          "aat:300000206"
        ],
        "id": 7282853,
        "name:xx": "Pelehue"
      }
    },
    {
      "geometry": {
        "type": "Point",
        "coordinates": [
          -73.4,
          -37.9
        ]
      },
      "type": "Feature",
      "properties": {
        "hierarchy": [
          "tgn:7282854",
          "tgn:1001637",
          "tgn:1000049",
          "tgn:1000002",
          "tgn:7029392"
        ],
        "placetype": [
          "aat:300008699"
        ],
        "id": 7282854,
        "name:xx": "Peleco, Río"
      }
    },
    {
      "geometry": {
        "type": "Point",
        "coordinates": [
          -73.383333,
          -37.9
        ]
      },
      "type": "Feature",
      "properties": {
        "hierarchy": [
          "tgn:7282855",
          "tgn:1001637",
          "tgn:1000049",
          "tgn:1000002",
          "tgn:7029392"
        ],
        "placetype": [
          "aat:300007783"
        ],
        "id": 7282855,
        "name:xx": "Estación Peleco"
      }
    },
    {
      "geometry": {
        "type": "Point",
        "coordinates": [
          -73.366667,
          -37.816667
        ]
      },
      "type": "Feature",
      "properties": {
        "hierarchy": [
          "tgn:7282856",
          "tgn:1001637",
          "tgn:1000049",
          "tgn:1000002",
          "tgn:7029392"
        ],
        "placetype": [
          "aat:300008777"
        ],
        "id": 7282856,
        "name:xx": "Peleco, Cerro"
      }
    },
    {
      "geometry": {
        "type": "Point",
        "coordinates": [
          -73.3,
          -39
        ]
      },
      "type": "Feature",
      "properties": {
        "hierarchy": [
          "tgn:7282857",
          "tgn:1001692",
          "tgn:1000049",
          "tgn:1000002",
          "tgn:7029392"
        ],
        "placetype": [
          "aat:300008347"
        ],
        "id": 7282857,
        "name:xx": "Peleco"
      }
    },
    {
      "geometry": {
        "type": "Point",
        "coordinates": [
          -72.366667,
          -31.583333
        ]
      },
      "type": "Feature",
      "properties": {
        "hierarchy": [
          "tgn:7282858",
          "tgn:1001699",
          "tgn:1000049",
          "tgn:1000002",
          "tgn:7029392"
        ],
        "placetype": [
          "aat:300387200"
        ],
        "id": 7282858,
        "name:xx": "Peleco"
      }
    },
    {
      "geometry": {
        "type": "Point",
        "coordinates": [
          -73.366667,
          -37.866667
        ]
      },
      "type": "Feature",
      "properties": {
        "hierarchy": [
          "tgn:7282859",
          "tgn:1001637",
          "tgn:1000049",
          "tgn:1000002",
          "tgn:7029392"
        ],
        "placetype": [
          "aat:300000206"
        ],
        "id": 7282859,
        "name:xx": "Peleco"
      }
    }
  ]
}
