{
  "geometry": {
    "type": "Point",
    "coordinates": [
      -77.8333,
      41.8333
    ]
  },
  "type": "Feature",
  "properties": {
    "hierarchy": [
      "tgn:2729300",
      "tgn:1000001",
      "tgn:7012149",
      "tgn:1002800",
      "tgn:7007710",
      "tgn:7029392"
    ],
    "placetype": [
      "aat:300008798"
    ],
    "id": 2729300,
    "name:xx": "Triple Divide"
  }
}
