{
  "geometry": {
    "type": "Point",
    "coordinates": [
      -87.3167,
      37.95
    ]
  },
  "type": "Feature",
  "properties": {
    "hierarchy": [
      "tgn:2441543",
      "tgn:1000001",
      "tgn:7012149",
      "tgn:2000560",
      "tgn:7007252",
      "tgn:7029392"
    ],
    "placetype": [
      "aat:300006075"
    ],
    "id": 2441543,
    "name:xx": "Koehler Ditch"
  }
}
