{
  "geometry": {
    "type": "Point",
    "coordinates": [
      24.4833,
      -6.1667
    ]
  },
  "type": "Feature",
  "properties": {
    "hierarchy": [
      "tgn:1089032",
      "tgn:7001242",
      "tgn:1001346",
      "tgn:1000159",
      "tgn:7029392"
    ],
    "placetype": [
      "aat:300008347"
    ],
    "id": 1089032,
    "name:xx": "Kabinda"
  }
}
