{
  "geometry": {
    "type": "Point",
    "coordinates": [
      49.3667,
      39.7667
    ]
  },
  "type": "Feature",
  "properties": {
    "hierarchy": [
      "tgn:1052371",
      "tgn:7011438",
      "tgn:1000004",
      "tgn:7006646",
      "tgn:7029392"
    ],
    "placetype": [
      "aat:300008347"
    ],
    "id": 1052371,
    "name:xx": "Byandovan"
  }
}
