{
  "geometry": {
    "type": "Point",
    "coordinates": [
      -150.1833,
      61.5167
    ]
  },
  "type": "Feature",
  "properties": {
    "hierarchy": [
      "tgn:2392930",
      "tgn:7006450",
      "tgn:1000001",
      "tgn:2124053",
      "tgn:7012149",
      "tgn:7029392"
    ],
    "placetype": [
      "aat:300008680"
    ],
    "id": 2392930,
    "name:xx": "Hock Lake"
  }
}
