{
  "geometry": {
    "type": "Point",
    "coordinates": [
      -93.7167,
      44.6333
    ]
  },
  "type": "Feature",
  "properties": {
    "hierarchy": [
      "tgn:2198510",
      "tgn:1000001",
      "tgn:7012149",
      "tgn:2001068",
      "tgn:7007521",
      "tgn:7029392"
    ],
    "placetype": [
      "aat:300008680"
    ],
    "id": 2198510,
    "name:xx": "Browns Lake"
  }
}
