{
  "geometry": {
    "type": "Point",
    "coordinates": [
      23.95,
      -28.3333
    ]
  },
  "type": "Feature",
  "properties": {
    "hierarchy": [
      "tgn:1110305",
      "tgn:7001242",
      "tgn:7029392"
    ],
    "placetype": [
      "aat:300132339"
    ],
    "id": 1110305,
    "name:xx": "Kaap Plato"
  }
}
