{
  "geometry": {
    "type": "Point",
    "coordinates": [
      -0.95,
      53.75
    ]
  },
  "type": "Feature",
  "properties": {
    "hierarchy": [
      "tgn:7010100",
      "tgn:7002445",
      "tgn:1000003",
      "tgn:7008117",
      "tgn:7008591",
      "tgn:7029392"
    ],
    "placetype": [
      "aat:300008707",
      "aat:300008699"
    ],
    "name:en": "Derwent",
    "id": 7010100
  }
}
