{
  "type": "FeatureCollection",
  "features": [
    {
      "geometry": {
        "type": "Point",
        "coordinates": [
          -70.15,
          -19.533333
        ]
      },
      "type": "Feature",
      "properties": {
        "hierarchy": [
          "tgn:7288370",
          "tgn:7002464",
          "tgn:1000049",
          "tgn:1000002",
          "tgn:7029392"
        ],
        "placetype": [
          "aat:300266554",
          "aat:300008699"
        ],
        "id": 7288370,
        "name:xx": "Jazpampa, Quebrada"
      }
    },
    {
      "geometry": {
        "type": "Point",
        "coordinates": [
          -71.4,
          -54.3
        ]
      },
      "type": "Feature",
      "properties": {
        "hierarchy": [
          "tgn:7288371",
          "tgn:1001702",
          "tgn:1000049",
          "tgn:1000002",
          "tgn:7029392"
        ],
        "placetype": [
          "aat:300008791"
        ],
        "id": 7288371,
        "name:xx": "Javiera, Isla"
      }
    },
    {
      "geometry": {
        "type": "Point",
        "coordinates": [
          -74.3,
          -47.083333
        ]
      },
      "type": "Feature",
      "properties": {
        "hierarchy": [
          "tgn:7288372",
          "tgn:1001623",
          "tgn:1000049",
          "tgn:1000002",
          "tgn:7029392"
        ],
        "placetype": [
          "aat:300386968"
        ],
        "id": 7288372,
        "name:xx": "Surgidero Javier"
      }
    },
    {
      "geometry": {
        "type": "Point",
        "coordinates": [
          -71.3,
          -32.466667
        ]
      },
      "type": "Feature",
      "properties": {
        "hierarchy": [
          "tgn:7288374",
          "tgn:1001768",
          "tgn:1000049",
          "tgn:1000002",
          "tgn:7029392"
        ],
        "placetype": [
          "aat:300000206"
        ],
        "id": 7288374,
        "name:xx": "Jaururo"
      }
    },
    {
      "geometry": {
        "type": "Point",
        "coordinates": [
          -74.9,
          -47.766667
        ]
      },
      "type": "Feature",
      "properties": {
        "hierarchy": [
          "tgn:7288375",
          "tgn:1001623",
          "tgn:1000049",
          "tgn:1000002",
          "tgn:7029392"
        ],
        "placetype": [
          "aat:300008791"
        ],
        "id": 7288375,
        "name:xx": "Jaures, Islote"
      }
    },
    {
      "geometry": {
        "type": "Point",
        "coordinates": [
          -68.7,
          -55.55
        ]
      },
      "type": "Feature",
      "properties": {
        "hierarchy": [
          "tgn:7288376",
          "tgn:1001702",
          "tgn:1000049",
          "tgn:1000002",
          "tgn:7029392"
        ],
        "placetype": [
          "aat:300008791"
        ],
        "id": 7288376,
        "name:xx": "Jaureguiberry, Isla"
      }
    },
    {
      "geometry": {
        "type": "Point",
        "coordinates": [
          -71.333333,
          -32.45
        ]
      },
      "type": "Feature",
      "properties": {
        "hierarchy": [
          "tgn:7288377",
          "tgn:1001768",
          "tgn:1000049",
          "tgn:1000002",
          "tgn:7029392"
        ],
        "placetype": [
          "aat:300008699"
        ],
        "id": 7288377,
        "name:xx": "Jauniro, Quebrada de"
      }
    },
    {
      "geometry": {
        "type": "Point",
        "coordinates": [
          -68.133333,
          -22.633333
        ]
      },
      "type": "Feature",
      "properties": {
        "hierarchy": [
          "tgn:7288378",
          "tgn:7016598",
          "tgn:1000049",
          "tgn:1000002",
          "tgn:7029392"
        ],
        "placetype": [
          "aat:300266554",
          "aat:300008699"
        ],
        "id": 7288378,
        "name:xx": "Jauna, Arroyo de"
      }
    },
    {
      "geometry": {
        "type": "Point",
        "coordinates": [
          -70.716667,
          -28.25
        ]
      },
      "type": "Feature",
      "properties": {
        "hierarchy": [
          "tgn:7288379",
          "tgn:1001630",
          "tgn:1000049",
          "tgn:1000002",
          "tgn:7029392"
        ],
        "placetype": [
          "aat:300008805"
        ],
        "id": 7288379,
        "name:xx": "Jaula, Llano de la"
      }
    }
  ]
}
