{
  "geometry": {
    "type": "Point",
    "coordinates": [
      77.584414,
      29.029351
    ]
  },
  "type": "Feature",
  "properties": {
    "hierarchy": [
      "tgn:7558766",
      "tgn:1000004",
      "tgn:7000198",
      "tgn:7016722",
      "tgn:7029392"
    ],
    "placetype": [
      "aat:300008347"
    ],
    "name:en": "Pūth Khās",
    "id": 7558766
  }
}
