{
  "geometry": {
    "type": "Point",
    "coordinates": [
      -99.9167,
      44.15
    ]
  },
  "type": "Feature",
  "properties": {
    "hierarchy": [
      "tgn:2228631",
      "tgn:1000001",
      "tgn:2001812",
      "tgn:7012149",
      "tgn:7007713",
      "tgn:7029392"
    ],
    "placetype": [
      "aat:300008791"
    ],
    "id": 2228631,
    "name:xx": "Cedar Creek Island"
  }
}
