{
  "geometry": {
    "type": "Point",
    "coordinates": [
      -71.2333,
      43.65
    ]
  },
  "type": "Feature",
  "properties": {
    "hierarchy": [
      "tgn:2063300",
      "tgn:2001423",
      "tgn:1000001",
      "tgn:7012149",
      "tgn:7007564",
      "tgn:7029392"
    ],
    "placetype": [
      "aat:300008347"
    ],
    "id": 2063300,
    "name:xx": "Center Tuftonboro"
  }
}
