{
  "type": "FeatureCollection",
  "features": [
    {
      "geometry": {
        "type": "Point",
        "coordinates": [
          -2.655556,
          51.086667
        ]
      },
      "type": "Feature",
      "properties": {
        "hierarchy": [
          "tgn:7465742",
          "tgn:7002445",
          "tgn:1000003",
          "tgn:7012032",
          "tgn:7008591",
          "tgn:7029392"
        ],
        "placetype": [
          "aat:300008347"
        ],
        "name:en": "Barton Saint David",
        "id": 7465742
      }
    },
    {
      "geometry": {
        "type": "Point",
        "coordinates": [
          -0.9,
          54.05
        ]
      },
      "type": "Feature",
      "properties": {
        "hierarchy": [
          "tgn:7465743",
          "tgn:7002445",
          "tgn:1000003",
          "tgn:7008166",
          "tgn:7008591",
          "tgn:7029392"
        ],
        "placetype": [
          "aat:300008347"
        ],
        "name:en": "Barton le Willows",
        "id": 7465743
      }
    },
    {
      "geometry": {
        "type": "Point",
        "coordinates": [
          -0.883333,
          54.15
        ]
      },
      "type": "Feature",
      "properties": {
        "hierarchy": [
          "tgn:7465744",
          "tgn:7002445",
          "tgn:1000003",
          "tgn:7008166",
          "tgn:7008591",
          "tgn:7029392"
        ],
        "placetype": [
          "aat:300008347"
        ],
        "name:en": "Barton le Street",
        "id": 7465744
      }
    },
    {
      "geometry": {
        "type": "Point",
        "coordinates": [
          -0.6,
          53.866667
        ]
      },
      "type": "Feature",
      "properties": {
        "hierarchy": [
          "tgn:7465747",
          "tgn:7002445",
          "tgn:1000003",
          "tgn:7019057",
          "tgn:7008591",
          "tgn:7029392"
        ],
        "placetype": [
          "aat:300008347"
        ],
        "name:en": "Arras",
        "id": 7465747
      }
    },
    {
      "geometry": {
        "type": "Point",
        "coordinates": [
          -0.433333,
          53.883333
        ]
      },
      "type": "Feature",
      "properties": {
        "hierarchy": [
          "tgn:7465749",
          "tgn:7002445",
          "tgn:1000003",
          "tgn:7019057",
          "tgn:7008591",
          "tgn:7029392"
        ],
        "placetype": [
          "aat:300008347"
        ],
        "name:en": "Arram",
        "id": 7465749
      }
    }
  ]
}
