{
  "geometry": {
    "type": "Point",
    "coordinates": [
      -87.9167,
      39.5333
    ]
  },
  "type": "Feature",
  "properties": {
    "hierarchy": [
      "tgn:2590836",
      "tgn:1000001",
      "tgn:7012149",
      "tgn:7007251",
      "tgn:7029392"
    ],
    "placetype": [
      "aat:300008706"
    ],
    "id": 2590836,
    "name:xx": "Polecat Creek"
  }
}
