{
  "geometry": {
    "type": "Point",
    "coordinates": [
      -80.8667,
      41.3167
    ]
  },
  "type": "Feature",
  "properties": {
    "hierarchy": [
      "tgn:2469036",
      "tgn:1000001",
      "tgn:7012149",
      "tgn:1002955",
      "tgn:7007706",
      "tgn:7029392"
    ],
    "placetype": [
      "aat:300008905"
    ],
    "id": 2469036,
    "name:xx": "Long Swamp"
  }
}
