{
  "geometry": {
    "type": "Point",
    "coordinates": [
      -80.45,
      40.6167
    ]
  },
  "type": "Feature",
  "properties": {
    "hierarchy": [
      "tgn:2749373",
      "tgn:1002171",
      "tgn:1000001",
      "tgn:7012149",
      "tgn:7007710",
      "tgn:7029392"
    ],
    "placetype": [
      "aat:300132348"
    ],
    "id": 2749373,
    "name:xx": "Wallory Bar"
  }
}
