{
  "geometry": {
    "type": "Point",
    "coordinates": [
      -86.0167,
      33.2167
    ]
  },
  "type": "Feature",
  "properties": {
    "hierarchy": [
      "tgn:2501195",
      "tgn:7002659",
      "tgn:1000001",
      "tgn:2000013",
      "tgn:7012149",
      "tgn:7029392"
    ],
    "placetype": [
      "aat:300000390"
    ],
    "id": 2501195,
    "name:xx": "McGhee Mine"
  }
}
