{
  "geometry": {
    "type": "Point",
    "coordinates": [
      -110.7833,
      34.4667
    ]
  },
  "type": "Feature",
  "properties": {
    "hierarchy": [
      "tgn:2359821",
      "tgn:1000001",
      "tgn:7006451",
      "tgn:7012149",
      "tgn:7029392"
    ],
    "placetype": [
      "aat:300008761"
    ],
    "id": 2359821,
    "name:xx": "Grapevine Draw"
  }
}
