{
  "geometry": {
    "type": "Point",
    "coordinates": [
      -86.55,
      39.4833
    ]
  },
  "type": "Feature",
  "properties": {
    "hierarchy": [
      "tgn:2208116",
      "tgn:1000001",
      "tgn:7012149",
      "tgn:1002694",
      "tgn:7007252",
      "tgn:7029392"
    ],
    "placetype": [
      "aat:300008706"
    ],
    "id": 2208116,
    "name:xx": "Burkhart Creek"
  }
}
