{
  "geometry": {
    "type": "Point",
    "coordinates": [
      -97.35,
      26.0667
    ]
  },
  "type": "Feature",
  "properties": {
    "hierarchy": [
      "tgn:2601242",
      "tgn:1000001",
      "tgn:7012149",
      "tgn:2001952",
      "tgn:7007826",
      "tgn:7029392"
    ],
    "placetype": [
      "aat:300008850"
    ],
    "id": 2601242,
    "name:xx": "Punta de las Bahias"
  }
}
