{
  "geometry": {
    "type": "Point",
    "coordinates": [
      -73.3833,
      42.8333
    ]
  },
  "type": "Feature",
  "properties": {
    "hierarchy": [
      "tgn:2595988",
      "tgn:1000001",
      "tgn:7012149",
      "tgn:1002821",
      "tgn:7007568",
      "tgn:7029392"
    ],
    "placetype": [
      "aat:300008347"
    ],
    "id": 2595988,
    "name:xx": "Potter Hill"
  }
}
