{
  "type": "FeatureCollection",
  "features": [
    {
      "geometry": {
        "type": "Point",
        "coordinates": [
          -118.1333,
          44.5833
        ]
      },
      "type": "Feature",
      "properties": {
        "hierarchy": [
          "tgn:2237520",
          "tgn:7013349",
          "tgn:1000001",
          "tgn:7012149",
          "tgn:7007708",
          "tgn:7029392"
        ],
        "placetype": [
          "aat:300008680"
        ],
        "id": 2237520,
        "name:xx": "China Lake"
      }
    },
    {
      "geometry": {
        "type": "Point",
        "coordinates": [
          -101.7167,
          31.9167
        ]
      },
      "type": "Feature",
      "properties": {
        "hierarchy": [
          "tgn:2237521",
          "tgn:1000001",
          "tgn:7012149",
          "tgn:2001991",
          "tgn:7007826",
          "tgn:7029392"
        ],
        "placetype": [
          "aat:300008680"
        ],
        "id": 2237521,
        "name:xx": "China Lake"
      }
    },
    {
      "geometry": {
        "type": "Point",
        "coordinates": [
          -103.2167,
          31.4833
        ]
      },
      "type": "Feature",
      "properties": {
        "hierarchy": [
          "tgn:2237522",
          "tgn:1000001",
          "tgn:7012149",
          "tgn:2002089",
          "tgn:7007826",
          "tgn:7029392"
        ],
        "placetype": [
          "aat:300008680"
        ],
        "id": 2237522,
        "name:xx": "China Lake"
      }
    },
    {
      "geometry": {
        "type": "Point",
        "coordinates": [
          -99.8333,
          33.7333
        ]
      },
      "type": "Feature",
      "properties": {
        "hierarchy": [
          "tgn:2237523",
          "tgn:1000001",
          "tgn:7012149",
          "tgn:2002023",
          "tgn:7007826",
          "tgn:7029392"
        ],
        "placetype": [
          "aat:300008680"
        ],
        "id": 2237523,
        "name:xx": "China Lake"
      }
    },
    {
      "geometry": {
        "type": "Point",
        "coordinates": [
          -110.4,
          40.9333
        ]
      },
      "type": "Feature",
      "properties": {
        "hierarchy": [
          "tgn:2237524",
          "tgn:1000001",
          "tgn:7012149",
          "tgn:2002122",
          "tgn:7007827",
          "tgn:7029392"
        ],
        "placetype": [
          "aat:300008680"
        ],
        "id": 2237524,
        "name:xx": "China Lake"
      }
    },
    {
      "geometry": {
        "type": "Point",
        "coordinates": [
          -110.4,
          40.9333
        ]
      },
      "type": "Feature",
      "properties": {
        "hierarchy": [
          "tgn:2237525",
          "tgn:1000001",
          "tgn:7012149",
          "tgn:2002122",
          "tgn:7007827",
          "tgn:7029392"
        ],
        "placetype": [
          "aat:300006191"
        ],
        "id": 2237525,
        "name:xx": "China Lake"
      }
    },
    {
      "geometry": {
        "type": "Point",
        "coordinates": [
          -123.8833,
          41.7
        ]
      },
      "type": "Feature",
      "properties": {
        "hierarchy": [
          "tgn:2237526",
          "tgn:1000001",
          "tgn:7012149",
          "tgn:2000180",
          "tgn:7007157",
          "tgn:7029392"
        ],
        "placetype": [
          "aat:300000390"
        ],
        "id": 2237526,
        "name:xx": "China Mine"
      }
    },
    {
      "geometry": {
        "type": "Point",
        "coordinates": [
          -120.8667,
          38.5833
        ]
      },
      "type": "Feature",
      "properties": {
        "hierarchy": [
          "tgn:2237527",
          "tgn:1000001",
          "tgn:7012149",
          "tgn:1002350",
          "tgn:7007157",
          "tgn:7029392"
        ],
        "placetype": [
          "aat:300008798"
        ],
        "id": 2237527,
        "name:xx": "China Mountain"
      }
    },
    {
      "geometry": {
        "type": "Point",
        "coordinates": [
          -122.5667,
          41.3667
        ]
      },
      "type": "Feature",
      "properties": {
        "hierarchy": [
          "tgn:2237528",
          "tgn:1000001",
          "tgn:7012149",
          "tgn:7007157",
          "tgn:2000189",
          "tgn:7029392"
        ],
        "placetype": [
          "aat:300008798"
        ],
        "id": 2237528,
        "name:xx": "China Mountain"
      }
    },
    {
      "geometry": {
        "type": "Point",
        "coordinates": [
          -114.85,
          42.05
        ]
      },
      "type": "Feature",
      "properties": {
        "hierarchy": [
          "tgn:2237529",
          "tgn:1000001",
          "tgn:7012149",
          "tgn:2000493",
          "tgn:7007250",
          "tgn:7029392"
        ],
        "placetype": [
          "aat:300008798"
        ],
        "id": 2237529,
        "name:xx": "China Mountain"
      }
    }
  ]
}
