{
  "geometry": {
    "type": "Point",
    "coordinates": [
      -74.6833,
      40.5667
    ]
  },
  "type": "Feature",
  "properties": {
    "hierarchy": [
      "tgn:2192298",
      "tgn:1000001",
      "tgn:1002903",
      "tgn:7012149",
      "tgn:7007565",
      "tgn:7029392"
    ],
    "placetype": [
      "aat:300008347"
    ],
    "id": 2192298,
    "name:xx": "Branchburg Park"
  }
}
