{
  "type": "FeatureCollection",
  "features": [
    {
      "geometry": {
        "type": "Point",
        "coordinates": [
          -75.45,
          42.5333
        ]
      },
      "type": "Feature",
      "properties": {
        "hierarchy": [
          "tgn:2424630",
          "tgn:1000001",
          "tgn:1002262",
          "tgn:7012149",
          "tgn:7007568",
          "tgn:7029392"
        ],
        "placetype": [
          "aat:300008706"
        ],
        "id": 2424630,
        "name:xx": "Johnson Creek"
      }
    },
    {
      "geometry": {
        "type": "Point",
        "coordinates": [
          -76.4167,
          34.75
        ]
      },
      "type": "Feature",
      "properties": {
        "hierarchy": [
          "tgn:2424631",
          "tgn:1000001",
          "tgn:2001477",
          "tgn:7012149",
          "tgn:7007709",
          "tgn:7029392"
        ],
        "placetype": [
          "aat:300132316"
        ],
        "id": 2424631,
        "name:xx": "Johnson Creek"
      }
    },
    {
      "geometry": {
        "type": "Point",
        "coordinates": [
          -79.45,
          35.8333
        ]
      },
      "type": "Feature",
      "properties": {
        "hierarchy": [
          "tgn:2424632",
          "tgn:1000001",
          "tgn:2001480",
          "tgn:7012149",
          "tgn:7007709",
          "tgn:7029392"
        ],
        "placetype": [
          "aat:300008706"
        ],
        "id": 2424632,
        "name:xx": "Johnson Creek"
      }
    },
    {
      "geometry": {
        "type": "Point",
        "coordinates": [
          -80.3667,
          36
        ]
      },
      "type": "Feature",
      "properties": {
        "hierarchy": [
          "tgn:2424633",
          "tgn:1000001",
          "tgn:7012149",
          "tgn:2001494",
          "tgn:7007709",
          "tgn:7029392"
        ],
        "placetype": [
          "aat:300008706"
        ],
        "id": 2424633,
        "name:xx": "Johnson Creek"
      }
    },
    {
      "geometry": {
        "type": "Point",
        "coordinates": [
          -78.6833,
          36.2
        ]
      },
      "type": "Feature",
      "properties": {
        "hierarchy": [
          "tgn:2424634",
          "tgn:1000001",
          "tgn:7012149",
          "tgn:7014128",
          "tgn:7007709",
          "tgn:7029392"
        ],
        "placetype": [
          "aat:300008706"
        ],
        "id": 2424634,
        "name:xx": "Johnson Creek"
      }
    },
    {
      "geometry": {
        "type": "Point",
        "coordinates": [
          -83.7333,
          35.1167
        ]
      },
      "type": "Feature",
      "properties": {
        "hierarchy": [
          "tgn:2424635",
          "tgn:1000001",
          "tgn:2001483",
          "tgn:7012149",
          "tgn:7007709",
          "tgn:7029392"
        ],
        "placetype": [
          "aat:300008706"
        ],
        "id": 2424635,
        "name:xx": "Johnson Creek"
      }
    },
    {
      "geometry": {
        "type": "Point",
        "coordinates": [
          -84.1167,
          35.15
        ]
      },
      "type": "Feature",
      "properties": {
        "hierarchy": [
          "tgn:2424636",
          "tgn:1000001",
          "tgn:2001481",
          "tgn:7012149",
          "tgn:7007709",
          "tgn:7029392"
        ],
        "placetype": [
          "aat:300008706"
        ],
        "id": 2424636,
        "name:xx": "Johnson Creek"
      }
    },
    {
      "geometry": {
        "type": "Point",
        "coordinates": [
          -81,
          35.4167
        ]
      },
      "type": "Feature",
      "properties": {
        "hierarchy": [
          "tgn:2424637",
          "tgn:1000001",
          "tgn:7012149",
          "tgn:7007709",
          "tgn:7029392"
        ],
        "placetype": [
          "aat:300008706"
        ],
        "id": 2424637,
        "name:xx": "Johnson Creek"
      }
    },
    {
      "geometry": {
        "type": "Point",
        "coordinates": [
          -96.3,
          34.1167
        ]
      },
      "type": "Feature",
      "properties": {
        "hierarchy": [
          "tgn:2424638",
          "tgn:1000001",
          "tgn:2001629",
          "tgn:7012149",
          "tgn:7007707",
          "tgn:7029392"
        ],
        "placetype": [
          "aat:300008706"
        ],
        "id": 2424638,
        "name:xx": "Johnson Creek"
      }
    },
    {
      "geometry": {
        "type": "Point",
        "coordinates": [
          -116.75,
          45.3
        ]
      },
      "type": "Feature",
      "properties": {
        "hierarchy": [
          "tgn:2424639",
          "tgn:1000001",
          "tgn:7012149",
          "tgn:2001722",
          "tgn:7007708",
          "tgn:7029392"
        ],
        "placetype": [
          "aat:300008706"
        ],
        "id": 2424639,
        "name:xx": "Johnson Creek"
      }
    }
  ]
}
