{
  "geometry": {
    "type": "Point",
    "coordinates": [
      -121.9833,
      41.9833
    ]
  },
  "type": "Feature",
  "properties": {
    "hierarchy": [
      "tgn:2529638",
      "tgn:1000001",
      "tgn:7012149",
      "tgn:7007157",
      "tgn:2000189",
      "tgn:7029392"
    ],
    "placetype": [
      "aat:300266640"
    ],
    "id": 2529638,
    "name:xx": "Mud Lake Ridge"
  }
}
