{
  "geometry": {
    "type": "Point",
    "coordinates": [
      -76.05,
      35.45
    ]
  },
  "type": "Feature",
  "properties": {
    "hierarchy": [
      "tgn:2075841",
      "tgn:1000001",
      "tgn:7012149",
      "tgn:2001506",
      "tgn:7007709",
      "tgn:7029392"
    ],
    "placetype": [
      "aat:300008347"
    ],
    "id": 2075841,
    "name:xx": "Nebraska"
  }
}
