{
  "geometry": {
    "type": "Point",
    "coordinates": [
      -93.8333,
      36.2833
    ]
  },
  "type": "Feature",
  "properties": {
    "hierarchy": [
      "tgn:2183408",
      "tgn:1000001",
      "tgn:7016172",
      "tgn:7012149",
      "tgn:2000148",
      "tgn:7029392"
    ],
    "placetype": [
      "aat:300008798"
    ],
    "id": 2183408,
    "name:xx": "Bluff Field Mountain"
  }
}
