{
  "geometry": {
    "type": "Point",
    "coordinates": [
      30.883333,
      29.35
    ]
  },
  "type": "Feature",
  "properties": {
    "hierarchy": [
      "tgn:7539283",
      "tgn:7001242",
      "tgn:7001105",
      "tgn:7016833",
      "tgn:7029392"
    ],
    "placetype": [
      "aat:300387086"
    ],
    "name:en": "Maţir Ţāris al Gharbī, Baḩr",
    "id": 7539283
  }
}
