{
  "geometry": {
    "type": "Point",
    "coordinates": [
      111.65,
      -7.55
    ]
  },
  "type": "Feature",
  "properties": {
    "hierarchy": [
      "tgn:1077569",
      "tgn:1000004",
      "tgn:1001323",
      "tgn:1000116",
      "tgn:7029392"
    ],
    "placetype": [
      "aat:300008347"
    ],
    "id": 1077569,
    "name:xx": "Caruban"
  }
}
