{
  "geometry": {
    "type": "Point",
    "coordinates": [
      -80.1333,
      25.9667
    ]
  },
  "type": "Feature",
  "properties": {
    "hierarchy": [
      "tgn:7013682",
      "tgn:1000001",
      "tgn:1002207",
      "tgn:7012149",
      "tgn:7007240",
      "tgn:7029392"
    ],
    "placetype": [
      "aat:300008347"
    ],
    "id": 7013682,
    "name:xx": "Hallandale"
  }
}
