{
  "geometry": {
    "type": "Point",
    "coordinates": [
      -101.25,
      41.15
    ]
  },
  "type": "Feature",
  "properties": {
    "hierarchy": [
      "tgn:2433072",
      "tgn:1000001",
      "tgn:7012149",
      "tgn:7007525",
      "tgn:7029392"
    ],
    "placetype": [
      "aat:300006075"
    ],
    "id": 2433072,
    "name:xx": "Keith Lincoln Canal"
  }
}
