{
  "geometry": {
    "type": "Point",
    "coordinates": [
      -8.0833,
      53.1667
    ]
  },
  "type": "Feature",
  "properties": {
    "hierarchy": [
      "tgn:1126178",
      "tgn:1000003",
      "tgn:1000078",
      "tgn:7029392"
    ],
    "placetype": [
      "aat:300008707"
    ],
    "id": 1126178,
    "name:xx": "Little Brosna River"
  }
}
