{
  "geometry": {
    "type": "Point",
    "coordinates": [
      80.75,
      7.3333
    ]
  },
  "type": "Feature",
  "properties": {
    "hierarchy": [
      "tgn:7000410",
      "tgn:1000004",
      "tgn:1000110",
      "tgn:7029392"
    ],
    "placetype": [
      "aat:300387064",
      "aat:300000774"
    ],
    "id": 7000410,
    "name:xx": "Central Province"
  }
}
