{
  "geometry": {
    "type": "Point",
    "coordinates": [
      -79.7833,
      37.5667
    ]
  },
  "type": "Feature",
  "properties": {
    "hierarchy": [
      "tgn:2002146",
      "tgn:1000001",
      "tgn:7012149",
      "tgn:7007919",
      "tgn:7029392"
    ],
    "placetype": [
      "aat:300387145",
      "aat:300000771"
    ],
    "id": 2002146,
    "name:xx": "Botetourt"
  }
}
