{
  "geometry": {
    "type": "Point",
    "coordinates": [
      34.50507,
      29.469289
    ]
  },
  "type": "Feature",
  "properties": {
    "hierarchy": [
      "tgn:7522579",
      "tgn:7001242",
      "tgn:7016833",
      "tgn:7001336",
      "tgn:7029392"
    ],
    "placetype": [
      "aat:300008795"
    ],
    "name:en": "Baḑiyah, Jabal al",
    "id": 7522579
  }
}
