{
  "geometry": {
    "type": "Point",
    "coordinates": [
      -80.9167,
      39.5333
    ]
  },
  "type": "Feature",
  "properties": {
    "hierarchy": [
      "tgn:2468948",
      "tgn:1000001",
      "tgn:7012149",
      "tgn:2002297",
      "tgn:7013961",
      "tgn:7029392"
    ],
    "placetype": [
      "aat:300008699"
    ],
    "id": 2468948,
    "name:xx": "Long Run"
  }
}
