{
  "geometry": {
    "type": "Point",
    "coordinates": [
      -85.7667,
      38.0333
    ]
  },
  "type": "Feature",
  "properties": {
    "hierarchy": [
      "tgn:2160579",
      "tgn:1000001",
      "tgn:2000774",
      "tgn:7012149",
      "tgn:7007255",
      "tgn:7029392"
    ],
    "placetype": [
      "aat:300266640"
    ],
    "id": 2160579,
    "name:xx": "Beghto Ridge"
  }
}
