{
  "geometry": {
    "type": "Point",
    "coordinates": [
      -73.9333,
      42.3667
    ]
  },
  "type": "Feature",
  "properties": {
    "hierarchy": [
      "tgn:2293054",
      "tgn:1000001",
      "tgn:7012149",
      "tgn:1002423",
      "tgn:7007568",
      "tgn:7029392"
    ],
    "placetype": [
      "aat:300008680"
    ],
    "id": 2293054,
    "name:xx": "Dots Lake"
  }
}
