{
  "geometry": {
    "type": "Point",
    "coordinates": [
      33.805303,
      25.954004
    ]
  },
  "type": "Feature",
  "properties": {
    "hierarchy": [
      "tgn:7528609",
      "tgn:7001242",
      "tgn:7001311",
      "tgn:7016833",
      "tgn:7029392"
    ],
    "placetype": [
      "aat:300008795"
    ],
    "name:en": "Umm Ḩumbuş, Jabal",
    "id": 7528609
  }
}
