{
  "geometry": {
    "type": "Point",
    "coordinates": [
      -86.8167,
      35.5167
    ]
  },
  "type": "Feature",
  "properties": {
    "hierarchy": [
      "tgn:2097923",
      "tgn:1000001",
      "tgn:7012149",
      "tgn:2001895",
      "tgn:7007825",
      "tgn:7029392"
    ],
    "placetype": [
      "aat:300008347",
      "aat:300387210"
    ],
    "id": 2097923,
    "name:xx": "Berlin"
  }
}
