{
  "geometry": {
    "type": "Point",
    "coordinates": [
      31.35,
      26.833333
    ]
  },
  "type": "Feature",
  "properties": {
    "hierarchy": [
      "tgn:7528028",
      "tgn:7001242",
      "tgn:7016833",
      "tgn:7000124",
      "tgn:7029392"
    ],
    "placetype": [
      "aat:300005926"
    ],
    "name:en": "Sīdī 'Abd Allāh",
    "id": 7528028
  }
}
