{
  "geometry": {
    "type": "Point",
    "coordinates": [
      -74.5667,
      43.2833
    ]
  },
  "type": "Feature",
  "properties": {
    "hierarchy": [
      "tgn:2449267",
      "tgn:1000001",
      "tgn:7012149",
      "tgn:1002440",
      "tgn:7007568",
      "tgn:7029392"
    ],
    "placetype": [
      "aat:300008706"
    ],
    "id": 2449267,
    "name:xx": "Limestone Creek"
  }
}
