{
  "geometry": {
    "type": "Point",
    "coordinates": [
      -131.9667,
      55.55
    ]
  },
  "type": "Feature",
  "properties": {
    "hierarchy": [
      "tgn:2493345",
      "tgn:7006450",
      "tgn:1000001",
      "tgn:7012149",
      "tgn:2000082",
      "tgn:7029392"
    ],
    "placetype": [
      "aat:300008798"
    ],
    "id": 2493345,
    "name:xx": "Marr, Mount"
  }
}
