{
  "geometry": {
    "type": "Point",
    "coordinates": [
      -85.2333,
      37.8833
    ]
  },
  "type": "Feature",
  "properties": {
    "hierarchy": [
      "tgn:2421530",
      "tgn:1000001",
      "tgn:7012149",
      "tgn:7007255",
      "tgn:7029392"
    ],
    "placetype": [
      "aat:300008699"
    ],
    "id": 2421530,
    "name:xx": "Jessie Run"
  }
}
