{
  "geometry": {
    "type": "Point",
    "coordinates": [
      -54.9833,
      -15.5167
    ]
  },
  "type": "Feature",
  "properties": {
    "hierarchy": [
      "tgn:1021241",
      "tgn:7006260",
      "tgn:7002454",
      "tgn:1000047",
      "tgn:1000002",
      "tgn:7029392"
    ],
    "placetype": [
      "aat:300008347"
    ],
    "id": 1021241,
    "name:xx": "Coronel Ponce"
  }
}
