{
  "geometry": {
    "type": "Point",
    "coordinates": [
      -85.85,
      31.4667
    ]
  },
  "type": "Feature",
  "properties": {
    "hierarchy": [
      "tgn:2333557",
      "tgn:7002659",
      "tgn:1000001",
      "tgn:2000015",
      "tgn:7012149",
      "tgn:7029392"
    ],
    "placetype": [
      "aat:300008706"
    ],
    "id": 2333557,
    "name:xx": "Folsome Mill Creek"
  }
}
