{
  "geometry": {
    "type": "Point",
    "coordinates": [
      -78.0833,
      36.9167
    ]
  },
  "type": "Feature",
  "properties": {
    "hierarchy": [
      "tgn:2110680",
      "tgn:1000001",
      "tgn:7012149",
      "tgn:2002171",
      "tgn:7007919",
      "tgn:7029392"
    ],
    "placetype": [
      "aat:300008347",
      "aat:300387210"
    ],
    "id": 2110680,
    "name:xx": "Bishops Corner"
  }
}
