{
  "geometry": {
    "type": "Point",
    "coordinates": [
      21.9667,
      60.1667
    ]
  },
  "type": "Feature",
  "properties": {
    "hierarchy": [
      "tgn:1008271",
      "tgn:7024077",
      "tgn:1000003",
      "tgn:1000069",
      "tgn:7029392"
    ],
    "placetype": [
      "aat:300008791"
    ],
    "id": 1008271,
    "name:xx": "Nagu"
  }
}
