{
  "geometry": {
    "type": "Point",
    "coordinates": [
      -80.4167,
      39.3167
    ]
  },
  "type": "Feature",
  "properties": {
    "hierarchy": [
      "tgn:2118789",
      "tgn:1000001",
      "tgn:7012149",
      "tgn:2002267",
      "tgn:7013961",
      "tgn:7029392"
    ],
    "placetype": [
      "aat:300008347"
    ],
    "id": 2118789,
    "name:xx": "Katy Lick"
  }
}
