{
  "geometry": {
    "type": "Point",
    "coordinates": [
      10.1167,
      46.8667
    ]
  },
  "type": "Feature",
  "properties": {
    "hierarchy": [
      "tgn:1107156",
      "tgn:1000003",
      "tgn:7029392"
    ],
    "placetype": [
      "aat:300008798"
    ],
    "id": 1107156,
    "name:de": "Buin, Piz"
  }
}
