{
  "geometry": {
    "type": "Point",
    "coordinates": [
      -85.9667,
      44.0833
    ]
  },
  "type": "Feature",
  "properties": {
    "hierarchy": [
      "tgn:2451398",
      "tgn:1000001",
      "tgn:7012149",
      "tgn:2000970",
      "tgn:7007520",
      "tgn:7029392"
    ],
    "placetype": [
      "aat:300008680"
    ],
    "id": 2451398,
    "name:xx": "Little Bass Lake"
  }
}
