{
  "geometry": {
    "type": "Point",
    "coordinates": [
      79.070955,
      26.830668
    ]
  },
  "type": "Feature",
  "properties": {
    "hierarchy": [
      "tgn:7561028",
      "tgn:1000004",
      "tgn:7000198",
      "tgn:7016722",
      "tgn:7029392"
    ],
    "placetype": [
      "aat:300008347"
    ],
    "name:en": "Kripālpur",
    "id": 7561028
  }
}
