{
  "type": "FeatureCollection",
  "features": [
    {
      "geometry": {
        "type": "Point",
        "coordinates": [
          -123.9333,
          45.05
        ]
      },
      "type": "Feature",
      "properties": {
        "hierarchy": [
          "tgn:2638500",
          "tgn:1000001",
          "tgn:7012149",
          "tgn:7007708",
          "tgn:7029392"
        ],
        "placetype": [
          "aat:300008706"
        ],
        "id": 2638500,
        "name:xx": "Salmon Creek"
      }
    },
    {
      "geometry": {
        "type": "Point",
        "coordinates": [
          -122.95,
          45.85
        ]
      },
      "type": "Feature",
      "properties": {
        "hierarchy": [
          "tgn:2638501",
          "tgn:1000001",
          "tgn:1002293",
          "tgn:7012149",
          "tgn:7007708",
          "tgn:7029392"
        ],
        "placetype": [
          "aat:300008706"
        ],
        "id": 2638501,
        "name:xx": "Salmon Creek"
      }
    },
    {
      "geometry": {
        "type": "Point",
        "coordinates": [
          -123.9667,
          43.35
        ]
      },
      "type": "Feature",
      "properties": {
        "hierarchy": [
          "tgn:2638502",
          "tgn:1000001",
          "tgn:2001702",
          "tgn:7012149",
          "tgn:7007708",
          "tgn:7029392"
        ],
        "placetype": [
          "aat:300008706"
        ],
        "id": 2638502,
        "name:xx": "Salmon Creek"
      }
    },
    {
      "geometry": {
        "type": "Point",
        "coordinates": [
          -122.1,
          43.75
        ]
      },
      "type": "Feature",
      "properties": {
        "hierarchy": [
          "tgn:2638503",
          "tgn:1000001",
          "tgn:7012149",
          "tgn:2001716",
          "tgn:7007708",
          "tgn:7029392"
        ],
        "placetype": [
          "aat:300008706"
        ],
        "id": 2638503,
        "name:xx": "Salmon Creek"
      }
    },
    {
      "geometry": {
        "type": "Point",
        "coordinates": [
          -120.5833,
          44.3833
        ]
      },
      "type": "Feature",
      "properties": {
        "hierarchy": [
          "tgn:2638504",
          "tgn:1000001",
          "tgn:2001703",
          "tgn:7012149",
          "tgn:7007708",
          "tgn:7029392"
        ],
        "placetype": [
          "aat:300008706"
        ],
        "id": 2638504,
        "name:xx": "Salmon Creek"
      }
    },
    {
      "geometry": {
        "type": "Point",
        "coordinates": [
          -118.0167,
          44.7667
        ]
      },
      "type": "Feature",
      "properties": {
        "hierarchy": [
          "tgn:2638505",
          "tgn:7013349",
          "tgn:1000001",
          "tgn:7012149",
          "tgn:7007708",
          "tgn:7029392"
        ],
        "placetype": [
          "aat:300008706"
        ],
        "id": 2638505,
        "name:xx": "Salmon Creek"
      }
    },
    {
      "geometry": {
        "type": "Point",
        "coordinates": [
          -123.6333,
          44.3833
        ]
      },
      "type": "Feature",
      "properties": {
        "hierarchy": [
          "tgn:2638506",
          "tgn:1000001",
          "tgn:2001701",
          "tgn:7012149",
          "tgn:7007708",
          "tgn:7029392"
        ],
        "placetype": [
          "aat:300008706"
        ],
        "id": 2638506,
        "name:xx": "Salmon Creek"
      }
    },
    {
      "geometry": {
        "type": "Point",
        "coordinates": [
          -122.4,
          45.5333
        ]
      },
      "type": "Feature",
      "properties": {
        "hierarchy": [
          "tgn:2638507",
          "tgn:1000001",
          "tgn:7012149",
          "tgn:1002699",
          "tgn:7007708",
          "tgn:7029392"
        ],
        "placetype": [
          "aat:300008706"
        ],
        "id": 2638507,
        "name:xx": "Salmon Creek"
      }
    },
    {
      "geometry": {
        "type": "Point",
        "coordinates": [
          -79.1,
          41.5333
        ]
      },
      "type": "Feature",
      "properties": {
        "hierarchy": [
          "tgn:2638508",
          "tgn:1000001",
          "tgn:7012149",
          "tgn:1002378",
          "tgn:7007710",
          "tgn:7029392"
        ],
        "placetype": [
          "aat:300008706"
        ],
        "id": 2638508,
        "name:xx": "Salmon Creek"
      }
    },
    {
      "geometry": {
        "type": "Point",
        "coordinates": [
          -77.9333,
          37.55
        ]
      },
      "type": "Feature",
      "properties": {
        "hierarchy": [
          "tgn:2638509",
          "tgn:1000001",
          "tgn:7012149",
          "tgn:2002181",
          "tgn:7007919",
          "tgn:7029392"
        ],
        "placetype": [
          "aat:300008706"
        ],
        "id": 2638509,
        "name:xx": "Salmon Creek"
      }
    }
  ]
}
