{
  "geometry": {
    "type": "Point",
    "coordinates": [
      -97.8833,
      25.3667
    ]
  },
  "type": "Feature",
  "properties": {
    "hierarchy": [
      "tgn:1017483",
      "tgn:1000001",
      "tgn:7005597",
      "tgn:7005560",
      "tgn:7029392"
    ],
    "placetype": [
      "aat:300008347"
    ],
    "id": 1017483,
    "name:xx": "Francisco González Villarreal"
  }
}
