{
  "type": "FeatureCollection",
  "features": [
    {
      "geometry": {
        "type": "Point",
        "coordinates": [
          -101.733333,
          22.616667
        ]
      },
      "type": "Feature",
      "properties": {
        "hierarchy": [
          "tgn:7389740",
          "tgn:1000001",
          "tgn:7005594",
          "tgn:7005560",
          "tgn:7029392"
        ],
        "placetype": [
          "aat:300007783"
        ],
        "id": 7389740,
        "name:xx": "Salinas"
      }
    },
    {
      "geometry": {
        "type": "Point",
        "coordinates": [
          -112.766667,
          27.8
        ]
      },
      "type": "Feature",
      "properties": {
        "hierarchy": [
          "tgn:7389741",
          "tgn:1001836",
          "tgn:1000001",
          "tgn:7005560",
          "tgn:7029392"
        ],
        "placetype": [
          "aat:300008347"
        ],
        "id": 7389741,
        "name:xx": "Salinas"
      }
    },
    {
      "geometry": {
        "type": "Point",
        "coordinates": [
          -106.25,
          27.7
        ]
      },
      "type": "Feature",
      "properties": {
        "hierarchy": [
          "tgn:7389742",
          "tgn:7005581",
          "tgn:1000001",
          "tgn:7005560",
          "tgn:7029392"
        ],
        "placetype": [
          "aat:300008347"
        ],
        "id": 7389742,
        "name:xx": "Salinas"
      }
    },
    {
      "geometry": {
        "type": "Point",
        "coordinates": [
          -102.4,
          27.633333
        ]
      },
      "type": "Feature",
      "properties": {
        "hierarchy": [
          "tgn:7389743",
          "tgn:1001853",
          "tgn:1000001",
          "tgn:7005560",
          "tgn:7029392"
        ],
        "placetype": [
          "aat:300008347"
        ],
        "id": 7389743,
        "name:xx": "Salinas"
      }
    },
    {
      "geometry": {
        "type": "Point",
        "coordinates": [
          -109.833333,
          26.766667
        ]
      },
      "type": "Feature",
      "properties": {
        "hierarchy": [
          "tgn:7389744",
          "tgn:1000001",
          "tgn:1001960",
          "tgn:7005560",
          "tgn:7029392"
        ],
        "placetype": [
          "aat:300008347"
        ],
        "id": 7389744,
        "name:xx": "Salinas"
      }
    },
    {
      "geometry": {
        "type": "Point",
        "coordinates": [
          -98.816667,
          26.283333
        ]
      },
      "type": "Feature",
      "properties": {
        "hierarchy": [
          "tgn:7389745",
          "tgn:1000001",
          "tgn:7005597",
          "tgn:7005560",
          "tgn:7029392"
        ],
        "placetype": [
          "aat:300008347"
        ],
        "id": 7389745,
        "name:xx": "Salinas"
      }
    },
    {
      "geometry": {
        "type": "Point",
        "coordinates": [
          -99.166667,
          25.85
        ]
      },
      "type": "Feature",
      "properties": {
        "hierarchy": [
          "tgn:7389746",
          "tgn:1000001",
          "tgn:7005589",
          "tgn:7005560",
          "tgn:7029392"
        ],
        "placetype": [
          "aat:300008347"
        ],
        "id": 7389746,
        "name:xx": "Salinas"
      }
    },
    {
      "geometry": {
        "type": "Point",
        "coordinates": [
          -108.433333,
          25.266667
        ]
      },
      "type": "Feature",
      "properties": {
        "hierarchy": [
          "tgn:7389747",
          "tgn:1000001",
          "tgn:1001960",
          "tgn:7005560",
          "tgn:7029392"
        ],
        "placetype": [
          "aat:300008347"
        ],
        "id": 7389747,
        "name:xx": "Salinas"
      }
    },
    {
      "geometry": {
        "type": "Point",
        "coordinates": [
          -110.266667,
          24.316667
        ]
      },
      "type": "Feature",
      "properties": {
        "hierarchy": [
          "tgn:7389748",
          "tgn:1001836",
          "tgn:1000001",
          "tgn:7005560",
          "tgn:7029392"
        ],
        "placetype": [
          "aat:300008347"
        ],
        "id": 7389748,
        "name:xx": "Salinas"
      }
    },
    {
      "geometry": {
        "type": "Point",
        "coordinates": [
          -109.933333,
          24.033333
        ]
      },
      "type": "Feature",
      "properties": {
        "hierarchy": [
          "tgn:7389749",
          "tgn:1001836",
          "tgn:1000001",
          "tgn:7005560",
          "tgn:7029392"
        ],
        "placetype": [
          "aat:300008347"
        ],
        "id": 7389749,
        "name:xx": "Salinas"
      }
    }
  ]
}
