{
  "geometry": {
    "type": "Point",
    "coordinates": [
      -113.8333,
      47.9833
    ]
  },
  "type": "Feature",
  "properties": {
    "hierarchy": [
      "tgn:2666548",
      "tgn:1000001",
      "tgn:7012149",
      "tgn:7007524",
      "tgn:7029392"
    ],
    "placetype": [
      "aat:300008798"
    ],
    "id": 2666548,
    "name:xx": "Sixmile Mountain"
  }
}
