{
  "geometry": {
    "type": "Point",
    "coordinates": [
      30.71179,
      29.29918
    ]
  },
  "type": "Feature",
  "properties": {
    "hierarchy": [
      "tgn:1095520",
      "tgn:7001242",
      "tgn:7001105",
      "tgn:7016833",
      "tgn:7029392"
    ],
    "placetype": [
      "aat:300008347"
    ],
    "name:en": "Jaradū",
    "id": 1095520
  }
}
