{
  "geometry": {
    "type": "Point",
    "coordinates": [
      -81.7167,
      36.2167
    ]
  },
  "type": "Feature",
  "properties": {
    "hierarchy": [
      "tgn:2200270",
      "tgn:1000001",
      "tgn:7012149",
      "tgn:2001551",
      "tgn:7007709",
      "tgn:7029392"
    ],
    "placetype": [
      "aat:300008699"
    ],
    "id": 2200270,
    "name:xx": "Brushy Fork"
  }
}
