{
  "geometry": {
    "type": "Point",
    "coordinates": [
      112.7167,
      29.0167
    ]
  },
  "type": "Feature",
  "properties": {
    "hierarchy": [
      "tgn:1070588",
      "tgn:1000004",
      "tgn:7002079",
      "tgn:1000111",
      "tgn:7029392"
    ],
    "placetype": [
      "aat:300008347"
    ],
    "id": 1070588,
    "name:xx": "Nandashan"
  }
}
