{
  "geometry": {
    "type": "Point",
    "coordinates": [
      -119.7333,
      48.55
    ]
  },
  "type": "Feature",
  "properties": {
    "hierarchy": [
      "tgn:1002742",
      "tgn:1000001",
      "tgn:7012149",
      "tgn:7007920",
      "tgn:7029392"
    ],
    "placetype": [
      "aat:300387145",
      "aat:300000771"
    ],
    "id": 1002742,
    "name:xx": "Okanogan"
  }
}
