{
  "geometry": {
    "type": "Point",
    "coordinates": [
      -85.7167,
      39.7833
    ]
  },
  "type": "Feature",
  "properties": {
    "hierarchy": [
      "tgn:2619066",
      "tgn:1000001",
      "tgn:7012149",
      "tgn:1002447",
      "tgn:7007252",
      "tgn:7029392"
    ],
    "placetype": [
      "aat:300008347"
    ],
    "id": 2619066,
    "name:xx": "Riley"
  }
}
