{
  "type": "FeatureCollection",
  "features": [
    {
      "geometry": {
        "type": "Point",
        "coordinates": [
          120.674637,
          24.025407
        ]
      },
      "type": "Feature",
      "properties": {
        "hierarchy": [
          "tgn:7488570",
          "tgn:1000004",
          "tgn:7001009",
          "tgn:1000141",
          "tgn:7029392"
        ],
        "placetype": [
          "aat:300008347"
        ],
        "id": 7488570,
        "name:xx": "Nanshi"
      }
    },
    {
      "geometry": {
        "type": "Point",
        "coordinates": [
          120.545571,
          23.9863
        ]
      },
      "type": "Feature",
      "properties": {
        "hierarchy": [
          "tgn:7488571",
          "tgn:1000004",
          "tgn:7467799",
          "tgn:1000141",
          "tgn:7029392"
        ],
        "placetype": [
          "aat:300008347"
        ],
        "id": 7488571,
        "name:xx": "Nanshi"
      }
    },
    {
      "geometry": {
        "type": "Point",
        "coordinates": [
          120.176111,
          23.147222
        ]
      },
      "type": "Feature",
      "properties": {
        "hierarchy": [
          "tgn:7488572",
          "tgn:1000004",
          "tgn:7490934",
          "tgn:1000141",
          "tgn:7029392"
        ],
        "placetype": [
          "aat:300008347"
        ],
        "id": 7488572,
        "name:xx": "Nanshi"
      }
    },
    {
      "geometry": {
        "type": "Point",
        "coordinates": [
          120.803843,
          24.470902
        ]
      },
      "type": "Feature",
      "properties": {
        "hierarchy": [
          "tgn:7488574",
          "tgn:7487020",
          "tgn:1000004",
          "tgn:1000141",
          "tgn:7029392"
        ],
        "placetype": [
          "aat:300008347"
        ],
        "id": 7488574,
        "name:xx": "Longchuan"
      }
    },
    {
      "geometry": {
        "type": "Point",
        "coordinates": [
          121.190833,
          23.156389
        ]
      },
      "type": "Feature",
      "properties": {
        "hierarchy": [
          "tgn:7488576",
          "tgn:7001010",
          "tgn:1000004",
          "tgn:1000141",
          "tgn:7029392"
        ],
        "placetype": [
          "aat:300008347"
        ],
        "id": 7488576,
        "name:xx": "Longquan"
      }
    },
    {
      "geometry": {
        "type": "Point",
        "coordinates": [
          120.423611,
          22.953889
        ]
      },
      "type": "Feature",
      "properties": {
        "hierarchy": [
          "tgn:7488577",
          "tgn:7001004",
          "tgn:1000004",
          "tgn:1000141",
          "tgn:7029392"
        ],
        "placetype": [
          "aat:300008347"
        ],
        "id": 7488577,
        "name:xx": "Pizi"
      }
    },
    {
      "geometry": {
        "type": "Point",
        "coordinates": [
          120.999444,
          22.691389
        ]
      },
      "type": "Feature",
      "properties": {
        "hierarchy": [
          "tgn:7488578",
          "tgn:1000004",
          "tgn:7491221",
          "tgn:1000141",
          "tgn:7029392"
        ],
        "placetype": [
          "aat:300008347"
        ],
        "id": 7488578,
        "name:xx": "Longquan"
      }
    },
    {
      "geometry": {
        "type": "Point",
        "coordinates": [
          120.601,
          22.6714
        ]
      },
      "type": "Feature",
      "properties": {
        "hierarchy": [
          "tgn:7488579",
          "tgn:1000004",
          "tgn:7492971",
          "tgn:1000141",
          "tgn:7029392"
        ],
        "placetype": [
          "aat:300008347"
        ],
        "id": 7488579,
        "name:xx": "Longquan"
      }
    }
  ]
}
