{
  "geometry": {
    "type": "Point",
    "coordinates": [
      -79.5333,
      37.7333
    ]
  },
  "type": "Feature",
  "properties": {
    "hierarchy": [
      "tgn:2436679",
      "tgn:1000001",
      "tgn:7012149",
      "tgn:2002186",
      "tgn:7007919",
      "tgn:7029392"
    ],
    "placetype": [
      "aat:300008798"
    ],
    "id": 2436679,
    "name:xx": "Kiger Hill"
  }
}
