{
  "geometry": {
    "type": "Point",
    "coordinates": [
      -87.3333,
      34.3667
    ]
  },
  "type": "Feature",
  "properties": {
    "hierarchy": [
      "tgn:2348407",
      "tgn:7002659",
      "tgn:1000001",
      "tgn:7012149",
      "tgn:2000039",
      "tgn:7029392"
    ],
    "placetype": [
      "aat:300008746"
    ],
    "id": 2348407,
    "name:xx": "Giant Cricket Cave"
  }
}
