{
  "geometry": {
    "type": "Point",
    "coordinates": [
      -70.25,
      -18.35
    ]
  },
  "type": "Feature",
  "properties": {
    "hierarchy": [
      "tgn:7283524",
      "tgn:7002464",
      "tgn:1000049",
      "tgn:1000002",
      "tgn:7029392"
    ],
    "placetype": [
      "aat:300387200"
    ],
    "id": 7283524,
    "name:xx": "Pampalluta"
  }
}
