{
  "geometry": {
    "type": "Point",
    "coordinates": [
      31.266667,
      29.933333
    ]
  },
  "type": "Feature",
  "properties": {
    "hierarchy": [
      "tgn:7527198",
      "tgn:7001242",
      "tgn:7016833",
      "tgn:1001091",
      "tgn:7029392"
    ],
    "placetype": [
      "aat:300008347"
    ],
    "name:en": "Ţurá al Ḩajjārah",
    "id": 7527198
  }
}
