{
  "geometry": {
    "type": "Point",
    "coordinates": [
      -85.75,
      30.1833
    ]
  },
  "type": "Feature",
  "properties": {
    "hierarchy": [
      "tgn:2019636",
      "tgn:2000258",
      "tgn:1000001",
      "tgn:7012149",
      "tgn:7007240",
      "tgn:7029392"
    ],
    "placetype": [
      "aat:300387016"
    ],
    "id": 2019636,
    "name:xx": "Holiday Plaza"
  }
}
