{
  "geometry": {
    "type": "Point",
    "coordinates": [
      -114.7167,
      46.3333
    ]
  },
  "type": "Feature",
  "properties": {
    "hierarchy": [
      "tgn:2436586",
      "tgn:1000001",
      "tgn:7012149",
      "tgn:2000476",
      "tgn:7007250",
      "tgn:7029392"
    ],
    "placetype": [
      "aat:300008680"
    ],
    "id": 2436586,
    "name:xx": "Kidney Lake"
  }
}
