{
  "type": "FeatureCollection",
  "features": [
    {
      "geometry": {
        "type": "Point",
        "coordinates": [
          -85.0333,
          35.6333
        ]
      },
      "type": "Feature",
      "properties": {
        "hierarchy": [
          "tgn:2293210",
          "tgn:1000001",
          "tgn:2001840",
          "tgn:7012149",
          "tgn:7007825",
          "tgn:7029392"
        ],
        "placetype": [
          "aat:300008699"
        ],
        "id": 2293210,
        "name:xx": "Double Branch"
      }
    },
    {
      "geometry": {
        "type": "Point",
        "coordinates": [
          -83.75,
          35.7667
        ]
      },
      "type": "Feature",
      "properties": {
        "hierarchy": [
          "tgn:2293211",
          "tgn:1000001",
          "tgn:7012149",
          "tgn:7007825",
          "tgn:7029392"
        ],
        "placetype": [
          "aat:300008699"
        ],
        "id": 2293211,
        "name:xx": "Double Branch"
      }
    },
    {
      "geometry": {
        "type": "Point",
        "coordinates": [
          -87.4,
          36
        ]
      },
      "type": "Feature",
      "properties": {
        "hierarchy": [
          "tgn:2293212",
          "tgn:1000001",
          "tgn:7012149",
          "tgn:2001858",
          "tgn:7007825",
          "tgn:7029392"
        ],
        "placetype": [
          "aat:300008699"
        ],
        "id": 2293212,
        "name:xx": "Double Branch"
      }
    },
    {
      "geometry": {
        "type": "Point",
        "coordinates": [
          -95.2333,
          32.1
        ]
      },
      "type": "Feature",
      "properties": {
        "hierarchy": [
          "tgn:2293213",
          "tgn:1000001",
          "tgn:7012149",
          "tgn:1002263",
          "tgn:7007826",
          "tgn:7029392"
        ],
        "placetype": [
          "aat:300008699"
        ],
        "id": 2293213,
        "name:xx": "Double Branch"
      }
    },
    {
      "geometry": {
        "type": "Point",
        "coordinates": [
          -95.6,
          32.9167
        ]
      },
      "type": "Feature",
      "properties": {
        "hierarchy": [
          "tgn:2293214",
          "tgn:1000001",
          "tgn:7012149",
          "tgn:1003034",
          "tgn:7007826",
          "tgn:7029392"
        ],
        "placetype": [
          "aat:300008699"
        ],
        "id": 2293214,
        "name:xx": "Double Branch"
      }
    },
    {
      "geometry": {
        "type": "Point",
        "coordinates": [
          -93.8667,
          30.5
        ]
      },
      "type": "Feature",
      "properties": {
        "hierarchy": [
          "tgn:2293215",
          "tgn:1000001",
          "tgn:7012149",
          "tgn:2002047",
          "tgn:7007826",
          "tgn:7029392"
        ],
        "placetype": [
          "aat:300008699"
        ],
        "id": 2293215,
        "name:xx": "Double Branch"
      }
    },
    {
      "geometry": {
        "type": "Point",
        "coordinates": [
          -94.7167,
          30.6333
        ]
      },
      "type": "Feature",
      "properties": {
        "hierarchy": [
          "tgn:2293216",
          "tgn:1000001",
          "tgn:7012149",
          "tgn:1002795",
          "tgn:7007826",
          "tgn:7029392"
        ],
        "placetype": [
          "aat:300008699"
        ],
        "id": 2293216,
        "name:xx": "Double Branch"
      }
    },
    {
      "geometry": {
        "type": "Point",
        "coordinates": [
          -80.35,
          37.4833
        ]
      },
      "type": "Feature",
      "properties": {
        "hierarchy": [
          "tgn:2293217",
          "tgn:1000001",
          "tgn:7012149",
          "tgn:2002154",
          "tgn:7007919",
          "tgn:7029392"
        ],
        "placetype": [
          "aat:300008699"
        ],
        "id": 2293217,
        "name:xx": "Double Branch"
      }
    },
    {
      "geometry": {
        "type": "Point",
        "coordinates": [
          -78.8833,
          36.85
        ]
      },
      "type": "Feature",
      "properties": {
        "hierarchy": [
          "tgn:2293218",
          "tgn:1000001",
          "tgn:7012149",
          "tgn:2002166",
          "tgn:7007919",
          "tgn:7029392"
        ],
        "placetype": [
          "aat:300008699"
        ],
        "id": 2293218,
        "name:xx": "Double Branch"
      }
    },
    {
      "geometry": {
        "type": "Point",
        "coordinates": [
          -78.85,
          37.1167
        ]
      },
      "type": "Feature",
      "properties": {
        "hierarchy": [
          "tgn:2293219",
          "tgn:1000001",
          "tgn:7012149",
          "tgn:7007919",
          "tgn:7029392"
        ],
        "placetype": [
          "aat:300008699"
        ],
        "id": 2293219,
        "name:xx": "Double Branch"
      }
    }
  ]
}
