{
  "geometry": {
    "type": "Point",
    "coordinates": [
      -93.0667,
      16.05
    ]
  },
  "type": "Feature",
  "properties": {
    "hierarchy": [
      "tgn:1017088",
      "tgn:7005580",
      "tgn:1000001",
      "tgn:7005560",
      "tgn:7029392"
    ],
    "placetype": [
      "aat:300008347"
    ],
    "id": 1017088,
    "name:xx": "Buenavista Revolución Mexicana"
  }
}
