{
  "geometry": {
    "type": "Point",
    "coordinates": [
      -104.0333,
      50.9333
    ]
  },
  "type": "Feature",
  "properties": {
    "hierarchy": [
      "tgn:1015902",
      "tgn:7005685",
      "tgn:1000001",
      "tgn:7005805",
      "tgn:7029392"
    ],
    "placetype": [
      "aat:300008347"
    ],
    "id": 1015902,
    "name:xx": "Dysart"
  }
}
