{
  "geometry": {
    "type": "Point",
    "coordinates": [
      -80.3667,
      42.0167
    ]
  },
  "type": "Feature",
  "properties": {
    "hierarchy": [
      "tgn:2716564",
      "tgn:1000001",
      "tgn:7012149",
      "tgn:1002358",
      "tgn:7007710",
      "tgn:7029392"
    ],
    "placetype": [
      "aat:300132316"
    ],
    "id": 2716564,
    "name:xx": "The Mouth"
  }
}
