{
  "geometry": {
    "type": "Point",
    "coordinates": [
      -110.6833,
      33.4167
    ]
  },
  "type": "Feature",
  "properties": {
    "hierarchy": [
      "tgn:2211212",
      "tgn:1000001",
      "tgn:7006451",
      "tgn:2000093",
      "tgn:7012149",
      "tgn:7029392"
    ],
    "placetype": [
      "aat:300006191"
    ],
    "id": 2211212,
    "name:xx": "Butta Tank"
  }
}
