{
  "geometry": {
    "type": "Point",
    "coordinates": [
      82.9167,
      44.9167
    ]
  },
  "type": "Feature",
  "properties": {
    "hierarchy": [
      "tgn:1118937",
      "tgn:1000004",
      "tgn:7001745",
      "tgn:1000111",
      "tgn:7029392"
    ],
    "placetype": [
      "aat:300266556"
    ],
    "id": 1118937,
    "name:xx": "Ebinur Hu"
  }
}
