{
  "type": "FeatureCollection",
  "features": [
    {
      "geometry": {
        "type": "Point",
        "coordinates": [
          -112.7667,
          47.3333
        ]
      },
      "type": "Feature",
      "properties": {
        "hierarchy": [
          "tgn:2698370",
          "tgn:1000001",
          "tgn:7012149",
          "tgn:2001284",
          "tgn:7007524",
          "tgn:7029392"
        ],
        "placetype": [
          "aat:300008706"
        ],
        "id": 2698370,
        "name:xx": "Straight Creek"
      }
    },
    {
      "geometry": {
        "type": "Point",
        "coordinates": [
          -75.1333,
          39.1833
        ]
      },
      "type": "Feature",
      "properties": {
        "hierarchy": [
          "tgn:2698371",
          "tgn:1002309",
          "tgn:1000001",
          "tgn:7012149",
          "tgn:7007565",
          "tgn:7029392"
        ],
        "placetype": [
          "aat:300008706"
        ],
        "id": 2698371,
        "name:xx": "Straight Creek"
      }
    },
    {
      "geometry": {
        "type": "Point",
        "coordinates": [
          -83.15,
          35.5667
        ]
      },
      "type": "Feature",
      "properties": {
        "hierarchy": [
          "tgn:2698372",
          "tgn:1000001",
          "tgn:7012149",
          "tgn:2001503",
          "tgn:7007709",
          "tgn:7029392"
        ],
        "placetype": [
          "aat:300008706"
        ],
        "id": 2698372,
        "name:xx": "Straight Creek"
      }
    },
    {
      "geometry": {
        "type": "Point",
        "coordinates": [
          -82.3333,
          35.7833
        ]
      },
      "type": "Feature",
      "properties": {
        "hierarchy": [
          "tgn:2698373",
          "tgn:1000001",
          "tgn:2001473",
          "tgn:7012149",
          "tgn:7007709",
          "tgn:7029392"
        ],
        "placetype": [
          "aat:300008706"
        ],
        "id": 2698373,
        "name:xx": "Straight Creek"
      }
    },
    {
      "geometry": {
        "type": "Point",
        "coordinates": [
          -75.8333,
          36.3
        ]
      },
      "type": "Feature",
      "properties": {
        "hierarchy": [
          "tgn:2698374",
          "tgn:1000001",
          "tgn:7012149",
          "tgn:1002312",
          "tgn:7007709",
          "tgn:7029392"
        ],
        "placetype": [
          "aat:300008706"
        ],
        "id": 2698374,
        "name:xx": "Straight Creek"
      }
    },
    {
      "geometry": {
        "type": "Point",
        "coordinates": [
          -96.0833,
          34.0667
        ]
      },
      "type": "Feature",
      "properties": {
        "hierarchy": [
          "tgn:2698376",
          "tgn:1000001",
          "tgn:2001629",
          "tgn:7012149",
          "tgn:7007707",
          "tgn:7029392"
        ],
        "placetype": [
          "aat:300008706"
        ],
        "id": 2698376,
        "name:xx": "Straight Creek"
      }
    },
    {
      "geometry": {
        "type": "Point",
        "coordinates": [
          -122.6667,
          44.1667
        ]
      },
      "type": "Feature",
      "properties": {
        "hierarchy": [
          "tgn:2698377",
          "tgn:1000001",
          "tgn:7012149",
          "tgn:2001716",
          "tgn:7007708",
          "tgn:7029392"
        ],
        "placetype": [
          "aat:300008706"
        ],
        "id": 2698377,
        "name:xx": "Straight Creek"
      }
    },
    {
      "geometry": {
        "type": "Point",
        "coordinates": [
          -119.4667,
          44.6333
        ]
      },
      "type": "Feature",
      "properties": {
        "hierarchy": [
          "tgn:2698378",
          "tgn:1000001",
          "tgn:7012149",
          "tgn:2001708",
          "tgn:7007708",
          "tgn:7029392"
        ],
        "placetype": [
          "aat:300008706"
        ],
        "id": 2698378,
        "name:xx": "Straight Creek"
      }
    },
    {
      "geometry": {
        "type": "Point",
        "coordinates": [
          -122.9167,
          43.0833
        ]
      },
      "type": "Feature",
      "properties": {
        "hierarchy": [
          "tgn:2698379",
          "tgn:1000001",
          "tgn:7012149",
          "tgn:2001706",
          "tgn:7007708",
          "tgn:7029392"
        ],
        "placetype": [
          "aat:300008706"
        ],
        "id": 2698379,
        "name:xx": "Straight Creek"
      }
    }
  ]
}
