{
  "geometry": {
    "type": "Point",
    "coordinates": [
      -77.0833,
      -12.0333
    ]
  },
  "type": "Feature",
  "properties": {
    "hierarchy": [
      "tgn:1024481",
      "tgn:1000670",
      "tgn:1000002",
      "tgn:1000056",
      "tgn:7029392"
    ],
    "placetype": [
      "aat:300008347"
    ],
    "id": 1024481,
    "name:xx": "Conderilla Señor"
  }
}
