{
  "geometry": {
    "type": "Point",
    "coordinates": [
      -90.0833,
      37.5333
    ]
  },
  "type": "Feature",
  "properties": {
    "hierarchy": [
      "tgn:2462501",
      "tgn:1000001",
      "tgn:7012149",
      "tgn:7007523",
      "tgn:7029392"
    ],
    "placetype": [
      "aat:300008706"
    ],
    "id": 2462501,
    "name:xx": "Little Whitewater Creek"
  }
}
