{
  "geometry": {
    "type": "Point",
    "coordinates": [
      -122.4167,
      46.4667
    ]
  },
  "type": "Feature",
  "properties": {
    "hierarchy": [
      "tgn:2201013",
      "tgn:1000001",
      "tgn:7012149",
      "tgn:1002594",
      "tgn:7007920",
      "tgn:7029392"
    ],
    "placetype": [
      "aat:300008680"
    ],
    "id": 2201013,
    "name:xx": "Bryant, Lake"
  }
}
