{
  "geometry": {
    "type": "Point",
    "coordinates": [
      -80.1333,
      40.35
    ]
  },
  "type": "Feature",
  "properties": {
    "hierarchy": [
      "tgn:2090925",
      "tgn:7013272",
      "tgn:1000001",
      "tgn:7012149",
      "tgn:7007710",
      "tgn:7029392"
    ],
    "placetype": [
      "aat:300008347"
    ],
    "id": 2090925,
    "name:xx": "Morgan"
  }
}
