{
  "geometry": {
    "type": "Point",
    "coordinates": [
      -98.3667,
      31.9833
    ]
  },
  "type": "Feature",
  "properties": {
    "hierarchy": [
      "tgn:2533582",
      "tgn:1000001",
      "tgn:7012149",
      "tgn:2001962",
      "tgn:7007826",
      "tgn:7029392"
    ],
    "placetype": [
      "aat:300008706"
    ],
    "id": 2533582,
    "name:xx": "Mustang Creek"
  }
}
