{
  "geometry": {
    "type": "Point",
    "coordinates": [
      -87.4667,
      32.7833
    ]
  },
  "type": "Feature",
  "properties": {
    "hierarchy": [
      "tgn:2416109",
      "tgn:7002659",
      "tgn:1000001",
      "tgn:7012149",
      "tgn:2000032",
      "tgn:7029392"
    ],
    "placetype": [
      "aat:300006191"
    ],
    "id": 2416109,
    "name:xx": "J B Thomas Lake"
  }
}
