{
  "type": "FeatureCollection",
  "features": [
    {
      "geometry": {
        "type": "Point",
        "coordinates": [
          -71.1167,
          -17.8167
        ]
      },
      "type": "Feature",
      "properties": {
        "hierarchy": [
          "tgn:7026150",
          "tgn:1000773",
          "tgn:1000002",
          "tgn:1000056",
          "tgn:7029392"
        ],
        "placetype": [
          "aat:300266554"
        ],
        "id": 7026150,
        "name:xx": "Tacahuay, Quebrada"
      }
    },
    {
      "geometry": {
        "type": "Point",
        "coordinates": [
          132.1833,
          61.8667
        ]
      },
      "type": "Feature",
      "properties": {
        "hierarchy": [
          "tgn:7026152",
          "tgn:1000004",
          "tgn:7011528",
          "tgn:7002435",
          "tgn:7029392"
        ],
        "placetype": [
          "aat:300008347"
        ],
        "id": 7026152,
        "name:xx": "Diring"
      }
    },
    {
      "geometry": {
        "type": "Point",
        "coordinates": [
          26.6333,
          47.4
        ]
      },
      "type": "Feature",
      "properties": {
        "hierarchy": [
          "tgn:7026153",
          "tgn:1000003",
          "tgn:7002700",
          "tgn:1000091",
          "tgn:7029392"
        ],
        "placetype": [
          "aat:300008347"
        ],
        "id": 7026153,
        "name:xx": "Probota"
      }
    },
    {
      "geometry": {
        "type": "Point",
        "coordinates": [
          26.6,
          47.4333
        ]
      },
      "type": "Feature",
      "properties": {
        "hierarchy": [
          "tgn:7026154",
          "tgn:1000003",
          "tgn:7002700",
          "tgn:1000091",
          "tgn:7029392"
        ],
        "placetype": [
          "aat:300008347"
        ],
        "id": 7026154,
        "name:xx": "Dolhasca"
      }
    },
    {
      "geometry": {
        "type": "Point",
        "coordinates": [
          8.6,
          47.5833
        ]
      },
      "type": "Feature",
      "properties": {
        "hierarchy": [
          "tgn:7026155",
          "tgn:1000003",
          "tgn:7003765",
          "tgn:7011731",
          "tgn:7029392"
        ],
        "placetype": [
          "aat:300008347"
        ],
        "id": 7026155,
        "name:xx": "Flaach"
      }
    },
    {
      "geometry": {
        "type": "Point",
        "coordinates": [
          29.211574,
          40.195692
        ]
      },
      "type": "Feature",
      "properties": {
        "hierarchy": [
          "tgn:7026158",
          "tgn:1001442",
          "tgn:1000004",
          "tgn:7018453",
          "tgn:1000144",
          "tgn:7029392"
        ],
        "placetype": [
          "aat:300000810",
          "aat:300019275",
          "aat:300387305",
          "aat:300387006"
        ],
        "id": 7026158,
        "name:xx": "Kestel"
      }
    },
    {
      "geometry": {
        "type": "Point",
        "coordinates": [
          -3.266667,
          51.560833
        ]
      },
      "type": "Feature",
      "properties": {
        "hierarchy": [
          "tgn:7026159",
          "tgn:7002443",
          "tgn:1000003",
          "tgn:7018963",
          "tgn:7008591",
          "tgn:7029392"
        ],
        "placetype": [
          "aat:300008347",
          "aat:300008372"
        ],
        "name:en": "Nantgarw",
        "id": 7026159
      }
    }
  ]
}
