{
  "geometry": {
    "type": "Point",
    "coordinates": [
      -81.3833,
      37.9667
    ]
  },
  "type": "Feature",
  "properties": {
    "hierarchy": [
      "tgn:2124629",
      "tgn:1000001",
      "tgn:7012149",
      "tgn:2002270",
      "tgn:7013961",
      "tgn:7029392"
    ],
    "placetype": [
      "aat:300008706"
    ],
    "id": 2124629,
    "name:xx": "Abbott Creek"
  }
}
