{
  "geometry": {
    "type": "Point",
    "coordinates": [
      -164.5833,
      60.9667
    ]
  },
  "type": "Feature",
  "properties": {
    "hierarchy": [
      "tgn:2432284",
      "tgn:7006450",
      "tgn:1000001",
      "tgn:7012149",
      "tgn:7029392"
    ],
    "placetype": [
      "aat:300008707"
    ],
    "id": 2432284,
    "name:xx": "Kealavik River"
  }
}
