{
  "geometry": {
    "type": "Point",
    "coordinates": [
      21.14528,
      42.11306
    ]
  },
  "type": "Feature",
  "properties": {
    "hierarchy": [
      "tgn:7594334",
      "tgn:1000003",
      "tgn:7006667",
      "tgn:7029392"
    ],
    "placetype": [
      "aat:300387064",
      "aat:300265612"
    ],
    "id": 7594334,
    "name:xx": "Jegunovce"
  }
}
