{
  "geometry": {
    "type": "Point",
    "coordinates": [
      -103.6333,
      30.25
    ]
  },
  "type": "Feature",
  "properties": {
    "hierarchy": [
      "tgn:2152642",
      "tgn:1000001",
      "tgn:2001945",
      "tgn:7012149",
      "tgn:7007826",
      "tgn:7029392"
    ],
    "placetype": [
      "aat:300006191"
    ],
    "id": 2152642,
    "name:xx": "Baylor Tank"
  }
}
