{
  "geometry": {
    "type": "Point",
    "coordinates": [
      -80.25,
      38.7667
    ]
  },
  "type": "Feature",
  "properties": {
    "hierarchy": [
      "tgn:2614284",
      "tgn:1000001",
      "tgn:7012149",
      "tgn:2002298",
      "tgn:7013961",
      "tgn:7029392"
    ],
    "placetype": [
      "aat:300008699"
    ],
    "id": 2614284,
    "name:xx": "Reger Run"
  }
}
