{
  "geometry": {
    "type": "Point",
    "coordinates": [
      -61.8167,
      17.7167
    ]
  },
  "type": "Feature",
  "properties": {
    "hierarchy": [
      "tgn:7005886",
      "tgn:7005328",
      "tgn:7593454",
      "tgn:1000009",
      "tgn:1000001",
      "tgn:7029392"
    ],
    "placetype": [
      "aat:300008347"
    ],
    "id": 7005886,
    "name:xx": "Codrington"
  }
}
