{
  "type": "FeatureCollection",
  "features": [
    {
      "geometry": {
        "type": "Point",
        "coordinates": [
          -119.6167,
          38.8667
        ]
      },
      "type": "Feature",
      "properties": {
        "hierarchy": [
          "tgn:1002340",
          "tgn:1000001",
          "tgn:7012149",
          "tgn:7007526",
          "tgn:7029392"
        ],
        "placetype": [
          "aat:300387145",
          "aat:300000771"
        ],
        "id": 1002340,
        "name:xx": "Douglas"
      }
    },
    {
      "geometry": {
        "type": "Point",
        "coordinates": [
          -70.75,
          41.3333
        ]
      },
      "type": "Feature",
      "properties": {
        "hierarchy": [
          "tgn:1002344",
          "tgn:1000001",
          "tgn:7012149",
          "tgn:7007517",
          "tgn:7029392"
        ],
        "placetype": [
          "aat:300387145",
          "aat:300000771"
        ],
        "id": 1002344,
        "name:xx": "Dukes"
      }
    },
    {
      "geometry": {
        "type": "Point",
        "coordinates": [
          -73.7333,
          41.7667
        ]
      },
      "type": "Feature",
      "properties": {
        "hierarchy": [
          "tgn:1002347",
          "tgn:1000001",
          "tgn:7012149",
          "tgn:7007568",
          "tgn:7029392"
        ],
        "placetype": [
          "aat:300387145",
          "aat:300000771"
        ],
        "id": 1002347,
        "name:xx": "Dutchess"
      }
    },
    {
      "geometry": {
        "type": "Point",
        "coordinates": [
          -88.5833,
          39.05
        ]
      },
      "type": "Feature",
      "properties": {
        "hierarchy": [
          "tgn:1002349",
          "tgn:1000001",
          "tgn:7012149",
          "tgn:7007251",
          "tgn:7029392"
        ],
        "placetype": [
          "aat:300387145",
          "aat:300000771"
        ],
        "id": 1002349,
        "name:xx": "Effingham"
      }
    }
  ]
}
