{
  "geometry": {
    "type": "Point",
    "coordinates": [
      75.629159,
      28.228499
    ]
  },
  "type": "Feature",
  "properties": {
    "hierarchy": [
      "tgn:7582634",
      "tgn:1000004",
      "tgn:7000198",
      "tgn:7016788",
      "tgn:7029392"
    ],
    "placetype": [
      "aat:300008347"
    ],
    "name:en": "Āka Ki Dhāni",
    "id": 7582634
  }
}
