{
  "geometry": {
    "type": "Point",
    "coordinates": [
      -113.1333,
      34.4333
    ]
  },
  "type": "Feature",
  "properties": {
    "hierarchy": [
      "tgn:2703019",
      "tgn:1000001",
      "tgn:7006451",
      "tgn:7012149",
      "tgn:2000103",
      "tgn:7029392"
    ],
    "placetype": [
      "aat:300000390"
    ],
    "id": 2703019,
    "name:xx": "Sultan Mine"
  }
}
