{
  "geometry": {
    "type": "Point",
    "coordinates": [
      -89.0333,
      35.3667
    ]
  },
  "type": "Feature",
  "properties": {
    "hierarchy": [
      "tgn:2733228",
      "tgn:1000001",
      "tgn:7012149",
      "tgn:2001871",
      "tgn:7007825",
      "tgn:7029392"
    ],
    "placetype": [
      "aat:300008680"
    ],
    "id": 2733228,
    "name:xx": "Turkey Pond"
  }
}
