{
  "geometry": {
    "type": "Point",
    "coordinates": [
      -81.9167,
      37.1167
    ]
  },
  "type": "Feature",
  "properties": {
    "hierarchy": [
      "tgn:2582280",
      "tgn:1000001",
      "tgn:7012149",
      "tgn:2002188",
      "tgn:7007919",
      "tgn:7029392"
    ],
    "placetype": [
      "aat:300008706"
    ],
    "id": 2582280,
    "name:xx": "Pine Creek"
  }
}
