{
  "geometry": {
    "type": "Point",
    "coordinates": [
      -75.5167,
      40.6333
    ]
  },
  "type": "Feature",
  "properties": {
    "hierarchy": [
      "tgn:2092893",
      "tgn:1000001",
      "tgn:7012149",
      "tgn:1002586",
      "tgn:7007710",
      "tgn:7029392"
    ],
    "placetype": [
      "aat:300387016"
    ],
    "id": 2092893,
    "name:xx": "Seiple"
  }
}
