{
  "type": "FeatureCollection",
  "features": [
    {
      "geometry": {
        "type": "Point",
        "coordinates": [
          -116.15,
          32.116667
        ]
      },
      "type": "Feature",
      "properties": {
        "hierarchy": [
          "tgn:7393280",
          "tgn:1001835",
          "tgn:1000001",
          "tgn:7005560",
          "tgn:7029392"
        ],
        "placetype": [
          "aat:300000241"
        ],
        "id": 7393280,
        "name:xx": "Rancho San Juan de Dios"
      }
    },
    {
      "geometry": {
        "type": "Point",
        "coordinates": [
          -112.916667,
          30.95
        ]
      },
      "type": "Feature",
      "properties": {
        "hierarchy": [
          "tgn:7393281",
          "tgn:1000001",
          "tgn:1001960",
          "tgn:7005560",
          "tgn:7029392"
        ],
        "placetype": [
          "aat:300000241"
        ],
        "id": 7393281,
        "name:xx": "Rancho San Juan de Dios"
      }
    },
    {
      "geometry": {
        "type": "Point",
        "coordinates": [
          -110.366667,
          30.7
        ]
      },
      "type": "Feature",
      "properties": {
        "hierarchy": [
          "tgn:7393282",
          "tgn:1000001",
          "tgn:1001960",
          "tgn:7005560",
          "tgn:7029392"
        ],
        "placetype": [
          "aat:300000241"
        ],
        "id": 7393282,
        "name:xx": "Rancho San Juán de Diós"
      }
    },
    {
      "geometry": {
        "type": "Point",
        "coordinates": [
          -115.1,
          30.15
        ]
      },
      "type": "Feature",
      "properties": {
        "hierarchy": [
          "tgn:7393283",
          "tgn:1001835",
          "tgn:1000001",
          "tgn:7005560",
          "tgn:7029392"
        ],
        "placetype": [
          "aat:300008795"
        ],
        "id": 7393283,
        "name:xx": "San Juan De Dios, Cerro"
      }
    },
    {
      "geometry": {
        "type": "Point",
        "coordinates": [
          -115.783333,
          30.033333
        ]
      },
      "type": "Feature",
      "properties": {
        "hierarchy": [
          "tgn:7393284",
          "tgn:1001835",
          "tgn:1000001",
          "tgn:7005560",
          "tgn:7029392"
        ],
        "placetype": [
          "aat:300008699"
        ],
        "id": 7393284,
        "name:xx": "San Juan de Dios, Arroyo"
      }
    },
    {
      "geometry": {
        "type": "Point",
        "coordinates": [
          -116.166667,
          32.132778
        ]
      },
      "type": "Feature",
      "properties": {
        "hierarchy": [
          "tgn:7393285",
          "tgn:1001835",
          "tgn:1000001",
          "tgn:7005560",
          "tgn:7029392"
        ],
        "placetype": [
          "aat:300008347"
        ],
        "id": 7393285,
        "name:xx": "San Juan de Dios"
      }
    },
    {
      "geometry": {
        "type": "Point",
        "coordinates": [
          -115.2,
          30.133333
        ]
      },
      "type": "Feature",
      "properties": {
        "hierarchy": [
          "tgn:7393286",
          "tgn:1001835",
          "tgn:1000001",
          "tgn:7005560",
          "tgn:7029392"
        ],
        "placetype": [
          "aat:300008347"
        ],
        "id": 7393286,
        "name:xx": "San Juan de Dios"
      }
    },
    {
      "geometry": {
        "type": "Point",
        "coordinates": [
          -107.916667,
          26.933333
        ]
      },
      "type": "Feature",
      "properties": {
        "hierarchy": [
          "tgn:7393287",
          "tgn:7005581",
          "tgn:1000001",
          "tgn:7005560",
          "tgn:7029392"
        ],
        "placetype": [
          "aat:300008347"
        ],
        "id": 7393287,
        "name:xx": "San Juan de Dios"
      }
    },
    {
      "geometry": {
        "type": "Point",
        "coordinates": [
          -100.656111,
          24.591111
        ]
      },
      "type": "Feature",
      "properties": {
        "hierarchy": [
          "tgn:7393288",
          "tgn:1000001",
          "tgn:7005589",
          "tgn:7005560",
          "tgn:7029392"
        ],
        "placetype": [
          "aat:300008347"
        ],
        "id": 7393288,
        "name:es": "San Juan de Dios"
      }
    },
    {
      "geometry": {
        "type": "Point",
        "coordinates": [
          -104.666667,
          24.1
        ]
      },
      "type": "Feature",
      "properties": {
        "hierarchy": [
          "tgn:7393289",
          "tgn:7005583",
          "tgn:1000001",
          "tgn:7005560",
          "tgn:7029392"
        ],
        "placetype": [
          "aat:300008347"
        ],
        "id": 7393289,
        "name:xx": "San Juan de Dios"
      }
    }
  ]
}
