{
  "geometry": {
    "type": "Point",
    "coordinates": [
      -94.8333,
      46.7167
    ]
  },
  "type": "Feature",
  "properties": {
    "hierarchy": [
      "tgn:2407229",
      "tgn:1000001",
      "tgn:7012149",
      "tgn:2001078",
      "tgn:7007521",
      "tgn:7029392"
    ],
    "placetype": [
      "aat:300008863"
    ],
    "id": 2407229,
    "name:xx": "Huntersville State Forest"
  }
}
