{
  "geometry": {
    "type": "Point",
    "coordinates": [
      -121.0833,
      46.4167
    ]
  },
  "type": "Feature",
  "properties": {
    "hierarchy": [
      "tgn:2675071",
      "tgn:1000001",
      "tgn:7012149",
      "tgn:1003042",
      "tgn:7007920",
      "tgn:7029392"
    ],
    "placetype": [
      "aat:300008761"
    ],
    "id": 2675071,
    "name:xx": "Soda Springs Canyon"
  }
}
