{
  "geometry": {
    "type": "Point",
    "coordinates": [
      -123.3833,
      43.1667
    ]
  },
  "type": "Feature",
  "properties": {
    "hierarchy": [
      "tgn:2462099",
      "tgn:1000001",
      "tgn:7012149",
      "tgn:2001706",
      "tgn:7007708",
      "tgn:7029392"
    ],
    "placetype": [
      "aat:300008761"
    ],
    "id": 2462099,
    "name:xx": "Little Valley"
  }
}
