{
  "geometry": {
    "type": "Point",
    "coordinates": [
      89.95,
      23.8667
    ]
  },
  "type": "Feature",
  "properties": {
    "hierarchy": [
      "tgn:1065798",
      "tgn:7000189",
      "tgn:1000004",
      "tgn:1000105",
      "tgn:7029392"
    ],
    "placetype": [
      "aat:300008347"
    ],
    "id": 1065798,
    "name:xx": "Mānikganj"
  }
}
