{
  "geometry": {
    "type": "Point",
    "coordinates": [
      20.75,
      50.75
    ]
  },
  "type": "Feature",
  "properties": {
    "hierarchy": [
      "tgn:7024129",
      "tgn:1000003",
      "tgn:7006366",
      "tgn:7029392"
    ],
    "placetype": [
      "aat:300387064",
      "aat:300235112"
    ],
    "id": 7024129,
    "name:xx": "Świe̜tokrzyskie"
  }
}
