{
  "geometry": {
    "type": "Point",
    "coordinates": [
      2.3167,
      48.85
    ]
  },
  "type": "Feature",
  "properties": {
    "hierarchy": [
      "tgn:1102936",
      "tgn:1000003",
      "tgn:7002883",
      "tgn:1000070",
      "tgn:7008038",
      "tgn:7029392"
    ],
    "placetype": [
      "aat:300008187"
    ],
    "id": 1102936,
    "name:xx": "Luxembourg, Jardin du"
  }
}
