{
  "geometry": {
    "type": "Point",
    "coordinates": [
      -91.3167,
      44.75
    ]
  },
  "type": "Feature",
  "properties": {
    "hierarchy": [
      "tgn:2600989",
      "tgn:1000001",
      "tgn:2002320",
      "tgn:7012149",
      "tgn:7007922",
      "tgn:7029392"
    ],
    "placetype": [
      "aat:300008761"
    ],
    "id": 2600989,
    "name:xx": "Pumpkin Valley"
  }
}
