{
  "geometry": {
    "type": "Point",
    "coordinates": [
      -99.8667,
      39.0167
    ]
  },
  "type": "Feature",
  "properties": {
    "hierarchy": [
      "tgn:2037288",
      "tgn:1000001",
      "tgn:7012149",
      "tgn:2000757",
      "tgn:7007254",
      "tgn:7029392"
    ],
    "placetype": [
      "aat:300008347"
    ],
    "id": 2037288,
    "name:xx": "WaKeeney"
  }
}
