{
  "type": "FeatureCollection",
  "features": [
    {
      "geometry": {
        "type": "Point",
        "coordinates": [
          10.166667,
          51
        ]
      },
      "type": "Feature",
      "properties": {
        "hierarchy": [
          "tgn:7201650",
          "tgn:1000003",
          "tgn:7003689",
          "tgn:7000084",
          "tgn:7029392"
        ],
        "placetype": [
          "aat:300008057"
        ],
        "id": 7201650,
        "name:xx": "Ruine Brandenburg"
      }
    },
    {
      "geometry": {
        "type": "Point",
        "coordinates": [
          13.5,
          52.5
        ]
      },
      "type": "Feature",
      "properties": {
        "hierarchy": [
          "tgn:7201651",
          "tgn:1000003",
          "tgn:7594165",
          "tgn:7000084",
          "tgn:7029392"
        ],
        "placetype": [
          "aat:300387064"
        ],
        "id": 7201651,
        "name:xx": "Land Brandenburg"
      }
    },
    {
      "geometry": {
        "type": "Point",
        "coordinates": [
          14,
          53
        ]
      },
      "type": "Feature",
      "properties": {
        "hierarchy": [
          "tgn:7201652",
          "tgn:1000003",
          "tgn:7594165",
          "tgn:7000084",
          "tgn:7029392"
        ],
        "placetype": [
          "aat:300387346"
        ],
        "id": 7201652,
        "name:xx": "Brandenburg"
      }
    },
    {
      "geometry": {
        "type": "Point",
        "coordinates": [
          6.15,
          50.7
        ]
      },
      "type": "Feature",
      "properties": {
        "hierarchy": [
          "tgn:7201654",
          "tgn:1000003",
          "tgn:7003677",
          "tgn:7000084",
          "tgn:7029392"
        ],
        "placetype": [
          "aat:300008347"
        ],
        "id": 7201654,
        "name:xx": "Brandenburg"
      }
    },
    {
      "geometry": {
        "type": "Point",
        "coordinates": [
          10.066667,
          48.233333
        ]
      },
      "type": "Feature",
      "properties": {
        "hierarchy": [
          "tgn:7201655",
          "tgn:7003692",
          "tgn:1000003",
          "tgn:7000084",
          "tgn:7029392"
        ],
        "placetype": [
          "aat:300008347"
        ],
        "id": 7201655,
        "name:xx": "Brandenburg"
      }
    },
    {
      "geometry": {
        "type": "Point",
        "coordinates": [
          9.183333,
          54.5
        ]
      },
      "type": "Feature",
      "properties": {
        "hierarchy": [
          "tgn:7201656",
          "tgn:1000003",
          "tgn:7003688",
          "tgn:7000084",
          "tgn:7029392"
        ],
        "placetype": [
          "aat:300000206"
        ],
        "id": 7201656,
        "name:xx": "Brandenburg"
      }
    },
    {
      "geometry": {
        "type": "Point",
        "coordinates": [
          9.166667,
          52.333333
        ]
      },
      "type": "Feature",
      "properties": {
        "hierarchy": [
          "tgn:7201657",
          "tgn:1000003",
          "tgn:7003676",
          "tgn:7000084",
          "tgn:7029392"
        ],
        "placetype": [
          "aat:300000206"
        ],
        "id": 7201657,
        "name:xx": "Brandenburg"
      }
    },
    {
      "geometry": {
        "type": "Point",
        "coordinates": [
          12.616667,
          53.35
        ]
      },
      "type": "Feature",
      "properties": {
        "hierarchy": [
          "tgn:7201658",
          "tgn:1000003",
          "tgn:7000094",
          "tgn:7000084",
          "tgn:7029392"
        ],
        "placetype": [
          "aat:300008903"
        ],
        "id": 7201658,
        "name:xx": "Brandenbruch"
      }
    },
    {
      "geometry": {
        "type": "Point",
        "coordinates": [
          6.416667,
          50.7
        ]
      },
      "type": "Feature",
      "properties": {
        "hierarchy": [
          "tgn:7201659",
          "tgn:1000003",
          "tgn:7003677",
          "tgn:7000084",
          "tgn:7029392"
        ],
        "placetype": [
          "aat:300008347"
        ],
        "id": 7201659,
        "name:xx": "Brandenberg"
      }
    }
  ]
}
