{
  "type": "FeatureCollection",
  "features": [
    {
      "geometry": {
        "type": "Point",
        "coordinates": [
          -97.8,
          32.75
        ]
      },
      "type": "Feature",
      "properties": {
        "hierarchy": [
          "tgn:2563990",
          "tgn:1000001",
          "tgn:7012149",
          "tgn:1002771",
          "tgn:7007826",
          "tgn:7029392"
        ],
        "placetype": [
          "aat:300008798"
        ],
        "id": 2563990,
        "name:xx": "Oyster Hill"
      }
    },
    {
      "geometry": {
        "type": "Point",
        "coordinates": [
          -80.2167,
          32.7333
        ]
      },
      "type": "Feature",
      "properties": {
        "hierarchy": [
          "tgn:2563991",
          "tgn:1000001",
          "tgn:2001734",
          "tgn:7012149",
          "tgn:7007712",
          "tgn:7029392"
        ],
        "placetype": [
          "aat:300008706"
        ],
        "id": 2563991,
        "name:xx": "Oyster House Creek"
      }
    },
    {
      "geometry": {
        "type": "Point",
        "coordinates": [
          -76.5333,
          36.7833
        ]
      },
      "type": "Feature",
      "properties": {
        "hierarchy": [
          "tgn:2563992",
          "tgn:1000001",
          "tgn:7012149",
          "tgn:7022217",
          "tgn:7007919",
          "tgn:7029392"
        ],
        "placetype": [
          "aat:300008706"
        ],
        "id": 2563992,
        "name:xx": "Oyster House Creek"
      }
    },
    {
      "geometry": {
        "type": "Point",
        "coordinates": [
          -107.4,
          39.9167
        ]
      },
      "type": "Feature",
      "properties": {
        "hierarchy": [
          "tgn:2563994",
          "tgn:1000001",
          "tgn:7012149",
          "tgn:7007158",
          "tgn:2000243",
          "tgn:7029392"
        ],
        "placetype": [
          "aat:300008680"
        ],
        "id": 2563994,
        "name:xx": "Oyster Lake"
      }
    },
    {
      "geometry": {
        "type": "Point",
        "coordinates": [
          -86.2333,
          30.35
        ]
      },
      "type": "Feature",
      "properties": {
        "hierarchy": [
          "tgn:2563995",
          "tgn:1000001",
          "tgn:7012149",
          "tgn:2000290",
          "tgn:7007240",
          "tgn:7029392"
        ],
        "placetype": [
          "aat:300008680"
        ],
        "id": 2563995,
        "name:xx": "Oyster Lake"
      }
    },
    {
      "geometry": {
        "type": "Point",
        "coordinates": [
          -93.3833,
          29.7833
        ]
      },
      "type": "Feature",
      "properties": {
        "hierarchy": [
          "tgn:2563996",
          "tgn:1000001",
          "tgn:7020676",
          "tgn:7012149",
          "tgn:7007256",
          "tgn:7029392"
        ],
        "placetype": [
          "aat:300008680"
        ],
        "id": 2563996,
        "name:xx": "Oyster Lake"
      }
    },
    {
      "geometry": {
        "type": "Point",
        "coordinates": [
          -91.8667,
          29.5167
        ]
      },
      "type": "Feature",
      "properties": {
        "hierarchy": [
          "tgn:2563997",
          "tgn:1000001",
          "tgn:7012149",
          "tgn:2000876",
          "tgn:7007256",
          "tgn:7029392"
        ],
        "placetype": [
          "aat:300008680"
        ],
        "id": 2563997,
        "name:xx": "Oyster Lake"
      }
    },
    {
      "geometry": {
        "type": "Point",
        "coordinates": [
          -83.6833,
          42.8333
        ]
      },
      "type": "Feature",
      "properties": {
        "hierarchy": [
          "tgn:2563998",
          "tgn:1000001",
          "tgn:7012149",
          "tgn:1002737",
          "tgn:7007520",
          "tgn:7029392"
        ],
        "placetype": [
          "aat:300008680"
        ],
        "id": 2563998,
        "name:xx": "Oyster Lake"
      }
    },
    {
      "geometry": {
        "type": "Point",
        "coordinates": [
          -92.1,
          48.2167
        ]
      },
      "type": "Feature",
      "properties": {
        "hierarchy": [
          "tgn:2563999",
          "tgn:1000001",
          "tgn:7012149",
          "tgn:2001067",
          "tgn:7007521",
          "tgn:7029392"
        ],
        "placetype": [
          "aat:300008680"
        ],
        "id": 2563999,
        "name:xx": "Oyster Lake"
      }
    }
  ]
}
