{
  "geometry": {
    "type": "Point",
    "coordinates": [
      31.170957,
      31.035283
    ]
  },
  "type": "Feature",
  "properties": {
    "hierarchy": [
      "tgn:7530986",
      "tgn:7001242",
      "tgn:7016833",
      "tgn:7001312",
      "tgn:7029392"
    ],
    "placetype": [
      "aat:300008347"
    ],
    "name:en": "Manshīyat al Umarā'",
    "id": 7530986
  }
}
