{
  "type": "FeatureCollection",
  "features": [
    {
      "geometry": {
        "type": "Point",
        "coordinates": [
          -74.9667,
          40.75
        ]
      },
      "type": "Feature",
      "properties": {
        "hierarchy": [
          "tgn:2066430",
          "tgn:1000001",
          "tgn:1002985",
          "tgn:7012149",
          "tgn:7007565",
          "tgn:7029392"
        ],
        "placetype": [
          "aat:300008347"
        ],
        "id": 2066430,
        "name:xx": "Washington"
      }
    },
    {
      "geometry": {
        "type": "Point",
        "coordinates": [
          -74.8667,
          40.2833
        ]
      },
      "type": "Feature",
      "properties": {
        "hierarchy": [
          "tgn:2066431",
          "tgn:1000001",
          "tgn:1002657",
          "tgn:7012149",
          "tgn:7007565",
          "tgn:7029392"
        ],
        "placetype": [
          "aat:300008347"
        ],
        "id": 2066431,
        "name:xx": "Washington Crossing"
      }
    },
    {
      "geometry": {
        "type": "Point",
        "coordinates": [
          -74.5167,
          40.8
        ]
      },
      "type": "Feature",
      "properties": {
        "hierarchy": [
          "tgn:2066433",
          "tgn:1000001",
          "tgn:1002695",
          "tgn:7012149",
          "tgn:7007565",
          "tgn:7029392"
        ],
        "placetype": [
          "aat:300008347"
        ],
        "id": 2066433,
        "name:xx": "Washington Valley"
      }
    },
    {
      "geometry": {
        "type": "Point",
        "coordinates": [
          -74.45,
          40.6333
        ]
      },
      "type": "Feature",
      "properties": {
        "hierarchy": [
          "tgn:2066434",
          "tgn:1000001",
          "tgn:1002903",
          "tgn:7012149",
          "tgn:7007565",
          "tgn:7029392"
        ],
        "placetype": [
          "aat:300008347"
        ],
        "id": 2066434,
        "name:xx": "Watchung"
      }
    },
    {
      "geometry": {
        "type": "Point",
        "coordinates": [
          -74.8333,
          39.7167
        ]
      },
      "type": "Feature",
      "properties": {
        "hierarchy": [
          "tgn:2066438",
          "tgn:1002227",
          "tgn:1000001",
          "tgn:7012149",
          "tgn:7007565",
          "tgn:7029392"
        ],
        "placetype": [
          "aat:300008347"
        ],
        "id": 2066438,
        "name:xx": "Waterford Works"
      }
    },
    {
      "geometry": {
        "type": "Point",
        "coordinates": [
          -74.75,
          40.9
        ]
      },
      "type": "Feature",
      "properties": {
        "hierarchy": [
          "tgn:2066439",
          "tgn:1000001",
          "tgn:1002934",
          "tgn:7012149",
          "tgn:7007565",
          "tgn:7029392"
        ],
        "placetype": [
          "aat:300008347"
        ],
        "id": 2066439,
        "name:xx": "Waterloo"
      }
    }
  ]
}
