{
  "geometry": {
    "type": "Point",
    "coordinates": [
      -87.1833,
      33.35
    ]
  },
  "type": "Feature",
  "properties": {
    "hierarchy": [
      "tgn:2785676",
      "tgn:7002659",
      "tgn:1000001",
      "tgn:7012149",
      "tgn:2000036",
      "tgn:7029392"
    ],
    "placetype": [
      "aat:300000390"
    ],
    "id": 2785676,
    "name:xx": "Yolande Mine Number 2"
  }
}
