{
  "geometry": {
    "type": "Point",
    "coordinates": [
      -84.7167,
      44.4667
    ]
  },
  "type": "Feature",
  "properties": {
    "hierarchy": [
      "tgn:1116599",
      "tgn:1000001",
      "tgn:7012149",
      "tgn:2000991",
      "tgn:7007520",
      "tgn:7029392"
    ],
    "placetype": [
      "aat:300008680"
    ],
    "id": 1116599,
    "name:xx": "Higgins Lake"
  }
}
