{
  "geometry": {
    "type": "Point",
    "coordinates": [
      42.1667,
      38.9667
    ]
  },
  "type": "Feature",
  "properties": {
    "hierarchy": [
      "tgn:1108753",
      "tgn:1001437",
      "tgn:1000004",
      "tgn:7018455",
      "tgn:1000144",
      "tgn:7029392"
    ],
    "placetype": [
      "aat:300008795"
    ],
    "id": 1108753,
    "name:xx": "Bilican Daglari"
  }
}
