{
  "type": "FeatureCollection",
  "features": [
    {
      "geometry": {
        "type": "Point",
        "coordinates": [
          1.75,
          52.5
        ]
      },
      "type": "Feature",
      "properties": {
        "hierarchy": [
          "tgn:4004671",
          "tgn:7002445",
          "tgn:1000003",
          "tgn:7008185",
          "tgn:7008591",
          "tgn:7029392"
        ],
        "placetype": [
          "aat:300008347"
        ],
        "name:en": "Gunton",
        "id": 4004671
      }
    },
    {
      "geometry": {
        "type": "Point",
        "coordinates": [
          10.633333,
          49.616667
        ]
      },
      "type": "Feature",
      "properties": {
        "hierarchy": [
          "tgn:4004673",
          "tgn:7003669",
          "tgn:1000003",
          "tgn:7000084",
          "tgn:7029392"
        ],
        "placetype": [
          "aat:300008347"
        ],
        "id": 4004673,
        "name:xx": "Gutenstetten"
      }
    },
    {
      "geometry": {
        "type": "Point",
        "coordinates": [
          0.066667,
          52.616667
        ]
      },
      "type": "Feature",
      "properties": {
        "hierarchy": [
          "tgn:4004676",
          "tgn:7002445",
          "tgn:7011980",
          "tgn:1000003",
          "tgn:7008591",
          "tgn:7029392"
        ],
        "placetype": [
          "aat:300008347"
        ],
        "name:en": "Guyhirn",
        "id": 4004676
      }
    }
  ]
}
