{
  "geometry": {
    "type": "Point",
    "coordinates": [
      120.270107,
      23.13907
    ]
  },
  "type": "Feature",
  "properties": {
    "hierarchy": [
      "tgn:7486654",
      "tgn:1000004",
      "tgn:7490934",
      "tgn:1000141",
      "tgn:7029392"
    ],
    "placetype": [
      "aat:300008347"
    ],
    "id": 7486654,
    "name:xx": "Bai'erjia"
  }
}
