{
  "geometry": {
    "type": "Point",
    "coordinates": [
      73.5833,
      43.9167
    ]
  },
  "type": "Feature",
  "properties": {
    "hierarchy": [
      "tgn:1125809",
      "tgn:1000004",
      "tgn:1003362",
      "tgn:7014786",
      "tgn:7029392"
    ],
    "placetype": [
      "aat:300008707"
    ],
    "id": 1125809,
    "name:xx": "Kuragaty"
  }
}
