{
  "geometry": {
    "type": "Point",
    "coordinates": [
      118.8333,
      30.2833
    ]
  },
  "type": "Feature",
  "properties": {
    "hierarchy": [
      "tgn:1071849",
      "tgn:7002075",
      "tgn:1000004",
      "tgn:1000111",
      "tgn:7029392"
    ],
    "placetype": [
      "aat:300008347"
    ],
    "id": 1071849,
    "name:xx": "Shuiduixia"
  }
}
