{
  "geometry": {
    "type": "Point",
    "coordinates": [
      31.481753,
      31.159845
    ]
  },
  "type": "Feature",
  "properties": {
    "hierarchy": [
      "tgn:7536703",
      "tgn:7001242",
      "tgn:1001059",
      "tgn:7016833",
      "tgn:7029392"
    ],
    "placetype": [
      "aat:300008347"
    ],
    "name:en": "Kafr Badawāy al Jadīd",
    "id": 7536703
  }
}
