{
  "type": "FeatureCollection",
  "features": [
    {
      "geometry": {
        "type": "Point",
        "coordinates": [
          -105.1,
          37.9333
        ]
      },
      "type": "Feature",
      "properties": {
        "hierarchy": [
          "tgn:2272690",
          "tgn:1000001",
          "tgn:7012149",
          "tgn:2000219",
          "tgn:7007158",
          "tgn:7029392"
        ],
        "placetype": [
          "aat:300008706"
        ],
        "id": 2272690,
        "name:xx": "Custer Creek"
      }
    },
    {
      "geometry": {
        "type": "Point",
        "coordinates": [
          -116.15,
          43.7667
        ]
      },
      "type": "Feature",
      "properties": {
        "hierarchy": [
          "tgn:2272691",
          "tgn:1000001",
          "tgn:2000459",
          "tgn:7012149",
          "tgn:7007250",
          "tgn:7029392"
        ],
        "placetype": [
          "aat:300008706"
        ],
        "id": 2272691,
        "name:xx": "Custer Creek"
      }
    },
    {
      "geometry": {
        "type": "Point",
        "coordinates": [
          -89.2833,
          46.4
        ]
      },
      "type": "Feature",
      "properties": {
        "hierarchy": [
          "tgn:2272692",
          "tgn:1000001",
          "tgn:7012149",
          "tgn:2000986",
          "tgn:7007520",
          "tgn:7029392"
        ],
        "placetype": [
          "aat:300008706"
        ],
        "id": 2272692,
        "name:xx": "Custer Creek"
      }
    },
    {
      "geometry": {
        "type": "Point",
        "coordinates": [
          -107.2833,
          45.5667
        ]
      },
      "type": "Feature",
      "properties": {
        "hierarchy": [
          "tgn:2272693",
          "tgn:1000001",
          "tgn:2001261",
          "tgn:7012149",
          "tgn:7007524",
          "tgn:7029392"
        ],
        "placetype": [
          "aat:300008706"
        ],
        "id": 2272693,
        "name:xx": "Custer Creek"
      }
    },
    {
      "geometry": {
        "type": "Point",
        "coordinates": [
          -109.1333,
          46.1667
        ]
      },
      "type": "Feature",
      "properties": {
        "hierarchy": [
          "tgn:2272694",
          "tgn:1000001",
          "tgn:7012149",
          "tgn:2001278",
          "tgn:7007524",
          "tgn:7029392"
        ],
        "placetype": [
          "aat:300008706"
        ],
        "id": 2272694,
        "name:xx": "Custer Creek"
      }
    },
    {
      "geometry": {
        "type": "Point",
        "coordinates": [
          -99.6,
          30.8
        ]
      },
      "type": "Feature",
      "properties": {
        "hierarchy": [
          "tgn:2272695",
          "tgn:1000001",
          "tgn:7012149",
          "tgn:2002040",
          "tgn:7007826",
          "tgn:7029392"
        ],
        "placetype": [
          "aat:300008706"
        ],
        "id": 2272695,
        "name:xx": "Custer Creek"
      }
    },
    {
      "geometry": {
        "type": "Point",
        "coordinates": [
          -123.4333,
          46.5667
        ]
      },
      "type": "Feature",
      "properties": {
        "hierarchy": [
          "tgn:2272696",
          "tgn:1000001",
          "tgn:7012149",
          "tgn:1002767",
          "tgn:7007920",
          "tgn:7029392"
        ],
        "placetype": [
          "aat:300008706"
        ],
        "id": 2272696,
        "name:xx": "Custer Creek"
      }
    },
    {
      "geometry": {
        "type": "Point",
        "coordinates": [
          -122.9167,
          41.5667
        ]
      },
      "type": "Feature",
      "properties": {
        "hierarchy": [
          "tgn:2272697",
          "tgn:1000001",
          "tgn:7012149",
          "tgn:7007157",
          "tgn:2000189",
          "tgn:7029392"
        ],
        "placetype": [
          "aat:300006075"
        ],
        "id": 2272697,
        "name:xx": "Custer Ditch"
      }
    },
    {
      "geometry": {
        "type": "Point",
        "coordinates": [
          -108.6167,
          37.95
        ]
      },
      "type": "Feature",
      "properties": {
        "hierarchy": [
          "tgn:2272698",
          "tgn:1000001",
          "tgn:7012149",
          "tgn:7007158",
          "tgn:2000248",
          "tgn:7029392"
        ],
        "placetype": [
          "aat:300006075"
        ],
        "id": 2272698,
        "name:xx": "Custer Ditch"
      }
    },
    {
      "geometry": {
        "type": "Point",
        "coordinates": [
          -106.0167,
          40.5833
        ]
      },
      "type": "Feature",
      "properties": {
        "hierarchy": [
          "tgn:2272699",
          "tgn:1000001",
          "tgn:7012149",
          "tgn:2000220",
          "tgn:7007158",
          "tgn:7029392"
        ],
        "placetype": [
          "aat:300008761"
        ],
        "id": 2272699,
        "name:xx": "Custer Draw"
      }
    }
  ]
}
