{
  "geometry": {
    "type": "Point",
    "coordinates": [
      -79.7667,
      42.0667
    ]
  },
  "type": "Feature",
  "properties": {
    "hierarchy": [
      "tgn:2295865",
      "tgn:1000001",
      "tgn:7012149",
      "tgn:1002358",
      "tgn:7007710",
      "tgn:7029392"
    ],
    "placetype": [
      "aat:300266640"
    ],
    "id": 2295865,
    "name:xx": "Drumlins"
  }
}
