{
  "geometry": {
    "type": "Point",
    "coordinates": [
      88.0833,
      28.9167
    ]
  },
  "type": "Feature",
  "properties": {
    "hierarchy": [
      "tgn:1071266",
      "tgn:1000004",
      "tgn:7001319",
      "tgn:1000111",
      "tgn:7029392"
    ],
    "placetype": [
      "aat:300008347"
    ],
    "id": 1071266,
    "name:xx": "Sajia"
  }
}
