{
  "type": "FeatureCollection",
  "features": [
    {
      "geometry": {
        "type": "Point",
        "coordinates": [
          77.1333,
          28.7
        ]
      },
      "type": "Feature",
      "properties": {
        "hierarchy": [
          "tgn:1005350",
          "tgn:1000004",
          "tgn:7000201",
          "tgn:7000198",
          "tgn:7029392"
        ],
        "placetype": [
          "aat:300000745"
        ],
        "id": 1005350,
        "name:xx": "Pitampura Kālan"
      }
    },
    {
      "geometry": {
        "type": "Point",
        "coordinates": [
          -9.1,
          38.744
        ]
      },
      "type": "Feature",
      "properties": {
        "hierarchy": [
          "tgn:1005352",
          "tgn:1000882",
          "tgn:1000003",
          "tgn:1000090",
          "tgn:7029392"
        ],
        "placetype": [
          "aat:300008347",
          "aat:300000745"
        ],
        "id": 1005352,
        "name:xx": "Poço do Bispo"
      }
    },
    {
      "geometry": {
        "type": "Point",
        "coordinates": [
          14.6,
          53.3667
        ]
      },
      "type": "Feature",
      "properties": {
        "hierarchy": [
          "tgn:1005353",
          "tgn:1000003",
          "tgn:7007809",
          "tgn:7024114",
          "tgn:7006366",
          "tgn:7029392"
        ],
        "placetype": [
          "aat:300000745"
        ],
        "id": 1005353,
        "name:xx": "Podjuchy"
      }
    },
    {
      "geometry": {
        "type": "Point",
        "coordinates": [
          37.4833,
          55.8167
        ]
      },
      "type": "Feature",
      "properties": {
        "hierarchy": [
          "tgn:1005355",
          "tgn:7012974",
          "tgn:1000004",
          "tgn:7018215",
          "tgn:7018214",
          "tgn:7002435",
          "tgn:7029392"
        ],
        "placetype": [
          "aat:300000745"
        ],
        "id": 1005355,
        "name:xx": "Pokrovsko-Streshnevo"
      }
    },
    {
      "geometry": {
        "type": "Point",
        "coordinates": [
          37.6333,
          55.6
        ]
      },
      "type": "Feature",
      "properties": {
        "hierarchy": [
          "tgn:1005356",
          "tgn:1000004",
          "tgn:7011573",
          "tgn:7012975",
          "tgn:7018214",
          "tgn:7002435",
          "tgn:7029392"
        ],
        "placetype": [
          "aat:300000745"
        ],
        "id": 1005356,
        "name:xx": "Pokrovskoye"
      }
    },
    {
      "geometry": {
        "type": "Point",
        "coordinates": [
          30.4167,
          59.9667
        ]
      },
      "type": "Feature",
      "properties": {
        "hierarchy": [
          "tgn:1005357",
          "tgn:7010273",
          "tgn:1000004",
          "tgn:7018216",
          "tgn:7018214",
          "tgn:7002435",
          "tgn:7029392"
        ],
        "placetype": [
          "aat:300000745"
        ],
        "id": 1005357,
        "name:xx": "Polyustrovo"
      }
    },
    {
      "geometry": {
        "type": "Point",
        "coordinates": [
          -0.05,
          51.65
        ]
      },
      "type": "Feature",
      "properties": {
        "hierarchy": [
          "tgn:1005358",
          "tgn:7002445",
          "tgn:7018914",
          "tgn:1000003",
          "tgn:7008136",
          "tgn:7008591",
          "tgn:7029392"
        ],
        "placetype": [
          "aat:300008347",
          "aat:300000745"
        ],
        "name:en": "Ponders End",
        "id": 1005358
      }
    },
    {
      "geometry": {
        "type": "Point",
        "coordinates": [
          -73.7,
          45.5667
        ]
      },
      "type": "Feature",
      "properties": {
        "hierarchy": [
          "tgn:1005359",
          "tgn:7005685",
          "tgn:1000001",
          "tgn:7005804",
          "tgn:1007525",
          "tgn:7029392"
        ],
        "placetype": [
          "aat:300008347"
        ],
        "id": 1005359,
        "name:xx": "Pont-Viau"
      }
    }
  ]
}
