{
  "geometry": {
    "type": "Point",
    "coordinates": [
      90.6667,
      24.4167
    ]
  },
  "type": "Feature",
  "properties": {
    "hierarchy": [
      "tgn:1065726",
      "tgn:7000189",
      "tgn:1000004",
      "tgn:1000105",
      "tgn:7029392"
    ],
    "placetype": [
      "aat:300008347"
    ],
    "id": 1065726,
    "name:xx": "Husainpur"
  }
}
