{
  "geometry": {
    "type": "Point",
    "coordinates": [
      -119.4667,
      40.8667
    ]
  },
  "type": "Feature",
  "properties": {
    "hierarchy": [
      "tgn:2747159",
      "tgn:1000001",
      "tgn:7012149",
      "tgn:1002999",
      "tgn:7007526",
      "tgn:7029392"
    ],
    "placetype": [
      "aat:300008706"
    ],
    "id": 2747159,
    "name:xx": "Wagon Tire Creek"
  }
}
