{
  "type": "FeatureCollection",
  "features": [
    {
      "geometry": {
        "type": "Point",
        "coordinates": [
          25.25,
          35.183333
        ]
      },
      "type": "Feature",
      "properties": {
        "hierarchy": [
          "tgn:7228920",
          "tgn:7002690",
          "tgn:7012056",
          "tgn:1000003",
          "tgn:1000074",
          "tgn:7029392"
        ],
        "placetype": [
          "aat:300008347"
        ],
        "id": 7228920,
        "name:xx": "Galatás"
      }
    },
    {
      "geometry": {
        "type": "Point",
        "coordinates": [
          22.383333,
          36.616667
        ]
      },
      "type": "Feature",
      "properties": {
        "hierarchy": [
          "tgn:7228921",
          "tgn:7002745",
          "tgn:7017076",
          "tgn:1000003",
          "tgn:1000074",
          "tgn:7029392"
        ],
        "placetype": [
          "aat:300008347"
        ],
        "id": 7228921,
        "name:xx": "Levkiás"
      }
    },
    {
      "geometry": {
        "type": "Point",
        "coordinates": [
          22.983333,
          36.483333
        ]
      },
      "type": "Feature",
      "properties": {
        "hierarchy": [
          "tgn:7228922",
          "tgn:7002745",
          "tgn:7017076",
          "tgn:1000003",
          "tgn:1000074",
          "tgn:7029392"
        ],
        "placetype": [
          "aat:300132316"
        ],
        "id": 7228922,
        "name:xx": "Lévki, Órmos"
      }
    },
    {
      "geometry": {
        "type": "Point",
        "coordinates": [
          24.866667,
          41.083333
        ]
      },
      "type": "Feature",
      "properties": {
        "hierarchy": [
          "tgn:7228923",
          "tgn:7011170",
          "tgn:7002715",
          "tgn:1000003",
          "tgn:1000074",
          "tgn:7029392"
        ],
        "placetype": [
          "aat:300008347"
        ],
        "id": 7228923,
        "name:xx": "Lévki"
      }
    },
    {
      "geometry": {
        "type": "Point",
        "coordinates": [
          24.516667,
          40.983333
        ]
      },
      "type": "Feature",
      "properties": {
        "hierarchy": [
          "tgn:7228924",
          "tgn:7011170",
          "tgn:7002715",
          "tgn:1000003",
          "tgn:1000074",
          "tgn:7029392"
        ],
        "placetype": [
          "aat:300008347"
        ],
        "id": 7228924,
        "name:xx": "Lévki"
      }
    },
    {
      "geometry": {
        "type": "Point",
        "coordinates": [
          21.2,
          40.3
        ]
      },
      "type": "Feature",
      "properties": {
        "hierarchy": [
          "tgn:7228925",
          "tgn:7002724",
          "tgn:7002715",
          "tgn:1000003",
          "tgn:1000074",
          "tgn:7029392"
        ],
        "placetype": [
          "aat:300008347"
        ],
        "id": 7228925,
        "name:xx": "Lévki"
      }
    },
    {
      "geometry": {
        "type": "Point",
        "coordinates": [
          22.183333,
          39.8
        ]
      },
      "type": "Feature",
      "properties": {
        "hierarchy": [
          "tgn:7228926",
          "tgn:7002750",
          "tgn:7001399",
          "tgn:1000003",
          "tgn:1000074",
          "tgn:7029392"
        ],
        "placetype": [
          "aat:300008347"
        ],
        "id": 7228926,
        "name:xx": "Lévki"
      }
    },
    {
      "geometry": {
        "type": "Point",
        "coordinates": [
          20.65,
          38.416667
        ]
      },
      "type": "Feature",
      "properties": {
        "hierarchy": [
          "tgn:7228927",
          "tgn:7011167",
          "tgn:7001338",
          "tgn:1000003",
          "tgn:1000074",
          "tgn:7029392"
        ],
        "placetype": [
          "aat:300008347"
        ],
        "id": 7228927,
        "name:xx": "Lévki"
      }
    },
    {
      "geometry": {
        "type": "Point",
        "coordinates": [
          22.083333,
          37.933333
        ]
      },
      "type": "Feature",
      "properties": {
        "hierarchy": [
          "tgn:7228928",
          "tgn:7002743",
          "tgn:7017076",
          "tgn:1000003",
          "tgn:1000074",
          "tgn:7029392"
        ],
        "placetype": [
          "aat:300008347"
        ],
        "id": 7228928,
        "name:xx": "Lévki"
      }
    },
    {
      "geometry": {
        "type": "Point",
        "coordinates": [
          21.666667,
          37.05
        ]
      },
      "type": "Feature",
      "properties": {
        "hierarchy": [
          "tgn:7228929",
          "tgn:7011369",
          "tgn:7017076",
          "tgn:1000003",
          "tgn:1000074",
          "tgn:7029392"
        ],
        "placetype": [
          "aat:300008347"
        ],
        "id": 7228929,
        "name:xx": "Lévki"
      }
    }
  ]
}
