{
  "geometry": {
    "type": "Point",
    "coordinates": [
      -73.35,
      44.4833
    ]
  },
  "type": "Feature",
  "properties": {
    "hierarchy": [
      "tgn:2648473",
      "tgn:1000001",
      "tgn:7012149",
      "tgn:2001461",
      "tgn:7007568",
      "tgn:7029392"
    ],
    "placetype": [
      "aat:300132348"
    ],
    "id": 2648473,
    "name:xx": "Schuyler Reef"
  }
}
