{
  "geometry": {
    "type": "Point",
    "coordinates": [
      -112.4833,
      42.15
    ]
  },
  "type": "Feature",
  "properties": {
    "hierarchy": [
      "tgn:2741005",
      "tgn:1000001",
      "tgn:7012149",
      "tgn:2000487",
      "tgn:7007250",
      "tgn:7029392"
    ],
    "placetype": [
      "aat:300008697"
    ],
    "id": 2741005,
    "name:xx": "Upper Spring"
  }
}
