{
  "type": "FeatureCollection",
  "features": [
    {
      "geometry": {
        "type": "Point",
        "coordinates": [
          -94.8333,
          46.8833
        ]
      },
      "type": "Feature",
      "properties": {
        "hierarchy": [
          "tgn:2415220",
          "tgn:1000001",
          "tgn:7012149",
          "tgn:2001027",
          "tgn:7007521",
          "tgn:7029392"
        ],
        "placetype": [
          "aat:300008680"
        ],
        "id": 2415220,
        "name:xx": "Island Lake"
      }
    },
    {
      "geometry": {
        "type": "Point",
        "coordinates": [
          -93.4,
          47.35
        ]
      },
      "type": "Feature",
      "properties": {
        "hierarchy": [
          "tgn:2415222",
          "tgn:1000001",
          "tgn:7012149",
          "tgn:2001029",
          "tgn:7007521",
          "tgn:7029392"
        ],
        "placetype": [
          "aat:300008680"
        ],
        "id": 2415222,
        "name:xx": "Island Lake"
      }
    },
    {
      "geometry": {
        "type": "Point",
        "coordinates": [
          -95.7,
          47.3667
        ]
      },
      "type": "Feature",
      "properties": {
        "hierarchy": [
          "tgn:2415223",
          "tgn:1000001",
          "tgn:7012149",
          "tgn:2001042",
          "tgn:7007521",
          "tgn:7029392"
        ],
        "placetype": [
          "aat:300008680"
        ],
        "id": 2415223,
        "name:xx": "Island Lake"
      }
    },
    {
      "geometry": {
        "type": "Point",
        "coordinates": [
          -96.0667,
          47.6167
        ]
      },
      "type": "Feature",
      "properties": {
        "hierarchy": [
          "tgn:2415224",
          "tgn:1000001",
          "tgn:7012149",
          "tgn:2001058",
          "tgn:7007521",
          "tgn:7029392"
        ],
        "placetype": [
          "aat:300008680"
        ],
        "id": 2415224,
        "name:xx": "Island Lake"
      }
    },
    {
      "geometry": {
        "type": "Point",
        "coordinates": [
          -95.0167,
          47.7667
        ]
      },
      "type": "Feature",
      "properties": {
        "hierarchy": [
          "tgn:2415225",
          "tgn:2001002",
          "tgn:1000001",
          "tgn:7012149",
          "tgn:7007521",
          "tgn:7029392"
        ],
        "placetype": [
          "aat:300008680"
        ],
        "id": 2415225,
        "name:xx": "Island Lake"
      }
    },
    {
      "geometry": {
        "type": "Point",
        "coordinates": [
          -92.7333,
          46.4
        ]
      },
      "type": "Feature",
      "properties": {
        "hierarchy": [
          "tgn:2415226",
          "tgn:1000001",
          "tgn:7012149",
          "tgn:2001056",
          "tgn:7007521",
          "tgn:7029392"
        ],
        "placetype": [
          "aat:300008680"
        ],
        "id": 2415226,
        "name:xx": "Island Lake"
      }
    },
    {
      "geometry": {
        "type": "Point",
        "coordinates": [
          -92.8667,
          46.6667
        ]
      },
      "type": "Feature",
      "properties": {
        "hierarchy": [
          "tgn:2415227",
          "tgn:1000001",
          "tgn:2001007",
          "tgn:7012149",
          "tgn:7007521",
          "tgn:7029392"
        ],
        "placetype": [
          "aat:300008680"
        ],
        "id": 2415227,
        "name:xx": "Island Lake"
      }
    },
    {
      "geometry": {
        "type": "Point",
        "coordinates": [
          -95.4833,
          47.2667
        ]
      },
      "type": "Feature",
      "properties": {
        "hierarchy": [
          "tgn:2415228",
          "tgn:1000001",
          "tgn:2001013",
          "tgn:7012149",
          "tgn:7007521",
          "tgn:7029392"
        ],
        "placetype": [
          "aat:300008680"
        ],
        "id": 2415228,
        "name:xx": "Island Lake"
      }
    },
    {
      "geometry": {
        "type": "Point",
        "coordinates": [
          -90.2333,
          34.15
        ]
      },
      "type": "Feature",
      "properties": {
        "hierarchy": [
          "tgn:2415229",
          "tgn:1000001",
          "tgn:7012149",
          "tgn:2001145",
          "tgn:7007522",
          "tgn:7029392"
        ],
        "placetype": [
          "aat:300008680"
        ],
        "id": 2415229,
        "name:xx": "Island Lake"
      }
    }
  ]
}
