{
  "geometry": {
    "type": "Point",
    "coordinates": [
      -87.0667,
      35.85
    ]
  },
  "type": "Feature",
  "properties": {
    "hierarchy": [
      "tgn:2680529",
      "tgn:1000001",
      "tgn:7012149",
      "tgn:2001930",
      "tgn:7007825",
      "tgn:7029392"
    ],
    "placetype": [
      "aat:300008699"
    ],
    "id": 2680529,
    "name:xx": "South Garrison Branch"
  }
}
