{
  "geometry": {
    "type": "Point",
    "coordinates": [
      -103.5333,
      34.8333
    ]
  },
  "type": "Feature",
  "properties": {
    "hierarchy": [
      "tgn:2586844",
      "tgn:1000001",
      "tgn:7012149",
      "tgn:2001448",
      "tgn:7007566",
      "tgn:7029392"
    ],
    "placetype": [
      "aat:300008347"
    ],
    "id": 2586844,
    "name:xx": "Plain"
  }
}
