{
  "type": "FeatureCollection",
  "features": [
    {
      "geometry": {
        "type": "Point",
        "coordinates": [
          -86.4167,
          39.4333
        ]
      },
      "type": "Feature",
      "properties": {
        "hierarchy": [
          "tgn:2449590",
          "tgn:1000001",
          "tgn:7012149",
          "tgn:1002694",
          "tgn:7007252",
          "tgn:7029392"
        ],
        "placetype": [
          "aat:300008798"
        ],
        "id": 2449590,
        "name:xx": "Lincoln Hill"
      }
    },
    {
      "geometry": {
        "type": "Point",
        "coordinates": [
          -70.7333,
          41.7667
        ]
      },
      "type": "Feature",
      "properties": {
        "hierarchy": [
          "tgn:2449591",
          "tgn:1000001",
          "tgn:7014423",
          "tgn:7012149",
          "tgn:7007517",
          "tgn:7029392"
        ],
        "placetype": [
          "aat:300008798"
        ],
        "id": 2449591,
        "name:xx": "Lincoln Hill"
      }
    },
    {
      "geometry": {
        "type": "Point",
        "coordinates": [
          -118.2,
          40.2833
        ]
      },
      "type": "Feature",
      "properties": {
        "hierarchy": [
          "tgn:2449592",
          "tgn:1000001",
          "tgn:2001419",
          "tgn:7012149",
          "tgn:7007526",
          "tgn:7029392"
        ],
        "placetype": [
          "aat:300008798"
        ],
        "id": 2449592,
        "name:xx": "Lincoln Hill"
      }
    },
    {
      "geometry": {
        "type": "Point",
        "coordinates": [
          -71.8333,
          43.0167
        ]
      },
      "type": "Feature",
      "properties": {
        "hierarchy": [
          "tgn:2449593",
          "tgn:1000001",
          "tgn:1002480",
          "tgn:7012149",
          "tgn:7007564",
          "tgn:7029392"
        ],
        "placetype": [
          "aat:300008798"
        ],
        "id": 2449593,
        "name:xx": "Lincoln Hill"
      }
    },
    {
      "geometry": {
        "type": "Point",
        "coordinates": [
          -77.2167,
          42.85
        ]
      },
      "type": "Feature",
      "properties": {
        "hierarchy": [
          "tgn:2449594",
          "tgn:1000001",
          "tgn:7012149",
          "tgn:1002747",
          "tgn:7007568",
          "tgn:7029392"
        ],
        "placetype": [
          "aat:300008798"
        ],
        "id": 2449594,
        "name:xx": "Lincoln Hill"
      }
    },
    {
      "geometry": {
        "type": "Point",
        "coordinates": [
          -73.1833,
          43.4
        ]
      },
      "type": "Feature",
      "properties": {
        "hierarchy": [
          "tgn:2449595",
          "tgn:1000001",
          "tgn:1002840",
          "tgn:7012149",
          "tgn:7007828",
          "tgn:7029392"
        ],
        "placetype": [
          "aat:300008798"
        ],
        "id": 2449595,
        "name:xx": "Lincoln Hill"
      }
    },
    {
      "geometry": {
        "type": "Point",
        "coordinates": [
          -73.0333,
          44.3
        ]
      },
      "type": "Feature",
      "properties": {
        "hierarchy": [
          "tgn:2449596",
          "tgn:1000001",
          "tgn:2002132",
          "tgn:7012149",
          "tgn:7007828",
          "tgn:7029392"
        ],
        "placetype": [
          "aat:300008798"
        ],
        "id": 2449596,
        "name:xx": "Lincoln Hill"
      }
    },
    {
      "geometry": {
        "type": "Point",
        "coordinates": [
          -78.7167,
          38.55
        ]
      },
      "type": "Feature",
      "properties": {
        "hierarchy": [
          "tgn:2449597",
          "tgn:1000001",
          "tgn:7012149",
          "tgn:2002187",
          "tgn:7007919",
          "tgn:7029392"
        ],
        "placetype": [
          "aat:300008798"
        ],
        "id": 2449597,
        "name:xx": "Lincoln Hill"
      }
    },
    {
      "geometry": {
        "type": "Point",
        "coordinates": [
          -118.2,
          40.2833
        ]
      },
      "type": "Feature",
      "properties": {
        "hierarchy": [
          "tgn:2449598",
          "tgn:1000001",
          "tgn:2001419",
          "tgn:7012149",
          "tgn:7007526",
          "tgn:7029392"
        ],
        "placetype": [
          "aat:300000390"
        ],
        "id": 2449598,
        "name:xx": "Lincoln Hill Mine"
      }
    },
    {
      "geometry": {
        "type": "Point",
        "coordinates": [
          -105.45,
          39.9167
        ]
      },
      "type": "Feature",
      "properties": {
        "hierarchy": [
          "tgn:2449599",
          "tgn:1000001",
          "tgn:7012149",
          "tgn:2000215",
          "tgn:7007158",
          "tgn:7029392"
        ],
        "placetype": [
          "aat:300008347"
        ],
        "id": 2449599,
        "name:xx": "Lincoln Hills"
      }
    }
  ]
}
