{
  "geometry": {
    "type": "Point",
    "coordinates": [
      -89.8167,
      42.3667
    ]
  },
  "type": "Feature",
  "properties": {
    "hierarchy": [
      "tgn:2028743",
      "tgn:1000001",
      "tgn:7012149",
      "tgn:2000532",
      "tgn:7007251",
      "tgn:7029392"
    ],
    "placetype": [
      "aat:300008347"
    ],
    "id": 2028743,
    "name:xx": "Lena"
  }
}
