{
  "geometry": {
    "type": "Point",
    "coordinates": [
      -105.3167,
      35.55
    ]
  },
  "type": "Feature",
  "properties": {
    "hierarchy": [
      "tgn:2213598",
      "tgn:1000001",
      "tgn:7012149",
      "tgn:2001453",
      "tgn:7007566",
      "tgn:7029392"
    ],
    "placetype": [
      "aat:300008699"
    ],
    "id": 2213598,
    "name:xx": "Cabo Lucero, Cañada del"
  }
}
