{
  "geometry": {
    "type": "Point",
    "coordinates": [
      12.85,
      52.55
    ]
  },
  "type": "Feature",
  "properties": {
    "hierarchy": [
      "tgn:7094553",
      "tgn:7000096",
      "tgn:1000003",
      "tgn:7000084",
      "tgn:7029392"
    ],
    "placetype": [
      "aat:300008777"
    ],
    "id": 7094553,
    "name:xx": "See-Berge"
  }
}
