{
  "geometry": {
    "type": "Point",
    "coordinates": [
      -118.2667,
      45.85
    ]
  },
  "type": "Feature",
  "properties": {
    "hierarchy": [
      "tgn:2449718",
      "tgn:1000001",
      "tgn:7012149",
      "tgn:2001720",
      "tgn:7007708",
      "tgn:7029392"
    ],
    "placetype": [
      "aat:300008798"
    ],
    "id": 2449718,
    "name:xx": "Lincton Mountain"
  }
}
