{
  "geometry": {
    "type": "Point",
    "coordinates": [
      -72.2167,
      42.5833
    ]
  },
  "type": "Feature",
  "properties": {
    "hierarchy": [
      "tgn:7023428",
      "tgn:1000001",
      "tgn:7012149",
      "tgn:7007517",
      "tgn:7029392"
    ],
    "placetype": [
      "aat:300006191"
    ],
    "id": 7023428,
    "name:xx": "Millers River Reservoir"
  }
}
