{
  "geometry": {
    "type": "Point",
    "coordinates": [
      -76.4667,
      34.7833
    ]
  },
  "type": "Feature",
  "properties": {
    "hierarchy": [
      "tgn:2257046",
      "tgn:1000001",
      "tgn:2001477",
      "tgn:7012149",
      "tgn:7007709",
      "tgn:7029392"
    ],
    "placetype": [
      "aat:300008850"
    ],
    "id": 2257046,
    "name:xx": "Corncrib Point"
  }
}
