{
  "geometry": {
    "type": "Point",
    "coordinates": [
      73.481965,
      27.306457
    ]
  },
  "type": "Feature",
  "properties": {
    "hierarchy": [
      "tgn:7571343",
      "tgn:1000004",
      "tgn:7000198",
      "tgn:7016788",
      "tgn:7029392"
    ],
    "placetype": [
      "aat:300008347"
    ],
    "name:en": "Kālri",
    "id": 7571343
  }
}
