{
  "geometry": {
    "type": "Point",
    "coordinates": [
      -82.3167,
      35.3667
    ]
  },
  "type": "Feature",
  "properties": {
    "hierarchy": [
      "tgn:2426623",
      "tgn:1000001",
      "tgn:7012149",
      "tgn:2001504",
      "tgn:7007709",
      "tgn:7029392"
    ],
    "placetype": [
      "aat:300008798"
    ],
    "id": 2426623,
    "name:xx": "Jones Knob"
  }
}
