{
  "geometry": {
    "type": "Point",
    "coordinates": [
      10.45,
      50.45
    ]
  },
  "type": "Feature",
  "properties": {
    "hierarchy": [
      "tgn:7109511",
      "tgn:1000003",
      "tgn:7003689",
      "tgn:7000084",
      "tgn:7029392"
    ],
    "placetype": [
      "aat:300008347"
    ],
    "id": 7109511,
    "name:xx": "Queienfeld"
  }
}
