{
  "geometry": {
    "type": "Point",
    "coordinates": [
      -105.4833,
      40.9833
    ]
  },
  "type": "Feature",
  "properties": {
    "hierarchy": [
      "tgn:2434095",
      "tgn:1000001",
      "tgn:7012149",
      "tgn:2000226",
      "tgn:7007158",
      "tgn:7029392"
    ],
    "placetype": [
      "aat:300006191"
    ],
    "id": 2434095,
    "name:xx": "Kelsey Lake"
  }
}
