{
  "geometry": {
    "type": "Point",
    "coordinates": [
      -85.6667,
      34.0667
    ]
  },
  "type": "Feature",
  "properties": {
    "hierarchy": [
      "tgn:2756120",
      "tgn:7002659",
      "tgn:1000001",
      "tgn:2000009",
      "tgn:7012149",
      "tgn:7029392"
    ],
    "placetype": [
      "aat:300006191"
    ],
    "id": 2756120,
    "name:xx": "Weisner, Lake"
  }
}
