{
  "geometry": {
    "type": "Point",
    "coordinates": [
      -143.4833,
      61.5333
    ]
  },
  "type": "Feature",
  "properties": {
    "hierarchy": [
      "tgn:2238475",
      "tgn:7006450",
      "tgn:1000001",
      "tgn:7012149",
      "tgn:2000086",
      "tgn:7029392"
    ],
    "placetype": [
      "aat:300008707"
    ],
    "id": 2238475,
    "name:xx": "Chokosna River"
  }
}
