{
  "geometry": {
    "type": "Point",
    "coordinates": [
      54.1167,
      36.7833
    ]
  },
  "type": "Feature",
  "properties": {
    "hierarchy": [
      "tgn:1079165",
      "tgn:1000004",
      "tgn:7029810",
      "tgn:7000231",
      "tgn:7029392"
    ],
    "placetype": [
      "aat:300008347"
    ],
    "id": 1079165,
    "name:xx": "Kord Kūy"
  }
}
