{
  "geometry": {
    "type": "Point",
    "coordinates": [
      -111.1333,
      39.7167
    ]
  },
  "type": "Feature",
  "properties": {
    "hierarchy": [
      "tgn:2304126",
      "tgn:1000001",
      "tgn:2002104",
      "tgn:7012149",
      "tgn:7007827",
      "tgn:7029392"
    ],
    "placetype": [
      "aat:300008761"
    ],
    "id": 2304126,
    "name:xx": "Eagles Canyon"
  }
}
