{
  "geometry": {
    "type": "Point",
    "coordinates": [
      -86.8667,
      36.2833
    ]
  },
  "type": "Feature",
  "properties": {
    "hierarchy": [
      "tgn:2457628",
      "tgn:1000001",
      "tgn:7012149",
      "tgn:7007825",
      "tgn:7029392"
    ],
    "placetype": [
      "aat:300008706"
    ],
    "id": 2457628,
    "name:xx": "Little Marrowbone Creek"
  }
}
