{
  "type": "FeatureCollection",
  "features": [
    {
      "geometry": {
        "type": "Point",
        "coordinates": [
          -95.816667,
          17.933333
        ]
      },
      "type": "Feature",
      "properties": {
        "hierarchy": [
          "tgn:7349060",
          "tgn:1000001",
          "tgn:7005591",
          "tgn:7005560",
          "tgn:7029392"
        ],
        "placetype": [
          "aat:300008347"
        ],
        "id": 7349060,
        "name:xx": "Aguacate"
      }
    },
    {
      "geometry": {
        "type": "Point",
        "coordinates": [
          -94.533333,
          16.45
        ]
      },
      "type": "Feature",
      "properties": {
        "hierarchy": [
          "tgn:7349061",
          "tgn:1000001",
          "tgn:7005591",
          "tgn:7005560",
          "tgn:7029392"
        ],
        "placetype": [
          "aat:300008347"
        ],
        "id": 7349061,
        "name:xx": "Aguacate"
      }
    },
    {
      "geometry": {
        "type": "Point",
        "coordinates": [
          -97.483333,
          16.266667
        ]
      },
      "type": "Feature",
      "properties": {
        "hierarchy": [
          "tgn:7349063",
          "tgn:1000001",
          "tgn:7005591",
          "tgn:7005560",
          "tgn:7029392"
        ],
        "placetype": [
          "aat:300008347"
        ],
        "id": 7349063,
        "name:xx": "Aguacate"
      }
    },
    {
      "geometry": {
        "type": "Point",
        "coordinates": [
          -96.583333,
          16.05
        ]
      },
      "type": "Feature",
      "properties": {
        "hierarchy": [
          "tgn:7349064",
          "tgn:1000001",
          "tgn:7005591",
          "tgn:7005560",
          "tgn:7029392"
        ],
        "placetype": [
          "aat:300008347"
        ],
        "id": 7349064,
        "name:xx": "Aguacate"
      }
    },
    {
      "geometry": {
        "type": "Point",
        "coordinates": [
          -100.583333,
          22.016667
        ]
      },
      "type": "Feature",
      "properties": {
        "hierarchy": [
          "tgn:7349065",
          "tgn:1000001",
          "tgn:7005594",
          "tgn:7005560",
          "tgn:7029392"
        ],
        "placetype": [
          "aat:300007783"
        ],
        "id": 7349065,
        "name:xx": "Aguacatal"
      }
    },
    {
      "geometry": {
        "type": "Point",
        "coordinates": [
          -100.6,
          22.05
        ]
      },
      "type": "Feature",
      "properties": {
        "hierarchy": [
          "tgn:7349066",
          "tgn:1000001",
          "tgn:7005594",
          "tgn:7005560",
          "tgn:7029392"
        ],
        "placetype": [
          "aat:300008347"
        ],
        "id": 7349066,
        "name:xx": "Aguacatal"
      }
    },
    {
      "geometry": {
        "type": "Point",
        "coordinates": [
          -107.833333,
          25.716667
        ]
      },
      "type": "Feature",
      "properties": {
        "hierarchy": [
          "tgn:7349067",
          "tgn:1000001",
          "tgn:7005595",
          "tgn:7005560",
          "tgn:7029392"
        ],
        "placetype": [
          "aat:300008347"
        ],
        "id": 7349067,
        "name:xx": "Aguacapas"
      }
    },
    {
      "geometry": {
        "type": "Point",
        "coordinates": [
          -95.3,
          18.366667
        ]
      },
      "type": "Feature",
      "properties": {
        "hierarchy": [
          "tgn:7349068",
          "tgn:1000001",
          "tgn:7005599",
          "tgn:7005560",
          "tgn:7029392"
        ],
        "placetype": [
          "aat:300007783"
        ],
        "id": 7349068,
        "name:xx": "Aguacapan"
      }
    },
    {
      "geometry": {
        "type": "Point",
        "coordinates": [
          -95.316667,
          18.366667
        ]
      },
      "type": "Feature",
      "properties": {
        "hierarchy": [
          "tgn:7349069",
          "tgn:1000001",
          "tgn:7005599",
          "tgn:7005560",
          "tgn:7029392"
        ],
        "placetype": [
          "aat:300008347"
        ],
        "id": 7349069,
        "name:xx": "Aguacapan"
      }
    }
  ]
}
