{
  "geometry": {
    "type": "Point",
    "coordinates": [
      -83.1667,
      37.8167
    ]
  },
  "type": "Feature",
  "properties": {
    "hierarchy": [
      "tgn:2288982",
      "tgn:1000001",
      "tgn:7012149",
      "tgn:7007255",
      "tgn:7029392"
    ],
    "placetype": [
      "aat:300266640"
    ],
    "id": 2288982,
    "name:xx": "Ditney Ridge"
  }
}
