{
  "geometry": {
    "type": "Point",
    "coordinates": [
      -107.1833,
      44.4167
    ]
  },
  "type": "Feature",
  "properties": {
    "hierarchy": [
      "tgn:2469874",
      "tgn:1000001",
      "tgn:7012149",
      "tgn:2002374",
      "tgn:7007923",
      "tgn:7029392"
    ],
    "placetype": [
      "aat:300008680"
    ],
    "id": 2469874,
    "name:xx": "Loomis Lake"
  }
}
