{
  "geometry": {
    "type": "Point",
    "coordinates": [
      -82.9667,
      36.3667
    ]
  },
  "type": "Feature",
  "properties": {
    "hierarchy": [
      "tgn:2502349",
      "tgn:1000001",
      "tgn:7012149",
      "tgn:2001873",
      "tgn:7007825",
      "tgn:7029392"
    ],
    "placetype": [
      "aat:300386853"
    ],
    "id": 2502349,
    "name:xx": "McKinneys Islands"
  }
}
