{
  "geometry": {
    "type": "Point",
    "coordinates": [
      -81.1667,
      32.4667
    ]
  },
  "type": "Feature",
  "properties": {
    "hierarchy": [
      "tgn:2166414",
      "tgn:1000001",
      "tgn:7012149",
      "tgn:2001751",
      "tgn:7007712",
      "tgn:7029392"
    ],
    "placetype": [
      "aat:300008905"
    ],
    "id": 2166414,
    "name:xx": "Big Boar Flat"
  }
}
