{
  "geometry": {
    "type": "Point",
    "coordinates": [
      -75.85,
      37.3667
    ]
  },
  "type": "Feature",
  "properties": {
    "hierarchy": [
      "tgn:2203349",
      "tgn:1000001",
      "tgn:7012149",
      "tgn:1002730",
      "tgn:7007919",
      "tgn:7029392"
    ],
    "placetype": [
      "aat:300008850"
    ],
    "id": 2203349,
    "name:xx": "Buckhorn Point"
  }
}
