{
  "geometry": {
    "type": "Point",
    "coordinates": [
      -86.0833,
      37.1667
    ]
  },
  "type": "Feature",
  "properties": {
    "hierarchy": [
      "tgn:2198909",
      "tgn:1000001",
      "tgn:7012149",
      "tgn:2000787",
      "tgn:7007255",
      "tgn:7029392"
    ],
    "placetype": [
      "aat:300008761"
    ],
    "id": 2198909,
    "name:xx": "Bruce Hollow"
  }
}
