{
  "geometry": {
    "type": "Point",
    "coordinates": [
      -116.8333,
      48.5167
    ]
  },
  "type": "Feature",
  "properties": {
    "hierarchy": [
      "tgn:2692434",
      "tgn:1000001",
      "tgn:2000460",
      "tgn:7012149",
      "tgn:7007250",
      "tgn:7029392"
    ],
    "placetype": [
      "aat:300132316"
    ],
    "id": 2692434,
    "name:xx": "Steamboat Bay"
  }
}
