{
  "geometry": {
    "type": "Point",
    "coordinates": [
      -77.1333,
      40.2333
    ]
  },
  "type": "Feature",
  "properties": {
    "hierarchy": [
      "tgn:2493058",
      "tgn:1000001",
      "tgn:1002310",
      "tgn:7012149",
      "tgn:7007710",
      "tgn:7029392"
    ],
    "placetype": [
      "aat:300008746"
    ],
    "id": 2493058,
    "name:xx": "Marl Cave"
  }
}
