{
  "type": "FeatureCollection",
  "features": [
    {
      "geometry": {
        "type": "Point",
        "coordinates": [
          -92.3,
          14.85
        ]
      },
      "type": "Feature",
      "properties": {
        "hierarchy": [
          "tgn:7395150",
          "tgn:7005580",
          "tgn:1000001",
          "tgn:7005560",
          "tgn:7029392"
        ],
        "placetype": [
          "aat:300008347"
        ],
        "id": 7395150,
        "name:xx": "San Diego"
      }
    },
    {
      "geometry": {
        "type": "Point",
        "coordinates": [
          -100.883333,
          20
        ]
      },
      "type": "Feature",
      "properties": {
        "hierarchy": [
          "tgn:7395151",
          "tgn:7005584",
          "tgn:1000001",
          "tgn:7005560",
          "tgn:7029392"
        ],
        "placetype": [
          "aat:300008795"
        ],
        "id": 7395151,
        "name:xx": "San Diego"
      }
    },
    {
      "geometry": {
        "type": "Point",
        "coordinates": [
          -101.216667,
          23.15
        ]
      },
      "type": "Feature",
      "properties": {
        "hierarchy": [
          "tgn:7395152",
          "tgn:1000001",
          "tgn:7005594",
          "tgn:7005560",
          "tgn:7029392"
        ],
        "placetype": [
          "aat:300387007"
        ],
        "id": 7395152,
        "name:xx": "San Diego"
      }
    },
    {
      "geometry": {
        "type": "Point",
        "coordinates": [
          -106.166667,
          27.166667
        ]
      },
      "type": "Feature",
      "properties": {
        "hierarchy": [
          "tgn:7395153",
          "tgn:7005581",
          "tgn:1000001",
          "tgn:7005560",
          "tgn:7029392"
        ],
        "placetype": [
          "aat:300008347"
        ],
        "id": 7395153,
        "name:xx": "Sandías"
      }
    },
    {
      "geometry": {
        "type": "Point",
        "coordinates": [
          -106.066667,
          26.6
        ]
      },
      "type": "Feature",
      "properties": {
        "hierarchy": [
          "tgn:7395154",
          "tgn:7005583",
          "tgn:1000001",
          "tgn:7005560",
          "tgn:7029392"
        ],
        "placetype": [
          "aat:300008347"
        ],
        "id": 7395154,
        "name:xx": "Sandías"
      }
    },
    {
      "geometry": {
        "type": "Point",
        "coordinates": [
          -105.6,
          25.25
        ]
      },
      "type": "Feature",
      "properties": {
        "hierarchy": [
          "tgn:7395155",
          "tgn:7005583",
          "tgn:1000001",
          "tgn:7005560",
          "tgn:7029392"
        ],
        "placetype": [
          "aat:300008347"
        ],
        "id": 7395155,
        "name:xx": "Sandías"
      }
    },
    {
      "geometry": {
        "type": "Point",
        "coordinates": [
          -101.666667,
          17.816667
        ]
      },
      "type": "Feature",
      "properties": {
        "hierarchy": [
          "tgn:7395156",
          "tgn:7005585",
          "tgn:1000001",
          "tgn:7005560",
          "tgn:7029392"
        ],
        "placetype": [
          "aat:300008347"
        ],
        "id": 7395156,
        "name:xx": "Sandial"
      }
    },
    {
      "geometry": {
        "type": "Point",
        "coordinates": [
          -100.55,
          24.3
        ]
      },
      "type": "Feature",
      "properties": {
        "hierarchy": [
          "tgn:7395157",
          "tgn:1000001",
          "tgn:7005589",
          "tgn:7005560",
          "tgn:7029392"
        ],
        "placetype": [
          "aat:300006191"
        ],
        "id": 7395157,
        "name:xx": "Tanque de la Sandía"
      }
    },
    {
      "geometry": {
        "type": "Point",
        "coordinates": [
          -98.9,
          23.433333
        ]
      },
      "type": "Feature",
      "properties": {
        "hierarchy": [
          "tgn:7395158",
          "tgn:1000001",
          "tgn:7005597",
          "tgn:7005560",
          "tgn:7029392"
        ],
        "placetype": [
          "aat:300008811"
        ],
        "id": 7395158,
        "name:xx": "Sandia, Mesa la"
      }
    },
    {
      "geometry": {
        "type": "Point",
        "coordinates": [
          -105.9,
          26.65
        ]
      },
      "type": "Feature",
      "properties": {
        "hierarchy": [
          "tgn:7395159",
          "tgn:7005583",
          "tgn:1000001",
          "tgn:7005560",
          "tgn:7029392"
        ],
        "placetype": [
          "aat:300266554",
          "aat:300008699"
        ],
        "id": 7395159,
        "name:xx": "Sandía, Arroyo de la"
      }
    }
  ]
}
