{
  "geometry": {
    "type": "Point",
    "coordinates": [
      -75.7167,
      35.9167
    ]
  },
  "type": "Feature",
  "properties": {
    "hierarchy": [
      "tgn:2180309",
      "tgn:1000001",
      "tgn:7012149",
      "tgn:2001488",
      "tgn:7007709",
      "tgn:7029392"
    ],
    "placetype": [
      "aat:300132348"
    ],
    "id": 2180309,
    "name:xx": "Blockade Shoal"
  }
}
