{
  "type": "FeatureCollection",
  "features": [
    {
      "geometry": {
        "type": "Point",
        "coordinates": [
          -86.7167,
          38.5333
        ]
      },
      "type": "Feature",
      "properties": {
        "hierarchy": [
          "tgn:2201600",
          "tgn:1000001",
          "tgn:7012149",
          "tgn:2000546",
          "tgn:7007252",
          "tgn:7029392"
        ],
        "placetype": [
          "aat:300008706"
        ],
        "id": 2201600,
        "name:xx": "Buck Creek"
      }
    },
    {
      "geometry": {
        "type": "Point",
        "coordinates": [
          -86.2833,
          39.4167
        ]
      },
      "type": "Feature",
      "properties": {
        "hierarchy": [
          "tgn:2201601",
          "tgn:1000001",
          "tgn:7012149",
          "tgn:1002694",
          "tgn:7007252",
          "tgn:7029392"
        ],
        "placetype": [
          "aat:300008706"
        ],
        "id": 2201601,
        "name:xx": "Buck Creek"
      }
    },
    {
      "geometry": {
        "type": "Point",
        "coordinates": [
          -86.95,
          39.4667
        ]
      },
      "type": "Feature",
      "properties": {
        "hierarchy": [
          "tgn:2201602",
          "tgn:1000001",
          "tgn:2000540",
          "tgn:7012149",
          "tgn:7007252",
          "tgn:7029392"
        ],
        "placetype": [
          "aat:300008706"
        ],
        "id": 2201602,
        "name:xx": "Buck Creek"
      }
    },
    {
      "geometry": {
        "type": "Point",
        "coordinates": [
          -87.4667,
          39.8167
        ]
      },
      "type": "Feature",
      "properties": {
        "hierarchy": [
          "tgn:2201603",
          "tgn:1000001",
          "tgn:7012149",
          "tgn:2000558",
          "tgn:7007252",
          "tgn:7029392"
        ],
        "placetype": [
          "aat:300008706"
        ],
        "id": 2201603,
        "name:xx": "Buck Creek"
      }
    },
    {
      "geometry": {
        "type": "Point",
        "coordinates": [
          -85.3833,
          39.85
        ]
      },
      "type": "Feature",
      "properties": {
        "hierarchy": [
          "tgn:2201604",
          "tgn:1000001",
          "tgn:7012149",
          "tgn:1002468",
          "tgn:7007252",
          "tgn:7029392"
        ],
        "placetype": [
          "aat:300008706"
        ],
        "id": 2201604,
        "name:xx": "Buck Creek"
      }
    },
    {
      "geometry": {
        "type": "Point",
        "coordinates": [
          -86.1333,
          40.3
        ]
      },
      "type": "Feature",
      "properties": {
        "hierarchy": [
          "tgn:2201605",
          "tgn:1000001",
          "tgn:7012149",
          "tgn:1002947",
          "tgn:7007252",
          "tgn:7029392"
        ],
        "placetype": [
          "aat:300008706"
        ],
        "id": 2201605,
        "name:xx": "Buck Creek"
      }
    },
    {
      "geometry": {
        "type": "Point",
        "coordinates": [
          -85.4833,
          41.6333
        ]
      },
      "type": "Feature",
      "properties": {
        "hierarchy": [
          "tgn:2201606",
          "tgn:1000001",
          "tgn:7012149",
          "tgn:1002565",
          "tgn:7007252",
          "tgn:7029392"
        ],
        "placetype": [
          "aat:300008706"
        ],
        "id": 2201606,
        "name:xx": "Buck Creek"
      }
    },
    {
      "geometry": {
        "type": "Point",
        "coordinates": [
          -87.4167,
          39.1333
        ]
      },
      "type": "Feature",
      "properties": {
        "hierarchy": [
          "tgn:2201607",
          "tgn:1000001",
          "tgn:7012149",
          "tgn:2000556",
          "tgn:7007252",
          "tgn:7029392"
        ],
        "placetype": [
          "aat:300008706"
        ],
        "id": 2201607,
        "name:xx": "Buck Creek"
      }
    },
    {
      "geometry": {
        "type": "Point",
        "coordinates": [
          -86.75,
          40.4833
        ]
      },
      "type": "Feature",
      "properties": {
        "hierarchy": [
          "tgn:2201608",
          "tgn:1000001",
          "tgn:7012149",
          "tgn:1002946",
          "tgn:7007252",
          "tgn:7029392"
        ],
        "placetype": [
          "aat:300008706"
        ],
        "id": 2201608,
        "name:xx": "Buck Creek"
      }
    },
    {
      "geometry": {
        "type": "Point",
        "coordinates": [
          -87.1833,
          39.1
        ]
      },
      "type": "Feature",
      "properties": {
        "hierarchy": [
          "tgn:2201609",
          "tgn:1000001",
          "tgn:7012149",
          "tgn:2000544",
          "tgn:7007252",
          "tgn:7029392"
        ],
        "placetype": [
          "aat:300008706"
        ],
        "id": 2201609,
        "name:xx": "Buck Creek"
      }
    }
  ]
}
