{
  "geometry": {
    "type": "Point",
    "coordinates": [
      -81.8333,
      39.1833
    ]
  },
  "type": "Feature",
  "properties": {
    "hierarchy": [
      "tgn:2711617",
      "tgn:2001610",
      "tgn:1000001",
      "tgn:7012149",
      "tgn:7007706",
      "tgn:7029392"
    ],
    "placetype": [
      "aat:300008706"
    ],
    "id": 2711617,
    "name:xx": "Tar Creek"
  }
}
