{
  "geometry": {
    "type": "Point",
    "coordinates": [
      78.640833,
      29.82
    ]
  },
  "type": "Feature",
  "properties": {
    "hierarchy": [
      "tgn:7567488",
      "tgn:1000004",
      "tgn:7000198",
      "tgn:7031786",
      "tgn:7029392"
    ],
    "placetype": [
      "aat:300008865"
    ],
    "name:en": "Bhānkot Reserved Forest",
    "id": 7567488
  }
}
