{
  "geometry": {
    "type": "Point",
    "coordinates": [
      -102.5333,
      38.4333
    ]
  },
  "type": "Feature",
  "properties": {
    "hierarchy": [
      "tgn:2015329",
      "tgn:1000001",
      "tgn:7012149",
      "tgn:2000222",
      "tgn:7007158",
      "tgn:7029392"
    ],
    "placetype": [
      "aat:300008347"
    ],
    "id": 2015329,
    "name:xx": "Chivington"
  }
}
