{
  "geometry": {
    "type": "Point",
    "coordinates": [
      -87.1667,
      45.15
    ]
  },
  "type": "Feature",
  "properties": {
    "hierarchy": [
      "tgn:2121157",
      "tgn:1000001",
      "tgn:2002317",
      "tgn:7012149",
      "tgn:7007922",
      "tgn:7029392"
    ],
    "placetype": [
      "aat:300008347"
    ],
    "id": 2121157,
    "name:xx": "Ephraim"
  }
}
