{
  "geometry": {
    "type": "Point",
    "coordinates": [
      -72.3833,
      43.6667
    ]
  },
  "type": "Feature",
  "properties": {
    "hierarchy": [
      "tgn:2230700",
      "tgn:1000001",
      "tgn:2002136",
      "tgn:7012149",
      "tgn:7007828",
      "tgn:7029392"
    ],
    "placetype": [
      "aat:300008347"
    ],
    "id": 2230700,
    "name:xx": "Centerville"
  }
}
