{
  "geometry": {
    "type": "Point",
    "coordinates": [
      14.4167,
      44.5833
    ]
  },
  "type": "Feature",
  "properties": {
    "hierarchy": [
      "tgn:1007893",
      "tgn:7017299",
      "tgn:1000003",
      "tgn:7006663",
      "tgn:7029392"
    ],
    "placetype": [
      "aat:300008791"
    ],
    "id": 1007893,
    "name:xx": "Lošinj"
  }
}
