{
  "geometry": {
    "type": "Point",
    "coordinates": [
      -117.0833,
      34.6833
    ]
  },
  "type": "Feature",
  "properties": {
    "hierarchy": [
      "tgn:2696058",
      "tgn:1000001",
      "tgn:7012149",
      "tgn:7007157",
      "tgn:1002857",
      "tgn:7029392"
    ],
    "placetype": [
      "aat:300008761"
    ],
    "id": 2696058,
    "name:xx": "Stoddard Valley"
  }
}
