{
  "geometry": {
    "type": "Point",
    "coordinates": [
      15.4333,
      66.7667
    ]
  },
  "type": "Feature",
  "properties": {
    "hierarchy": [
      "tgn:1048625",
      "tgn:7003644",
      "tgn:1000003",
      "tgn:1000088",
      "tgn:7029392"
    ],
    "placetype": [
      "aat:300008347"
    ],
    "id": 1048625,
    "name:xx": "Lønsdal"
  }
}
