{
  "geometry": {
    "type": "Point",
    "coordinates": [
      -109.0667,
      44.8167
    ]
  },
  "type": "Feature",
  "properties": {
    "hierarchy": [
      "tgn:2133972",
      "tgn:1000001",
      "tgn:7012149",
      "tgn:2002379",
      "tgn:7007923",
      "tgn:7029392"
    ],
    "placetype": [
      "aat:300006191"
    ],
    "id": 2133972,
    "name:xx": "Angle Detention Dam"
  }
}
