{
  "geometry": {
    "type": "Point",
    "coordinates": [
      -105.35,
      43.9333
    ]
  },
  "type": "Feature",
  "properties": {
    "hierarchy": [
      "tgn:2464888",
      "tgn:1000001",
      "tgn:2002367",
      "tgn:7012149",
      "tgn:7007923",
      "tgn:7029392"
    ],
    "placetype": [
      "aat:300008798"
    ],
    "id": 2464888,
    "name:xx": "Logan, Mount"
  }
}
