{
  "geometry": {
    "type": "Point",
    "coordinates": [
      -75.9667,
      42.0167
    ]
  },
  "type": "Feature",
  "properties": {
    "hierarchy": [
      "tgn:2174940",
      "tgn:1000001",
      "tgn:1002206",
      "tgn:7012149",
      "tgn:7007568",
      "tgn:7029392"
    ],
    "placetype": [
      "aat:300008905"
    ],
    "id": 2174940,
    "name:xx": "Black Ash Swamp"
  }
}
