{
  "geometry": {
    "type": "Point",
    "coordinates": [
      -89.15,
      30.35
    ]
  },
  "type": "Feature",
  "properties": {
    "hierarchy": [
      "tgn:2056843",
      "tgn:1000001",
      "tgn:7012149",
      "tgn:2001109",
      "tgn:7007522",
      "tgn:7029392"
    ],
    "placetype": [
      "aat:300008347"
    ],
    "id": 2056843,
    "name:xx": "Long Beach"
  }
}
