{
  "geometry": {
    "type": "Point",
    "coordinates": [
      32.2833,
      4.4833
    ]
  },
  "type": "Feature",
  "properties": {
    "hierarchy": [
      "tgn:1094332",
      "tgn:7001242",
      "tgn:1001082",
      "tgn:7441551",
      "tgn:7029392"
    ],
    "placetype": [
      "aat:300008347"
    ],
    "id": 1094332,
    "name:xx": "Longairo"
  }
}
