{
  "geometry": {
    "type": "Point",
    "coordinates": [
      -114.4667,
      47.75
    ]
  },
  "type": "Feature",
  "properties": {
    "hierarchy": [
      "tgn:2702310",
      "tgn:1000001",
      "tgn:7012149",
      "tgn:7007524",
      "tgn:7029392"
    ],
    "placetype": [
      "aat:300008761"
    ],
    "id": 2702310,
    "name:xx": "Sullivan Gulch"
  }
}
