{
  "geometry": {
    "type": "Point",
    "coordinates": [
      -83.8167,
      35.5167
    ]
  },
  "type": "Feature",
  "properties": {
    "hierarchy": [
      "tgn:2529147",
      "tgn:1000001",
      "tgn:2001841",
      "tgn:7012149",
      "tgn:7007825",
      "tgn:7029392"
    ],
    "placetype": [
      "aat:300008699"
    ],
    "id": 2529147,
    "name:xx": "Mud Gap Branch"
  }
}
