{
  "geometry": {
    "type": "Point",
    "coordinates": [
      -79.2667,
      41.1667
    ]
  },
  "type": "Feature",
  "properties": {
    "hierarchy": [
      "tgn:2089221",
      "tgn:1000001",
      "tgn:1002272",
      "tgn:7012149",
      "tgn:7007710",
      "tgn:7029392"
    ],
    "placetype": [
      "aat:300387016"
    ],
    "id": 2089221,
    "name:xx": "Henderson"
  }
}
