{
  "geometry": {
    "type": "Point",
    "coordinates": [
      31.842255,
      30.11316
    ]
  },
  "type": "Feature",
  "properties": {
    "hierarchy": [
      "tgn:7520769",
      "tgn:7001242",
      "tgn:7016833",
      "tgn:1001091",
      "tgn:7029392"
    ],
    "placetype": [
      "aat:300008773",
      "aat:300379998"
    ],
    "name:en": "Abū 'Allāwī, Wādī",
    "id": 7520769
  }
}
