{
  "geometry": {
    "type": "Point",
    "coordinates": [
      -94.4333,
      38.5333
    ]
  },
  "type": "Feature",
  "properties": {
    "hierarchy": [
      "tgn:2386933",
      "tgn:1000001",
      "tgn:2001182",
      "tgn:7012149",
      "tgn:7007523",
      "tgn:7029392"
    ],
    "placetype": [
      "aat:300008798"
    ],
    "id": 2386933,
    "name:xx": "Herrell Hill"
  }
}
