{
  "geometry": {
    "type": "Point",
    "coordinates": [
      -121.05,
      44.4333
    ]
  },
  "type": "Feature",
  "properties": {
    "hierarchy": [
      "tgn:2465642",
      "tgn:1000001",
      "tgn:7012149",
      "tgn:7007708",
      "tgn:7029392"
    ],
    "placetype": [
      "aat:300008706"
    ],
    "id": 2465642,
    "name:xx": "Lone Pine Creek"
  }
}
