{
  "geometry": {
    "type": "Point",
    "coordinates": [
      -115.75,
      31.016667
    ]
  },
  "type": "Feature",
  "properties": {
    "hierarchy": [
      "tgn:7394765",
      "tgn:1001835",
      "tgn:1000001",
      "tgn:7005560",
      "tgn:7029392"
    ],
    "placetype": [
      "aat:300008347"
    ],
    "id": 7394765,
    "name:xx": "San José de Castillo"
  }
}
