{
  "geometry": {
    "type": "Point",
    "coordinates": [
      -86.4333,
      36.75
    ]
  },
  "type": "Feature",
  "properties": {
    "hierarchy": [
      "tgn:2039099",
      "tgn:1000001",
      "tgn:7012149",
      "tgn:2000842",
      "tgn:7007255",
      "tgn:7029392"
    ],
    "placetype": [
      "aat:300008347",
      "aat:300387210"
    ],
    "id": 2039099,
    "name:xx": "Gold City"
  }
}
