{
  "geometry": {
    "type": "Point",
    "coordinates": [
      -106.0167,
      37.0167
    ]
  },
  "type": "Feature",
  "properties": {
    "hierarchy": [
      "tgn:2016258",
      "tgn:1000001",
      "tgn:2000202",
      "tgn:7012149",
      "tgn:7007158",
      "tgn:7029392"
    ],
    "placetype": [
      "aat:300008347"
    ],
    "id": 2016258,
    "name:xx": "San Antonio"
  }
}
