{
  "geometry": {
    "type": "Point",
    "coordinates": [
      -118.4333,
      46.0333
    ]
  },
  "type": "Feature",
  "properties": {
    "hierarchy": [
      "tgn:2289710",
      "tgn:1000001",
      "tgn:7012149",
      "tgn:2002251",
      "tgn:7007920",
      "tgn:7029392"
    ],
    "placetype": [
      "aat:300008706"
    ],
    "id": 2289710,
    "name:xx": "Doan Creek"
  }
}
