{
  "geometry": {
    "type": "Point",
    "coordinates": [
      118.7833,
      26.1667
    ]
  },
  "type": "Feature",
  "properties": {
    "hierarchy": [
      "tgn:1066706",
      "tgn:1000004",
      "tgn:7001796",
      "tgn:1000111",
      "tgn:7029392"
    ],
    "placetype": [
      "aat:300008347"
    ],
    "id": 1066706,
    "name:xx": "Baiyundu"
  }
}
