{
  "geometry": {
    "type": "Point",
    "coordinates": [
      -105.7333,
      36.1833
    ]
  },
  "type": "Feature",
  "properties": {
    "hierarchy": [
      "tgn:2316698",
      "tgn:1000001",
      "tgn:7012149",
      "tgn:7007566",
      "tgn:7029392"
    ],
    "placetype": [
      "aat:300008706"
    ],
    "id": 2316698,
    "name:xx": "Embudo Creek"
  }
}
