{
  "geometry": {
    "type": "Point",
    "coordinates": [
      14.1167,
      58.6833
    ]
  },
  "type": "Feature",
  "properties": {
    "hierarchy": [
      "tgn:1063720",
      "tgn:1000003",
      "tgn:7024620",
      "tgn:1000097",
      "tgn:7029392"
    ],
    "placetype": [
      "aat:300008347"
    ],
    "id": 1063720,
    "name:xx": "Töreboda"
  }
}
