{
  "geometry": {
    "type": "Point",
    "coordinates": [
      65.9333,
      29.4167
    ]
  },
  "type": "Feature",
  "properties": {
    "hierarchy": [
      "tgn:1083333",
      "tgn:7000360",
      "tgn:1000004",
      "tgn:1000133",
      "tgn:7029392"
    ],
    "placetype": [
      "aat:300008347"
    ],
    "id": 1083333,
    "name:xx": "Ahmad Wāl"
  }
}
