{
  "geometry": {
    "type": "Point",
    "coordinates": [
      18.65,
      -13.7333
    ]
  },
  "type": "Feature",
  "properties": {
    "hierarchy": [
      "tgn:1087730",
      "tgn:7001242",
      "tgn:1000149",
      "tgn:1000899",
      "tgn:7029392"
    ],
    "placetype": [
      "aat:300008347"
    ],
    "id": 1087730,
    "name:xx": "Chá Pungana"
  }
}
