{
  "geometry": {
    "type": "Point",
    "coordinates": [
      -85.9667,
      38.1167
    ]
  },
  "type": "Feature",
  "properties": {
    "hierarchy": [
      "tgn:2323613",
      "tgn:1000001",
      "tgn:7012149",
      "tgn:1002457",
      "tgn:7007252",
      "tgn:7029392"
    ],
    "placetype": [
      "aat:300008680"
    ],
    "id": 2323613,
    "name:xx": "Farris Lake"
  }
}
