{
  "type": "FeatureCollection",
  "features": [
    {
      "geometry": {
        "type": "Point",
        "coordinates": [
          15.7833,
          -4.8333
        ]
      },
      "type": "Feature",
      "properties": {
        "hierarchy": [
          "tgn:1089120",
          "tgn:7001242",
          "tgn:1001359",
          "tgn:1000159",
          "tgn:7029392"
        ],
        "placetype": [
          "aat:300008347"
        ],
        "id": 1089120,
        "name:xx": "Kikimi"
      }
    },
    {
      "geometry": {
        "type": "Point",
        "coordinates": [
          18.8333,
          -5.6167
        ]
      },
      "type": "Feature",
      "properties": {
        "hierarchy": [
          "tgn:1089121",
          "tgn:1001143",
          "tgn:7001242",
          "tgn:1000159",
          "tgn:7029392"
        ],
        "placetype": [
          "aat:300008347"
        ],
        "id": 1089121,
        "name:xx": "Kikombo"
      }
    },
    {
      "geometry": {
        "type": "Point",
        "coordinates": [
          17.2833,
          -4.2667
        ]
      },
      "type": "Feature",
      "properties": {
        "hierarchy": [
          "tgn:1089122",
          "tgn:1001143",
          "tgn:7001242",
          "tgn:1000159",
          "tgn:7029392"
        ],
        "placetype": [
          "aat:300008347"
        ],
        "id": 1089122,
        "name:xx": "Kikongo"
      }
    },
    {
      "geometry": {
        "type": "Point",
        "coordinates": [
          19.9,
          -5.7833
        ]
      },
      "type": "Feature",
      "properties": {
        "hierarchy": [
          "tgn:1089124",
          "tgn:1001143",
          "tgn:7001242",
          "tgn:1000159",
          "tgn:7029392"
        ],
        "placetype": [
          "aat:300008347"
        ],
        "id": 1089124,
        "name:xx": "Kilembe"
      }
    },
    {
      "geometry": {
        "type": "Point",
        "coordinates": [
          29.2,
          -0.9833
        ]
      },
      "type": "Feature",
      "properties": {
        "hierarchy": [
          "tgn:1089125",
          "tgn:7001242",
          "tgn:7016707",
          "tgn:1000159",
          "tgn:7029392"
        ],
        "placetype": [
          "aat:300008347"
        ],
        "id": 1089125,
        "name:xx": "Kilima"
      }
    },
    {
      "geometry": {
        "type": "Point",
        "coordinates": [
          30.2333,
          1.8
        ]
      },
      "type": "Feature",
      "properties": {
        "hierarchy": [
          "tgn:1089126",
          "tgn:7001242",
          "tgn:7016755",
          "tgn:1000159",
          "tgn:7029392"
        ],
        "placetype": [
          "aat:300008347"
        ],
        "id": 1089126,
        "name:xx": "Kilomines"
      }
    },
    {
      "geometry": {
        "type": "Point",
        "coordinates": [
          26.7,
          -1.4333
        ]
      },
      "type": "Feature",
      "properties": {
        "hierarchy": [
          "tgn:1089128",
          "tgn:7001242",
          "tgn:7016707",
          "tgn:1000159",
          "tgn:7029392"
        ],
        "placetype": [
          "aat:300008347"
        ],
        "id": 1089128,
        "name:xx": "Kima"
      }
    },
    {
      "geometry": {
        "type": "Point",
        "coordinates": [
          18.5,
          -4.2667
        ]
      },
      "type": "Feature",
      "properties": {
        "hierarchy": [
          "tgn:1089129",
          "tgn:1001143",
          "tgn:7001242",
          "tgn:1000159",
          "tgn:7029392"
        ],
        "placetype": [
          "aat:300008347"
        ],
        "id": 1089129,
        "name:xx": "Kimbanda"
      }
    }
  ]
}
