{
  "geometry": {
    "type": "Point",
    "coordinates": [
      -113.6667,
      32.25
    ]
  },
  "type": "Feature",
  "properties": {
    "hierarchy": [
      "tgn:2295334",
      "tgn:1000001",
      "tgn:7006451",
      "tgn:7012149",
      "tgn:2000104",
      "tgn:7029392"
    ],
    "placetype": [
      "aat:300266640"
    ],
    "id": 2295334,
    "name:xx": "Drift Hills"
  }
}
