{
  "geometry": {
    "type": "Point",
    "coordinates": [
      -94.6833,
      39.55
    ]
  },
  "type": "Feature",
  "properties": {
    "hierarchy": [
      "tgn:2587210",
      "tgn:1000001",
      "tgn:2001175",
      "tgn:7012149",
      "tgn:7007523",
      "tgn:7029392"
    ],
    "placetype": [
      "aat:300008347"
    ],
    "id": 2587210,
    "name:xx": "Platte River"
  }
}
