{
  "type": "FeatureCollection",
  "features": [
    {
      "geometry": {
        "type": "Point",
        "coordinates": [
          -99.118056,
          21.25
        ]
      },
      "type": "Feature",
      "properties": {
        "hierarchy": [
          "tgn:7400100",
          "tgn:1000001",
          "tgn:7005593",
          "tgn:7005560",
          "tgn:7029392"
        ],
        "placetype": [
          "aat:300008347"
        ],
        "id": 7400100,
        "name:xx": "Río Verdito"
      }
    },
    {
      "geometry": {
        "type": "Point",
        "coordinates": [
          -99.1,
          21.266667
        ]
      },
      "type": "Feature",
      "properties": {
        "hierarchy": [
          "tgn:7400102",
          "tgn:1000001",
          "tgn:7005593",
          "tgn:7005560",
          "tgn:7029392"
        ],
        "placetype": [
          "aat:300008767"
        ],
        "id": 7400102,
        "name:xx": "Arroyo Hondo, Barranca"
      }
    },
    {
      "geometry": {
        "type": "Point",
        "coordinates": [
          -99.172222,
          21.291667
        ]
      },
      "type": "Feature",
      "properties": {
        "hierarchy": [
          "tgn:7400103",
          "tgn:1000001",
          "tgn:7005593",
          "tgn:7005560",
          "tgn:7029392"
        ],
        "placetype": [
          "aat:300008795"
        ],
        "id": 7400103,
        "name:xx": "Cuchilla Alta de Santa Anita, Cerro"
      }
    },
    {
      "geometry": {
        "type": "Point",
        "coordinates": [
          -99.172222,
          21.318056
        ]
      },
      "type": "Feature",
      "properties": {
        "hierarchy": [
          "tgn:7400105",
          "tgn:1000001",
          "tgn:7005593",
          "tgn:7005560",
          "tgn:7029392"
        ],
        "placetype": [
          "aat:300008347"
        ],
        "id": 7400105,
        "name:xx": "Pinalito de la Cruz"
      }
    },
    {
      "geometry": {
        "type": "Point",
        "coordinates": [
          -99.2,
          21.266667
        ]
      },
      "type": "Feature",
      "properties": {
        "hierarchy": [
          "tgn:7400106",
          "tgn:1000001",
          "tgn:7005593",
          "tgn:7005560",
          "tgn:7029392"
        ],
        "placetype": [
          "aat:300008767"
        ],
        "id": 7400106,
        "name:xx": "Cumbi, Barranca"
      }
    },
    {
      "geometry": {
        "type": "Point",
        "coordinates": [
          -99.2,
          21.369444
        ]
      },
      "type": "Feature",
      "properties": {
        "hierarchy": [
          "tgn:7400107",
          "tgn:1000001",
          "tgn:7005593",
          "tgn:7005560",
          "tgn:7029392"
        ],
        "placetype": [
          "aat:300008347"
        ],
        "id": 7400107,
        "name:xx": "Valle de Guadalupe"
      }
    },
    {
      "geometry": {
        "type": "Point",
        "coordinates": [
          -99.195833,
          21.384722
        ]
      },
      "type": "Feature",
      "properties": {
        "hierarchy": [
          "tgn:7400108",
          "tgn:1000001",
          "tgn:7005593",
          "tgn:7005560",
          "tgn:7029392"
        ],
        "placetype": [
          "aat:300008347"
        ],
        "id": 7400108,
        "name:xx": "El Charco"
      }
    },
    {
      "geometry": {
        "type": "Point",
        "coordinates": [
          -99.25,
          21.4
        ]
      },
      "type": "Feature",
      "properties": {
        "hierarchy": [
          "tgn:7400109",
          "tgn:1000001",
          "tgn:7005593",
          "tgn:7005560",
          "tgn:7029392"
        ],
        "placetype": [
          "aat:300008347"
        ],
        "id": 7400109,
        "name:xx": "El Cañon"
      }
    }
  ]
}
