{
  "type": "FeatureCollection",
  "features": [
    {
      "geometry": {
        "type": "Point",
        "coordinates": [
          -112.9333,
          41.15
        ]
      },
      "type": "Feature",
      "properties": {
        "hierarchy": [
          "tgn:2397050",
          "tgn:1000001",
          "tgn:2002102",
          "tgn:7012149",
          "tgn:7007827",
          "tgn:7029392"
        ],
        "placetype": [
          "aat:300008798"
        ],
        "id": 2397050,
        "name:xx": "Homestead Knoll"
      }
    },
    {
      "geometry": {
        "type": "Point",
        "coordinates": [
          -149.85,
          61.5
        ]
      },
      "type": "Feature",
      "properties": {
        "hierarchy": [
          "tgn:2397051",
          "tgn:7006450",
          "tgn:1000001",
          "tgn:2124053",
          "tgn:7012149",
          "tgn:7029392"
        ],
        "placetype": [
          "aat:300008680"
        ],
        "id": 2397051,
        "name:xx": "Homestead Lake"
      }
    },
    {
      "geometry": {
        "type": "Point",
        "coordinates": [
          -87.55,
          37.1667
        ]
      },
      "type": "Feature",
      "properties": {
        "hierarchy": [
          "tgn:2397052",
          "tgn:1000001",
          "tgn:7012149",
          "tgn:2000801",
          "tgn:7007255",
          "tgn:7029392"
        ],
        "placetype": [
          "aat:300006191"
        ],
        "id": 2397052,
        "name:xx": "Homestead Lake"
      }
    },
    {
      "geometry": {
        "type": "Point",
        "coordinates": [
          -85.45,
          46.6333
        ]
      },
      "type": "Feature",
      "properties": {
        "hierarchy": [
          "tgn:2397053",
          "tgn:1000001",
          "tgn:7012149",
          "tgn:2000972",
          "tgn:7007520",
          "tgn:7029392"
        ],
        "placetype": [
          "aat:300008680"
        ],
        "id": 2397053,
        "name:xx": "Homestead Lake"
      }
    },
    {
      "geometry": {
        "type": "Point",
        "coordinates": [
          -91.1667,
          47.6333
        ]
      },
      "type": "Feature",
      "properties": {
        "hierarchy": [
          "tgn:2397054",
          "tgn:1000001",
          "tgn:7012149",
          "tgn:2001036",
          "tgn:7007521",
          "tgn:7029392"
        ],
        "placetype": [
          "aat:300008680"
        ],
        "id": 2397054,
        "name:xx": "Homestead Lake"
      }
    },
    {
      "geometry": {
        "type": "Point",
        "coordinates": [
          -93.5167,
          47.6833
        ]
      },
      "type": "Feature",
      "properties": {
        "hierarchy": [
          "tgn:2397055",
          "tgn:1000001",
          "tgn:7012149",
          "tgn:2001029",
          "tgn:7007521",
          "tgn:7029392"
        ],
        "placetype": [
          "aat:300008680"
        ],
        "id": 2397055,
        "name:xx": "Homestead Lake"
      }
    },
    {
      "geometry": {
        "type": "Point",
        "coordinates": [
          -104.5833,
          48.3667
        ]
      },
      "type": "Feature",
      "properties": {
        "hierarchy": [
          "tgn:2397056",
          "tgn:1000001",
          "tgn:7012149",
          "tgn:7007524",
          "tgn:7029392"
        ],
        "placetype": [
          "aat:300006191"
        ],
        "id": 2397056,
        "name:xx": "Homestead Lake"
      }
    },
    {
      "geometry": {
        "type": "Point",
        "coordinates": [
          -104.5667,
          48.4
        ]
      },
      "type": "Feature",
      "properties": {
        "hierarchy": [
          "tgn:2397057",
          "tgn:1000001",
          "tgn:7012149",
          "tgn:2001305",
          "tgn:7007524",
          "tgn:7029392"
        ],
        "placetype": [
          "aat:300006191"
        ],
        "id": 2397057,
        "name:xx": "Homestead Lake"
      }
    },
    {
      "geometry": {
        "type": "Point",
        "coordinates": [
          -102.6,
          41.8833
        ]
      },
      "type": "Feature",
      "properties": {
        "hierarchy": [
          "tgn:2397058",
          "tgn:1000001",
          "tgn:2001350",
          "tgn:7012149",
          "tgn:7007525",
          "tgn:7029392"
        ],
        "placetype": [
          "aat:300008680"
        ],
        "id": 2397058,
        "name:xx": "Homestead Lake"
      }
    },
    {
      "geometry": {
        "type": "Point",
        "coordinates": [
          -100.55,
          42.45
        ]
      },
      "type": "Feature",
      "properties": {
        "hierarchy": [
          "tgn:2397059",
          "tgn:1000001",
          "tgn:2001331",
          "tgn:7012149",
          "tgn:7007525",
          "tgn:7029392"
        ],
        "placetype": [
          "aat:300008680"
        ],
        "id": 2397059,
        "name:xx": "Homestead Lake"
      }
    }
  ]
}
