{
  "type": "FeatureCollection",
  "features": [
    {
      "geometry": {
        "type": "Point",
        "coordinates": [
          -105.662222,
          24.116667
        ]
      },
      "type": "Feature",
      "properties": {
        "hierarchy": [
          "tgn:7374760",
          "tgn:7005583",
          "tgn:1000001",
          "tgn:7005560",
          "tgn:7029392"
        ],
        "placetype": [
          "aat:300000241"
        ],
        "id": 7374760,
        "name:xx": "Rancho La Boquilla"
      }
    },
    {
      "geometry": {
        "type": "Point",
        "coordinates": [
          -102.65,
          29.133333
        ]
      },
      "type": "Feature",
      "properties": {
        "hierarchy": [
          "tgn:7374761",
          "tgn:1001853",
          "tgn:1000001",
          "tgn:7005560",
          "tgn:7029392"
        ],
        "placetype": [
          "aat:300259572"
        ],
        "id": 7374761,
        "name:xx": "La Boquilla, Puerto"
      }
    },
    {
      "geometry": {
        "type": "Point",
        "coordinates": [
          -102.316667,
          27.65
        ]
      },
      "type": "Feature",
      "properties": {
        "hierarchy": [
          "tgn:7374762",
          "tgn:1001853",
          "tgn:1000001",
          "tgn:7005560",
          "tgn:7029392"
        ],
        "placetype": [
          "aat:300259572"
        ],
        "id": 7374762,
        "name:xx": "La Boquilla, Puerto"
      }
    },
    {
      "geometry": {
        "type": "Point",
        "coordinates": [
          -104.766667,
          29.25
        ]
      },
      "type": "Feature",
      "properties": {
        "hierarchy": [
          "tgn:7374763",
          "tgn:7005581",
          "tgn:1000001",
          "tgn:7005560",
          "tgn:7029392"
        ],
        "placetype": [
          "aat:300008795"
        ],
        "id": 7374763,
        "name:xx": "La Boquilla, Cerro"
      }
    },
    {
      "geometry": {
        "type": "Point",
        "coordinates": [
          -103.9,
          23.583333
        ]
      },
      "type": "Feature",
      "properties": {
        "hierarchy": [
          "tgn:7374764",
          "tgn:1000001",
          "tgn:7005601",
          "tgn:7005560",
          "tgn:7029392"
        ],
        "placetype": [
          "aat:300007783"
        ],
        "id": 7374764,
        "name:xx": "La Boquilla"
      }
    },
    {
      "geometry": {
        "type": "Point",
        "coordinates": [
          -104.733333,
          29.25
        ]
      },
      "type": "Feature",
      "properties": {
        "hierarchy": [
          "tgn:7374765",
          "tgn:7005581",
          "tgn:1000001",
          "tgn:7005560",
          "tgn:7029392"
        ],
        "placetype": [
          "aat:300008347"
        ],
        "id": 7374765,
        "name:xx": "La Boquilla"
      }
    },
    {
      "geometry": {
        "type": "Point",
        "coordinates": [
          -108.033333,
          29.133333
        ]
      },
      "type": "Feature",
      "properties": {
        "hierarchy": [
          "tgn:7374766",
          "tgn:7005581",
          "tgn:1000001",
          "tgn:7005560",
          "tgn:7029392"
        ],
        "placetype": [
          "aat:300008347"
        ],
        "id": 7374766,
        "name:xx": "La Boquilla"
      }
    },
    {
      "geometry": {
        "type": "Point",
        "coordinates": [
          -107.2,
          28.516667
        ]
      },
      "type": "Feature",
      "properties": {
        "hierarchy": [
          "tgn:7374767",
          "tgn:7005581",
          "tgn:1000001",
          "tgn:7005560",
          "tgn:7029392"
        ],
        "placetype": [
          "aat:300008347"
        ],
        "id": 7374767,
        "name:xx": "La Boquilla"
      }
    },
    {
      "geometry": {
        "type": "Point",
        "coordinates": [
          -107.45,
          28.4
        ]
      },
      "type": "Feature",
      "properties": {
        "hierarchy": [
          "tgn:7374768",
          "tgn:7005581",
          "tgn:1000001",
          "tgn:7005560",
          "tgn:7029392"
        ],
        "placetype": [
          "aat:300008347"
        ],
        "id": 7374768,
        "name:xx": "La Boquilla"
      }
    },
    {
      "geometry": {
        "type": "Point",
        "coordinates": [
          -105.416667,
          28.483333
        ]
      },
      "type": "Feature",
      "properties": {
        "hierarchy": [
          "tgn:7374769",
          "tgn:7005581",
          "tgn:1000001",
          "tgn:7005560",
          "tgn:7029392"
        ],
        "placetype": [
          "aat:300008347"
        ],
        "id": 7374769,
        "name:xx": "La Boquilla"
      }
    }
  ]
}
