{
  "geometry": {
    "type": "Point",
    "coordinates": [
      -81.7833,
      31.45
    ]
  },
  "type": "Feature",
  "properties": {
    "hierarchy": [
      "tgn:2368962",
      "tgn:1000001",
      "tgn:7012149",
      "tgn:2000442",
      "tgn:7007248",
      "tgn:7029392"
    ],
    "placetype": [
      "aat:300008699"
    ],
    "id": 2368962,
    "name:xx": "Gum Branch"
  }
}
