{
  "geometry": {
    "type": "Point",
    "coordinates": [
      -115.3333,
      45.1833
    ]
  },
  "type": "Feature",
  "properties": {
    "hierarchy": [
      "tgn:2757078",
      "tgn:1000001",
      "tgn:7012149",
      "tgn:2000494",
      "tgn:7007250",
      "tgn:7029392"
    ],
    "placetype": [
      "aat:300000390"
    ],
    "id": 2757078,
    "name:xx": "Werdenhoff Mine"
  }
}
