{
  "geometry": {
    "type": "Point",
    "coordinates": [
      75.728796,
      25.929658
    ]
  },
  "type": "Feature",
  "properties": {
    "hierarchy": [
      "tgn:7570083",
      "tgn:1000004",
      "tgn:7000198",
      "tgn:7016788",
      "tgn:7029392"
    ],
    "placetype": [
      "aat:300008347"
    ],
    "name:en": "Hāroti",
    "id": 7570083
  }
}
