{
  "geometry": {
    "type": "Point",
    "coordinates": [
      -116.2833,
      38.6167
    ]
  },
  "type": "Feature",
  "properties": {
    "hierarchy": [
      "tgn:2402634",
      "tgn:1000001",
      "tgn:2001418",
      "tgn:7012149",
      "tgn:7007526",
      "tgn:7029392"
    ],
    "placetype": [
      "aat:300008798"
    ],
    "id": 2402634,
    "name:xx": "Hot Creek North Summit"
  }
}
