{
  "geometry": {
    "type": "Point",
    "coordinates": [
      -152.2167,
      62.8833
    ]
  },
  "type": "Feature",
  "properties": {
    "hierarchy": [
      "tgn:2458095",
      "tgn:7006450",
      "tgn:1000001",
      "tgn:7030547",
      "tgn:7012149",
      "tgn:7029392"
    ],
    "placetype": [
      "aat:300008798"
    ],
    "id": 2458095,
    "name:xx": "Little Mountain"
  }
}
