{
  "geometry": {
    "type": "Point",
    "coordinates": [
      -120.8667,
      45.9167
    ]
  },
  "type": "Feature",
  "properties": {
    "hierarchy": [
      "tgn:2222365",
      "tgn:1000001",
      "tgn:7012149",
      "tgn:1002554",
      "tgn:7007920",
      "tgn:7029392"
    ],
    "placetype": [
      "aat:300008680"
    ],
    "id": 2222365,
    "name:xx": "Carp Lake"
  }
}
