{
  "geometry": {
    "type": "Point",
    "coordinates": [
      -75.85,
      39.1833
    ]
  },
  "type": "Feature",
  "properties": {
    "hierarchy": [
      "tgn:2048858",
      "tgn:1000001",
      "tgn:2124025",
      "tgn:7012149",
      "tgn:7007516",
      "tgn:7029392"
    ],
    "placetype": [
      "aat:300008347"
    ],
    "id": 2048858,
    "name:xx": "Sudlersville"
  }
}
