{
  "geometry": {
    "type": "Point",
    "coordinates": [
      -118.5333,
      36.7167
    ]
  },
  "type": "Feature",
  "properties": {
    "hierarchy": [
      "tgn:2684274",
      "tgn:1000001",
      "tgn:7012149",
      "tgn:7007157",
      "tgn:1002956",
      "tgn:7029392"
    ],
    "placetype": [
      "aat:300266640"
    ],
    "id": 2684274,
    "name:xx": "Sphinx Crest"
  }
}
