{
  "geometry": {
    "type": "Point",
    "coordinates": [
      89.05,
      26.783333
    ]
  },
  "type": "Feature",
  "properties": {
    "hierarchy": [
      "tgn:7552980",
      "tgn:1000004",
      "tgn:7000198",
      "tgn:1001977",
      "tgn:7029392"
    ],
    "placetype": [
      "aat:300387502"
    ],
    "name:en": "Marāghāt Tea Garden",
    "id": 7552980
  }
}
