{
  "geometry": {
    "type": "Point",
    "coordinates": [
      69.05,
      40.2667
    ]
  },
  "type": "Feature",
  "properties": {
    "hierarchy": [
      "tgn:1053613",
      "tgn:1000004",
      "tgn:7012255",
      "tgn:7006661",
      "tgn:7029392"
    ],
    "placetype": [
      "aat:300008347"
    ],
    "id": 1053613,
    "name:xx": "Dimitrovskoye"
  }
}
