{
  "geometry": {
    "type": "Point",
    "coordinates": [
      -85.2333,
      42.4333
    ]
  },
  "type": "Feature",
  "properties": {
    "hierarchy": [
      "tgn:2685981",
      "tgn:1000001",
      "tgn:7012149",
      "tgn:7007520",
      "tgn:7029392"
    ],
    "placetype": [
      "aat:300008699"
    ],
    "id": 2685981,
    "name:xx": "Spring Brook"
  }
}
