{
  "type": "FeatureCollection",
  "features": [
    {
      "geometry": {
        "type": "Point",
        "coordinates": [
          11.316667,
          45.916667
        ]
      },
      "type": "Feature",
      "properties": {
        "hierarchy": [
          "tgn:7053780",
          "tgn:7003008",
          "tgn:1000003",
          "tgn:7002997",
          "tgn:1000080",
          "tgn:7029392"
        ],
        "placetype": [
          "aat:300008347"
        ],
        "id": 7053780,
        "name:xx": "Luserna"
      }
    },
    {
      "geometry": {
        "type": "Point",
        "coordinates": [
          12.283333,
          45.216667
        ]
      },
      "type": "Feature",
      "properties": {
        "hierarchy": [
          "tgn:7053781",
          "tgn:7003006",
          "tgn:1000003",
          "tgn:7002997",
          "tgn:1000080",
          "tgn:7029392"
        ],
        "placetype": [
          "aat:300008679"
        ],
        "id": 7053781,
        "name:xx": "Lusenzo, Laguna di"
      }
    },
    {
      "geometry": {
        "type": "Point",
        "coordinates": [
          11.116667,
          43.1
        ]
      },
      "type": "Feature",
      "properties": {
        "hierarchy": [
          "tgn:7053783",
          "tgn:7003168",
          "tgn:1000003",
          "tgn:7009760",
          "tgn:1000080",
          "tgn:7029392"
        ],
        "placetype": [
          "aat:300008347"
        ],
        "id": 7053783,
        "name:xx": "Luriano"
      }
    },
    {
      "geometry": {
        "type": "Point",
        "coordinates": [
          8.9,
          40.916667
        ]
      },
      "type": "Feature",
      "properties": {
        "hierarchy": [
          "tgn:7053784",
          "tgn:7015163",
          "tgn:1000003",
          "tgn:7003121",
          "tgn:1000080",
          "tgn:7029392"
        ],
        "placetype": [
          "aat:300008347"
        ],
        "id": 7053784,
        "name:xx": "Lu Bozzoni"
      }
    },
    {
      "geometry": {
        "type": "Point",
        "coordinates": [
          9.016667,
          45.766667
        ]
      },
      "type": "Feature",
      "properties": {
        "hierarchy": [
          "tgn:7053785",
          "tgn:7005852",
          "tgn:1000003",
          "tgn:7003237",
          "tgn:1000080",
          "tgn:7029392"
        ],
        "placetype": [
          "aat:300008347"
        ],
        "id": 7053785,
        "name:xx": "Lurate Caccivio"
      }
    },
    {
      "geometry": {
        "type": "Point",
        "coordinates": [
          9,
          45.766667
        ]
      },
      "type": "Feature",
      "properties": {
        "hierarchy": [
          "tgn:7053786",
          "tgn:7005852",
          "tgn:1000003",
          "tgn:7003237",
          "tgn:1000080",
          "tgn:7029392"
        ],
        "placetype": [
          "aat:300387198",
          "aat:300265612"
        ],
        "id": 7053786,
        "name:xx": "Lurate Caccivio"
      }
    },
    {
      "geometry": {
        "type": "Point",
        "coordinates": [
          12.366667,
          44.933333
        ]
      },
      "type": "Feature",
      "properties": {
        "hierarchy": [
          "tgn:7053787",
          "tgn:7002995",
          "tgn:1000003",
          "tgn:7002997",
          "tgn:1000080",
          "tgn:7029392"
        ],
        "placetype": [
          "aat:300008347"
        ],
        "id": 7053787,
        "name:xx": "Porto Tolle"
      }
    },
    {
      "geometry": {
        "type": "Point",
        "coordinates": [
          8.4,
          39.2
        ]
      },
      "type": "Feature",
      "properties": {
        "hierarchy": [
          "tgn:7053788",
          "tgn:1001641",
          "tgn:1000003",
          "tgn:7003121",
          "tgn:1000080",
          "tgn:7029392"
        ],
        "placetype": [
          "aat:300004847"
        ],
        "id": 7053788,
        "name:xx": "Torre Portoscuso"
      }
    }
  ]
}
