{
  "geometry": {
    "type": "Point",
    "coordinates": [
      -104.5333,
      44.4667
    ]
  },
  "type": "Feature",
  "properties": {
    "hierarchy": [
      "tgn:2647487",
      "tgn:1000001",
      "tgn:2002370",
      "tgn:7012149",
      "tgn:7007923",
      "tgn:7029392"
    ],
    "placetype": [
      "aat:300266640"
    ],
    "id": 2647487,
    "name:xx": "Schoepf Divide"
  }
}
