{
  "geometry": {
    "type": "Point",
    "coordinates": [
      -92.1333,
      32.0167
    ]
  },
  "type": "Feature",
  "properties": {
    "hierarchy": [
      "tgn:2042531",
      "tgn:1000001",
      "tgn:2000864",
      "tgn:7012149",
      "tgn:7007256",
      "tgn:7029392"
    ],
    "placetype": [
      "aat:300008347"
    ],
    "id": 2042531,
    "name:xx": "Clarks"
  }
}
