{
  "geometry": {
    "type": "Point",
    "coordinates": [
      -105.7167,
      32.9833
    ]
  },
  "type": "Feature",
  "properties": {
    "hierarchy": [
      "tgn:2664230",
      "tgn:1000001",
      "tgn:7012149",
      "tgn:2001447",
      "tgn:7007566",
      "tgn:7029392"
    ],
    "placetype": [
      "aat:300008706"
    ],
    "id": 2664230,
    "name:xx": "Silver Springs Creek"
  }
}
