{
  "type": "FeatureCollection",
  "features": [
    {
      "geometry": {
        "type": "Point",
        "coordinates": [
          -106.5,
          32.4333
        ]
      },
      "type": "Feature",
      "properties": {
        "hierarchy": [
          "tgn:2354180",
          "tgn:1000001",
          "tgn:2001435",
          "tgn:7012149",
          "tgn:7007566",
          "tgn:7029392"
        ],
        "placetype": [
          "aat:300000390"
        ],
        "id": 2354180,
        "name:xx": "Golden Lily Prospect"
      }
    },
    {
      "geometry": {
        "type": "Point",
        "coordinates": [
          -117.1167,
          40.5167
        ]
      },
      "type": "Feature",
      "properties": {
        "hierarchy": [
          "tgn:2354181",
          "tgn:1000001",
          "tgn:2001415",
          "tgn:7012149",
          "tgn:7007526",
          "tgn:7029392"
        ],
        "placetype": [
          "aat:300000390"
        ],
        "id": 2354181,
        "name:xx": "Golden Line Mine"
      }
    },
    {
      "geometry": {
        "type": "Point",
        "coordinates": [
          -93.65,
          32.4333
        ]
      },
      "type": "Feature",
      "properties": {
        "hierarchy": [
          "tgn:2354182",
          "tgn:1000001",
          "tgn:2000861",
          "tgn:7012149",
          "tgn:7007256",
          "tgn:7029392"
        ],
        "placetype": [
          "aat:300008347"
        ],
        "id": 2354182,
        "name:xx": "Golden Meadows"
      }
    },
    {
      "geometry": {
        "type": "Point",
        "coordinates": [
          -84.1,
          35.9667
        ]
      },
      "type": "Feature",
      "properties": {
        "hierarchy": [
          "tgn:2354183",
          "tgn:1000001",
          "tgn:7012149",
          "tgn:2001883",
          "tgn:7007825",
          "tgn:7029392"
        ],
        "placetype": [
          "aat:300008347"
        ],
        "id": 2354183,
        "name:xx": "Golden Meadows"
      }
    },
    {
      "geometry": {
        "type": "Point",
        "coordinates": [
          -111.9,
          40.8667
        ]
      },
      "type": "Feature",
      "properties": {
        "hierarchy": [
          "tgn:2354184",
          "tgn:1000001",
          "tgn:2002106",
          "tgn:7012149",
          "tgn:7007827",
          "tgn:7029392"
        ],
        "placetype": [
          "aat:300008347"
        ],
        "id": 2354184,
        "name:xx": "Golden Meadows"
      }
    },
    {
      "geometry": {
        "type": "Point",
        "coordinates": [
          -89.4,
          32.5667
        ]
      },
      "type": "Feature",
      "properties": {
        "hierarchy": [
          "tgn:2354185",
          "tgn:1000001",
          "tgn:7012149",
          "tgn:2001147",
          "tgn:7007522",
          "tgn:7029392"
        ],
        "placetype": [
          "aat:300006191"
        ],
        "id": 2354185,
        "name:xx": "Golden Memorial Park Lake"
      }
    },
    {
      "geometry": {
        "type": "Point",
        "coordinates": [
          -114.1333,
          35.9167
        ]
      },
      "type": "Feature",
      "properties": {
        "hierarchy": [
          "tgn:2354187",
          "tgn:1000001",
          "tgn:7006451",
          "tgn:7012149",
          "tgn:2000098",
          "tgn:7029392"
        ],
        "placetype": [
          "aat:300000390"
        ],
        "id": 2354187,
        "name:xx": "Golden Mile Mine"
      }
    },
    {
      "geometry": {
        "type": "Point",
        "coordinates": [
          -117.8333,
          38.5167
        ]
      },
      "type": "Feature",
      "properties": {
        "hierarchy": [
          "tgn:2354188",
          "tgn:1000001",
          "tgn:2001417",
          "tgn:7012149",
          "tgn:7007526",
          "tgn:7029392"
        ],
        "placetype": [
          "aat:300000390"
        ],
        "id": 2354188,
        "name:xx": "Golden Mile Mine"
      }
    },
    {
      "geometry": {
        "type": "Point",
        "coordinates": [
          -112.0167,
          45.9
        ]
      },
      "type": "Feature",
      "properties": {
        "hierarchy": [
          "tgn:2354189",
          "tgn:1000001",
          "tgn:7012149",
          "tgn:2001281",
          "tgn:7007524",
          "tgn:7029392"
        ],
        "placetype": [
          "aat:300000390"
        ],
        "id": 2354189,
        "name:xx": "Golden Mine"
      }
    }
  ]
}
