{
  "type": "FeatureCollection",
  "features": [
    {
      "geometry": {
        "type": "Point",
        "coordinates": [
          -81.6,
          36.0167
        ]
      },
      "type": "Feature",
      "properties": {
        "hierarchy": [
          "tgn:2621420",
          "tgn:1000001",
          "tgn:2001476",
          "tgn:7012149",
          "tgn:7007709",
          "tgn:7029392"
        ],
        "placetype": [
          "aat:300008706"
        ],
        "id": 2621420,
        "name:xx": "Roaring Creek"
      }
    },
    {
      "geometry": {
        "type": "Point",
        "coordinates": [
          -97.9167,
          34.8
        ]
      },
      "type": "Feature",
      "properties": {
        "hierarchy": [
          "tgn:2621421",
          "tgn:1000001",
          "tgn:2001648",
          "tgn:7012149",
          "tgn:7007707",
          "tgn:7029392"
        ],
        "placetype": [
          "aat:300008706"
        ],
        "id": 2621421,
        "name:xx": "Roaring Creek"
      }
    },
    {
      "geometry": {
        "type": "Point",
        "coordinates": [
          -121.7,
          44.5167
        ]
      },
      "type": "Feature",
      "properties": {
        "hierarchy": [
          "tgn:2621422",
          "tgn:1000001",
          "tgn:7012149",
          "tgn:2001712",
          "tgn:7007708",
          "tgn:7029392"
        ],
        "placetype": [
          "aat:300008706"
        ],
        "id": 2621422,
        "name:xx": "Roaring Creek"
      }
    },
    {
      "geometry": {
        "type": "Point",
        "coordinates": [
          -123.3333,
          45.4333
        ]
      },
      "type": "Feature",
      "properties": {
        "hierarchy": [
          "tgn:2621423",
          "tgn:1000001",
          "tgn:7012149",
          "tgn:1002994",
          "tgn:7007708",
          "tgn:7029392"
        ],
        "placetype": [
          "aat:300008706"
        ],
        "id": 2621423,
        "name:xx": "Roaring Creek"
      }
    },
    {
      "geometry": {
        "type": "Point",
        "coordinates": [
          -123.2167,
          46.05
        ]
      },
      "type": "Feature",
      "properties": {
        "hierarchy": [
          "tgn:2621424",
          "tgn:1000001",
          "tgn:1002293",
          "tgn:7012149",
          "tgn:7007708",
          "tgn:7029392"
        ],
        "placetype": [
          "aat:300008706"
        ],
        "id": 2621424,
        "name:xx": "Roaring Creek"
      }
    },
    {
      "geometry": {
        "type": "Point",
        "coordinates": [
          -121.85,
          44.7667
        ]
      },
      "type": "Feature",
      "properties": {
        "hierarchy": [
          "tgn:2621425",
          "tgn:1000001",
          "tgn:7012149",
          "tgn:1002636",
          "tgn:7007708",
          "tgn:7029392"
        ],
        "placetype": [
          "aat:300008706"
        ],
        "id": 2621425,
        "name:xx": "Roaring Creek"
      }
    },
    {
      "geometry": {
        "type": "Point",
        "coordinates": [
          -122.7833,
          44.3833
        ]
      },
      "type": "Feature",
      "properties": {
        "hierarchy": [
          "tgn:2621426",
          "tgn:1000001",
          "tgn:7012149",
          "tgn:2001717",
          "tgn:7007708",
          "tgn:7029392"
        ],
        "placetype": [
          "aat:300008706"
        ],
        "id": 2621426,
        "name:xx": "Roaring Creek"
      }
    },
    {
      "geometry": {
        "type": "Point",
        "coordinates": [
          -76.2833,
          40.8833
        ]
      },
      "type": "Feature",
      "properties": {
        "hierarchy": [
          "tgn:2621427",
          "tgn:1000001",
          "tgn:7012149",
          "tgn:7007710",
          "tgn:7029392"
        ],
        "placetype": [
          "aat:300008706"
        ],
        "id": 2621427,
        "name:xx": "Roaring Creek"
      }
    },
    {
      "geometry": {
        "type": "Point",
        "coordinates": [
          -84.2833,
          36.1167
        ]
      },
      "type": "Feature",
      "properties": {
        "hierarchy": [
          "tgn:2621428",
          "tgn:2001837",
          "tgn:1000001",
          "tgn:7012149",
          "tgn:7007825",
          "tgn:7029392"
        ],
        "placetype": [
          "aat:300008706"
        ],
        "id": 2621428,
        "name:xx": "Roaring Creek"
      }
    },
    {
      "geometry": {
        "type": "Point",
        "coordinates": [
          -84.25,
          36.1833
        ]
      },
      "type": "Feature",
      "properties": {
        "hierarchy": [
          "tgn:2621429",
          "tgn:1000001",
          "tgn:7012149",
          "tgn:2001843",
          "tgn:7007825",
          "tgn:7029392"
        ],
        "placetype": [
          "aat:300008706"
        ],
        "id": 2621429,
        "name:xx": "Roaring Creek"
      }
    }
  ]
}
