{
  "geometry": {
    "type": "Point",
    "coordinates": [
      -87.6833,
      36.2167
    ]
  },
  "type": "Feature",
  "properties": {
    "hierarchy": [
      "tgn:2733857",
      "tgn:1000001",
      "tgn:7012149",
      "tgn:2001878",
      "tgn:7007825",
      "tgn:7029392"
    ],
    "placetype": [
      "aat:300008761"
    ],
    "id": 2733857,
    "name:xx": "Turner Hollow"
  }
}
