{
  "geometry": {
    "type": "Point",
    "coordinates": [
      -114.35,
      34.0833
    ]
  },
  "type": "Feature",
  "properties": {
    "hierarchy": [
      "tgn:2735024",
      "tgn:1000001",
      "tgn:7006451",
      "tgn:7012149",
      "tgn:2000104",
      "tgn:7029392"
    ],
    "placetype": [
      "aat:300006075"
    ],
    "id": 2735024,
    "name:xx": "Twenty-seven R, Lateral"
  }
}
