{
  "geometry": {
    "type": "Point",
    "coordinates": [
      -89.05,
      34.0167
    ]
  },
  "type": "Feature",
  "properties": {
    "hierarchy": [
      "tgn:2758642",
      "tgn:1000001",
      "tgn:2001094",
      "tgn:7012149",
      "tgn:7007522",
      "tgn:7029392"
    ],
    "placetype": [
      "aat:300008706"
    ],
    "id": 2758642,
    "name:xx": "West Creek"
  }
}
