{
  "geometry": {
    "type": "Point",
    "coordinates": [
      -75.9667,
      35.6833
    ]
  },
  "type": "Feature",
  "properties": {
    "hierarchy": [
      "tgn:2764509",
      "tgn:1000001",
      "tgn:7012149",
      "tgn:2001488",
      "tgn:7007709",
      "tgn:7029392"
    ],
    "placetype": [
      "aat:300008680"
    ],
    "id": 2764509,
    "name:xx": "Whipping Creek Lake"
  }
}
