{
  "geometry": {
    "type": "Point",
    "coordinates": [
      -79.5333,
      41.0667
    ]
  },
  "type": "Feature",
  "properties": {
    "hierarchy": [
      "tgn:2723436",
      "tgn:1000001",
      "tgn:1002272",
      "tgn:7012149",
      "tgn:7007710",
      "tgn:7029392"
    ],
    "placetype": [
      "aat:300008347"
    ],
    "id": 2723436,
    "name:xx": "Toby"
  }
}
