{
  "geometry": {
    "type": "Point",
    "coordinates": [
      -78.5833,
      36.3833
    ]
  },
  "type": "Feature",
  "properties": {
    "hierarchy": [
      "tgn:2415107",
      "tgn:1000001",
      "tgn:7012149",
      "tgn:7029392"
    ],
    "placetype": [
      "aat:300008706"
    ],
    "id": 2415107,
    "name:xx": "Island Creek"
  }
}
