{
  "geometry": {
    "type": "Point",
    "coordinates": [
      -122.0333,
      37.8667
    ]
  },
  "type": "Feature",
  "properties": {
    "hierarchy": [
      "tgn:1111761",
      "tgn:1000001",
      "tgn:7012149",
      "tgn:7007157",
      "tgn:7029392"
    ],
    "placetype": [
      "aat:300008761"
    ],
    "id": 1111761,
    "name:xx": "San Ramon Valley"
  }
}
