{
  "geometry": {
    "type": "Point",
    "coordinates": [
      -87.6667,
      35.4833
    ]
  },
  "type": "Feature",
  "properties": {
    "hierarchy": [
      "tgn:2731079",
      "tgn:1000001",
      "tgn:7012149",
      "tgn:7007825",
      "tgn:7029392"
    ],
    "placetype": [
      "aat:300008699"
    ],
    "id": 2731079,
    "name:xx": "Tucker Branch"
  }
}
