{
  "geometry": {
    "type": "Point",
    "coordinates": [
      -90.0167,
      46.2333
    ]
  },
  "type": "Feature",
  "properties": {
    "hierarchy": [
      "tgn:2282806",
      "tgn:1000001",
      "tgn:7012149",
      "tgn:2002327",
      "tgn:7007922",
      "tgn:7029392"
    ],
    "placetype": [
      "aat:300008680"
    ],
    "id": 2282806,
    "name:xx": "Deertail Lake"
  }
}
