{
  "geometry": {
    "type": "Point",
    "coordinates": [
      -135.45,
      56.7667
    ]
  },
  "type": "Feature",
  "properties": {
    "hierarchy": [
      "tgn:2423693",
      "tgn:7006450",
      "tgn:1000001",
      "tgn:7012149",
      "tgn:2124002",
      "tgn:7029392"
    ],
    "placetype": [
      "aat:300008791"
    ],
    "id": 2423693,
    "name:xx": "John Rock"
  }
}
