{
  "geometry": {
    "type": "Point",
    "coordinates": [
      -89.5833,
      44.3333
    ]
  },
  "type": "Feature",
  "properties": {
    "hierarchy": [
      "tgn:2552011",
      "tgn:1000001",
      "tgn:7012149",
      "tgn:2002347",
      "tgn:7007922",
      "tgn:7029392"
    ],
    "placetype": [
      "aat:300006075"
    ],
    "id": 2552011,
    "name:xx": "Number Four, Ditch"
  }
}
