{
  "geometry": {
    "type": "Point",
    "coordinates": [
      25.301836,
      29.246639
    ]
  },
  "type": "Feature",
  "properties": {
    "hierarchy": [
      "tgn:7537012",
      "tgn:7001242",
      "tgn:7016833",
      "tgn:1001418",
      "tgn:7029392"
    ],
    "placetype": [
      "aat:300008777"
    ],
    "name:en": "Ḩājj Raḩḩūmah, Qārat al",
    "id": 7537012
  }
}
