{
  "geometry": {
    "type": "Point",
    "coordinates": [
      -80.65,
      39.6833
    ]
  },
  "type": "Feature",
  "properties": {
    "hierarchy": [
      "tgn:2395731",
      "tgn:1000001",
      "tgn:7012149",
      "tgn:2002301",
      "tgn:7013961",
      "tgn:7029392"
    ],
    "placetype": [
      "aat:300266640"
    ],
    "id": 2395731,
    "name:xx": "Hollman Ridge"
  }
}
