{
  "geometry": {
    "type": "Point",
    "coordinates": [
      -111.0167,
      48.25
    ]
  },
  "type": "Feature",
  "properties": {
    "hierarchy": [
      "tgn:2600531",
      "tgn:1000001",
      "tgn:7012149",
      "tgn:2001285",
      "tgn:7007524",
      "tgn:7029392"
    ],
    "placetype": [
      "aat:300006191"
    ],
    "id": 2600531,
    "name:xx": "Pugsley Reservoir"
  }
}
