{
  "geometry": {
    "type": "Point",
    "coordinates": [
      -94.9667,
      29.65
    ]
  },
  "type": "Feature",
  "properties": {
    "hierarchy": [
      "tgn:1006339",
      "tgn:1000001",
      "tgn:7012149",
      "tgn:1002251",
      "tgn:7007826",
      "tgn:7029392"
    ],
    "placetype": [
      "aat:300008791"
    ],
    "id": 1006339,
    "name:xx": "Atkinson Island"
  }
}
