{
  "geometry": {
    "type": "Point",
    "coordinates": [
      -99.7333,
      29.85
    ]
  },
  "type": "Feature",
  "properties": {
    "hierarchy": [
      "tgn:2618146",
      "tgn:1000001",
      "tgn:7012149",
      "tgn:2002060",
      "tgn:7007826",
      "tgn:7029392"
    ],
    "placetype": [
      "aat:300008706"
    ],
    "id": 2618146,
    "name:xx": "Riemer Creek"
  }
}
