{
  "geometry": {
    "type": "Point",
    "coordinates": [
      18.9667,
      12.2333
    ]
  },
  "type": "Feature",
  "properties": {
    "hierarchy": [
      "tgn:1104796",
      "tgn:7001242",
      "tgn:1000979",
      "tgn:1000156",
      "tgn:7029392"
    ],
    "placetype": [
      "aat:300008795"
    ],
    "id": 1104796,
    "name:xx": "GUédi, Mont"
  }
}
