{
  "geometry": {
    "type": "Point",
    "coordinates": [
      -112.3833,
      34.3833
    ]
  },
  "type": "Feature",
  "properties": {
    "hierarchy": [
      "tgn:2496178",
      "tgn:1000001",
      "tgn:7006451",
      "tgn:7012149",
      "tgn:2000103",
      "tgn:7029392"
    ],
    "placetype": [
      "aat:300000390"
    ],
    "id": 2496178,
    "name:xx": "Mastadon Mine"
  }
}
