{
  "geometry": {
    "type": "Point",
    "coordinates": [
      31.933333,
      31.45
    ]
  },
  "type": "Feature",
  "properties": {
    "hierarchy": [
      "tgn:7533836",
      "tgn:7001242",
      "tgn:7016833",
      "tgn:1001225",
      "tgn:7029392"
    ],
    "placetype": [
      "aat:300266559"
    ],
    "name:en": "Ḩanash, Ţawwāl al",
    "id": 7533836
  }
}
