{
  "geometry": {
    "type": "Point",
    "coordinates": [
      -78.3333,
      41.0167
    ]
  },
  "type": "Feature",
  "properties": {
    "hierarchy": [
      "tgn:2091141",
      "tgn:1000001",
      "tgn:1002278",
      "tgn:7012149",
      "tgn:7007710",
      "tgn:7029392"
    ],
    "placetype": [
      "aat:300008347",
      "aat:300387210"
    ],
    "id": 2091141,
    "name:xx": "Needful"
  }
}
