{
  "geometry": {
    "type": "Point",
    "coordinates": [
      -91.4667,
      36.4333
    ]
  },
  "type": "Feature",
  "properties": {
    "hierarchy": [
      "tgn:2766762",
      "tgn:1000001",
      "tgn:7016172",
      "tgn:7012149",
      "tgn:2000129",
      "tgn:7029392"
    ],
    "placetype": [
      "aat:300008697"
    ],
    "id": 2766762,
    "name:xx": "White Oak Spring"
  }
}
