{
  "type": "FeatureCollection",
  "features": [
    {
      "geometry": {
        "type": "Point",
        "coordinates": [
          -78.5,
          -8
        ]
      },
      "type": "Feature",
      "properties": {
        "hierarchy": [
          "tgn:1000660",
          "tgn:1000002",
          "tgn:1000056",
          "tgn:7029392"
        ],
        "placetype": [
          "aat:300387064",
          "aat:300000772",
          "aat:300236112"
        ],
        "id": 1000660,
        "name:xx": "La Libertad"
      }
    },
    {
      "geometry": {
        "type": "Point",
        "coordinates": [
          -87.9167,
          14.0833
        ]
      },
      "type": "Feature",
      "properties": {
        "hierarchy": [
          "tgn:1000661",
          "tgn:1000001",
          "tgn:7005554",
          "tgn:7029392"
        ],
        "placetype": [
          "aat:300387064",
          "aat:300000772"
        ],
        "id": 1000661,
        "name:xx": "La Paz"
      }
    },
    {
      "geometry": {
        "type": "Point",
        "coordinates": [
          -68,
          -15.5
        ]
      },
      "type": "Feature",
      "properties": {
        "hierarchy": [
          "tgn:1000662",
          "tgn:1000046",
          "tgn:1000002",
          "tgn:7029392"
        ],
        "placetype": [
          "aat:300387064",
          "aat:300000772"
        ],
        "id": 1000662,
        "name:xx": "La Paz"
      }
    },
    {
      "geometry": {
        "type": "Point",
        "coordinates": [
          2.666,
          33.583
        ]
      },
      "type": "Feature",
      "properties": {
        "hierarchy": [
          "tgn:1000663",
          "tgn:7001242",
          "tgn:7016752",
          "tgn:7029392"
        ],
        "placetype": [
          "aat:300387064",
          "aat:300000772"
        ],
        "id": 1000663,
        "name:xx": "Laghouat"
      }
    },
    {
      "geometry": {
        "type": "Point",
        "coordinates": [
          -5.75,
          5.8333
        ]
      },
      "type": "Feature",
      "properties": {
        "hierarchy": [
          "tgn:1000664",
          "tgn:7001242",
          "tgn:1000168",
          "tgn:7029392"
        ],
        "placetype": [
          "aat:300387064",
          "aat:300000772"
        ],
        "id": 1000664,
        "name:xx": "Lakota, Département de"
      }
    },
    {
      "geometry": {
        "type": "Point",
        "coordinates": [
          -80,
          -6.3333
        ]
      },
      "type": "Feature",
      "properties": {
        "hierarchy": [
          "tgn:1000665",
          "tgn:1000002",
          "tgn:1000056",
          "tgn:7029392"
        ],
        "placetype": [
          "aat:300387064",
          "aat:300000772",
          "aat:300236112"
        ],
        "id": 1000665,
        "name:xx": "Lambayeque"
      }
    },
    {
      "geometry": {
        "type": "Point",
        "coordinates": [
          -86.5833,
          12.5833
        ]
      },
      "type": "Feature",
      "properties": {
        "hierarchy": [
          "tgn:1000667",
          "tgn:1000001",
          "tgn:7005562",
          "tgn:7029392"
        ],
        "placetype": [
          "aat:300387064",
          "aat:300000772"
        ],
        "id": 1000667,
        "name:xx": "León"
      }
    },
    {
      "geometry": {
        "type": "Point",
        "coordinates": [
          3,
          35.8333
        ]
      },
      "type": "Feature",
      "properties": {
        "hierarchy": [
          "tgn:1000668",
          "tgn:7001242",
          "tgn:7016752",
          "tgn:7029392"
        ],
        "placetype": [
          "aat:300387064",
          "aat:300000772"
        ],
        "id": 1000668,
        "name:xx": "Médéa"
      }
    },
    {
      "geometry": {
        "type": "Point",
        "coordinates": [
          -88.5833,
          14.5
        ]
      },
      "type": "Feature",
      "properties": {
        "hierarchy": [
          "tgn:1000669",
          "tgn:1000001",
          "tgn:7005554",
          "tgn:7029392"
        ],
        "placetype": [
          "aat:300387064",
          "aat:300000772"
        ],
        "id": 1000669,
        "name:xx": "Lempira"
      }
    }
  ]
}
