{
  "geometry": {
    "type": "Point",
    "coordinates": [
      -90.6667,
      39.4667
    ]
  },
  "type": "Feature",
  "properties": {
    "hierarchy": [
      "tgn:2165262",
      "tgn:1000001",
      "tgn:7012149",
      "tgn:7007251",
      "tgn:7029392"
    ],
    "placetype": [
      "aat:300008706"
    ],
    "id": 2165262,
    "name:xx": "Bettell Creek"
  }
}
