{
  "geometry": {
    "type": "Point",
    "coordinates": [
      31.2351,
      30.006462
    ]
  },
  "type": "Feature",
  "properties": {
    "hierarchy": [
      "tgn:7529804",
      "tgn:7001242",
      "tgn:7016833",
      "tgn:1001091",
      "tgn:7029392"
    ],
    "placetype": [
      "aat:300004792"
    ],
    "id": 7529804,
    "name:xx": "Al Muqāwilūn al 'Arab Qiţā' al Taḩarrukāt wa Idārat al Maḩājir"
  }
}
