{
  "geometry": {
    "type": "Point",
    "coordinates": [
      -120.65,
      37.9833
    ]
  },
  "type": "Feature",
  "properties": {
    "hierarchy": [
      "tgn:2388645",
      "tgn:1000001",
      "tgn:1002219",
      "tgn:7012149",
      "tgn:7007157",
      "tgn:7029392"
    ],
    "placetype": [
      "aat:300008697"
    ],
    "id": 2388645,
    "name:xx": "Hicks Spring"
  }
}
