{
  "geometry": {
    "type": "Point",
    "coordinates": [
      79.793784,
      26.715479
    ]
  },
  "type": "Feature",
  "properties": {
    "hierarchy": [
      "tgn:7566426",
      "tgn:1000004",
      "tgn:7000198",
      "tgn:7016722",
      "tgn:7029392"
    ],
    "placetype": [
      "aat:300008347"
    ],
    "name:en": "Nawāda Kachhwāin",
    "id": 7566426
  }
}
