{
  "geometry": {
    "type": "Point",
    "coordinates": [
      -70.15,
      -19.95
    ]
  },
  "type": "Feature",
  "properties": {
    "hierarchy": [
      "tgn:7275227",
      "tgn:7002464",
      "tgn:1000049",
      "tgn:1000002",
      "tgn:7029392"
    ],
    "placetype": [
      "aat:300011692"
    ],
    "id": 7275227,
    "name:xx": "Unión, Rocas"
  }
}
