{
  "geometry": {
    "type": "Point",
    "coordinates": [
      -81.15,
      43.0167
    ]
  },
  "type": "Feature",
  "properties": {
    "hierarchy": [
      "tgn:1014703",
      "tgn:7005685",
      "tgn:1000001",
      "tgn:7013154",
      "tgn:7029392"
    ],
    "placetype": [
      "aat:300008347"
    ],
    "id": 1014703,
    "name:xx": "Crumlin"
  }
}
