{
  "geometry": {
    "type": "Point",
    "coordinates": [
      21.483,
      55.35
    ]
  },
  "type": "Feature",
  "properties": {
    "hierarchy": [
      "tgn:7006607",
      "tgn:1000003",
      "tgn:7006542",
      "tgn:7029392"
    ],
    "placetype": [
      "aat:300387064",
      "aat:300265612",
      "aat:300387081"
    ],
    "id": 7006607,
    "name:xx": "Šilutė"
  }
}
