{
  "geometry": {
    "type": "Point",
    "coordinates": [
      -83.1667,
      37.85
    ]
  },
  "type": "Feature",
  "properties": {
    "hierarchy": [
      "tgn:2289207",
      "tgn:1000001",
      "tgn:7012149",
      "tgn:2000828",
      "tgn:7007255",
      "tgn:7029392"
    ],
    "placetype": [
      "aat:300266640"
    ],
    "id": 2289207,
    "name:xx": "Dividing Ridge"
  }
}
