{
  "geometry": {
    "type": "Point",
    "coordinates": [
      -76.1833,
      42.9333
    ]
  },
  "type": "Feature",
  "properties": {
    "hierarchy": [
      "tgn:2366335",
      "tgn:1000001",
      "tgn:7012149",
      "tgn:1002746",
      "tgn:7007568",
      "tgn:7029392"
    ],
    "placetype": [
      "aat:300008347"
    ],
    "id": 2366335,
    "name:xx": "Griffins Corners"
  }
}
