{
  "geometry": {
    "type": "Point",
    "coordinates": [
      -94.0667,
      35.0333
    ]
  },
  "type": "Feature",
  "properties": {
    "hierarchy": [
      "tgn:2709941",
      "tgn:1000001",
      "tgn:7016172",
      "tgn:7012149",
      "tgn:2000146",
      "tgn:7029392"
    ],
    "placetype": [
      "aat:300008680"
    ],
    "id": 2709941,
    "name:xx": "Takima, Lake"
  }
}
