{
  "geometry": {
    "type": "Point",
    "coordinates": [
      -98.7833,
      37.4167
    ]
  },
  "type": "Feature",
  "properties": {
    "hierarchy": [
      "tgn:2677853",
      "tgn:2000663",
      "tgn:1000001",
      "tgn:7012149",
      "tgn:7007254",
      "tgn:7029392"
    ],
    "placetype": [
      "aat:300008706"
    ],
    "id": 2677853,
    "name:xx": "South Elm Creek"
  }
}
