{
  "geometry": {
    "type": "Point",
    "coordinates": [
      -119.0167,
      37.4667
    ]
  },
  "type": "Feature",
  "properties": {
    "hierarchy": [
      "tgn:2661326",
      "tgn:1000001",
      "tgn:7012149",
      "tgn:1002392",
      "tgn:7007157",
      "tgn:7029392"
    ],
    "placetype": [
      "aat:300008680"
    ],
    "id": 2661326,
    "name:xx": "Shorty Lake"
  }
}
