{
  "geometry": {
    "type": "Point",
    "coordinates": [
      -75.6667,
      39.3333
    ]
  },
  "type": "Feature",
  "properties": {
    "hierarchy": [
      "tgn:2177983",
      "tgn:7014201",
      "tgn:1000001",
      "tgn:7012149",
      "tgn:7007239",
      "tgn:7029392"
    ],
    "placetype": [
      "aat:300008863"
    ],
    "id": 2177983,
    "name:xx": "Blackbird State Forest Tybout Tract"
  }
}
