{
  "geometry": {
    "type": "Point",
    "coordinates": [
      -108.8667,
      44.9833
    ]
  },
  "type": "Feature",
  "properties": {
    "hierarchy": [
      "tgn:2314093",
      "tgn:1000001",
      "tgn:7012149",
      "tgn:2002379",
      "tgn:7007923",
      "tgn:7029392"
    ],
    "placetype": [
      "aat:300386845"
    ],
    "id": 2314093,
    "name:xx": "Elk Basin"
  }
}
