{
  "geometry": {
    "type": "Point",
    "coordinates": [
      -104.983333,
      19.35
    ]
  },
  "type": "Feature",
  "properties": {
    "hierarchy": [
      "tgn:1128878",
      "tgn:7005586",
      "tgn:1000001",
      "tgn:7005560",
      "tgn:7029392"
    ],
    "placetype": [
      "aat:300008707",
      "aat:300008699"
    ],
    "id": 1128878,
    "name:xx": "Purificación"
  }
}
