{
  "geometry": {
    "type": "Point",
    "coordinates": [
      31.81366,
      26.288534
    ]
  },
  "type": "Feature",
  "properties": {
    "hierarchy": [
      "tgn:7523644",
      "tgn:7001242",
      "tgn:7016833",
      "tgn:7001334",
      "tgn:7029392"
    ],
    "placetype": [
      "aat:300008347"
    ],
    "name:en": "Bayt Dāwūd Sahl",
    "id": 7523644
  }
}
