{
  "geometry": {
    "type": "Point",
    "coordinates": [
      31.218859,
      30.651635
    ]
  },
  "type": "Feature",
  "properties": {
    "hierarchy": [
      "tgn:7540399",
      "tgn:7001242",
      "tgn:7016833",
      "tgn:7001312",
      "tgn:7029392"
    ],
    "placetype": [
      "aat:300008347"
    ],
    "name:en": "Minshāt aş Şabbāḩī",
    "id": 7540399
  }
}
