{
  "geometry": {
    "type": "Point",
    "coordinates": [
      -123.15,
      44.7833
    ]
  },
  "type": "Feature",
  "properties": {
    "hierarchy": [
      "tgn:2299614",
      "tgn:1000001",
      "tgn:7012149",
      "tgn:1002794",
      "tgn:7007708",
      "tgn:7029392"
    ],
    "placetype": [
      "aat:300008699"
    ],
    "id": 2299614,
    "name:xx": "Duck Slough"
  }
}
