{
  "geometry": {
    "type": "Point",
    "coordinates": [
      -84.2833,
      30.3833
    ]
  },
  "type": "Feature",
  "properties": {
    "hierarchy": [
      "tgn:2385912",
      "tgn:1000001",
      "tgn:7012149",
      "tgn:2000276",
      "tgn:7007240",
      "tgn:7029392"
    ],
    "placetype": [
      "aat:300008347"
    ],
    "id": 2385912,
    "name:xx": "Henrietta"
  }
}
