{
  "type": "FeatureCollection",
  "features": [
    {
      "geometry": {
        "type": "Point",
        "coordinates": [
          5.039812,
          50.281268
        ]
      },
      "type": "Feature",
      "properties": {
        "hierarchy": [
          "tgn:7245680",
          "tgn:7003466",
          "tgn:1000003",
          "tgn:1000063",
          "tgn:4012014",
          "tgn:7029392"
        ],
        "placetype": [
          "aat:300008863"
        ],
        "id": 7245680,
        "name:xx": "Ciney, Bois de"
      }
    },
    {
      "geometry": {
        "type": "Point",
        "coordinates": [
          4,
          51.15
        ]
      },
      "type": "Feature",
      "properties": {
        "hierarchy": [
          "tgn:7245683",
          "tgn:7003457",
          "tgn:1000003",
          "tgn:1000063",
          "tgn:7018236",
          "tgn:7029392"
        ],
        "placetype": [
          "aat:300008699"
        ],
        "id": 7245683,
        "name:xx": "Brugsvaardeken"
      }
    },
    {
      "geometry": {
        "type": "Point",
        "coordinates": [
          3.9,
          51.05
        ]
      },
      "type": "Feature",
      "properties": {
        "hierarchy": [
          "tgn:7245684",
          "tgn:7003457",
          "tgn:1000003",
          "tgn:1000063",
          "tgn:7018236",
          "tgn:7029392"
        ],
        "placetype": [
          "aat:300008347"
        ],
        "id": 7245684,
        "name:xx": "Brugstraat"
      }
    },
    {
      "geometry": {
        "type": "Point",
        "coordinates": [
          4.166667,
          51.15
        ]
      },
      "type": "Feature",
      "properties": {
        "hierarchy": [
          "tgn:7245685",
          "tgn:7003457",
          "tgn:1000003",
          "tgn:1000063",
          "tgn:7018236",
          "tgn:7029392"
        ],
        "placetype": [
          "aat:300008347"
        ],
        "id": 7245685,
        "name:xx": "Brugsken"
      }
    },
    {
      "geometry": {
        "type": "Point",
        "coordinates": [
          3.966667,
          51
        ]
      },
      "type": "Feature",
      "properties": {
        "hierarchy": [
          "tgn:7245686",
          "tgn:7003457",
          "tgn:1000003",
          "tgn:1000063",
          "tgn:7018236",
          "tgn:7029392"
        ],
        "placetype": [
          "aat:300008347"
        ],
        "id": 7245686,
        "name:xx": "Brugsken"
      }
    },
    {
      "geometry": {
        "type": "Point",
        "coordinates": [
          4.033333,
          51.2
        ]
      },
      "type": "Feature",
      "properties": {
        "hierarchy": [
          "tgn:7245687",
          "tgn:7003457",
          "tgn:1000003",
          "tgn:1000063",
          "tgn:7018236",
          "tgn:7029392"
        ],
        "placetype": [
          "aat:300008347"
        ],
        "id": 7245687,
        "name:xx": "Bruggewijk"
      }
    },
    {
      "geometry": {
        "type": "Point",
        "coordinates": [
          3.497378,
          51.099047
        ]
      },
      "type": "Feature",
      "properties": {
        "hierarchy": [
          "tgn:7245688",
          "tgn:7003457",
          "tgn:1000003",
          "tgn:1000063",
          "tgn:7018236",
          "tgn:7029392"
        ],
        "placetype": [
          "aat:300008347"
        ],
        "id": 7245688,
        "name:xx": "Bruggewijk"
      }
    },
    {
      "geometry": {
        "type": "Point",
        "coordinates": [
          4.117128,
          50.75864
        ]
      },
      "type": "Feature",
      "properties": {
        "hierarchy": [
          "tgn:7245689",
          "tgn:7003457",
          "tgn:1000003",
          "tgn:1000063",
          "tgn:7018236",
          "tgn:7029392"
        ],
        "placetype": [
          "aat:300008699"
        ],
        "id": 7245689,
        "name:xx": "Bruggeplasbeek"
      }
    }
  ]
}
