{
  "geometry": {
    "type": "Point",
    "coordinates": [
      24.0833,
      49.9833
    ]
  },
  "type": "Feature",
  "properties": {
    "hierarchy": [
      "tgn:1056050",
      "tgn:1000003",
      "tgn:7011664",
      "tgn:7006660",
      "tgn:7029392"
    ],
    "placetype": [
      "aat:300008347"
    ],
    "id": 1056050,
    "name:xx": "Kulikov"
  }
}
