{
  "geometry": {
    "type": "Point",
    "coordinates": [
      -92.7667,
      34.4833
    ]
  },
  "type": "Feature",
  "properties": {
    "hierarchy": [
      "tgn:2474054",
      "tgn:1000001",
      "tgn:7016172",
      "tgn:7012149",
      "tgn:2000130",
      "tgn:7029392"
    ],
    "placetype": [
      "aat:300006191"
    ],
    "id": 2474054,
    "name:xx": "Lower Lake"
  }
}
