{
  "type": "FeatureCollection",
  "features": [
    {
      "geometry": {
        "type": "Point",
        "coordinates": [
          -83.7167,
          39.2
        ]
      },
      "type": "Feature",
      "properties": {
        "hierarchy": [
          "tgn:2079530",
          "tgn:1000001",
          "tgn:7012149",
          "tgn:1002476",
          "tgn:7007706",
          "tgn:7029392"
        ],
        "placetype": [
          "aat:300008347"
        ],
        "id": 2079530,
        "name:xx": "Fairview"
      }
    },
    {
      "geometry": {
        "type": "Point",
        "coordinates": [
          -83.3,
          39.4667
        ]
      },
      "type": "Feature",
      "properties": {
        "hierarchy": [
          "tgn:2079532",
          "tgn:1000001",
          "tgn:7012149",
          "tgn:1002372",
          "tgn:7007706",
          "tgn:7029392"
        ],
        "placetype": [
          "aat:300387016"
        ],
        "id": 2079532,
        "name:xx": "Fairview"
      }
    },
    {
      "geometry": {
        "type": "Point",
        "coordinates": [
          -82.65,
          41.4167
        ]
      },
      "type": "Feature",
      "properties": {
        "hierarchy": [
          "tgn:2079534",
          "tgn:1000001",
          "tgn:7012149",
          "tgn:1002357",
          "tgn:7007706",
          "tgn:7029392"
        ],
        "placetype": [
          "aat:300008347"
        ],
        "id": 2079534,
        "name:xx": "Fairview Lanes"
      }
    },
    {
      "geometry": {
        "type": "Point",
        "coordinates": [
          -81.85,
          41.4333
        ]
      },
      "type": "Feature",
      "properties": {
        "hierarchy": [
          "tgn:2079535",
          "tgn:1000001",
          "tgn:1002313",
          "tgn:7012149",
          "tgn:7007706",
          "tgn:7029392"
        ],
        "placetype": [
          "aat:300008347"
        ],
        "id": 2079535,
        "name:xx": "Fairview Park"
      }
    }
  ]
}
