{
  "geometry": {
    "type": "Point",
    "coordinates": [
      -103.6333,
      43.5333
    ]
  },
  "type": "Feature",
  "properties": {
    "hierarchy": [
      "tgn:2136894",
      "tgn:1000001",
      "tgn:2001786",
      "tgn:7012149",
      "tgn:7007713",
      "tgn:7029392"
    ],
    "placetype": [
      "aat:300008347"
    ],
    "id": 2136894,
    "name:xx": "Argyle"
  }
}
