{
  "type": "FeatureCollection",
  "features": [
    {
      "geometry": {
        "type": "Point",
        "coordinates": [
          -81.3167,
          38.9333
        ]
      },
      "type": "Feature",
      "properties": {
        "hierarchy": [
          "tgn:2661220",
          "tgn:1000001",
          "tgn:7012149",
          "tgn:2002302",
          "tgn:7013961",
          "tgn:7029392"
        ],
        "placetype": [
          "aat:300008699"
        ],
        "id": 2661220,
        "name:xx": "Short Run"
      }
    },
    {
      "geometry": {
        "type": "Point",
        "coordinates": [
          -80.0667,
          38.9167
        ]
      },
      "type": "Feature",
      "properties": {
        "hierarchy": [
          "tgn:2661221",
          "tgn:1000001",
          "tgn:7012149",
          "tgn:2002291",
          "tgn:7013961",
          "tgn:7029392"
        ],
        "placetype": [
          "aat:300008699"
        ],
        "id": 2661221,
        "name:xx": "Short Run"
      }
    },
    {
      "geometry": {
        "type": "Point",
        "coordinates": [
          -81.6833,
          39.1167
        ]
      },
      "type": "Feature",
      "properties": {
        "hierarchy": [
          "tgn:2661222",
          "tgn:1000001",
          "tgn:7012149",
          "tgn:2002303",
          "tgn:7013961",
          "tgn:7029392"
        ],
        "placetype": [
          "aat:300008699"
        ],
        "id": 2661222,
        "name:xx": "Short Run"
      }
    },
    {
      "geometry": {
        "type": "Point",
        "coordinates": [
          -80.7667,
          39.15
        ]
      },
      "type": "Feature",
      "properties": {
        "hierarchy": [
          "tgn:2661223",
          "tgn:1000001",
          "tgn:2002260",
          "tgn:7012149",
          "tgn:7013961",
          "tgn:7029392"
        ],
        "placetype": [
          "aat:300008699"
        ],
        "id": 2661223,
        "name:xx": "Short Run"
      }
    },
    {
      "geometry": {
        "type": "Point",
        "coordinates": [
          -81.2333,
          39.2167
        ]
      },
      "type": "Feature",
      "properties": {
        "hierarchy": [
          "tgn:2661224",
          "tgn:1000001",
          "tgn:7012149",
          "tgn:2002292",
          "tgn:7013961",
          "tgn:7029392"
        ],
        "placetype": [
          "aat:300008699"
        ],
        "id": 2661224,
        "name:xx": "Short Run"
      }
    },
    {
      "geometry": {
        "type": "Point",
        "coordinates": [
          -80.05,
          39.3167
        ]
      },
      "type": "Feature",
      "properties": {
        "hierarchy": [
          "tgn:2661225",
          "tgn:1000001",
          "tgn:7012149",
          "tgn:2002295",
          "tgn:7013961",
          "tgn:7029392"
        ],
        "placetype": [
          "aat:300008699"
        ],
        "id": 2661225,
        "name:xx": "Short Run"
      }
    },
    {
      "geometry": {
        "type": "Point",
        "coordinates": [
          -80.4833,
          38.7333
        ]
      },
      "type": "Feature",
      "properties": {
        "hierarchy": [
          "tgn:2661226",
          "tgn:1000001",
          "tgn:2002256",
          "tgn:7012149",
          "tgn:7013961",
          "tgn:7029392"
        ],
        "placetype": [
          "aat:300008699"
        ],
        "id": 2661226,
        "name:xx": "Short Run"
      }
    },
    {
      "geometry": {
        "type": "Point",
        "coordinates": [
          -80.8833,
          39.3167
        ]
      },
      "type": "Feature",
      "properties": {
        "hierarchy": [
          "tgn:2661227",
          "tgn:1000001",
          "tgn:7012149",
          "tgn:2002297",
          "tgn:7013961",
          "tgn:7029392"
        ],
        "placetype": [
          "aat:300008699"
        ],
        "id": 2661227,
        "name:xx": "Short Run"
      }
    },
    {
      "geometry": {
        "type": "Point",
        "coordinates": [
          -123.9,
          45.7667
        ]
      },
      "type": "Feature",
      "properties": {
        "hierarchy": [
          "tgn:2661228",
          "tgn:1000001",
          "tgn:7012149",
          "tgn:1002943",
          "tgn:7007708",
          "tgn:7029392"
        ],
        "placetype": [
          "aat:300008706"
        ],
        "id": 2661228,
        "name:xx": "Short Sand Creek"
      }
    }
  ]
}
