{
  "type": "FeatureCollection",
  "features": [
    {
      "geometry": {
        "type": "Point",
        "coordinates": [
          -84.2,
          30.0833
        ]
      },
      "type": "Feature",
      "properties": {
        "hierarchy": [
          "tgn:2685450",
          "tgn:1000001",
          "tgn:7012149",
          "tgn:2000289",
          "tgn:7007240",
          "tgn:7029392"
        ],
        "placetype": [
          "aat:300008791"
        ],
        "id": 2685450,
        "name:xx": "Sprague Island"
      }
    },
    {
      "geometry": {
        "type": "Point",
        "coordinates": [
          -85.4333,
          44
        ]
      },
      "type": "Feature",
      "properties": {
        "hierarchy": [
          "tgn:2685451",
          "tgn:1000001",
          "tgn:7012149",
          "tgn:2000987",
          "tgn:7007520",
          "tgn:7029392"
        ],
        "placetype": [
          "aat:300008680"
        ],
        "id": 2685451,
        "name:xx": "Sprague Lake"
      }
    },
    {
      "geometry": {
        "type": "Point",
        "coordinates": [
          -93.4667,
          44.2
        ]
      },
      "type": "Feature",
      "properties": {
        "hierarchy": [
          "tgn:2685452",
          "tgn:1000001",
          "tgn:7012149",
          "tgn:2001038",
          "tgn:7007521",
          "tgn:7029392"
        ],
        "placetype": [
          "aat:300008680"
        ],
        "id": 2685452,
        "name:xx": "Sprague Lake"
      }
    },
    {
      "geometry": {
        "type": "Point",
        "coordinates": [
          -97.5333,
          46.0167
        ]
      },
      "type": "Feature",
      "properties": {
        "hierarchy": [
          "tgn:2685453",
          "tgn:1000001",
          "tgn:2001597",
          "tgn:7012149",
          "tgn:7007705",
          "tgn:7029392"
        ],
        "placetype": [
          "aat:300008680"
        ],
        "id": 2685453,
        "name:xx": "Sprague Lake"
      }
    },
    {
      "geometry": {
        "type": "Point",
        "coordinates": [
          -121.8,
          44.7167
        ]
      },
      "type": "Feature",
      "properties": {
        "hierarchy": [
          "tgn:2685454",
          "tgn:1000001",
          "tgn:7012149",
          "tgn:1002636",
          "tgn:7007708",
          "tgn:7029392"
        ],
        "placetype": [
          "aat:300008680"
        ],
        "id": 2685454,
        "name:xx": "Sprague Lake"
      }
    },
    {
      "geometry": {
        "type": "Point",
        "coordinates": [
          -122.1333,
          48.9167
        ]
      },
      "type": "Feature",
      "properties": {
        "hierarchy": [
          "tgn:2685455",
          "tgn:1000001",
          "tgn:7012149",
          "tgn:1003020",
          "tgn:7007920",
          "tgn:7029392"
        ],
        "placetype": [
          "aat:300008680"
        ],
        "id": 2685455,
        "name:xx": "Sprague Lake"
      }
    },
    {
      "geometry": {
        "type": "Point",
        "coordinates": [
          -118.05,
          47.25
        ]
      },
      "type": "Feature",
      "properties": {
        "hierarchy": [
          "tgn:2685456",
          "tgn:1000001",
          "tgn:7012149",
          "tgn:7007920",
          "tgn:7029392"
        ],
        "placetype": [
          "aat:300008680"
        ],
        "id": 2685456,
        "name:xx": "Sprague Lake"
      }
    },
    {
      "geometry": {
        "type": "Point",
        "coordinates": [
          -118.1,
          47.2167
        ]
      },
      "type": "Feature",
      "properties": {
        "hierarchy": [
          "tgn:2685457",
          "tgn:2002238",
          "tgn:1000001",
          "tgn:7012149",
          "tgn:7007920",
          "tgn:7029392"
        ],
        "placetype": [
          "aat:300006191"
        ],
        "id": 2685457,
        "name:xx": "Sprague Lake"
      }
    },
    {
      "geometry": {
        "type": "Point",
        "coordinates": [
          -68.5,
          44.0833
        ]
      },
      "type": "Feature",
      "properties": {
        "hierarchy": [
          "tgn:2685458",
          "tgn:1000001",
          "tgn:2000922",
          "tgn:7012149",
          "tgn:7007515",
          "tgn:7029392"
        ],
        "placetype": [
          "aat:300132348"
        ],
        "id": 2685458,
        "name:xx": "Sprague Ledge"
      }
    },
    {
      "geometry": {
        "type": "Point",
        "coordinates": [
          -68.9167,
          44.3333
        ]
      },
      "type": "Feature",
      "properties": {
        "hierarchy": [
          "tgn:2685459",
          "tgn:1000001",
          "tgn:7012149",
          "tgn:2000931",
          "tgn:7007515",
          "tgn:7029392"
        ],
        "placetype": [
          "aat:300132348"
        ],
        "id": 2685459,
        "name:xx": "Sprague Ledge"
      }
    }
  ]
}
