{
  "geometry": {
    "type": "Point",
    "coordinates": [
      74.747222,
      34.1375
    ]
  },
  "type": "Feature",
  "properties": {
    "hierarchy": [
      "tgn:7587432",
      "tgn:1000004",
      "tgn:7000198",
      "tgn:7000799",
      "tgn:7029392"
    ],
    "placetype": [
      "aat:300008347"
    ],
    "name:en": "Bar Ūdar",
    "id": 7587432
  }
}
