{
  "type": "FeatureCollection",
  "features": [
    {
      "geometry": {
        "type": "Point",
        "coordinates": [
          -1.666667,
          60.35
        ]
      },
      "type": "Feature",
      "properties": {
        "hierarchy": [
          "tgn:7457390",
          "tgn:7002444",
          "tgn:1000003",
          "tgn:7029508",
          "tgn:7008591",
          "tgn:7029392"
        ],
        "placetype": [
          "aat:300008804"
        ],
        "name:en": "North Ness",
        "id": 7457390
      }
    },
    {
      "geometry": {
        "type": "Point",
        "coordinates": [
          -0.75,
          50.8
        ]
      },
      "type": "Feature",
      "properties": {
        "hierarchy": [
          "tgn:7457392",
          "tgn:7002445",
          "tgn:1000003",
          "tgn:7008134",
          "tgn:7008591",
          "tgn:7029392"
        ],
        "placetype": [
          "aat:300008347"
        ],
        "name:en": "North Mundham",
        "id": 7457392
      }
    },
    {
      "geometry": {
        "type": "Point",
        "coordinates": [
          -1.383333,
          51.716667
        ]
      },
      "type": "Feature",
      "properties": {
        "hierarchy": [
          "tgn:7457394",
          "tgn:7002445",
          "tgn:1000003",
          "tgn:7008168",
          "tgn:7008591",
          "tgn:7029392"
        ],
        "placetype": [
          "aat:300008347"
        ],
        "name:en": "Northmoor",
        "id": 7457394
      }
    },
    {
      "geometry": {
        "type": "Point",
        "coordinates": [
          -5.833333,
          58.166667
        ]
      },
      "type": "Feature",
      "properties": {
        "hierarchy": [
          "tgn:7457396",
          "tgn:7002444",
          "tgn:1000003",
          "tgn:7008082",
          "tgn:7008591",
          "tgn:7029392"
        ],
        "placetype": [
          "aat:300266559"
        ],
        "name:en": "North Minch",
        "id": 7457396
      }
    },
    {
      "geometry": {
        "type": "Point",
        "coordinates": [
          -0.25,
          51.716667
        ]
      },
      "type": "Feature",
      "properties": {
        "hierarchy": [
          "tgn:7457397",
          "tgn:7002445",
          "tgn:1000003",
          "tgn:7008145",
          "tgn:7008591",
          "tgn:7029392"
        ],
        "placetype": [
          "aat:300008187"
        ],
        "name:en": "North Mimms Park",
        "id": 7457397
      }
    }
  ]
}
