{
  "geometry": {
    "type": "Point",
    "coordinates": [
      -91.0167,
      30.3667
    ]
  },
  "type": "Feature",
  "properties": {
    "hierarchy": [
      "tgn:2225060",
      "tgn:1000001",
      "tgn:2000870",
      "tgn:7012149",
      "tgn:7007256",
      "tgn:7029392"
    ],
    "placetype": [
      "aat:300008347"
    ],
    "id": 2225060,
    "name:xx": "Castille"
  }
}
