{
  "geometry": {
    "type": "Point",
    "coordinates": [
      -86.35,
      33.4667
    ]
  },
  "type": "Feature",
  "properties": {
    "hierarchy": [
      "tgn:2004692",
      "tgn:7002659",
      "tgn:1000001",
      "tgn:7012149",
      "tgn:2000057",
      "tgn:7029392"
    ],
    "placetype": [
      "aat:300008347"
    ],
    "id": 2004692,
    "name:xx": "New London"
  }
}
