{
  "geometry": {
    "type": "Point",
    "coordinates": [
      -82.15,
      40.3333
    ]
  },
  "type": "Feature",
  "properties": {
    "hierarchy": [
      "tgn:2080973",
      "tgn:1000001",
      "tgn:1002304",
      "tgn:7012149",
      "tgn:7007706",
      "tgn:7029392"
    ],
    "placetype": [
      "aat:300008347"
    ],
    "id": 2080973,
    "name:xx": "Newcastle"
  }
}
