{
  "geometry": {
    "type": "Point",
    "coordinates": [
      -90.5667,
      38.5167
    ]
  },
  "type": "Feature",
  "properties": {
    "hierarchy": [
      "tgn:2516047",
      "tgn:1000001",
      "tgn:7012149",
      "tgn:7016167",
      "tgn:7007523",
      "tgn:7029392"
    ],
    "placetype": [
      "aat:300008761"
    ],
    "id": 2516047,
    "name:xx": "Mincke Hollow"
  }
}
