{
  "geometry": {
    "type": "Point",
    "coordinates": [
      118.25,
      40.8833
    ]
  },
  "type": "Feature",
  "properties": {
    "hierarchy": [
      "tgn:1073496",
      "tgn:1000004",
      "tgn:7002077",
      "tgn:1000111",
      "tgn:7029392"
    ],
    "placetype": [
      "aat:300008347"
    ],
    "id": 1073496,
    "name:xx": "Yezhuhe"
  }
}
