{
  "geometry": {
    "type": "Point",
    "coordinates": [
      124.3333,
      50.0333
    ]
  },
  "type": "Feature",
  "properties": {
    "hierarchy": [
      "tgn:1067136",
      "tgn:1000004",
      "tgn:7001838",
      "tgn:1000111",
      "tgn:7029392"
    ],
    "placetype": [
      "aat:300008347"
    ],
    "id": 1067136,
    "name:xx": "Chaoyangcun"
  }
}
