{
  "geometry": {
    "type": "Point",
    "coordinates": [
      26.5333,
      42.5167
    ]
  },
  "type": "Feature",
  "properties": {
    "hierarchy": [
      "tgn:1127235",
      "tgn:7593878",
      "tgn:1000003",
      "tgn:7006413",
      "tgn:7029392"
    ],
    "placetype": [
      "aat:300008707"
    ],
    "id": 1127235,
    "name:xx": "Mochuritsa"
  }
}
