{
  "type": "FeatureCollection",
  "features": [
    {
      "geometry": {
        "type": "Point",
        "coordinates": [
          -163.7,
          64.5833
        ]
      },
      "type": "Feature",
      "properties": {
        "hierarchy": [
          "tgn:2150360",
          "tgn:7006450",
          "tgn:1000001",
          "tgn:7012149",
          "tgn:2000079",
          "tgn:7029392"
        ],
        "placetype": [
          "aat:300008706"
        ],
        "id": 2150360,
        "name:xx": "Basin Creek"
      }
    },
    {
      "geometry": {
        "type": "Point",
        "coordinates": [
          -144.3167,
          60.2333
        ]
      },
      "type": "Feature",
      "properties": {
        "hierarchy": [
          "tgn:2150361",
          "tgn:7006450",
          "tgn:1000001",
          "tgn:7012149",
          "tgn:2000086",
          "tgn:7029392"
        ],
        "placetype": [
          "aat:300008706"
        ],
        "id": 2150361,
        "name:xx": "Basin Creek"
      }
    },
    {
      "geometry": {
        "type": "Point",
        "coordinates": [
          -92.8333,
          34.5
        ]
      },
      "type": "Feature",
      "properties": {
        "hierarchy": [
          "tgn:2150362",
          "tgn:1000001",
          "tgn:7016172",
          "tgn:7012149",
          "tgn:7029392"
        ],
        "placetype": [
          "aat:300008706"
        ],
        "id": 2150362,
        "name:xx": "Basin Creek"
      }
    },
    {
      "geometry": {
        "type": "Point",
        "coordinates": [
          -119.1,
          36.9333
        ]
      },
      "type": "Feature",
      "properties": {
        "hierarchy": [
          "tgn:2150363",
          "tgn:1000001",
          "tgn:7012149",
          "tgn:1002392",
          "tgn:7007157",
          "tgn:7029392"
        ],
        "placetype": [
          "aat:300008706"
        ],
        "id": 2150363,
        "name:xx": "Basin Creek"
      }
    },
    {
      "geometry": {
        "type": "Point",
        "coordinates": [
          -120.0667,
          38.3167
        ]
      },
      "type": "Feature",
      "properties": {
        "hierarchy": [
          "tgn:2150364",
          "tgn:1000001",
          "tgn:7012149",
          "tgn:7007157",
          "tgn:1002957",
          "tgn:7029392"
        ],
        "placetype": [
          "aat:300008706"
        ],
        "id": 2150364,
        "name:xx": "Basin Creek"
      }
    },
    {
      "geometry": {
        "type": "Point",
        "coordinates": [
          -122.85,
          39.5667
        ]
      },
      "type": "Feature",
      "properties": {
        "hierarchy": [
          "tgn:2150365",
          "tgn:1000001",
          "tgn:7012149",
          "tgn:7007157",
          "tgn:7029392"
        ],
        "placetype": [
          "aat:300008706"
        ],
        "id": 2150365,
        "name:xx": "Basin Creek"
      }
    },
    {
      "geometry": {
        "type": "Point",
        "coordinates": [
          -122.7167,
          40.05
        ]
      },
      "type": "Feature",
      "properties": {
        "hierarchy": [
          "tgn:2150366",
          "tgn:1000001",
          "tgn:7012149",
          "tgn:7007157",
          "tgn:2000190",
          "tgn:7029392"
        ],
        "placetype": [
          "aat:300008706"
        ],
        "id": 2150366,
        "name:xx": "Basin Creek"
      }
    },
    {
      "geometry": {
        "type": "Point",
        "coordinates": [
          -123.6667,
          40.2833
        ]
      },
      "type": "Feature",
      "properties": {
        "hierarchy": [
          "tgn:2150367",
          "tgn:1000001",
          "tgn:7012149",
          "tgn:2000181",
          "tgn:7007157",
          "tgn:7029392"
        ],
        "placetype": [
          "aat:300008706"
        ],
        "id": 2150367,
        "name:xx": "Basin Creek"
      }
    },
    {
      "geometry": {
        "type": "Point",
        "coordinates": [
          -121.4,
          36.35
        ]
      },
      "type": "Feature",
      "properties": {
        "hierarchy": [
          "tgn:2150368",
          "tgn:1000001",
          "tgn:7012149",
          "tgn:7007157",
          "tgn:1002684",
          "tgn:7029392"
        ],
        "placetype": [
          "aat:300008706"
        ],
        "id": 2150368,
        "name:xx": "Basin Creek"
      }
    },
    {
      "geometry": {
        "type": "Point",
        "coordinates": [
          -107.3833,
          39.2333
        ]
      },
      "type": "Feature",
      "properties": {
        "hierarchy": [
          "tgn:2150369",
          "tgn:1000001",
          "tgn:7012149",
          "tgn:2000217",
          "tgn:7007158",
          "tgn:7029392"
        ],
        "placetype": [
          "aat:300008706"
        ],
        "id": 2150369,
        "name:xx": "Basin Creek"
      }
    }
  ]
}
