{
  "geometry": {
    "type": "Point",
    "coordinates": [
      -87.95,
      35.35
    ]
  },
  "type": "Feature",
  "properties": {
    "hierarchy": [
      "tgn:2173120",
      "tgn:1000001",
      "tgn:7012149",
      "tgn:2001927",
      "tgn:7007825",
      "tgn:7029392"
    ],
    "placetype": [
      "aat:300008699"
    ],
    "id": 2173120,
    "name:xx": "Bingham Branch"
  }
}
