{
  "geometry": {
    "type": "Point",
    "coordinates": [
      -79.1167,
      38.1833
    ]
  },
  "type": "Feature",
  "properties": {
    "hierarchy": [
      "tgn:2339184",
      "tgn:2002142",
      "tgn:1000001",
      "tgn:7012149",
      "tgn:7007919",
      "tgn:7029392"
    ],
    "placetype": [
      "aat:300008746"
    ],
    "id": 2339184,
    "name:xx": "Franks Mill Cave Number 7"
  }
}
