{
  "geometry": {
    "type": "Point",
    "coordinates": [
      -80.05,
      35.3667
    ]
  },
  "type": "Feature",
  "properties": {
    "hierarchy": [
      "tgn:2573936",
      "tgn:1000001",
      "tgn:7012149",
      "tgn:7029392"
    ],
    "placetype": [
      "aat:300008707"
    ],
    "id": 2573936,
    "name:xx": "Pee Dee River"
  }
}
