{
  "geometry": {
    "type": "Point",
    "coordinates": [
      -103.8167,
      44.3333
    ]
  },
  "type": "Feature",
  "properties": {
    "hierarchy": [
      "tgn:2145202",
      "tgn:1000001",
      "tgn:2001810",
      "tgn:7012149",
      "tgn:7007713",
      "tgn:7029392"
    ],
    "placetype": [
      "aat:300008798"
    ],
    "id": 2145202,
    "name:xx": "Bald Mountain"
  }
}
