{
  "geometry": {
    "type": "Point",
    "coordinates": [
      -121.7833,
      46.3667
    ]
  },
  "type": "Feature",
  "properties": {
    "hierarchy": [
      "tgn:2358939",
      "tgn:1000001",
      "tgn:7012149",
      "tgn:1002897",
      "tgn:7007920",
      "tgn:7029392"
    ],
    "placetype": [
      "aat:300008706"
    ],
    "id": 2358939,
    "name:xx": "Granite Creek"
  }
}
