{
  "geometry": {
    "type": "Point",
    "coordinates": [
      -86.6833,
      40.9667
    ]
  },
  "type": "Feature",
  "properties": {
    "hierarchy": [
      "tgn:2204039",
      "tgn:1000001",
      "tgn:7012149",
      "tgn:1002809",
      "tgn:7007252",
      "tgn:7029392"
    ],
    "placetype": [
      "aat:300006075"
    ],
    "id": 2204039,
    "name:xx": "Budd Fisher Ditch"
  }
}
