{
  "geometry": {
    "type": "Point",
    "coordinates": [
      -93.5667,
      44.35
    ]
  },
  "type": "Feature",
  "properties": {
    "hierarchy": [
      "tgn:2292611",
      "tgn:1000001",
      "tgn:7012149",
      "tgn:2001038",
      "tgn:7007521",
      "tgn:7029392"
    ],
    "placetype": [
      "aat:300008680"
    ],
    "id": 2292611,
    "name:xx": "Dora, Lake"
  }
}
