{
  "type": "FeatureCollection",
  "features": [
    {
      "geometry": {
        "type": "Point",
        "coordinates": [
          -99.816667,
          25.216667
        ]
      },
      "type": "Feature",
      "properties": {
        "hierarchy": [
          "tgn:7353000",
          "tgn:1000001",
          "tgn:7005589",
          "tgn:7005560",
          "tgn:7029392"
        ],
        "placetype": [
          "aat:300008347"
        ],
        "id": 7353000,
        "name:xx": "Buenavista"
      }
    },
    {
      "geometry": {
        "type": "Point",
        "coordinates": [
          -104.483333,
          25.133333
        ]
      },
      "type": "Feature",
      "properties": {
        "hierarchy": [
          "tgn:7353001",
          "tgn:7005583",
          "tgn:1000001",
          "tgn:7005560",
          "tgn:7029392"
        ],
        "placetype": [
          "aat:300008347"
        ],
        "id": 7353001,
        "name:xx": "Buenavista"
      }
    },
    {
      "geometry": {
        "type": "Point",
        "coordinates": [
          -99.1,
          25.083333
        ]
      },
      "type": "Feature",
      "properties": {
        "hierarchy": [
          "tgn:7353002",
          "tgn:1000001",
          "tgn:7005589",
          "tgn:7005560",
          "tgn:7029392"
        ],
        "placetype": [
          "aat:300008347"
        ],
        "id": 7353002,
        "name:xx": "Buenavista"
      }
    },
    {
      "geometry": {
        "type": "Point",
        "coordinates": [
          -97.933333,
          24.866667
        ]
      },
      "type": "Feature",
      "properties": {
        "hierarchy": [
          "tgn:7353003",
          "tgn:1000001",
          "tgn:7005597",
          "tgn:7005560",
          "tgn:7029392"
        ],
        "placetype": [
          "aat:300008347"
        ],
        "id": 7353003,
        "name:xx": "Buenavista"
      }
    },
    {
      "geometry": {
        "type": "Point",
        "coordinates": [
          -107.766389,
          24.74
        ]
      },
      "type": "Feature",
      "properties": {
        "hierarchy": [
          "tgn:7353004",
          "tgn:1000001",
          "tgn:7005595",
          "tgn:7005560",
          "tgn:7029392"
        ],
        "placetype": [
          "aat:300008347"
        ],
        "id": 7353004,
        "name:xx": "Buenavista"
      }
    },
    {
      "geometry": {
        "type": "Point",
        "coordinates": [
          -99.816944,
          24.485556
        ]
      },
      "type": "Feature",
      "properties": {
        "hierarchy": [
          "tgn:7353005",
          "tgn:1000001",
          "tgn:7005589",
          "tgn:7005560",
          "tgn:7029392"
        ],
        "placetype": [
          "aat:300008347"
        ],
        "id": 7353005,
        "name:xx": "Buenavista"
      }
    },
    {
      "geometry": {
        "type": "Point",
        "coordinates": [
          -99.65,
          24.55
        ]
      },
      "type": "Feature",
      "properties": {
        "hierarchy": [
          "tgn:7353006",
          "tgn:1000001",
          "tgn:7005597",
          "tgn:7005560",
          "tgn:7029392"
        ],
        "placetype": [
          "aat:300008347"
        ],
        "id": 7353006,
        "name:xx": "Buenavista"
      }
    },
    {
      "geometry": {
        "type": "Point",
        "coordinates": [
          -99.633333,
          24.4
        ]
      },
      "type": "Feature",
      "properties": {
        "hierarchy": [
          "tgn:7353008",
          "tgn:1000001",
          "tgn:7005589",
          "tgn:7005560",
          "tgn:7029392"
        ],
        "placetype": [
          "aat:300008347"
        ],
        "id": 7353008,
        "name:xx": "Buenavista"
      }
    },
    {
      "geometry": {
        "type": "Point",
        "coordinates": [
          -106.828333,
          24.344722
        ]
      },
      "type": "Feature",
      "properties": {
        "hierarchy": [
          "tgn:7353009",
          "tgn:1000001",
          "tgn:7005595",
          "tgn:7005560",
          "tgn:7029392"
        ],
        "placetype": [
          "aat:300008347"
        ],
        "id": 7353009,
        "name:xx": "Buenavista"
      }
    }
  ]
}
