{
  "geometry": {
    "type": "Point",
    "coordinates": [
      -116.85,
      32.8167
    ]
  },
  "type": "Feature",
  "properties": {
    "hierarchy": [
      "tgn:2612167",
      "tgn:1000001",
      "tgn:7012149",
      "tgn:7007157",
      "tgn:1002858",
      "tgn:7029392"
    ],
    "placetype": [
      "aat:300000390"
    ],
    "id": 2612167,
    "name:xx": "Red Rose Quarry"
  }
}
