{
  "geometry": {
    "type": "Point",
    "coordinates": [
      119.85,
      33.7667
    ]
  },
  "type": "Feature",
  "properties": {
    "hierarchy": [
      "tgn:1135877",
      "tgn:1000004",
      "tgn:7002081",
      "tgn:1000111",
      "tgn:7029392"
    ],
    "placetype": [
      "aat:300006075"
    ],
    "id": 1135877,
    "name:xx": "Chuanchang"
  }
}
