{
  "type": "FeatureCollection",
  "features": [
    {
      "geometry": {
        "type": "Point",
        "coordinates": [
          9.8,
          48.6
        ]
      },
      "type": "Feature",
      "properties": {
        "hierarchy": [
          "tgn:7208551",
          "tgn:7003692",
          "tgn:1000003",
          "tgn:7000084",
          "tgn:7029392"
        ],
        "placetype": [
          "aat:300008347"
        ],
        "id": 7208551,
        "name:xx": "Bad Überkingen"
      }
    },
    {
      "geometry": {
        "type": "Point",
        "coordinates": [
          11.504722,
          47.753056
        ]
      },
      "type": "Feature",
      "properties": {
        "hierarchy": [
          "tgn:7208552",
          "tgn:7003669",
          "tgn:1000003",
          "tgn:7000084",
          "tgn:7029392"
        ],
        "placetype": [
          "aat:300387198"
        ],
        "id": 7208552,
        "name:xx": "Landkreis Bad Tölz-Wolfratshausen"
      }
    },
    {
      "geometry": {
        "type": "Point",
        "coordinates": [
          8.683333,
          48.7
        ]
      },
      "type": "Feature",
      "properties": {
        "hierarchy": [
          "tgn:7208555",
          "tgn:7003692",
          "tgn:1000003",
          "tgn:7000084",
          "tgn:7029392"
        ],
        "placetype": [
          "aat:300000745"
        ],
        "id": 7208555,
        "name:xx": "Bad Teinach"
      }
    },
    {
      "geometry": {
        "type": "Point",
        "coordinates": [
          7.75,
          47.816667
        ]
      },
      "type": "Feature",
      "properties": {
        "hierarchy": [
          "tgn:7208557",
          "tgn:7003692",
          "tgn:1000003",
          "tgn:7000084",
          "tgn:7029392"
        ],
        "placetype": [
          "aat:300008347"
        ],
        "id": 7208557,
        "name:xx": "Bad Sulzburg"
      }
    },
    {
      "geometry": {
        "type": "Point",
        "coordinates": [
          11.633333,
          51.1
        ]
      },
      "type": "Feature",
      "properties": {
        "hierarchy": [
          "tgn:7208558",
          "tgn:1000003",
          "tgn:7003689",
          "tgn:7000084",
          "tgn:7029392"
        ],
        "placetype": [
          "aat:300007783"
        ],
        "id": 7208558,
        "name:xx": "Bahnhof Bad Sulza"
      }
    }
  ]
}
