{
  "geometry": {
    "type": "Point",
    "coordinates": [
      -87.7167,
      31.3333
    ]
  },
  "type": "Feature",
  "properties": {
    "hierarchy": [
      "tgn:2596135",
      "tgn:7002659",
      "tgn:1000001",
      "tgn:7012149",
      "tgn:7029392"
    ],
    "placetype": [
      "aat:300132348"
    ],
    "id": 2596135,
    "name:xx": "Potts Bar"
  }
}
