{
  "geometry": {
    "type": "Point",
    "coordinates": [
      -79.5833,
      33.5833
    ]
  },
  "type": "Feature",
  "properties": {
    "hierarchy": [
      "tgn:2289858",
      "tgn:1000001",
      "tgn:7012149",
      "tgn:2001769",
      "tgn:7007712",
      "tgn:7029392"
    ],
    "placetype": [
      "aat:300386845"
    ],
    "id": 2289858,
    "name:xx": "Dobson Bay"
  }
}
