{
  "geometry": {
    "type": "Point",
    "coordinates": [
      -150.8667,
      60.6167
    ]
  },
  "type": "Feature",
  "properties": {
    "hierarchy": [
      "tgn:2602764",
      "tgn:7006450",
      "tgn:1000001",
      "tgn:7019698",
      "tgn:7012149",
      "tgn:7029392"
    ],
    "placetype": [
      "aat:300008680"
    ],
    "id": 2602764,
    "name:xx": "Quake Lake"
  }
}
