{
  "type": "FeatureCollection",
  "features": [
    {
      "geometry": {
        "type": "Point",
        "coordinates": [
          -70.733333,
          -32.9
        ]
      },
      "type": "Feature",
      "properties": {
        "hierarchy": [
          "tgn:7314170",
          "tgn:1001768",
          "tgn:1000049",
          "tgn:1000002",
          "tgn:7029392"
        ],
        "placetype": [
          "aat:300387200"
        ],
        "id": 7314170,
        "name:xx": "Los Maitenes"
      }
    },
    {
      "geometry": {
        "type": "Point",
        "coordinates": [
          -73.066667,
          -40.883333
        ]
      },
      "type": "Feature",
      "properties": {
        "hierarchy": [
          "tgn:7314171",
          "tgn:1001699",
          "tgn:1000049",
          "tgn:1000002",
          "tgn:7029392"
        ],
        "placetype": [
          "aat:300000206"
        ],
        "id": 7314171,
        "name:xx": "Los Maitenes"
      }
    },
    {
      "geometry": {
        "type": "Point",
        "coordinates": [
          -72.25,
          -38.6
        ]
      },
      "type": "Feature",
      "properties": {
        "hierarchy": [
          "tgn:7314172",
          "tgn:1001692",
          "tgn:1000049",
          "tgn:1000002",
          "tgn:7029392"
        ],
        "placetype": [
          "aat:300000206"
        ],
        "id": 7314172,
        "name:xx": "Los Maitenes"
      }
    },
    {
      "geometry": {
        "type": "Point",
        "coordinates": [
          -70.466667,
          -35.066667
        ]
      },
      "type": "Feature",
      "properties": {
        "hierarchy": [
          "tgn:7314173",
          "tgn:1001705",
          "tgn:1000049",
          "tgn:1000002",
          "tgn:7029392"
        ],
        "placetype": [
          "aat:300000206"
        ],
        "id": 7314173,
        "name:xx": "Los Maitenes"
      }
    },
    {
      "geometry": {
        "type": "Point",
        "coordinates": [
          -71.116667,
          -34.466667
        ]
      },
      "type": "Feature",
      "properties": {
        "hierarchy": [
          "tgn:7314174",
          "tgn:1001695",
          "tgn:1000049",
          "tgn:1000002",
          "tgn:7029392"
        ],
        "placetype": [
          "aat:300000206"
        ],
        "id": 7314174,
        "name:xx": "Los Maitenes"
      }
    },
    {
      "geometry": {
        "type": "Point",
        "coordinates": [
          -71.6,
          -34.383333
        ]
      },
      "type": "Feature",
      "properties": {
        "hierarchy": [
          "tgn:7314175",
          "tgn:1001695",
          "tgn:1000049",
          "tgn:1000002",
          "tgn:7029392"
        ],
        "placetype": [
          "aat:300000206"
        ],
        "id": 7314175,
        "name:xx": "Los Maitenes"
      }
    },
    {
      "geometry": {
        "type": "Point",
        "coordinates": [
          -70.883333,
          -34.333333
        ]
      },
      "type": "Feature",
      "properties": {
        "hierarchy": [
          "tgn:7314176",
          "tgn:1001695",
          "tgn:1000049",
          "tgn:1000002",
          "tgn:7029392"
        ],
        "placetype": [
          "aat:300000206"
        ],
        "id": 7314176,
        "name:xx": "Los Maitenes"
      }
    },
    {
      "geometry": {
        "type": "Point",
        "coordinates": [
          -71.333333,
          -33.833333
        ]
      },
      "type": "Feature",
      "properties": {
        "hierarchy": [
          "tgn:7314177",
          "tgn:1001708",
          "tgn:1000049",
          "tgn:1000002",
          "tgn:7029392"
        ],
        "placetype": [
          "aat:300000206"
        ],
        "id": 7314177,
        "name:xx": "Los Maitenes"
      }
    },
    {
      "geometry": {
        "type": "Point",
        "coordinates": [
          -70.283333,
          -33.533333
        ]
      },
      "type": "Feature",
      "properties": {
        "hierarchy": [
          "tgn:7314178",
          "tgn:1001708",
          "tgn:1000049",
          "tgn:1000002",
          "tgn:7029392"
        ],
        "placetype": [
          "aat:300000517"
        ],
        "id": 7314178,
        "name:xx": "Los Maitenes"
      }
    },
    {
      "geometry": {
        "type": "Point",
        "coordinates": [
          -73.566667,
          -45.183333
        ]
      },
      "type": "Feature",
      "properties": {
        "hierarchy": [
          "tgn:7314179",
          "tgn:1001623",
          "tgn:1000049",
          "tgn:1000002",
          "tgn:7029392"
        ],
        "placetype": [
          "aat:300387026"
        ],
        "id": 7314179,
        "name:xx": "Los Maceteros, Paso"
      }
    }
  ]
}
