{
  "geometry": {
    "type": "Point",
    "coordinates": [
      -127.7333,
      54.4167
    ]
  },
  "type": "Feature",
  "properties": {
    "hierarchy": [
      "tgn:1107314",
      "tgn:7005735",
      "tgn:7005685",
      "tgn:1000001",
      "tgn:7029392"
    ],
    "placetype": [
      "aat:300008798"
    ],
    "id": 1107314,
    "name:xx": "Howson Peak"
  }
}
