{
  "geometry": {
    "type": "Point",
    "coordinates": [
      -106.1833,
      39.6833
    ]
  },
  "type": "Feature",
  "properties": {
    "hierarchy": [
      "tgn:2188246",
      "tgn:1000001",
      "tgn:7012149",
      "tgn:7007158",
      "tgn:2000250",
      "tgn:7029392"
    ],
    "placetype": [
      "aat:300000390"
    ],
    "id": 2188246,
    "name:xx": "Boss Mine"
  }
}
