{
  "geometry": {
    "type": "Point",
    "coordinates": [
      -88.1833,
      45.1667
    ]
  },
  "type": "Feature",
  "properties": {
    "hierarchy": [
      "tgn:2606974",
      "tgn:1000001",
      "tgn:7012149",
      "tgn:2002341",
      "tgn:7007922",
      "tgn:7029392"
    ],
    "placetype": [
      "aat:300008680"
    ],
    "id": 2606974,
    "name:xx": "Ranch Lake"
  }
}
