{
  "geometry": {
    "type": "Point",
    "coordinates": [
      74.8625,
      32.513889
    ]
  },
  "type": "Feature",
  "properties": {
    "hierarchy": [
      "tgn:7590672",
      "tgn:1000004",
      "tgn:7000198",
      "tgn:7000799",
      "tgn:7029392"
    ],
    "placetype": [
      "aat:300008347"
    ],
    "name:en": "Kathār",
    "id": 7590672
  }
}
