{
  "geometry": {
    "type": "Point",
    "coordinates": [
      -106.6667,
      38.3333
    ]
  },
  "type": "Feature",
  "properties": {
    "hierarchy": [
      "tgn:2599756",
      "tgn:1000001",
      "tgn:7012149",
      "tgn:7007158",
      "tgn:2000246",
      "tgn:7029392"
    ],
    "placetype": [
      "aat:300008798"
    ],
    "id": 2599756,
    "name:xx": "Prosser Rock"
  }
}
