{
  "geometry": {
    "type": "Point",
    "coordinates": [
      -113.65,
      33.3833
    ]
  },
  "type": "Feature",
  "properties": {
    "hierarchy": [
      "tgn:2632336",
      "tgn:1000001",
      "tgn:7006451",
      "tgn:7012149",
      "tgn:2000104",
      "tgn:7029392"
    ],
    "placetype": [
      "aat:300386837"
    ],
    "id": 2632336,
    "name:xx": "Royal Arch"
  }
}
