{
  "geometry": {
    "type": "Point",
    "coordinates": [
      -95.7167,
      39.3333
    ]
  },
  "type": "Feature",
  "properties": {
    "hierarchy": [
      "tgn:2036770",
      "tgn:1000001",
      "tgn:2000702",
      "tgn:7012149",
      "tgn:7007254",
      "tgn:7029392"
    ],
    "placetype": [
      "aat:300008347"
    ],
    "id": 2036770,
    "name:xx": "Mayetta"
  }
}
