{
  "geometry": {
    "type": "Point",
    "coordinates": [
      -119.3333,
      46.3333
    ]
  },
  "type": "Feature",
  "properties": {
    "hierarchy": [
      "tgn:2399404",
      "tgn:2002240",
      "tgn:1000001",
      "tgn:7012149",
      "tgn:7007920",
      "tgn:7029392"
    ],
    "placetype": [
      "aat:300006075"
    ],
    "id": 2399404,
    "name:xx": "Horn Rapids Ditch"
  }
}
