{
  "geometry": {
    "type": "Point",
    "coordinates": [
      25.3167,
      57.85
    ]
  },
  "type": "Feature",
  "properties": {
    "hierarchy": [
      "tgn:1058797",
      "tgn:7012152",
      "tgn:1000003",
      "tgn:7006541",
      "tgn:7029392"
    ],
    "placetype": [
      "aat:300008347"
    ],
    "id": 1058797,
    "name:xx": "Rūjiena"
  }
}
