{
  "geometry": {
    "type": "Point",
    "coordinates": [
      -99.4667,
      27.8667
    ]
  },
  "type": "Feature",
  "properties": {
    "hierarchy": [
      "tgn:2714029",
      "tgn:1000001",
      "tgn:7012149",
      "tgn:2002090",
      "tgn:7007826",
      "tgn:7029392"
    ],
    "placetype": [
      "aat:300008706"
    ],
    "id": 2714029,
    "name:xx": "Tejones Creek"
  }
}
