{
  "geometry": {
    "type": "Point",
    "coordinates": [
      -80.6833,
      34.5833
    ]
  },
  "type": "Feature",
  "properties": {
    "hierarchy": [
      "tgn:2374939",
      "tgn:1000001",
      "tgn:7012149",
      "tgn:7007712",
      "tgn:7029392"
    ],
    "placetype": [
      "aat:300008706"
    ],
    "id": 2374939,
    "name:xx": "Hanging Rock Creek"
  }
}
