{
  "type": "FeatureCollection",
  "features": [
    {
      "geometry": {
        "type": "Point",
        "coordinates": [
          70.05,
          38.8833
        ]
      },
      "type": "Feature",
      "properties": {
        "hierarchy": [
          "tgn:1127982",
          "tgn:1000004",
          "tgn:7014835",
          "tgn:7029392"
        ],
        "placetype": [
          "aat:300008707"
        ],
        "id": 1127982,
        "name:xx": "Obikhingou"
      }
    },
    {
      "geometry": {
        "type": "Point",
        "coordinates": [
          -89.05,
          36.2667
        ]
      },
      "type": "Feature",
      "properties": {
        "hierarchy": [
          "tgn:1127983",
          "tgn:1000001",
          "tgn:7012149",
          "tgn:7007825",
          "tgn:7029392"
        ],
        "placetype": [
          "aat:300008707"
        ],
        "id": 1127983,
        "name:xx": "Obion"
      }
    },
    {
      "geometry": {
        "type": "Point",
        "coordinates": [
          139.9,
          35.4167
        ]
      },
      "type": "Feature",
      "properties": {
        "hierarchy": [
          "tgn:1127987",
          "tgn:1000971",
          "tgn:1000004",
          "tgn:7000894",
          "tgn:1000120",
          "tgn:7029392"
        ],
        "placetype": [
          "aat:300008707"
        ],
        "id": 1127987,
        "name:xx": "Obitsu-gawa"
      }
    },
    {
      "geometry": {
        "type": "Point",
        "coordinates": [
          29,
          55.4167
        ]
      },
      "type": "Feature",
      "properties": {
        "hierarchy": [
          "tgn:1127989",
          "tgn:1000003",
          "tgn:7029392"
        ],
        "placetype": [
          "aat:300008707"
        ],
        "id": 1127989,
        "name:be": "Obol'"
      }
    }
  ]
}
