{
  "type": "FeatureCollection",
  "features": [
    {
      "geometry": {
        "type": "Point",
        "coordinates": [
          -84.9,
          35.6333
        ]
      },
      "type": "Feature",
      "properties": {
        "hierarchy": [
          "tgn:2726560",
          "tgn:1000001",
          "tgn:7012149",
          "tgn:2001908",
          "tgn:7007825",
          "tgn:7029392"
        ],
        "placetype": [
          "aat:300008706"
        ],
        "id": 2726560,
        "name:xx": "Town Creek"
      }
    },
    {
      "geometry": {
        "type": "Point",
        "coordinates": [
          -99.1167,
          30.15
        ]
      },
      "type": "Feature",
      "properties": {
        "hierarchy": [
          "tgn:2726561",
          "tgn:1000001",
          "tgn:7012149",
          "tgn:7007826",
          "tgn:7029392"
        ],
        "placetype": [
          "aat:300008706"
        ],
        "id": 2726561,
        "name:xx": "Town Creek"
      }
    },
    {
      "geometry": {
        "type": "Point",
        "coordinates": [
          -98.8667,
          30.3
        ]
      },
      "type": "Feature",
      "properties": {
        "hierarchy": [
          "tgn:2726562",
          "tgn:1000001",
          "tgn:7012149",
          "tgn:2001990",
          "tgn:7007826",
          "tgn:7029392"
        ],
        "placetype": [
          "aat:300008706"
        ],
        "id": 2726562,
        "name:xx": "Town Creek"
      }
    },
    {
      "geometry": {
        "type": "Point",
        "coordinates": [
          -98.4,
          30.2333
        ]
      },
      "type": "Feature",
      "properties": {
        "hierarchy": [
          "tgn:2726563",
          "tgn:1000001",
          "tgn:2001942",
          "tgn:7012149",
          "tgn:7007826",
          "tgn:7029392"
        ],
        "placetype": [
          "aat:300008706"
        ],
        "id": 2726563,
        "name:xx": "Town Creek"
      }
    },
    {
      "geometry": {
        "type": "Point",
        "coordinates": [
          -100.4,
          32.45
        ]
      },
      "type": "Feature",
      "properties": {
        "hierarchy": [
          "tgn:2726564",
          "tgn:1000001",
          "tgn:7012149",
          "tgn:2002048",
          "tgn:7007826",
          "tgn:7029392"
        ],
        "placetype": [
          "aat:300008706"
        ],
        "id": 2726564,
        "name:xx": "Town Creek"
      }
    },
    {
      "geometry": {
        "type": "Point",
        "coordinates": [
          -97.8667,
          32.8167
        ]
      },
      "type": "Feature",
      "properties": {
        "hierarchy": [
          "tgn:2726565",
          "tgn:1000001",
          "tgn:7012149",
          "tgn:1002771",
          "tgn:7007826",
          "tgn:7029392"
        ],
        "placetype": [
          "aat:300008706"
        ],
        "id": 2726565,
        "name:xx": "Town Creek"
      }
    },
    {
      "geometry": {
        "type": "Point",
        "coordinates": [
          -94.0667,
          31.7
        ]
      },
      "type": "Feature",
      "properties": {
        "hierarchy": [
          "tgn:2726566",
          "tgn:1000001",
          "tgn:7012149",
          "tgn:2002073",
          "tgn:7007826",
          "tgn:7029392"
        ],
        "placetype": [
          "aat:300008706"
        ],
        "id": 2726566,
        "name:xx": "Town Creek"
      }
    },
    {
      "geometry": {
        "type": "Point",
        "coordinates": [
          -95.6333,
          31.7333
        ]
      },
      "type": "Feature",
      "properties": {
        "hierarchy": [
          "tgn:2726567",
          "tgn:1002148",
          "tgn:1000001",
          "tgn:7012149",
          "tgn:7007826",
          "tgn:7029392"
        ],
        "placetype": [
          "aat:300008706"
        ],
        "id": 2726567,
        "name:xx": "Town Creek"
      }
    },
    {
      "geometry": {
        "type": "Point",
        "coordinates": [
          -98.2333,
          29.6
        ]
      },
      "type": "Feature",
      "properties": {
        "hierarchy": [
          "tgn:2726568",
          "tgn:1000001",
          "tgn:7012149",
          "tgn:1002431",
          "tgn:7007826",
          "tgn:7029392"
        ],
        "placetype": [
          "aat:300008701"
        ],
        "id": 2726568,
        "name:xx": "Town Creek"
      }
    },
    {
      "geometry": {
        "type": "Point",
        "coordinates": [
          -81.95,
          36.7333
        ]
      },
      "type": "Feature",
      "properties": {
        "hierarchy": [
          "tgn:2726569",
          "tgn:1000001",
          "tgn:7012149",
          "tgn:2002194",
          "tgn:7007919",
          "tgn:7029392"
        ],
        "placetype": [
          "aat:300008706"
        ],
        "id": 2726569,
        "name:xx": "Town Creek"
      }
    }
  ]
}
