{
  "geometry": {
    "type": "Point",
    "coordinates": [
      -78.35,
      41.0333
    ]
  },
  "type": "Feature",
  "properties": {
    "hierarchy": [
      "tgn:2285872",
      "tgn:1000001",
      "tgn:1002278",
      "tgn:7012149",
      "tgn:7007710",
      "tgn:7029392"
    ],
    "placetype": [
      "aat:300008699"
    ],
    "id": 2285872,
    "name:xx": "Devils Run"
  }
}
