{
  "geometry": {
    "type": "Point",
    "coordinates": [
      -86.9833,
      34.1333
    ]
  },
  "type": "Feature",
  "properties": {
    "hierarchy": [
      "tgn:2570822",
      "tgn:7002659",
      "tgn:1000001",
      "tgn:7012149",
      "tgn:2000021",
      "tgn:7029392"
    ],
    "placetype": [
      "aat:300008699"
    ],
    "id": 2570822,
    "name:xx": "Patterson Branch"
  }
}
