{
  "geometry": {
    "type": "Point",
    "coordinates": [
      -73.9333,
      42.0333
    ]
  },
  "type": "Feature",
  "properties": {
    "hierarchy": [
      "tgn:2635969",
      "tgn:1000001",
      "tgn:7012149",
      "tgn:7007568",
      "tgn:7029392"
    ],
    "placetype": [
      "aat:300132348"
    ],
    "id": 2635969,
    "name:xx": "Saddle Bags"
  }
}
