{
  "geometry": {
    "type": "Point",
    "coordinates": [
      -119.5333,
      41.5167
    ]
  },
  "type": "Feature",
  "properties": {
    "hierarchy": [
      "tgn:2740075",
      "tgn:1000001",
      "tgn:7012149",
      "tgn:1002999",
      "tgn:7007526",
      "tgn:7029392"
    ],
    "placetype": [
      "aat:300008761"
    ],
    "id": 2740075,
    "name:xx": "Upper High Rock Canyon"
  }
}
