{
  "geometry": {
    "type": "Point",
    "coordinates": [
      11.9167,
      55.0167
    ]
  },
  "type": "Feature",
  "properties": {
    "hierarchy": [
      "tgn:7003609",
      "tgn:7594008",
      "tgn:1000003",
      "tgn:1000066",
      "tgn:7029392"
    ],
    "placetype": [
      "aat:300008347"
    ],
    "id": 7003609,
    "name:xx": "Vordingborg"
  }
}
