{
  "geometry": {
    "type": "Point",
    "coordinates": [
      -86.2333,
      36.45
    ]
  },
  "type": "Feature",
  "properties": {
    "hierarchy": [
      "tgn:2102163",
      "tgn:1000001",
      "tgn:7012149",
      "tgn:2001919",
      "tgn:7007825",
      "tgn:7029392"
    ],
    "placetype": [
      "aat:300387210",
      "aat:300008798"
    ],
    "id": 2102163,
    "name:xx": "Wolf Hill"
  }
}
