{
  "geometry": {
    "type": "Point",
    "coordinates": [
      13.016,
      42.75
    ]
  },
  "type": "Feature",
  "properties": {
    "hierarchy": [
      "tgn:7005198",
      "tgn:7003170",
      "tgn:1000003",
      "tgn:7003125",
      "tgn:1000080",
      "tgn:7029392"
    ],
    "placetype": [
      "aat:300008347"
    ],
    "id": 7005198,
    "name:xx": "San Giorgio"
  }
}
