{
  "geometry": {
    "type": "Point",
    "coordinates": [
      -83.6667,
      33.9833
    ]
  },
  "type": "Feature",
  "properties": {
    "hierarchy": [
      "tgn:2474904",
      "tgn:1000001",
      "tgn:2000298",
      "tgn:7012149",
      "tgn:7007248",
      "tgn:7029392"
    ],
    "placetype": [
      "aat:300006191"
    ],
    "id": 2474904,
    "name:xx": "Lower Twin Lake"
  }
}
