{
  "type": "FeatureCollection",
  "features": [
    {
      "geometry": {
        "type": "Point",
        "coordinates": [
          -122.7333,
          44.6167
        ]
      },
      "type": "Feature",
      "properties": {
        "hierarchy": [
          "tgn:2393221",
          "tgn:1000001",
          "tgn:7012149",
          "tgn:2001717",
          "tgn:7007708",
          "tgn:7029392"
        ],
        "placetype": [
          "aat:300006191"
        ],
        "id": 2393221,
        "name:xx": "Hoerauf Reservoir"
      }
    },
    {
      "geometry": {
        "type": "Point",
        "coordinates": [
          -77.5333,
          36.1
        ]
      },
      "type": "Feature",
      "properties": {
        "hierarchy": [
          "tgn:2393222",
          "tgn:1000001",
          "tgn:7012149",
          "tgn:2001501",
          "tgn:7007709",
          "tgn:7029392"
        ],
        "placetype": [
          "aat:300006191"
        ],
        "id": 2393222,
        "name:xx": "Hoerner Waldorf Pond"
      }
    },
    {
      "geometry": {
        "type": "Point",
        "coordinates": [
          -88.3,
          45.0167
        ]
      },
      "type": "Feature",
      "properties": {
        "hierarchy": [
          "tgn:2393223",
          "tgn:1000001",
          "tgn:7012149",
          "tgn:2002341",
          "tgn:7007922",
          "tgn:7029392"
        ],
        "placetype": [
          "aat:300008680"
        ],
        "id": 2393223,
        "name:xx": "Hoerth Lake"
      }
    },
    {
      "geometry": {
        "type": "Point",
        "coordinates": [
          -74.1,
          43.0167
        ]
      },
      "type": "Feature",
      "properties": {
        "hierarchy": [
          "tgn:2393224",
          "tgn:1000001",
          "tgn:7012149",
          "tgn:1002397",
          "tgn:7007568",
          "tgn:7029392"
        ],
        "placetype": [
          "aat:300008347"
        ],
        "id": 2393224,
        "name:xx": "Hoeseville"
      }
    },
    {
      "geometry": {
        "type": "Point",
        "coordinates": [
          -98.9,
          45.9667
        ]
      },
      "type": "Feature",
      "properties": {
        "hierarchy": [
          "tgn:2393226",
          "tgn:1000001",
          "tgn:7012149",
          "tgn:7029392"
        ],
        "placetype": [
          "aat:300008761"
        ],
        "id": 2393226,
        "name:xx": "Hoevens Gulch"
      }
    },
    {
      "geometry": {
        "type": "Point",
        "coordinates": [
          -123.5833,
          45.6833
        ]
      },
      "type": "Feature",
      "properties": {
        "hierarchy": [
          "tgn:2393227",
          "tgn:1000001",
          "tgn:7012149",
          "tgn:1002943",
          "tgn:7007708",
          "tgn:7029392"
        ],
        "placetype": [
          "aat:300008706"
        ],
        "id": 2393227,
        "name:xx": "Hoevet Creek"
      }
    },
    {
      "geometry": {
        "type": "Point",
        "coordinates": [
          -121.95,
          43.4833
        ]
      },
      "type": "Feature",
      "properties": {
        "hierarchy": [
          "tgn:2393228",
          "tgn:1000001",
          "tgn:7012149",
          "tgn:2001714",
          "tgn:7007708",
          "tgn:7029392"
        ],
        "placetype": [
          "aat:300008850"
        ],
        "id": 2393228,
        "name:xx": "Hoey Point"
      }
    },
    {
      "geometry": {
        "type": "Point",
        "coordinates": [
          -99.8333,
          42.3833
        ]
      },
      "type": "Feature",
      "properties": {
        "hierarchy": [
          "tgn:2393229",
          "tgn:1000001",
          "tgn:2001324",
          "tgn:7012149",
          "tgn:7007525",
          "tgn:7029392"
        ],
        "placetype": [
          "aat:300008680"
        ],
        "id": 2393229,
        "name:xx": "Hofeld Lake"
      }
    }
  ]
}
