{
  "geometry": {
    "type": "Point",
    "coordinates": [
      -86.8333,
      38.8667
    ]
  },
  "type": "Feature",
  "properties": {
    "hierarchy": [
      "tgn:2184991",
      "tgn:1000001",
      "tgn:7012149",
      "tgn:2000546",
      "tgn:7007252",
      "tgn:7029392"
    ],
    "placetype": [
      "aat:300008706"
    ],
    "id": 2184991,
    "name:xx": "Boggs Creek"
  }
}
