{
  "geometry": {
    "type": "Point",
    "coordinates": [
      -101.6833,
      44.4167
    ]
  },
  "type": "Feature",
  "properties": {
    "hierarchy": [
      "tgn:2376429",
      "tgn:1000001",
      "tgn:7012149",
      "tgn:7007713",
      "tgn:7029392"
    ],
    "placetype": [
      "aat:300008706"
    ],
    "id": 2376429,
    "name:xx": "Harding Creek"
  }
}
