{
  "geometry": {
    "type": "Point",
    "coordinates": [
      -78.8333,
      40.2167
    ]
  },
  "type": "Feature",
  "properties": {
    "hierarchy": [
      "tgn:2688630",
      "tgn:1000001",
      "tgn:7012149",
      "tgn:1002904",
      "tgn:7007710",
      "tgn:7029392"
    ],
    "placetype": [
      "aat:300008699"
    ],
    "id": 2688630,
    "name:xx": "Spruce Run"
  }
}
