{
  "geometry": {
    "type": "Point",
    "coordinates": [
      -81.0833,
      35.6667
    ]
  },
  "type": "Feature",
  "properties": {
    "hierarchy": [
      "tgn:2533032",
      "tgn:1000001",
      "tgn:2001479",
      "tgn:7012149",
      "tgn:7007709",
      "tgn:7029392"
    ],
    "placetype": [
      "aat:300008347"
    ],
    "id": 2533032,
    "name:xx": "Murrays Hill"
  }
}
