{
  "type": "FeatureCollection",
  "features": [
    {
      "geometry": {
        "type": "Point",
        "coordinates": [
          -109.2833,
          45.35
        ]
      },
      "type": "Feature",
      "properties": {
        "hierarchy": [
          "tgn:2211260",
          "tgn:1000001",
          "tgn:2001264",
          "tgn:7012149",
          "tgn:7007524",
          "tgn:7029392"
        ],
        "placetype": [
          "aat:300008706"
        ],
        "id": 2211260,
        "name:xx": "Butte Creek"
      }
    },
    {
      "geometry": {
        "type": "Point",
        "coordinates": [
          -106.9833,
          45.6333
        ]
      },
      "type": "Feature",
      "properties": {
        "hierarchy": [
          "tgn:2211261",
          "tgn:1000001",
          "tgn:2001261",
          "tgn:7012149",
          "tgn:7007524",
          "tgn:7029392"
        ],
        "placetype": [
          "aat:300008706"
        ],
        "id": 2211261,
        "name:xx": "Butte Creek"
      }
    },
    {
      "geometry": {
        "type": "Point",
        "coordinates": [
          -105.1833,
          45.7833
        ]
      },
      "type": "Feature",
      "properties": {
        "hierarchy": [
          "tgn:2211262",
          "tgn:1000001",
          "tgn:7012149",
          "tgn:7007524",
          "tgn:7029392"
        ],
        "placetype": [
          "aat:300008706"
        ],
        "id": 2211262,
        "name:xx": "Butte Creek"
      }
    },
    {
      "geometry": {
        "type": "Point",
        "coordinates": [
          -105.7667,
          45.9667
        ]
      },
      "type": "Feature",
      "properties": {
        "hierarchy": [
          "tgn:2211263",
          "tgn:1000001",
          "tgn:2001268",
          "tgn:7012149",
          "tgn:7007524",
          "tgn:7029392"
        ],
        "placetype": [
          "aat:300008706"
        ],
        "id": 2211263,
        "name:xx": "Butte Creek"
      }
    },
    {
      "geometry": {
        "type": "Point",
        "coordinates": [
          -106.4,
          46.1667
        ]
      },
      "type": "Feature",
      "properties": {
        "hierarchy": [
          "tgn:2211264",
          "tgn:1000001",
          "tgn:7012149",
          "tgn:2001303",
          "tgn:7007524",
          "tgn:7029392"
        ],
        "placetype": [
          "aat:300008706"
        ],
        "id": 2211264,
        "name:xx": "Butte Creek"
      }
    },
    {
      "geometry": {
        "type": "Point",
        "coordinates": [
          -107.75,
          46.35
        ]
      },
      "type": "Feature",
      "properties": {
        "hierarchy": [
          "tgn:2211265",
          "tgn:1000001",
          "tgn:7012149",
          "tgn:2001311",
          "tgn:7007524",
          "tgn:7029392"
        ],
        "placetype": [
          "aat:300008706"
        ],
        "id": 2211265,
        "name:xx": "Butte Creek"
      }
    },
    {
      "geometry": {
        "type": "Point",
        "coordinates": [
          -110.2,
          47.4667
        ]
      },
      "type": "Feature",
      "properties": {
        "hierarchy": [
          "tgn:2211266",
          "tgn:1000001",
          "tgn:2001267",
          "tgn:7012149",
          "tgn:7007524",
          "tgn:7029392"
        ],
        "placetype": [
          "aat:300008706"
        ],
        "id": 2211266,
        "name:xx": "Butte Creek"
      }
    },
    {
      "geometry": {
        "type": "Point",
        "coordinates": [
          -105.95,
          48.8833
        ]
      },
      "type": "Feature",
      "properties": {
        "hierarchy": [
          "tgn:2211267",
          "tgn:1000001",
          "tgn:2001269",
          "tgn:7012149",
          "tgn:7007524",
          "tgn:7029392"
        ],
        "placetype": [
          "aat:300008706"
        ],
        "id": 2211267,
        "name:xx": "Butte Creek"
      }
    },
    {
      "geometry": {
        "type": "Point",
        "coordinates": [
          -118.4,
          41.9667
        ]
      },
      "type": "Feature",
      "properties": {
        "hierarchy": [
          "tgn:2211268",
          "tgn:1000001",
          "tgn:2001414",
          "tgn:7012149",
          "tgn:7007526",
          "tgn:7029392"
        ],
        "placetype": [
          "aat:300008706"
        ],
        "id": 2211268,
        "name:xx": "Butte Creek"
      }
    },
    {
      "geometry": {
        "type": "Point",
        "coordinates": [
          -114.9833,
          40.1833
        ]
      },
      "type": "Feature",
      "properties": {
        "hierarchy": [
          "tgn:2211269",
          "tgn:1000001",
          "tgn:2001411",
          "tgn:7012149",
          "tgn:7007526",
          "tgn:7029392"
        ],
        "placetype": [
          "aat:300008706"
        ],
        "id": 2211269,
        "name:xx": "Butte Creek"
      }
    }
  ]
}
