{
  "geometry": {
    "type": "Point",
    "coordinates": [
      -82.0833,
      38.4833
    ]
  },
  "type": "Feature",
  "properties": {
    "hierarchy": [
      "tgn:2618659",
      "tgn:1000001",
      "tgn:2002257",
      "tgn:7012149",
      "tgn:7013961",
      "tgn:7029392"
    ],
    "placetype": [
      "aat:300008706"
    ],
    "id": 2618659,
    "name:xx": "Right Fork Mill Creek"
  }
}
