{
  "type": "FeatureCollection",
  "features": [
    {
      "geometry": {
        "type": "Point",
        "coordinates": [
          -84.7333,
          36.2833
        ]
      },
      "type": "Feature",
      "properties": {
        "hierarchy": [
          "tgn:2201720",
          "tgn:1000001",
          "tgn:7012149",
          "tgn:2001901",
          "tgn:7007825",
          "tgn:7029392"
        ],
        "placetype": [
          "aat:300008706"
        ],
        "id": 2201720,
        "name:xx": "Buck Creek"
      }
    },
    {
      "geometry": {
        "type": "Point",
        "coordinates": [
          -87.85,
          35.1833
        ]
      },
      "type": "Feature",
      "properties": {
        "hierarchy": [
          "tgn:2201721",
          "tgn:1000001",
          "tgn:7012149",
          "tgn:2001927",
          "tgn:7007825",
          "tgn:7029392"
        ],
        "placetype": [
          "aat:300008706"
        ],
        "id": 2201721,
        "name:xx": "Buck Creek"
      }
    },
    {
      "geometry": {
        "type": "Point",
        "coordinates": [
          -85.7833,
          35.3667
        ]
      },
      "type": "Feature",
      "properties": {
        "hierarchy": [
          "tgn:2201722",
          "tgn:1000001",
          "tgn:7012149",
          "tgn:2001867",
          "tgn:7007825",
          "tgn:7029392"
        ],
        "placetype": [
          "aat:300008706"
        ],
        "id": 2201722,
        "name:xx": "Buck Creek"
      }
    },
    {
      "geometry": {
        "type": "Point",
        "coordinates": [
          -89.1333,
          35.7833
        ]
      },
      "type": "Feature",
      "properties": {
        "hierarchy": [
          "tgn:2201723",
          "tgn:1000001",
          "tgn:7012149",
          "tgn:2001853",
          "tgn:7007825",
          "tgn:7029392"
        ],
        "placetype": [
          "aat:300008706"
        ],
        "id": 2201723,
        "name:xx": "Buck Creek"
      }
    },
    {
      "geometry": {
        "type": "Point",
        "coordinates": [
          -84.9833,
          35.85
        ]
      },
      "type": "Feature",
      "properties": {
        "hierarchy": [
          "tgn:2201724",
          "tgn:1000001",
          "tgn:7012149",
          "tgn:2001854",
          "tgn:7007825",
          "tgn:7029392"
        ],
        "placetype": [
          "aat:300008706"
        ],
        "id": 2201724,
        "name:xx": "Buck Creek"
      }
    },
    {
      "geometry": {
        "type": "Point",
        "coordinates": [
          -89.0167,
          35.9167
        ]
      },
      "type": "Feature",
      "properties": {
        "hierarchy": [
          "tgn:2201725",
          "tgn:1000001",
          "tgn:7012149",
          "tgn:7007825",
          "tgn:7029392"
        ],
        "placetype": [
          "aat:300008706"
        ],
        "id": 2201725,
        "name:xx": "Buck Creek"
      }
    },
    {
      "geometry": {
        "type": "Point",
        "coordinates": [
          -94.4,
          33.0167
        ]
      },
      "type": "Feature",
      "properties": {
        "hierarchy": [
          "tgn:2201726",
          "tgn:1000001",
          "tgn:7012149",
          "tgn:1002244",
          "tgn:7007826",
          "tgn:7029392"
        ],
        "placetype": [
          "aat:300008706"
        ],
        "id": 2201726,
        "name:xx": "Buck Creek"
      }
    },
    {
      "geometry": {
        "type": "Point",
        "coordinates": [
          -102.2167,
          30.1
        ]
      },
      "type": "Feature",
      "properties": {
        "hierarchy": [
          "tgn:2201727",
          "tgn:1000001",
          "tgn:7012149",
          "tgn:2002082",
          "tgn:7007826",
          "tgn:7029392"
        ],
        "placetype": [
          "aat:300008706"
        ],
        "id": 2201727,
        "name:xx": "Buck Creek"
      }
    },
    {
      "geometry": {
        "type": "Point",
        "coordinates": [
          -96.6667,
          30.1167
        ]
      },
      "type": "Feature",
      "properties": {
        "hierarchy": [
          "tgn:2201728",
          "tgn:1000001",
          "tgn:7012149",
          "tgn:1002374",
          "tgn:7007826",
          "tgn:7029392"
        ],
        "placetype": [
          "aat:300008706"
        ],
        "id": 2201728,
        "name:xx": "Buck Creek"
      }
    },
    {
      "geometry": {
        "type": "Point",
        "coordinates": [
          -99.75,
          32
        ]
      },
      "type": "Feature",
      "properties": {
        "hierarchy": [
          "tgn:2201729",
          "tgn:1000001",
          "tgn:7012149",
          "tgn:7007826",
          "tgn:7029392"
        ],
        "placetype": [
          "aat:300008706"
        ],
        "id": 2201729,
        "name:xx": "Buck Creek"
      }
    }
  ]
}
