{
  "geometry": {
    "type": "Point",
    "coordinates": [
      -174.1333,
      52.1667
    ]
  },
  "type": "Feature",
  "properties": {
    "hierarchy": [
      "tgn:2599338",
      "tgn:7030516",
      "tgn:7006450",
      "tgn:1000001",
      "tgn:7012149",
      "tgn:7029392"
    ],
    "placetype": [
      "aat:300008850"
    ],
    "id": 2599338,
    "name:xx": "Profile Point"
  }
}
