{
  "geometry": {
    "type": "Point",
    "coordinates": [
      -83.1167,
      35.65
    ]
  },
  "type": "Feature",
  "properties": {
    "hierarchy": [
      "tgn:2276658",
      "tgn:1000001",
      "tgn:7012149",
      "tgn:2001503",
      "tgn:7007709",
      "tgn:7029392"
    ],
    "placetype": [
      "aat:300008699"
    ],
    "id": 2276658,
    "name:xx": "Davidson Branch"
  }
}
