{
  "geometry": {
    "type": "Point",
    "coordinates": [
      124.0667,
      41.8333
    ]
  },
  "type": "Feature",
  "properties": {
    "hierarchy": [
      "tgn:1139985",
      "tgn:1000004",
      "tgn:1001390",
      "tgn:1000111",
      "tgn:7029392"
    ],
    "placetype": [
      "aat:300008347"
    ],
    "id": 1139985,
    "name:xx": "Yingchengzi"
  }
}
