{
  "geometry": {
    "type": "Point",
    "coordinates": [
      26.35,
      62.6333
    ]
  },
  "type": "Feature",
  "properties": {
    "hierarchy": [
      "tgn:1031534",
      "tgn:7594394",
      "tgn:1000003",
      "tgn:1000069",
      "tgn:7029392"
    ],
    "placetype": [
      "aat:300008347"
    ],
    "id": 1031534,
    "name:xx": "Rautalampi"
  }
}
