{
  "geometry": {
    "type": "Point",
    "coordinates": [
      -120.3167,
      47.85
    ]
  },
  "type": "Feature",
  "properties": {
    "hierarchy": [
      "tgn:2595395",
      "tgn:1000001",
      "tgn:1002260",
      "tgn:7012149",
      "tgn:7007920",
      "tgn:7029392"
    ],
    "placetype": [
      "aat:300008706"
    ],
    "id": 2595395,
    "name:xx": "Potato Creek"
  }
}
