{
  "geometry": {
    "type": "Point",
    "coordinates": [
      -99.5833,
      55.5833
    ]
  },
  "type": "Feature",
  "properties": {
    "hierarchy": [
      "tgn:1115434",
      "tgn:7005685",
      "tgn:1000001",
      "tgn:7005734",
      "tgn:7029392"
    ],
    "placetype": [
      "aat:300008680"
    ],
    "id": 1115434,
    "name:xx": "Apeganau Lake"
  }
}
