{
  "geometry": {
    "type": "Point",
    "coordinates": [
      -87.85,
      37.4667
    ]
  },
  "type": "Feature",
  "properties": {
    "hierarchy": [
      "tgn:2551404",
      "tgn:1000001",
      "tgn:7012149",
      "tgn:2000851",
      "tgn:7007255",
      "tgn:7029392"
    ],
    "placetype": [
      "aat:300000390"
    ],
    "id": 2551404,
    "name:xx": "Number 10, Mine"
  }
}
