{
  "type": "FeatureCollection",
  "features": [
    {
      "geometry": {
        "type": "Point",
        "coordinates": [
          -95.4,
          33.85
        ]
      },
      "type": "Feature",
      "properties": {
        "hierarchy": [
          "tgn:2107700",
          "tgn:1000001",
          "tgn:7012149",
          "tgn:2002024",
          "tgn:7007826",
          "tgn:7029392"
        ],
        "placetype": [
          "aat:300008347",
          "aat:300387210"
        ],
        "id": 2107700,
        "name:xx": "Slate Shoals"
      }
    },
    {
      "geometry": {
        "type": "Point",
        "coordinates": [
          -101.6333,
          33.4333
        ]
      },
      "type": "Feature",
      "properties": {
        "hierarchy": [
          "tgn:2107701",
          "tgn:1000001",
          "tgn:7012149",
          "tgn:2002032",
          "tgn:7007826",
          "tgn:7029392"
        ],
        "placetype": [
          "aat:300008347"
        ],
        "id": 2107701,
        "name:xx": "Slaton"
      }
    },
    {
      "geometry": {
        "type": "Point",
        "coordinates": [
          -101.9167,
          33.4
        ]
      },
      "type": "Feature",
      "properties": {
        "hierarchy": [
          "tgn:2107704",
          "tgn:1000001",
          "tgn:7012149",
          "tgn:2002032",
          "tgn:7007826",
          "tgn:7029392"
        ],
        "placetype": [
          "aat:300008347",
          "aat:300387210"
        ],
        "id": 2107704,
        "name:xx": "Slide"
      }
    },
    {
      "geometry": {
        "type": "Point",
        "coordinates": [
          -95.45,
          31.6167
        ]
      },
      "type": "Feature",
      "properties": {
        "hierarchy": [
          "tgn:2107707",
          "tgn:1002148",
          "tgn:1000001",
          "tgn:7012149",
          "tgn:7007826",
          "tgn:7029392"
        ],
        "placetype": [
          "aat:300008347"
        ],
        "id": 2107707,
        "name:xx": "Slocum"
      }
    },
    {
      "geometry": {
        "type": "Point",
        "coordinates": [
          -95.85,
          32.7333
        ]
      },
      "type": "Feature",
      "properties": {
        "hierarchy": [
          "tgn:2107708",
          "tgn:1000001",
          "tgn:7012149",
          "tgn:1002969",
          "tgn:7007826",
          "tgn:7029392"
        ],
        "placetype": [
          "aat:300008347",
          "aat:300387210"
        ],
        "id": 2107708,
        "name:xx": "Small"
      }
    },
    {
      "geometry": {
        "type": "Point",
        "coordinates": [
          -96.45,
          30.65
        ]
      },
      "type": "Feature",
      "properties": {
        "hierarchy": [
          "tgn:2107709",
          "tgn:1000001",
          "tgn:1002199",
          "tgn:7012149",
          "tgn:7007826",
          "tgn:7029392"
        ],
        "placetype": [
          "aat:300008347",
          "aat:300387210"
        ],
        "id": 2107709,
        "name:xx": "Smetana"
      }
    }
  ]
}
