{
  "geometry": {
    "type": "Point",
    "coordinates": [
      -83.3333,
      38.9833
    ]
  },
  "type": "Feature",
  "properties": {
    "hierarchy": [
      "tgn:2582611",
      "tgn:1002136",
      "tgn:1000001",
      "tgn:7012149",
      "tgn:7007706",
      "tgn:7029392"
    ],
    "placetype": [
      "aat:300008798"
    ],
    "id": 2582611,
    "name:xx": "Pine Hill"
  }
}
