{
  "geometry": {
    "type": "Point",
    "coordinates": [
      -84.2167,
      30.6167
    ]
  },
  "type": "Feature",
  "properties": {
    "hierarchy": [
      "tgn:2445915",
      "tgn:1000001",
      "tgn:7012149",
      "tgn:2000276",
      "tgn:7007240",
      "tgn:7029392"
    ],
    "placetype": [
      "aat:300008791"
    ],
    "id": 2445915,
    "name:xx": "Lester Island"
  }
}
