{
  "type": "FeatureCollection",
  "features": [
    {
      "geometry": {
        "type": "Point",
        "coordinates": [
          -76.5167,
          37.4
        ]
      },
      "type": "Feature",
      "properties": {
        "hierarchy": [
          "tgn:2111950",
          "tgn:1000001",
          "tgn:7012149",
          "tgn:1002411",
          "tgn:7007919",
          "tgn:7029392"
        ],
        "placetype": [
          "aat:300008347"
        ],
        "id": 2111950,
        "name:xx": "Gloucester"
      }
    },
    {
      "geometry": {
        "type": "Point",
        "coordinates": [
          -76.4833,
          37.25
        ]
      },
      "type": "Feature",
      "properties": {
        "hierarchy": [
          "tgn:2111953",
          "tgn:1000001",
          "tgn:7012149",
          "tgn:1002411",
          "tgn:7007919",
          "tgn:7029392"
        ],
        "placetype": [
          "aat:300008347"
        ],
        "id": 2111953,
        "name:xx": "Gloucester Point"
      }
    },
    {
      "geometry": {
        "type": "Point",
        "coordinates": [
          -77.5,
          37.9667
        ]
      },
      "type": "Feature",
      "properties": {
        "hierarchy": [
          "tgn:2111957",
          "tgn:1000001",
          "tgn:1002235",
          "tgn:7012149",
          "tgn:7007919",
          "tgn:7029392"
        ],
        "placetype": [
          "aat:300008347"
        ],
        "id": 2111957,
        "name:xx": "Golansville"
      }
    },
    {
      "geometry": {
        "type": "Point",
        "coordinates": [
          -80.6667,
          37.3667
        ]
      },
      "type": "Feature",
      "properties": {
        "hierarchy": [
          "tgn:2111958",
          "tgn:1000001",
          "tgn:7012149",
          "tgn:2002162",
          "tgn:7007919",
          "tgn:7029392"
        ],
        "placetype": [
          "aat:300008347"
        ],
        "id": 2111958,
        "name:xx": "Goldbond"
      }
    }
  ]
}
