{
  "type": "FeatureCollection",
  "features": [
    {
      "geometry": {
        "type": "Point",
        "coordinates": [
          30.233333,
          31.033333
        ]
      },
      "type": "Feature",
      "properties": {
        "hierarchy": [
          "tgn:7520280",
          "tgn:7001242",
          "tgn:1001075",
          "tgn:7016833",
          "tgn:7029392"
        ],
        "placetype": [
          "aat:300000206"
        ],
        "name:en": "'Izbat 'Abbās Abū ar Rīsh",
        "id": 7520280
      }
    },
    {
      "geometry": {
        "type": "Point",
        "coordinates": [
          32.283333,
          22.633333
        ]
      },
      "type": "Feature",
      "properties": {
        "hierarchy": [
          "tgn:7520281",
          "tgn:7001242",
          "tgn:7001311",
          "tgn:7016833",
          "tgn:7029392"
        ],
        "placetype": [
          "aat:300379998"
        ],
        "name:en": "'Abbās, Wādī",
        "id": 7520281
      }
    },
    {
      "geometry": {
        "type": "Point",
        "coordinates": [
          30.830879,
          28.596809
        ]
      },
      "type": "Feature",
      "properties": {
        "hierarchy": [
          "tgn:7520282",
          "tgn:7001242",
          "tgn:7016833",
          "tgn:1001088",
          "tgn:7029392"
        ],
        "placetype": [
          "aat:300008347"
        ],
        "name:en": "'Abbād Shārūnah",
        "id": 7520282
      }
    },
    {
      "geometry": {
        "type": "Point",
        "coordinates": [
          33.554696,
          25.33797
        ]
      },
      "type": "Feature",
      "properties": {
        "hierarchy": [
          "tgn:7520283",
          "tgn:7001242",
          "tgn:7001311",
          "tgn:7016833",
          "tgn:7029392"
        ],
        "placetype": [
          "aat:300379998"
        ],
        "name:en": "'Abbâdîya, Wâdi",
        "id": 7520283
      }
    },
    {
      "geometry": {
        "type": "Point",
        "coordinates": [
          33.018881,
          25.011942
        ]
      },
      "type": "Feature",
      "properties": {
        "hierarchy": [
          "tgn:7520284",
          "tgn:7001242",
          "tgn:7001311",
          "tgn:7016833",
          "tgn:7029392"
        ],
        "placetype": [
          "aat:300379998"
        ],
        "name:en": "'Abbād, Wādī",
        "id": 7520284
      }
    },
    {
      "geometry": {
        "type": "Point",
        "coordinates": [
          33.052927,
          25.027588
        ]
      },
      "type": "Feature",
      "properties": {
        "hierarchy": [
          "tgn:7520285",
          "tgn:7001242",
          "tgn:7001311",
          "tgn:7016833",
          "tgn:7029392"
        ],
        "placetype": [
          "aat:300006207"
        ],
        "name:en": "Bi'r 'Abbād",
        "id": 7520285
      }
    },
    {
      "geometry": {
        "type": "Point",
        "coordinates": [
          30.273889,
          30.848889
        ]
      },
      "type": "Feature",
      "properties": {
        "hierarchy": [
          "tgn:7520286",
          "tgn:7001242",
          "tgn:1001075",
          "tgn:7016833",
          "tgn:7029392"
        ],
        "placetype": [
          "aat:300000206"
        ],
        "name:en": "'Ezbet Abâza el-Qiblîya",
        "id": 7520286
      }
    },
    {
      "geometry": {
        "type": "Point",
        "coordinates": [
          26.316667,
          31.366667
        ]
      },
      "type": "Feature",
      "properties": {
        "hierarchy": [
          "tgn:7520287",
          "tgn:7001242",
          "tgn:7016833",
          "tgn:1001418",
          "tgn:7029392"
        ],
        "placetype": [
          "aat:300005926"
        ],
        "name:en": "Qubûret el 'Abâya",
        "id": 7520287
      }
    },
    {
      "geometry": {
        "type": "Point",
        "coordinates": [
          34.839659,
          24.188819
        ]
      },
      "type": "Feature",
      "properties": {
        "hierarchy": [
          "tgn:7520288",
          "tgn:7001242",
          "tgn:7001311",
          "tgn:7016833",
          "tgn:7029392"
        ],
        "placetype": [
          "aat:300008795"
        ],
        "name:en": "Abarūn, Jabal",
        "id": 7520288
      }
    },
    {
      "geometry": {
        "type": "Point",
        "coordinates": [
          32.471149,
          29.93268
        ]
      },
      "type": "Feature",
      "properties": {
        "hierarchy": [
          "tgn:7520289",
          "tgn:7001242",
          "tgn:7016833",
          "tgn:1001110",
          "tgn:7029392"
        ],
        "placetype": [
          "aat:300379998"
        ],
        "name:en": "Ābār, Wādī al",
        "id": 7520289
      }
    }
  ]
}
