{
  "geometry": {
    "type": "Point",
    "coordinates": [
      -108.55,
      43.2833
    ]
  },
  "type": "Feature",
  "properties": {
    "hierarchy": [
      "tgn:2530750",
      "tgn:1000001",
      "tgn:7012149",
      "tgn:2002371",
      "tgn:7007923",
      "tgn:7029392"
    ],
    "placetype": [
      "aat:300006075"
    ],
    "id": 2530750,
    "name:xx": "Muddy Ridge Canal"
  }
}
