{
  "geometry": {
    "type": "Point",
    "coordinates": [
      -83.1833,
      35.5333
    ]
  },
  "type": "Feature",
  "properties": {
    "hierarchy": [
      "tgn:2423529",
      "tgn:1000001",
      "tgn:7012149",
      "tgn:2001543",
      "tgn:7007709",
      "tgn:7029392"
    ],
    "placetype": [
      "aat:300008706"
    ],
    "id": 2423529,
    "name:xx": "John Henry Camp Creek"
  }
}
