{
  "geometry": {
    "type": "Point",
    "coordinates": [
      76.9833,
      37.0167
    ]
  },
  "type": "Feature",
  "properties": {
    "hierarchy": [
      "tgn:1066505",
      "tgn:1000004",
      "tgn:7001745",
      "tgn:1000111",
      "tgn:7029392"
    ],
    "placetype": [
      "aat:300008347"
    ],
    "id": 1066505,
    "name:xx": "Alasitan"
  }
}
