{
  "geometry": {
    "type": "Point",
    "coordinates": [
      -90.8833,
      31.7833
    ]
  },
  "type": "Feature",
  "properties": {
    "hierarchy": [
      "tgn:2405504",
      "tgn:1000001",
      "tgn:7012149",
      "tgn:7007522",
      "tgn:7029392"
    ],
    "placetype": [
      "aat:300008706"
    ],
    "id": 2405504,
    "name:xx": "Hughes Creek"
  }
}
