{
  "geometry": {
    "type": "Point",
    "coordinates": [
      -84.2833,
      35.2167
    ]
  },
  "type": "Feature",
  "properties": {
    "hierarchy": [
      "tgn:2759691",
      "tgn:1000001",
      "tgn:7012149",
      "tgn:7007825",
      "tgn:7029392"
    ],
    "placetype": [
      "aat:300008707"
    ],
    "id": 2759691,
    "name:xx": "West Fork Hiwassee River"
  }
}
