{
  "geometry": {
    "type": "Point",
    "coordinates": [
      -107.7667,
      47.9333
    ]
  },
  "type": "Feature",
  "properties": {
    "hierarchy": [
      "tgn:2170624",
      "tgn:1000001",
      "tgn:7012149",
      "tgn:2001295",
      "tgn:7007524",
      "tgn:7029392"
    ],
    "placetype": [
      "aat:300386845"
    ],
    "id": 2170624,
    "name:xx": "Big Sag, The"
  }
}
