{
  "geometry": {
    "type": "Point",
    "coordinates": [
      -76.6167,
      38.8167
    ]
  },
  "type": "Feature",
  "properties": {
    "hierarchy": [
      "tgn:2477437",
      "tgn:1000001",
      "tgn:7012149",
      "tgn:7007516",
      "tgn:7029392"
    ],
    "placetype": [
      "aat:300008706"
    ],
    "id": 2477437,
    "name:xx": "Lyons Creek"
  }
}
