{
  "geometry": {
    "type": "Point",
    "coordinates": [
      -113.0167,
      44.1667
    ]
  },
  "type": "Feature",
  "properties": {
    "hierarchy": [
      "tgn:2431856",
      "tgn:1000001",
      "tgn:7012149",
      "tgn:7007250",
      "tgn:7029392"
    ],
    "placetype": [
      "aat:300008761"
    ],
    "id": 2431856,
    "name:xx": "Kaufman Gulch"
  }
}
