{
  "geometry": {
    "type": "Point",
    "coordinates": [
      -107.6833,
      38.0167
    ]
  },
  "type": "Feature",
  "properties": {
    "hierarchy": [
      "tgn:2736313",
      "tgn:1000001",
      "tgn:7012149",
      "tgn:2000237",
      "tgn:7007158",
      "tgn:7029392"
    ],
    "placetype": [
      "aat:300008798"
    ],
    "id": 2736313,
    "name:xx": "Twin Peaks"
  }
}
