{
  "type": "FeatureCollection",
  "features": [
    {
      "geometry": {
        "type": "Point",
        "coordinates": [
          -83.2,
          38.0167
        ]
      },
      "type": "Feature",
      "properties": {
        "hierarchy": [
          "tgn:2756670",
          "tgn:1000001",
          "tgn:7012149",
          "tgn:1002354",
          "tgn:7007255",
          "tgn:7029392"
        ],
        "placetype": [
          "aat:300008706"
        ],
        "id": 2756670,
        "name:xx": "Wells Creek"
      }
    },
    {
      "geometry": {
        "type": "Point",
        "coordinates": [
          -83.7667,
          38.6
        ]
      },
      "type": "Feature",
      "properties": {
        "hierarchy": [
          "tgn:2756671",
          "tgn:1000001",
          "tgn:7012149",
          "tgn:1002644",
          "tgn:7007255",
          "tgn:7029392"
        ],
        "placetype": [
          "aat:300008706"
        ],
        "id": 2756671,
        "name:xx": "Wells Creek"
      }
    },
    {
      "geometry": {
        "type": "Point",
        "coordinates": [
          -90,
          30.7167
        ]
      },
      "type": "Feature",
      "properties": {
        "hierarchy": [
          "tgn:2756672",
          "tgn:1000001",
          "tgn:7012149",
          "tgn:2000912",
          "tgn:7007256",
          "tgn:7029392"
        ],
        "placetype": [
          "aat:300008706"
        ],
        "id": 2756672,
        "name:xx": "Wells Creek"
      }
    },
    {
      "geometry": {
        "type": "Point",
        "coordinates": [
          -70.3333,
          41.7167
        ]
      },
      "type": "Feature",
      "properties": {
        "hierarchy": [
          "tgn:2756673",
          "tgn:1002165",
          "tgn:1000001",
          "tgn:7012149",
          "tgn:7007517",
          "tgn:7029392"
        ],
        "placetype": [
          "aat:300008706"
        ],
        "id": 2756673,
        "name:xx": "Wells Creek"
      }
    },
    {
      "geometry": {
        "type": "Point",
        "coordinates": [
          -84.1333,
          44.0667
        ]
      },
      "type": "Feature",
      "properties": {
        "hierarchy": [
          "tgn:2756674",
          "tgn:2000946",
          "tgn:1000001",
          "tgn:7012149",
          "tgn:7007520",
          "tgn:7029392"
        ],
        "placetype": [
          "aat:300008706"
        ],
        "id": 2756674,
        "name:xx": "Wells Creek"
      }
    },
    {
      "geometry": {
        "type": "Point",
        "coordinates": [
          -92.5667,
          44.3833
        ]
      },
      "type": "Feature",
      "properties": {
        "hierarchy": [
          "tgn:2756675",
          "tgn:1000001",
          "tgn:2001023",
          "tgn:7012149",
          "tgn:7007521",
          "tgn:7029392"
        ],
        "placetype": [
          "aat:300008706"
        ],
        "id": 2756675,
        "name:xx": "Wells Creek"
      }
    },
    {
      "geometry": {
        "type": "Point",
        "coordinates": [
          -91.05,
          31.5667
        ]
      },
      "type": "Feature",
      "properties": {
        "hierarchy": [
          "tgn:2756676",
          "tgn:1000001",
          "tgn:7012149",
          "tgn:2001104",
          "tgn:7007522",
          "tgn:7029392"
        ],
        "placetype": [
          "aat:300008706"
        ],
        "id": 2756676,
        "name:xx": "Wells Creek"
      }
    },
    {
      "geometry": {
        "type": "Point",
        "coordinates": [
          -90.7667,
          36.55
        ]
      },
      "type": "Feature",
      "properties": {
        "hierarchy": [
          "tgn:2756677",
          "tgn:1000001",
          "tgn:7012149",
          "tgn:2001237",
          "tgn:7007523",
          "tgn:7029392"
        ],
        "placetype": [
          "aat:300008706"
        ],
        "id": 2756677,
        "name:xx": "Wells Creek"
      }
    },
    {
      "geometry": {
        "type": "Point",
        "coordinates": [
          -97.15,
          41.85
        ]
      },
      "type": "Feature",
      "properties": {
        "hierarchy": [
          "tgn:2756678",
          "tgn:1000001",
          "tgn:7012149",
          "tgn:2001399",
          "tgn:7007525",
          "tgn:7029392"
        ],
        "placetype": [
          "aat:300008706"
        ],
        "id": 2756678,
        "name:xx": "Wells Creek"
      }
    },
    {
      "geometry": {
        "type": "Point",
        "coordinates": [
          -72.5167,
          40.85
        ]
      },
      "type": "Feature",
      "properties": {
        "hierarchy": [
          "tgn:2756679",
          "tgn:1000001",
          "tgn:7012149",
          "tgn:1002924",
          "tgn:7007568",
          "tgn:7029392"
        ],
        "placetype": [
          "aat:300132316"
        ],
        "id": 2756679,
        "name:xx": "Wells Creek"
      }
    }
  ]
}
