{
  "geometry": {
    "type": "Point",
    "coordinates": [
      -1.6833,
      53.3167
    ]
  },
  "type": "Feature",
  "properties": {
    "hierarchy": [
      "tgn:7025263",
      "tgn:7002445",
      "tgn:1000003",
      "tgn:7008118",
      "tgn:7008591",
      "tgn:7029392"
    ],
    "placetype": [
      "aat:300386886"
    ],
    "id": 7025263,
    "name:ang": "Offretune"
  }
}
