{
  "type": "FeatureCollection",
  "features": [
    {
      "geometry": {
        "type": "Point",
        "coordinates": [
          22.7,
          -6.0667
        ]
      },
      "type": "Feature",
      "properties": {
        "hierarchy": [
          "tgn:1089070",
          "tgn:7001242",
          "tgn:1001345",
          "tgn:1000159",
          "tgn:7029392"
        ],
        "placetype": [
          "aat:300008347"
        ],
        "id": 1089070,
        "name:xx": "Kamwandu"
      }
    },
    {
      "geometry": {
        "type": "Point",
        "coordinates": [
          23.6,
          -6.9333
        ]
      },
      "type": "Feature",
      "properties": {
        "hierarchy": [
          "tgn:1089072",
          "tgn:7001242",
          "tgn:1001346",
          "tgn:1000159",
          "tgn:7029392"
        ],
        "placetype": [
          "aat:300008347"
        ],
        "id": 1089072,
        "name:xx": "Kanda-Kanda"
      }
    },
    {
      "geometry": {
        "type": "Point",
        "coordinates": [
          19.4,
          -6.0333
        ]
      },
      "type": "Feature",
      "properties": {
        "hierarchy": [
          "tgn:1089073",
          "tgn:1001143",
          "tgn:7001242",
          "tgn:1000159",
          "tgn:7029392"
        ],
        "placetype": [
          "aat:300008347"
        ],
        "id": 1089073,
        "name:xx": "Kandala"
      }
    },
    {
      "geometry": {
        "type": "Point",
        "coordinates": [
          22.8,
          -9.9167
        ]
      },
      "type": "Feature",
      "properties": {
        "hierarchy": [
          "tgn:1089074",
          "tgn:7001242",
          "tgn:7016706",
          "tgn:1000159",
          "tgn:7029392"
        ],
        "placetype": [
          "aat:300008347"
        ],
        "id": 1089074,
        "name:xx": "Kangowa"
      }
    },
    {
      "geometry": {
        "type": "Point",
        "coordinates": [
          24.1833,
          -7.5333
        ]
      },
      "type": "Feature",
      "properties": {
        "hierarchy": [
          "tgn:1089075",
          "tgn:7001242",
          "tgn:7016706",
          "tgn:1000159",
          "tgn:7029392"
        ],
        "placetype": [
          "aat:300008347"
        ],
        "id": 1089075,
        "name:xx": "Kaniama"
      }
    },
    {
      "geometry": {
        "type": "Point",
        "coordinates": [
          26.95,
          -7.45
        ]
      },
      "type": "Feature",
      "properties": {
        "hierarchy": [
          "tgn:1089076",
          "tgn:7001242",
          "tgn:7016706",
          "tgn:1000159",
          "tgn:7029392"
        ],
        "placetype": [
          "aat:300008347"
        ],
        "id": 1089076,
        "name:xx": "Kaniamba"
      }
    },
    {
      "geometry": {
        "type": "Point",
        "coordinates": [
          27.35,
          -9
        ]
      },
      "type": "Feature",
      "properties": {
        "hierarchy": [
          "tgn:1089077",
          "tgn:7001242",
          "tgn:7016706",
          "tgn:1000159",
          "tgn:7029392"
        ],
        "placetype": [
          "aat:300008347"
        ],
        "id": 1089077,
        "name:xx": "Kaniepa"
      }
    },
    {
      "geometry": {
        "type": "Point",
        "coordinates": [
          26.0667,
          -10.3
        ]
      },
      "type": "Feature",
      "properties": {
        "hierarchy": [
          "tgn:1089078",
          "tgn:7001242",
          "tgn:7016706",
          "tgn:1000159",
          "tgn:7029392"
        ],
        "placetype": [
          "aat:300008347"
        ],
        "id": 1089078,
        "name:xx": "Kansenia"
      }
    },
    {
      "geometry": {
        "type": "Point",
        "coordinates": [
          25.2167,
          -10.4833
        ]
      },
      "type": "Feature",
      "properties": {
        "hierarchy": [
          "tgn:1089079",
          "tgn:7001242",
          "tgn:7016706",
          "tgn:1000159",
          "tgn:7029392"
        ],
        "placetype": [
          "aat:300008347"
        ],
        "id": 1089079,
        "name:xx": "Kanzenze"
      }
    }
  ]
}
