{
  "geometry": {
    "type": "Point",
    "coordinates": [
      -86.6333,
      34.8333
    ]
  },
  "type": "Feature",
  "properties": {
    "hierarchy": [
      "tgn:2334995",
      "tgn:7002659",
      "tgn:1000001",
      "tgn:7012149",
      "tgn:2000044",
      "tgn:7029392"
    ],
    "placetype": [
      "aat:300008746"
    ],
    "id": 2334995,
    "name:xx": "Formation Pit"
  }
}
