{
  "geometry": {
    "type": "Point",
    "coordinates": [
      -116.5167,
      33.05
    ]
  },
  "type": "Feature",
  "properties": {
    "hierarchy": [
      "tgn:2607036",
      "tgn:1000001",
      "tgn:7012149",
      "tgn:7007157",
      "tgn:1002858",
      "tgn:7029392"
    ],
    "placetype": [
      "aat:300000390"
    ],
    "id": 2607036,
    "name:xx": "Ranchito Mine"
  }
}
