{
  "geometry": {
    "type": "Point",
    "coordinates": [
      -2.1333,
      51.95
    ]
  },
  "type": "Feature",
  "properties": {
    "hierarchy": [
      "tgn:7026645",
      "tgn:7002445",
      "tgn:1000003",
      "tgn:7008132",
      "tgn:7008591",
      "tgn:7029392"
    ],
    "placetype": [
      "aat:300008347"
    ],
    "id": 7026645,
    "name:xx": "Hardwicke"
  }
}
