{
  "type": "FeatureCollection",
  "features": [
    {
      "geometry": {
        "type": "Point",
        "coordinates": [
          32.887786,
          30.263673
        ]
      },
      "type": "Feature",
      "properties": {
        "hierarchy": [
          "tgn:7533640",
          "tgn:7001242",
          "tgn:7016833",
          "tgn:7001335",
          "tgn:7029392"
        ],
        "placetype": [
          "aat:300008777"
        ],
        "name:en": "Jarād, Ruwaysāt al",
        "id": 7533640
      }
    },
    {
      "geometry": {
        "type": "Point",
        "coordinates": [
          31.646962,
          29.119388
        ]
      },
      "type": "Feature",
      "properties": {
        "hierarchy": [
          "tgn:7533641",
          "tgn:7001242",
          "tgn:7016833",
          "tgn:7029392"
        ],
        "placetype": [
          "aat:300132339"
        ],
        "name:en": "Jarād, Farsh al",
        "id": 7533641
      }
    },
    {
      "geometry": {
        "type": "Point",
        "coordinates": [
          30.833333,
          28.566667
        ]
      },
      "type": "Feature",
      "properties": {
        "hierarchy": [
          "tgn:7533642",
          "tgn:7001242",
          "tgn:7016833",
          "tgn:1001088",
          "tgn:7029392"
        ],
        "placetype": [
          "aat:300008791"
        ],
        "name:en": "Jarābi', Jazīrat al",
        "id": 7533642
      }
    },
    {
      "geometry": {
        "type": "Point",
        "coordinates": [
          30.233333,
          31.066667
        ]
      },
      "type": "Feature",
      "properties": {
        "hierarchy": [
          "tgn:7533645",
          "tgn:7001242",
          "tgn:1001075",
          "tgn:7016833",
          "tgn:7029392"
        ],
        "placetype": [
          "aat:300000206"
        ],
        "name:en": "'Izbat Jān 'Īd",
        "id": 7533645
      }
    },
    {
      "geometry": {
        "type": "Point",
        "coordinates": [
          25.923111,
          29.255092
        ]
      },
      "type": "Feature",
      "properties": {
        "hierarchy": [
          "tgn:7533647",
          "tgn:7001242",
          "tgn:7016833",
          "tgn:1001418",
          "tgn:7029392"
        ],
        "placetype": [
          "aat:300008697"
        ],
        "name:en": "Janbī, 'Ayn al",
        "id": 7533647
      }
    },
    {
      "geometry": {
        "type": "Point",
        "coordinates": [
          32.087778,
          31.3125
        ]
      },
      "type": "Feature",
      "properties": {
        "hierarchy": [
          "tgn:7533648",
          "tgn:7001242",
          "tgn:7016833",
          "tgn:1001123",
          "tgn:7029392"
        ],
        "placetype": [
          "aat:300386846"
        ],
        "id": 7533648,
        "name:xx": "Janb at Timsāḩ, Ra's"
      }
    },
    {
      "geometry": {
        "type": "Point",
        "coordinates": [
          32.061476,
          31.318135
        ]
      },
      "type": "Feature",
      "properties": {
        "hierarchy": [
          "tgn:7533649",
          "tgn:7001242",
          "tgn:7016833",
          "tgn:1001123",
          "tgn:7029392"
        ],
        "placetype": [
          "aat:300008680"
        ],
        "id": 7533649,
        "name:xx": "Janb at Timsāḩ, Baḩr"
      }
    }
  ]
}
