{
  "geometry": {
    "type": "Point",
    "coordinates": [
      25.35,
      35.15
    ]
  },
  "type": "Feature",
  "properties": {
    "hierarchy": [
      "tgn:7217746",
      "tgn:7002692",
      "tgn:7012056",
      "tgn:1000003",
      "tgn:1000074",
      "tgn:7029392"
    ],
    "placetype": [
      "aat:300008347"
    ],
    "id": 7217746,
    "name:xx": "Yerákion"
  }
}
