{
  "geometry": {
    "type": "Point",
    "coordinates": [
      -118.5833,
      44.55
    ]
  },
  "type": "Feature",
  "properties": {
    "hierarchy": [
      "tgn:2545500",
      "tgn:1000001",
      "tgn:7012149",
      "tgn:2001708",
      "tgn:7007708",
      "tgn:7029392"
    ],
    "placetype": [
      "aat:300008706"
    ],
    "id": 2545500,
    "name:xx": "North Fork Bridge Creek"
  }
}
