{
  "geometry": {
    "type": "Point",
    "coordinates": [
      -87.2333,
      39.0167
    ]
  },
  "type": "Feature",
  "properties": {
    "hierarchy": [
      "tgn:2615368",
      "tgn:1000001",
      "tgn:7012149",
      "tgn:7007252",
      "tgn:7029392"
    ],
    "placetype": [
      "aat:300006191"
    ],
    "id": 2615368,
    "name:xx": "Reservoir Number Twenty-six"
  }
}
