{
  "geometry": {
    "type": "Point",
    "coordinates": [
      -87.45,
      45.2667
    ]
  },
  "type": "Feature",
  "properties": {
    "hierarchy": [
      "tgn:2425166",
      "tgn:1000001",
      "tgn:7012149",
      "tgn:2000978",
      "tgn:7007520",
      "tgn:7029392"
    ],
    "placetype": [
      "aat:300008347"
    ],
    "id": 2425166,
    "name:xx": "Johnson Landing"
  }
}
