{
  "geometry": {
    "type": "Point",
    "coordinates": [
      -75.85,
      37.9333
    ]
  },
  "type": "Feature",
  "properties": {
    "hierarchy": [
      "tgn:1132581",
      "tgn:1000001",
      "tgn:1002902",
      "tgn:7012149",
      "tgn:7007516",
      "tgn:7029392"
    ],
    "placetype": [
      "aat:300008706"
    ],
    "id": 1132581,
    "name:xx": "Broad Creek"
  }
}
