{
  "type": "FeatureCollection",
  "features": [
    {
      "geometry": {
        "type": "Point",
        "coordinates": [
          -73.5333,
          43.9167
        ]
      },
      "type": "Feature",
      "properties": {
        "hierarchy": [
          "tgn:2069882",
          "tgn:1000001",
          "tgn:7012149",
          "tgn:2001461",
          "tgn:7007568",
          "tgn:7029392"
        ],
        "placetype": [
          "aat:300008347"
        ],
        "id": 2069882,
        "name:xx": "Ironville"
      }
    },
    {
      "geometry": {
        "type": "Point",
        "coordinates": [
          -79.1,
          42.5667
        ]
      },
      "type": "Feature",
      "properties": {
        "hierarchy": [
          "tgn:2069883",
          "tgn:1000001",
          "tgn:1002259",
          "tgn:7012149",
          "tgn:7007568",
          "tgn:7029392"
        ],
        "placetype": [
          "aat:300008347"
        ],
        "id": 2069883,
        "name:xx": "Irving"
      }
    },
    {
      "geometry": {
        "type": "Point",
        "coordinates": [
          -78.4,
          42.2333
        ]
      },
      "type": "Feature",
      "properties": {
        "hierarchy": [
          "tgn:2069887",
          "tgn:1000001",
          "tgn:1002245",
          "tgn:7012149",
          "tgn:7007568",
          "tgn:7029392"
        ],
        "placetype": [
          "aat:300008347"
        ],
        "id": 2069887,
        "name:xx": "Ischua"
      }
    },
    {
      "geometry": {
        "type": "Point",
        "coordinates": [
          -77.6333,
          43.2667
        ]
      },
      "type": "Feature",
      "properties": {
        "hierarchy": [
          "tgn:2069888",
          "tgn:1000001",
          "tgn:7012149",
          "tgn:1002681",
          "tgn:7007568",
          "tgn:7029392"
        ],
        "placetype": [
          "aat:300008347"
        ],
        "id": 2069888,
        "name:xx": "Island Cottage Beach"
      }
    }
  ]
}
