{
  "geometry": {
    "type": "Point",
    "coordinates": [
      35.5667,
      33.8667
    ]
  },
  "type": "Feature",
  "properties": {
    "hierarchy": [
      "tgn:1082631",
      "tgn:1001317",
      "tgn:1000004",
      "tgn:1000126",
      "tgn:7029392"
    ],
    "placetype": [
      "aat:300008347"
    ],
    "id": 1082631,
    "name:xx": "Mār Yūsuf"
  }
}
