{
  "geometry": {
    "type": "Point",
    "coordinates": [
      -120.25,
      41.1833
    ]
  },
  "type": "Feature",
  "properties": {
    "hierarchy": [
      "tgn:2488509",
      "tgn:1000001",
      "tgn:7012149",
      "tgn:7007157",
      "tgn:7029392"
    ],
    "placetype": [
      "aat:300266640"
    ],
    "id": 2488509,
    "name:xx": "Mahogany Ridge"
  }
}
