{
  "geometry": {
    "type": "Point",
    "coordinates": [
      -90.35,
      37.3833
    ]
  },
  "type": "Feature",
  "properties": {
    "hierarchy": [
      "tgn:2146218",
      "tgn:1000001",
      "tgn:7012149",
      "tgn:2001217",
      "tgn:7007523",
      "tgn:7029392"
    ],
    "placetype": [
      "aat:300008761"
    ],
    "id": 2146218,
    "name:xx": "Ballew Hollow"
  }
}
