{
  "geometry": {
    "type": "Point",
    "coordinates": [
      -120.5167,
      45.1167
    ]
  },
  "type": "Feature",
  "properties": {
    "hierarchy": [
      "tgn:2548908",
      "tgn:1000001",
      "tgn:7012149",
      "tgn:7007708",
      "tgn:7029392"
    ],
    "placetype": [
      "aat:300266640"
    ],
    "id": 2548908,
    "name:xx": "North Pole Ridge"
  }
}
