{
  "geometry": {
    "type": "Point",
    "coordinates": [
      -156.5333,
      64.4833
    ]
  },
  "type": "Feature",
  "properties": {
    "hierarchy": [
      "tgn:2435738",
      "tgn:7006450",
      "tgn:1000001",
      "tgn:7012149",
      "tgn:2000089",
      "tgn:7029392"
    ],
    "placetype": [
      "aat:300008798"
    ],
    "id": 2435738,
    "name:xx": "Ketlkede Mountain"
  }
}
