{
  "geometry": {
    "type": "Point",
    "coordinates": [
      -77.1833,
      41.1667
    ]
  },
  "type": "Feature",
  "properties": {
    "hierarchy": [
      "tgn:2524469",
      "tgn:1000001",
      "tgn:7012149",
      "tgn:1002613",
      "tgn:7007710",
      "tgn:7029392"
    ],
    "placetype": [
      "aat:300008699"
    ],
    "id": 2524469,
    "name:xx": "Morgan Valley Run"
  }
}
