{
  "geometry": {
    "type": "Point",
    "coordinates": [
      47.6667,
      -15.5167
    ]
  },
  "type": "Feature",
  "properties": {
    "hierarchy": [
      "tgn:1090988",
      "tgn:7001242",
      "tgn:1001405",
      "tgn:1000173",
      "tgn:7029392"
    ],
    "placetype": [
      "aat:300008347"
    ],
    "id": 1090988,
    "name:xx": "Port-Bergé"
  }
}
