{
  "geometry": {
    "type": "Point",
    "coordinates": [
      -82.6333,
      41.4833
    ]
  },
  "type": "Feature",
  "properties": {
    "hierarchy": [
      "tgn:7021638",
      "tgn:1000001",
      "tgn:7012149",
      "tgn:1002761",
      "tgn:7007706",
      "tgn:7029392"
    ],
    "placetype": [
      "aat:300008347"
    ],
    "id": 7021638,
    "name:xx": "Mineyahta on-the-Bay"
  }
}
