{
  "geometry": {
    "type": "Point",
    "coordinates": [
      114.05,
      23.85
    ]
  },
  "type": "Feature",
  "properties": {
    "hierarchy": [
      "tgn:1067738",
      "tgn:1000004",
      "tgn:7005232",
      "tgn:1000111",
      "tgn:7029392"
    ],
    "placetype": [
      "aat:300008347"
    ],
    "id": 1067738,
    "name:xx": "Dipai"
  }
}
