{
  "geometry": {
    "type": "Point",
    "coordinates": [
      -88.55,
      42.8833
    ]
  },
  "type": "Feature",
  "properties": {
    "hierarchy": [
      "tgn:2741016",
      "tgn:1000001",
      "tgn:7012149",
      "tgn:1002522",
      "tgn:7007922",
      "tgn:7029392"
    ],
    "placetype": [
      "aat:300006191"
    ],
    "id": 2741016,
    "name:xx": "Upper Spring Lake"
  }
}
