{
  "geometry": {
    "type": "Point",
    "coordinates": [
      -107.1833,
      36.5167
    ]
  },
  "type": "Feature",
  "properties": {
    "hierarchy": [
      "tgn:2263964",
      "tgn:1000001",
      "tgn:7012149",
      "tgn:2001449",
      "tgn:7007566",
      "tgn:7029392"
    ],
    "placetype": [
      "aat:300008680"
    ],
    "id": 2263964,
    "name:xx": "Coyote Lake"
  }
}
