{
  "geometry": {
    "type": "Point",
    "coordinates": [
      -116.7833,
      47.2167
    ]
  },
  "type": "Feature",
  "properties": {
    "hierarchy": [
      "tgn:2025376",
      "tgn:2000456",
      "tgn:1000001",
      "tgn:7012149",
      "tgn:7007250",
      "tgn:7029392"
    ],
    "placetype": [
      "aat:300008347",
      "aat:300387210"
    ],
    "id": 2025376,
    "name:xx": "Benewah"
  }
}
