{
  "geometry": {
    "type": "Point",
    "coordinates": [
      -75.8667,
      39.7667
    ]
  },
  "type": "Feature",
  "properties": {
    "hierarchy": [
      "tgn:2754634",
      "tgn:1000001",
      "tgn:1002266",
      "tgn:7012149",
      "tgn:7007710",
      "tgn:7029392"
    ],
    "placetype": [
      "aat:300008699"
    ],
    "id": 2754634,
    "name:xx": "Ways Run"
  }
}
