{
  "geometry": {
    "type": "Point",
    "coordinates": [
      -116.8167,
      42.4167
    ]
  },
  "type": "Feature",
  "properties": {
    "hierarchy": [
      "tgn:2624731",
      "tgn:1000001",
      "tgn:7012149",
      "tgn:2000488",
      "tgn:7007250",
      "tgn:7029392"
    ],
    "placetype": [
      "aat:300008697"
    ],
    "id": 2624731,
    "name:xx": "Rock Spring"
  }
}
