{
  "geometry": {
    "type": "Point",
    "coordinates": [
      -121.2667,
      37.1833
    ]
  },
  "type": "Feature",
  "properties": {
    "hierarchy": [
      "tgn:2616950",
      "tgn:1000001",
      "tgn:7012149",
      "tgn:7007157",
      "tgn:1002915",
      "tgn:7029392"
    ],
    "placetype": [
      "aat:300008706"
    ],
    "id": 2616950,
    "name:xx": "Richard Creek"
  }
}
