{
  "type": "FeatureCollection",
  "features": [
    {
      "geometry": {
        "type": "Point",
        "coordinates": [
          -81.4,
          38.6333
        ]
      },
      "type": "Feature",
      "properties": {
        "hierarchy": [
          "tgn:2120361",
          "tgn:1000001",
          "tgn:7012149",
          "tgn:2002293",
          "tgn:7013961",
          "tgn:7029392"
        ],
        "placetype": [
          "aat:300008347"
        ],
        "id": 2120361,
        "name:xx": "Walton"
      }
    },
    {
      "geometry": {
        "type": "Point",
        "coordinates": [
          -80.2833,
          39.7
        ]
      },
      "type": "Feature",
      "properties": {
        "hierarchy": [
          "tgn:2120362",
          "tgn:1000001",
          "tgn:7012149",
          "tgn:2002281",
          "tgn:7013961",
          "tgn:7029392"
        ],
        "placetype": [
          "aat:300008347"
        ],
        "id": 2120362,
        "name:xx": "Wana"
      }
    },
    {
      "geometry": {
        "type": "Point",
        "coordinates": [
          -81.9167,
          37.85
        ]
      },
      "type": "Feature",
      "properties": {
        "hierarchy": [
          "tgn:2120363",
          "tgn:1000001",
          "tgn:7012149",
          "tgn:2002273",
          "tgn:7013961",
          "tgn:7029392"
        ],
        "placetype": [
          "aat:300008347"
        ],
        "id": 2120363,
        "name:xx": "Wanda"
      }
    },
    {
      "geometry": {
        "type": "Point",
        "coordinates": [
          -78.7333,
          39.3833
        ]
      },
      "type": "Feature",
      "properties": {
        "hierarchy": [
          "tgn:2120364",
          "tgn:1000001",
          "tgn:7012149",
          "tgn:2002265",
          "tgn:7013961",
          "tgn:7029392"
        ],
        "placetype": [
          "aat:300387016"
        ],
        "id": 2120364,
        "name:xx": "Wapocomo"
      }
    },
    {
      "geometry": {
        "type": "Point",
        "coordinates": [
          -81.6833,
          37.3
        ]
      },
      "type": "Feature",
      "properties": {
        "hierarchy": [
          "tgn:2120365",
          "tgn:1000001",
          "tgn:7012149",
          "tgn:2002274",
          "tgn:7013961",
          "tgn:7029392"
        ],
        "placetype": [
          "aat:300008347"
        ],
        "id": 2120365,
        "name:xx": "War"
      }
    },
    {
      "geometry": {
        "type": "Point",
        "coordinates": [
          -81.3833,
          38.2333
        ]
      },
      "type": "Feature",
      "properties": {
        "hierarchy": [
          "tgn:2120369",
          "tgn:1000001",
          "tgn:7012149",
          "tgn:2002270",
          "tgn:7013961",
          "tgn:7029392"
        ],
        "placetype": [
          "aat:300008347",
          "aat:300387210"
        ],
        "id": 2120369,
        "name:xx": "Ward"
      }
    }
  ]
}
