{
  "type": "FeatureCollection",
  "features": [
    {
      "geometry": {
        "type": "Point",
        "coordinates": [
          -95.8333,
          40.8
        ]
      },
      "type": "Feature",
      "properties": {
        "hierarchy": [
          "tgn:2426830",
          "tgn:1000001",
          "tgn:2001328",
          "tgn:7012149",
          "tgn:7007525",
          "tgn:7029392"
        ],
        "placetype": [
          "aat:300008850"
        ],
        "id": 2426830,
        "name:xx": "Jones Point"
      }
    },
    {
      "geometry": {
        "type": "Point",
        "coordinates": [
          -74.05,
          40.3667
        ]
      },
      "type": "Feature",
      "properties": {
        "hierarchy": [
          "tgn:2426831",
          "tgn:1000001",
          "tgn:7014090",
          "tgn:7012149",
          "tgn:7007565",
          "tgn:7029392"
        ],
        "placetype": [
          "aat:300008850"
        ],
        "id": 2426831,
        "name:xx": "Jones Point"
      }
    },
    {
      "geometry": {
        "type": "Point",
        "coordinates": [
          -73.95,
          41.2833
        ]
      },
      "type": "Feature",
      "properties": {
        "hierarchy": [
          "tgn:2426832",
          "tgn:1000001",
          "tgn:7012149",
          "tgn:1002833",
          "tgn:7007568",
          "tgn:7029392"
        ],
        "placetype": [
          "aat:300008850"
        ],
        "id": 2426832,
        "name:xx": "Jones Point"
      }
    },
    {
      "geometry": {
        "type": "Point",
        "coordinates": [
          -73.35,
          44.3667
        ]
      },
      "type": "Feature",
      "properties": {
        "hierarchy": [
          "tgn:2426833",
          "tgn:1000001",
          "tgn:7012149",
          "tgn:2001461",
          "tgn:7007568",
          "tgn:7029392"
        ],
        "placetype": [
          "aat:300008850"
        ],
        "id": 2426833,
        "name:xx": "Jones Point"
      }
    },
    {
      "geometry": {
        "type": "Point",
        "coordinates": [
          -76.45,
          43.1
        ]
      },
      "type": "Feature",
      "properties": {
        "hierarchy": [
          "tgn:2426834",
          "tgn:1000001",
          "tgn:7012149",
          "tgn:1002746",
          "tgn:7007568",
          "tgn:7029392"
        ],
        "placetype": [
          "aat:300008347"
        ],
        "id": 2426834,
        "name:xx": "Jones Point"
      }
    },
    {
      "geometry": {
        "type": "Point",
        "coordinates": [
          -85.5833,
          35.1333
        ]
      },
      "type": "Feature",
      "properties": {
        "hierarchy": [
          "tgn:2426835",
          "tgn:1000001",
          "tgn:7012149",
          "tgn:2001894",
          "tgn:7007825",
          "tgn:7029392"
        ],
        "placetype": [
          "aat:300008850"
        ],
        "id": 2426835,
        "name:xx": "Jones Point"
      }
    },
    {
      "geometry": {
        "type": "Point",
        "coordinates": [
          -88.0333,
          44.4667
        ]
      },
      "type": "Feature",
      "properties": {
        "hierarchy": [
          "tgn:2426838",
          "tgn:1000001",
          "tgn:2002309",
          "tgn:7012149",
          "tgn:7007922",
          "tgn:7029392"
        ],
        "placetype": [
          "aat:300008850"
        ],
        "id": 2426838,
        "name:xx": "Jones Point"
      }
    },
    {
      "geometry": {
        "type": "Point",
        "coordinates": [
          -86.0667,
          32.8833
        ]
      },
      "type": "Feature",
      "properties": {
        "hierarchy": [
          "tgn:2426839",
          "tgn:7002659",
          "tgn:1000001",
          "tgn:2000018",
          "tgn:7012149",
          "tgn:7029392"
        ],
        "placetype": [
          "aat:300006191"
        ],
        "id": 2426839,
        "name:xx": "Jones Pond"
      }
    }
  ]
}
