{
  "geometry": {
    "type": "Point",
    "coordinates": [
      -82.95,
      38.8833
    ]
  },
  "type": "Feature",
  "properties": {
    "hierarchy": [
      "tgn:2182531",
      "tgn:1000001",
      "tgn:7012149",
      "tgn:1002877",
      "tgn:7007706",
      "tgn:7029392"
    ],
    "placetype": [
      "aat:300008699"
    ],
    "id": 2182531,
    "name:xx": "Blue Run"
  }
}
