{
  "geometry": {
    "type": "Point",
    "coordinates": [
      -84.0167,
      38.9333
    ]
  },
  "type": "Feature",
  "properties": {
    "hierarchy": [
      "tgn:2082706",
      "tgn:1000001",
      "tgn:1002210",
      "tgn:7012149",
      "tgn:7007706",
      "tgn:7029392"
    ],
    "placetype": [
      "aat:300008347"
    ],
    "id": 2082706,
    "name:xx": "Yankeetown"
  }
}
