{
  "geometry": {
    "type": "Point",
    "coordinates": [
      -82.8833,
      43.8167
    ]
  },
  "type": "Feature",
  "properties": {
    "hierarchy": [
      "tgn:2686795",
      "tgn:1000001",
      "tgn:7012149",
      "tgn:2000964",
      "tgn:7007520",
      "tgn:7029392"
    ],
    "placetype": [
      "aat:300006075"
    ],
    "id": 2686795,
    "name:xx": "Spring Creek Drain"
  }
}
