{
  "geometry": {
    "type": "Point",
    "coordinates": [
      2.0833,
      41.55
    ]
  },
  "type": "Feature",
  "properties": {
    "hierarchy": [
      "tgn:1061896",
      "tgn:7002808",
      "tgn:7030216",
      "tgn:1000003",
      "tgn:1000095",
      "tgn:7029392"
    ],
    "placetype": [
      "aat:300008347"
    ],
    "id": 1061896,
    "name:xx": "Can Rull"
  }
}
