{
  "geometry": {
    "type": "Point",
    "coordinates": [
      -72.9833,
      40.6833
    ]
  },
  "type": "Feature",
  "properties": {
    "hierarchy": [
      "tgn:2067965",
      "tgn:1000001",
      "tgn:7012149",
      "tgn:1002924",
      "tgn:7007568",
      "tgn:7029392"
    ],
    "placetype": [
      "aat:300008347",
      "aat:300387247"
    ],
    "id": 2067965,
    "name:xx": "Bayberry Dunes"
  }
}
