{
  "geometry": {
    "type": "Point",
    "coordinates": [
      6.2167,
      59.15
    ]
  },
  "type": "Feature",
  "properties": {
    "hierarchy": [
      "tgn:4000314",
      "tgn:7003652",
      "tgn:1000003",
      "tgn:1000088",
      "tgn:7029392"
    ],
    "placetype": [
      "aat:300008347"
    ],
    "id": 4000314,
    "name:xx": "Årdal"
  }
}
