{
  "type": "FeatureCollection",
  "features": [
    {
      "geometry": {
        "type": "Point",
        "coordinates": [
          -96.5667,
          34.6833
        ]
      },
      "type": "Feature",
      "properties": {
        "hierarchy": [
          "tgn:2084180",
          "tgn:1000001",
          "tgn:7012149",
          "tgn:2001684",
          "tgn:7007707",
          "tgn:7029392"
        ],
        "placetype": [
          "aat:300008347"
        ],
        "id": 2084180,
        "name:xx": "Union Valley"
      }
    },
    {
      "geometry": {
        "type": "Point",
        "coordinates": [
          -96.2167,
          33.9
        ]
      },
      "type": "Feature",
      "properties": {
        "hierarchy": [
          "tgn:2084182",
          "tgn:1000001",
          "tgn:2001629",
          "tgn:7012149",
          "tgn:7007707",
          "tgn:7029392"
        ],
        "placetype": [
          "aat:300008347"
        ],
        "id": 2084182,
        "name:xx": "Utica"
      }
    },
    {
      "geometry": {
        "type": "Point",
        "coordinates": [
          -97.4667,
          35.4
        ]
      },
      "type": "Feature",
      "properties": {
        "hierarchy": [
          "tgn:2084183",
          "tgn:1000001",
          "tgn:7012149",
          "tgn:2001677",
          "tgn:7007707",
          "tgn:7029392"
        ],
        "placetype": [
          "aat:300008347"
        ],
        "id": 2084183,
        "name:xx": "Valley Brook"
      }
    },
    {
      "geometry": {
        "type": "Point",
        "coordinates": [
          -95.0833,
          34
        ]
      },
      "type": "Feature",
      "properties": {
        "hierarchy": [
          "tgn:2084185",
          "tgn:1000001",
          "tgn:7012149",
          "tgn:2001667",
          "tgn:7007707",
          "tgn:7029392"
        ],
        "placetype": [
          "aat:300008347"
        ],
        "id": 2084185,
        "name:xx": "Valliant"
      }
    },
    {
      "geometry": {
        "type": "Point",
        "coordinates": [
          -96.6667,
          34.9833
        ]
      },
      "type": "Feature",
      "properties": {
        "hierarchy": [
          "tgn:2084186",
          "tgn:1000001",
          "tgn:7012149",
          "tgn:2001689",
          "tgn:7007707",
          "tgn:7029392"
        ],
        "placetype": [
          "aat:300008347"
        ],
        "id": 2084186,
        "name:xx": "Vamoosa"
      }
    },
    {
      "geometry": {
        "type": "Point",
        "coordinates": [
          -97.9,
          36.3333
        ]
      },
      "type": "Feature",
      "properties": {
        "hierarchy": [
          "tgn:2084187",
          "tgn:1000001",
          "tgn:2001646",
          "tgn:7012149",
          "tgn:7007707",
          "tgn:7029392"
        ],
        "placetype": [
          "aat:300386994"
        ],
        "id": 2084187,
        "name:xx": "Vance Air Force Base"
      }
    },
    {
      "geometry": {
        "type": "Point",
        "coordinates": [
          -96.8667,
          34.75
        ]
      },
      "type": "Feature",
      "properties": {
        "hierarchy": [
          "tgn:2084188",
          "tgn:1000001",
          "tgn:7012149",
          "tgn:2001684",
          "tgn:7007707",
          "tgn:7029392"
        ],
        "placetype": [
          "aat:300008347"
        ],
        "id": 2084188,
        "name:xx": "Vanoss"
      }
    },
    {
      "geometry": {
        "type": "Point",
        "coordinates": [
          -97.6667,
          34.45
        ]
      },
      "type": "Feature",
      "properties": {
        "hierarchy": [
          "tgn:2084189",
          "tgn:1000001",
          "tgn:7012149",
          "tgn:2001691",
          "tgn:7007707",
          "tgn:7029392"
        ],
        "placetype": [
          "aat:300008347"
        ],
        "id": 2084189,
        "name:xx": "Velma"
      }
    }
  ]
}
