{
  "geometry": {
    "type": "Point",
    "coordinates": [
      -117.4167,
      46.2167
    ]
  },
  "type": "Feature",
  "properties": {
    "hierarchy": [
      "tgn:2584861",
      "tgn:1000001",
      "tgn:2002245",
      "tgn:7012149",
      "tgn:7007920",
      "tgn:7029392"
    ],
    "placetype": [
      "aat:300008798"
    ],
    "id": 2584861,
    "name:xx": "Pinkham Butte"
  }
}
