{
  "type": "FeatureCollection",
  "features": [
    {
      "geometry": {
        "type": "Point",
        "coordinates": [
          -83.35,
          34.8
        ]
      },
      "type": "Feature",
      "properties": {
        "hierarchy": [
          "tgn:7023944",
          "tgn:1000001",
          "tgn:7012149",
          "tgn:7029392"
        ],
        "placetype": [
          "aat:300008707"
        ],
        "id": 7023944,
        "name:xx": "Chattooga River"
      }
    },
    {
      "geometry": {
        "type": "Point",
        "coordinates": [
          35.0333,
          39.7333
        ]
      },
      "type": "Feature",
      "properties": {
        "hierarchy": [
          "tgn:7023945",
          "tgn:1000004",
          "tgn:1001606",
          "tgn:7018453",
          "tgn:1000144",
          "tgn:7029392"
        ],
        "placetype": [
          "aat:300000810",
          "aat:300167671",
          "aat:300008372"
        ],
        "id": 7023945,
        "name:xx": "Pteria"
      }
    },
    {
      "geometry": {
        "type": "Point",
        "coordinates": [
          35.0333,
          39.7333
        ]
      },
      "type": "Feature",
      "properties": {
        "hierarchy": [
          "tgn:7023947",
          "tgn:1000004",
          "tgn:1001606",
          "tgn:7018453",
          "tgn:1000144",
          "tgn:7029392"
        ],
        "placetype": [
          "aat:300008795"
        ],
        "id": 7023947,
        "name:xx": "Kerkenes Dağı"
      }
    },
    {
      "geometry": {
        "type": "Point",
        "coordinates": [
          0.1167,
          52.25
        ]
      },
      "type": "Feature",
      "properties": {
        "hierarchy": [
          "tgn:7023948",
          "tgn:7002445",
          "tgn:7011980",
          "tgn:1000003",
          "tgn:7008591",
          "tgn:7029392"
        ],
        "placetype": [
          "aat:300008347",
          "aat:300008372"
        ],
        "id": 7023948,
        "name:ang": "Epintone"
      }
    },
    {
      "geometry": {
        "type": "Point",
        "coordinates": [
          -88.57,
          20.682
        ]
      },
      "type": "Feature",
      "properties": {
        "hierarchy": [
          "tgn:7023949",
          "tgn:1000001",
          "tgn:7005600",
          "tgn:7005560",
          "tgn:7029392"
        ],
        "placetype": [
          "aat:300017826",
          "aat:300008347",
          "aat:300000810",
          "aat:300167671",
          "aat:300263063"
        ],
        "id": 7023949,
        "name:xx": "Chichén Itzá"
      }
    }
  ]
}
