{
  "geometry": {
    "type": "Point",
    "coordinates": [
      87.725499,
      21.84875
    ]
  },
  "type": "Feature",
  "properties": {
    "hierarchy": [
      "tgn:7572357",
      "tgn:1000004",
      "tgn:7000198",
      "tgn:1001977",
      "tgn:7029392"
    ],
    "placetype": [
      "aat:300008347"
    ],
    "name:en": "Gopālpur",
    "id": 7572357
  }
}
