{
  "geometry": {
    "type": "Point",
    "coordinates": [
      -110.75,
      39.0167
    ]
  },
  "type": "Feature",
  "properties": {
    "hierarchy": [
      "tgn:2745647",
      "tgn:1000001",
      "tgn:2002108",
      "tgn:7012149",
      "tgn:7007827",
      "tgn:7029392"
    ],
    "placetype": [
      "aat:300008761"
    ],
    "id": 2745647,
    "name:xx": "Virgin Spring Canyon"
  }
}
