{
  "type": "FeatureCollection",
  "features": [
    {
      "geometry": {
        "type": "Point",
        "coordinates": [
          -2.083333,
          52.6
        ]
      },
      "type": "Feature",
      "properties": {
        "hierarchy": [
          "tgn:7445300",
          "tgn:7002445",
          "tgn:7019032",
          "tgn:1000003",
          "tgn:7029506",
          "tgn:7008591",
          "tgn:7029392"
        ],
        "placetype": [
          "aat:300008347"
        ],
        "name:en": "Wednesfield",
        "id": 7445300
      }
    },
    {
      "geometry": {
        "type": "Point",
        "coordinates": [
          -2.566667,
          55.75
        ]
      },
      "type": "Feature",
      "properties": {
        "hierarchy": [
          "tgn:7445304",
          "tgn:7002444",
          "tgn:1000003",
          "tgn:7008072",
          "tgn:7008591",
          "tgn:7029392"
        ],
        "placetype": [
          "aat:300008347"
        ],
        "name:en": "Wedderlie",
        "id": 7445304
      }
    },
    {
      "geometry": {
        "type": "Point",
        "coordinates": [
          -0.883333,
          60.65
        ]
      },
      "type": "Feature",
      "properties": {
        "hierarchy": [
          "tgn:7445305",
          "tgn:7002444",
          "tgn:1000003",
          "tgn:7029508",
          "tgn:7008591",
          "tgn:7029392"
        ],
        "placetype": [
          "aat:300008791"
        ],
        "name:en": "Wedder Holm",
        "id": 7445305
      }
    },
    {
      "geometry": {
        "type": "Point",
        "coordinates": [
          -7.1,
          57.6
        ]
      },
      "type": "Feature",
      "properties": {
        "hierarchy": [
          "tgn:7445307",
          "tgn:7002444",
          "tgn:1000003",
          "tgn:7008094",
          "tgn:7008591",
          "tgn:7029392"
        ],
        "placetype": [
          "aat:300386846"
        ],
        "name:en": "Weavers Point",
        "id": 7445307
      }
    }
  ]
}
