{
  "geometry": {
    "type": "Point",
    "coordinates": [
      -97.3167,
      43.1667
    ]
  },
  "type": "Feature",
  "properties": {
    "hierarchy": [
      "tgn:2097441",
      "tgn:1000001",
      "tgn:7012149",
      "tgn:2001835",
      "tgn:7007713",
      "tgn:7029392"
    ],
    "placetype": [
      "aat:300008347",
      "aat:300387210"
    ],
    "id": 2097441,
    "name:xx": "Pearsons Corner"
  }
}
