{
  "geometry": {
    "type": "Point",
    "coordinates": [
      -112.6667,
      38.4667
    ]
  },
  "type": "Feature",
  "properties": {
    "hierarchy": [
      "tgn:2337106",
      "tgn:2002101",
      "tgn:1000001",
      "tgn:7012149",
      "tgn:7007827",
      "tgn:7029392"
    ],
    "placetype": [
      "aat:300008697"
    ],
    "id": 2337106,
    "name:xx": "Fourmile Spring"
  }
}
