{
  "geometry": {
    "type": "Point",
    "coordinates": [
      -107.25,
      33.0833
    ]
  },
  "type": "Feature",
  "properties": {
    "hierarchy": [
      "tgn:2139016",
      "tgn:1000001",
      "tgn:7012149",
      "tgn:2001455",
      "tgn:7007566",
      "tgn:7029392"
    ],
    "placetype": [
      "aat:300000390"
    ],
    "id": 2139016,
    "name:xx": "Ashland Claim"
  }
}
