{
  "geometry": {
    "type": "Point",
    "coordinates": [
      120.0167,
      48.25
    ]
  },
  "type": "Feature",
  "properties": {
    "hierarchy": [
      "tgn:1068762",
      "tgn:1000004",
      "tgn:7001838",
      "tgn:1000111",
      "tgn:7029392"
    ],
    "placetype": [
      "aat:300008347"
    ],
    "id": 1068762,
    "name:xx": "Honghuaerji"
  }
}
