{
  "geometry": {
    "type": "Point",
    "coordinates": [
      -113.0667,
      33.2833
    ]
  },
  "type": "Feature",
  "properties": {
    "hierarchy": [
      "tgn:2343790",
      "tgn:1000001",
      "tgn:7006451",
      "tgn:7012149",
      "tgn:2000097",
      "tgn:7029392"
    ],
    "placetype": [
      "aat:300006191"
    ],
    "id": 2343790,
    "name:xx": "Galleto Tank"
  }
}
