{
  "type": "FeatureCollection",
  "features": [
    {
      "geometry": {
        "type": "Point",
        "coordinates": [
          -69.083333,
          -25.533333
        ]
      },
      "type": "Feature",
      "properties": {
        "hierarchy": [
          "tgn:7282600",
          "tgn:7016598",
          "tgn:1000049",
          "tgn:1000002",
          "tgn:7029392"
        ],
        "placetype": [
          "aat:300006207"
        ],
        "id": 7282600,
        "name:xx": "Pereda Norte"
      }
    },
    {
      "geometry": {
        "type": "Point",
        "coordinates": [
          -69.066667,
          -25.566667
        ]
      },
      "type": "Feature",
      "properties": {
        "hierarchy": [
          "tgn:7282601",
          "tgn:1001630",
          "tgn:1000049",
          "tgn:1000002",
          "tgn:7029392"
        ],
        "placetype": [
          "aat:300259572"
        ],
        "id": 7282601,
        "name:xx": "Pereda, Portezuelo"
      }
    },
    {
      "geometry": {
        "type": "Point",
        "coordinates": [
          -70.833333,
          -29.533333
        ]
      },
      "type": "Feature",
      "properties": {
        "hierarchy": [
          "tgn:7282602",
          "tgn:1001657",
          "tgn:1000049",
          "tgn:1000002",
          "tgn:7029392"
        ],
        "placetype": [
          "aat:300008805"
        ],
        "id": 7282602,
        "name:xx": "Pereda, Llano"
      }
    },
    {
      "geometry": {
        "type": "Point",
        "coordinates": [
          -69.1,
          -25.6
        ]
      },
      "type": "Feature",
      "properties": {
        "hierarchy": [
          "tgn:7282603",
          "tgn:1001630",
          "tgn:1000049",
          "tgn:1000002",
          "tgn:7029392"
        ],
        "placetype": [
          "aat:300008795"
        ],
        "id": 7282603,
        "name:xx": "Pereda, Cerro"
      }
    },
    {
      "geometry": {
        "type": "Point",
        "coordinates": [
          -69.266667,
          -25.6
        ]
      },
      "type": "Feature",
      "properties": {
        "hierarchy": [
          "tgn:7282604",
          "tgn:7016598",
          "tgn:1000049",
          "tgn:1000002",
          "tgn:7029392"
        ],
        "placetype": [
          "aat:300008697"
        ],
        "id": 7282604,
        "name:xx": "Pereda, Aguada de"
      }
    },
    {
      "geometry": {
        "type": "Point",
        "coordinates": [
          -70.066667,
          -20.083333
        ]
      },
      "type": "Feature",
      "properties": {
        "hierarchy": [
          "tgn:7282605",
          "tgn:7002464",
          "tgn:1000049",
          "tgn:1000002",
          "tgn:7029392"
        ],
        "placetype": [
          "aat:300008805"
        ],
        "id": 7282605,
        "name:xx": "Perdiz, Pampa de la"
      }
    },
    {
      "geometry": {
        "type": "Point",
        "coordinates": [
          -67.316667,
          -23.6
        ]
      },
      "type": "Feature",
      "properties": {
        "hierarchy": [
          "tgn:7282606",
          "tgn:7016598",
          "tgn:1000049",
          "tgn:1000002",
          "tgn:7029392"
        ],
        "placetype": [
          "aat:300008697"
        ],
        "id": 7282606,
        "name:xx": "Perdiz, Aguada de la"
      }
    },
    {
      "geometry": {
        "type": "Point",
        "coordinates": [
          -68.516667,
          -24.283333
        ]
      },
      "type": "Feature",
      "properties": {
        "hierarchy": [
          "tgn:7282607",
          "tgn:7016598",
          "tgn:1000049",
          "tgn:1000002",
          "tgn:7029392"
        ],
        "placetype": [
          "aat:300008697"
        ],
        "id": 7282607,
        "name:xx": "Perdiz, Aguada"
      }
    },
    {
      "geometry": {
        "type": "Point",
        "coordinates": [
          -68.783333,
          -21.383333
        ]
      },
      "type": "Feature",
      "properties": {
        "hierarchy": [
          "tgn:7282608",
          "tgn:7016598",
          "tgn:1000049",
          "tgn:1000002",
          "tgn:7029392"
        ],
        "placetype": [
          "aat:300008795"
        ],
        "id": 7282608,
        "name:xx": "Perdisuno, Cerro"
      }
    },
    {
      "geometry": {
        "type": "Point",
        "coordinates": [
          -68.466667,
          -21.033333
        ]
      },
      "type": "Feature",
      "properties": {
        "hierarchy": [
          "tgn:7282609",
          "tgn:7016598",
          "tgn:1000049",
          "tgn:1000002",
          "tgn:7029392"
        ],
        "placetype": [
          "aat:300008697"
        ],
        "id": 7282609,
        "name:xx": "Perdisuno, Aguada de"
      }
    }
  ]
}
