{
  "type": "FeatureCollection",
  "features": [
    {
      "geometry": {
        "type": "Point",
        "coordinates": [
          -105.653889,
          24.196667
        ]
      },
      "type": "Feature",
      "properties": {
        "hierarchy": [
          "tgn:7396220",
          "tgn:7005583",
          "tgn:1000001",
          "tgn:7005560",
          "tgn:7029392"
        ],
        "placetype": [
          "aat:300008699"
        ],
        "id": 7396220,
        "name:xx": "San Antonio, Arroyo"
      }
    },
    {
      "geometry": {
        "type": "Point",
        "coordinates": [
          -88.583333,
          21.166667
        ]
      },
      "type": "Feature",
      "properties": {
        "hierarchy": [
          "tgn:7396221",
          "tgn:1000001",
          "tgn:7005600",
          "tgn:7005560",
          "tgn:7029392"
        ],
        "placetype": [
          "aat:300343547"
        ],
        "id": 7396221,
        "name:xx": "San Antonio, Aguada"
      }
    },
    {
      "geometry": {
        "type": "Point",
        "coordinates": [
          -99.766667,
          23.983333
        ]
      },
      "type": "Feature",
      "properties": {
        "hierarchy": [
          "tgn:7396223",
          "tgn:1000001",
          "tgn:7005589",
          "tgn:7005560",
          "tgn:7029392"
        ],
        "placetype": [
          "aat:300008699"
        ],
        "id": 7396223,
        "name:xx": "San Antonio"
      }
    },
    {
      "geometry": {
        "type": "Point",
        "coordinates": [
          -104.083333,
          21.65
        ]
      },
      "type": "Feature",
      "properties": {
        "hierarchy": [
          "tgn:7396224",
          "tgn:7005586",
          "tgn:1000001",
          "tgn:7005560",
          "tgn:7029392"
        ],
        "placetype": [
          "aat:300008699"
        ],
        "id": 7396224,
        "name:xx": "San Antonio"
      }
    },
    {
      "geometry": {
        "type": "Point",
        "coordinates": [
          -103.616667,
          20.883333
        ]
      },
      "type": "Feature",
      "properties": {
        "hierarchy": [
          "tgn:7396225",
          "tgn:7005586",
          "tgn:1000001",
          "tgn:7005560",
          "tgn:7029392"
        ],
        "placetype": [
          "aat:300008699"
        ],
        "id": 7396225,
        "name:xx": "San Antonio"
      }
    },
    {
      "geometry": {
        "type": "Point",
        "coordinates": [
          -104.35,
          19.983333
        ]
      },
      "type": "Feature",
      "properties": {
        "hierarchy": [
          "tgn:7396226",
          "tgn:7005586",
          "tgn:1000001",
          "tgn:7005560",
          "tgn:7029392"
        ],
        "placetype": [
          "aat:300008699"
        ],
        "id": 7396226,
        "name:xx": "San Antonio"
      }
    },
    {
      "geometry": {
        "type": "Point",
        "coordinates": [
          -100.433333,
          19.933333
        ]
      },
      "type": "Feature",
      "properties": {
        "hierarchy": [
          "tgn:7396227",
          "tgn:1000001",
          "tgn:7005590",
          "tgn:7005560",
          "tgn:7029392"
        ],
        "placetype": [
          "aat:300007783"
        ],
        "id": 7396227,
        "name:xx": "San Antonio"
      }
    },
    {
      "geometry": {
        "type": "Point",
        "coordinates": [
          -96.15,
          18.8
        ]
      },
      "type": "Feature",
      "properties": {
        "hierarchy": [
          "tgn:7396228",
          "tgn:1000001",
          "tgn:7005599",
          "tgn:7005560",
          "tgn:7029392"
        ],
        "placetype": [
          "aat:300007783"
        ],
        "id": 7396228,
        "name:xx": "San Antonio"
      }
    },
    {
      "geometry": {
        "type": "Point",
        "coordinates": [
          -97.116667,
          18.116667
        ]
      },
      "type": "Feature",
      "properties": {
        "hierarchy": [
          "tgn:7396229",
          "tgn:1000001",
          "tgn:7005591",
          "tgn:7005560",
          "tgn:7029392"
        ],
        "placetype": [
          "aat:300007783"
        ],
        "id": 7396229,
        "name:xx": "San Antonio"
      }
    }
  ]
}
