{
  "geometry": {
    "type": "Point",
    "coordinates": [
      -122.1167,
      38.75
    ]
  },
  "type": "Feature",
  "properties": {
    "hierarchy": [
      "tgn:2220292",
      "tgn:1000001",
      "tgn:7012149",
      "tgn:7007157",
      "tgn:1003046",
      "tgn:7029392"
    ],
    "placetype": [
      "aat:300386831"
    ],
    "id": 2220292,
    "name:xx": "Capay Hills"
  }
}
