{
  "geometry": {
    "type": "Point",
    "coordinates": [
      -93.9333,
      34.1333
    ]
  },
  "type": "Feature",
  "properties": {
    "hierarchy": [
      "tgn:2456229",
      "tgn:1000001",
      "tgn:7016172",
      "tgn:7012149",
      "tgn:2000135",
      "tgn:7029392"
    ],
    "placetype": [
      "aat:300008706"
    ],
    "id": 2456229,
    "name:xx": "Little Holly Creek"
  }
}
