{
  "type": "FeatureCollection",
  "features": [
    {
      "geometry": {
        "type": "Point",
        "coordinates": [
          -115.5833,
          32.7333
        ]
      },
      "type": "Feature",
      "properties": {
        "hierarchy": [
          "tgn:2472100",
          "tgn:1000001",
          "tgn:7012149",
          "tgn:2000182",
          "tgn:7007157",
          "tgn:7029392"
        ],
        "placetype": [
          "aat:300006075"
        ],
        "id": 2472100,
        "name:xx": "Lotus Drain"
      }
    },
    {
      "geometry": {
        "type": "Point",
        "coordinates": [
          -75.9,
          44.3667
        ]
      },
      "type": "Feature",
      "properties": {
        "hierarchy": [
          "tgn:2472101",
          "tgn:1000001",
          "tgn:7012149",
          "tgn:1002518",
          "tgn:7007568",
          "tgn:7029392"
        ],
        "placetype": [
          "aat:300008791"
        ],
        "id": 2472101,
        "name:xx": "Lotus Island"
      }
    },
    {
      "geometry": {
        "type": "Point",
        "coordinates": [
          -83.4167,
          42.6833
        ]
      },
      "type": "Feature",
      "properties": {
        "hierarchy": [
          "tgn:2472102",
          "tgn:1000001",
          "tgn:7012149",
          "tgn:1002737",
          "tgn:7007520",
          "tgn:7029392"
        ],
        "placetype": [
          "aat:300008680"
        ],
        "id": 2472102,
        "name:xx": "Lotus Lake"
      }
    },
    {
      "geometry": {
        "type": "Point",
        "coordinates": [
          -83.4667,
          45.2833
        ]
      },
      "type": "Feature",
      "properties": {
        "hierarchy": [
          "tgn:2472103",
          "tgn:1000001",
          "tgn:7012149",
          "tgn:2000990",
          "tgn:7007520",
          "tgn:7029392"
        ],
        "placetype": [
          "aat:300008680"
        ],
        "id": 2472103,
        "name:xx": "Lotus Lake"
      }
    },
    {
      "geometry": {
        "type": "Point",
        "coordinates": [
          -93.5167,
          44.8667
        ]
      },
      "type": "Feature",
      "properties": {
        "hierarchy": [
          "tgn:2472104",
          "tgn:1000001",
          "tgn:2001008",
          "tgn:7012149",
          "tgn:7007521",
          "tgn:7029392"
        ],
        "placetype": [
          "aat:300008680"
        ],
        "id": 2472104,
        "name:xx": "Lotus Lake"
      }
    },
    {
      "geometry": {
        "type": "Point",
        "coordinates": [
          -73.0667,
          40.7333
        ]
      },
      "type": "Feature",
      "properties": {
        "hierarchy": [
          "tgn:2472105",
          "tgn:1000001",
          "tgn:7012149",
          "tgn:1002924",
          "tgn:7007568",
          "tgn:7029392"
        ],
        "placetype": [
          "aat:300006191"
        ],
        "id": 2472105,
        "name:xx": "Lotus Lake"
      }
    },
    {
      "geometry": {
        "type": "Point",
        "coordinates": [
          -124.0667,
          44.4333
        ]
      },
      "type": "Feature",
      "properties": {
        "hierarchy": [
          "tgn:2472106",
          "tgn:1000001",
          "tgn:7012149",
          "tgn:1002599",
          "tgn:7007708",
          "tgn:7029392"
        ],
        "placetype": [
          "aat:300008680"
        ],
        "id": 2472106,
        "name:xx": "Lotus Lake"
      }
    },
    {
      "geometry": {
        "type": "Point",
        "coordinates": [
          -92.5833,
          45.3333
        ]
      },
      "type": "Feature",
      "properties": {
        "hierarchy": [
          "tgn:2472107",
          "tgn:1000001",
          "tgn:7012149",
          "tgn:2002346",
          "tgn:7007922",
          "tgn:7029392"
        ],
        "placetype": [
          "aat:300008680"
        ],
        "id": 2472107,
        "name:xx": "Lotus Lake"
      }
    },
    {
      "geometry": {
        "type": "Point",
        "coordinates": [
          -89.3167,
          45.9167
        ]
      },
      "type": "Feature",
      "properties": {
        "hierarchy": [
          "tgn:2472108",
          "tgn:1000001",
          "tgn:7012149",
          "tgn:2002359",
          "tgn:7007922",
          "tgn:7029392"
        ],
        "placetype": [
          "aat:300008680"
        ],
        "id": 2472108,
        "name:xx": "Lotus Lake"
      }
    },
    {
      "geometry": {
        "type": "Point",
        "coordinates": [
          -117.1167,
          35.85
        ]
      },
      "type": "Feature",
      "properties": {
        "hierarchy": [
          "tgn:2472109",
          "tgn:1000001",
          "tgn:7012149",
          "tgn:2000183",
          "tgn:7007157",
          "tgn:7029392"
        ],
        "placetype": [
          "aat:300000390"
        ],
        "id": 2472109,
        "name:xx": "Lotus Mine"
      }
    }
  ]
}
