{
  "geometry": {
    "type": "Point",
    "coordinates": [
      -116.9833,
      43.0167
    ]
  },
  "type": "Feature",
  "properties": {
    "hierarchy": [
      "tgn:2684931",
      "tgn:1000001",
      "tgn:7012149",
      "tgn:2000488",
      "tgn:7007250",
      "tgn:7029392"
    ],
    "placetype": [
      "aat:300008761"
    ],
    "id": 2684931,
    "name:xx": "Split Rock Canyon"
  }
}
