{
  "geometry": {
    "type": "Point",
    "coordinates": [
      -99.5333,
      32.25
    ]
  },
  "type": "Feature",
  "properties": {
    "hierarchy": [
      "tgn:2103766",
      "tgn:1000001",
      "tgn:7012149",
      "tgn:2001951",
      "tgn:7007826",
      "tgn:7029392"
    ],
    "placetype": [
      "aat:300008347",
      "aat:300387210"
    ],
    "id": 2103766,
    "name:xx": "Denton"
  }
}
