{
  "geometry": {
    "type": "Point",
    "coordinates": [
      79.9907,
      27.0931
    ]
  },
  "type": "Feature",
  "properties": {
    "hierarchy": [
      "tgn:7562014",
      "tgn:1000004",
      "tgn:7000198",
      "tgn:7016722",
      "tgn:7029392"
    ],
    "placetype": [
      "aat:300008347"
    ],
    "name:en": "Sunāli Purwa",
    "id": 7562014
  }
}
