{
  "geometry": {
    "type": "Point",
    "coordinates": [
      113.6333,
      29.5167
    ]
  },
  "type": "Feature",
  "properties": {
    "hierarchy": [
      "tgn:1073357",
      "tgn:1000004",
      "tgn:7002079",
      "tgn:1000111",
      "tgn:7029392"
    ],
    "placetype": [
      "aat:300008347"
    ],
    "id": 1073357,
    "name:xx": "Yanglousi"
  }
}
