{
  "geometry": {
    "type": "Point",
    "coordinates": [
      -115.2833,
      41.7833
    ]
  },
  "type": "Feature",
  "properties": {
    "hierarchy": [
      "tgn:2419441",
      "tgn:1000001",
      "tgn:2001411",
      "tgn:7012149",
      "tgn:7007526",
      "tgn:7029392"
    ],
    "placetype": [
      "aat:300008863"
    ],
    "id": 2419441,
    "name:xx": "Jarbidge Ranger Distrist"
  }
}
