{
  "geometry": {
    "type": "Point",
    "coordinates": [
      -79.8667,
      40.55
    ]
  },
  "type": "Feature",
  "properties": {
    "hierarchy": [
      "tgn:2217760",
      "tgn:7013272",
      "tgn:1000001",
      "tgn:7012149",
      "tgn:7007710",
      "tgn:7029392"
    ],
    "placetype": [
      "aat:300008699"
    ],
    "id": 2217760,
    "name:xx": "Campbell Run"
  }
}
