{
  "geometry": {
    "type": "Point",
    "coordinates": [
      -83.55,
      35.1833
    ]
  },
  "type": "Feature",
  "properties": {
    "hierarchy": [
      "tgn:2444576",
      "tgn:1000001",
      "tgn:7012149",
      "tgn:2001515",
      "tgn:7007709",
      "tgn:7029392"
    ],
    "placetype": [
      "aat:300008699"
    ],
    "id": 2444576,
    "name:xx": "Left Prong Ray Branch"
  }
}
