{
  "geometry": {
    "type": "Point",
    "coordinates": [
      -111.6167,
      42.2167
    ]
  },
  "type": "Feature",
  "properties": {
    "hierarchy": [
      "tgn:2678677",
      "tgn:1000001",
      "tgn:7012149",
      "tgn:2000472",
      "tgn:7007250",
      "tgn:7029392"
    ],
    "placetype": [
      "aat:300008706"
    ],
    "id": 2678677,
    "name:xx": "South Fork Dry Creek"
  }
}
