{
  "geometry": {
    "type": "Point",
    "coordinates": [
      -89.5833,
      31.0833
    ]
  },
  "type": "Feature",
  "properties": {
    "hierarchy": [
      "tgn:2664730",
      "tgn:1000001",
      "tgn:7012149",
      "tgn:2001122",
      "tgn:7007522",
      "tgn:7029392"
    ],
    "placetype": [
      "aat:300008699"
    ],
    "id": 2664730,
    "name:xx": "Simmons Springs Branch"
  }
}
