{
  "geometry": {
    "type": "Point",
    "coordinates": [
      52.95,
      56.2167
    ]
  },
  "type": "Feature",
  "properties": {
    "hierarchy": [
      "tgn:1057466",
      "tgn:1000004",
      "tgn:7002435",
      "tgn:7011524",
      "tgn:7029392"
    ],
    "placetype": [
      "aat:300008347"
    ],
    "id": 1057466,
    "name:xx": "Nižneje Kučukovo"
  }
}
