{
  "type": "FeatureCollection",
  "features": [
    {
      "geometry": {
        "type": "Point",
        "coordinates": [
          -88.4,
          37.7167
        ]
      },
      "type": "Feature",
      "properties": {
        "hierarchy": [
          "tgn:2745510",
          "tgn:1000001",
          "tgn:7012149",
          "tgn:2000530",
          "tgn:7007251",
          "tgn:7029392"
        ],
        "placetype": [
          "aat:300000390"
        ],
        "id": 2745510,
        "name:xx": "Vinyard Mine"
      }
    },
    {
      "geometry": {
        "type": "Point",
        "coordinates": [
          -81.8667,
          31.75
        ]
      },
      "type": "Feature",
      "properties": {
        "hierarchy": [
          "tgn:2745511",
          "tgn:1000001",
          "tgn:7012149",
          "tgn:2000382",
          "tgn:7007248",
          "tgn:7029392"
        ],
        "placetype": [
          "aat:300008905"
        ],
        "id": 2745511,
        "name:xx": "Vinzant Swamp"
      }
    },
    {
      "geometry": {
        "type": "Point",
        "coordinates": [
          -104.6,
          37.1333
        ]
      },
      "type": "Feature",
      "properties": {
        "hierarchy": [
          "tgn:2745512",
          "tgn:1000001",
          "tgn:7012149",
          "tgn:2000227",
          "tgn:7007158",
          "tgn:7029392"
        ],
        "placetype": [
          "aat:300008347"
        ],
        "id": 2745512,
        "name:xx": "Viola"
      }
    },
    {
      "geometry": {
        "type": "Point",
        "coordinates": [
          -85.1333,
          33.25
        ]
      },
      "type": "Feature",
      "properties": {
        "hierarchy": [
          "tgn:2745513",
          "tgn:1000001",
          "tgn:7012149",
          "tgn:2000365",
          "tgn:7007248",
          "tgn:7029392"
        ],
        "placetype": [
          "aat:300008347"
        ],
        "id": 2745513,
        "name:xx": "Viola"
      }
    },
    {
      "geometry": {
        "type": "Point",
        "coordinates": [
          -90.2833,
          30.65
        ]
      },
      "type": "Feature",
      "properties": {
        "hierarchy": [
          "tgn:2745514",
          "tgn:1000001",
          "tgn:7012149",
          "tgn:2000906",
          "tgn:7007256",
          "tgn:7029392"
        ],
        "placetype": [
          "aat:300008347"
        ],
        "id": 2745514,
        "name:xx": "Viola"
      }
    },
    {
      "geometry": {
        "type": "Point",
        "coordinates": [
          -93.5667,
          36.5667
        ]
      },
      "type": "Feature",
      "properties": {
        "hierarchy": [
          "tgn:2745515",
          "tgn:1000001",
          "tgn:7012149",
          "tgn:2001249",
          "tgn:7007523",
          "tgn:7029392"
        ],
        "placetype": [
          "aat:300008347"
        ],
        "id": 2745515,
        "name:xx": "Viola"
      }
    },
    {
      "geometry": {
        "type": "Point",
        "coordinates": [
          -114.3833,
          37.25
        ]
      },
      "type": "Feature",
      "properties": {
        "hierarchy": [
          "tgn:2745516",
          "tgn:1000001",
          "tgn:2001416",
          "tgn:7012149",
          "tgn:7007526",
          "tgn:7029392"
        ],
        "placetype": [
          "aat:300008347"
        ],
        "id": 2745516,
        "name:xx": "Viola"
      }
    },
    {
      "geometry": {
        "type": "Point",
        "coordinates": [
          -107.7167,
          32.9
        ]
      },
      "type": "Feature",
      "properties": {
        "hierarchy": [
          "tgn:2745517",
          "tgn:1000001",
          "tgn:7012149",
          "tgn:2001455",
          "tgn:7007566",
          "tgn:7029392"
        ],
        "placetype": [
          "aat:300000390"
        ],
        "id": 2745517,
        "name:xx": "Viola"
      }
    },
    {
      "geometry": {
        "type": "Point",
        "coordinates": [
          -78.4,
          40.75
        ]
      },
      "type": "Feature",
      "properties": {
        "hierarchy": [
          "tgn:2745518",
          "tgn:1000001",
          "tgn:1002278",
          "tgn:7012149",
          "tgn:7007710",
          "tgn:7029392"
        ],
        "placetype": [
          "aat:300008347"
        ],
        "id": 2745518,
        "name:xx": "Viola"
      }
    },
    {
      "geometry": {
        "type": "Point",
        "coordinates": [
          -118.8667,
          45.3667
        ]
      },
      "type": "Feature",
      "properties": {
        "hierarchy": [
          "tgn:2745519",
          "tgn:1000001",
          "tgn:7012149",
          "tgn:2001720",
          "tgn:7007708",
          "tgn:7029392"
        ],
        "placetype": [
          "aat:300008761"
        ],
        "id": 2745519,
        "name:xx": "Viola Canyon"
      }
    }
  ]
}
