{
  "geometry": {
    "type": "Point",
    "coordinates": [
      -120.25,
      52.4167
    ]
  },
  "type": "Feature",
  "properties": {
    "hierarchy": [
      "tgn:1102626",
      "tgn:7005735",
      "tgn:7005685",
      "tgn:1000001",
      "tgn:7029392"
    ],
    "placetype": [
      "aat:300008195"
    ],
    "id": 1102626,
    "name:xx": "Wells Gray Provincial Park"
  }
}
