{
  "geometry": {
    "type": "Point",
    "coordinates": [
      75.661819,
      28.243138
    ]
  },
  "type": "Feature",
  "properties": {
    "hierarchy": [
      "tgn:7582646",
      "tgn:1000004",
      "tgn:7000198",
      "tgn:7016788",
      "tgn:7029392"
    ],
    "placetype": [
      "aat:300008347"
    ],
    "name:en": "Dālmiān Ki Dhāni",
    "id": 7582646
  }
}
