{
  "geometry": {
    "type": "Point",
    "coordinates": [
      -112.4833,
      42.95
    ]
  },
  "type": "Feature",
  "properties": {
    "hierarchy": [
      "tgn:2144236",
      "tgn:2000454",
      "tgn:1000001",
      "tgn:7012149",
      "tgn:7007250",
      "tgn:7029392"
    ],
    "placetype": [
      "aat:300006075"
    ],
    "id": 2144236,
    "name:xx": "Baker Lateral"
  }
}
