{
  "geometry": {
    "type": "Point",
    "coordinates": [
      7.2167,
      47.9167
    ]
  },
  "type": "Feature",
  "properties": {
    "hierarchy": [
      "tgn:7008121",
      "tgn:7002870",
      "tgn:1000003",
      "tgn:1000070",
      "tgn:7029392"
    ],
    "placetype": [
      "aat:300008347"
    ],
    "id": 7008121,
    "name:xx": "Guebwiller"
  }
}
