{
  "type": "FeatureCollection",
  "features": [
    {
      "geometry": {
        "type": "Point",
        "coordinates": [
          -76.6333,
          39.1833
        ]
      },
      "type": "Feature",
      "properties": {
        "hierarchy": [
          "tgn:2049270",
          "tgn:7014651",
          "tgn:1000001",
          "tgn:7012149",
          "tgn:7007516",
          "tgn:7029392"
        ],
        "placetype": [
          "aat:300008347"
        ],
        "id": 2049270,
        "name:xx": "Woodlawn Heights"
      }
    },
    {
      "geometry": {
        "type": "Point",
        "coordinates": [
          -77.7333,
          39.65
        ]
      },
      "type": "Feature",
      "properties": {
        "hierarchy": [
          "tgn:2049272",
          "tgn:1000001",
          "tgn:7016106",
          "tgn:7012149",
          "tgn:7007516",
          "tgn:7029392"
        ],
        "placetype": [
          "aat:300008347"
        ],
        "id": 2049272,
        "name:xx": "Wood Point"
      }
    },
    {
      "geometry": {
        "type": "Point",
        "coordinates": [
          -77.3,
          39.5167
        ]
      },
      "type": "Feature",
      "properties": {
        "hierarchy": [
          "tgn:2049273",
          "tgn:1000001",
          "tgn:7016101",
          "tgn:7012149",
          "tgn:7007516",
          "tgn:7029392"
        ],
        "placetype": [
          "aat:300008347"
        ],
        "id": 2049273,
        "name:xx": "Woodsboro"
      }
    },
    {
      "geometry": {
        "type": "Point",
        "coordinates": [
          -76.9167,
          38.8167
        ]
      },
      "type": "Feature",
      "properties": {
        "hierarchy": [
          "tgn:2049276",
          "tgn:1000001",
          "tgn:2124001",
          "tgn:7012149",
          "tgn:7007516",
          "tgn:7029392"
        ],
        "placetype": [
          "aat:300008347",
          "aat:300387210"
        ],
        "id": 2049276,
        "name:xx": "Woods Corner"
      }
    },
    {
      "geometry": {
        "type": "Point",
        "coordinates": [
          -76.8667,
          39.3167
        ]
      },
      "type": "Feature",
      "properties": {
        "hierarchy": [
          "tgn:2049277",
          "tgn:1000001",
          "tgn:1002488",
          "tgn:7012149",
          "tgn:7007516",
          "tgn:7029392"
        ],
        "placetype": [
          "aat:300008347"
        ],
        "id": 2049277,
        "name:xx": "Woodstock"
      }
    },
    {
      "geometry": {
        "type": "Point",
        "coordinates": [
          -77.1667,
          39.4
        ]
      },
      "type": "Feature",
      "properties": {
        "hierarchy": [
          "tgn:2049278",
          "tgn:1000001",
          "tgn:7016101",
          "tgn:7012149",
          "tgn:7007516",
          "tgn:7029392"
        ],
        "placetype": [
          "aat:300008347",
          "aat:300387210"
        ],
        "id": 2049278,
        "name:xx": "Woodville"
      }
    }
  ]
}
