{
  "geometry": {
    "type": "Point",
    "coordinates": [
      50.0333,
      52.7333
    ]
  },
  "type": "Feature",
  "properties": {
    "hierarchy": [
      "tgn:1137733",
      "tgn:1000004",
      "tgn:1003407",
      "tgn:7018214",
      "tgn:7002435",
      "tgn:7029392"
    ],
    "placetype": [
      "aat:300008347"
    ],
    "id": 1137733,
    "name:xx": "Krasnoarmejskoje"
  }
}
