{
  "type": "FeatureCollection",
  "features": [
    {
      "geometry": {
        "type": "Point",
        "coordinates": [
          -72.2667,
          44.7
        ]
      },
      "type": "Feature",
      "properties": {
        "hierarchy": [
          "tgn:2694050",
          "tgn:1000001",
          "tgn:1002753",
          "tgn:7012149",
          "tgn:7007828",
          "tgn:7029392"
        ],
        "placetype": [
          "aat:300008699"
        ],
        "id": 2694050,
        "name:xx": "Stevens Brook"
      }
    },
    {
      "geometry": {
        "type": "Point",
        "coordinates": [
          -73.05,
          44.8
        ]
      },
      "type": "Feature",
      "properties": {
        "hierarchy": [
          "tgn:2694051",
          "tgn:1000001",
          "tgn:1002389",
          "tgn:7012149",
          "tgn:7007828",
          "tgn:7029392"
        ],
        "placetype": [
          "aat:300008699"
        ],
        "id": 2694051,
        "name:xx": "Stevens Brook"
      }
    },
    {
      "geometry": {
        "type": "Point",
        "coordinates": [
          -109.8833,
          46.7167
        ]
      },
      "type": "Feature",
      "properties": {
        "hierarchy": [
          "tgn:2694052",
          "tgn:1000001",
          "tgn:7012149",
          "tgn:2001282",
          "tgn:7007524",
          "tgn:7029392"
        ],
        "placetype": [
          "aat:300008798"
        ],
        "id": 2694052,
        "name:xx": "Stevens Butte"
      }
    },
    {
      "geometry": {
        "type": "Point",
        "coordinates": [
          -120.6333,
          43.5
        ]
      },
      "type": "Feature",
      "properties": {
        "hierarchy": [
          "tgn:2694053",
          "tgn:1000001",
          "tgn:7012149",
          "tgn:2001715",
          "tgn:7007708",
          "tgn:7029392"
        ],
        "placetype": [
          "aat:300008798"
        ],
        "id": 2694053,
        "name:xx": "Stevens Butte"
      }
    },
    {
      "geometry": {
        "type": "Point",
        "coordinates": [
          -118.1333,
          36.75
        ]
      },
      "type": "Feature",
      "properties": {
        "hierarchy": [
          "tgn:2694054",
          "tgn:1000001",
          "tgn:7012149",
          "tgn:2000183",
          "tgn:7007157",
          "tgn:7029392"
        ],
        "placetype": [
          "aat:300006075"
        ],
        "id": 2694054,
        "name:xx": "Stevens Canal"
      }
    },
    {
      "geometry": {
        "type": "Point",
        "coordinates": [
          -78.95,
          34.45
        ]
      },
      "type": "Feature",
      "properties": {
        "hierarchy": [
          "tgn:2694055",
          "tgn:1000001",
          "tgn:7012149",
          "tgn:2001534",
          "tgn:7007709",
          "tgn:7029392"
        ],
        "placetype": [
          "aat:300006075"
        ],
        "id": 2694055,
        "name:xx": "Stevens Canal"
      }
    },
    {
      "geometry": {
        "type": "Point",
        "coordinates": [
          -110.7667,
          31.6
        ]
      },
      "type": "Feature",
      "properties": {
        "hierarchy": [
          "tgn:2694056",
          "tgn:1000001",
          "tgn:7006451",
          "tgn:7012149",
          "tgn:2000102",
          "tgn:7029392"
        ],
        "placetype": [
          "aat:300008761"
        ],
        "id": 2694056,
        "name:xx": "Stevens Canyon"
      }
    },
    {
      "geometry": {
        "type": "Point",
        "coordinates": [
          -108.9833,
          38.0333
        ]
      },
      "type": "Feature",
      "properties": {
        "hierarchy": [
          "tgn:2694057",
          "tgn:1000001",
          "tgn:7012149",
          "tgn:7007158",
          "tgn:2000248",
          "tgn:7029392"
        ],
        "placetype": [
          "aat:300008761"
        ],
        "id": 2694057,
        "name:xx": "Stevens Canyon"
      }
    },
    {
      "geometry": {
        "type": "Point",
        "coordinates": [
          -121.5167,
          44.3333
        ]
      },
      "type": "Feature",
      "properties": {
        "hierarchy": [
          "tgn:2694058",
          "tgn:1000001",
          "tgn:7012149",
          "tgn:7007708",
          "tgn:7029392"
        ],
        "placetype": [
          "aat:300008761"
        ],
        "id": 2694058,
        "name:xx": "Stevens Canyon"
      }
    },
    {
      "geometry": {
        "type": "Point",
        "coordinates": [
          -119.6333,
          45.1
        ]
      },
      "type": "Feature",
      "properties": {
        "hierarchy": [
          "tgn:2694059",
          "tgn:1000001",
          "tgn:7012149",
          "tgn:2001719",
          "tgn:7007708",
          "tgn:7029392"
        ],
        "placetype": [
          "aat:300008761"
        ],
        "id": 2694059,
        "name:xx": "Stevens Canyon"
      }
    }
  ]
}
