{
  "geometry": {
    "type": "Point",
    "coordinates": [
      -96.8833,
      39.85
    ]
  },
  "type": "Feature",
  "properties": {
    "hierarchy": [
      "tgn:2378037",
      "tgn:1000001",
      "tgn:7012149",
      "tgn:2000725",
      "tgn:7007254",
      "tgn:7029392"
    ],
    "placetype": [
      "aat:300008706"
    ],
    "id": 2378037,
    "name:xx": "Harris Creek"
  }
}
