{
  "geometry": {
    "type": "Point",
    "coordinates": [
      -103.6833,
      40.1667
    ]
  },
  "type": "Feature",
  "properties": {
    "hierarchy": [
      "tgn:2631479",
      "tgn:1000001",
      "tgn:7012149",
      "tgn:2000235",
      "tgn:7007158",
      "tgn:7029392"
    ],
    "placetype": [
      "aat:300008798"
    ],
    "id": 2631479,
    "name:xx": "Round Top"
  }
}
