{
  "geometry": {
    "type": "Point",
    "coordinates": [
      -77.0167,
      37.7833
    ]
  },
  "type": "Feature",
  "properties": {
    "hierarchy": [
      "tgn:2291288",
      "tgn:1000001",
      "tgn:7012149",
      "tgn:1002549",
      "tgn:7007919",
      "tgn:7029392"
    ],
    "placetype": [
      "aat:300008699"
    ],
    "id": 2291288,
    "name:xx": "Dogwood Fork"
  }
}
