{
  "geometry": {
    "type": "Point",
    "coordinates": [
      -70.1167,
      45.25
    ]
  },
  "type": "Feature",
  "properties": {
    "hierarchy": [
      "tgn:2383890",
      "tgn:1000001",
      "tgn:7012149",
      "tgn:2000930",
      "tgn:7007515",
      "tgn:7029392"
    ],
    "placetype": [
      "aat:300008798"
    ],
    "id": 2383890,
    "name:xx": "Hedgehog Mountain"
  }
}
