{
  "type": "FeatureCollection",
  "features": [
    {
      "geometry": {
        "type": "Point",
        "coordinates": [
          -102.8667,
          45
        ]
      },
      "type": "Feature",
      "properties": {
        "hierarchy": [
          "tgn:2097390",
          "tgn:1000001",
          "tgn:2001816",
          "tgn:7012149",
          "tgn:7007713",
          "tgn:7029392"
        ],
        "placetype": [
          "aat:300008347"
        ],
        "id": 2097390,
        "name:xx": "Mud Butte"
      }
    },
    {
      "geometry": {
        "type": "Point",
        "coordinates": [
          -100.7,
          43.8833
        ]
      },
      "type": "Feature",
      "properties": {
        "hierarchy": [
          "tgn:2097391",
          "tgn:1000001",
          "tgn:2001807",
          "tgn:7012149",
          "tgn:7007713",
          "tgn:7029392"
        ],
        "placetype": [
          "aat:300008347"
        ],
        "id": 2097391,
        "name:xx": "Murdo"
      }
    },
    {
      "geometry": {
        "type": "Point",
        "coordinates": [
          -103.6333,
          44.0667
        ]
      },
      "type": "Feature",
      "properties": {
        "hierarchy": [
          "tgn:2097392",
          "tgn:1000001",
          "tgn:7012149",
          "tgn:2001821",
          "tgn:7007713",
          "tgn:7029392"
        ],
        "placetype": [
          "aat:300008347",
          "aat:300387210"
        ],
        "id": 2097392,
        "name:xx": "Mystic"
      }
    },
    {
      "geometry": {
        "type": "Point",
        "coordinates": [
          -97.5,
          44.7667
        ]
      },
      "type": "Feature",
      "properties": {
        "hierarchy": [
          "tgn:2097394",
          "tgn:1000001",
          "tgn:2001782",
          "tgn:7012149",
          "tgn:7007713",
          "tgn:7029392"
        ],
        "placetype": [
          "aat:300008347"
        ],
        "id": 2097394,
        "name:xx": "Naples"
      }
    },
    {
      "geometry": {
        "type": "Point",
        "coordinates": [
          -103.5,
          44.1833
        ]
      },
      "type": "Feature",
      "properties": {
        "hierarchy": [
          "tgn:2097395",
          "tgn:1000001",
          "tgn:2001810",
          "tgn:7012149",
          "tgn:7007713",
          "tgn:7029392"
        ],
        "placetype": [
          "aat:300008347"
        ],
        "id": 2097395,
        "name:xx": "Nemo"
      }
    },
    {
      "geometry": {
        "type": "Point",
        "coordinates": [
          -96.9167,
          45.85
        ]
      },
      "type": "Feature",
      "properties": {
        "hierarchy": [
          "tgn:2097396",
          "tgn:1000001",
          "tgn:7012149",
          "tgn:2001824",
          "tgn:7007713",
          "tgn:7029392"
        ],
        "placetype": [
          "aat:300008347"
        ],
        "id": 2097396,
        "name:xx": "New Effington"
      }
    },
    {
      "geometry": {
        "type": "Point",
        "coordinates": [
          -103.4167,
          44.7
        ]
      },
      "type": "Feature",
      "properties": {
        "hierarchy": [
          "tgn:2097397",
          "tgn:1000001",
          "tgn:2001779",
          "tgn:7012149",
          "tgn:7007713",
          "tgn:7029392"
        ],
        "placetype": [
          "aat:300008347"
        ],
        "id": 2097397,
        "name:xx": "Newell"
      }
    },
    {
      "geometry": {
        "type": "Point",
        "coordinates": [
          -97.8167,
          43.4833
        ]
      },
      "type": "Feature",
      "properties": {
        "hierarchy": [
          "tgn:2097398",
          "tgn:1000001",
          "tgn:2001803",
          "tgn:7012149",
          "tgn:7007713",
          "tgn:7029392"
        ],
        "placetype": [
          "aat:300008347",
          "aat:300387210"
        ],
        "id": 2097398,
        "name:xx": "New Elm Springs Colony"
      }
    },
    {
      "geometry": {
        "type": "Point",
        "coordinates": [
          -98.6,
          43.4167
        ]
      },
      "type": "Feature",
      "properties": {
        "hierarchy": [
          "tgn:2097399",
          "tgn:1000001",
          "tgn:2001791",
          "tgn:7012149",
          "tgn:7007713",
          "tgn:7029392"
        ],
        "placetype": [
          "aat:300008347"
        ],
        "id": 2097399,
        "name:xx": "New Holland"
      }
    }
  ]
}
