{
  "geometry": {
    "type": "Point",
    "coordinates": [
      -71.2833,
      42.4333
    ]
  },
  "type": "Feature",
  "properties": {
    "hierarchy": [
      "tgn:2333502",
      "tgn:1000001",
      "tgn:1002665",
      "tgn:7012149",
      "tgn:7007517",
      "tgn:7029392"
    ],
    "placetype": [
      "aat:300008680"
    ],
    "id": 2333502,
    "name:xx": "Folly Pond"
  }
}
