{
  "type": "FeatureCollection",
  "features": [
    {
      "geometry": {
        "type": "Point",
        "coordinates": [
          -71.7833,
          42.1
        ]
      },
      "type": "Feature",
      "properties": {
        "hierarchy": [
          "tgn:2705910",
          "tgn:1000001",
          "tgn:7012149",
          "tgn:1003038",
          "tgn:7007517",
          "tgn:7029392"
        ],
        "placetype": [
          "aat:300006191"
        ],
        "id": 2705910,
        "name:xx": "Sutton Pond"
      }
    },
    {
      "geometry": {
        "type": "Point",
        "coordinates": [
          -84.1667,
          44.8667
        ]
      },
      "type": "Feature",
      "properties": {
        "hierarchy": [
          "tgn:2705911",
          "tgn:1000001",
          "tgn:7012149",
          "tgn:2000982",
          "tgn:7007520",
          "tgn:7029392"
        ],
        "placetype": [
          "aat:300008680"
        ],
        "id": 2705911,
        "name:xx": "Sutton Pond"
      }
    },
    {
      "geometry": {
        "type": "Point",
        "coordinates": [
          -74.6,
          43.95
        ]
      },
      "type": "Feature",
      "properties": {
        "hierarchy": [
          "tgn:2705912",
          "tgn:1000001",
          "tgn:7012149",
          "tgn:1002440",
          "tgn:7007568",
          "tgn:7029392"
        ],
        "placetype": [
          "aat:300008680"
        ],
        "id": 2705912,
        "name:xx": "Sutton Pond"
      }
    },
    {
      "geometry": {
        "type": "Point",
        "coordinates": [
          -117.8333,
          46.8833
        ]
      },
      "type": "Feature",
      "properties": {
        "hierarchy": [
          "tgn:2705913",
          "tgn:1000001",
          "tgn:7012149",
          "tgn:2002252",
          "tgn:7007920",
          "tgn:7029392"
        ],
        "placetype": [
          "aat:300008680"
        ],
        "id": 2705913,
        "name:xx": "Sutton Pond"
      }
    },
    {
      "geometry": {
        "type": "Point",
        "coordinates": [
          -108.2667,
          37.5833
        ]
      },
      "type": "Feature",
      "properties": {
        "hierarchy": [
          "tgn:2705914",
          "tgn:1000001",
          "tgn:7012149",
          "tgn:2000233",
          "tgn:7007158",
          "tgn:7029392"
        ],
        "placetype": [
          "aat:300006191"
        ],
        "id": 2705914,
        "name:xx": "Sutton Reservoir"
      }
    },
    {
      "geometry": {
        "type": "Point",
        "coordinates": [
          -84.9333,
          39.15
        ]
      },
      "type": "Feature",
      "properties": {
        "hierarchy": [
          "tgn:2705915",
          "tgn:1000001",
          "tgn:1002324",
          "tgn:7012149",
          "tgn:7007252",
          "tgn:7029392"
        ],
        "placetype": [
          "aat:300266640"
        ],
        "id": 2705915,
        "name:xx": "Sutton Ridge"
      }
    },
    {
      "geometry": {
        "type": "Point",
        "coordinates": [
          -91.8333,
          31.0333
        ]
      },
      "type": "Feature",
      "properties": {
        "hierarchy": [
          "tgn:2705916",
          "tgn:2000858",
          "tgn:1000001",
          "tgn:7012149",
          "tgn:7007256",
          "tgn:7029392"
        ],
        "placetype": [
          "aat:300266640"
        ],
        "id": 2705916,
        "name:xx": "Sutton Ridge"
      }
    },
    {
      "geometry": {
        "type": "Point",
        "coordinates": [
          -83.2,
          35.7667
        ]
      },
      "type": "Feature",
      "properties": {
        "hierarchy": [
          "tgn:2705917",
          "tgn:1000001",
          "tgn:7012149",
          "tgn:2001851",
          "tgn:7007825",
          "tgn:7029392"
        ],
        "placetype": [
          "aat:300266640"
        ],
        "id": 2705917,
        "name:xx": "Sutton Ridge"
      }
    },
    {
      "geometry": {
        "type": "Point",
        "coordinates": [
          -84.0333,
          36.3667
        ]
      },
      "type": "Feature",
      "properties": {
        "hierarchy": [
          "tgn:2705918",
          "tgn:1000001",
          "tgn:7012149",
          "tgn:2001843",
          "tgn:7007825",
          "tgn:7029392"
        ],
        "placetype": [
          "aat:300266640"
        ],
        "id": 2705918,
        "name:xx": "Sutton Ridge"
      }
    },
    {
      "geometry": {
        "type": "Point",
        "coordinates": [
          -72.05,
          44.7
        ]
      },
      "type": "Feature",
      "properties": {
        "hierarchy": [
          "tgn:2705919",
          "tgn:2002131",
          "tgn:1000001",
          "tgn:7012149",
          "tgn:7007828",
          "tgn:7029392"
        ],
        "placetype": [
          "aat:300008707"
        ],
        "id": 2705919,
        "name:xx": "Sutton River"
      }
    }
  ]
}
