{
  "geometry": {
    "type": "Point",
    "coordinates": [
      -80.2167,
      39.1833
    ]
  },
  "type": "Feature",
  "properties": {
    "hierarchy": [
      "tgn:2174137",
      "tgn:1000001",
      "tgn:7012149",
      "tgn:2002267",
      "tgn:7013961",
      "tgn:7029392"
    ],
    "placetype": [
      "aat:300008699"
    ],
    "id": 2174137,
    "name:xx": "Birds Run"
  }
}
