{
  "geometry": {
    "type": "Point",
    "coordinates": [
      -75.0667,
      42.4833
    ]
  },
  "type": "Feature",
  "properties": {
    "hierarchy": [
      "tgn:2777572",
      "tgn:1000001",
      "tgn:7012149",
      "tgn:7014318",
      "tgn:7007568",
      "tgn:7029392"
    ],
    "placetype": [
      "aat:300008798"
    ],
    "id": 2777572,
    "name:xx": "Winnie Hill"
  }
}
