{
  "type": "FeatureCollection",
  "features": [
    {
      "geometry": {
        "type": "Point",
        "coordinates": [
          15.25,
          52.25
        ]
      },
      "type": "Feature",
      "properties": {
        "hierarchy": [
          "tgn:7024120",
          "tgn:1000003",
          "tgn:7006366",
          "tgn:7029392"
        ],
        "placetype": [
          "aat:300387064",
          "aat:300235112"
        ],
        "id": 7024120,
        "name:xx": "Lubuskie"
      }
    },
    {
      "geometry": {
        "type": "Point",
        "coordinates": [
          19.5,
          51.5
        ]
      },
      "type": "Feature",
      "properties": {
        "hierarchy": [
          "tgn:7024121",
          "tgn:1000003",
          "tgn:7006366",
          "tgn:7029392"
        ],
        "placetype": [
          "aat:300387064",
          "aat:300235112"
        ],
        "id": 7024121,
        "name:xx": "Łódzkie"
      }
    },
    {
      "geometry": {
        "type": "Point",
        "coordinates": [
          21,
          52.25
        ]
      },
      "type": "Feature",
      "properties": {
        "hierarchy": [
          "tgn:7024122",
          "tgn:1000003",
          "tgn:7006366",
          "tgn:7029392"
        ],
        "placetype": [
          "aat:300387064",
          "aat:300235112"
        ],
        "id": 7024122,
        "name:xx": "Mazowieckie"
      }
    },
    {
      "geometry": {
        "type": "Point",
        "coordinates": [
          16.5,
          51
        ]
      },
      "type": "Feature",
      "properties": {
        "hierarchy": [
          "tgn:7024123",
          "tgn:1000003",
          "tgn:7006366",
          "tgn:7029392"
        ],
        "placetype": [
          "aat:300387064",
          "aat:300235112"
        ],
        "id": 7024123,
        "name:xx": "Dolnośla̜skie"
      }
    },
    {
      "geometry": {
        "type": "Point",
        "coordinates": [
          18,
          50.5
        ]
      },
      "type": "Feature",
      "properties": {
        "hierarchy": [
          "tgn:7024124",
          "tgn:1000003",
          "tgn:7006366",
          "tgn:7029392"
        ],
        "placetype": [
          "aat:300387064",
          "aat:300235112"
        ],
        "id": 7024124,
        "name:xx": "Opolskie"
      }
    },
    {
      "geometry": {
        "type": "Point",
        "coordinates": [
          19,
          50.25
        ]
      },
      "type": "Feature",
      "properties": {
        "hierarchy": [
          "tgn:7024125",
          "tgn:1000003",
          "tgn:7006366",
          "tgn:7029392"
        ],
        "placetype": [
          "aat:300387064",
          "aat:300235112"
        ],
        "id": 7024125,
        "name:xx": "Śla̜skie"
      }
    },
    {
      "geometry": {
        "type": "Point",
        "coordinates": [
          22,
          50
        ]
      },
      "type": "Feature",
      "properties": {
        "hierarchy": [
          "tgn:7024126",
          "tgn:1000003",
          "tgn:7006366",
          "tgn:7029392"
        ],
        "placetype": [
          "aat:300387064",
          "aat:300235112"
        ],
        "id": 7024126,
        "name:xx": "Podkarpackie"
      }
    },
    {
      "geometry": {
        "type": "Point",
        "coordinates": [
          20.5,
          49.75
        ]
      },
      "type": "Feature",
      "properties": {
        "hierarchy": [
          "tgn:7024127",
          "tgn:1000003",
          "tgn:7006366",
          "tgn:7029392"
        ],
        "placetype": [
          "aat:300387064",
          "aat:300235112"
        ],
        "id": 7024127,
        "name:xx": "Małopolskie"
      }
    },
    {
      "geometry": {
        "type": "Point",
        "coordinates": [
          23,
          51
        ]
      },
      "type": "Feature",
      "properties": {
        "hierarchy": [
          "tgn:7024128",
          "tgn:1000003",
          "tgn:7006366",
          "tgn:7029392"
        ],
        "placetype": [
          "aat:300387064",
          "aat:300235112"
        ],
        "id": 7024128,
        "name:xx": "Lubelskie"
      }
    },
    {
      "geometry": {
        "type": "Point",
        "coordinates": [
          20.75,
          50.75
        ]
      },
      "type": "Feature",
      "properties": {
        "hierarchy": [
          "tgn:7024129",
          "tgn:1000003",
          "tgn:7006366",
          "tgn:7029392"
        ],
        "placetype": [
          "aat:300387064",
          "aat:300235112"
        ],
        "id": 7024129,
        "name:xx": "Świe̜tokrzyskie"
      }
    }
  ]
}
