{
  "geometry": {
    "type": "Point",
    "coordinates": [
      -43.3167,
      -22.1833
    ]
  },
  "type": "Feature",
  "properties": {
    "hierarchy": [
      "tgn:1133327",
      "tgn:1001942",
      "tgn:1000047",
      "tgn:7002457",
      "tgn:1000002",
      "tgn:7029392"
    ],
    "placetype": [
      "aat:300008706"
    ],
    "id": 1133327,
    "name:xx": "Grande, Ribeirão"
  }
}
