{
  "type": "FeatureCollection",
  "features": [
    {
      "geometry": {
        "type": "Point",
        "coordinates": [
          -71.666667,
          -34.2
        ]
      },
      "type": "Feature",
      "properties": {
        "hierarchy": [
          "tgn:7291150",
          "tgn:1001695",
          "tgn:1000049",
          "tgn:1000002",
          "tgn:7029392"
        ],
        "placetype": [
          "aat:300008699"
        ],
        "id": 7291150,
        "name:xx": "Fuente, Quebrada de la"
      }
    },
    {
      "geometry": {
        "type": "Point",
        "coordinates": [
          -70.233333,
          -54.183333
        ]
      },
      "type": "Feature",
      "properties": {
        "hierarchy": [
          "tgn:7291151",
          "tgn:1001702",
          "tgn:1000049",
          "tgn:1000002",
          "tgn:7029392"
        ],
        "placetype": [
          "aat:300008791"
        ],
        "id": 7291151,
        "name:xx": "Fuente, Isla de la"
      }
    },
    {
      "geometry": {
        "type": "Point",
        "coordinates": [
          -69.2,
          -25.333333
        ]
      },
      "type": "Feature",
      "properties": {
        "hierarchy": [
          "tgn:7291152",
          "tgn:7016598",
          "tgn:1000049",
          "tgn:1000002",
          "tgn:7029392"
        ],
        "placetype": [
          "aat:300008795"
        ],
        "id": 7291152,
        "name:xx": "Fuelle, Cerro del"
      }
    },
    {
      "geometry": {
        "type": "Point",
        "coordinates": [
          -72.333333,
          -47.066667
        ]
      },
      "type": "Feature",
      "properties": {
        "hierarchy": [
          "tgn:7291153",
          "tgn:1001623",
          "tgn:1000049",
          "tgn:1000002",
          "tgn:7029392"
        ],
        "placetype": [
          "aat:300008699"
        ],
        "id": 7291153,
        "name:xx": "Fudoso, Río"
      }
    },
    {
      "geometry": {
        "type": "Point",
        "coordinates": [
          -74.8,
          -50.116667
        ]
      },
      "type": "Feature",
      "properties": {
        "hierarchy": [
          "tgn:7291154",
          "tgn:1001702",
          "tgn:1000049",
          "tgn:1000002",
          "tgn:7029392"
        ],
        "placetype": [
          "aat:300132317"
        ],
        "id": 7291154,
        "name:xx": "Fuchoue, Bahía"
      }
    },
    {
      "geometry": {
        "type": "Point",
        "coordinates": [
          -72.933333,
          -36.6
        ]
      },
      "type": "Feature",
      "properties": {
        "hierarchy": [
          "tgn:7291155",
          "tgn:1001637",
          "tgn:1000049",
          "tgn:1000002",
          "tgn:7029392"
        ],
        "placetype": [
          "aat:300008347"
        ],
        "id": 7291155,
        "name:xx": "Frutillares"
      }
    },
    {
      "geometry": {
        "type": "Point",
        "coordinates": [
          -71.15,
          -32.2
        ]
      },
      "type": "Feature",
      "properties": {
        "hierarchy": [
          "tgn:7291156",
          "tgn:1001768",
          "tgn:1000049",
          "tgn:1000002",
          "tgn:7029392"
        ],
        "placetype": [
          "aat:300008699"
        ],
        "id": 7291156,
        "name:xx": "Frutillar, Quebrada"
      }
    },
    {
      "geometry": {
        "type": "Point",
        "coordinates": [
          -72.9675,
          -43.747778
        ]
      },
      "type": "Feature",
      "properties": {
        "hierarchy": [
          "tgn:7291157",
          "tgn:1001623",
          "tgn:1000049",
          "tgn:1000002",
          "tgn:7029392"
        ],
        "placetype": [
          "aat:300386846"
        ],
        "id": 7291157,
        "name:xx": "Fruitillar, Punta"
      }
    },
    {
      "geometry": {
        "type": "Point",
        "coordinates": [
          -71.15,
          -35.8
        ]
      },
      "type": "Feature",
      "properties": {
        "hierarchy": [
          "tgn:7291158",
          "tgn:1001705",
          "tgn:1000049",
          "tgn:1000002",
          "tgn:7029392"
        ],
        "placetype": [
          "aat:300008795"
        ],
        "id": 7291158,
        "name:xx": "Frutillar, Cordón"
      }
    },
    {
      "geometry": {
        "type": "Point",
        "coordinates": [
          -73,
          -41.133333
        ]
      },
      "type": "Feature",
      "properties": {
        "hierarchy": [
          "tgn:7291159",
          "tgn:1001699",
          "tgn:1000049",
          "tgn:1000002",
          "tgn:7029392"
        ],
        "placetype": [
          "aat:300132316"
        ],
        "id": 7291159,
        "name:xx": "Frutillar, Bahía"
      }
    }
  ]
}
