{
  "type": "FeatureCollection",
  "features": [
    {
      "geometry": {
        "type": "Point",
        "coordinates": [
          28.25,
          -29.5
        ]
      },
      "type": "Feature",
      "properties": {
        "name:en": "Lesotho",
        "hierarchy": [
          "tgn:7001660",
          "tgn:7001242",
          "tgn:7029392"
        ],
        "name:ar": "سًُوثو",
        "placetype": [
          "aat:300387054",
          "aat:300235115",
          "aat:300128207",
          "aat:300387174",
          "aat:300387136",
          "aat:300235096"
        ],
        "name:fr": "Lesotho",
        "name:ru": "Лесото",
        "name:st": "Lesotho",
        "name:zh": "莱索托",
        "id": 7001660,
        "name:es": "Lesotho"
      }
    },
    {
      "geometry": {
        "type": "Point",
        "coordinates": [
          21.4333,
          32.4667
        ]
      },
      "type": "Feature",
      "properties": {
        "hierarchy": [
          "tgn:7001663",
          "tgn:7000606",
          "tgn:7001242",
          "tgn:1000172",
          "tgn:7029392"
        ],
        "placetype": [
          "aat:300008347",
          "aat:300000810"
        ],
        "id": 7001663,
        "name:xx": "Qaşr Lībīyā"
      }
    },
    {
      "geometry": {
        "type": "Point",
        "coordinates": [
          45.1667,
          -12.8333
        ]
      },
      "type": "Feature",
      "properties": {
        "hierarchy": [
          "tgn:7001669",
          "tgn:7001242",
          "tgn:7029392"
        ],
        "placetype": [
          "aat:300387054",
          "aat:300235115",
          "aat:300386853",
          "aat:300387176"
        ],
        "name:en": "Mayotte",
        "id": 7001669
      }
    }
  ]
}
