{
  "geometry": {
    "type": "Point",
    "coordinates": [
      14.75,
      47.1833
    ]
  },
  "type": "Feature",
  "properties": {
    "hierarchy": [
      "tgn:1134090",
      "tgn:7003028",
      "tgn:1000003",
      "tgn:1000062",
      "tgn:7029392"
    ],
    "placetype": [
      "aat:300008706"
    ],
    "id": 1134090,
    "name:xx": "Pölsbach"
  }
}
