{
  "geometry": {
    "type": "Point",
    "coordinates": [
      -75.8333,
      40.1667
    ]
  },
  "type": "Feature",
  "properties": {
    "hierarchy": [
      "tgn:2426761",
      "tgn:1000001",
      "tgn:7013387",
      "tgn:7012149",
      "tgn:7007710",
      "tgn:7029392"
    ],
    "placetype": [
      "aat:300008680"
    ],
    "id": 2426761,
    "name:xx": "Jones Millpond"
  }
}
