{
  "geometry": {
    "type": "Point",
    "coordinates": [
      -88.0833,
      37.55
    ]
  },
  "type": "Feature",
  "properties": {
    "hierarchy": [
      "tgn:2411394",
      "tgn:1000001",
      "tgn:7012149",
      "tgn:2000847",
      "tgn:7007255",
      "tgn:7029392"
    ],
    "placetype": [
      "aat:300008798"
    ],
    "id": 2411394,
    "name:xx": "Indian Hill"
  }
}
