{
  "geometry": {
    "type": "Point",
    "coordinates": [
      -122.0333,
      47.7167
    ]
  },
  "type": "Feature",
  "properties": {
    "hierarchy": [
      "tgn:2756319",
      "tgn:1000001",
      "tgn:7012149",
      "tgn:7018871",
      "tgn:7007920",
      "tgn:7029392"
    ],
    "placetype": [
      "aat:300006191"
    ],
    "id": 2756319,
    "name:xx": "Welcome Lake"
  }
}
