{
  "geometry": {
    "type": "Point",
    "coordinates": [
      -79.1667,
      40.8167
    ]
  },
  "type": "Feature",
  "properties": {
    "hierarchy": [
      "tgn:2544277",
      "tgn:1000001",
      "tgn:7012149",
      "tgn:7007710",
      "tgn:7029392"
    ],
    "placetype": [
      "aat:300008706"
    ],
    "id": 2544277,
    "name:xx": "North Branch Plum Creek"
  }
}
