{
  "geometry": {
    "type": "Point",
    "coordinates": [
      -73.6333,
      44.3333
    ]
  },
  "type": "Feature",
  "properties": {
    "hierarchy": [
      "tgn:2393381",
      "tgn:1000001",
      "tgn:7012149",
      "tgn:2001461",
      "tgn:7007568",
      "tgn:7029392"
    ],
    "placetype": [
      "aat:300008798"
    ],
    "id": 2393381,
    "name:xx": "Hog Back Mountain"
  }
}
