{
  "geometry": {
    "type": "Point",
    "coordinates": [
      -78.0333,
      40.8333
    ]
  },
  "type": "Feature",
  "properties": {
    "hierarchy": [
      "tgn:2136711",
      "tgn:1000001",
      "tgn:1002249",
      "tgn:7012149",
      "tgn:7007710",
      "tgn:7029392"
    ],
    "placetype": [
      "aat:300008761"
    ],
    "id": 2136711,
    "name:xx": "Ardery Hollow"
  }
}
