{
  "geometry": {
    "type": "Point",
    "coordinates": [
      -111.2333,
      37.0167
    ]
  },
  "type": "Feature",
  "properties": {
    "hierarchy": [
      "tgn:2506850",
      "tgn:1000001",
      "tgn:7012149",
      "tgn:2002119",
      "tgn:7007827",
      "tgn:7029392"
    ],
    "placetype": [
      "aat:300132316"
    ],
    "id": 2506850,
    "name:xx": "Meskin Bar"
  }
}
