{
  "geometry": {
    "type": "Point",
    "coordinates": [
      -73.6833,
      44.75
    ]
  },
  "type": "Feature",
  "properties": {
    "hierarchy": [
      "tgn:2219249",
      "tgn:1000001",
      "tgn:1002284",
      "tgn:7012149",
      "tgn:7007568",
      "tgn:7029392"
    ],
    "placetype": [
      "aat:300008699"
    ],
    "id": 2219249,
    "name:xx": "Canfield Brook"
  }
}
