{
  "type": "FeatureCollection",
  "features": [
    {
      "geometry": {
        "type": "Point",
        "coordinates": [
          -86.1833,
          31.8
        ]
      },
      "type": "Feature",
      "properties": {
        "hierarchy": [
          "tgn:2567130",
          "tgn:7002659",
          "tgn:1000001",
          "tgn:7012149",
          "tgn:2000054",
          "tgn:7029392"
        ],
        "placetype": [
          "aat:300008798"
        ],
        "id": 2567130,
        "name:xx": "Panther Hill"
      }
    },
    {
      "geometry": {
        "type": "Point",
        "coordinates": [
          -91.2833,
          36.1833
        ]
      },
      "type": "Feature",
      "properties": {
        "hierarchy": [
          "tgn:2567131",
          "tgn:1000001",
          "tgn:7016172",
          "tgn:7012149",
          "tgn:2000142",
          "tgn:7029392"
        ],
        "placetype": [
          "aat:300008798"
        ],
        "id": 2567131,
        "name:xx": "Panther Hill"
      }
    },
    {
      "geometry": {
        "type": "Point",
        "coordinates": [
          -91.0167,
          37.3167
        ]
      },
      "type": "Feature",
      "properties": {
        "hierarchy": [
          "tgn:2567132",
          "tgn:1000001",
          "tgn:7012149",
          "tgn:2001236",
          "tgn:7007523",
          "tgn:7029392"
        ],
        "placetype": [
          "aat:300008798"
        ],
        "id": 2567132,
        "name:xx": "Panther Hill"
      }
    },
    {
      "geometry": {
        "type": "Point",
        "coordinates": [
          -104.5333,
          33.6
        ]
      },
      "type": "Feature",
      "properties": {
        "hierarchy": [
          "tgn:2567133",
          "tgn:1000001",
          "tgn:2001430",
          "tgn:7012149",
          "tgn:7007566",
          "tgn:7029392"
        ],
        "placetype": [
          "aat:300008798"
        ],
        "id": 2567133,
        "name:xx": "Panther Hill"
      }
    },
    {
      "geometry": {
        "type": "Point",
        "coordinates": [
          -73.9333,
          44.7833
        ]
      },
      "type": "Feature",
      "properties": {
        "hierarchy": [
          "tgn:2567134",
          "tgn:1000001",
          "tgn:1002284",
          "tgn:7012149",
          "tgn:7007568",
          "tgn:7029392"
        ],
        "placetype": [
          "aat:300008798"
        ],
        "id": 2567134,
        "name:xx": "Panther Hill"
      }
    },
    {
      "geometry": {
        "type": "Point",
        "coordinates": [
          -75.6,
          41.25
        ]
      },
      "type": "Feature",
      "properties": {
        "hierarchy": [
          "tgn:2567135",
          "tgn:1000001",
          "tgn:7012149",
          "tgn:1002564",
          "tgn:7007710",
          "tgn:7029392"
        ],
        "placetype": [
          "aat:300008798"
        ],
        "id": 2567135,
        "name:xx": "Panther Hill"
      }
    },
    {
      "geometry": {
        "type": "Point",
        "coordinates": [
          -99.5333,
          29.6667
        ]
      },
      "type": "Feature",
      "properties": {
        "hierarchy": [
          "tgn:2567136",
          "tgn:1000001",
          "tgn:2001938",
          "tgn:7012149",
          "tgn:7007826",
          "tgn:7029392"
        ],
        "placetype": [
          "aat:300008798"
        ],
        "id": 2567136,
        "name:xx": "Panther Hill"
      }
    },
    {
      "geometry": {
        "type": "Point",
        "coordinates": [
          -91.7167,
          44.9
        ]
      },
      "type": "Feature",
      "properties": {
        "hierarchy": [
          "tgn:2567137",
          "tgn:1000001",
          "tgn:2002319",
          "tgn:7012149",
          "tgn:7007922",
          "tgn:7029392"
        ],
        "placetype": [
          "aat:300008798"
        ],
        "id": 2567137,
        "name:xx": "Panther Hill"
      }
    },
    {
      "geometry": {
        "type": "Point",
        "coordinates": [
          -83.3833,
          36.1833
        ]
      },
      "type": "Feature",
      "properties": {
        "hierarchy": [
          "tgn:2567138",
          "tgn:1000001",
          "tgn:7012149",
          "tgn:2001868",
          "tgn:7007825",
          "tgn:7029392"
        ],
        "placetype": [
          "aat:300008347"
        ],
        "id": 2567138,
        "name:xx": "Panther Hills"
      }
    },
    {
      "geometry": {
        "type": "Point",
        "coordinates": [
          -77.9833,
          40.4333
        ]
      },
      "type": "Feature",
      "properties": {
        "hierarchy": [
          "tgn:2567139",
          "tgn:1000001",
          "tgn:7012149",
          "tgn:1002494",
          "tgn:7007710",
          "tgn:7029392"
        ],
        "placetype": [
          "aat:300008746"
        ],
        "id": 2567139,
        "name:xx": "Panther Hole"
      }
    }
  ]
}
