{
  "geometry": {
    "type": "Point",
    "coordinates": [
      76.883333,
      8.883333
    ]
  },
  "type": "Feature",
  "properties": {
    "hierarchy": [
      "tgn:7548187",
      "tgn:1000004",
      "tgn:7000198",
      "tgn:1001886",
      "tgn:7029392"
    ],
    "placetype": [
      "aat:300008347"
    ],
    "name:en": "Ayūr",
    "id": 7548187
  }
}
