{
  "geometry": {
    "type": "Point",
    "coordinates": [
      -78.3667,
      34.4833
    ]
  },
  "type": "Feature",
  "properties": {
    "hierarchy": [
      "tgn:2340633",
      "tgn:1000001",
      "tgn:2001471",
      "tgn:7012149",
      "tgn:7007709",
      "tgn:7029392"
    ],
    "placetype": [
      "aat:300008706"
    ],
    "id": 2340633,
    "name:xx": "Frenchs Creek"
  }
}
