{
  "geometry": {
    "type": "Point",
    "coordinates": [
      -97.2333,
      44.3667
    ]
  },
  "type": "Feature",
  "properties": {
    "hierarchy": [
      "tgn:2097245",
      "tgn:1000001",
      "tgn:2001808",
      "tgn:7012149",
      "tgn:7007713",
      "tgn:7029392"
    ],
    "placetype": [
      "aat:300008347"
    ],
    "id": 2097245,
    "name:xx": "Hetland"
  }
}
