{
  "geometry": {
    "type": "Point",
    "coordinates": [
      -90.7167,
      29.1833
    ]
  },
  "type": "Feature",
  "properties": {
    "hierarchy": [
      "tgn:2451472",
      "tgn:1000001",
      "tgn:7012149",
      "tgn:2000908",
      "tgn:7007256",
      "tgn:7029392"
    ],
    "placetype": [
      "aat:300008680"
    ],
    "id": 2451472,
    "name:xx": "Little Bay Jose"
  }
}
