{
  "geometry": {
    "type": "Point",
    "coordinates": [
      -84.6833,
      34.6167
    ]
  },
  "type": "Feature",
  "properties": {
    "hierarchy": [
      "tgn:2180502",
      "tgn:1000001",
      "tgn:7012149",
      "tgn:2000396",
      "tgn:7007248",
      "tgn:7029392"
    ],
    "placetype": [
      "aat:300008347"
    ],
    "id": 2180502,
    "name:xx": "Bloodtown"
  }
}
