{
  "geometry": {
    "type": "Point",
    "coordinates": [
      27.728,
      -26.083
    ]
  },
  "type": "Feature",
  "properties": {
    "hierarchy": [
      "tgn:7031955",
      "tgn:7001242",
      "tgn:7017576",
      "tgn:1000193",
      "tgn:7029392"
    ],
    "placetype": [
      "aat:300008181"
    ],
    "id": 7031955,
    "name:xx": "Krugersdorp Wildtuin"
  }
}
