{
  "type": "FeatureCollection",
  "features": [
    {
      "geometry": {
        "type": "Point",
        "coordinates": [
          -105.6167,
          32.65
        ]
      },
      "type": "Feature",
      "properties": {
        "hierarchy": [
          "tgn:2183260",
          "tgn:1000001",
          "tgn:7012149",
          "tgn:2001447",
          "tgn:7007566",
          "tgn:7029392"
        ],
        "placetype": [
          "aat:300008761"
        ],
        "id": 2183260,
        "name:xx": "Bluewater Canyon"
      }
    },
    {
      "geometry": {
        "type": "Point",
        "coordinates": [
          -87.4,
          34.8
        ]
      },
      "type": "Feature",
      "properties": {
        "hierarchy": [
          "tgn:2183261",
          "tgn:1000001",
          "tgn:7012149",
          "tgn:7029392"
        ],
        "placetype": [
          "aat:300008706"
        ],
        "id": 2183261,
        "name:xx": "Bluewater Creek"
      }
    },
    {
      "geometry": {
        "type": "Point",
        "coordinates": [
          -83.0333,
          32.35
        ]
      },
      "type": "Feature",
      "properties": {
        "hierarchy": [
          "tgn:2183262",
          "tgn:1000001",
          "tgn:7012149",
          "tgn:2000378",
          "tgn:7007248",
          "tgn:7029392"
        ],
        "placetype": [
          "aat:300008706"
        ],
        "id": 2183262,
        "name:xx": "Bluewater Creek"
      }
    },
    {
      "geometry": {
        "type": "Point",
        "coordinates": [
          -90.4167,
          36.9167
        ]
      },
      "type": "Feature",
      "properties": {
        "hierarchy": [
          "tgn:2183263",
          "tgn:1000001",
          "tgn:7012149",
          "tgn:7007523",
          "tgn:7029392"
        ],
        "placetype": [
          "aat:300008706"
        ],
        "id": 2183263,
        "name:xx": "Bluewater Creek"
      }
    },
    {
      "geometry": {
        "type": "Point",
        "coordinates": [
          -108.6667,
          45.3
        ]
      },
      "type": "Feature",
      "properties": {
        "hierarchy": [
          "tgn:2183264",
          "tgn:1000001",
          "tgn:7012149",
          "tgn:7007524",
          "tgn:7029392"
        ],
        "placetype": [
          "aat:300008706"
        ],
        "id": 2183264,
        "name:xx": "Bluewater Creek"
      }
    },
    {
      "geometry": {
        "type": "Point",
        "coordinates": [
          -105.6167,
          32.65
        ]
      },
      "type": "Feature",
      "properties": {
        "hierarchy": [
          "tgn:2183265",
          "tgn:1000001",
          "tgn:7012149",
          "tgn:7007566",
          "tgn:7029392"
        ],
        "placetype": [
          "aat:300008706"
        ],
        "id": 2183265,
        "name:xx": "Bluewater Creek"
      }
    },
    {
      "geometry": {
        "type": "Point",
        "coordinates": [
          -105.2,
          33.5667
        ]
      },
      "type": "Feature",
      "properties": {
        "hierarchy": [
          "tgn:2183266",
          "tgn:1000001",
          "tgn:7012149",
          "tgn:2001442",
          "tgn:7007566",
          "tgn:7029392"
        ],
        "placetype": [
          "aat:300008706"
        ],
        "id": 2183266,
        "name:xx": "Bluewater Creek"
      }
    },
    {
      "geometry": {
        "type": "Point",
        "coordinates": [
          -103.8333,
          35.0667
        ]
      },
      "type": "Feature",
      "properties": {
        "hierarchy": [
          "tgn:2183267",
          "tgn:1000001",
          "tgn:7012149",
          "tgn:2001448",
          "tgn:7007566",
          "tgn:7029392"
        ],
        "placetype": [
          "aat:300008706"
        ],
        "id": 2183267,
        "name:xx": "Bluewater Creek"
      }
    },
    {
      "geometry": {
        "type": "Point",
        "coordinates": [
          -108.3,
          35.1667
        ]
      },
      "type": "Feature",
      "properties": {
        "hierarchy": [
          "tgn:2183268",
          "tgn:1000001",
          "tgn:2001431",
          "tgn:7012149",
          "tgn:7007566",
          "tgn:7029392"
        ],
        "placetype": [
          "aat:300008706"
        ],
        "id": 2183268,
        "name:xx": "Bluewater Creek"
      }
    }
  ]
}
