{
  "geometry": {
    "type": "Point",
    "coordinates": [
      -87.25,
      35.8833
    ]
  },
  "type": "Feature",
  "properties": {
    "hierarchy": [
      "tgn:2350181",
      "tgn:1000001",
      "tgn:7012149",
      "tgn:7015666",
      "tgn:7007825",
      "tgn:7029392"
    ],
    "placetype": [
      "aat:300008699"
    ],
    "id": 2350181,
    "name:xx": "Gin Branch"
  }
}
