{
  "geometry": {
    "type": "Point",
    "coordinates": [
      45.3333,
      4.4167
    ]
  },
  "type": "Feature",
  "properties": {
    "hierarchy": [
      "tgn:1092723",
      "tgn:7001242",
      "tgn:1001681",
      "tgn:1000192",
      "tgn:7029392"
    ],
    "placetype": [
      "aat:300008347"
    ],
    "id": 1092723,
    "name:xx": "Jiiqley"
  }
}
