{
  "geometry": {
    "type": "Point",
    "coordinates": [
      -81.7333,
      36.2333
    ]
  },
  "type": "Feature",
  "properties": {
    "hierarchy": [
      "tgn:2472854",
      "tgn:1000001",
      "tgn:7012149",
      "tgn:2001551",
      "tgn:7007709",
      "tgn:7029392"
    ],
    "placetype": [
      "aat:300008347"
    ],
    "id": 2472854,
    "name:xx": "Lovill"
  }
}
