{
  "geometry": {
    "type": "Point",
    "coordinates": [
      -121.4667,
      47.6667
    ]
  },
  "type": "Feature",
  "properties": {
    "hierarchy": [
      "tgn:2352270",
      "tgn:1000001",
      "tgn:7012149",
      "tgn:7018871",
      "tgn:7007920",
      "tgn:7029392"
    ],
    "placetype": [
      "aat:300386845"
    ],
    "id": 2352270,
    "name:xx": "Goat Basin"
  }
}
