{
  "geometry": {
    "type": "Point",
    "coordinates": [
      -80.7667,
      38.75
    ]
  },
  "type": "Feature",
  "properties": {
    "hierarchy": [
      "tgn:2461844",
      "tgn:1000001",
      "tgn:2002256",
      "tgn:7012149",
      "tgn:7013961",
      "tgn:7029392"
    ],
    "placetype": [
      "aat:300008699"
    ],
    "id": 2461844,
    "name:xx": "Little Trace Run"
  }
}
