{
  "geometry": {
    "type": "Point",
    "coordinates": [
      -124.0333,
      42.6833
    ]
  },
  "type": "Feature",
  "properties": {
    "hierarchy": [
      "tgn:2172610",
      "tgn:1000001",
      "tgn:7012149",
      "tgn:7007708",
      "tgn:7029392"
    ],
    "placetype": [
      "aat:300008706"
    ],
    "id": 2172610,
    "name:xx": "Billings Creek"
  }
}
