{
  "geometry": {
    "type": "Point",
    "coordinates": [
      -84.35,
      35.65
    ]
  },
  "type": "Feature",
  "properties": {
    "hierarchy": [
      "tgn:2608958",
      "tgn:1000001",
      "tgn:7012149",
      "tgn:2001889",
      "tgn:7007825",
      "tgn:7029392"
    ],
    "placetype": [
      "aat:300008706"
    ],
    "id": 2608958,
    "name:xx": "Rausin Creek"
  }
}
