{
  "geometry": {
    "type": "Point",
    "coordinates": [
      -90.5667,
      39.8667
    ]
  },
  "type": "Feature",
  "properties": {
    "hierarchy": [
      "tgn:2172627",
      "tgn:1000001",
      "tgn:7012149",
      "tgn:1002693",
      "tgn:7007251",
      "tgn:7029392"
    ],
    "placetype": [
      "aat:300008680"
    ],
    "id": 2172627,
    "name:xx": "Billings Lake"
  }
}
