{
  "geometry": {
    "type": "Point",
    "coordinates": [
      -119.2833,
      36.95
    ]
  },
  "type": "Feature",
  "properties": {
    "hierarchy": [
      "tgn:2192545",
      "tgn:1000001",
      "tgn:7012149",
      "tgn:1002392",
      "tgn:7007157",
      "tgn:7029392"
    ],
    "placetype": [
      "aat:300008798"
    ],
    "id": 2192545,
    "name:xx": "Branford Mountain"
  }
}
