{
  "geometry": {
    "type": "Point",
    "coordinates": [
      -93.4667,
      42.4833
    ]
  },
  "type": "Feature",
  "properties": {
    "hierarchy": [
      "tgn:2165911",
      "tgn:1000001",
      "tgn:2000602",
      "tgn:7012149",
      "tgn:7007253",
      "tgn:7029392"
    ],
    "placetype": [
      "aat:300006075"
    ],
    "id": 2165911,
    "name:xx": "Big 4 Drainage Ditch"
  }
}
