{
  "geometry": {
    "type": "Point",
    "coordinates": [
      -124.5833,
      48.3667
    ]
  },
  "type": "Feature",
  "properties": {
    "hierarchy": [
      "tgn:2141634",
      "tgn:1000001",
      "tgn:1002271",
      "tgn:7012149",
      "tgn:7007920",
      "tgn:7029392"
    ],
    "placetype": [
      "aat:300008850"
    ],
    "id": 2141634,
    "name:xx": "Baada Point"
  }
}
