{
  "geometry": {
    "type": "Point",
    "coordinates": [
      -158.1167,
      62.0333
    ]
  },
  "type": "Feature",
  "properties": {
    "hierarchy": [
      "tgn:2673827",
      "tgn:7006450",
      "tgn:1000001",
      "tgn:7012149",
      "tgn:2000089",
      "tgn:7029392"
    ],
    "placetype": [
      "aat:300008761"
    ],
    "id": 2673827,
    "name:xx": "Snow Gulch"
  }
}
