{
  "geometry": {
    "type": "Point",
    "coordinates": [
      -88.1667,
      32.75
    ]
  },
  "type": "Feature",
  "properties": {
    "hierarchy": [
      "tgn:2274258",
      "tgn:7002659",
      "tgn:1000001",
      "tgn:7012149",
      "tgn:2000059",
      "tgn:7029392"
    ],
    "placetype": [
      "aat:300006191"
    ],
    "id": 2274258,
    "name:xx": "Daisy Falls Lake"
  }
}
