{
  "type": "FeatureCollection",
  "features": [
    {
      "geometry": {
        "type": "Point",
        "coordinates": [
          14.25,
          52.633333
        ]
      },
      "type": "Feature",
      "properties": {
        "hierarchy": [
          "tgn:7124410",
          "tgn:7000096",
          "tgn:1000003",
          "tgn:7000084",
          "tgn:7029392"
        ],
        "placetype": [
          "aat:300055621"
        ],
        "id": 7124410,
        "name:xx": "Neuhardenberger Loose"
      }
    },
    {
      "geometry": {
        "type": "Point",
        "coordinates": [
          14.2,
          52.616667
        ]
      },
      "type": "Feature",
      "properties": {
        "hierarchy": [
          "tgn:7124411",
          "tgn:7000096",
          "tgn:1000003",
          "tgn:7000084",
          "tgn:7029392"
        ],
        "placetype": [
          "aat:300008863"
        ],
        "id": 7124411,
        "name:xx": "Neuhardenberger, Forst"
      }
    },
    {
      "geometry": {
        "type": "Point",
        "coordinates": [
          14.25,
          52.6
        ]
      },
      "type": "Feature",
      "properties": {
        "hierarchy": [
          "tgn:7124412",
          "tgn:7000096",
          "tgn:1000003",
          "tgn:7000084",
          "tgn:7029392"
        ],
        "placetype": [
          "aat:300008347"
        ],
        "id": 7124412,
        "name:xx": "Marxwalde"
      }
    },
    {
      "geometry": {
        "type": "Point",
        "coordinates": [
          7.916667,
          52.633333
        ]
      },
      "type": "Feature",
      "properties": {
        "hierarchy": [
          "tgn:7124413",
          "tgn:1000003",
          "tgn:7003676",
          "tgn:7000084",
          "tgn:7029392"
        ],
        "placetype": [
          "aat:300000206"
        ],
        "id": 7124413,
        "name:xx": "Neu Hammerstein"
      }
    },
    {
      "geometry": {
        "type": "Point",
        "coordinates": [
          14.8,
          51.4
        ]
      },
      "type": "Feature",
      "properties": {
        "hierarchy": [
          "tgn:7124414",
          "tgn:1000003",
          "tgn:7003685",
          "tgn:7000084",
          "tgn:7029392"
        ],
        "placetype": [
          "aat:300008347"
        ],
        "id": 7124414,
        "name:xx": "Neuhammer"
      }
    },
    {
      "geometry": {
        "type": "Point",
        "coordinates": [
          12.183333,
          50.7
        ]
      },
      "type": "Feature",
      "properties": {
        "hierarchy": [
          "tgn:7124415",
          "tgn:1000003",
          "tgn:7003689",
          "tgn:7000084",
          "tgn:7029392"
        ],
        "placetype": [
          "aat:300008347"
        ],
        "id": 7124415,
        "name:xx": "Neuhammer"
      }
    },
    {
      "geometry": {
        "type": "Point",
        "coordinates": [
          11,
          50.5
        ]
      },
      "type": "Feature",
      "properties": {
        "hierarchy": [
          "tgn:7124416",
          "tgn:1000003",
          "tgn:7003689",
          "tgn:7000084",
          "tgn:7029392"
        ],
        "placetype": [
          "aat:300008347"
        ],
        "id": 7124416,
        "name:xx": "Neuhammer"
      }
    },
    {
      "geometry": {
        "type": "Point",
        "coordinates": [
          8.033333,
          49.533333
        ]
      },
      "type": "Feature",
      "properties": {
        "hierarchy": [
          "tgn:7124417",
          "tgn:1000003",
          "tgn:7003682",
          "tgn:7000084",
          "tgn:7029392"
        ],
        "placetype": [
          "aat:300008347"
        ],
        "id": 7124417,
        "name:xx": "Neuhamer"
      }
    },
    {
      "geometry": {
        "type": "Point",
        "coordinates": [
          12.75,
          49.1
        ]
      },
      "type": "Feature",
      "properties": {
        "hierarchy": [
          "tgn:7124418",
          "tgn:7003669",
          "tgn:1000003",
          "tgn:7000084",
          "tgn:7029392"
        ],
        "placetype": [
          "aat:300000206"
        ],
        "id": 7124418,
        "name:xx": "Neuhammer"
      }
    },
    {
      "geometry": {
        "type": "Point",
        "coordinates": [
          8.45,
          53.516667
        ]
      },
      "type": "Feature",
      "properties": {
        "hierarchy": [
          "tgn:7124419",
          "tgn:1000003",
          "tgn:7003676",
          "tgn:7000084",
          "tgn:7029392"
        ],
        "placetype": [
          "aat:300000206"
        ],
        "id": 7124419,
        "name:xx": "Neuhamm"
      }
    }
  ]
}
