{
  "geometry": {
    "type": "Point",
    "coordinates": [
      -99.914444,
      26.9925
    ]
  },
  "type": "Feature",
  "properties": {
    "hierarchy": [
      "tgn:7419388",
      "tgn:1000001",
      "tgn:7005589",
      "tgn:7005560",
      "tgn:7029392"
    ],
    "placetype": [
      "aat:300008699"
    ],
    "id": 7419388,
    "name:es": "Salado, Río"
  }
}
