{
  "geometry": {
    "type": "Point",
    "coordinates": [
      -95.6833,
      37.75
    ]
  },
  "type": "Feature",
  "properties": {
    "hierarchy": [
      "tgn:2180579",
      "tgn:1000001",
      "tgn:7012149",
      "tgn:7007254",
      "tgn:7029392"
    ],
    "placetype": [
      "aat:300008699"
    ],
    "id": 2180579,
    "name:xx": "Bloody Run"
  }
}
