{
  "geometry": {
    "type": "Point",
    "coordinates": [
      1.9667,
      50.4833
    ]
  },
  "type": "Feature",
  "properties": {
    "hierarchy": [
      "tgn:1033011",
      "tgn:1000003",
      "tgn:7001097",
      "tgn:1000070",
      "tgn:7029392"
    ],
    "placetype": [
      "aat:300008347"
    ],
    "id": 1033011,
    "name:xx": "Embry"
  }
}
