{
  "geometry": {
    "type": "Point",
    "coordinates": [
      34.5833,
      58.5167
    ]
  },
  "type": "Feature",
  "properties": {
    "hierarchy": [
      "tgn:1057054",
      "tgn:1000004",
      "tgn:4008031",
      "tgn:7018214",
      "tgn:7002435",
      "tgn:7029392"
    ],
    "placetype": [
      "aat:300008347"
    ],
    "id": 1057054,
    "name:xx": "Moshenskoye"
  }
}
