{
  "type": "FeatureCollection",
  "features": [
    {
      "geometry": {
        "type": "Point",
        "coordinates": [
          -86.85,
          33.15
        ]
      },
      "type": "Feature",
      "properties": {
        "hierarchy": [
          "tgn:2005592",
          "tgn:7002659",
          "tgn:1000001",
          "tgn:7012149",
          "tgn:2000058",
          "tgn:7029392"
        ],
        "placetype": [
          "aat:300008347"
        ],
        "id": 2005592,
        "name:xx": "Underwood"
      }
    },
    {
      "geometry": {
        "type": "Point",
        "coordinates": [
          -87.5167,
          34.75
        ]
      },
      "type": "Feature",
      "properties": {
        "hierarchy": [
          "tgn:2005593",
          "tgn:7002659",
          "tgn:1000001",
          "tgn:2000016",
          "tgn:7012149",
          "tgn:7029392"
        ],
        "placetype": [
          "aat:300008347",
          "aat:300387210"
        ],
        "id": 2005593,
        "name:xx": "Underwood Crossroads"
      }
    },
    {
      "geometry": {
        "type": "Point",
        "coordinates": [
          -86.2,
          34.15
        ]
      },
      "type": "Feature",
      "properties": {
        "hierarchy": [
          "tgn:2005595",
          "tgn:7002659",
          "tgn:1000001",
          "tgn:7012149",
          "tgn:2000027",
          "tgn:7029392"
        ],
        "placetype": [
          "aat:300008347",
          "aat:300387210"
        ],
        "id": 2005595,
        "name:xx": "Union"
      }
    },
    {
      "geometry": {
        "type": "Point",
        "coordinates": [
          -85.1833,
          31.5167
        ]
      },
      "type": "Feature",
      "properties": {
        "hierarchy": [
          "tgn:2005596",
          "tgn:7002659",
          "tgn:1000001",
          "tgn:7012149",
          "tgn:2000033",
          "tgn:7029392"
        ],
        "placetype": [
          "aat:300008347",
          "aat:300387210"
        ],
        "id": 2005596,
        "name:xx": "Union"
      }
    },
    {
      "geometry": {
        "type": "Point",
        "coordinates": [
          -87.9,
          32.9833
        ]
      },
      "type": "Feature",
      "properties": {
        "hierarchy": [
          "tgn:2005597",
          "tgn:7002659",
          "tgn:1000001",
          "tgn:7012149",
          "tgn:2000031",
          "tgn:7029392"
        ],
        "placetype": [
          "aat:300008347"
        ],
        "id": 2005597,
        "name:xx": "Union"
      }
    },
    {
      "geometry": {
        "type": "Point",
        "coordinates": [
          -85.8333,
          32.6833
        ]
      },
      "type": "Feature",
      "properties": {
        "hierarchy": [
          "tgn:2005598",
          "tgn:7002659",
          "tgn:1000001",
          "tgn:7012149",
          "tgn:2000061",
          "tgn:7029392"
        ],
        "placetype": [
          "aat:300008347",
          "aat:300387210"
        ],
        "id": 2005598,
        "name:xx": "Union"
      }
    },
    {
      "geometry": {
        "type": "Point",
        "coordinates": [
          -86.7333,
          34.45
        ]
      },
      "type": "Feature",
      "properties": {
        "hierarchy": [
          "tgn:2005599",
          "tgn:7002659",
          "tgn:1000001",
          "tgn:7012149",
          "tgn:2000051",
          "tgn:7029392"
        ],
        "placetype": [
          "aat:300008347",
          "aat:300387210"
        ],
        "id": 2005599,
        "name:xx": "Union"
      }
    }
  ]
}
