{
  "geometry": {
    "type": "Point",
    "coordinates": [
      -87.85,
      34.55
    ]
  },
  "type": "Feature",
  "properties": {
    "hierarchy": [
      "tgn:2507856",
      "tgn:7002659",
      "tgn:1000001",
      "tgn:7012149",
      "tgn:2000029",
      "tgn:7029392"
    ],
    "placetype": [
      "aat:300008699"
    ],
    "id": 2507856,
    "name:xx": "Mickins Branch"
  }
}
