{
  "type": "FeatureCollection",
  "features": [
    {
      "geometry": {
        "type": "Point",
        "coordinates": [
          8.366667,
          52.9
        ]
      },
      "type": "Feature",
      "properties": {
        "hierarchy": [
          "tgn:7063521",
          "tgn:1000003",
          "tgn:7003676",
          "tgn:7000084",
          "tgn:7029392"
        ],
        "placetype": [
          "aat:300008347"
        ],
        "id": 7063521,
        "name:xx": "Aumühle"
      }
    },
    {
      "geometry": {
        "type": "Point",
        "coordinates": [
          13.3,
          48.416667
        ]
      },
      "type": "Feature",
      "properties": {
        "hierarchy": [
          "tgn:7063522",
          "tgn:7003669",
          "tgn:1000003",
          "tgn:7000084",
          "tgn:7029392"
        ],
        "placetype": [
          "aat:300008347"
        ],
        "id": 7063522,
        "name:xx": "Aumühle"
      }
    },
    {
      "geometry": {
        "type": "Point",
        "coordinates": [
          12.9,
          48.216667
        ]
      },
      "type": "Feature",
      "properties": {
        "hierarchy": [
          "tgn:7063523",
          "tgn:7003669",
          "tgn:1000003",
          "tgn:7000084",
          "tgn:7029392"
        ],
        "placetype": [
          "aat:300000206"
        ],
        "id": 7063523,
        "name:xx": "Aumühle"
      }
    },
    {
      "geometry": {
        "type": "Point",
        "coordinates": [
          8.25,
          50.4
        ]
      },
      "type": "Feature",
      "properties": {
        "hierarchy": [
          "tgn:7063524",
          "tgn:1000003",
          "tgn:7003678",
          "tgn:7000084",
          "tgn:7029392"
        ],
        "placetype": [
          "aat:300008347"
        ],
        "id": 7063524,
        "name:xx": "Aumenau"
      }
    },
    {
      "geometry": {
        "type": "Point",
        "coordinates": [
          12.416667,
          49.05
        ]
      },
      "type": "Feature",
      "properties": {
        "hierarchy": [
          "tgn:7063525",
          "tgn:7003669",
          "tgn:1000003",
          "tgn:7000084",
          "tgn:7029392"
        ],
        "placetype": [
          "aat:300000206"
        ],
        "id": 7063525,
        "name:xx": "Aumbrunn"
      }
    },
    {
      "geometry": {
        "type": "Point",
        "coordinates": [
          12.433333,
          49.05
        ]
      },
      "type": "Feature",
      "properties": {
        "hierarchy": [
          "tgn:7063526",
          "tgn:7003669",
          "tgn:1000003",
          "tgn:7000084",
          "tgn:7029392"
        ],
        "placetype": [
          "aat:300008347"
        ],
        "id": 7063526,
        "name:xx": "Aumbach"
      }
    },
    {
      "geometry": {
        "type": "Point",
        "coordinates": [
          13.216667,
          48.416667
        ]
      },
      "type": "Feature",
      "properties": {
        "hierarchy": [
          "tgn:7063527",
          "tgn:7003669",
          "tgn:1000003",
          "tgn:7000084",
          "tgn:7029392"
        ],
        "placetype": [
          "aat:300000206"
        ],
        "id": 7063527,
        "name:xx": "Aumann"
      }
    },
    {
      "geometry": {
        "type": "Point",
        "coordinates": [
          12.066667,
          50.766667
        ]
      },
      "type": "Feature",
      "properties": {
        "hierarchy": [
          "tgn:7063528",
          "tgn:1000003",
          "tgn:7003689",
          "tgn:7000084",
          "tgn:7029392"
        ],
        "placetype": [
          "aat:300008699"
        ],
        "id": 7063528,
        "name:xx": "Auma"
      }
    }
  ]
}
