{
  "geometry": {
    "type": "Point",
    "coordinates": [
      69.6667,
      58.75
    ]
  },
  "type": "Feature",
  "properties": {
    "hierarchy": [
      "tgn:1052350",
      "tgn:1000004",
      "tgn:1003413",
      "tgn:7018214",
      "tgn:7002435",
      "tgn:7029392"
    ],
    "placetype": [
      "aat:300008347"
    ],
    "id": 1052350,
    "name:xx": "Atnis"
  }
}
