{
  "geometry": {
    "type": "Point",
    "coordinates": [
      -115.5667,
      51.1667
    ]
  },
  "type": "Feature",
  "properties": {
    "hierarchy": [
      "tgn:7013004",
      "tgn:7005694",
      "tgn:7005685",
      "tgn:1000001",
      "tgn:7029392"
    ],
    "placetype": [
      "aat:300008347",
      "aat:300008375",
      "aat:300387291"
    ],
    "id": 7013004,
    "name:xx": "Banff"
  }
}
