{
  "geometry": {
    "type": "Point",
    "coordinates": [
      14.7167,
      55.1167
    ]
  },
  "type": "Feature",
  "properties": {
    "hierarchy": [
      "tgn:7003585",
      "tgn:7594005",
      "tgn:1000003",
      "tgn:1000066",
      "tgn:7029392"
    ],
    "placetype": [
      "aat:300008347",
      "aat:300008416",
      "aat:300387511",
      "aat:300008375"
    ],
    "name:da": "Rønne",
    "id": 7003585
  }
}
