{
  "geometry": {
    "type": "Point",
    "coordinates": [
      -85.2667,
      46.5167
    ]
  },
  "type": "Feature",
  "properties": {
    "hierarchy": [
      "tgn:2171347",
      "tgn:1000001",
      "tgn:7012149",
      "tgn:2000972",
      "tgn:7007520",
      "tgn:7029392"
    ],
    "placetype": [
      "aat:300008697"
    ],
    "id": 2171347,
    "name:xx": "Big Spring, The"
  }
}
