{
  "geometry": {
    "type": "Point",
    "coordinates": [
      -100.7833,
      34.7333
    ]
  },
  "type": "Feature",
  "properties": {
    "hierarchy": [
      "tgn:2590867",
      "tgn:1000001",
      "tgn:7012149",
      "tgn:2001995",
      "tgn:7007826",
      "tgn:7029392"
    ],
    "placetype": [
      "aat:300008706"
    ],
    "id": 2590867,
    "name:xx": "Polecat Creek"
  }
}
