{
  "type": "FeatureCollection",
  "features": [
    {
      "geometry": {
        "type": "Point",
        "coordinates": [
          -123.05,
          48.1
        ]
      },
      "type": "Feature",
      "properties": {
        "hierarchy": [
          "tgn:2362260",
          "tgn:1000001",
          "tgn:1002271",
          "tgn:7012149",
          "tgn:7007920",
          "tgn:7029392"
        ],
        "placetype": [
          "aat:300008905"
        ],
        "id": 2362260,
        "name:xx": "Grays Marsh"
      }
    },
    {
      "geometry": {
        "type": "Point",
        "coordinates": [
          -89.7833,
          43.7833
        ]
      },
      "type": "Feature",
      "properties": {
        "hierarchy": [
          "tgn:2362261",
          "tgn:2002305",
          "tgn:1000001",
          "tgn:7012149",
          "tgn:7007922",
          "tgn:7029392"
        ],
        "placetype": [
          "aat:300008905"
        ],
        "id": 2362261,
        "name:xx": "Grays Marsh"
      }
    },
    {
      "geometry": {
        "type": "Point",
        "coordinates": [
          -71.1167,
          41.55
        ]
      },
      "type": "Feature",
      "properties": {
        "hierarchy": [
          "tgn:2362262",
          "tgn:1000001",
          "tgn:7012149",
          "tgn:7029392"
        ],
        "placetype": [
          "aat:300008680"
        ],
        "id": 2362262,
        "name:xx": "Grays Mill Pond"
      }
    },
    {
      "geometry": {
        "type": "Point",
        "coordinates": [
          -71.1167,
          41.55
        ]
      },
      "type": "Feature",
      "properties": {
        "hierarchy": [
          "tgn:2362263",
          "tgn:1002716",
          "tgn:1000001",
          "tgn:7012149",
          "tgn:7007711",
          "tgn:7029392"
        ],
        "placetype": [
          "aat:300008680"
        ],
        "id": 2362263,
        "name:xx": "Grays Mill Pond"
      }
    },
    {
      "geometry": {
        "type": "Point",
        "coordinates": [
          -76.1667,
          43.4
        ]
      },
      "type": "Feature",
      "properties": {
        "hierarchy": [
          "tgn:2362264",
          "tgn:1000001",
          "tgn:7012149",
          "tgn:1002758",
          "tgn:7007568",
          "tgn:7029392"
        ],
        "placetype": [
          "aat:300006191"
        ],
        "id": 2362264,
        "name:xx": "Grays Millpond"
      }
    },
    {
      "geometry": {
        "type": "Point",
        "coordinates": [
          -77.65,
          35.35
        ]
      },
      "type": "Feature",
      "properties": {
        "hierarchy": [
          "tgn:2362265",
          "tgn:1000001",
          "tgn:7012149",
          "tgn:2001499",
          "tgn:7007709",
          "tgn:7029392"
        ],
        "placetype": [
          "aat:300006191"
        ],
        "id": 2362265,
        "name:xx": "Grays Millpond"
      }
    },
    {
      "geometry": {
        "type": "Point",
        "coordinates": [
          -70.3667,
          44.5833
        ]
      },
      "type": "Feature",
      "properties": {
        "hierarchy": [
          "tgn:2362266",
          "tgn:1000001",
          "tgn:2000921",
          "tgn:7012149",
          "tgn:7007515",
          "tgn:7029392"
        ],
        "placetype": [
          "aat:300008798"
        ],
        "id": 2362266,
        "name:xx": "Grays Mountain"
      }
    },
    {
      "geometry": {
        "type": "Point",
        "coordinates": [
          -74.75,
          42.1667
        ]
      },
      "type": "Feature",
      "properties": {
        "hierarchy": [
          "tgn:2362267",
          "tgn:1000001",
          "tgn:1002328",
          "tgn:7012149",
          "tgn:7007568",
          "tgn:7029392"
        ],
        "placetype": [
          "aat:300008798"
        ],
        "id": 2362267,
        "name:xx": "Grays Mountain"
      }
    },
    {
      "geometry": {
        "type": "Point",
        "coordinates": [
          -123.9,
          45.5833
        ]
      },
      "type": "Feature",
      "properties": {
        "hierarchy": [
          "tgn:2362268",
          "tgn:1000001",
          "tgn:7012149",
          "tgn:1002943",
          "tgn:7007708",
          "tgn:7029392"
        ],
        "placetype": [
          "aat:300008798"
        ],
        "id": 2362268,
        "name:xx": "Grays Mountain"
      }
    },
    {
      "geometry": {
        "type": "Point",
        "coordinates": [
          -72.1167,
          44.6333
        ]
      },
      "type": "Feature",
      "properties": {
        "hierarchy": [
          "tgn:2362269",
          "tgn:2002131",
          "tgn:1000001",
          "tgn:7012149",
          "tgn:7007828",
          "tgn:7029392"
        ],
        "placetype": [
          "aat:300008798"
        ],
        "id": 2362269,
        "name:xx": "Grays Mountain"
      }
    }
  ]
}
