{
  "geometry": {
    "type": "Point",
    "coordinates": [
      -98.2667,
      31.1167
    ]
  },
  "type": "Feature",
  "properties": {
    "hierarchy": [
      "tgn:2223774",
      "tgn:1000001",
      "tgn:7012149",
      "tgn:2002026",
      "tgn:7007826",
      "tgn:7029392"
    ],
    "placetype": [
      "aat:300008798"
    ],
    "id": 2223774,
    "name:xx": "Carter Mountains"
  }
}
