{
  "geometry": {
    "type": "Point",
    "coordinates": [
      -122.7667,
      47.1833
    ]
  },
  "type": "Feature",
  "properties": {
    "hierarchy": [
      "tgn:2712496",
      "tgn:1000001",
      "tgn:7012149",
      "tgn:1002785",
      "tgn:7007920",
      "tgn:7029392"
    ],
    "placetype": [
      "aat:300132316"
    ],
    "id": 2712496,
    "name:xx": "Taylor Bay"
  }
}
