{
  "type": "FeatureCollection",
  "features": [
    {
      "geometry": {
        "type": "Point",
        "coordinates": [
          -113.9,
          47.0167
        ]
      },
      "type": "Feature",
      "properties": {
        "hierarchy": [
          "tgn:2223730",
          "tgn:1000001",
          "tgn:7012149",
          "tgn:2001291",
          "tgn:7007524",
          "tgn:7029392"
        ],
        "placetype": [
          "aat:300008680"
        ],
        "id": 2223730,
        "name:xx": "Carter Lake"
      }
    },
    {
      "geometry": {
        "type": "Point",
        "coordinates": [
          -113.9,
          47.0167
        ]
      },
      "type": "Feature",
      "properties": {
        "hierarchy": [
          "tgn:2223731",
          "tgn:1000001",
          "tgn:7012149",
          "tgn:2001291",
          "tgn:7007524",
          "tgn:7029392"
        ],
        "placetype": [
          "aat:300006191"
        ],
        "id": 2223731,
        "name:xx": "Carter Lake"
      }
    },
    {
      "geometry": {
        "type": "Point",
        "coordinates": [
          -107.45,
          48.6
        ]
      },
      "type": "Feature",
      "properties": {
        "hierarchy": [
          "tgn:2223732",
          "tgn:1000001",
          "tgn:7012149",
          "tgn:2001295",
          "tgn:7007524",
          "tgn:7029392"
        ],
        "placetype": [
          "aat:300008680"
        ],
        "id": 2223732,
        "name:xx": "Carter Lake"
      }
    },
    {
      "geometry": {
        "type": "Point",
        "coordinates": [
          -95.9167,
          41.3
        ]
      },
      "type": "Feature",
      "properties": {
        "hierarchy": [
          "tgn:2223733",
          "tgn:1000001",
          "tgn:2001343",
          "tgn:7012149",
          "tgn:7007525",
          "tgn:7029392"
        ],
        "placetype": [
          "aat:300008680"
        ],
        "id": 2223733,
        "name:xx": "Carter Lake"
      }
    },
    {
      "geometry": {
        "type": "Point",
        "coordinates": [
          -95.9,
          41.3
        ]
      },
      "type": "Feature",
      "properties": {
        "hierarchy": [
          "tgn:2223734",
          "tgn:1000001",
          "tgn:7012149",
          "tgn:7029392"
        ],
        "placetype": [
          "aat:300008680"
        ],
        "id": 2223734,
        "name:xx": "Carter Lake"
      }
    },
    {
      "geometry": {
        "type": "Point",
        "coordinates": [
          -79.7167,
          35.6833
        ]
      },
      "type": "Feature",
      "properties": {
        "hierarchy": [
          "tgn:2223735",
          "tgn:1000001",
          "tgn:7012149",
          "tgn:2001532",
          "tgn:7007709",
          "tgn:7029392"
        ],
        "placetype": [
          "aat:300006191"
        ],
        "id": 2223735,
        "name:xx": "Carter Lake"
      }
    },
    {
      "geometry": {
        "type": "Point",
        "coordinates": [
          -79.8167,
          36.2333
        ]
      },
      "type": "Feature",
      "properties": {
        "hierarchy": [
          "tgn:2223736",
          "tgn:1000001",
          "tgn:7012149",
          "tgn:2001500",
          "tgn:7007709",
          "tgn:7029392"
        ],
        "placetype": [
          "aat:300006191"
        ],
        "id": 2223736,
        "name:xx": "Carter Lake"
      }
    },
    {
      "geometry": {
        "type": "Point",
        "coordinates": [
          -84.35,
          39.2667
        ]
      },
      "type": "Feature",
      "properties": {
        "hierarchy": [
          "tgn:2223737",
          "tgn:1000001",
          "tgn:7012149",
          "tgn:1002441",
          "tgn:7007706",
          "tgn:7029392"
        ],
        "placetype": [
          "aat:300008680"
        ],
        "id": 2223737,
        "name:xx": "Carter Lake"
      }
    },
    {
      "geometry": {
        "type": "Point",
        "coordinates": [
          -81.4167,
          41.1167
        ]
      },
      "type": "Feature",
      "properties": {
        "hierarchy": [
          "tgn:2223738",
          "tgn:1000001",
          "tgn:7012149",
          "tgn:1002928",
          "tgn:7007706",
          "tgn:7029392"
        ],
        "placetype": [
          "aat:300006191"
        ],
        "id": 2223738,
        "name:xx": "Carter Lake"
      }
    },
    {
      "geometry": {
        "type": "Point",
        "coordinates": [
          -94.7167,
          35.1833
        ]
      },
      "type": "Feature",
      "properties": {
        "hierarchy": [
          "tgn:2223739",
          "tgn:1000001",
          "tgn:7012149",
          "tgn:2001662",
          "tgn:7007707",
          "tgn:7029392"
        ],
        "placetype": [
          "aat:300008680"
        ],
        "id": 2223739,
        "name:xx": "Carter Lake"
      }
    }
  ]
}
