{
  "geometry": {
    "type": "Point",
    "coordinates": [
      -73.9667,
      44.7167
    ]
  },
  "type": "Feature",
  "properties": {
    "hierarchy": [
      "tgn:2411925",
      "tgn:1000001",
      "tgn:1002284",
      "tgn:7012149",
      "tgn:7007568",
      "tgn:7029392"
    ],
    "placetype": [
      "aat:300008850"
    ],
    "id": 2411925,
    "name:xx": "Indian Point"
  }
}
