{
  "geometry": {
    "type": "Point",
    "coordinates": [
      32.8167,
      47.8333
    ]
  },
  "type": "Feature",
  "properties": {
    "hierarchy": [
      "tgn:1055189",
      "tgn:1000003",
      "tgn:7011665",
      "tgn:7006660",
      "tgn:7029392"
    ],
    "placetype": [
      "aat:300008347"
    ],
    "id": 1055189,
    "name:xx": "Kazanka"
  }
}
