{
  "geometry": {
    "type": "Point",
    "coordinates": [
      -103.3333,
      29.7833
    ]
  },
  "type": "Feature",
  "properties": {
    "hierarchy": [
      "tgn:2783933",
      "tgn:1000001",
      "tgn:2001945",
      "tgn:7012149",
      "tgn:7007826",
      "tgn:7029392"
    ],
    "placetype": [
      "aat:300008798"
    ],
    "id": 2783933,
    "name:xx": "Y E Mesa"
  }
}
