{
  "geometry": {
    "type": "Point",
    "coordinates": [
      -80.5667,
      41.2833
    ]
  },
  "type": "Feature",
  "properties": {
    "hierarchy": [
      "tgn:2500194",
      "tgn:1000001",
      "tgn:7012149",
      "tgn:7029392"
    ],
    "placetype": [
      "aat:300008699"
    ],
    "id": 2500194,
    "name:xx": "McCullough Run"
  }
}
