{
  "geometry": {
    "type": "Point",
    "coordinates": [
      -95.7333,
      48.65
    ]
  },
  "type": "Feature",
  "properties": {
    "hierarchy": [
      "tgn:2055699",
      "tgn:1000001",
      "tgn:7012149",
      "tgn:2001066",
      "tgn:7007521",
      "tgn:7029392"
    ],
    "placetype": [
      "aat:300008347"
    ],
    "id": 2055699,
    "name:xx": "Wannaska"
  }
}
