{
  "geometry": {
    "type": "Point",
    "coordinates": [
      -72.1333,
      43.0333
    ]
  },
  "type": "Feature",
  "properties": {
    "hierarchy": [
      "tgn:2505516",
      "tgn:7019618",
      "tgn:1000001",
      "tgn:7012149",
      "tgn:7007564",
      "tgn:7029392"
    ],
    "placetype": [
      "aat:300008798"
    ],
    "id": 2505516,
    "name:xx": "Melville Hill"
  }
}
