{
  "geometry": {
    "type": "Point",
    "coordinates": [
      -104.9667,
      37.9167
    ]
  },
  "type": "Feature",
  "properties": {
    "hierarchy": [
      "tgn:2271125",
      "tgn:1000001",
      "tgn:7012149",
      "tgn:7007158",
      "tgn:2000242",
      "tgn:7029392"
    ],
    "placetype": [
      "aat:300008347"
    ],
    "id": 2271125,
    "name:xx": "Cuerna Verde Park"
  }
}
