{
  "geometry": {
    "type": "Point",
    "coordinates": [
      -119.2833,
      43.8333
    ]
  },
  "type": "Feature",
  "properties": {
    "hierarchy": [
      "tgn:2158483",
      "tgn:1000001",
      "tgn:7012149",
      "tgn:2001709",
      "tgn:7007708",
      "tgn:7029392"
    ],
    "placetype": [
      "aat:300008706"
    ],
    "id": 2158483,
    "name:xx": "Beaverdam Creek"
  }
}
