{
  "geometry": {
    "type": "Point",
    "coordinates": [
      -69.2167,
      46.4333
    ]
  },
  "type": "Feature",
  "properties": {
    "hierarchy": [
      "tgn:2549843",
      "tgn:1000001",
      "tgn:7012149",
      "tgn:2000928",
      "tgn:7007515",
      "tgn:7029392"
    ],
    "placetype": [
      "aat:300008699"
    ],
    "id": 2549843,
    "name:xx": "North Twin Brook"
  }
}
