{
  "geometry": {
    "type": "Point",
    "coordinates": [
      16.7167,
      -11.4833
    ]
  },
  "type": "Feature",
  "properties": {
    "hierarchy": [
      "tgn:1087620",
      "tgn:1000815",
      "tgn:7001242",
      "tgn:1000149",
      "tgn:7029392"
    ],
    "placetype": [
      "aat:300008347"
    ],
    "id": 1087620,
    "name:xx": "Andulo"
  }
}
