{
  "geometry": {
    "type": "Point",
    "coordinates": [
      -107.7667,
      39.2333
    ]
  },
  "type": "Feature",
  "properties": {
    "hierarchy": [
      "tgn:2318543",
      "tgn:1000001",
      "tgn:7012149",
      "tgn:2000230",
      "tgn:7007158",
      "tgn:7029392"
    ],
    "placetype": [
      "aat:300006075"
    ],
    "id": 2318543,
    "name:xx": "Erie Canal"
  }
}
