{
  "geometry": {
    "type": "Point",
    "coordinates": [
      45.6333,
      29.7667
    ]
  },
  "type": "Feature",
  "properties": {
    "hierarchy": [
      "tgn:1079444",
      "tgn:1001089",
      "tgn:1000004",
      "tgn:1000118",
      "tgn:7029392"
    ],
    "placetype": [
      "aat:300008347"
    ],
    "id": 1079444,
    "name:xx": "Tukayyid"
  }
}
