{
  "geometry": {
    "type": "Point",
    "coordinates": [
      -122.4667,
      47.1167
    ]
  },
  "type": "Feature",
  "properties": {
    "hierarchy": [
      "tgn:2524007",
      "tgn:1000001",
      "tgn:7012149",
      "tgn:1002785",
      "tgn:7007920",
      "tgn:7029392"
    ],
    "placetype": [
      "aat:300008706"
    ],
    "id": 2524007,
    "name:xx": "Morey Creek"
  }
}
