{
  "geometry": {
    "type": "Point",
    "coordinates": [
      -83.4833,
      34.8333
    ]
  },
  "type": "Feature",
  "properties": {
    "hierarchy": [
      "tgn:2696895",
      "tgn:1000001",
      "tgn:7012149",
      "tgn:2000410",
      "tgn:7007248",
      "tgn:7029392"
    ],
    "placetype": [
      "aat:300008706"
    ],
    "id": 2696895,
    "name:xx": "Stonewall Creek"
  }
}
