{
  "type": "FeatureCollection",
  "features": [
    {
      "geometry": {
        "type": "Point",
        "coordinates": [
          -97.833333,
          16.616667
        ]
      },
      "type": "Feature",
      "properties": {
        "hierarchy": [
          "tgn:7364680",
          "tgn:1000001",
          "tgn:7005591",
          "tgn:7005560",
          "tgn:7029392"
        ],
        "placetype": [
          "aat:300008347"
        ],
        "id": 7364680,
        "name:xx": "El Zapote"
      }
    },
    {
      "geometry": {
        "type": "Point",
        "coordinates": [
          -92.966667,
          16.6
        ]
      },
      "type": "Feature",
      "properties": {
        "hierarchy": [
          "tgn:7364681",
          "tgn:7005580",
          "tgn:1000001",
          "tgn:7005560",
          "tgn:7029392"
        ],
        "placetype": [
          "aat:300008347"
        ],
        "id": 7364681,
        "name:xx": "El Zapote"
      }
    },
    {
      "geometry": {
        "type": "Point",
        "coordinates": [
          -98.983333,
          24.6
        ]
      },
      "type": "Feature",
      "properties": {
        "hierarchy": [
          "tgn:7364682",
          "tgn:1000001",
          "tgn:7005597",
          "tgn:7005560",
          "tgn:7029392"
        ],
        "placetype": [
          "aat:300008347"
        ],
        "id": 7364682,
        "name:xx": "El Zapotal"
      }
    },
    {
      "geometry": {
        "type": "Point",
        "coordinates": [
          -98.383333,
          21.6
        ]
      },
      "type": "Feature",
      "properties": {
        "hierarchy": [
          "tgn:7364683",
          "tgn:1000001",
          "tgn:7005599",
          "tgn:7005560",
          "tgn:7029392"
        ],
        "placetype": [
          "aat:300008347"
        ],
        "id": 7364683,
        "name:xx": "El Zapotal"
      }
    },
    {
      "geometry": {
        "type": "Point",
        "coordinates": [
          -97.666667,
          21.166667
        ]
      },
      "type": "Feature",
      "properties": {
        "hierarchy": [
          "tgn:7364684",
          "tgn:1000001",
          "tgn:7005599",
          "tgn:7005560",
          "tgn:7029392"
        ],
        "placetype": [
          "aat:300008347"
        ],
        "id": 7364684,
        "name:xx": "El Zapotal"
      }
    },
    {
      "geometry": {
        "type": "Point",
        "coordinates": [
          -96.066667,
          18.7
        ]
      },
      "type": "Feature",
      "properties": {
        "hierarchy": [
          "tgn:7364685",
          "tgn:1000001",
          "tgn:7005599",
          "tgn:7005560",
          "tgn:7029392"
        ],
        "placetype": [
          "aat:300008347"
        ],
        "id": 7364685,
        "name:xx": "El Zapotal"
      }
    },
    {
      "geometry": {
        "type": "Point",
        "coordinates": [
          -95.55,
          18.483333
        ]
      },
      "type": "Feature",
      "properties": {
        "hierarchy": [
          "tgn:7364686",
          "tgn:1000001",
          "tgn:7005599",
          "tgn:7005560",
          "tgn:7029392"
        ],
        "placetype": [
          "aat:300008347"
        ],
        "id": 7364686,
        "name:xx": "El Zapotal"
      }
    },
    {
      "geometry": {
        "type": "Point",
        "coordinates": [
          -92.716667,
          16.6
        ]
      },
      "type": "Feature",
      "properties": {
        "hierarchy": [
          "tgn:7364687",
          "tgn:7005580",
          "tgn:1000001",
          "tgn:7005560",
          "tgn:7029392"
        ],
        "placetype": [
          "aat:300008347"
        ],
        "id": 7364687,
        "name:xx": "El Zapotal"
      }
    },
    {
      "geometry": {
        "type": "Point",
        "coordinates": [
          -91.333333,
          16.533333
        ]
      },
      "type": "Feature",
      "properties": {
        "hierarchy": [
          "tgn:7364688",
          "tgn:7005580",
          "tgn:1000001",
          "tgn:7005560",
          "tgn:7029392"
        ],
        "placetype": [
          "aat:300008347"
        ],
        "id": 7364688,
        "name:xx": "El Zapotal"
      }
    },
    {
      "geometry": {
        "type": "Point",
        "coordinates": [
          -105.783333,
          25.816667
        ]
      },
      "type": "Feature",
      "properties": {
        "hierarchy": [
          "tgn:7364689",
          "tgn:7005583",
          "tgn:1000001",
          "tgn:7005560",
          "tgn:7029392"
        ],
        "placetype": [
          "aat:300008347"
        ],
        "id": 7364689,
        "name:xx": "El Zape Chico"
      }
    }
  ]
}
