{
  "type": "FeatureCollection",
  "features": [
    {
      "geometry": {
        "type": "Point",
        "coordinates": [
          8.866667,
          47.716667
        ]
      },
      "type": "Feature",
      "properties": {
        "hierarchy": [
          "tgn:7170391",
          "tgn:7003692",
          "tgn:1000003",
          "tgn:7000084",
          "tgn:7029392"
        ],
        "placetype": [
          "aat:300000206"
        ],
        "id": 7170391,
        "name:xx": "Hittisheim"
      }
    },
    {
      "geometry": {
        "type": "Point",
        "coordinates": [
          13.066667,
          48.816667
        ]
      },
      "type": "Feature",
      "properties": {
        "hierarchy": [
          "tgn:7170392",
          "tgn:7003669",
          "tgn:1000003",
          "tgn:7000084",
          "tgn:7029392"
        ],
        "placetype": [
          "aat:300000206"
        ],
        "id": 7170392,
        "name:xx": "Hitting"
      }
    },
    {
      "geometry": {
        "type": "Point",
        "coordinates": [
          13.25,
          48.366667
        ]
      },
      "type": "Feature",
      "properties": {
        "hierarchy": [
          "tgn:7170393",
          "tgn:7003669",
          "tgn:1000003",
          "tgn:7000084",
          "tgn:7029392"
        ],
        "placetype": [
          "aat:300000206"
        ],
        "id": 7170393,
        "name:xx": "Hinterberg"
      }
    },
    {
      "geometry": {
        "type": "Point",
        "coordinates": [
          12.766667,
          48.166667
        ]
      },
      "type": "Feature",
      "properties": {
        "hierarchy": [
          "tgn:7170394",
          "tgn:7003669",
          "tgn:1000003",
          "tgn:7000084",
          "tgn:7029392"
        ],
        "placetype": [
          "aat:300000206"
        ],
        "id": 7170394,
        "name:xx": "Hinterberg"
      }
    },
    {
      "geometry": {
        "type": "Point",
        "coordinates": [
          12.666667,
          48.166667
        ]
      },
      "type": "Feature",
      "properties": {
        "hierarchy": [
          "tgn:7170395",
          "tgn:7003669",
          "tgn:1000003",
          "tgn:7000084",
          "tgn:7029392"
        ],
        "placetype": [
          "aat:300000206"
        ],
        "id": 7170395,
        "name:xx": "Hinterberg"
      }
    },
    {
      "geometry": {
        "type": "Point",
        "coordinates": [
          9.05,
          47.883333
        ]
      },
      "type": "Feature",
      "properties": {
        "hierarchy": [
          "tgn:7170396",
          "tgn:7003692",
          "tgn:1000003",
          "tgn:7000084",
          "tgn:7029392"
        ],
        "placetype": [
          "aat:300000206"
        ],
        "id": 7170396,
        "name:xx": "Hinterberg"
      }
    },
    {
      "geometry": {
        "type": "Point",
        "coordinates": [
          9.95,
          47.75
        ]
      },
      "type": "Feature",
      "properties": {
        "hierarchy": [
          "tgn:7170397",
          "tgn:7003692",
          "tgn:1000003",
          "tgn:7000084",
          "tgn:7029392"
        ],
        "placetype": [
          "aat:300000206"
        ],
        "id": 7170397,
        "name:xx": "Hinterberg"
      }
    }
  ]
}
