{
  "geometry": {
    "type": "Point",
    "coordinates": [
      -91.1333,
      42.2833
    ]
  },
  "type": "Feature",
  "properties": {
    "hierarchy": [
      "tgn:7019154",
      "tgn:1000001",
      "tgn:7012149",
      "tgn:2000613",
      "tgn:7007253",
      "tgn:7029392"
    ],
    "placetype": [
      "aat:300008706"
    ],
    "id": 7019154,
    "name:xx": "Tibbetts Creek"
  }
}
