{
  "geometry": {
    "type": "Point",
    "coordinates": [
      -109.7167,
      39.3833
    ]
  },
  "type": "Feature",
  "properties": {
    "hierarchy": [
      "tgn:2741263",
      "tgn:1000001",
      "tgn:7012149",
      "tgn:7007827",
      "tgn:7029392"
    ],
    "placetype": [
      "aat:300008761"
    ],
    "id": 2741263,
    "name:xx": "Upper Wagon Canyon"
  }
}
