{
  "geometry": {
    "type": "Point",
    "coordinates": [
      9.05,
      47.85
    ]
  },
  "type": "Feature",
  "properties": {
    "hierarchy": [
      "tgn:7079731",
      "tgn:7003692",
      "tgn:1000003",
      "tgn:7000084",
      "tgn:7029392"
    ],
    "placetype": [
      "aat:300008347"
    ],
    "id": 7079731,
    "name:xx": "Winterspüren"
  }
}
