{
  "geometry": {
    "type": "Point",
    "coordinates": [
      5.0667,
      45.5833
    ]
  },
  "type": "Feature",
  "properties": {
    "hierarchy": [
      "tgn:1033744",
      "tgn:1000003",
      "tgn:1000070",
      "tgn:7002897",
      "tgn:7029392"
    ],
    "placetype": [
      "aat:300008347"
    ],
    "id": 1033744,
    "name:xx": "Lafayette"
  }
}
