{
  "geometry": {
    "type": "Point",
    "coordinates": [
      37.8333,
      55.8333
    ]
  },
  "type": "Feature",
  "properties": {
    "hierarchy": [
      "tgn:1051915",
      "tgn:1000004",
      "tgn:7011573",
      "tgn:7018214",
      "tgn:7002435",
      "tgn:7029392"
    ],
    "placetype": [
      "aat:300008347"
    ],
    "id": 1051915,
    "name:xx": "Abramtsevo"
  }
}
