{
  "type": "FeatureCollection",
  "features": [
    {
      "geometry": {
        "type": "Point",
        "coordinates": [
          33.376668,
          31.000313
        ]
      },
      "type": "Feature",
      "properties": {
        "hierarchy": [
          "tgn:7539290",
          "tgn:7001242",
          "tgn:7016833",
          "tgn:7001335",
          "tgn:7029392"
        ],
        "placetype": [
          "aat:300006207"
        ],
        "name:en": "Bîr el-Matha",
        "id": 7539290
      }
    },
    {
      "geometry": {
        "type": "Point",
        "coordinates": [
          31.276025,
          30.80292
        ]
      },
      "type": "Feature",
      "properties": {
        "hierarchy": [
          "tgn:7539291",
          "tgn:7001242",
          "tgn:1001059",
          "tgn:7016833",
          "tgn:7029392"
        ],
        "placetype": [
          "aat:300008347"
        ],
        "name:en": "Şahrajt as Şughrá",
        "id": 7539291
      }
    },
    {
      "geometry": {
        "type": "Point",
        "coordinates": [
          31.926275,
          31.299093
        ]
      },
      "type": "Feature",
      "properties": {
        "hierarchy": [
          "tgn:7539293",
          "tgn:7001242",
          "tgn:1001059",
          "tgn:7016833",
          "tgn:7029392"
        ],
        "placetype": [
          "aat:300008791"
        ],
        "name:en": "Şaḩrā' aş Şaghīrah, Jazīrat aş",
        "id": 7539293
      }
    },
    {
      "geometry": {
        "type": "Point",
        "coordinates": [
          31.930317,
          31.294745
        ]
      },
      "type": "Feature",
      "properties": {
        "hierarchy": [
          "tgn:7539294",
          "tgn:7001242",
          "tgn:1001059",
          "tgn:7016833",
          "tgn:7029392"
        ],
        "placetype": [
          "aat:300008791"
        ],
        "name:en": "Şaḩrā' al Kabīrah, 'Alāwī aş",
        "id": 7539294
      }
    },
    {
      "geometry": {
        "type": "Point",
        "coordinates": [
          34.034372,
          27.893173
        ]
      },
      "type": "Feature",
      "properties": {
        "hierarchy": [
          "tgn:7539295",
          "tgn:7001242",
          "tgn:7016833",
          "tgn:7001336",
          "tgn:7029392"
        ],
        "placetype": [
          "aat:300379998"
        ],
        "name:en": "Şaḩrā', Wādī",
        "id": 7539295
      }
    },
    {
      "geometry": {
        "type": "Point",
        "coordinates": [
          34.131547,
          28.000271
        ]
      },
      "type": "Feature",
      "properties": {
        "hierarchy": [
          "tgn:7539296",
          "tgn:7001242",
          "tgn:7016833",
          "tgn:7001336",
          "tgn:7029392"
        ],
        "placetype": [
          "aat:300008795"
        ],
        "name:en": "Şaḩrā', Jabal",
        "id": 7539296
      }
    },
    {
      "geometry": {
        "type": "Point",
        "coordinates": [
          31.941778,
          31.303589
        ]
      },
      "type": "Feature",
      "properties": {
        "hierarchy": [
          "tgn:7539298",
          "tgn:7001242",
          "tgn:1001059",
          "tgn:7016833",
          "tgn:7029392"
        ],
        "placetype": [
          "aat:300008791"
        ],
        "name:en": "Şaḩrā', 'Alāwī aş",
        "id": 7539298
      }
    },
    {
      "geometry": {
        "type": "Point",
        "coordinates": [
          30.163889,
          30.731111
        ]
      },
      "type": "Feature",
      "properties": {
        "hierarchy": [
          "tgn:7539299",
          "tgn:7001242",
          "tgn:1001075",
          "tgn:7016833",
          "tgn:7029392"
        ],
        "placetype": [
          "aat:300386860"
        ],
        "name:en": "Tifla, Ṣaḥn el-",
        "id": 7539299
      }
    }
  ]
}
