{
  "type": "FeatureCollection",
  "features": [
    {
      "geometry": {
        "type": "Point",
        "coordinates": [
          121.9167,
          20.6667
        ]
      },
      "type": "Feature",
      "properties": {
        "hierarchy": [
          "tgn:7000372",
          "tgn:1000004",
          "tgn:1000135",
          "tgn:7029392"
        ],
        "placetype": [
          "aat:300387064",
          "aat:300000774"
        ],
        "id": 7000372,
        "name:xx": "Batanes"
      }
    },
    {
      "geometry": {
        "type": "Point",
        "coordinates": [
          120.9667,
          14.6167
        ]
      },
      "type": "Feature",
      "properties": {
        "hierarchy": [
          "tgn:7000373",
          "tgn:1000004",
          "tgn:1000135",
          "tgn:7029392"
        ],
        "placetype": [
          "aat:300236112"
        ],
        "id": 7000373,
        "name:xx": "Manila"
      }
    },
    {
      "geometry": {
        "type": "Point",
        "coordinates": [
          121.75,
          16
        ]
      },
      "type": "Feature",
      "properties": {
        "hierarchy": [
          "tgn:7000374",
          "tgn:1000004",
          "tgn:1000135",
          "tgn:7029392"
        ],
        "placetype": [
          "aat:300387064",
          "aat:300000774"
        ],
        "id": 7000374,
        "name:xx": "Aurora"
      }
    }
  ]
}
