{
  "geometry": {
    "type": "Point",
    "coordinates": [
      -83.6167,
      43.0667
    ]
  },
  "type": "Feature",
  "properties": {
    "hierarchy": [
      "tgn:2222466",
      "tgn:1000001",
      "tgn:7012149",
      "tgn:1002406",
      "tgn:7007520",
      "tgn:7029392"
    ],
    "placetype": [
      "aat:300006075"
    ],
    "id": 2222466,
    "name:xx": "Carpenter Drain"
  }
}
