{
  "geometry": {
    "type": "Point",
    "coordinates": [
      120.5833,
      15.35
    ]
  },
  "type": "Feature",
  "properties": {
    "hierarchy": [
      "tgn:1084707",
      "tgn:1000004",
      "tgn:1001565",
      "tgn:1000135",
      "tgn:7029392"
    ],
    "placetype": [
      "aat:300008347",
      "aat:300387223",
      "aat:300008375"
    ],
    "id": 1084707,
    "name:xx": "Tarlac"
  }
}
