{
  "geometry": {
    "type": "Point",
    "coordinates": [
      -97.0833,
      43.9167
    ]
  },
  "type": "Feature",
  "properties": {
    "hierarchy": [
      "tgn:2333271",
      "tgn:1000001",
      "tgn:2001809",
      "tgn:7012149",
      "tgn:7007713",
      "tgn:7029392"
    ],
    "placetype": [
      "aat:300008905"
    ],
    "id": 2333271,
    "name:xx": "Fods Slough"
  }
}
