{
  "geometry": {
    "type": "Point",
    "coordinates": [
      8.8333,
      53.05
    ]
  },
  "type": "Feature",
  "properties": {
    "hierarchy": [
      "tgn:7003672",
      "tgn:1000003",
      "tgn:7000084",
      "tgn:7029392"
    ],
    "placetype": [
      "aat:300387064",
      "aat:300000776"
    ],
    "id": 7003672,
    "name:de": "Bremen"
  }
}
