{
  "geometry": {
    "type": "Point",
    "coordinates": [
      -116.4667,
      43.4667
    ]
  },
  "type": "Feature",
  "properties": {
    "hierarchy": [
      "tgn:2742803",
      "tgn:1000001",
      "tgn:7012149",
      "tgn:7007250",
      "tgn:7029392"
    ],
    "placetype": [
      "aat:300006075"
    ],
    "id": 2742803,
    "name:xx": "Van Duzer Lateral"
  }
}
