{
  "geometry": {
    "type": "Point",
    "coordinates": [
      -123.1333,
      47.7333
    ]
  },
  "type": "Feature",
  "properties": {
    "hierarchy": [
      "tgn:2253043",
      "tgn:1000001",
      "tgn:7012149",
      "tgn:1002521",
      "tgn:7007920",
      "tgn:7029392"
    ],
    "placetype": [
      "aat:300008706"
    ],
    "id": 2253043,
    "name:xx": "Constance Creek"
  }
}
