{
  "geometry": {
    "type": "Point",
    "coordinates": [
      31.21778,
      30.009959
    ]
  },
  "type": "Feature",
  "properties": {
    "hierarchy": [
      "tgn:7530068",
      "tgn:7001242",
      "tgn:7016833",
      "tgn:1001083",
      "tgn:7029392"
    ],
    "placetype": [
      "aat:300007544"
    ],
    "id": 7530068,
    "name:xx": "Masjid Aḩmad Dhakī"
  }
}
