{
  "geometry": {
    "type": "Point",
    "coordinates": [
      -97.1667,
      29.75
    ]
  },
  "type": "Feature",
  "properties": {
    "hierarchy": [
      "tgn:2455274",
      "tgn:1000001",
      "tgn:7012149",
      "tgn:7007826",
      "tgn:7029392"
    ],
    "placetype": [
      "aat:300008706"
    ],
    "id": 2455274,
    "name:xx": "Little Fivemile Creek"
  }
}
