{
  "geometry": {
    "type": "Point",
    "coordinates": [
      -123.6667,
      42.4833
    ]
  },
  "type": "Feature",
  "properties": {
    "hierarchy": [
      "tgn:2466063",
      "tgn:1000001",
      "tgn:7012149",
      "tgn:2001713",
      "tgn:7007708",
      "tgn:7029392"
    ],
    "placetype": [
      "aat:300266640"
    ],
    "id": 2466063,
    "name:xx": "Lone Tree Ridge"
  }
}
