{
  "geometry": {
    "type": "Point",
    "coordinates": [
      -70.4167,
      43.5667
    ]
  },
  "type": "Feature",
  "properties": {
    "hierarchy": [
      "tgn:2699641",
      "tgn:1000001",
      "tgn:7012149",
      "tgn:7007515",
      "tgn:7029392"
    ],
    "placetype": [
      "aat:300008699"
    ],
    "id": 2699641,
    "name:xx": "Stuart Brook"
  }
}
