{
  "geometry": {
    "type": "Point",
    "coordinates": [
      5.3167,
      60.4333
    ]
  },
  "type": "Feature",
  "properties": {
    "hierarchy": [
      "tgn:1048515",
      "tgn:7003646",
      "tgn:1000003",
      "tgn:1000088",
      "tgn:7029392"
    ],
    "placetype": [
      "aat:300008347"
    ],
    "id": 1048515,
    "name:xx": "Eidsvåg"
  }
}
