{
  "geometry": {
    "type": "Point",
    "coordinates": [
      -75.2833,
      39.4167
    ]
  },
  "type": "Feature",
  "properties": {
    "hierarchy": [
      "tgn:2530766",
      "tgn:1002309",
      "tgn:1000001",
      "tgn:7012149",
      "tgn:7007565",
      "tgn:7029392"
    ],
    "placetype": [
      "aat:300008699"
    ],
    "id": 2530766,
    "name:xx": "Muddy Run"
  }
}
