{
  "type": "FeatureCollection",
  "features": [
    {
      "geometry": {
        "type": "Point",
        "coordinates": [
          10,
          50.5
        ]
      },
      "type": "Feature",
      "properties": {
        "hierarchy": [
          "tgn:1109532",
          "tgn:7003669",
          "tgn:1000003",
          "tgn:7000084",
          "tgn:7029392"
        ],
        "placetype": [
          "aat:300008795"
        ],
        "id": 1109532,
        "name:xx": "Rhön"
      }
    },
    {
      "geometry": {
        "type": "Point",
        "coordinates": [
          -4.366667,
          55.15
        ]
      },
      "type": "Feature",
      "properties": {
        "hierarchy": [
          "tgn:1109534",
          "tgn:7002444",
          "tgn:7008074",
          "tgn:1000003",
          "tgn:7008591",
          "tgn:7029392"
        ],
        "placetype": [
          "aat:300008795"
        ],
        "name:en": "Rhinns of Kells",
        "id": 1109534
      }
    },
    {
      "geometry": {
        "type": "Point",
        "coordinates": [
          24.5,
          41.5
        ]
      },
      "type": "Feature",
      "properties": {
        "name:en": "Rhodope Mountains",
        "name:xx": "Rodhópis, Orosirá",
        "hierarchy": [
          "tgn:1109535",
          "tgn:1000003",
          "tgn:7029392"
        ],
        "placetype": [
          "aat:300386831"
        ],
        "name:bg": "Rodopi Planina",
        "id": 1109535
      }
    },
    {
      "geometry": {
        "type": "Point",
        "coordinates": [
          168.516667,
          -44.75
        ]
      },
      "type": "Feature",
      "properties": {
        "hierarchy": [
          "tgn:1109537",
          "tgn:1009227",
          "tgn:1000226",
          "tgn:7018437",
          "tgn:1000006",
          "tgn:7029392"
        ],
        "placetype": [
          "aat:300008795"
        ],
        "name:en": "Richardson Mountains",
        "id": 1109537
      }
    }
  ]
}
