{
  "type": "FeatureCollection",
  "features": [
    {
      "geometry": {
        "type": "Point",
        "coordinates": [
          -84.9833,
          39.1333
        ]
      },
      "type": "Feature",
      "properties": {
        "hierarchy": [
          "tgn:2032490",
          "tgn:1000001",
          "tgn:1002324",
          "tgn:7012149",
          "tgn:7007252",
          "tgn:7029392"
        ],
        "placetype": [
          "aat:300008347",
          "aat:300387210"
        ],
        "id": 2032490,
        "name:xx": "Kyle"
      }
    },
    {
      "geometry": {
        "type": "Point",
        "coordinates": [
          -86.0833,
          38.0167
        ]
      },
      "type": "Feature",
      "properties": {
        "hierarchy": [
          "tgn:2032491",
          "tgn:1000001",
          "tgn:7012149",
          "tgn:1002457",
          "tgn:7007252",
          "tgn:7029392"
        ],
        "placetype": [
          "aat:300008347"
        ],
        "id": 2032491,
        "name:xx": "Laconia"
      }
    },
    {
      "geometry": {
        "type": "Point",
        "coordinates": [
          -86.8833,
          41.3167
        ]
      },
      "type": "Feature",
      "properties": {
        "hierarchy": [
          "tgn:2032492",
          "tgn:1000001",
          "tgn:7012149",
          "tgn:1002561",
          "tgn:7007252",
          "tgn:7029392"
        ],
        "placetype": [
          "aat:300008347"
        ],
        "id": 2032492,
        "name:xx": "La Crosse"
      }
    },
    {
      "geometry": {
        "type": "Point",
        "coordinates": [
          -86.8,
          39.9
        ]
      },
      "type": "Feature",
      "properties": {
        "hierarchy": [
          "tgn:2032493",
          "tgn:1000001",
          "tgn:7012149",
          "tgn:2000547",
          "tgn:7007252",
          "tgn:7029392"
        ],
        "placetype": [
          "aat:300008347"
        ],
        "id": 2032493,
        "name:xx": "Ladoga"
      }
    }
  ]
}
