{
  "geometry": {
    "type": "Point",
    "coordinates": [
      -75.55,
      35.8167
    ]
  },
  "type": "Feature",
  "properties": {
    "hierarchy": [
      "tgn:2593855",
      "tgn:1000001",
      "tgn:7012149",
      "tgn:2001488",
      "tgn:7007709",
      "tgn:7029392"
    ],
    "placetype": [
      "aat:300132316"
    ],
    "id": 2593855,
    "name:xx": "Port Ferinando"
  }
}
