{
  "geometry": {
    "type": "Point",
    "coordinates": [
      30.8833,
      53.5667
    ]
  },
  "type": "Feature",
  "properties": {
    "hierarchy": [
      "tgn:1056536",
      "tgn:7011700",
      "tgn:1000003",
      "tgn:7006657",
      "tgn:7029392"
    ],
    "placetype": [
      "aat:300008347"
    ],
    "id": 1056536,
    "name:xx": "Lopatiči"
  }
}
