{
  "type": "FeatureCollection",
  "features": [
    {
      "geometry": {
        "type": "Point",
        "coordinates": [
          -105.6333,
          40.25
        ]
      },
      "type": "Feature",
      "properties": {
        "hierarchy": [
          "tgn:2341830",
          "tgn:1000001",
          "tgn:2000198",
          "tgn:7012149",
          "tgn:7007158",
          "tgn:7029392"
        ],
        "placetype": [
          "aat:300008680"
        ],
        "id": 2341830,
        "name:xx": "Frozen Lake"
      }
    },
    {
      "geometry": {
        "type": "Point",
        "coordinates": [
          -105.6667,
          39.5667
        ]
      },
      "type": "Feature",
      "properties": {
        "hierarchy": [
          "tgn:2341831",
          "tgn:1000001",
          "tgn:2000201",
          "tgn:7012149",
          "tgn:7007158",
          "tgn:7029392"
        ],
        "placetype": [
          "aat:300008680"
        ],
        "id": 2341831,
        "name:xx": "Frozen Lake"
      }
    },
    {
      "geometry": {
        "type": "Point",
        "coordinates": [
          -114.6667,
          48.9833
        ]
      },
      "type": "Feature",
      "properties": {
        "hierarchy": [
          "tgn:2341832",
          "tgn:1000001",
          "tgn:7012149",
          "tgn:2001274",
          "tgn:7007524",
          "tgn:7029392"
        ],
        "placetype": [
          "aat:300008680"
        ],
        "id": 2341832,
        "name:xx": "Frozen Lake"
      }
    },
    {
      "geometry": {
        "type": "Point",
        "coordinates": [
          -82.8667,
          35.0833
        ]
      },
      "type": "Feature",
      "properties": {
        "hierarchy": [
          "tgn:2341833",
          "tgn:1000001",
          "tgn:7012149",
          "tgn:2001544",
          "tgn:7007709",
          "tgn:7029392"
        ],
        "placetype": [
          "aat:300006191"
        ],
        "id": 2341833,
        "name:xx": "Frozen Lake"
      }
    },
    {
      "geometry": {
        "type": "Point",
        "coordinates": [
          -121.65,
          46.9167
        ]
      },
      "type": "Feature",
      "properties": {
        "hierarchy": [
          "tgn:2341834",
          "tgn:1000001",
          "tgn:7012149",
          "tgn:1002785",
          "tgn:7007920",
          "tgn:7029392"
        ],
        "placetype": [
          "aat:300006191"
        ],
        "id": 2341834,
        "name:xx": "Frozen Lake"
      }
    },
    {
      "geometry": {
        "type": "Point",
        "coordinates": [
          -121.4833,
          47.45
        ]
      },
      "type": "Feature",
      "properties": {
        "hierarchy": [
          "tgn:2341835",
          "tgn:1000001",
          "tgn:7012149",
          "tgn:7018871",
          "tgn:7007920",
          "tgn:7029392"
        ],
        "placetype": [
          "aat:300008680"
        ],
        "id": 2341835,
        "name:xx": "Frozen Lake"
      }
    },
    {
      "geometry": {
        "type": "Point",
        "coordinates": [
          -109.75,
          43.8
        ]
      },
      "type": "Feature",
      "properties": {
        "hierarchy": [
          "tgn:2341836",
          "tgn:1000001",
          "tgn:7012149",
          "tgn:2002371",
          "tgn:7007923",
          "tgn:7029392"
        ],
        "placetype": [
          "aat:300008680"
        ],
        "id": 2341836,
        "name:xx": "Frozen Lake"
      }
    },
    {
      "geometry": {
        "type": "Point",
        "coordinates": [
          -109.4833,
          44.95
        ]
      },
      "type": "Feature",
      "properties": {
        "hierarchy": [
          "tgn:2341837",
          "tgn:1000001",
          "tgn:7012149",
          "tgn:2002379",
          "tgn:7007923",
          "tgn:7029392"
        ],
        "placetype": [
          "aat:300008680"
        ],
        "id": 2341837,
        "name:xx": "Frozen Lake"
      }
    },
    {
      "geometry": {
        "type": "Point",
        "coordinates": [
          -109.75,
          43.8
        ]
      },
      "type": "Feature",
      "properties": {
        "hierarchy": [
          "tgn:2341838",
          "tgn:1000001",
          "tgn:7012149",
          "tgn:2002371",
          "tgn:7007923",
          "tgn:7029392"
        ],
        "placetype": [
          "aat:300008706"
        ],
        "id": 2341838,
        "name:xx": "Frozen Lake Creek"
      }
    },
    {
      "geometry": {
        "type": "Point",
        "coordinates": [
          -109.15,
          42.6833
        ]
      },
      "type": "Feature",
      "properties": {
        "hierarchy": [
          "tgn:2341839",
          "tgn:1000001",
          "tgn:7012149",
          "tgn:2002382",
          "tgn:7007923",
          "tgn:7029392"
        ],
        "placetype": [
          "aat:300008680"
        ],
        "id": 2341839,
        "name:xx": "Frozen Lakes"
      }
    }
  ]
}
