{
  "geometry": {
    "type": "Point",
    "coordinates": [
      -94.7667,
      32.1667
    ]
  },
  "type": "Feature",
  "properties": {
    "hierarchy": [
      "tgn:2126075",
      "tgn:1000001",
      "tgn:7012149",
      "tgn:1002839",
      "tgn:7007826",
      "tgn:7029392"
    ],
    "placetype": [
      "aat:300008706"
    ],
    "id": 2126075,
    "name:xx": "Adaway Creek"
  }
}
