{
  "geometry": {
    "type": "Point",
    "coordinates": [
      16.3333,
      66.5667
    ]
  },
  "type": "Feature",
  "properties": {
    "hierarchy": [
      "tgn:1063864",
      "tgn:1000003",
      "tgn:7003774",
      "tgn:1000097",
      "tgn:7029392"
    ],
    "placetype": [
      "aat:300008347"
    ],
    "id": 1063864,
    "name:xx": "Vuoggatjålme"
  }
}
