{
  "geometry": {
    "type": "Point",
    "coordinates": [
      -85.7833,
      32.3333
    ]
  },
  "type": "Feature",
  "properties": {
    "hierarchy": [
      "tgn:2158402",
      "tgn:7002659",
      "tgn:1000001",
      "tgn:7012149",
      "tgn:2000043",
      "tgn:7029392"
    ],
    "placetype": [
      "aat:300008706"
    ],
    "id": 2158402,
    "name:xx": "Beaverdam Creek"
  }
}
