{
  "geometry": {
    "type": "Point",
    "coordinates": [
      -90.2833,
      43.0167
    ]
  },
  "type": "Feature",
  "properties": {
    "hierarchy": [
      "tgn:2176129",
      "tgn:1000001",
      "tgn:7012149",
      "tgn:2002326",
      "tgn:7007922",
      "tgn:7029392"
    ],
    "placetype": [
      "aat:300006191"
    ],
    "id": 2176129,
    "name:xx": "Black Hawk Lake"
  }
}
