{
  "geometry": {
    "type": "Point",
    "coordinates": [
      -79.2667,
      38.4833
    ]
  },
  "type": "Feature",
  "properties": {
    "hierarchy": [
      "tgn:2447755",
      "tgn:1000001",
      "tgn:7012149",
      "tgn:7014398",
      "tgn:7013961",
      "tgn:7029392"
    ],
    "placetype": [
      "aat:300008699"
    ],
    "id": 2447755,
    "name:xx": "Lick Run"
  }
}
