{
  "geometry": {
    "type": "Point",
    "coordinates": [
      -75.1333,
      43.6667
    ]
  },
  "type": "Feature",
  "properties": {
    "hierarchy": [
      "tgn:2459120",
      "tgn:1000001",
      "tgn:7012149",
      "tgn:1002593",
      "tgn:7007568",
      "tgn:7029392"
    ],
    "placetype": [
      "aat:300008680"
    ],
    "id": 2459120,
    "name:xx": "Little Pine Lake"
  }
}
