{
  "geometry": {
    "type": "Point",
    "coordinates": [
      121.4167,
      36.9833
    ]
  },
  "type": "Feature",
  "properties": {
    "hierarchy": [
      "tgn:1073738",
      "tgn:1000004",
      "tgn:7002085",
      "tgn:1000111",
      "tgn:7029392"
    ],
    "placetype": [
      "aat:300008347"
    ],
    "id": 1073738,
    "name:xx": "Yuli"
  }
}
