{
  "geometry": {
    "type": "Point",
    "coordinates": [
      -81.15,
      26.9167
    ]
  },
  "type": "Feature",
  "properties": {
    "hierarchy": [
      "tgn:2636059",
      "tgn:1000001",
      "tgn:1002408",
      "tgn:7012149",
      "tgn:7007240",
      "tgn:7029392"
    ],
    "placetype": [
      "aat:300008791"
    ],
    "id": 2636059,
    "name:xx": "Saddle Hammock"
  }
}
