{
  "geometry": {
    "type": "Point",
    "coordinates": [
      -120.6333,
      35.5667
    ]
  },
  "type": "Feature",
  "properties": {
    "hierarchy": [
      "tgn:2536526",
      "tgn:1000001",
      "tgn:7012149",
      "tgn:7007157",
      "tgn:1002863",
      "tgn:7029392"
    ],
    "placetype": [
      "aat:300008697"
    ],
    "id": 2536526,
    "name:xx": "Neals Spring"
  }
}
