{
  "geometry": {
    "type": "Point",
    "coordinates": [
      23.0833,
      46.3833
    ]
  },
  "type": "Feature",
  "properties": {
    "hierarchy": [
      "tgn:1050054",
      "tgn:1000336",
      "tgn:1000003",
      "tgn:1000091",
      "tgn:7029392"
    ],
    "placetype": [
      "aat:300008347"
    ],
    "id": 1050054,
    "name:xx": "Cîmpeni"
  }
}
