{
  "geometry": {
    "type": "Point",
    "coordinates": [
      20.813,
      44.478
    ]
  },
  "type": "Feature",
  "properties": {
    "hierarchy": [
      "tgn:7032172",
      "tgn:1000003",
      "tgn:7006669",
      "tgn:7029392"
    ],
    "placetype": [
      "aat:300008347"
    ],
    "id": 7032172,
    "name:xx": "Velika Krsna"
  }
}
