{
  "geometry": {
    "type": "Point",
    "coordinates": [
      136.2833,
      35.2167
    ]
  },
  "type": "Feature",
  "properties": {
    "hierarchy": [
      "tgn:1140591",
      "tgn:1000004",
      "tgn:7000896",
      "tgn:7000277",
      "tgn:1000120",
      "tgn:7029392"
    ],
    "placetype": [
      "aat:300008347"
    ],
    "id": 1140591,
    "name:xx": "Taga"
  }
}
