{
  "geometry": {
    "type": "Point",
    "coordinates": [
      -89.45,
      41.5667
    ]
  },
  "type": "Feature",
  "properties": {
    "hierarchy": [
      "tgn:2749561",
      "tgn:1000001",
      "tgn:2000497",
      "tgn:7012149",
      "tgn:7007251",
      "tgn:7029392"
    ],
    "placetype": [
      "aat:300008706"
    ],
    "id": 2749561,
    "name:xx": "Walnut Creek"
  }
}
