{
  "geometry": {
    "type": "Point",
    "coordinates": [
      -83.6333,
      36.0167
    ]
  },
  "type": "Feature",
  "properties": {
    "hierarchy": [
      "tgn:2718229",
      "tgn:1000001",
      "tgn:7012149",
      "tgn:7007825",
      "tgn:7029392"
    ],
    "placetype": [
      "aat:300008706"
    ],
    "id": 2718229,
    "name:xx": "Thompson Creek"
  }
}
