{
  "geometry": {
    "type": "Point",
    "coordinates": [
      6.0625,
      50.2475
    ]
  },
  "type": "Feature",
  "properties": {
    "hierarchy": [
      "tgn:7240239",
      "tgn:7003460",
      "tgn:1000003",
      "tgn:1000063",
      "tgn:4012014",
      "tgn:7029392"
    ],
    "placetype": [
      "aat:300008777"
    ],
    "id": 7240239,
    "name:xx": "Eienberg"
  }
}
