{
  "type": "FeatureCollection",
  "features": [
    {
      "geometry": {
        "type": "Point",
        "coordinates": [
          -94.0833,
          33.6333
        ]
      },
      "type": "Feature",
      "properties": {
        "hierarchy": [
          "tgn:2378180",
          "tgn:1000001",
          "tgn:7016172",
          "tgn:7012149",
          "tgn:2000145",
          "tgn:7029392"
        ],
        "placetype": [
          "aat:300006191"
        ],
        "id": 2378180,
        "name:xx": "Harris Lake"
      }
    },
    {
      "geometry": {
        "type": "Point",
        "coordinates": [
          -92.9167,
          33.1833
        ]
      },
      "type": "Feature",
      "properties": {
        "hierarchy": [
          "tgn:2378181",
          "tgn:1000001",
          "tgn:7016172",
          "tgn:7012149",
          "tgn:2000174",
          "tgn:7029392"
        ],
        "placetype": [
          "aat:300006191"
        ],
        "id": 2378181,
        "name:xx": "Harris Lake"
      }
    },
    {
      "geometry": {
        "type": "Point",
        "coordinates": [
          -106.8,
          37.15
        ]
      },
      "type": "Feature",
      "properties": {
        "hierarchy": [
          "tgn:2378182",
          "tgn:2000195",
          "tgn:1000001",
          "tgn:7012149",
          "tgn:7007158",
          "tgn:7029392"
        ],
        "placetype": [
          "aat:300008680"
        ],
        "id": 2378182,
        "name:xx": "Harris Lake"
      }
    },
    {
      "geometry": {
        "type": "Point",
        "coordinates": [
          -106.8,
          37.15
        ]
      },
      "type": "Feature",
      "properties": {
        "hierarchy": [
          "tgn:2378183",
          "tgn:2000195",
          "tgn:1000001",
          "tgn:7012149",
          "tgn:7007158",
          "tgn:7029392"
        ],
        "placetype": [
          "aat:300006191"
        ],
        "id": 2378183,
        "name:xx": "Harris Lake"
      }
    },
    {
      "geometry": {
        "type": "Point",
        "coordinates": [
          -84,
          33.9833
        ]
      },
      "type": "Feature",
      "properties": {
        "hierarchy": [
          "tgn:2378184",
          "tgn:1000001",
          "tgn:7012149",
          "tgn:2000358",
          "tgn:7007248",
          "tgn:7029392"
        ],
        "placetype": [
          "aat:300006191"
        ],
        "id": 2378184,
        "name:xx": "Harris Lake"
      }
    },
    {
      "geometry": {
        "type": "Point",
        "coordinates": [
          -85.4,
          34.7833
        ]
      },
      "type": "Feature",
      "properties": {
        "hierarchy": [
          "tgn:2378185",
          "tgn:1000001",
          "tgn:7012149",
          "tgn:2000437",
          "tgn:7007248",
          "tgn:7029392"
        ],
        "placetype": [
          "aat:300006191"
        ],
        "id": 2378185,
        "name:xx": "Harris Lake"
      }
    },
    {
      "geometry": {
        "type": "Point",
        "coordinates": [
          -84.5333,
          33.5
        ]
      },
      "type": "Feature",
      "properties": {
        "hierarchy": [
          "tgn:2378186",
          "tgn:1000001",
          "tgn:7012149",
          "tgn:2000347",
          "tgn:7007248",
          "tgn:7029392"
        ],
        "placetype": [
          "aat:300006191"
        ],
        "id": 2378186,
        "name:xx": "Harris Lake"
      }
    },
    {
      "geometry": {
        "type": "Point",
        "coordinates": [
          -83.3667,
          32.3667
        ]
      },
      "type": "Feature",
      "properties": {
        "hierarchy": [
          "tgn:2378187",
          "tgn:1000001",
          "tgn:2000303",
          "tgn:7012149",
          "tgn:7007248",
          "tgn:7029392"
        ],
        "placetype": [
          "aat:300006191"
        ],
        "id": 2378187,
        "name:xx": "Harris Lake"
      }
    },
    {
      "geometry": {
        "type": "Point",
        "coordinates": [
          -82.0833,
          32.1833
        ]
      },
      "type": "Feature",
      "properties": {
        "hierarchy": [
          "tgn:2378188",
          "tgn:1000001",
          "tgn:7012149",
          "tgn:2000423",
          "tgn:7007248",
          "tgn:7029392"
        ],
        "placetype": [
          "aat:300006191"
        ],
        "id": 2378188,
        "name:xx": "Harris Lake"
      }
    },
    {
      "geometry": {
        "type": "Point",
        "coordinates": [
          -115.9,
          42.1833
        ]
      },
      "type": "Feature",
      "properties": {
        "hierarchy": [
          "tgn:2378189",
          "tgn:1000001",
          "tgn:7012149",
          "tgn:2000488",
          "tgn:7007250",
          "tgn:7029392"
        ],
        "placetype": [
          "aat:300008680"
        ],
        "id": 2378189,
        "name:xx": "Harris Lake"
      }
    }
  ]
}
