{
  "geometry": {
    "type": "Point",
    "coordinates": [
      -74.3667,
      39.4167
    ]
  },
  "type": "Feature",
  "properties": {
    "hierarchy": [
      "tgn:2675722",
      "tgn:1002157",
      "tgn:1000001",
      "tgn:7012149",
      "tgn:7007565",
      "tgn:7029392"
    ],
    "placetype": [
      "aat:300132316"
    ],
    "id": 2675722,
    "name:xx": "Somers Bay"
  }
}
