{
  "type": "FeatureCollection",
  "features": [
    {
      "geometry": {
        "type": "Point",
        "coordinates": [
          -61.3333,
          15.5
        ]
      },
      "type": "Feature",
      "properties": {
        "name:en": "Dominica",
        "hierarchy": [
          "tgn:7004641",
          "tgn:1000001",
          "tgn:7029392"
        ],
        "name:ar": "دوم يِكَا",
        "placetype": [
          "aat:300387054",
          "aat:300235115",
          "aat:300387062",
          "aat:300179493",
          "aat:300128207",
          "aat:300387174"
        ],
        "name:fr": "Dominique",
        "name:ru": "Доминика",
        "name:zh": "多米尼克",
        "id": 7004641,
        "name:es": "Dominica"
      }
    },
    {
      "geometry": {
        "type": "Point",
        "coordinates": [
          -66.55,
          18.2333
        ]
      },
      "type": "Feature",
      "properties": {
        "hierarchy": [
          "tgn:7004643",
          "tgn:1000001",
          "tgn:7029392"
        ],
        "placetype": [
          "aat:300387054",
          "aat:300235115",
          "aat:300387176",
          "aat:300154236"
        ],
        "name:en": "Puerto Rico",
        "id": 7004643
      }
    },
    {
      "geometry": {
        "type": "Point",
        "coordinates": [
          14.55,
          40.916667
        ]
      },
      "type": "Feature",
      "properties": {
        "hierarchy": [
          "tgn:7004644",
          "tgn:7003013",
          "tgn:7003005",
          "tgn:1000003",
          "tgn:1000080",
          "tgn:7029392"
        ],
        "placetype": [
          "aat:300387273",
          "aat:300008347",
          "aat:300008375"
        ],
        "id": 7004644,
        "name:xx": "Nola"
      }
    },
    {
      "geometry": {
        "type": "Point",
        "coordinates": [
          14.116667,
          40.816667
        ]
      },
      "type": "Feature",
      "properties": {
        "hierarchy": [
          "tgn:7004647",
          "tgn:7003013",
          "tgn:7003005",
          "tgn:1000003",
          "tgn:1000080",
          "tgn:7029392"
        ],
        "placetype": [
          "aat:300008347",
          "aat:300000810",
          "aat:300008389",
          "aat:300387512",
          "aat:300387272",
          "aat:300120599"
        ],
        "id": 7004647,
        "name:xx": "Pozzuoli"
      }
    },
    {
      "geometry": {
        "type": "Point",
        "coordinates": [
          14.366667,
          40.616667
        ]
      },
      "type": "Feature",
      "properties": {
        "hierarchy": [
          "tgn:7004648",
          "tgn:7003013",
          "tgn:7003005",
          "tgn:1000003",
          "tgn:1000080",
          "tgn:7029392"
        ],
        "placetype": [
          "aat:300008347",
          "aat:300008375",
          "aat:300120599",
          "aat:300387292"
        ],
        "id": 7004648,
        "name:it": "Sorrento"
      }
    }
  ]
}
