{
  "geometry": {
    "type": "Point",
    "coordinates": [
      -77.7667,
      37.6333
    ]
  },
  "type": "Feature",
  "properties": {
    "hierarchy": [
      "tgn:2223848",
      "tgn:1000001",
      "tgn:7012149",
      "tgn:2002163",
      "tgn:7007919",
      "tgn:7029392"
    ],
    "placetype": [
      "aat:300006191"
    ],
    "id": 2223848,
    "name:xx": "Carter and Harrell Lake"
  }
}
