{
  "geometry": {
    "type": "Point",
    "coordinates": [
      -112.3333,
      34.1833
    ]
  },
  "type": "Feature",
  "properties": {
    "hierarchy": [
      "tgn:2476074",
      "tgn:1000001",
      "tgn:7006451",
      "tgn:7012149",
      "tgn:2000103",
      "tgn:7029392"
    ],
    "placetype": [
      "aat:300266640"
    ],
    "id": 2476074,
    "name:xx": "Lukes Hoist Divide"
  }
}
