{
  "geometry": {
    "type": "Point",
    "coordinates": [
      176.05,
      -39.1333
    ]
  },
  "type": "Feature",
  "properties": {
    "hierarchy": [
      "tgn:1105501",
      "tgn:1008380",
      "tgn:7520093",
      "tgn:1000226",
      "tgn:1000006",
      "tgn:7029392"
    ],
    "placetype": [
      "aat:300008795"
    ],
    "id": 1105501,
    "name:xx": "Makorako"
  }
}
