{
  "geometry": {
    "type": "Point",
    "coordinates": [
      -88.0167,
      46.1333
    ]
  },
  "type": "Feature",
  "properties": {
    "hierarchy": [
      "tgn:2353950",
      "tgn:1000001",
      "tgn:2000956",
      "tgn:7012149",
      "tgn:7007520",
      "tgn:7029392"
    ],
    "placetype": [
      "aat:300008347"
    ],
    "id": 2353950,
    "name:xx": "Golden"
  }
}
