{
  "geometry": {
    "type": "Point",
    "coordinates": [
      -59.2333,
      -35.1667
    ]
  },
  "type": "Feature",
  "properties": {
    "hierarchy": [
      "tgn:1019599",
      "tgn:1001160",
      "tgn:7006477",
      "tgn:1000002",
      "tgn:7029392"
    ],
    "placetype": [
      "aat:300008347"
    ],
    "id": 1019599,
    "name:xx": "José Santos Arévalo"
  }
}
