{
  "geometry": {
    "type": "Point",
    "coordinates": [
      30.816667,
      27.55
    ]
  },
  "type": "Feature",
  "properties": {
    "hierarchy": [
      "tgn:7528748",
      "tgn:7001242",
      "tgn:7016833",
      "tgn:1001114",
      "tgn:7029392"
    ],
    "placetype": [
      "aat:300005926"
    ],
    "name:en": "Sīdī 'Abd al Qādir",
    "id": 7528748
  }
}
