{
  "geometry": {
    "type": "Point",
    "coordinates": [
      30.853173,
      28.738369
    ]
  },
  "type": "Feature",
  "properties": {
    "hierarchy": [
      "tgn:7541416",
      "tgn:7001242",
      "tgn:7016833",
      "tgn:1001142",
      "tgn:7029392"
    ],
    "placetype": [
      "aat:300008347"
    ],
    "name:en": "Nazlat an Naşārá",
    "id": 7541416
  }
}
