{
  "geometry": {
    "type": "Point",
    "coordinates": [
      -118.7167,
      37.4333
    ]
  },
  "type": "Feature",
  "properties": {
    "hierarchy": [
      "tgn:2338654",
      "tgn:1000001",
      "tgn:7012149",
      "tgn:2000183",
      "tgn:7007157",
      "tgn:7029392"
    ],
    "placetype": [
      "aat:300008680"
    ],
    "id": 2338654,
    "name:xx": "Francis Lake"
  }
}
