{
  "geometry": {
    "type": "Point",
    "coordinates": [
      -82.2667,
      31.2667
    ]
  },
  "type": "Feature",
  "properties": {
    "hierarchy": [
      "tgn:2023200",
      "tgn:1000001",
      "tgn:7012149",
      "tgn:2000404",
      "tgn:7007248",
      "tgn:7029392"
    ],
    "placetype": [
      "aat:300387016"
    ],
    "id": 2023200,
    "name:xx": "Homestead"
  }
}
