{
  "geometry": {
    "type": "Point",
    "coordinates": [
      -71.8667,
      10.1833
    ]
  },
  "type": "Feature",
  "properties": {
    "hierarchy": [
      "tgn:1128339",
      "tgn:1001985",
      "tgn:1000002",
      "tgn:1000059",
      "tgn:7029392"
    ],
    "placetype": [
      "aat:300008707"
    ],
    "id": 1128339,
    "name:xx": "Palmar, Río"
  }
}
