{
  "geometry": {
    "type": "Point",
    "coordinates": [
      -113.2667,
      34.55
    ]
  },
  "type": "Feature",
  "properties": {
    "hierarchy": [
      "tgn:2256147",
      "tgn:1000001",
      "tgn:7006451",
      "tgn:7012149",
      "tgn:2000103",
      "tgn:7029392"
    ],
    "placetype": [
      "aat:300266640"
    ],
    "id": 2256147,
    "name:xx": "Copper Ridge"
  }
}
