{
  "geometry": {
    "type": "Point",
    "coordinates": [
      -75.3833,
      42.3167
    ]
  },
  "type": "Feature",
  "properties": {
    "hierarchy": [
      "tgn:2525875",
      "tgn:1000001",
      "tgn:7012149",
      "tgn:7014318",
      "tgn:7007568",
      "tgn:7029392"
    ],
    "placetype": [
      "aat:300008798"
    ],
    "id": 2525875,
    "name:xx": "Moses, Mount"
  }
}
