{
  "geometry": {
    "type": "Point",
    "coordinates": [
      -89.7333,
      30.9833
    ]
  },
  "type": "Feature",
  "properties": {
    "hierarchy": [
      "tgn:2621097",
      "tgn:1000001",
      "tgn:7012149",
      "tgn:2000912",
      "tgn:7007256",
      "tgn:7029392"
    ],
    "placetype": [
      "aat:300008680"
    ],
    "id": 2621097,
    "name:xx": "Road Lake"
  }
}
