{
  "geometry": {
    "type": "Point",
    "coordinates": [
      29.2333,
      36.7333
    ]
  },
  "type": "Feature",
  "properties": {
    "hierarchy": [
      "tgn:1085855",
      "tgn:1001438",
      "tgn:1000004",
      "tgn:7018451",
      "tgn:1000144",
      "tgn:7029392"
    ],
    "placetype": [
      "aat:300008347"
    ],
    "id": 1085855,
    "name:xx": "Uzumlu"
  }
}
