{
  "geometry": {
    "type": "Point",
    "coordinates": [
      -83.4833,
      37.4333
    ]
  },
  "type": "Feature",
  "properties": {
    "hierarchy": [
      "tgn:2650570",
      "tgn:1000001",
      "tgn:2000772",
      "tgn:7012149",
      "tgn:7007255",
      "tgn:7029392"
    ],
    "placetype": [
      "aat:300008699"
    ],
    "id": 2650570,
    "name:xx": "Sebastian Branch"
  }
}
