{
  "geometry": {
    "type": "Point",
    "coordinates": [
      -87.55,
      31.3167
    ]
  },
  "type": "Feature",
  "properties": {
    "hierarchy": [
      "tgn:2641213",
      "tgn:7002659",
      "tgn:1000001",
      "tgn:7012149",
      "tgn:2000049",
      "tgn:7029392"
    ],
    "placetype": [
      "aat:300008706"
    ],
    "id": 2641213,
    "name:xx": "Sand Creek"
  }
}
