{
  "geometry": {
    "type": "Point",
    "coordinates": [
      22.25,
      56.983
    ]
  },
  "type": "Feature",
  "properties": {
    "hierarchy": [
      "tgn:7006612",
      "tgn:1000003",
      "tgn:7006542",
      "tgn:7029392"
    ],
    "placetype": [
      "aat:300387064",
      "aat:300265612",
      "aat:300387081"
    ],
    "id": 7006612,
    "name:xx": "Telšiai"
  }
}
