{
  "geometry": {
    "type": "Point",
    "coordinates": [
      -103.4167,
      68.0333
    ]
  },
  "type": "Feature",
  "properties": {
    "hierarchy": [
      "tgn:1123712",
      "tgn:7005685",
      "tgn:1000001",
      "tgn:7024197",
      "tgn:7029392"
    ],
    "placetype": [
      "aat:300008707"
    ],
    "id": 1123712,
    "name:xx": "Ellice"
  }
}
