{
  "geometry": {
    "type": "Point",
    "coordinates": [
      -104.45,
      48.4667
    ]
  },
  "type": "Feature",
  "properties": {
    "hierarchy": [
      "tgn:2198978",
      "tgn:1000001",
      "tgn:7012149",
      "tgn:2001305",
      "tgn:7007524",
      "tgn:7029392"
    ],
    "placetype": [
      "aat:300008791"
    ],
    "id": 2198978,
    "name:xx": "Bruces Island"
  }
}
