{
  "type": "FeatureCollection",
  "features": [
    {
      "geometry": {
        "type": "Point",
        "coordinates": [
          7.133333,
          50.466667
        ]
      },
      "type": "Feature",
      "properties": {
        "hierarchy": [
          "tgn:7107360",
          "tgn:1000003",
          "tgn:7003682",
          "tgn:7000084",
          "tgn:7029392"
        ],
        "placetype": [
          "aat:300008347"
        ],
        "id": 7107360,
        "name:xx": "Schelborn"
      }
    },
    {
      "geometry": {
        "type": "Point",
        "coordinates": [
          12.6,
          48.183333
        ]
      },
      "type": "Feature",
      "properties": {
        "hierarchy": [
          "tgn:7107361",
          "tgn:7003669",
          "tgn:1000003",
          "tgn:7000084",
          "tgn:7029392"
        ],
        "placetype": [
          "aat:300000206"
        ],
        "id": 7107361,
        "name:xx": "Scheitzenham"
      }
    },
    {
      "geometry": {
        "type": "Point",
        "coordinates": [
          13.283333,
          50.7
        ]
      },
      "type": "Feature",
      "properties": {
        "hierarchy": [
          "tgn:7107362",
          "tgn:1000003",
          "tgn:7003685",
          "tgn:7000084",
          "tgn:7029392"
        ],
        "placetype": [
          "aat:300008863"
        ],
        "id": 7107362,
        "name:xx": "Scheitwald"
      }
    },
    {
      "geometry": {
        "type": "Point",
        "coordinates": [
          9.533333,
          50.083333
        ]
      },
      "type": "Feature",
      "properties": {
        "hierarchy": [
          "tgn:7107363",
          "tgn:7003669",
          "tgn:1000003",
          "tgn:7000084",
          "tgn:7029392"
        ],
        "placetype": [
          "aat:300008863"
        ],
        "id": 7107363,
        "name:xx": "Scheit-Wald"
      }
    },
    {
      "geometry": {
        "type": "Point",
        "coordinates": [
          11.1,
          51.366667
        ]
      },
      "type": "Feature",
      "properties": {
        "hierarchy": [
          "tgn:7107364",
          "tgn:1000003",
          "tgn:7003689",
          "tgn:7000084",
          "tgn:7029392"
        ],
        "placetype": [
          "aat:300008777"
        ],
        "id": 7107364,
        "name:xx": "Scheitsköpfe"
      }
    },
    {
      "geometry": {
        "type": "Point",
        "coordinates": [
          11.4,
          50.566667
        ]
      },
      "type": "Feature",
      "properties": {
        "hierarchy": [
          "tgn:7107365",
          "tgn:1000003",
          "tgn:7003689",
          "tgn:7000084",
          "tgn:7029392"
        ],
        "placetype": [
          "aat:300008777"
        ],
        "id": 7107365,
        "name:xx": "Scheitingshügel"
      }
    },
    {
      "geometry": {
        "type": "Point",
        "coordinates": [
          11.083333,
          47.783333
        ]
      },
      "type": "Feature",
      "properties": {
        "hierarchy": [
          "tgn:7107366",
          "tgn:7003669",
          "tgn:1000003",
          "tgn:7000084",
          "tgn:7029392"
        ],
        "placetype": [
          "aat:300386886"
        ],
        "id": 7107366,
        "name:xx": "Scheithaufer Filz"
      }
    },
    {
      "geometry": {
        "type": "Point",
        "coordinates": [
          8.516667,
          51.516667
        ]
      },
      "type": "Feature",
      "properties": {
        "hierarchy": [
          "tgn:7107367",
          "tgn:1000003",
          "tgn:7003677",
          "tgn:7000084",
          "tgn:7029392"
        ],
        "placetype": [
          "aat:300000206"
        ],
        "id": 7107367,
        "name:xx": "Scheiterfeld"
      }
    },
    {
      "geometry": {
        "type": "Point",
        "coordinates": [
          9.7,
          49.466667
        ]
      },
      "type": "Feature",
      "properties": {
        "hierarchy": [
          "tgn:7107368",
          "tgn:7003692",
          "tgn:1000003",
          "tgn:7000084",
          "tgn:7029392"
        ],
        "placetype": [
          "aat:300008863"
        ],
        "id": 7107368,
        "name:xx": "Scheitenschlag"
      }
    },
    {
      "geometry": {
        "type": "Point",
        "coordinates": [
          6.2,
          50.016667
        ]
      },
      "type": "Feature",
      "properties": {
        "hierarchy": [
          "tgn:7107369",
          "tgn:1000003",
          "tgn:7003682",
          "tgn:7000084",
          "tgn:7029392"
        ],
        "placetype": [
          "aat:300008347"
        ],
        "id": 7107369,
        "name:xx": "Scheitenkorb"
      }
    }
  ]
}
