{
  "geometry": {
    "type": "Point",
    "coordinates": [
      110.7667,
      19.6833
    ]
  },
  "type": "Feature",
  "properties": {
    "hierarchy": [
      "tgn:1072559",
      "tgn:1000004",
      "tgn:7001800",
      "tgn:1000111",
      "tgn:7029392"
    ],
    "placetype": [
      "aat:300008347"
    ],
    "id": 1072559,
    "name:xx": "Wenchang"
  }
}
