{
  "geometry": {
    "type": "Point",
    "coordinates": [
      -80.45,
      39.6333
    ]
  },
  "type": "Feature",
  "properties": {
    "hierarchy": [
      "tgn:2727571",
      "tgn:1000001",
      "tgn:7012149",
      "tgn:2002301",
      "tgn:7013961",
      "tgn:7029392"
    ],
    "placetype": [
      "aat:300008699"
    ],
    "id": 2727571,
    "name:xx": "Trail Fork"
  }
}
