{
  "geometry": {
    "type": "Point",
    "coordinates": [
      13.6167,
      -21.1833
    ]
  },
  "type": "Feature",
  "properties": {
    "hierarchy": [
      "tgn:1131213",
      "tgn:7001242",
      "tgn:1000198",
      "tgn:7029392"
    ],
    "placetype": [
      "aat:300008707"
    ],
    "id": 1131213,
    "name:xx": "Ugab"
  }
}
