{
  "type": "FeatureCollection",
  "features": [
    {
      "geometry": {
        "type": "Point",
        "coordinates": [
          9.416667,
          47.8
        ]
      },
      "type": "Feature",
      "properties": {
        "hierarchy": [
          "tgn:7062630",
          "tgn:7003692",
          "tgn:1000003",
          "tgn:7000084",
          "tgn:7029392"
        ],
        "placetype": [
          "aat:300008347"
        ],
        "id": 7062630,
        "name:xx": "Azenweiler"
      }
    },
    {
      "geometry": {
        "type": "Point",
        "coordinates": [
          11.3,
          50.033333
        ]
      },
      "type": "Feature",
      "properties": {
        "hierarchy": [
          "tgn:7062631",
          "tgn:7003669",
          "tgn:1000003",
          "tgn:7000084",
          "tgn:7029392"
        ],
        "placetype": [
          "aat:300008347"
        ],
        "id": 7062631,
        "name:xx": "Azendorf"
      }
    },
    {
      "geometry": {
        "type": "Point",
        "coordinates": [
          10.766667,
          48.4
        ]
      },
      "type": "Feature",
      "properties": {
        "hierarchy": [
          "tgn:7062632",
          "tgn:7003669",
          "tgn:1000003",
          "tgn:7000084",
          "tgn:7029392"
        ],
        "placetype": [
          "aat:300008347"
        ],
        "id": 7062632,
        "name:xx": "Aystetten"
      }
    },
    {
      "geometry": {
        "type": "Point",
        "coordinates": [
          12.933333,
          49.05
        ]
      },
      "type": "Feature",
      "properties": {
        "hierarchy": [
          "tgn:7062633",
          "tgn:7003669",
          "tgn:1000003",
          "tgn:7000084",
          "tgn:7029392"
        ],
        "placetype": [
          "aat:300008347"
        ],
        "id": 7062633,
        "name:xx": "Ayrhof"
      }
    },
    {
      "geometry": {
        "type": "Point",
        "coordinates": [
          12.15,
          51.066667
        ]
      },
      "type": "Feature",
      "properties": {
        "hierarchy": [
          "tgn:7062634",
          "tgn:1000003",
          "tgn:7003687",
          "tgn:7000084",
          "tgn:7029392"
        ],
        "placetype": [
          "aat:300008347"
        ],
        "id": 7062634,
        "name:xx": "Aylsdorf"
      }
    },
    {
      "geometry": {
        "type": "Point",
        "coordinates": [
          8.966667,
          52.383333
        ]
      },
      "type": "Feature",
      "properties": {
        "hierarchy": [
          "tgn:7062635",
          "tgn:1000003",
          "tgn:7003676",
          "tgn:7000084",
          "tgn:7029392"
        ],
        "placetype": [
          "aat:300008699"
        ],
        "id": 7062635,
        "name:xx": "Aue"
      }
    },
    {
      "geometry": {
        "type": "Point",
        "coordinates": [
          10.383333,
          52.35
        ]
      },
      "type": "Feature",
      "properties": {
        "hierarchy": [
          "tgn:7062636",
          "tgn:1000003",
          "tgn:7003676",
          "tgn:7000084",
          "tgn:7029392"
        ],
        "placetype": [
          "aat:300008699"
        ],
        "id": 7062636,
        "name:xx": "Aue"
      }
    }
  ]
}
