{
  "type": "FeatureCollection",
  "features": [
    {
      "geometry": {
        "type": "Point",
        "coordinates": [
          -1.183333,
          60.433333
        ]
      },
      "type": "Feature",
      "properties": {
        "hierarchy": [
          "tgn:7448820",
          "tgn:7002444",
          "tgn:1000003",
          "tgn:7029508",
          "tgn:7008591",
          "tgn:7029392"
        ],
        "placetype": [
          "aat:300132316"
        ],
        "name:en": "Swinister Voe",
        "id": 7448820
      }
    },
    {
      "geometry": {
        "type": "Point",
        "coordinates": [
          -1.15,
          60.4
        ]
      },
      "type": "Feature",
      "properties": {
        "hierarchy": [
          "tgn:7448821",
          "tgn:7002444",
          "tgn:1000003",
          "tgn:7029508",
          "tgn:7008591",
          "tgn:7029392"
        ],
        "placetype": [
          "aat:300132316"
        ],
        "name:en": "Swining Voe",
        "id": 7448821
      }
    },
    {
      "geometry": {
        "type": "Point",
        "coordinates": [
          -1.666667,
          55.533333
        ]
      },
      "type": "Feature",
      "properties": {
        "hierarchy": [
          "tgn:7448823",
          "tgn:7002445",
          "tgn:1000003",
          "tgn:7008165",
          "tgn:7008591",
          "tgn:7029392"
        ],
        "placetype": [
          "aat:300008347"
        ],
        "name:en": "Swinhoe",
        "id": 7448823
      }
    },
    {
      "geometry": {
        "type": "Point",
        "coordinates": [
          1.183333,
          51.133333
        ]
      },
      "type": "Feature",
      "properties": {
        "hierarchy": [
          "tgn:7448824",
          "tgn:7002445",
          "tgn:1000003",
          "tgn:7008153",
          "tgn:7008591",
          "tgn:7029392"
        ],
        "placetype": [
          "aat:300008347"
        ],
        "name:en": "Swingfield",
        "id": 7448824
      }
    },
    {
      "geometry": {
        "type": "Point",
        "coordinates": [
          -3.316667,
          58.3
        ]
      },
      "type": "Feature",
      "properties": {
        "hierarchy": [
          "tgn:7448826",
          "tgn:7002444",
          "tgn:1000003",
          "tgn:7008082",
          "tgn:7008591",
          "tgn:7029392"
        ],
        "placetype": [
          "aat:300008347"
        ],
        "name:en": "Swiney",
        "id": 7448826
      }
    },
    {
      "geometry": {
        "type": "Point",
        "coordinates": [
          -0.833333,
          53.683333
        ]
      },
      "type": "Feature",
      "properties": {
        "hierarchy": [
          "tgn:7448829",
          "tgn:7002445",
          "tgn:1000003",
          "tgn:7019057",
          "tgn:7008591",
          "tgn:7029392"
        ],
        "placetype": [
          "aat:300008347"
        ],
        "name:en": "Swinefleet",
        "id": 7448829
      }
    }
  ]
}
