{
  "geometry": {
    "type": "Point",
    "coordinates": [
      -123.45,
      40.3333
    ]
  },
  "type": "Feature",
  "properties": {
    "hierarchy": [
      "tgn:2285089",
      "tgn:1000001",
      "tgn:7012149",
      "tgn:7007157",
      "tgn:2000191",
      "tgn:7029392"
    ],
    "placetype": [
      "aat:300266640"
    ],
    "id": 2285089,
    "name:xx": "Devils Backbone"
  }
}
