{
  "geometry": {
    "type": "Point",
    "coordinates": [
      -83.0667,
      35.1833
    ]
  },
  "type": "Feature",
  "properties": {
    "hierarchy": [
      "tgn:2144926",
      "tgn:1000001",
      "tgn:7012149",
      "tgn:2001508",
      "tgn:7007709",
      "tgn:7029392"
    ],
    "placetype": [
      "aat:300008798"
    ],
    "id": 2144926,
    "name:xx": "Bald Knob"
  }
}
