{
  "geometry": {
    "type": "Point",
    "coordinates": [
      -95.0167,
      29.1667
    ]
  },
  "type": "Feature",
  "properties": {
    "hierarchy": [
      "tgn:2487983",
      "tgn:1000001",
      "tgn:7012149",
      "tgn:1002401",
      "tgn:7007826",
      "tgn:7029392"
    ],
    "placetype": [
      "aat:300008850"
    ],
    "id": 2487983,
    "name:xx": "Maggies Point"
  }
}
