{
  "geometry": {
    "type": "Point",
    "coordinates": [
      -94.1167,
      36.7333
    ]
  },
  "type": "Feature",
  "properties": {
    "hierarchy": [
      "tgn:2238802",
      "tgn:1000001",
      "tgn:7012149",
      "tgn:2001216",
      "tgn:7007523",
      "tgn:7029392"
    ],
    "placetype": [
      "aat:300008697"
    ],
    "id": 2238802,
    "name:xx": "Christian Spring"
  }
}
