{
  "geometry": {
    "type": "Point",
    "coordinates": [
      -77.6333,
      40.65
    ]
  },
  "type": "Feature",
  "properties": {
    "hierarchy": [
      "tgn:2247508",
      "tgn:1000001",
      "tgn:7012149",
      "tgn:1002669",
      "tgn:7007710",
      "tgn:7029392"
    ],
    "placetype": [
      "aat:300008699"
    ],
    "id": 2247508,
    "name:xx": "Coffee Run"
  }
}
