{
  "geometry": {
    "type": "Point",
    "coordinates": [
      -134.6833,
      56.2667
    ]
  },
  "type": "Feature",
  "properties": {
    "hierarchy": [
      "tgn:2445595",
      "tgn:7006450",
      "tgn:1000001",
      "tgn:7012149",
      "tgn:2124002",
      "tgn:7029392"
    ],
    "placetype": [
      "aat:300008680"
    ],
    "id": 2445595,
    "name:xx": "Leona Lake"
  }
}
