{
  "type": "FeatureCollection",
  "features": [
    {
      "geometry": {
        "type": "Point",
        "coordinates": [
          -103.9333,
          43.1
        ]
      },
      "type": "Feature",
      "properties": {
        "hierarchy": [
          "tgn:2245780",
          "tgn:1000001",
          "tgn:2001793",
          "tgn:7012149",
          "tgn:7007713",
          "tgn:7029392"
        ],
        "placetype": [
          "aat:300008706"
        ],
        "id": 2245780,
        "name:xx": "Coal Creek"
      }
    },
    {
      "geometry": {
        "type": "Point",
        "coordinates": [
          -83.8333,
          36.55
        ]
      },
      "type": "Feature",
      "properties": {
        "hierarchy": [
          "tgn:2245782",
          "tgn:1000001",
          "tgn:7012149",
          "tgn:2001849",
          "tgn:7007825",
          "tgn:7029392"
        ],
        "placetype": [
          "aat:300008706"
        ],
        "id": 2245782,
        "name:xx": "Coal Creek"
      }
    },
    {
      "geometry": {
        "type": "Point",
        "coordinates": [
          -84.9333,
          35.8
        ]
      },
      "type": "Feature",
      "properties": {
        "hierarchy": [
          "tgn:2245783",
          "tgn:1000001",
          "tgn:7012149",
          "tgn:7007825",
          "tgn:7029392"
        ],
        "placetype": [
          "aat:300008706"
        ],
        "id": 2245783,
        "name:xx": "Coal Creek"
      }
    },
    {
      "geometry": {
        "type": "Point",
        "coordinates": [
          -84.2333,
          36.15
        ]
      },
      "type": "Feature",
      "properties": {
        "hierarchy": [
          "tgn:2245784",
          "tgn:2001837",
          "tgn:1000001",
          "tgn:7012149",
          "tgn:7007825",
          "tgn:7029392"
        ],
        "placetype": [
          "aat:300008706"
        ],
        "id": 2245784,
        "name:xx": "Coal Creek"
      }
    },
    {
      "geometry": {
        "type": "Point",
        "coordinates": [
          -99.4167,
          29.8833
        ]
      },
      "type": "Feature",
      "properties": {
        "hierarchy": [
          "tgn:2245785",
          "tgn:1000001",
          "tgn:2001938",
          "tgn:7012149",
          "tgn:7007826",
          "tgn:7029392"
        ],
        "placetype": [
          "aat:300008706"
        ],
        "id": 2245785,
        "name:xx": "Coal Creek"
      }
    },
    {
      "geometry": {
        "type": "Point",
        "coordinates": [
          -95.15,
          33.6667
        ]
      },
      "type": "Feature",
      "properties": {
        "hierarchy": [
          "tgn:2245786",
          "tgn:1000001",
          "tgn:7012149",
          "tgn:2002061",
          "tgn:7007826",
          "tgn:7029392"
        ],
        "placetype": [
          "aat:300008706"
        ],
        "id": 2245786,
        "name:xx": "Coal Creek"
      }
    },
    {
      "geometry": {
        "type": "Point",
        "coordinates": [
          -96.8833,
          29.2333
        ]
      },
      "type": "Feature",
      "properties": {
        "hierarchy": [
          "tgn:2245787",
          "tgn:1000001",
          "tgn:7012149",
          "tgn:1002578",
          "tgn:7007826",
          "tgn:7029392"
        ],
        "placetype": [
          "aat:300008706"
        ],
        "id": 2245787,
        "name:xx": "Coal Creek"
      }
    },
    {
      "geometry": {
        "type": "Point",
        "coordinates": [
          -98.6833,
          30.4167
        ]
      },
      "type": "Feature",
      "properties": {
        "hierarchy": [
          "tgn:2245788",
          "tgn:1000001",
          "tgn:7012149",
          "tgn:7007826",
          "tgn:7029392"
        ],
        "placetype": [
          "aat:300008706"
        ],
        "id": 2245788,
        "name:xx": "Coal Creek"
      }
    },
    {
      "geometry": {
        "type": "Point",
        "coordinates": [
          -99.1,
          33.5667
        ]
      },
      "type": "Feature",
      "properties": {
        "hierarchy": [
          "tgn:2245789",
          "tgn:1000001",
          "tgn:2001939",
          "tgn:7012149",
          "tgn:7007826",
          "tgn:7029392"
        ],
        "placetype": [
          "aat:300008706"
        ],
        "id": 2245789,
        "name:xx": "Coal Creek"
      }
    }
  ]
}
