{
  "geometry": {
    "type": "Point",
    "coordinates": [
      -79.5667,
      44.95
    ]
  },
  "type": "Feature",
  "properties": {
    "hierarchy": [
      "tgn:1117500",
      "tgn:7005685",
      "tgn:1000001",
      "tgn:7013154",
      "tgn:7029392"
    ],
    "placetype": [
      "aat:300008680"
    ],
    "id": 1117500,
    "name:xx": "Nine Mile Lake"
  }
}
