{
  "geometry": {
    "type": "Point",
    "coordinates": [
      -80.6833,
      34.7833
    ]
  },
  "type": "Feature",
  "properties": {
    "hierarchy": [
      "tgn:2160927",
      "tgn:1000001",
      "tgn:7012149",
      "tgn:2001753",
      "tgn:7007712",
      "tgn:7029392"
    ],
    "placetype": [
      "aat:300006191"
    ],
    "id": 2160927,
    "name:xx": "Belks Pond"
  }
}
