{
  "geometry": {
    "type": "Point",
    "coordinates": [
      -78.55,
      35.65
    ]
  },
  "type": "Feature",
  "properties": {
    "hierarchy": [
      "tgn:2745143",
      "tgn:1000001",
      "tgn:7012149",
      "tgn:2001548",
      "tgn:7007709",
      "tgn:7029392"
    ],
    "placetype": [
      "aat:300008347"
    ],
    "id": 2745143,
    "name:xx": "Village Of White Oak"
  }
}
