{
  "geometry": {
    "type": "Point",
    "coordinates": [
      -82.15,
      26.6167
    ]
  },
  "type": "Feature",
  "properties": {
    "hierarchy": [
      "tgn:2607888",
      "tgn:1000001",
      "tgn:7012149",
      "tgn:1002582",
      "tgn:7007240",
      "tgn:7029392"
    ],
    "placetype": [
      "aat:300008791"
    ],
    "id": 2607888,
    "name:xx": "Rat Key"
  }
}
