{
  "geometry": {
    "type": "Point",
    "coordinates": [
      -80.55,
      38.4667
    ]
  },
  "type": "Feature",
  "properties": {
    "hierarchy": [
      "tgn:2120386",
      "tgn:1000001",
      "tgn:7012149",
      "tgn:2002300",
      "tgn:7013961",
      "tgn:7029392"
    ],
    "placetype": [
      "aat:300387016"
    ],
    "id": 2120386,
    "name:xx": "Weese"
  }
}
