{
  "geometry": {
    "type": "Point",
    "coordinates": [
      -87.35,
      41.35
    ]
  },
  "type": "Feature",
  "properties": {
    "hierarchy": [
      "tgn:2687672",
      "tgn:1000001",
      "tgn:7012149",
      "tgn:1002569",
      "tgn:7007252",
      "tgn:7029392"
    ],
    "placetype": [
      "aat:300008699"
    ],
    "id": 2687672,
    "name:xx": "Spring Run"
  }
}
