{
  "geometry": {
    "type": "Point",
    "coordinates": [
      -73.5667,
      41.2833
    ]
  },
  "type": "Feature",
  "properties": {
    "hierarchy": [
      "tgn:2746548",
      "tgn:1000001",
      "tgn:7012149",
      "tgn:7014612",
      "tgn:7007568",
      "tgn:7029392"
    ],
    "placetype": [
      "aat:300008707"
    ],
    "id": 2746548,
    "name:xx": "Waccabuc River"
  }
}
