{
  "geometry": {
    "type": "Point",
    "coordinates": [
      74.977778,
      34.35
    ]
  },
  "type": "Feature",
  "properties": {
    "hierarchy": [
      "tgn:7586175",
      "tgn:1000004",
      "tgn:7000198",
      "tgn:7000799",
      "tgn:7029392"
    ],
    "placetype": [
      "aat:300008347"
    ],
    "name:en": "Narāyannāg",
    "id": 7586175
  }
}
