{
  "geometry": {
    "type": "Point",
    "coordinates": [
      -108.8333,
      37.8667
    ]
  },
  "type": "Feature",
  "properties": {
    "hierarchy": [
      "tgn:7023054",
      "tgn:1000001",
      "tgn:7012149",
      "tgn:7007158",
      "tgn:7029392"
    ],
    "placetype": [
      "aat:300006191"
    ],
    "id": 7023054,
    "name:xx": "Sand Rock Reservoir"
  }
}
