{
  "geometry": {
    "type": "Point",
    "coordinates": [
      -81.2833,
      26.2833
    ]
  },
  "type": "Feature",
  "properties": {
    "hierarchy": [
      "tgn:1135451",
      "tgn:1000001",
      "tgn:1002289",
      "tgn:7012149",
      "tgn:7007240",
      "tgn:7029392"
    ],
    "placetype": [
      "aat:300343520"
    ],
    "id": 1135451,
    "name:xx": "Okaloacoochee Slough"
  }
}
