{
  "geometry": {
    "type": "Point",
    "coordinates": [
      -66.45,
      -55.183333
    ]
  },
  "type": "Feature",
  "properties": {
    "hierarchy": [
      "tgn:7280092",
      "tgn:1001702",
      "tgn:1000049",
      "tgn:1000002",
      "tgn:7029392"
    ],
    "placetype": [
      "aat:300386846"
    ],
    "id": 7280092,
    "name:xx": "Revellín, Punta"
  }
}
