{
  "geometry": {
    "type": "Point",
    "coordinates": [
      -107.95,
      35.3333
    ]
  },
  "type": "Feature",
  "properties": {
    "hierarchy": [
      "tgn:2402501",
      "tgn:1000001",
      "tgn:7012149",
      "tgn:7019676",
      "tgn:7007566",
      "tgn:7029392"
    ],
    "placetype": [
      "aat:300000390"
    ],
    "id": 2402501,
    "name:xx": "Hoskins and Robinson Pit"
  }
}
