{
  "geometry": {
    "type": "Point",
    "coordinates": [
      19.5833,
      49.3667
    ]
  },
  "type": "Feature",
  "properties": {
    "hierarchy": [
      "tgn:1027601",
      "tgn:7027130",
      "tgn:1000003",
      "tgn:7011765",
      "tgn:7029392"
    ],
    "placetype": [
      "aat:300008347"
    ],
    "id": 1027601,
    "name:xx": "Trstená"
  }
}
