{
  "geometry": {
    "type": "Point",
    "coordinates": [
      21.4333,
      47.8333
    ]
  },
  "type": "Feature",
  "properties": {
    "hierarchy": [
      "tgn:1042348",
      "tgn:1000385",
      "tgn:1000003",
      "tgn:7006278",
      "tgn:7029392"
    ],
    "placetype": [
      "aat:300008347"
    ],
    "id": 1042348,
    "name:xx": "Hajdúnánás"
  }
}
