{
  "geometry": {
    "type": "Point",
    "coordinates": [
      -82.4167,
      27.2833
    ]
  },
  "type": "Feature",
  "properties": {
    "hierarchy": [
      "tgn:2491796",
      "tgn:1000001",
      "tgn:7012149",
      "tgn:1002870",
      "tgn:7007240",
      "tgn:7029392"
    ],
    "placetype": [
      "aat:300008680"
    ],
    "id": 2491796,
    "name:xx": "Marae, Lake"
  }
}
