{
  "geometry": {
    "type": "Point",
    "coordinates": [
      -134.9167,
      57.2667
    ]
  },
  "type": "Feature",
  "properties": {
    "hierarchy": [
      "tgn:2716251",
      "tgn:7006450",
      "tgn:1000001",
      "tgn:7012149",
      "tgn:2124002",
      "tgn:7029392"
    ],
    "placetype": [
      "aat:300386845"
    ],
    "id": 2716251,
    "name:xx": "The Basin"
  }
}
