{
  "geometry": {
    "type": "Point",
    "coordinates": [
      -76.25,
      38.7167
    ]
  },
  "type": "Feature",
  "properties": {
    "hierarchy": [
      "tgn:2584580",
      "tgn:1000001",
      "tgn:2000939",
      "tgn:7012149",
      "tgn:7007516",
      "tgn:7029392"
    ],
    "placetype": [
      "aat:300008850"
    ],
    "id": 2584580,
    "name:xx": "Piney Point"
  }
}
