{
  "geometry": {
    "type": "Point",
    "coordinates": [
      -93.8833,
      35.3333
    ]
  },
  "type": "Feature",
  "properties": {
    "hierarchy": [
      "tgn:2666485",
      "tgn:1000001",
      "tgn:7016172",
      "tgn:7012149",
      "tgn:2000128",
      "tgn:7029392"
    ],
    "placetype": [
      "aat:300006191"
    ],
    "id": 2666485,
    "name:xx": "Sixmile Creek Site 25 Reservoir"
  }
}
