{
  "type": "FeatureCollection",
  "features": [
    {
      "geometry": {
        "type": "Point",
        "coordinates": [
          -76.25,
          35.75
        ]
      },
      "type": "Feature",
      "properties": {
        "hierarchy": [
          "tgn:2429420",
          "tgn:1000001",
          "tgn:7012149",
          "tgn:2001545",
          "tgn:7007709",
          "tgn:7029392"
        ],
        "placetype": [
          "aat:300008706"
        ],
        "id": 2429420,
        "name:xx": "Juniper Creek"
      }
    },
    {
      "geometry": {
        "type": "Point",
        "coordinates": [
          -78.0833,
          35.7667
        ]
      },
      "type": "Feature",
      "properties": {
        "hierarchy": [
          "tgn:2429421",
          "tgn:1000001",
          "tgn:7012149",
          "tgn:7007709",
          "tgn:7029392"
        ],
        "placetype": [
          "aat:300008706"
        ],
        "id": 2429421,
        "name:xx": "Juniper Creek"
      }
    },
    {
      "geometry": {
        "type": "Point",
        "coordinates": [
          -79.4833,
          34.9333
        ]
      },
      "type": "Feature",
      "properties": {
        "hierarchy": [
          "tgn:2429422",
          "tgn:1000001",
          "tgn:7012149",
          "tgn:2001539",
          "tgn:7007709",
          "tgn:7029392"
        ],
        "placetype": [
          "aat:300008706"
        ],
        "id": 2429422,
        "name:xx": "Juniper Creek"
      }
    },
    {
      "geometry": {
        "type": "Point",
        "coordinates": [
          -79.2333,
          35.1333
        ]
      },
      "type": "Feature",
      "properties": {
        "hierarchy": [
          "tgn:2429423",
          "tgn:1000001",
          "tgn:7012149",
          "tgn:2001505",
          "tgn:7007709",
          "tgn:7029392"
        ],
        "placetype": [
          "aat:300008706"
        ],
        "id": 2429423,
        "name:xx": "Juniper Creek"
      }
    },
    {
      "geometry": {
        "type": "Point",
        "coordinates": [
          -78.6167,
          35.3167
        ]
      },
      "type": "Feature",
      "properties": {
        "hierarchy": [
          "tgn:2429424",
          "tgn:1000001",
          "tgn:7012149",
          "tgn:2001502",
          "tgn:7007709",
          "tgn:7029392"
        ],
        "placetype": [
          "aat:300008706"
        ],
        "id": 2429424,
        "name:xx": "Juniper Creek"
      }
    },
    {
      "geometry": {
        "type": "Point",
        "coordinates": [
          -79.2,
          35.3333
        ]
      },
      "type": "Feature",
      "properties": {
        "hierarchy": [
          "tgn:2429425",
          "tgn:1000001",
          "tgn:7012149",
          "tgn:2001511",
          "tgn:7007709",
          "tgn:7029392"
        ],
        "placetype": [
          "aat:300008706"
        ],
        "id": 2429425,
        "name:xx": "Juniper Creek"
      }
    },
    {
      "geometry": {
        "type": "Point",
        "coordinates": [
          -77.6667,
          34.5333
        ]
      },
      "type": "Feature",
      "properties": {
        "hierarchy": [
          "tgn:2429426",
          "tgn:1000001",
          "tgn:7012149",
          "tgn:2001527",
          "tgn:7007709",
          "tgn:7029392"
        ],
        "placetype": [
          "aat:300008706"
        ],
        "id": 2429426,
        "name:xx": "Juniper Creek"
      }
    },
    {
      "geometry": {
        "type": "Point",
        "coordinates": [
          -120.2,
          42.5333
        ]
      },
      "type": "Feature",
      "properties": {
        "hierarchy": [
          "tgn:2429427",
          "tgn:1000001",
          "tgn:7012149",
          "tgn:2001715",
          "tgn:7007708",
          "tgn:7029392"
        ],
        "placetype": [
          "aat:300008706"
        ],
        "id": 2429427,
        "name:xx": "Juniper Creek"
      }
    },
    {
      "geometry": {
        "type": "Point",
        "coordinates": [
          -117.3833,
          43.2667
        ]
      },
      "type": "Feature",
      "properties": {
        "hierarchy": [
          "tgn:2429428",
          "tgn:1000001",
          "tgn:7012149",
          "tgn:2001718",
          "tgn:7007708",
          "tgn:7029392"
        ],
        "placetype": [
          "aat:300008706"
        ],
        "id": 2429428,
        "name:xx": "Juniper Creek"
      }
    },
    {
      "geometry": {
        "type": "Point",
        "coordinates": [
          -120.8,
          44.75
        ]
      },
      "type": "Feature",
      "properties": {
        "hierarchy": [
          "tgn:2429429",
          "tgn:1000001",
          "tgn:7012149",
          "tgn:2001712",
          "tgn:7007708",
          "tgn:7029392"
        ],
        "placetype": [
          "aat:300008706"
        ],
        "id": 2429429,
        "name:xx": "Juniper Creek"
      }
    }
  ]
}
