{
  "geometry": {
    "type": "Point",
    "coordinates": [
      -73.3833,
      44.85
    ]
  },
  "type": "Feature",
  "properties": {
    "hierarchy": [
      "tgn:2729557",
      "tgn:1000001",
      "tgn:1002284",
      "tgn:7012149",
      "tgn:7007568",
      "tgn:7029392"
    ],
    "placetype": [
      "aat:300132316"
    ],
    "id": 2729557,
    "name:xx": "Trombley Bay"
  }
}
