{
  "geometry": {
    "type": "Point",
    "coordinates": [
      -84.3333,
      36.4833
    ]
  },
  "type": "Feature",
  "properties": {
    "hierarchy": [
      "tgn:2536752",
      "tgn:1000001",
      "tgn:7012149",
      "tgn:7007825",
      "tgn:7029392"
    ],
    "placetype": [
      "aat:300008798"
    ],
    "id": 2536752,
    "name:xx": "Ned Mountain"
  }
}
