{
  "geometry": {
    "type": "Point",
    "coordinates": [
      -104.8167,
      31.7667
    ]
  },
  "type": "Feature",
  "properties": {
    "hierarchy": [
      "tgn:2465382",
      "tgn:1000001",
      "tgn:7012149",
      "tgn:2001969",
      "tgn:7007826",
      "tgn:7029392"
    ],
    "placetype": [
      "aat:300008798"
    ],
    "id": 2465382,
    "name:xx": "Lone Cone"
  }
}
