{
  "geometry": {
    "type": "Point",
    "coordinates": [
      -88.05,
      31.9667
    ]
  },
  "type": "Feature",
  "properties": {
    "hierarchy": [
      "tgn:2579325",
      "tgn:7002659",
      "tgn:1000001",
      "tgn:2000012",
      "tgn:7012149",
      "tgn:7029392"
    ],
    "placetype": [
      "aat:300008347"
    ],
    "id": 2579325,
    "name:xx": "Pickens Landing"
  }
}
