{
  "type": "FeatureCollection",
  "features": [
    {
      "geometry": {
        "type": "Point",
        "coordinates": [
          16.1833,
          48.0167
        ]
      },
      "type": "Feature",
      "properties": {
        "hierarchy": [
          "tgn:1103830",
          "tgn:7003025",
          "tgn:1000003",
          "tgn:1000062",
          "tgn:7029392"
        ],
        "placetype": [
          "aat:300008795"
        ],
        "id": 1103830,
        "name:xx": "Badner Lindkogel"
      }
    },
    {
      "geometry": {
        "type": "Point",
        "coordinates": [
          8.75,
          17.7167
        ]
      },
      "type": "Feature",
      "properties": {
        "hierarchy": [
          "tgn:1103834",
          "tgn:1000488",
          "tgn:7001242",
          "tgn:1000181",
          "tgn:7029392"
        ],
        "placetype": [
          "aat:300008795"
        ],
        "id": 1103834,
        "name:xx": "Bagzane"
      }
    },
    {
      "geometry": {
        "type": "Point",
        "coordinates": [
          76.5333,
          32.85
        ]
      },
      "type": "Feature",
      "properties": {
        "hierarchy": [
          "tgn:1103837",
          "tgn:1000004",
          "tgn:7000198",
          "tgn:1001996",
          "tgn:7029392"
        ],
        "placetype": [
          "aat:300008795"
        ],
        "id": 1103837,
        "name:xx": "Baihāli Jot"
      }
    },
    {
      "geometry": {
        "type": "Point",
        "coordinates": [
          115.6,
          39.85
        ]
      },
      "type": "Feature",
      "properties": {
        "hierarchy": [
          "tgn:1103838",
          "tgn:1000004",
          "tgn:7002077",
          "tgn:1000111",
          "tgn:7029392"
        ],
        "placetype": [
          "aat:300008795"
        ],
        "id": 1103838,
        "name:xx": "Baihua Shan"
      }
    },
    {
      "geometry": {
        "type": "Point",
        "coordinates": [
          110.5333,
          27.2
        ]
      },
      "type": "Feature",
      "properties": {
        "hierarchy": [
          "tgn:1103839",
          "tgn:1000004",
          "tgn:7002079",
          "tgn:1000111",
          "tgn:7029392"
        ],
        "placetype": [
          "aat:300008795"
        ],
        "id": 1103839,
        "name:xx": "Baima Shan"
      }
    }
  ]
}
