{
  "geometry": {
    "type": "Point",
    "coordinates": [
      -107.3167,
      39.8333
    ]
  },
  "type": "Feature",
  "properties": {
    "hierarchy": [
      "tgn:2678293",
      "tgn:1000001",
      "tgn:7012149",
      "tgn:7007158",
      "tgn:7029392"
    ],
    "placetype": [
      "aat:300008761"
    ],
    "id": 2678293,
    "name:xx": "South Fork Canyon"
  }
}
