{
  "geometry": {
    "type": "Point",
    "coordinates": [
      -112.2167,
      45.5333
    ]
  },
  "type": "Feature",
  "properties": {
    "hierarchy": [
      "tgn:2635514",
      "tgn:1000001",
      "tgn:7012149",
      "tgn:2001288",
      "tgn:7007524",
      "tgn:7029392"
    ],
    "placetype": [
      "aat:300000390"
    ],
    "id": 2635514,
    "name:xx": "SW NE Section 27 Mine"
  }
}
