{
  "geometry": {
    "type": "Point",
    "coordinates": [
      -110.45,
      31.4333
    ]
  },
  "type": "Feature",
  "properties": {
    "hierarchy": [
      "tgn:2250278",
      "tgn:1000001",
      "tgn:7006451",
      "tgn:2000091",
      "tgn:7012149",
      "tgn:7029392"
    ],
    "placetype": [
      "aat:300008697"
    ],
    "id": 2250278,
    "name:xx": "Collins Spring"
  }
}
