{
  "type": "FeatureCollection",
  "features": [
    {
      "geometry": {
        "type": "Point",
        "coordinates": [
          -0.0167,
          51.6167
        ]
      },
      "type": "Feature",
      "properties": {
        "hierarchy": [
          "tgn:1120700",
          "tgn:7002445",
          "tgn:7018913",
          "tgn:1000003",
          "tgn:7008136",
          "tgn:7008591",
          "tgn:7029392"
        ],
        "placetype": [
          "aat:300006191"
        ],
        "id": 1120700,
        "name:xx": "William Girling Reservoir"
      }
    },
    {
      "geometry": {
        "type": "Point",
        "coordinates": [
          -84.5167,
          38.6667
        ]
      },
      "type": "Feature",
      "properties": {
        "hierarchy": [
          "tgn:1120702",
          "tgn:1000001",
          "tgn:7012149",
          "tgn:1002417",
          "tgn:7007255",
          "tgn:7029392"
        ],
        "placetype": [
          "aat:300006191"
        ],
        "id": 1120702,
        "name:xx": "Williamstown Lake"
      }
    },
    {
      "geometry": {
        "type": "Point",
        "coordinates": [
          -123.6667,
          55.6667
        ]
      },
      "type": "Feature",
      "properties": {
        "hierarchy": [
          "tgn:1120703",
          "tgn:7005735",
          "tgn:7005685",
          "tgn:1000001",
          "tgn:7029392"
        ],
        "placetype": [
          "aat:300006191"
        ],
        "id": 1120703,
        "name:xx": "Williston Lake"
      }
    },
    {
      "geometry": {
        "type": "Point",
        "coordinates": [
          -89.8333,
          45.7
        ]
      },
      "type": "Feature",
      "properties": {
        "hierarchy": [
          "tgn:1120704",
          "tgn:1000001",
          "tgn:7012149",
          "tgn:2002342",
          "tgn:7007922",
          "tgn:7029392"
        ],
        "placetype": [
          "aat:300006191"
        ],
        "id": 1120704,
        "name:xx": "Willow Reservoir"
      }
    },
    {
      "geometry": {
        "type": "Point",
        "coordinates": [
          150.5,
          -34.5667
        ]
      },
      "type": "Feature",
      "properties": {
        "hierarchy": [
          "tgn:1120708",
          "tgn:7000490",
          "tgn:1000006",
          "tgn:7001828",
          "tgn:7029392"
        ],
        "placetype": [
          "aat:300006191"
        ],
        "id": 1120708,
        "name:xx": "Wingecarribee Reservoir"
      }
    }
  ]
}
