{
  "geometry": {
    "type": "Point",
    "coordinates": [
      -131.4667,
      55.05
    ]
  },
  "type": "Feature",
  "properties": {
    "hierarchy": [
      "tgn:2710639",
      "tgn:7006450",
      "tgn:1000001",
      "tgn:7012149",
      "tgn:2000082",
      "tgn:7029392"
    ],
    "placetype": [
      "aat:300008680"
    ],
    "id": 2710639,
    "name:xx": "Tamgas Lake"
  }
}
