{
  "geometry": {
    "type": "Point",
    "coordinates": [
      -95.5833,
      37.6167
    ]
  },
  "type": "Feature",
  "properties": {
    "hierarchy": [
      "tgn:2745100",
      "tgn:1000001",
      "tgn:7012149",
      "tgn:7007254",
      "tgn:7029392"
    ],
    "placetype": [
      "aat:300008706"
    ],
    "id": 2745100,
    "name:xx": "Village Creek"
  }
}
