{
  "geometry": {
    "type": "Point",
    "coordinates": [
      -66.2333,
      -28.1833
    ]
  },
  "type": "Feature",
  "properties": {
    "hierarchy": [
      "tgn:1020054",
      "tgn:1001182",
      "tgn:7006477",
      "tgn:1000002",
      "tgn:7029392"
    ],
    "placetype": [
      "aat:300008347"
    ],
    "id": 1020054,
    "name:xx": "Saujil"
  }
}
