{
  "geometry": {
    "type": "Point",
    "coordinates": [
      12.8333,
      12.1667
    ]
  },
  "type": "Feature",
  "properties": {
    "hierarchy": [
      "tgn:1092152",
      "tgn:7001242",
      "tgn:7000542",
      "tgn:1000182",
      "tgn:7029392"
    ],
    "placetype": [
      "aat:300008347"
    ],
    "id": 1092152,
    "name:xx": "Magumeri"
  }
}
