{
  "geometry": {
    "type": "Point",
    "coordinates": [
      -109.7333,
      46.3333
    ]
  },
  "type": "Feature",
  "properties": {
    "hierarchy": [
      "tgn:2770299",
      "tgn:1000001",
      "tgn:7012149",
      "tgn:2001313",
      "tgn:7007524",
      "tgn:7029392"
    ],
    "placetype": [
      "aat:300008798"
    ],
    "id": 2770299,
    "name:xx": "Wild Horse Butte"
  }
}
