{
  "geometry": {
    "type": "Point",
    "coordinates": [
      29.85,
      41.1333
    ]
  },
  "type": "Feature",
  "properties": {
    "hierarchy": [
      "tgn:1085910",
      "tgn:1001052",
      "tgn:1000004",
      "tgn:7018450",
      "tgn:1000144",
      "tgn:7029392"
    ],
    "placetype": [
      "aat:300008347"
    ],
    "id": 1085910,
    "name:xx": "Ağva"
  }
}
