{
  "geometry": {
    "type": "Point",
    "coordinates": [
      -106.95,
      31.333333
    ]
  },
  "type": "Feature",
  "properties": {
    "hierarchy": [
      "tgn:7428626",
      "tgn:7005581",
      "tgn:1000001",
      "tgn:7005560",
      "tgn:7029392"
    ],
    "placetype": [
      "aat:300007783"
    ],
    "id": 7428626,
    "name:xx": "Estación Placa KB 490"
  }
}
