{
  "geometry": {
    "type": "Point",
    "coordinates": [
      -80.85,
      33.4667
    ]
  },
  "type": "Feature",
  "properties": {
    "hierarchy": [
      "tgn:2386618",
      "tgn:1000001",
      "tgn:7012149",
      "tgn:2001762",
      "tgn:7007712",
      "tgn:7029392"
    ],
    "placetype": [
      "aat:300008347"
    ],
    "id": 2386618,
    "name:xx": "Heritage Subdivision"
  }
}
