{
  "type": "FeatureCollection",
  "features": [
    {
      "geometry": {
        "type": "Point",
        "coordinates": [
          -75.2,
          39.85
        ]
      },
      "type": "Feature",
      "properties": {
        "hierarchy": [
          "tgn:2488890",
          "tgn:1000001",
          "tgn:1002410",
          "tgn:7012149",
          "tgn:7007565",
          "tgn:7029392"
        ],
        "placetype": [
          "aat:300006075"
        ],
        "id": 2488890,
        "name:xx": "Main Ditch"
      }
    },
    {
      "geometry": {
        "type": "Point",
        "coordinates": [
          -107.9833,
          35.25
        ]
      },
      "type": "Feature",
      "properties": {
        "hierarchy": [
          "tgn:2488891",
          "tgn:1000001",
          "tgn:2001431",
          "tgn:7012149",
          "tgn:7007566",
          "tgn:7029392"
        ],
        "placetype": [
          "aat:300006075"
        ],
        "id": 2488891,
        "name:xx": "Main Ditch"
      }
    },
    {
      "geometry": {
        "type": "Point",
        "coordinates": [
          -119.5833,
          48.3833
        ]
      },
      "type": "Feature",
      "properties": {
        "hierarchy": [
          "tgn:2488892",
          "tgn:1000001",
          "tgn:7012149",
          "tgn:1002742",
          "tgn:7007920",
          "tgn:7029392"
        ],
        "placetype": [
          "aat:300006075"
        ],
        "id": 2488892,
        "name:xx": "Main Ditch"
      }
    },
    {
      "geometry": {
        "type": "Point",
        "coordinates": [
          -88.0833,
          43.8333
        ]
      },
      "type": "Feature",
      "properties": {
        "hierarchy": [
          "tgn:2488893",
          "tgn:1000001",
          "tgn:7012149",
          "tgn:2002355",
          "tgn:7007922",
          "tgn:7029392"
        ],
        "placetype": [
          "aat:300006075"
        ],
        "id": 2488893,
        "name:xx": "Main Ditch"
      }
    },
    {
      "geometry": {
        "type": "Point",
        "coordinates": [
          -88.6333,
          43.5333
        ]
      },
      "type": "Feature",
      "properties": {
        "hierarchy": [
          "tgn:2488894",
          "tgn:1000001",
          "tgn:7012149",
          "tgn:7007922",
          "tgn:7029392"
        ],
        "placetype": [
          "aat:300006075"
        ],
        "id": 2488894,
        "name:xx": "Main Ditch"
      }
    },
    {
      "geometry": {
        "type": "Point",
        "coordinates": [
          -121.7167,
          39.45
        ]
      },
      "type": "Feature",
      "properties": {
        "hierarchy": [
          "tgn:2488895",
          "tgn:1000001",
          "tgn:1002218",
          "tgn:7012149",
          "tgn:7007157",
          "tgn:7029392"
        ],
        "placetype": [
          "aat:300006075"
        ],
        "id": 2488895,
        "name:xx": "Main Ditch A"
      }
    },
    {
      "geometry": {
        "type": "Point",
        "coordinates": [
          -90.6,
          33.0167
        ]
      },
      "type": "Feature",
      "properties": {
        "hierarchy": [
          "tgn:2488896",
          "tgn:1000001",
          "tgn:7012149",
          "tgn:7007522",
          "tgn:7029392"
        ],
        "placetype": [
          "aat:300006075"
        ],
        "id": 2488896,
        "name:xx": "Main Ditch A"
      }
    },
    {
      "geometry": {
        "type": "Point",
        "coordinates": [
          -121.7333,
          39.45
        ]
      },
      "type": "Feature",
      "properties": {
        "hierarchy": [
          "tgn:2488897",
          "tgn:1000001",
          "tgn:1002218",
          "tgn:7012149",
          "tgn:7007157",
          "tgn:7029392"
        ],
        "placetype": [
          "aat:300006075"
        ],
        "id": 2488897,
        "name:xx": "Main Ditch B"
      }
    },
    {
      "geometry": {
        "type": "Point",
        "coordinates": [
          -90.5833,
          33.0833
        ]
      },
      "type": "Feature",
      "properties": {
        "hierarchy": [
          "tgn:2488898",
          "tgn:1000001",
          "tgn:7012149",
          "tgn:7007522",
          "tgn:7029392"
        ],
        "placetype": [
          "aat:300006075"
        ],
        "id": 2488898,
        "name:xx": "Main Ditch B"
      }
    },
    {
      "geometry": {
        "type": "Point",
        "coordinates": [
          -90.0833,
          36.4333
        ]
      },
      "type": "Feature",
      "properties": {
        "hierarchy": [
          "tgn:2488899",
          "tgn:1000001",
          "tgn:7012149",
          "tgn:2001197",
          "tgn:7007523",
          "tgn:7029392"
        ],
        "placetype": [
          "aat:300006075"
        ],
        "id": 2488899,
        "name:xx": "Main Ditch District Number 10"
      }
    }
  ]
}
