{
  "type": "FeatureCollection",
  "features": [
    {
      "geometry": {
        "type": "Point",
        "coordinates": [
          -99.95,
          29.6
        ]
      },
      "type": "Feature",
      "properties": {
        "hierarchy": [
          "tgn:2609180",
          "tgn:1000001",
          "tgn:7012149",
          "tgn:2002087",
          "tgn:7007826",
          "tgn:7029392"
        ],
        "placetype": [
          "aat:300008798"
        ],
        "id": 2609180,
        "name:xx": "Rawhide Mountains"
      }
    },
    {
      "geometry": {
        "type": "Point",
        "coordinates": [
          -116.3333,
          41.7
        ]
      },
      "type": "Feature",
      "properties": {
        "hierarchy": [
          "tgn:2609181",
          "tgn:1000001",
          "tgn:2001411",
          "tgn:7012149",
          "tgn:7007526",
          "tgn:7029392"
        ],
        "placetype": [
          "aat:300006191"
        ],
        "id": 2609181,
        "name:xx": "Rawhide Reservoir"
      }
    },
    {
      "geometry": {
        "type": "Point",
        "coordinates": [
          -83.1667,
          29.85
        ]
      },
      "type": "Feature",
      "properties": {
        "hierarchy": [
          "tgn:2609183",
          "tgn:1000001",
          "tgn:2000275",
          "tgn:7012149",
          "tgn:7007240",
          "tgn:7029392"
        ],
        "placetype": [
          "aat:300008905"
        ],
        "id": 2609183,
        "name:xx": "Rawhide Sog"
      }
    },
    {
      "geometry": {
        "type": "Point",
        "coordinates": [
          -112.2333,
          43.0667
        ]
      },
      "type": "Feature",
      "properties": {
        "hierarchy": [
          "tgn:2609184",
          "tgn:1000001",
          "tgn:2000457",
          "tgn:7012149",
          "tgn:7007250",
          "tgn:7029392"
        ],
        "placetype": [
          "aat:300008697"
        ],
        "id": 2609184,
        "name:xx": "Rawhide Spring"
      }
    },
    {
      "geometry": {
        "type": "Point",
        "coordinates": [
          -116.3833,
          38.2667
        ]
      },
      "type": "Feature",
      "properties": {
        "hierarchy": [
          "tgn:2609185",
          "tgn:1000001",
          "tgn:2001418",
          "tgn:7012149",
          "tgn:7007526",
          "tgn:7029392"
        ],
        "placetype": [
          "aat:300008697"
        ],
        "id": 2609185,
        "name:xx": "Rawhide Spring"
      }
    },
    {
      "geometry": {
        "type": "Point",
        "coordinates": [
          -117.85,
          40.5833
        ]
      },
      "type": "Feature",
      "properties": {
        "hierarchy": [
          "tgn:2609186",
          "tgn:1000001",
          "tgn:2001419",
          "tgn:7012149",
          "tgn:7007526",
          "tgn:7029392"
        ],
        "placetype": [
          "aat:300008697"
        ],
        "id": 2609186,
        "name:xx": "Rawhide Spring"
      }
    },
    {
      "geometry": {
        "type": "Point",
        "coordinates": [
          -107.75,
          36.95
        ]
      },
      "type": "Feature",
      "properties": {
        "hierarchy": [
          "tgn:2609187",
          "tgn:1000001",
          "tgn:7012149",
          "tgn:2001452",
          "tgn:7007566",
          "tgn:7029392"
        ],
        "placetype": [
          "aat:300008697"
        ],
        "id": 2609187,
        "name:xx": "Rawhide Spring"
      }
    },
    {
      "geometry": {
        "type": "Point",
        "coordinates": [
          -119.0333,
          43.9
        ]
      },
      "type": "Feature",
      "properties": {
        "hierarchy": [
          "tgn:2609188",
          "tgn:1000001",
          "tgn:7012149",
          "tgn:2001709",
          "tgn:7007708",
          "tgn:7029392"
        ],
        "placetype": [
          "aat:300008697"
        ],
        "id": 2609188,
        "name:xx": "Rawhide Spring"
      }
    },
    {
      "geometry": {
        "type": "Point",
        "coordinates": [
          -99.95,
          29.6
        ]
      },
      "type": "Feature",
      "properties": {
        "hierarchy": [
          "tgn:2609189",
          "tgn:1000001",
          "tgn:7012149",
          "tgn:2002087",
          "tgn:7007826",
          "tgn:7029392"
        ],
        "placetype": [
          "aat:300008697"
        ],
        "id": 2609189,
        "name:xx": "Rawhide Spring"
      }
    }
  ]
}
