{
  "geometry": {
    "type": "Point",
    "coordinates": [
      -106.5667,
      39.0833
    ]
  },
  "type": "Feature",
  "properties": {
    "hierarchy": [
      "tgn:2527638",
      "tgn:1000001",
      "tgn:7012149",
      "tgn:2000224",
      "tgn:7007158",
      "tgn:7029392"
    ],
    "placetype": [
      "aat:300008761"
    ],
    "id": 2527638,
    "name:xx": "Mountain Boy Gulch"
  }
}
