{
  "geometry": {
    "type": "Point",
    "coordinates": [
      -76.1667,
      38.55
    ]
  },
  "type": "Feature",
  "properties": {
    "hierarchy": [
      "tgn:2670928",
      "tgn:1002338",
      "tgn:1000001",
      "tgn:7012149",
      "tgn:7007516",
      "tgn:7029392"
    ],
    "placetype": [
      "aat:300132316"
    ],
    "id": 2670928,
    "name:xx": "Smith Cove"
  }
}
