{
  "geometry": {
    "type": "Point",
    "coordinates": [
      -97.8833,
      30.55
    ]
  },
  "type": "Feature",
  "properties": {
    "hierarchy": [
      "tgn:2678213",
      "tgn:1000001",
      "tgn:7012149",
      "tgn:1003026",
      "tgn:7007826",
      "tgn:7029392"
    ],
    "placetype": [
      "aat:300008706"
    ],
    "id": 2678213,
    "name:xx": "South Fork Brushy Creek"
  }
}
