{
  "geometry": {
    "type": "Point",
    "coordinates": [
      -74.9833,
      42.7667
    ]
  },
  "type": "Feature",
  "properties": {
    "hierarchy": [
      "tgn:2567230",
      "tgn:1000001",
      "tgn:7012149",
      "tgn:7014318",
      "tgn:7007568",
      "tgn:7029392"
    ],
    "placetype": [
      "aat:300008798"
    ],
    "id": 2567230,
    "name:xx": "Panther Mountain"
  }
}
