{
  "geometry": {
    "type": "Point",
    "coordinates": [
      19.4167,
      46.6667
    ]
  },
  "type": "Feature",
  "properties": {
    "hierarchy": [
      "tgn:1101635",
      "tgn:1000340",
      "tgn:1000003",
      "tgn:7006278",
      "tgn:7029392"
    ],
    "placetype": [
      "aat:300008189"
    ],
    "id": 1101635,
    "name:xx": "Kiskunsági Nemzeti Park"
  }
}
