{
  "geometry": {
    "type": "Point",
    "coordinates": [
      75.677899,
      26.889128
    ]
  },
  "type": "Feature",
  "properties": {
    "hierarchy": [
      "tgn:7560099",
      "tgn:1000004",
      "tgn:7000198",
      "tgn:7016788",
      "tgn:7029392"
    ],
    "placetype": [
      "aat:300008347"
    ],
    "name:en": "Jamādār ki Dhāni",
    "id": 7560099
  }
}
