{
  "geometry": {
    "type": "Point",
    "coordinates": [
      -81.0833,
      37.85
    ]
  },
  "type": "Feature",
  "properties": {
    "hierarchy": [
      "tgn:2120182",
      "tgn:1000001",
      "tgn:7012149",
      "tgn:2002290",
      "tgn:7013961",
      "tgn:7029392"
    ],
    "placetype": [
      "aat:300008347"
    ],
    "id": 2120182,
    "name:xx": "Terry"
  }
}
