{
  "geometry": {
    "type": "Point",
    "coordinates": [
      -117.15,
      32.9667
    ]
  },
  "type": "Feature",
  "properties": {
    "hierarchy": [
      "tgn:2354594",
      "tgn:1000001",
      "tgn:7012149",
      "tgn:7007157",
      "tgn:1002858",
      "tgn:7029392"
    ],
    "placetype": [
      "aat:300008761"
    ],
    "id": 2354594,
    "name:xx": "Gonzales Canyon"
  }
}
