{
  "type": "FeatureCollection",
  "features": [
    {
      "geometry": {
        "type": "Point",
        "coordinates": [
          121.062778,
          24.556944
        ]
      },
      "type": "Feature",
      "properties": {
        "hierarchy": [
          "tgn:7490392",
          "tgn:1000004",
          "tgn:7471332",
          "tgn:1000141",
          "tgn:7029392"
        ],
        "placetype": [
          "aat:300008798"
        ],
        "id": 7490392,
        "name:xx": "Dawo Shan"
      }
    },
    {
      "geometry": {
        "type": "Point",
        "coordinates": [
          120.95654,
          24.551274
        ]
      },
      "type": "Feature",
      "properties": {
        "hierarchy": [
          "tgn:7490393",
          "tgn:7487020",
          "tgn:1000004",
          "tgn:1000141",
          "tgn:7029392"
        ],
        "placetype": [
          "aat:300008798"
        ],
        "id": 7490393,
        "name:xx": "Dawo Shan"
      }
    },
    {
      "geometry": {
        "type": "Point",
        "coordinates": [
          121.101111,
          24.661667
        ]
      },
      "type": "Feature",
      "properties": {
        "hierarchy": [
          "tgn:7490394",
          "tgn:1000004",
          "tgn:7471332",
          "tgn:1000141",
          "tgn:7029392"
        ],
        "placetype": [
          "aat:300008347"
        ],
        "id": 7490394,
        "name:xx": "Dawolang"
      }
    },
    {
      "geometry": {
        "type": "Point",
        "coordinates": [
          120.765658,
          24.501685
        ]
      },
      "type": "Feature",
      "properties": {
        "hierarchy": [
          "tgn:7490395",
          "tgn:7487020",
          "tgn:1000004",
          "tgn:1000141",
          "tgn:7029392"
        ],
        "placetype": [
          "aat:300008347"
        ],
        "id": 7490395,
        "name:xx": "Dawo"
      }
    },
    {
      "geometry": {
        "type": "Point",
        "coordinates": [
          120.902085,
          24.487545
        ]
      },
      "type": "Feature",
      "properties": {
        "hierarchy": [
          "tgn:7490396",
          "tgn:7487020",
          "tgn:1000004",
          "tgn:1000141",
          "tgn:7029392"
        ],
        "placetype": [
          "aat:300008347"
        ],
        "id": 7490396,
        "name:xx": "Dawo"
      }
    },
    {
      "geometry": {
        "type": "Point",
        "coordinates": [
          120.499725,
          23.181314
        ]
      },
      "type": "Feature",
      "properties": {
        "hierarchy": [
          "tgn:7490398",
          "tgn:1000004",
          "tgn:7490934",
          "tgn:1000141",
          "tgn:7029392"
        ],
        "placetype": [
          "aat:300008777"
        ],
        "id": 7490398,
        "name:xx": "Dawen Shan"
      }
    }
  ]
}
