{
  "geometry": {
    "type": "Point",
    "coordinates": [
      36.8167,
      36.1333
    ]
  },
  "type": "Feature",
  "properties": {
    "hierarchy": [
      "tgn:1085058",
      "tgn:1002052",
      "tgn:1000004",
      "tgn:1000140",
      "tgn:7029392"
    ],
    "placetype": [
      "aat:300008347"
    ],
    "id": 1085058,
    "name:xx": "Al Atārib"
  }
}
