{
  "geometry": {
    "type": "Point",
    "coordinates": [
      1.0333,
      12.4667
    ]
  },
  "type": "Feature",
  "properties": {
    "hierarchy": [
      "tgn:1095833",
      "tgn:7024148",
      "tgn:7001242",
      "tgn:1000604",
      "tgn:1000208",
      "tgn:7029392"
    ],
    "placetype": [
      "aat:300008347"
    ],
    "id": 1095833,
    "name:xx": "Matiacoli"
  }
}
