{
  "geometry": {
    "type": "Point",
    "coordinates": [
      -83.15,
      41.0667
    ]
  },
  "type": "Feature",
  "properties": {
    "hierarchy": [
      "tgn:2348709",
      "tgn:1000001",
      "tgn:7012149",
      "tgn:1002883",
      "tgn:7007706",
      "tgn:7029392"
    ],
    "placetype": [
      "aat:300008706"
    ],
    "id": 2348709,
    "name:xx": "Gibson Creek"
  }
}
