{
  "geometry": {
    "type": "Point",
    "coordinates": [
      -72.7667,
      41.7667
    ]
  },
  "type": "Feature",
  "properties": {
    "hierarchy": [
      "tgn:1002461",
      "tgn:1000001",
      "tgn:7012149",
      "tgn:7007159",
      "tgn:7029392"
    ],
    "placetype": [
      "aat:300387145",
      "aat:300000771"
    ],
    "id": 1002461,
    "name:xx": "Hartford"
  }
}
