{
  "geometry": {
    "type": "Point",
    "coordinates": [
      17.25,
      59.0833
    ]
  },
  "type": "Feature",
  "properties": {
    "hierarchy": [
      "tgn:7009840",
      "tgn:1000003",
      "tgn:7003781",
      "tgn:1000097",
      "tgn:7029392"
    ],
    "placetype": [
      "aat:300008347"
    ],
    "id": 7009840,
    "name:xx": "Mariefred"
  }
}
