{
  "geometry": {
    "type": "Point",
    "coordinates": [
      -90.7167,
      41.4833
    ]
  },
  "type": "Feature",
  "properties": {
    "hierarchy": [
      "tgn:2290314",
      "tgn:1000001",
      "tgn:7012149",
      "tgn:2000642",
      "tgn:7007253",
      "tgn:7029392"
    ],
    "placetype": [
      "aat:300008706"
    ],
    "id": 2290314,
    "name:xx": "Dodges Creek"
  }
}
