{
  "geometry": {
    "type": "Point",
    "coordinates": [
      79.335034,
      26.017982
    ]
  },
  "type": "Feature",
  "properties": {
    "hierarchy": [
      "tgn:7566107",
      "tgn:1000004",
      "tgn:7000198",
      "tgn:7016722",
      "tgn:7029392"
    ],
    "placetype": [
      "aat:300008347"
    ],
    "name:en": "Mallūpura",
    "id": 7566107
  }
}
