{
  "geometry": {
    "type": "Point",
    "coordinates": [
      -73.05,
      42.8333
    ]
  },
  "type": "Feature",
  "properties": {
    "hierarchy": [
      "tgn:2217003",
      "tgn:1002176",
      "tgn:1000001",
      "tgn:7012149",
      "tgn:7007828",
      "tgn:7029392"
    ],
    "placetype": [
      "aat:300008905"
    ],
    "id": 2217003,
    "name:xx": "Camp Meadows"
  }
}
