{
  "geometry": {
    "type": "Point",
    "coordinates": [
      -76.4667,
      43.3833
    ]
  },
  "type": "Feature",
  "properties": {
    "hierarchy": [
      "tgn:2070581",
      "tgn:1000001",
      "tgn:7012149",
      "tgn:1002758",
      "tgn:7007568",
      "tgn:7029392"
    ],
    "placetype": [
      "aat:300008347"
    ],
    "id": 2070581,
    "name:xx": "Minetto"
  }
}
