{
  "geometry": {
    "type": "Point",
    "coordinates": [
      -80.1333,
      40.1167
    ]
  },
  "type": "Feature",
  "properties": {
    "hierarchy": [
      "tgn:2275356",
      "tgn:1000001",
      "tgn:7012149",
      "tgn:1002995",
      "tgn:7007710",
      "tgn:7029392"
    ],
    "placetype": [
      "aat:300008699"
    ],
    "id": 2275356,
    "name:xx": "Daniels Run"
  }
}
