{
  "type": "FeatureCollection",
  "features": [
    {
      "geometry": {
        "type": "Point",
        "coordinates": [
          5.75,
          51.7333
        ]
      },
      "type": "Feature",
      "properties": {
        "hierarchy": [
          "tgn:4001650",
          "tgn:1000003",
          "tgn:7003624",
          "tgn:7016845",
          "tgn:7029392"
        ],
        "placetype": [
          "aat:300008347"
        ],
        "id": 4001650,
        "name:xx": "Bokhoven"
      }
    },
    {
      "geometry": {
        "type": "Point",
        "coordinates": [
          0.016667,
          53.15
        ]
      },
      "type": "Feature",
      "properties": {
        "hierarchy": [
          "tgn:4001652",
          "tgn:7002445",
          "tgn:1000003",
          "tgn:7008157",
          "tgn:7008591",
          "tgn:7029392"
        ],
        "placetype": [
          "aat:300008347"
        ],
        "name:en": "Bolingbroke",
        "id": 4001652
      }
    },
    {
      "geometry": {
        "type": "Point",
        "coordinates": [
          -6.133333,
          37.333333
        ]
      },
      "type": "Feature",
      "properties": {
        "hierarchy": [
          "tgn:4001654",
          "tgn:7002758",
          "tgn:7002841",
          "tgn:1000003",
          "tgn:1000095",
          "tgn:7029392"
        ],
        "placetype": [
          "aat:300008347"
        ],
        "id": 4001654,
        "name:xx": "Bollullos de la Mitación"
      }
    }
  ]
}
