{
  "geometry": {
    "type": "Point",
    "coordinates": [
      32.67042,
      30.799508
    ]
  },
  "type": "Feature",
  "properties": {
    "hierarchy": [
      "tgn:7533371",
      "tgn:7001242",
      "tgn:7016833",
      "tgn:7001335",
      "tgn:7029392"
    ],
    "placetype": [
      "aat:300008750"
    ],
    "id": 7533371,
    "name:xx": "Jufayr, Kathīb al"
  }
}
