{
  "geometry": {
    "type": "Point",
    "coordinates": [
      -111.5667,
      40.5667
    ]
  },
  "type": "Feature",
  "properties": {
    "hierarchy": [
      "tgn:2692590",
      "tgn:1000001",
      "tgn:7012149",
      "tgn:2002126",
      "tgn:7007827",
      "tgn:7029392"
    ],
    "placetype": [
      "aat:300000390"
    ],
    "id": 2692590,
    "name:xx": "Steamboat Tunnel"
  }
}
