{
  "geometry": {
    "type": "Point",
    "coordinates": [
      84.489808,
      25.895265
    ]
  },
  "type": "Feature",
  "properties": {
    "hierarchy": [
      "tgn:7550324",
      "tgn:1000004",
      "tgn:1001842",
      "tgn:7000198",
      "tgn:7029392"
    ],
    "placetype": [
      "aat:300008699"
    ],
    "name:en": "Dāha Nadī",
    "id": 7550324
  }
}
