{
  "geometry": {
    "type": "Point",
    "coordinates": [
      -83.4167,
      43.0167
    ]
  },
  "type": "Feature",
  "properties": {
    "hierarchy": [
      "tgn:2728355",
      "tgn:1000001",
      "tgn:7012149",
      "tgn:1002576",
      "tgn:7007520",
      "tgn:7029392"
    ],
    "placetype": [
      "aat:300006075"
    ],
    "id": 2728355,
    "name:xx": "Treadway and Powelson Drain"
  }
}
