{
  "geometry": {
    "type": "Point",
    "coordinates": [
      77.2667,
      28.55
    ]
  },
  "type": "Feature",
  "properties": {
    "hierarchy": [
      "tgn:1004789",
      "tgn:1000004",
      "tgn:7000201",
      "tgn:7000198",
      "tgn:7029392"
    ],
    "placetype": [
      "aat:300008347",
      "aat:300000745"
    ],
    "name:en": "Kālkāji Devi",
    "id": 1004789
  }
}
