{
  "geometry": {
    "type": "Point",
    "coordinates": [
      99.7333,
      19.5667
    ]
  },
  "type": "Feature",
  "properties": {
    "hierarchy": [
      "tgn:1085622",
      "tgn:7000916",
      "tgn:7005194",
      "tgn:1000004",
      "tgn:1000142",
      "tgn:7029392"
    ],
    "placetype": [
      "aat:300008347"
    ],
    "id": 1085622,
    "name:xx": "Phan"
  }
}
