{
  "geometry": {
    "type": "Point",
    "coordinates": [
      14.8333,
      -15.3333
    ]
  },
  "type": "Feature",
  "properties": {
    "hierarchy": [
      "tgn:1101413",
      "tgn:7001242",
      "tgn:1000149",
      "tgn:1000867",
      "tgn:7029392"
    ],
    "placetype": [
      "aat:300008189"
    ],
    "id": 1101413,
    "name:xx": "Bikuar, Parque Nacional do"
  }
}
