{
  "geometry": {
    "type": "Point",
    "coordinates": [
      -166.4833,
      60.3833
    ]
  },
  "type": "Feature",
  "properties": {
    "hierarchy": [
      "tgn:2138355",
      "tgn:7006450",
      "tgn:2000069",
      "tgn:1000001",
      "tgn:7012149",
      "tgn:7029392"
    ],
    "placetype": [
      "aat:300008791"
    ],
    "id": 2138355,
    "name:xx": "Arwirnuk Rock"
  }
}
