{
  "type": "FeatureCollection",
  "features": [
    {
      "geometry": {
        "type": "Point",
        "coordinates": [
          -105.616667,
          27
        ]
      },
      "type": "Feature",
      "properties": {
        "hierarchy": [
          "tgn:7370881",
          "tgn:7005581",
          "tgn:1000001",
          "tgn:7005560",
          "tgn:7029392"
        ],
        "placetype": [
          "aat:300007783"
        ],
        "id": 7370881,
        "name:xx": "Gomera"
      }
    },
    {
      "geometry": {
        "type": "Point",
        "coordinates": [
          -97.966667,
          23.766667
        ]
      },
      "type": "Feature",
      "properties": {
        "hierarchy": [
          "tgn:7370882",
          "tgn:1000001",
          "tgn:7005597",
          "tgn:7005560",
          "tgn:7029392"
        ],
        "placetype": [
          "aat:300008679"
        ],
        "id": 7370882,
        "name:xx": "Gomeño, Laguna el"
      }
    },
    {
      "geometry": {
        "type": "Point",
        "coordinates": [
          -108.433333,
          25.5
        ]
      },
      "type": "Feature",
      "properties": {
        "hierarchy": [
          "tgn:7370883",
          "tgn:1000001",
          "tgn:7005595",
          "tgn:7005560",
          "tgn:7029392"
        ],
        "placetype": [
          "aat:300008347"
        ],
        "id": 7370883,
        "name:xx": "Jesús Maria"
      }
    },
    {
      "geometry": {
        "type": "Point",
        "coordinates": [
          -99.716667,
          25.266667
        ]
      },
      "type": "Feature",
      "properties": {
        "hierarchy": [
          "tgn:7370884",
          "tgn:1000001",
          "tgn:7005589",
          "tgn:7005560",
          "tgn:7029392"
        ],
        "placetype": [
          "aat:300008347"
        ],
        "id": 7370884,
        "name:xx": "Jesús María"
      }
    },
    {
      "geometry": {
        "type": "Point",
        "coordinates": [
          -99.366667,
          25.25
        ]
      },
      "type": "Feature",
      "properties": {
        "hierarchy": [
          "tgn:7370885",
          "tgn:1000001",
          "tgn:7005589",
          "tgn:7005560",
          "tgn:7029392"
        ],
        "placetype": [
          "aat:300008347"
        ],
        "id": 7370885,
        "name:xx": "Jesús Maria"
      }
    },
    {
      "geometry": {
        "type": "Point",
        "coordinates": [
          -101.616667,
          24.833333
        ]
      },
      "type": "Feature",
      "properties": {
        "hierarchy": [
          "tgn:7370887",
          "tgn:1000001",
          "tgn:7005601",
          "tgn:7005560",
          "tgn:7029392"
        ],
        "placetype": [
          "aat:300008347"
        ],
        "id": 7370887,
        "name:xx": "Jesús María"
      }
    },
    {
      "geometry": {
        "type": "Point",
        "coordinates": [
          -100.95,
          24.8
        ]
      },
      "type": "Feature",
      "properties": {
        "hierarchy": [
          "tgn:7370888",
          "tgn:1001853",
          "tgn:1000001",
          "tgn:7005560",
          "tgn:7029392"
        ],
        "placetype": [
          "aat:300008347"
        ],
        "id": 7370888,
        "name:xx": "Jesús María"
      }
    },
    {
      "geometry": {
        "type": "Point",
        "coordinates": [
          -99.584722,
          24.733056
        ]
      },
      "type": "Feature",
      "properties": {
        "hierarchy": [
          "tgn:7370889",
          "tgn:1000001",
          "tgn:7005589",
          "tgn:7005560",
          "tgn:7029392"
        ],
        "placetype": [
          "aat:300008347"
        ],
        "id": 7370889,
        "name:xx": "Jesús María"
      }
    }
  ]
}
