{
  "geometry": {
    "type": "Point",
    "coordinates": [
      -81.5833,
      36.8167
    ]
  },
  "type": "Feature",
  "properties": {
    "hierarchy": [
      "tgn:2502921",
      "tgn:1000001",
      "tgn:7012149",
      "tgn:2002191",
      "tgn:7007919",
      "tgn:7029392"
    ],
    "placetype": [
      "aat:300008746"
    ],
    "id": 2502921,
    "name:xx": "McMullin Cave"
  }
}
