{
  "type": "FeatureCollection",
  "features": [
    {
      "geometry": {
        "type": "Point",
        "coordinates": [
          -57.7833,
          -4.6
        ]
      },
      "type": "Feature",
      "properties": {
        "hierarchy": [
          "tgn:1128381",
          "tgn:1000047",
          "tgn:1000002",
          "tgn:7029392"
        ],
        "placetype": [
          "aat:300008707"
        ],
        "id": 1128381,
        "name:xx": "Paracari, Rio"
      }
    },
    {
      "geometry": {
        "type": "Point",
        "coordinates": [
          -45.0667,
          -16.5
        ]
      },
      "type": "Feature",
      "properties": {
        "hierarchy": [
          "tgn:1128382",
          "tgn:7006237",
          "tgn:1000047",
          "tgn:7002457",
          "tgn:1000002",
          "tgn:7029392"
        ],
        "placetype": [
          "aat:300008707"
        ],
        "id": 1128382,
        "name:xx": "Paracatu"
      }
    },
    {
      "geometry": {
        "type": "Point",
        "coordinates": [
          -55.65,
          -10.2833
        ]
      },
      "type": "Feature",
      "properties": {
        "hierarchy": [
          "tgn:1128383",
          "tgn:7006260",
          "tgn:7002454",
          "tgn:1000047",
          "tgn:1000002",
          "tgn:7029392"
        ],
        "placetype": [
          "aat:300008707"
        ],
        "id": 1128383,
        "name:xx": "Parado"
      }
    },
    {
      "geometry": {
        "type": "Point",
        "coordinates": [
          -61.116,
          -16.083
        ]
      },
      "type": "Feature",
      "properties": {
        "hierarchy": [
          "tgn:1128384",
          "tgn:1000752",
          "tgn:1000046",
          "tgn:1000002",
          "tgn:7029392"
        ],
        "placetype": [
          "aat:300008707"
        ],
        "id": 1128384,
        "name:xx": "Paraguá, Rio"
      }
    },
    {
      "geometry": {
        "type": "Point",
        "coordinates": [
          -62.9167,
          6.9167
        ]
      },
      "type": "Feature",
      "properties": {
        "hierarchy": [
          "tgn:1128385",
          "tgn:1001843",
          "tgn:1000002",
          "tgn:1000059",
          "tgn:7029392"
        ],
        "placetype": [
          "aat:300008707"
        ],
        "id": 1128385,
        "name:xx": "Paragua, Río"
      }
    },
    {
      "geometry": {
        "type": "Point",
        "coordinates": [
          -38.9,
          -12.75
        ]
      },
      "type": "Feature",
      "properties": {
        "hierarchy": [
          "tgn:1128386",
          "tgn:1001834",
          "tgn:1000047",
          "tgn:7002455",
          "tgn:1000002",
          "tgn:7029392"
        ],
        "placetype": [
          "aat:300008707"
        ],
        "id": 1128386,
        "name:xx": "Paraguaçu"
      }
    },
    {
      "geometry": {
        "type": "Point",
        "coordinates": [
          -58,
          -25
        ]
      },
      "type": "Feature",
      "properties": {
        "hierarchy": [
          "tgn:1128387",
          "tgn:1000002",
          "tgn:7029392"
        ],
        "placetype": [
          "aat:300008707"
        ],
        "id": 1128387,
        "name:xx": "Paraguay"
      }
    },
    {
      "geometry": {
        "type": "Point",
        "coordinates": [
          -43.1333,
          -22.1
        ]
      },
      "type": "Feature",
      "properties": {
        "hierarchy": [
          "tgn:1128388",
          "tgn:1001942",
          "tgn:1000047",
          "tgn:7002457",
          "tgn:1000002",
          "tgn:7029392"
        ],
        "placetype": [
          "aat:300008707"
        ],
        "id": 1128388,
        "name:xx": "Paraibuna"
      }
    },
    {
      "geometry": {
        "type": "Point",
        "coordinates": [
          -45.6667,
          -23.3667
        ]
      },
      "type": "Feature",
      "properties": {
        "hierarchy": [
          "tgn:1128389",
          "tgn:1001945",
          "tgn:1000047",
          "tgn:7002457",
          "tgn:1000002",
          "tgn:7029392"
        ],
        "placetype": [
          "aat:300008707"
        ],
        "id": 1128389,
        "name:xx": "Paraitinga"
      }
    }
  ]
}
