{
  "type": "FeatureCollection",
  "features": [
    {
      "geometry": {
        "type": "Point",
        "coordinates": [
          14.610977,
          52.597776
        ]
      },
      "type": "Feature",
      "properties": {
        "hierarchy": [
          "tgn:1131640",
          "tgn:1000003",
          "tgn:7006366",
          "tgn:7029392"
        ],
        "placetype": [
          "aat:300008707"
        ],
        "id": 1131640,
        "name:xx": "Warta"
      }
    },
    {
      "geometry": {
        "type": "Point",
        "coordinates": [
          -75.5833,
          37.7
        ]
      },
      "type": "Feature",
      "properties": {
        "hierarchy": [
          "tgn:1131642",
          "tgn:1002132",
          "tgn:1000001",
          "tgn:7012149",
          "tgn:7007919",
          "tgn:7029392"
        ],
        "placetype": [
          "aat:300008707"
        ],
        "id": 1131642,
        "name:xx": "Warwick"
      }
    },
    {
      "geometry": {
        "type": "Point",
        "coordinates": [
          10.1,
          8.45
        ]
      },
      "type": "Feature",
      "properties": {
        "hierarchy": [
          "tgn:1131643",
          "tgn:7001242",
          "tgn:1000182",
          "tgn:7029392"
        ],
        "placetype": [
          "aat:300008707"
        ],
        "id": 1131643,
        "name:xx": "Wase River"
      }
    },
    {
      "geometry": {
        "type": "Point",
        "coordinates": [
          -122.1333,
          45.7833
        ]
      },
      "type": "Feature",
      "properties": {
        "hierarchy": [
          "tgn:1131646",
          "tgn:1000001",
          "tgn:7012149",
          "tgn:7007920",
          "tgn:7029392"
        ],
        "placetype": [
          "aat:300008707"
        ],
        "id": 1131646,
        "name:xx": "Washougal"
      }
    },
    {
      "geometry": {
        "type": "Point",
        "coordinates": [
          -117.2,
          54.75
        ]
      },
      "type": "Feature",
      "properties": {
        "hierarchy": [
          "tgn:1131648",
          "tgn:7005694",
          "tgn:7005685",
          "tgn:1000001",
          "tgn:7029392"
        ],
        "placetype": [
          "aat:300008707"
        ],
        "id": 1131648,
        "name:xx": "Waskahigan"
      }
    },
    {
      "geometry": {
        "type": "Point",
        "coordinates": [
          -84.438,
          14.633
        ]
      },
      "type": "Feature",
      "properties": {
        "hierarchy": [
          "tgn:1131649",
          "tgn:7593358",
          "tgn:1000001",
          "tgn:7005562",
          "tgn:7029392"
        ],
        "placetype": [
          "aat:300008707"
        ],
        "id": 1131649,
        "name:xx": "Waspuk, Río"
      }
    }
  ]
}
