{
  "geometry": {
    "type": "Point",
    "coordinates": [
      -68.35,
      44.3667
    ]
  },
  "type": "Feature",
  "properties": {
    "hierarchy": [
      "tgn:2044988",
      "tgn:1000001",
      "tgn:2000922",
      "tgn:7012149",
      "tgn:7007515",
      "tgn:7029392"
    ],
    "placetype": [
      "aat:300008347",
      "aat:300387210"
    ],
    "id": 2044988,
    "name:xx": "Indian Point"
  }
}
