{
  "geometry": {
    "type": "Point",
    "coordinates": [
      -108.65,
      44.3333
    ]
  },
  "type": "Feature",
  "properties": {
    "hierarchy": [
      "tgn:2607476",
      "tgn:1000001",
      "tgn:7012149",
      "tgn:2002379",
      "tgn:7007923",
      "tgn:7029392"
    ],
    "placetype": [
      "aat:300006075"
    ],
    "id": 2607476,
    "name:xx": "Rankin Ditch"
  }
}
