{
  "type": "FeatureCollection",
  "features": [
    {
      "geometry": {
        "type": "Point",
        "coordinates": [
          -123.3333,
          47.8667
        ]
      },
      "type": "Feature",
      "properties": {
        "hierarchy": [
          "tgn:2523510",
          "tgn:1000001",
          "tgn:1002271",
          "tgn:7012149",
          "tgn:7007920",
          "tgn:7029392"
        ],
        "placetype": [
          "aat:300008680"
        ],
        "id": 2523510,
        "name:xx": "Moose Lake"
      }
    },
    {
      "geometry": {
        "type": "Point",
        "coordinates": [
          -80.5333,
          39.85
        ]
      },
      "type": "Feature",
      "properties": {
        "hierarchy": [
          "tgn:2523511",
          "tgn:1000001",
          "tgn:7012149",
          "tgn:2002276",
          "tgn:7013961",
          "tgn:7029392"
        ],
        "placetype": [
          "aat:300006191"
        ],
        "id": 2523511,
        "name:xx": "Moose Lake"
      }
    },
    {
      "geometry": {
        "type": "Point",
        "coordinates": [
          -88.4,
          43.1333
        ]
      },
      "type": "Feature",
      "properties": {
        "hierarchy": [
          "tgn:2523512",
          "tgn:1000001",
          "tgn:7012149",
          "tgn:1003002",
          "tgn:7007922",
          "tgn:7029392"
        ],
        "placetype": [
          "aat:300008680"
        ],
        "id": 2523512,
        "name:xx": "Moose Lake"
      }
    },
    {
      "geometry": {
        "type": "Point",
        "coordinates": [
          -89.0333,
          45.0667
        ]
      },
      "type": "Feature",
      "properties": {
        "hierarchy": [
          "tgn:2523513",
          "tgn:1000001",
          "tgn:7012149",
          "tgn:2002333",
          "tgn:7007922",
          "tgn:7029392"
        ],
        "placetype": [
          "aat:300008680"
        ],
        "id": 2523513,
        "name:xx": "Moose Lake"
      }
    },
    {
      "geometry": {
        "type": "Point",
        "coordinates": [
          -87.9,
          45.4167
        ]
      },
      "type": "Feature",
      "properties": {
        "hierarchy": [
          "tgn:2523514",
          "tgn:1000001",
          "tgn:7012149",
          "tgn:2002337",
          "tgn:7007922",
          "tgn:7029392"
        ],
        "placetype": [
          "aat:300008680"
        ],
        "id": 2523514,
        "name:xx": "Moose Lake"
      }
    },
    {
      "geometry": {
        "type": "Point",
        "coordinates": [
          -90.2167,
          46.2167
        ]
      },
      "type": "Feature",
      "properties": {
        "hierarchy": [
          "tgn:2523515",
          "tgn:1000001",
          "tgn:7012149",
          "tgn:2002327",
          "tgn:7007922",
          "tgn:7029392"
        ],
        "placetype": [
          "aat:300008680"
        ],
        "id": 2523515,
        "name:xx": "Moose Lake"
      }
    },
    {
      "geometry": {
        "type": "Point",
        "coordinates": [
          -91.9167,
          46.4167
        ]
      },
      "type": "Feature",
      "properties": {
        "hierarchy": [
          "tgn:2523516",
          "tgn:1000001",
          "tgn:2002318",
          "tgn:7012149",
          "tgn:7007922",
          "tgn:7029392"
        ],
        "placetype": [
          "aat:300008680"
        ],
        "id": 2523516,
        "name:xx": "Moose Lake"
      }
    },
    {
      "geometry": {
        "type": "Point",
        "coordinates": [
          -91.15,
          46.6667
        ]
      },
      "type": "Feature",
      "properties": {
        "hierarchy": [
          "tgn:2523517",
          "tgn:2002308",
          "tgn:1000001",
          "tgn:7012149",
          "tgn:7007922",
          "tgn:7029392"
        ],
        "placetype": [
          "aat:300008680"
        ],
        "id": 2523517,
        "name:xx": "Moose Lake"
      }
    },
    {
      "geometry": {
        "type": "Point",
        "coordinates": [
          -91.0167,
          46.0167
        ]
      },
      "type": "Feature",
      "properties": {
        "hierarchy": [
          "tgn:2523518",
          "tgn:1000001",
          "tgn:7012149",
          "tgn:2002353",
          "tgn:7007922",
          "tgn:7029392"
        ],
        "placetype": [
          "aat:300008680"
        ],
        "id": 2523518,
        "name:xx": "Moose Lake"
      }
    },
    {
      "geometry": {
        "type": "Point",
        "coordinates": [
          -109.4333,
          42.8167
        ]
      },
      "type": "Feature",
      "properties": {
        "hierarchy": [
          "tgn:2523519",
          "tgn:1000001",
          "tgn:7012149",
          "tgn:2002382",
          "tgn:7007923",
          "tgn:7029392"
        ],
        "placetype": [
          "aat:300008680"
        ],
        "id": 2523519,
        "name:xx": "Moose Lake"
      }
    }
  ]
}
