{
  "geometry": {
    "type": "Point",
    "coordinates": [
      -69.842,
      18.592
    ]
  },
  "type": "Feature",
  "properties": {
    "hierarchy": [
      "tgn:7593540",
      "tgn:7593368",
      "tgn:1000001",
      "tgn:7005388",
      "tgn:7029392"
    ],
    "placetype": [
      "aat:300008347"
    ],
    "id": 7593540,
    "name:xx": "La Victoria"
  }
}
