{
  "type": "FeatureCollection",
  "features": [
    {
      "geometry": {
        "type": "Point",
        "coordinates": [
          21.666667,
          36.95
        ]
      },
      "type": "Feature",
      "properties": {
        "hierarchy": [
          "tgn:7222600",
          "tgn:7011369",
          "tgn:7017076",
          "tgn:1000003",
          "tgn:1000074",
          "tgn:7029392"
        ],
        "placetype": [
          "aat:300387026"
        ],
        "id": 7222600,
        "name:xx": "Sikiás, Stenón"
      }
    },
    {
      "geometry": {
        "type": "Point",
        "coordinates": [
          23.966667,
          40.05
        ]
      },
      "type": "Feature",
      "properties": {
        "hierarchy": [
          "tgn:7222601",
          "tgn:7011170",
          "tgn:7002715",
          "tgn:1000003",
          "tgn:1000074",
          "tgn:7029392"
        ],
        "placetype": [
          "aat:300132316"
        ],
        "id": 7222601,
        "name:xx": "Sikiás, Órmos"
      }
    },
    {
      "geometry": {
        "type": "Point",
        "coordinates": [
          22.533333,
          38.333333
        ]
      },
      "type": "Feature",
      "properties": {
        "hierarchy": [
          "tgn:7222602",
          "tgn:7002741",
          "tgn:7017076",
          "tgn:1000003",
          "tgn:1000074",
          "tgn:7029392"
        ],
        "placetype": [
          "aat:300132316"
        ],
        "id": 7222602,
        "name:xx": "Sikiás, Órmos"
      }
    },
    {
      "geometry": {
        "type": "Point",
        "coordinates": [
          26.123611,
          38.463333
        ]
      },
      "type": "Feature",
      "properties": {
        "hierarchy": [
          "tgn:7222603",
          "tgn:7011161",
          "tgn:7002674",
          "tgn:1000003",
          "tgn:1000074",
          "tgn:7029392"
        ],
        "placetype": [
          "aat:300008347"
        ],
        "id": 7222603,
        "name:xx": "Sykiáda"
      }
    },
    {
      "geometry": {
        "type": "Point",
        "coordinates": [
          24.15,
          37.716667
        ]
      },
      "type": "Feature",
      "properties": {
        "hierarchy": [
          "tgn:7222604",
          "tgn:7002681",
          "tgn:7001395",
          "tgn:1000003",
          "tgn:1000074",
          "tgn:7029392"
        ],
        "placetype": [
          "aat:300132316"
        ],
        "id": 7222604,
        "name:xx": "Sikiá, Órmos"
      }
    },
    {
      "geometry": {
        "type": "Point",
        "coordinates": [
          24.516667,
          36.783333
        ]
      },
      "type": "Feature",
      "properties": {
        "hierarchy": [
          "tgn:7222605",
          "tgn:7011270",
          "tgn:7002674",
          "tgn:1000003",
          "tgn:1000074",
          "tgn:7029392"
        ],
        "placetype": [
          "aat:300132316"
        ],
        "id": 7222605,
        "name:xx": "Sikiá, Órmos"
      }
    },
    {
      "geometry": {
        "type": "Point",
        "coordinates": [
          23.15,
          37.233333
        ]
      },
      "type": "Feature",
      "properties": {
        "hierarchy": [
          "tgn:7222606",
          "tgn:7002681",
          "tgn:7001395",
          "tgn:1000003",
          "tgn:1000074",
          "tgn:7029392"
        ],
        "placetype": [
          "aat:300008850"
        ],
        "id": 7222606,
        "name:xx": "Sikiá, Kávos"
      }
    },
    {
      "geometry": {
        "type": "Point",
        "coordinates": [
          24,
          40.05
        ]
      },
      "type": "Feature",
      "properties": {
        "hierarchy": [
          "tgn:7222607",
          "tgn:7011170",
          "tgn:7002715",
          "tgn:1000003",
          "tgn:1000074",
          "tgn:7029392"
        ],
        "placetype": [
          "aat:300008850"
        ],
        "id": 7222607,
        "name:xx": "Sikiá, Ákra"
      }
    },
    {
      "geometry": {
        "type": "Point",
        "coordinates": [
          20.716667,
          38.233333
        ]
      },
      "type": "Feature",
      "properties": {
        "hierarchy": [
          "tgn:7222608",
          "tgn:7011167",
          "tgn:7001338",
          "tgn:1000003",
          "tgn:1000074",
          "tgn:7029392"
        ],
        "placetype": [
          "aat:300008850"
        ],
        "id": 7222608,
        "name:xx": "Makryá Poúnta, Ákra"
      }
    }
  ]
}
