{
  "geometry": {
    "type": "Point",
    "coordinates": [
      -109.2833,
      43.05
    ]
  },
  "type": "Feature",
  "properties": {
    "hierarchy": [
      "tgn:2740575",
      "tgn:1000001",
      "tgn:7012149",
      "tgn:2002371",
      "tgn:7007923",
      "tgn:7029392"
    ],
    "placetype": [
      "aat:300008680"
    ],
    "id": 2740575,
    "name:xx": "Upper Paradise Lake"
  }
}
