{
  "geometry": {
    "type": "Point",
    "coordinates": [
      75.33927,
      28.045456
    ]
  },
  "type": "Feature",
  "properties": {
    "hierarchy": [
      "tgn:7584893",
      "tgn:1000004",
      "tgn:7000198",
      "tgn:7016788",
      "tgn:7029392"
    ],
    "placetype": [
      "aat:300008347"
    ],
    "name:en": "Swāmi ka Bās",
    "id": 7584893
  }
}
