{
  "geometry": {
    "type": "Point",
    "coordinates": [
      -90.75,
      42.6167
    ]
  },
  "type": "Feature",
  "properties": {
    "hierarchy": [
      "tgn:2180575",
      "tgn:1000001",
      "tgn:2000591",
      "tgn:7012149",
      "tgn:7007253",
      "tgn:7029392"
    ],
    "placetype": [
      "aat:300008699"
    ],
    "id": 2180575,
    "name:xx": "Bloody Run"
  }
}
