{
  "geometry": {
    "type": "Point",
    "coordinates": [
      -123.9667,
      41.6667
    ]
  },
  "type": "Feature",
  "properties": {
    "hierarchy": [
      "tgn:2580699",
      "tgn:1000001",
      "tgn:7012149",
      "tgn:2000180",
      "tgn:7007157",
      "tgn:7029392"
    ],
    "placetype": [
      "aat:300008697"
    ],
    "id": 2580699,
    "name:xx": "Pigeon Roost Spring"
  }
}
