{
  "geometry": {
    "type": "Point",
    "coordinates": [
      33.811452,
      27.965995
    ]
  },
  "type": "Feature",
  "properties": {
    "hierarchy": [
      "tgn:7537350",
      "tgn:7001242",
      "tgn:7016833",
      "tgn:7001336",
      "tgn:7029392"
    ],
    "placetype": [
      "aat:300008808"
    ],
    "name:en": "Quţţâfa, Sha'ab",
    "id": 7537350
  }
}
