{
  "geometry": {
    "type": "Point",
    "coordinates": [
      -99.25,
      35.8167
    ]
  },
  "type": "Feature",
  "properties": {
    "hierarchy": [
      "tgn:2477725",
      "tgn:1000001",
      "tgn:2001644",
      "tgn:7012149",
      "tgn:7007707",
      "tgn:7029392"
    ],
    "placetype": [
      "aat:300006191"
    ],
    "id": 2477725,
    "name:xx": "Mabry Lake"
  }
}
