{
  "geometry": {
    "type": "Point",
    "coordinates": [
      -80.2333,
      37.8833
    ]
  },
  "type": "Feature",
  "properties": {
    "hierarchy": [
      "tgn:2298524",
      "tgn:1000001",
      "tgn:7012149",
      "tgn:2002264",
      "tgn:7013961",
      "tgn:7029392"
    ],
    "placetype": [
      "aat:300008699"
    ],
    "id": 2298524,
    "name:xx": "Dry Run"
  }
}
