{
  "geometry": {
    "type": "Point",
    "coordinates": [
      -71.0833,
      44.35
    ]
  },
  "type": "Feature",
  "properties": {
    "hierarchy": [
      "tgn:2305418",
      "tgn:1002300",
      "tgn:1000001",
      "tgn:7012149",
      "tgn:7007564",
      "tgn:7029392"
    ],
    "placetype": [
      "aat:300008699"
    ],
    "id": 2305418,
    "name:xx": "East Brook"
  }
}
