{
  "geometry": {
    "type": "Point",
    "coordinates": [
      27.172234,
      31.34438
    ]
  },
  "type": "Feature",
  "properties": {
    "hierarchy": [
      "tgn:7523451",
      "tgn:7001242",
      "tgn:7016833",
      "tgn:1001418",
      "tgn:7029392"
    ],
    "placetype": [
      "aat:300006207"
    ],
    "name:en": "Sânyet 'Eilet Dolâf",
    "id": 7523451
  }
}
