{
  "geometry": {
    "type": "Point",
    "coordinates": [
      -118.2167,
      33.8333
    ]
  },
  "type": "Feature",
  "properties": {
    "hierarchy": [
      "tgn:2010597",
      "tgn:1000001",
      "tgn:7016499",
      "tgn:7012149",
      "tgn:7007157",
      "tgn:1002608",
      "tgn:7029392"
    ],
    "placetype": [
      "aat:300000745"
    ],
    "id": 2010597,
    "name:xx": "Dominguez"
  }
}
