{
  "geometry": {
    "type": "Point",
    "coordinates": [
      -113.5167,
      34.95
    ]
  },
  "type": "Feature",
  "properties": {
    "hierarchy": [
      "tgn:2288111",
      "tgn:1000001",
      "tgn:7006451",
      "tgn:7012149",
      "tgn:2000098",
      "tgn:7029392"
    ],
    "placetype": [
      "aat:300008697"
    ],
    "id": 2288111,
    "name:xx": "Dinner Spring"
  }
}
