{
  "geometry": {
    "type": "Point",
    "coordinates": [
      -120.5667,
      39.1833
    ]
  },
  "type": "Feature",
  "properties": {
    "hierarchy": [
      "tgn:2765033",
      "tgn:1000001",
      "tgn:7012149",
      "tgn:7007157",
      "tgn:1002791",
      "tgn:7029392"
    ],
    "placetype": [
      "aat:300008798"
    ],
    "id": 2765033,
    "name:xx": "Whisky Hill"
  }
}
