{
  "geometry": {
    "type": "Point",
    "coordinates": [
      -82.9167,
      39.5333
    ]
  },
  "type": "Feature",
  "properties": {
    "hierarchy": [
      "tgn:2079933",
      "tgn:1000001",
      "tgn:7012149",
      "tgn:1002784",
      "tgn:7007706",
      "tgn:7029392"
    ],
    "placetype": [
      "aat:300387016"
    ],
    "id": 2079933,
    "name:xx": "Hayesville"
  }
}
