{
  "geometry": {
    "type": "Point",
    "coordinates": [
      31.305383,
      30.075552
    ]
  },
  "type": "Feature",
  "properties": {
    "hierarchy": [
      "tgn:7526320",
      "tgn:7001242",
      "tgn:7016833",
      "tgn:1001091",
      "tgn:7029392"
    ],
    "placetype": [
      "aat:300004792"
    ],
    "id": 7526320,
    "name:xx": "Mashrū' Tis'at 'Imārāt"
  }
}
