{
  "geometry": {
    "type": "Point",
    "coordinates": [
      -141.7333,
      63.9667
    ]
  },
  "type": "Feature",
  "properties": {
    "hierarchy": [
      "tgn:2139979",
      "tgn:7006450",
      "tgn:1000001",
      "tgn:7012149",
      "tgn:2000085",
      "tgn:7029392"
    ],
    "placetype": [
      "aat:300008706"
    ],
    "id": 2139979,
    "name:xx": "Atwater Creek"
  }
}
