{
  "geometry": {
    "type": "Point",
    "coordinates": [
      74.198057,
      22.741493
    ]
  },
  "type": "Feature",
  "properties": {
    "hierarchy": [
      "tgn:7571934",
      "tgn:1000004",
      "tgn:1001869",
      "tgn:7000198",
      "tgn:7029392"
    ],
    "placetype": [
      "aat:300008347"
    ],
    "name:en": "Jesāwāra",
    "id": 7571934
  }
}
