{
  "geometry": {
    "type": "Point",
    "coordinates": [
      31.811944,
      31.401389
    ]
  },
  "type": "Feature",
  "properties": {
    "hierarchy": [
      "tgn:7532505",
      "tgn:7001242",
      "tgn:7016833",
      "tgn:1001225",
      "tgn:7029392"
    ],
    "placetype": [
      "aat:300008347"
    ],
    "name:en": "Shaṭṭ Muhibb el-Saiyâla",
    "id": 7532505
  }
}
