{
  "type": "FeatureCollection",
  "features": [
    {
      "geometry": {
        "type": "Point",
        "coordinates": [
          3.3,
          44.55
        ]
      },
      "type": "Feature",
      "properties": {
        "hierarchy": [
          "tgn:7009330",
          "tgn:1000003",
          "tgn:7002885",
          "tgn:1000070",
          "tgn:7029392"
        ],
        "placetype": [
          "aat:300008347"
        ],
        "id": 7009330,
        "name:xx": "Marvejols"
      }
    },
    {
      "geometry": {
        "type": "Point",
        "coordinates": [
          3.9667,
          50.2833
        ]
      },
      "type": "Feature",
      "properties": {
        "hierarchy": [
          "tgn:7009331",
          "tgn:1000003",
          "tgn:7001097",
          "tgn:1000070",
          "tgn:7029392"
        ],
        "placetype": [
          "aat:300008347",
          "aat:300008389",
          "aat:300387302"
        ],
        "id": 7009331,
        "name:xx": "Maubeuge"
      }
    },
    {
      "geometry": {
        "type": "Point",
        "coordinates": [
          6.1667,
          48.7167
        ]
      },
      "type": "Feature",
      "properties": {
        "hierarchy": [
          "tgn:7009332",
          "tgn:1000003",
          "tgn:7002888",
          "tgn:1000070",
          "tgn:7029392"
        ],
        "placetype": [
          "aat:300008347"
        ],
        "id": 7009332,
        "name:xx": "Maxéville"
      }
    },
    {
      "geometry": {
        "type": "Point",
        "coordinates": [
          2,
          48.95
        ]
      },
      "type": "Feature",
      "properties": {
        "hierarchy": [
          "tgn:7009333",
          "tgn:1000003",
          "tgn:7002883",
          "tgn:1000070",
          "tgn:7029392"
        ],
        "placetype": [
          "aat:300008347"
        ],
        "id": 7009333,
        "name:xx": "Médan"
      }
    },
    {
      "geometry": {
        "type": "Point",
        "coordinates": [
          1.4,
          47.6333
        ]
      },
      "type": "Feature",
      "properties": {
        "hierarchy": [
          "tgn:7009334",
          "tgn:1000003",
          "tgn:7002877",
          "tgn:1000070",
          "tgn:7029392"
        ],
        "placetype": [
          "aat:300008347"
        ],
        "id": 7009334,
        "name:xx": "Menars"
      }
    },
    {
      "geometry": {
        "type": "Point",
        "coordinates": [
          3.5,
          44.5333
        ]
      },
      "type": "Feature",
      "properties": {
        "hierarchy": [
          "tgn:7009335",
          "tgn:1000003",
          "tgn:7002885",
          "tgn:1000070",
          "tgn:7029392"
        ],
        "placetype": [
          "aat:300008347"
        ],
        "id": 7009335,
        "name:xx": "Mende"
      }
    },
    {
      "geometry": {
        "type": "Point",
        "coordinates": [
          5.75,
          44.8167
        ]
      },
      "type": "Feature",
      "properties": {
        "hierarchy": [
          "tgn:7009336",
          "tgn:1000003",
          "tgn:1000070",
          "tgn:7002897",
          "tgn:7029392"
        ],
        "placetype": [
          "aat:300008347"
        ],
        "id": 7009336,
        "name:xx": "Mens"
      }
    },
    {
      "geometry": {
        "type": "Point",
        "coordinates": [
          7.5,
          43.7833
        ]
      },
      "type": "Feature",
      "properties": {
        "hierarchy": [
          "tgn:7009337",
          "tgn:1000003",
          "tgn:1000070",
          "tgn:7002895",
          "tgn:7029392"
        ],
        "placetype": [
          "aat:300008347",
          "aat:300179493",
          "aat:300387330",
          "aat:300008375",
          "aat:300387292",
          "aat:300387291"
        ],
        "id": 7009337,
        "name:xx": "Menton"
      }
    },
    {
      "geometry": {
        "type": "Point",
        "coordinates": [
          1.5,
          47.7167
        ]
      },
      "type": "Feature",
      "properties": {
        "hierarchy": [
          "tgn:7009338",
          "tgn:1000003",
          "tgn:7002877",
          "tgn:1000070",
          "tgn:7029392"
        ],
        "placetype": [
          "aat:300008347"
        ],
        "id": 7009338,
        "name:xx": "Mer"
      }
    },
    {
      "geometry": {
        "type": "Point",
        "coordinates": [
          2.0833,
          48.3
        ]
      },
      "type": "Feature",
      "properties": {
        "hierarchy": [
          "tgn:7009339",
          "tgn:1000003",
          "tgn:7002883",
          "tgn:1000070",
          "tgn:7029392"
        ],
        "placetype": [
          "aat:300008347"
        ],
        "id": 7009339,
        "name:xx": "Méréville"
      }
    }
  ]
}
