{
  "geometry": {
    "type": "Point",
    "coordinates": [
      -79.0833,
      36.5333
    ]
  },
  "type": "Feature",
  "properties": {
    "hierarchy": [
      "tgn:2777603",
      "tgn:1000001",
      "tgn:7012149",
      "tgn:7029392"
    ],
    "placetype": [
      "aat:300008706"
    ],
    "id": 2777603,
    "name:xx": "Winns Creek"
  }
}
