{
  "geometry": {
    "type": "Point",
    "coordinates": [
      -105.7333,
      37.1667
    ]
  },
  "type": "Feature",
  "properties": {
    "hierarchy": [
      "tgn:2640612",
      "tgn:1000001",
      "tgn:7012149",
      "tgn:7007158",
      "tgn:7029392"
    ],
    "placetype": [
      "aat:300386831"
    ],
    "id": 2640612,
    "name:xx": "San Luis Hills"
  }
}
