{
  "geometry": {
    "type": "Point",
    "coordinates": [
      142.0833,
      -34.1833
    ]
  },
  "type": "Feature",
  "properties": {
    "hierarchy": [
      "tgn:1097530",
      "tgn:7000490",
      "tgn:1000006",
      "tgn:7006238",
      "tgn:7029392"
    ],
    "placetype": [
      "aat:300008347"
    ],
    "id": 1097530,
    "name:xx": "Merbein"
  }
}
