{
  "type": "FeatureCollection",
  "features": [
    {
      "geometry": {
        "type": "Point",
        "coordinates": [
          9.183333,
          45.033333
        ]
      },
      "type": "Feature",
      "properties": {
        "hierarchy": [
          "tgn:7040500",
          "tgn:1000003",
          "tgn:7003151",
          "tgn:7003237",
          "tgn:1000080",
          "tgn:7029392"
        ],
        "placetype": [
          "aat:300008347"
        ],
        "id": 7040500,
        "name:xx": "Santa Giuletta"
      }
    },
    {
      "geometry": {
        "type": "Point",
        "coordinates": [
          15.533333,
          38.283333
        ]
      },
      "type": "Feature",
      "properties": {
        "hierarchy": [
          "tgn:7040501",
          "tgn:1000003",
          "tgn:7003122",
          "tgn:7003157",
          "tgn:1000080",
          "tgn:7029392"
        ],
        "placetype": [
          "aat:300008347"
        ],
        "id": 7040501,
        "name:xx": "Santa Giorgia"
      }
    },
    {
      "geometry": {
        "type": "Point",
        "coordinates": [
          9.014722,
          39.213889
        ]
      },
      "type": "Feature",
      "properties": {
        "hierarchy": [
          "tgn:7040502",
          "tgn:1001641",
          "tgn:1000003",
          "tgn:7003121",
          "tgn:1000080",
          "tgn:7029392"
        ],
        "placetype": [
          "aat:300386871"
        ],
        "id": 7040502,
        "name:xx": "Santa Gilla, Saline di"
      }
    },
    {
      "geometry": {
        "type": "Point",
        "coordinates": [
          14.366667,
          40.6
        ]
      },
      "type": "Feature",
      "properties": {
        "hierarchy": [
          "tgn:7040504",
          "tgn:7003013",
          "tgn:7003005",
          "tgn:1000003",
          "tgn:1000080",
          "tgn:7029392"
        ],
        "placetype": [
          "aat:300008347"
        ],
        "id": 7040504,
        "name:xx": "Sant'Agata su due Golfi"
      }
    },
    {
      "geometry": {
        "type": "Point",
        "coordinates": [
          15.983333,
          39.616667
        ]
      },
      "type": "Feature",
      "properties": {
        "hierarchy": [
          "tgn:7040508",
          "tgn:1003450",
          "tgn:7007850",
          "tgn:1000003",
          "tgn:1000080",
          "tgn:7029392"
        ],
        "placetype": [
          "aat:300008347"
        ],
        "id": 7040508,
        "name:xx": "Sant'Agata di Esaro"
      }
    }
  ]
}
