{
  "geometry": {
    "type": "Point",
    "coordinates": [
      -109.4667,
      33.3167
    ]
  },
  "type": "Feature",
  "properties": {
    "hierarchy": [
      "tgn:2642957",
      "tgn:1000001",
      "tgn:7006451",
      "tgn:2000095",
      "tgn:7012149",
      "tgn:7029392"
    ],
    "placetype": [
      "aat:300006191"
    ],
    "id": 2642957,
    "name:xx": "Sandstone Tank"
  }
}
