{
  "geometry": {
    "type": "Point",
    "coordinates": [
      -121.1833,
      40.1333
    ]
  },
  "type": "Feature",
  "properties": {
    "hierarchy": [
      "tgn:2544197",
      "tgn:1000001",
      "tgn:7012149",
      "tgn:7007157",
      "tgn:2000187",
      "tgn:7029392"
    ],
    "placetype": [
      "aat:300008706"
    ],
    "id": 2544197,
    "name:xx": "North Branch Mosquito Creek"
  }
}
