{
  "geometry": {
    "type": "Point",
    "coordinates": [
      -70.6167,
      41.65
    ]
  },
  "type": "Feature",
  "properties": {
    "hierarchy": [
      "tgn:2607294",
      "tgn:1002165",
      "tgn:1000001",
      "tgn:7012149",
      "tgn:7007517",
      "tgn:7029392"
    ],
    "placetype": [
      "aat:300386845"
    ],
    "id": 2607294,
    "name:xx": "Rands Harbor"
  }
}
