{
  "geometry": {
    "type": "Point",
    "coordinates": [
      -81.7833,
      39.15
    ]
  },
  "type": "Feature",
  "properties": {
    "hierarchy": [
      "tgn:2701618",
      "tgn:1000001",
      "tgn:7012149",
      "tgn:2001616",
      "tgn:7007706",
      "tgn:7029392"
    ],
    "placetype": [
      "aat:300008699"
    ],
    "id": 2701618,
    "name:xx": "Sugarcamp Run"
  }
}
