{
  "type": "FeatureCollection",
  "features": [
    {
      "geometry": {
        "type": "Point",
        "coordinates": [
          -110.8,
          29.4
        ]
      },
      "type": "Feature",
      "properties": {
        "hierarchy": [
          "tgn:7365900",
          "tgn:1000001",
          "tgn:1001960",
          "tgn:7005560",
          "tgn:7029392"
        ],
        "placetype": [
          "aat:300008347"
        ],
        "id": 7365900,
        "name:xx": "Galera"
      }
    },
    {
      "geometry": {
        "type": "Point",
        "coordinates": [
          -110.5,
          29.366667
        ]
      },
      "type": "Feature",
      "properties": {
        "hierarchy": [
          "tgn:7365901",
          "tgn:1000001",
          "tgn:1001960",
          "tgn:7005560",
          "tgn:7029392"
        ],
        "placetype": [
          "aat:300008347"
        ],
        "id": 7365901,
        "name:xx": "Galera"
      }
    },
    {
      "geometry": {
        "type": "Point",
        "coordinates": [
          -110.783333,
          29.2
        ]
      },
      "type": "Feature",
      "properties": {
        "hierarchy": [
          "tgn:7365902",
          "tgn:1000001",
          "tgn:1001960",
          "tgn:7005560",
          "tgn:7029392"
        ],
        "placetype": [
          "aat:300008347"
        ],
        "id": 7365902,
        "name:xx": "Galera"
      }
    },
    {
      "geometry": {
        "type": "Point",
        "coordinates": [
          -106.333333,
          26.933333
        ]
      },
      "type": "Feature",
      "properties": {
        "hierarchy": [
          "tgn:7365903",
          "tgn:7005581",
          "tgn:1000001",
          "tgn:7005560",
          "tgn:7029392"
        ],
        "placetype": [
          "aat:300008347"
        ],
        "id": 7365903,
        "name:xx": "Galera"
      }
    },
    {
      "geometry": {
        "type": "Point",
        "coordinates": [
          -100.816667,
          21.75
        ]
      },
      "type": "Feature",
      "properties": {
        "hierarchy": [
          "tgn:7365904",
          "tgn:1000001",
          "tgn:7005594",
          "tgn:7005560",
          "tgn:7029392"
        ],
        "placetype": [
          "aat:300008347"
        ],
        "id": 7365904,
        "name:xx": "Galera"
      }
    },
    {
      "geometry": {
        "type": "Point",
        "coordinates": [
          -98.233333,
          21.283333
        ]
      },
      "type": "Feature",
      "properties": {
        "hierarchy": [
          "tgn:7365905",
          "tgn:1000001",
          "tgn:7005599",
          "tgn:7005560",
          "tgn:7029392"
        ],
        "placetype": [
          "aat:300008347"
        ],
        "id": 7365905,
        "name:xx": "Galera"
      }
    },
    {
      "geometry": {
        "type": "Point",
        "coordinates": [
          -100.316667,
          19.333333
        ]
      },
      "type": "Feature",
      "properties": {
        "hierarchy": [
          "tgn:7365906",
          "tgn:1000001",
          "tgn:1001893",
          "tgn:7005560",
          "tgn:7029392"
        ],
        "placetype": [
          "aat:300008347"
        ],
        "id": 7365906,
        "name:xx": "Galera"
      }
    },
    {
      "geometry": {
        "type": "Point",
        "coordinates": [
          -96.316667,
          18.316667
        ]
      },
      "type": "Feature",
      "properties": {
        "hierarchy": [
          "tgn:7365907",
          "tgn:1000001",
          "tgn:7005591",
          "tgn:7005560",
          "tgn:7029392"
        ],
        "placetype": [
          "aat:300008347"
        ],
        "id": 7365907,
        "name:xx": "Galera"
      }
    },
    {
      "geometry": {
        "type": "Point",
        "coordinates": [
          -106.116667,
          25.183333
        ]
      },
      "type": "Feature",
      "properties": {
        "hierarchy": [
          "tgn:7365908",
          "tgn:7005583",
          "tgn:1000001",
          "tgn:7005560",
          "tgn:7029392"
        ],
        "placetype": [
          "aat:300008795"
        ],
        "id": 7365908,
        "name:xx": "Galeana, Cerro"
      }
    },
    {
      "geometry": {
        "type": "Point",
        "coordinates": [
          -107.1,
          25.866667
        ]
      },
      "type": "Feature",
      "properties": {
        "hierarchy": [
          "tgn:7365909",
          "tgn:7005581",
          "tgn:1000001",
          "tgn:7005560",
          "tgn:7029392"
        ],
        "placetype": [
          "aat:300008699"
        ],
        "id": 7365909,
        "name:xx": "Galeana, Arroyo"
      }
    }
  ]
}
