{
  "geometry": {
    "type": "Point",
    "coordinates": [
      -146.5833,
      60.8333
    ]
  },
  "type": "Feature",
  "properties": {
    "hierarchy": [
      "tgn:2481794",
      "tgn:7006450",
      "tgn:1000001",
      "tgn:7012149",
      "tgn:2000086",
      "tgn:7029392"
    ],
    "placetype": [
      "aat:300132316"
    ],
    "id": 2481794,
    "name:xx": "Landlocked Bay"
  }
}
