{
  "type": "FeatureCollection",
  "features": [
    {
      "geometry": {
        "type": "Point",
        "coordinates": [
          121.87716,
          25.120856
        ]
      },
      "type": "Feature",
      "properties": {
        "hierarchy": [
          "tgn:7488821",
          "tgn:1000004",
          "tgn:1000454",
          "tgn:1000141",
          "tgn:7029392"
        ],
        "placetype": [
          "aat:300008347"
        ],
        "id": 7488821,
        "name:xx": "Nanya"
      }
    },
    {
      "geometry": {
        "type": "Point",
        "coordinates": [
          121.5265,
          25.1092
        ]
      },
      "type": "Feature",
      "properties": {
        "hierarchy": [
          "tgn:7488822",
          "tgn:1000004",
          "tgn:1000959",
          "tgn:1000141",
          "tgn:7029392"
        ],
        "placetype": [
          "aat:300008347"
        ],
        "id": 7488822,
        "name:xx": "Nanya"
      }
    },
    {
      "geometry": {
        "type": "Point",
        "coordinates": [
          120.966944,
          24.823333
        ]
      },
      "type": "Feature",
      "properties": {
        "hierarchy": [
          "tgn:7488823",
          "tgn:1000004",
          "tgn:7001002",
          "tgn:1000141",
          "tgn:7029392"
        ],
        "placetype": [
          "aat:300008347"
        ],
        "id": 7488823,
        "name:xx": "Nanya"
      }
    },
    {
      "geometry": {
        "type": "Point",
        "coordinates": [
          120.60499,
          23.918634
        ]
      },
      "type": "Feature",
      "properties": {
        "hierarchy": [
          "tgn:7488824",
          "tgn:1000004",
          "tgn:7467799",
          "tgn:1000141",
          "tgn:7029392"
        ],
        "placetype": [
          "aat:300008347"
        ],
        "id": 7488824,
        "name:xx": "Nanya"
      }
    },
    {
      "geometry": {
        "type": "Point",
        "coordinates": [
          120.699997,
          23.830514
        ]
      },
      "type": "Feature",
      "properties": {
        "hierarchy": [
          "tgn:7488825",
          "tgn:7488858",
          "tgn:1000004",
          "tgn:1000141",
          "tgn:7029392"
        ],
        "placetype": [
          "aat:300387173"
        ],
        "id": 7488825,
        "name:xx": "Nanya Cun"
      }
    },
    {
      "geometry": {
        "type": "Point",
        "coordinates": [
          121.104167,
          24.879722
        ]
      },
      "type": "Feature",
      "properties": {
        "hierarchy": [
          "tgn:7488826",
          "tgn:1000004",
          "tgn:7471332",
          "tgn:1000141",
          "tgn:7029392"
        ],
        "placetype": [
          "aat:300008347"
        ],
        "id": 7488826,
        "name:xx": "Nanwo"
      }
    },
    {
      "geometry": {
        "type": "Point",
        "coordinates": [
          121.111389,
          24.701389
        ]
      },
      "type": "Feature",
      "properties": {
        "hierarchy": [
          "tgn:7488827",
          "tgn:1000004",
          "tgn:7471332",
          "tgn:1000141",
          "tgn:7029392"
        ],
        "placetype": [
          "aat:300008347"
        ],
        "id": 7488827,
        "name:xx": "Nanwo"
      }
    },
    {
      "geometry": {
        "type": "Point",
        "coordinates": [
          120.755,
          24.484167
        ]
      },
      "type": "Feature",
      "properties": {
        "hierarchy": [
          "tgn:7488828",
          "tgn:7487020",
          "tgn:1000004",
          "tgn:1000141",
          "tgn:7029392"
        ],
        "placetype": [
          "aat:300008347"
        ],
        "id": 7488828,
        "name:xx": "Nanwo"
      }
    },
    {
      "geometry": {
        "type": "Point",
        "coordinates": [
          119.498056,
          23.233056
        ]
      },
      "type": "Feature",
      "properties": {
        "hierarchy": [
          "tgn:7488829",
          "tgn:1000004",
          "tgn:7004300",
          "tgn:1000141",
          "tgn:7029392"
        ],
        "placetype": [
          "aat:300011692"
        ],
        "id": 7488829,
        "name:xx": "Liwenzi"
      }
    }
  ]
}
