{
  "geometry": {
    "type": "Point",
    "coordinates": [
      26.1333,
      50.1667
    ]
  },
  "type": "Feature",
  "properties": {
    "hierarchy": [
      "tgn:1051745",
      "tgn:1000003",
      "tgn:7011668",
      "tgn:7006660",
      "tgn:7029392"
    ],
    "placetype": [
      "aat:300008347"
    ],
    "id": 1051745,
    "name:xx": "Shumskoye"
  }
}
