{
  "geometry": {
    "type": "Point",
    "coordinates": [
      -111.7833,
      45.8167
    ]
  },
  "type": "Feature",
  "properties": {
    "hierarchy": [
      "tgn:2635433",
      "tgn:1000001",
      "tgn:7012149",
      "tgn:2001281",
      "tgn:7007524",
      "tgn:7029392"
    ],
    "placetype": [
      "aat:300000390"
    ],
    "id": 2635433,
    "name:xx": "SE SW Section 24 Mine"
  }
}
