{
  "geometry": {
    "type": "Point",
    "coordinates": [
      -87.5167,
      33.2833
    ]
  },
  "type": "Feature",
  "properties": {
    "hierarchy": [
      "tgn:2198700",
      "tgn:7002659",
      "tgn:1000001",
      "tgn:7012149",
      "tgn:2000062",
      "tgn:7029392"
    ],
    "placetype": [
      "aat:300008697"
    ],
    "id": 2198700,
    "name:xx": "Browns Spring"
  }
}
