{
  "geometry": {
    "type": "Point",
    "coordinates": [
      -73.95,
      45.3833
    ]
  },
  "type": "Feature",
  "properties": {
    "hierarchy": [
      "tgn:1015270",
      "tgn:7005685",
      "tgn:1000001",
      "tgn:7005804",
      "tgn:1008582",
      "tgn:7029392"
    ],
    "placetype": [
      "aat:300008347"
    ],
    "id": 1015270,
    "name:xx": "Île-Perrot"
  }
}
