{
  "geometry": {
    "type": "Point",
    "coordinates": [
      -73.45,
      -43.066667
    ]
  },
  "type": "Feature",
  "properties": {
    "hierarchy": [
      "tgn:7292637",
      "tgn:1001699",
      "tgn:1000049",
      "tgn:1000002",
      "tgn:7029392"
    ],
    "placetype": [
      "aat:300011692"
    ],
    "id": 7292637,
    "name:xx": "El Navío, Roca"
  }
}
