{
  "type": "FeatureCollection",
  "features": [
    {
      "geometry": {
        "type": "Point",
        "coordinates": [
          -120.8,
          39.5333
        ]
      },
      "type": "Feature",
      "properties": {
        "hierarchy": [
          "tgn:2668460",
          "tgn:1000001",
          "tgn:7012149",
          "tgn:7007157",
          "tgn:1002894",
          "tgn:7029392"
        ],
        "placetype": [
          "aat:300008706"
        ],
        "id": 2668460,
        "name:xx": "Slate Castle Creek"
      }
    },
    {
      "geometry": {
        "type": "Point",
        "coordinates": [
          -87.4,
          33.7833
        ]
      },
      "type": "Feature",
      "properties": {
        "hierarchy": [
          "tgn:2668461",
          "tgn:7002659",
          "tgn:1000001",
          "tgn:7012149",
          "tgn:2000063",
          "tgn:7029392"
        ],
        "placetype": [
          "aat:300008706"
        ],
        "id": 2668461,
        "name:xx": "Slate Creek"
      }
    },
    {
      "geometry": {
        "type": "Point",
        "coordinates": [
          -133.3667,
          57.5167
        ]
      },
      "type": "Feature",
      "properties": {
        "hierarchy": [
          "tgn:2668462",
          "tgn:7006450",
          "tgn:1000001",
          "tgn:7012149",
          "tgn:7019760",
          "tgn:7029392"
        ],
        "placetype": [
          "aat:300008706"
        ],
        "id": 2668462,
        "name:xx": "Slate Creek"
      }
    },
    {
      "geometry": {
        "type": "Point",
        "coordinates": [
          -134.6833,
          58.4333
        ]
      },
      "type": "Feature",
      "properties": {
        "hierarchy": [
          "tgn:2668463",
          "tgn:7006450",
          "tgn:1000001",
          "tgn:2124089",
          "tgn:7012149",
          "tgn:7029392"
        ],
        "placetype": [
          "aat:300008706"
        ],
        "id": 2668463,
        "name:xx": "Slate Creek"
      }
    },
    {
      "geometry": {
        "type": "Point",
        "coordinates": [
          -160.0667,
          60.1833
        ]
      },
      "type": "Feature",
      "properties": {
        "hierarchy": [
          "tgn:2668464",
          "tgn:7006450",
          "tgn:2000069",
          "tgn:1000001",
          "tgn:7012149",
          "tgn:7029392"
        ],
        "placetype": [
          "aat:300008706"
        ],
        "id": 2668464,
        "name:xx": "Slate Creek"
      }
    },
    {
      "geometry": {
        "type": "Point",
        "coordinates": [
          -149.5833,
          60.6
        ]
      },
      "type": "Feature",
      "properties": {
        "hierarchy": [
          "tgn:2668465",
          "tgn:7006450",
          "tgn:1000001",
          "tgn:7019698",
          "tgn:7012149",
          "tgn:7029392"
        ],
        "placetype": [
          "aat:300008706"
        ],
        "id": 2668465,
        "name:xx": "Slate Creek"
      }
    },
    {
      "geometry": {
        "type": "Point",
        "coordinates": [
          -145.2833,
          61.4
        ]
      },
      "type": "Feature",
      "properties": {
        "hierarchy": [
          "tgn:2668466",
          "tgn:7006450",
          "tgn:1000001",
          "tgn:7012149",
          "tgn:2000086",
          "tgn:7029392"
        ],
        "placetype": [
          "aat:300008706"
        ],
        "id": 2668466,
        "name:xx": "Slate Creek"
      }
    },
    {
      "geometry": {
        "type": "Point",
        "coordinates": [
          -158.75,
          62
        ]
      },
      "type": "Feature",
      "properties": {
        "hierarchy": [
          "tgn:2668467",
          "tgn:7006450",
          "tgn:1000001",
          "tgn:7012149",
          "tgn:2000089",
          "tgn:7029392"
        ],
        "placetype": [
          "aat:300008706"
        ],
        "id": 2668467,
        "name:xx": "Slate Creek"
      }
    },
    {
      "geometry": {
        "type": "Point",
        "coordinates": [
          -151.6667,
          62.45
        ]
      },
      "type": "Feature",
      "properties": {
        "hierarchy": [
          "tgn:2668468",
          "tgn:7006450",
          "tgn:1000001",
          "tgn:2124053",
          "tgn:7012149",
          "tgn:7029392"
        ],
        "placetype": [
          "aat:300008706"
        ],
        "id": 2668468,
        "name:xx": "Slate Creek"
      }
    },
    {
      "geometry": {
        "type": "Point",
        "coordinates": [
          -144.7667,
          63.1667
        ]
      },
      "type": "Feature",
      "properties": {
        "hierarchy": [
          "tgn:2668469",
          "tgn:7006450",
          "tgn:1000001",
          "tgn:7012149",
          "tgn:2000085",
          "tgn:7029392"
        ],
        "placetype": [
          "aat:300008706"
        ],
        "id": 2668469,
        "name:xx": "Slate Creek"
      }
    }
  ]
}
