{
  "geometry": {
    "type": "Point",
    "coordinates": [
      -93.7667,
      35.8167
    ]
  },
  "type": "Feature",
  "properties": {
    "hierarchy": [
      "tgn:2305999",
      "tgn:1000001",
      "tgn:7016172",
      "tgn:7012149",
      "tgn:7029392"
    ],
    "placetype": [
      "aat:300008706"
    ],
    "id": 2305999,
    "name:xx": "East Fleming Creek"
  }
}
