{
  "geometry": {
    "type": "Point",
    "coordinates": [
      23.7667,
      54.9333
    ]
  },
  "type": "Feature",
  "properties": {
    "hierarchy": [
      "tgn:1127726",
      "tgn:1000003",
      "tgn:7006542",
      "tgn:7029392"
    ],
    "placetype": [
      "aat:300008707"
    ],
    "id": 1127726,
    "name:xx": "Nevėžis"
  }
}
