{
  "geometry": {
    "type": "Point",
    "coordinates": [
      -148.7167,
      60.6833
    ]
  },
  "type": "Feature",
  "properties": {
    "hierarchy": [
      "tgn:2252040",
      "tgn:7006450",
      "tgn:1000001",
      "tgn:7019698",
      "tgn:7012149",
      "tgn:7029392"
    ],
    "placetype": [
      "aat:300008835"
    ],
    "id": 2252040,
    "name:xx": "Concordia Glacier"
  }
}
