{
  "geometry": {
    "type": "Point",
    "coordinates": [
      71.7167,
      28.3667
    ]
  },
  "type": "Feature",
  "properties": {
    "hierarchy": [
      "tgn:1083561",
      "tgn:1000004",
      "tgn:1001490",
      "tgn:1000133",
      "tgn:7029392"
    ],
    "placetype": [
      "aat:300008347"
    ],
    "id": 1083561,
    "name:xx": "Khāngarh"
  }
}
