{
  "geometry": {
    "type": "Point",
    "coordinates": [
      -83.6833,
      38.0167
    ]
  },
  "type": "Feature",
  "properties": {
    "hierarchy": [
      "tgn:2540906",
      "tgn:1002169",
      "tgn:1000001",
      "tgn:7012149",
      "tgn:7007255",
      "tgn:7029392"
    ],
    "placetype": [
      "aat:300008699"
    ],
    "id": 2540906,
    "name:xx": "Nichols Branch"
  }
}
