{
  "geometry": {
    "type": "Point",
    "coordinates": [
      -2.55,
      41.483333
    ]
  },
  "type": "Feature",
  "properties": {
    "hierarchy": [
      "tgn:7303741",
      "tgn:7002842",
      "tgn:7001158",
      "tgn:1000003",
      "tgn:1000095",
      "tgn:7029392"
    ],
    "placetype": [
      "aat:300008699"
    ],
    "id": 7303741,
    "name:xx": "Morón, Río"
  }
}
