{
  "geometry": {
    "type": "Point",
    "coordinates": [
      3.9667,
      45.7167
    ]
  },
  "type": "Feature",
  "properties": {
    "hierarchy": [
      "tgn:1035213",
      "tgn:1000003",
      "tgn:1000070",
      "tgn:7002897",
      "tgn:7029392"
    ],
    "placetype": [
      "aat:300008347"
    ],
    "id": 1035213,
    "name:xx": "Sail-sous-Couzan"
  }
}
