{
  "geometry": {
    "type": "Point",
    "coordinates": [
      -74.5167,
      41.15
    ]
  },
  "type": "Feature",
  "properties": {
    "hierarchy": [
      "tgn:2175730",
      "tgn:1000001",
      "tgn:1002934",
      "tgn:7012149",
      "tgn:7007565",
      "tgn:7029392"
    ],
    "placetype": [
      "aat:300008706"
    ],
    "id": 2175730,
    "name:xx": "Black Creek"
  }
}
