{
  "geometry": {
    "type": "Point",
    "coordinates": [
      -93.0167,
      30.1833
    ]
  },
  "type": "Feature",
  "properties": {
    "hierarchy": [
      "tgn:2306641",
      "tgn:1000001",
      "tgn:2000863",
      "tgn:7012149",
      "tgn:7007256",
      "tgn:7029392"
    ],
    "placetype": [
      "aat:300008699"
    ],
    "id": 2306641,
    "name:xx": "East Fork English Bayou"
  }
}
