{
  "geometry": {
    "type": "Point",
    "coordinates": [
      88.4167,
      22.9167
    ]
  },
  "type": "Feature",
  "properties": {
    "hierarchy": [
      "tgn:1075825",
      "tgn:1000004",
      "tgn:7000198",
      "tgn:1001977",
      "tgn:7029392"
    ],
    "placetype": [
      "aat:300008347"
    ],
    "id": 1075825,
    "name:xx": "Khāsbāti"
  }
}
