{
  "geometry": {
    "type": "Point",
    "coordinates": [
      -118.7833,
      43.0333
    ]
  },
  "type": "Feature",
  "properties": {
    "hierarchy": [
      "tgn:2286773",
      "tgn:1000001",
      "tgn:7012149",
      "tgn:2001709",
      "tgn:7007708",
      "tgn:7029392"
    ],
    "placetype": [
      "aat:300008905"
    ],
    "id": 2286773,
    "name:xx": "Diamond Swamp"
  }
}
