{
  "geometry": {
    "type": "Point",
    "coordinates": [
      -107.2333,
      37.7667
    ]
  },
  "type": "Feature",
  "properties": {
    "hierarchy": [
      "tgn:2781759",
      "tgn:1000001",
      "tgn:7012149",
      "tgn:2000227",
      "tgn:7007158",
      "tgn:7029392"
    ],
    "placetype": [
      "aat:300008761"
    ],
    "id": 2781759,
    "name:xx": "Woods Canyon"
  }
}
