{
  "geometry": {
    "type": "Point",
    "coordinates": [
      -82.15,
      39.1833
    ]
  },
  "type": "Feature",
  "properties": {
    "hierarchy": [
      "tgn:2329776",
      "tgn:1000001",
      "tgn:7012149",
      "tgn:2001616",
      "tgn:7007706",
      "tgn:7029392"
    ],
    "placetype": [
      "aat:300008699"
    ],
    "id": 2329776,
    "name:xx": "Fivemile Run"
  }
}
