{
  "geometry": {
    "type": "Point",
    "coordinates": [
      -119.05,
      48.25
    ]
  },
  "type": "Feature",
  "properties": {
    "hierarchy": [
      "tgn:2574000",
      "tgn:1000001",
      "tgn:7012149",
      "tgn:1002742",
      "tgn:7007920",
      "tgn:7029392"
    ],
    "placetype": [
      "aat:300008706"
    ],
    "id": 2574000,
    "name:xx": "Peel Creek"
  }
}
