{
  "geometry": {
    "type": "Point",
    "coordinates": [
      1.25,
      9.1667
    ]
  },
  "type": "Feature",
  "properties": {
    "hierarchy": [
      "tgn:7000495",
      "tgn:7001242",
      "tgn:7029392"
    ],
    "placetype": [
      "aat:300008707"
    ],
    "id": 7000495,
    "name:xx": "Volta Blanche"
  }
}
