{
  "geometry": {
    "type": "Point",
    "coordinates": [
      79.75,
      19.833333
    ]
  },
  "type": "Feature",
  "properties": {
    "hierarchy": [
      "tgn:7570704",
      "tgn:1000004",
      "tgn:7000198",
      "tgn:1001895",
      "tgn:7029392"
    ],
    "placetype": [
      "aat:300008347"
    ],
    "name:en": "Ghānpur",
    "id": 7570704
  }
}
