{
  "geometry": {
    "type": "Point",
    "coordinates": [
      28.05,
      -26.25
    ]
  },
  "type": "Feature",
  "properties": {
    "hierarchy": [
      "tgn:1005466",
      "tgn:7001242",
      "tgn:7017576",
      "tgn:1000193",
      "tgn:7029392"
    ],
    "placetype": [
      "aat:300000745"
    ],
    "id": 1005466,
    "name:xx": "Rosettenville"
  }
}
