{
  "geometry": {
    "type": "Point",
    "coordinates": [
      -85.25,
      43.8167
    ]
  },
  "type": "Feature",
  "properties": {
    "hierarchy": [
      "tgn:2171463",
      "tgn:1000001",
      "tgn:7012149",
      "tgn:2000987",
      "tgn:7007520",
      "tgn:7029392"
    ],
    "placetype": [
      "aat:300008706"
    ],
    "id": 2171463,
    "name:xx": "Big Stone Creek"
  }
}
