{
  "type": "FeatureCollection",
  "features": [
    {
      "geometry": {
        "type": "Point",
        "coordinates": [
          -2.05,
          52.1
        ]
      },
      "type": "Feature",
      "properties": {
        "hierarchy": [
          "tgn:7442651",
          "tgn:7002445",
          "tgn:1000003",
          "tgn:5000227",
          "tgn:7008591",
          "tgn:7029392"
        ],
        "placetype": [
          "aat:300008347"
        ],
        "name:en": "Wick",
        "id": 7442651
      }
    },
    {
      "geometry": {
        "type": "Point",
        "coordinates": [
          -2.423611,
          51.453056
        ]
      },
      "type": "Feature",
      "properties": {
        "hierarchy": [
          "tgn:7442652",
          "tgn:7002445",
          "tgn:1000003",
          "tgn:7019020",
          "tgn:7008591",
          "tgn:7029392"
        ],
        "placetype": [
          "aat:300008347"
        ],
        "name:en": "Wick",
        "id": 7442652
      }
    },
    {
      "geometry": {
        "type": "Point",
        "coordinates": [
          -3.549444,
          51.439444
        ]
      },
      "type": "Feature",
      "properties": {
        "hierarchy": [
          "tgn:7442653",
          "tgn:7002443",
          "tgn:1000003",
          "tgn:7018966",
          "tgn:7008591",
          "tgn:7029392"
        ],
        "placetype": [
          "aat:300008347"
        ],
        "name:en": "Wick",
        "id": 7442653
      }
    },
    {
      "geometry": {
        "type": "Point",
        "coordinates": [
          -0.533333,
          50.816667
        ]
      },
      "type": "Feature",
      "properties": {
        "hierarchy": [
          "tgn:7442655",
          "tgn:7002445",
          "tgn:1000003",
          "tgn:7008134",
          "tgn:7008591",
          "tgn:7029392"
        ],
        "placetype": [
          "aat:300008347"
        ],
        "name:en": "Wick",
        "id": 7442655
      }
    },
    {
      "geometry": {
        "type": "Point",
        "coordinates": [
          -1.283333,
          52.466667
        ]
      },
      "type": "Feature",
      "properties": {
        "hierarchy": [
          "tgn:7442658",
          "tgn:7002445",
          "tgn:1000003",
          "tgn:7008178",
          "tgn:7008591",
          "tgn:7029392"
        ],
        "placetype": [
          "aat:300008347"
        ],
        "name:en": "Wibtoft",
        "id": 7442658
      }
    }
  ]
}
