{
  "type": "FeatureCollection",
  "features": [
    {
      "geometry": {
        "type": "Point",
        "coordinates": [
          125.2833,
          24.9
        ]
      },
      "type": "Feature",
      "properties": {
        "hierarchy": [
          "tgn:1080451",
          "tgn:1010150",
          "tgn:7004299",
          "tgn:7004290",
          "tgn:1009136",
          "tgn:1000004",
          "tgn:1001016",
          "tgn:1000120",
          "tgn:7029392"
        ],
        "placetype": [
          "aat:300008347"
        ],
        "id": 1080451,
        "name:xx": "Karimata"
      }
    },
    {
      "geometry": {
        "type": "Point",
        "coordinates": [
          137,
          35
        ]
      },
      "type": "Feature",
      "properties": {
        "hierarchy": [
          "tgn:1080452",
          "tgn:7016579",
          "tgn:7000895",
          "tgn:1000004",
          "tgn:1000120",
          "tgn:7029392"
        ],
        "placetype": [
          "aat:300008347"
        ],
        "id": 1080452,
        "name:xx": "Kariya"
      }
    },
    {
      "geometry": {
        "type": "Point",
        "coordinates": [
          141.5,
          40.2667
        ]
      },
      "type": "Feature",
      "properties": {
        "hierarchy": [
          "tgn:1080454",
          "tgn:7016687",
          "tgn:1000004",
          "tgn:7000893",
          "tgn:1000120",
          "tgn:7029392"
        ],
        "placetype": [
          "aat:300008347"
        ],
        "id": 1080454,
        "name:xx": "Karumai"
      }
    },
    {
      "geometry": {
        "type": "Point",
        "coordinates": [
          135.9333,
          34.75
        ]
      },
      "type": "Feature",
      "properties": {
        "hierarchy": [
          "tgn:1080455",
          "tgn:1000004",
          "tgn:1000998",
          "tgn:7000896",
          "tgn:1000120",
          "tgn:7029392"
        ],
        "placetype": [
          "aat:300008347"
        ],
        "id": 1080455,
        "name:xx": "Kasagi"
      }
    },
    {
      "geometry": {
        "type": "Point",
        "coordinates": [
          137.15,
          35.2833
        ]
      },
      "type": "Feature",
      "properties": {
        "hierarchy": [
          "tgn:1080456",
          "tgn:7000895",
          "tgn:1000004",
          "tgn:1000977",
          "tgn:1000120",
          "tgn:7029392"
        ],
        "placetype": [
          "aat:300008347"
        ],
        "id": 1080456,
        "name:xx": "Kasahara"
      }
    },
    {
      "geometry": {
        "type": "Point",
        "coordinates": [
          139.4167,
          35.9
        ]
      },
      "type": "Feature",
      "properties": {
        "hierarchy": [
          "tgn:1080457",
          "tgn:1000004",
          "tgn:7000894",
          "tgn:7016797",
          "tgn:1000120",
          "tgn:7029392"
        ],
        "placetype": [
          "aat:300008347"
        ],
        "id": 1080457,
        "name:xx": "Kasahata"
      }
    },
    {
      "geometry": {
        "type": "Point",
        "coordinates": [
          137.666,
          34.766
        ]
      },
      "type": "Feature",
      "properties": {
        "hierarchy": [
          "tgn:1080458",
          "tgn:7016675",
          "tgn:1000004",
          "tgn:7000896",
          "tgn:1000120",
          "tgn:7029392"
        ],
        "placetype": [
          "aat:300008347"
        ],
        "id": 1080458,
        "name:xx": "Kasai"
      }
    },
    {
      "geometry": {
        "type": "Point",
        "coordinates": [
          139.2833,
          36.3833
        ]
      },
      "type": "Feature",
      "properties": {
        "hierarchy": [
          "tgn:1080459",
          "tgn:1000980",
          "tgn:1000004",
          "tgn:7000894",
          "tgn:1000120",
          "tgn:7029392"
        ],
        "placetype": [
          "aat:300008347"
        ],
        "id": 1080459,
        "name:xx": "Kasakake"
      }
    }
  ]
}
