{
  "geometry": {
    "type": "Point",
    "coordinates": [
      10.4333,
      47.3833
    ]
  },
  "type": "Feature",
  "properties": {
    "hierarchy": [
      "tgn:1104936",
      "tgn:7003029",
      "tgn:1000003",
      "tgn:1000062",
      "tgn:7029392"
    ],
    "placetype": [
      "aat:300008795"
    ],
    "id": 1104936,
    "name:xx": "Hochvoget"
  }
}
