{
  "type": "FeatureCollection",
  "features": [
    {
      "geometry": {
        "type": "Point",
        "coordinates": [
          -74.8,
          38.95
        ]
      },
      "type": "Feature",
      "properties": {
        "hierarchy": [
          "tgn:2734340",
          "tgn:1002232",
          "tgn:1000001",
          "tgn:7012149",
          "tgn:7007565",
          "tgn:7029392"
        ],
        "placetype": [
          "aat:300132348"
        ],
        "id": 2734340,
        "name:xx": "Turtle Gut Shoals"
      }
    },
    {
      "geometry": {
        "type": "Point",
        "coordinates": [
          -80.2333,
          25.25
        ]
      },
      "type": "Feature",
      "properties": {
        "hierarchy": [
          "tgn:2734341",
          "tgn:1000001",
          "tgn:7012149",
          "tgn:1002676",
          "tgn:7007240",
          "tgn:7029392"
        ],
        "placetype": [
          "aat:300008678"
        ],
        "id": 2734341,
        "name:xx": "Turtle Harbor"
      }
    },
    {
      "geometry": {
        "type": "Point",
        "coordinates": [
          -85,
          29.7333
        ]
      },
      "type": "Feature",
      "properties": {
        "hierarchy": [
          "tgn:2734342",
          "tgn:1000001",
          "tgn:2000267",
          "tgn:7012149",
          "tgn:7007240",
          "tgn:7029392"
        ],
        "placetype": [
          "aat:300008680"
        ],
        "id": 2734342,
        "name:xx": "Turtle Harbor"
      }
    },
    {
      "geometry": {
        "type": "Point",
        "coordinates": [
          -68.8667,
          44.3833
        ]
      },
      "type": "Feature",
      "properties": {
        "hierarchy": [
          "tgn:2734343",
          "tgn:1000001",
          "tgn:7012149",
          "tgn:2000931",
          "tgn:7007515",
          "tgn:7029392"
        ],
        "placetype": [
          "aat:300008850"
        ],
        "id": 2734343,
        "name:xx": "Turtle Head"
      }
    },
    {
      "geometry": {
        "type": "Point",
        "coordinates": [
          -68.8833,
          44.3667
        ]
      },
      "type": "Feature",
      "properties": {
        "hierarchy": [
          "tgn:2734344",
          "tgn:1000001",
          "tgn:7012149",
          "tgn:2000931",
          "tgn:7007515",
          "tgn:7029392"
        ],
        "placetype": [
          "aat:300132316"
        ],
        "id": 2734344,
        "name:xx": "Turtle Head Cove"
      }
    },
    {
      "geometry": {
        "type": "Point",
        "coordinates": [
          -87.8,
          41.6333
        ]
      },
      "type": "Feature",
      "properties": {
        "hierarchy": [
          "tgn:2734345",
          "tgn:1000001",
          "tgn:7013649",
          "tgn:7012149",
          "tgn:7007251",
          "tgn:7029392"
        ],
        "placetype": [
          "aat:300008680"
        ],
        "id": 2734345,
        "name:xx": "Turtle Head Lake"
      }
    },
    {
      "geometry": {
        "type": "Point",
        "coordinates": [
          -150.8,
          63.3833
        ]
      },
      "type": "Feature",
      "properties": {
        "hierarchy": [
          "tgn:2734346",
          "tgn:7006450",
          "tgn:1000001",
          "tgn:7030547",
          "tgn:7012149",
          "tgn:7029392"
        ],
        "placetype": [
          "aat:300008798"
        ],
        "id": 2734346,
        "name:xx": "Turtle Hill"
      }
    },
    {
      "geometry": {
        "type": "Point",
        "coordinates": [
          -110.2,
          41.3
        ]
      },
      "type": "Feature",
      "properties": {
        "hierarchy": [
          "tgn:2734347",
          "tgn:1000001",
          "tgn:7012149",
          "tgn:2002385",
          "tgn:7007923",
          "tgn:7029392"
        ],
        "placetype": [
          "aat:300008798"
        ],
        "id": 2734347,
        "name:xx": "Turtle Hill"
      }
    },
    {
      "geometry": {
        "type": "Point",
        "coordinates": [
          -117.7833,
          47.4
        ]
      },
      "type": "Feature",
      "properties": {
        "hierarchy": [
          "tgn:2734348",
          "tgn:1000001",
          "tgn:7012149",
          "tgn:2002249",
          "tgn:7007920",
          "tgn:7029392"
        ],
        "placetype": [
          "aat:300008905"
        ],
        "id": 2734348,
        "name:xx": "Turtle Hole"
      }
    },
    {
      "geometry": {
        "type": "Point",
        "coordinates": [
          -98.5167,
          33.2167
        ]
      },
      "type": "Feature",
      "properties": {
        "hierarchy": [
          "tgn:2734349",
          "tgn:1000001",
          "tgn:7012149",
          "tgn:2002098",
          "tgn:7007826",
          "tgn:7029392"
        ],
        "placetype": [
          "aat:300008706"
        ],
        "id": 2734349,
        "name:xx": "Turtle Hole Creek"
      }
    }
  ]
}
