{
  "geometry": {
    "type": "Point",
    "coordinates": [
      -111.5167,
      38.6333
    ]
  },
  "type": "Feature",
  "properties": {
    "hierarchy": [
      "tgn:2680921",
      "tgn:1000001",
      "tgn:7012149",
      "tgn:2002121",
      "tgn:7007827",
      "tgn:7029392"
    ],
    "placetype": [
      "aat:300008706"
    ],
    "id": 2680921,
    "name:xx": "South Last Chance Creek"
  }
}
