{
  "geometry": {
    "type": "Point",
    "coordinates": [
      38.6833,
      7.8833
    ]
  },
  "type": "Feature",
  "properties": {
    "hierarchy": [
      "tgn:1089680",
      "tgn:7001242",
      "tgn:1001535",
      "tgn:7000489",
      "tgn:7029392"
    ],
    "placetype": [
      "aat:300008347"
    ],
    "id": 1089680,
    "name:xx": "Ādamī Tulu"
  }
}
