{
  "geometry": {
    "type": "Point",
    "coordinates": [
      -74.0667,
      47.0333
    ]
  },
  "type": "Feature",
  "properties": {
    "hierarchy": [
      "tgn:1015465",
      "tgn:7005685",
      "tgn:1000001",
      "tgn:7005804",
      "tgn:7029392"
    ],
    "placetype": [
      "aat:300008347"
    ],
    "id": 1015465,
    "name:xx": "Lac-Masson"
  }
}
