{
  "geometry": {
    "type": "Point",
    "coordinates": [
      -67.2167,
      -10.3333
    ]
  },
  "type": "Feature",
  "properties": {
    "hierarchy": [
      "tgn:1022514",
      "tgn:1001822",
      "tgn:1000047",
      "tgn:7002456",
      "tgn:1000002",
      "tgn:7029392"
    ],
    "placetype": [
      "aat:300008347"
    ],
    "id": 1022514,
    "name:xx": "Plácido de Castro"
  }
}
