{
  "type": "FeatureCollection",
  "features": [
    {
      "geometry": {
        "type": "Point",
        "coordinates": [
          -83.749,
          12.086
        ]
      },
      "type": "Feature",
      "properties": {
        "hierarchy": [
          "tgn:1123810",
          "tgn:7593359",
          "tgn:1000001",
          "tgn:7005562",
          "tgn:7029392"
        ],
        "placetype": [
          "aat:300008707"
        ],
        "id": 1123810,
        "name:xx": "Escondido, Río"
      }
    },
    {
      "geometry": {
        "type": "Point",
        "coordinates": [
          4.7,
          44.4833
        ]
      },
      "type": "Feature",
      "properties": {
        "hierarchy": [
          "tgn:1123811",
          "tgn:1000003",
          "tgn:1000070",
          "tgn:7002897",
          "tgn:7029392"
        ],
        "placetype": [
          "aat:300008707"
        ],
        "id": 1123811,
        "name:xx": "Escoutay"
      }
    },
    {
      "geometry": {
        "type": "Point",
        "coordinates": [
          13.366667,
          43.65
        ]
      },
      "type": "Feature",
      "properties": {
        "hierarchy": [
          "tgn:1123814",
          "tgn:1003429",
          "tgn:1000003",
          "tgn:7003240",
          "tgn:1000080",
          "tgn:7029392"
        ],
        "placetype": [
          "aat:300008707",
          "aat:300008699"
        ],
        "id": 1123814,
        "name:xx": "Esino"
      }
    },
    {
      "geometry": {
        "type": "Point",
        "coordinates": [
          -3.05,
          55.95
        ]
      },
      "type": "Feature",
      "properties": {
        "hierarchy": [
          "tgn:1123815",
          "tgn:7002445",
          "tgn:1000003",
          "tgn:7008166",
          "tgn:7008591",
          "tgn:7029392"
        ],
        "placetype": [
          "aat:300008707",
          "aat:300008699"
        ],
        "name:en": "Esk",
        "id": 1123815
      }
    },
    {
      "geometry": {
        "type": "Point",
        "coordinates": [
          -3.066667,
          54.966667
        ]
      },
      "type": "Feature",
      "properties": {
        "hierarchy": [
          "tgn:1123816",
          "tgn:7002444",
          "tgn:1000003",
          "tgn:7008591",
          "tgn:7029392"
        ],
        "placetype": [
          "aat:300008707",
          "aat:300008699"
        ],
        "name:en": "Esk",
        "id": 1123816
      }
    },
    {
      "geometry": {
        "type": "Point",
        "coordinates": [
          -0.6,
          54.5
        ]
      },
      "type": "Feature",
      "properties": {
        "hierarchy": [
          "tgn:1123817",
          "tgn:7008653",
          "tgn:1000003",
          "tgn:7008591",
          "tgn:7029392"
        ],
        "placetype": [
          "aat:300008707",
          "aat:300008699"
        ],
        "name:en": "Esk",
        "id": 1123817
      }
    },
    {
      "geometry": {
        "type": "Point",
        "coordinates": [
          171.95,
          -43.1
        ]
      },
      "type": "Feature",
      "properties": {
        "hierarchy": [
          "tgn:1123818",
          "tgn:1009227",
          "tgn:7001866",
          "tgn:1000226",
          "tgn:1000006",
          "tgn:7029392"
        ],
        "placetype": [
          "aat:300008707",
          "aat:300008699"
        ],
        "id": 1123818,
        "name:xx": "Esk"
      }
    }
  ]
}
