{
  "geometry": {
    "type": "Point",
    "coordinates": [
      -80.1333,
      37.8833
    ]
  },
  "type": "Feature",
  "properties": {
    "hierarchy": [
      "tgn:2426589",
      "tgn:2002138",
      "tgn:1000001",
      "tgn:7012149",
      "tgn:7007919",
      "tgn:7029392"
    ],
    "placetype": [
      "aat:300008761"
    ],
    "id": 2426589,
    "name:xx": "Jones Hollow"
  }
}
