{
  "type": "FeatureCollection",
  "features": [
    {
      "geometry": {
        "type": "Point",
        "coordinates": [
          -99.1,
          24.516667
        ]
      },
      "type": "Feature",
      "properties": {
        "hierarchy": [
          "tgn:7373580",
          "tgn:1000001",
          "tgn:7005597",
          "tgn:7005560",
          "tgn:7029392"
        ],
        "placetype": [
          "aat:300008347"
        ],
        "id": 7373580,
        "name:xx": "La Gloria"
      }
    },
    {
      "geometry": {
        "type": "Point",
        "coordinates": [
          -99.466667,
          23.316667
        ]
      },
      "type": "Feature",
      "properties": {
        "hierarchy": [
          "tgn:7373581",
          "tgn:1000001",
          "tgn:7005597",
          "tgn:7005560",
          "tgn:7029392"
        ],
        "placetype": [
          "aat:300008347"
        ],
        "id": 7373581,
        "name:xx": "La Gloria"
      }
    },
    {
      "geometry": {
        "type": "Point",
        "coordinates": [
          -102.983333,
          22.066667
        ]
      },
      "type": "Feature",
      "properties": {
        "hierarchy": [
          "tgn:7373582",
          "tgn:1000001",
          "tgn:7005601",
          "tgn:7005560",
          "tgn:7029392"
        ],
        "placetype": [
          "aat:300008347"
        ],
        "id": 7373582,
        "name:xx": "La Gloria"
      }
    },
    {
      "geometry": {
        "type": "Point",
        "coordinates": [
          -105.133333,
          21.683333
        ]
      },
      "type": "Feature",
      "properties": {
        "hierarchy": [
          "tgn:7373583",
          "tgn:1000001",
          "tgn:1001906",
          "tgn:7005560",
          "tgn:7029392"
        ],
        "placetype": [
          "aat:300008347"
        ],
        "id": 7373583,
        "name:xx": "La Gloria"
      }
    },
    {
      "geometry": {
        "type": "Point",
        "coordinates": [
          -101.5,
          20.433333
        ]
      },
      "type": "Feature",
      "properties": {
        "hierarchy": [
          "tgn:7373584",
          "tgn:7005584",
          "tgn:1000001",
          "tgn:7005560",
          "tgn:7029392"
        ],
        "placetype": [
          "aat:300008347"
        ],
        "id": 7373584,
        "name:xx": "La Gloria"
      }
    },
    {
      "geometry": {
        "type": "Point",
        "coordinates": [
          -96.733333,
          20.15
        ]
      },
      "type": "Feature",
      "properties": {
        "hierarchy": [
          "tgn:7373585",
          "tgn:1000001",
          "tgn:7005599",
          "tgn:7005560",
          "tgn:7029392"
        ],
        "placetype": [
          "aat:300008347"
        ],
        "id": 7373585,
        "name:xx": "La Gloria"
      }
    },
    {
      "geometry": {
        "type": "Point",
        "coordinates": [
          -105.366667,
          19.933333
        ]
      },
      "type": "Feature",
      "properties": {
        "hierarchy": [
          "tgn:7373586",
          "tgn:7005586",
          "tgn:1000001",
          "tgn:7005560",
          "tgn:7029392"
        ],
        "placetype": [
          "aat:300008347"
        ],
        "id": 7373586,
        "name:xx": "La Gloria"
      }
    },
    {
      "geometry": {
        "type": "Point",
        "coordinates": [
          -104.383333,
          19.8
        ]
      },
      "type": "Feature",
      "properties": {
        "hierarchy": [
          "tgn:7373587",
          "tgn:7005586",
          "tgn:1000001",
          "tgn:7005560",
          "tgn:7029392"
        ],
        "placetype": [
          "aat:300008347"
        ],
        "id": 7373587,
        "name:xx": "La Gloria"
      }
    },
    {
      "geometry": {
        "type": "Point",
        "coordinates": [
          -96.4,
          19.416667
        ]
      },
      "type": "Feature",
      "properties": {
        "hierarchy": [
          "tgn:7373588",
          "tgn:1000001",
          "tgn:7005599",
          "tgn:7005560",
          "tgn:7029392"
        ],
        "placetype": [
          "aat:300008347"
        ],
        "id": 7373588,
        "name:xx": "La Gloria"
      }
    },
    {
      "geometry": {
        "type": "Point",
        "coordinates": [
          -102.183333,
          20.833333
        ]
      },
      "type": "Feature",
      "properties": {
        "hierarchy": [
          "tgn:7373589",
          "tgn:7005586",
          "tgn:1000001",
          "tgn:7005560",
          "tgn:7029392"
        ],
        "placetype": [
          "aat:300000241"
        ],
        "id": 7373589,
        "name:xx": "La Aurora"
      }
    }
  ]
}
