{
  "geometry": {
    "type": "Point",
    "coordinates": [
      74.25,
      17.833333
    ]
  },
  "type": "Feature",
  "properties": {
    "hierarchy": [
      "tgn:1110074",
      "tgn:1000004",
      "tgn:7000198",
      "tgn:1001895",
      "tgn:7029392"
    ],
    "placetype": [
      "aat:300386831",
      "aat:300008795"
    ],
    "id": 1110074,
    "name:xx": "Mahādeo Range"
  }
}
