{
  "geometry": {
    "type": "Point",
    "coordinates": [
      -109.7167,
      45.0833
    ]
  },
  "type": "Feature",
  "properties": {
    "hierarchy": [
      "tgn:2703520",
      "tgn:1000001",
      "tgn:2001264",
      "tgn:7012149",
      "tgn:7007524",
      "tgn:7029392"
    ],
    "placetype": [
      "aat:300008798"
    ],
    "id": 2703520,
    "name:xx": "Summit Mountain"
  }
}
