{
  "geometry": {
    "type": "Point",
    "coordinates": [
      -90.3333,
      36.8833
    ]
  },
  "type": "Feature",
  "properties": {
    "hierarchy": [
      "tgn:2369251",
      "tgn:1000001",
      "tgn:2001176",
      "tgn:7012149",
      "tgn:7007523",
      "tgn:7029392"
    ],
    "placetype": [
      "aat:300008761"
    ],
    "id": 2369251,
    "name:xx": "Gum Spring Hollow"
  }
}
