{
  "geometry": {
    "type": "Point",
    "coordinates": [
      -81.1333,
      35.2333
    ]
  },
  "type": "Feature",
  "properties": {
    "hierarchy": [
      "tgn:2660177",
      "tgn:1000001",
      "tgn:7012149",
      "tgn:2001496",
      "tgn:7007709",
      "tgn:7029392"
    ],
    "placetype": [
      "aat:300008699"
    ],
    "id": 2660177,
    "name:xx": "Shoal Branch"
  }
}
