{
  "geometry": {
    "type": "Point",
    "coordinates": [
      -73.65,
      42.9167
    ]
  },
  "type": "Feature",
  "properties": {
    "hierarchy": [
      "tgn:2398387",
      "tgn:1000001",
      "tgn:7012149",
      "tgn:7029392"
    ],
    "placetype": [
      "aat:300008707"
    ],
    "id": 2398387,
    "name:xx": "Hoosic River"
  }
}
