{
  "geometry": {
    "type": "Point",
    "coordinates": [
      75.3948,
      28.8381
    ]
  },
  "type": "Feature",
  "properties": {
    "hierarchy": [
      "tgn:7584157",
      "tgn:1000004",
      "tgn:7000198",
      "tgn:7016788",
      "tgn:7029392"
    ],
    "placetype": [
      "aat:300008688"
    ],
    "name:en": "Dūrjāna Johra",
    "id": 7584157
  }
}
