{
  "geometry": {
    "type": "Point",
    "coordinates": [
      -87.6833,
      40.1333
    ]
  },
  "type": "Feature",
  "properties": {
    "hierarchy": [
      "tgn:2377147",
      "tgn:1000001",
      "tgn:7012149",
      "tgn:1002974",
      "tgn:7007251",
      "tgn:7029392"
    ],
    "placetype": [
      "aat:300000390"
    ],
    "id": 2377147,
    "name:xx": "Harmattan Strip Mine"
  }
}
