{
  "geometry": {
    "type": "Point",
    "coordinates": [
      -98.7833,
      30.0833
    ]
  },
  "type": "Feature",
  "properties": {
    "hierarchy": [
      "tgn:2605194",
      "tgn:1000001",
      "tgn:7012149",
      "tgn:2002015",
      "tgn:7007826",
      "tgn:7029392"
    ],
    "placetype": [
      "aat:300008761"
    ],
    "id": 2605194,
    "name:xx": "Rafter Hollow"
  }
}
