{
  "geometry": {
    "type": "Point",
    "coordinates": [
      114.1167,
      28.9333
    ]
  },
  "type": "Feature",
  "properties": {
    "hierarchy": [
      "tgn:1074177",
      "tgn:1000004",
      "tgn:7002082",
      "tgn:1000111",
      "tgn:7029392"
    ],
    "placetype": [
      "aat:300008347"
    ],
    "id": 1074177,
    "name:xx": "Zhuxichang"
  }
}
