{
  "geometry": {
    "type": "Point",
    "coordinates": [
      -92.5667,
      38.5167
    ]
  },
  "type": "Feature",
  "properties": {
    "hierarchy": [
      "tgn:2284360",
      "tgn:1000001",
      "tgn:7012149",
      "tgn:2001220",
      "tgn:7007523",
      "tgn:7029392"
    ],
    "placetype": [
      "aat:300006191"
    ],
    "id": 2284360,
    "name:xx": "Derbey Lake"
  }
}
