{
  "geometry": {
    "type": "Point",
    "coordinates": [
      -110.8333,
      37.4667
    ]
  },
  "type": "Feature",
  "properties": {
    "hierarchy": [
      "tgn:2536215",
      "tgn:1000001",
      "tgn:7012149",
      "tgn:2002113",
      "tgn:7007827",
      "tgn:7029392"
    ],
    "placetype": [
      "aat:300008706"
    ],
    "id": 2536215,
    "name:xx": "Navajo Creek"
  }
}
