{
  "geometry": {
    "type": "Point",
    "coordinates": [
      -78.3833,
      41.0667
    ]
  },
  "type": "Feature",
  "properties": {
    "hierarchy": [
      "tgn:2331672",
      "tgn:1000001",
      "tgn:1002278",
      "tgn:7012149",
      "tgn:7007710",
      "tgn:7029392"
    ],
    "placetype": [
      "aat:300008699"
    ],
    "id": 2331672,
    "name:xx": "Flegals Run"
  }
}
