{
  "geometry": {
    "type": "Point",
    "coordinates": [
      -82.4167,
      35.25
    ]
  },
  "type": "Feature",
  "properties": {
    "hierarchy": [
      "tgn:2151141",
      "tgn:1000001",
      "tgn:7012149",
      "tgn:2001504",
      "tgn:7007709",
      "tgn:7029392"
    ],
    "placetype": [
      "aat:300008699"
    ],
    "id": 2151141,
    "name:xx": "Bat Fork"
  }
}
