{
  "geometry": {
    "type": "Point",
    "coordinates": [
      -84.5167,
      36.3667
    ]
  },
  "type": "Feature",
  "properties": {
    "hierarchy": [
      "tgn:2366383",
      "tgn:1000001",
      "tgn:7012149",
      "tgn:2001912",
      "tgn:7007825",
      "tgn:7029392"
    ],
    "placetype": [
      "aat:300008761"
    ],
    "id": 2366383,
    "name:xx": "Griffith Hollow"
  }
}
