{
  "geometry": {
    "type": "Point",
    "coordinates": [
      -116.4333,
      45.55
    ]
  },
  "type": "Feature",
  "properties": {
    "hierarchy": [
      "tgn:2181753",
      "tgn:1000001",
      "tgn:7012149",
      "tgn:2000476",
      "tgn:7007250",
      "tgn:7029392"
    ],
    "placetype": [
      "aat:300000390"
    ],
    "id": 2181753,
    "name:xx": "Blue Jacket Mine"
  }
}
