{
  "geometry": {
    "type": "Point",
    "coordinates": [
      -79.2667,
      39.4167
    ]
  },
  "type": "Feature",
  "properties": {
    "hierarchy": [
      "tgn:2678524",
      "tgn:1000001",
      "tgn:2000935",
      "tgn:7012149",
      "tgn:7007516",
      "tgn:7029392"
    ],
    "placetype": [
      "aat:300008706"
    ],
    "id": 2678524,
    "name:xx": "South Fork Crabtree Creek"
  }
}
