{
  "geometry": {
    "type": "Point",
    "coordinates": [
      -67.1667,
      18.3167
    ]
  },
  "type": "Feature",
  "properties": {
    "hierarchy": [
      "tgn:1109573",
      "tgn:7017438",
      "tgn:1000001",
      "tgn:7004643",
      "tgn:7029392"
    ],
    "placetype": [
      "aat:300386831"
    ],
    "id": 1109573,
    "name:xx": "San Francisco, La Cadena"
  }
}
