{
  "geometry": {
    "type": "Point",
    "coordinates": [
      -108.55,
      37.25
    ]
  },
  "type": "Feature",
  "properties": {
    "hierarchy": [
      "tgn:2723613",
      "tgn:1000001",
      "tgn:7012149",
      "tgn:2000233",
      "tgn:7007158",
      "tgn:7029392"
    ],
    "placetype": [
      "aat:300000390"
    ],
    "id": 2723613,
    "name:xx": "Todd Mine"
  }
}
