{
  "geometry": {
    "type": "Point",
    "coordinates": [
      24.2833,
      62.5333
    ]
  },
  "type": "Feature",
  "properties": {
    "hierarchy": [
      "tgn:1031466",
      "tgn:7024077",
      "tgn:1000003",
      "tgn:1000069",
      "tgn:7029392"
    ],
    "placetype": [
      "aat:300008347"
    ],
    "id": 1031466,
    "name:xx": "Myllymäki"
  }
}
