{
  "type": "FeatureCollection",
  "features": [
    {
      "geometry": {
        "type": "Point",
        "coordinates": [
          -93.75,
          32.8
        ]
      },
      "type": "Feature",
      "properties": {
        "hierarchy": [
          "tgn:2199950",
          "tgn:1000001",
          "tgn:2000861",
          "tgn:7012149",
          "tgn:7007256",
          "tgn:7029392"
        ],
        "placetype": [
          "aat:300008699"
        ],
        "id": 2199950,
        "name:xx": "Brushy Branch"
      }
    },
    {
      "geometry": {
        "type": "Point",
        "coordinates": [
          -88.8,
          31.65
        ]
      },
      "type": "Feature",
      "properties": {
        "hierarchy": [
          "tgn:2199951",
          "tgn:1000001",
          "tgn:7012149",
          "tgn:2001162",
          "tgn:7007522",
          "tgn:7029392"
        ],
        "placetype": [
          "aat:300008699"
        ],
        "id": 2199951,
        "name:xx": "Brushy Branch"
      }
    },
    {
      "geometry": {
        "type": "Point",
        "coordinates": [
          -89.15,
          31.7667
        ]
      },
      "type": "Feature",
      "properties": {
        "hierarchy": [
          "tgn:2199952",
          "tgn:1000001",
          "tgn:7012149",
          "tgn:2001119",
          "tgn:7007522",
          "tgn:7029392"
        ],
        "placetype": [
          "aat:300008699"
        ],
        "id": 2199952,
        "name:xx": "Brushy Branch"
      }
    },
    {
      "geometry": {
        "type": "Point",
        "coordinates": [
          -91.65,
          39.05
        ]
      },
      "type": "Feature",
      "properties": {
        "hierarchy": [
          "tgn:2199953",
          "tgn:1000001",
          "tgn:7012149",
          "tgn:7007523",
          "tgn:7029392"
        ],
        "placetype": [
          "aat:300008699"
        ],
        "id": 2199953,
        "name:xx": "Brushy Branch"
      }
    },
    {
      "geometry": {
        "type": "Point",
        "coordinates": [
          -91.95,
          39.1833
        ]
      },
      "type": "Feature",
      "properties": {
        "hierarchy": [
          "tgn:2199954",
          "tgn:1002158",
          "tgn:1000001",
          "tgn:7012149",
          "tgn:7007523",
          "tgn:7029392"
        ],
        "placetype": [
          "aat:300008699"
        ],
        "id": 2199954,
        "name:xx": "Brushy Branch"
      }
    },
    {
      "geometry": {
        "type": "Point",
        "coordinates": [
          -93.0667,
          39.9167
        ]
      },
      "type": "Feature",
      "properties": {
        "hierarchy": [
          "tgn:2199955",
          "tgn:1000001",
          "tgn:7012149",
          "tgn:2001214",
          "tgn:7007523",
          "tgn:7029392"
        ],
        "placetype": [
          "aat:300008699"
        ],
        "id": 2199955,
        "name:xx": "Brushy Branch"
      }
    },
    {
      "geometry": {
        "type": "Point",
        "coordinates": [
          -92.9667,
          38.5833
        ]
      },
      "type": "Feature",
      "properties": {
        "hierarchy": [
          "tgn:2199956",
          "tgn:1000001",
          "tgn:7012149",
          "tgn:2001221",
          "tgn:7007523",
          "tgn:7029392"
        ],
        "placetype": [
          "aat:300008699"
        ],
        "id": 2199956,
        "name:xx": "Brushy Branch"
      }
    },
    {
      "geometry": {
        "type": "Point",
        "coordinates": [
          -93.2833,
          40.1
        ]
      },
      "type": "Feature",
      "properties": {
        "hierarchy": [
          "tgn:2199957",
          "tgn:1000001",
          "tgn:7012149",
          "tgn:2001250",
          "tgn:7007523",
          "tgn:7029392"
        ],
        "placetype": [
          "aat:300008699"
        ],
        "id": 2199957,
        "name:xx": "Brushy Branch"
      }
    },
    {
      "geometry": {
        "type": "Point",
        "coordinates": [
          -91.4833,
          38.4167
        ]
      },
      "type": "Feature",
      "properties": {
        "hierarchy": [
          "tgn:2199958",
          "tgn:1000001",
          "tgn:7012149",
          "tgn:1002402",
          "tgn:7007523",
          "tgn:7029392"
        ],
        "placetype": [
          "aat:300008699"
        ],
        "id": 2199958,
        "name:xx": "Brushy Branch"
      }
    }
  ]
}
