{
  "type": "FeatureCollection",
  "features": [
    {
      "geometry": {
        "type": "Point",
        "coordinates": [
          -151.6833,
          66.55
        ]
      },
      "type": "Feature",
      "properties": {
        "hierarchy": [
          "tgn:2517380",
          "tgn:7006450",
          "tgn:1000001",
          "tgn:7012149",
          "tgn:2000089",
          "tgn:7029392"
        ],
        "placetype": [
          "aat:300008680"
        ],
        "id": 2517380,
        "name:xx": "Minnkokut Lake"
      }
    },
    {
      "geometry": {
        "type": "Point",
        "coordinates": [
          -83.6333,
          42.8167
        ]
      },
      "type": "Feature",
      "properties": {
        "hierarchy": [
          "tgn:2517381",
          "tgn:1000001",
          "tgn:7012149",
          "tgn:1002737",
          "tgn:7007520",
          "tgn:7029392"
        ],
        "placetype": [
          "aat:300008680"
        ],
        "id": 2517381,
        "name:xx": "Minnock Lake"
      }
    },
    {
      "geometry": {
        "type": "Point",
        "coordinates": [
          -86.4667,
          41.5
        ]
      },
      "type": "Feature",
      "properties": {
        "hierarchy": [
          "tgn:2517382",
          "tgn:1000001",
          "tgn:7012149",
          "tgn:7014366",
          "tgn:7007252",
          "tgn:7029392"
        ],
        "placetype": [
          "aat:300008699"
        ],
        "id": 2517382,
        "name:xx": "Minnow Branch"
      }
    },
    {
      "geometry": {
        "type": "Point",
        "coordinates": [
          -88.4833,
          36.65
        ]
      },
      "type": "Feature",
      "properties": {
        "hierarchy": [
          "tgn:2517383",
          "tgn:1000001",
          "tgn:7012149",
          "tgn:7007255",
          "tgn:7029392"
        ],
        "placetype": [
          "aat:300008699"
        ],
        "id": 2517383,
        "name:xx": "Minnow Branch"
      }
    },
    {
      "geometry": {
        "type": "Point",
        "coordinates": [
          -88.75,
          33.2667
        ]
      },
      "type": "Feature",
      "properties": {
        "hierarchy": [
          "tgn:2517384",
          "tgn:1000001",
          "tgn:7012149",
          "tgn:2001137",
          "tgn:7007522",
          "tgn:7029392"
        ],
        "placetype": [
          "aat:300008699"
        ],
        "id": 2517384,
        "name:xx": "Minnow Branch"
      }
    },
    {
      "geometry": {
        "type": "Point",
        "coordinates": [
          -93,
          38.3167
        ]
      },
      "type": "Feature",
      "properties": {
        "hierarchy": [
          "tgn:2517385",
          "tgn:1000001",
          "tgn:7012149",
          "tgn:7007523",
          "tgn:7029392"
        ],
        "placetype": [
          "aat:300008699"
        ],
        "id": 2517385,
        "name:xx": "Minnow Branch"
      }
    },
    {
      "geometry": {
        "type": "Point",
        "coordinates": [
          -91.4333,
          39.7167
        ]
      },
      "type": "Feature",
      "properties": {
        "hierarchy": [
          "tgn:2517386",
          "tgn:1000001",
          "tgn:7012149",
          "tgn:1002634",
          "tgn:7007523",
          "tgn:7029392"
        ],
        "placetype": [
          "aat:300008699"
        ],
        "id": 2517386,
        "name:xx": "Minnow Branch"
      }
    },
    {
      "geometry": {
        "type": "Point",
        "coordinates": [
          -87.0667,
          35.35
        ]
      },
      "type": "Feature",
      "properties": {
        "hierarchy": [
          "tgn:2517387",
          "tgn:1000001",
          "tgn:7012149",
          "tgn:2001864",
          "tgn:7007825",
          "tgn:7029392"
        ],
        "placetype": [
          "aat:300008699"
        ],
        "id": 2517387,
        "name:xx": "Minnow Branch"
      }
    },
    {
      "geometry": {
        "type": "Point",
        "coordinates": [
          -87.65,
          35.4167
        ]
      },
      "type": "Feature",
      "properties": {
        "hierarchy": [
          "tgn:2517388",
          "tgn:1000001",
          "tgn:7012149",
          "tgn:2001927",
          "tgn:7007825",
          "tgn:7029392"
        ],
        "placetype": [
          "aat:300008699"
        ],
        "id": 2517388,
        "name:xx": "Minnow Branch"
      }
    },
    {
      "geometry": {
        "type": "Point",
        "coordinates": [
          -87.4333,
          35.75
        ]
      },
      "type": "Feature",
      "properties": {
        "hierarchy": [
          "tgn:2517389",
          "tgn:1000001",
          "tgn:7012149",
          "tgn:7015666",
          "tgn:7007825",
          "tgn:7029392"
        ],
        "placetype": [
          "aat:300008699"
        ],
        "id": 2517389,
        "name:xx": "Minnow Branch"
      }
    }
  ]
}
