{
  "geometry": {
    "type": "Point",
    "coordinates": [
      -160.6667,
      55.6333
    ]
  },
  "type": "Feature",
  "properties": {
    "hierarchy": [
      "tgn:2602402",
      "tgn:7030515",
      "tgn:7006450",
      "tgn:1000001",
      "tgn:7012149",
      "tgn:7029392"
    ],
    "placetype": [
      "aat:300008798"
    ],
    "id": 2602402,
    "name:xx": "Pyramid Mountain"
  }
}
