{
  "geometry": {
    "type": "Point",
    "coordinates": [
      15.93,
      50.339
    ]
  },
  "type": "Feature",
  "properties": {
    "hierarchy": [
      "tgn:4005457",
      "tgn:7593914",
      "tgn:1000003",
      "tgn:1001780",
      "tgn:7029392"
    ],
    "placetype": [
      "aat:300008347"
    ],
    "id": 4005457,
    "name:xx": "Josefov"
  }
}
