{
  "type": "FeatureCollection",
  "features": [
    {
      "geometry": {
        "type": "Point",
        "coordinates": [
          -71.6,
          41.95
        ]
      },
      "type": "Feature",
      "properties": {
        "hierarchy": [
          "tgn:2095120",
          "tgn:1002808",
          "tgn:1000001",
          "tgn:7012149",
          "tgn:7007711",
          "tgn:7029392"
        ],
        "placetype": [
          "aat:300008347"
        ],
        "id": 2095120,
        "name:xx": "Tarkiln"
      }
    },
    {
      "geometry": {
        "type": "Point",
        "coordinates": [
          -71.2,
          41.6167
        ]
      },
      "type": "Feature",
      "properties": {
        "hierarchy": [
          "tgn:2095122",
          "tgn:1002716",
          "tgn:1000001",
          "tgn:7012149",
          "tgn:7007711",
          "tgn:7029392"
        ],
        "placetype": [
          "aat:300008347"
        ],
        "id": 2095122,
        "name:xx": "Tiverton"
      }
    },
    {
      "geometry": {
        "type": "Point",
        "coordinates": [
          -71.1833,
          41.5667
        ]
      },
      "type": "Feature",
      "properties": {
        "hierarchy": [
          "tgn:2095125",
          "tgn:1002716",
          "tgn:1000001",
          "tgn:7012149",
          "tgn:7007711",
          "tgn:7029392"
        ],
        "placetype": [
          "aat:300008798"
        ],
        "id": 2095125,
        "name:xx": "Tiverton Four Corners"
      }
    },
    {
      "geometry": {
        "type": "Point",
        "coordinates": [
          -71.5333,
          41.4167
        ]
      },
      "type": "Feature",
      "properties": {
        "hierarchy": [
          "tgn:2095126",
          "tgn:1002996",
          "tgn:1000001",
          "tgn:7012149",
          "tgn:7007711",
          "tgn:7029392"
        ],
        "placetype": [
          "aat:300008347",
          "aat:300387210"
        ],
        "id": 2095126,
        "name:xx": "Tuckertown"
      }
    },
    {
      "geometry": {
        "type": "Point",
        "coordinates": [
          -71.5333,
          41.9833
        ]
      },
      "type": "Feature",
      "properties": {
        "hierarchy": [
          "tgn:2095128",
          "tgn:1002808",
          "tgn:1000001",
          "tgn:7012149",
          "tgn:7007711",
          "tgn:7029392"
        ],
        "placetype": [
          "aat:300008347"
        ],
        "id": 2095128,
        "name:xx": "Union Village"
      }
    },
    {
      "geometry": {
        "type": "Point",
        "coordinates": [
          -71.6,
          41.5
        ]
      },
      "type": "Feature",
      "properties": {
        "hierarchy": [
          "tgn:2095129",
          "tgn:1002996",
          "tgn:1000001",
          "tgn:7012149",
          "tgn:7007711",
          "tgn:7029392"
        ],
        "placetype": [
          "aat:300008347"
        ],
        "id": 2095129,
        "name:xx": "Usquepaug"
      }
    }
  ]
}
