{
  "geometry": {
    "type": "Point",
    "coordinates": [
      -74.4833,
      41.7667
    ]
  },
  "type": "Feature",
  "properties": {
    "hierarchy": [
      "tgn:2738155",
      "tgn:1000001",
      "tgn:7012149",
      "tgn:1002961",
      "tgn:7007568",
      "tgn:7029392"
    ],
    "placetype": [
      "aat:300008680"
    ],
    "id": 2738155,
    "name:xx": "Ulster Heights Lake"
  }
}
