{
  "type": "FeatureCollection",
  "features": [
    {
      "geometry": {
        "type": "Point",
        "coordinates": [
          -113.4,
          46.0333
        ]
      },
      "type": "Feature",
      "properties": {
        "hierarchy": [
          "tgn:2503870",
          "tgn:1000001",
          "tgn:7012149",
          "tgn:2001279",
          "tgn:7007524",
          "tgn:7029392"
        ],
        "placetype": [
          "aat:300008706"
        ],
        "id": 2503870,
        "name:xx": "Meadow Creek"
      }
    },
    {
      "geometry": {
        "type": "Point",
        "coordinates": [
          -109.4667,
          47.2667
        ]
      },
      "type": "Feature",
      "properties": {
        "hierarchy": [
          "tgn:2503871",
          "tgn:1000001",
          "tgn:7012149",
          "tgn:2001273",
          "tgn:7007524",
          "tgn:7029392"
        ],
        "placetype": [
          "aat:300008706"
        ],
        "id": 2503871,
        "name:xx": "Meadow Creek"
      }
    },
    {
      "geometry": {
        "type": "Point",
        "coordinates": [
          -115.1167,
          47.8667
        ]
      },
      "type": "Feature",
      "properties": {
        "hierarchy": [
          "tgn:2503872",
          "tgn:1000001",
          "tgn:7012149",
          "tgn:2001304",
          "tgn:7007524",
          "tgn:7029392"
        ],
        "placetype": [
          "aat:300008706"
        ],
        "id": 2503872,
        "name:xx": "Meadow Creek"
      }
    },
    {
      "geometry": {
        "type": "Point",
        "coordinates": [
          -115.3167,
          41.6
        ]
      },
      "type": "Feature",
      "properties": {
        "hierarchy": [
          "tgn:2503873",
          "tgn:1000001",
          "tgn:2001411",
          "tgn:7012149",
          "tgn:7007526",
          "tgn:7029392"
        ],
        "placetype": [
          "aat:300008706"
        ],
        "id": 2503873,
        "name:xx": "Meadow Creek"
      }
    },
    {
      "geometry": {
        "type": "Point",
        "coordinates": [
          -116.9,
          38.7333
        ]
      },
      "type": "Feature",
      "properties": {
        "hierarchy": [
          "tgn:2503874",
          "tgn:1000001",
          "tgn:2001418",
          "tgn:7012149",
          "tgn:7007526",
          "tgn:7029392"
        ],
        "placetype": [
          "aat:300008706"
        ],
        "id": 2503874,
        "name:xx": "Meadow Creek"
      }
    },
    {
      "geometry": {
        "type": "Point",
        "coordinates": [
          -114.6,
          39.5167
        ]
      },
      "type": "Feature",
      "properties": {
        "hierarchy": [
          "tgn:2503875",
          "tgn:1000001",
          "tgn:7012149",
          "tgn:2001420",
          "tgn:7007526",
          "tgn:7029392"
        ],
        "placetype": [
          "aat:300008706"
        ],
        "id": 2503875,
        "name:xx": "Meadow Creek"
      }
    },
    {
      "geometry": {
        "type": "Point",
        "coordinates": [
          -74.8667,
          38.9667
        ]
      },
      "type": "Feature",
      "properties": {
        "hierarchy": [
          "tgn:2503877",
          "tgn:1002232",
          "tgn:1000001",
          "tgn:7012149",
          "tgn:7007565",
          "tgn:7029392"
        ],
        "placetype": [
          "aat:300008706"
        ],
        "id": 2503877,
        "name:xx": "Meadow Creek"
      }
    },
    {
      "geometry": {
        "type": "Point",
        "coordinates": [
          -108.1167,
          32.9167
        ]
      },
      "type": "Feature",
      "properties": {
        "hierarchy": [
          "tgn:2503878",
          "tgn:1000001",
          "tgn:7012149",
          "tgn:2001437",
          "tgn:7007566",
          "tgn:7029392"
        ],
        "placetype": [
          "aat:300008706"
        ],
        "id": 2503878,
        "name:xx": "Meadow Creek"
      }
    },
    {
      "geometry": {
        "type": "Point",
        "coordinates": [
          -79.55,
          35.3667
        ]
      },
      "type": "Feature",
      "properties": {
        "hierarchy": [
          "tgn:2503879",
          "tgn:1000001",
          "tgn:7012149",
          "tgn:2001521",
          "tgn:7007709",
          "tgn:7029392"
        ],
        "placetype": [
          "aat:300008706"
        ],
        "id": 2503879,
        "name:xx": "Meadow Creek"
      }
    }
  ]
}
