{
  "geometry": {
    "type": "Point",
    "coordinates": [
      -89.3667,
      31.9333
    ]
  },
  "type": "Feature",
  "properties": {
    "hierarchy": [
      "tgn:2436093",
      "tgn:1000001",
      "tgn:7012149",
      "tgn:2001150",
      "tgn:7007522",
      "tgn:7029392"
    ],
    "placetype": [
      "aat:300008706"
    ],
    "id": 2436093,
    "name:xx": "Keys Mill Creek"
  }
}
