{
  "geometry": {
    "type": "Point",
    "coordinates": [
      -80.0667,
      42.15
    ]
  },
  "type": "Feature",
  "properties": {
    "hierarchy": [
      "tgn:2402030",
      "tgn:1000001",
      "tgn:7012149",
      "tgn:1002358",
      "tgn:7007710",
      "tgn:7029392"
    ],
    "placetype": [
      "aat:300008680"
    ],
    "id": 2402030,
    "name:xx": "Horseshoe Pond"
  }
}
