{
  "geometry": {
    "type": "Point",
    "coordinates": [
      -85.55,
      41.2667
    ]
  },
  "type": "Feature",
  "properties": {
    "hierarchy": [
      "tgn:2557270",
      "tgn:1000001",
      "tgn:7012149",
      "tgn:1003022",
      "tgn:7007252",
      "tgn:7029392"
    ],
    "placetype": [
      "aat:300008680"
    ],
    "id": 2557270,
    "name:xx": "Old Lake"
  }
}
