{
  "geometry": {
    "type": "Point",
    "coordinates": [
      79.9289,
      27.2076
    ]
  },
  "type": "Feature",
  "properties": {
    "hierarchy": [
      "tgn:7561844",
      "tgn:1000004",
      "tgn:7000198",
      "tgn:7016722",
      "tgn:7029392"
    ],
    "placetype": [
      "aat:300008347"
    ],
    "name:en": "Usar Purwa",
    "id": 7561844
  }
}
