{
  "geometry": {
    "type": "Point",
    "coordinates": [
      -85.85,
      46.1833
    ]
  },
  "type": "Feature",
  "properties": {
    "hierarchy": [
      "tgn:2699673",
      "tgn:1000001",
      "tgn:7012149",
      "tgn:2000973",
      "tgn:7007520",
      "tgn:7029392"
    ],
    "placetype": [
      "aat:300008680"
    ],
    "id": 2699673,
    "name:xx": "Stuart Lake"
  }
}
