{
  "geometry": {
    "type": "Point",
    "coordinates": [
      -90.0667,
      38.8333
    ]
  },
  "type": "Feature",
  "properties": {
    "hierarchy": [
      "tgn:2029986",
      "tgn:1000001",
      "tgn:7012149",
      "tgn:1002622",
      "tgn:7007251",
      "tgn:7029392"
    ],
    "placetype": [
      "aat:300008347"
    ],
    "id": 2029986,
    "name:xx": "Roxana"
  }
}
