{
  "geometry": {
    "type": "Point",
    "coordinates": [
      -116.7167,
      32.6333
    ]
  },
  "type": "Feature",
  "properties": {
    "hierarchy": [
      "tgn:2766347",
      "tgn:1000001",
      "tgn:7012149",
      "tgn:7007157",
      "tgn:1002858",
      "tgn:7029392"
    ],
    "placetype": [
      "aat:300008798"
    ],
    "id": 2766347,
    "name:xx": "White Mountain"
  }
}
