{
  "geometry": {
    "type": "Point",
    "coordinates": [
      85.04048,
      22.841911
    ]
  },
  "type": "Feature",
  "properties": {
    "hierarchy": [
      "tgn:7552275",
      "tgn:1000004",
      "tgn:7000198",
      "tgn:7031783",
      "tgn:7029392"
    ],
    "placetype": [
      "aat:300008347"
    ],
    "name:en": "Manhātu",
    "id": 7552275
  }
}
