{
  "type": "FeatureCollection",
  "features": [
    {
      "geometry": {
        "type": "Point",
        "coordinates": [
          0.833333,
          52.983333
        ]
      },
      "type": "Feature",
      "properties": {
        "hierarchy": [
          "tgn:7462491",
          "tgn:7002445",
          "tgn:1000003",
          "tgn:7008160",
          "tgn:7008591",
          "tgn:7029392"
        ],
        "placetype": [
          "aat:300008850"
        ],
        "name:en": "High Cape",
        "id": 7462491
      }
    },
    {
      "geometry": {
        "type": "Point",
        "coordinates": [
          -1.633333,
          55.383333
        ]
      },
      "type": "Feature",
      "properties": {
        "hierarchy": [
          "tgn:7462492",
          "tgn:7002445",
          "tgn:1000003",
          "tgn:7008165",
          "tgn:7008591",
          "tgn:7029392"
        ],
        "placetype": [
          "aat:300008347"
        ],
        "name:en": "High Buston",
        "id": 7462492
      }
    },
    {
      "geometry": {
        "type": "Point",
        "coordinates": [
          -0.1,
          51.55
        ]
      },
      "type": "Feature",
      "properties": {
        "hierarchy": [
          "tgn:7462493",
          "tgn:7002445",
          "tgn:7018922",
          "tgn:7011781",
          "tgn:1000003",
          "tgn:7008136",
          "tgn:7008591",
          "tgn:7029392"
        ],
        "placetype": [
          "aat:300008347",
          "aat:300000745"
        ],
        "name:en": "Highbury",
        "id": 7462493
      }
    },
    {
      "geometry": {
        "type": "Point",
        "coordinates": [
          -4.1,
          55.766667
        ]
      },
      "type": "Feature",
      "properties": {
        "hierarchy": [
          "tgn:7462496",
          "tgn:7002444",
          "tgn:1000003",
          "tgn:7019090",
          "tgn:7008591",
          "tgn:7029392"
        ],
        "placetype": [
          "aat:300008347"
        ],
        "name:en": "High Blantyre",
        "id": 7462496
      }
    },
    {
      "geometry": {
        "type": "Point",
        "coordinates": [
          -0.2,
          51.65
        ]
      },
      "type": "Feature",
      "properties": {
        "hierarchy": [
          "tgn:7462499",
          "tgn:7026508",
          "tgn:7002445",
          "tgn:1000003",
          "tgn:7008136",
          "tgn:7008591",
          "tgn:7029392"
        ],
        "placetype": [
          "aat:300007783"
        ],
        "name:en": "High Barnet",
        "id": 7462499
      }
    }
  ]
}
