{
  "geometry": {
    "type": "Point",
    "coordinates": [
      118.8167,
      9.8833
    ]
  },
  "type": "Feature",
  "properties": {
    "hierarchy": [
      "tgn:1113139",
      "tgn:1000004",
      "tgn:1001481",
      "tgn:1000135",
      "tgn:7029392"
    ],
    "placetype": [
      "aat:300132316"
    ],
    "id": 1113139,
    "name:xx": "Honda Bay"
  }
}
