{
  "geometry": {
    "type": "Point",
    "coordinates": [
      -112.4167,
      41.35
    ]
  },
  "type": "Feature",
  "properties": {
    "hierarchy": [
      "tgn:2656084",
      "tgn:1000001",
      "tgn:2002102",
      "tgn:7012149",
      "tgn:7007827",
      "tgn:7029392"
    ],
    "placetype": [
      "aat:300008697"
    ],
    "id": 2656084,
    "name:xx": "Shaw Spring"
  }
}
