{
  "geometry": {
    "type": "Point",
    "coordinates": [
      -114.35,
      40.1167
    ]
  },
  "type": "Feature",
  "properties": {
    "hierarchy": [
      "tgn:2438968",
      "tgn:1000001",
      "tgn:2001411",
      "tgn:7012149",
      "tgn:7007526",
      "tgn:7029392"
    ],
    "placetype": [
      "aat:300000390"
    ],
    "id": 2438968,
    "name:xx": "Kinsley Mine"
  }
}
