{
  "geometry": {
    "type": "Point",
    "coordinates": [
      -82.95,
      32.7333
    ]
  },
  "type": "Feature",
  "properties": {
    "hierarchy": [
      "tgn:2723342",
      "tgn:1000001",
      "tgn:7012149",
      "tgn:2000449",
      "tgn:7007248",
      "tgn:7029392"
    ],
    "placetype": [
      "aat:300008680"
    ],
    "id": 2723342,
    "name:xx": "Tobe Lake"
  }
}
