{
  "type": "FeatureCollection",
  "features": [
    {
      "geometry": {
        "type": "Point",
        "coordinates": [
          -111.2,
          24.3
        ]
      },
      "type": "Feature",
      "properties": {
        "hierarchy": [
          "tgn:7369220",
          "tgn:1001836",
          "tgn:1000001",
          "tgn:7005560",
          "tgn:7029392"
        ],
        "placetype": [
          "aat:300008699"
        ],
        "id": 7369220,
        "name:xx": "Guadalupe, Arroyo"
      }
    },
    {
      "geometry": {
        "type": "Point",
        "coordinates": [
          -98.283333,
          23.433333
        ]
      },
      "type": "Feature",
      "properties": {
        "hierarchy": [
          "tgn:7369221",
          "tgn:1000001",
          "tgn:7005597",
          "tgn:7005560",
          "tgn:7029392"
        ],
        "placetype": [
          "aat:300387033"
        ],
        "id": 7369221,
        "name:xx": "Guadalupe"
      }
    },
    {
      "geometry": {
        "type": "Point",
        "coordinates": [
          -99.833333,
          23.933333
        ]
      },
      "type": "Feature",
      "properties": {
        "hierarchy": [
          "tgn:7369222",
          "tgn:1000001",
          "tgn:7005589",
          "tgn:7005560",
          "tgn:7029392"
        ],
        "placetype": [
          "aat:300266554",
          "aat:300008699"
        ],
        "id": 7369222,
        "name:xx": "Guadalupe"
      }
    },
    {
      "geometry": {
        "type": "Point",
        "coordinates": [
          -100.45,
          25.516667
        ]
      },
      "type": "Feature",
      "properties": {
        "hierarchy": [
          "tgn:7369223",
          "tgn:1000001",
          "tgn:7005589",
          "tgn:7005560",
          "tgn:7029392"
        ],
        "placetype": [
          "aat:300007783"
        ],
        "id": 7369223,
        "name:xx": "Guadalupe"
      }
    },
    {
      "geometry": {
        "type": "Point",
        "coordinates": [
          -101.616667,
          25.416667
        ]
      },
      "type": "Feature",
      "properties": {
        "hierarchy": [
          "tgn:7369224",
          "tgn:1001853",
          "tgn:1000001",
          "tgn:7005560",
          "tgn:7029392"
        ],
        "placetype": [
          "aat:300007783"
        ],
        "id": 7369224,
        "name:xx": "Guadalupe"
      }
    },
    {
      "geometry": {
        "type": "Point",
        "coordinates": [
          -111.972778,
          25.590833
        ]
      },
      "type": "Feature",
      "properties": {
        "hierarchy": [
          "tgn:7369225",
          "tgn:1001836",
          "tgn:1000001",
          "tgn:7005560",
          "tgn:7029392"
        ],
        "placetype": [
          "aat:300008347"
        ],
        "id": 7369225,
        "name:xx": "Guadalupe"
      }
    },
    {
      "geometry": {
        "type": "Point",
        "coordinates": [
          -103.3,
          19.116667
        ]
      },
      "type": "Feature",
      "properties": {
        "hierarchy": [
          "tgn:7369226",
          "tgn:7005586",
          "tgn:1000001",
          "tgn:7005560",
          "tgn:7029392"
        ],
        "placetype": [
          "aat:300000241"
        ],
        "id": 7369226,
        "name:xx": "Guadalupe"
      }
    },
    {
      "geometry": {
        "type": "Point",
        "coordinates": [
          -106.316667,
          30.566667
        ]
      },
      "type": "Feature",
      "properties": {
        "hierarchy": [
          "tgn:7369227",
          "tgn:7005581",
          "tgn:1000001",
          "tgn:7005560",
          "tgn:7029392"
        ],
        "placetype": [
          "aat:300008347"
        ],
        "id": 7369227,
        "name:xx": "Guadalupe"
      }
    },
    {
      "geometry": {
        "type": "Point",
        "coordinates": [
          -106.633333,
          30.533333
        ]
      },
      "type": "Feature",
      "properties": {
        "hierarchy": [
          "tgn:7369228",
          "tgn:7005581",
          "tgn:1000001",
          "tgn:7005560",
          "tgn:7029392"
        ],
        "placetype": [
          "aat:300008347"
        ],
        "id": 7369228,
        "name:xx": "Guadalupe"
      }
    },
    {
      "geometry": {
        "type": "Point",
        "coordinates": [
          -107.916667,
          30.35
        ]
      },
      "type": "Feature",
      "properties": {
        "hierarchy": [
          "tgn:7369229",
          "tgn:7005581",
          "tgn:1000001",
          "tgn:7005560",
          "tgn:7029392"
        ],
        "placetype": [
          "aat:300008347"
        ],
        "id": 7369229,
        "name:xx": "Guadalupe"
      }
    }
  ]
}
