{
  "type": "FeatureCollection",
  "features": [
    {
      "geometry": {
        "type": "Point",
        "coordinates": [
          -71.25,
          -34.283333
        ]
      },
      "type": "Feature",
      "properties": {
        "hierarchy": [
          "tgn:7285980",
          "tgn:1001695",
          "tgn:1000049",
          "tgn:1000002",
          "tgn:7029392"
        ],
        "placetype": [
          "aat:300387200"
        ],
        "id": 7285980,
        "name:xx": "La Esperanza"
      }
    },
    {
      "geometry": {
        "type": "Point",
        "coordinates": [
          -70.833333,
          -33.266667
        ]
      },
      "type": "Feature",
      "properties": {
        "hierarchy": [
          "tgn:7285981",
          "tgn:1001708",
          "tgn:1000049",
          "tgn:1000002",
          "tgn:7029392"
        ],
        "placetype": [
          "aat:300387200"
        ],
        "id": 7285981,
        "name:xx": "La Esperanza"
      }
    },
    {
      "geometry": {
        "type": "Point",
        "coordinates": [
          -71.983333,
          -40.333333
        ]
      },
      "type": "Feature",
      "properties": {
        "hierarchy": [
          "tgn:7285982",
          "tgn:1001699",
          "tgn:1000049",
          "tgn:1000002",
          "tgn:7029392"
        ],
        "placetype": [
          "aat:300000206"
        ],
        "id": 7285982,
        "name:xx": "La Esperanza"
      }
    },
    {
      "geometry": {
        "type": "Point",
        "coordinates": [
          -72.55,
          -40.1
        ]
      },
      "type": "Feature",
      "properties": {
        "hierarchy": [
          "tgn:7285983",
          "tgn:1001699",
          "tgn:1000049",
          "tgn:1000002",
          "tgn:7029392"
        ],
        "placetype": [
          "aat:300000206"
        ],
        "id": 7285983,
        "name:xx": "La Esperanza"
      }
    },
    {
      "geometry": {
        "type": "Point",
        "coordinates": [
          -72.15,
          -38.516667
        ]
      },
      "type": "Feature",
      "properties": {
        "hierarchy": [
          "tgn:7285984",
          "tgn:1001692",
          "tgn:1000049",
          "tgn:1000002",
          "tgn:7029392"
        ],
        "placetype": [
          "aat:300000206"
        ],
        "id": 7285984,
        "name:xx": "La Esperanza"
      }
    },
    {
      "geometry": {
        "type": "Point",
        "coordinates": [
          -72.366667,
          -37.816667
        ]
      },
      "type": "Feature",
      "properties": {
        "hierarchy": [
          "tgn:7285985",
          "tgn:1001637",
          "tgn:1000049",
          "tgn:1000002",
          "tgn:7029392"
        ],
        "placetype": [
          "aat:300000206"
        ],
        "id": 7285985,
        "name:xx": "La Esperanza"
      }
    },
    {
      "geometry": {
        "type": "Point",
        "coordinates": [
          -72.933333,
          -37.65
        ]
      },
      "type": "Feature",
      "properties": {
        "hierarchy": [
          "tgn:7285986",
          "tgn:1001692",
          "tgn:1000049",
          "tgn:1000002",
          "tgn:7029392"
        ],
        "placetype": [
          "aat:300000206"
        ],
        "id": 7285986,
        "name:xx": "La Esperanza"
      }
    },
    {
      "geometry": {
        "type": "Point",
        "coordinates": [
          -72.116667,
          -35.75
        ]
      },
      "type": "Feature",
      "properties": {
        "hierarchy": [
          "tgn:7285987",
          "tgn:1001705",
          "tgn:1000049",
          "tgn:1000002",
          "tgn:7029392"
        ],
        "placetype": [
          "aat:300000206"
        ],
        "id": 7285987,
        "name:xx": "La Esperanza"
      }
    },
    {
      "geometry": {
        "type": "Point",
        "coordinates": [
          -71.633333,
          -35.7
        ]
      },
      "type": "Feature",
      "properties": {
        "hierarchy": [
          "tgn:7285988",
          "tgn:1001705",
          "tgn:1000049",
          "tgn:1000002",
          "tgn:7029392"
        ],
        "placetype": [
          "aat:300000206"
        ],
        "id": 7285988,
        "name:xx": "La Esperanza"
      }
    },
    {
      "geometry": {
        "type": "Point",
        "coordinates": [
          -71.216667,
          -35.7
        ]
      },
      "type": "Feature",
      "properties": {
        "hierarchy": [
          "tgn:7285989",
          "tgn:1001705",
          "tgn:1000049",
          "tgn:1000002",
          "tgn:7029392"
        ],
        "placetype": [
          "aat:300000206"
        ],
        "id": 7285989,
        "name:xx": "La Esperanza"
      }
    }
  ]
}
