{
  "geometry": {
    "type": "Point",
    "coordinates": [
      -116.0333,
      40.1167
    ]
  },
  "type": "Feature",
  "properties": {
    "hierarchy": [
      "tgn:2155201",
      "tgn:1000001",
      "tgn:2001413",
      "tgn:7012149",
      "tgn:7007526",
      "tgn:7029392"
    ],
    "placetype": [
      "aat:300000390"
    ],
    "id": 2155201,
    "name:xx": "Bear Mine"
  }
}
