{
  "geometry": {
    "type": "Point",
    "coordinates": [
      -71.8167,
      41.55
    ]
  },
  "type": "Feature",
  "properties": {
    "hierarchy": [
      "tgn:2180220",
      "tgn:1000001",
      "tgn:1002714",
      "tgn:7012149",
      "tgn:7007159",
      "tgn:7029392"
    ],
    "placetype": [
      "aat:300008699"
    ],
    "id": 2180220,
    "name:xx": "Bliven Brook"
  }
}
