{
  "geometry": {
    "type": "Point",
    "coordinates": [
      -106.0167,
      48.9167
    ]
  },
  "type": "Feature",
  "properties": {
    "hierarchy": [
      "tgn:2330147",
      "tgn:1000001",
      "tgn:2001269",
      "tgn:7012149",
      "tgn:7007524",
      "tgn:7029392"
    ],
    "placetype": [
      "aat:300008761"
    ],
    "id": 2330147,
    "name:xx": "Flaherty Coulee"
  }
}
