{
  "geometry": {
    "type": "Point",
    "coordinates": [
      -75.8333,
      35.5667
    ]
  },
  "type": "Feature",
  "properties": {
    "hierarchy": [
      "tgn:2609239",
      "tgn:1000001",
      "tgn:7012149",
      "tgn:2001488",
      "tgn:7007709",
      "tgn:7029392"
    ],
    "placetype": [
      "aat:300008791"
    ],
    "id": 2609239,
    "name:xx": "Rawls Island"
  }
}
