{
  "geometry": {
    "type": "Point",
    "coordinates": [
      -107.8333,
      50.6333
    ]
  },
  "type": "Feature",
  "properties": {
    "hierarchy": [
      "tgn:1016125",
      "tgn:7005685",
      "tgn:1000001",
      "tgn:7005805",
      "tgn:7029392"
    ],
    "placetype": [
      "aat:300008347"
    ],
    "id": 1016125,
    "name:xx": "Stewart Valley"
  }
}
