{
  "geometry": {
    "type": "Point",
    "coordinates": [
      79.700485,
      27.64588
    ]
  },
  "type": "Feature",
  "properties": {
    "hierarchy": [
      "tgn:7560084",
      "tgn:1000004",
      "tgn:7000198",
      "tgn:7016722",
      "tgn:7029392"
    ],
    "placetype": [
      "aat:300008347"
    ],
    "name:en": "Barwāra",
    "id": 7560084
  }
}
