{
  "geometry": {
    "type": "Point",
    "coordinates": [
      -75.0667,
      40.4333
    ]
  },
  "type": "Feature",
  "properties": {
    "hierarchy": [
      "tgn:2597205",
      "tgn:1000001",
      "tgn:1002213",
      "tgn:7012149",
      "tgn:7007710",
      "tgn:7029392"
    ],
    "placetype": [
      "aat:300008791"
    ],
    "id": 2597205,
    "name:xx": "Prahls Island"
  }
}
