{
  "type": "FeatureCollection",
  "features": [
    {
      "geometry": {
        "type": "Point",
        "coordinates": [
          -6,
          43.516667
        ]
      },
      "type": "Feature",
      "properties": {
        "hierarchy": [
          "tgn:7304920",
          "tgn:7008911",
          "tgn:1000003",
          "tgn:7002763",
          "tgn:1000095",
          "tgn:7029392"
        ],
        "placetype": [
          "aat:300008347"
        ],
        "id": 7304920,
        "name:xx": "La Torre"
      }
    },
    {
      "geometry": {
        "type": "Point",
        "coordinates": [
          -5.133333,
          43.466667
        ]
      },
      "type": "Feature",
      "properties": {
        "hierarchy": [
          "tgn:7304921",
          "tgn:7008911",
          "tgn:1000003",
          "tgn:7002763",
          "tgn:1000095",
          "tgn:7029392"
        ],
        "placetype": [
          "aat:300008347"
        ],
        "id": 7304921,
        "name:xx": "La Torre"
      }
    },
    {
      "geometry": {
        "type": "Point",
        "coordinates": [
          -6.133333,
          43.166667
        ]
      },
      "type": "Feature",
      "properties": {
        "hierarchy": [
          "tgn:7304922",
          "tgn:7008911",
          "tgn:1000003",
          "tgn:7002763",
          "tgn:1000095",
          "tgn:7029392"
        ],
        "placetype": [
          "aat:300008347"
        ],
        "id": 7304922,
        "name:xx": "La Torre"
      }
    },
    {
      "geometry": {
        "type": "Point",
        "coordinates": [
          0.333611,
          42.346522
        ]
      },
      "type": "Feature",
      "properties": {
        "hierarchy": [
          "tgn:7304923",
          "tgn:7002759",
          "tgn:7008909",
          "tgn:1000003",
          "tgn:1000095",
          "tgn:7029392"
        ],
        "placetype": [
          "aat:300008347"
        ],
        "id": 7304923,
        "name:xx": "Latorre"
      }
    },
    {
      "geometry": {
        "type": "Point",
        "coordinates": [
          0.156034,
          42.313077
        ]
      },
      "type": "Feature",
      "properties": {
        "hierarchy": [
          "tgn:7304924",
          "tgn:7002759",
          "tgn:7008909",
          "tgn:1000003",
          "tgn:1000095",
          "tgn:7029392"
        ],
        "placetype": [
          "aat:300008347"
        ],
        "id": 7304924,
        "name:xx": "Latorre"
      }
    },
    {
      "geometry": {
        "type": "Point",
        "coordinates": [
          -8.083333,
          42.2
        ]
      },
      "type": "Feature",
      "properties": {
        "hierarchy": [
          "tgn:7304925",
          "tgn:7002831",
          "tgn:1000003",
          "tgn:7002786",
          "tgn:1000095",
          "tgn:7029392"
        ],
        "placetype": [
          "aat:300008347"
        ],
        "id": 7304925,
        "name:xx": "La Torre"
      }
    },
    {
      "geometry": {
        "type": "Point",
        "coordinates": [
          -4.966667,
          40.583333
        ]
      },
      "type": "Feature",
      "properties": {
        "hierarchy": [
          "tgn:7304926",
          "tgn:7002806",
          "tgn:7001158",
          "tgn:1000003",
          "tgn:1000095",
          "tgn:7029392"
        ],
        "placetype": [
          "aat:300008347"
        ],
        "id": 7304926,
        "name:xx": "La Torre"
      }
    },
    {
      "geometry": {
        "type": "Point",
        "coordinates": [
          -1.016667,
          39.966667
        ]
      },
      "type": "Feature",
      "properties": {
        "hierarchy": [
          "tgn:7304927",
          "tgn:7001165",
          "tgn:1000003",
          "tgn:7002793",
          "tgn:1000095",
          "tgn:7029392"
        ],
        "placetype": [
          "aat:300008347"
        ],
        "id": 7304927,
        "name:xx": "La Torre"
      }
    },
    {
      "geometry": {
        "type": "Point",
        "coordinates": [
          -1.25,
          39.666667
        ]
      },
      "type": "Feature",
      "properties": {
        "hierarchy": [
          "tgn:7304928",
          "tgn:7001165",
          "tgn:1000003",
          "tgn:7002793",
          "tgn:1000095",
          "tgn:7029392"
        ],
        "placetype": [
          "aat:300008347"
        ],
        "id": 7304928,
        "name:xx": "La Torre"
      }
    },
    {
      "geometry": {
        "type": "Point",
        "coordinates": [
          -0.266667,
          39.583333
        ]
      },
      "type": "Feature",
      "properties": {
        "hierarchy": [
          "tgn:7304929",
          "tgn:7001165",
          "tgn:1000003",
          "tgn:7002793",
          "tgn:1000095",
          "tgn:7029392"
        ],
        "placetype": [
          "aat:300008347"
        ],
        "id": 7304929,
        "name:xx": "La Torre"
      }
    }
  ]
}
