{
  "type": "FeatureCollection",
  "features": [
    {
      "geometry": {
        "type": "Point",
        "coordinates": [
          4.855518,
          50.255027
        ]
      },
      "type": "Feature",
      "properties": {
        "hierarchy": [
          "tgn:7246030",
          "tgn:7003466",
          "tgn:1000003",
          "tgn:1000063",
          "tgn:4012014",
          "tgn:7029392"
        ],
        "placetype": [
          "aat:300008863"
        ],
        "id": 7246030,
        "name:xx": "Bry, Bois de"
      }
    },
    {
      "geometry": {
        "type": "Point",
        "coordinates": [
          3.766667,
          50.466667
        ]
      },
      "type": "Feature",
      "properties": {
        "hierarchy": [
          "tgn:7246031",
          "tgn:7007877",
          "tgn:1000003",
          "tgn:1000063",
          "tgn:4012014",
          "tgn:7029392"
        ],
        "placetype": [
          "aat:300008347"
        ],
        "id": 7246031,
        "name:xx": "Bruyères Montoises"
      }
    },
    {
      "geometry": {
        "type": "Point",
        "coordinates": [
          4.975189,
          50.268467
        ]
      },
      "type": "Feature",
      "properties": {
        "hierarchy": [
          "tgn:7246032",
          "tgn:7003466",
          "tgn:1000003",
          "tgn:1000063",
          "tgn:4012014",
          "tgn:7029392"
        ],
        "placetype": [
          "aat:300008863"
        ],
        "id": 7246032,
        "name:xx": "Bruyères, Bois des"
      }
    },
    {
      "geometry": {
        "type": "Point",
        "coordinates": [
          4.633333,
          50.15
        ]
      },
      "type": "Feature",
      "properties": {
        "hierarchy": [
          "tgn:7246033",
          "tgn:7003466",
          "tgn:1000003",
          "tgn:1000063",
          "tgn:4012014",
          "tgn:7029392"
        ],
        "placetype": [
          "aat:300008699"
        ],
        "id": 7246033,
        "name:xx": "Bruyères"
      }
    },
    {
      "geometry": {
        "type": "Point",
        "coordinates": [
          5.783333,
          50.616667
        ]
      },
      "type": "Feature",
      "properties": {
        "hierarchy": [
          "tgn:7246034",
          "tgn:7003460",
          "tgn:1000003",
          "tgn:1000063",
          "tgn:4012014",
          "tgn:7029392"
        ],
        "placetype": [
          "aat:300008347"
        ],
        "id": 7246034,
        "name:xx": "Bruyères"
      }
    },
    {
      "geometry": {
        "type": "Point",
        "coordinates": [
          4.6,
          50.65
        ]
      },
      "type": "Feature",
      "properties": {
        "hierarchy": [
          "tgn:7246035",
          "tgn:7018238",
          "tgn:1000003",
          "tgn:1000063",
          "tgn:4012014",
          "tgn:7029392"
        ],
        "placetype": [
          "aat:300008347"
        ],
        "id": 7246035,
        "name:xx": "Bruyères"
      }
    },
    {
      "geometry": {
        "type": "Point",
        "coordinates": [
          4.6,
          50.55
        ]
      },
      "type": "Feature",
      "properties": {
        "hierarchy": [
          "tgn:7246037",
          "tgn:7003466",
          "tgn:1000003",
          "tgn:1000063",
          "tgn:4012014",
          "tgn:7029392"
        ],
        "placetype": [
          "aat:300008347"
        ],
        "id": 7246037,
        "name:xx": "Bruyères"
      }
    },
    {
      "geometry": {
        "type": "Point",
        "coordinates": [
          3.75,
          50.483333
        ]
      },
      "type": "Feature",
      "properties": {
        "hierarchy": [
          "tgn:7246038",
          "tgn:7007877",
          "tgn:1000003",
          "tgn:1000063",
          "tgn:4012014",
          "tgn:7029392"
        ],
        "placetype": [
          "aat:300008347"
        ],
        "id": 7246038,
        "name:xx": "Bruyères"
      }
    },
    {
      "geometry": {
        "type": "Point",
        "coordinates": [
          4.283333,
          50.4
        ]
      },
      "type": "Feature",
      "properties": {
        "hierarchy": [
          "tgn:7246039",
          "tgn:7007877",
          "tgn:1000003",
          "tgn:1000063",
          "tgn:4012014",
          "tgn:7029392"
        ],
        "placetype": [
          "aat:300008347"
        ],
        "id": 7246039,
        "name:xx": "Bruyère Polvée"
      }
    }
  ]
}
