{
  "geometry": {
    "type": "Point",
    "coordinates": [
      -84.05,
      35.8167
    ]
  },
  "type": "Feature",
  "properties": {
    "hierarchy": [
      "tgn:2099983",
      "tgn:1000001",
      "tgn:2001841",
      "tgn:7012149",
      "tgn:7007825",
      "tgn:7029392"
    ],
    "placetype": [
      "aat:300008347"
    ],
    "id": 2099983,
    "name:xx": "Lakeview"
  }
}
