{
  "geometry": {
    "type": "Point",
    "coordinates": [
      -72.4833,
      42.3667
    ]
  },
  "type": "Feature",
  "properties": {
    "hierarchy": [
      "tgn:2309542",
      "tgn:1000001",
      "tgn:7013686",
      "tgn:7012149",
      "tgn:7007517",
      "tgn:7029392"
    ],
    "placetype": [
      "aat:300008347"
    ],
    "id": 2309542,
    "name:xx": "East Village"
  }
}
