{
  "geometry": {
    "type": "Point",
    "coordinates": [
      -89.9167,
      43.0667
    ]
  },
  "type": "Feature",
  "properties": {
    "hierarchy": [
      "tgn:2441425",
      "tgn:1000001",
      "tgn:7012149",
      "tgn:2002326",
      "tgn:7007922",
      "tgn:7029392"
    ],
    "placetype": [
      "aat:300008699"
    ],
    "id": 2441425,
    "name:xx": "Knudson Branch"
  }
}
