{
  "geometry": {
    "type": "Point",
    "coordinates": [
      -87.6833,
      38.2833
    ]
  },
  "type": "Feature",
  "properties": {
    "hierarchy": [
      "tgn:2133659",
      "tgn:1000001",
      "tgn:7012149",
      "tgn:2000543",
      "tgn:7007252",
      "tgn:7029392"
    ],
    "placetype": [
      "aat:300008699"
    ],
    "id": 2133659,
    "name:xx": "Andrews Run"
  }
}
