{
  "geometry": {
    "type": "Point",
    "coordinates": [
      -97.0833,
      31.7667
    ]
  },
  "type": "Feature",
  "properties": {
    "hierarchy": [
      "tgn:2461641",
      "tgn:1000001",
      "tgn:7012149",
      "tgn:7021748",
      "tgn:7007826",
      "tgn:7029392"
    ],
    "placetype": [
      "aat:300008706"
    ],
    "id": 2461641,
    "name:xx": "Little Tehuacana Creek"
  }
}
