{
  "geometry": {
    "type": "Point",
    "coordinates": [
      34.262671,
      28.144056
    ]
  },
  "type": "Feature",
  "properties": {
    "hierarchy": [
      "tgn:7523489",
      "tgn:7001242",
      "tgn:7016833",
      "tgn:7001336",
      "tgn:7029392"
    ],
    "placetype": [
      "aat:300008795"
    ],
    "name:en": "Biţāḩ, Jabal",
    "id": 7523489
  }
}
