{
  "geometry": {
    "type": "Point",
    "coordinates": [
      -72.1333,
      41.7333
    ]
  },
  "type": "Feature",
  "properties": {
    "hierarchy": [
      "tgn:1135165",
      "tgn:1000001",
      "tgn:7012149",
      "tgn:7029392"
    ],
    "placetype": [
      "aat:300008703"
    ],
    "id": 1135165,
    "name:xx": "Beaver Brook"
  }
}
