{
  "type": "FeatureCollection",
  "features": [
    {
      "geometry": {
        "type": "Point",
        "coordinates": [
          138.0167,
          36.4167
        ]
      },
      "type": "Feature",
      "properties": {
        "hierarchy": [
          "tgn:1081190",
          "tgn:7000895",
          "tgn:1000004",
          "tgn:1001010",
          "tgn:1000120",
          "tgn:7029392"
        ],
        "placetype": [
          "aat:300008347"
        ],
        "id": 1081190,
        "name:xx": "Sakakita"
      }
    },
    {
      "geometry": {
        "type": "Point",
        "coordinates": [
          137.5333,
          35.5667
        ]
      },
      "type": "Feature",
      "properties": {
        "hierarchy": [
          "tgn:1081191",
          "tgn:7000895",
          "tgn:1000004",
          "tgn:1000977",
          "tgn:1000120",
          "tgn:7029392"
        ],
        "placetype": [
          "aat:300008347"
        ],
        "id": 1081191,
        "name:xx": "Sakashita"
      }
    },
    {
      "geometry": {
        "type": "Point",
        "coordinates": [
          136.4167,
          35.6
        ]
      },
      "type": "Feature",
      "properties": {
        "hierarchy": [
          "tgn:1081193",
          "tgn:7000895",
          "tgn:1000004",
          "tgn:1000977",
          "tgn:1000120",
          "tgn:7029392"
        ],
        "placetype": [
          "aat:300008347"
        ],
        "id": 1081193,
        "name:xx": "Sakauchi"
      }
    },
    {
      "geometry": {
        "type": "Point",
        "coordinates": [
          133.2833,
          33.5
        ]
      },
      "type": "Feature",
      "properties": {
        "hierarchy": [
          "tgn:1081194",
          "tgn:1000991",
          "tgn:1000004",
          "tgn:7000903",
          "tgn:1000120",
          "tgn:7029392"
        ],
        "placetype": [
          "aat:300008347"
        ],
        "id": 1081194,
        "name:xx": "Sakawa"
      }
    },
    {
      "geometry": {
        "type": "Point",
        "coordinates": [
          129.55,
          33
        ]
      },
      "type": "Feature",
      "properties": {
        "hierarchy": [
          "tgn:1081195",
          "tgn:7000276",
          "tgn:1000004",
          "tgn:7000901",
          "tgn:1000120",
          "tgn:7029392"
        ],
        "placetype": [
          "aat:300008347"
        ],
        "id": 1081195,
        "name:xx": "Sakito"
      }
    },
    {
      "geometry": {
        "type": "Point",
        "coordinates": [
          135.7833,
          34.8833
        ]
      },
      "type": "Feature",
      "properties": {
        "hierarchy": [
          "tgn:1081196",
          "tgn:1000004",
          "tgn:1000998",
          "tgn:7000896",
          "tgn:1000120",
          "tgn:7029392"
        ],
        "placetype": [
          "aat:300008347"
        ],
        "id": 1081196,
        "name:xx": "Sako"
      }
    },
    {
      "geometry": {
        "type": "Point",
        "coordinates": [
          132.7167,
          34.8667
        ]
      },
      "type": "Feature",
      "properties": {
        "hierarchy": [
          "tgn:1081198",
          "tgn:1000984",
          "tgn:7000897",
          "tgn:1000004",
          "tgn:1000120",
          "tgn:7029392"
        ],
        "placetype": [
          "aat:300008347"
        ],
        "id": 1081198,
        "name:xx": "Sakugi"
      }
    },
    {
      "geometry": {
        "type": "Point",
        "coordinates": [
          137.8167,
          35.1
        ]
      },
      "type": "Feature",
      "properties": {
        "hierarchy": [
          "tgn:1081199",
          "tgn:7000895",
          "tgn:1000004",
          "tgn:1001031",
          "tgn:1000120",
          "tgn:7029392"
        ],
        "placetype": [
          "aat:300008347"
        ],
        "id": 1081199,
        "name:xx": "Sakuma"
      }
    }
  ]
}
