{
  "geometry": {
    "type": "Point",
    "coordinates": [
      -120.1833,
      39.5333
    ]
  },
  "type": "Feature",
  "properties": {
    "hierarchy": [
      "tgn:2644590",
      "tgn:1000001",
      "tgn:7012149",
      "tgn:7007157",
      "tgn:1002894",
      "tgn:7029392"
    ],
    "placetype": [
      "aat:300008798"
    ],
    "id": 2644590,
    "name:xx": "Sardine Peak"
  }
}
