{
  "geometry": {
    "type": "Point",
    "coordinates": [
      -108.5833,
      45.5167
    ]
  },
  "type": "Feature",
  "properties": {
    "hierarchy": [
      "tgn:2181303",
      "tgn:1000001",
      "tgn:7012149",
      "tgn:2001315",
      "tgn:7007524",
      "tgn:7029392"
    ],
    "placetype": [
      "aat:300008706"
    ],
    "id": 2181303,
    "name:xx": "Blue Creek"
  }
}
