{
  "geometry": {
    "type": "Point",
    "coordinates": [
      -121.6333,
      47.2667
    ]
  },
  "type": "Feature",
  "properties": {
    "hierarchy": [
      "tgn:2546312",
      "tgn:1000001",
      "tgn:7012149",
      "tgn:7018871",
      "tgn:7007920",
      "tgn:7029392"
    ],
    "placetype": [
      "aat:300008707"
    ],
    "id": 2546312,
    "name:xx": "North Fork Green River"
  }
}
