{
  "geometry": {
    "type": "Point",
    "coordinates": [
      73.9667,
      39.6667
    ]
  },
  "type": "Feature",
  "properties": {
    "hierarchy": [
      "tgn:1054405",
      "tgn:1000004",
      "tgn:7012212",
      "tgn:7006655",
      "tgn:7029392"
    ],
    "placetype": [
      "aat:300008347"
    ],
    "id": 1054405,
    "name:xx": "Irkeshtam"
  }
}
