{
  "geometry": {
    "type": "Point",
    "coordinates": [
      -93.3833,
      47.5167
    ]
  },
  "type": "Feature",
  "properties": {
    "hierarchy": [
      "tgn:2146408",
      "tgn:1000001",
      "tgn:7012149",
      "tgn:2001029",
      "tgn:7007521",
      "tgn:7029392"
    ],
    "placetype": [
      "aat:300008706"
    ],
    "id": 2146408,
    "name:xx": "Balsam Creek"
  }
}
