{
  "geometry": {
    "type": "Point",
    "coordinates": [
      -76.8333,
      41.3667
    ]
  },
  "type": "Feature",
  "properties": {
    "hierarchy": [
      "tgn:2672170",
      "tgn:1000001",
      "tgn:7012149",
      "tgn:1002613",
      "tgn:7007710",
      "tgn:7029392"
    ],
    "placetype": [
      "aat:300008798"
    ],
    "id": 2672170,
    "name:xx": "Smiths Knob Vista"
  }
}
