{
  "type": "FeatureCollection",
  "features": [
    {
      "geometry": {
        "type": "Point",
        "coordinates": [
          -94,
          46.7167
        ]
      },
      "type": "Feature",
      "properties": {
        "hierarchy": [
          "tgn:2253650",
          "tgn:1000001",
          "tgn:2001016",
          "tgn:7012149",
          "tgn:7007521",
          "tgn:7029392"
        ],
        "placetype": [
          "aat:300008850"
        ],
        "id": 2253650,
        "name:xx": "Cook Point"
      }
    },
    {
      "geometry": {
        "type": "Point",
        "coordinates": [
          -77.35,
          42.7
        ]
      },
      "type": "Feature",
      "properties": {
        "hierarchy": [
          "tgn:2253651",
          "tgn:1000001",
          "tgn:7012149",
          "tgn:1002747",
          "tgn:7007568",
          "tgn:7029392"
        ],
        "placetype": [
          "aat:300008850"
        ],
        "id": 2253651,
        "name:xx": "Cook Point"
      }
    },
    {
      "geometry": {
        "type": "Point",
        "coordinates": [
          -76.2667,
          38.6
        ]
      },
      "type": "Feature",
      "properties": {
        "hierarchy": [
          "tgn:2253652",
          "tgn:1002338",
          "tgn:1000001",
          "tgn:7012149",
          "tgn:7007516",
          "tgn:7029392"
        ],
        "placetype": [
          "aat:300132316"
        ],
        "id": 2253652,
        "name:xx": "Cook Point Cove"
      }
    },
    {
      "geometry": {
        "type": "Point",
        "coordinates": [
          -86.05,
          30.9833
        ]
      },
      "type": "Feature",
      "properties": {
        "hierarchy": [
          "tgn:2253653",
          "tgn:7002659",
          "tgn:1000001",
          "tgn:7012149",
          "tgn:2000030",
          "tgn:7029392"
        ],
        "placetype": [
          "aat:300008680"
        ],
        "id": 2253653,
        "name:xx": "Cook Pond"
      }
    },
    {
      "geometry": {
        "type": "Point",
        "coordinates": [
          -113.3833,
          36.45
        ]
      },
      "type": "Feature",
      "properties": {
        "hierarchy": [
          "tgn:2253654",
          "tgn:1000001",
          "tgn:7006451",
          "tgn:7012149",
          "tgn:2000098",
          "tgn:7029392"
        ],
        "placetype": [
          "aat:300006191"
        ],
        "id": 2253654,
        "name:xx": "Cook Pond"
      }
    },
    {
      "geometry": {
        "type": "Point",
        "coordinates": [
          -84.5667,
          31.15
        ]
      },
      "type": "Feature",
      "properties": {
        "hierarchy": [
          "tgn:2253655",
          "tgn:1000001",
          "tgn:7012149",
          "tgn:2000391",
          "tgn:7007248",
          "tgn:7029392"
        ],
        "placetype": [
          "aat:300008680"
        ],
        "id": 2253655,
        "name:xx": "Cook Pond"
      }
    },
    {
      "geometry": {
        "type": "Point",
        "coordinates": [
          -84.4667,
          32.3667
        ]
      },
      "type": "Feature",
      "properties": {
        "hierarchy": [
          "tgn:2253656",
          "tgn:1000001",
          "tgn:7012149",
          "tgn:2000389",
          "tgn:7007248",
          "tgn:7029392"
        ],
        "placetype": [
          "aat:300008680"
        ],
        "id": 2253656,
        "name:xx": "Cook Pond"
      }
    },
    {
      "geometry": {
        "type": "Point",
        "coordinates": [
          -71.85,
          42.2833
        ]
      },
      "type": "Feature",
      "properties": {
        "hierarchy": [
          "tgn:2253657",
          "tgn:1000001",
          "tgn:7012149",
          "tgn:1003038",
          "tgn:7007517",
          "tgn:7029392"
        ],
        "placetype": [
          "aat:300006191"
        ],
        "id": 2253657,
        "name:xx": "Cook Pond"
      }
    },
    {
      "geometry": {
        "type": "Point",
        "coordinates": [
          -72.05,
          42.5167
        ]
      },
      "type": "Feature",
      "properties": {
        "hierarchy": [
          "tgn:2253658",
          "tgn:1000001",
          "tgn:7012149",
          "tgn:1003038",
          "tgn:7007517",
          "tgn:7029392"
        ],
        "placetype": [
          "aat:300008680"
        ],
        "id": 2253658,
        "name:xx": "Cook Pond"
      }
    },
    {
      "geometry": {
        "type": "Point",
        "coordinates": [
          -71.1667,
          41.6667
        ]
      },
      "type": "Feature",
      "properties": {
        "hierarchy": [
          "tgn:2253659",
          "tgn:1000001",
          "tgn:7012149",
          "tgn:7029392"
        ],
        "placetype": [
          "aat:300008680"
        ],
        "id": 2253659,
        "name:xx": "Cook Pond"
      }
    }
  ]
}
