{
  "geometry": {
    "type": "Point",
    "coordinates": [
      -104.5167,
      42.0167
    ]
  },
  "type": "Feature",
  "properties": {
    "hierarchy": [
      "tgn:2356867",
      "tgn:1000001",
      "tgn:7012149",
      "tgn:7029392"
    ],
    "placetype": [
      "aat:300386845"
    ],
    "id": 2356867,
    "name:xx": "Goshen Hole"
  }
}
