{
  "geometry": {
    "type": "Point",
    "coordinates": [
      -104.2167,
      37.8167
    ]
  },
  "type": "Feature",
  "properties": {
    "hierarchy": [
      "tgn:2519128",
      "tgn:1000001",
      "tgn:7012149",
      "tgn:7007158",
      "tgn:2000242",
      "tgn:7029392"
    ],
    "placetype": [
      "aat:300006191"
    ],
    "id": 2519128,
    "name:xx": "Mobley Reservoir"
  }
}
