{
  "geometry": {
    "type": "Point",
    "coordinates": [
      -83.5333,
      42.9333
    ]
  },
  "type": "Feature",
  "properties": {
    "hierarchy": [
      "tgn:2051161",
      "tgn:1000001",
      "tgn:7012149",
      "tgn:1002406",
      "tgn:7007520",
      "tgn:7029392"
    ],
    "placetype": [
      "aat:300008347"
    ],
    "id": 2051161,
    "name:xx": "Atlas"
  }
}
