{
  "type": "FeatureCollection",
  "features": [
    {
      "geometry": {
        "type": "Point",
        "coordinates": [
          -91.3167,
          46.0167
        ]
      },
      "type": "Feature",
      "properties": {
        "hierarchy": [
          "tgn:2392250",
          "tgn:1000001",
          "tgn:7012149",
          "tgn:2002353",
          "tgn:7007922",
          "tgn:7029392"
        ],
        "placetype": [
          "aat:300132316"
        ],
        "id": 2392250,
        "name:xx": "Hinton Bay"
      }
    },
    {
      "geometry": {
        "type": "Point",
        "coordinates": [
          -84.65,
          32.9833
        ]
      },
      "type": "Feature",
      "properties": {
        "hierarchy": [
          "tgn:2392251",
          "tgn:1000001",
          "tgn:7012149",
          "tgn:2000390",
          "tgn:7007248",
          "tgn:7029392"
        ],
        "placetype": [
          "aat:300008699"
        ],
        "id": 2392251,
        "name:xx": "Hinton Branch"
      }
    },
    {
      "geometry": {
        "type": "Point",
        "coordinates": [
          -86.2833,
          36.65
        ]
      },
      "type": "Feature",
      "properties": {
        "hierarchy": [
          "tgn:2392252",
          "tgn:2000766",
          "tgn:1000001",
          "tgn:7012149",
          "tgn:7007255",
          "tgn:7029392"
        ],
        "placetype": [
          "aat:300008699"
        ],
        "id": 2392252,
        "name:xx": "Hinton Branch"
      }
    },
    {
      "geometry": {
        "type": "Point",
        "coordinates": [
          -84,
          37.6333
        ]
      },
      "type": "Feature",
      "properties": {
        "hierarchy": [
          "tgn:2392253",
          "tgn:1000001",
          "tgn:7012149",
          "tgn:2000788",
          "tgn:7007255",
          "tgn:7029392"
        ],
        "placetype": [
          "aat:300008699"
        ],
        "id": 2392253,
        "name:xx": "Hinton Branch"
      }
    },
    {
      "geometry": {
        "type": "Point",
        "coordinates": [
          -110.3,
          33.0333
        ]
      },
      "type": "Feature",
      "properties": {
        "hierarchy": [
          "tgn:2392254",
          "tgn:1000001",
          "tgn:7006451",
          "tgn:2000094",
          "tgn:7012149",
          "tgn:7029392"
        ],
        "placetype": [
          "aat:300008761"
        ],
        "id": 2392254,
        "name:xx": "Hinton Canyon"
      }
    },
    {
      "geometry": {
        "type": "Point",
        "coordinates": [
          -110.8833,
          33.8333
        ]
      },
      "type": "Feature",
      "properties": {
        "hierarchy": [
          "tgn:2392255",
          "tgn:1000001",
          "tgn:7006451",
          "tgn:2000093",
          "tgn:7012149",
          "tgn:7029392"
        ],
        "placetype": [
          "aat:300008706"
        ],
        "id": 2392255,
        "name:xx": "Hinton Creek"
      }
    },
    {
      "geometry": {
        "type": "Point",
        "coordinates": [
          -90.7667,
          34.9667
        ]
      },
      "type": "Feature",
      "properties": {
        "hierarchy": [
          "tgn:2392256",
          "tgn:1000001",
          "tgn:7016172",
          "tgn:7012149",
          "tgn:2000166",
          "tgn:7029392"
        ],
        "placetype": [
          "aat:300008706"
        ],
        "id": 2392256,
        "name:xx": "Hinton Creek"
      }
    },
    {
      "geometry": {
        "type": "Point",
        "coordinates": [
          -84.4333,
          34.4833
        ]
      },
      "type": "Feature",
      "properties": {
        "hierarchy": [
          "tgn:2392257",
          "tgn:1000001",
          "tgn:7012149",
          "tgn:2000403",
          "tgn:7007248",
          "tgn:7029392"
        ],
        "placetype": [
          "aat:300008706"
        ],
        "id": 2392257,
        "name:xx": "Hinton Creek"
      }
    },
    {
      "geometry": {
        "type": "Point",
        "coordinates": [
          -85.3667,
          34.3167
        ]
      },
      "type": "Feature",
      "properties": {
        "hierarchy": [
          "tgn:2392258",
          "tgn:1000001",
          "tgn:2000318",
          "tgn:7012149",
          "tgn:7007248",
          "tgn:7029392"
        ],
        "placetype": [
          "aat:300008706"
        ],
        "id": 2392258,
        "name:xx": "Hinton Creek"
      }
    },
    {
      "geometry": {
        "type": "Point",
        "coordinates": [
          -84.6333,
          32.6667
        ]
      },
      "type": "Feature",
      "properties": {
        "hierarchy": [
          "tgn:2392259",
          "tgn:1000001",
          "tgn:7012149",
          "tgn:7007248",
          "tgn:7029392"
        ],
        "placetype": [
          "aat:300008706"
        ],
        "id": 2392259,
        "name:xx": "Hinton Creek"
      }
    }
  ]
}
