{
  "geometry": {
    "type": "Point",
    "coordinates": [
      88.2167,
      57.3333
    ]
  },
  "type": "Feature",
  "properties": {
    "hierarchy": [
      "tgn:1060211",
      "tgn:1000004",
      "tgn:7011604",
      "tgn:7018214",
      "tgn:7002435",
      "tgn:7029392"
    ],
    "placetype": [
      "aat:300008347"
    ],
    "id": 1060211,
    "name:xx": "Tegul'det"
  }
}
