{
  "type": "FeatureCollection",
  "features": [
    {
      "geometry": {
        "type": "Point",
        "coordinates": [
          -100.916667,
          22.666667
        ]
      },
      "type": "Feature",
      "properties": {
        "hierarchy": [
          "tgn:7379140",
          "tgn:1000001",
          "tgn:7005594",
          "tgn:7005560",
          "tgn:7029392"
        ],
        "placetype": [
          "aat:300008347"
        ],
        "id": 7379140,
        "name:xx": "Mezquite"
      }
    },
    {
      "geometry": {
        "type": "Point",
        "coordinates": [
          -101.216667,
          21.933333
        ]
      },
      "type": "Feature",
      "properties": {
        "hierarchy": [
          "tgn:7379141",
          "tgn:1000001",
          "tgn:7005594",
          "tgn:7005560",
          "tgn:7029392"
        ],
        "placetype": [
          "aat:300008347"
        ],
        "id": 7379141,
        "name:xx": "Mezquite"
      }
    },
    {
      "geometry": {
        "type": "Point",
        "coordinates": [
          -101.466667,
          21.716667
        ]
      },
      "type": "Feature",
      "properties": {
        "hierarchy": [
          "tgn:7379142",
          "tgn:7005586",
          "tgn:1000001",
          "tgn:7005560",
          "tgn:7029392"
        ],
        "placetype": [
          "aat:300008347"
        ],
        "id": 7379142,
        "name:xx": "Mezquite"
      }
    },
    {
      "geometry": {
        "type": "Point",
        "coordinates": [
          -99.283333,
          20.883333
        ]
      },
      "type": "Feature",
      "properties": {
        "hierarchy": [
          "tgn:7379143",
          "tgn:7005587",
          "tgn:1000001",
          "tgn:7005560",
          "tgn:7029392"
        ],
        "placetype": [
          "aat:300008347"
        ],
        "id": 7379143,
        "name:xx": "Mezquite"
      }
    },
    {
      "geometry": {
        "type": "Point",
        "coordinates": [
          -95.966667,
          16.466667
        ]
      },
      "type": "Feature",
      "properties": {
        "hierarchy": [
          "tgn:7379144",
          "tgn:1000001",
          "tgn:7005591",
          "tgn:7005560",
          "tgn:7029392"
        ],
        "placetype": [
          "aat:300008347"
        ],
        "id": 7379144,
        "name:xx": "Mezquite"
      }
    },
    {
      "geometry": {
        "type": "Point",
        "coordinates": [
          -109.033333,
          27.383333
        ]
      },
      "type": "Feature",
      "properties": {
        "hierarchy": [
          "tgn:7379145",
          "tgn:1000001",
          "tgn:1001960",
          "tgn:7005560",
          "tgn:7029392"
        ],
        "placetype": [
          "aat:300387007"
        ],
        "id": 7379145,
        "name:xx": "Mezquite"
      }
    },
    {
      "geometry": {
        "type": "Point",
        "coordinates": [
          -104.266667,
          21.15
        ]
      },
      "type": "Feature",
      "properties": {
        "hierarchy": [
          "tgn:7379146",
          "tgn:1000001",
          "tgn:1001906",
          "tgn:7005560",
          "tgn:7029392"
        ],
        "placetype": [
          "aat:300008347"
        ],
        "id": 7379146,
        "name:xx": "Mezquitán"
      }
    },
    {
      "geometry": {
        "type": "Point",
        "coordinates": [
          -104.316667,
          19.816667
        ]
      },
      "type": "Feature",
      "properties": {
        "hierarchy": [
          "tgn:7379147",
          "tgn:7005586",
          "tgn:1000001",
          "tgn:7005560",
          "tgn:7029392"
        ],
        "placetype": [
          "aat:300008347"
        ],
        "id": 7379147,
        "name:xx": "Mezquitán"
      }
    },
    {
      "geometry": {
        "type": "Point",
        "coordinates": [
          -108.783333,
          26.15
        ]
      },
      "type": "Feature",
      "properties": {
        "hierarchy": [
          "tgn:7379148",
          "tgn:1000001",
          "tgn:7005595",
          "tgn:7005560",
          "tgn:7029392"
        ],
        "placetype": [
          "aat:300008347"
        ],
        "id": 7379148,
        "name:xx": "Mezquitalito"
      }
    },
    {
      "geometry": {
        "type": "Point",
        "coordinates": [
          -111,
          29.066667
        ]
      },
      "type": "Feature",
      "properties": {
        "hierarchy": [
          "tgn:7379149",
          "tgn:1000001",
          "tgn:1001960",
          "tgn:7005560",
          "tgn:7029392"
        ],
        "placetype": [
          "aat:300008347"
        ],
        "id": 7379149,
        "name:xx": "Mezquital del Oro"
      }
    }
  ]
}
