{
  "geometry": {
    "type": "Point",
    "coordinates": [
      -85.75,
      33.4833
    ]
  },
  "type": "Feature",
  "properties": {
    "hierarchy": [
      "tgn:2706393",
      "tgn:7002659",
      "tgn:1000001",
      "tgn:7012149",
      "tgn:7029392"
    ],
    "placetype": [
      "aat:300008699"
    ],
    "id": 2706393,
    "name:xx": "Swan Branch"
  }
}
