{
  "type": "FeatureCollection",
  "features": [
    {
      "geometry": {
        "type": "Point",
        "coordinates": [
          -68.933333,
          -26.983333
        ]
      },
      "type": "Feature",
      "properties": {
        "hierarchy": [
          "tgn:7317910",
          "tgn:1001630",
          "tgn:1000049",
          "tgn:1000002",
          "tgn:7029392"
        ],
        "placetype": [
          "aat:300259572"
        ],
        "id": 7317910,
        "name:xx": "Colorado, Portezuelo"
      }
    },
    {
      "geometry": {
        "type": "Point",
        "coordinates": [
          -70.416667,
          -25.283333
        ]
      },
      "type": "Feature",
      "properties": {
        "hierarchy": [
          "tgn:7317911",
          "tgn:7016598",
          "tgn:1000049",
          "tgn:1000002",
          "tgn:7029392"
        ],
        "placetype": [
          "aat:300006207"
        ],
        "id": 7317911,
        "name:xx": "Pique Colorado"
      }
    },
    {
      "geometry": {
        "type": "Point",
        "coordinates": [
          -71.483333,
          -34.783333
        ]
      },
      "type": "Feature",
      "properties": {
        "hierarchy": [
          "tgn:7317912",
          "tgn:1001695",
          "tgn:1000049",
          "tgn:1000002",
          "tgn:7029392"
        ],
        "placetype": [
          "aat:300008795"
        ],
        "id": 7317912,
        "name:xx": "Colorado, Morro"
      }
    },
    {
      "geometry": {
        "type": "Point",
        "coordinates": [
          -71.166667,
          -33.3
        ]
      },
      "type": "Feature",
      "properties": {
        "hierarchy": [
          "tgn:7317913",
          "tgn:1001708",
          "tgn:1000049",
          "tgn:1000002",
          "tgn:7029392"
        ],
        "placetype": [
          "aat:300008795"
        ],
        "id": 7317913,
        "name:xx": "Colorado, Morro"
      }
    },
    {
      "geometry": {
        "type": "Point",
        "coordinates": [
          -70.4,
          -32.416667
        ]
      },
      "type": "Feature",
      "properties": {
        "hierarchy": [
          "tgn:7317914",
          "tgn:1001768",
          "tgn:1000049",
          "tgn:1000002",
          "tgn:7029392"
        ],
        "placetype": [
          "aat:300008795"
        ],
        "id": 7317914,
        "name:xx": "Colorado, Morro"
      }
    },
    {
      "geometry": {
        "type": "Point",
        "coordinates": [
          -71.4,
          -33.816667
        ]
      },
      "type": "Feature",
      "properties": {
        "hierarchy": [
          "tgn:7317915",
          "tgn:1001708",
          "tgn:1000049",
          "tgn:1000002",
          "tgn:7029392"
        ],
        "placetype": [
          "aat:300008777"
        ],
        "id": 7317915,
        "name:xx": "Colorado, Morro"
      }
    },
    {
      "geometry": {
        "type": "Point",
        "coordinates": [
          -71.116667,
          -33.2
        ]
      },
      "type": "Feature",
      "properties": {
        "hierarchy": [
          "tgn:7317916",
          "tgn:1001768",
          "tgn:1000049",
          "tgn:1000002",
          "tgn:7029392"
        ],
        "placetype": [
          "aat:300008777"
        ],
        "id": 7317916,
        "name:xx": "Colorado, Morro"
      }
    },
    {
      "geometry": {
        "type": "Point",
        "coordinates": [
          -69.883333,
          -21.15
        ]
      },
      "type": "Feature",
      "properties": {
        "hierarchy": [
          "tgn:7317917",
          "tgn:7002464",
          "tgn:1000049",
          "tgn:1000002",
          "tgn:7029392"
        ],
        "placetype": [
          "aat:300008795"
        ],
        "id": 7317917,
        "name:xx": "Colorado, Morrillo"
      }
    },
    {
      "geometry": {
        "type": "Point",
        "coordinates": [
          -70.366667,
          -32.366667
        ]
      },
      "type": "Feature",
      "properties": {
        "hierarchy": [
          "tgn:7317918",
          "tgn:1001768",
          "tgn:1000049",
          "tgn:1000002",
          "tgn:7029392"
        ],
        "placetype": [
          "aat:300008795"
        ],
        "id": 7317918,
        "name:xx": "Colorado, Monte"
      }
    },
    {
      "geometry": {
        "type": "Point",
        "coordinates": [
          -71.85,
          -44.733333
        ]
      },
      "type": "Feature",
      "properties": {
        "hierarchy": [
          "tgn:7317919",
          "tgn:1001623",
          "tgn:1000049",
          "tgn:1000002",
          "tgn:7029392"
        ],
        "placetype": [
          "aat:300008876"
        ],
        "id": 7317919,
        "name:xx": "Colorado, Mallín"
      }
    }
  ]
}
