{
  "geometry": {
    "type": "Point",
    "coordinates": [
      -91.05,
      31.6333
    ]
  },
  "type": "Feature",
  "properties": {
    "hierarchy": [
      "tgn:2132109",
      "tgn:1000001",
      "tgn:7012149",
      "tgn:2001117",
      "tgn:7007522",
      "tgn:7029392"
    ],
    "placetype": [
      "aat:300006191"
    ],
    "id": 2132109,
    "name:xx": "American Legion Lake"
  }
}
