{
  "geometry": {
    "type": "Point",
    "coordinates": [
      -122.3333,
      47.7333
    ]
  },
  "type": "Feature",
  "properties": {
    "hierarchy": [
      "tgn:2338433",
      "tgn:1000001",
      "tgn:7012149",
      "tgn:7018871",
      "tgn:7007920",
      "tgn:7029392"
    ],
    "placetype": [
      "aat:300008347"
    ],
    "id": 2338433,
    "name:xx": "Foy"
  }
}
