{
  "geometry": {
    "type": "Point",
    "coordinates": [
      -80.0833,
      39.8667
    ]
  },
  "type": "Feature",
  "properties": {
    "hierarchy": [
      "tgn:2341789",
      "tgn:1000001",
      "tgn:7012149",
      "tgn:2001724",
      "tgn:7007710",
      "tgn:7029392"
    ],
    "placetype": [
      "aat:300008699"
    ],
    "id": 2341789,
    "name:xx": "Frosty Run"
  }
}
