{
  "geometry": {
    "type": "Point",
    "coordinates": [
      -116.4833,
      46.9333
    ]
  },
  "type": "Feature",
  "properties": {
    "hierarchy": [
      "tgn:2709988",
      "tgn:1000001",
      "tgn:7012149",
      "tgn:2000480",
      "tgn:7007250",
      "tgn:7029392"
    ],
    "placetype": [
      "aat:300008706"
    ],
    "id": 2709988,
    "name:xx": "Talapus Creek"
  }
}
