{
  "geometry": {
    "type": "Point",
    "coordinates": [
      -90.95,
      39.1333
    ]
  },
  "type": "Feature",
  "properties": {
    "hierarchy": [
      "tgn:2701016",
      "tgn:1000001",
      "tgn:7012149",
      "tgn:1002598",
      "tgn:7007523",
      "tgn:7029392"
    ],
    "placetype": [
      "aat:300008706"
    ],
    "id": 2701016,
    "name:xx": "Sugar Creek"
  }
}
