{
  "type": "FeatureCollection",
  "features": [
    {
      "geometry": {
        "type": "Point",
        "coordinates": [
          0.183333,
          51.1
        ]
      },
      "type": "Feature",
      "properties": {
        "hierarchy": [
          "tgn:4004600",
          "tgn:7002445",
          "tgn:1000003",
          "tgn:7008129",
          "tgn:7008591",
          "tgn:7029392"
        ],
        "placetype": [
          "aat:300008347"
        ],
        "name:en": "Groombridge",
        "id": 4004600
      }
    },
    {
      "geometry": {
        "type": "Point",
        "coordinates": [
          13.7333,
          54.0833
        ]
      },
      "type": "Feature",
      "properties": {
        "hierarchy": [
          "tgn:4004602",
          "tgn:1000003",
          "tgn:7000094",
          "tgn:7000084",
          "tgn:7029392"
        ],
        "placetype": [
          "aat:300008347"
        ],
        "id": 4004602,
        "name:xx": "Gross Ernsthof"
      }
    },
    {
      "geometry": {
        "type": "Point",
        "coordinates": [
          16.626,
          48.414
        ]
      },
      "type": "Feature",
      "properties": {
        "hierarchy": [
          "tgn:4004604",
          "tgn:7003025",
          "tgn:1000003",
          "tgn:1000062",
          "tgn:7029392"
        ],
        "placetype": [
          "aat:300008347"
        ],
        "id": 4004604,
        "name:xx": "Gross-Schweinbarth"
      }
    }
  ]
}
