{
  "geometry": {
    "type": "Point",
    "coordinates": [
      -87.65,
      45.3833
    ]
  },
  "type": "Feature",
  "properties": {
    "hierarchy": [
      "tgn:2456929",
      "tgn:1000001",
      "tgn:7012149",
      "tgn:2000978",
      "tgn:7007520",
      "tgn:7029392"
    ],
    "placetype": [
      "aat:300008706"
    ],
    "id": 2456929,
    "name:xx": "Little Kelley Creek"
  }
}
