{
  "geometry": {
    "type": "Point",
    "coordinates": [
      -6.7333,
      53.4833
    ]
  },
  "type": "Feature",
  "properties": {
    "hierarchy": [
      "tgn:1043020",
      "tgn:7001199",
      "tgn:7003491",
      "tgn:1000003",
      "tgn:1000078",
      "tgn:7029392"
    ],
    "placetype": [
      "aat:300008347"
    ],
    "id": 1043020,
    "name:xx": "Summerhill"
  }
}
