{
  "geometry": {
    "type": "Point",
    "coordinates": [
      -81.25,
      26.1833
    ]
  },
  "type": "Feature",
  "properties": {
    "hierarchy": [
      "tgn:2377416",
      "tgn:1000001",
      "tgn:1002289",
      "tgn:7012149",
      "tgn:7007240",
      "tgn:7029392"
    ],
    "placetype": [
      "aat:300008905"
    ],
    "id": 2377416,
    "name:xx": "Harold Strand"
  }
}
