{
  "geometry": {
    "type": "Point",
    "coordinates": [
      -1.2667,
      47.0833
    ]
  },
  "type": "Feature",
  "properties": {
    "hierarchy": [
      "tgn:1032701",
      "tgn:1000003",
      "tgn:7002893",
      "tgn:1000070",
      "tgn:7029392"
    ],
    "placetype": [
      "aat:300008347"
    ],
    "id": 1032701,
    "name:xx": "Clisson"
  }
}
