{
  "geometry": {
    "type": "Point",
    "coordinates": [
      150.7333,
      -34.0333
    ]
  },
  "type": "Feature",
  "properties": {
    "hierarchy": [
      "tgn:1097738",
      "tgn:7000490",
      "tgn:1000006",
      "tgn:7001828",
      "tgn:7029392"
    ],
    "placetype": [
      "aat:300008347"
    ],
    "id": 1097738,
    "name:xx": "Narellan"
  }
}
