{
  "geometry": {
    "type": "Point",
    "coordinates": [
      -90.1833,
      45.8333
    ]
  },
  "type": "Feature",
  "properties": {
    "hierarchy": [
      "tgn:2593353",
      "tgn:1000001",
      "tgn:7012149",
      "tgn:2002348",
      "tgn:7007922",
      "tgn:7029392"
    ],
    "placetype": [
      "aat:300008706"
    ],
    "id": 2593353,
    "name:xx": "Popple Creek"
  }
}
