{
  "type": "FeatureCollection",
  "features": [
    {
      "geometry": {
        "type": "Point",
        "coordinates": [
          5.7,
          49.6
        ]
      },
      "type": "Feature",
      "properties": {
        "hierarchy": [
          "tgn:7256910",
          "tgn:7003465",
          "tgn:1000003",
          "tgn:1000063",
          "tgn:4012014",
          "tgn:7029392"
        ],
        "placetype": [
          "aat:300008863"
        ],
        "id": 7256910,
        "name:xx": "Willancourt, Bois de"
      }
    },
    {
      "geometry": {
        "type": "Point",
        "coordinates": [
          5.7,
          49.583333
        ]
      },
      "type": "Feature",
      "properties": {
        "hierarchy": [
          "tgn:7256911",
          "tgn:7003465",
          "tgn:1000003",
          "tgn:1000063",
          "tgn:4012014",
          "tgn:7029392"
        ],
        "placetype": [
          "aat:300008347"
        ],
        "id": 7256911,
        "name:xx": "Willancourt"
      }
    },
    {
      "geometry": {
        "type": "Point",
        "coordinates": [
          4.3,
          50.583333
        ]
      },
      "type": "Feature",
      "properties": {
        "hierarchy": [
          "tgn:7256912",
          "tgn:7007877",
          "tgn:1000003",
          "tgn:1000063",
          "tgn:4012014",
          "tgn:7029392"
        ],
        "placetype": [
          "aat:300000206"
        ],
        "id": 7256912,
        "name:xx": "Willambroux"
      }
    },
    {
      "geometry": {
        "type": "Point",
        "coordinates": [
          4.983333,
          51.133333
        ]
      },
      "type": "Feature",
      "properties": {
        "hierarchy": [
          "tgn:7256913",
          "tgn:7003456",
          "tgn:1000003",
          "tgn:1000063",
          "tgn:7018236",
          "tgn:7029392"
        ],
        "placetype": [
          "aat:300008347"
        ],
        "id": 7256913,
        "name:xx": "Willaars"
      }
    },
    {
      "geometry": {
        "type": "Point",
        "coordinates": [
          3.966667,
          50.7
        ]
      },
      "type": "Feature",
      "properties": {
        "hierarchy": [
          "tgn:7256914",
          "tgn:7003457",
          "tgn:1000003",
          "tgn:1000063",
          "tgn:7018236",
          "tgn:7029392"
        ],
        "placetype": [
          "aat:300000206"
        ],
        "id": 7256914,
        "name:xx": "Wilgendam"
      }
    },
    {
      "geometry": {
        "type": "Point",
        "coordinates": [
          4.465644,
          51.425532
        ]
      },
      "type": "Feature",
      "properties": {
        "hierarchy": [
          "tgn:7256915",
          "tgn:7003456",
          "tgn:1000003",
          "tgn:1000063",
          "tgn:7018236",
          "tgn:7029392"
        ],
        "placetype": [
          "aat:300008347"
        ],
        "id": 7256915,
        "name:xx": "Wildert"
      }
    },
    {
      "geometry": {
        "type": "Point",
        "coordinates": [
          5.033333,
          51.383333
        ]
      },
      "type": "Feature",
      "properties": {
        "hierarchy": [
          "tgn:7256916",
          "tgn:7003456",
          "tgn:1000003",
          "tgn:1000063",
          "tgn:7018236",
          "tgn:7029392"
        ],
        "placetype": [
          "aat:300008347"
        ],
        "id": 7256916,
        "name:xx": "Wildert"
      }
    },
    {
      "geometry": {
        "type": "Point",
        "coordinates": [
          4.759052,
          50.843743
        ]
      },
      "type": "Feature",
      "properties": {
        "hierarchy": [
          "tgn:7256917",
          "tgn:7018239",
          "tgn:1000003",
          "tgn:1000063",
          "tgn:7018236",
          "tgn:7029392"
        ],
        "placetype": [
          "aat:300005567"
        ],
        "id": 7256917,
        "name:xx": "Kasteel Wilderhof"
      }
    },
    {
      "geometry": {
        "type": "Point",
        "coordinates": [
          6.65,
          52.9
        ]
      },
      "type": "Feature",
      "properties": {
        "hierarchy": [
          "tgn:7256919",
          "tgn:7003614",
          "tgn:1000003",
          "tgn:7016845",
          "tgn:7029392"
        ],
        "placetype": [
          "aat:300008178"
        ],
        "name:nl": "Blankeveen",
        "id": 7256919
      }
    }
  ]
}
