{
  "geometry": {
    "type": "Point",
    "coordinates": [
      14.2833,
      47.1333
    ]
  },
  "type": "Feature",
  "properties": {
    "hierarchy": [
      "tgn:1133531",
      "tgn:7003028",
      "tgn:1000003",
      "tgn:1000062",
      "tgn:7029392"
    ],
    "placetype": [
      "aat:300008706"
    ],
    "id": 1133531,
    "name:xx": "Katschbach"
  }
}
