{
  "geometry": {
    "type": "Point",
    "coordinates": [
      -83.0667,
      38.7167
    ]
  },
  "type": "Feature",
  "properties": {
    "hierarchy": [
      "tgn:2197159",
      "tgn:1000001",
      "tgn:7012149",
      "tgn:1002877",
      "tgn:7007706",
      "tgn:7029392"
    ],
    "placetype": [
      "aat:300008699"
    ],
    "id": 2197159,
    "name:xx": "Brouse Run"
  }
}
