{
  "geometry": {
    "type": "Point",
    "coordinates": [
      -74.7667,
      44.4167
    ]
  },
  "type": "Feature",
  "properties": {
    "hierarchy": [
      "tgn:2248306",
      "tgn:1000001",
      "tgn:7012149",
      "tgn:7016021",
      "tgn:7007568",
      "tgn:7029392"
    ],
    "placetype": [
      "aat:300008680"
    ],
    "id": 2248306,
    "name:xx": "Cold Pond"
  }
}
