{
  "geometry": {
    "type": "Point",
    "coordinates": [
      37.4167,
      48.5667
    ]
  },
  "type": "Feature",
  "properties": {
    "hierarchy": [
      "tgn:7023883",
      "tgn:7012076",
      "tgn:1000003",
      "tgn:7006660",
      "tgn:7029392"
    ],
    "placetype": [
      "aat:300008347",
      "aat:300008375"
    ],
    "id": 7023883,
    "name:xx": "Novohryhorivka"
  }
}
