{
  "geometry": {
    "type": "Point",
    "coordinates": [
      -105.0333,
      41.1667
    ]
  },
  "type": "Feature",
  "properties": {
    "hierarchy": [
      "tgn:2663423",
      "tgn:1000001",
      "tgn:7012149",
      "tgn:2002375",
      "tgn:7007923",
      "tgn:7029392"
    ],
    "placetype": [
      "aat:300008347"
    ],
    "id": 2663423,
    "name:xx": "Silver Crown"
  }
}
