{
  "type": "FeatureCollection",
  "features": [
    {
      "geometry": {
        "type": "Point",
        "coordinates": [
          -107.55,
          34.3
        ]
      },
      "type": "Feature",
      "properties": {
        "hierarchy": [
          "tgn:2466940",
          "tgn:1000001",
          "tgn:7012149",
          "tgn:2001456",
          "tgn:7007566",
          "tgn:7029392"
        ],
        "placetype": [
          "aat:300008761"
        ],
        "id": 2466940,
        "name:xx": "Long Canyon"
      }
    },
    {
      "geometry": {
        "type": "Point",
        "coordinates": [
          -104.0333,
          34.4833
        ]
      },
      "type": "Feature",
      "properties": {
        "hierarchy": [
          "tgn:2466941",
          "tgn:1000001",
          "tgn:7019560",
          "tgn:7012149",
          "tgn:7007566",
          "tgn:7029392"
        ],
        "placetype": [
          "aat:300008761"
        ],
        "id": 2466941,
        "name:xx": "Long Canyon"
      }
    },
    {
      "geometry": {
        "type": "Point",
        "coordinates": [
          -108.9333,
          31.8833
        ]
      },
      "type": "Feature",
      "properties": {
        "hierarchy": [
          "tgn:2466942",
          "tgn:1000001",
          "tgn:7012149",
          "tgn:2001440",
          "tgn:7007566",
          "tgn:7029392"
        ],
        "placetype": [
          "aat:300008761"
        ],
        "id": 2466942,
        "name:xx": "Long Canyon"
      }
    },
    {
      "geometry": {
        "type": "Point",
        "coordinates": [
          -120.05,
          42.05
        ]
      },
      "type": "Feature",
      "properties": {
        "hierarchy": [
          "tgn:2466943",
          "tgn:1000001",
          "tgn:7012149",
          "tgn:2001715",
          "tgn:7007708",
          "tgn:7029392"
        ],
        "placetype": [
          "aat:300008761"
        ],
        "id": 2466943,
        "name:xx": "Long Canyon"
      }
    },
    {
      "geometry": {
        "type": "Point",
        "coordinates": [
          -119.3167,
          45.05
        ]
      },
      "type": "Feature",
      "properties": {
        "hierarchy": [
          "tgn:2466944",
          "tgn:1000001",
          "tgn:7012149",
          "tgn:2001719",
          "tgn:7007708",
          "tgn:7029392"
        ],
        "placetype": [
          "aat:300008761"
        ],
        "id": 2466944,
        "name:xx": "Long Canyon"
      }
    },
    {
      "geometry": {
        "type": "Point",
        "coordinates": [
          -118.7,
          45.4167
        ]
      },
      "type": "Feature",
      "properties": {
        "hierarchy": [
          "tgn:2466945",
          "tgn:1000001",
          "tgn:7012149",
          "tgn:2001720",
          "tgn:7007708",
          "tgn:7029392"
        ],
        "placetype": [
          "aat:300008761"
        ],
        "id": 2466945,
        "name:xx": "Long Canyon"
      }
    },
    {
      "geometry": {
        "type": "Point",
        "coordinates": [
          -118.1,
          43.2333
        ]
      },
      "type": "Feature",
      "properties": {
        "hierarchy": [
          "tgn:2466946",
          "tgn:1000001",
          "tgn:7012149",
          "tgn:2001718",
          "tgn:7007708",
          "tgn:7029392"
        ],
        "placetype": [
          "aat:300008761"
        ],
        "id": 2466946,
        "name:xx": "Long Canyon"
      }
    },
    {
      "geometry": {
        "type": "Point",
        "coordinates": [
          -122.5167,
          42.4333
        ]
      },
      "type": "Feature",
      "properties": {
        "hierarchy": [
          "tgn:2466947",
          "tgn:1000001",
          "tgn:7012149",
          "tgn:2001711",
          "tgn:7007708",
          "tgn:7029392"
        ],
        "placetype": [
          "aat:300008761"
        ],
        "id": 2466947,
        "name:xx": "Long Canyon"
      }
    },
    {
      "geometry": {
        "type": "Point",
        "coordinates": [
          -99.7,
          29.45
        ]
      },
      "type": "Feature",
      "properties": {
        "hierarchy": [
          "tgn:2466948",
          "tgn:1000001",
          "tgn:7012149",
          "tgn:2002087",
          "tgn:7007826",
          "tgn:7029392"
        ],
        "placetype": [
          "aat:300008761"
        ],
        "id": 2466948,
        "name:xx": "Long Canyon"
      }
    },
    {
      "geometry": {
        "type": "Point",
        "coordinates": [
          -100.5333,
          31.7833
        ]
      },
      "type": "Feature",
      "properties": {
        "hierarchy": [
          "tgn:2466949",
          "tgn:1000001",
          "tgn:7012149",
          "tgn:2001958",
          "tgn:7007826",
          "tgn:7029392"
        ],
        "placetype": [
          "aat:300008761"
        ],
        "id": 2466949,
        "name:xx": "Long Canyon"
      }
    }
  ]
}
