{
  "type": "FeatureCollection",
  "features": [
    {
      "geometry": {
        "type": "Point",
        "coordinates": [
          -83.05,
          36.3
        ]
      },
      "type": "Feature",
      "properties": {
        "hierarchy": [
          "tgn:2522700",
          "tgn:1000001",
          "tgn:7012149",
          "tgn:2001873",
          "tgn:7007825",
          "tgn:7029392"
        ],
        "placetype": [
          "aat:300008699"
        ],
        "id": 2522700,
        "name:xx": "Moore Branch"
      }
    },
    {
      "geometry": {
        "type": "Point",
        "coordinates": [
          -87.5667,
          36.3333
        ]
      },
      "type": "Feature",
      "properties": {
        "hierarchy": [
          "tgn:2522701",
          "tgn:1000001",
          "tgn:7012149",
          "tgn:7007825",
          "tgn:7029392"
        ],
        "placetype": [
          "aat:300008699"
        ],
        "id": 2522701,
        "name:xx": "Moore Branch"
      }
    },
    {
      "geometry": {
        "type": "Point",
        "coordinates": [
          -89,
          35
        ]
      },
      "type": "Feature",
      "properties": {
        "hierarchy": [
          "tgn:2522702",
          "tgn:1000001",
          "tgn:7012149",
          "tgn:2001871",
          "tgn:7007825",
          "tgn:7029392"
        ],
        "placetype": [
          "aat:300008699"
        ],
        "id": 2522702,
        "name:xx": "Moore Branch"
      }
    },
    {
      "geometry": {
        "type": "Point",
        "coordinates": [
          -83.3167,
          36
        ]
      },
      "type": "Feature",
      "properties": {
        "hierarchy": [
          "tgn:2522703",
          "tgn:1000001",
          "tgn:7012149",
          "tgn:2001881",
          "tgn:7007825",
          "tgn:7029392"
        ],
        "placetype": [
          "aat:300008699"
        ],
        "id": 2522703,
        "name:xx": "Moore Branch"
      }
    },
    {
      "geometry": {
        "type": "Point",
        "coordinates": [
          -84.0167,
          36.1167
        ]
      },
      "type": "Feature",
      "properties": {
        "hierarchy": [
          "tgn:2522704",
          "tgn:2001837",
          "tgn:1000001",
          "tgn:7012149",
          "tgn:7007825",
          "tgn:7029392"
        ],
        "placetype": [
          "aat:300008699"
        ],
        "id": 2522704,
        "name:xx": "Moore Branch"
      }
    },
    {
      "geometry": {
        "type": "Point",
        "coordinates": [
          -96.8833,
          30.3667
        ]
      },
      "type": "Feature",
      "properties": {
        "hierarchy": [
          "tgn:2522705",
          "tgn:1000001",
          "tgn:7012149",
          "tgn:1002584",
          "tgn:7007826",
          "tgn:7029392"
        ],
        "placetype": [
          "aat:300008699"
        ],
        "id": 2522705,
        "name:xx": "Moore Branch"
      }
    },
    {
      "geometry": {
        "type": "Point",
        "coordinates": [
          -95.1,
          32.6833
        ]
      },
      "type": "Feature",
      "properties": {
        "hierarchy": [
          "tgn:2522706",
          "tgn:1000001",
          "tgn:7012149",
          "tgn:1002966",
          "tgn:7007826",
          "tgn:7029392"
        ],
        "placetype": [
          "aat:300008699"
        ],
        "id": 2522706,
        "name:xx": "Moore Branch"
      }
    },
    {
      "geometry": {
        "type": "Point",
        "coordinates": [
          -94.1833,
          32.9333
        ]
      },
      "type": "Feature",
      "properties": {
        "hierarchy": [
          "tgn:2522707",
          "tgn:1000001",
          "tgn:7012149",
          "tgn:1002244",
          "tgn:7007826",
          "tgn:7029392"
        ],
        "placetype": [
          "aat:300008699"
        ],
        "id": 2522707,
        "name:xx": "Moore Branch"
      }
    },
    {
      "geometry": {
        "type": "Point",
        "coordinates": [
          -96.8167,
          30.65
        ]
      },
      "type": "Feature",
      "properties": {
        "hierarchy": [
          "tgn:2522708",
          "tgn:1000001",
          "tgn:7012149",
          "tgn:1002670",
          "tgn:7007826",
          "tgn:7029392"
        ],
        "placetype": [
          "aat:300008699"
        ],
        "id": 2522708,
        "name:xx": "Moore Branch"
      }
    },
    {
      "geometry": {
        "type": "Point",
        "coordinates": [
          -94.6167,
          31.9333
        ]
      },
      "type": "Feature",
      "properties": {
        "hierarchy": [
          "tgn:2522709",
          "tgn:1000001",
          "tgn:7012149",
          "tgn:1002839",
          "tgn:7007826",
          "tgn:7029392"
        ],
        "placetype": [
          "aat:300008699"
        ],
        "id": 2522709,
        "name:xx": "Moore Branch"
      }
    }
  ]
}
