{
  "geometry": {
    "type": "Point",
    "coordinates": [
      -96.1333,
      30.5833
    ]
  },
  "type": "Feature",
  "properties": {
    "hierarchy": [
      "tgn:2481153",
      "tgn:1000001",
      "tgn:7012149",
      "tgn:1002429",
      "tgn:7007826",
      "tgn:7029392"
    ],
    "placetype": [
      "aat:300008697"
    ],
    "id": 2481153,
    "name:xx": "Lamb Spring"
  }
}
