{
  "geometry": {
    "type": "Point",
    "coordinates": [
      -85.983,
      14.416
    ]
  },
  "type": "Feature",
  "properties": {
    "hierarchy": [
      "tgn:1124462",
      "tgn:1000715",
      "tgn:1000001",
      "tgn:7005554",
      "tgn:7029392"
    ],
    "placetype": [
      "aat:300008707"
    ],
    "id": 1124462,
    "name:xx": "Guayape, Río"
  }
}
