{
  "geometry": {
    "type": "Point",
    "coordinates": [
      -149.2667,
      64.9167
    ]
  },
  "type": "Feature",
  "properties": {
    "hierarchy": [
      "tgn:2706789",
      "tgn:7006450",
      "tgn:1000001",
      "tgn:7012149",
      "tgn:2000089",
      "tgn:7029392"
    ],
    "placetype": [
      "aat:300008699"
    ],
    "id": 2706789,
    "name:xx": "Swanneck Slough"
  }
}
