{
  "geometry": {
    "type": "Point",
    "coordinates": [
      -73.0833,
      -49.8667
    ]
  },
  "type": "Feature",
  "properties": {
    "hierarchy": [
      "tgn:1101679",
      "tgn:7006477",
      "tgn:1001522",
      "tgn:1000002",
      "tgn:7029392"
    ],
    "placetype": [
      "aat:300008189",
      "aat:300263063"
    ],
    "id": 1101679,
    "name:xx": "Los Glaciares, Parque Nacional"
  }
}
