{
  "geometry": {
    "type": "Point",
    "coordinates": [
      -90.0833,
      41.4833
    ]
  },
  "type": "Feature",
  "properties": {
    "hierarchy": [
      "tgn:2181812",
      "tgn:1000001",
      "tgn:7012149",
      "tgn:2000511",
      "tgn:7007251",
      "tgn:7029392"
    ],
    "placetype": [
      "aat:300006075"
    ],
    "id": 2181812,
    "name:xx": "Blue Joint Ditch"
  }
}
