{
  "geometry": {
    "type": "Point",
    "coordinates": [
      -107.05,
      44.3667
    ]
  },
  "type": "Feature",
  "properties": {
    "hierarchy": [
      "tgn:2134546",
      "tgn:1000001",
      "tgn:7012149",
      "tgn:2002374",
      "tgn:7007923",
      "tgn:7029392"
    ],
    "placetype": [
      "aat:300008798"
    ],
    "id": 2134546,
    "name:xx": "Ant Hill"
  }
}
