{
  "geometry": {
    "type": "Point",
    "coordinates": [
      4.6833,
      36.6167
    ]
  },
  "type": "Feature",
  "properties": {
    "hierarchy": [
      "tgn:1087551",
      "tgn:7001242",
      "tgn:1000524",
      "tgn:7016752",
      "tgn:7029392"
    ],
    "placetype": [
      "aat:300008347"
    ],
    "id": 1087551,
    "name:xx": "Sidi Aïch"
  }
}
