{
  "geometry": {
    "type": "Point",
    "coordinates": [
      50.5333,
      52.8167
    ]
  },
  "type": "Feature",
  "properties": {
    "hierarchy": [
      "tgn:1058489",
      "tgn:1000004",
      "tgn:1003407",
      "tgn:7018214",
      "tgn:7002435",
      "tgn:7029392"
    ],
    "placetype": [
      "aat:300008347"
    ],
    "id": 1058489,
    "name:xx": "Podjom-Michajlovka"
  }
}
