{
  "geometry": {
    "type": "Point",
    "coordinates": [
      -58.7167,
      -34.55
    ]
  },
  "type": "Feature",
  "properties": {
    "hierarchy": [
      "tgn:1019516",
      "tgn:1001160",
      "tgn:7006477",
      "tgn:1000002",
      "tgn:7029392"
    ],
    "placetype": [
      "aat:300008347",
      "aat:300000874",
      "aat:300008375",
      "aat:300387332"
    ],
    "id": 1019516,
    "name:xx": "General Sarmiento"
  }
}
