{
  "geometry": {
    "type": "Point",
    "coordinates": [
      -107.9833,
      38.4833
    ]
  },
  "type": "Feature",
  "properties": {
    "hierarchy": [
      "tgn:2339022",
      "tgn:1000001",
      "tgn:7012149",
      "tgn:2000234",
      "tgn:7007158",
      "tgn:7029392"
    ],
    "placetype": [
      "aat:300008798"
    ],
    "id": 2339022,
    "name:xx": "Franklin Mesa"
  }
}
