{
  "geometry": {
    "type": "Point",
    "coordinates": [
      -121.0333,
      40.6167
    ]
  },
  "type": "Feature",
  "properties": {
    "hierarchy": [
      "tgn:2265844",
      "tgn:1000001",
      "tgn:7012149",
      "tgn:7007157",
      "tgn:2000184",
      "tgn:7029392"
    ],
    "placetype": [
      "aat:300008798"
    ],
    "id": 2265844,
    "name:xx": "Crater Mountain"
  }
}
