{
  "geometry": {
    "type": "Point",
    "coordinates": [
      78.796391,
      24.137439
    ]
  },
  "type": "Feature",
  "properties": {
    "hierarchy": [
      "tgn:7582583",
      "tgn:1000004",
      "tgn:7000198",
      "tgn:1001894",
      "tgn:7029392"
    ],
    "placetype": [
      "aat:300008795"
    ],
    "name:en": "Rāmgara Pahār",
    "id": 7582583
  }
}
