{
  "geometry": {
    "type": "Point",
    "coordinates": [
      110.3833,
      -7.9167
    ]
  },
  "type": "Feature",
  "properties": {
    "hierarchy": [
      "tgn:1077720",
      "tgn:1000004",
      "tgn:7003701",
      "tgn:1000116",
      "tgn:7029392"
    ],
    "placetype": [
      "aat:300008347"
    ],
    "id": 1077720,
    "name:xx": "Imogiri"
  }
}
