{
  "geometry": {
    "type": "Point",
    "coordinates": [
      78.38846,
      28.340665
    ]
  },
  "type": "Feature",
  "properties": {
    "hierarchy": [
      "tgn:7556498",
      "tgn:1000004",
      "tgn:7000198",
      "tgn:7016722",
      "tgn:7029392"
    ],
    "placetype": [
      "aat:300008347"
    ],
    "name:en": "Rājpura",
    "id": 7556498
  }
}
