{
  "type": "FeatureCollection",
  "features": [
    {
      "geometry": {
        "type": "Point",
        "coordinates": [
          172.666667,
          -42.483333
        ]
      },
      "type": "Feature",
      "properties": {
        "hierarchy": [
          "tgn:7516970",
          "tgn:1009227",
          "tgn:7001866",
          "tgn:1000226",
          "tgn:1000006",
          "tgn:7029392"
        ],
        "placetype": [
          "aat:300008795"
        ],
        "name:en": "Miromiro",
        "id": 7516970
      }
    },
    {
      "geometry": {
        "type": "Point",
        "coordinates": [
          173.883333,
          -41.083333
        ]
      },
      "type": "Feature",
      "properties": {
        "hierarchy": [
          "tgn:7516971",
          "tgn:1009227",
          "tgn:1000226",
          "tgn:7016729",
          "tgn:1000006",
          "tgn:7029392"
        ],
        "placetype": [
          "aat:300132316"
        ],
        "name:en": "Miro Bay",
        "id": 7516971
      }
    },
    {
      "geometry": {
        "type": "Point",
        "coordinates": [
          174.6,
          -38.983333
        ]
      },
      "type": "Feature",
      "properties": {
        "hierarchy": [
          "tgn:7516972",
          "tgn:1008380",
          "tgn:1000226",
          "tgn:7016827",
          "tgn:1000006",
          "tgn:7029392"
        ],
        "placetype": [
          "aat:300008795"
        ],
        "name:en": "Miro",
        "id": 7516972
      }
    },
    {
      "geometry": {
        "type": "Point",
        "coordinates": [
          171.6,
          -42.183333
        ]
      },
      "type": "Feature",
      "properties": {
        "hierarchy": [
          "tgn:7516973",
          "tgn:1009227",
          "tgn:1000226",
          "tgn:1000006",
          "tgn:7016850",
          "tgn:7029392"
        ],
        "placetype": [
          "aat:300008699"
        ],
        "name:en": "Mirfin Creek",
        "id": 7516973
      }
    },
    {
      "geometry": {
        "type": "Point",
        "coordinates": [
          175,
          -38.583333
        ]
      },
      "type": "Feature",
      "properties": {
        "hierarchy": [
          "tgn:7516974",
          "tgn:1008380",
          "tgn:1000226",
          "tgn:7018426",
          "tgn:1000006",
          "tgn:7029392"
        ],
        "placetype": [
          "aat:300008777"
        ],
        "name:en": "Mirepekau",
        "id": 7516974
      }
    },
    {
      "geometry": {
        "type": "Point",
        "coordinates": [
          175.316667,
          -37.2
        ]
      },
      "type": "Feature",
      "properties": {
        "hierarchy": [
          "tgn:7516975",
          "tgn:1008380",
          "tgn:1000226",
          "tgn:7018426",
          "tgn:1000006",
          "tgn:7029392"
        ],
        "placetype": [
          "aat:300008347"
        ],
        "name:en": "Miranda",
        "id": 7516975
      }
    },
    {
      "geometry": {
        "type": "Point",
        "coordinates": [
          174.816667,
          -41.316667
        ]
      },
      "type": "Feature",
      "properties": {
        "hierarchy": [
          "tgn:7516976",
          "tgn:1009227",
          "tgn:1000226",
          "tgn:7016729",
          "tgn:1000006",
          "tgn:7029392"
        ],
        "placetype": [
          "aat:300008347"
        ],
        "name:en": "Miramar",
        "id": 7516976
      }
    },
    {
      "geometry": {
        "type": "Point",
        "coordinates": [
          169.45,
          -45.7
        ]
      },
      "type": "Feature",
      "properties": {
        "hierarchy": [
          "tgn:7516977",
          "tgn:1009227",
          "tgn:1000226",
          "tgn:7018437",
          "tgn:1000006",
          "tgn:7029392"
        ],
        "placetype": [
          "aat:300008699"
        ],
        "name:en": "Minzion Burn",
        "id": 7516977
      }
    },
    {
      "geometry": {
        "type": "Point",
        "coordinates": [
          167.8,
          -44.816667
        ]
      },
      "type": "Feature",
      "properties": {
        "hierarchy": [
          "tgn:7516978",
          "tgn:1009227",
          "tgn:1000226",
          "tgn:7016822",
          "tgn:1000006",
          "tgn:7029392"
        ],
        "placetype": [
          "aat:300008680"
        ],
        "name:en": "Mintaro, Lake",
        "id": 7516978
      }
    },
    {
      "geometry": {
        "type": "Point",
        "coordinates": [
          168.45,
          -44.933333
        ]
      },
      "type": "Feature",
      "properties": {
        "hierarchy": [
          "tgn:7516979",
          "tgn:1009227",
          "tgn:1000226",
          "tgn:7016822",
          "tgn:1000006",
          "tgn:7029392"
        ],
        "placetype": [
          "aat:300008798"
        ],
        "name:en": "Minor Peak",
        "id": 7516979
      }
    }
  ]
}
