{
  "geometry": {
    "type": "Point",
    "coordinates": [
      -70.0167,
      41.3667
    ]
  },
  "type": "Feature",
  "properties": {
    "hierarchy": [
      "tgn:2343976",
      "tgn:1008293",
      "tgn:1000001",
      "tgn:1002705",
      "tgn:7012149",
      "tgn:7007517",
      "tgn:7029392"
    ],
    "placetype": [
      "aat:300008794"
    ],
    "id": 2343976,
    "name:xx": "Galls, The"
  }
}
