{
  "type": "FeatureCollection",
  "features": [
    {
      "geometry": {
        "type": "Point",
        "coordinates": [
          -97.3333,
          31.9
        ]
      },
      "type": "Feature",
      "properties": {
        "hierarchy": [
          "tgn:2108610",
          "tgn:1000001",
          "tgn:7012149",
          "tgn:1002478",
          "tgn:7007826",
          "tgn:7029392"
        ],
        "placetype": [
          "aat:300008347",
          "aat:300387210"
        ],
        "id": 2108610,
        "name:xx": "Woodland Hills"
      }
    },
    {
      "geometry": {
        "type": "Point",
        "coordinates": [
          -94.7667,
          31.35
        ]
      },
      "type": "Feature",
      "properties": {
        "hierarchy": [
          "tgn:2108613",
          "tgn:1002149",
          "tgn:1000001",
          "tgn:7012149",
          "tgn:7007826",
          "tgn:7029392"
        ],
        "placetype": [
          "aat:300008347",
          "aat:300387210"
        ],
        "id": 2108613,
        "name:xx": "Woodlawn"
      }
    },
    {
      "geometry": {
        "type": "Point",
        "coordinates": [
          -94.3333,
          32.6667
        ]
      },
      "type": "Feature",
      "properties": {
        "hierarchy": [
          "tgn:2108614",
          "tgn:1000001",
          "tgn:7012149",
          "tgn:1002460",
          "tgn:7007826",
          "tgn:7029392"
        ],
        "placetype": [
          "aat:300008347"
        ],
        "id": 2108614,
        "name:xx": "Woodlawn"
      }
    },
    {
      "geometry": {
        "type": "Point",
        "coordinates": [
          -101.8333,
          33.4333
        ]
      },
      "type": "Feature",
      "properties": {
        "hierarchy": [
          "tgn:2108619",
          "tgn:1000001",
          "tgn:7012149",
          "tgn:2002032",
          "tgn:7007826",
          "tgn:7029392"
        ],
        "placetype": [
          "aat:300008347"
        ],
        "id": 2108619,
        "name:xx": "Woodrow"
      }
    }
  ]
}
