{
  "geometry": {
    "type": "Point",
    "coordinates": [
      -78.6167,
      39.0333
    ]
  },
  "type": "Feature",
  "properties": {
    "hierarchy": [
      "tgn:2771202",
      "tgn:1000001",
      "tgn:7012149",
      "tgn:2002266",
      "tgn:7013961",
      "tgn:7029392"
    ],
    "placetype": [
      "aat:300266640"
    ],
    "id": 2771202,
    "name:xx": "Wildcat Ridge"
  }
}
