{
  "type": "FeatureCollection",
  "features": [
    {
      "geometry": {
        "type": "Point",
        "coordinates": [
          -85.3167,
          45
        ]
      },
      "type": "Feature",
      "properties": {
        "hierarchy": [
          "tgn:2556480",
          "tgn:2000945",
          "tgn:1000001",
          "tgn:7012149",
          "tgn:7007520",
          "tgn:7029392"
        ],
        "placetype": [
          "aat:300008798"
        ],
        "id": 2556480,
        "name:xx": "Old Baldy"
      }
    },
    {
      "geometry": {
        "type": "Point",
        "coordinates": [
          -109.3,
          46.75
        ]
      },
      "type": "Feature",
      "properties": {
        "hierarchy": [
          "tgn:2556481",
          "tgn:1000001",
          "tgn:7012149",
          "tgn:2001273",
          "tgn:7007524",
          "tgn:7029392"
        ],
        "placetype": [
          "aat:300008798"
        ],
        "id": 2556481,
        "name:xx": "Old Baldy"
      }
    },
    {
      "geometry": {
        "type": "Point",
        "coordinates": [
          -111.2,
          46.9833
        ]
      },
      "type": "Feature",
      "properties": {
        "hierarchy": [
          "tgn:2556482",
          "tgn:1000001",
          "tgn:7012149",
          "tgn:2001289",
          "tgn:7007524",
          "tgn:7029392"
        ],
        "placetype": [
          "aat:300008798"
        ],
        "id": 2556482,
        "name:xx": "Old Baldy"
      }
    },
    {
      "geometry": {
        "type": "Point",
        "coordinates": [
          -112.8167,
          47.85
        ]
      },
      "type": "Feature",
      "properties": {
        "hierarchy": [
          "tgn:2556483",
          "tgn:1000001",
          "tgn:7012149",
          "tgn:2001309",
          "tgn:7007524",
          "tgn:7029392"
        ],
        "placetype": [
          "aat:300008798"
        ],
        "id": 2556483,
        "name:xx": "Old Baldy"
      }
    },
    {
      "geometry": {
        "type": "Point",
        "coordinates": [
          -101.7333,
          40.3333
        ]
      },
      "type": "Feature",
      "properties": {
        "hierarchy": [
          "tgn:2556484",
          "tgn:1000001",
          "tgn:2001344",
          "tgn:7012149",
          "tgn:7007525",
          "tgn:7029392"
        ],
        "placetype": [
          "aat:300008798"
        ],
        "id": 2556484,
        "name:xx": "Old Baldy"
      }
    },
    {
      "geometry": {
        "type": "Point",
        "coordinates": [
          -102.0167,
          41.4667
        ]
      },
      "type": "Feature",
      "properties": {
        "hierarchy": [
          "tgn:2556485",
          "tgn:1000001",
          "tgn:2001350",
          "tgn:7012149",
          "tgn:7007525",
          "tgn:7029392"
        ],
        "placetype": [
          "aat:300008798"
        ],
        "id": 2556485,
        "name:xx": "Old Baldy"
      }
    },
    {
      "geometry": {
        "type": "Point",
        "coordinates": [
          -98.4667,
          42.9333
        ]
      },
      "type": "Feature",
      "properties": {
        "hierarchy": [
          "tgn:2556486",
          "tgn:1000001",
          "tgn:2001323",
          "tgn:7012149",
          "tgn:7007525",
          "tgn:7029392"
        ],
        "placetype": [
          "aat:300008798"
        ],
        "id": 2556486,
        "name:xx": "Old Baldy"
      }
    },
    {
      "geometry": {
        "type": "Point",
        "coordinates": [
          -108.1333,
          31.95
        ]
      },
      "type": "Feature",
      "properties": {
        "hierarchy": [
          "tgn:2556487",
          "tgn:1000001",
          "tgn:7012149",
          "tgn:2001444",
          "tgn:7007566",
          "tgn:7029392"
        ],
        "placetype": [
          "aat:300008798"
        ],
        "id": 2556487,
        "name:xx": "Old Baldy"
      }
    },
    {
      "geometry": {
        "type": "Point",
        "coordinates": [
          -103.2833,
          32.1333
        ]
      },
      "type": "Feature",
      "properties": {
        "hierarchy": [
          "tgn:2556488",
          "tgn:1000001",
          "tgn:7012149",
          "tgn:2001441",
          "tgn:7007566",
          "tgn:7029392"
        ],
        "placetype": [
          "aat:300008798"
        ],
        "id": 2556488,
        "name:xx": "Old Baldy"
      }
    },
    {
      "geometry": {
        "type": "Point",
        "coordinates": [
          -78.4,
          42.05
        ]
      },
      "type": "Feature",
      "properties": {
        "hierarchy": [
          "tgn:2556489",
          "tgn:1000001",
          "tgn:1002245",
          "tgn:7012149",
          "tgn:7007568",
          "tgn:7029392"
        ],
        "placetype": [
          "aat:300008798"
        ],
        "id": 2556489,
        "name:xx": "Old Baldy"
      }
    }
  ]
}
