{
  "geometry": {
    "type": "Point",
    "coordinates": [
      -85.7667,
      34.7333
    ]
  },
  "type": "Feature",
  "properties": {
    "hierarchy": [
      "tgn:2639555",
      "tgn:7002659",
      "tgn:1000001",
      "tgn:7012149",
      "tgn:2000035",
      "tgn:7029392"
    ],
    "placetype": [
      "aat:300008746"
    ],
    "id": 2639555,
    "name:xx": "Saltpetre Cave"
  }
}
