{
  "geometry": {
    "type": "Point",
    "coordinates": [
      -91.45,
      31.9667
    ]
  },
  "type": "Feature",
  "properties": {
    "hierarchy": [
      "tgn:2287032",
      "tgn:1000001",
      "tgn:7012149",
      "tgn:2000907",
      "tgn:7007256",
      "tgn:7029392"
    ],
    "placetype": [
      "aat:300008699"
    ],
    "id": 2287032,
    "name:xx": "Dickard Bayou"
  }
}
