{
  "geometry": {
    "type": "Point",
    "coordinates": [
      -79.95,
      41.5833
    ]
  },
  "type": "Feature",
  "properties": {
    "hierarchy": [
      "tgn:2527150",
      "tgn:1000001",
      "tgn:1002308",
      "tgn:7012149",
      "tgn:7007710",
      "tgn:7029392"
    ],
    "placetype": [
      "aat:300008347"
    ],
    "id": 2527150,
    "name:xx": "Mount Hope"
  }
}
