{
  "geometry": {
    "type": "Point",
    "coordinates": [
      -89.5833,
      37.5333
    ]
  },
  "type": "Feature",
  "properties": {
    "hierarchy": [
      "tgn:2472629",
      "tgn:1000001",
      "tgn:2001179",
      "tgn:7012149",
      "tgn:7007523",
      "tgn:7029392"
    ],
    "placetype": [
      "aat:300008706"
    ],
    "id": 2472629,
    "name:xx": "Lovejoy Creek"
  }
}
