{
  "geometry": {
    "type": "Point",
    "coordinates": [
      -120.1333,
      39.3333
    ]
  },
  "type": "Feature",
  "properties": {
    "hierarchy": [
      "tgn:2590365",
      "tgn:1000001",
      "tgn:7012149",
      "tgn:7007157",
      "tgn:1002710",
      "tgn:7029392"
    ],
    "placetype": [
      "aat:300008347"
    ],
    "id": 2590365,
    "name:xx": "Polaris"
  }
}
