{
  "geometry": {
    "type": "Point",
    "coordinates": [
      -83.5167,
      35.8833
    ]
  },
  "type": "Feature",
  "properties": {
    "hierarchy": [
      "tgn:2433519",
      "tgn:1000001",
      "tgn:7012149",
      "tgn:2001914",
      "tgn:7007825",
      "tgn:7029392"
    ],
    "placetype": [
      "aat:300008706"
    ],
    "id": 2433519,
    "name:xx": "Kellum Creek"
  }
}
