{
  "geometry": {
    "type": "Point",
    "coordinates": [
      -118.1667,
      43.5667
    ]
  },
  "type": "Feature",
  "properties": {
    "hierarchy": [
      "tgn:2620720",
      "tgn:1000001",
      "tgn:7012149",
      "tgn:2001718",
      "tgn:7007708",
      "tgn:7029392"
    ],
    "placetype": [
      "aat:300006191"
    ],
    "id": 2620720,
    "name:xx": "Riverside Reservoir Number Two"
  }
}
