{
  "geometry": {
    "type": "Point",
    "coordinates": [
      -107.8333,
      34.2167
    ]
  },
  "type": "Feature",
  "properties": {
    "hierarchy": [
      "tgn:2543368",
      "tgn:1000001",
      "tgn:2001429",
      "tgn:7012149",
      "tgn:7007566",
      "tgn:7029392"
    ],
    "placetype": [
      "aat:300008697"
    ],
    "id": 2543368,
    "name:xx": "Norman Spring"
  }
}
