{
  "geometry": {
    "type": "Point",
    "coordinates": [
      -91.4167,
      34.7333
    ]
  },
  "type": "Feature",
  "properties": {
    "hierarchy": [
      "tgn:2575606",
      "tgn:1000001",
      "tgn:7016172",
      "tgn:7012149",
      "tgn:2000163",
      "tgn:7029392"
    ],
    "placetype": [
      "aat:300008680"
    ],
    "id": 2575606,
    "name:xx": "Peppers Lake"
  }
}
