{
  "geometry": {
    "type": "Point",
    "coordinates": [
      -101.2167,
      36.0167
    ]
  },
  "type": "Feature",
  "properties": {
    "hierarchy": [
      "tgn:2396487",
      "tgn:1000001",
      "tgn:7012149",
      "tgn:2002006",
      "tgn:7007826",
      "tgn:7029392"
    ],
    "placetype": [
      "aat:300008347"
    ],
    "id": 2396487,
    "name:xx": "Holt"
  }
}
