{
  "type": "FeatureCollection",
  "features": [
    {
      "geometry": {
        "type": "Point",
        "coordinates": [
          -89.6167,
          40.55
        ]
      },
      "type": "Feature",
      "properties": {
        "hierarchy": [
          "tgn:2507500",
          "tgn:1000001",
          "tgn:7012149",
          "tgn:2000533",
          "tgn:7007251",
          "tgn:7029392"
        ],
        "placetype": [
          "aat:300008680"
        ],
        "id": 2507500,
        "name:xx": "Meyers Lake"
      }
    },
    {
      "geometry": {
        "type": "Point",
        "coordinates": [
          -92.2833,
          42.45
        ]
      },
      "type": "Feature",
      "properties": {
        "hierarchy": [
          "tgn:2507501",
          "tgn:2000567",
          "tgn:1000001",
          "tgn:7012149",
          "tgn:7007253",
          "tgn:7029392"
        ],
        "placetype": [
          "aat:300008680"
        ],
        "id": 2507501,
        "name:xx": "Meyers Lake"
      }
    },
    {
      "geometry": {
        "type": "Point",
        "coordinates": [
          -83.5,
          42.7
        ]
      },
      "type": "Feature",
      "properties": {
        "hierarchy": [
          "tgn:2507502",
          "tgn:1000001",
          "tgn:7012149",
          "tgn:1002737",
          "tgn:7007520",
          "tgn:7029392"
        ],
        "placetype": [
          "aat:300008680"
        ],
        "id": 2507502,
        "name:xx": "Meyers Lake"
      }
    },
    {
      "geometry": {
        "type": "Point",
        "coordinates": [
          -94.55,
          45.4
        ]
      },
      "type": "Feature",
      "properties": {
        "hierarchy": [
          "tgn:2507503",
          "tgn:1000001",
          "tgn:7012149",
          "tgn:2001071",
          "tgn:7007521",
          "tgn:7029392"
        ],
        "placetype": [
          "aat:300008680"
        ],
        "id": 2507503,
        "name:xx": "Meyers Lake"
      }
    },
    {
      "geometry": {
        "type": "Point",
        "coordinates": [
          -81.4167,
          40.8167
        ]
      },
      "type": "Feature",
      "properties": {
        "hierarchy": [
          "tgn:2507504",
          "tgn:1000001",
          "tgn:7012149",
          "tgn:1002917",
          "tgn:7007706",
          "tgn:7029392"
        ],
        "placetype": [
          "aat:300008680"
        ],
        "id": 2507504,
        "name:xx": "Meyers Lake"
      }
    },
    {
      "geometry": {
        "type": "Point",
        "coordinates": [
          -89.2833,
          44.4667
        ]
      },
      "type": "Feature",
      "properties": {
        "hierarchy": [
          "tgn:2507505",
          "tgn:1000001",
          "tgn:7012149",
          "tgn:2002347",
          "tgn:7007922",
          "tgn:7029392"
        ],
        "placetype": [
          "aat:300008680"
        ],
        "id": 2507505,
        "name:xx": "Meyers Lake"
      }
    },
    {
      "geometry": {
        "type": "Point",
        "coordinates": [
          -74.1833,
          41.0333
        ]
      },
      "type": "Feature",
      "properties": {
        "hierarchy": [
          "tgn:2507506",
          "tgn:1002178",
          "tgn:1000001",
          "tgn:7012149",
          "tgn:7007565",
          "tgn:7029392"
        ],
        "placetype": [
          "aat:300006191"
        ],
        "id": 2507506,
        "name:xx": "Meyers Lakes"
      }
    },
    {
      "geometry": {
        "type": "Point",
        "coordinates": [
          -75.5833,
          41.5167
        ]
      },
      "type": "Feature",
      "properties": {
        "hierarchy": [
          "tgn:2507508",
          "tgn:1000001",
          "tgn:7012149",
          "tgn:1002564",
          "tgn:7007710",
          "tgn:7029392"
        ],
        "placetype": [
          "aat:300008798"
        ],
        "id": 2507508,
        "name:xx": "Meyers Mountain"
      }
    },
    {
      "geometry": {
        "type": "Point",
        "coordinates": [
          -120.9,
          36.5333
        ]
      },
      "type": "Feature",
      "properties": {
        "hierarchy": [
          "tgn:2507509",
          "tgn:1000001",
          "tgn:7012149",
          "tgn:7007157",
          "tgn:1002856",
          "tgn:7029392"
        ],
        "placetype": [
          "aat:300008798"
        ],
        "id": 2507509,
        "name:xx": "Meyers Peak"
      }
    }
  ]
}
