{
  "geometry": {
    "type": "Point",
    "coordinates": [
      -77.3333,
      37.7667
    ]
  },
  "type": "Feature",
  "properties": {
    "hierarchy": [
      "tgn:2504632",
      "tgn:1000001",
      "tgn:7012149",
      "tgn:1002451",
      "tgn:7007919",
      "tgn:7029392"
    ],
    "placetype": [
      "aat:300006191"
    ],
    "id": 2504632,
    "name:xx": "Mechumps Pond"
  }
}
