{
  "geometry": {
    "type": "Point",
    "coordinates": [
      -68.95,
      -20.05
    ]
  },
  "type": "Feature",
  "properties": {
    "hierarchy": [
      "tgn:7318613",
      "tgn:7002464",
      "tgn:1000049",
      "tgn:1000002",
      "tgn:7029392"
    ],
    "placetype": [
      "aat:300008795"
    ],
    "id": 7318613,
    "name:xx": "Collacagua, Morro"
  }
}
