{
  "geometry": {
    "type": "Point",
    "coordinates": [
      -70.466667,
      -25.25
    ]
  },
  "type": "Feature",
  "properties": {
    "hierarchy": [
      "tgn:7309697",
      "tgn:7016598",
      "tgn:1000049",
      "tgn:1000002",
      "tgn:7029392"
    ],
    "placetype": [
      "aat:300132316"
    ],
    "id": 7309697,
    "name:xx": "Nuestra Señora, Bahía"
  }
}
