{
  "geometry": {
    "type": "Point",
    "coordinates": [
      -88.2167,
      46.1167
    ]
  },
  "type": "Feature",
  "properties": {
    "hierarchy": [
      "tgn:2490895",
      "tgn:1000001",
      "tgn:7012149",
      "tgn:2000966",
      "tgn:7007520",
      "tgn:7029392"
    ],
    "placetype": [
      "aat:300008347"
    ],
    "id": 2490895,
    "name:xx": "Mansfield Location"
  }
}
