{
  "geometry": {
    "type": "Point",
    "coordinates": [
      -119.6167,
      40.8667
    ]
  },
  "type": "Feature",
  "properties": {
    "hierarchy": [
      "tgn:2299196",
      "tgn:1000001",
      "tgn:7012149",
      "tgn:1002999",
      "tgn:7007526",
      "tgn:7029392"
    ],
    "placetype": [
      "aat:300008699"
    ],
    "id": 2299196,
    "name:xx": "Duck Flat Wash"
  }
}
