{
  "geometry": {
    "type": "Point",
    "coordinates": [
      -74.7667,
      46.3833
    ]
  },
  "type": "Feature",
  "properties": {
    "hierarchy": [
      "tgn:1124029",
      "tgn:7005685",
      "tgn:1000001",
      "tgn:7005804",
      "tgn:7029392"
    ],
    "placetype": [
      "aat:300008707"
    ],
    "id": 1124029,
    "name:xx": "Froid, Ruisseau"
  }
}
