{
  "type": "FeatureCollection",
  "features": [
    {
      "geometry": {
        "type": "Point",
        "coordinates": [
          -76.7,
          37.8167
        ]
      },
      "type": "Feature",
      "properties": {
        "hierarchy": [
          "tgn:2114200",
          "tgn:1000001",
          "tgn:7012149",
          "tgn:7014334",
          "tgn:7007919",
          "tgn:7029392"
        ],
        "placetype": [
          "aat:300008347"
        ],
        "id": 2114200,
        "name:xx": "Sharps"
      }
    },
    {
      "geometry": {
        "type": "Point",
        "coordinates": [
          -78.3333,
          39.1833
        ]
      },
      "type": "Feature",
      "properties": {
        "hierarchy": [
          "tgn:2114201",
          "tgn:1000001",
          "tgn:7012149",
          "tgn:2002161",
          "tgn:7007919",
          "tgn:7029392"
        ],
        "placetype": [
          "aat:300008347"
        ],
        "id": 2114201,
        "name:xx": "Shawnee Land"
      }
    },
    {
      "geometry": {
        "type": "Point",
        "coordinates": [
          -80.25,
          37.1667
        ]
      },
      "type": "Feature",
      "properties": {
        "hierarchy": [
          "tgn:2114202",
          "tgn:1000001",
          "tgn:7012149",
          "tgn:2002174",
          "tgn:7007919",
          "tgn:7029392"
        ],
        "placetype": [
          "aat:300008347"
        ],
        "id": 2114202,
        "name:xx": "Shawsville"
      }
    },
    {
      "geometry": {
        "type": "Point",
        "coordinates": [
          -81.35,
          37.15
        ]
      },
      "type": "Feature",
      "properties": {
        "hierarchy": [
          "tgn:2114203",
          "tgn:1000001",
          "tgn:7012149",
          "tgn:2002192",
          "tgn:7007919",
          "tgn:7029392"
        ],
        "placetype": [
          "aat:300008347",
          "aat:300387210"
        ],
        "id": 2114203,
        "name:xx": "Shawver Mill"
      }
    },
    {
      "geometry": {
        "type": "Point",
        "coordinates": [
          -80.9,
          36.8167
        ]
      },
      "type": "Feature",
      "properties": {
        "hierarchy": [
          "tgn:2114204",
          "tgn:1000001",
          "tgn:2002151",
          "tgn:7012149",
          "tgn:7007919",
          "tgn:7029392"
        ],
        "placetype": [
          "aat:300008347",
          "aat:300387210"
        ],
        "id": 2114204,
        "name:xx": "Sheep Town"
      }
    },
    {
      "geometry": {
        "type": "Point",
        "coordinates": [
          -79.85,
          36.6
        ]
      },
      "type": "Feature",
      "properties": {
        "hierarchy": [
          "tgn:2114205",
          "tgn:1000001",
          "tgn:7012149",
          "tgn:2002167",
          "tgn:7007919",
          "tgn:7029392"
        ],
        "placetype": [
          "aat:300008347"
        ],
        "id": 2114205,
        "name:xx": "Sheffield Terrace"
      }
    },
    {
      "geometry": {
        "type": "Point",
        "coordinates": [
          -78.3,
          38.3167
        ]
      },
      "type": "Feature",
      "properties": {
        "hierarchy": [
          "tgn:2114207",
          "tgn:1000001",
          "tgn:7012149",
          "tgn:2002172",
          "tgn:7007919",
          "tgn:7029392"
        ],
        "placetype": [
          "aat:300008347",
          "aat:300387210"
        ],
        "id": 2114207,
        "name:xx": "Shelby"
      }
    },
    {
      "geometry": {
        "type": "Point",
        "coordinates": [
          -77.8667,
          37.8
        ]
      },
      "type": "Feature",
      "properties": {
        "hierarchy": [
          "tgn:2114208",
          "tgn:1000001",
          "tgn:7012149",
          "tgn:2002170",
          "tgn:7007919",
          "tgn:7029392"
        ],
        "placetype": [
          "aat:300008347",
          "aat:300387210"
        ],
        "id": 2114208,
        "name:xx": "Shelfar"
      }
    }
  ]
}
