{
  "geometry": {
    "type": "Point",
    "coordinates": [
      -88.0667,
      38.0167
    ]
  },
  "type": "Feature",
  "properties": {
    "hierarchy": [
      "tgn:2746494",
      "tgn:1000001",
      "tgn:7012149",
      "tgn:2000537",
      "tgn:7007251",
      "tgn:7029392"
    ],
    "placetype": [
      "aat:300006075"
    ],
    "id": 2746494,
    "name:xx": "Wabash Levee Ditch"
  }
}
