{
  "geometry": {
    "type": "Point",
    "coordinates": [
      25.85,
      52.5167
    ]
  },
  "type": "Feature",
  "properties": {
    "hierarchy": [
      "tgn:1060222",
      "tgn:1003357",
      "tgn:1000003",
      "tgn:7006657",
      "tgn:7029392"
    ],
    "placetype": [
      "aat:300008347"
    ],
    "id": 1060222,
    "name:xx": "Telekhany"
  }
}
