{
  "geometry": {
    "type": "Point",
    "coordinates": [
      -82.95,
      38.8833
    ]
  },
  "type": "Feature",
  "properties": {
    "hierarchy": [
      "tgn:2629053",
      "tgn:1000001",
      "tgn:7012149",
      "tgn:1002877",
      "tgn:7007706",
      "tgn:7029392"
    ],
    "placetype": [
      "aat:300008798"
    ],
    "id": 2629053,
    "name:xx": "Rose Hill"
  }
}
