{
  "geometry": {
    "type": "Point",
    "coordinates": [
      -116.15,
      41.6833
    ]
  },
  "type": "Feature",
  "properties": {
    "hierarchy": [
      "tgn:2310442",
      "tgn:1000001",
      "tgn:2001411",
      "tgn:7012149",
      "tgn:7007526",
      "tgn:7029392"
    ],
    "placetype": [
      "aat:300008761"
    ],
    "id": 2310442,
    "name:xx": "Echo Canyon"
  }
}
