{
  "type": "FeatureCollection",
  "features": [
    {
      "geometry": {
        "type": "Point",
        "coordinates": [
          -99.1333,
          26.6167
        ]
      },
      "type": "Feature",
      "properties": {
        "hierarchy": [
          "tgn:2504850",
          "tgn:1000001",
          "tgn:7012149",
          "tgn:2002099",
          "tgn:7007826",
          "tgn:7029392"
        ],
        "placetype": [
          "aat:300008761"
        ],
        "id": 2504850,
        "name:xx": "Medio, Arroyo"
      }
    },
    {
      "geometry": {
        "type": "Point",
        "coordinates": [
          -107.1,
          35.8667
        ]
      },
      "type": "Feature",
      "properties": {
        "hierarchy": [
          "tgn:2504851",
          "tgn:1000001",
          "tgn:7012149",
          "tgn:2001451",
          "tgn:7007566",
          "tgn:7029392"
        ],
        "placetype": [
          "aat:300008761"
        ],
        "id": 2504851,
        "name:xx": "Medio, Cañon"
      }
    },
    {
      "geometry": {
        "type": "Point",
        "coordinates": [
          -106.4333,
          35.9
        ]
      },
      "type": "Feature",
      "properties": {
        "hierarchy": [
          "tgn:2504852",
          "tgn:1000001",
          "tgn:7012149",
          "tgn:2001451",
          "tgn:7007566",
          "tgn:7029392"
        ],
        "placetype": [
          "aat:300008798"
        ],
        "id": 2504852,
        "name:xx": "Medio, Cerro del"
      }
    },
    {
      "geometry": {
        "type": "Point",
        "coordinates": [
          -104.8833,
          35.0667
        ]
      },
      "type": "Feature",
      "properties": {
        "hierarchy": [
          "tgn:2504853",
          "tgn:1000001",
          "tgn:7012149",
          "tgn:2001438",
          "tgn:7007566",
          "tgn:7029392"
        ],
        "placetype": [
          "aat:300008798"
        ],
        "id": 2504853,
        "name:xx": "Medio, Mesa del"
      }
    },
    {
      "geometry": {
        "type": "Point",
        "coordinates": [
          -104.4,
          35.2167
        ]
      },
      "type": "Feature",
      "properties": {
        "hierarchy": [
          "tgn:2504854",
          "tgn:1000001",
          "tgn:7012149",
          "tgn:2001453",
          "tgn:7007566",
          "tgn:7029392"
        ],
        "placetype": [
          "aat:300008798"
        ],
        "id": 2504854,
        "name:xx": "Medio, Mesa del"
      }
    },
    {
      "geometry": {
        "type": "Point",
        "coordinates": [
          -106.3833,
          36.4167
        ]
      },
      "type": "Feature",
      "properties": {
        "hierarchy": [
          "tgn:2504855",
          "tgn:1000001",
          "tgn:7012149",
          "tgn:2001449",
          "tgn:7007566",
          "tgn:7029392"
        ],
        "placetype": [
          "aat:300008798"
        ],
        "id": 2504855,
        "name:xx": "Medio, Mesa del"
      }
    },
    {
      "geometry": {
        "type": "Point",
        "coordinates": [
          -105.6333,
          35.95
        ]
      },
      "type": "Feature",
      "properties": {
        "hierarchy": [
          "tgn:2504856",
          "tgn:1000001",
          "tgn:7012149",
          "tgn:7007566",
          "tgn:7029392"
        ],
        "placetype": [
          "aat:300008699"
        ],
        "id": 2504856,
        "name:xx": "Medio, Rio"
      }
    },
    {
      "geometry": {
        "type": "Point",
        "coordinates": [
          -105.7667,
          35.7833
        ]
      },
      "type": "Feature",
      "properties": {
        "hierarchy": [
          "tgn:2504857",
          "tgn:1000001",
          "tgn:7012149",
          "tgn:2001454",
          "tgn:7007566",
          "tgn:7029392"
        ],
        "placetype": [
          "aat:300008699"
        ],
        "id": 2504857,
        "name:xx": "Medio, Rio en"
      }
    },
    {
      "geometry": {
        "type": "Point",
        "coordinates": [
          -106.4,
          36.55
        ]
      },
      "type": "Feature",
      "properties": {
        "hierarchy": [
          "tgn:2504858",
          "tgn:1000001",
          "tgn:7012149",
          "tgn:2001449",
          "tgn:7007566",
          "tgn:7029392"
        ],
        "placetype": [
          "aat:300008699"
        ],
        "id": 2504858,
        "name:xx": "Medio, Rito del"
      }
    },
    {
      "geometry": {
        "type": "Point",
        "coordinates": [
          -105.4833,
          36.7833
        ]
      },
      "type": "Feature",
      "properties": {
        "hierarchy": [
          "tgn:2504859",
          "tgn:1000001",
          "tgn:7012149",
          "tgn:2001457",
          "tgn:7007566",
          "tgn:7029392"
        ],
        "placetype": [
          "aat:300008699"
        ],
        "id": 2504859,
        "name:xx": "Medio, Rito del"
      }
    }
  ]
}
