{
  "type": "FeatureCollection",
  "features": [
    {
      "geometry": {
        "type": "Point",
        "coordinates": [
          -4.816667,
          55.183333
        ]
      },
      "type": "Feature",
      "properties": {
        "hierarchy": [
          "tgn:7457071",
          "tgn:7002444",
          "tgn:1000003",
          "tgn:7019085",
          "tgn:7008591",
          "tgn:7029392"
        ],
        "placetype": [
          "aat:300008347"
        ],
        "name:en": "Pinmore",
        "id": 7457071
      }
    },
    {
      "geometry": {
        "type": "Point",
        "coordinates": [
          -1.1,
          54.533333
        ]
      },
      "type": "Feature",
      "properties": {
        "hierarchy": [
          "tgn:7457073",
          "tgn:7002445",
          "tgn:1000003",
          "tgn:7019065",
          "tgn:7008591",
          "tgn:7029392"
        ],
        "placetype": [
          "aat:300007783"
        ],
        "name:en": "Pinchingthorpe Station",
        "id": 7457073
      }
    },
    {
      "geometry": {
        "type": "Point",
        "coordinates": [
          -2.133333,
          50.883333
        ]
      },
      "type": "Feature",
      "properties": {
        "hierarchy": [
          "tgn:7457075",
          "tgn:7002445",
          "tgn:1000003",
          "tgn:7011961",
          "tgn:7008591",
          "tgn:7029392"
        ],
        "placetype": [
          "aat:300008347"
        ],
        "name:en": "Pimperne",
        "id": 7457075
      }
    },
    {
      "geometry": {
        "type": "Point",
        "coordinates": [
          -2.587222,
          51.165278
        ]
      },
      "type": "Feature",
      "properties": {
        "hierarchy": [
          "tgn:7457077",
          "tgn:7002445",
          "tgn:1000003",
          "tgn:7012032",
          "tgn:7008591",
          "tgn:7029392"
        ],
        "placetype": [
          "aat:300008347"
        ],
        "name:en": "Pilton",
        "id": 7457077
      }
    },
    {
      "geometry": {
        "type": "Point",
        "coordinates": [
          -4.85,
          54.866667
        ]
      },
      "type": "Feature",
      "properties": {
        "hierarchy": [
          "tgn:7457079",
          "tgn:7002444",
          "tgn:7008074",
          "tgn:1000003",
          "tgn:7008591",
          "tgn:7029392"
        ],
        "placetype": [
          "aat:300008699"
        ],
        "name:en": "Piltanton Burn",
        "id": 7457079
      }
    }
  ]
}
