{
  "geometry": {
    "type": "Point",
    "coordinates": [
      -79.7333,
      -2.0333
    ]
  },
  "type": "Feature",
  "properties": {
    "hierarchy": [
      "tgn:1131970",
      "tgn:1001277",
      "tgn:7002560",
      "tgn:1000051",
      "tgn:1000002",
      "tgn:7029392"
    ],
    "placetype": [
      "aat:300008707"
    ],
    "id": 1131970,
    "name:xx": "Yaguachi, Río"
  }
}
