{
  "geometry": {
    "type": "Point",
    "coordinates": [
      -110.1333,
      43.7333
    ]
  },
  "type": "Feature",
  "properties": {
    "hierarchy": [
      "tgn:2684939",
      "tgn:1000001",
      "tgn:7012149",
      "tgn:2002384",
      "tgn:7007923",
      "tgn:7029392"
    ],
    "placetype": [
      "aat:300008706"
    ],
    "id": 2684939,
    "name:xx": "Split Rock Creek"
  }
}
