{
  "type": "FeatureCollection",
  "features": [
    {
      "geometry": {
        "type": "Point",
        "coordinates": [
          11.4,
          47.916667
        ]
      },
      "type": "Feature",
      "properties": {
        "hierarchy": [
          "tgn:7130320",
          "tgn:7003669",
          "tgn:1000003",
          "tgn:7000084",
          "tgn:7029392"
        ],
        "placetype": [
          "aat:300008347"
        ],
        "id": 7130320,
        "name:xx": "Meilenberg"
      }
    },
    {
      "geometry": {
        "type": "Point",
        "coordinates": [
          13.216667,
          50.6
        ]
      },
      "type": "Feature",
      "properties": {
        "hierarchy": [
          "tgn:7130321",
          "tgn:1000003",
          "tgn:7003685",
          "tgn:7000084",
          "tgn:7029392"
        ],
        "placetype": [
          "aat:300008795"
        ],
        "id": 7130321,
        "name:xx": "Meilen-Berg"
      }
    },
    {
      "geometry": {
        "type": "Point",
        "coordinates": [
          11.3,
          49.15
        ]
      },
      "type": "Feature",
      "properties": {
        "hierarchy": [
          "tgn:7130322",
          "tgn:7003669",
          "tgn:1000003",
          "tgn:7000084",
          "tgn:7029392"
        ],
        "placetype": [
          "aat:300008347"
        ],
        "id": 7130322,
        "name:xx": "Meilenbach"
      }
    },
    {
      "geometry": {
        "type": "Point",
        "coordinates": [
          6.55,
          49.9
        ]
      },
      "type": "Feature",
      "properties": {
        "hierarchy": [
          "tgn:7130323",
          "tgn:1000003",
          "tgn:7003682",
          "tgn:7000084",
          "tgn:7029392"
        ],
        "placetype": [
          "aat:300000206"
        ],
        "id": 7130323,
        "name:xx": "Meilbrück"
      }
    },
    {
      "geometry": {
        "type": "Point",
        "coordinates": [
          11.633333,
          49
        ]
      },
      "type": "Feature",
      "properties": {
        "hierarchy": [
          "tgn:7130325",
          "tgn:7003669",
          "tgn:1000003",
          "tgn:7000084",
          "tgn:7029392"
        ],
        "placetype": [
          "aat:300008347"
        ],
        "id": 7130325,
        "name:xx": "Meihern"
      }
    },
    {
      "geometry": {
        "type": "Point",
        "coordinates": [
          7.116667,
          51.166667
        ]
      },
      "type": "Feature",
      "properties": {
        "hierarchy": [
          "tgn:7130326",
          "tgn:1000003",
          "tgn:7003677",
          "tgn:7000084",
          "tgn:7029392"
        ],
        "placetype": [
          "aat:300000206"
        ],
        "id": 7130326,
        "name:xx": "Meigen"
      }
    },
    {
      "geometry": {
        "type": "Point",
        "coordinates": [
          12.5,
          49.316667
        ]
      },
      "type": "Feature",
      "properties": {
        "hierarchy": [
          "tgn:7130327",
          "tgn:7003669",
          "tgn:1000003",
          "tgn:7000084",
          "tgn:7029392"
        ],
        "placetype": [
          "aat:300008347"
        ],
        "id": 7130327,
        "name:xx": "Meigelsried"
      }
    },
    {
      "geometry": {
        "type": "Point",
        "coordinates": [
          9.5,
          54.816667
        ]
      },
      "type": "Feature",
      "properties": {
        "hierarchy": [
          "tgn:7130328",
          "tgn:1000003",
          "tgn:7003688",
          "tgn:7000084",
          "tgn:7029392"
        ],
        "placetype": [
          "aat:300000206"
        ],
        "id": 7130328,
        "name:xx": "Meierwik"
      }
    },
    {
      "geometry": {
        "type": "Point",
        "coordinates": [
          10.666667,
          47.966667
        ]
      },
      "type": "Feature",
      "properties": {
        "hierarchy": [
          "tgn:7130329",
          "tgn:7003669",
          "tgn:1000003",
          "tgn:7000084",
          "tgn:7029392"
        ],
        "placetype": [
          "aat:300008863"
        ],
        "id": 7130329,
        "name:xx": "Meier Wald"
      }
    }
  ]
}
