{
  "geometry": {
    "type": "Point",
    "coordinates": [
      74.646086,
      34.03526
    ]
  },
  "type": "Feature",
  "properties": {
    "hierarchy": [
      "tgn:7588312",
      "tgn:1000004",
      "tgn:7000198",
      "tgn:7000799",
      "tgn:7029392"
    ],
    "placetype": [
      "aat:300008347"
    ],
    "name:en": "Mām",
    "id": 7588312
  }
}
