{
  "geometry": {
    "type": "Point",
    "coordinates": [
      -55.7167,
      -34.2167
    ]
  },
  "type": "Feature",
  "properties": {
    "hierarchy": [
      "tgn:1024898",
      "tgn:1000611",
      "tgn:1000002",
      "tgn:1000058",
      "tgn:7029392"
    ],
    "placetype": [
      "aat:300008347"
    ],
    "id": 1024898,
    "name:xx": "Fray Marcos"
  }
}
