{
  "geometry": {
    "type": "Point",
    "coordinates": [
      -78.3667,
      41.8333
    ]
  },
  "type": "Feature",
  "properties": {
    "hierarchy": [
      "tgn:2434981",
      "tgn:1000001",
      "tgn:7012149",
      "tgn:7016020",
      "tgn:7007710",
      "tgn:7029392"
    ],
    "placetype": [
      "aat:300008761"
    ],
    "id": 2434981,
    "name:xx": "Kent Hollow"
  }
}
