{
  "geometry": {
    "type": "Point",
    "coordinates": [
      -79.0833,
      37.0667
    ]
  },
  "type": "Feature",
  "properties": {
    "hierarchy": [
      "tgn:2112736",
      "tgn:1000001",
      "tgn:2002150",
      "tgn:7012149",
      "tgn:7007919",
      "tgn:7029392"
    ],
    "placetype": [
      "aat:300008347"
    ],
    "id": 2112736,
    "name:xx": "Long Island"
  }
}
