{
  "geometry": {
    "type": "Point",
    "coordinates": [
      -73.8833,
      42.1667
    ]
  },
  "type": "Feature",
  "properties": {
    "hierarchy": [
      "tgn:2410049",
      "tgn:1000001",
      "tgn:7012149",
      "tgn:1002423",
      "tgn:7007568",
      "tgn:7029392"
    ],
    "placetype": [
      "aat:300132316"
    ],
    "id": 2410049,
    "name:xx": "Inbocht Bay"
  }
}
