{
  "geometry": {
    "type": "Point",
    "coordinates": [
      -77.5667,
      42.3333
    ]
  },
  "type": "Feature",
  "properties": {
    "hierarchy": [
      "tgn:2406477",
      "tgn:1000001",
      "tgn:7012149",
      "tgn:1002920",
      "tgn:7007568",
      "tgn:7029392"
    ],
    "placetype": [
      "aat:300008761"
    ],
    "id": 2406477,
    "name:xx": "Hungry Hollow"
  }
}
