{
  "geometry": {
    "type": "Point",
    "coordinates": [
      -86.6667,
      35.7333
    ]
  },
  "type": "Feature",
  "properties": {
    "hierarchy": [
      "tgn:7023620",
      "tgn:1000001",
      "tgn:7012149",
      "tgn:7007825",
      "tgn:7029392"
    ],
    "placetype": [
      "aat:300008706"
    ],
    "id": 7023620,
    "name:xx": "Overall Creek"
  }
}
