{
  "geometry": {
    "type": "Point",
    "coordinates": [
      -159.1167,
      67.9833
    ]
  },
  "type": "Feature",
  "properties": {
    "hierarchy": [
      "tgn:2431085",
      "tgn:7006450",
      "tgn:1000001",
      "tgn:7012149",
      "tgn:7029392"
    ],
    "placetype": [
      "aat:300008680"
    ],
    "id": 2431085,
    "name:xx": "Kangilipak, Lake"
  }
}
