{
  "geometry": {
    "type": "Point",
    "coordinates": [
      -112.3333,
      46.4167
    ]
  },
  "type": "Feature",
  "properties": {
    "hierarchy": [
      "tgn:2559522",
      "tgn:1000001",
      "tgn:7012149",
      "tgn:2001298",
      "tgn:7007524",
      "tgn:7029392"
    ],
    "placetype": [
      "aat:300000390"
    ],
    "id": 2559522,
    "name:xx": "Ontario Millsite"
  }
}
