{
  "geometry": {
    "type": "Point",
    "coordinates": [
      -79.1167,
      39.3167
    ]
  },
  "type": "Feature",
  "properties": {
    "hierarchy": [
      "tgn:2668093",
      "tgn:1000001",
      "tgn:7012149",
      "tgn:2002279",
      "tgn:7013961",
      "tgn:7029392"
    ],
    "placetype": [
      "aat:300008347"
    ],
    "id": 2668093,
    "name:xx": "Skyline"
  }
}
