{
  "geometry": {
    "type": "Point",
    "coordinates": [
      33.5667,
      4.2667
    ]
  },
  "type": "Feature",
  "properties": {
    "hierarchy": [
      "tgn:1094386",
      "tgn:7001242",
      "tgn:1001082",
      "tgn:7441551",
      "tgn:7029392"
    ],
    "placetype": [
      "aat:300008347"
    ],
    "id": 1094386,
    "name:xx": "Nagishot"
  }
}
