{
  "geometry": {
    "type": "Point",
    "coordinates": [
      -78.95,
      42.3333
    ]
  },
  "type": "Feature",
  "properties": {
    "hierarchy": [
      "tgn:2068957",
      "tgn:1000001",
      "tgn:1002245",
      "tgn:7012149",
      "tgn:7007568",
      "tgn:7029392"
    ],
    "placetype": [
      "aat:300008347",
      "aat:300387210"
    ],
    "id": 2068957,
    "name:xx": "East Leon"
  }
}
