{
  "geometry": {
    "type": "Point",
    "coordinates": [
      -105.4833,
      40.5333
    ]
  },
  "type": "Feature",
  "properties": {
    "hierarchy": [
      "tgn:2514499",
      "tgn:1000001",
      "tgn:7012149",
      "tgn:2000226",
      "tgn:7007158",
      "tgn:7029392"
    ],
    "placetype": [
      "aat:300008699"
    ],
    "id": 2514499,
    "name:xx": "Miller Fork"
  }
}
