{
  "type": "FeatureCollection",
  "features": [
    {
      "geometry": {
        "type": "Point",
        "coordinates": [
          -9.4167,
          18.4333
        ]
      },
      "type": "Feature",
      "properties": {
        "hierarchy": [
          "tgn:6005950",
          "tgn:7001242",
          "tgn:1001755",
          "tgn:1000176",
          "tgn:7029392"
        ],
        "placetype": [
          "aat:300008347",
          "aat:300000810",
          "aat:300167671"
        ],
        "id": 6005950,
        "name:xx": "Tichitt"
      }
    },
    {
      "geometry": {
        "type": "Point",
        "coordinates": [
          121.2333,
          29.5
        ]
      },
      "type": "Feature",
      "properties": {
        "hierarchy": [
          "tgn:6005956",
          "tgn:1000004",
          "tgn:7002076",
          "tgn:1000111",
          "tgn:7029392"
        ],
        "placetype": [
          "aat:300008795"
        ],
        "id": 6005956,
        "name:xx": "T'ien-t'ai Shan"
      }
    },
    {
      "geometry": {
        "type": "Point",
        "coordinates": [
          6.13302,
          55.07419
        ]
      },
      "type": "Feature",
      "properties": {
        "hierarchy": [
          "tgn:6005959",
          "tgn:7002448",
          "tgn:7019157",
          "tgn:1000003",
          "tgn:7008591",
          "tgn:7029392"
        ],
        "placetype": [
          "aat:300387007",
          "aat:300000390",
          "aat:300387005",
          "aat:300008777"
        ],
        "id": 6005959,
        "name:xx": "Tievebulliagh"
      }
    }
  ]
}
