{
  "geometry": {
    "type": "Point",
    "coordinates": [
      -80.7667,
      37.4833
    ]
  },
  "type": "Feature",
  "properties": {
    "hierarchy": [
      "tgn:2767533",
      "tgn:1000001",
      "tgn:7012149",
      "tgn:2002282",
      "tgn:7013961",
      "tgn:7029392"
    ],
    "placetype": [
      "aat:300008798"
    ],
    "id": 2767533,
    "name:xx": "White Tree Hill"
  }
}
