{
  "geometry": {
    "type": "Point",
    "coordinates": [
      -112.05,
      43.3667
    ]
  },
  "type": "Feature",
  "properties": {
    "hierarchy": [
      "tgn:2263201",
      "tgn:1000001",
      "tgn:2000457",
      "tgn:7012149",
      "tgn:7007250",
      "tgn:7029392"
    ],
    "placetype": [
      "aat:300008347"
    ],
    "id": 2263201,
    "name:xx": "Cox"
  }
}
