{
  "geometry": {
    "type": "Point",
    "coordinates": [
      14.0833,
      15.0833
    ]
  },
  "type": "Feature",
  "properties": {
    "hierarchy": [
      "tgn:1112074",
      "tgn:7001242",
      "tgn:1000589",
      "tgn:1000181",
      "tgn:7029392"
    ],
    "placetype": [
      "aat:300387346"
    ],
    "id": 1112074,
    "name:xx": "Manga"
  }
}
