{
  "geometry": {
    "type": "Point",
    "coordinates": [
      -87.5333,
      37.2167
    ]
  },
  "type": "Feature",
  "properties": {
    "hierarchy": [
      "tgn:2587672",
      "tgn:1000001",
      "tgn:7012149",
      "tgn:2000801",
      "tgn:7007255",
      "tgn:7029392"
    ],
    "placetype": [
      "aat:300008699"
    ],
    "id": 2587672,
    "name:xx": "Pleasant Run"
  }
}
