{
  "geometry": {
    "type": "Point",
    "coordinates": [
      -89.7333,
      30.15
    ]
  },
  "type": "Feature",
  "properties": {
    "hierarchy": [
      "tgn:2577860",
      "tgn:1000001",
      "tgn:7012149",
      "tgn:2000889",
      "tgn:7007256",
      "tgn:7029392"
    ],
    "placetype": [
      "aat:300008791"
    ],
    "id": 2577860,
    "name:xx": "Petites Coquilles"
  }
}
