{
  "geometry": {
    "type": "Point",
    "coordinates": [
      -101.35,
      41.1167
    ]
  },
  "type": "Feature",
  "properties": {
    "hierarchy": [
      "tgn:2062543",
      "tgn:1000001",
      "tgn:2001366",
      "tgn:7012149",
      "tgn:7007525",
      "tgn:7029392"
    ],
    "placetype": [
      "aat:300008347"
    ],
    "id": 2062543,
    "name:xx": "Paxton"
  }
}
