{
  "geometry": {
    "type": "Point",
    "coordinates": [
      -112.3833,
      37.4833
    ]
  },
  "type": "Feature",
  "properties": {
    "hierarchy": [
      "tgn:2444473",
      "tgn:1000001",
      "tgn:7012149",
      "tgn:2002113",
      "tgn:7007827",
      "tgn:7029392"
    ],
    "placetype": [
      "aat:300008761"
    ],
    "id": 2444473,
    "name:xx": "Left Hand Canyon"
  }
}
