{
  "geometry": {
    "type": "Point",
    "coordinates": [
      -85.1333,
      31.7167
    ]
  },
  "type": "Feature",
  "properties": {
    "hierarchy": [
      "tgn:2591094",
      "tgn:7002659",
      "tgn:1000001",
      "tgn:7012149",
      "tgn:2000033",
      "tgn:7029392"
    ],
    "placetype": [
      "aat:300008699"
    ],
    "id": 2591094,
    "name:xx": "Polk Spring Branch"
  }
}
