{
  "geometry": {
    "type": "Point",
    "coordinates": [
      -103.7167,
      41.9167
    ]
  },
  "type": "Feature",
  "properties": {
    "hierarchy": [
      "tgn:2730894",
      "tgn:1000001",
      "tgn:7012149",
      "tgn:2001394",
      "tgn:7007525",
      "tgn:7029392"
    ],
    "placetype": [
      "aat:300008697"
    ],
    "id": 2730894,
    "name:xx": "Tub Springs"
  }
}
