{
  "geometry": {
    "type": "Point",
    "coordinates": [
      -99.2833,
      30.0667
    ]
  },
  "type": "Feature",
  "properties": {
    "hierarchy": [
      "tgn:2750239",
      "tgn:1000001",
      "tgn:7012149",
      "tgn:2002018",
      "tgn:7007826",
      "tgn:7029392"
    ],
    "placetype": [
      "aat:300008347"
    ],
    "id": 2750239,
    "name:xx": "Waltonia"
  }
}
