{
  "geometry": {
    "type": "Point",
    "coordinates": [
      -107.4833,
      40.8167
    ]
  },
  "type": "Feature",
  "properties": {
    "hierarchy": [
      "tgn:2494465",
      "tgn:1000001",
      "tgn:7012149",
      "tgn:2000232",
      "tgn:7007158",
      "tgn:7029392"
    ],
    "placetype": [
      "aat:300006191"
    ],
    "id": 2494465,
    "name:xx": "Martin Cull Reservoir"
  }
}
