{
  "geometry": {
    "type": "Point",
    "coordinates": [
      -75.05,
      43.45
    ]
  },
  "type": "Feature",
  "properties": {
    "hierarchy": [
      "tgn:2531270",
      "tgn:1000001",
      "tgn:7012149",
      "tgn:1002472",
      "tgn:7007568",
      "tgn:7029392"
    ],
    "placetype": [
      "aat:300008697"
    ],
    "id": 2531270,
    "name:xx": "Mulchy Spring"
  }
}
