{
  "geometry": {
    "type": "Point",
    "coordinates": [
      -110.35,
      46.1167
    ]
  },
  "type": "Feature",
  "properties": {
    "hierarchy": [
      "tgn:2677939",
      "tgn:1000001",
      "tgn:7012149",
      "tgn:7007524",
      "tgn:7029392"
    ],
    "placetype": [
      "aat:300008699"
    ],
    "id": 2677939,
    "name:xx": "South Fork American Fork"
  }
}
