{
  "geometry": {
    "type": "Point",
    "coordinates": [
      -115.9833,
      41.65
    ]
  },
  "type": "Feature",
  "properties": {
    "hierarchy": [
      "tgn:2289900",
      "tgn:1000001",
      "tgn:2001411",
      "tgn:7012149",
      "tgn:7007526",
      "tgn:7029392"
    ],
    "placetype": [
      "aat:300008706"
    ],
    "id": 2289900,
    "name:xx": "Doby George Creek"
  }
}
