{
  "geometry": {
    "type": "Point",
    "coordinates": [
      -108.25,
      32.1667
    ]
  },
  "type": "Feature",
  "properties": {
    "hierarchy": [
      "tgn:2368292",
      "tgn:1000001",
      "tgn:7012149",
      "tgn:2001437",
      "tgn:7007566",
      "tgn:7029392"
    ],
    "placetype": [
      "aat:300008347"
    ],
    "id": 2368292,
    "name:xx": "Guess Place"
  }
}
