{
  "geometry": {
    "type": "Point",
    "coordinates": [
      40.1667,
      47.4167
    ]
  },
  "type": "Feature",
  "properties": {
    "hierarchy": [
      "tgn:1131162",
      "tgn:1000003",
      "tgn:7029392"
    ],
    "placetype": [
      "aat:300008707"
    ],
    "id": 1131162,
    "name:xx": "Tuzlov"
  }
}
