{
  "geometry": {
    "type": "Point",
    "coordinates": [
      32.192,
      31.262
    ]
  },
  "type": "Feature",
  "properties": {
    "hierarchy": [
      "tgn:1117203",
      "tgn:7001242",
      "tgn:7016833",
      "tgn:1001123",
      "tgn:7029392"
    ],
    "placetype": [
      "aat:300008680"
    ],
    "id": 1117203,
    "name:xx": "Manzilah, Buḩayrat al"
  }
}
