{
  "geometry": {
    "type": "Point",
    "coordinates": [
      -97.85,
      30.3833
    ]
  },
  "type": "Feature",
  "properties": {
    "hierarchy": [
      "tgn:2206528",
      "tgn:1000001",
      "tgn:7012149",
      "tgn:1002952",
      "tgn:7007826",
      "tgn:7029392"
    ],
    "placetype": [
      "aat:300008761"
    ],
    "id": 2206528,
    "name:xx": "Bullick Hollow"
  }
}
