{
  "geometry": {
    "type": "Point",
    "coordinates": [
      72.9833,
      49.7333
    ]
  },
  "type": "Feature",
  "properties": {
    "hierarchy": [
      "tgn:1137147",
      "tgn:1000004",
      "tgn:7011459",
      "tgn:7014786",
      "tgn:7029392"
    ],
    "placetype": [
      "aat:300008347",
      "aat:300008375"
    ],
    "id": 1137147,
    "name:xx": "Aktas"
  }
}
