{
  "geometry": {
    "type": "Point",
    "coordinates": [
      -82.25,
      27.7667
    ]
  },
  "type": "Feature",
  "properties": {
    "hierarchy": [
      "tgn:2185152",
      "tgn:1000001",
      "tgn:1002479",
      "tgn:7012149",
      "tgn:7007240",
      "tgn:7029392"
    ],
    "placetype": [
      "aat:300008706"
    ],
    "id": 2185152,
    "name:xx": "Boggy Creek"
  }
}
