{
  "geometry": {
    "type": "Point",
    "coordinates": [
      -112.2333,
      32.35
    ]
  },
  "type": "Feature",
  "properties": {
    "hierarchy": [
      "tgn:2776775",
      "tgn:1000001",
      "tgn:7006451",
      "tgn:7012149",
      "tgn:2000100",
      "tgn:7029392"
    ],
    "placetype": [
      "aat:300008798"
    ],
    "id": 2776775,
    "name:xx": "Window Mountain"
  }
}
