{
  "type": "FeatureCollection",
  "features": [
    {
      "geometry": {
        "type": "Point",
        "coordinates": [
          -119.5833,
          38.6833
        ]
      },
      "type": "Feature",
      "properties": {
        "hierarchy": [
          "tgn:2291890",
          "tgn:1000001",
          "tgn:7012149",
          "tgn:7007157",
          "tgn:7029392"
        ],
        "placetype": [
          "aat:300008798"
        ],
        "id": 2291890,
        "name:xx": "Dome Two"
      }
    },
    {
      "geometry": {
        "type": "Point",
        "coordinates": [
          -114.2167,
          32.6667
        ]
      },
      "type": "Feature",
      "properties": {
        "hierarchy": [
          "tgn:2291891",
          "tgn:1000001",
          "tgn:7006451",
          "tgn:7012149",
          "tgn:2000104",
          "tgn:7029392"
        ],
        "placetype": [
          "aat:300008761"
        ],
        "id": 2291891,
        "name:xx": "Dome Valley"
      }
    },
    {
      "geometry": {
        "type": "Point",
        "coordinates": [
          -121.6833,
          41.8
        ]
      },
      "type": "Feature",
      "properties": {
        "hierarchy": [
          "tgn:2291892",
          "tgn:1000001",
          "tgn:7012149",
          "tgn:7007157",
          "tgn:2000189",
          "tgn:7029392"
        ],
        "placetype": [
          "aat:300008798"
        ],
        "id": 2291892,
        "name:xx": "Dome, Mount"
      }
    },
    {
      "geometry": {
        "type": "Point",
        "coordinates": [
          -110.1167,
          31.7
        ]
      },
      "type": "Feature",
      "properties": {
        "hierarchy": [
          "tgn:2291893",
          "tgn:1000001",
          "tgn:7006451",
          "tgn:2000091",
          "tgn:7012149",
          "tgn:7029392"
        ],
        "placetype": [
          "aat:300008798"
        ],
        "id": 2291893,
        "name:xx": "Dome, The"
      }
    },
    {
      "geometry": {
        "type": "Point",
        "coordinates": [
          -112.8833,
          36.2667
        ]
      },
      "type": "Feature",
      "properties": {
        "hierarchy": [
          "tgn:2291894",
          "tgn:1000001",
          "tgn:7006451",
          "tgn:7012149",
          "tgn:2000098",
          "tgn:7029392"
        ],
        "placetype": [
          "aat:300008798"
        ],
        "id": 2291894,
        "name:xx": "Dome, The"
      }
    },
    {
      "geometry": {
        "type": "Point",
        "coordinates": [
          -106.7,
          40.6833
        ]
      },
      "type": "Feature",
      "properties": {
        "hierarchy": [
          "tgn:2291895",
          "tgn:1000001",
          "tgn:7012149",
          "tgn:7007158",
          "tgn:2000245",
          "tgn:7029392"
        ],
        "placetype": [
          "aat:300008798"
        ],
        "id": 2291895,
        "name:xx": "Dome, The"
      }
    },
    {
      "geometry": {
        "type": "Point",
        "coordinates": [
          -116.6833,
          42.25
        ]
      },
      "type": "Feature",
      "properties": {
        "hierarchy": [
          "tgn:2291896",
          "tgn:1000001",
          "tgn:7012149",
          "tgn:2000488",
          "tgn:7007250",
          "tgn:7029392"
        ],
        "placetype": [
          "aat:300008798"
        ],
        "id": 2291896,
        "name:xx": "Dome, The"
      }
    },
    {
      "geometry": {
        "type": "Point",
        "coordinates": [
          -105.7,
          35.9667
        ]
      },
      "type": "Feature",
      "properties": {
        "hierarchy": [
          "tgn:2291897",
          "tgn:1000001",
          "tgn:7012149",
          "tgn:7007566",
          "tgn:7029392"
        ],
        "placetype": [
          "aat:300008798"
        ],
        "id": 2291897,
        "name:xx": "Dome, The"
      }
    },
    {
      "geometry": {
        "type": "Point",
        "coordinates": [
          -120.8333,
          42.4667
        ]
      },
      "type": "Feature",
      "properties": {
        "hierarchy": [
          "tgn:2291898",
          "tgn:1000001",
          "tgn:7012149",
          "tgn:2001715",
          "tgn:7007708",
          "tgn:7029392"
        ],
        "placetype": [
          "aat:300008798"
        ],
        "id": 2291898,
        "name:xx": "Dome, The"
      }
    },
    {
      "geometry": {
        "type": "Point",
        "coordinates": [
          -121.1833,
          43.6833
        ]
      },
      "type": "Feature",
      "properties": {
        "hierarchy": [
          "tgn:2291899",
          "tgn:1000001",
          "tgn:2001705",
          "tgn:7012149",
          "tgn:7007708",
          "tgn:7029392"
        ],
        "placetype": [
          "aat:300008798"
        ],
        "id": 2291899,
        "name:xx": "Dome, The"
      }
    }
  ]
}
