{
  "geometry": {
    "type": "Point",
    "coordinates": [
      32.55,
      25.266667
    ]
  },
  "type": "Feature",
  "properties": {
    "hierarchy": [
      "tgn:7526795",
      "tgn:7001242",
      "tgn:7016833",
      "tgn:7000123",
      "tgn:7029392"
    ],
    "placetype": [
      "aat:300343519"
    ],
    "name:en": "Wīsī, Ḩawḑ al",
    "id": 7526795
  }
}
