{
  "geometry": {
    "type": "Point",
    "coordinates": [
      100.65,
      1.4167
    ]
  },
  "type": "Feature",
  "properties": {
    "hierarchy": [
      "tgn:1078392",
      "tgn:1000004",
      "tgn:1001502",
      "tgn:1000116",
      "tgn:7029392"
    ],
    "placetype": [
      "aat:300008347"
    ],
    "id": 1078392,
    "name:xx": "Pujut"
  }
}
