{
  "geometry": {
    "type": "Point",
    "coordinates": [
      31.52957,
      30.060875
    ]
  },
  "type": "Feature",
  "properties": {
    "hierarchy": [
      "tgn:7537743",
      "tgn:7001242",
      "tgn:7016833",
      "tgn:7029392"
    ],
    "placetype": [
      "aat:300008777"
    ],
    "id": 7537743,
    "name:xx": "Nāşūrī, Jabal an"
  }
}
