{
  "geometry": {
    "type": "Point",
    "coordinates": [
      -70.9167,
      42.4833
    ]
  },
  "type": "Feature",
  "properties": {
    "hierarchy": [
      "tgn:2336199",
      "tgn:1000001",
      "tgn:1002359",
      "tgn:7012149",
      "tgn:7007517",
      "tgn:7029392"
    ],
    "placetype": [
      "aat:300008680"
    ],
    "id": 2336199,
    "name:xx": "Foster Pond"
  }
}
