{
  "geometry": {
    "type": "Point",
    "coordinates": [
      13.683333,
      52.95
    ]
  },
  "type": "Feature",
  "properties": {
    "hierarchy": [
      "tgn:7083840",
      "tgn:7000096",
      "tgn:1000003",
      "tgn:7000084",
      "tgn:7029392"
    ],
    "placetype": [
      "aat:300004792"
    ],
    "id": 7083840,
    "name:xx": "Försterei Wilhelmseichen"
  }
}
