{
  "geometry": {
    "type": "Point",
    "coordinates": [
      -74.7667,
      42.05
    ]
  },
  "type": "Feature",
  "properties": {
    "hierarchy": [
      "tgn:2739393",
      "tgn:1000001",
      "tgn:7012149",
      "tgn:7007568",
      "tgn:7029392"
    ],
    "placetype": [
      "aat:300008699"
    ],
    "id": 2739393,
    "name:xx": "Upper Beech Hill Brook"
  }
}
