{
  "geometry": {
    "type": "Point",
    "coordinates": [
      -102.441667,
      18.95
    ]
  },
  "type": "Feature",
  "properties": {
    "hierarchy": [
      "tgn:7409955",
      "tgn:1000001",
      "tgn:7005590",
      "tgn:7005560",
      "tgn:7029392"
    ],
    "placetype": [
      "aat:300008347"
    ],
    "id": 7409955,
    "name:xx": "Cuauhtémoc Cárdenas"
  }
}
