{
  "type": "FeatureCollection",
  "features": [
    {
      "geometry": {
        "type": "Point",
        "coordinates": [
          -86.5833,
          34.7667
        ]
      },
      "type": "Feature",
      "properties": {
        "hierarchy": [
          "tgn:2351490",
          "tgn:7002659",
          "tgn:1000001",
          "tgn:7012149",
          "tgn:2000044",
          "tgn:7029392"
        ],
        "placetype": [
          "aat:300008347"
        ],
        "id": 2351490,
        "name:xx": "Glen Park"
      }
    },
    {
      "geometry": {
        "type": "Point",
        "coordinates": [
          -83.5167,
          46
        ]
      },
      "type": "Feature",
      "properties": {
        "hierarchy": [
          "tgn:2351492",
          "tgn:1000001",
          "tgn:2000952",
          "tgn:7012149",
          "tgn:7007520",
          "tgn:7029392"
        ],
        "placetype": [
          "aat:300008850"
        ],
        "id": 2351492,
        "name:xx": "Glen Point"
      }
    },
    {
      "geometry": {
        "type": "Point",
        "coordinates": [
          -105.5,
          39.9333
        ]
      },
      "type": "Feature",
      "properties": {
        "hierarchy": [
          "tgn:2351493",
          "tgn:1000001",
          "tgn:2000198",
          "tgn:7012149",
          "tgn:7007158",
          "tgn:7029392"
        ],
        "placetype": [
          "aat:300006191"
        ],
        "id": 2351493,
        "name:xx": "Glen Reservoir"
      }
    },
    {
      "geometry": {
        "type": "Point",
        "coordinates": [
          -106.7167,
          47.9
        ]
      },
      "type": "Feature",
      "properties": {
        "hierarchy": [
          "tgn:2351494",
          "tgn:1000001",
          "tgn:7012149",
          "tgn:2001312",
          "tgn:7007524",
          "tgn:7029392"
        ],
        "placetype": [
          "aat:300006191"
        ],
        "id": 2351494,
        "name:xx": "Glen Reservoir"
      }
    },
    {
      "geometry": {
        "type": "Point",
        "coordinates": [
          -73.05,
          41.5
        ]
      },
      "type": "Feature",
      "properties": {
        "hierarchy": [
          "tgn:2351495",
          "tgn:1000001",
          "tgn:1002712",
          "tgn:7012149",
          "tgn:7007159",
          "tgn:7029392"
        ],
        "placetype": [
          "aat:300008347"
        ],
        "id": 2351495,
        "name:xx": "Glen Ridge"
      }
    },
    {
      "geometry": {
        "type": "Point",
        "coordinates": [
          -82.3333,
          36.3333
        ]
      },
      "type": "Feature",
      "properties": {
        "hierarchy": [
          "tgn:2351496",
          "tgn:1000001",
          "tgn:7012149",
          "tgn:2001926",
          "tgn:7007825",
          "tgn:7029392"
        ],
        "placetype": [
          "aat:300008347"
        ],
        "id": 2351496,
        "name:xx": "Glen Ridge"
      }
    },
    {
      "geometry": {
        "type": "Point",
        "coordinates": [
          -84.2667,
          39.1
        ]
      },
      "type": "Feature",
      "properties": {
        "hierarchy": [
          "tgn:2351497",
          "tgn:1000001",
          "tgn:1002279",
          "tgn:7012149",
          "tgn:7007706",
          "tgn:7029392"
        ],
        "placetype": [
          "aat:300008347"
        ],
        "id": 2351497,
        "name:xx": "Glen Ridge Acres"
      }
    },
    {
      "geometry": {
        "type": "Point",
        "coordinates": [
          -84.2667,
          39.1
        ]
      },
      "type": "Feature",
      "properties": {
        "hierarchy": [
          "tgn:2351498",
          "tgn:1000001",
          "tgn:1002279",
          "tgn:7012149",
          "tgn:7007706",
          "tgn:7029392"
        ],
        "placetype": [
          "aat:300006191"
        ],
        "id": 2351498,
        "name:xx": "Glen Ridge Lake"
      }
    },
    {
      "geometry": {
        "type": "Point",
        "coordinates": [
          -75.6333,
          42.35
        ]
      },
      "type": "Feature",
      "properties": {
        "hierarchy": [
          "tgn:2351499",
          "tgn:1000001",
          "tgn:1002262",
          "tgn:7012149",
          "tgn:7007568",
          "tgn:7029392"
        ],
        "placetype": [
          "aat:300008699"
        ],
        "id": 2351499,
        "name:xx": "Glen Road Brook"
      }
    }
  ]
}
