{
  "geometry": {
    "type": "Point",
    "coordinates": [
      -90.7667,
      40.8667
    ]
  },
  "type": "Feature",
  "properties": {
    "hierarchy": [
      "tgn:2774405",
      "tgn:1000001",
      "tgn:2000589",
      "tgn:7012149",
      "tgn:7007253",
      "tgn:7029392"
    ],
    "placetype": [
      "aat:300008680"
    ],
    "id": 2774405,
    "name:xx": "Willow Lake"
  }
}
