{
  "geometry": {
    "type": "Point",
    "coordinates": [
      -77.0333,
      35.4667
    ]
  },
  "type": "Feature",
  "properties": {
    "hierarchy": [
      "tgn:2616422",
      "tgn:1000001",
      "tgn:7013368",
      "tgn:7012149",
      "tgn:7007709",
      "tgn:7029392"
    ],
    "placetype": [
      "aat:300008706"
    ],
    "id": 2616422,
    "name:xx": "Rice Creek"
  }
}
