{
  "geometry": {
    "type": "Point",
    "coordinates": [
      -141.35,
      64.1833
    ]
  },
  "type": "Feature",
  "properties": {
    "hierarchy": [
      "tgn:2357684",
      "tgn:7006450",
      "tgn:1000001",
      "tgn:7012149",
      "tgn:2000085",
      "tgn:7029392"
    ],
    "placetype": [
      "aat:300008706"
    ],
    "id": 2357684,
    "name:xx": "Grace Creek"
  }
}
