{
  "geometry": {
    "type": "Point",
    "coordinates": [
      -90.6167,
      32.75
    ]
  },
  "type": "Feature",
  "properties": {
    "hierarchy": [
      "tgn:2347569",
      "tgn:1000001",
      "tgn:7012149",
      "tgn:2001167",
      "tgn:7007522",
      "tgn:7029392"
    ],
    "placetype": [
      "aat:300008680"
    ],
    "id": 2347569,
    "name:xx": "George, Lake"
  }
}
