{
  "type": "FeatureCollection",
  "features": [
    {
      "geometry": {
        "type": "Point",
        "coordinates": [
          -98.016667,
          26.05
        ]
      },
      "type": "Feature",
      "properties": {
        "hierarchy": [
          "tgn:7436560",
          "tgn:1000001",
          "tgn:7005597",
          "tgn:7005560",
          "tgn:7029392"
        ],
        "placetype": [
          "aat:300008347"
        ],
        "id": 7436560,
        "name:xx": "Santo Domingo"
      }
    },
    {
      "geometry": {
        "type": "Point",
        "coordinates": [
          -97.316667,
          25.9
        ]
      },
      "type": "Feature",
      "properties": {
        "hierarchy": [
          "tgn:7436561",
          "tgn:1000001",
          "tgn:7005597",
          "tgn:7005560",
          "tgn:7029392"
        ],
        "placetype": [
          "aat:300008347"
        ],
        "id": 7436561,
        "name:xx": "Santo Domingo"
      }
    },
    {
      "geometry": {
        "type": "Point",
        "coordinates": [
          -98.3,
          25.766667
        ]
      },
      "type": "Feature",
      "properties": {
        "hierarchy": [
          "tgn:7436564",
          "tgn:1000001",
          "tgn:7005597",
          "tgn:7005560",
          "tgn:7029392"
        ],
        "placetype": [
          "aat:300008347"
        ],
        "id": 7436564,
        "name:xx": "Santo Domingo"
      }
    },
    {
      "geometry": {
        "type": "Point",
        "coordinates": [
          -100.233333,
          25.75
        ]
      },
      "type": "Feature",
      "properties": {
        "hierarchy": [
          "tgn:7436565",
          "tgn:1000001",
          "tgn:7005589",
          "tgn:7005560",
          "tgn:7029392"
        ],
        "placetype": [
          "aat:300008347"
        ],
        "id": 7436565,
        "name:xx": "Santo Domingo"
      }
    },
    {
      "geometry": {
        "type": "Point",
        "coordinates": [
          -111.533333,
          25.733333
        ]
      },
      "type": "Feature",
      "properties": {
        "hierarchy": [
          "tgn:7436566",
          "tgn:1001836",
          "tgn:1000001",
          "tgn:7005560",
          "tgn:7029392"
        ],
        "placetype": [
          "aat:300008347"
        ],
        "id": 7436566,
        "name:xx": "Santo Domingo"
      }
    },
    {
      "geometry": {
        "type": "Point",
        "coordinates": [
          -105.15,
          24.966667
        ]
      },
      "type": "Feature",
      "properties": {
        "hierarchy": [
          "tgn:7436568",
          "tgn:7005583",
          "tgn:1000001",
          "tgn:7005560",
          "tgn:7029392"
        ],
        "placetype": [
          "aat:300008347"
        ],
        "id": 7436568,
        "name:xx": "Santo Domingo"
      }
    },
    {
      "geometry": {
        "type": "Point",
        "coordinates": [
          -99.624167,
          24.795833
        ]
      },
      "type": "Feature",
      "properties": {
        "hierarchy": [
          "tgn:7436569",
          "tgn:1000001",
          "tgn:7005589",
          "tgn:7005560",
          "tgn:7029392"
        ],
        "placetype": [
          "aat:300008347"
        ],
        "id": 7436569,
        "name:xx": "Santo Domingo"
      }
    }
  ]
}
