{
  "geometry": {
    "type": "Point",
    "coordinates": [
      -93.1667,
      37.75
    ]
  },
  "type": "Feature",
  "properties": {
    "hierarchy": [
      "tgn:2772021",
      "tgn:1000001",
      "tgn:7012149",
      "tgn:7007523",
      "tgn:7029392"
    ],
    "placetype": [
      "aat:300008706"
    ],
    "id": 2772021,
    "name:xx": "Wilkinson Creek"
  }
}
