{
  "geometry": {
    "type": "Point",
    "coordinates": [
      -70.35,
      41.6833
    ]
  },
  "type": "Feature",
  "properties": {
    "hierarchy": [
      "tgn:2194152",
      "tgn:1002165",
      "tgn:1000001",
      "tgn:7012149",
      "tgn:7007517",
      "tgn:7029392"
    ],
    "placetype": [
      "aat:300008706"
    ],
    "id": 2194152,
    "name:xx": "Brickyard Creek"
  }
}
