{
  "type": "FeatureCollection",
  "features": [
    {
      "geometry": {
        "type": "Point",
        "coordinates": [
          -5,
          54.833333
        ]
      },
      "type": "Feature",
      "properties": {
        "hierarchy": [
          "tgn:1012961",
          "tgn:7002444",
          "tgn:7008074",
          "tgn:1000003",
          "tgn:7008591",
          "tgn:7029392"
        ],
        "placetype": [
          "aat:300008804"
        ],
        "name:en": "Rhins, The",
        "id": 1012961
      }
    },
    {
      "geometry": {
        "type": "Point",
        "coordinates": [
          -122.4667,
          37.8833
        ]
      },
      "type": "Feature",
      "properties": {
        "hierarchy": [
          "tgn:1012962",
          "tgn:1000001",
          "tgn:7012149",
          "tgn:7007157",
          "tgn:7014005",
          "tgn:7029392"
        ],
        "placetype": [
          "aat:300008804"
        ],
        "id": 1012962,
        "name:xx": "Tiburon Peninsula"
      }
    },
    {
      "geometry": {
        "type": "Point",
        "coordinates": [
          -122.7667,
          47.75
        ]
      },
      "type": "Feature",
      "properties": {
        "hierarchy": [
          "tgn:1012963",
          "tgn:1000001",
          "tgn:7012149",
          "tgn:1002521",
          "tgn:7007920",
          "tgn:7029392"
        ],
        "placetype": [
          "aat:300008804"
        ],
        "id": 1012963,
        "name:xx": "Toandos Peninsula"
      }
    },
    {
      "geometry": {
        "type": "Point",
        "coordinates": [
          -75.5,
          -46.833333
        ]
      },
      "type": "Feature",
      "properties": {
        "hierarchy": [
          "tgn:1012965",
          "tgn:1001623",
          "tgn:1000049",
          "tgn:1000002",
          "tgn:7029392"
        ],
        "placetype": [
          "aat:300008804"
        ],
        "id": 1012965,
        "name:xx": "Tres Montes, Península"
      }
    },
    {
      "geometry": {
        "type": "Point",
        "coordinates": [
          -131.3333,
          69.75
        ]
      },
      "type": "Feature",
      "properties": {
        "hierarchy": [
          "tgn:1012968",
          "tgn:7005685",
          "tgn:1000001",
          "tgn:1000296",
          "tgn:7029392"
        ],
        "placetype": [
          "aat:300008804"
        ],
        "id": 1012968,
        "name:xx": "Tuktoyaktuk Peninsula"
      }
    },
    {
      "geometry": {
        "type": "Point",
        "coordinates": [
          -12.35,
          7.35
        ]
      },
      "type": "Feature",
      "properties": {
        "hierarchy": [
          "tgn:1012969",
          "tgn:7001242",
          "tgn:1001543",
          "tgn:1000191",
          "tgn:7029392"
        ],
        "placetype": [
          "aat:300008804"
        ],
        "id": 1012969,
        "name:xx": "Turners Peninsula"
      }
    }
  ]
}
