{
  "geometry": {
    "type": "Point",
    "coordinates": [
      31.830002,
      26.276384
    ]
  },
  "type": "Feature",
  "properties": {
    "hierarchy": [
      "tgn:7521113",
      "tgn:7001242",
      "tgn:7016833",
      "tgn:7001334",
      "tgn:7029392"
    ],
    "placetype": [
      "aat:300008347"
    ],
    "name:en": "Al Maḩāsinah",
    "id": 7521113
  }
}
