{
  "geometry": {
    "type": "Point",
    "coordinates": [
      -90.0167,
      41.0167
    ]
  },
  "type": "Feature",
  "properties": {
    "hierarchy": [
      "tgn:2192510",
      "tgn:1000001",
      "tgn:7012149",
      "tgn:7007251",
      "tgn:7029392"
    ],
    "placetype": [
      "aat:300008706"
    ],
    "id": 2192510,
    "name:xx": "Brandywine Creek"
  }
}
