{
  "geometry": {
    "type": "Point",
    "coordinates": [
      -89.3333,
      43.05
    ]
  },
  "type": "Feature",
  "properties": {
    "hierarchy": [
      "tgn:2689175",
      "tgn:1000001",
      "tgn:1002316",
      "tgn:7012149",
      "tgn:7007922",
      "tgn:7029392"
    ],
    "placetype": [
      "aat:300132316"
    ],
    "id": 2689175,
    "name:xx": "Squaw Bay"
  }
}
