{
  "geometry": {
    "type": "Point",
    "coordinates": [
      -88.9167,
      44.35
    ]
  },
  "type": "Feature",
  "properties": {
    "hierarchy": [
      "tgn:2766232",
      "tgn:1000001",
      "tgn:7012149",
      "tgn:2002361",
      "tgn:7007922",
      "tgn:7029392"
    ],
    "placetype": [
      "aat:300008680"
    ],
    "id": 2766232,
    "name:xx": "White Lake"
  }
}
