{
  "geometry": {
    "type": "Point",
    "coordinates": [
      -80.1667,
      37.3667
    ]
  },
  "type": "Feature",
  "properties": {
    "hierarchy": [
      "tgn:2515068",
      "tgn:1000001",
      "tgn:7012149",
      "tgn:2002154",
      "tgn:7007919",
      "tgn:7029392"
    ],
    "placetype": [
      "aat:300008761"
    ],
    "id": 2515068,
    "name:xx": "Millers Cove"
  }
}
