{
  "geometry": {
    "type": "Point",
    "coordinates": [
      5.8667,
      48.95
    ]
  },
  "type": "Feature",
  "properties": {
    "hierarchy": [
      "tgn:1035850",
      "tgn:1000003",
      "tgn:7002888",
      "tgn:1000070",
      "tgn:7029392"
    ],
    "placetype": [
      "aat:300008347"
    ],
    "id": 1035850,
    "name:xx": "Thiaucourt-Regniéville"
  }
}
