{
  "geometry": {
    "type": "Point",
    "coordinates": [
      -83.4333,
      36.6667
    ]
  },
  "type": "Feature",
  "properties": {
    "hierarchy": [
      "tgn:1106975",
      "tgn:1000001",
      "tgn:7012149",
      "tgn:7029392"
    ],
    "placetype": [
      "aat:300008795"
    ],
    "id": 1106975,
    "name:xx": "White Rocks"
  }
}
