{
  "geometry": {
    "type": "Point",
    "coordinates": [
      -107.5333,
      35.2833
    ]
  },
  "type": "Feature",
  "properties": {
    "hierarchy": [
      "tgn:2561535",
      "tgn:1000001",
      "tgn:2001431",
      "tgn:7012149",
      "tgn:7007566",
      "tgn:7029392"
    ],
    "placetype": [
      "aat:300008798"
    ],
    "id": 2561535,
    "name:xx": "Osha, Cerro"
  }
}
