{
  "geometry": {
    "type": "Point",
    "coordinates": [
      47.6833,
      30.3833
    ]
  },
  "type": "Feature",
  "properties": {
    "hierarchy": [
      "tgn:1079413",
      "tgn:1001072",
      "tgn:1000004",
      "tgn:1000118",
      "tgn:7029392"
    ],
    "placetype": [
      "aat:300008347"
    ],
    "id": 1079413,
    "name:xx": "Az-Zubayr"
  }
}
