{
  "type": "FeatureCollection",
  "features": [
    {
      "geometry": {
        "type": "Point",
        "coordinates": [
          29.75,
          31.066667
        ]
      },
      "type": "Feature",
      "properties": {
        "hierarchy": [
          "tgn:7536940",
          "tgn:7001242",
          "tgn:7016833",
          "tgn:1001079",
          "tgn:7029392"
        ],
        "placetype": [
          "aat:300008347"
        ],
        "name:en": "'Izbat 'Umar Abū Ḩafīz̧ah",
        "id": 7536940
      }
    },
    {
      "geometry": {
        "type": "Point",
        "coordinates": [
          29.237534,
          25.483297
        ]
      },
      "type": "Feature",
      "properties": {
        "hierarchy": [
          "tgn:7536941",
          "tgn:7001242",
          "tgn:7016833",
          "tgn:7001334",
          "tgn:7029392"
        ],
        "placetype": [
          "aat:300008347"
        ],
        "name:en": "'Izbat Ţulayţilah",
        "id": 7536941
      }
    },
    {
      "geometry": {
        "type": "Point",
        "coordinates": [
          31.076495,
          30.819044
        ]
      },
      "type": "Feature",
      "properties": {
        "hierarchy": [
          "tgn:7536942",
          "tgn:7001242",
          "tgn:7016833",
          "tgn:7001312",
          "tgn:7029392"
        ],
        "placetype": [
          "aat:300008347"
        ],
        "name:en": "'Izbat Ţūkh",
        "id": 7536942
      }
    },
    {
      "geometry": {
        "type": "Point",
        "coordinates": [
          35.41324,
          24.212273
        ]
      },
      "type": "Feature",
      "properties": {
        "hierarchy": [
          "tgn:7536943",
          "tgn:7001242",
          "tgn:7001311",
          "tgn:7016833",
          "tgn:7029392"
        ],
        "placetype": [
          "aat:300379998"
        ],
        "name:en": "Laḩmī, Wādī",
        "id": 7536943
      }
    },
    {
      "geometry": {
        "type": "Point",
        "coordinates": [
          32.875594,
          29.254385
        ]
      },
      "type": "Feature",
      "properties": {
        "hierarchy": [
          "tgn:7536945",
          "tgn:7001242",
          "tgn:7016833",
          "tgn:7001336",
          "tgn:7029392"
        ],
        "placetype": [
          "aat:300386846"
        ],
        "id": 7536945,
        "name:xx": "Lajjīah, Ra's"
      }
    },
    {
      "geometry": {
        "type": "Point",
        "coordinates": [
          33.533333,
          30.816667
        ]
      },
      "type": "Feature",
      "properties": {
        "hierarchy": [
          "tgn:7536946",
          "tgn:7001242",
          "tgn:7016833",
          "tgn:7001335",
          "tgn:7029392"
        ],
        "placetype": [
          "aat:300379998"
        ],
        "name:en": "Lagama, Wâdi el-",
        "id": 7536946
      }
    },
    {
      "geometry": {
        "type": "Point",
        "coordinates": [
          27.032591,
          30.252216
        ]
      },
      "type": "Feature",
      "properties": {
        "hierarchy": [
          "tgn:7536947",
          "tgn:7001242",
          "tgn:7016833",
          "tgn:1001418",
          "tgn:7029392"
        ],
        "placetype": [
          "aat:300008777"
        ],
        "name:en": "Lafi, Kolef el",
        "id": 7536947
      }
    },
    {
      "geometry": {
        "type": "Point",
        "coordinates": [
          30.2125,
          30.947222
        ]
      },
      "type": "Feature",
      "properties": {
        "hierarchy": [
          "tgn:7536948",
          "tgn:7001242",
          "tgn:1001075",
          "tgn:7016833",
          "tgn:7029392"
        ],
        "placetype": [
          "aat:300000206"
        ],
        "name:en": "'Ezbet el-Lâfi",
        "id": 7536948
      }
    }
  ]
}
