{
  "geometry": {
    "type": "Point",
    "coordinates": [
      -106.6833,
      40.5667
    ]
  },
  "type": "Feature",
  "properties": {
    "hierarchy": [
      "tgn:2234128",
      "tgn:1000001",
      "tgn:7012149",
      "tgn:2000220",
      "tgn:7007158",
      "tgn:7029392"
    ],
    "placetype": [
      "aat:300008706"
    ],
    "id": 2234128,
    "name:xx": "Chedsey Creek"
  }
}
