{
  "geometry": {
    "type": "Point",
    "coordinates": [
      -108.2167,
      38.0667
    ]
  },
  "type": "Feature",
  "properties": {
    "hierarchy": [
      "tgn:2257297",
      "tgn:1000001",
      "tgn:7012149",
      "tgn:7007158",
      "tgn:2000248",
      "tgn:7029392"
    ],
    "placetype": [
      "aat:300006075"
    ],
    "id": 2257297,
    "name:xx": "Cornforth Ditch"
  }
}
