{
  "geometry": {
    "type": "Point",
    "coordinates": [
      -91.0833,
      43.0833
    ]
  },
  "type": "Feature",
  "properties": {
    "hierarchy": [
      "tgn:2217447",
      "tgn:1000001",
      "tgn:2002316",
      "tgn:7012149",
      "tgn:7007922",
      "tgn:7029392"
    ],
    "placetype": [
      "aat:300008761"
    ],
    "id": 2217447,
    "name:xx": "Campbell Coulee"
  }
}
