{
  "geometry": {
    "type": "Point",
    "coordinates": [
      -80.95,
      32.2333
    ]
  },
  "type": "Feature",
  "properties": {
    "hierarchy": [
      "tgn:2096517",
      "tgn:2001731",
      "tgn:1000001",
      "tgn:7012149",
      "tgn:7007712",
      "tgn:7029392"
    ],
    "placetype": [
      "aat:300008347",
      "aat:300387210"
    ],
    "id": 2096517,
    "name:xx": "Pritchardville"
  }
}
