{
  "geometry": {
    "type": "Point",
    "coordinates": [
      -76.0833,
      41.9167
    ]
  },
  "type": "Feature",
  "properties": {
    "hierarchy": [
      "tgn:2703218",
      "tgn:1000001",
      "tgn:7012149",
      "tgn:1002932",
      "tgn:7007710",
      "tgn:7029392"
    ],
    "placetype": [
      "aat:300008706"
    ],
    "id": 2703218,
    "name:xx": "Summers Creek"
  }
}
