{
  "geometry": {
    "type": "Point",
    "coordinates": [
      -98.7667,
      30.3333
    ]
  },
  "type": "Feature",
  "properties": {
    "hierarchy": [
      "tgn:2547956",
      "tgn:1000001",
      "tgn:7012149",
      "tgn:7007826",
      "tgn:7029392"
    ],
    "placetype": [
      "aat:300008706"
    ],
    "id": 2547956,
    "name:xx": "North Grape Creek"
  }
}
