{
  "geometry": {
    "type": "Point",
    "coordinates": [
      -98.0333,
      29.5167
    ]
  },
  "type": "Feature",
  "properties": {
    "hierarchy": [
      "tgn:2217416",
      "tgn:1000001",
      "tgn:7012149",
      "tgn:1002431",
      "tgn:7007826",
      "tgn:7029392"
    ],
    "placetype": [
      "aat:300008699"
    ],
    "id": 2217416,
    "name:xx": "Campbell Branch"
  }
}
