{
  "geometry": {
    "type": "Point",
    "coordinates": [
      -73.8833,
      44.75
    ]
  },
  "type": "Feature",
  "properties": {
    "hierarchy": [
      "tgn:2191761",
      "tgn:1000001",
      "tgn:1002284",
      "tgn:7012149",
      "tgn:7007568",
      "tgn:7029392"
    ],
    "placetype": [
      "aat:300008680"
    ],
    "id": 2191761,
    "name:xx": "Bradley Pond"
  }
}
