{
  "geometry": {
    "type": "Point",
    "coordinates": [
      36.4667,
      36.3667
    ]
  },
  "type": "Feature",
  "properties": {
    "hierarchy": [
      "tgn:1120899",
      "tgn:1000004",
      "tgn:7029392"
    ],
    "placetype": [
      "aat:300008707"
    ],
    "id": 1120899,
    "name:xx": "ʻAfrīn"
  }
}
