{
  "type": "FeatureCollection",
  "features": [
    {
      "geometry": {
        "type": "Point",
        "coordinates": [
          -2.916667,
          58.783333
        ]
      },
      "type": "Feature",
      "properties": {
        "hierarchy": [
          "tgn:7447460",
          "tgn:7002444",
          "tgn:1000003",
          "tgn:7009907",
          "tgn:7008591",
          "tgn:7029392"
        ],
        "placetype": [
          "aat:300386846"
        ],
        "name:en": "Stews Taing",
        "id": 7447460
      }
    },
    {
      "geometry": {
        "type": "Point",
        "coordinates": [
          -3.683333,
          56.6
        ]
      },
      "type": "Feature",
      "properties": {
        "hierarchy": [
          "tgn:7447464",
          "tgn:7002444",
          "tgn:1000003",
          "tgn:7019152",
          "tgn:7008591",
          "tgn:7029392"
        ],
        "placetype": [
          "aat:300008347"
        ],
        "name:en": "Stewartfield",
        "id": 7447464
      }
    },
    {
      "geometry": {
        "type": "Point",
        "coordinates": [
          -4.533333,
          54.983333
        ]
      },
      "type": "Feature",
      "properties": {
        "hierarchy": [
          "tgn:7447465",
          "tgn:7002444",
          "tgn:7008074",
          "tgn:1000003",
          "tgn:7008591",
          "tgn:7029392"
        ],
        "placetype": [
          "aat:300004792"
        ],
        "name:en": "Castle Stewart",
        "id": 7447465
      }
    },
    {
      "geometry": {
        "type": "Point",
        "coordinates": [
          -1.316667,
          51.616667
        ]
      },
      "type": "Feature",
      "properties": {
        "hierarchy": [
          "tgn:7447467",
          "tgn:7002445",
          "tgn:1000003",
          "tgn:7008168",
          "tgn:7008591",
          "tgn:7029392"
        ],
        "placetype": [
          "aat:300008347"
        ],
        "name:en": "Steventon",
        "id": 7447467
      }
    }
  ]
}
