{
  "type": "FeatureCollection",
  "features": [
    {
      "geometry": {
        "type": "Point",
        "coordinates": [
          -115.4833,
          46.6
        ]
      },
      "type": "Feature",
      "properties": {
        "hierarchy": [
          "tgn:2512590",
          "tgn:1000001",
          "tgn:2000469",
          "tgn:7012149",
          "tgn:7007250",
          "tgn:7029392"
        ],
        "placetype": [
          "aat:300008706"
        ],
        "id": 2512590,
        "name:xx": "Mill Creek"
      }
    },
    {
      "geometry": {
        "type": "Point",
        "coordinates": [
          -116.05,
          48.8667
        ]
      },
      "type": "Feature",
      "properties": {
        "hierarchy": [
          "tgn:2512591",
          "tgn:1000001",
          "tgn:2000462",
          "tgn:7012149",
          "tgn:7007250",
          "tgn:7029392"
        ],
        "placetype": [
          "aat:300008706"
        ],
        "id": 2512591,
        "name:xx": "Mill Creek"
      }
    },
    {
      "geometry": {
        "type": "Point",
        "coordinates": [
          -112.4333,
          44.45
        ]
      },
      "type": "Feature",
      "properties": {
        "hierarchy": [
          "tgn:2512592",
          "tgn:1000001",
          "tgn:2000468",
          "tgn:7012149",
          "tgn:7007250",
          "tgn:7029392"
        ],
        "placetype": [
          "aat:300008706"
        ],
        "id": 2512592,
        "name:xx": "Mill Creek"
      }
    },
    {
      "geometry": {
        "type": "Point",
        "coordinates": [
          -111.2167,
          43.45
        ]
      },
      "type": "Feature",
      "properties": {
        "hierarchy": [
          "tgn:2512593",
          "tgn:1000001",
          "tgn:2000461",
          "tgn:7012149",
          "tgn:7007250",
          "tgn:7029392"
        ],
        "placetype": [
          "aat:300008706"
        ],
        "id": 2512593,
        "name:xx": "Mill Creek"
      }
    },
    {
      "geometry": {
        "type": "Point",
        "coordinates": [
          -88.8167,
          37.3833
        ]
      },
      "type": "Feature",
      "properties": {
        "hierarchy": [
          "tgn:2512594",
          "tgn:1000001",
          "tgn:7012149",
          "tgn:2000515",
          "tgn:7007251",
          "tgn:7029392"
        ],
        "placetype": [
          "aat:300008706"
        ],
        "id": 2512594,
        "name:xx": "Mill Creek"
      }
    },
    {
      "geometry": {
        "type": "Point",
        "coordinates": [
          -90.4667,
          40.1
        ]
      },
      "type": "Feature",
      "properties": {
        "hierarchy": [
          "tgn:2512595",
          "tgn:1000001",
          "tgn:7012149",
          "tgn:1002874",
          "tgn:7007251",
          "tgn:7029392"
        ],
        "placetype": [
          "aat:300008706"
        ],
        "id": 2512595,
        "name:xx": "Mill Creek"
      }
    },
    {
      "geometry": {
        "type": "Point",
        "coordinates": [
          -87.8333,
          41.65
        ]
      },
      "type": "Feature",
      "properties": {
        "hierarchy": [
          "tgn:2512596",
          "tgn:1000001",
          "tgn:7013649",
          "tgn:7012149",
          "tgn:7007251",
          "tgn:7029392"
        ],
        "placetype": [
          "aat:300008706"
        ],
        "id": 2512596,
        "name:xx": "Mill Creek"
      }
    },
    {
      "geometry": {
        "type": "Point",
        "coordinates": [
          -91.2,
          39.9833
        ]
      },
      "type": "Feature",
      "properties": {
        "hierarchy": [
          "tgn:2512597",
          "tgn:1002134",
          "tgn:1000001",
          "tgn:7012149",
          "tgn:7007251",
          "tgn:7029392"
        ],
        "placetype": [
          "aat:300008706"
        ],
        "id": 2512597,
        "name:xx": "Mill Creek"
      }
    },
    {
      "geometry": {
        "type": "Point",
        "coordinates": [
          -90.55,
          41.45
        ]
      },
      "type": "Feature",
      "properties": {
        "hierarchy": [
          "tgn:2512598",
          "tgn:1000001",
          "tgn:7012149",
          "tgn:2000528",
          "tgn:7007251",
          "tgn:7029392"
        ],
        "placetype": [
          "aat:300008706"
        ],
        "id": 2512598,
        "name:xx": "Mill Creek"
      }
    },
    {
      "geometry": {
        "type": "Point",
        "coordinates": [
          -89.9,
          38.7167
        ]
      },
      "type": "Feature",
      "properties": {
        "hierarchy": [
          "tgn:2512599",
          "tgn:1000001",
          "tgn:7012149",
          "tgn:1002622",
          "tgn:7007251",
          "tgn:7029392"
        ],
        "placetype": [
          "aat:300008706"
        ],
        "id": 2512599,
        "name:xx": "Mill Creek"
      }
    }
  ]
}
