{
  "geometry": {
    "type": "Point",
    "coordinates": [
      -81.6833,
      36.6167
    ]
  },
  "type": "Feature",
  "properties": {
    "hierarchy": [
      "tgn:2766487",
      "tgn:1000001",
      "tgn:7012149",
      "tgn:2002194",
      "tgn:7007919",
      "tgn:7029392"
    ],
    "placetype": [
      "aat:300008699"
    ],
    "id": 2766487,
    "name:xx": "White Oak Branch"
  }
}
