{
  "geometry": {
    "type": "Point",
    "coordinates": [
      -120.8167,
      39.8667
    ]
  },
  "type": "Feature",
  "properties": {
    "hierarchy": [
      "tgn:2317826",
      "tgn:1000001",
      "tgn:7012149",
      "tgn:7007157",
      "tgn:2000187",
      "tgn:7029392"
    ],
    "placetype": [
      "aat:300132348"
    ],
    "id": 2317826,
    "name:xx": "English Bar"
  }
}
