{
  "type": "FeatureCollection",
  "features": [
    {
      "geometry": {
        "type": "Point",
        "coordinates": [
          18.0833,
          42.6667
        ]
      },
      "type": "Feature",
      "properties": {
        "hierarchy": [
          "tgn:4006130",
          "tgn:7017310",
          "tgn:1000003",
          "tgn:7006663",
          "tgn:7029392"
        ],
        "placetype": [
          "aat:300008347"
        ],
        "id": 4006130,
        "name:xx": "Lapad"
      }
    },
    {
      "geometry": {
        "type": "Point",
        "coordinates": [
          13.766667,
          43.1
        ]
      },
      "type": "Feature",
      "properties": {
        "hierarchy": [
          "tgn:4006131",
          "tgn:1003432",
          "tgn:1000003",
          "tgn:7003240",
          "tgn:1000080",
          "tgn:7029392"
        ],
        "placetype": [
          "aat:300008347"
        ],
        "id": 4006131,
        "name:xx": "Lapedona"
      }
    },
    {
      "geometry": {
        "type": "Point",
        "coordinates": [
          -3.25,
          36.833333
        ]
      },
      "type": "Feature",
      "properties": {
        "hierarchy": [
          "tgn:4006139",
          "tgn:7002758",
          "tgn:7002821",
          "tgn:1000003",
          "tgn:1000095",
          "tgn:7029392"
        ],
        "placetype": [
          "aat:300386831",
          "aat:300008795"
        ],
        "id": 4006139,
        "name:xx": "Las Alpujarras"
      }
    }
  ]
}
