{
  "geometry": {
    "type": "Point",
    "coordinates": [
      73.15,
      20.166667
    ]
  },
  "type": "Feature",
  "properties": {
    "hierarchy": [
      "tgn:7545305",
      "tgn:1000004",
      "tgn:1001992",
      "tgn:7000198",
      "tgn:7029392"
    ],
    "placetype": [
      "aat:300008347"
    ],
    "name:en": "Ambābāri",
    "id": 7545305
  }
}
