{
  "geometry": {
    "type": "Point",
    "coordinates": [
      -88.3667,
      37.1333
    ]
  },
  "type": "Feature",
  "properties": {
    "hierarchy": [
      "tgn:2430561",
      "tgn:1000001",
      "tgn:7012149",
      "tgn:2000814",
      "tgn:7007255",
      "tgn:7029392"
    ],
    "placetype": [
      "aat:300000390"
    ],
    "id": 2430561,
    "name:xx": "Kalberer Quarry"
  }
}
