{
  "type": "FeatureCollection",
  "features": [
    {
      "geometry": {
        "type": "Point",
        "coordinates": [
          31.72934,
          30.501339
        ]
      },
      "type": "Feature",
      "properties": {
        "hierarchy": [
          "tgn:7543210",
          "tgn:7001242",
          "tgn:7016833",
          "tgn:1001113",
          "tgn:7029392"
        ],
        "placetype": [
          "aat:300008347"
        ],
        "id": 7543210,
        "name:xx": "Ashtīlah"
      }
    },
    {
      "geometry": {
        "type": "Point",
        "coordinates": [
          31.600477,
          30.633966
        ]
      },
      "type": "Feature",
      "properties": {
        "hierarchy": [
          "tgn:7543211",
          "tgn:7001242",
          "tgn:7016833",
          "tgn:1001113",
          "tgn:7029392"
        ],
        "placetype": [
          "aat:300008347"
        ],
        "id": 7543211,
        "name:xx": "Ash Shawādifah"
      }
    },
    {
      "geometry": {
        "type": "Point",
        "coordinates": [
          31.754249,
          31.034497
        ]
      },
      "type": "Feature",
      "properties": {
        "hierarchy": [
          "tgn:7543212",
          "tgn:7001242",
          "tgn:7016833",
          "tgn:1001113",
          "tgn:7029392"
        ],
        "placetype": [
          "aat:300008347"
        ],
        "name:en": "'Izbat Abū ar Rūs",
        "id": 7543212
      }
    },
    {
      "geometry": {
        "type": "Point",
        "coordinates": [
          31.96171,
          31.054926
        ]
      },
      "type": "Feature",
      "properties": {
        "hierarchy": [
          "tgn:7543213",
          "tgn:7001242",
          "tgn:7016833",
          "tgn:1001113",
          "tgn:7029392"
        ],
        "placetype": [
          "aat:300000206"
        ],
        "name:en": "'Izbat al Wābūr",
        "id": 7543213
      }
    },
    {
      "geometry": {
        "type": "Point",
        "coordinates": [
          31.957182,
          31.059595
        ]
      },
      "type": "Feature",
      "properties": {
        "hierarchy": [
          "tgn:7543214",
          "tgn:7001242",
          "tgn:7016833",
          "tgn:1001113",
          "tgn:7029392"
        ],
        "placetype": [
          "aat:300000206"
        ],
        "name:en": "'Izbat Abū Yūrah",
        "id": 7543214
      }
    },
    {
      "geometry": {
        "type": "Point",
        "coordinates": [
          31.106409,
          31.140248
        ]
      },
      "type": "Feature",
      "properties": {
        "hierarchy": [
          "tgn:7543215",
          "tgn:7001242",
          "tgn:7016833",
          "tgn:7001312",
          "tgn:7029392"
        ],
        "placetype": [
          "aat:300008347"
        ],
        "name:en": "'Izbat Warathat Barakāt",
        "id": 7543215
      }
    },
    {
      "geometry": {
        "type": "Point",
        "coordinates": [
          31.182275,
          31.141691
        ]
      },
      "type": "Feature",
      "properties": {
        "hierarchy": [
          "tgn:7543216",
          "tgn:7001242",
          "tgn:7016833",
          "tgn:7001312",
          "tgn:7029392"
        ],
        "placetype": [
          "aat:300000206"
        ],
        "name:en": "'Izbat Bakhātī",
        "id": 7543216
      }
    },
    {
      "geometry": {
        "type": "Point",
        "coordinates": [
          31.165608,
          31.138879
        ]
      },
      "type": "Feature",
      "properties": {
        "hierarchy": [
          "tgn:7543217",
          "tgn:7001242",
          "tgn:7016833",
          "tgn:7001312",
          "tgn:7029392"
        ],
        "placetype": [
          "aat:300000206"
        ],
        "name:en": "'Izbat al Buhūt",
        "id": 7543217
      }
    },
    {
      "geometry": {
        "type": "Point",
        "coordinates": [
          31.157435,
          31.13737
        ]
      },
      "type": "Feature",
      "properties": {
        "hierarchy": [
          "tgn:7543218",
          "tgn:7001242",
          "tgn:7016833",
          "tgn:1001335",
          "tgn:7029392"
        ],
        "placetype": [
          "aat:300000206"
        ],
        "name:en": "'Izbat al Jam'īyah",
        "id": 7543218
      }
    },
    {
      "geometry": {
        "type": "Point",
        "coordinates": [
          31.127055,
          31.136521
        ]
      },
      "type": "Feature",
      "properties": {
        "hierarchy": [
          "tgn:7543219",
          "tgn:7001242",
          "tgn:7016833",
          "tgn:7001312",
          "tgn:7029392"
        ],
        "placetype": [
          "aat:300000206"
        ],
        "name:en": "'Izbat ar Rawḑah",
        "id": 7543219
      }
    }
  ]
}
