{
  "geometry": {
    "type": "Point",
    "coordinates": [
      -85.1833,
      36.8833
    ]
  },
  "type": "Feature",
  "properties": {
    "hierarchy": [
      "tgn:2038368",
      "tgn:1000001",
      "tgn:7012149",
      "tgn:2000841",
      "tgn:7007255",
      "tgn:7029392"
    ],
    "placetype": [
      "aat:300008347",
      "aat:300387210"
    ],
    "id": 2038368,
    "name:xx": "Creelsboro"
  }
}
