{
  "geometry": {
    "type": "Point",
    "coordinates": [
      120.31778,
      23.935474
    ]
  },
  "type": "Feature",
  "properties": {
    "hierarchy": [
      "tgn:7472738",
      "tgn:1000004",
      "tgn:7467799",
      "tgn:1000141",
      "tgn:7029392"
    ],
    "placetype": [
      "aat:300387057"
    ],
    "id": 7472738,
    "name:xx": "Erlin Xikou"
  }
}
