{
  "geometry": {
    "type": "Point",
    "coordinates": [
      -72.8333,
      40.9667
    ]
  },
  "type": "Feature",
  "properties": {
    "hierarchy": [
      "tgn:2386872",
      "tgn:1000001",
      "tgn:7012149",
      "tgn:1002924",
      "tgn:7007568",
      "tgn:7029392"
    ],
    "placetype": [
      "aat:300132348"
    ],
    "id": 2386872,
    "name:xx": "Herod Point Shoal"
  }
}
