{
  "geometry": {
    "type": "Point",
    "coordinates": [
      -81.6667,
      36.8667
    ]
  },
  "type": "Feature",
  "properties": {
    "hierarchy": [
      "tgn:2782904",
      "tgn:1000001",
      "tgn:7012149",
      "tgn:2002191",
      "tgn:7007919",
      "tgn:7029392"
    ],
    "placetype": [
      "aat:300000390"
    ],
    "id": 2782904,
    "name:xx": "Worthy Mine"
  }
}
