{
  "geometry": {
    "type": "Point",
    "coordinates": [
      3.4167,
      45.25
    ]
  },
  "type": "Feature",
  "properties": {
    "hierarchy": [
      "tgn:1129271",
      "tgn:7002871",
      "tgn:1000003",
      "tgn:1000070",
      "tgn:7029392"
    ],
    "placetype": [
      "aat:300008707"
    ],
    "id": 1129271,
    "name:xx": "Sénouire"
  }
}
