{
  "geometry": {
    "type": "Point",
    "coordinates": [
      14.6667,
      45.1833
    ]
  },
  "type": "Feature",
  "properties": {
    "hierarchy": [
      "tgn:1064966",
      "tgn:7017299",
      "tgn:1000003",
      "tgn:7006663",
      "tgn:7029392"
    ],
    "placetype": [
      "aat:300008347"
    ],
    "id": 1064966,
    "name:xx": "Crikvenica"
  }
}
