{
  "geometry": {
    "type": "Point",
    "coordinates": [
      -106.2167,
      35.35
    ]
  },
  "type": "Feature",
  "properties": {
    "hierarchy": [
      "tgn:2725244",
      "tgn:1000001",
      "tgn:7012149",
      "tgn:7007566",
      "tgn:7029392"
    ],
    "placetype": [
      "aat:300008699"
    ],
    "id": 2725244,
    "name:xx": "Tonque, Arroyo"
  }
}
