{
  "geometry": {
    "type": "Point",
    "coordinates": [
      -94.7667,
      31.1333
    ]
  },
  "type": "Feature",
  "properties": {
    "hierarchy": [
      "tgn:2633868",
      "tgn:1002149",
      "tgn:1000001",
      "tgn:7012149",
      "tgn:7007826",
      "tgn:7029392"
    ],
    "placetype": [
      "aat:300008905"
    ],
    "id": 2633868,
    "name:xx": "Rush Pond"
  }
}
