{
  "geometry": {
    "type": "Point",
    "coordinates": [
      116.0833,
      39.5833
    ]
  },
  "type": "Feature",
  "properties": {
    "hierarchy": [
      "tgn:1123312",
      "tgn:1000956",
      "tgn:1000004",
      "tgn:1000111",
      "tgn:7029392"
    ],
    "placetype": [
      "aat:300008707"
    ],
    "id": 1123312,
    "name:xx": "Dashi"
  }
}
