{
  "geometry": {
    "type": "Point",
    "coordinates": [
      -83.2667,
      35.6833
    ]
  },
  "type": "Feature",
  "properties": {
    "hierarchy": [
      "tgn:2232865",
      "tgn:1000001",
      "tgn:7012149",
      "tgn:7029392"
    ],
    "placetype": [
      "aat:300008798"
    ],
    "id": 2232865,
    "name:xx": "Chapman, Mount"
  }
}
