{
  "geometry": {
    "type": "Point",
    "coordinates": [
      -90.5333,
      45.9167
    ]
  },
  "type": "Feature",
  "properties": {
    "hierarchy": [
      "tgn:2332303",
      "tgn:1000001",
      "tgn:7012149",
      "tgn:2002348",
      "tgn:7007922",
      "tgn:7029392"
    ],
    "placetype": [
      "aat:300008706"
    ],
    "id": 2332303,
    "name:xx": "Flood Creek"
  }
}
