{
  "geometry": {
    "type": "Point",
    "coordinates": [
      -106.9833,
      33.9833
    ]
  },
  "type": "Feature",
  "properties": {
    "hierarchy": [
      "tgn:2475799",
      "tgn:1000001",
      "tgn:7012149",
      "tgn:2001456",
      "tgn:7007566",
      "tgn:7029392"
    ],
    "placetype": [
      "aat:300000390"
    ],
    "id": 2475799,
    "name:xx": "Lucky Strike Number 1-Luis Lopez District"
  }
}
