{
  "geometry": {
    "type": "Point",
    "coordinates": [
      -92.6667,
      38.3167
    ]
  },
  "type": "Feature",
  "properties": {
    "hierarchy": [
      "tgn:2502185",
      "tgn:1000001",
      "tgn:7012149",
      "tgn:7007523",
      "tgn:7029392"
    ],
    "placetype": [
      "aat:300008706"
    ],
    "id": 2502185,
    "name:xx": "McKinley Creek"
  }
}
