{
  "geometry": {
    "type": "Point",
    "coordinates": [
      -78.8167,
      41.2333
    ]
  },
  "type": "Feature",
  "properties": {
    "hierarchy": [
      "tgn:2512925",
      "tgn:1000001",
      "tgn:7012149",
      "tgn:1002520",
      "tgn:7007710",
      "tgn:7029392"
    ],
    "placetype": [
      "aat:300008706"
    ],
    "id": 2512925,
    "name:xx": "Mill Creek"
  }
}
