{
  "geometry": {
    "type": "Point",
    "coordinates": [
      -88.2333,
      34.3333
    ]
  },
  "type": "Feature",
  "properties": {
    "hierarchy": [
      "tgn:2309878",
      "tgn:1000001",
      "tgn:7012149",
      "tgn:2001114",
      "tgn:7007522",
      "tgn:7029392"
    ],
    "placetype": [
      "aat:300008347"
    ],
    "id": 2309878,
    "name:xx": "Eastman"
  }
}
