{
  "geometry": {
    "type": "Point",
    "coordinates": [
      -95.35,
      40.4833
    ]
  },
  "type": "Feature",
  "properties": {
    "hierarchy": [
      "tgn:2230636",
      "tgn:2001169",
      "tgn:1000001",
      "tgn:7012149",
      "tgn:7007523",
      "tgn:7029392"
    ],
    "placetype": [
      "aat:300006191"
    ],
    "id": 2230636,
    "name:xx": "Center View Lake"
  }
}
