{
  "geometry": {
    "type": "Point",
    "coordinates": [
      -120.1667,
      44.45
    ]
  },
  "type": "Feature",
  "properties": {
    "hierarchy": [
      "tgn:2308781",
      "tgn:1000001",
      "tgn:7012149",
      "tgn:2001723",
      "tgn:7007708",
      "tgn:7029392"
    ],
    "placetype": [
      "aat:300008850"
    ],
    "id": 2308781,
    "name:xx": "East Point"
  }
}
