{
  "geometry": {
    "type": "Point",
    "coordinates": [
      32.614712,
      25.84899
    ]
  },
  "type": "Feature",
  "properties": {
    "hierarchy": [
      "tgn:7537465",
      "tgn:7001242",
      "tgn:7016833",
      "tgn:7001334",
      "tgn:7029392"
    ],
    "placetype": [
      "aat:300379998"
    ],
    "name:en": "Naq' al Birkah, Wādī",
    "id": 7537465
  }
}
