{
  "geometry": {
    "type": "Point",
    "coordinates": [
      -109.0333,
      41.3833
    ]
  },
  "type": "Feature",
  "properties": {
    "hierarchy": [
      "tgn:2134797",
      "tgn:1000001",
      "tgn:7012149",
      "tgn:2002383",
      "tgn:7007923",
      "tgn:7029392"
    ],
    "placetype": [
      "aat:300008761"
    ],
    "id": 2134797,
    "name:xx": "Antelope Draw"
  }
}
