{
  "geometry": {
    "type": "Point",
    "coordinates": [
      32.916667,
      24.316667
    ]
  },
  "type": "Feature",
  "properties": {
    "hierarchy": [
      "tgn:7520387",
      "tgn:7001242",
      "tgn:7016833",
      "tgn:7000122",
      "tgn:7029392"
    ],
    "placetype": [
      "aat:300007783"
    ],
    "name:en": "Maḩaţţat al Ja'āfirah",
    "id": 7520387
  }
}
