{
  "geometry": {
    "type": "Point",
    "coordinates": [
      -97.5167,
      33.7333
    ]
  },
  "type": "Feature",
  "properties": {
    "hierarchy": [
      "tgn:2356551",
      "tgn:1000001",
      "tgn:7012149",
      "tgn:2002044",
      "tgn:7007826",
      "tgn:7029392"
    ],
    "placetype": [
      "aat:300008798"
    ],
    "id": 2356551,
    "name:xx": "Gordon Mountain"
  }
}
