{
  "geometry": {
    "type": "Point",
    "coordinates": [
      45.4833,
      36.15
    ]
  },
  "type": "Feature",
  "properties": {
    "hierarchy": [
      "tgn:1140284",
      "tgn:1001048",
      "tgn:1000004",
      "tgn:7000231",
      "tgn:7029392"
    ],
    "placetype": [
      "aat:300008347"
    ],
    "id": 1140284,
    "name:xx": "Sar Dasht"
  }
}
