{
  "geometry": {
    "type": "Point",
    "coordinates": [
      -76.1333,
      42.7167
    ]
  },
  "type": "Feature",
  "properties": {
    "hierarchy": [
      "tgn:2072312",
      "tgn:1000001",
      "tgn:1002302",
      "tgn:7012149",
      "tgn:7007568",
      "tgn:7029392"
    ],
    "placetype": [
      "aat:300008347",
      "aat:300387210"
    ],
    "id": 2072312,
    "name:xx": "Slab City"
  }
}
