{
  "type": "FeatureCollection",
  "features": [
    {
      "geometry": {
        "type": "Point",
        "coordinates": [
          -100.816667,
          25.633333
        ]
      },
      "type": "Feature",
      "properties": {
        "hierarchy": [
          "tgn:7384800",
          "tgn:1001853",
          "tgn:1000001",
          "tgn:7005560",
          "tgn:7029392"
        ],
        "placetype": [
          "aat:300007783"
        ],
        "id": 7384800,
        "name:xx": "Ojo Caliente"
      }
    },
    {
      "geometry": {
        "type": "Point",
        "coordinates": [
          -102.95,
          29.166667
        ]
      },
      "type": "Feature",
      "properties": {
        "hierarchy": [
          "tgn:7384801",
          "tgn:1001853",
          "tgn:1000001",
          "tgn:7005560",
          "tgn:7029392"
        ],
        "placetype": [
          "aat:300000241"
        ],
        "id": 7384801,
        "name:xx": "Ojo Caliente"
      }
    },
    {
      "geometry": {
        "type": "Point",
        "coordinates": [
          -107.55,
          31.3
        ]
      },
      "type": "Feature",
      "properties": {
        "hierarchy": [
          "tgn:7384802",
          "tgn:7005581",
          "tgn:1000001",
          "tgn:7005560",
          "tgn:7029392"
        ],
        "placetype": [
          "aat:300008347"
        ],
        "id": 7384802,
        "name:xx": "Ojo Caliente"
      }
    },
    {
      "geometry": {
        "type": "Point",
        "coordinates": [
          -108.283333,
          31
        ]
      },
      "type": "Feature",
      "properties": {
        "hierarchy": [
          "tgn:7384803",
          "tgn:7005581",
          "tgn:1000001",
          "tgn:7005560",
          "tgn:7029392"
        ],
        "placetype": [
          "aat:300008347"
        ],
        "id": 7384803,
        "name:xx": "Ojo Caliente"
      }
    },
    {
      "geometry": {
        "type": "Point",
        "coordinates": [
          -107.6,
          30.216667
        ]
      },
      "type": "Feature",
      "properties": {
        "hierarchy": [
          "tgn:7384805",
          "tgn:7005581",
          "tgn:1000001",
          "tgn:7005560",
          "tgn:7029392"
        ],
        "placetype": [
          "aat:300008347"
        ],
        "id": 7384805,
        "name:xx": "Ojo Caliente"
      }
    },
    {
      "geometry": {
        "type": "Point",
        "coordinates": [
          -107.266667,
          29.9
        ]
      },
      "type": "Feature",
      "properties": {
        "hierarchy": [
          "tgn:7384806",
          "tgn:7005581",
          "tgn:1000001",
          "tgn:7005560",
          "tgn:7029392"
        ],
        "placetype": [
          "aat:300008347"
        ],
        "id": 7384806,
        "name:xx": "Ojo Caliente"
      }
    },
    {
      "geometry": {
        "type": "Point",
        "coordinates": [
          -107.266667,
          29.566667
        ]
      },
      "type": "Feature",
      "properties": {
        "hierarchy": [
          "tgn:7384807",
          "tgn:7005581",
          "tgn:1000001",
          "tgn:7005560",
          "tgn:7029392"
        ],
        "placetype": [
          "aat:300008347"
        ],
        "id": 7384807,
        "name:xx": "Ojo Caliente"
      }
    },
    {
      "geometry": {
        "type": "Point",
        "coordinates": [
          -102.866667,
          29.233333
        ]
      },
      "type": "Feature",
      "properties": {
        "hierarchy": [
          "tgn:7384808",
          "tgn:1001853",
          "tgn:1000001",
          "tgn:7005560",
          "tgn:7029392"
        ],
        "placetype": [
          "aat:300008347"
        ],
        "id": 7384808,
        "name:xx": "Ojo Caliente"
      }
    },
    {
      "geometry": {
        "type": "Point",
        "coordinates": [
          -106.933333,
          28.633333
        ]
      },
      "type": "Feature",
      "properties": {
        "hierarchy": [
          "tgn:7384809",
          "tgn:7005581",
          "tgn:1000001",
          "tgn:7005560",
          "tgn:7029392"
        ],
        "placetype": [
          "aat:300008347"
        ],
        "id": 7384809,
        "name:xx": "Ojo Caliente"
      }
    }
  ]
}
