{
  "geometry": {
    "type": "Point",
    "coordinates": [
      16.1333,
      29.1667
    ]
  },
  "type": "Feature",
  "properties": {
    "hierarchy": [
      "tgn:1090725",
      "tgn:7001242",
      "tgn:7000608",
      "tgn:1000172",
      "tgn:7029392"
    ],
    "placetype": [
      "aat:300008347"
    ],
    "id": 1090725,
    "name:xx": "Waddān"
  }
}
