{
  "geometry": {
    "type": "Point",
    "coordinates": [
      -69.5667,
      46.3667
    ]
  },
  "type": "Feature",
  "properties": {
    "hierarchy": [
      "tgn:2304771",
      "tgn:1000001",
      "tgn:7012149",
      "tgn:2000928",
      "tgn:7007515",
      "tgn:7029392"
    ],
    "placetype": [
      "aat:300008699"
    ],
    "id": 2304771,
    "name:xx": "East Branch Allagash Stream"
  }
}
