{
  "geometry": {
    "type": "Point",
    "coordinates": [
      -75.4167,
      37.8833
    ]
  },
  "type": "Feature",
  "properties": {
    "hierarchy": [
      "tgn:2374076",
      "tgn:1002132",
      "tgn:1000001",
      "tgn:7012149",
      "tgn:7007919",
      "tgn:7029392"
    ],
    "placetype": [
      "aat:300008850"
    ],
    "id": 2374076,
    "name:xx": "Hammock Point"
  }
}
