{
  "geometry": {
    "type": "Point",
    "coordinates": [
      -72.2167,
      42.0333
    ]
  },
  "type": "Feature",
  "properties": {
    "hierarchy": [
      "tgn:7022787",
      "tgn:1000001",
      "tgn:7012149",
      "tgn:7029392"
    ],
    "placetype": [
      "aat:300008699"
    ],
    "id": 7022787,
    "name:xx": "Delphi Brook"
  }
}
