{
  "type": "FeatureCollection",
  "features": [
    {
      "geometry": {
        "type": "Point",
        "coordinates": [
          -92.65,
          38.5333
        ]
      },
      "type": "Feature",
      "properties": {
        "hierarchy": [
          "tgn:2153650",
          "tgn:1000001",
          "tgn:7012149",
          "tgn:2001220",
          "tgn:7007523",
          "tgn:7029392"
        ],
        "placetype": [
          "aat:300008699"
        ],
        "id": 2153650,
        "name:xx": "Bear Branch"
      }
    },
    {
      "geometry": {
        "type": "Point",
        "coordinates": [
          -93.4667,
          38.85
        ]
      },
      "type": "Feature",
      "properties": {
        "hierarchy": [
          "tgn:2153651",
          "tgn:1000001",
          "tgn:7012149",
          "tgn:2001229",
          "tgn:7007523",
          "tgn:7029392"
        ],
        "placetype": [
          "aat:300008699"
        ],
        "id": 2153651,
        "name:xx": "Bear Branch"
      }
    },
    {
      "geometry": {
        "type": "Point",
        "coordinates": [
          -91.5833,
          39.3167
        ]
      },
      "type": "Feature",
      "properties": {
        "hierarchy": [
          "tgn:2153652",
          "tgn:1000001",
          "tgn:7012149",
          "tgn:1002817",
          "tgn:7007523",
          "tgn:7029392"
        ],
        "placetype": [
          "aat:300008699"
        ],
        "id": 2153652,
        "name:xx": "Bear Branch"
      }
    },
    {
      "geometry": {
        "type": "Point",
        "coordinates": [
          -93.0333,
          39.9333
        ]
      },
      "type": "Feature",
      "properties": {
        "hierarchy": [
          "tgn:2153653",
          "tgn:1000001",
          "tgn:7012149",
          "tgn:2001214",
          "tgn:7007523",
          "tgn:7029392"
        ],
        "placetype": [
          "aat:300008347"
        ],
        "id": 2153653,
        "name:xx": "Bear Branch"
      }
    },
    {
      "geometry": {
        "type": "Point",
        "coordinates": [
          -74.9667,
          39.4833
        ]
      },
      "type": "Feature",
      "properties": {
        "hierarchy": [
          "tgn:2153654",
          "tgn:1002309",
          "tgn:1000001",
          "tgn:7012149",
          "tgn:7007565",
          "tgn:7029392"
        ],
        "placetype": [
          "aat:300008699"
        ],
        "id": 2153654,
        "name:xx": "Bear Branch"
      }
    },
    {
      "geometry": {
        "type": "Point",
        "coordinates": [
          -78.6333,
          34.1667
        ]
      },
      "type": "Feature",
      "properties": {
        "hierarchy": [
          "tgn:2153655",
          "tgn:1000001",
          "tgn:2001485",
          "tgn:7012149",
          "tgn:7007709",
          "tgn:7029392"
        ],
        "placetype": [
          "aat:300008699"
        ],
        "id": 2153655,
        "name:xx": "Bear Branch"
      }
    },
    {
      "geometry": {
        "type": "Point",
        "coordinates": [
          -78.1667,
          34.3
        ]
      },
      "type": "Feature",
      "properties": {
        "hierarchy": [
          "tgn:2153656",
          "tgn:1000001",
          "tgn:2001472",
          "tgn:7012149",
          "tgn:7007709",
          "tgn:7029392"
        ],
        "placetype": [
          "aat:300008699"
        ],
        "id": 2153656,
        "name:xx": "Bear Branch"
      }
    },
    {
      "geometry": {
        "type": "Point",
        "coordinates": [
          -78.0667,
          34.4333
        ]
      },
      "type": "Feature",
      "properties": {
        "hierarchy": [
          "tgn:2153657",
          "tgn:1000001",
          "tgn:7012149",
          "tgn:2001527",
          "tgn:7007709",
          "tgn:7029392"
        ],
        "placetype": [
          "aat:300008699"
        ],
        "id": 2153657,
        "name:xx": "Bear Branch"
      }
    },
    {
      "geometry": {
        "type": "Point",
        "coordinates": [
          -83.75,
          35.15
        ]
      },
      "type": "Feature",
      "properties": {
        "hierarchy": [
          "tgn:2153658",
          "tgn:1000001",
          "tgn:2001481",
          "tgn:7012149",
          "tgn:7007709",
          "tgn:7029392"
        ],
        "placetype": [
          "aat:300008699"
        ],
        "id": 2153658,
        "name:xx": "Bear Branch"
      }
    },
    {
      "geometry": {
        "type": "Point",
        "coordinates": [
          -77.1,
          35.2833
        ]
      },
      "type": "Feature",
      "properties": {
        "hierarchy": [
          "tgn:2153659",
          "tgn:1000001",
          "tgn:7012149",
          "tgn:2001486",
          "tgn:7007709",
          "tgn:7029392"
        ],
        "placetype": [
          "aat:300008699"
        ],
        "id": 2153659,
        "name:xx": "Bear Branch"
      }
    }
  ]
}
