{
  "type": "FeatureCollection",
  "features": [
    {
      "geometry": {
        "type": "Point",
        "coordinates": [
          -75.4667,
          40.65
        ]
      },
      "type": "Feature",
      "properties": {
        "hierarchy": [
          "tgn:2091390",
          "tgn:1000001",
          "tgn:7012149",
          "tgn:1002729",
          "tgn:7007710",
          "tgn:7029392"
        ],
        "placetype": [
          "aat:300008347"
        ],
        "id": 2091390,
        "name:xx": "North Catasauqua"
      }
    },
    {
      "geometry": {
        "type": "Point",
        "coordinates": [
          -79.9,
          40.15
        ]
      },
      "type": "Feature",
      "properties": {
        "hierarchy": [
          "tgn:2091391",
          "tgn:1000001",
          "tgn:7012149",
          "tgn:1002995",
          "tgn:7007710",
          "tgn:7029392"
        ],
        "placetype": [
          "aat:300008347"
        ],
        "id": 2091391,
        "name:xx": "North Charleroi"
      }
    },
    {
      "geometry": {
        "type": "Point",
        "coordinates": [
          -79.4167,
          41.2333
        ]
      },
      "type": "Feature",
      "properties": {
        "hierarchy": [
          "tgn:2091394",
          "tgn:1000001",
          "tgn:1002272",
          "tgn:7012149",
          "tgn:7007710",
          "tgn:7029392"
        ],
        "placetype": [
          "aat:300387016"
        ],
        "id": 2091394,
        "name:xx": "Clarion Junction"
      }
    },
    {
      "geometry": {
        "type": "Point",
        "coordinates": [
          -79.8333,
          42.2
        ]
      },
      "type": "Feature",
      "properties": {
        "hierarchy": [
          "tgn:2091396",
          "tgn:1000001",
          "tgn:7012149",
          "tgn:1002358",
          "tgn:7007710",
          "tgn:7029392"
        ],
        "placetype": [
          "aat:300008347"
        ],
        "id": 2091396,
        "name:xx": "North East"
      }
    },
    {
      "geometry": {
        "type": "Point",
        "coordinates": [
          -80.4333,
          41.0167
        ]
      },
      "type": "Feature",
      "properties": {
        "hierarchy": [
          "tgn:2091397",
          "tgn:1000001",
          "tgn:7012149",
          "tgn:1002580",
          "tgn:7007710",
          "tgn:7029392"
        ],
        "placetype": [
          "aat:300008347"
        ],
        "id": 2091397,
        "name:xx": "North Edinburg"
      }
    },
    {
      "geometry": {
        "type": "Point",
        "coordinates": [
          -77.6167,
          41.9667
        ]
      },
      "type": "Feature",
      "properties": {
        "hierarchy": [
          "tgn:2091398",
          "tgn:1000001",
          "tgn:7012149",
          "tgn:1002800",
          "tgn:7007710",
          "tgn:7029392"
        ],
        "placetype": [
          "aat:300008347"
        ],
        "id": 2091398,
        "name:xx": "North Fork"
      }
    }
  ]
}
