{
  "geometry": {
    "type": "Point",
    "coordinates": [
      -84.8833,
      38.0167
    ]
  },
  "type": "Feature",
  "properties": {
    "hierarchy": [
      "tgn:2228041",
      "tgn:1000001",
      "tgn:7012149",
      "tgn:7007255",
      "tgn:7029392"
    ],
    "placetype": [
      "aat:300008699"
    ],
    "id": 2228041,
    "name:xx": "Cedar Brook"
  }
}
