{
  "geometry": {
    "type": "Point",
    "coordinates": [
      -115.7833,
      48.5833
    ]
  },
  "type": "Feature",
  "properties": {
    "hierarchy": [
      "tgn:2699852",
      "tgn:1000001",
      "tgn:7012149",
      "tgn:2001286",
      "tgn:7007524",
      "tgn:7029392"
    ],
    "placetype": [
      "aat:300008761"
    ],
    "id": 2699852,
    "name:xx": "Studebaker Draw"
  }
}
