{
  "type": "FeatureCollection",
  "features": [
    {
      "geometry": {
        "type": "Point",
        "coordinates": [
          -91.3667,
          38.0667
        ]
      },
      "type": "Feature",
      "properties": {
        "hierarchy": [
          "tgn:2597340",
          "tgn:1000001",
          "tgn:7012149",
          "tgn:2001190",
          "tgn:7007523",
          "tgn:7029392"
        ],
        "placetype": [
          "aat:300008706"
        ],
        "id": 2597340,
        "name:xx": "Prairie Creek"
      }
    },
    {
      "geometry": {
        "type": "Point",
        "coordinates": [
          -94.7167,
          39.3
        ]
      },
      "type": "Feature",
      "properties": {
        "hierarchy": [
          "tgn:2597341",
          "tgn:1000001",
          "tgn:7012149",
          "tgn:2001231",
          "tgn:7007523",
          "tgn:7029392"
        ],
        "placetype": [
          "aat:300008706"
        ],
        "id": 2597341,
        "name:xx": "Prairie Creek"
      }
    },
    {
      "geometry": {
        "type": "Point",
        "coordinates": [
          -105.2,
          45.65
        ]
      },
      "type": "Feature",
      "properties": {
        "hierarchy": [
          "tgn:2597344",
          "tgn:1000001",
          "tgn:7012149",
          "tgn:2001297",
          "tgn:7007524",
          "tgn:7029392"
        ],
        "placetype": [
          "aat:300008706"
        ],
        "id": 2597344,
        "name:xx": "Prairie Creek"
      }
    },
    {
      "geometry": {
        "type": "Point",
        "coordinates": [
          -110.9667,
          46.3667
        ]
      },
      "type": "Feature",
      "properties": {
        "hierarchy": [
          "tgn:2597345",
          "tgn:1000001",
          "tgn:7012149",
          "tgn:2001289",
          "tgn:7007524",
          "tgn:7029392"
        ],
        "placetype": [
          "aat:300008706"
        ],
        "id": 2597345,
        "name:xx": "Prairie Creek"
      }
    },
    {
      "geometry": {
        "type": "Point",
        "coordinates": [
          -105.4167,
          46.5333
        ]
      },
      "type": "Feature",
      "properties": {
        "hierarchy": [
          "tgn:2597346",
          "tgn:1000001",
          "tgn:2001268",
          "tgn:7012149",
          "tgn:7007524",
          "tgn:7029392"
        ],
        "placetype": [
          "aat:300008706"
        ],
        "id": 2597346,
        "name:xx": "Prairie Creek"
      }
    },
    {
      "geometry": {
        "type": "Point",
        "coordinates": [
          -113,
          47.6
        ]
      },
      "type": "Feature",
      "properties": {
        "hierarchy": [
          "tgn:2597347",
          "tgn:1000001",
          "tgn:7012149",
          "tgn:2001284",
          "tgn:7007524",
          "tgn:7029392"
        ],
        "placetype": [
          "aat:300008706"
        ],
        "id": 2597347,
        "name:xx": "Prairie Creek"
      }
    },
    {
      "geometry": {
        "type": "Point",
        "coordinates": [
          -113.85,
          45.75
        ]
      },
      "type": "Feature",
      "properties": {
        "hierarchy": [
          "tgn:2597348",
          "tgn:1000001",
          "tgn:2001260",
          "tgn:7012149",
          "tgn:7007524",
          "tgn:7029392"
        ],
        "placetype": [
          "aat:300008706"
        ],
        "id": 2597348,
        "name:xx": "Prairie Creek"
      }
    },
    {
      "geometry": {
        "type": "Point",
        "coordinates": [
          -84.2833,
          41.0833
        ]
      },
      "type": "Feature",
      "properties": {
        "hierarchy": [
          "tgn:2597349",
          "tgn:1000001",
          "tgn:7012149",
          "tgn:7007706",
          "tgn:7029392"
        ],
        "placetype": [
          "aat:300008706"
        ],
        "id": 2597349,
        "name:xx": "Prairie Creek"
      }
    }
  ]
}
