{
  "geometry": {
    "type": "Point",
    "coordinates": [
      -79.1833,
      34.45
    ]
  },
  "type": "Feature",
  "properties": {
    "hierarchy": [
      "tgn:2399671",
      "tgn:1000001",
      "tgn:7012149",
      "tgn:2001534",
      "tgn:7007709",
      "tgn:7029392"
    ],
    "placetype": [
      "aat:300006191"
    ],
    "id": 2399671,
    "name:xx": "Horns Old Millpond"
  }
}
