{
  "type": "FeatureCollection",
  "features": [
    {
      "geometry": {
        "type": "Point",
        "coordinates": [
          5.666667,
          50.433333
        ]
      },
      "type": "Feature",
      "properties": {
        "hierarchy": [
          "tgn:7238520",
          "tgn:7003460",
          "tgn:1000003",
          "tgn:1000063",
          "tgn:4012014",
          "tgn:7029392"
        ],
        "placetype": [
          "aat:300008347"
        ],
        "id": 7238520,
        "name:xx": "Harzé"
      }
    },
    {
      "geometry": {
        "type": "Point",
        "coordinates": [
          3.983333,
          50.383333
        ]
      },
      "type": "Feature",
      "properties": {
        "hierarchy": [
          "tgn:7238522",
          "tgn:7007877",
          "tgn:1000003",
          "tgn:1000063",
          "tgn:4012014",
          "tgn:7029392"
        ],
        "placetype": [
          "aat:300008699"
        ],
        "id": 7238522,
        "name:xx": "Blangeroy, Ruisseau"
      }
    },
    {
      "geometry": {
        "type": "Point",
        "coordinates": [
          3.983333,
          50.4
        ]
      },
      "type": "Feature",
      "properties": {
        "hierarchy": [
          "tgn:7238523",
          "tgn:7007877",
          "tgn:1000003",
          "tgn:1000063",
          "tgn:4012014",
          "tgn:7029392"
        ],
        "placetype": [
          "aat:300008347"
        ],
        "id": 7238523,
        "name:xx": "Harveng"
      }
    },
    {
      "geometry": {
        "type": "Point",
        "coordinates": [
          6.133333,
          50.5
        ]
      },
      "type": "Feature",
      "properties": {
        "hierarchy": [
          "tgn:7238525",
          "tgn:7003460",
          "tgn:1000003",
          "tgn:1000063",
          "tgn:4012014",
          "tgn:7029392"
        ],
        "placetype": [
          "aat:300008863"
        ],
        "id": 7238525,
        "name:xx": "Harth"
      }
    },
    {
      "geometry": {
        "type": "Point",
        "coordinates": [
          5.65,
          50.383333
        ]
      },
      "type": "Feature",
      "properties": {
        "hierarchy": [
          "tgn:7238526",
          "tgn:7003460",
          "tgn:1000003",
          "tgn:1000063",
          "tgn:4012014",
          "tgn:7029392"
        ],
        "placetype": [
          "aat:300008347"
        ],
        "id": 7238526,
        "name:xx": "Grand Trixhe"
      }
    },
    {
      "geometry": {
        "type": "Point",
        "coordinates": [
          4.5,
          50.433333
        ]
      },
      "type": "Feature",
      "properties": {
        "hierarchy": [
          "tgn:7238527",
          "tgn:7007877",
          "tgn:1000003",
          "tgn:1000063",
          "tgn:4012014",
          "tgn:7029392"
        ],
        "placetype": [
          "aat:300008347"
        ],
        "id": 7238527,
        "name:xx": "Grand Trieu"
      }
    },
    {
      "geometry": {
        "type": "Point",
        "coordinates": [
          4.1,
          50.383333
        ]
      },
      "type": "Feature",
      "properties": {
        "hierarchy": [
          "tgn:7238528",
          "tgn:7007877",
          "tgn:1000003",
          "tgn:1000063",
          "tgn:4012014",
          "tgn:7029392"
        ],
        "placetype": [
          "aat:300008347"
        ],
        "id": 7238528,
        "name:xx": "Grand Trieu"
      }
    },
    {
      "geometry": {
        "type": "Point",
        "coordinates": [
          5.234753,
          50.419582
        ]
      },
      "type": "Feature",
      "properties": {
        "hierarchy": [
          "tgn:7238529",
          "tgn:7003460",
          "tgn:1000003",
          "tgn:1000063",
          "tgn:4012014",
          "tgn:7029392"
        ],
        "placetype": [
          "aat:300008863"
        ],
        "id": 7238529,
        "name:xx": "Grand Taillis, Bois du"
      }
    }
  ]
}
