{
  "geometry": {
    "type": "Point",
    "coordinates": [
      -114.6167,
      41.9667
    ]
  },
  "type": "Feature",
  "properties": {
    "hierarchy": [
      "tgn:2620712",
      "tgn:1000001",
      "tgn:2001411",
      "tgn:7012149",
      "tgn:7007526",
      "tgn:7029392"
    ],
    "placetype": [
      "aat:300008347"
    ],
    "id": 2620712,
    "name:xx": "Riverside Park"
  }
}
