{
  "geometry": {
    "type": "Point",
    "coordinates": [
      12.7667,
      49.5833
    ]
  },
  "type": "Feature",
  "properties": {
    "hierarchy": [
      "tgn:1027571",
      "tgn:7593919",
      "tgn:1000003",
      "tgn:1001780",
      "tgn:7029392"
    ],
    "placetype": [
      "aat:300008347"
    ],
    "id": 1027571,
    "name:xx": "Svržno"
  }
}
