{
  "geometry": {
    "type": "Point",
    "coordinates": [
      -108.8167,
      44.45
    ]
  },
  "type": "Feature",
  "properties": {
    "hierarchy": [
      "tgn:2546040",
      "tgn:1000001",
      "tgn:7012149",
      "tgn:2002379",
      "tgn:7007923",
      "tgn:7029392"
    ],
    "placetype": [
      "aat:300008706"
    ],
    "id": 2546040,
    "name:xx": "North Fork Dry Creek"
  }
}
