{
  "geometry": {
    "type": "Point",
    "coordinates": [
      -106.9167,
      45.5833
    ]
  },
  "type": "Feature",
  "properties": {
    "hierarchy": [
      "tgn:2456037",
      "tgn:1000001",
      "tgn:2001261",
      "tgn:7012149",
      "tgn:7007524",
      "tgn:7029392"
    ],
    "placetype": [
      "aat:300008680"
    ],
    "id": 2456037,
    "name:xx": "Little Hawk Lake"
  }
}
