{
  "geometry": {
    "type": "Point",
    "coordinates": [
      19.383,
      -15.947
    ]
  },
  "type": "Feature",
  "properties": {
    "hierarchy": [
      "tgn:1000833",
      "tgn:7001242",
      "tgn:1000149",
      "tgn:7029392"
    ],
    "placetype": [
      "aat:300387064",
      "aat:300000774"
    ],
    "id": 1000833,
    "name:xx": "Kuando Kubango"
  }
}
