{
  "geometry": {
    "type": "Point",
    "coordinates": [
      -90.6333,
      35.8833
    ]
  },
  "type": "Feature",
  "properties": {
    "hierarchy": [
      "tgn:2202579",
      "tgn:1000001",
      "tgn:7016172",
      "tgn:2000120",
      "tgn:7012149",
      "tgn:7029392"
    ],
    "placetype": [
      "aat:300008347"
    ],
    "id": 2202579,
    "name:xx": "Buck Snort"
  }
}
