{
  "geometry": {
    "type": "Point",
    "coordinates": [
      -109.0167,
      31.4833
    ]
  },
  "type": "Feature",
  "properties": {
    "hierarchy": [
      "tgn:2245140",
      "tgn:1000001",
      "tgn:7012149",
      "tgn:7007566",
      "tgn:7029392"
    ],
    "placetype": [
      "aat:300008706"
    ],
    "id": 2245140,
    "name:xx": "Cloverdale Creek"
  }
}
