{
  "geometry": {
    "type": "Point",
    "coordinates": [
      -105.6667,
      40.2167
    ]
  },
  "type": "Feature",
  "properties": {
    "hierarchy": [
      "tgn:2243520",
      "tgn:1000001",
      "tgn:7012149",
      "tgn:7007158",
      "tgn:7029392"
    ],
    "placetype": [
      "aat:300008798"
    ],
    "id": 2243520,
    "name:xx": "Cleaver, The"
  }
}
