{
  "geometry": {
    "type": "Point",
    "coordinates": [
      -80.6167,
      36.35
    ]
  },
  "type": "Feature",
  "properties": {
    "hierarchy": [
      "tgn:2394112",
      "tgn:1000001",
      "tgn:7012149",
      "tgn:7007709",
      "tgn:7029392"
    ],
    "placetype": [
      "aat:300008706"
    ],
    "id": 2394112,
    "name:xx": "Hogan Creek"
  }
}
