{
  "geometry": {
    "type": "Point",
    "coordinates": [
      -91.4667,
      45.8167
    ]
  },
  "type": "Feature",
  "properties": {
    "hierarchy": [
      "tgn:2188061",
      "tgn:1000001",
      "tgn:7012149",
      "tgn:2002353",
      "tgn:7007922",
      "tgn:7029392"
    ],
    "placetype": [
      "aat:300008905"
    ],
    "id": 2188061,
    "name:xx": "Borns Lake"
  }
}
