{
  "geometry": {
    "type": "Point",
    "coordinates": [
      -157.3167,
      62.3167
    ]
  },
  "type": "Feature",
  "properties": {
    "hierarchy": [
      "tgn:2691758",
      "tgn:7006450",
      "tgn:1000001",
      "tgn:7012149",
      "tgn:2000089",
      "tgn:7029392"
    ],
    "placetype": [
      "aat:300008706"
    ],
    "id": 2691758,
    "name:xx": "Starr Creek"
  }
}
