{
  "geometry": {
    "type": "Point",
    "coordinates": [
      120.55,
      6.1333
    ]
  },
  "type": "Feature",
  "properties": {
    "hierarchy": [
      "tgn:1009579",
      "tgn:1010207",
      "tgn:1000004",
      "tgn:1001552",
      "tgn:1000135",
      "tgn:7029392"
    ],
    "placetype": [
      "aat:300008791"
    ],
    "id": 1009579,
    "name:xx": "Usada Island"
  }
}
