{
  "type": "FeatureCollection",
  "features": [
    {
      "geometry": {
        "type": "Point",
        "coordinates": [
          -90.8333,
          38.5833
        ]
      },
      "type": "Feature",
      "properties": {
        "hierarchy": [
          "tgn:2440350",
          "tgn:1000001",
          "tgn:7012149",
          "tgn:7016166",
          "tgn:7007523",
          "tgn:7029392"
        ],
        "placetype": [
          "aat:300006191"
        ],
        "id": 2440350,
        "name:xx": "Klondike Lake"
      }
    },
    {
      "geometry": {
        "type": "Point",
        "coordinates": [
          -112.15,
          41.5
        ]
      },
      "type": "Feature",
      "properties": {
        "hierarchy": [
          "tgn:2440351",
          "tgn:1000001",
          "tgn:2002102",
          "tgn:7012149",
          "tgn:7007827",
          "tgn:7029392"
        ],
        "placetype": [
          "aat:300008680"
        ],
        "id": 2440351,
        "name:xx": "Klondike Lake"
      }
    },
    {
      "geometry": {
        "type": "Point",
        "coordinates": [
          -89.6167,
          45.9667
        ]
      },
      "type": "Feature",
      "properties": {
        "hierarchy": [
          "tgn:2440352",
          "tgn:1000001",
          "tgn:7012149",
          "tgn:2002359",
          "tgn:7007922",
          "tgn:7029392"
        ],
        "placetype": [
          "aat:300008680"
        ],
        "id": 2440352,
        "name:xx": "Klondike Lake"
      }
    },
    {
      "geometry": {
        "type": "Point",
        "coordinates": [
          -106.3,
          41.35
        ]
      },
      "type": "Feature",
      "properties": {
        "hierarchy": [
          "tgn:2440353",
          "tgn:2002365",
          "tgn:1000001",
          "tgn:7012149",
          "tgn:7007923",
          "tgn:7029392"
        ],
        "placetype": [
          "aat:300008680"
        ],
        "id": 2440353,
        "name:xx": "Klondike Lake"
      }
    },
    {
      "geometry": {
        "type": "Point",
        "coordinates": [
          -109.6333,
          43.2333
        ]
      },
      "type": "Feature",
      "properties": {
        "hierarchy": [
          "tgn:2440354",
          "tgn:1000001",
          "tgn:7012149",
          "tgn:2002371",
          "tgn:7007923",
          "tgn:7029392"
        ],
        "placetype": [
          "aat:300008680"
        ],
        "id": 2440354,
        "name:xx": "Klondike Lake"
      }
    },
    {
      "geometry": {
        "type": "Point",
        "coordinates": [
          -103.9333,
          36.9167
        ]
      },
      "type": "Feature",
      "properties": {
        "hierarchy": [
          "tgn:2440356",
          "tgn:1000001",
          "tgn:7012149",
          "tgn:2001459",
          "tgn:7007566",
          "tgn:7029392"
        ],
        "placetype": [
          "aat:300008798"
        ],
        "id": 2440356,
        "name:xx": "Klondike Mesa"
      }
    },
    {
      "geometry": {
        "type": "Point",
        "coordinates": [
          -87.2333,
          33.6667
        ]
      },
      "type": "Feature",
      "properties": {
        "hierarchy": [
          "tgn:2440357",
          "tgn:7002659",
          "tgn:1000001",
          "tgn:7012149",
          "tgn:2000063",
          "tgn:7029392"
        ],
        "placetype": [
          "aat:300000390"
        ],
        "id": 2440357,
        "name:xx": "Klondike Mine"
      }
    }
  ]
}
