{
  "geometry": {
    "type": "Point",
    "coordinates": [
      -106.0667,
      36.55
    ]
  },
  "type": "Feature",
  "properties": {
    "hierarchy": [
      "tgn:2439130",
      "tgn:1000001",
      "tgn:7012149",
      "tgn:2001449",
      "tgn:7007566",
      "tgn:7029392"
    ],
    "placetype": [
      "aat:300000390"
    ],
    "id": 2439130,
    "name:xx": "Kiowa View 1"
  }
}
