{
  "geometry": {
    "type": "Point",
    "coordinates": [
      -93.4667,
      39.75
    ]
  },
  "type": "Feature",
  "properties": {
    "hierarchy": [
      "tgn:2059916",
      "tgn:1000001",
      "tgn:7012149",
      "tgn:2001215",
      "tgn:7007523",
      "tgn:7029392"
    ],
    "placetype": [
      "aat:300387016"
    ],
    "id": 2059916,
    "name:xx": "Norville"
  }
}
