{
  "type": "FeatureCollection",
  "features": [
    {
      "geometry": {
        "type": "Point",
        "coordinates": [
          -79.7,
          38.9
        ]
      },
      "type": "Feature",
      "properties": {
        "hierarchy": [
          "tgn:2117550",
          "tgn:1000001",
          "tgn:7012149",
          "tgn:2002291",
          "tgn:7013961",
          "tgn:7029392"
        ],
        "placetype": [
          "aat:300008347"
        ],
        "id": 2117550,
        "name:xx": "Bowden"
      }
    },
    {
      "geometry": {
        "type": "Point",
        "coordinates": [
          -80.7167,
          38.85
        ]
      },
      "type": "Feature",
      "properties": {
        "hierarchy": [
          "tgn:2117552",
          "tgn:1000001",
          "tgn:2002256",
          "tgn:7012149",
          "tgn:7013961",
          "tgn:7029392"
        ],
        "placetype": [
          "aat:300387016"
        ],
        "id": 2117552,
        "name:xx": "Bower"
      }
    },
    {
      "geometry": {
        "type": "Point",
        "coordinates": [
          -80.0167,
          39.7
        ]
      },
      "type": "Feature",
      "properties": {
        "hierarchy": [
          "tgn:2117553",
          "tgn:1000001",
          "tgn:7012149",
          "tgn:2002281",
          "tgn:7013961",
          "tgn:7029392"
        ],
        "placetype": [
          "aat:300008347"
        ],
        "id": 2117553,
        "name:xx": "Bowlby"
      }
    },
    {
      "geometry": {
        "type": "Point",
        "coordinates": [
          -82.05,
          38.3167
        ]
      },
      "type": "Feature",
      "properties": {
        "hierarchy": [
          "tgn:2117554",
          "tgn:1000001",
          "tgn:7012149",
          "tgn:2002272",
          "tgn:7013961",
          "tgn:7029392"
        ],
        "placetype": [
          "aat:300008347",
          "aat:300387210"
        ],
        "id": 2117554,
        "name:xx": "Bowles"
      }
    },
    {
      "geometry": {
        "type": "Point",
        "coordinates": [
          -79.8,
          38.4833
        ]
      },
      "type": "Feature",
      "properties": {
        "hierarchy": [
          "tgn:2117557",
          "tgn:1000001",
          "tgn:7012149",
          "tgn:2002287",
          "tgn:7013961",
          "tgn:7029392"
        ],
        "placetype": [
          "aat:300008347"
        ],
        "id": 2117557,
        "name:xx": "Boyer"
      }
    },
    {
      "geometry": {
        "type": "Point",
        "coordinates": [
          -80.8167,
          37.45
        ]
      },
      "type": "Feature",
      "properties": {
        "hierarchy": [
          "tgn:2117558",
          "tgn:1000001",
          "tgn:7012149",
          "tgn:2002282",
          "tgn:7013961",
          "tgn:7029392"
        ],
        "placetype": [
          "aat:300008347"
        ],
        "id": 2117558,
        "name:xx": "Bozoo"
      }
    },
    {
      "geometry": {
        "type": "Point",
        "coordinates": [
          -81.1833,
          37.85
        ]
      },
      "type": "Feature",
      "properties": {
        "hierarchy": [
          "tgn:2117559",
          "tgn:1000001",
          "tgn:7012149",
          "tgn:2002290",
          "tgn:7013961",
          "tgn:7029392"
        ],
        "placetype": [
          "aat:300008347"
        ],
        "id": 2117559,
        "name:xx": "Bradley"
      }
    }
  ]
}
