{
  "geometry": {
    "type": "Point",
    "coordinates": [
      -90.3833,
      41.25
    ]
  },
  "type": "Feature",
  "properties": {
    "hierarchy": [
      "tgn:2559813",
      "tgn:1000001",
      "tgn:7012149",
      "tgn:2000511",
      "tgn:7007251",
      "tgn:7029392"
    ],
    "placetype": [
      "aat:300008347"
    ],
    "id": 2559813,
    "name:xx": "Ophiem"
  }
}
