{
  "geometry": {
    "type": "Point",
    "coordinates": [
      -96.95,
      44.3333
    ]
  },
  "type": "Feature",
  "properties": {
    "hierarchy": [
      "tgn:2354429",
      "tgn:1000001",
      "tgn:2001775",
      "tgn:7012149",
      "tgn:7007713",
      "tgn:7029392"
    ],
    "placetype": [
      "aat:300008680"
    ],
    "id": 2354429,
    "name:xx": "Goldsmith, Lake"
  }
}
