{
  "geometry": {
    "type": "Point",
    "coordinates": [
      0.2333,
      49.15
    ]
  },
  "type": "Feature",
  "properties": {
    "hierarchy": [
      "tgn:1128138",
      "tgn:7002872",
      "tgn:1000003",
      "tgn:1000070",
      "tgn:7029392"
    ],
    "placetype": [
      "aat:300008707"
    ],
    "id": 1128138,
    "name:xx": "Orbec"
  }
}
