{
  "geometry": {
    "type": "Point",
    "coordinates": [
      -77.0833,
      -12.0167
    ]
  },
  "type": "Feature",
  "properties": {
    "hierarchy": [
      "tgn:1024442",
      "tgn:1001172",
      "tgn:1000002",
      "tgn:1000056",
      "tgn:7029392"
    ],
    "placetype": [
      "aat:300008347"
    ],
    "id": 1024442,
    "name:xx": "Chavarría"
  }
}
