{
  "type": "FeatureCollection",
  "features": [
    {
      "geometry": {
        "type": "Point",
        "coordinates": [
          -83.0667,
          35.4333
        ]
      },
      "type": "Feature",
      "properties": {
        "hierarchy": [
          "tgn:2240930",
          "tgn:1000001",
          "tgn:7012149",
          "tgn:2001503",
          "tgn:7007709",
          "tgn:7029392"
        ],
        "placetype": [
          "aat:300008347"
        ],
        "id": 2240930,
        "name:xx": "Clark"
      }
    },
    {
      "geometry": {
        "type": "Point",
        "coordinates": [
          -84.7167,
          40
        ]
      },
      "type": "Feature",
      "properties": {
        "hierarchy": [
          "tgn:2240931",
          "tgn:1000001",
          "tgn:1002317",
          "tgn:7012149",
          "tgn:7007706",
          "tgn:7029392"
        ],
        "placetype": [
          "aat:300008347"
        ],
        "id": 2240931,
        "name:xx": "Clark"
      }
    },
    {
      "geometry": {
        "type": "Point",
        "coordinates": [
          -82.75,
          36.9833
        ]
      },
      "type": "Feature",
      "properties": {
        "hierarchy": [
          "tgn:2240932",
          "tgn:1000001",
          "tgn:7012149",
          "tgn:2002195",
          "tgn:7007919",
          "tgn:7029392"
        ],
        "placetype": [
          "aat:300008347"
        ],
        "id": 2240932,
        "name:xx": "Clark"
      }
    },
    {
      "geometry": {
        "type": "Point",
        "coordinates": [
          -91.65,
          37.65
        ]
      },
      "type": "Feature",
      "properties": {
        "hierarchy": [
          "tgn:2240933",
          "tgn:1000001",
          "tgn:7012149",
          "tgn:2001195",
          "tgn:7007523",
          "tgn:7029392"
        ],
        "placetype": [
          "aat:300000390"
        ],
        "id": 2240933,
        "name:xx": "Clark Bank"
      }
    },
    {
      "geometry": {
        "type": "Point",
        "coordinates": [
          -132.6167,
          55.4833
        ]
      },
      "type": "Feature",
      "properties": {
        "hierarchy": [
          "tgn:2240934",
          "tgn:7006450",
          "tgn:1000001",
          "tgn:7012149",
          "tgn:2000082",
          "tgn:7029392"
        ],
        "placetype": [
          "aat:300132316"
        ],
        "id": 2240934,
        "name:xx": "Clark Bay"
      }
    },
    {
      "geometry": {
        "type": "Point",
        "coordinates": [
          -160,
          55.7667
        ]
      },
      "type": "Feature",
      "properties": {
        "hierarchy": [
          "tgn:2240935",
          "tgn:7006450",
          "tgn:1000001",
          "tgn:7012149",
          "tgn:7029392"
        ],
        "placetype": [
          "aat:300132316"
        ],
        "id": 2240935,
        "name:xx": "Clark Bay"
      }
    },
    {
      "geometry": {
        "type": "Point",
        "coordinates": [
          -81.2333,
          29.1167
        ]
      },
      "type": "Feature",
      "properties": {
        "hierarchy": [
          "tgn:2240936",
          "tgn:1000001",
          "tgn:7012149",
          "tgn:1002977",
          "tgn:7007240",
          "tgn:7029392"
        ],
        "placetype": [
          "aat:300008905"
        ],
        "id": 2240936,
        "name:xx": "Clark Bay"
      }
    },
    {
      "geometry": {
        "type": "Point",
        "coordinates": [
          -89.55,
          47.9833
        ]
      },
      "type": "Feature",
      "properties": {
        "hierarchy": [
          "tgn:2240937",
          "tgn:1000001",
          "tgn:2001014",
          "tgn:7012149",
          "tgn:7007521",
          "tgn:7029392"
        ],
        "placetype": [
          "aat:300132316"
        ],
        "id": 2240937,
        "name:xx": "Clark Bay"
      }
    },
    {
      "geometry": {
        "type": "Point",
        "coordinates": [
          -75.6667,
          37.5667
        ]
      },
      "type": "Feature",
      "properties": {
        "hierarchy": [
          "tgn:2240938",
          "tgn:1002132",
          "tgn:1000001",
          "tgn:7012149",
          "tgn:7007919",
          "tgn:7029392"
        ],
        "placetype": [
          "aat:300132316"
        ],
        "id": 2240938,
        "name:xx": "Clark Bay"
      }
    },
    {
      "geometry": {
        "type": "Point",
        "coordinates": [
          -92.2167,
          34.6333
        ]
      },
      "type": "Feature",
      "properties": {
        "hierarchy": [
          "tgn:2240939",
          "tgn:1000001",
          "tgn:7016172",
          "tgn:7012149",
          "tgn:2000164",
          "tgn:7029392"
        ],
        "placetype": [
          "aat:300008699"
        ],
        "id": 2240939,
        "name:xx": "Clark Bayou"
      }
    }
  ]
}
