{
  "geometry": {
    "type": "Point",
    "coordinates": [
      33.2833,
      49.3833
    ]
  },
  "type": "Feature",
  "properties": {
    "hierarchy": [
      "tgn:1054011",
      "tgn:1000003",
      "tgn:7011666",
      "tgn:7006660",
      "tgn:7029392"
    ],
    "placetype": [
      "aat:300008347"
    ],
    "id": 1054011,
    "name:xx": "Hlobyne"
  }
}
