{
  "geometry": {
    "type": "Point",
    "coordinates": [
      26.175853,
      31.347128
    ]
  },
  "type": "Feature",
  "properties": {
    "hierarchy": [
      "tgn:7520354",
      "tgn:7001242",
      "tgn:7016833",
      "tgn:1001418",
      "tgn:7029392"
    ],
    "placetype": [
      "aat:300006207"
    ],
    "name:en": "Ābār Abū Sir'",
    "id": 7520354
  }
}
