{
  "geometry": {
    "type": "Point",
    "coordinates": [
      -107.1333,
      32.6667
    ]
  },
  "type": "Feature",
  "properties": {
    "hierarchy": [
      "tgn:2379955",
      "tgn:1000001",
      "tgn:2001435",
      "tgn:7012149",
      "tgn:7007566",
      "tgn:7029392"
    ],
    "placetype": [
      "aat:300006075"
    ],
    "id": 2379955,
    "name:xx": "Hatch Drain"
  }
}
