{
  "geometry": {
    "type": "Point",
    "coordinates": [
      -71.2667,
      41.8333
    ]
  },
  "type": "Feature",
  "properties": {
    "hierarchy": [
      "tgn:2222414",
      "tgn:1002201",
      "tgn:1000001",
      "tgn:7012149",
      "tgn:7007517",
      "tgn:7029392"
    ],
    "placetype": [
      "aat:300008699"
    ],
    "id": 2222414,
    "name:xx": "Carpenter Brook"
  }
}
