{
  "geometry": {
    "type": "Point",
    "coordinates": [
      -95.65,
      29.0333
    ]
  },
  "type": "Feature",
  "properties": {
    "hierarchy": [
      "tgn:2312621",
      "tgn:1000001",
      "tgn:1002198",
      "tgn:7012149",
      "tgn:7007826",
      "tgn:7029392"
    ],
    "placetype": [
      "aat:300008347"
    ],
    "id": 2312621,
    "name:xx": "El Bernardo"
  }
}
