{
  "geometry": {
    "type": "Point",
    "coordinates": [
      -79.6167,
      38.4667
    ]
  },
  "type": "Feature",
  "properties": {
    "hierarchy": [
      "tgn:2698433",
      "tgn:1000001",
      "tgn:7012149",
      "tgn:7029392"
    ],
    "placetype": [
      "aat:300008699"
    ],
    "id": 2698433,
    "name:xx": "Straight Fork"
  }
}
