{
  "geometry": {
    "type": "Point",
    "coordinates": [
      -91.5333,
      35.9333
    ]
  },
  "type": "Feature",
  "properties": {
    "hierarchy": [
      "tgn:2007925",
      "tgn:1000001",
      "tgn:7016172",
      "tgn:7012149",
      "tgn:2000172",
      "tgn:7029392"
    ],
    "placetype": [
      "aat:300008347"
    ],
    "id": 2007925,
    "name:xx": "Cave City"
  }
}
