{
  "geometry": {
    "type": "Point",
    "coordinates": [
      -91.65,
      37.3667
    ]
  },
  "type": "Feature",
  "properties": {
    "hierarchy": [
      "tgn:2433158",
      "tgn:1000001",
      "tgn:7012149",
      "tgn:7007523",
      "tgn:7029392"
    ],
    "placetype": [
      "aat:300008761"
    ],
    "id": 2433158,
    "name:xx": "Kell Hollow"
  }
}
