{
  "geometry": {
    "type": "Point",
    "coordinates": [
      -82.0667,
      26.95
    ]
  },
  "type": "Feature",
  "properties": {
    "hierarchy": [
      "tgn:2018863",
      "tgn:1000001",
      "tgn:1002258",
      "tgn:7012149",
      "tgn:7007240",
      "tgn:7029392"
    ],
    "placetype": [
      "aat:300008347"
    ],
    "id": 2018863,
    "name:xx": "Charlotte Harbor"
  }
}
