{
  "geometry": {
    "type": "Point",
    "coordinates": [
      14.5667,
      -3.2667
    ]
  },
  "type": "Feature",
  "properties": {
    "hierarchy": [
      "tgn:1088728",
      "tgn:7001242",
      "tgn:1001023",
      "tgn:1000158",
      "tgn:7029392"
    ],
    "placetype": [
      "aat:300008347"
    ],
    "id": 1088728,
    "name:xx": "Pangala"
  }
}
