{
  "geometry": {
    "type": "Point",
    "coordinates": [
      -75.0333,
      40.75
    ]
  },
  "type": "Feature",
  "properties": {
    "hierarchy": [
      "tgn:2133957",
      "tgn:1000001",
      "tgn:1002985",
      "tgn:7012149",
      "tgn:7007565",
      "tgn:7029392"
    ],
    "placetype": [
      "aat:300006191"
    ],
    "id": 2133957,
    "name:xx": "Angens Pond"
  }
}
