{
  "geometry": {
    "type": "Point",
    "coordinates": [
      -106.65,
      42.8333
    ]
  },
  "type": "Feature",
  "properties": {
    "hierarchy": [
      "tgn:2424756",
      "tgn:1000001",
      "tgn:7012149",
      "tgn:2002377",
      "tgn:7007923",
      "tgn:7029392"
    ],
    "placetype": [
      "aat:300006075"
    ],
    "id": 2424756,
    "name:xx": "Johnson Ditch"
  }
}
