{
  "geometry": {
    "type": "Point",
    "coordinates": [
      -63.3333,
      46.4333
    ]
  },
  "type": "Feature",
  "properties": {
    "hierarchy": [
      "tgn:1015254",
      "tgn:7005685",
      "tgn:1000001",
      "tgn:7005803",
      "tgn:7029392"
    ],
    "placetype": [
      "aat:300008347"
    ],
    "id": 1015254,
    "name:xx": "North Rustico"
  }
}
