{
  "geometry": {
    "type": "Point",
    "coordinates": [
      -121.8667,
      37.85
    ]
  },
  "type": "Feature",
  "properties": {
    "hierarchy": [
      "tgn:2777072",
      "tgn:1000001",
      "tgn:7012149",
      "tgn:1002298",
      "tgn:7007157",
      "tgn:7029392"
    ],
    "placetype": [
      "aat:300008798"
    ],
    "id": 2777072,
    "name:xx": "Windy Point"
  }
}
