{
  "geometry": {
    "type": "Point",
    "coordinates": [
      -102.75,
      30.0167
    ]
  },
  "type": "Feature",
  "properties": {
    "hierarchy": [
      "tgn:2553565",
      "tgn:1000001",
      "tgn:2001945",
      "tgn:7012149",
      "tgn:7007826",
      "tgn:7029392"
    ],
    "placetype": [
      "aat:300008761"
    ],
    "id": 2553565,
    "name:xx": "Oak Draw"
  }
}
