{
  "type": "FeatureCollection",
  "features": [
    {
      "geometry": {
        "type": "Point",
        "coordinates": [
          9.483333,
          50.366667
        ]
      },
      "type": "Feature",
      "properties": {
        "hierarchy": [
          "tgn:7202530",
          "tgn:1000003",
          "tgn:7003678",
          "tgn:7000084",
          "tgn:7029392"
        ],
        "placetype": [
          "aat:300008347"
        ],
        "id": 7202530,
        "name:xx": "Breitenbach"
      }
    },
    {
      "geometry": {
        "type": "Point",
        "coordinates": [
          9.816667,
          50.283333
        ]
      },
      "type": "Feature",
      "properties": {
        "hierarchy": [
          "tgn:7202531",
          "tgn:7003669",
          "tgn:1000003",
          "tgn:7000084",
          "tgn:7029392"
        ],
        "placetype": [
          "aat:300008347"
        ],
        "id": 7202531,
        "name:xx": "Breitenbach"
      }
    },
    {
      "geometry": {
        "type": "Point",
        "coordinates": [
          11.166667,
          49.783333
        ]
      },
      "type": "Feature",
      "properties": {
        "hierarchy": [
          "tgn:7202532",
          "tgn:7003669",
          "tgn:1000003",
          "tgn:7000084",
          "tgn:7029392"
        ],
        "placetype": [
          "aat:300008347"
        ],
        "id": 7202532,
        "name:xx": "Breitenbach"
      }
    },
    {
      "geometry": {
        "type": "Point",
        "coordinates": [
          7.266667,
          49.433333
        ]
      },
      "type": "Feature",
      "properties": {
        "hierarchy": [
          "tgn:7202533",
          "tgn:1000003",
          "tgn:7003682",
          "tgn:7000084",
          "tgn:7029392"
        ],
        "placetype": [
          "aat:300008347"
        ],
        "id": 7202533,
        "name:xx": "Breitenbach"
      }
    },
    {
      "geometry": {
        "type": "Point",
        "coordinates": [
          12.45,
          49.116667
        ]
      },
      "type": "Feature",
      "properties": {
        "hierarchy": [
          "tgn:7202534",
          "tgn:7003669",
          "tgn:1000003",
          "tgn:7000084",
          "tgn:7029392"
        ],
        "placetype": [
          "aat:300008347"
        ],
        "id": 7202534,
        "name:xx": "Breitenbach"
      }
    },
    {
      "geometry": {
        "type": "Point",
        "coordinates": [
          10.216667,
          49.033333
        ]
      },
      "type": "Feature",
      "properties": {
        "hierarchy": [
          "tgn:7202535",
          "tgn:7003692",
          "tgn:1000003",
          "tgn:7000084",
          "tgn:7029392"
        ],
        "placetype": [
          "aat:300008347"
        ],
        "id": 7202535,
        "name:xx": "Breitenbach"
      }
    },
    {
      "geometry": {
        "type": "Point",
        "coordinates": [
          10.1,
          47.916667
        ]
      },
      "type": "Feature",
      "properties": {
        "hierarchy": [
          "tgn:7202537",
          "tgn:7003692",
          "tgn:1000003",
          "tgn:7000084",
          "tgn:7029392"
        ],
        "placetype": [
          "aat:300008347"
        ],
        "id": 7202537,
        "name:xx": "Breitenbach"
      }
    },
    {
      "geometry": {
        "type": "Point",
        "coordinates": [
          11.85,
          47.733333
        ]
      },
      "type": "Feature",
      "properties": {
        "hierarchy": [
          "tgn:7202538",
          "tgn:7003669",
          "tgn:1000003",
          "tgn:7000084",
          "tgn:7029392"
        ],
        "placetype": [
          "aat:300008347"
        ],
        "id": 7202538,
        "name:xx": "Breitenbach"
      }
    },
    {
      "geometry": {
        "type": "Point",
        "coordinates": [
          13.016667,
          48.85
        ]
      },
      "type": "Feature",
      "properties": {
        "hierarchy": [
          "tgn:7202539",
          "tgn:7003669",
          "tgn:1000003",
          "tgn:7000084",
          "tgn:7029392"
        ],
        "placetype": [
          "aat:300000206"
        ],
        "id": 7202539,
        "name:xx": "Breitenbach"
      }
    }
  ]
}
