{
  "geometry": {
    "type": "Point",
    "coordinates": [
      -149.55,
      60.7667
    ]
  },
  "type": "Feature",
  "properties": {
    "hierarchy": [
      "tgn:2707846",
      "tgn:7006450",
      "tgn:1000001",
      "tgn:7019698",
      "tgn:7012149",
      "tgn:7029392"
    ],
    "placetype": [
      "aat:300000390"
    ],
    "id": 2707846,
    "name:xx": "Swetmann Mine"
  }
}
