{
  "geometry": {
    "type": "Point",
    "coordinates": [
      -97.6833,
      31.1833
    ]
  },
  "type": "Feature",
  "properties": {
    "hierarchy": [
      "tgn:2613461",
      "tgn:1000001",
      "tgn:7012149",
      "tgn:1002303",
      "tgn:7007826",
      "tgn:7029392"
    ],
    "placetype": [
      "aat:300008798"
    ],
    "id": 2613461,
    "name:xx": "Reed Mountain"
  }
}
