{
  "type": "FeatureCollection",
  "features": [
    {
      "geometry": {
        "type": "Point",
        "coordinates": [
          -87.1667,
          36.5
        ]
      },
      "type": "Feature",
      "properties": {
        "hierarchy": [
          "tgn:2301831",
          "tgn:1000001",
          "tgn:7012149",
          "tgn:2001899",
          "tgn:7007825",
          "tgn:7029392"
        ],
        "placetype": [
          "aat:300008746"
        ],
        "id": 2301831,
        "name:xx": "Durham Cave"
      }
    },
    {
      "geometry": {
        "type": "Point",
        "coordinates": [
          -75.2,
          40.5833
        ]
      },
      "type": "Feature",
      "properties": {
        "hierarchy": [
          "tgn:2301832",
          "tgn:1000001",
          "tgn:1002213",
          "tgn:7012149",
          "tgn:7007710",
          "tgn:7029392"
        ],
        "placetype": [
          "aat:300008746"
        ],
        "id": 2301832,
        "name:xx": "Durham Cave Number One"
      }
    },
    {
      "geometry": {
        "type": "Point",
        "coordinates": [
          -106.1167,
          47.9
        ]
      },
      "type": "Feature",
      "properties": {
        "hierarchy": [
          "tgn:2301834",
          "tgn:1000001",
          "tgn:7012149",
          "tgn:2001287",
          "tgn:7007524",
          "tgn:7029392"
        ],
        "placetype": [
          "aat:300008761"
        ],
        "id": 2301834,
        "name:xx": "Durham Coulee"
      }
    },
    {
      "geometry": {
        "type": "Point",
        "coordinates": [
          -146,
          62
        ]
      },
      "type": "Feature",
      "properties": {
        "hierarchy": [
          "tgn:2301835",
          "tgn:7006450",
          "tgn:1000001",
          "tgn:7012149",
          "tgn:2000086",
          "tgn:7029392"
        ],
        "placetype": [
          "aat:300008706"
        ],
        "id": 2301835,
        "name:xx": "Durham Creek"
      }
    },
    {
      "geometry": {
        "type": "Point",
        "coordinates": [
          -115.75,
          47.0333
        ]
      },
      "type": "Feature",
      "properties": {
        "hierarchy": [
          "tgn:2301836",
          "tgn:1000001",
          "tgn:7012149",
          "tgn:2000491",
          "tgn:7007250",
          "tgn:7029392"
        ],
        "placetype": [
          "aat:300008706"
        ],
        "id": 2301836,
        "name:xx": "Durham Creek"
      }
    },
    {
      "geometry": {
        "type": "Point",
        "coordinates": [
          -96.8833,
          37.45
        ]
      },
      "type": "Feature",
      "properties": {
        "hierarchy": [
          "tgn:2301837",
          "tgn:1000001",
          "tgn:2000677",
          "tgn:7012149",
          "tgn:7007254",
          "tgn:7029392"
        ],
        "placetype": [
          "aat:300008706"
        ],
        "id": 2301837,
        "name:xx": "Durham Creek"
      }
    },
    {
      "geometry": {
        "type": "Point",
        "coordinates": [
          -96.1167,
          37.7667
        ]
      },
      "type": "Feature",
      "properties": {
        "hierarchy": [
          "tgn:2301838",
          "tgn:1000001",
          "tgn:2000696",
          "tgn:7012149",
          "tgn:7007254",
          "tgn:7029392"
        ],
        "placetype": [
          "aat:300008706"
        ],
        "id": 2301838,
        "name:xx": "Durham Creek"
      }
    },
    {
      "geometry": {
        "type": "Point",
        "coordinates": [
          -76.9,
          35.2833
        ]
      },
      "type": "Feature",
      "properties": {
        "hierarchy": [
          "tgn:2301839",
          "tgn:1000001",
          "tgn:7013368",
          "tgn:7012149",
          "tgn:7007709",
          "tgn:7029392"
        ],
        "placetype": [
          "aat:300008706"
        ],
        "id": 2301839,
        "name:xx": "Durham Creek"
      }
    }
  ]
}
