{
  "geometry": {
    "type": "Point",
    "coordinates": [
      -88.9167,
      42.8333
    ]
  },
  "type": "Feature",
  "properties": {
    "hierarchy": [
      "tgn:2121538",
      "tgn:1000001",
      "tgn:7012149",
      "tgn:7014350",
      "tgn:7007922",
      "tgn:7029392"
    ],
    "placetype": [
      "aat:300008347",
      "aat:300387210"
    ],
    "id": 2121538,
    "name:xx": "Koshkonong"
  }
}
