{
  "geometry": {
    "type": "Point",
    "coordinates": [
      -92.9667,
      37.2167
    ]
  },
  "type": "Feature",
  "properties": {
    "hierarchy": [
      "tgn:2227386",
      "tgn:1000001",
      "tgn:7012149",
      "tgn:2001256",
      "tgn:7007523",
      "tgn:7029392"
    ],
    "placetype": [
      "aat:300008697"
    ],
    "id": 2227386,
    "name:xx": "Cave Spring"
  }
}
