{
  "geometry": {
    "type": "Point",
    "coordinates": [
      -86.1333,
      39.2333
    ]
  },
  "type": "Feature",
  "properties": {
    "hierarchy": [
      "tgn:2528128",
      "tgn:1000001",
      "tgn:7012149",
      "tgn:7007252",
      "tgn:7029392"
    ],
    "placetype": [
      "aat:300266640"
    ],
    "id": 2528128,
    "name:xx": "Mountain Tea Ridge"
  }
}
