{
  "geometry": {
    "type": "Point",
    "coordinates": [
      -76.6833,
      39.5833
    ]
  },
  "type": "Feature",
  "properties": {
    "hierarchy": [
      "tgn:2192498",
      "tgn:7016099",
      "tgn:1000001",
      "tgn:7012149",
      "tgn:7007516",
      "tgn:7029392"
    ],
    "placetype": [
      "aat:300008347"
    ],
    "id": 2192498,
    "name:xx": "Brandy Springs"
  }
}
