{
  "geometry": {
    "type": "Point",
    "coordinates": [
      -79.0667,
      33.8167
    ]
  },
  "type": "Feature",
  "properties": {
    "hierarchy": [
      "tgn:2404644",
      "tgn:1000001",
      "tgn:7012149",
      "tgn:2001750",
      "tgn:7007712",
      "tgn:7029392"
    ],
    "placetype": [
      "aat:300008347"
    ],
    "id": 2404644,
    "name:xx": "Huckabee Heights"
  }
}
