{
  "geometry": {
    "type": "Point",
    "coordinates": [
      17.0333,
      -1.4333
    ]
  },
  "type": "Feature",
  "properties": {
    "hierarchy": [
      "tgn:1089375",
      "tgn:7001242",
      "tgn:7016654",
      "tgn:1000159",
      "tgn:7029392"
    ],
    "placetype": [
      "aat:300008347"
    ],
    "id": 1089375,
    "name:xx": "Mpoka"
  }
}
