{
  "geometry": {
    "type": "Point",
    "coordinates": [
      -91.0333,
      38.5833
    ]
  },
  "type": "Feature",
  "properties": {
    "hierarchy": [
      "tgn:2637379",
      "tgn:1000001",
      "tgn:7012149",
      "tgn:1002384",
      "tgn:7007523",
      "tgn:7029392"
    ],
    "placetype": [
      "aat:300055621"
    ],
    "id": 2637379,
    "name:xx": "Saint Johns Island"
  }
}
