{
  "geometry": {
    "type": "Point",
    "coordinates": [
      126.6333,
      37.9833
    ]
  },
  "type": "Feature",
  "properties": {
    "hierarchy": [
      "tgn:7002377",
      "tgn:1001302",
      "tgn:1000004",
      "tgn:1000122",
      "tgn:7029392"
    ],
    "placetype": [
      "aat:300008347"
    ],
    "id": 7002377,
    "name:xx": "Panmunjŏm"
  }
}
