{
  "type": "FeatureCollection",
  "features": [
    {
      "geometry": {
        "type": "Point",
        "coordinates": [
          -144.1833,
          64.35
        ]
      },
      "type": "Feature",
      "properties": {
        "hierarchy": [
          "tgn:2703350",
          "tgn:7006450",
          "tgn:1000001",
          "tgn:7012149",
          "tgn:2000085",
          "tgn:7029392"
        ],
        "placetype": [
          "aat:300008706"
        ],
        "id": 2703350,
        "name:xx": "Summit Creek"
      }
    },
    {
      "geometry": {
        "type": "Point",
        "coordinates": [
          -155.3833,
          60.7833
        ]
      },
      "type": "Feature",
      "properties": {
        "hierarchy": [
          "tgn:2703351",
          "tgn:7006450",
          "tgn:1000001",
          "tgn:7030517",
          "tgn:7012149",
          "tgn:7029392"
        ],
        "placetype": [
          "aat:300008706"
        ],
        "id": 2703351,
        "name:xx": "Summit Creek"
      }
    },
    {
      "geometry": {
        "type": "Point",
        "coordinates": [
          -165,
          64.7333
        ]
      },
      "type": "Feature",
      "properties": {
        "hierarchy": [
          "tgn:2703352",
          "tgn:7006450",
          "tgn:1000001",
          "tgn:7012149",
          "tgn:2000079",
          "tgn:7029392"
        ],
        "placetype": [
          "aat:300008706"
        ],
        "id": 2703352,
        "name:xx": "Summit Creek"
      }
    },
    {
      "geometry": {
        "type": "Point",
        "coordinates": [
          -136.1667,
          59.3333
        ]
      },
      "type": "Feature",
      "properties": {
        "hierarchy": [
          "tgn:2703353",
          "tgn:7006450",
          "tgn:1000001",
          "tgn:7012149",
          "tgn:7029392"
        ],
        "placetype": [
          "aat:300008706"
        ],
        "id": 2703353,
        "name:xx": "Summit Creek"
      }
    },
    {
      "geometry": {
        "type": "Point",
        "coordinates": [
          -121.4167,
          40.4833
        ]
      },
      "type": "Feature",
      "properties": {
        "hierarchy": [
          "tgn:2703354",
          "tgn:1000001",
          "tgn:7012149",
          "tgn:7007157",
          "tgn:2000188",
          "tgn:7029392"
        ],
        "placetype": [
          "aat:300008706"
        ],
        "id": 2703354,
        "name:xx": "Summit Creek"
      }
    },
    {
      "geometry": {
        "type": "Point",
        "coordinates": [
          -123.7333,
          40.9333
        ]
      },
      "type": "Feature",
      "properties": {
        "hierarchy": [
          "tgn:2703355",
          "tgn:1000001",
          "tgn:7012149",
          "tgn:2000181",
          "tgn:7007157",
          "tgn:7029392"
        ],
        "placetype": [
          "aat:300008706"
        ],
        "id": 2703355,
        "name:xx": "Summit Creek"
      }
    },
    {
      "geometry": {
        "type": "Point",
        "coordinates": [
          -119.1833,
          37.0833
        ]
      },
      "type": "Feature",
      "properties": {
        "hierarchy": [
          "tgn:2703356",
          "tgn:1000001",
          "tgn:7012149",
          "tgn:1002392",
          "tgn:7007157",
          "tgn:7029392"
        ],
        "placetype": [
          "aat:300008706"
        ],
        "id": 2703356,
        "name:xx": "Summit Creek"
      }
    },
    {
      "geometry": {
        "type": "Point",
        "coordinates": [
          -119.65,
          38.2167
        ]
      },
      "type": "Feature",
      "properties": {
        "hierarchy": [
          "tgn:2703357",
          "tgn:1000001",
          "tgn:7012149",
          "tgn:7007157",
          "tgn:1002957",
          "tgn:7029392"
        ],
        "placetype": [
          "aat:300008706"
        ],
        "id": 2703357,
        "name:xx": "Summit Creek"
      }
    },
    {
      "geometry": {
        "type": "Point",
        "coordinates": [
          -121.5167,
          40.3833
        ]
      },
      "type": "Feature",
      "properties": {
        "hierarchy": [
          "tgn:2703358",
          "tgn:1000001",
          "tgn:7012149",
          "tgn:7007157",
          "tgn:2000190",
          "tgn:7029392"
        ],
        "placetype": [
          "aat:300008706"
        ],
        "id": 2703358,
        "name:xx": "Summit Creek"
      }
    },
    {
      "geometry": {
        "type": "Point",
        "coordinates": [
          -122.9833,
          40.5667
        ]
      },
      "type": "Feature",
      "properties": {
        "hierarchy": [
          "tgn:2703359",
          "tgn:1000001",
          "tgn:7012149",
          "tgn:7007157",
          "tgn:2000191",
          "tgn:7029392"
        ],
        "placetype": [
          "aat:300008706"
        ],
        "id": 2703359,
        "name:xx": "Summit Creek"
      }
    }
  ]
}
