{
  "geometry": {
    "type": "Point",
    "coordinates": [
      -97.8333,
      38.6167
    ]
  },
  "type": "Feature",
  "properties": {
    "hierarchy": [
      "tgn:2606354",
      "tgn:1000001",
      "tgn:7012149",
      "tgn:2000744",
      "tgn:7007254",
      "tgn:7029392"
    ],
    "placetype": [
      "aat:300008706"
    ],
    "id": 2606354,
    "name:xx": "Ralston Creek"
  }
}
