{
  "type": "FeatureCollection",
  "features": [
    {
      "geometry": {
        "type": "Point",
        "coordinates": [
          -111.1,
          40.65
        ]
      },
      "type": "Feature",
      "properties": {
        "hierarchy": [
          "tgn:2254890",
          "tgn:1000001",
          "tgn:7012149",
          "tgn:2002122",
          "tgn:7007827",
          "tgn:7029392"
        ],
        "placetype": [
          "aat:300008706"
        ],
        "id": 2254890,
        "name:xx": "Coop Creek"
      }
    },
    {
      "geometry": {
        "type": "Point",
        "coordinates": [
          -107.8167,
          37.2
        ]
      },
      "type": "Feature",
      "properties": {
        "hierarchy": [
          "tgn:2254891",
          "tgn:1000001",
          "tgn:7012149",
          "tgn:2000225",
          "tgn:7007158",
          "tgn:7029392"
        ],
        "placetype": [
          "aat:300006075"
        ],
        "id": 2254891,
        "name:xx": "Coop Ditch"
      }
    },
    {
      "geometry": {
        "type": "Point",
        "coordinates": [
          -108.5,
          32.45
        ]
      },
      "type": "Feature",
      "properties": {
        "hierarchy": [
          "tgn:2254892",
          "tgn:1000001",
          "tgn:7012149",
          "tgn:2001437",
          "tgn:7007566",
          "tgn:7029392"
        ],
        "placetype": [
          "aat:300000390"
        ],
        "id": 2254892,
        "name:xx": "Coop Mine"
      }
    },
    {
      "geometry": {
        "type": "Point",
        "coordinates": [
          -82.8,
          29.85
        ]
      },
      "type": "Feature",
      "properties": {
        "hierarchy": [
          "tgn:2254893",
          "tgn:1000001",
          "tgn:2000269",
          "tgn:7012149",
          "tgn:7007240",
          "tgn:7029392"
        ],
        "placetype": [
          "aat:300008680"
        ],
        "id": 2254893,
        "name:xx": "Coop Pond"
      }
    },
    {
      "geometry": {
        "type": "Point",
        "coordinates": [
          -94.2,
          35.05
        ]
      },
      "type": "Feature",
      "properties": {
        "hierarchy": [
          "tgn:2254894",
          "tgn:1000001",
          "tgn:7016172",
          "tgn:7012149",
          "tgn:7029392"
        ],
        "placetype": [
          "aat:300266640"
        ],
        "id": 2254894,
        "name:xx": "Coop Ridge"
      }
    },
    {
      "geometry": {
        "type": "Point",
        "coordinates": [
          -111.7667,
          35.3333
        ]
      },
      "type": "Feature",
      "properties": {
        "hierarchy": [
          "tgn:2254895",
          "tgn:1000001",
          "tgn:7006451",
          "tgn:2000092",
          "tgn:7012149",
          "tgn:7029392"
        ],
        "placetype": [
          "aat:300006191"
        ],
        "id": 2254895,
        "name:xx": "Coop Tank"
      }
    },
    {
      "geometry": {
        "type": "Point",
        "coordinates": [
          -112.7667,
          34.7667
        ]
      },
      "type": "Feature",
      "properties": {
        "hierarchy": [
          "tgn:2254896",
          "tgn:1000001",
          "tgn:7006451",
          "tgn:7012149",
          "tgn:2000103",
          "tgn:7029392"
        ],
        "placetype": [
          "aat:300006191"
        ],
        "id": 2254896,
        "name:xx": "Coop Tank"
      }
    },
    {
      "geometry": {
        "type": "Point",
        "coordinates": [
          -86.5333,
          32.7667
        ]
      },
      "type": "Feature",
      "properties": {
        "hierarchy": [
          "tgn:2254897",
          "tgn:7002659",
          "tgn:1000001",
          "tgn:2000010",
          "tgn:7012149",
          "tgn:7029392"
        ],
        "placetype": [
          "aat:300008347"
        ],
        "id": 2254897,
        "name:xx": "Cooper"
      }
    },
    {
      "geometry": {
        "type": "Point",
        "coordinates": [
          -93.7167,
          34.2667
        ]
      },
      "type": "Feature",
      "properties": {
        "hierarchy": [
          "tgn:2254898",
          "tgn:1000001",
          "tgn:7016172",
          "tgn:7012149",
          "tgn:2000159",
          "tgn:7029392"
        ],
        "placetype": [
          "aat:300008347"
        ],
        "id": 2254898,
        "name:xx": "Cooper"
      }
    },
    {
      "geometry": {
        "type": "Point",
        "coordinates": [
          -123,
          39.2167
        ]
      },
      "type": "Feature",
      "properties": {
        "hierarchy": [
          "tgn:2254899",
          "tgn:1000001",
          "tgn:7012149",
          "tgn:7007157",
          "tgn:1002566",
          "tgn:7029392"
        ],
        "placetype": [
          "aat:300008347"
        ],
        "id": 2254899,
        "name:xx": "Cooper"
      }
    }
  ]
}
