{
  "geometry": {
    "type": "Point",
    "coordinates": [
      -78.1667,
      36.75
    ]
  },
  "type": "Feature",
  "properties": {
    "hierarchy": [
      "tgn:2113684",
      "tgn:1000001",
      "tgn:7012149",
      "tgn:2002173",
      "tgn:7007919",
      "tgn:7029392"
    ],
    "placetype": [
      "aat:300008347",
      "aat:300387210"
    ],
    "id": 2113684,
    "name:xx": "Pleasant Grove"
  }
}
