{
  "geometry": {
    "type": "Point",
    "coordinates": [
      -122.6667,
      39.9167
    ]
  },
  "type": "Feature",
  "properties": {
    "hierarchy": [
      "tgn:2631058",
      "tgn:1000001",
      "tgn:7012149",
      "tgn:7007157",
      "tgn:2000190",
      "tgn:7029392"
    ],
    "placetype": [
      "aat:300008798"
    ],
    "id": 2631058,
    "name:xx": "Round Mountain"
  }
}
