{
  "geometry": {
    "type": "Point",
    "coordinates": [
      -123.65,
      46.2833
    ]
  },
  "type": "Feature",
  "properties": {
    "hierarchy": [
      "tgn:2115686",
      "tgn:1000001",
      "tgn:7012149",
      "tgn:1002979",
      "tgn:7007920",
      "tgn:7029392"
    ],
    "placetype": [
      "aat:300008347",
      "aat:300387210"
    ],
    "id": 2115686,
    "name:xx": "Eden"
  }
}
