{
  "geometry": {
    "type": "Point",
    "coordinates": [
      -71.2333,
      44.5333
    ]
  },
  "type": "Feature",
  "properties": {
    "hierarchy": [
      "tgn:2256354",
      "tgn:1002300",
      "tgn:1000001",
      "tgn:7012149",
      "tgn:7007564",
      "tgn:7029392"
    ],
    "placetype": [
      "aat:300008347"
    ],
    "id": 2256354,
    "name:xx": "Copperville"
  }
}
