{
  "geometry": {
    "type": "Point",
    "coordinates": [
      101.1333,
      27.9167
    ]
  },
  "type": "Feature",
  "properties": {
    "hierarchy": [
      "tgn:1067331",
      "tgn:1000004",
      "tgn:7002087",
      "tgn:1000111",
      "tgn:7029392"
    ],
    "placetype": [
      "aat:300008347"
    ],
    "id": 1067331,
    "name:xx": "Dacun"
  }
}
