{
  "geometry": {
    "type": "Point",
    "coordinates": [
      -117.5167,
      51.2833
    ]
  },
  "type": "Feature",
  "properties": {
    "hierarchy": [
      "tgn:1108535",
      "tgn:7005735",
      "tgn:7005685",
      "tgn:1000001",
      "tgn:7029392"
    ],
    "placetype": [
      "aat:300259572"
    ],
    "id": 1108535,
    "name:xx": "Rogers Pass"
  }
}
