{
  "geometry": {
    "type": "Point",
    "coordinates": [
      -116.3833,
      42.35
    ]
  },
  "type": "Feature",
  "properties": {
    "hierarchy": [
      "tgn:2259094",
      "tgn:1000001",
      "tgn:7012149",
      "tgn:2000488",
      "tgn:7007250",
      "tgn:7029392"
    ],
    "placetype": [
      "aat:300008761"
    ],
    "id": 2259094,
    "name:xx": "Cottonwood Draw"
  }
}
