{
  "type": "FeatureCollection",
  "features": [
    {
      "geometry": {
        "type": "Point",
        "coordinates": [
          -90.45,
          47.85
        ]
      },
      "type": "Feature",
      "properties": {
        "hierarchy": [
          "tgn:2558810",
          "tgn:1000001",
          "tgn:2001014",
          "tgn:7012149",
          "tgn:7007521",
          "tgn:7029392"
        ],
        "placetype": [
          "aat:300008680"
        ],
        "id": 2558810,
        "name:xx": "Olso Lake"
      }
    },
    {
      "geometry": {
        "type": "Point",
        "coordinates": [
          -105.15,
          45.6833
        ]
      },
      "type": "Feature",
      "properties": {
        "hierarchy": [
          "tgn:2558811",
          "tgn:1000001",
          "tgn:7012149",
          "tgn:2001297",
          "tgn:7007524",
          "tgn:7029392"
        ],
        "placetype": [
          "aat:300008761"
        ],
        "id": 2558811,
        "name:xx": "Olson Coulee"
      }
    },
    {
      "geometry": {
        "type": "Point",
        "coordinates": [
          -105.8333,
          48.8167
        ]
      },
      "type": "Feature",
      "properties": {
        "hierarchy": [
          "tgn:2558812",
          "tgn:1000001",
          "tgn:2001269",
          "tgn:7012149",
          "tgn:7007524",
          "tgn:7029392"
        ],
        "placetype": [
          "aat:300008761"
        ],
        "id": 2558812,
        "name:xx": "Olson Coulee"
      }
    },
    {
      "geometry": {
        "type": "Point",
        "coordinates": [
          -105.2667,
          47.35
        ]
      },
      "type": "Feature",
      "properties": {
        "hierarchy": [
          "tgn:2558813",
          "tgn:1000001",
          "tgn:7012149",
          "tgn:2001270",
          "tgn:7007524",
          "tgn:7029392"
        ],
        "placetype": [
          "aat:300008761"
        ],
        "id": 2558813,
        "name:xx": "Olson Coulee"
      }
    },
    {
      "geometry": {
        "type": "Point",
        "coordinates": [
          -90.9167,
          43.9833
        ]
      },
      "type": "Feature",
      "properties": {
        "hierarchy": [
          "tgn:2558814",
          "tgn:1000001",
          "tgn:7012149",
          "tgn:2002331",
          "tgn:7007922",
          "tgn:7029392"
        ],
        "placetype": [
          "aat:300008761"
        ],
        "id": 2558814,
        "name:xx": "Olson Coulee"
      }
    },
    {
      "geometry": {
        "type": "Point",
        "coordinates": [
          -150.5333,
          60.4333
        ]
      },
      "type": "Feature",
      "properties": {
        "hierarchy": [
          "tgn:2558815",
          "tgn:7006450",
          "tgn:1000001",
          "tgn:7019698",
          "tgn:7012149",
          "tgn:7029392"
        ],
        "placetype": [
          "aat:300008706"
        ],
        "id": 2558815,
        "name:xx": "Olson Creek"
      }
    },
    {
      "geometry": {
        "type": "Point",
        "coordinates": [
          -151.0833,
          61.3333
        ]
      },
      "type": "Feature",
      "properties": {
        "hierarchy": [
          "tgn:2558816",
          "tgn:7006450",
          "tgn:1000001",
          "tgn:7012149",
          "tgn:7029392"
        ],
        "placetype": [
          "aat:300008706"
        ],
        "id": 2558816,
        "name:xx": "Olson Creek"
      }
    },
    {
      "geometry": {
        "type": "Point",
        "coordinates": [
          -116.1167,
          44.4333
        ]
      },
      "type": "Feature",
      "properties": {
        "hierarchy": [
          "tgn:2558817",
          "tgn:1000001",
          "tgn:7012149",
          "tgn:2000494",
          "tgn:7007250",
          "tgn:7029392"
        ],
        "placetype": [
          "aat:300008706"
        ],
        "id": 2558817,
        "name:xx": "Olson Creek"
      }
    },
    {
      "geometry": {
        "type": "Point",
        "coordinates": [
          -115.9,
          46.4667
        ]
      },
      "type": "Feature",
      "properties": {
        "hierarchy": [
          "tgn:2558818",
          "tgn:1000001",
          "tgn:2000469",
          "tgn:7012149",
          "tgn:7007250",
          "tgn:7029392"
        ],
        "placetype": [
          "aat:300008706"
        ],
        "id": 2558818,
        "name:xx": "Olson Creek"
      }
    },
    {
      "geometry": {
        "type": "Point",
        "coordinates": [
          -116.2833,
          47.1333
        ]
      },
      "type": "Feature",
      "properties": {
        "hierarchy": [
          "tgn:2558819",
          "tgn:1000001",
          "tgn:7012149",
          "tgn:7007250",
          "tgn:7029392"
        ],
        "placetype": [
          "aat:300008706"
        ],
        "id": 2558819,
        "name:xx": "Olson Creek"
      }
    }
  ]
}
