{
  "geometry": {
    "type": "Point",
    "coordinates": [
      -99.6833,
      29.4333
    ]
  },
  "type": "Feature",
  "properties": {
    "hierarchy": [
      "tgn:2151123",
      "tgn:1000001",
      "tgn:7012149",
      "tgn:2002087",
      "tgn:7007826",
      "tgn:7029392"
    ],
    "placetype": [
      "aat:300008746"
    ],
    "id": 2151123,
    "name:xx": "Bat Cave"
  }
}
