{
  "geometry": {
    "type": "Point",
    "coordinates": [
      23.1667,
      61.75
    ]
  },
  "type": "Feature",
  "properties": {
    "hierarchy": [
      "tgn:1116938",
      "tgn:7024077",
      "tgn:1000003",
      "tgn:1000069",
      "tgn:7029392"
    ],
    "placetype": [
      "aat:300008680"
    ],
    "id": 1116938,
    "name:xx": "Kyrösjärvi"
  }
}
