{
  "geometry": {
    "type": "Point",
    "coordinates": [
      -81.2667,
      38.7333
    ]
  },
  "type": "Feature",
  "properties": {
    "hierarchy": [
      "tgn:2245086",
      "tgn:1000001",
      "tgn:7012149",
      "tgn:2002293",
      "tgn:7013961",
      "tgn:7029392"
    ],
    "placetype": [
      "aat:300008699"
    ],
    "id": 2245086,
    "name:xx": "Clover Run"
  }
}
