{
  "geometry": {
    "type": "Point",
    "coordinates": [
      -107.6333,
      34.5167
    ]
  },
  "type": "Feature",
  "properties": {
    "hierarchy": [
      "tgn:2611343",
      "tgn:1000001",
      "tgn:7012149",
      "tgn:2001456",
      "tgn:7007566",
      "tgn:7029392"
    ],
    "placetype": [
      "aat:300008680"
    ],
    "id": 2611343,
    "name:xx": "Red Lake"
  }
}
