{
  "geometry": {
    "type": "Point",
    "coordinates": [
      -91.7167,
      34.15
    ]
  },
  "type": "Feature",
  "properties": {
    "hierarchy": [
      "tgn:2500531",
      "tgn:1000001",
      "tgn:7016172",
      "tgn:7012149",
      "tgn:2000144",
      "tgn:7029392"
    ],
    "placetype": [
      "aat:300008680"
    ],
    "id": 2500531,
    "name:xx": "McDonald Lake"
  }
}
