{
  "geometry": {
    "type": "Point",
    "coordinates": [
      -70.55,
      43.3667
    ]
  },
  "type": "Feature",
  "properties": {
    "hierarchy": [
      "tgn:2325170",
      "tgn:1000001",
      "tgn:7012149",
      "tgn:2000933",
      "tgn:7007515",
      "tgn:7029392"
    ],
    "placetype": [
      "aat:300008699"
    ],
    "id": 2325170,
    "name:xx": "Fernald Brook"
  }
}
