{
  "geometry": {
    "type": "Point",
    "coordinates": [
      113.0333,
      30.8167
    ]
  },
  "type": "Feature",
  "properties": {
    "hierarchy": [
      "tgn:1072414",
      "tgn:1000004",
      "tgn:7002078",
      "tgn:1000111",
      "tgn:7029392"
    ],
    "placetype": [
      "aat:300008347"
    ],
    "id": 1072414,
    "name:xx": "Wamiao"
  }
}
