{
  "type": "FeatureCollection",
  "features": [
    {
      "geometry": {
        "type": "Point",
        "coordinates": [
          -75.9833,
          43.3833
        ]
      },
      "type": "Feature",
      "properties": {
        "hierarchy": [
          "tgn:2073030",
          "tgn:1000001",
          "tgn:7012149",
          "tgn:1002758",
          "tgn:7007568",
          "tgn:7029392"
        ],
        "placetype": [
          "aat:300008347"
        ],
        "id": 2073030,
        "name:xx": "West Amboy"
      }
    },
    {
      "geometry": {
        "type": "Point",
        "coordinates": [
          -73.8333,
          42.2833
        ]
      },
      "type": "Feature",
      "properties": {
        "hierarchy": [
          "tgn:2073032",
          "tgn:1000001",
          "tgn:7012149",
          "tgn:1002423",
          "tgn:7007568",
          "tgn:7029392"
        ],
        "placetype": [
          "aat:300387016"
        ],
        "id": 2073032,
        "name:xx": "West Athens"
      }
    },
    {
      "geometry": {
        "type": "Point",
        "coordinates": [
          -73.35,
          40.7167
        ]
      },
      "type": "Feature",
      "properties": {
        "hierarchy": [
          "tgn:2073033",
          "tgn:1000001",
          "tgn:7012149",
          "tgn:1002924",
          "tgn:7007568",
          "tgn:7029392"
        ],
        "placetype": [
          "aat:300008347"
        ],
        "id": 2073033,
        "name:xx": "West Babylon"
      }
    },
    {
      "geometry": {
        "type": "Point",
        "coordinates": [
          -75.5333,
          42.3
        ]
      },
      "type": "Feature",
      "properties": {
        "hierarchy": [
          "tgn:2073037",
          "tgn:1000001",
          "tgn:1002262",
          "tgn:7012149",
          "tgn:7007568",
          "tgn:7029392"
        ],
        "placetype": [
          "aat:300008347"
        ],
        "id": 2073037,
        "name:xx": "West Bainbridge"
      }
    },
    {
      "geometry": {
        "type": "Point",
        "coordinates": [
          -74.4333,
          44.8
        ]
      },
      "type": "Feature",
      "properties": {
        "hierarchy": [
          "tgn:2073038",
          "tgn:1000001",
          "tgn:7012149",
          "tgn:7013941",
          "tgn:7007568",
          "tgn:7029392"
        ],
        "placetype": [
          "aat:300008347"
        ],
        "id": 2073038,
        "name:xx": "West Bangor"
      }
    },
    {
      "geometry": {
        "type": "Point",
        "coordinates": [
          -78.25,
          43.15
        ]
      },
      "type": "Feature",
      "properties": {
        "hierarchy": [
          "tgn:2073039",
          "tgn:1000001",
          "tgn:7012149",
          "tgn:1002752",
          "tgn:7007568",
          "tgn:7029392"
        ],
        "placetype": [
          "aat:300008347"
        ],
        "id": 2073039,
        "name:xx": "West Barre"
      }
    }
  ]
}
