{
  "geometry": {
    "type": "Point",
    "coordinates": [
      -90.6167,
      36.6667
    ]
  },
  "type": "Feature",
  "properties": {
    "hierarchy": [
      "tgn:2683881",
      "tgn:1000001",
      "tgn:7012149",
      "tgn:7007523",
      "tgn:7029392"
    ],
    "placetype": [
      "aat:300008699"
    ],
    "id": 2683881,
    "name:xx": "Spell Branch"
  }
}
