{
  "geometry": {
    "type": "Point",
    "coordinates": [
      -98.5333,
      32.8167
    ]
  },
  "type": "Feature",
  "properties": {
    "hierarchy": [
      "tgn:2159424",
      "tgn:1000001",
      "tgn:7012149",
      "tgn:2002053",
      "tgn:7007826",
      "tgn:7029392"
    ],
    "placetype": [
      "aat:300008706"
    ],
    "id": 2159424,
    "name:xx": "Bee Creek"
  }
}
