{
  "geometry": {
    "type": "Point",
    "coordinates": [
      -115.7167,
      43.5667
    ]
  },
  "type": "Feature",
  "properties": {
    "hierarchy": [
      "tgn:2185704",
      "tgn:1000001",
      "tgn:7012149",
      "tgn:7007250",
      "tgn:7029392"
    ],
    "placetype": [
      "aat:300008178"
    ],
    "id": 2185704,
    "name:xx": "Boise River Wildlife Management Area"
  }
}
