{
  "geometry": {
    "type": "Point",
    "coordinates": [
      -117.75,
      45.5833
    ]
  },
  "type": "Feature",
  "properties": {
    "hierarchy": [
      "tgn:2749284",
      "tgn:1000001",
      "tgn:7012149",
      "tgn:2001721",
      "tgn:7007708",
      "tgn:7029392"
    ],
    "placetype": [
      "aat:300006191"
    ],
    "id": 2749284,
    "name:xx": "Waller Reservoir 3"
  }
}
