{
  "geometry": {
    "type": "Point",
    "coordinates": [
      -124.7333,
      48.1667
    ]
  },
  "type": "Feature",
  "properties": {
    "hierarchy": [
      "tgn:2730784",
      "tgn:1000001",
      "tgn:1002271",
      "tgn:7012149",
      "tgn:7007920",
      "tgn:7029392"
    ],
    "placetype": [
      "aat:300008791"
    ],
    "id": 2730784,
    "name:xx": "Tskawahyah Island"
  }
}
