{
  "type": "FeatureCollection",
  "features": [
    {
      "geometry": {
        "type": "Point",
        "coordinates": [
          6.116667,
          51.5
        ]
      },
      "type": "Feature",
      "properties": {
        "hierarchy": [
          "tgn:7261660",
          "tgn:1000003",
          "tgn:7003622",
          "tgn:7016845",
          "tgn:7029392"
        ],
        "placetype": [
          "aat:300008347"
        ],
        "name:nl": "Gun",
        "id": 7261660
      }
    },
    {
      "geometry": {
        "type": "Point",
        "coordinates": [
          5.9,
          50.8
        ]
      },
      "type": "Feature",
      "properties": {
        "hierarchy": [
          "tgn:7261661",
          "tgn:1000003",
          "tgn:7003622",
          "tgn:7016845",
          "tgn:7029392"
        ],
        "placetype": [
          "aat:300008777"
        ],
        "name:nl": "Gulperber",
        "id": 7261661
      }
    },
    {
      "geometry": {
        "type": "Point",
        "coordinates": [
          5.883333,
          50.8
        ]
      },
      "type": "Feature",
      "properties": {
        "hierarchy": [
          "tgn:7261664",
          "tgn:1000003",
          "tgn:7003622",
          "tgn:7016845",
          "tgn:7029392"
        ],
        "placetype": [
          "aat:300008863"
        ],
        "name:nl": "Gulpdal",
        "id": 7261664
      }
    },
    {
      "geometry": {
        "type": "Point",
        "coordinates": [
          5.9,
          50.816667
        ]
      },
      "type": "Feature",
      "properties": {
        "hierarchy": [
          "tgn:7261665",
          "tgn:1000003",
          "tgn:7003622",
          "tgn:7016845",
          "tgn:7029392"
        ],
        "placetype": [
          "aat:300008699"
        ],
        "name:nl": "Gulp",
        "id": 7261665
      }
    },
    {
      "geometry": {
        "type": "Point",
        "coordinates": [
          5.566667,
          51.45
        ]
      },
      "type": "Feature",
      "properties": {
        "hierarchy": [
          "tgn:7261666",
          "tgn:1000003",
          "tgn:7003624",
          "tgn:7016845",
          "tgn:7029392"
        ],
        "placetype": [
          "aat:300008903"
        ],
        "name:nl": "Gulbergsven",
        "id": 7261666
      }
    },
    {
      "geometry": {
        "type": "Point",
        "coordinates": [
          5.716667,
          50.85
        ]
      },
      "type": "Feature",
      "properties": {
        "hierarchy": [
          "tgn:7261667",
          "tgn:1000003",
          "tgn:7003622",
          "tgn:7016845",
          "tgn:7029392"
        ],
        "placetype": [
          "aat:300387502"
        ],
        "name:nl": "Guesselt",
        "id": 7261667
      }
    },
    {
      "geometry": {
        "type": "Point",
        "coordinates": [
          6.15,
          51.416667
        ]
      },
      "type": "Feature",
      "properties": {
        "hierarchy": [
          "tgn:7261669",
          "tgn:1000003",
          "tgn:7003622",
          "tgn:7016845",
          "tgn:7029392"
        ],
        "placetype": [
          "aat:300008347"
        ],
        "name:nl": "Grubbenvorst",
        "id": 7261669
      }
    }
  ]
}
