{
  "geometry": {
    "type": "Point",
    "coordinates": [
      148.3667,
      -5.5667
    ]
  },
  "type": "Feature",
  "properties": {
    "hierarchy": [
      "tgn:1099570",
      "tgn:7006160",
      "tgn:1000946",
      "tgn:1000006",
      "tgn:7029392"
    ],
    "placetype": [
      "aat:300008347"
    ],
    "id": 1099570,
    "name:xx": "Sag Sag"
  }
}
