{
  "geometry": {
    "type": "Point",
    "coordinates": [
      -110.7833,
      44.1167
    ]
  },
  "type": "Feature",
  "properties": {
    "hierarchy": [
      "tgn:2360579",
      "tgn:1000001",
      "tgn:7012149",
      "tgn:2002384",
      "tgn:7007923",
      "tgn:7029392"
    ],
    "placetype": [
      "aat:300008706"
    ],
    "id": 2360579,
    "name:xx": "Grassy Creek"
  }
}
