{
  "geometry": {
    "type": "Point",
    "coordinates": [
      25.44951,
      36.383281
    ]
  },
  "type": "Feature",
  "properties": {
    "hierarchy": [
      "tgn:7224107",
      "tgn:7011270",
      "tgn:7002674",
      "tgn:1000003",
      "tgn:1000074",
      "tgn:7029392"
    ],
    "placetype": [
      "aat:300008347"
    ],
    "id": 7224107,
    "name:xx": "Pýrgos"
  }
}
