{
  "geometry": {
    "type": "Point",
    "coordinates": [
      -80.0667,
      26.4167
    ]
  },
  "type": "Feature",
  "properties": {
    "hierarchy": [
      "tgn:2729580",
      "tgn:1000001",
      "tgn:7012149",
      "tgn:1002768",
      "tgn:7007240",
      "tgn:7029392"
    ],
    "placetype": [
      "aat:300008678"
    ],
    "id": 2729580,
    "name:xx": "Tropic Isle Harbor"
  }
}
