{
  "geometry": {
    "type": "Point",
    "coordinates": [
      -5.65,
      40.85
    ]
  },
  "type": "Feature",
  "properties": {
    "hierarchy": [
      "tgn:7303260",
      "tgn:7002835",
      "tgn:7001158",
      "tgn:1000003",
      "tgn:1000095",
      "tgn:7029392"
    ],
    "placetype": [
      "aat:300008347"
    ],
    "id": 7303260,
    "name:xx": "Mozárbez"
  }
}
