{
  "geometry": {
    "type": "Point",
    "coordinates": [
      -95.2167,
      33.1167
    ]
  },
  "type": "Feature",
  "properties": {
    "hierarchy": [
      "tgn:2183625",
      "tgn:1000001",
      "tgn:7012149",
      "tgn:7007826",
      "tgn:7029392"
    ],
    "placetype": [
      "aat:300008706"
    ],
    "id": 2183625,
    "name:xx": "Blundell Creek"
  }
}
