{
  "geometry": {
    "type": "Point",
    "coordinates": [
      -83.9333,
      39.0833
    ]
  },
  "type": "Feature",
  "properties": {
    "hierarchy": [
      "tgn:2336921",
      "tgn:1000001",
      "tgn:7012149",
      "tgn:7007706",
      "tgn:7029392"
    ],
    "placetype": [
      "aat:300008706"
    ],
    "id": 2336921,
    "name:xx": "Fourmile Creek"
  }
}
