{
  "geometry": {
    "type": "Point",
    "coordinates": [
      39.85,
      48.85
    ]
  },
  "type": "Feature",
  "properties": {
    "hierarchy": [
      "tgn:1055787",
      "tgn:1000003",
      "tgn:7012067",
      "tgn:7006660",
      "tgn:7029392"
    ],
    "placetype": [
      "aat:300008347"
    ],
    "id": 1055787,
    "name:xx": "Krasnaja Talovka"
  }
}
