{
  "geometry": {
    "type": "Point",
    "coordinates": [
      -81.2167,
      32.4833
    ]
  },
  "type": "Feature",
  "properties": {
    "hierarchy": [
      "tgn:2461001",
      "tgn:1000001",
      "tgn:7012149",
      "tgn:2001751",
      "tgn:7007712",
      "tgn:7029392"
    ],
    "placetype": [
      "aat:300008680"
    ],
    "id": 2461001,
    "name:xx": "Little Snooks Lake"
  }
}
