{
  "type": "FeatureCollection",
  "features": [
    {
      "geometry": {
        "type": "Point",
        "coordinates": [
          -83.6167,
          40.15
        ]
      },
      "type": "Feature",
      "properties": {
        "hierarchy": [
          "tgn:2438320",
          "tgn:1000001",
          "tgn:1002254",
          "tgn:7012149",
          "tgn:7007706",
          "tgn:7029392"
        ],
        "placetype": [
          "aat:300008706"
        ],
        "id": 2438320,
        "name:xx": "Kings Creek"
      }
    },
    {
      "geometry": {
        "type": "Point",
        "coordinates": [
          -95.2,
          35.2
        ]
      },
      "type": "Feature",
      "properties": {
        "hierarchy": [
          "tgn:2438321",
          "tgn:1000001",
          "tgn:2001653",
          "tgn:7012149",
          "tgn:7007707",
          "tgn:7029392"
        ],
        "placetype": [
          "aat:300008706"
        ],
        "id": 2438321,
        "name:xx": "Kings Creek"
      }
    },
    {
      "geometry": {
        "type": "Point",
        "coordinates": [
          -76.6,
          41.5833
        ]
      },
      "type": "Feature",
      "properties": {
        "hierarchy": [
          "tgn:2438322",
          "tgn:1000001",
          "tgn:7012149",
          "tgn:7007710",
          "tgn:7029392"
        ],
        "placetype": [
          "aat:300008706"
        ],
        "id": 2438322,
        "name:xx": "Kings Creek"
      }
    },
    {
      "geometry": {
        "type": "Point",
        "coordinates": [
          -80.4333,
          40.45
        ]
      },
      "type": "Feature",
      "properties": {
        "hierarchy": [
          "tgn:2438323",
          "tgn:1000001",
          "tgn:7012149",
          "tgn:7029392"
        ],
        "placetype": [
          "aat:300008706"
        ],
        "id": 2438323,
        "name:xx": "Kings Creek"
      }
    },
    {
      "geometry": {
        "type": "Point",
        "coordinates": [
          -81.55,
          34.3833
        ]
      },
      "type": "Feature",
      "properties": {
        "hierarchy": [
          "tgn:2438324",
          "tgn:1000001",
          "tgn:7012149",
          "tgn:2001760",
          "tgn:7007712",
          "tgn:7029392"
        ],
        "placetype": [
          "aat:300008706"
        ],
        "id": 2438324,
        "name:xx": "Kings Creek"
      }
    },
    {
      "geometry": {
        "type": "Point",
        "coordinates": [
          -89.2167,
          35.2
        ]
      },
      "type": "Feature",
      "properties": {
        "hierarchy": [
          "tgn:2438325",
          "tgn:1000001",
          "tgn:7012149",
          "tgn:2001860",
          "tgn:7007825",
          "tgn:7029392"
        ],
        "placetype": [
          "aat:300008706"
        ],
        "id": 2438325,
        "name:xx": "Kings Creek"
      }
    },
    {
      "geometry": {
        "type": "Point",
        "coordinates": [
          -96.25,
          32.8
        ]
      },
      "type": "Feature",
      "properties": {
        "hierarchy": [
          "tgn:2438326",
          "tgn:1000001",
          "tgn:7012149",
          "tgn:1002535",
          "tgn:7007826",
          "tgn:7029392"
        ],
        "placetype": [
          "aat:300008706"
        ],
        "id": 2438326,
        "name:xx": "Kings Creek"
      }
    },
    {
      "geometry": {
        "type": "Point",
        "coordinates": [
          -76.5167,
          36.95
        ]
      },
      "type": "Feature",
      "properties": {
        "hierarchy": [
          "tgn:2438327",
          "tgn:1000001",
          "tgn:7012149",
          "tgn:1002506",
          "tgn:7007919",
          "tgn:7029392"
        ],
        "placetype": [
          "aat:300008706"
        ],
        "id": 2438327,
        "name:xx": "Kings Creek"
      }
    },
    {
      "geometry": {
        "type": "Point",
        "coordinates": [
          -76.2167,
          36.8
        ]
      },
      "type": "Feature",
      "properties": {
        "hierarchy": [
          "tgn:2438328",
          "tgn:1000001",
          "tgn:7012149",
          "tgn:7007919",
          "tgn:7029392"
        ],
        "placetype": [
          "aat:300008706"
        ],
        "id": 2438328,
        "name:xx": "Kings Creek"
      }
    },
    {
      "geometry": {
        "type": "Point",
        "coordinates": [
          -75.9667,
          37.2667
        ]
      },
      "type": "Feature",
      "properties": {
        "hierarchy": [
          "tgn:2438329",
          "tgn:1000001",
          "tgn:7012149",
          "tgn:1002730",
          "tgn:7007919",
          "tgn:7029392"
        ],
        "placetype": [
          "aat:300008706"
        ],
        "id": 2438329,
        "name:xx": "Kings Creek"
      }
    }
  ]
}
