{
  "geometry": {
    "type": "Point",
    "coordinates": [
      -91.6167,
      33.8833
    ]
  },
  "type": "Feature",
  "properties": {
    "hierarchy": [
      "tgn:2401460",
      "tgn:1000001",
      "tgn:7016172",
      "tgn:7012149",
      "tgn:2000144",
      "tgn:7029392"
    ],
    "placetype": [
      "aat:300008905"
    ],
    "id": 2401460,
    "name:xx": "Horseshoe Brake"
  }
}
