{
  "geometry": {
    "type": "Point",
    "coordinates": [
      38.1667,
      47.3333
    ]
  },
  "type": "Feature",
  "properties": {
    "hierarchy": [
      "tgn:1055567",
      "tgn:7012076",
      "tgn:1000003",
      "tgn:7006660",
      "tgn:7029392"
    ],
    "placetype": [
      "aat:300008347"
    ],
    "id": 1055567,
    "name:xx": "Kon'kove"
  }
}
