{
  "geometry": {
    "type": "Point",
    "coordinates": [
      35.8667,
      32.6333
    ]
  },
  "type": "Feature",
  "properties": {
    "hierarchy": [
      "tgn:1081870",
      "tgn:1000004",
      "tgn:1002085",
      "tgn:1000121",
      "tgn:7029392"
    ],
    "placetype": [
      "aat:300008347"
    ],
    "id": 1081870,
    "name:xx": "Al-Qiṣfah"
  }
}
