{
  "geometry": {
    "type": "Point",
    "coordinates": [
      -73.75,
      42.5667
    ]
  },
  "type": "Feature",
  "properties": {
    "hierarchy": [
      "tgn:2690006",
      "tgn:1000001",
      "tgn:7012149",
      "tgn:1002821",
      "tgn:7007568",
      "tgn:7029392"
    ],
    "placetype": [
      "aat:300008850"
    ],
    "id": 2690006,
    "name:xx": "Staats Point"
  }
}
