{
  "type": "FeatureCollection",
  "features": [
    {
      "geometry": {
        "type": "Point",
        "coordinates": [
          -92.533333,
          15.266667
        ]
      },
      "type": "Feature",
      "properties": {
        "hierarchy": [
          "tgn:7438600",
          "tgn:7005580",
          "tgn:1000001",
          "tgn:7005560",
          "tgn:7029392"
        ],
        "placetype": [
          "aat:300008795"
        ],
        "id": 7438600,
        "name:xx": "Tierra Blanca, Cerro"
      }
    },
    {
      "geometry": {
        "type": "Point",
        "coordinates": [
          -106.433333,
          31.483333
        ]
      },
      "type": "Feature",
      "properties": {
        "hierarchy": [
          "tgn:7438601",
          "tgn:7005581",
          "tgn:1000001",
          "tgn:7005560",
          "tgn:7029392"
        ],
        "placetype": [
          "aat:300007783"
        ],
        "id": 7438601,
        "name:xx": "Tierra Blanca"
      }
    },
    {
      "geometry": {
        "type": "Point",
        "coordinates": [
          -104.183333,
          28.65
        ]
      },
      "type": "Feature",
      "properties": {
        "hierarchy": [
          "tgn:7438602",
          "tgn:7005581",
          "tgn:1000001",
          "tgn:7005560",
          "tgn:7029392"
        ],
        "placetype": [
          "aat:300008347"
        ],
        "id": 7438602,
        "name:xx": "Tierra Blanca"
      }
    },
    {
      "geometry": {
        "type": "Point",
        "coordinates": [
          -109.333333,
          27.183333
        ]
      },
      "type": "Feature",
      "properties": {
        "hierarchy": [
          "tgn:7438604",
          "tgn:1000001",
          "tgn:1001960",
          "tgn:7005560",
          "tgn:7029392"
        ],
        "placetype": [
          "aat:300008347"
        ],
        "id": 7438604,
        "name:xx": "Tierra Blanca"
      }
    },
    {
      "geometry": {
        "type": "Point",
        "coordinates": [
          -106.716667,
          27.1
        ]
      },
      "type": "Feature",
      "properties": {
        "hierarchy": [
          "tgn:7438605",
          "tgn:7005581",
          "tgn:1000001",
          "tgn:7005560",
          "tgn:7029392"
        ],
        "placetype": [
          "aat:300008347"
        ],
        "id": 7438605,
        "name:xx": "Tierra Blanca"
      }
    },
    {
      "geometry": {
        "type": "Point",
        "coordinates": [
          -100.233333,
          25.983333
        ]
      },
      "type": "Feature",
      "properties": {
        "hierarchy": [
          "tgn:7438606",
          "tgn:1000001",
          "tgn:7005589",
          "tgn:7005560",
          "tgn:7029392"
        ],
        "placetype": [
          "aat:300008347"
        ],
        "id": 7438606,
        "name:xx": "Tierra Blanca"
      }
    },
    {
      "geometry": {
        "type": "Point",
        "coordinates": [
          -99.9,
          25.616667
        ]
      },
      "type": "Feature",
      "properties": {
        "hierarchy": [
          "tgn:7438607",
          "tgn:1000001",
          "tgn:7005589",
          "tgn:7005560",
          "tgn:7029392"
        ],
        "placetype": [
          "aat:300008347"
        ],
        "id": 7438607,
        "name:xx": "Tierra Blanca"
      }
    },
    {
      "geometry": {
        "type": "Point",
        "coordinates": [
          -103.3,
          25.416667
        ]
      },
      "type": "Feature",
      "properties": {
        "hierarchy": [
          "tgn:7438608",
          "tgn:1001853",
          "tgn:1000001",
          "tgn:7005560",
          "tgn:7029392"
        ],
        "placetype": [
          "aat:300008347"
        ],
        "id": 7438608,
        "name:xx": "Tierra Blanca"
      }
    },
    {
      "geometry": {
        "type": "Point",
        "coordinates": [
          -104.566667,
          25.216667
        ]
      },
      "type": "Feature",
      "properties": {
        "hierarchy": [
          "tgn:7438609",
          "tgn:7005583",
          "tgn:1000001",
          "tgn:7005560",
          "tgn:7029392"
        ],
        "placetype": [
          "aat:300008347"
        ],
        "id": 7438609,
        "name:xx": "Tierra Blanca"
      }
    }
  ]
}
