{
  "geometry": {
    "type": "Point",
    "coordinates": [
      -104.4833,
      44.1667
    ]
  },
  "type": "Feature",
  "properties": {
    "hierarchy": [
      "tgn:2420087",
      "tgn:1000001",
      "tgn:7012149",
      "tgn:2002387",
      "tgn:7007923",
      "tgn:7029392"
    ],
    "placetype": [
      "aat:300006191"
    ],
    "id": 2420087,
    "name:xx": "Jeff Davis Reservoir"
  }
}
