{
  "geometry": {
    "type": "Point",
    "coordinates": [
      -93.55,
      47.6333
    ]
  },
  "type": "Feature",
  "properties": {
    "hierarchy": [
      "tgn:2219581",
      "tgn:1000001",
      "tgn:7012149",
      "tgn:2001029",
      "tgn:7007521",
      "tgn:7029392"
    ],
    "placetype": [
      "aat:300008680"
    ],
    "id": 2219581,
    "name:xx": "Canoe Lake"
  }
}
