{
  "geometry": {
    "type": "Point",
    "coordinates": [
      -102.2167,
      45.75
    ]
  },
  "type": "Feature",
  "properties": {
    "hierarchy": [
      "tgn:2435767",
      "tgn:1000001",
      "tgn:7012149",
      "tgn:2001822",
      "tgn:7007713",
      "tgn:7029392"
    ],
    "placetype": [
      "aat:300008850"
    ],
    "id": 2435767,
    "name:xx": "Ketterlins Point"
  }
}
