{
  "geometry": {
    "type": "Point",
    "coordinates": [
      -71.4833,
      41.5833
    ]
  },
  "type": "Feature",
  "properties": {
    "hierarchy": [
      "tgn:2406759",
      "tgn:1000001",
      "tgn:7012149",
      "tgn:7007711",
      "tgn:7029392"
    ],
    "placetype": [
      "aat:300008707"
    ],
    "id": 2406759,
    "name:xx": "Hunt River"
  }
}
