{
  "geometry": {
    "type": "Point",
    "coordinates": [
      -75.2833,
      40.2333
    ]
  },
  "type": "Feature",
  "properties": {
    "hierarchy": [
      "tgn:2089960",
      "tgn:1000001",
      "tgn:7012149",
      "tgn:1002690",
      "tgn:7007710",
      "tgn:7029392"
    ],
    "placetype": [
      "aat:300008347"
    ],
    "id": 2089960,
    "name:xx": "Lansdale"
  }
}
