{
  "geometry": {
    "type": "Point",
    "coordinates": [
      -110.7833,
      34.2833
    ]
  },
  "type": "Feature",
  "properties": {
    "hierarchy": [
      "tgn:2656780",
      "tgn:1000001",
      "tgn:7006451",
      "tgn:7012149",
      "tgn:7029392"
    ],
    "placetype": [
      "aat:300008850"
    ],
    "id": 2656780,
    "name:xx": "Sheep Creek Point"
  }
}
