{
  "geometry": {
    "type": "Point",
    "coordinates": [
      22.6667,
      44.25
    ]
  },
  "type": "Feature",
  "properties": {
    "hierarchy": [
      "tgn:1130868",
      "tgn:1000003",
      "tgn:7029392"
    ],
    "placetype": [
      "aat:300008707"
    ],
    "id": 1130868,
    "name:xx": "Timok"
  }
}
