{
  "type": "FeatureCollection",
  "features": [
    {
      "geometry": {
        "type": "Point",
        "coordinates": [
          -143.6167,
          70.1167
        ]
      },
      "type": "Feature",
      "properties": {
        "hierarchy": [
          "tgn:2006155",
          "tgn:7006450",
          "tgn:1000001",
          "tgn:7019716",
          "tgn:7012149",
          "tgn:2124005",
          "tgn:7029392"
        ],
        "placetype": [
          "aat:300008347"
        ],
        "id": 2006155,
        "name:xx": "Kaktovik"
      }
    },
    {
      "geometry": {
        "type": "Point",
        "coordinates": [
          -158.7167,
          64.3167
        ]
      },
      "type": "Feature",
      "properties": {
        "hierarchy": [
          "tgn:2006159",
          "tgn:7006450",
          "tgn:1000001",
          "tgn:7012149",
          "tgn:2000089",
          "tgn:7029392"
        ],
        "placetype": [
          "aat:300008347"
        ],
        "id": 2006159,
        "name:xx": "Kaltag"
      }
    }
  ]
}
