{
  "geometry": {
    "type": "Point",
    "coordinates": [
      -111.2667,
      31.4667
    ]
  },
  "type": "Feature",
  "properties": {
    "hierarchy": [
      "tgn:2566421",
      "tgn:1000001",
      "tgn:7006451",
      "tgn:7012149",
      "tgn:2000102",
      "tgn:7029392"
    ],
    "placetype": [
      "aat:300006191"
    ],
    "id": 2566421,
    "name:xx": "Palomas Tank"
  }
}
