{
  "type": "FeatureCollection",
  "features": [
    {
      "geometry": {
        "type": "Point",
        "coordinates": [
          -4.216667,
          55.75
        ]
      },
      "type": "Feature",
      "properties": {
        "hierarchy": [
          "tgn:7450010",
          "tgn:7002444",
          "tgn:1000003",
          "tgn:7019090",
          "tgn:7008591",
          "tgn:7029392"
        ],
        "placetype": [
          "aat:300007783"
        ],
        "name:en": "Hairmyres Station",
        "id": 7450010
      }
    },
    {
      "geometry": {
        "type": "Point",
        "coordinates": [
          -1.483333,
          51.8
        ]
      },
      "type": "Feature",
      "properties": {
        "hierarchy": [
          "tgn:7450015",
          "tgn:7002445",
          "tgn:1000003",
          "tgn:7008168",
          "tgn:7008591",
          "tgn:7029392"
        ],
        "placetype": [
          "aat:300008347"
        ],
        "name:en": "Hailey",
        "id": 7450015
      }
    },
    {
      "geometry": {
        "type": "Point",
        "coordinates": [
          0.116667,
          53.5
        ]
      },
      "type": "Feature",
      "properties": {
        "hierarchy": [
          "tgn:7450016",
          "tgn:7002445",
          "tgn:1000003",
          "tgn:7008157",
          "tgn:7008591",
          "tgn:7029392"
        ],
        "placetype": [
          "aat:300386970"
        ],
        "name:en": "Haile Sand",
        "id": 7450016
      }
    },
    {
      "geometry": {
        "type": "Point",
        "coordinates": [
          -1.55,
          53.6
        ]
      },
      "type": "Feature",
      "properties": {
        "hierarchy": [
          "tgn:7450018",
          "tgn:7019048",
          "tgn:7002445",
          "tgn:1000003",
          "tgn:7029505",
          "tgn:7008591",
          "tgn:7029392"
        ],
        "placetype": [
          "aat:300008347"
        ],
        "name:en": "Haigh",
        "id": 7450018
      }
    }
  ]
}
