{
  "geometry": {
    "type": "Point",
    "coordinates": [
      -82.6667,
      33.0333
    ]
  },
  "type": "Feature",
  "properties": {
    "hierarchy": [
      "tgn:7023166",
      "tgn:1000001",
      "tgn:7012149",
      "tgn:2000441",
      "tgn:7007248",
      "tgn:7029392"
    ],
    "placetype": [
      "aat:300006191"
    ],
    "id": 7023166,
    "name:xx": "Jordan Millpond"
  }
}
