{
  "geometry": {
    "type": "Point",
    "coordinates": [
      -82.95,
      34.5833
    ]
  },
  "type": "Feature",
  "properties": {
    "hierarchy": [
      "tgn:7021761",
      "tgn:1000001",
      "tgn:7012149",
      "tgn:7007712",
      "tgn:7029392"
    ],
    "placetype": [
      "aat:300008706"
    ],
    "id": 7021761,
    "name:xx": "Little Beaverdam Creek"
  }
}
