{
  "type": "FeatureCollection",
  "features": [
    {
      "geometry": {
        "type": "Point",
        "coordinates": [
          -106.5667,
          32.4167
        ]
      },
      "type": "Feature",
      "properties": {
        "hierarchy": [
          "tgn:1108540",
          "tgn:1000001",
          "tgn:2001435",
          "tgn:7012149",
          "tgn:7007566",
          "tgn:7029392"
        ],
        "placetype": [
          "aat:300259572"
        ],
        "id": 1108540,
        "name:xx": "San Augustin Pass"
      }
    },
    {
      "geometry": {
        "type": "Point",
        "coordinates": [
          -68.3333,
          -26.8333
        ]
      },
      "type": "Feature",
      "properties": {
        "hierarchy": [
          "tgn:1108542",
          "tgn:1000002",
          "tgn:7029392"
        ],
        "placetype": [
          "aat:300259572"
        ],
        "id": 1108542,
        "name:xx": "San Francisco, Paso de"
      }
    },
    {
      "geometry": {
        "type": "Point",
        "coordinates": [
          29.3,
          -29.6
        ]
      },
      "type": "Feature",
      "properties": {
        "hierarchy": [
          "tgn:1108544",
          "tgn:7001242",
          "tgn:7029392"
        ],
        "placetype": [
          "aat:300259572"
        ],
        "id": 1108544,
        "name:xx": "Sani Pass"
      }
    },
    {
      "geometry": {
        "type": "Point",
        "coordinates": [
          -121.85,
          44.4
        ]
      },
      "type": "Feature",
      "properties": {
        "hierarchy": [
          "tgn:1108546",
          "tgn:1000001",
          "tgn:7012149",
          "tgn:2001717",
          "tgn:7007708",
          "tgn:7029392"
        ],
        "placetype": [
          "aat:300259572"
        ],
        "id": 1108546,
        "name:xx": "Santiam Pass"
      }
    },
    {
      "geometry": {
        "type": "Point",
        "coordinates": [
          71.5333,
          36.6667
        ]
      },
      "type": "Feature",
      "properties": {
        "hierarchy": [
          "tgn:1108547",
          "tgn:7016612",
          "tgn:7011625",
          "tgn:1000004",
          "tgn:7029392"
        ],
        "placetype": [
          "aat:300259572"
        ],
        "id": 1108547,
        "name:xx": "Sardab"
      }
    },
    {
      "geometry": {
        "type": "Point",
        "coordinates": [
          11.2667,
          47.4
        ]
      },
      "type": "Feature",
      "properties": {
        "hierarchy": [
          "tgn:1108548",
          "tgn:1000003",
          "tgn:7029392"
        ],
        "placetype": [
          "aat:300259572"
        ],
        "id": 1108548,
        "name:de": "Scharnitzer Klause"
      }
    },
    {
      "geometry": {
        "type": "Point",
        "coordinates": [
          7.0167,
          48.05
        ]
      },
      "type": "Feature",
      "properties": {
        "hierarchy": [
          "tgn:1108549",
          "tgn:1000003",
          "tgn:7002888",
          "tgn:1000070",
          "tgn:7029392"
        ],
        "placetype": [
          "aat:300259572"
        ],
        "id": 1108549,
        "name:xx": "Schlucht, Col de la"
      }
    }
  ]
}
