{
  "geometry": {
    "type": "Point",
    "coordinates": [
      -70.75,
      -32.35
    ]
  },
  "type": "Feature",
  "properties": {
    "hierarchy": [
      "tgn:7308256",
      "tgn:1001768",
      "tgn:1000049",
      "tgn:1000002",
      "tgn:7029392"
    ],
    "placetype": [
      "aat:300266554",
      "aat:300008699"
    ],
    "id": 7308256,
    "name:xx": "Matuasto, Quebrada"
  }
}
