{
  "geometry": {
    "type": "Point",
    "coordinates": [
      -94.9833,
      45.2833
    ]
  },
  "type": "Feature",
  "properties": {
    "hierarchy": [
      "tgn:2229060",
      "tgn:1000001",
      "tgn:7012149",
      "tgn:2001032",
      "tgn:7007521",
      "tgn:7029392"
    ],
    "placetype": [
      "aat:300008905"
    ],
    "id": 2229060,
    "name:xx": "Cedar Island Lake"
  }
}
