{
  "geometry": {
    "type": "Point",
    "coordinates": [
      -90.65,
      14.7167
    ]
  },
  "type": "Feature",
  "properties": {
    "hierarchy": [
      "tgn:1016706",
      "tgn:1000621",
      "tgn:1000001",
      "tgn:7005493",
      "tgn:7029392"
    ],
    "placetype": [
      "aat:300008347"
    ],
    "id": 1016706,
    "name:xx": "San Juan Sacatepéquez"
  }
}
