{
  "geometry": {
    "type": "Point",
    "coordinates": [
      -93.05,
      31.8667
    ]
  },
  "type": "Feature",
  "properties": {
    "hierarchy": [
      "tgn:2630809",
      "tgn:1000001",
      "tgn:7012149",
      "tgn:2000888",
      "tgn:7007256",
      "tgn:7029392"
    ],
    "placetype": [
      "aat:300008680"
    ],
    "id": 2630809,
    "name:xx": "Round Lake"
  }
}
