{
  "geometry": {
    "type": "Point",
    "coordinates": [
      78.8667,
      57.2167
    ]
  },
  "type": "Feature",
  "properties": {
    "hierarchy": [
      "tgn:1051632",
      "tgn:1000004",
      "tgn:7011604",
      "tgn:7018214",
      "tgn:7002435",
      "tgn:7029392"
    ],
    "placetype": [
      "aat:300008347"
    ],
    "id": 1051632,
    "name:xx": "Sherstobitovo"
  }
}
