{
  "geometry": {
    "type": "Point",
    "coordinates": [
      20.85,
      -0.25
    ]
  },
  "type": "Feature",
  "properties": {
    "hierarchy": [
      "tgn:1088830",
      "tgn:7001242",
      "tgn:7016654",
      "tgn:1000159",
      "tgn:7029392"
    ],
    "placetype": [
      "aat:300008347"
    ],
    "id": 1088830,
    "name:xx": "Boende"
  }
}
