{
  "type": "FeatureCollection",
  "features": [
    {
      "geometry": {
        "type": "Point",
        "coordinates": [
          -83.5,
          34.8833
        ]
      },
      "type": "Feature",
      "properties": {
        "hierarchy": [
          "tgn:2179340",
          "tgn:1000001",
          "tgn:7012149",
          "tgn:2000410",
          "tgn:7007248",
          "tgn:7029392"
        ],
        "placetype": [
          "aat:300008347"
        ],
        "id": 2179340,
        "name:xx": "Blalock"
      }
    },
    {
      "geometry": {
        "type": "Point",
        "coordinates": [
          -120.3333,
          45.6167
        ]
      },
      "type": "Feature",
      "properties": {
        "hierarchy": [
          "tgn:2179343",
          "tgn:1000001",
          "tgn:7012149",
          "tgn:7029392"
        ],
        "placetype": [
          "aat:300008761"
        ],
        "id": 2179343,
        "name:xx": "Blalock Canyon"
      }
    },
    {
      "geometry": {
        "type": "Point",
        "coordinates": [
          -85.25,
          33.6667
        ]
      },
      "type": "Feature",
      "properties": {
        "hierarchy": [
          "tgn:2179344",
          "tgn:1000001",
          "tgn:7012149",
          "tgn:7007248",
          "tgn:7029392"
        ],
        "placetype": [
          "aat:300008706"
        ],
        "id": 2179344,
        "name:xx": "Blalock Creek"
      }
    },
    {
      "geometry": {
        "type": "Point",
        "coordinates": [
          -89.45,
          40.8333
        ]
      },
      "type": "Feature",
      "properties": {
        "hierarchy": [
          "tgn:2179345",
          "tgn:1000001",
          "tgn:7012149",
          "tgn:1003035",
          "tgn:7007251",
          "tgn:7029392"
        ],
        "placetype": [
          "aat:300008706"
        ],
        "id": 2179345,
        "name:xx": "Blalock Creek"
      }
    },
    {
      "geometry": {
        "type": "Point",
        "coordinates": [
          -93.5333,
          38.1
        ]
      },
      "type": "Feature",
      "properties": {
        "hierarchy": [
          "tgn:2179346",
          "tgn:1000001",
          "tgn:7012149",
          "tgn:2001239",
          "tgn:7007523",
          "tgn:7029392"
        ],
        "placetype": [
          "aat:300008761"
        ],
        "id": 2179346,
        "name:xx": "Blalock Hollow"
      }
    },
    {
      "geometry": {
        "type": "Point",
        "coordinates": [
          -119.6333,
          45.9
        ]
      },
      "type": "Feature",
      "properties": {
        "hierarchy": [
          "tgn:2179347",
          "tgn:2002240",
          "tgn:1000001",
          "tgn:7012149",
          "tgn:7007920",
          "tgn:7029392"
        ],
        "placetype": [
          "aat:300386853"
        ],
        "id": 2179347,
        "name:xx": "Blalock Islands"
      }
    },
    {
      "geometry": {
        "type": "Point",
        "coordinates": [
          -85.0167,
          35.7667
        ]
      },
      "type": "Feature",
      "properties": {
        "hierarchy": [
          "tgn:2179348",
          "tgn:1000001",
          "tgn:7012149",
          "tgn:2001854",
          "tgn:7007825",
          "tgn:7029392"
        ],
        "placetype": [
          "aat:300008798"
        ],
        "id": 2179348,
        "name:xx": "Blalock Knob"
      }
    },
    {
      "geometry": {
        "type": "Point",
        "coordinates": [
          -83.4,
          34.8
        ]
      },
      "type": "Feature",
      "properties": {
        "hierarchy": [
          "tgn:2179349",
          "tgn:1000001",
          "tgn:7012149",
          "tgn:2000410",
          "tgn:7007248",
          "tgn:7029392"
        ],
        "placetype": [
          "aat:300006191"
        ],
        "id": 2179349,
        "name:xx": "Blalock Lake"
      }
    }
  ]
}
