{
  "geometry": {
    "type": "Point",
    "coordinates": [
      -97.6667,
      31.3333
    ]
  },
  "type": "Feature",
  "properties": {
    "hierarchy": [
      "tgn:2482254",
      "tgn:1000001",
      "tgn:7012149",
      "tgn:1002303",
      "tgn:7007826",
      "tgn:7029392"
    ],
    "placetype": [
      "aat:300008798"
    ],
    "id": 2482254,
    "name:xx": "Langford Mountain"
  }
}
