{
  "geometry": {
    "type": "Point",
    "coordinates": [
      79.9791,
      27.0127
    ]
  },
  "type": "Feature",
  "properties": {
    "hierarchy": [
      "tgn:7559599",
      "tgn:1000004",
      "tgn:7000198",
      "tgn:7016722",
      "tgn:7029392"
    ],
    "placetype": [
      "aat:300008347"
    ],
    "name:en": "Mehdīpur",
    "id": 7559599
  }
}
