{
  "type": "FeatureCollection",
  "features": [
    {
      "geometry": {
        "type": "Point",
        "coordinates": [
          7.683333,
          49.6
        ]
      },
      "type": "Feature",
      "properties": {
        "hierarchy": [
          "tgn:7167530",
          "tgn:1000003",
          "tgn:7003682",
          "tgn:7000084",
          "tgn:7029392"
        ],
        "placetype": [
          "aat:300008347"
        ],
        "id": 7167530,
        "name:xx": "Hefersweiler"
      }
    },
    {
      "geometry": {
        "type": "Point",
        "coordinates": [
          10.6,
          47.833333
        ]
      },
      "type": "Feature",
      "properties": {
        "hierarchy": [
          "tgn:7167531",
          "tgn:7003669",
          "tgn:1000003",
          "tgn:7000084",
          "tgn:7029392"
        ],
        "placetype": [
          "aat:300000206"
        ],
        "id": 7167531,
        "name:xx": "Hefele"
      }
    },
    {
      "geometry": {
        "type": "Point",
        "coordinates": [
          7.05,
          51.35
        ]
      },
      "type": "Feature",
      "properties": {
        "hierarchy": [
          "tgn:7167532",
          "tgn:1000003",
          "tgn:7003677",
          "tgn:7000084",
          "tgn:7029392"
        ],
        "placetype": [
          "aat:300008347"
        ],
        "id": 7167532,
        "name:xx": "Hefel"
      }
    },
    {
      "geometry": {
        "type": "Point",
        "coordinates": [
          7.033333,
          52.466667
        ]
      },
      "type": "Feature",
      "properties": {
        "hierarchy": [
          "tgn:7167533",
          "tgn:1000003",
          "tgn:7003676",
          "tgn:7000084",
          "tgn:7029392"
        ],
        "placetype": [
          "aat:300000206"
        ],
        "id": 7167533,
        "name:xx": "Heetlage"
      }
    },
    {
      "geometry": {
        "type": "Point",
        "coordinates": [
          7.8,
          53
        ]
      },
      "type": "Feature",
      "properties": {
        "hierarchy": [
          "tgn:7167534",
          "tgn:1000003",
          "tgn:7003676",
          "tgn:7000084",
          "tgn:7029392"
        ],
        "placetype": [
          "aat:300386886"
        ],
        "id": 7167534,
        "name:xx": "Heetbergsmoor"
      }
    },
    {
      "geometry": {
        "type": "Point",
        "coordinates": [
          7.8,
          53
        ]
      },
      "type": "Feature",
      "properties": {
        "hierarchy": [
          "tgn:7167535",
          "tgn:1000003",
          "tgn:7003676",
          "tgn:7000084",
          "tgn:7029392"
        ],
        "placetype": [
          "aat:300008347"
        ],
        "id": 7167535,
        "name:xx": "Heetberg"
      }
    },
    {
      "geometry": {
        "type": "Point",
        "coordinates": [
          7.3,
          53.233333
        ]
      },
      "type": "Feature",
      "properties": {
        "hierarchy": [
          "tgn:7167536",
          "tgn:1000003",
          "tgn:7003676",
          "tgn:7000084",
          "tgn:7029392"
        ],
        "placetype": [
          "aat:300008699"
        ],
        "id": 7167536,
        "name:xx": "Heester Tief"
      }
    },
    {
      "geometry": {
        "type": "Point",
        "coordinates": [
          6.75,
          52.6
        ]
      },
      "type": "Feature",
      "properties": {
        "hierarchy": [
          "tgn:7167537",
          "tgn:1000003",
          "tgn:7003676",
          "tgn:7000084",
          "tgn:7029392"
        ],
        "placetype": [
          "aat:300008347"
        ],
        "id": 7167537,
        "name:xx": "Heesterkante"
      }
    },
    {
      "geometry": {
        "type": "Point",
        "coordinates": [
          8.983333,
          51.85
        ]
      },
      "type": "Feature",
      "properties": {
        "hierarchy": [
          "tgn:7167538",
          "tgn:1000003",
          "tgn:7003677",
          "tgn:7000084",
          "tgn:7029392"
        ],
        "placetype": [
          "aat:300008347"
        ],
        "id": 7167538,
        "name:xx": "Heesten"
      }
    },
    {
      "geometry": {
        "type": "Point",
        "coordinates": [
          9.1,
          52.233333
        ]
      },
      "type": "Feature",
      "properties": {
        "hierarchy": [
          "tgn:7167539",
          "tgn:1000003",
          "tgn:7003676",
          "tgn:7000084",
          "tgn:7029392"
        ],
        "placetype": [
          "aat:300008347"
        ],
        "id": 7167539,
        "name:xx": "Heeßen"
      }
    }
  ]
}
