{
  "geometry": {
    "type": "Point",
    "coordinates": [
      -87.1667,
      30.3333
    ]
  },
  "type": "Feature",
  "properties": {
    "hierarchy": [
      "tgn:2282405",
      "tgn:1000001",
      "tgn:7012149",
      "tgn:2000285",
      "tgn:7007240",
      "tgn:7029392"
    ],
    "placetype": [
      "aat:300008850"
    ],
    "id": 2282405,
    "name:xx": "Deer Point"
  }
}
