{
  "type": "FeatureCollection",
  "features": [
    {
      "geometry": {
        "type": "Point",
        "coordinates": [
          3.05,
          39.266667
        ]
      },
      "type": "Feature",
      "properties": {
        "hierarchy": [
          "tgn:1011161",
          "tgn:7001122",
          "tgn:1000003",
          "tgn:7002765",
          "tgn:1000095",
          "tgn:7007959",
          "tgn:7029392"
        ],
        "placetype": [
          "aat:300008850"
        ],
        "id": 1011161,
        "name:xx": "Salinas, Cabo de"
      }
    },
    {
      "geometry": {
        "type": "Point",
        "coordinates": [
          -61.1167,
          14.5167
        ]
      },
      "type": "Feature",
      "properties": {
        "hierarchy": [
          "tgn:1011162",
          "tgn:7015035",
          "tgn:1000001",
          "tgn:7005870",
          "tgn:7029392"
        ],
        "placetype": [
          "aat:300008850"
        ],
        "id": 1011162,
        "name:xx": "Salomon, Cap"
      }
    },
    {
      "geometry": {
        "type": "Point",
        "coordinates": [
          -69.152,
          19.301
        ]
      },
      "type": "Feature",
      "properties": {
        "hierarchy": [
          "tgn:1011163",
          "tgn:7005416",
          "tgn:1000001",
          "tgn:7005388",
          "tgn:7029392"
        ],
        "placetype": [
          "aat:300008850"
        ],
        "id": 1011163,
        "name:xx": "Samaná, Cabo"
      }
    },
    {
      "geometry": {
        "type": "Point",
        "coordinates": [
          126.2,
          6.2833
        ]
      },
      "type": "Feature",
      "properties": {
        "hierarchy": [
          "tgn:1011165",
          "tgn:1000004",
          "tgn:1001217",
          "tgn:1000135",
          "tgn:7029392"
        ],
        "placetype": [
          "aat:300008850"
        ],
        "id": 1011165,
        "name:xx": "San Agustin, Cape"
      }
    },
    {
      "geometry": {
        "type": "Point",
        "coordinates": [
          -56.7,
          -36.6667
        ]
      },
      "type": "Feature",
      "properties": {
        "hierarchy": [
          "tgn:1011167",
          "tgn:1001160",
          "tgn:7006477",
          "tgn:1000002",
          "tgn:7029392"
        ],
        "placetype": [
          "aat:300008850"
        ],
        "id": 1011167,
        "name:xx": "San Antonio, Cabo"
      }
    },
    {
      "geometry": {
        "type": "Point",
        "coordinates": [
          -85.35,
          29.65
        ]
      },
      "type": "Feature",
      "properties": {
        "hierarchy": [
          "tgn:1011169",
          "tgn:1000001",
          "tgn:2000270",
          "tgn:7012149",
          "tgn:7007240",
          "tgn:7029392"
        ],
        "placetype": [
          "aat:300008850"
        ],
        "id": 1011169,
        "name:xx": "San Blas, Cape"
      }
    }
  ]
}
