{
  "geometry": {
    "type": "Point",
    "coordinates": [
      -90.3333,
      45.7167
    ]
  },
  "type": "Feature",
  "properties": {
    "hierarchy": [
      "tgn:2454445",
      "tgn:1000001",
      "tgn:7012149",
      "tgn:2002348",
      "tgn:7007922",
      "tgn:7029392"
    ],
    "placetype": [
      "aat:300008680"
    ],
    "id": 2454445,
    "name:xx": "Little Dardis Lake"
  }
}
