{
  "geometry": {
    "type": "Point",
    "coordinates": [
      4.4333,
      51.9333
    ]
  },
  "type": "Feature",
  "properties": {
    "hierarchy": [
      "tgn:1005292",
      "tgn:1000003",
      "tgn:7003632",
      "tgn:7016845",
      "tgn:7029392"
    ],
    "placetype": [
      "aat:300008347"
    ],
    "id": 1005292,
    "name:xx": "Overschie"
  }
}
