{
  "geometry": {
    "type": "Point",
    "coordinates": [
      -78.7833,
      -8.75
    ]
  },
  "type": "Feature",
  "properties": {
    "hierarchy": [
      "tgn:1006771",
      "tgn:1000660",
      "tgn:1000002",
      "tgn:1000056",
      "tgn:7029392"
    ],
    "placetype": [
      "aat:300008791"
    ],
    "id": 1006771,
    "name:xx": "Chao, Isla"
  }
}
