{
  "type": "FeatureCollection",
  "features": [
    {
      "geometry": {
        "type": "Point",
        "coordinates": [
          -92.5833,
          46.2833
        ]
      },
      "type": "Feature",
      "properties": {
        "hierarchy": [
          "tgn:2462610",
          "tgn:1000001",
          "tgn:7012149",
          "tgn:2001056",
          "tgn:7007521",
          "tgn:7029392"
        ],
        "placetype": [
          "aat:300008707"
        ],
        "id": 2462610,
        "name:xx": "Little Willow River"
      }
    },
    {
      "geometry": {
        "type": "Point",
        "coordinates": [
          -93.6833,
          46.7167
        ]
      },
      "type": "Feature",
      "properties": {
        "hierarchy": [
          "tgn:2462611",
          "tgn:2000999",
          "tgn:1000001",
          "tgn:7012149",
          "tgn:7007521",
          "tgn:7029392"
        ],
        "placetype": [
          "aat:300008707"
        ],
        "id": 2462611,
        "name:xx": "Little Willow River"
      }
    },
    {
      "geometry": {
        "type": "Point",
        "coordinates": [
          -114.1833,
          42
        ]
      },
      "type": "Feature",
      "properties": {
        "hierarchy": [
          "tgn:2462612",
          "tgn:1000001",
          "tgn:2000467",
          "tgn:7012149",
          "tgn:7007250",
          "tgn:7029392"
        ],
        "placetype": [
          "aat:300008697"
        ],
        "id": 2462612,
        "name:xx": "Little Willow Spring"
      }
    },
    {
      "geometry": {
        "type": "Point",
        "coordinates": [
          -116.9833,
          42.4333
        ]
      },
      "type": "Feature",
      "properties": {
        "hierarchy": [
          "tgn:2462613",
          "tgn:1000001",
          "tgn:7012149",
          "tgn:2000488",
          "tgn:7007250",
          "tgn:7029392"
        ],
        "placetype": [
          "aat:300008697"
        ],
        "id": 2462613,
        "name:xx": "Little Willow Spring"
      }
    },
    {
      "geometry": {
        "type": "Point",
        "coordinates": [
          -115.6,
          39.7167
        ]
      },
      "type": "Feature",
      "properties": {
        "hierarchy": [
          "tgn:2462614",
          "tgn:1000001",
          "tgn:7012149",
          "tgn:2001420",
          "tgn:7007526",
          "tgn:7029392"
        ],
        "placetype": [
          "aat:300008697"
        ],
        "id": 2462614,
        "name:xx": "Little Willow Spring"
      }
    },
    {
      "geometry": {
        "type": "Point",
        "coordinates": [
          -104.05,
          31.0167
        ]
      },
      "type": "Feature",
      "properties": {
        "hierarchy": [
          "tgn:2462615",
          "tgn:1000001",
          "tgn:7012149",
          "tgn:2002010",
          "tgn:7007826",
          "tgn:7029392"
        ],
        "placetype": [
          "aat:300008697"
        ],
        "id": 2462615,
        "name:xx": "Little Willow Spring"
      }
    },
    {
      "geometry": {
        "type": "Point",
        "coordinates": [
          -78.75,
          39.9333
        ]
      },
      "type": "Feature",
      "properties": {
        "hierarchy": [
          "tgn:2462618",
          "tgn:1000001",
          "tgn:7012149",
          "tgn:7007710",
          "tgn:7029392"
        ],
        "placetype": [
          "aat:300008706"
        ],
        "id": 2462618,
        "name:xx": "Little Wills Creek"
      }
    },
    {
      "geometry": {
        "type": "Point",
        "coordinates": [
          -85.7,
          34.45
        ]
      },
      "type": "Feature",
      "properties": {
        "hierarchy": [
          "tgn:2462619",
          "tgn:7002659",
          "tgn:1000001",
          "tgn:7012149",
          "tgn:7029392"
        ],
        "placetype": [
          "aat:300008761"
        ],
        "id": 2462619,
        "name:xx": "Little Wills Valley"
      }
    }
  ]
}
