{
  "geometry": {
    "type": "Point",
    "coordinates": [
      126.8333,
      61.15
    ]
  },
  "type": "Feature",
  "properties": {
    "hierarchy": [
      "tgn:1059436",
      "tgn:1000004",
      "tgn:7011528",
      "tgn:7002435",
      "tgn:7029392"
    ],
    "placetype": [
      "aat:300008347"
    ],
    "id": 1059436,
    "name:xx": "Sinskoye"
  }
}
