{
  "type": "FeatureCollection",
  "features": [
    {
      "geometry": {
        "type": "Point",
        "coordinates": [
          -2.766667,
          52.516667
        ]
      },
      "type": "Feature",
      "properties": {
        "hierarchy": [
          "tgn:7443532",
          "tgn:7002445",
          "tgn:1000003",
          "tgn:7012034",
          "tgn:7008591",
          "tgn:7029392"
        ],
        "placetype": [
          "aat:300008347"
        ],
        "name:en": "Ticklerton",
        "id": 7443532
      }
    },
    {
      "geometry": {
        "type": "Point",
        "coordinates": [
          -0.533333,
          52.666667
        ]
      },
      "type": "Feature",
      "properties": {
        "hierarchy": [
          "tgn:7443534",
          "tgn:7002445",
          "tgn:1000003",
          "tgn:5000748",
          "tgn:7008591",
          "tgn:7029392"
        ],
        "placetype": [
          "aat:300008347",
          "aat:300387092"
        ],
        "name:en": "Tickencote",
        "id": 7443534
      }
    },
    {
      "geometry": {
        "type": "Point",
        "coordinates": [
          -1.183333,
          51.066667
        ]
      },
      "type": "Feature",
      "properties": {
        "hierarchy": [
          "tgn:7443535",
          "tgn:7002445",
          "tgn:1000003",
          "tgn:7008139",
          "tgn:7008591",
          "tgn:7029392"
        ],
        "placetype": [
          "aat:300008347"
        ],
        "name:en": "Tichborne",
        "id": 7443535
      }
    },
    {
      "geometry": {
        "type": "Point",
        "coordinates": [
          1.15,
          52.466667
        ]
      },
      "type": "Feature",
      "properties": {
        "hierarchy": [
          "tgn:7443539",
          "tgn:7002445",
          "tgn:1000003",
          "tgn:7008160",
          "tgn:7008591",
          "tgn:7029392"
        ],
        "placetype": [
          "aat:300008347"
        ],
        "name:en": "Tibenham",
        "id": 7443539
      }
    }
  ]
}
