{
  "geometry": {
    "type": "Point",
    "coordinates": [
      -87.8333,
      41.5333
    ]
  },
  "type": "Feature",
  "properties": {
    "hierarchy": [
      "tgn:2026352",
      "tgn:1000001",
      "tgn:7012149",
      "tgn:1003024",
      "tgn:7007251",
      "tgn:7029392"
    ],
    "placetype": [
      "aat:300008347"
    ],
    "id": 2026352,
    "name:xx": "Arbury Hills"
  }
}
