{
  "type": "FeatureCollection",
  "features": [
    {
      "geometry": {
        "type": "Point",
        "coordinates": [
          -77.45,
          41.0833
        ]
      },
      "type": "Feature",
      "properties": {
        "hierarchy": [
          "tgn:2171130",
          "tgn:1000001",
          "tgn:1002286",
          "tgn:7012149",
          "tgn:7007710",
          "tgn:7029392"
        ],
        "placetype": [
          "aat:300008697"
        ],
        "id": 2171130,
        "name:xx": "Big Spring"
      }
    },
    {
      "geometry": {
        "type": "Point",
        "coordinates": [
          -77.4,
          40.1167
        ]
      },
      "type": "Feature",
      "properties": {
        "hierarchy": [
          "tgn:2171131",
          "tgn:1000001",
          "tgn:1002310",
          "tgn:7012149",
          "tgn:7007710",
          "tgn:7029392"
        ],
        "placetype": [
          "aat:300008697"
        ],
        "id": 2171131,
        "name:xx": "Big Spring"
      }
    },
    {
      "geometry": {
        "type": "Point",
        "coordinates": [
          -78.0333,
          39.8333
        ]
      },
      "type": "Feature",
      "properties": {
        "hierarchy": [
          "tgn:2171132",
          "tgn:1000001",
          "tgn:7012149",
          "tgn:1002399",
          "tgn:7007710",
          "tgn:7029392"
        ],
        "placetype": [
          "aat:300008697"
        ],
        "id": 2171132,
        "name:xx": "Big Spring"
      }
    },
    {
      "geometry": {
        "type": "Point",
        "coordinates": [
          -76.25,
          39.9833
        ]
      },
      "type": "Feature",
      "properties": {
        "hierarchy": [
          "tgn:2171133",
          "tgn:1000001",
          "tgn:7012149",
          "tgn:7013867",
          "tgn:7007710",
          "tgn:7029392"
        ],
        "placetype": [
          "aat:300008697"
        ],
        "id": 2171133,
        "name:xx": "Big Spring"
      }
    },
    {
      "geometry": {
        "type": "Point",
        "coordinates": [
          -78.2333,
          40.6667
        ]
      },
      "type": "Feature",
      "properties": {
        "hierarchy": [
          "tgn:2171134",
          "tgn:1000001",
          "tgn:1002185",
          "tgn:7012149",
          "tgn:7007710",
          "tgn:7029392"
        ],
        "placetype": [
          "aat:300008697"
        ],
        "id": 2171134,
        "name:xx": "Big Spring"
      }
    },
    {
      "geometry": {
        "type": "Point",
        "coordinates": [
          -103.9667,
          44.4333
        ]
      },
      "type": "Feature",
      "properties": {
        "hierarchy": [
          "tgn:2171135",
          "tgn:1000001",
          "tgn:2001810",
          "tgn:7012149",
          "tgn:7007713",
          "tgn:7029392"
        ],
        "placetype": [
          "aat:300008697"
        ],
        "id": 2171135,
        "name:xx": "Big Spring"
      }
    },
    {
      "geometry": {
        "type": "Point",
        "coordinates": [
          -97.0333,
          45.4833
        ]
      },
      "type": "Feature",
      "properties": {
        "hierarchy": [
          "tgn:2171136",
          "tgn:1000001",
          "tgn:7012149",
          "tgn:2001824",
          "tgn:7007713",
          "tgn:7029392"
        ],
        "placetype": [
          "aat:300008697"
        ],
        "id": 2171136,
        "name:xx": "Big Spring"
      }
    },
    {
      "geometry": {
        "type": "Point",
        "coordinates": [
          -85.9667,
          35.1833
        ]
      },
      "type": "Feature",
      "properties": {
        "hierarchy": [
          "tgn:2171137",
          "tgn:1000001",
          "tgn:7012149",
          "tgn:2001852",
          "tgn:7007825",
          "tgn:7029392"
        ],
        "placetype": [
          "aat:300008697"
        ],
        "id": 2171137,
        "name:xx": "Big Spring"
      }
    },
    {
      "geometry": {
        "type": "Point",
        "coordinates": [
          -86.05,
          35.2
        ]
      },
      "type": "Feature",
      "properties": {
        "hierarchy": [
          "tgn:2171138",
          "tgn:1000001",
          "tgn:7012149",
          "tgn:2001862",
          "tgn:7007825",
          "tgn:7029392"
        ],
        "placetype": [
          "aat:300008697"
        ],
        "id": 2171138,
        "name:xx": "Big Spring"
      }
    },
    {
      "geometry": {
        "type": "Point",
        "coordinates": [
          -86.9167,
          35.2333
        ]
      },
      "type": "Feature",
      "properties": {
        "hierarchy": [
          "tgn:2171139",
          "tgn:1000001",
          "tgn:7012149",
          "tgn:2001864",
          "tgn:7007825",
          "tgn:7029392"
        ],
        "placetype": [
          "aat:300008697"
        ],
        "id": 2171139,
        "name:xx": "Big Spring"
      }
    }
  ]
}
