{
  "geometry": {
    "type": "Point",
    "coordinates": [
      -88.0833,
      35.5333
    ]
  },
  "type": "Feature",
  "properties": {
    "hierarchy": [
      "tgn:2649111",
      "tgn:1000001",
      "tgn:7012149",
      "tgn:2001856",
      "tgn:7007825",
      "tgn:7029392"
    ],
    "placetype": [
      "aat:300008761"
    ],
    "id": 2649111,
    "name:xx": "Scott Hollow"
  }
}
