{
  "geometry": {
    "type": "Point",
    "coordinates": [
      -87.1833,
      32.3167
    ]
  },
  "type": "Feature",
  "properties": {
    "hierarchy": [
      "tgn:1132476",
      "tgn:7002659",
      "tgn:1000001",
      "tgn:7012149",
      "tgn:2000023",
      "tgn:7029392"
    ],
    "placetype": [
      "aat:300008706"
    ],
    "id": 1132476,
    "name:xx": "Big Swamp Creek"
  }
}
