{
  "geometry": {
    "type": "Point",
    "coordinates": [
      78.947951,
      24.916691
    ]
  },
  "type": "Feature",
  "properties": {
    "hierarchy": [
      "tgn:7584121",
      "tgn:1000004",
      "tgn:7000198",
      "tgn:1001894",
      "tgn:7029392"
    ],
    "placetype": [
      "aat:300008795"
    ],
    "name:en": "Gumāngan Pahār",
    "id": 7584121
  }
}
