{
  "geometry": {
    "type": "Point",
    "coordinates": [
      -86.95,
      37.5167
    ]
  },
  "type": "Feature",
  "properties": {
    "hierarchy": [
      "tgn:2458534",
      "tgn:1000001",
      "tgn:7012149",
      "tgn:2000834",
      "tgn:7007255",
      "tgn:7029392"
    ],
    "placetype": [
      "aat:300008706"
    ],
    "id": 2458534,
    "name:xx": "Little No Creek"
  }
}
