{
  "geometry": {
    "type": "Point",
    "coordinates": [
      21.2167,
      54.0333
    ]
  },
  "type": "Feature",
  "properties": {
    "hierarchy": [
      "tgn:4000249",
      "tgn:1000003",
      "tgn:7024118",
      "tgn:7006366",
      "tgn:7029392"
    ],
    "placetype": [
      "aat:300008347"
    ],
    "id": 4000249,
    "name:xx": "Święta Lipka"
  }
}
