{
  "type": "FeatureCollection",
  "features": [
    {
      "geometry": {
        "type": "Point",
        "coordinates": [
          -98.666667,
          22.783333
        ]
      },
      "type": "Feature",
      "properties": {
        "hierarchy": [
          "tgn:7384220",
          "tgn:1000001",
          "tgn:7005597",
          "tgn:7005560",
          "tgn:7029392"
        ],
        "placetype": [
          "aat:300008699"
        ],
        "id": 7384220,
        "name:xx": "Naranjal, Arroyo"
      }
    },
    {
      "geometry": {
        "type": "Point",
        "coordinates": [
          -108.283333,
          29.866667
        ]
      },
      "type": "Feature",
      "properties": {
        "hierarchy": [
          "tgn:7384221",
          "tgn:7005581",
          "tgn:1000001",
          "tgn:7005560",
          "tgn:7029392"
        ],
        "placetype": [
          "aat:300008347"
        ],
        "id": 7384221,
        "name:xx": "Moctezuma"
      }
    },
    {
      "geometry": {
        "type": "Point",
        "coordinates": [
          -98.883333,
          24.733333
        ]
      },
      "type": "Feature",
      "properties": {
        "hierarchy": [
          "tgn:7384223",
          "tgn:1000001",
          "tgn:7005597",
          "tgn:7005560",
          "tgn:7029392"
        ],
        "placetype": [
          "aat:300008347"
        ],
        "id": 7384223,
        "name:xx": "Moctezuma"
      }
    },
    {
      "geometry": {
        "type": "Point",
        "coordinates": [
          -87.216667,
          21.35
        ]
      },
      "type": "Feature",
      "properties": {
        "hierarchy": [
          "tgn:7384226",
          "tgn:1000001",
          "tgn:7005600",
          "tgn:7005560",
          "tgn:7029392"
        ],
        "placetype": [
          "aat:300008347"
        ],
        "id": 7384226,
        "name:xx": "Moctezuma"
      }
    },
    {
      "geometry": {
        "type": "Point",
        "coordinates": [
          -90.8,
          19.05
        ]
      },
      "type": "Feature",
      "properties": {
        "hierarchy": [
          "tgn:7384227",
          "tgn:7005578",
          "tgn:1000001",
          "tgn:7005560",
          "tgn:7029392"
        ],
        "placetype": [
          "aat:300008347"
        ],
        "id": 7384227,
        "name:xx": "Moctezuma"
      }
    },
    {
      "geometry": {
        "type": "Point",
        "coordinates": [
          -109.716667,
          26.95
        ]
      },
      "type": "Feature",
      "properties": {
        "hierarchy": [
          "tgn:7384228",
          "tgn:1000001",
          "tgn:1001960",
          "tgn:7005560",
          "tgn:7029392"
        ],
        "placetype": [
          "aat:300008347"
        ],
        "id": 7384228,
        "name:xx": "Mocorúa"
      }
    },
    {
      "geometry": {
        "type": "Point",
        "coordinates": [
          -108.233333,
          25.166667
        ]
      },
      "type": "Feature",
      "properties": {
        "hierarchy": [
          "tgn:7384229",
          "tgn:1000001",
          "tgn:7005595",
          "tgn:7005560",
          "tgn:7029392"
        ],
        "placetype": [
          "aat:300008699"
        ],
        "id": 7384229,
        "name:xx": "Mocorito, Río"
      }
    }
  ]
}
