{
  "geometry": {
    "type": "Point",
    "coordinates": [
      -110.5833,
      33.9167
    ]
  },
  "type": "Feature",
  "properties": {
    "hierarchy": [
      "tgn:2234107",
      "tgn:1000001",
      "tgn:7006451",
      "tgn:2000093",
      "tgn:7012149",
      "tgn:7029392"
    ],
    "placetype": [
      "aat:300006191"
    ],
    "id": 2234107,
    "name:xx": "Checker Tank"
  }
}
