{
  "geometry": {
    "type": "Point",
    "coordinates": [
      -107.6167,
      37.6167
    ]
  },
  "type": "Feature",
  "properties": {
    "hierarchy": [
      "tgn:2632701",
      "tgn:1000001",
      "tgn:7012149",
      "tgn:7007158",
      "tgn:7029392"
    ],
    "placetype": [
      "aat:300008706"
    ],
    "id": 2632701,
    "name:xx": "Ruby Creek"
  }
}
