{
  "geometry": {
    "type": "Point",
    "coordinates": [
      -85.0333,
      34.9167
    ]
  },
  "type": "Feature",
  "properties": {
    "hierarchy": [
      "tgn:2023297",
      "tgn:1000001",
      "tgn:2000314",
      "tgn:7012149",
      "tgn:7007248",
      "tgn:7029392"
    ],
    "placetype": [
      "aat:300008347"
    ],
    "id": 2023297,
    "name:xx": "Keith"
  }
}
