{
  "geometry": {
    "type": "Point",
    "coordinates": [
      81.44835,
      25.14349
    ]
  },
  "type": "Feature",
  "properties": {
    "hierarchy": [
      "tgn:7545200",
      "tgn:1000004",
      "tgn:7000198",
      "tgn:7016722",
      "tgn:7029392"
    ],
    "placetype": [
      "aat:300008347"
    ],
    "name:en": "Bargarh",
    "id": 7545200
  }
}
