{
  "geometry": {
    "type": "Point",
    "coordinates": [
      -104.8667,
      46.0167
    ]
  },
  "type": "Feature",
  "properties": {
    "hierarchy": [
      "tgn:2545260",
      "tgn:1000001",
      "tgn:7012149",
      "tgn:7007524",
      "tgn:7029392"
    ],
    "placetype": [
      "aat:300008706"
    ],
    "id": 2545260,
    "name:xx": "North Fork Alkali Creek"
  }
}
