{
  "geometry": {
    "type": "Point",
    "coordinates": [
      -121.25,
      44.15
    ]
  },
  "type": "Feature",
  "properties": {
    "hierarchy": [
      "tgn:2084639",
      "tgn:1000001",
      "tgn:2001705",
      "tgn:7012149",
      "tgn:7007708",
      "tgn:7029392"
    ],
    "placetype": [
      "aat:300008347",
      "aat:300387210"
    ],
    "id": 2084639,
    "name:xx": "Deschutes Junction"
  }
}
