{
  "geometry": {
    "type": "Point",
    "coordinates": [
      -92.6333,
      34.6333
    ]
  },
  "type": "Feature",
  "properties": {
    "hierarchy": [
      "tgn:2695179",
      "tgn:1000001",
      "tgn:7016172",
      "tgn:7012149",
      "tgn:2000167",
      "tgn:7029392"
    ],
    "placetype": [
      "aat:300008761"
    ],
    "id": 2695179,
    "name:xx": "Stillhouse Hollow"
  }
}
