{
  "geometry": {
    "type": "Point",
    "coordinates": [
      36.3167,
      35.7667
    ]
  },
  "type": "Feature",
  "properties": {
    "hierarchy": [
      "tgn:5003640",
      "tgn:1000004",
      "tgn:1002084",
      "tgn:1000140",
      "tgn:7029392"
    ],
    "placetype": [
      "aat:300008347",
      "aat:300008375"
    ],
    "id": 5003640,
    "name:xx": "Kufayr"
  }
}
