{
  "geometry": {
    "type": "Point",
    "coordinates": [
      -82.5167,
      35.95
    ]
  },
  "type": "Feature",
  "properties": {
    "hierarchy": [
      "tgn:2317821",
      "tgn:1000001",
      "tgn:7012149",
      "tgn:2001516",
      "tgn:7007709",
      "tgn:7029392"
    ],
    "placetype": [
      "aat:300008347"
    ],
    "id": 2317821,
    "name:xx": "English"
  }
}
