{
  "geometry": {
    "type": "Point",
    "coordinates": [
      -111.5833,
      39.95
    ]
  },
  "type": "Feature",
  "properties": {
    "hierarchy": [
      "tgn:2488518",
      "tgn:1000001",
      "tgn:7012149",
      "tgn:2002125",
      "tgn:7007827",
      "tgn:7029392"
    ],
    "placetype": [
      "aat:300266640"
    ],
    "id": 2488518,
    "name:xx": "Mahogany Ridge"
  }
}
