{
  "geometry": {
    "type": "Point",
    "coordinates": [
      -85.1667,
      36.75
    ]
  },
  "type": "Feature",
  "properties": {
    "hierarchy": [
      "tgn:2377575",
      "tgn:1000001",
      "tgn:2000783",
      "tgn:7012149",
      "tgn:7007255",
      "tgn:7029392"
    ],
    "placetype": [
      "aat:300008798"
    ],
    "id": 2377575,
    "name:xx": "Harper Mountain"
  }
}
