{
  "geometry": {
    "type": "Point",
    "coordinates": [
      -70.6667,
      41.3333
    ]
  },
  "type": "Feature",
  "properties": {
    "hierarchy": [
      "tgn:2177166",
      "tgn:7014010",
      "tgn:1000001",
      "tgn:1002344",
      "tgn:7012149",
      "tgn:7007517",
      "tgn:7029392"
    ],
    "placetype": [
      "aat:300008680"
    ],
    "id": 2177166,
    "name:xx": "Black Point Pond"
  }
}
