{
  "geometry": {
    "type": "Point",
    "coordinates": [
      19.5333,
      45.6167
    ]
  },
  "type": "Feature",
  "properties": {
    "hierarchy": [
      "tgn:1065088",
      "tgn:1000003",
      "tgn:4011927",
      "tgn:7006669",
      "tgn:7029392"
    ],
    "placetype": [
      "aat:300008347"
    ],
    "id": 1065088,
    "name:xx": "Kula"
  }
}
