{
  "geometry": {
    "type": "Point",
    "coordinates": [
      -72.5667,
      40.9333
    ]
  },
  "type": "Feature",
  "properties": {
    "hierarchy": [
      "tgn:2507585",
      "tgn:1000001",
      "tgn:7012149",
      "tgn:1002924",
      "tgn:7007568",
      "tgn:7029392"
    ],
    "placetype": [
      "aat:300008850"
    ],
    "id": 2507585,
    "name:xx": "Miamogue Point"
  }
}
