{
  "geometry": {
    "type": "Point",
    "coordinates": [
      -71.2167,
      41.65
    ]
  },
  "type": "Feature",
  "properties": {
    "hierarchy": [
      "tgn:2251551",
      "tgn:1002716",
      "tgn:1000001",
      "tgn:7012149",
      "tgn:7007711",
      "tgn:7029392"
    ],
    "placetype": [
      "aat:300008850"
    ],
    "id": 2251551,
    "name:xx": "Common Fence Point"
  }
}
