{
  "geometry": {
    "type": "Point",
    "coordinates": [
      -90.1833,
      39.45
    ]
  },
  "type": "Feature",
  "properties": {
    "hierarchy": [
      "tgn:2026416",
      "tgn:1000001",
      "tgn:7012149",
      "tgn:1002422",
      "tgn:7007251",
      "tgn:7029392"
    ],
    "placetype": [
      "aat:300008347"
    ],
    "id": 2026416,
    "name:xx": "Athensville"
  }
}
