{
  "geometry": {
    "type": "Point",
    "coordinates": [
      -109.55,
      36.4833
    ]
  },
  "type": "Feature",
  "properties": {
    "hierarchy": [
      "tgn:2776779",
      "tgn:2000090",
      "tgn:1000001",
      "tgn:7006451",
      "tgn:7012149",
      "tgn:7029392"
    ],
    "placetype": [
      "aat:300008798"
    ],
    "id": 2776779,
    "name:xx": "Window Rock"
  }
}
