{
  "type": "FeatureCollection",
  "features": [
    {
      "geometry": {
        "type": "Point",
        "coordinates": [
          -76.15,
          41.15
        ]
      },
      "type": "Feature",
      "properties": {
        "hierarchy": [
          "tgn:2093020",
          "tgn:1000001",
          "tgn:7012149",
          "tgn:1002612",
          "tgn:7007710",
          "tgn:7029392"
        ],
        "placetype": [
          "aat:300008347"
        ],
        "id": 2093020,
        "name:xx": "Shickshinny"
      }
    },
    {
      "geometry": {
        "type": "Point",
        "coordinates": [
          -79.4333,
          40.3833
        ]
      },
      "type": "Feature",
      "properties": {
        "hierarchy": [
          "tgn:2093021",
          "tgn:1000001",
          "tgn:7012149",
          "tgn:1003017",
          "tgn:7007710",
          "tgn:7029392"
        ],
        "placetype": [
          "aat:300008347"
        ],
        "id": 2093021,
        "name:xx": "Shieldsburg"
      }
    },
    {
      "geometry": {
        "type": "Point",
        "coordinates": [
          -75.95,
          40.3
        ]
      },
      "type": "Feature",
      "properties": {
        "hierarchy": [
          "tgn:2093022",
          "tgn:1000001",
          "tgn:7013387",
          "tgn:7012149",
          "tgn:7007710",
          "tgn:7029392"
        ],
        "placetype": [
          "aat:300008347"
        ],
        "id": 2093022,
        "name:xx": "Shillington"
      }
    },
    {
      "geometry": {
        "type": "Point",
        "coordinates": [
          -76.7833,
          39.9667
        ]
      },
      "type": "Feature",
      "properties": {
        "hierarchy": [
          "tgn:2093023",
          "tgn:1000001",
          "tgn:7012149",
          "tgn:1003047",
          "tgn:7007710",
          "tgn:7029392"
        ],
        "placetype": [
          "aat:300008347"
        ],
        "id": 2093023,
        "name:xx": "Shiloh"
      }
    }
  ]
}
