{
  "geometry": {
    "type": "Point",
    "coordinates": [
      -73.5667,
      45.6667
    ]
  },
  "type": "Feature",
  "properties": {
    "hierarchy": [
      "tgn:1005506",
      "tgn:7005685",
      "tgn:1000001",
      "tgn:7005804",
      "tgn:1007525",
      "tgn:7029392"
    ],
    "placetype": [
      "aat:300008347"
    ],
    "id": 1005506,
    "name:xx": "Saint-François-de-Laval"
  }
}
