{
  "type": "FeatureCollection",
  "features": [
    {
      "geometry": {
        "type": "Point",
        "coordinates": [
          -2.633333,
          52.433333
        ]
      },
      "type": "Feature",
      "properties": {
        "hierarchy": [
          "tgn:7447020",
          "tgn:7002445",
          "tgn:1000003",
          "tgn:7012034",
          "tgn:7008591",
          "tgn:7029392"
        ],
        "placetype": [
          "aat:300008347"
        ],
        "name:en": "Stoke Saint Milborough",
        "id": 7447020
      }
    },
    {
      "geometry": {
        "type": "Point",
        "coordinates": [
          -2.931111,
          51.040278
        ]
      },
      "type": "Feature",
      "properties": {
        "hierarchy": [
          "tgn:7447021",
          "tgn:7002445",
          "tgn:1000003",
          "tgn:7012032",
          "tgn:7008591",
          "tgn:7029392"
        ],
        "placetype": [
          "aat:300008347"
        ],
        "name:en": "Stoke Saint Gregory",
        "id": 7447021
      }
    },
    {
      "geometry": {
        "type": "Point",
        "coordinates": [
          -2.066667,
          52.3
        ]
      },
      "type": "Feature",
      "properties": {
        "hierarchy": [
          "tgn:7447023",
          "tgn:7002445",
          "tgn:1000003",
          "tgn:5000227",
          "tgn:7008591",
          "tgn:7029392"
        ],
        "placetype": [
          "aat:300008347"
        ],
        "name:en": "Stoke Prior",
        "id": 7447023
      }
    },
    {
      "geometry": {
        "type": "Point",
        "coordinates": [
          -4.016667,
          50.3
        ]
      },
      "type": "Feature",
      "properties": {
        "hierarchy": [
          "tgn:7447025",
          "tgn:7002445",
          "tgn:1000003",
          "tgn:7012077",
          "tgn:7008591",
          "tgn:7029392"
        ],
        "placetype": [
          "aat:300386846"
        ],
        "name:en": "Stoke Point",
        "id": 7447025
      }
    },
    {
      "geometry": {
        "type": "Point",
        "coordinates": [
          -3.666667,
          50.266667
        ]
      },
      "type": "Feature",
      "properties": {
        "hierarchy": [
          "tgn:7447028",
          "tgn:7002445",
          "tgn:1000003",
          "tgn:7012077",
          "tgn:7008591",
          "tgn:7029392"
        ],
        "placetype": [
          "aat:300008347"
        ],
        "name:en": "Stokenham",
        "id": 7447028
      }
    }
  ]
}
