{
  "geometry": {
    "type": "Point",
    "coordinates": [
      -77.8333,
      42.3667
    ]
  },
  "type": "Feature",
  "properties": {
    "hierarchy": [
      "tgn:2391960",
      "tgn:1002141",
      "tgn:1000001",
      "tgn:7012149",
      "tgn:7007568",
      "tgn:7029392"
    ],
    "placetype": [
      "aat:300008347"
    ],
    "id": 2391960,
    "name:xx": "Hiltonville"
  }
}
