{
  "geometry": {
    "type": "Point",
    "coordinates": [
      -91.6833,
      39.5167
    ]
  },
  "type": "Feature",
  "properties": {
    "hierarchy": [
      "tgn:2655801",
      "tgn:1000001",
      "tgn:7012149",
      "tgn:1002817",
      "tgn:7007523",
      "tgn:7029392"
    ],
    "placetype": [
      "aat:300008347"
    ],
    "id": 2655801,
    "name:xx": "Shaver Ford"
  }
}
