{
  "type": "FeatureCollection",
  "features": [
    {
      "geometry": {
        "type": "Point",
        "coordinates": [
          -73.3833,
          44.7667
        ]
      },
      "type": "Feature",
      "properties": {
        "hierarchy": [
          "tgn:2510080",
          "tgn:1000001",
          "tgn:1002284",
          "tgn:7012149",
          "tgn:7007568",
          "tgn:7029392"
        ],
        "placetype": [
          "aat:300008850"
        ],
        "id": 2510080,
        "name:xx": "Middle Point"
      }
    },
    {
      "geometry": {
        "type": "Point",
        "coordinates": [
          -76.3,
          35.35
        ]
      },
      "type": "Feature",
      "properties": {
        "hierarchy": [
          "tgn:2510081",
          "tgn:1000001",
          "tgn:7012149",
          "tgn:2001506",
          "tgn:7007709",
          "tgn:7029392"
        ],
        "placetype": [
          "aat:300008850"
        ],
        "id": 2510081,
        "name:xx": "Middle Point"
      }
    },
    {
      "geometry": {
        "type": "Point",
        "coordinates": [
          -84.4333,
          40.85
        ]
      },
      "type": "Feature",
      "properties": {
        "hierarchy": [
          "tgn:2510082",
          "tgn:1000001",
          "tgn:7012149",
          "tgn:1002968",
          "tgn:7007706",
          "tgn:7029392"
        ],
        "placetype": [
          "aat:300008850"
        ],
        "id": 2510082,
        "name:xx": "Middle Point"
      }
    },
    {
      "geometry": {
        "type": "Point",
        "coordinates": [
          -117.4833,
          45.8
        ]
      },
      "type": "Feature",
      "properties": {
        "hierarchy": [
          "tgn:2510083",
          "tgn:1000001",
          "tgn:7012149",
          "tgn:2001722",
          "tgn:7007708",
          "tgn:7029392"
        ],
        "placetype": [
          "aat:300008850"
        ],
        "id": 2510083,
        "name:xx": "Middle Point"
      }
    },
    {
      "geometry": {
        "type": "Point",
        "coordinates": [
          -124.1167,
          43.7667
        ]
      },
      "type": "Feature",
      "properties": {
        "hierarchy": [
          "tgn:2510084",
          "tgn:1000001",
          "tgn:7012149",
          "tgn:2001706",
          "tgn:7007708",
          "tgn:7029392"
        ],
        "placetype": [
          "aat:300008850"
        ],
        "id": 2510084,
        "name:xx": "Middle Point"
      }
    },
    {
      "geometry": {
        "type": "Point",
        "coordinates": [
          -85.65,
          35.0833
        ]
      },
      "type": "Feature",
      "properties": {
        "hierarchy": [
          "tgn:2510085",
          "tgn:1000001",
          "tgn:7012149",
          "tgn:2001894",
          "tgn:7007825",
          "tgn:7029392"
        ],
        "placetype": [
          "aat:300008850"
        ],
        "id": 2510085,
        "name:xx": "Middle Point"
      }
    },
    {
      "geometry": {
        "type": "Point",
        "coordinates": [
          -85.7833,
          35.3167
        ]
      },
      "type": "Feature",
      "properties": {
        "hierarchy": [
          "tgn:2510086",
          "tgn:1000001",
          "tgn:7012149",
          "tgn:2001867",
          "tgn:7007825",
          "tgn:7029392"
        ],
        "placetype": [
          "aat:300008850"
        ],
        "id": 2510086,
        "name:xx": "Middle Point"
      }
    },
    {
      "geometry": {
        "type": "Point",
        "coordinates": [
          -110.8167,
          37.65
        ]
      },
      "type": "Feature",
      "properties": {
        "hierarchy": [
          "tgn:2510087",
          "tgn:1000001",
          "tgn:2002109",
          "tgn:7012149",
          "tgn:7007827",
          "tgn:7029392"
        ],
        "placetype": [
          "aat:300008850"
        ],
        "id": 2510087,
        "name:xx": "Middle Point"
      }
    },
    {
      "geometry": {
        "type": "Point",
        "coordinates": [
          -110.1,
          37.9167
        ]
      },
      "type": "Feature",
      "properties": {
        "hierarchy": [
          "tgn:2510088",
          "tgn:1000001",
          "tgn:7012149",
          "tgn:2002119",
          "tgn:7007827",
          "tgn:7029392"
        ],
        "placetype": [
          "aat:300008850"
        ],
        "id": 2510088,
        "name:xx": "Middle Point"
      }
    },
    {
      "geometry": {
        "type": "Point",
        "coordinates": [
          -122.5333,
          47.5667
        ]
      },
      "type": "Feature",
      "properties": {
        "hierarchy": [
          "tgn:2510089",
          "tgn:1000001",
          "tgn:7012149",
          "tgn:1002552",
          "tgn:7007920",
          "tgn:7029392"
        ],
        "placetype": [
          "aat:300008850"
        ],
        "id": 2510089,
        "name:xx": "Middle Point"
      }
    }
  ]
}
