{
  "type": "FeatureCollection",
  "features": [
    {
      "geometry": {
        "type": "Point",
        "coordinates": [
          -111.6167,
          40.45
        ]
      },
      "type": "Feature",
      "properties": {
        "hierarchy": [
          "tgn:2582750",
          "tgn:1000001",
          "tgn:7012149",
          "tgn:2002125",
          "tgn:7007827",
          "tgn:7029392"
        ],
        "placetype": [
          "aat:300008761"
        ],
        "id": 2582750,
        "name:xx": "Pine Hollow"
      }
    },
    {
      "geometry": {
        "type": "Point",
        "coordinates": [
          -80.9333,
          37.1
        ]
      },
      "type": "Feature",
      "properties": {
        "hierarchy": [
          "tgn:2582751",
          "tgn:1000001",
          "tgn:7012149",
          "tgn:7007919",
          "tgn:7029392"
        ],
        "placetype": [
          "aat:300008761"
        ],
        "id": 2582751,
        "name:xx": "Pine Hollow"
      }
    },
    {
      "geometry": {
        "type": "Point",
        "coordinates": [
          -79.95,
          38.0667
        ]
      },
      "type": "Feature",
      "properties": {
        "hierarchy": [
          "tgn:2582752",
          "tgn:2002143",
          "tgn:1000001",
          "tgn:7012149",
          "tgn:7007919",
          "tgn:7029392"
        ],
        "placetype": [
          "aat:300008761"
        ],
        "id": 2582752,
        "name:xx": "Pine Hollow"
      }
    },
    {
      "geometry": {
        "type": "Point",
        "coordinates": [
          -89.9,
          43.3667
        ]
      },
      "type": "Feature",
      "properties": {
        "hierarchy": [
          "tgn:2582753",
          "tgn:1000001",
          "tgn:7012149",
          "tgn:2002352",
          "tgn:7007922",
          "tgn:7029392"
        ],
        "placetype": [
          "aat:300008761"
        ],
        "id": 2582753,
        "name:xx": "Pine Hollow"
      }
    },
    {
      "geometry": {
        "type": "Point",
        "coordinates": [
          -90.75,
          43.75
        ]
      },
      "type": "Feature",
      "properties": {
        "hierarchy": [
          "tgn:2582754",
          "tgn:1000001",
          "tgn:7012149",
          "tgn:2002340",
          "tgn:7007922",
          "tgn:7029392"
        ],
        "placetype": [
          "aat:300008761"
        ],
        "id": 2582754,
        "name:xx": "Pine Hollow"
      }
    },
    {
      "geometry": {
        "type": "Point",
        "coordinates": [
          -110.4,
          42.3
        ]
      },
      "type": "Feature",
      "properties": {
        "hierarchy": [
          "tgn:2582755",
          "tgn:1000001",
          "tgn:7012149",
          "tgn:2002382",
          "tgn:7007923",
          "tgn:7029392"
        ],
        "placetype": [
          "aat:300008761"
        ],
        "id": 2582755,
        "name:xx": "Pine Hollow"
      }
    },
    {
      "geometry": {
        "type": "Point",
        "coordinates": [
          -112.1,
          37
        ]
      },
      "type": "Feature",
      "properties": {
        "hierarchy": [
          "tgn:2582756",
          "tgn:1000001",
          "tgn:7012149",
          "tgn:2002113",
          "tgn:7007827",
          "tgn:7029392"
        ],
        "placetype": [
          "aat:300008761"
        ],
        "id": 2582756,
        "name:xx": "Pine Hollow Canyon"
      }
    },
    {
      "geometry": {
        "type": "Point",
        "coordinates": [
          -92.8167,
          36.1
        ]
      },
      "type": "Feature",
      "properties": {
        "hierarchy": [
          "tgn:2582757",
          "tgn:1000001",
          "tgn:7016172",
          "tgn:7012149",
          "tgn:2000149",
          "tgn:7029392"
        ],
        "placetype": [
          "aat:300008706"
        ],
        "id": 2582757,
        "name:xx": "Pine Hollow Creek"
      }
    },
    {
      "geometry": {
        "type": "Point",
        "coordinates": [
          -76.4667,
          42.7
        ]
      },
      "type": "Feature",
      "properties": {
        "hierarchy": [
          "tgn:2582758",
          "tgn:1000001",
          "tgn:1002246",
          "tgn:7012149",
          "tgn:7007568",
          "tgn:7029392"
        ],
        "placetype": [
          "aat:300008706"
        ],
        "id": 2582758,
        "name:xx": "Pine Hollow Creek"
      }
    },
    {
      "geometry": {
        "type": "Point",
        "coordinates": [
          -80.6167,
          41.0333
        ]
      },
      "type": "Feature",
      "properties": {
        "hierarchy": [
          "tgn:2582759",
          "tgn:1000001",
          "tgn:7012149",
          "tgn:1002627",
          "tgn:7007706",
          "tgn:7029392"
        ],
        "placetype": [
          "aat:300008706"
        ],
        "id": 2582759,
        "name:xx": "Pine Hollow Creek"
      }
    }
  ]
}
