{
  "geometry": {
    "type": "Point",
    "coordinates": [
      -73.5333,
      40.6333
    ]
  },
  "type": "Feature",
  "properties": {
    "hierarchy": [
      "tgn:2541265",
      "tgn:1000001",
      "tgn:7012149",
      "tgn:1002708",
      "tgn:7007568",
      "tgn:7029392"
    ],
    "placetype": [
      "aat:300008850"
    ],
    "id": 2541265,
    "name:xx": "Nicks Point"
  }
}
