{
  "geometry": {
    "type": "Point",
    "coordinates": [
      8.3167,
      46.4167
    ]
  },
  "type": "Feature",
  "properties": {
    "hierarchy": [
      "tgn:1103997",
      "tgn:1000003",
      "tgn:7029392"
    ],
    "placetype": [
      "aat:300008795"
    ],
    "id": 1103997,
    "name:de": "Blindenhorn"
  }
}
