{
  "geometry": {
    "type": "Point",
    "coordinates": [
      -83.1833,
      39.3833
    ]
  },
  "type": "Feature",
  "properties": {
    "hierarchy": [
      "tgn:2081693",
      "tgn:1000001",
      "tgn:7012149",
      "tgn:1002835",
      "tgn:7007706",
      "tgn:7029392"
    ],
    "placetype": [
      "aat:300008347"
    ],
    "id": 2081693,
    "name:xx": "Roxabell"
  }
}
