{
  "geometry": {
    "type": "Point",
    "coordinates": [
      -112.95,
      34.6833
    ]
  },
  "type": "Feature",
  "properties": {
    "hierarchy": [
      "tgn:2416996",
      "tgn:1000001",
      "tgn:7006451",
      "tgn:7012149",
      "tgn:2000103",
      "tgn:7029392"
    ],
    "placetype": [
      "aat:300008697"
    ],
    "id": 2416996,
    "name:xx": "Jackass Spring"
  }
}
