{
  "geometry": {
    "type": "Point",
    "coordinates": [
      78.466944,
      17.8775
    ]
  },
  "type": "Feature",
  "properties": {
    "hierarchy": [
      "tgn:7567276",
      "tgn:1001828",
      "tgn:1000004",
      "tgn:7000198",
      "tgn:7029392"
    ],
    "placetype": [
      "aat:300007783"
    ],
    "name:en": "Māsaipet Railroad Station",
    "id": 7567276
  }
}
