{
  "geometry": {
    "type": "Point",
    "coordinates": [
      -89.6333,
      32.6833
    ]
  },
  "type": "Feature",
  "properties": {
    "hierarchy": [
      "tgn:2298812",
      "tgn:1000001",
      "tgn:7012149",
      "tgn:2001125",
      "tgn:7007522",
      "tgn:7029392"
    ],
    "placetype": [
      "aat:300008347"
    ],
    "id": 2298812,
    "name:xx": "Drysdale"
  }
}
