{
  "geometry": {
    "type": "Point",
    "coordinates": [
      -71.2667,
      41.85
    ]
  },
  "type": "Feature",
  "properties": {
    "hierarchy": [
      "tgn:2626450",
      "tgn:1002201",
      "tgn:1000001",
      "tgn:7012149",
      "tgn:7007517",
      "tgn:7029392"
    ],
    "placetype": [
      "aat:300008798"
    ],
    "id": 2626450,
    "name:xx": "Rocky Hill"
  }
}
