{
  "geometry": {
    "type": "Point",
    "coordinates": [
      -91.45,
      36.4833
    ]
  },
  "type": "Feature",
  "properties": {
    "hierarchy": [
      "tgn:2633594",
      "tgn:1000001",
      "tgn:7012149",
      "tgn:7029392"
    ],
    "placetype": [
      "aat:300008761"
    ],
    "id": 2633594,
    "name:xx": "Ruprecht Hollow"
  }
}
