{
  "geometry": {
    "type": "Point",
    "coordinates": [
      -82.65,
      35.1167
    ]
  },
  "type": "Feature",
  "properties": {
    "hierarchy": [
      "tgn:2720438",
      "tgn:1000001",
      "tgn:7012149",
      "tgn:7029392"
    ],
    "placetype": [
      "aat:300006191"
    ],
    "id": 2720438,
    "name:xx": "Thunder Lake"
  }
}
