{
  "geometry": {
    "type": "Point",
    "coordinates": [
      -108.8667,
      33.2333
    ]
  },
  "type": "Feature",
  "properties": {
    "hierarchy": [
      "tgn:2640388",
      "tgn:1000001",
      "tgn:2001429",
      "tgn:7012149",
      "tgn:7007566",
      "tgn:7029392"
    ],
    "placetype": [
      "aat:300008697"
    ],
    "id": 2640388,
    "name:xx": "San Francisco Hot Springs"
  }
}
