{
  "geometry": {
    "type": "Point",
    "coordinates": [
      -83.5833,
      46.0833
    ]
  },
  "type": "Feature",
  "properties": {
    "hierarchy": [
      "tgn:2609550",
      "tgn:1000001",
      "tgn:2000952",
      "tgn:7012149",
      "tgn:7007520",
      "tgn:7029392"
    ],
    "placetype": [
      "aat:300132316"
    ],
    "id": 2609550,
    "name:xx": "Raynolds Bay"
  }
}
