{
  "geometry": {
    "type": "Point",
    "coordinates": [
      -83.2667,
      41.1167
    ]
  },
  "type": "Feature",
  "properties": {
    "hierarchy": [
      "tgn:2692269",
      "tgn:1000001",
      "tgn:7012149",
      "tgn:1002883",
      "tgn:7007706",
      "tgn:7029392"
    ],
    "placetype": [
      "aat:300006075"
    ],
    "id": 2692269,
    "name:xx": "Staub Ditch"
  }
}
