{
  "geometry": {
    "type": "Point",
    "coordinates": [
      -73.1667,
      43.95
    ]
  },
  "type": "Feature",
  "properties": {
    "hierarchy": [
      "tgn:2395520",
      "tgn:2002130",
      "tgn:1000001",
      "tgn:7012149",
      "tgn:7007828",
      "tgn:7029392"
    ],
    "placetype": [
      "aat:300008791"
    ],
    "id": 2395520,
    "name:xx": "Hollands Pasture Island"
  }
}
