{
  "geometry": {
    "type": "Point",
    "coordinates": [
      -104.05,
      29.3333
    ]
  },
  "type": "Feature",
  "properties": {
    "hierarchy": [
      "tgn:2250666",
      "tgn:1000001",
      "tgn:7012149",
      "tgn:2002057",
      "tgn:7007826",
      "tgn:7029392"
    ],
    "placetype": [
      "aat:300008761"
    ],
    "id": 2250666,
    "name:xx": "Colorado, Canyon"
  }
}
