{
  "geometry": {
    "type": "Point",
    "coordinates": [
      89.8167,
      24.75
    ]
  },
  "type": "Feature",
  "properties": {
    "hierarchy": [
      "tgn:1065734",
      "tgn:7000189",
      "tgn:1000004",
      "tgn:1000105",
      "tgn:7029392"
    ],
    "placetype": [
      "aat:300008347"
    ],
    "id": 1065734,
    "name:xx": "Jagannāthganj Ghāt"
  }
}
