{
  "geometry": {
    "type": "Point",
    "coordinates": [
      -81.7667,
      34.9833
    ]
  },
  "type": "Feature",
  "properties": {
    "hierarchy": [
      "tgn:2547948",
      "tgn:1000001",
      "tgn:2001735",
      "tgn:7012149",
      "tgn:7007712",
      "tgn:7029392"
    ],
    "placetype": [
      "aat:300008706"
    ],
    "id": 2547948,
    "name:xx": "North Goucher Creek"
  }
}
