{
  "geometry": {
    "type": "Point",
    "coordinates": [
      -118.2667,
      38.4333
    ]
  },
  "type": "Feature",
  "properties": {
    "hierarchy": [
      "tgn:2151169",
      "tgn:1000001",
      "tgn:2001417",
      "tgn:7012149",
      "tgn:7007526",
      "tgn:7029392"
    ],
    "placetype": [
      "aat:300000390"
    ],
    "id": 2151169,
    "name:xx": "Bataan Mine"
  }
}
