{
  "geometry": {
    "type": "Point",
    "coordinates": [
      -98.6667,
      34.45
    ]
  },
  "type": "Feature",
  "properties": {
    "hierarchy": [
      "tgn:2576642",
      "tgn:1000001",
      "tgn:7012149",
      "tgn:7007707",
      "tgn:7029392"
    ],
    "placetype": [
      "aat:300008706"
    ],
    "id": 2576642,
    "name:xx": "Persimmon Creek"
  }
}
