{
  "geometry": {
    "type": "Point",
    "coordinates": [
      30.805011,
      31.158723
    ]
  },
  "type": "Feature",
  "properties": {
    "hierarchy": [
      "tgn:7533006",
      "tgn:7001242",
      "tgn:7016833",
      "tgn:1001335",
      "tgn:7029392"
    ],
    "placetype": [
      "aat:300006075"
    ],
    "name:en": "Tur'at ar Ramyah wa al Manḩalah",
    "id": 7533006
  }
}
