{
  "geometry": {
    "type": "Point",
    "coordinates": [
      -81.2833,
      39.0167
    ]
  },
  "type": "Feature",
  "properties": {
    "hierarchy": [
      "tgn:2280226",
      "tgn:1000001",
      "tgn:7012149",
      "tgn:2002302",
      "tgn:7013961",
      "tgn:7029392"
    ],
    "placetype": [
      "aat:300008699"
    ],
    "id": 2280226,
    "name:xx": "Deaver Fork"
  }
}
