{
  "geometry": {
    "type": "Point",
    "coordinates": [
      79.38445,
      27.051908
    ]
  },
  "type": "Feature",
  "properties": {
    "hierarchy": [
      "tgn:7562503",
      "tgn:1000004",
      "tgn:7000198",
      "tgn:7016722",
      "tgn:7029392"
    ],
    "placetype": [
      "aat:300008347"
    ],
    "name:en": "Nagla Karnāi",
    "id": 7562503
  }
}
