{
  "geometry": {
    "type": "Point",
    "coordinates": [
      -79.7333,
      38.6667
    ]
  },
  "type": "Feature",
  "properties": {
    "hierarchy": [
      "tgn:2477206",
      "tgn:1000001",
      "tgn:7012149",
      "tgn:2002287",
      "tgn:7013961",
      "tgn:7029392"
    ],
    "placetype": [
      "aat:300008798"
    ],
    "id": 2477206,
    "name:xx": "Lynn Knob"
  }
}
