{
  "geometry": {
    "type": "Point",
    "coordinates": [
      -160.4333,
      55.2833
    ]
  },
  "type": "Feature",
  "properties": {
    "hierarchy": [
      "tgn:2610598",
      "tgn:7030515",
      "tgn:7006450",
      "tgn:1000001",
      "tgn:7012149",
      "tgn:7029392"
    ],
    "placetype": [
      "aat:300132316"
    ],
    "id": 2610598,
    "name:xx": "Red Cove"
  }
}
