{
  "geometry": {
    "type": "Point",
    "coordinates": [
      -93.9333,
      47.65
    ]
  },
  "type": "Feature",
  "properties": {
    "hierarchy": [
      "tgn:2249206",
      "tgn:1000001",
      "tgn:7012149",
      "tgn:2001029",
      "tgn:7007521",
      "tgn:7029392"
    ],
    "placetype": [
      "aat:300008680"
    ],
    "id": 2249206,
    "name:xx": "Cole Lake"
  }
}
