{
  "geometry": {
    "type": "Point",
    "coordinates": [
      -80.1667,
      37.8833
    ]
  },
  "type": "Feature",
  "properties": {
    "hierarchy": [
      "tgn:2692414",
      "tgn:1000001",
      "tgn:7012149",
      "tgn:2002264",
      "tgn:7013961",
      "tgn:7029392"
    ],
    "placetype": [
      "aat:300008761"
    ],
    "id": 2692414,
    "name:xx": "Steam Mill Hollow"
  }
}
