{
  "geometry": {
    "type": "Point",
    "coordinates": [
      -78.2833,
      38.95
    ]
  },
  "type": "Feature",
  "properties": {
    "hierarchy": [
      "tgn:2114931",
      "tgn:1000001",
      "tgn:7012149",
      "tgn:2002193",
      "tgn:7007919",
      "tgn:7029392"
    ],
    "placetype": [
      "aat:300008347",
      "aat:300387210"
    ],
    "id": 2114931,
    "name:xx": "Waterlick"
  }
}
