{
  "geometry": {
    "type": "Point",
    "coordinates": [
      72.861,
      24.883
    ]
  },
  "type": "Feature",
  "properties": {
    "hierarchy": [
      "tgn:1077005",
      "tgn:1000004",
      "tgn:7000198",
      "tgn:7016788",
      "tgn:7029392"
    ],
    "placetype": [
      "aat:300008347"
    ],
    "name:en": "Sirohi",
    "id": 1077005
  }
}
