{
  "geometry": {
    "type": "Point",
    "coordinates": [
      27.9833,
      50.6833
    ]
  },
  "type": "Feature",
  "properties": {
    "hierarchy": [
      "tgn:1052524",
      "tgn:1000003",
      "tgn:7011671",
      "tgn:7006660",
      "tgn:7029392"
    ],
    "placetype": [
      "aat:300008347"
    ],
    "id": 1052524,
    "name:xx": "Barashi"
  }
}
