{
  "type": "FeatureCollection",
  "features": [
    {
      "geometry": {
        "type": "Point",
        "coordinates": [
          -100.8833,
          38.6333
        ]
      },
      "type": "Feature",
      "properties": {
        "hierarchy": [
          "tgn:2641530",
          "tgn:1000001",
          "tgn:7012149",
          "tgn:2000745",
          "tgn:7007254",
          "tgn:7029392"
        ],
        "placetype": [
          "aat:300008761"
        ],
        "id": 2641530,
        "name:xx": "Sand Draw"
      }
    },
    {
      "geometry": {
        "type": "Point",
        "coordinates": [
          -102.5833,
          41.0667
        ]
      },
      "type": "Feature",
      "properties": {
        "hierarchy": [
          "tgn:2641531",
          "tgn:1000001",
          "tgn:2001332",
          "tgn:7012149",
          "tgn:7007525",
          "tgn:7029392"
        ],
        "placetype": [
          "aat:300008761"
        ],
        "id": 2641531,
        "name:xx": "Sand Draw"
      }
    },
    {
      "geometry": {
        "type": "Point",
        "coordinates": [
          -100,
          42.5667
        ]
      },
      "type": "Feature",
      "properties": {
        "hierarchy": [
          "tgn:2641532",
          "tgn:1000001",
          "tgn:2001324",
          "tgn:7012149",
          "tgn:7007525",
          "tgn:7029392"
        ],
        "placetype": [
          "aat:300008761"
        ],
        "id": 2641532,
        "name:xx": "Sand Draw"
      }
    },
    {
      "geometry": {
        "type": "Point",
        "coordinates": [
          -103.6,
          41.15
        ]
      },
      "type": "Feature",
      "properties": {
        "hierarchy": [
          "tgn:2641533",
          "tgn:1000001",
          "tgn:7012149",
          "tgn:7007525",
          "tgn:7029392"
        ],
        "placetype": [
          "aat:300008761"
        ],
        "id": 2641533,
        "name:xx": "Sand Draw"
      }
    },
    {
      "geometry": {
        "type": "Point",
        "coordinates": [
          -102.3333,
          42.7167
        ]
      },
      "type": "Feature",
      "properties": {
        "hierarchy": [
          "tgn:2641534",
          "tgn:1000001",
          "tgn:7012149",
          "tgn:2001396",
          "tgn:7007525",
          "tgn:7029392"
        ],
        "placetype": [
          "aat:300008761"
        ],
        "id": 2641534,
        "name:xx": "Sand Draw"
      }
    },
    {
      "geometry": {
        "type": "Point",
        "coordinates": [
          -101.7167,
          40.4667
        ]
      },
      "type": "Feature",
      "properties": {
        "hierarchy": [
          "tgn:2641535",
          "tgn:1000001",
          "tgn:2001330",
          "tgn:7012149",
          "tgn:7007525",
          "tgn:7029392"
        ],
        "placetype": [
          "aat:300008761"
        ],
        "id": 2641535,
        "name:xx": "Sand Draw"
      }
    },
    {
      "geometry": {
        "type": "Point",
        "coordinates": [
          -104.1833,
          33.2833
        ]
      },
      "type": "Feature",
      "properties": {
        "hierarchy": [
          "tgn:2641536",
          "tgn:1000001",
          "tgn:2001430",
          "tgn:7012149",
          "tgn:7007566",
          "tgn:7029392"
        ],
        "placetype": [
          "aat:300008761"
        ],
        "id": 2641536,
        "name:xx": "Sand Draw"
      }
    },
    {
      "geometry": {
        "type": "Point",
        "coordinates": [
          -106.4167,
          34.3
        ]
      },
      "type": "Feature",
      "properties": {
        "hierarchy": [
          "tgn:2641537",
          "tgn:1000001",
          "tgn:7012149",
          "tgn:7007566",
          "tgn:7029392"
        ],
        "placetype": [
          "aat:300008761"
        ],
        "id": 2641537,
        "name:xx": "Sand Draw"
      }
    },
    {
      "geometry": {
        "type": "Point",
        "coordinates": [
          -102.5,
          44.1167
        ]
      },
      "type": "Feature",
      "properties": {
        "hierarchy": [
          "tgn:2641538",
          "tgn:1000001",
          "tgn:7012149",
          "tgn:2001821",
          "tgn:7007713",
          "tgn:7029392"
        ],
        "placetype": [
          "aat:300008761"
        ],
        "id": 2641538,
        "name:xx": "Sand Draw"
      }
    },
    {
      "geometry": {
        "type": "Point",
        "coordinates": [
          -101.9833,
          45.25
        ]
      },
      "type": "Feature",
      "properties": {
        "hierarchy": [
          "tgn:2641539",
          "tgn:1000001",
          "tgn:7012149",
          "tgn:2001836",
          "tgn:7007713",
          "tgn:7029392"
        ],
        "placetype": [
          "aat:300008761"
        ],
        "id": 2641539,
        "name:xx": "Sand Draw"
      }
    }
  ]
}
