{
  "geometry": {
    "type": "Point",
    "coordinates": [
      -122.3333,
      45.4833
    ]
  },
  "type": "Feature",
  "properties": {
    "hierarchy": [
      "tgn:2160754",
      "tgn:1000001",
      "tgn:7012149",
      "tgn:1002699",
      "tgn:7007708",
      "tgn:7029392"
    ],
    "placetype": [
      "aat:300006191"
    ],
    "id": 2160754,
    "name:xx": "Belchers Reservoir"
  }
}
