{
  "geometry": {
    "type": "Point",
    "coordinates": [
      31.220358,
      29.035228
    ]
  },
  "type": "Feature",
  "properties": {
    "hierarchy": [
      "tgn:7523672",
      "tgn:7001242",
      "tgn:7001311",
      "tgn:7016833",
      "tgn:7029392"
    ],
    "placetype": [
      "aat:300379998"
    ],
    "name:en": "Bayāḑ, Wādī",
    "id": 7523672
  }
}
