{
  "geometry": {
    "type": "Point",
    "coordinates": [
      -120.3667,
      40.2833
    ]
  },
  "type": "Feature",
  "properties": {
    "hierarchy": [
      "tgn:2379223",
      "tgn:1000001",
      "tgn:7012149",
      "tgn:7007157",
      "tgn:2000184",
      "tgn:7029392"
    ],
    "placetype": [
      "aat:300008680"
    ],
    "id": 2379223,
    "name:xx": "Hartson Lake"
  }
}
