{
  "type": "FeatureCollection",
  "features": [
    {
      "geometry": {
        "type": "Point",
        "coordinates": [
          -65.338,
          -23.1
        ]
      },
      "type": "Feature",
      "properties": {
        "hierarchy": [
          "tgn:7032340",
          "tgn:7006477",
          "tgn:1001328",
          "tgn:1000002",
          "tgn:7029392"
        ],
        "placetype": [
          "aat:300263063",
          "aat:300008761"
        ],
        "id": 7032340,
        "name:xx": "Humahuaca, Quebrada de"
      }
    },
    {
      "geometry": {
        "type": "Point",
        "coordinates": [
          44.711,
          41.095
        ]
      },
      "type": "Feature",
      "properties": {
        "hierarchy": [
          "tgn:7032341",
          "tgn:1000004",
          "tgn:7024036",
          "tgn:7006651",
          "tgn:7029392"
        ],
        "placetype": [
          "aat:300008347"
        ],
        "id": 7032341,
        "name:xx": "Haghpat"
      }
    },
    {
      "geometry": {
        "type": "Point",
        "coordinates": [
          44.779,
          40.139
        ]
      },
      "type": "Feature",
      "properties": {
        "hierarchy": [
          "tgn:7032344",
          "tgn:1000004",
          "tgn:7024037",
          "tgn:7006651",
          "tgn:7029392"
        ],
        "placetype": [
          "aat:300008347"
        ],
        "id": 7032344,
        "name:xx": "Goght'"
      }
    }
  ]
}
