{
  "geometry": {
    "type": "Point",
    "coordinates": [
      16.1667,
      46.6667
    ]
  },
  "type": "Feature",
  "properties": {
    "hierarchy": [
      "tgn:1112126",
      "tgn:1000003",
      "tgn:7006670",
      "tgn:7029392"
    ],
    "placetype": [
      "aat:300387346"
    ],
    "id": 1112126,
    "name:xx": "Prekmurje"
  }
}
