{
  "geometry": {
    "type": "Point",
    "coordinates": [
      -89.4833,
      37.45
    ]
  },
  "type": "Feature",
  "properties": {
    "hierarchy": [
      "tgn:2189436",
      "tgn:1000001",
      "tgn:2001179",
      "tgn:7012149",
      "tgn:7007523",
      "tgn:7029392"
    ],
    "placetype": [
      "aat:300006191"
    ],
    "id": 2189436,
    "name:xx": "Boutin, Lake"
  }
}
