{
  "geometry": {
    "type": "Point",
    "coordinates": [
      -72.2833,
      41.4333
    ]
  },
  "type": "Feature",
  "properties": {
    "hierarchy": [
      "tgn:2229551",
      "tgn:1000001",
      "tgn:1002714",
      "tgn:7012149",
      "tgn:7007159",
      "tgn:7029392"
    ],
    "placetype": [
      "aat:300008699"
    ],
    "id": 2229551,
    "name:xx": "Cedar Pond Brook"
  }
}
