{
  "geometry": {
    "type": "Point",
    "coordinates": [
      -122.4667,
      37.5667
    ]
  },
  "type": "Feature",
  "properties": {
    "hierarchy": [
      "tgn:2640778",
      "tgn:1000001",
      "tgn:7012149",
      "tgn:7007157",
      "tgn:1002864",
      "tgn:7029392"
    ],
    "placetype": [
      "aat:300008761"
    ],
    "id": 2640778,
    "name:xx": "San Pedro Valley"
  }
}
