{
  "type": "FeatureCollection",
  "features": [
    {
      "geometry": {
        "type": "Point",
        "coordinates": [
          26,
          8.15
        ]
      },
      "type": "Feature",
      "properties": {
        "hierarchy": [
          "tgn:7441560",
          "tgn:7001242",
          "tgn:7441551",
          "tgn:7029392"
        ],
        "placetype": [
          "aat:300387064",
          "aat:300000776"
        ],
        "id": 7441560,
        "name:xx": "Western Bahr El Ghazal"
      }
    },
    {
      "geometry": {
        "type": "Point",
        "coordinates": [
          -3.833333,
          53.15
        ]
      },
      "type": "Feature",
      "properties": {
        "hierarchy": [
          "tgn:7441563",
          "tgn:7002443",
          "tgn:7026970",
          "tgn:1000003",
          "tgn:7008591",
          "tgn:7029392"
        ],
        "placetype": [
          "aat:300008347"
        ],
        "name:en": "Trefriw",
        "id": 7441563
      }
    },
    {
      "geometry": {
        "type": "Point",
        "coordinates": [
          -3.326944,
          51.585278
        ]
      },
      "type": "Feature",
      "properties": {
        "hierarchy": [
          "tgn:7441565",
          "tgn:7002443",
          "tgn:1000003",
          "tgn:7018963",
          "tgn:7008591",
          "tgn:7029392"
        ],
        "placetype": [
          "aat:300008347"
        ],
        "name:en": "Treforest",
        "id": 7441565
      }
    },
    {
      "geometry": {
        "type": "Point",
        "coordinates": [
          -3.1,
          52.833333
        ]
      },
      "type": "Feature",
      "properties": {
        "hierarchy": [
          "tgn:7441567",
          "tgn:7002445",
          "tgn:1000003",
          "tgn:7012034",
          "tgn:7008591",
          "tgn:7029392"
        ],
        "placetype": [
          "aat:300008347"
        ],
        "name:en": "Trefonen",
        "id": 7441567
      }
    },
    {
      "geometry": {
        "type": "Point",
        "coordinates": [
          -3.433333,
          53.216667
        ]
      },
      "type": "Feature",
      "properties": {
        "hierarchy": [
          "tgn:7441569",
          "tgn:7002443",
          "tgn:5000555",
          "tgn:1000003",
          "tgn:7008591",
          "tgn:7029392"
        ],
        "placetype": [
          "aat:300008347"
        ],
        "name:en": "Trefnant",
        "id": 7441569
      }
    }
  ]
}
