{
  "geometry": {
    "type": "Point",
    "coordinates": [
      -79.9167,
      38.35
    ]
  },
  "type": "Feature",
  "properties": {
    "hierarchy": [
      "tgn:2666104",
      "tgn:1000001",
      "tgn:7012149",
      "tgn:2002287",
      "tgn:7013961",
      "tgn:7029392"
    ],
    "placetype": [
      "aat:300008347"
    ],
    "id": 2666104,
    "name:xx": "Sitlington"
  }
}
