{
  "geometry": {
    "type": "Point",
    "coordinates": [
      31.7167,
      5.0167
    ]
  },
  "type": "Feature",
  "properties": {
    "hierarchy": [
      "tgn:1094459",
      "tgn:7441552",
      "tgn:7001242",
      "tgn:7441551",
      "tgn:7029392"
    ],
    "placetype": [
      "aat:300008347"
    ],
    "id": 1094459,
    "name:xx": "Tibari"
  }
}
