{
  "geometry": {
    "type": "Point",
    "coordinates": [
      -85.0667,
      29.7833
    ]
  },
  "type": "Feature",
  "properties": {
    "hierarchy": [
      "tgn:2226320",
      "tgn:1000001",
      "tgn:2000270",
      "tgn:7012149",
      "tgn:7007240",
      "tgn:7029392"
    ],
    "placetype": [
      "aat:300008699"
    ],
    "id": 2226320,
    "name:xx": "Catfish Slough"
  }
}
