{
  "geometry": {
    "type": "Point",
    "coordinates": [
      -87.5333,
      34.4167
    ]
  },
  "type": "Feature",
  "properties": {
    "hierarchy": [
      "tgn:2695166",
      "tgn:7002659",
      "tgn:1000001",
      "tgn:7012149",
      "tgn:2000029",
      "tgn:7029392"
    ],
    "placetype": [
      "aat:300008761"
    ],
    "id": 2695166,
    "name:xx": "Stillhouse Hollow"
  }
}
