{
  "type": "FeatureCollection",
  "features": [
    {
      "geometry": {
        "type": "Point",
        "coordinates": [
          -82.4833,
          36.1667
        ]
      },
      "type": "Feature",
      "properties": {
        "hierarchy": [
          "tgn:2553860",
          "tgn:1000001",
          "tgn:7012149",
          "tgn:2001926",
          "tgn:7007825",
          "tgn:7029392"
        ],
        "placetype": [
          "aat:300008761"
        ],
        "id": 2553860,
        "name:xx": "Oak Hollow"
      }
    },
    {
      "geometry": {
        "type": "Point",
        "coordinates": [
          -98.4667,
          28.9167
        ]
      },
      "type": "Feature",
      "properties": {
        "hierarchy": [
          "tgn:2553861",
          "tgn:1000001",
          "tgn:2001936",
          "tgn:7012149",
          "tgn:7007826",
          "tgn:7029392"
        ],
        "placetype": [
          "aat:300008761"
        ],
        "id": 2553861,
        "name:xx": "Oak Hollow"
      }
    },
    {
      "geometry": {
        "type": "Point",
        "coordinates": [
          -112.2667,
          37.5
        ]
      },
      "type": "Feature",
      "properties": {
        "hierarchy": [
          "tgn:2553862",
          "tgn:1000001",
          "tgn:7012149",
          "tgn:2002113",
          "tgn:7007827",
          "tgn:7029392"
        ],
        "placetype": [
          "aat:300008761"
        ],
        "id": 2553862,
        "name:xx": "Oak Hollow"
      }
    },
    {
      "geometry": {
        "type": "Point",
        "coordinates": [
          -112.3,
          38.6333
        ]
      },
      "type": "Feature",
      "properties": {
        "hierarchy": [
          "tgn:2553863",
          "tgn:1000001",
          "tgn:7012149",
          "tgn:2002121",
          "tgn:7007827",
          "tgn:7029392"
        ],
        "placetype": [
          "aat:300008761"
        ],
        "id": 2553863,
        "name:xx": "Oak Hollow"
      }
    },
    {
      "geometry": {
        "type": "Point",
        "coordinates": [
          -111.85,
          40.4667
        ]
      },
      "type": "Feature",
      "properties": {
        "hierarchy": [
          "tgn:2553864",
          "tgn:1000001",
          "tgn:7012149",
          "tgn:2002118",
          "tgn:7007827",
          "tgn:7029392"
        ],
        "placetype": [
          "aat:300008761"
        ],
        "id": 2553864,
        "name:xx": "Oak Hollow"
      }
    },
    {
      "geometry": {
        "type": "Point",
        "coordinates": [
          -111.8667,
          40.4667
        ]
      },
      "type": "Feature",
      "properties": {
        "hierarchy": [
          "tgn:2553865",
          "tgn:1000001",
          "tgn:7012149",
          "tgn:7007827",
          "tgn:7029392"
        ],
        "placetype": [
          "aat:300008761"
        ],
        "id": 2553865,
        "name:xx": "Oak Hollow"
      }
    },
    {
      "geometry": {
        "type": "Point",
        "coordinates": [
          -111.9,
          41.0833
        ]
      },
      "type": "Feature",
      "properties": {
        "hierarchy": [
          "tgn:2553866",
          "tgn:1000001",
          "tgn:2002106",
          "tgn:7012149",
          "tgn:7007827",
          "tgn:7029392"
        ],
        "placetype": [
          "aat:300008347"
        ],
        "id": 2553866,
        "name:xx": "Oak Hollow"
      }
    },
    {
      "geometry": {
        "type": "Point",
        "coordinates": [
          -123.3167,
          41.8167
        ]
      },
      "type": "Feature",
      "properties": {
        "hierarchy": [
          "tgn:2553867",
          "tgn:1000001",
          "tgn:7012149",
          "tgn:7007157",
          "tgn:2000189",
          "tgn:7029392"
        ],
        "placetype": [
          "aat:300008706"
        ],
        "id": 2553867,
        "name:xx": "Oak Hollow Creek"
      }
    },
    {
      "geometry": {
        "type": "Point",
        "coordinates": [
          -79.9833,
          36
        ]
      },
      "type": "Feature",
      "properties": {
        "hierarchy": [
          "tgn:2553868",
          "tgn:1000001",
          "tgn:7012149",
          "tgn:2001500",
          "tgn:7007709",
          "tgn:7029392"
        ],
        "placetype": [
          "aat:300006191"
        ],
        "id": 2553868,
        "name:xx": "Oak Hollow Lake"
      }
    },
    {
      "geometry": {
        "type": "Point",
        "coordinates": [
          -80,
          36
        ]
      },
      "type": "Feature",
      "properties": {
        "hierarchy": [
          "tgn:2553869",
          "tgn:1000001",
          "tgn:7012149",
          "tgn:2001494",
          "tgn:7007709",
          "tgn:7029392"
        ],
        "placetype": [
          "aat:300008680"
        ],
        "id": 2553869,
        "name:xx": "Oak Hollow Lake"
      }
    }
  ]
}
