{
  "geometry": {
    "type": "Point",
    "coordinates": [
      -121.95,
      42.2833
    ]
  },
  "type": "Feature",
  "properties": {
    "hierarchy": [
      "tgn:2479527",
      "tgn:1000001",
      "tgn:7012149",
      "tgn:2001714",
      "tgn:7007708",
      "tgn:7029392"
    ],
    "placetype": [
      "aat:300008706"
    ],
    "id": 2479527,
    "name:xx": "Lajeunesse Creek"
  }
}
