{
  "geometry": {
    "type": "Point",
    "coordinates": [
      119.2167,
      10.9333
    ]
  },
  "type": "Feature",
  "properties": {
    "hierarchy": [
      "tgn:1011109",
      "tgn:1000004",
      "tgn:1001481",
      "tgn:1000135",
      "tgn:7029392"
    ],
    "placetype": [
      "aat:300008850"
    ],
    "id": 1011109,
    "name:xx": "Ross, Cape"
  }
}
