{
  "geometry": {
    "type": "Point",
    "coordinates": [
      -112.1167,
      42.8333
    ]
  },
  "type": "Feature",
  "properties": {
    "hierarchy": [
      "tgn:2182019",
      "tgn:1000001",
      "tgn:2000466",
      "tgn:7012149",
      "tgn:7007250",
      "tgn:7029392"
    ],
    "placetype": [
      "aat:300008761"
    ],
    "id": 2182019,
    "name:xx": "Blue Lake Gulch"
  }
}
