{
  "geometry": {
    "type": "Point",
    "coordinates": [
      -78.7833,
      39.9167
    ]
  },
  "type": "Feature",
  "properties": {
    "hierarchy": [
      "tgn:2778800",
      "tgn:1000001",
      "tgn:7012149",
      "tgn:7007710",
      "tgn:7029392"
    ],
    "placetype": [
      "aat:300008699"
    ],
    "id": 2778800,
    "name:xx": "Wolf Camp Run"
  }
}
