{
  "geometry": {
    "type": "Point",
    "coordinates": [
      -65.4333,
      -38.8333
    ]
  },
  "type": "Feature",
  "properties": {
    "hierarchy": [
      "tgn:1019466",
      "tgn:7006477",
      "tgn:7006348",
      "tgn:1000002",
      "tgn:7029392"
    ],
    "placetype": [
      "aat:300008347"
    ],
    "id": 1019466,
    "name:xx": "Fortín Uno"
  }
}
