{
  "geometry": {
    "type": "Point",
    "coordinates": [
      -87.65,
      37.0333
    ]
  },
  "type": "Feature",
  "properties": {
    "hierarchy": [
      "tgn:2244365",
      "tgn:1000001",
      "tgn:2000780",
      "tgn:7012149",
      "tgn:7007255",
      "tgn:7029392"
    ],
    "placetype": [
      "aat:300008706"
    ],
    "id": 2244365,
    "name:xx": "Clifty Creek"
  }
}
