{
  "geometry": {
    "type": "Point",
    "coordinates": [
      43.95,
      12.6333
    ]
  },
  "type": "Feature",
  "properties": {
    "hierarchy": [
      "tgn:1011540",
      "tgn:1000139",
      "tgn:7004345",
      "tgn:1000004",
      "tgn:7000261",
      "tgn:7029392"
    ],
    "placetype": [
      "aat:300386846"
    ],
    "id": 1011540,
    "name:xx": "ʻĀrah, Ra's al-"
  }
}
