{
  "geometry": {
    "type": "Point",
    "coordinates": [
      -77.45,
      41.3667
    ]
  },
  "type": "Feature",
  "properties": {
    "hierarchy": [
      "tgn:2514918",
      "tgn:1000001",
      "tgn:7012149",
      "tgn:1002613",
      "tgn:7007710",
      "tgn:7029392"
    ],
    "placetype": [
      "aat:300055621"
    ],
    "id": 2514918,
    "name:xx": "Miller Run Natural Area"
  }
}
