{
  "geometry": {
    "type": "Point",
    "coordinates": [
      -122.1833,
      40.8167
    ]
  },
  "type": "Feature",
  "properties": {
    "hierarchy": [
      "tgn:2759448",
      "tgn:1000001",
      "tgn:7012149",
      "tgn:7007157",
      "tgn:2000188",
      "tgn:7029392"
    ],
    "placetype": [
      "aat:300008706"
    ],
    "id": 2759448,
    "name:xx": "West Fork Didallas Creek"
  }
}
