{
  "geometry": {
    "type": "Point",
    "coordinates": [
      -122.3167,
      39.0333
    ]
  },
  "type": "Feature",
  "properties": {
    "hierarchy": [
      "tgn:2569618",
      "tgn:1000001",
      "tgn:7012149",
      "tgn:1002296",
      "tgn:7007157",
      "tgn:7029392"
    ],
    "placetype": [
      "aat:300008697"
    ],
    "id": 2569618,
    "name:xx": "Parry Spring"
  }
}
