{
  "geometry": {
    "type": "Point",
    "coordinates": [
      -62.9167,
      -36.75
    ]
  },
  "type": "Feature",
  "properties": {
    "hierarchy": [
      "tgn:1019966",
      "tgn:1001160",
      "tgn:7006477",
      "tgn:1000002",
      "tgn:7029392"
    ],
    "placetype": [
      "aat:300008347"
    ],
    "id": 1019966,
    "name:xx": "Salliqueló"
  }
}
