{
  "geometry": {
    "type": "Point",
    "coordinates": [
      -111.9333,
      40.7833
    ]
  },
  "type": "Feature",
  "properties": {
    "hierarchy": [
      "tgn:2774511",
      "tgn:1000001",
      "tgn:7012149",
      "tgn:2002118",
      "tgn:7007827",
      "tgn:7029392"
    ],
    "placetype": [
      "aat:300008347"
    ],
    "id": 2774511,
    "name:xx": "Willow Place"
  }
}
