{
  "geometry": {
    "type": "Point",
    "coordinates": [
      120.2469,
      23.279897
    ]
  },
  "type": "Feature",
  "properties": {
    "hierarchy": [
      "tgn:7481380",
      "tgn:1000004",
      "tgn:7490934",
      "tgn:1000141",
      "tgn:7029392"
    ],
    "placetype": [
      "aat:300007836"
    ],
    "id": 7481380,
    "name:xx": "Hongcuoliao Qiao"
  }
}
