{
  "geometry": {
    "type": "Point",
    "coordinates": [
      21.0667,
      1.7333
    ]
  },
  "type": "Feature",
  "properties": {
    "hierarchy": [
      "tgn:1089355",
      "tgn:7001242",
      "tgn:7016654",
      "tgn:1000159",
      "tgn:7029392"
    ],
    "placetype": [
      "aat:300008347"
    ],
    "id": 1089355,
    "name:xx": "Mokumbusu"
  }
}
