{
  "geometry": {
    "type": "Point",
    "coordinates": [
      -105.0167,
      36.1333
    ]
  },
  "type": "Feature",
  "properties": {
    "hierarchy": [
      "tgn:2443492",
      "tgn:1000001",
      "tgn:7012149",
      "tgn:2001446",
      "tgn:7007566",
      "tgn:7029392"
    ],
    "placetype": [
      "aat:300008699"
    ],
    "id": 2443492,
    "name:xx": "La Cañada"
  }
}
