{
  "geometry": {
    "type": "Point",
    "coordinates": [
      30.712231,
      31.17243
    ]
  },
  "type": "Feature",
  "properties": {
    "hierarchy": [
      "tgn:7532395",
      "tgn:7001242",
      "tgn:7016833",
      "tgn:1001335",
      "tgn:7029392"
    ],
    "placetype": [
      "aat:300008347"
    ],
    "name:en": "Kawm al Jazīrah",
    "id": 7532395
  }
}
