{
  "geometry": {
    "type": "Point",
    "coordinates": [
      112.7833,
      33.7833
    ]
  },
  "type": "Feature",
  "properties": {
    "hierarchy": [
      "tgn:1068301",
      "tgn:1000004",
      "tgn:7016672",
      "tgn:1000111",
      "tgn:7029392"
    ],
    "placetype": [
      "aat:300008347"
    ],
    "id": 1068301,
    "name:xx": "Gengji"
  }
}
