{
  "geometry": {
    "type": "Point",
    "coordinates": [
      -83.2667,
      43.05
    ]
  },
  "type": "Feature",
  "properties": {
    "hierarchy": [
      "tgn:2320020",
      "tgn:1000001",
      "tgn:7012149",
      "tgn:1002576",
      "tgn:7007520",
      "tgn:7029392"
    ],
    "placetype": [
      "aat:300006075"
    ],
    "id": 2320020,
    "name:xx": "Evans Drain"
  }
}
