{
  "geometry": {
    "type": "Point",
    "coordinates": [
      35.0667,
      9.7833
    ]
  },
  "type": "Feature",
  "properties": {
    "hierarchy": [
      "tgn:1089900",
      "tgn:7001242",
      "tgn:1001597",
      "tgn:7000489",
      "tgn:7029392"
    ],
    "placetype": [
      "aat:300008347"
    ],
    "id": 1089900,
    "name:xx": "Mendī"
  }
}
