{
  "geometry": {
    "type": "Point",
    "coordinates": [
      -118.0833,
      44.1833
    ]
  },
  "type": "Feature",
  "properties": {
    "hierarchy": [
      "tgn:2302270",
      "tgn:1000001",
      "tgn:7012149",
      "tgn:2001718",
      "tgn:7007708",
      "tgn:7029392"
    ],
    "placetype": [
      "aat:300008706"
    ],
    "id": 2302270,
    "name:xx": "Dutch John Creek"
  }
}
