{
  "geometry": {
    "type": "Point",
    "coordinates": [
      36.9167,
      49.8667
    ]
  },
  "type": "Feature",
  "properties": {
    "hierarchy": [
      "tgn:1058247",
      "tgn:1003361",
      "tgn:1000003",
      "tgn:7006660",
      "tgn:7029392"
    ],
    "placetype": [
      "aat:300008347"
    ],
    "id": 1058247,
    "name:xx": "Pečenegi"
  }
}
