{
  "geometry": {
    "type": "Point",
    "coordinates": [
      -81.9333,
      37.6667
    ]
  },
  "type": "Feature",
  "properties": {
    "hierarchy": [
      "tgn:2616765",
      "tgn:1000001",
      "tgn:7012149",
      "tgn:2002273",
      "tgn:7013961",
      "tgn:7029392"
    ],
    "placetype": [
      "aat:300008706"
    ],
    "id": 2616765,
    "name:xx": "Rich Creek"
  }
}
