{
  "geometry": {
    "type": "Point",
    "coordinates": [
      -84.5833,
      41.0167
    ]
  },
  "type": "Feature",
  "properties": {
    "hierarchy": [
      "tgn:2393278",
      "tgn:1002143",
      "tgn:1000001",
      "tgn:7012149",
      "tgn:7007252",
      "tgn:7029392"
    ],
    "placetype": [
      "aat:300008706"
    ],
    "id": 2393278,
    "name:xx": "Hoffman Creek"
  }
}
