{
  "geometry": {
    "type": "Point",
    "coordinates": [
      -76.5167,
      36.1333
    ]
  },
  "type": "Feature",
  "properties": {
    "hierarchy": [
      "tgn:2785473",
      "tgn:1000001",
      "tgn:7012149",
      "tgn:2001528",
      "tgn:7007709",
      "tgn:7029392"
    ],
    "placetype": [
      "aat:300008347"
    ],
    "id": 2785473,
    "name:xx": "Yeopim"
  }
}
