{
  "geometry": {
    "type": "Point",
    "coordinates": [
      -91.2667,
      31.75
    ]
  },
  "type": "Feature",
  "properties": {
    "hierarchy": [
      "tgn:2438447",
      "tgn:1000001",
      "tgn:7012149",
      "tgn:2000907",
      "tgn:7007256",
      "tgn:7029392"
    ],
    "placetype": [
      "aat:300008850"
    ],
    "id": 2438447,
    "name:xx": "Kings Point"
  }
}
