{
  "geometry": {
    "type": "Point",
    "coordinates": [
      -95.1667,
      35.2333
    ]
  },
  "type": "Feature",
  "properties": {
    "hierarchy": [
      "tgn:2324761",
      "tgn:1000001",
      "tgn:2001653",
      "tgn:7012149",
      "tgn:7007707",
      "tgn:7029392"
    ],
    "placetype": [
      "aat:300006191"
    ],
    "id": 2324761,
    "name:xx": "Fenton Lake"
  }
}
