{
  "geometry": {
    "type": "Point",
    "coordinates": [
      -79.6167,
      40.4167
    ]
  },
  "type": "Feature",
  "properties": {
    "hierarchy": [
      "tgn:2088297",
      "tgn:1000001",
      "tgn:7012149",
      "tgn:1003017",
      "tgn:7007710",
      "tgn:7029392"
    ],
    "placetype": [
      "aat:300008347"
    ],
    "id": 2088297,
    "name:xx": "Export"
  }
}
