{
  "geometry": {
    "type": "Point",
    "coordinates": [
      -79.4667,
      33.8167
    ]
  },
  "type": "Feature",
  "properties": {
    "hierarchy": [
      "tgn:2721045",
      "tgn:1000001",
      "tgn:2001745",
      "tgn:7012149",
      "tgn:7007712",
      "tgn:7029392"
    ],
    "placetype": [
      "aat:300008680"
    ],
    "id": 2721045,
    "name:xx": "Tie Lake"
  }
}
