{
  "type": "FeatureCollection",
  "features": [
    {
      "geometry": {
        "type": "Point",
        "coordinates": [
          -3.65,
          55.833333
        ]
      },
      "type": "Feature",
      "properties": {
        "hierarchy": [
          "tgn:7464670",
          "tgn:7002444",
          "tgn:1000003",
          "tgn:7019121",
          "tgn:7008591",
          "tgn:7029392"
        ],
        "placetype": [
          "aat:300008347"
        ],
        "name:en": "Bents",
        "id": 7464670
      }
    },
    {
      "geometry": {
        "type": "Point",
        "coordinates": [
          -3.083333,
          55.2
        ]
      },
      "type": "Feature",
      "properties": {
        "hierarchy": [
          "tgn:7464671",
          "tgn:7002444",
          "tgn:7008074",
          "tgn:1000003",
          "tgn:7008591",
          "tgn:7029392"
        ],
        "placetype": [
          "aat:300008347"
        ],
        "name:en": "Bentpath",
        "id": 7464671
      }
    },
    {
      "geometry": {
        "type": "Point",
        "coordinates": [
          -2,
          52.283333
        ]
      },
      "type": "Feature",
      "properties": {
        "hierarchy": [
          "tgn:7464674",
          "tgn:7002445",
          "tgn:1000003",
          "tgn:5000227",
          "tgn:7008591",
          "tgn:7029392"
        ],
        "placetype": [
          "aat:300008347"
        ],
        "name:en": "Bentley",
        "id": 7464674
      }
    },
    {
      "geometry": {
        "type": "Point",
        "coordinates": [
          1.083333,
          51.983333
        ]
      },
      "type": "Feature",
      "properties": {
        "hierarchy": [
          "tgn:7464675",
          "tgn:7002445",
          "tgn:1000003",
          "tgn:7008185",
          "tgn:7008591",
          "tgn:7029392"
        ],
        "placetype": [
          "aat:300008347"
        ],
        "name:en": "Bentley",
        "id": 7464675
      }
    },
    {
      "geometry": {
        "type": "Point",
        "coordinates": [
          -0.866667,
          51.183333
        ]
      },
      "type": "Feature",
      "properties": {
        "hierarchy": [
          "tgn:7464676",
          "tgn:7002445",
          "tgn:1000003",
          "tgn:7008139",
          "tgn:7008591",
          "tgn:7029392"
        ],
        "placetype": [
          "aat:300008347"
        ],
        "name:en": "Bentley",
        "id": 7464676
      }
    },
    {
      "geometry": {
        "type": "Point",
        "coordinates": [
          -1.8,
          53.916667
        ]
      },
      "type": "Feature",
      "properties": {
        "hierarchy": [
          "tgn:7464678",
          "tgn:1003567",
          "tgn:7002445",
          "tgn:1000003",
          "tgn:7029507",
          "tgn:7008591",
          "tgn:7029392"
        ],
        "placetype": [
          "aat:300008347"
        ],
        "name:en": "Ben Rhydding",
        "id": 7464678
      }
    }
  ]
}
