{
  "geometry": {
    "type": "Point",
    "coordinates": [
      -157.4833,
      1.9833
    ]
  },
  "type": "Feature",
  "properties": {
    "hierarchy": [
      "tgn:1011672",
      "tgn:7002038",
      "tgn:1006044",
      "tgn:1000217",
      "tgn:1000006",
      "tgn:7029392"
    ],
    "placetype": [
      "aat:300386846"
    ],
    "id": 1011672,
    "name:xx": "Bridges Point"
  }
}
