{
  "geometry": {
    "type": "Point",
    "coordinates": [
      -79.4333,
      34.05
    ]
  },
  "type": "Feature",
  "properties": {
    "hierarchy": [
      "tgn:2709158",
      "tgn:1000001",
      "tgn:7012149",
      "tgn:2001758",
      "tgn:7007712",
      "tgn:7029392"
    ],
    "placetype": [
      "aat:300008347"
    ],
    "id": 2709158,
    "name:xx": "Tabernacle"
  }
}
