{
  "geometry": {
    "type": "Point",
    "coordinates": [
      34.7667,
      39.5167
    ]
  },
  "type": "Feature",
  "properties": {
    "hierarchy": [
      "tgn:1085836",
      "tgn:1000004",
      "tgn:1001606",
      "tgn:7018453",
      "tgn:1000144",
      "tgn:7029392"
    ],
    "placetype": [
      "aat:300008347"
    ],
    "id": 1085836,
    "name:xx": "Şefaatlı"
  }
}
