{
  "type": "FeatureCollection",
  "features": [
    {
      "geometry": {
        "type": "Point",
        "coordinates": [
          -77.7833,
          36.5
        ]
      },
      "type": "Feature",
      "properties": {
        "hierarchy": [
          "tgn:2771980",
          "tgn:1000001",
          "tgn:7012149",
          "tgn:1002728",
          "tgn:7007709",
          "tgn:7029392"
        ],
        "placetype": [
          "aat:300008798"
        ],
        "id": 2771980,
        "name:xx": "Wilkins Hill"
      }
    },
    {
      "geometry": {
        "type": "Point",
        "coordinates": [
          -115.7167,
          42.9333
        ]
      },
      "type": "Feature",
      "properties": {
        "hierarchy": [
          "tgn:2771981",
          "tgn:1000001",
          "tgn:7012149",
          "tgn:2000488",
          "tgn:7007250",
          "tgn:7029392"
        ],
        "placetype": [
          "aat:300008791"
        ],
        "id": 2771981,
        "name:xx": "Wilkins Island"
      }
    },
    {
      "geometry": {
        "type": "Point",
        "coordinates": [
          -115.3833,
          42
        ]
      },
      "type": "Feature",
      "properties": {
        "hierarchy": [
          "tgn:2771982",
          "tgn:1000001",
          "tgn:7012149",
          "tgn:2000488",
          "tgn:7007250",
          "tgn:7029392"
        ],
        "placetype": [
          "aat:300055621"
        ],
        "id": 2771982,
        "name:xx": "Wilkins Island"
      }
    },
    {
      "geometry": {
        "type": "Point",
        "coordinates": [
          -90.3,
          36.0667
        ]
      },
      "type": "Feature",
      "properties": {
        "hierarchy": [
          "tgn:2771983",
          "tgn:1000001",
          "tgn:7012149",
          "tgn:2001197",
          "tgn:7007523",
          "tgn:7029392"
        ],
        "placetype": [
          "aat:300055621"
        ],
        "id": 2771983,
        "name:xx": "Wilkins Island"
      }
    },
    {
      "geometry": {
        "type": "Point",
        "coordinates": [
          -97.6833,
          40.6
        ]
      },
      "type": "Feature",
      "properties": {
        "hierarchy": [
          "tgn:2771984",
          "tgn:1000001",
          "tgn:2001345",
          "tgn:7012149",
          "tgn:7007525",
          "tgn:7029392"
        ],
        "placetype": [
          "aat:300008905"
        ],
        "id": 2771984,
        "name:xx": "Wilkins Lagoon National Management Area"
      }
    },
    {
      "geometry": {
        "type": "Point",
        "coordinates": [
          -91.9167,
          34.25
        ]
      },
      "type": "Feature",
      "properties": {
        "hierarchy": [
          "tgn:2771985",
          "tgn:1000001",
          "tgn:7016172",
          "tgn:7012149",
          "tgn:2000139",
          "tgn:7029392"
        ],
        "placetype": [
          "aat:300008680"
        ],
        "id": 2771985,
        "name:xx": "Wilkins Lake"
      }
    },
    {
      "geometry": {
        "type": "Point",
        "coordinates": [
          -92.1333,
          34.9833
        ]
      },
      "type": "Feature",
      "properties": {
        "hierarchy": [
          "tgn:2771986",
          "tgn:1000001",
          "tgn:7016172",
          "tgn:7012149",
          "tgn:2000164",
          "tgn:7029392"
        ],
        "placetype": [
          "aat:300006191"
        ],
        "id": 2771986,
        "name:xx": "Wilkins Lake"
      }
    },
    {
      "geometry": {
        "type": "Point",
        "coordinates": [
          -89.5,
          38.4833
        ]
      },
      "type": "Feature",
      "properties": {
        "hierarchy": [
          "tgn:2771987",
          "tgn:1000001",
          "tgn:1002281",
          "tgn:7012149",
          "tgn:7007251",
          "tgn:7029392"
        ],
        "placetype": [
          "aat:300008680"
        ],
        "id": 2771987,
        "name:xx": "Wilkins Lake"
      }
    },
    {
      "geometry": {
        "type": "Point",
        "coordinates": [
          -93.4833,
          46.6333
        ]
      },
      "type": "Feature",
      "properties": {
        "hierarchy": [
          "tgn:2771988",
          "tgn:2000999",
          "tgn:1000001",
          "tgn:7012149",
          "tgn:7007521",
          "tgn:7029392"
        ],
        "placetype": [
          "aat:300008680"
        ],
        "id": 2771988,
        "name:xx": "Wilkins Lake"
      }
    }
  ]
}
