{
  "geometry": {
    "type": "Point",
    "coordinates": [
      -94.2167,
      36.4167
    ]
  },
  "type": "Feature",
  "properties": {
    "hierarchy": [
      "tgn:2007708",
      "tgn:1000001",
      "tgn:2000108",
      "tgn:7016172",
      "tgn:7012149",
      "tgn:7029392"
    ],
    "placetype": [
      "aat:300008347"
    ],
    "id": 2007708,
    "name:xx": "Bella Vista"
  }
}
