{
  "geometry": {
    "type": "Point",
    "coordinates": [
      -88.1333,
      30.8833
    ]
  },
  "type": "Feature",
  "properties": {
    "hierarchy": [
      "tgn:2507833",
      "tgn:7002659",
      "tgn:1000001",
      "tgn:7012149",
      "tgn:2000048",
      "tgn:7029392"
    ],
    "placetype": [
      "aat:300008706"
    ],
    "id": 2507833,
    "name:xx": "Mickers Creek"
  }
}
