{
  "type": "FeatureCollection",
  "features": [
    {
      "geometry": {
        "type": "Point",
        "coordinates": [
          -103.2,
          40.6167
        ]
      },
      "type": "Feature",
      "properties": {
        "hierarchy": [
          "tgn:2016353",
          "tgn:1000001",
          "tgn:7012149",
          "tgn:2000229",
          "tgn:7007158",
          "tgn:7029392"
        ],
        "placetype": [
          "aat:300008347"
        ],
        "id": 2016353,
        "name:xx": "Sterling"
      }
    },
    {
      "geometry": {
        "type": "Point",
        "coordinates": [
          -103.65,
          40.6
        ]
      },
      "type": "Feature",
      "properties": {
        "hierarchy": [
          "tgn:2016354",
          "tgn:1000001",
          "tgn:7012149",
          "tgn:7007158",
          "tgn:2000253",
          "tgn:7029392"
        ],
        "placetype": [
          "aat:300008347"
        ],
        "id": 2016354,
        "name:xx": "Stoneham"
      }
    },
    {
      "geometry": {
        "type": "Point",
        "coordinates": [
          -108.3167,
          37.5833
        ]
      },
      "type": "Feature",
      "properties": {
        "hierarchy": [
          "tgn:2016355",
          "tgn:1000001",
          "tgn:7012149",
          "tgn:2000233",
          "tgn:7007158",
          "tgn:7029392"
        ],
        "placetype": [
          "aat:300008347"
        ],
        "id": 2016355,
        "name:xx": "Stoner"
      }
    },
    {
      "geometry": {
        "type": "Point",
        "coordinates": [
          -105.0167,
          37.15
        ]
      },
      "type": "Feature",
      "properties": {
        "hierarchy": [
          "tgn:2016356",
          "tgn:1000001",
          "tgn:7012149",
          "tgn:2000227",
          "tgn:7007158",
          "tgn:7029392"
        ],
        "placetype": [
          "aat:300008347"
        ],
        "id": 2016356,
        "name:xx": "Stonewall"
      }
    },
    {
      "geometry": {
        "type": "Point",
        "coordinates": [
          -102.1833,
          37.2833
        ]
      },
      "type": "Feature",
      "properties": {
        "hierarchy": [
          "tgn:2016357",
          "tgn:2000196",
          "tgn:1000001",
          "tgn:7012149",
          "tgn:7007158",
          "tgn:7029392"
        ],
        "placetype": [
          "aat:300008347"
        ],
        "id": 2016357,
        "name:xx": "Stonington"
      }
    },
    {
      "geometry": {
        "type": "Point",
        "coordinates": [
          -104.3167,
          39.7333
        ]
      },
      "type": "Feature",
      "properties": {
        "hierarchy": [
          "tgn:2016358",
          "tgn:2000192",
          "tgn:1000001",
          "tgn:7012149",
          "tgn:7007158",
          "tgn:7029392"
        ],
        "placetype": [
          "aat:300008347"
        ],
        "id": 2016358,
        "name:xx": "Strasburg"
      }
    }
  ]
}
