{
  "type": "FeatureCollection",
  "features": [
    {
      "geometry": {
        "type": "Point",
        "coordinates": [
          -112.066667,
          26.766667
        ]
      },
      "type": "Feature",
      "properties": {
        "hierarchy": [
          "tgn:7377050",
          "tgn:1001836",
          "tgn:1000001",
          "tgn:7005560",
          "tgn:7029392"
        ],
        "placetype": [
          "aat:300008347"
        ],
        "id": 7377050,
        "name:xx": "La Trinidad"
      }
    },
    {
      "geometry": {
        "type": "Point",
        "coordinates": [
          -105.133333,
          25.783333
        ]
      },
      "type": "Feature",
      "properties": {
        "hierarchy": [
          "tgn:7377051",
          "tgn:7005583",
          "tgn:1000001",
          "tgn:7005560",
          "tgn:7029392"
        ],
        "placetype": [
          "aat:300008347"
        ],
        "id": 7377051,
        "name:xx": "La Trinidad"
      }
    },
    {
      "geometry": {
        "type": "Point",
        "coordinates": [
          -108.483333,
          25.733333
        ]
      },
      "type": "Feature",
      "properties": {
        "hierarchy": [
          "tgn:7377052",
          "tgn:1000001",
          "tgn:7005595",
          "tgn:7005560",
          "tgn:7029392"
        ],
        "placetype": [
          "aat:300008347"
        ],
        "id": 7377052,
        "name:xx": "La Trinidad"
      }
    },
    {
      "geometry": {
        "type": "Point",
        "coordinates": [
          -100.133333,
          25.216667
        ]
      },
      "type": "Feature",
      "properties": {
        "hierarchy": [
          "tgn:7377053",
          "tgn:1000001",
          "tgn:7005589",
          "tgn:7005560",
          "tgn:7029392"
        ],
        "placetype": [
          "aat:300008347"
        ],
        "id": 7377053,
        "name:xx": "La Trinidad"
      }
    },
    {
      "geometry": {
        "type": "Point",
        "coordinates": [
          -103.366667,
          25.15
        ]
      },
      "type": "Feature",
      "properties": {
        "hierarchy": [
          "tgn:7377054",
          "tgn:1001853",
          "tgn:1000001",
          "tgn:7005560",
          "tgn:7029392"
        ],
        "placetype": [
          "aat:300008347"
        ],
        "id": 7377054,
        "name:xx": "La Trinidad"
      }
    },
    {
      "geometry": {
        "type": "Point",
        "coordinates": [
          -99.25,
          24.983333
        ]
      },
      "type": "Feature",
      "properties": {
        "hierarchy": [
          "tgn:7377055",
          "tgn:1000001",
          "tgn:7005589",
          "tgn:7005560",
          "tgn:7029392"
        ],
        "placetype": [
          "aat:300008347"
        ],
        "id": 7377055,
        "name:xx": "La Trinidad"
      }
    },
    {
      "geometry": {
        "type": "Point",
        "coordinates": [
          -100.4,
          24.916667
        ]
      },
      "type": "Feature",
      "properties": {
        "hierarchy": [
          "tgn:7377056",
          "tgn:1000001",
          "tgn:7005589",
          "tgn:7005560",
          "tgn:7029392"
        ],
        "placetype": [
          "aat:300008347"
        ],
        "id": 7377056,
        "name:xx": "La Trinidad"
      }
    },
    {
      "geometry": {
        "type": "Point",
        "coordinates": [
          -106.032222,
          24.589167
        ]
      },
      "type": "Feature",
      "properties": {
        "hierarchy": [
          "tgn:7377057",
          "tgn:7005583",
          "tgn:1000001",
          "tgn:7005560",
          "tgn:7029392"
        ],
        "placetype": [
          "aat:300008347"
        ],
        "id": 7377057,
        "name:xx": "La Trinidad"
      }
    },
    {
      "geometry": {
        "type": "Point",
        "coordinates": [
          -102.566667,
          24.5
        ]
      },
      "type": "Feature",
      "properties": {
        "hierarchy": [
          "tgn:7377058",
          "tgn:7005583",
          "tgn:1000001",
          "tgn:7005560",
          "tgn:7029392"
        ],
        "placetype": [
          "aat:300008347"
        ],
        "id": 7377058,
        "name:xx": "La Trinidad"
      }
    },
    {
      "geometry": {
        "type": "Point",
        "coordinates": [
          -105.816667,
          24.35
        ]
      },
      "type": "Feature",
      "properties": {
        "hierarchy": [
          "tgn:7377059",
          "tgn:7005583",
          "tgn:1000001",
          "tgn:7005560",
          "tgn:7029392"
        ],
        "placetype": [
          "aat:300008347"
        ],
        "id": 7377059,
        "name:xx": "La Trinidad"
      }
    }
  ]
}
