{
  "type": "FeatureCollection",
  "features": [
    {
      "geometry": {
        "type": "Point",
        "coordinates": [
          -84.6667,
          40.6
        ]
      },
      "type": "Feature",
      "properties": {
        "hierarchy": [
          "tgn:2452090",
          "tgn:1000001",
          "tgn:7012149",
          "tgn:1002658",
          "tgn:7007706",
          "tgn:7029392"
        ],
        "placetype": [
          "aat:300008706"
        ],
        "id": 2452090,
        "name:xx": "Little Black Creek"
      }
    },
    {
      "geometry": {
        "type": "Point",
        "coordinates": [
          -75.9333,
          40.9833
        ]
      },
      "type": "Feature",
      "properties": {
        "hierarchy": [
          "tgn:2452091",
          "tgn:1000001",
          "tgn:7012149",
          "tgn:1002612",
          "tgn:7007710",
          "tgn:7029392"
        ],
        "placetype": [
          "aat:300008706"
        ],
        "id": 2452091,
        "name:xx": "Little Black Creek"
      }
    },
    {
      "geometry": {
        "type": "Point",
        "coordinates": [
          -80.2,
          33.3
        ]
      },
      "type": "Feature",
      "properties": {
        "hierarchy": [
          "tgn:2452092",
          "tgn:1000001",
          "tgn:7012149",
          "tgn:7007712",
          "tgn:7029392"
        ],
        "placetype": [
          "aat:300008706"
        ],
        "id": 2452092,
        "name:xx": "Little Black Creek"
      }
    },
    {
      "geometry": {
        "type": "Point",
        "coordinates": [
          -80.3167,
          34.7333
        ]
      },
      "type": "Feature",
      "properties": {
        "hierarchy": [
          "tgn:2452094",
          "tgn:1000001",
          "tgn:2001737",
          "tgn:7012149",
          "tgn:7007712",
          "tgn:7029392"
        ],
        "placetype": [
          "aat:300008706"
        ],
        "id": 2452094,
        "name:xx": "Little Black Creek"
      }
    },
    {
      "geometry": {
        "type": "Point",
        "coordinates": [
          -94.15,
          30.4333
        ]
      },
      "type": "Feature",
      "properties": {
        "hierarchy": [
          "tgn:2452095",
          "tgn:1000001",
          "tgn:7012149",
          "tgn:1002454",
          "tgn:7007826",
          "tgn:7029392"
        ],
        "placetype": [
          "aat:300008706"
        ],
        "id": 2452095,
        "name:xx": "Little Black Creek"
      }
    },
    {
      "geometry": {
        "type": "Point",
        "coordinates": [
          -79.6833,
          38.95
        ]
      },
      "type": "Feature",
      "properties": {
        "hierarchy": [
          "tgn:2452096",
          "tgn:1000001",
          "tgn:7012149",
          "tgn:2002291",
          "tgn:7013961",
          "tgn:7029392"
        ],
        "placetype": [
          "aat:300008699"
        ],
        "id": 2452096,
        "name:xx": "Little Black Fork"
      }
    },
    {
      "geometry": {
        "type": "Point",
        "coordinates": [
          -121.8667,
          41.3333
        ]
      },
      "type": "Feature",
      "properties": {
        "hierarchy": [
          "tgn:2452097",
          "tgn:1000001",
          "tgn:7012149",
          "tgn:7007157",
          "tgn:2000189",
          "tgn:7029392"
        ],
        "placetype": [
          "aat:300008798"
        ],
        "id": 2452097,
        "name:xx": "Little Black Fox Mountain"
      }
    },
    {
      "geometry": {
        "type": "Point",
        "coordinates": [
          -113.0167,
          34
        ]
      },
      "type": "Feature",
      "properties": {
        "hierarchy": [
          "tgn:2452098",
          "tgn:1000001",
          "tgn:7006451",
          "tgn:7012149",
          "tgn:2000103",
          "tgn:7029392"
        ],
        "placetype": [
          "aat:300006191"
        ],
        "id": 2452098,
        "name:xx": "Little Black Hill Tank"
      }
    },
    {
      "geometry": {
        "type": "Point",
        "coordinates": [
          -111.0667,
          35.6
        ]
      },
      "type": "Feature",
      "properties": {
        "hierarchy": [
          "tgn:2452099",
          "tgn:1000001",
          "tgn:7006451",
          "tgn:2000092",
          "tgn:7012149",
          "tgn:7029392"
        ],
        "placetype": [
          "aat:300006191"
        ],
        "id": 2452099,
        "name:xx": "Little Black Hill Tank"
      }
    }
  ]
}
