{
  "geometry": {
    "type": "Point",
    "coordinates": [
      -80.0833,
      35.2167
    ]
  },
  "type": "Feature",
  "properties": {
    "hierarchy": [
      "tgn:2075923",
      "tgn:1000001",
      "tgn:7012149",
      "tgn:2001540",
      "tgn:7007709",
      "tgn:7029392"
    ],
    "placetype": [
      "aat:300008347",
      "aat:300387210"
    ],
    "id": 2075923,
    "name:xx": "Norwood Beach"
  }
}
