{
  "type": "FeatureCollection",
  "features": [
    {
      "geometry": {
        "type": "Point",
        "coordinates": [
          -73.75,
          -52.933333
        ]
      },
      "type": "Feature",
      "properties": {
        "hierarchy": [
          "tgn:7290340",
          "tgn:1001702",
          "tgn:1000049",
          "tgn:1000002",
          "tgn:7029392"
        ],
        "placetype": [
          "aat:300008791"
        ],
        "id": 7290340,
        "name:xx": "Dolphin, Isla"
      }
    },
    {
      "geometry": {
        "type": "Point",
        "coordinates": [
          -73.933333,
          -53.033333
        ]
      },
      "type": "Feature",
      "properties": {
        "hierarchy": [
          "tgn:7290341",
          "tgn:1001702",
          "tgn:1000049",
          "tgn:1000002",
          "tgn:7029392"
        ],
        "placetype": [
          "aat:300386846"
        ],
        "id": 7290341,
        "name:xx": "Dolores, Punta"
      }
    },
    {
      "geometry": {
        "type": "Point",
        "coordinates": [
          -73.616667,
          -52.316667
        ]
      },
      "type": "Feature",
      "properties": {
        "hierarchy": [
          "tgn:7290342",
          "tgn:1001702",
          "tgn:1000049",
          "tgn:1000002",
          "tgn:7029392"
        ],
        "placetype": [
          "aat:300386846"
        ],
        "id": 7290342,
        "name:xx": "Dolores, Punta"
      }
    },
    {
      "geometry": {
        "type": "Point",
        "coordinates": [
          -70.066667,
          -33.933333
        ]
      },
      "type": "Feature",
      "properties": {
        "hierarchy": [
          "tgn:7290343",
          "tgn:1001708",
          "tgn:1000049",
          "tgn:1000002",
          "tgn:7029392"
        ],
        "placetype": [
          "aat:300259572"
        ],
        "id": 7290343,
        "name:xx": "Dolores, Portezuelo"
      }
    },
    {
      "geometry": {
        "type": "Point",
        "coordinates": [
          -73.533333,
          -37.05
        ]
      },
      "type": "Feature",
      "properties": {
        "hierarchy": [
          "tgn:7290344",
          "tgn:1001637",
          "tgn:1000049",
          "tgn:1000002",
          "tgn:7029392"
        ],
        "placetype": [
          "aat:300008777"
        ],
        "id": 7290344,
        "name:xx": "Dolores, Morro"
      }
    },
    {
      "geometry": {
        "type": "Point",
        "coordinates": [
          -70.35,
          -33.166667
        ]
      },
      "type": "Feature",
      "properties": {
        "hierarchy": [
          "tgn:7290345",
          "tgn:1001708",
          "tgn:1000049",
          "tgn:1000002",
          "tgn:7029392"
        ],
        "placetype": [
          "aat:300008699"
        ],
        "id": 7290345,
        "name:xx": "Dolores, Estero de"
      }
    },
    {
      "geometry": {
        "type": "Point",
        "coordinates": [
          -74.433333,
          -49.366667
        ]
      },
      "type": "Feature",
      "properties": {
        "hierarchy": [
          "tgn:7290346",
          "tgn:1001702",
          "tgn:1000049",
          "tgn:1000002",
          "tgn:7029392"
        ],
        "placetype": [
          "aat:300008808"
        ],
        "id": 7290346,
        "name:xx": "Dolores, Arrecife"
      }
    },
    {
      "geometry": {
        "type": "Point",
        "coordinates": [
          -69.95,
          -19.666667
        ]
      },
      "type": "Feature",
      "properties": {
        "hierarchy": [
          "tgn:7290347",
          "tgn:7002464",
          "tgn:1000049",
          "tgn:1000002",
          "tgn:7029392"
        ],
        "placetype": [
          "aat:300008347"
        ],
        "id": 7290347,
        "name:xx": "Dolores"
      }
    },
    {
      "geometry": {
        "type": "Point",
        "coordinates": [
          -72.433333,
          -38.6
        ]
      },
      "type": "Feature",
      "properties": {
        "hierarchy": [
          "tgn:7290348",
          "tgn:1001692",
          "tgn:1000049",
          "tgn:1000002",
          "tgn:7029392"
        ],
        "placetype": [
          "aat:300008699"
        ],
        "id": 7290348,
        "name:xx": "Dollinco, Río"
      }
    },
    {
      "geometry": {
        "type": "Point",
        "coordinates": [
          -73.15,
          -40.383333
        ]
      },
      "type": "Feature",
      "properties": {
        "hierarchy": [
          "tgn:7290349",
          "tgn:1001699",
          "tgn:1000049",
          "tgn:1000002",
          "tgn:7029392"
        ],
        "placetype": [
          "aat:300008699"
        ],
        "id": 7290349,
        "name:xx": "Dollinco, Estero"
      }
    }
  ]
}
