{
  "type": "FeatureCollection",
  "features": [
    {
      "geometry": {
        "type": "Point",
        "coordinates": [
          47.2167,
          40.2
        ]
      },
      "type": "Feature",
      "properties": {
        "hierarchy": [
          "tgn:1122650",
          "tgn:1000004",
          "tgn:7006646",
          "tgn:7029392"
        ],
        "placetype": [
          "aat:300008707"
        ],
        "id": 1122650,
        "name:xx": "Khachinchay"
      }
    },
    {
      "geometry": {
        "type": "Point",
        "coordinates": [
          -108,
          36.0833
        ]
      },
      "type": "Feature",
      "properties": {
        "hierarchy": [
          "tgn:1122651",
          "tgn:1000001",
          "tgn:7012149",
          "tgn:2001452",
          "tgn:7007566",
          "tgn:7029392"
        ],
        "placetype": [
          "aat:300008707"
        ],
        "id": 1122651,
        "name:xx": "Chaco"
      }
    },
    {
      "geometry": {
        "type": "Point",
        "coordinates": [
          -81.2167,
          41.5667
        ]
      },
      "type": "Feature",
      "properties": {
        "hierarchy": [
          "tgn:1122653",
          "tgn:1000001",
          "tgn:7012149",
          "tgn:7007706",
          "tgn:7029392"
        ],
        "placetype": [
          "aat:300008707"
        ],
        "id": 1122653,
        "name:xx": "Chagrin"
      }
    },
    {
      "geometry": {
        "type": "Point",
        "coordinates": [
          123.85,
          42.3333
        ]
      },
      "type": "Feature",
      "properties": {
        "hierarchy": [
          "tgn:1122655",
          "tgn:1000004",
          "tgn:1001390",
          "tgn:1000111",
          "tgn:7029392"
        ],
        "placetype": [
          "aat:300008707"
        ],
        "id": 1122655,
        "name:xx": "Chai He"
      }
    },
    {
      "geometry": {
        "type": "Point",
        "coordinates": [
          3.9,
          47.3833
        ]
      },
      "type": "Feature",
      "properties": {
        "hierarchy": [
          "tgn:1122656",
          "tgn:1000003",
          "tgn:7002875",
          "tgn:1000070",
          "tgn:7029392"
        ],
        "placetype": [
          "aat:300008707"
        ],
        "id": 1122656,
        "name:xx": "Chalaux"
      }
    },
    {
      "geometry": {
        "type": "Point",
        "coordinates": [
          117.8333,
          48
        ]
      },
      "type": "Feature",
      "properties": {
        "hierarchy": [
          "tgn:1122657",
          "tgn:1000004",
          "tgn:7029392"
        ],
        "placetype": [
          "aat:300008707"
        ],
        "id": 1122657,
        "name:xx": "Chalchyn"
      }
    },
    {
      "geometry": {
        "type": "Point",
        "coordinates": [
          -71.616,
          9.066
        ]
      },
      "type": "Feature",
      "properties": {
        "hierarchy": [
          "tgn:1122658",
          "tgn:1001985",
          "tgn:1000002",
          "tgn:1000059",
          "tgn:7029392"
        ],
        "placetype": [
          "aat:300008707"
        ],
        "id": 1122658,
        "name:xx": "Chama, Río"
      }
    },
    {
      "geometry": {
        "type": "Point",
        "coordinates": [
          -106.0833,
          36.0333
        ]
      },
      "type": "Feature",
      "properties": {
        "hierarchy": [
          "tgn:1122659",
          "tgn:1000001",
          "tgn:7012149",
          "tgn:7029392"
        ],
        "placetype": [
          "aat:300008707"
        ],
        "id": 1122659,
        "name:xx": "Chama, Rio"
      }
    }
  ]
}
