{
  "geometry": {
    "type": "Point",
    "coordinates": [
      -71.9667,
      42.2667
    ]
  },
  "type": "Feature",
  "properties": {
    "hierarchy": [
      "tgn:2741329",
      "tgn:1000001",
      "tgn:7012149",
      "tgn:1003038",
      "tgn:7007517",
      "tgn:7029392"
    ],
    "placetype": [
      "aat:300008347"
    ],
    "id": 2741329,
    "name:xx": "Upper Wire Village"
  }
}
