{
  "geometry": {
    "type": "Point",
    "coordinates": [
      -91.7333,
      30.8333
    ]
  },
  "type": "Feature",
  "properties": {
    "hierarchy": [
      "tgn:2538970",
      "tgn:1000001",
      "tgn:7012149",
      "tgn:2000892",
      "tgn:7007256",
      "tgn:7029392"
    ],
    "placetype": [
      "aat:300008347"
    ],
    "id": 2538970,
    "name:xx": "New California"
  }
}
