{
  "geometry": {
    "type": "Point",
    "coordinates": [
      83.418697,
      26.75111
    ]
  },
  "type": "Feature",
  "properties": {
    "hierarchy": [
      "tgn:7574540",
      "tgn:1000004",
      "tgn:7000198",
      "tgn:7016722",
      "tgn:7029392"
    ],
    "placetype": [
      "aat:300007783"
    ],
    "name:en": "Kunrāghat",
    "id": 7574540
  }
}
