{
  "type": "FeatureCollection",
  "features": [
    {
      "geometry": {
        "type": "Point",
        "coordinates": [
          -69.7833,
          43.7333
        ]
      },
      "type": "Feature",
      "properties": {
        "hierarchy": [
          "tgn:2525510",
          "tgn:1000001",
          "tgn:7012149",
          "tgn:2000929",
          "tgn:7007515",
          "tgn:7029392"
        ],
        "placetype": [
          "aat:300008850"
        ],
        "id": 2525510,
        "name:xx": "Morse Point"
      }
    },
    {
      "geometry": {
        "type": "Point",
        "coordinates": [
          -75.9833,
          36.5333
        ]
      },
      "type": "Feature",
      "properties": {
        "hierarchy": [
          "tgn:2525511",
          "tgn:1000001",
          "tgn:7012149",
          "tgn:7029392"
        ],
        "placetype": [
          "aat:300008850"
        ],
        "id": 2525511,
        "name:xx": "Morse Point"
      }
    },
    {
      "geometry": {
        "type": "Point",
        "coordinates": [
          -69.8,
          45.0667
        ]
      },
      "type": "Feature",
      "properties": {
        "hierarchy": [
          "tgn:2525513",
          "tgn:1000001",
          "tgn:7012149",
          "tgn:2000930",
          "tgn:7007515",
          "tgn:7029392"
        ],
        "placetype": [
          "aat:300008680"
        ],
        "id": 2525513,
        "name:xx": "Morse Pond"
      }
    },
    {
      "geometry": {
        "type": "Point",
        "coordinates": [
          -71.0833,
          42.0333
        ]
      },
      "type": "Feature",
      "properties": {
        "hierarchy": [
          "tgn:2525515",
          "tgn:1002201",
          "tgn:1000001",
          "tgn:7012149",
          "tgn:7007517",
          "tgn:7029392"
        ],
        "placetype": [
          "aat:300006191"
        ],
        "id": 2525515,
        "name:xx": "Morse Pond"
      }
    },
    {
      "geometry": {
        "type": "Point",
        "coordinates": [
          -70.6,
          41.55
        ]
      },
      "type": "Feature",
      "properties": {
        "hierarchy": [
          "tgn:2525516",
          "tgn:1002165",
          "tgn:1000001",
          "tgn:7012149",
          "tgn:7007517",
          "tgn:7029392"
        ],
        "placetype": [
          "aat:300008680"
        ],
        "id": 2525516,
        "name:xx": "Morse Pond"
      }
    },
    {
      "geometry": {
        "type": "Point",
        "coordinates": [
          -79.7,
          34.9333
        ]
      },
      "type": "Feature",
      "properties": {
        "hierarchy": [
          "tgn:2525517",
          "tgn:1000001",
          "tgn:7012149",
          "tgn:2001533",
          "tgn:7007709",
          "tgn:7029392"
        ],
        "placetype": [
          "aat:300006191"
        ],
        "id": 2525517,
        "name:xx": "Morse Pond"
      }
    },
    {
      "geometry": {
        "type": "Point",
        "coordinates": [
          -82.7333,
          39.7667
        ]
      },
      "type": "Feature",
      "properties": {
        "hierarchy": [
          "tgn:2525518",
          "tgn:1000001",
          "tgn:7012149",
          "tgn:2001611",
          "tgn:7007706",
          "tgn:7029392"
        ],
        "placetype": [
          "aat:300006191"
        ],
        "id": 2525518,
        "name:xx": "Morse Pond"
      }
    },
    {
      "geometry": {
        "type": "Point",
        "coordinates": [
          -89.5333,
          43.0167
        ]
      },
      "type": "Feature",
      "properties": {
        "hierarchy": [
          "tgn:2525519",
          "tgn:1000001",
          "tgn:1002316",
          "tgn:7012149",
          "tgn:7007922",
          "tgn:7029392"
        ],
        "placetype": [
          "aat:300008680"
        ],
        "id": 2525519,
        "name:xx": "Morse Pond"
      }
    }
  ]
}
