{
  "geometry": {
    "type": "Point",
    "coordinates": [
      -73.3667,
      44.4833
    ]
  },
  "type": "Feature",
  "properties": {
    "hierarchy": [
      "tgn:2648471",
      "tgn:1000001",
      "tgn:7012149",
      "tgn:2001461",
      "tgn:7007568",
      "tgn:7029392"
    ],
    "placetype": [
      "aat:300008791"
    ],
    "id": 2648471,
    "name:xx": "Schuyler Island"
  }
}
