{
  "geometry": {
    "type": "Point",
    "coordinates": [
      -100.8833,
      42.5833
    ]
  },
  "type": "Feature",
  "properties": {
    "hierarchy": [
      "tgn:2227916",
      "tgn:1000001",
      "tgn:2001331",
      "tgn:7012149",
      "tgn:7007525",
      "tgn:7029392"
    ],
    "placetype": [
      "aat:300132316"
    ],
    "id": 2227916,
    "name:xx": "Cedar Bay"
  }
}
