{
  "type": "FeatureCollection",
  "features": [
    {
      "geometry": {
        "type": "Point",
        "coordinates": [
          -96.45,
          38.45
        ]
      },
      "type": "Feature",
      "properties": {
        "hierarchy": [
          "tgn:2205430",
          "tgn:1000001",
          "tgn:2000668",
          "tgn:7012149",
          "tgn:7007254",
          "tgn:7029392"
        ],
        "placetype": [
          "aat:300008706"
        ],
        "id": 2205430,
        "name:xx": "Bull Creek"
      }
    },
    {
      "geometry": {
        "type": "Point",
        "coordinates": [
          -87.3167,
          37.0333
        ]
      },
      "type": "Feature",
      "properties": {
        "hierarchy": [
          "tgn:2205431",
          "tgn:1000001",
          "tgn:2000780",
          "tgn:7012149",
          "tgn:7007255",
          "tgn:7029392"
        ],
        "placetype": [
          "aat:300008706"
        ],
        "id": 2205431,
        "name:xx": "Bull Creek"
      }
    },
    {
      "geometry": {
        "type": "Point",
        "coordinates": [
          -87.7167,
          37.1833
        ]
      },
      "type": "Feature",
      "properties": {
        "hierarchy": [
          "tgn:2205432",
          "tgn:1000001",
          "tgn:7012149",
          "tgn:2000801",
          "tgn:7007255",
          "tgn:7029392"
        ],
        "placetype": [
          "aat:300008706"
        ],
        "id": 2205432,
        "name:xx": "Bull Creek"
      }
    },
    {
      "geometry": {
        "type": "Point",
        "coordinates": [
          -83.45,
          37.15
        ]
      },
      "type": "Feature",
      "properties": {
        "hierarchy": [
          "tgn:2205433",
          "tgn:1000001",
          "tgn:7012149",
          "tgn:2000811",
          "tgn:7007255",
          "tgn:7029392"
        ],
        "placetype": [
          "aat:300008706"
        ],
        "id": 2205433,
        "name:xx": "Bull Creek"
      }
    },
    {
      "geometry": {
        "type": "Point",
        "coordinates": [
          -87.6167,
          37.45
        ]
      },
      "type": "Feature",
      "properties": {
        "hierarchy": [
          "tgn:2205434",
          "tgn:1000001",
          "tgn:7012149",
          "tgn:2000851",
          "tgn:7007255",
          "tgn:7029392"
        ],
        "placetype": [
          "aat:300008706"
        ],
        "id": 2205434,
        "name:xx": "Bull Creek"
      }
    },
    {
      "geometry": {
        "type": "Point",
        "coordinates": [
          -82.9333,
          37.5333
        ]
      },
      "type": "Feature",
      "properties": {
        "hierarchy": [
          "tgn:2205435",
          "tgn:1000001",
          "tgn:7012149",
          "tgn:2000821",
          "tgn:7007255",
          "tgn:7029392"
        ],
        "placetype": [
          "aat:300008706"
        ],
        "id": 2205435,
        "name:xx": "Bull Creek"
      }
    },
    {
      "geometry": {
        "type": "Point",
        "coordinates": [
          -85.5167,
          38.4167
        ]
      },
      "type": "Feature",
      "properties": {
        "hierarchy": [
          "tgn:2205436",
          "tgn:1000001",
          "tgn:7012149",
          "tgn:1002744",
          "tgn:7007255",
          "tgn:7029392"
        ],
        "placetype": [
          "aat:300008706"
        ],
        "id": 2205436,
        "name:xx": "Bull Creek"
      }
    },
    {
      "geometry": {
        "type": "Point",
        "coordinates": [
          -82.9833,
          37.1667
        ]
      },
      "type": "Feature",
      "properties": {
        "hierarchy": [
          "tgn:2205437",
          "tgn:1000001",
          "tgn:7012149",
          "tgn:7007255",
          "tgn:7029392"
        ],
        "placetype": [
          "aat:300008706"
        ],
        "id": 2205437,
        "name:xx": "Bull Creek"
      }
    },
    {
      "geometry": {
        "type": "Point",
        "coordinates": [
          -82.7667,
          37.6
        ]
      },
      "type": "Feature",
      "properties": {
        "hierarchy": [
          "tgn:2205438",
          "tgn:1000001",
          "tgn:7012149",
          "tgn:2000789",
          "tgn:7007255",
          "tgn:7029392"
        ],
        "placetype": [
          "aat:300008706"
        ],
        "id": 2205438,
        "name:xx": "Bull Creek"
      }
    },
    {
      "geometry": {
        "type": "Point",
        "coordinates": [
          -86.5333,
          37.85
        ]
      },
      "type": "Feature",
      "properties": {
        "hierarchy": [
          "tgn:2205439",
          "tgn:1000001",
          "tgn:2000773",
          "tgn:7012149",
          "tgn:7007255",
          "tgn:7029392"
        ],
        "placetype": [
          "aat:300008706"
        ],
        "id": 2205439,
        "name:xx": "Bull Creek"
      }
    }
  ]
}
