{
  "type": "FeatureCollection",
  "features": [
    {
      "geometry": {
        "type": "Point",
        "coordinates": [
          13.416667,
          53.9
        ]
      },
      "type": "Feature",
      "properties": {
        "hierarchy": [
          "tgn:7152140",
          "tgn:1000003",
          "tgn:7000094",
          "tgn:7000084",
          "tgn:7029392"
        ],
        "placetype": [
          "aat:300008347"
        ],
        "id": 7152140,
        "name:xx": "Kagenow"
      }
    },
    {
      "geometry": {
        "type": "Point",
        "coordinates": [
          10.866667,
          49.5
        ]
      },
      "type": "Feature",
      "properties": {
        "hierarchy": [
          "tgn:7152141",
          "tgn:7003669",
          "tgn:1000003",
          "tgn:7000084",
          "tgn:7029392"
        ],
        "placetype": [
          "aat:300008347"
        ],
        "id": 7152141,
        "name:xx": "Kagenhof"
      }
    },
    {
      "geometry": {
        "type": "Point",
        "coordinates": [
          13.733333,
          53.8
        ]
      },
      "type": "Feature",
      "properties": {
        "hierarchy": [
          "tgn:7152142",
          "tgn:1000003",
          "tgn:7000094",
          "tgn:7000084",
          "tgn:7029392"
        ],
        "placetype": [
          "aat:300008347"
        ],
        "id": 7152142,
        "name:xx": "Kagendorf"
      }
    },
    {
      "geometry": {
        "type": "Point",
        "coordinates": [
          13.383333,
          51.166667
        ]
      },
      "type": "Feature",
      "properties": {
        "hierarchy": [
          "tgn:7152143",
          "tgn:1000003",
          "tgn:7003685",
          "tgn:7000084",
          "tgn:7029392"
        ],
        "placetype": [
          "aat:300008347"
        ],
        "id": 7152143,
        "name:xx": "Kagen"
      }
    },
    {
      "geometry": {
        "type": "Point",
        "coordinates": [
          12.266667,
          48.3
        ]
      },
      "type": "Feature",
      "properties": {
        "hierarchy": [
          "tgn:7152144",
          "tgn:7003669",
          "tgn:1000003",
          "tgn:7000084",
          "tgn:7029392"
        ],
        "placetype": [
          "aat:300008347"
        ],
        "id": 7152144,
        "name:xx": "Kagen"
      }
    },
    {
      "geometry": {
        "type": "Point",
        "coordinates": [
          12.283333,
          48.2
        ]
      },
      "type": "Feature",
      "properties": {
        "hierarchy": [
          "tgn:7152145",
          "tgn:7003669",
          "tgn:1000003",
          "tgn:7000084",
          "tgn:7029392"
        ],
        "placetype": [
          "aat:300000206"
        ],
        "id": 7152145,
        "name:xx": "Kagen"
      }
    },
    {
      "geometry": {
        "type": "Point",
        "coordinates": [
          13.916667,
          52.466667
        ]
      },
      "type": "Feature",
      "properties": {
        "hierarchy": [
          "tgn:7152146",
          "tgn:7000096",
          "tgn:1000003",
          "tgn:7000084",
          "tgn:7029392"
        ],
        "placetype": [
          "aat:300008347"
        ],
        "id": 7152146,
        "name:xx": "Kagel"
      }
    },
    {
      "geometry": {
        "type": "Point",
        "coordinates": [
          10.216667,
          48.6
        ]
      },
      "type": "Feature",
      "properties": {
        "hierarchy": [
          "tgn:7152147",
          "tgn:7003692",
          "tgn:1000003",
          "tgn:7000084",
          "tgn:7029392"
        ],
        "placetype": [
          "aat:300008777"
        ],
        "id": 7152147,
        "name:xx": "Kagberg"
      }
    },
    {
      "geometry": {
        "type": "Point",
        "coordinates": [
          12.816667,
          53.133333
        ]
      },
      "type": "Feature",
      "properties": {
        "hierarchy": [
          "tgn:7152148",
          "tgn:7000096",
          "tgn:1000003",
          "tgn:7000084",
          "tgn:7029392"
        ],
        "placetype": [
          "aat:300008680"
        ],
        "id": 7152148,
        "name:xx": "Kagarsee"
      }
    },
    {
      "geometry": {
        "type": "Point",
        "coordinates": [
          12.833333,
          53.133333
        ]
      },
      "type": "Feature",
      "properties": {
        "hierarchy": [
          "tgn:7152149",
          "tgn:7000096",
          "tgn:1000003",
          "tgn:7000084",
          "tgn:7029392"
        ],
        "placetype": [
          "aat:300008699"
        ],
        "id": 7152149,
        "name:xx": "Kagar-Bach"
      }
    }
  ]
}
