{
  "geometry": {
    "type": "Point",
    "coordinates": [
      -123.2833,
      47.7333
    ]
  },
  "type": "Feature",
  "properties": {
    "hierarchy": [
      "tgn:2286667",
      "tgn:1000001",
      "tgn:7012149",
      "tgn:1002521",
      "tgn:7007920",
      "tgn:7029392"
    ],
    "placetype": [
      "aat:300008798"
    ],
    "id": 2286667,
    "name:xx": "Diamond Mountain"
  }
}
