{
  "type": "FeatureCollection",
  "features": [
    {
      "geometry": {
        "type": "Point",
        "coordinates": [
          -103.033333,
          25.716667
        ]
      },
      "type": "Feature",
      "properties": {
        "hierarchy": [
          "tgn:7367710",
          "tgn:1001853",
          "tgn:1000001",
          "tgn:7005560",
          "tgn:7029392"
        ],
        "placetype": [
          "aat:300008347"
        ],
        "id": 7367710,
        "name:xx": "El Venado"
      }
    },
    {
      "geometry": {
        "type": "Point",
        "coordinates": [
          -101.95,
          25.483333
        ]
      },
      "type": "Feature",
      "properties": {
        "hierarchy": [
          "tgn:7367711",
          "tgn:1001853",
          "tgn:1000001",
          "tgn:7005560",
          "tgn:7029392"
        ],
        "placetype": [
          "aat:300008347"
        ],
        "id": 7367711,
        "name:xx": "El Venado"
      }
    },
    {
      "geometry": {
        "type": "Point",
        "coordinates": [
          -100.866667,
          24.933333
        ]
      },
      "type": "Feature",
      "properties": {
        "hierarchy": [
          "tgn:7367712",
          "tgn:1001853",
          "tgn:1000001",
          "tgn:7005560",
          "tgn:7029392"
        ],
        "placetype": [
          "aat:300008347"
        ],
        "id": 7367712,
        "name:xx": "El Venado"
      }
    },
    {
      "geometry": {
        "type": "Point",
        "coordinates": [
          -98.016667,
          23.9
        ]
      },
      "type": "Feature",
      "properties": {
        "hierarchy": [
          "tgn:7367713",
          "tgn:1000001",
          "tgn:7005597",
          "tgn:7005560",
          "tgn:7029392"
        ],
        "placetype": [
          "aat:300008347"
        ],
        "id": 7367713,
        "name:xx": "El Venado"
      }
    },
    {
      "geometry": {
        "type": "Point",
        "coordinates": [
          -97.95,
          22.616667
        ]
      },
      "type": "Feature",
      "properties": {
        "hierarchy": [
          "tgn:7367714",
          "tgn:1000001",
          "tgn:7005597",
          "tgn:7005560",
          "tgn:7029392"
        ],
        "placetype": [
          "aat:300008347"
        ],
        "id": 7367714,
        "name:xx": "El Venado"
      }
    },
    {
      "geometry": {
        "type": "Point",
        "coordinates": [
          -105,
          21.933333
        ]
      },
      "type": "Feature",
      "properties": {
        "hierarchy": [
          "tgn:7367715",
          "tgn:1000001",
          "tgn:1001906",
          "tgn:7005560",
          "tgn:7029392"
        ],
        "placetype": [
          "aat:300008347"
        ],
        "id": 7367715,
        "name:xx": "El Venado"
      }
    },
    {
      "geometry": {
        "type": "Point",
        "coordinates": [
          -102.883333,
          20.583333
        ]
      },
      "type": "Feature",
      "properties": {
        "hierarchy": [
          "tgn:7367716",
          "tgn:7005586",
          "tgn:1000001",
          "tgn:7005560",
          "tgn:7029392"
        ],
        "placetype": [
          "aat:300008347"
        ],
        "id": 7367716,
        "name:xx": "El Venado"
      }
    },
    {
      "geometry": {
        "type": "Point",
        "coordinates": [
          -102.433333,
          20.466667
        ]
      },
      "type": "Feature",
      "properties": {
        "hierarchy": [
          "tgn:7367717",
          "tgn:7005586",
          "tgn:1000001",
          "tgn:7005560",
          "tgn:7029392"
        ],
        "placetype": [
          "aat:300008347"
        ],
        "id": 7367717,
        "name:xx": "El Venado"
      }
    },
    {
      "geometry": {
        "type": "Point",
        "coordinates": [
          -99.033333,
          25.7
        ]
      },
      "type": "Feature",
      "properties": {
        "hierarchy": [
          "tgn:7367718",
          "tgn:1000001",
          "tgn:7005589",
          "tgn:7005560",
          "tgn:7029392"
        ],
        "placetype": [
          "aat:300008347"
        ],
        "id": 7367718,
        "name:xx": "El Venadito de Amado Cantú"
      }
    },
    {
      "geometry": {
        "type": "Point",
        "coordinates": [
          -99.716667,
          27.283333
        ]
      },
      "type": "Feature",
      "properties": {
        "hierarchy": [
          "tgn:7367719",
          "tgn:1000001",
          "tgn:7005597",
          "tgn:7005560",
          "tgn:7029392"
        ],
        "placetype": [
          "aat:300000241"
        ],
        "id": 7367719,
        "name:xx": "Rancho El Venadito"
      }
    }
  ]
}
