{
  "geometry": {
    "type": "Point",
    "coordinates": [
      -81.2333,
      36.7333
    ]
  },
  "type": "Feature",
  "properties": {
    "hierarchy": [
      "tgn:2111297",
      "tgn:1000001",
      "tgn:7012149",
      "tgn:2002164",
      "tgn:7007919",
      "tgn:7029392"
    ],
    "placetype": [
      "aat:300008347"
    ],
    "id": 2111297,
    "name:xx": "Comers Rock"
  }
}
