{
  "geometry": {
    "type": "Point",
    "coordinates": [
      -114.6833,
      38.2833
    ]
  },
  "type": "Feature",
  "properties": {
    "hierarchy": [
      "tgn:2681193",
      "tgn:1000001",
      "tgn:2001416",
      "tgn:7012149",
      "tgn:7007526",
      "tgn:7029392"
    ],
    "placetype": [
      "aat:300008697"
    ],
    "id": 2681193,
    "name:xx": "South Mud Spring"
  }
}
