{
  "geometry": {
    "type": "Point",
    "coordinates": [
      -81.4833,
      41.4833
    ]
  },
  "type": "Feature",
  "properties": {
    "hierarchy": [
      "tgn:1133165",
      "tgn:1000001",
      "tgn:1002313",
      "tgn:7012149",
      "tgn:7007706",
      "tgn:7029392"
    ],
    "placetype": [
      "aat:300008706"
    ],
    "id": 1133165,
    "name:xx": "Euclid Creek"
  }
}
