{
  "geometry": {
    "type": "Point",
    "coordinates": [
      -98.1667,
      45.9333
    ]
  },
  "type": "Feature",
  "properties": {
    "hierarchy": [
      "tgn:2274338",
      "tgn:1000001",
      "tgn:2001567",
      "tgn:7012149",
      "tgn:7007705",
      "tgn:7029392"
    ],
    "placetype": [
      "aat:300006191"
    ],
    "id": 2274338,
    "name:xx": "Dakota Lake"
  }
}
