{
  "geometry": {
    "type": "Point",
    "coordinates": [
      119.7833,
      36.7833
    ]
  },
  "type": "Feature",
  "properties": {
    "hierarchy": [
      "tgn:1073841",
      "tgn:1000004",
      "tgn:7002085",
      "tgn:1000111",
      "tgn:7029392"
    ],
    "placetype": [
      "aat:300008347"
    ],
    "id": 1073841,
    "name:xx": "Zhanggezhuang"
  }
}
