{
  "geometry": {
    "type": "Point",
    "coordinates": [
      -71.85,
      42.0333
    ]
  },
  "type": "Feature",
  "properties": {
    "hierarchy": [
      "tgn:2448683",
      "tgn:1000001",
      "tgn:7012149",
      "tgn:1003038",
      "tgn:7007517",
      "tgn:7029392"
    ],
    "placetype": [
      "aat:300008680"
    ],
    "id": 2448683,
    "name:xx": "Lily Pond"
  }
}
