{
  "geometry": {
    "type": "Point",
    "coordinates": [
      -88.0833,
      40.1833
    ]
  },
  "type": "Feature",
  "properties": {
    "hierarchy": [
      "tgn:2738754",
      "tgn:1000001",
      "tgn:1002253",
      "tgn:7012149",
      "tgn:7007251",
      "tgn:7029392"
    ],
    "placetype": [
      "aat:300006075"
    ],
    "id": 2738754,
    "name:xx": "Union Drainage Ditch Number 1"
  }
}
