{
  "geometry": {
    "type": "Point",
    "coordinates": [
      -123.1167,
      38.55
    ]
  },
  "type": "Feature",
  "properties": {
    "hierarchy": [
      "tgn:2169871",
      "tgn:1000001",
      "tgn:7012149",
      "tgn:7007157",
      "tgn:7014516",
      "tgn:7029392"
    ],
    "placetype": [
      "aat:300008706"
    ],
    "id": 2169871,
    "name:xx": "Big Oat Creek"
  }
}
