{
  "geometry": {
    "type": "Point",
    "coordinates": [
      29.4333,
      -13.6667
    ]
  },
  "type": "Feature",
  "properties": {
    "hierarchy": [
      "tgn:1095977",
      "tgn:1001187",
      "tgn:7001242",
      "tgn:1000209",
      "tgn:7029392"
    ],
    "placetype": [
      "aat:300008347"
    ],
    "id": 1095977,
    "name:xx": "Mkushi"
  }
}
