{
  "type": "FeatureCollection",
  "features": [
    {
      "geometry": {
        "type": "Point",
        "coordinates": [
          -93.4,
          43.65
        ]
      },
      "type": "Feature",
      "properties": {
        "hierarchy": [
          "tgn:2766180",
          "tgn:1000001",
          "tgn:2001022",
          "tgn:7012149",
          "tgn:7007521",
          "tgn:7029392"
        ],
        "placetype": [
          "aat:300008680"
        ],
        "id": 2766180,
        "name:xx": "White Lake"
      }
    },
    {
      "geometry": {
        "type": "Point",
        "coordinates": [
          -91.8667,
          47.2
        ]
      },
      "type": "Feature",
      "properties": {
        "hierarchy": [
          "tgn:2766181",
          "tgn:1000001",
          "tgn:7012149",
          "tgn:2001067",
          "tgn:7007521",
          "tgn:7029392"
        ],
        "placetype": [
          "aat:300008680"
        ],
        "id": 2766181,
        "name:xx": "White Lake"
      }
    },
    {
      "geometry": {
        "type": "Point",
        "coordinates": [
          -88.6,
          31.05
        ]
      },
      "type": "Feature",
      "properties": {
        "hierarchy": [
          "tgn:2766182",
          "tgn:1000001",
          "tgn:7012149",
          "tgn:2001106",
          "tgn:7007522",
          "tgn:7029392"
        ],
        "placetype": [
          "aat:300008680"
        ],
        "id": 2766182,
        "name:xx": "White Lake"
      }
    },
    {
      "geometry": {
        "type": "Point",
        "coordinates": [
          -89.9167,
          32.5167
        ]
      },
      "type": "Feature",
      "properties": {
        "hierarchy": [
          "tgn:2766183",
          "tgn:1000001",
          "tgn:7012149",
          "tgn:2001146",
          "tgn:7007522",
          "tgn:7029392"
        ],
        "placetype": [
          "aat:300008680"
        ],
        "id": 2766183,
        "name:xx": "White Lake"
      }
    },
    {
      "geometry": {
        "type": "Point",
        "coordinates": [
          -90.0833,
          33.8
        ]
      },
      "type": "Feature",
      "properties": {
        "hierarchy": [
          "tgn:2766184",
          "tgn:1000001",
          "tgn:7012149",
          "tgn:2001153",
          "tgn:7007522",
          "tgn:7029392"
        ],
        "placetype": [
          "aat:300008680"
        ],
        "id": 2766184,
        "name:xx": "White Lake"
      }
    },
    {
      "geometry": {
        "type": "Point",
        "coordinates": [
          -90.4667,
          32.4667
        ]
      },
      "type": "Feature",
      "properties": {
        "hierarchy": [
          "tgn:2766185",
          "tgn:1000001",
          "tgn:7012149",
          "tgn:2001110",
          "tgn:7007522",
          "tgn:7029392"
        ],
        "placetype": [
          "aat:300006191"
        ],
        "id": 2766185,
        "name:xx": "White Lake"
      }
    },
    {
      "geometry": {
        "type": "Point",
        "coordinates": [
          -91.1667,
          39.4667
        ]
      },
      "type": "Feature",
      "properties": {
        "hierarchy": [
          "tgn:2766186",
          "tgn:1000001",
          "tgn:7012149",
          "tgn:1002787",
          "tgn:7007523",
          "tgn:7029392"
        ],
        "placetype": [
          "aat:300006191"
        ],
        "id": 2766186,
        "name:xx": "White Lake"
      }
    },
    {
      "geometry": {
        "type": "Point",
        "coordinates": [
          -92.9667,
          39.7
        ]
      },
      "type": "Feature",
      "properties": {
        "hierarchy": [
          "tgn:2766187",
          "tgn:1000001",
          "tgn:2001184",
          "tgn:7012149",
          "tgn:7007523",
          "tgn:7029392"
        ],
        "placetype": [
          "aat:300006191"
        ],
        "id": 2766187,
        "name:xx": "White Lake"
      }
    },
    {
      "geometry": {
        "type": "Point",
        "coordinates": [
          -93.6833,
          39.3333
        ]
      },
      "type": "Feature",
      "properties": {
        "hierarchy": [
          "tgn:2766188",
          "tgn:1000001",
          "tgn:2001180",
          "tgn:7012149",
          "tgn:7007523",
          "tgn:7029392"
        ],
        "placetype": [
          "aat:300006191"
        ],
        "id": 2766188,
        "name:xx": "White Lake"
      }
    },
    {
      "geometry": {
        "type": "Point",
        "coordinates": [
          -114.4,
          46.0833
        ]
      },
      "type": "Feature",
      "properties": {
        "hierarchy": [
          "tgn:2766189",
          "tgn:1000001",
          "tgn:7012149",
          "tgn:2001300",
          "tgn:7007524",
          "tgn:7029392"
        ],
        "placetype": [
          "aat:300008680"
        ],
        "id": 2766189,
        "name:xx": "White Lake"
      }
    }
  ]
}
