{
  "geometry": {
    "type": "Point",
    "coordinates": [
      -81.0667,
      35.8667
    ]
  },
  "type": "Feature",
  "properties": {
    "hierarchy": [
      "tgn:2543011",
      "tgn:2001464",
      "tgn:1000001",
      "tgn:7012149",
      "tgn:7007709",
      "tgn:7029392"
    ],
    "placetype": [
      "aat:300006191"
    ],
    "id": 2543011,
    "name:xx": "Noname"
  }
}
