{
  "geometry": {
    "type": "Point",
    "coordinates": [
      112.9167,
      23.8167
    ]
  },
  "type": "Feature",
  "properties": {
    "hierarchy": [
      "tgn:1074151",
      "tgn:1000004",
      "tgn:7005232",
      "tgn:1000111",
      "tgn:7029392"
    ],
    "placetype": [
      "aat:300008347"
    ],
    "id": 1074151,
    "name:xx": "Zhukeng"
  }
}
