{
  "geometry": {
    "type": "Point",
    "coordinates": [
      -165.9833,
      61.9167
    ]
  },
  "type": "Feature",
  "properties": {
    "hierarchy": [
      "tgn:2538420",
      "tgn:7006450",
      "tgn:1000001",
      "tgn:7012149",
      "tgn:2000087",
      "tgn:7029392"
    ],
    "placetype": [
      "aat:300008791"
    ],
    "id": 2538420,
    "name:xx": "Neragon Island"
  }
}
