{
  "type": "FeatureCollection",
  "features": [
    {
      "geometry": {
        "type": "Point",
        "coordinates": [
          -87.5667,
          30.6667
        ]
      },
      "type": "Feature",
      "properties": {
        "hierarchy": [
          "tgn:2296050",
          "tgn:2000001",
          "tgn:7002659",
          "tgn:1000001",
          "tgn:7012149",
          "tgn:7029392"
        ],
        "placetype": [
          "aat:300008699"
        ],
        "id": 2296050,
        "name:xx": "Dry Branch"
      }
    },
    {
      "geometry": {
        "type": "Point",
        "coordinates": [
          -87.2833,
          31.05
        ]
      },
      "type": "Feature",
      "properties": {
        "hierarchy": [
          "tgn:2296051",
          "tgn:7002659",
          "tgn:1000001",
          "tgn:7012149",
          "tgn:2000026",
          "tgn:7029392"
        ],
        "placetype": [
          "aat:300008699"
        ],
        "id": 2296051,
        "name:xx": "Dry Branch"
      }
    },
    {
      "geometry": {
        "type": "Point",
        "coordinates": [
          -85.55,
          31.6
        ]
      },
      "type": "Feature",
      "properties": {
        "hierarchy": [
          "tgn:2296052",
          "tgn:7002659",
          "tgn:1000001",
          "tgn:7012149",
          "tgn:2000022",
          "tgn:7029392"
        ],
        "placetype": [
          "aat:300008699"
        ],
        "id": 2296052,
        "name:xx": "Dry Branch"
      }
    },
    {
      "geometry": {
        "type": "Point",
        "coordinates": [
          -87.9,
          31.8667
        ]
      },
      "type": "Feature",
      "properties": {
        "hierarchy": [
          "tgn:2296053",
          "tgn:7002659",
          "tgn:1000001",
          "tgn:2000012",
          "tgn:7012149",
          "tgn:7029392"
        ],
        "placetype": [
          "aat:300008699"
        ],
        "id": 2296053,
        "name:xx": "Dry Branch"
      }
    },
    {
      "geometry": {
        "type": "Point",
        "coordinates": [
          -86.15,
          31.9667
        ]
      },
      "type": "Feature",
      "properties": {
        "hierarchy": [
          "tgn:2296054",
          "tgn:7002659",
          "tgn:1000001",
          "tgn:7012149",
          "tgn:7029392"
        ],
        "placetype": [
          "aat:300008699"
        ],
        "id": 2296054,
        "name:xx": "Dry Branch"
      }
    },
    {
      "geometry": {
        "type": "Point",
        "coordinates": [
          -86.5,
          32.4333
        ]
      },
      "type": "Feature",
      "properties": {
        "hierarchy": [
          "tgn:2296055",
          "tgn:2000000",
          "tgn:7002659",
          "tgn:1000001",
          "tgn:7012149",
          "tgn:7029392"
        ],
        "placetype": [
          "aat:300008699"
        ],
        "id": 2296055,
        "name:xx": "Dry Branch"
      }
    },
    {
      "geometry": {
        "type": "Point",
        "coordinates": [
          -86.5,
          32.9667
        ]
      },
      "type": "Feature",
      "properties": {
        "hierarchy": [
          "tgn:2296056",
          "tgn:7002659",
          "tgn:1000001",
          "tgn:2000018",
          "tgn:7012149",
          "tgn:7029392"
        ],
        "placetype": [
          "aat:300008699"
        ],
        "id": 2296056,
        "name:xx": "Dry Branch"
      }
    },
    {
      "geometry": {
        "type": "Point",
        "coordinates": [
          -86.4833,
          33.2167
        ]
      },
      "type": "Feature",
      "properties": {
        "hierarchy": [
          "tgn:2296057",
          "tgn:7002659",
          "tgn:1000001",
          "tgn:7012149",
          "tgn:2000058",
          "tgn:7029392"
        ],
        "placetype": [
          "aat:300008699"
        ],
        "id": 2296057,
        "name:xx": "Dry Branch"
      }
    },
    {
      "geometry": {
        "type": "Point",
        "coordinates": [
          -87.5167,
          33.5333
        ]
      },
      "type": "Feature",
      "properties": {
        "hierarchy": [
          "tgn:2296058",
          "tgn:7002659",
          "tgn:1000001",
          "tgn:7012149",
          "tgn:2000062",
          "tgn:7029392"
        ],
        "placetype": [
          "aat:300008699"
        ],
        "id": 2296058,
        "name:xx": "Dry Branch"
      }
    },
    {
      "geometry": {
        "type": "Point",
        "coordinates": [
          -85.8333,
          33.5167
        ]
      },
      "type": "Feature",
      "properties": {
        "hierarchy": [
          "tgn:2296059",
          "tgn:7002659",
          "tgn:1000001",
          "tgn:7012149",
          "tgn:2000060",
          "tgn:7029392"
        ],
        "placetype": [
          "aat:300008699"
        ],
        "id": 2296059,
        "name:xx": "Dry Branch"
      }
    }
  ]
}
