{
  "geometry": {
    "type": "Point",
    "coordinates": [
      127.8833,
      37.9333
    ]
  },
  "type": "Feature",
  "properties": {
    "hierarchy": [
      "tgn:1120497",
      "tgn:1001342",
      "tgn:1000004",
      "tgn:7000299",
      "tgn:7029392"
    ],
    "placetype": [
      "aat:300006191"
    ],
    "id": 1120497,
    "name:xx": "Soyang-chŏsuji"
  }
}
