{
  "geometry": {
    "type": "Point",
    "coordinates": [
      169.95,
      -44.45
    ]
  },
  "type": "Feature",
  "properties": {
    "hierarchy": [
      "tgn:7507121",
      "tgn:1009227",
      "tgn:1000226",
      "tgn:7018437",
      "tgn:1000006",
      "tgn:7029392"
    ],
    "placetype": [
      "aat:300008699"
    ],
    "name:en": "Quail Burn",
    "id": 7507121
  }
}
