{
  "type": "FeatureCollection",
  "features": [
    {
      "geometry": {
        "type": "Point",
        "coordinates": [
          -105.233333,
          26.55
        ]
      },
      "type": "Feature",
      "properties": {
        "hierarchy": [
          "tgn:7359040",
          "tgn:7005581",
          "tgn:1000001",
          "tgn:7005560",
          "tgn:7029392"
        ],
        "placetype": [
          "aat:300008347"
        ],
        "id": 7359040,
        "name:xx": "El Águila"
      }
    },
    {
      "geometry": {
        "type": "Point",
        "coordinates": [
          -109.15,
          25.916667
        ]
      },
      "type": "Feature",
      "properties": {
        "hierarchy": [
          "tgn:7359041",
          "tgn:1000001",
          "tgn:7005595",
          "tgn:7005560",
          "tgn:7029392"
        ],
        "placetype": [
          "aat:300008347"
        ],
        "id": 7359041,
        "name:xx": "El Águila"
      }
    },
    {
      "geometry": {
        "type": "Point",
        "coordinates": [
          -103.333333,
          25.516667
        ]
      },
      "type": "Feature",
      "properties": {
        "hierarchy": [
          "tgn:7359042",
          "tgn:1001853",
          "tgn:1000001",
          "tgn:7005560",
          "tgn:7029392"
        ],
        "placetype": [
          "aat:300008347"
        ],
        "id": 7359042,
        "name:xx": "El Aguila"
      }
    },
    {
      "geometry": {
        "type": "Point",
        "coordinates": [
          -103.183333,
          23.366667
        ]
      },
      "type": "Feature",
      "properties": {
        "hierarchy": [
          "tgn:7359043",
          "tgn:1000001",
          "tgn:7005601",
          "tgn:7005560",
          "tgn:7029392"
        ],
        "placetype": [
          "aat:300008347"
        ],
        "id": 7359043,
        "name:xx": "El Águila"
      }
    },
    {
      "geometry": {
        "type": "Point",
        "coordinates": [
          -104.016667,
          21.116667
        ]
      },
      "type": "Feature",
      "properties": {
        "hierarchy": [
          "tgn:7359044",
          "tgn:7005586",
          "tgn:1000001",
          "tgn:7005560",
          "tgn:7029392"
        ],
        "placetype": [
          "aat:300008347"
        ],
        "id": 7359044,
        "name:xx": "El Águila"
      }
    },
    {
      "geometry": {
        "type": "Point",
        "coordinates": [
          -102.233333,
          20.9
        ]
      },
      "type": "Feature",
      "properties": {
        "hierarchy": [
          "tgn:7359045",
          "tgn:7005586",
          "tgn:1000001",
          "tgn:7005560",
          "tgn:7029392"
        ],
        "placetype": [
          "aat:300008347"
        ],
        "id": 7359045,
        "name:xx": "El Águila"
      }
    },
    {
      "geometry": {
        "type": "Point",
        "coordinates": [
          -101.9,
          18.1
        ]
      },
      "type": "Feature",
      "properties": {
        "hierarchy": [
          "tgn:7359046",
          "tgn:7005585",
          "tgn:1000001",
          "tgn:7005560",
          "tgn:7029392"
        ],
        "placetype": [
          "aat:300008347"
        ],
        "id": 7359046,
        "name:xx": "El Águila"
      }
    },
    {
      "geometry": {
        "type": "Point",
        "coordinates": [
          -101.833333,
          17.95
        ]
      },
      "type": "Feature",
      "properties": {
        "hierarchy": [
          "tgn:7359047",
          "tgn:7005585",
          "tgn:1000001",
          "tgn:7005560",
          "tgn:7029392"
        ],
        "placetype": [
          "aat:300008347"
        ],
        "id": 7359047,
        "name:xx": "El Águila"
      }
    },
    {
      "geometry": {
        "type": "Point",
        "coordinates": [
          -91.25,
          17.65
        ]
      },
      "type": "Feature",
      "properties": {
        "hierarchy": [
          "tgn:7359048",
          "tgn:1000001",
          "tgn:7005596",
          "tgn:7005560",
          "tgn:7029392"
        ],
        "placetype": [
          "aat:300008347"
        ],
        "id": 7359048,
        "name:xx": "El Aguila"
      }
    },
    {
      "geometry": {
        "type": "Point",
        "coordinates": [
          -92.183333,
          15.083333
        ]
      },
      "type": "Feature",
      "properties": {
        "hierarchy": [
          "tgn:7359049",
          "tgn:7005580",
          "tgn:1000001",
          "tgn:7005560",
          "tgn:7029392"
        ],
        "placetype": [
          "aat:300008347"
        ],
        "id": 7359049,
        "name:xx": "El Aguila"
      }
    }
  ]
}
