{
  "geometry": {
    "type": "Point",
    "coordinates": [
      120.7667,
      15.6667
    ]
  },
  "type": "Feature",
  "properties": {
    "hierarchy": [
      "tgn:1084234",
      "tgn:1000004",
      "tgn:1001464",
      "tgn:1000135",
      "tgn:7029392"
    ],
    "placetype": [
      "aat:300008347"
    ],
    "id": 1084234,
    "name:xx": "Guimba"
  }
}
