{
  "type": "FeatureCollection",
  "features": [
    {
      "geometry": {
        "type": "Point",
        "coordinates": [
          -120.65,
          39.6667
        ]
      },
      "type": "Feature",
      "properties": {
        "hierarchy": [
          "tgn:2353640",
          "tgn:1000001",
          "tgn:7012149",
          "tgn:7007157",
          "tgn:1002894",
          "tgn:7029392"
        ],
        "placetype": [
          "aat:300008680"
        ],
        "id": 2353640,
        "name:xx": "Gold Lake"
      }
    },
    {
      "geometry": {
        "type": "Point",
        "coordinates": [
          -121.1333,
          39.9333
        ]
      },
      "type": "Feature",
      "properties": {
        "hierarchy": [
          "tgn:2353641",
          "tgn:1000001",
          "tgn:7012149",
          "tgn:7007157",
          "tgn:2000187",
          "tgn:7029392"
        ],
        "placetype": [
          "aat:300008680"
        ],
        "id": 2353641,
        "name:xx": "Gold Lake"
      }
    },
    {
      "geometry": {
        "type": "Point",
        "coordinates": [
          -105.4333,
          40.0833
        ]
      },
      "type": "Feature",
      "properties": {
        "hierarchy": [
          "tgn:2353642",
          "tgn:1000001",
          "tgn:2000198",
          "tgn:7012149",
          "tgn:7007158",
          "tgn:7029392"
        ],
        "placetype": [
          "aat:300006191"
        ],
        "id": 2353642,
        "name:xx": "Gold Lake"
      }
    },
    {
      "geometry": {
        "type": "Point",
        "coordinates": [
          -82.35,
          28.4667
        ]
      },
      "type": "Feature",
      "properties": {
        "hierarchy": [
          "tgn:2353643",
          "tgn:1000001",
          "tgn:1002473",
          "tgn:7012149",
          "tgn:7007240",
          "tgn:7029392"
        ],
        "placetype": [
          "aat:300008680"
        ],
        "id": 2353643,
        "name:xx": "Gold Lake"
      }
    },
    {
      "geometry": {
        "type": "Point",
        "coordinates": [
          -82.2333,
          31.2167
        ]
      },
      "type": "Feature",
      "properties": {
        "hierarchy": [
          "tgn:2353644",
          "tgn:1000001",
          "tgn:7012149",
          "tgn:2000404",
          "tgn:7007248",
          "tgn:7029392"
        ],
        "placetype": [
          "aat:300008680"
        ],
        "id": 2353644,
        "name:xx": "Gold Lake"
      }
    },
    {
      "geometry": {
        "type": "Point",
        "coordinates": [
          -115.2667,
          46.9333
        ]
      },
      "type": "Feature",
      "properties": {
        "hierarchy": [
          "tgn:2353645",
          "tgn:1000001",
          "tgn:7012149",
          "tgn:2000491",
          "tgn:7007250",
          "tgn:7029392"
        ],
        "placetype": [
          "aat:300008680"
        ],
        "id": 2353645,
        "name:xx": "Gold Lake"
      }
    },
    {
      "geometry": {
        "type": "Point",
        "coordinates": [
          -115.3667,
          47.3
        ]
      },
      "type": "Feature",
      "properties": {
        "hierarchy": [
          "tgn:2353646",
          "tgn:1000001",
          "tgn:7012149",
          "tgn:2001290",
          "tgn:7007524",
          "tgn:7029392"
        ],
        "placetype": [
          "aat:300008680"
        ],
        "id": 2353646,
        "name:xx": "Gold Lake"
      }
    },
    {
      "geometry": {
        "type": "Point",
        "coordinates": [
          -115.4167,
          48.9833
        ]
      },
      "type": "Feature",
      "properties": {
        "hierarchy": [
          "tgn:2353647",
          "tgn:1000001",
          "tgn:7012149",
          "tgn:2001286",
          "tgn:7007524",
          "tgn:7029392"
        ],
        "placetype": [
          "aat:300008680"
        ],
        "id": 2353647,
        "name:xx": "Gold Lake"
      }
    },
    {
      "geometry": {
        "type": "Point",
        "coordinates": [
          -98.9167,
          42.2667
        ]
      },
      "type": "Feature",
      "properties": {
        "hierarchy": [
          "tgn:2353648",
          "tgn:1000001",
          "tgn:2001360",
          "tgn:7012149",
          "tgn:7007525",
          "tgn:7029392"
        ],
        "placetype": [
          "aat:300008680"
        ],
        "id": 2353648,
        "name:xx": "Gold Lake"
      }
    },
    {
      "geometry": {
        "type": "Point",
        "coordinates": [
          -108.3,
          32.5333
        ]
      },
      "type": "Feature",
      "properties": {
        "hierarchy": [
          "tgn:2353649",
          "tgn:1000001",
          "tgn:7012149",
          "tgn:2001437",
          "tgn:7007566",
          "tgn:7029392"
        ],
        "placetype": [
          "aat:300006191"
        ],
        "id": 2353649,
        "name:xx": "Gold Lake"
      }
    }
  ]
}
