{
  "geometry": {
    "type": "Point",
    "coordinates": [
      -72.1667,
      41.5167
    ]
  },
  "type": "Feature",
  "properties": {
    "hierarchy": [
      "tgn:2516613",
      "tgn:1000001",
      "tgn:1002714",
      "tgn:7012149",
      "tgn:7007159",
      "tgn:7029392"
    ],
    "placetype": [
      "aat:300008699"
    ],
    "id": 2516613,
    "name:xx": "Mineral Spring Brook"
  }
}
