{
  "geometry": {
    "type": "Point",
    "coordinates": [
      -95.5833,
      30.3167
    ]
  },
  "type": "Feature",
  "properties": {
    "hierarchy": [
      "tgn:2334565",
      "tgn:1000001",
      "tgn:7012149",
      "tgn:1002691",
      "tgn:7007826",
      "tgn:7029392"
    ],
    "placetype": [
      "aat:300006191"
    ],
    "id": 2334565,
    "name:xx": "Forest, Lake"
  }
}
