{
  "geometry": {
    "type": "Point",
    "coordinates": [
      28.47919,
      31.065251
    ]
  },
  "type": "Feature",
  "properties": {
    "hierarchy": [
      "tgn:7525042",
      "tgn:7001242",
      "tgn:7016833",
      "tgn:1001418",
      "tgn:7029392"
    ],
    "placetype": [
      "aat:300386968"
    ],
    "name:en": "Marsá aḑ Ḑab'ah",
    "id": 7525042
  }
}
