{
  "geometry": {
    "type": "Point",
    "coordinates": [
      88.3333,
      22.95
    ]
  },
  "type": "Feature",
  "properties": {
    "hierarchy": [
      "tgn:1074804",
      "tgn:1000004",
      "tgn:7000198",
      "tgn:1001977",
      "tgn:7029392"
    ],
    "placetype": [
      "aat:300008347"
    ],
    "id": 1074804,
    "name:xx": "Bhoāgāchi"
  }
}
