{
  "type": "FeatureCollection",
  "features": [
    {
      "geometry": {
        "type": "Point",
        "coordinates": [
          -110.183333,
          29.183333
        ]
      },
      "type": "Feature",
      "properties": {
        "hierarchy": [
          "tgn:7372490",
          "tgn:1000001",
          "tgn:1001960",
          "tgn:7005560",
          "tgn:7029392"
        ],
        "placetype": [
          "aat:300000241"
        ],
        "id": 7372490,
        "name:xx": "Rancho La Junta"
      }
    },
    {
      "geometry": {
        "type": "Point",
        "coordinates": [
          -108.566667,
          29.166667
        ]
      },
      "type": "Feature",
      "properties": {
        "hierarchy": [
          "tgn:7372491",
          "tgn:7005581",
          "tgn:1000001",
          "tgn:7005560",
          "tgn:7029392"
        ],
        "placetype": [
          "aat:300000241"
        ],
        "id": 7372491,
        "name:xx": "Rancho La Junta"
      }
    },
    {
      "geometry": {
        "type": "Point",
        "coordinates": [
          -106,
          28.266667
        ]
      },
      "type": "Feature",
      "properties": {
        "hierarchy": [
          "tgn:7372492",
          "tgn:7005581",
          "tgn:1000001",
          "tgn:7005560",
          "tgn:7029392"
        ],
        "placetype": [
          "aat:300000241"
        ],
        "id": 7372492,
        "name:xx": "Rancho La Junta"
      }
    },
    {
      "geometry": {
        "type": "Point",
        "coordinates": [
          -108.466667,
          28.05
        ]
      },
      "type": "Feature",
      "properties": {
        "hierarchy": [
          "tgn:7372493",
          "tgn:7005581",
          "tgn:1000001",
          "tgn:7005560",
          "tgn:7029392"
        ],
        "placetype": [
          "aat:300000241"
        ],
        "id": 7372493,
        "name:xx": "Rancho La Junta"
      }
    },
    {
      "geometry": {
        "type": "Point",
        "coordinates": [
          -108.5,
          27.466667
        ]
      },
      "type": "Feature",
      "properties": {
        "hierarchy": [
          "tgn:7372494",
          "tgn:7005581",
          "tgn:1000001",
          "tgn:7005560",
          "tgn:7029392"
        ],
        "placetype": [
          "aat:300000241"
        ],
        "id": 7372494,
        "name:xx": "Rancho La Junta"
      }
    },
    {
      "geometry": {
        "type": "Point",
        "coordinates": [
          -100.333333,
          19.616667
        ]
      },
      "type": "Feature",
      "properties": {
        "hierarchy": [
          "tgn:7372495",
          "tgn:1000001",
          "tgn:7005590",
          "tgn:7005560",
          "tgn:7029392"
        ],
        "placetype": [
          "aat:300007783"
        ],
        "id": 7372495,
        "name:xx": "La Junta"
      }
    },
    {
      "geometry": {
        "type": "Point",
        "coordinates": [
          -110.266667,
          30.183333
        ]
      },
      "type": "Feature",
      "properties": {
        "hierarchy": [
          "tgn:7372496",
          "tgn:1000001",
          "tgn:1001960",
          "tgn:7005560",
          "tgn:7029392"
        ],
        "placetype": [
          "aat:300008347"
        ],
        "id": 7372496,
        "name:xx": "La Junta"
      }
    },
    {
      "geometry": {
        "type": "Point",
        "coordinates": [
          -109.633333,
          29.45
        ]
      },
      "type": "Feature",
      "properties": {
        "hierarchy": [
          "tgn:7372497",
          "tgn:1000001",
          "tgn:1001960",
          "tgn:7005560",
          "tgn:7029392"
        ],
        "placetype": [
          "aat:300008347"
        ],
        "id": 7372497,
        "name:xx": "La Junta"
      }
    },
    {
      "geometry": {
        "type": "Point",
        "coordinates": [
          -108.45,
          29.05
        ]
      },
      "type": "Feature",
      "properties": {
        "hierarchy": [
          "tgn:7372498",
          "tgn:7005581",
          "tgn:1000001",
          "tgn:7005560",
          "tgn:7029392"
        ],
        "placetype": [
          "aat:300008347"
        ],
        "id": 7372498,
        "name:xx": "La Junta"
      }
    },
    {
      "geometry": {
        "type": "Point",
        "coordinates": [
          -107.933333,
          28.933333
        ]
      },
      "type": "Feature",
      "properties": {
        "hierarchy": [
          "tgn:7372499",
          "tgn:7005581",
          "tgn:1000001",
          "tgn:7005560",
          "tgn:7029392"
        ],
        "placetype": [
          "aat:300008347"
        ],
        "id": 7372499,
        "name:xx": "La Junta"
      }
    }
  ]
}
