{
  "type": "FeatureCollection",
  "features": [
    {
      "geometry": {
        "type": "Point",
        "coordinates": [
          12.6,
          53.733333
        ]
      },
      "type": "Feature",
      "properties": {
        "hierarchy": [
          "tgn:7162910",
          "tgn:1000003",
          "tgn:7000094",
          "tgn:7000084",
          "tgn:7029392"
        ],
        "placetype": [
          "aat:300008777"
        ],
        "id": 7162910,
        "name:xx": "Hütte-Berge"
      }
    },
    {
      "geometry": {
        "type": "Point",
        "coordinates": [
          9.666667,
          51.516667
        ]
      },
      "type": "Feature",
      "properties": {
        "hierarchy": [
          "tgn:7162911",
          "tgn:1000003",
          "tgn:7003676",
          "tgn:7000084",
          "tgn:7029392"
        ],
        "placetype": [
          "aat:300132356"
        ],
        "id": 7162911,
        "name:xx": "Hütten-Berg"
      }
    },
    {
      "geometry": {
        "type": "Point",
        "coordinates": [
          12.65,
          48.2
        ]
      },
      "type": "Feature",
      "properties": {
        "hierarchy": [
          "tgn:7162912",
          "tgn:7003669",
          "tgn:1000003",
          "tgn:7000084",
          "tgn:7029392"
        ],
        "placetype": [
          "aat:300008347"
        ],
        "id": 7162912,
        "name:xx": "Hüttenberg"
      }
    },
    {
      "geometry": {
        "type": "Point",
        "coordinates": [
          10.25,
          47.516667
        ]
      },
      "type": "Feature",
      "properties": {
        "hierarchy": [
          "tgn:7162913",
          "tgn:7003669",
          "tgn:1000003",
          "tgn:7000084",
          "tgn:7029392"
        ],
        "placetype": [
          "aat:300008347"
        ],
        "id": 7162913,
        "name:xx": "Hüttenberg"
      }
    },
    {
      "geometry": {
        "type": "Point",
        "coordinates": [
          8.15,
          50.983333
        ]
      },
      "type": "Feature",
      "properties": {
        "hierarchy": [
          "tgn:7162914",
          "tgn:1000003",
          "tgn:7003677",
          "tgn:7000084",
          "tgn:7029392"
        ],
        "placetype": [
          "aat:300008795"
        ],
        "id": 7162914,
        "name:xx": "Hütten-Berg"
      }
    },
    {
      "geometry": {
        "type": "Point",
        "coordinates": [
          8.066667,
          49.316667
        ]
      },
      "type": "Feature",
      "properties": {
        "hierarchy": [
          "tgn:7162915",
          "tgn:1000003",
          "tgn:7003682",
          "tgn:7000084",
          "tgn:7029392"
        ],
        "placetype": [
          "aat:300008795"
        ],
        "id": 7162915,
        "name:xx": "Hüttenberg"
      }
    },
    {
      "geometry": {
        "type": "Point",
        "coordinates": [
          12.916667,
          53.533333
        ]
      },
      "type": "Feature",
      "properties": {
        "hierarchy": [
          "tgn:7162916",
          "tgn:1000003",
          "tgn:7000094",
          "tgn:7000084",
          "tgn:7029392"
        ],
        "placetype": [
          "aat:300008777"
        ],
        "id": 7162916,
        "name:xx": "Hütten-Berg"
      }
    },
    {
      "geometry": {
        "type": "Point",
        "coordinates": [
          13.516667,
          53.4
        ]
      },
      "type": "Feature",
      "properties": {
        "hierarchy": [
          "tgn:7162917",
          "tgn:1000003",
          "tgn:7000094",
          "tgn:7000084",
          "tgn:7029392"
        ],
        "placetype": [
          "aat:300008777"
        ],
        "id": 7162917,
        "name:xx": "Hütten-Berg"
      }
    },
    {
      "geometry": {
        "type": "Point",
        "coordinates": [
          9.416667,
          52.933333
        ]
      },
      "type": "Feature",
      "properties": {
        "hierarchy": [
          "tgn:7162918",
          "tgn:1000003",
          "tgn:7003676",
          "tgn:7000084",
          "tgn:7029392"
        ],
        "placetype": [
          "aat:300008777"
        ],
        "id": 7162918,
        "name:xx": "Hütten-Berg"
      }
    },
    {
      "geometry": {
        "type": "Point",
        "coordinates": [
          11.083333,
          52.766667
        ]
      },
      "type": "Feature",
      "properties": {
        "hierarchy": [
          "tgn:7162919",
          "tgn:1000003",
          "tgn:7003687",
          "tgn:7000084",
          "tgn:7029392"
        ],
        "placetype": [
          "aat:300008777"
        ],
        "id": 7162919,
        "name:xx": "Hütten-Berg"
      }
    }
  ]
}
