{
  "type": "FeatureCollection",
  "features": [
    {
      "geometry": {
        "type": "Point",
        "coordinates": [
          24.366667,
          37.583333
        ]
      },
      "type": "Feature",
      "properties": {
        "hierarchy": [
          "tgn:7218680",
          "tgn:7002681",
          "tgn:7001395",
          "tgn:1000003",
          "tgn:1000074",
          "tgn:7029392"
        ],
        "placetype": [
          "aat:300132316"
        ],
        "id": 7218680,
        "name:xx": "Vrísais, Órmos"
      }
    },
    {
      "geometry": {
        "type": "Point",
        "coordinates": [
          21.716667,
          37.25
        ]
      },
      "type": "Feature",
      "properties": {
        "hierarchy": [
          "tgn:7218681",
          "tgn:7011369",
          "tgn:7017076",
          "tgn:1000003",
          "tgn:1000074",
          "tgn:7029392"
        ],
        "placetype": [
          "aat:300008347"
        ],
        "id": 7218681,
        "name:xx": "Vrísai"
      }
    },
    {
      "geometry": {
        "type": "Point",
        "coordinates": [
          22.483333,
          36.7
        ]
      },
      "type": "Feature",
      "properties": {
        "hierarchy": [
          "tgn:7218682",
          "tgn:7002735",
          "tgn:7017076",
          "tgn:1000003",
          "tgn:1000074",
          "tgn:7029392"
        ],
        "placetype": [
          "aat:300008347"
        ],
        "id": 7218682,
        "name:xx": "Vrísai"
      }
    },
    {
      "geometry": {
        "type": "Point",
        "coordinates": [
          23.883333,
          35.5
        ]
      },
      "type": "Feature",
      "properties": {
        "hierarchy": [
          "tgn:7218683",
          "tgn:7002690",
          "tgn:7012056",
          "tgn:1000003",
          "tgn:1000074",
          "tgn:7029392"
        ],
        "placetype": [
          "aat:300008347"
        ],
        "id": 7218683,
        "name:xx": "Vrísai"
      }
    },
    {
      "geometry": {
        "type": "Point",
        "coordinates": [
          24.2,
          35.383333
        ]
      },
      "type": "Feature",
      "properties": {
        "hierarchy": [
          "tgn:7218684",
          "tgn:7002689",
          "tgn:7012056",
          "tgn:1000003",
          "tgn:1000074",
          "tgn:7029392"
        ],
        "placetype": [
          "aat:300008347"
        ],
        "id": 7218684,
        "name:xx": "Vrýsai"
      }
    },
    {
      "geometry": {
        "type": "Point",
        "coordinates": [
          25.616667,
          35.233333
        ]
      },
      "type": "Feature",
      "properties": {
        "hierarchy": [
          "tgn:7218686",
          "tgn:7002692",
          "tgn:7012056",
          "tgn:1000003",
          "tgn:1000074",
          "tgn:7029392"
        ],
        "placetype": [
          "aat:300008347"
        ],
        "id": 7218686,
        "name:xx": "Vrísai"
      }
    },
    {
      "geometry": {
        "type": "Point",
        "coordinates": [
          24.583333,
          35.166667
        ]
      },
      "type": "Feature",
      "properties": {
        "hierarchy": [
          "tgn:7218687",
          "tgn:7002690",
          "tgn:7012056",
          "tgn:1000003",
          "tgn:1000074",
          "tgn:7029392"
        ],
        "placetype": [
          "aat:300008347"
        ],
        "id": 7218687,
        "name:xx": "Vrísai"
      }
    },
    {
      "geometry": {
        "type": "Point",
        "coordinates": [
          26.201111,
          39.039444
        ]
      },
      "type": "Feature",
      "properties": {
        "hierarchy": [
          "tgn:7218689",
          "tgn:7011163",
          "tgn:7002674",
          "tgn:1000003",
          "tgn:1000074",
          "tgn:7029392"
        ],
        "placetype": [
          "aat:300008347"
        ],
        "id": 7218689,
        "name:xx": "Vrísa"
      }
    }
  ]
}
