{
  "geometry": {
    "type": "Point",
    "coordinates": [
      -120.5833,
      48.4833
    ]
  },
  "type": "Feature",
  "properties": {
    "hierarchy": [
      "tgn:2548348",
      "tgn:1000001",
      "tgn:7012149",
      "tgn:1002742",
      "tgn:7007920",
      "tgn:7029392"
    ],
    "placetype": [
      "aat:300008680"
    ],
    "id": 2548348,
    "name:xx": "North Lake"
  }
}
