{
  "geometry": {
    "type": "Point",
    "coordinates": [
      -115.8167,
      47.6333
    ]
  },
  "type": "Feature",
  "properties": {
    "hierarchy": [
      "tgn:2757225",
      "tgn:1000001",
      "tgn:7012149",
      "tgn:2000491",
      "tgn:7007250",
      "tgn:7029392"
    ],
    "placetype": [
      "aat:300008761"
    ],
    "id": 2757225,
    "name:xx": "Wesp Gulch"
  }
}
