{
  "geometry": {
    "type": "Point",
    "coordinates": [
      46.5833,
      -21.1667
    ]
  },
  "type": "Feature",
  "properties": {
    "hierarchy": [
      "tgn:1090905",
      "tgn:7001242",
      "tgn:7000556",
      "tgn:1000173",
      "tgn:7029392"
    ],
    "placetype": [
      "aat:300008347"
    ],
    "id": 1090905,
    "name:xx": "Ikalamavony"
  }
}
