{
  "geometry": {
    "type": "Point",
    "coordinates": [
      30.7833,
      53.1333
    ]
  },
  "type": "Feature",
  "properties": {
    "hierarchy": [
      "tgn:1137706",
      "tgn:7012187",
      "tgn:1000003",
      "tgn:7006657",
      "tgn:7029392"
    ],
    "placetype": [
      "aat:300008347",
      "aat:300008375"
    ],
    "id": 1137706,
    "name:xx": "Korma"
  }
}
