{
  "geometry": {
    "type": "Point",
    "coordinates": [
      -82.4667,
      29.7833
    ]
  },
  "type": "Feature",
  "properties": {
    "hierarchy": [
      "tgn:2208477",
      "tgn:2000256",
      "tgn:1000001",
      "tgn:7012149",
      "tgn:7007240",
      "tgn:7029392"
    ],
    "placetype": [
      "aat:300008680"
    ],
    "id": 2208477,
    "name:xx": "Burnetts Lake"
  }
}
