{
  "geometry": {
    "type": "Point",
    "coordinates": [
      75.164466,
      18.259358
    ]
  },
  "type": "Feature",
  "properties": {
    "hierarchy": [
      "tgn:7572047",
      "tgn:1000004",
      "tgn:7000198",
      "tgn:1001895",
      "tgn:7029392"
    ],
    "placetype": [
      "aat:300008347"
    ],
    "name:en": "Jeūr",
    "id": 7572047
  }
}
