{
  "geometry": {
    "type": "Point",
    "coordinates": [
      -83.2333,
      36.65
    ]
  },
  "type": "Feature",
  "properties": {
    "hierarchy": [
      "tgn:2255478",
      "tgn:1000001",
      "tgn:7012149",
      "tgn:2002169",
      "tgn:7007919",
      "tgn:7029392"
    ],
    "placetype": [
      "aat:300008746"
    ],
    "id": 2255478,
    "name:xx": "Cope Cave"
  }
}
