{
  "geometry": {
    "type": "Point",
    "coordinates": [
      -89.9667,
      34.75
    ]
  },
  "type": "Feature",
  "properties": {
    "hierarchy": [
      "tgn:2056860",
      "tgn:1000001",
      "tgn:2001102",
      "tgn:7012149",
      "tgn:7007522",
      "tgn:7029392"
    ],
    "placetype": [
      "aat:300008347",
      "aat:300387210"
    ],
    "id": 2056860,
    "name:xx": "Love"
  }
}
