{
  "geometry": {
    "type": "Point",
    "coordinates": [
      -120.9333,
      39.0167
    ]
  },
  "type": "Feature",
  "properties": {
    "hierarchy": [
      "tgn:2177004",
      "tgn:1000001",
      "tgn:7012149",
      "tgn:7007157",
      "tgn:1002791",
      "tgn:7029392"
    ],
    "placetype": [
      "aat:300000390"
    ],
    "id": 2177004,
    "name:xx": "Black Oak Mine"
  }
}
