{
  "geometry": {
    "type": "Point",
    "coordinates": [
      -72.7333,
      43.5333
    ]
  },
  "type": "Feature",
  "properties": {
    "hierarchy": [
      "tgn:2631619",
      "tgn:1000001",
      "tgn:2002136",
      "tgn:7012149",
      "tgn:7007828",
      "tgn:7029392"
    ],
    "placetype": [
      "aat:300055621"
    ],
    "id": 2631619,
    "name:xx": "Round Top Mountain Ski Area"
  }
}
