{
  "type": "FeatureCollection",
  "features": [
    {
      "geometry": {
        "type": "Point",
        "coordinates": [
          6.9833,
          51.5333
        ]
      },
      "type": "Feature",
      "properties": {
        "hierarchy": [
          "tgn:1005890",
          "tgn:1000003",
          "tgn:7003677",
          "tgn:7000084",
          "tgn:7004945",
          "tgn:7029392"
        ],
        "placetype": [
          "aat:300000745",
          "aat:300387332"
        ],
        "id": 1005890,
        "name:xx": "Welheim"
      }
    },
    {
      "geometry": {
        "type": "Point",
        "coordinates": [
          0.1167,
          51.4667
        ]
      },
      "type": "Feature",
      "properties": {
        "hierarchy": [
          "tgn:1005891",
          "tgn:7018908",
          "tgn:7002445",
          "tgn:1000003",
          "tgn:7008136",
          "tgn:7008591",
          "tgn:7029392"
        ],
        "placetype": [
          "aat:300008347",
          "aat:300000745"
        ],
        "name:en": "Welling",
        "id": 1005891
      }
    },
    {
      "geometry": {
        "type": "Point",
        "coordinates": [
          7.4833,
          51.4667
        ]
      },
      "type": "Feature",
      "properties": {
        "hierarchy": [
          "tgn:1005892",
          "tgn:1000003",
          "tgn:7003677",
          "tgn:7000084",
          "tgn:7004982",
          "tgn:7029392"
        ],
        "placetype": [
          "aat:300000745",
          "aat:300387332"
        ],
        "id": 1005892,
        "name:xx": "Wellinghofen"
      }
    },
    {
      "geometry": {
        "type": "Point",
        "coordinates": [
          0.2167,
          51.5
        ]
      },
      "type": "Feature",
      "properties": {
        "hierarchy": [
          "tgn:1005894",
          "tgn:7002445",
          "tgn:7018919",
          "tgn:1000003",
          "tgn:7008136",
          "tgn:7008591",
          "tgn:7029392"
        ],
        "placetype": [
          "aat:300000745"
        ],
        "id": 1005894,
        "name:xx": "Wennington"
      }
    },
    {
      "geometry": {
        "type": "Point",
        "coordinates": [
          7.3,
          51.483333
        ]
      },
      "type": "Feature",
      "properties": {
        "hierarchy": [
          "tgn:1005896",
          "tgn:1000003",
          "tgn:7003677",
          "tgn:7000084",
          "tgn:7004904",
          "tgn:7029392"
        ],
        "placetype": [
          "aat:300000745",
          "aat:300387332"
        ],
        "id": 1005896,
        "name:xx": "Werne"
      }
    },
    {
      "geometry": {
        "type": "Point",
        "coordinates": [
          6.816667,
          51.183333
        ]
      },
      "type": "Feature",
      "properties": {
        "hierarchy": [
          "tgn:1005897",
          "tgn:1000003",
          "tgn:7003677",
          "tgn:7000084",
          "tgn:7004443",
          "tgn:7029392"
        ],
        "placetype": [
          "aat:300000745",
          "aat:300387332"
        ],
        "id": 1005897,
        "name:xx": "Wersten"
      }
    },
    {
      "geometry": {
        "type": "Point",
        "coordinates": [
          -2.9,
          53.4333
        ]
      },
      "type": "Feature",
      "properties": {
        "hierarchy": [
          "tgn:1005898",
          "tgn:1003614",
          "tgn:7002445",
          "tgn:7010597",
          "tgn:1000003",
          "tgn:7029504",
          "tgn:7008591",
          "tgn:7029392"
        ],
        "placetype": [
          "aat:300000745"
        ],
        "id": 1005898,
        "name:xx": "West Derby"
      }
    },
    {
      "geometry": {
        "type": "Point",
        "coordinates": [
          -0.4667,
          51.5
        ]
      },
      "type": "Feature",
      "properties": {
        "hierarchy": [
          "tgn:1005899",
          "tgn:7002445",
          "tgn:7018920",
          "tgn:1000003",
          "tgn:7008136",
          "tgn:7008591",
          "tgn:7029392"
        ],
        "placetype": [
          "aat:300008347",
          "aat:300000745",
          "aat:300008372"
        ],
        "id": 1005899,
        "name:xx": "West Drayton"
      }
    }
  ]
}
