{
  "geometry": {
    "type": "Point",
    "coordinates": [
      -66.4167,
      54.6667
    ]
  },
  "type": "Feature",
  "properties": {
    "hierarchy": [
      "tgn:1117719",
      "tgn:7005685",
      "tgn:1000001",
      "tgn:7005801",
      "tgn:7029392"
    ],
    "placetype": [
      "aat:300008680"
    ],
    "id": 1117719,
    "name:xx": "Petitsikapau Lake"
  }
}
