{
  "geometry": {
    "type": "Point",
    "coordinates": [
      -88.2167,
      45.0333
    ]
  },
  "type": "Feature",
  "properties": {
    "hierarchy": [
      "tgn:2363718",
      "tgn:1000001",
      "tgn:7012149",
      "tgn:2002341",
      "tgn:7007922",
      "tgn:7029392"
    ],
    "placetype": [
      "aat:300008791"
    ],
    "id": 2363718,
    "name:xx": "Green Island"
  }
}
