{
  "geometry": {
    "type": "Point",
    "coordinates": [
      -101.4833,
      48.55
    ]
  },
  "type": "Feature",
  "properties": {
    "hierarchy": [
      "tgn:1133126",
      "tgn:1000001",
      "tgn:7012149",
      "tgn:7007705",
      "tgn:7029392"
    ],
    "placetype": [
      "aat:300008706"
    ],
    "id": 1133126,
    "name:xx": "Egg Creek"
  }
}
