{
  "geometry": {
    "type": "Point",
    "coordinates": [
      -86.1167,
      39.8333
    ]
  },
  "type": "Feature",
  "properties": {
    "hierarchy": [
      "tgn:2378559",
      "tgn:1000001",
      "tgn:7012149",
      "tgn:1002633",
      "tgn:7007252",
      "tgn:7029392"
    ],
    "placetype": [
      "aat:300008347"
    ],
    "id": 2378559,
    "name:xx": "Harrison Place"
  }
}
