{
  "geometry": {
    "type": "Point",
    "coordinates": [
      -132.4833,
      55.3833
    ]
  },
  "type": "Feature",
  "properties": {
    "hierarchy": [
      "tgn:2006322",
      "tgn:7006450",
      "tgn:1000001",
      "tgn:7012149",
      "tgn:2000082",
      "tgn:7029392"
    ],
    "placetype": [
      "aat:300387016"
    ],
    "id": 2006322,
    "name:xx": "Polk Inlet"
  }
}
