{
  "geometry": {
    "type": "Point",
    "coordinates": [
      15.5667,
      53.2833
    ]
  },
  "type": "Feature",
  "properties": {
    "hierarchy": [
      "tgn:1049414",
      "tgn:1000003",
      "tgn:7024114",
      "tgn:7006366",
      "tgn:7029392"
    ],
    "placetype": [
      "aat:300008347"
    ],
    "id": 1049414,
    "name:xx": "Recz"
  }
}
