{
  "geometry": {
    "type": "Point",
    "coordinates": [
      35.4667,
      30.0167
    ]
  },
  "type": "Feature",
  "properties": {
    "hierarchy": [
      "tgn:1107043",
      "tgn:1000004",
      "tgn:1000121",
      "tgn:1002092",
      "tgn:7029392"
    ],
    "placetype": [
      "aat:300008795"
    ],
    "id": 1107043,
    "name:xx": "Yamām, Jabal al-"
  }
}
