{
  "geometry": {
    "type": "Point",
    "coordinates": [
      -122.4333,
      37.7667
    ]
  },
  "type": "Feature",
  "properties": {
    "hierarchy": [
      "tgn:2131755",
      "tgn:1000001",
      "tgn:7012149",
      "tgn:7007157",
      "tgn:1002859",
      "tgn:7029392"
    ],
    "placetype": [
      "aat:300008347"
    ],
    "id": 2131755,
    "name:xx": "Amanico Ergina Village"
  }
}
