{
  "type": "FeatureCollection",
  "features": [
    {
      "geometry": {
        "type": "Point",
        "coordinates": [
          -154.0333,
          57.65
        ]
      },
      "type": "Feature",
      "properties": {
        "hierarchy": [
          "tgn:2154930",
          "tgn:7006450",
          "tgn:1000001",
          "tgn:2124012",
          "tgn:7012149",
          "tgn:7029392"
        ],
        "placetype": [
          "aat:300008791"
        ],
        "id": 2154930,
        "name:xx": "Bear Island"
      }
    },
    {
      "geometry": {
        "type": "Point",
        "coordinates": [
          -138.4333,
          59.15
        ]
      },
      "type": "Feature",
      "properties": {
        "hierarchy": [
          "tgn:2154931",
          "tgn:7006450",
          "tgn:1000001",
          "tgn:7012149",
          "tgn:7030574",
          "tgn:7029392"
        ],
        "placetype": [
          "aat:300008791"
        ],
        "id": 2154931,
        "name:xx": "Bear Island"
      }
    },
    {
      "geometry": {
        "type": "Point",
        "coordinates": [
          -155.3167,
          59.2
        ]
      },
      "type": "Feature",
      "properties": {
        "hierarchy": [
          "tgn:2154932",
          "tgn:7006450",
          "tgn:1000001",
          "tgn:7030517",
          "tgn:7012149",
          "tgn:7029392"
        ],
        "placetype": [
          "aat:300008791"
        ],
        "id": 2154932,
        "name:xx": "Bear Island"
      }
    },
    {
      "geometry": {
        "type": "Point",
        "coordinates": [
          -151.05,
          59.7167
        ]
      },
      "type": "Feature",
      "properties": {
        "hierarchy": [
          "tgn:2154933",
          "tgn:7006450",
          "tgn:1000001",
          "tgn:7019698",
          "tgn:7012149",
          "tgn:7029392"
        ],
        "placetype": [
          "aat:300008791"
        ],
        "id": 2154933,
        "name:xx": "Bear Island"
      }
    },
    {
      "geometry": {
        "type": "Point",
        "coordinates": [
          -142.4333,
          61.1
        ]
      },
      "type": "Feature",
      "properties": {
        "hierarchy": [
          "tgn:2154934",
          "tgn:7006450",
          "tgn:1000001",
          "tgn:7012149",
          "tgn:2000086",
          "tgn:7029392"
        ],
        "placetype": [
          "aat:300008791"
        ],
        "id": 2154934,
        "name:xx": "Bear Island"
      }
    },
    {
      "geometry": {
        "type": "Point",
        "coordinates": [
          -155.35,
          66.7333
        ]
      },
      "type": "Feature",
      "properties": {
        "hierarchy": [
          "tgn:2154935",
          "tgn:7006450",
          "tgn:1000001",
          "tgn:7012149",
          "tgn:2124014",
          "tgn:7029392"
        ],
        "placetype": [
          "aat:300008791"
        ],
        "id": 2154935,
        "name:xx": "Bear Island"
      }
    },
    {
      "geometry": {
        "type": "Point",
        "coordinates": [
          -90.2333,
          36.1667
        ]
      },
      "type": "Feature",
      "properties": {
        "hierarchy": [
          "tgn:2154936",
          "tgn:1000001",
          "tgn:7016172",
          "tgn:7012149",
          "tgn:2000132",
          "tgn:7029392"
        ],
        "placetype": [
          "aat:300008791"
        ],
        "id": 2154936,
        "name:xx": "Bear Island"
      }
    },
    {
      "geometry": {
        "type": "Point",
        "coordinates": [
          -72.7333,
          41.25
        ]
      },
      "type": "Feature",
      "properties": {
        "hierarchy": [
          "tgn:2154937",
          "tgn:1000001",
          "tgn:1002712",
          "tgn:7012149",
          "tgn:7007159",
          "tgn:7029392"
        ],
        "placetype": [
          "aat:300008791"
        ],
        "id": 2154937,
        "name:xx": "Bear Island"
      }
    },
    {
      "geometry": {
        "type": "Point",
        "coordinates": [
          -81.25,
          26.2167
        ]
      },
      "type": "Feature",
      "properties": {
        "hierarchy": [
          "tgn:2154938",
          "tgn:1000001",
          "tgn:1002289",
          "tgn:7012149",
          "tgn:7007240",
          "tgn:7029392"
        ],
        "placetype": [
          "aat:300008791"
        ],
        "id": 2154938,
        "name:xx": "Bear Island"
      }
    },
    {
      "geometry": {
        "type": "Point",
        "coordinates": [
          -80.7833,
          27.5333
        ]
      },
      "type": "Feature",
      "properties": {
        "hierarchy": [
          "tgn:2154939",
          "tgn:1000001",
          "tgn:7012149",
          "tgn:1002743",
          "tgn:7007240",
          "tgn:7029392"
        ],
        "placetype": [
          "aat:300008791"
        ],
        "id": 2154939,
        "name:xx": "Bear Island"
      }
    }
  ]
}
