{
  "type": "FeatureCollection",
  "features": [
    {
      "geometry": {
        "type": "Point",
        "coordinates": [
          31.55,
          48.3167
        ]
      },
      "type": "Feature",
      "properties": {
        "hierarchy": [
          "tgn:1057790",
          "tgn:1000003",
          "tgn:7011662",
          "tgn:7006660",
          "tgn:7029392"
        ],
        "placetype": [
          "aat:300008347"
        ],
        "id": 1057790,
        "name:xx": "Novoukrainka"
      }
    },
    {
      "geometry": {
        "type": "Point",
        "coordinates": [
          48.45,
          54.1667
        ]
      },
      "type": "Feature",
      "properties": {
        "hierarchy": [
          "tgn:1057791",
          "tgn:1000004",
          "tgn:7011609",
          "tgn:7018214",
          "tgn:7002435",
          "tgn:7029392"
        ],
        "placetype": [
          "aat:300008347"
        ],
        "id": 1057791,
        "name:xx": "Novoulyanovsk"
      }
    },
    {
      "geometry": {
        "type": "Point",
        "coordinates": [
          57.25,
          51.25
        ]
      },
      "type": "Feature",
      "properties": {
        "hierarchy": [
          "tgn:1057792",
          "tgn:1000004",
          "tgn:1003398",
          "tgn:7018214",
          "tgn:7002435",
          "tgn:7029392"
        ],
        "placetype": [
          "aat:300008347"
        ],
        "id": 1057792,
        "name:xx": "Novouralsk"
      }
    },
    {
      "geometry": {
        "type": "Point",
        "coordinates": [
          49.6667,
          58.5
        ]
      },
      "type": "Feature",
      "properties": {
        "hierarchy": [
          "tgn:1057794",
          "tgn:1000004",
          "tgn:1003379",
          "tgn:7018214",
          "tgn:7002435",
          "tgn:7029392"
        ],
        "placetype": [
          "aat:300008347"
        ],
        "id": 1057794,
        "name:xx": "Novo-Vyatsk"
      }
    },
    {
      "geometry": {
        "type": "Point",
        "coordinates": [
          42.1667,
          56.2
        ]
      },
      "type": "Feature",
      "properties": {
        "hierarchy": [
          "tgn:1057795",
          "tgn:1000004",
          "tgn:1003421",
          "tgn:7018214",
          "tgn:7002435",
          "tgn:7029392"
        ],
        "placetype": [
          "aat:300008347"
        ],
        "id": 1057795,
        "name:xx": "Novovyazniki"
      }
    },
    {
      "geometry": {
        "type": "Point",
        "coordinates": [
          74.6833,
          54.2
        ]
      },
      "type": "Feature",
      "properties": {
        "hierarchy": [
          "tgn:1057796",
          "tgn:1000004",
          "tgn:6004412",
          "tgn:7018214",
          "tgn:7002435",
          "tgn:7029392"
        ],
        "placetype": [
          "aat:300008347"
        ],
        "id": 1057796,
        "name:xx": "Novovarshavka"
      }
    },
    {
      "geometry": {
        "type": "Point",
        "coordinates": [
          35.7333,
          46.8
        ]
      },
      "type": "Feature",
      "properties": {
        "hierarchy": [
          "tgn:1057797",
          "tgn:1000003",
          "tgn:7011670",
          "tgn:7006660",
          "tgn:7029392"
        ],
        "placetype": [
          "aat:300008347",
          "aat:300008375"
        ],
        "id": 1057797,
        "name:xx": "Novovasylivka"
      }
    },
    {
      "geometry": {
        "type": "Point",
        "coordinates": [
          24.0833,
          50.8333
        ]
      },
      "type": "Feature",
      "properties": {
        "hierarchy": [
          "tgn:1057798",
          "tgn:1000003",
          "tgn:1003422",
          "tgn:7006660",
          "tgn:7029392"
        ],
        "placetype": [
          "aat:300008347"
        ],
        "id": 1057798,
        "name:xx": "Novovolyns'k"
      }
    },
    {
      "geometry": {
        "type": "Point",
        "coordinates": [
          33.9,
          47.4833
        ]
      },
      "type": "Feature",
      "properties": {
        "hierarchy": [
          "tgn:1057799",
          "tgn:7011651",
          "tgn:1000003",
          "tgn:7006660",
          "tgn:7029392"
        ],
        "placetype": [
          "aat:300008347"
        ],
        "id": 1057799,
        "name:xx": "Novovoroncovka"
      }
    }
  ]
}
