{
  "geometry": {
    "type": "Point",
    "coordinates": [
      74.23006,
      33.174028
    ]
  },
  "type": "Feature",
  "properties": {
    "hierarchy": [
      "tgn:7591907",
      "tgn:1000004",
      "tgn:7000198",
      "tgn:7000799",
      "tgn:7029392"
    ],
    "placetype": [
      "aat:300008347"
    ],
    "name:en": "Daliāri",
    "id": 7591907
  }
}
