{
  "geometry": {
    "type": "Point",
    "coordinates": [
      -119.9667,
      44.1333
    ]
  },
  "type": "Feature",
  "properties": {
    "hierarchy": [
      "tgn:2783891",
      "tgn:1000001",
      "tgn:2001703",
      "tgn:7012149",
      "tgn:7007708",
      "tgn:7029392"
    ],
    "placetype": [
      "aat:300266640"
    ],
    "id": 2783891,
    "name:xx": "X X Ridge"
  }
}
