{
  "type": "FeatureCollection",
  "features": [
    {
      "geometry": {
        "type": "Point",
        "coordinates": [
          -1.683333,
          55.016667
        ]
      },
      "type": "Feature",
      "properties": {
        "hierarchy": [
          "tgn:7444790",
          "tgn:7019073",
          "tgn:7002445",
          "tgn:1000003",
          "tgn:7012033",
          "tgn:7008591",
          "tgn:7029392"
        ],
        "placetype": [
          "aat:300387502"
        ],
        "name:en": "Woolsington Hall",
        "id": 7444790
      }
    },
    {
      "geometry": {
        "type": "Point",
        "coordinates": [
          0.566667,
          53.05
        ]
      },
      "type": "Feature",
      "properties": {
        "hierarchy": [
          "tgn:7444792",
          "tgn:7002445",
          "tgn:1000003",
          "tgn:7008160",
          "tgn:7008591",
          "tgn:7029392"
        ],
        "placetype": [
          "aat:300387036"
        ],
        "name:en": "Woolpack",
        "id": 7444792
      }
    },
    {
      "geometry": {
        "type": "Point",
        "coordinates": [
          1.2,
          51.416667
        ]
      },
      "type": "Feature",
      "properties": {
        "hierarchy": [
          "tgn:7444793",
          "tgn:7002445",
          "tgn:1000003",
          "tgn:7008153",
          "tgn:7008591",
          "tgn:7029392"
        ],
        "placetype": [
          "aat:300387036"
        ],
        "name:en": "Woolpack",
        "id": 7444793
      }
    },
    {
      "geometry": {
        "type": "Point",
        "coordinates": [
          -4.133333,
          55.6
        ]
      },
      "type": "Feature",
      "properties": {
        "hierarchy": [
          "tgn:7444795",
          "tgn:7002444",
          "tgn:1000003",
          "tgn:7019090",
          "tgn:7008591",
          "tgn:7029392"
        ],
        "placetype": [
          "aat:300008699"
        ],
        "name:en": "Woollen Burn",
        "id": 7444795
      }
    },
    {
      "geometry": {
        "type": "Point",
        "coordinates": [
          -4.662222,
          51.658611
        ]
      },
      "type": "Feature",
      "properties": {
        "hierarchy": [
          "tgn:7444797",
          "tgn:7002443",
          "tgn:1000003",
          "tgn:7018993",
          "tgn:7008591",
          "tgn:7029392"
        ],
        "placetype": [
          "aat:300008808"
        ],
        "name:en": "Woolhouse Rocks",
        "id": 7444797
      }
    }
  ]
}
