{
  "geometry": {
    "type": "Point",
    "coordinates": [
      -104.2833,
      32.4167
    ]
  },
  "type": "Feature",
  "properties": {
    "hierarchy": [
      "tgn:2370669",
      "tgn:1000001",
      "tgn:2001436",
      "tgn:7012149",
      "tgn:7007566",
      "tgn:7029392"
    ],
    "placetype": [
      "aat:300055621"
    ],
    "id": 2370669,
    "name:xx": "Hackberry Slope"
  }
}
