{
  "geometry": {
    "type": "Point",
    "coordinates": [
      -78.8833,
      37.9667
    ]
  },
  "type": "Feature",
  "properties": {
    "hierarchy": [
      "tgn:2289838",
      "tgn:1000001",
      "tgn:7012149",
      "tgn:2002175",
      "tgn:7007919",
      "tgn:7029392"
    ],
    "placetype": [
      "aat:300008798"
    ],
    "id": 2289838,
    "name:xx": "Dobie Mountain"
  }
}
