{
  "geometry": {
    "type": "Point",
    "coordinates": [
      4.983333,
      52.65
    ]
  },
  "type": "Feature",
  "properties": {
    "hierarchy": [
      "tgn:7273241",
      "tgn:1000003",
      "tgn:7006951",
      "tgn:7016845",
      "tgn:7029392"
    ],
    "placetype": [
      "aat:300006163"
    ],
    "name:nl": "Westerkogge, Polder de",
    "id": 7273241
  }
}
