{
  "geometry": {
    "type": "Point",
    "coordinates": [
      29.783333,
      31.15
    ]
  },
  "type": "Feature",
  "properties": {
    "hierarchy": [
      "tgn:7521382",
      "tgn:7001242",
      "tgn:7016833",
      "tgn:1001079",
      "tgn:7029392"
    ],
    "placetype": [
      "aat:300008791"
    ],
    "name:en": "Akrāsh, Jazīrat al",
    "id": 7521382
  }
}
