{
  "geometry": {
    "type": "Point",
    "coordinates": [
      -92.65,
      32.8167
    ]
  },
  "type": "Feature",
  "properties": {
    "hierarchy": [
      "tgn:2205442",
      "tgn:1000001",
      "tgn:7012149",
      "tgn:2000909",
      "tgn:7007256",
      "tgn:7029392"
    ],
    "placetype": [
      "aat:300008706"
    ],
    "id": 2205442,
    "name:xx": "Bull Creek"
  }
}
