{
  "type": "FeatureCollection",
  "features": [
    {
      "geometry": {
        "type": "Point",
        "coordinates": [
          -71.583333,
          -38.1
        ]
      },
      "type": "Feature",
      "properties": {
        "hierarchy": [
          "tgn:7321210",
          "tgn:1001637",
          "tgn:1000049",
          "tgn:1000002",
          "tgn:7029392"
        ],
        "placetype": [
          "aat:300008795"
        ],
        "id": 7321210,
        "name:xx": "Campamento, Cerro"
      }
    },
    {
      "geometry": {
        "type": "Point",
        "coordinates": [
          -73.166667,
          -38
        ]
      },
      "type": "Feature",
      "properties": {
        "hierarchy": [
          "tgn:7321211",
          "tgn:1001692",
          "tgn:1000049",
          "tgn:1000002",
          "tgn:7029392"
        ],
        "placetype": [
          "aat:300008795"
        ],
        "id": 7321211,
        "name:xx": "Campamento, Cerro"
      }
    },
    {
      "geometry": {
        "type": "Point",
        "coordinates": [
          -71.216667,
          -37.666667
        ]
      },
      "type": "Feature",
      "properties": {
        "hierarchy": [
          "tgn:7321212",
          "tgn:1001637",
          "tgn:1000049",
          "tgn:1000002",
          "tgn:7029392"
        ],
        "placetype": [
          "aat:300008795"
        ],
        "id": 7321212,
        "name:xx": "Campamento, Cerro"
      }
    },
    {
      "geometry": {
        "type": "Point",
        "coordinates": [
          -69.966667,
          -20.266667
        ]
      },
      "type": "Feature",
      "properties": {
        "hierarchy": [
          "tgn:7321213",
          "tgn:7002464",
          "tgn:1000049",
          "tgn:1000002",
          "tgn:7029392"
        ],
        "placetype": [
          "aat:300008795"
        ],
        "id": 7321213,
        "name:xx": "Campamento, Cerro"
      }
    },
    {
      "geometry": {
        "type": "Point",
        "coordinates": [
          -74.216667,
          -45.683333
        ]
      },
      "type": "Feature",
      "properties": {
        "hierarchy": [
          "tgn:7321214",
          "tgn:1001623",
          "tgn:1000049",
          "tgn:1000002",
          "tgn:7029392"
        ],
        "placetype": [
          "aat:300132317"
        ],
        "id": 7321214,
        "name:xx": "Campamento, Caleta"
      }
    },
    {
      "geometry": {
        "type": "Point",
        "coordinates": [
          -69.666667,
          -25.233333
        ]
      },
      "type": "Feature",
      "properties": {
        "hierarchy": [
          "tgn:7321215",
          "tgn:7016598",
          "tgn:1000049",
          "tgn:1000002",
          "tgn:7029392"
        ],
        "placetype": [
          "aat:300387033"
        ],
        "id": 7321215,
        "name:xx": "Campamento"
      }
    },
    {
      "geometry": {
        "type": "Point",
        "coordinates": [
          -69.216667,
          -24.483333
        ]
      },
      "type": "Feature",
      "properties": {
        "hierarchy": [
          "tgn:7321216",
          "tgn:7016598",
          "tgn:1000049",
          "tgn:1000002",
          "tgn:7029392"
        ],
        "placetype": [
          "aat:300387033"
        ],
        "id": 7321216,
        "name:xx": "Campamento"
      }
    },
    {
      "geometry": {
        "type": "Point",
        "coordinates": [
          -69.25,
          -19.9
        ]
      },
      "type": "Feature",
      "properties": {
        "hierarchy": [
          "tgn:7321217",
          "tgn:7002464",
          "tgn:1000049",
          "tgn:1000002",
          "tgn:7029392"
        ],
        "placetype": [
          "aat:300008795"
        ],
        "id": 7321217,
        "name:xx": "Campahue, Morro"
      }
    },
    {
      "geometry": {
        "type": "Point",
        "coordinates": [
          -69.233333,
          -19.883333
        ]
      },
      "type": "Feature",
      "properties": {
        "hierarchy": [
          "tgn:7321218",
          "tgn:7002464",
          "tgn:1000049",
          "tgn:1000002",
          "tgn:7029392"
        ],
        "placetype": [
          "aat:300387033"
        ],
        "id": 7321218,
        "name:xx": "Campahue"
      }
    },
    {
      "geometry": {
        "type": "Point",
        "coordinates": [
          -71.066667,
          -54.35
        ]
      },
      "type": "Feature",
      "properties": {
        "hierarchy": [
          "tgn:7321219",
          "tgn:1001702",
          "tgn:1000049",
          "tgn:1000002",
          "tgn:7029392"
        ],
        "placetype": [
          "aat:300386846"
        ],
        "id": 7321219,
        "name:xx": "Camote, Punta"
      }
    }
  ]
}
