{
  "geometry": {
    "type": "Point",
    "coordinates": [
      -79.9667,
      39.0667
    ]
  },
  "type": "Feature",
  "properties": {
    "hierarchy": [
      "tgn:2528348",
      "tgn:2002253",
      "tgn:1000001",
      "tgn:7012149",
      "tgn:7013961",
      "tgn:7029392"
    ],
    "placetype": [
      "aat:300008699"
    ],
    "id": 2528348,
    "name:xx": "Mouse Run"
  }
}
