{
  "geometry": {
    "type": "Point",
    "coordinates": [
      -81.8833,
      36.8833
    ]
  },
  "type": "Feature",
  "properties": {
    "hierarchy": [
      "tgn:2203372",
      "tgn:1000001",
      "tgn:7012149",
      "tgn:7007919",
      "tgn:7029392"
    ],
    "placetype": [
      "aat:300266640"
    ],
    "id": 2203372,
    "name:xx": "Buckhorn Ridge"
  }
}
