{
  "geometry": {
    "type": "Point",
    "coordinates": [
      -81.9167,
      36.1833
    ]
  },
  "type": "Feature",
  "properties": {
    "hierarchy": [
      "tgn:2666854",
      "tgn:2001468",
      "tgn:1000001",
      "tgn:7012149",
      "tgn:7007709",
      "tgn:7029392"
    ],
    "placetype": [
      "aat:300008699"
    ],
    "id": 2666854,
    "name:xx": "Skalley Branch"
  }
}
