{
  "geometry": {
    "type": "Point",
    "coordinates": [
      79.712966,
      27.730178
    ]
  },
  "type": "Feature",
  "properties": {
    "hierarchy": [
      "tgn:7559788",
      "tgn:1000004",
      "tgn:7000198",
      "tgn:7016722",
      "tgn:7029392"
    ],
    "placetype": [
      "aat:300008347"
    ],
    "name:en": "Machhriyāi",
    "id": 7559788
  }
}
