{
  "geometry": {
    "type": "Point",
    "coordinates": [
      -76.6833,
      39.35
    ]
  },
  "type": "Feature",
  "properties": {
    "hierarchy": [
      "tgn:2235910",
      "tgn:7021987",
      "tgn:1000001",
      "tgn:7012149",
      "tgn:7007516",
      "tgn:7029392"
    ],
    "placetype": [
      "aat:300008347"
    ],
    "id": 2235910,
    "name:xx": "Cheswolde"
  }
}
