{
  "geometry": {
    "type": "Point",
    "coordinates": [
      -88.9833,
      46.3333
    ]
  },
  "type": "Feature",
  "properties": {
    "hierarchy": [
      "tgn:2140832",
      "tgn:1000001",
      "tgn:7012149",
      "tgn:2000986",
      "tgn:7007520",
      "tgn:7029392"
    ],
    "placetype": [
      "aat:300008680"
    ],
    "id": 2140832,
    "name:xx": "Avant Pond"
  }
}
