{
  "geometry": {
    "type": "Point",
    "coordinates": [
      -75.2333,
      20.15
    ]
  },
  "type": "Feature",
  "properties": {
    "hierarchy": [
      "tgn:1016357",
      "tgn:1001276",
      "tgn:1000001",
      "tgn:7004624",
      "tgn:7029392"
    ],
    "placetype": [
      "aat:300008347",
      "aat:300008389",
      "aat:300387223",
      "aat:300387302"
    ],
    "id": 1016357,
    "name:xx": "Guantánamo"
  }
}
