{
  "geometry": {
    "type": "Point",
    "coordinates": [
      -94.6833,
      44.9333
    ]
  },
  "type": "Feature",
  "properties": {
    "hierarchy": [
      "tgn:2054193",
      "tgn:1000001",
      "tgn:7012149",
      "tgn:2001045",
      "tgn:7007521",
      "tgn:7029392"
    ],
    "placetype": [
      "aat:300008347"
    ],
    "id": 2054193,
    "name:xx": "Cosmos"
  }
}
