{
  "geometry": {
    "type": "Point",
    "coordinates": [
      -119.8333,
      38.7833
    ]
  },
  "type": "Feature",
  "properties": {
    "hierarchy": [
      "tgn:2746690",
      "tgn:1002145",
      "tgn:1000001",
      "tgn:7012149",
      "tgn:7007157",
      "tgn:7029392"
    ],
    "placetype": [
      "aat:300008761"
    ],
    "id": 2746690,
    "name:xx": "Wade Canyon"
  }
}
