{
  "geometry": {
    "type": "Point",
    "coordinates": [
      -85.9333,
      40.5167
    ]
  },
  "type": "Feature",
  "properties": {
    "hierarchy": [
      "tgn:2496717",
      "tgn:1000001",
      "tgn:7012149",
      "tgn:1002487",
      "tgn:7007252",
      "tgn:7029392"
    ],
    "placetype": [
      "aat:300006075"
    ],
    "id": 2496717,
    "name:xx": "Matthew Howell Ditch"
  }
}
