{
  "type": "FeatureCollection",
  "features": [
    {
      "geometry": {
        "type": "Point",
        "coordinates": [
          -99.733333,
          17.6
        ]
      },
      "type": "Feature",
      "properties": {
        "hierarchy": [
          "tgn:7369321",
          "tgn:7005585",
          "tgn:1000001",
          "tgn:7005560",
          "tgn:7029392"
        ],
        "placetype": [
          "aat:300008347"
        ],
        "id": 7369321,
        "name:xx": "Iyotla"
      }
    },
    {
      "geometry": {
        "type": "Point",
        "coordinates": [
          -97.816667,
          19.9
        ]
      },
      "type": "Feature",
      "properties": {
        "hierarchy": [
          "tgn:7369322",
          "tgn:1000001",
          "tgn:7005592",
          "tgn:7005560",
          "tgn:7029392"
        ],
        "placetype": [
          "aat:300008347"
        ],
        "id": 7369322,
        "name:xx": "Ixtolco de Morelos"
      }
    },
    {
      "geometry": {
        "type": "Point",
        "coordinates": [
          -100.75,
          25.95
        ]
      },
      "type": "Feature",
      "properties": {
        "hierarchy": [
          "tgn:7369323",
          "tgn:1000001",
          "tgn:7005589",
          "tgn:7005560",
          "tgn:7029392"
        ],
        "placetype": [
          "aat:300007783"
        ],
        "id": 7369323,
        "name:xx": "Estación Ixtle"
      }
    },
    {
      "geometry": {
        "type": "Point",
        "coordinates": [
          -104.183333,
          19.983333
        ]
      },
      "type": "Feature",
      "properties": {
        "hierarchy": [
          "tgn:7369324",
          "tgn:7005586",
          "tgn:1000001",
          "tgn:7005560",
          "tgn:7029392"
        ],
        "placetype": [
          "aat:300008347"
        ],
        "id": 7369324,
        "name:xx": "Ixtlanuacan de Santiago"
      }
    },
    {
      "geometry": {
        "type": "Point",
        "coordinates": [
          -104.35,
          21.033333
        ]
      },
      "type": "Feature",
      "properties": {
        "hierarchy": [
          "tgn:7369328",
          "tgn:1000001",
          "tgn:1001906",
          "tgn:7005560",
          "tgn:7029392"
        ],
        "placetype": [
          "aat:300007783"
        ],
        "id": 7369328,
        "name:xx": "Ixtlán"
      }
    }
  ]
}
