{
  "geometry": {
    "type": "Point",
    "coordinates": [
      3.5333,
      50.3667
    ]
  },
  "type": "Feature",
  "properties": {
    "hierarchy": [
      "tgn:7008471",
      "tgn:1000003",
      "tgn:7001097",
      "tgn:1000070",
      "tgn:7029392"
    ],
    "placetype": [
      "aat:300008347",
      "aat:300387218",
      "aat:300008375",
      "aat:300387302"
    ],
    "id": 7008471,
    "name:xx": "Valenciennes"
  }
}
