{
  "geometry": {
    "type": "Point",
    "coordinates": [
      -82.4833,
      36.3167
    ]
  },
  "type": "Feature",
  "properties": {
    "hierarchy": [
      "tgn:2136550",
      "tgn:1000001",
      "tgn:7012149",
      "tgn:2001926",
      "tgn:7007825",
      "tgn:7029392"
    ],
    "placetype": [
      "aat:300266640"
    ],
    "id": 2136550,
    "name:xx": "Archer Ridge"
  }
}
