{
  "geometry": {
    "type": "Point",
    "coordinates": [
      34.390278,
      28.701944
    ]
  },
  "type": "Feature",
  "properties": {
    "hierarchy": [
      "tgn:7542796",
      "tgn:7001242",
      "tgn:7016833",
      "tgn:7001336",
      "tgn:7029392"
    ],
    "placetype": [
      "aat:300379998"
    ],
    "name:en": "Abū Samrah, Wādī",
    "id": 7542796
  }
}
