{
  "geometry": {
    "type": "Point",
    "coordinates": [
      -81.1167,
      38.3667
    ]
  },
  "type": "Feature",
  "properties": {
    "hierarchy": [
      "tgn:2224053",
      "tgn:1000001",
      "tgn:2002259",
      "tgn:7012149",
      "tgn:7013961",
      "tgn:7029392"
    ],
    "placetype": [
      "aat:300008699"
    ],
    "id": 2224053,
    "name:xx": "Carver Fork"
  }
}
