{
  "type": "FeatureCollection",
  "features": [
    {
      "geometry": {
        "type": "Point",
        "coordinates": [
          -2.077778,
          51.525
        ]
      },
      "type": "Feature",
      "properties": {
        "hierarchy": [
          "tgn:7449180",
          "tgn:7002445",
          "tgn:1000003",
          "tgn:7008180",
          "tgn:7008591",
          "tgn:7029392"
        ],
        "placetype": [
          "aat:300008347"
        ],
        "name:en": "Upper Seagry",
        "id": 7449180
      }
    },
    {
      "geometry": {
        "type": "Point",
        "coordinates": [
          -6.416667,
          54.433333
        ]
      },
      "type": "Feature",
      "properties": {
        "hierarchy": [
          "tgn:7449182",
          "tgn:7002448",
          "tgn:7019200",
          "tgn:1000003",
          "tgn:7008591",
          "tgn:7029392"
        ],
        "placetype": [
          "aat:300008347"
        ],
        "name:en": "Seagoe",
        "id": 7449182
      }
    },
    {
      "geometry": {
        "type": "Point",
        "coordinates": [
          -6.716667,
          58
        ]
      },
      "type": "Feature",
      "properties": {
        "hierarchy": [
          "tgn:7449183",
          "tgn:7002444",
          "tgn:1000003",
          "tgn:7008094",
          "tgn:7008591",
          "tgn:7029392"
        ],
        "placetype": [
          "aat:300008791"
        ],
        "name:en": "Seaforth, Eilean",
        "id": 7449183
      }
    },
    {
      "geometry": {
        "type": "Point",
        "coordinates": [
          -5.85,
          54.316667
        ]
      },
      "type": "Feature",
      "properties": {
        "hierarchy": [
          "tgn:7449185",
          "tgn:7002448",
          "tgn:7008698",
          "tgn:1000003",
          "tgn:7008591",
          "tgn:7029392"
        ],
        "placetype": [
          "aat:300387502"
        ],
        "name:en": "Seaforde House",
        "id": 7449185
      }
    },
    {
      "geometry": {
        "type": "Point",
        "coordinates": [
          -5.833333,
          54.3
        ]
      },
      "type": "Feature",
      "properties": {
        "hierarchy": [
          "tgn:7449186",
          "tgn:7002448",
          "tgn:7008698",
          "tgn:1000003",
          "tgn:7008591",
          "tgn:7029392"
        ],
        "placetype": [
          "aat:300008347"
        ],
        "name:en": "Seaforde",
        "id": 7449186
      }
    },
    {
      "geometry": {
        "type": "Point",
        "coordinates": [
          -3.15,
          55.966667
        ]
      },
      "type": "Feature",
      "properties": {
        "hierarchy": [
          "tgn:7449188",
          "tgn:7002444",
          "tgn:1000003",
          "tgn:7019109",
          "tgn:7008591",
          "tgn:7029392"
        ],
        "placetype": [
          "aat:300008347"
        ],
        "name:en": "Seafield",
        "id": 7449188
      }
    },
    {
      "geometry": {
        "type": "Point",
        "coordinates": [
          -1.4,
          60.333333
        ]
      },
      "type": "Feature",
      "properties": {
        "hierarchy": [
          "tgn:7449189",
          "tgn:7002444",
          "tgn:1000003",
          "tgn:7029508",
          "tgn:7008591",
          "tgn:7029392"
        ],
        "placetype": [
          "aat:300266559"
        ],
        "name:en": "Rona, The",
        "id": 7449189
      }
    }
  ]
}
