{
  "type": "FeatureCollection",
  "features": [
    {
      "geometry": {
        "type": "Point",
        "coordinates": [
          -72.933333,
          -51.816667
        ]
      },
      "type": "Feature",
      "properties": {
        "hierarchy": [
          "tgn:7320930",
          "tgn:1001702",
          "tgn:1000049",
          "tgn:1000002",
          "tgn:7029392"
        ],
        "placetype": [
          "aat:300008791"
        ],
        "id": 7320930,
        "name:xx": "Ballesteros, Isla"
      }
    },
    {
      "geometry": {
        "type": "Point",
        "coordinates": [
          -70.7,
          -25.733333
        ]
      },
      "type": "Feature",
      "properties": {
        "hierarchy": [
          "tgn:7320932",
          "tgn:7016598",
          "tgn:1000049",
          "tgn:1000002",
          "tgn:7029392"
        ],
        "placetype": [
          "aat:300132316"
        ],
        "id": 7320932,
        "name:xx": "Ballenita, Bahía"
      }
    },
    {
      "geometry": {
        "type": "Point",
        "coordinates": [
          -71,
          -54.833333
        ]
      },
      "type": "Feature",
      "properties": {
        "hierarchy": [
          "tgn:7320933",
          "tgn:1001702",
          "tgn:1000049",
          "tgn:1000002",
          "tgn:7029392"
        ],
        "placetype": [
          "aat:300387026"
        ],
        "id": 7320933,
        "name:xx": "Ballenero, Canal"
      }
    },
    {
      "geometry": {
        "type": "Point",
        "coordinates": [
          -74.8,
          -52.4
        ]
      },
      "type": "Feature",
      "properties": {
        "hierarchy": [
          "tgn:7320934",
          "tgn:1001702",
          "tgn:1000049",
          "tgn:1000002",
          "tgn:7029392"
        ],
        "placetype": [
          "aat:300011692"
        ],
        "id": 7320934,
        "name:xx": "Ballenato, Roca"
      }
    },
    {
      "geometry": {
        "type": "Point",
        "coordinates": [
          -68.816667,
          -24.033333
        ]
      },
      "type": "Feature",
      "properties": {
        "hierarchy": [
          "tgn:7320935",
          "tgn:7016598",
          "tgn:1000049",
          "tgn:1000002",
          "tgn:7029392"
        ],
        "placetype": [
          "aat:300008795"
        ],
        "id": 7320935,
        "name:xx": "Ballenato, Cerro"
      }
    },
    {
      "geometry": {
        "type": "Point",
        "coordinates": [
          -70.1,
          -19.066667
        ]
      },
      "type": "Feature",
      "properties": {
        "hierarchy": [
          "tgn:7320936",
          "tgn:7002464",
          "tgn:1000049",
          "tgn:1000002",
          "tgn:7029392"
        ],
        "placetype": [
          "aat:300387033"
        ],
        "id": 7320936,
        "name:xx": "Ballenato"
      }
    },
    {
      "geometry": {
        "type": "Point",
        "coordinates": [
          -74.883333,
          -47.766667
        ]
      },
      "type": "Feature",
      "properties": {
        "hierarchy": [
          "tgn:7320937",
          "tgn:1001623",
          "tgn:1000049",
          "tgn:1000002",
          "tgn:7029392"
        ],
        "placetype": [
          "aat:300008777"
        ],
        "id": 7320937,
        "name:xx": "Ballenas, Tetas de"
      }
    },
    {
      "geometry": {
        "type": "Point",
        "coordinates": [
          -72.716667,
          -51.8
        ]
      },
      "type": "Feature",
      "properties": {
        "hierarchy": [
          "tgn:7320938",
          "tgn:1001702",
          "tgn:1000049",
          "tgn:1000002",
          "tgn:7029392"
        ],
        "placetype": [
          "aat:300008795"
        ],
        "id": 7320938,
        "name:xx": "Ballenas, Tetas"
      }
    },
    {
      "geometry": {
        "type": "Point",
        "coordinates": [
          -74.9,
          -47.766667
        ]
      },
      "type": "Feature",
      "properties": {
        "hierarchy": [
          "tgn:7320939",
          "tgn:1001623",
          "tgn:1000049",
          "tgn:1000002",
          "tgn:7029392"
        ],
        "placetype": [
          "aat:300008678"
        ],
        "id": 7320939,
        "name:xx": "Ballenas, Puerto"
      }
    }
  ]
}
