{
  "type": "FeatureCollection",
  "features": [
    {
      "geometry": {
        "type": "Point",
        "coordinates": [
          -154.15,
          59.75
        ]
      },
      "type": "Feature",
      "properties": {
        "hierarchy": [
          "tgn:2006301",
          "tgn:7006450",
          "tgn:1000001",
          "tgn:7030517",
          "tgn:7012149",
          "tgn:7029392"
        ],
        "placetype": [
          "aat:300132316"
        ],
        "id": 2006301,
        "name:xx": "Pedro Bay"
      }
    },
    {
      "geometry": {
        "type": "Point",
        "coordinates": [
          -136.2167,
          57.95
        ]
      },
      "type": "Feature",
      "properties": {
        "hierarchy": [
          "tgn:2006302",
          "tgn:7006450",
          "tgn:1000001",
          "tgn:7012149",
          "tgn:7019760",
          "tgn:7029392"
        ],
        "placetype": [
          "aat:300008347"
        ],
        "id": 2006302,
        "name:xx": "Pelican"
      }
    },
    {
      "geometry": {
        "type": "Point",
        "coordinates": [
          -165.4,
          64.55
        ]
      },
      "type": "Feature",
      "properties": {
        "hierarchy": [
          "tgn:2006305",
          "tgn:7006450",
          "tgn:1000001",
          "tgn:7012149",
          "tgn:2000079",
          "tgn:7029392"
        ],
        "placetype": [
          "aat:300008347"
        ],
        "id": 2006305,
        "name:xx": "Perkinsville"
      }
    },
    {
      "geometry": {
        "type": "Point",
        "coordinates": [
          -159.1333,
          55.9
        ]
      },
      "type": "Feature",
      "properties": {
        "hierarchy": [
          "tgn:2006306",
          "tgn:7006450",
          "tgn:1000001",
          "tgn:7030517",
          "tgn:7012149",
          "tgn:7029392"
        ],
        "placetype": [
          "aat:300008347"
        ],
        "id": 2006306,
        "name:xx": "Perryville"
      }
    },
    {
      "geometry": {
        "type": "Point",
        "coordinates": [
          -157.5667,
          57.55
        ]
      },
      "type": "Feature",
      "properties": {
        "hierarchy": [
          "tgn:2006309",
          "tgn:7006450",
          "tgn:1000001",
          "tgn:7030517",
          "tgn:7012149",
          "tgn:7029392"
        ],
        "placetype": [
          "aat:300008347"
        ],
        "id": 2006309,
        "name:xx": "Pilot Point"
      }
    }
  ]
}
