{
  "geometry": {
    "type": "Point",
    "coordinates": [
      30.15,
      31.166667
    ]
  },
  "type": "Feature",
  "properties": {
    "hierarchy": [
      "tgn:7535142",
      "tgn:7001242",
      "tgn:1001075",
      "tgn:7016833",
      "tgn:7029392"
    ],
    "placetype": [
      "aat:300387086"
    ],
    "name:en": "Kafr ad Dawwār, Maşrif",
    "id": 7535142
  }
}
