{
  "geometry": {
    "type": "Point",
    "coordinates": [
      -99.3333,
      29.8667
    ]
  },
  "type": "Feature",
  "properties": {
    "hierarchy": [
      "tgn:2765421",
      "tgn:1000001",
      "tgn:2001938",
      "tgn:7012149",
      "tgn:7007826",
      "tgn:7029392"
    ],
    "placetype": [
      "aat:300008798"
    ],
    "id": 2765421,
    "name:xx": "White Bluff"
  }
}
