{
  "geometry": {
    "type": "Point",
    "coordinates": [
      -79.1667,
      38.95
    ]
  },
  "type": "Feature",
  "properties": {
    "hierarchy": [
      "tgn:2369099",
      "tgn:1000001",
      "tgn:2002263",
      "tgn:7012149",
      "tgn:7013961",
      "tgn:7029392"
    ],
    "placetype": [
      "aat:300008761"
    ],
    "id": 2369099,
    "name:xx": "Gum Hollow"
  }
}
