{
  "geometry": {
    "type": "Point",
    "coordinates": [
      -155.7333,
      19.2667
    ]
  },
  "type": "Feature",
  "properties": {
    "hierarchy": [
      "tgn:2129364",
      "tgn:7023902",
      "tgn:1000001",
      "tgn:7012149",
      "tgn:7007249",
      "tgn:7029392"
    ],
    "placetype": [
      "aat:300008798"
    ],
    "id": 2129364,
    "name:xx": "Alika Cone"
  }
}
