{
  "geometry": {
    "type": "Point",
    "coordinates": [
      -78.1667,
      38.75
    ]
  },
  "type": "Feature",
  "properties": {
    "hierarchy": [
      "tgn:2572685",
      "tgn:1000001",
      "tgn:7012149",
      "tgn:2002184",
      "tgn:7007919",
      "tgn:7029392"
    ],
    "placetype": [
      "aat:300008798"
    ],
    "id": 2572685,
    "name:xx": "Peak, The"
  }
}
