{
  "geometry": {
    "type": "Point",
    "coordinates": [
      99.1333,
      25.1167
    ]
  },
  "type": "Feature",
  "properties": {
    "hierarchy": [
      "tgn:1066784",
      "tgn:1000004",
      "tgn:7018118",
      "tgn:1000111",
      "tgn:7029392"
    ],
    "placetype": [
      "aat:300008347"
    ],
    "id": 1066784,
    "name:xx": "Baoshan"
  }
}
