{
  "geometry": {
    "type": "Point",
    "coordinates": [
      106.35,
      29.2167
    ]
  },
  "type": "Feature",
  "properties": {
    "hierarchy": [
      "tgn:1130410",
      "tgn:1000004",
      "tgn:1000111",
      "tgn:7029392"
    ],
    "placetype": [
      "aat:300008707"
    ],
    "id": 1130410,
    "name:xx": "Sun"
  }
}
