{
  "geometry": {
    "type": "Point",
    "coordinates": [
      -71.7333,
      44.6667
    ]
  },
  "type": "Feature",
  "properties": {
    "hierarchy": [
      "tgn:2205813",
      "tgn:1000001",
      "tgn:1002361",
      "tgn:7012149",
      "tgn:7007828",
      "tgn:7029392"
    ],
    "placetype": [
      "aat:300008798"
    ],
    "id": 2205813,
    "name:xx": "Bull Mountain"
  }
}
