{
  "geometry": {
    "type": "Point",
    "coordinates": [
      76.72854,
      30.096029
    ]
  },
  "type": "Feature",
  "properties": {
    "hierarchy": [
      "tgn:7584952",
      "tgn:1000004",
      "tgn:1001871",
      "tgn:7000198",
      "tgn:7029392"
    ],
    "placetype": [
      "aat:300008347"
    ],
    "name:en": "Duniya Mājra",
    "id": 7584952
  }
}
