{
  "geometry": {
    "type": "Point",
    "coordinates": [
      -107.6833,
      38.6833
    ]
  },
  "type": "Feature",
  "properties": {
    "hierarchy": [
      "tgn:2358508",
      "tgn:1000001",
      "tgn:7012149",
      "tgn:2000206",
      "tgn:7007158",
      "tgn:7029392"
    ],
    "placetype": [
      "aat:300008798"
    ],
    "id": 2358508,
    "name:xx": "Grand Vrew Mesa"
  }
}
