{
  "geometry": {
    "type": "Point",
    "coordinates": [
      2.5833,
      45.4167
    ]
  },
  "type": "Feature",
  "properties": {
    "hierarchy": [
      "tgn:7024266",
      "tgn:1000003",
      "tgn:7029392"
    ],
    "placetype": [
      "aat:300387178"
    ],
    "name:fr": "Auvergne",
    "id": 7024266
  }
}
