{
  "geometry": {
    "type": "Point",
    "coordinates": [
      -113.1833,
      45.9167
    ]
  },
  "type": "Feature",
  "properties": {
    "hierarchy": [
      "tgn:2142443",
      "tgn:1000001",
      "tgn:7012149",
      "tgn:7020792",
      "tgn:7007524",
      "tgn:7029392"
    ],
    "placetype": [
      "aat:300006075"
    ],
    "id": 2142443,
    "name:xx": "Bacon Ditch"
  }
}
