{
  "geometry": {
    "type": "Point",
    "coordinates": [
      84.75,
      19.066667
    ]
  },
  "type": "Feature",
  "properties": {
    "hierarchy": [
      "tgn:7545843",
      "tgn:1000004",
      "tgn:7000198",
      "tgn:7016694",
      "tgn:7029392"
    ],
    "placetype": [
      "aat:300008699"
    ],
    "name:en": "Bāhuda River",
    "id": 7545843
  }
}
