{
  "geometry": {
    "type": "Point",
    "coordinates": [
      -77.3833,
      40.8833
    ]
  },
  "type": "Feature",
  "properties": {
    "hierarchy": [
      "tgn:2782316",
      "tgn:1000001",
      "tgn:1002249",
      "tgn:7012149",
      "tgn:2782325",
      "tgn:7007710",
      "tgn:7029392"
    ],
    "placetype": [
      "aat:300008746"
    ],
    "id": 2782316,
    "name:xx": "Woodward Number 2 Cave"
  }
}
