{
  "geometry": {
    "type": "Point",
    "coordinates": [
      -81.4333,
      29.3667
    ]
  },
  "type": "Feature",
  "properties": {
    "hierarchy": [
      "tgn:2380729",
      "tgn:1000001",
      "tgn:7012149",
      "tgn:7007240",
      "tgn:7029392"
    ],
    "placetype": [
      "aat:300008178"
    ],
    "id": 2380729,
    "name:xx": "Haw Creek State Preserve"
  }
}
