{
  "geometry": {
    "type": "Point",
    "coordinates": [
      -163.15,
      67.7833
    ]
  },
  "type": "Feature",
  "properties": {
    "hierarchy": [
      "tgn:2436748",
      "tgn:7006450",
      "tgn:1000001",
      "tgn:7012149",
      "tgn:2124014",
      "tgn:7029392"
    ],
    "placetype": [
      "aat:300008798"
    ],
    "id": 2436748,
    "name:xx": "Kikmiksot Mountain"
  }
}
