{
  "geometry": {
    "type": "Point",
    "coordinates": [
      -78.8833,
      35.3667
    ]
  },
  "type": "Feature",
  "properties": {
    "hierarchy": [
      "tgn:2424342",
      "tgn:1000001",
      "tgn:7012149",
      "tgn:2001502",
      "tgn:7007709",
      "tgn:7029392"
    ],
    "placetype": [
      "aat:300008699"
    ],
    "id": 2424342,
    "name:xx": "Johnson Branch"
  }
}
