{
  "geometry": {
    "type": "Point",
    "coordinates": [
      -8.1833,
      52.3833
    ]
  },
  "type": "Feature",
  "properties": {
    "hierarchy": [
      "tgn:1104655",
      "tgn:7003499",
      "tgn:7001201",
      "tgn:1000003",
      "tgn:1000078",
      "tgn:7029392"
    ],
    "placetype": [
      "aat:300008795"
    ],
    "id": 1104655,
    "name:xx": "Galtymore Mountain"
  }
}
