{
  "geometry": {
    "type": "Point",
    "coordinates": [
      -74.9167,
      42.9667
    ]
  },
  "type": "Feature",
  "properties": {
    "hierarchy": [
      "tgn:2311316",
      "tgn:1000001",
      "tgn:7012149",
      "tgn:1002472",
      "tgn:7007568",
      "tgn:7029392"
    ],
    "placetype": [
      "aat:300008347"
    ],
    "id": 2311316,
    "name:xx": "Edicks"
  }
}
