{
  "geometry": {
    "type": "Point",
    "coordinates": [
      -116.85,
      45.4333
    ]
  },
  "type": "Feature",
  "properties": {
    "hierarchy": [
      "tgn:2197457",
      "tgn:1000001",
      "tgn:7012149",
      "tgn:2001722",
      "tgn:7007708",
      "tgn:7029392"
    ],
    "placetype": [
      "aat:300008706"
    ],
    "id": 2197457,
    "name:xx": "Brown Creek"
  }
}
