{
  "geometry": {
    "type": "Point",
    "coordinates": [
      -90.85,
      39.3167
    ]
  },
  "type": "Feature",
  "properties": {
    "hierarchy": [
      "tgn:2200577",
      "tgn:1000001",
      "tgn:7012149",
      "tgn:1002787",
      "tgn:7007523",
      "tgn:7029392"
    ],
    "placetype": [
      "aat:300008680"
    ],
    "id": 2200577,
    "name:xx": "Brushy Pond"
  }
}
