{
  "geometry": {
    "type": "Point",
    "coordinates": [
      -112.15,
      40.35
    ]
  },
  "type": "Feature",
  "properties": {
    "hierarchy": [
      "tgn:2720034",
      "tgn:1000001",
      "tgn:7012149",
      "tgn:2002125",
      "tgn:7007827",
      "tgn:7029392"
    ],
    "placetype": [
      "aat:300008761"
    ],
    "id": 2720034,
    "name:xx": "Threemile Canyon"
  }
}
