{
  "type": "FeatureCollection",
  "features": [
    {
      "geometry": {
        "type": "Point",
        "coordinates": [
          61.5,
          53
        ]
      },
      "type": "Feature",
      "properties": {
        "hierarchy": [
          "tgn:1110381",
          "tgn:1000004",
          "tgn:7029392"
        ],
        "placetype": [
          "aat:300132339"
        ],
        "id": 1110381,
        "name:xx": "Oral Syrty Üstirti"
      }
    },
    {
      "geometry": {
        "type": "Point",
        "coordinates": [
          38.3,
          33.9167
        ]
      },
      "type": "Feature",
      "properties": {
        "hierarchy": [
          "tgn:1110382",
          "tgn:1000004",
          "tgn:1002054",
          "tgn:1000140",
          "tgn:7029392"
        ],
        "placetype": [
          "aat:300008777"
        ],
        "id": 1110382,
        "name:xx": "ʻUlab, Ṭaraq al-"
      }
    },
    {
      "geometry": {
        "type": "Point",
        "coordinates": [
          31.35,
          29.9
        ]
      },
      "type": "Feature",
      "properties": {
        "hierarchy": [
          "tgn:1110383",
          "tgn:7001242",
          "tgn:7001311",
          "tgn:7016833",
          "tgn:7029392"
        ],
        "placetype": [
          "aat:300008777",
          "aat:300008795"
        ],
        "name:en": "Ḩawf, Jabal",
        "id": 1110383
      }
    },
    {
      "geometry": {
        "type": "Point",
        "coordinates": [
          27.7333,
          6.1
        ]
      },
      "type": "Feature",
      "properties": {
        "hierarchy": [
          "tgn:1110384",
          "tgn:7001242",
          "tgn:1001081",
          "tgn:7441551",
          "tgn:7029392"
        ],
        "placetype": [
          "aat:300008777"
        ],
        "id": 1110384,
        "name:xx": "Abū Gatta Hills"
      }
    },
    {
      "geometry": {
        "type": "Point",
        "coordinates": [
          -10.4333,
          16.9333
        ]
      },
      "type": "Feature",
      "properties": {
        "hierarchy": [
          "tgn:1110385",
          "tgn:7001242",
          "tgn:1000176",
          "tgn:7029392"
        ],
        "placetype": [
          "aat:300008777"
        ],
        "id": 1110385,
        "name:xx": "Afollé"
      }
    },
    {
      "geometry": {
        "type": "Point",
        "coordinates": [
          21.1667,
          -19.75
        ]
      },
      "type": "Feature",
      "properties": {
        "hierarchy": [
          "tgn:1110386",
          "tgn:7001242",
          "tgn:7029392"
        ],
        "placetype": [
          "aat:300008777"
        ],
        "id": 1110386,
        "name:xx": "Aha Hills"
      }
    },
    {
      "geometry": {
        "type": "Point",
        "coordinates": [
          17.1667,
          27
        ]
      },
      "type": "Feature",
      "properties": {
        "hierarchy": [
          "tgn:1110387",
          "tgn:7001242",
          "tgn:1000172",
          "tgn:7029392"
        ],
        "placetype": [
          "aat:300008777"
        ],
        "id": 1110387,
        "name:xx": "Al Harūj al Aswad"
      }
    },
    {
      "geometry": {
        "type": "Point",
        "coordinates": [
          12.75,
          41.75
        ]
      },
      "type": "Feature",
      "properties": {
        "hierarchy": [
          "tgn:1110388",
          "tgn:7003138",
          "tgn:1000003",
          "tgn:7003080",
          "tgn:1000080",
          "tgn:7029392"
        ],
        "placetype": [
          "aat:300008777"
        ],
        "id": 1110388,
        "name:xx": "Albani, Colli"
      }
    }
  ]
}
