{
  "geometry": {
    "type": "Point",
    "coordinates": [
      -92.8333,
      31.2167
    ]
  },
  "type": "Feature",
  "properties": {
    "hierarchy": [
      "tgn:2489136",
      "tgn:1000001",
      "tgn:7012149",
      "tgn:7007256",
      "tgn:7029392"
    ],
    "placetype": [
      "aat:300008699"
    ],
    "id": 2489136,
    "name:xx": "Majors Branch"
  }
}
