{
  "geometry": {
    "type": "Point",
    "coordinates": [
      -81.4167,
      28.9167
    ]
  },
  "type": "Feature",
  "properties": {
    "hierarchy": [
      "tgn:2021340",
      "tgn:1000001",
      "tgn:7012149",
      "tgn:1002567",
      "tgn:7007240",
      "tgn:7029392"
    ],
    "placetype": [
      "aat:300008347"
    ],
    "id": 2021340,
    "name:xx": "South Pine Lakes"
  }
}
