{
  "geometry": {
    "type": "Point",
    "coordinates": [
      -88.5833,
      46.7667
    ]
  },
  "type": "Feature",
  "properties": {
    "hierarchy": [
      "tgn:2366868",
      "tgn:2000947",
      "tgn:1000001",
      "tgn:7012149",
      "tgn:7007520",
      "tgn:7029392"
    ],
    "placetype": [
      "aat:300008706"
    ],
    "id": 2366868,
    "name:xx": "Gristmill Creek"
  }
}
