{
  "type": "FeatureCollection",
  "features": [
    {
      "geometry": {
        "type": "Point",
        "coordinates": [
          -78.1333,
          39.7333
        ]
      },
      "type": "Feature",
      "properties": {
        "hierarchy": [
          "tgn:2468470",
          "tgn:1000001",
          "tgn:7012149",
          "tgn:1002399",
          "tgn:7007710",
          "tgn:7029392"
        ],
        "placetype": [
          "aat:300008798"
        ],
        "id": 2468470,
        "name:xx": "Long Point"
      }
    },
    {
      "geometry": {
        "type": "Point",
        "coordinates": [
          -71.45,
          41.5667
        ]
      },
      "type": "Feature",
      "properties": {
        "hierarchy": [
          "tgn:2468471",
          "tgn:1002996",
          "tgn:1000001",
          "tgn:7012149",
          "tgn:7007711",
          "tgn:7029392"
        ],
        "placetype": [
          "aat:300008850"
        ],
        "id": 2468471,
        "name:xx": "Long Point"
      }
    },
    {
      "geometry": {
        "type": "Point",
        "coordinates": [
          -71.4333,
          41.6667
        ]
      },
      "type": "Feature",
      "properties": {
        "hierarchy": [
          "tgn:2468472",
          "tgn:1002541",
          "tgn:1000001",
          "tgn:7012149",
          "tgn:7007711",
          "tgn:7029392"
        ],
        "placetype": [
          "aat:300008850"
        ],
        "id": 2468472,
        "name:xx": "Long Point"
      }
    },
    {
      "geometry": {
        "type": "Point",
        "coordinates": [
          -71.3333,
          41.65
        ]
      },
      "type": "Feature",
      "properties": {
        "hierarchy": [
          "tgn:2468473",
          "tgn:1002716",
          "tgn:1000001",
          "tgn:7012149",
          "tgn:7007711",
          "tgn:7029392"
        ],
        "placetype": [
          "aat:300008850"
        ],
        "id": 2468473,
        "name:xx": "Long Point"
      }
    },
    {
      "geometry": {
        "type": "Point",
        "coordinates": [
          -80.6,
          32.45
        ]
      },
      "type": "Feature",
      "properties": {
        "hierarchy": [
          "tgn:2468474",
          "tgn:2001731",
          "tgn:1000001",
          "tgn:7012149",
          "tgn:7007712",
          "tgn:7029392"
        ],
        "placetype": [
          "aat:300008850"
        ],
        "id": 2468474,
        "name:xx": "Long Point"
      }
    },
    {
      "geometry": {
        "type": "Point",
        "coordinates": [
          -85.4667,
          35.0833
        ]
      },
      "type": "Feature",
      "properties": {
        "hierarchy": [
          "tgn:2468475",
          "tgn:1000001",
          "tgn:7012149",
          "tgn:2001894",
          "tgn:7007825",
          "tgn:7029392"
        ],
        "placetype": [
          "aat:300008850"
        ],
        "id": 2468475,
        "name:xx": "Long Point"
      }
    },
    {
      "geometry": {
        "type": "Point",
        "coordinates": [
          -88,
          35.5833
        ]
      },
      "type": "Feature",
      "properties": {
        "hierarchy": [
          "tgn:2468476",
          "tgn:1000001",
          "tgn:7012149",
          "tgn:2001904",
          "tgn:7007825",
          "tgn:7029392"
        ],
        "placetype": [
          "aat:300008850"
        ],
        "id": 2468476,
        "name:xx": "Long Point"
      }
    },
    {
      "geometry": {
        "type": "Point",
        "coordinates": [
          -89.3167,
          36.4667
        ]
      },
      "type": "Feature",
      "properties": {
        "hierarchy": [
          "tgn:2468477",
          "tgn:1000001",
          "tgn:7012149",
          "tgn:2001902",
          "tgn:7007825",
          "tgn:7029392"
        ],
        "placetype": [
          "aat:300008850"
        ],
        "id": 2468477,
        "name:xx": "Long Point"
      }
    },
    {
      "geometry": {
        "type": "Point",
        "coordinates": [
          -94.1,
          32.6667
        ]
      },
      "type": "Feature",
      "properties": {
        "hierarchy": [
          "tgn:2468478",
          "tgn:1000001",
          "tgn:7012149",
          "tgn:1002460",
          "tgn:7007826",
          "tgn:7029392"
        ],
        "placetype": [
          "aat:300008850"
        ],
        "id": 2468478,
        "name:xx": "Long Point"
      }
    },
    {
      "geometry": {
        "type": "Point",
        "coordinates": [
          -97.2,
          33.1333
        ]
      },
      "type": "Feature",
      "properties": {
        "hierarchy": [
          "tgn:2468479",
          "tgn:1000001",
          "tgn:7012149",
          "tgn:1002331",
          "tgn:7007826",
          "tgn:7029392"
        ],
        "placetype": [
          "aat:300008798"
        ],
        "id": 2468479,
        "name:xx": "Long Point"
      }
    }
  ]
}
