{
  "type": "FeatureCollection",
  "features": [
    {
      "geometry": {
        "type": "Point",
        "coordinates": [
          14.116667,
          51.183333
        ]
      },
      "type": "Feature",
      "properties": {
        "hierarchy": [
          "tgn:7161310",
          "tgn:1000003",
          "tgn:7003685",
          "tgn:7000084",
          "tgn:7029392"
        ],
        "placetype": [
          "aat:300008777"
        ],
        "id": 7161310,
        "name:xx": "Hoch-Stein"
      }
    },
    {
      "geometry": {
        "type": "Point",
        "coordinates": [
          8.916667,
          51.183333
        ]
      },
      "type": "Feature",
      "properties": {
        "hierarchy": [
          "tgn:7161311",
          "tgn:1000003",
          "tgn:7003678",
          "tgn:7000084",
          "tgn:7029392"
        ],
        "placetype": [
          "aat:300008777"
        ],
        "id": 7161311,
        "name:xx": "Hochstein"
      }
    },
    {
      "geometry": {
        "type": "Point",
        "coordinates": [
          14.566667,
          51.116667
        ]
      },
      "type": "Feature",
      "properties": {
        "hierarchy": [
          "tgn:7161312",
          "tgn:1000003",
          "tgn:7003685",
          "tgn:7000084",
          "tgn:7029392"
        ],
        "placetype": [
          "aat:300008777"
        ],
        "id": 7161312,
        "name:xx": "Hochstein"
      }
    },
    {
      "geometry": {
        "type": "Point",
        "coordinates": [
          13.933333,
          50.866667
        ]
      },
      "type": "Feature",
      "properties": {
        "hierarchy": [
          "tgn:7161313",
          "tgn:1000003",
          "tgn:7003685",
          "tgn:7000084",
          "tgn:7029392"
        ],
        "placetype": [
          "aat:300008777"
        ],
        "id": 7161313,
        "name:xx": "Hoch-Stein"
      }
    },
    {
      "geometry": {
        "type": "Point",
        "coordinates": [
          7.216667,
          50.366667
        ]
      },
      "type": "Feature",
      "properties": {
        "hierarchy": [
          "tgn:7161314",
          "tgn:1000003",
          "tgn:7003682",
          "tgn:7000084",
          "tgn:7029392"
        ],
        "placetype": [
          "aat:300008777"
        ],
        "id": 7161314,
        "name:xx": "Hochstein"
      }
    },
    {
      "geometry": {
        "type": "Point",
        "coordinates": [
          13.15,
          48.333333
        ]
      },
      "type": "Feature",
      "properties": {
        "hierarchy": [
          "tgn:7161315",
          "tgn:7003669",
          "tgn:1000003",
          "tgn:7000084",
          "tgn:7029392"
        ],
        "placetype": [
          "aat:300000206"
        ],
        "id": 7161315,
        "name:xx": "Hochstein"
      }
    },
    {
      "geometry": {
        "type": "Point",
        "coordinates": [
          10.166667,
          52
        ]
      },
      "type": "Feature",
      "properties": {
        "hierarchy": [
          "tgn:7161316",
          "tgn:1000003",
          "tgn:7003676",
          "tgn:7000084",
          "tgn:7029392"
        ],
        "placetype": [
          "aat:300008347"
        ],
        "id": 7161316,
        "name:xx": "Hochstedt"
      }
    },
    {
      "geometry": {
        "type": "Point",
        "coordinates": [
          10.7,
          51.516667
        ]
      },
      "type": "Feature",
      "properties": {
        "hierarchy": [
          "tgn:7161317",
          "tgn:1000003",
          "tgn:7003689",
          "tgn:7000084",
          "tgn:7029392"
        ],
        "placetype": [
          "aat:300008347"
        ],
        "id": 7161317,
        "name:xx": "Hochstedt"
      }
    },
    {
      "geometry": {
        "type": "Point",
        "coordinates": [
          11.133333,
          50.983333
        ]
      },
      "type": "Feature",
      "properties": {
        "hierarchy": [
          "tgn:7161318",
          "tgn:1000003",
          "tgn:7003689",
          "tgn:7000084",
          "tgn:7029392"
        ],
        "placetype": [
          "aat:300008347"
        ],
        "id": 7161318,
        "name:xx": "Hochstedt"
      }
    },
    {
      "geometry": {
        "type": "Point",
        "coordinates": [
          7,
          50.25
        ]
      },
      "type": "Feature",
      "properties": {
        "hierarchy": [
          "tgn:7161319",
          "tgn:1000003",
          "tgn:7003682",
          "tgn:7000084",
          "tgn:7029392"
        ],
        "placetype": [
          "aat:300008347"
        ],
        "id": 7161319,
        "name:xx": "Höchstberg"
      }
    }
  ]
}
