{
  "geometry": {
    "type": "Point",
    "coordinates": [
      78.97544,
      24.90733
    ]
  },
  "type": "Feature",
  "properties": {
    "hierarchy": [
      "tgn:7584122",
      "tgn:1000004",
      "tgn:7000198",
      "tgn:1001894",
      "tgn:7029392"
    ],
    "placetype": [
      "aat:300266554",
      "aat:300008699"
    ],
    "name:en": "Jamnāra Nāla",
    "id": 7584122
  }
}
