{
  "type": "FeatureCollection",
  "features": [
    {
      "geometry": {
        "type": "Point",
        "coordinates": [
          -110.1,
          27.5
        ]
      },
      "type": "Feature",
      "properties": {
        "hierarchy": [
          "tgn:7372270",
          "tgn:1000001",
          "tgn:1001960",
          "tgn:7005560",
          "tgn:7029392"
        ],
        "placetype": [
          "aat:300008347"
        ],
        "id": 7372270,
        "name:xx": "La Noria"
      }
    },
    {
      "geometry": {
        "type": "Point",
        "coordinates": [
          -105.783333,
          27.416667
        ]
      },
      "type": "Feature",
      "properties": {
        "hierarchy": [
          "tgn:7372271",
          "tgn:7005581",
          "tgn:1000001",
          "tgn:7005560",
          "tgn:7029392"
        ],
        "placetype": [
          "aat:300008347"
        ],
        "id": 7372271,
        "name:xx": "La Noria"
      }
    },
    {
      "geometry": {
        "type": "Point",
        "coordinates": [
          -105.816667,
          27.133333
        ]
      },
      "type": "Feature",
      "properties": {
        "hierarchy": [
          "tgn:7372272",
          "tgn:7005581",
          "tgn:1000001",
          "tgn:7005560",
          "tgn:7029392"
        ],
        "placetype": [
          "aat:300008347"
        ],
        "id": 7372272,
        "name:xx": "La Noria"
      }
    },
    {
      "geometry": {
        "type": "Point",
        "coordinates": [
          -102.433333,
          27.116667
        ]
      },
      "type": "Feature",
      "properties": {
        "hierarchy": [
          "tgn:7372273",
          "tgn:1001853",
          "tgn:1000001",
          "tgn:7005560",
          "tgn:7029392"
        ],
        "placetype": [
          "aat:300008347"
        ],
        "id": 7372273,
        "name:xx": "La Noria"
      }
    },
    {
      "geometry": {
        "type": "Point",
        "coordinates": [
          -108.8,
          26.983333
        ]
      },
      "type": "Feature",
      "properties": {
        "hierarchy": [
          "tgn:7372274",
          "tgn:1000001",
          "tgn:1001960",
          "tgn:7005560",
          "tgn:7029392"
        ],
        "placetype": [
          "aat:300008347"
        ],
        "id": 7372274,
        "name:xx": "La Noria"
      }
    },
    {
      "geometry": {
        "type": "Point",
        "coordinates": [
          -106.066667,
          26.95
        ]
      },
      "type": "Feature",
      "properties": {
        "hierarchy": [
          "tgn:7372275",
          "tgn:7005581",
          "tgn:1000001",
          "tgn:7005560",
          "tgn:7029392"
        ],
        "placetype": [
          "aat:300008347"
        ],
        "id": 7372275,
        "name:xx": "La Noria"
      }
    },
    {
      "geometry": {
        "type": "Point",
        "coordinates": [
          -103.416667,
          26.9
        ]
      },
      "type": "Feature",
      "properties": {
        "hierarchy": [
          "tgn:7372276",
          "tgn:1001853",
          "tgn:1000001",
          "tgn:7005560",
          "tgn:7029392"
        ],
        "placetype": [
          "aat:300008347"
        ],
        "id": 7372276,
        "name:xx": "La Noria"
      }
    },
    {
      "geometry": {
        "type": "Point",
        "coordinates": [
          -105.583333,
          26.833333
        ]
      },
      "type": "Feature",
      "properties": {
        "hierarchy": [
          "tgn:7372277",
          "tgn:7005581",
          "tgn:1000001",
          "tgn:7005560",
          "tgn:7029392"
        ],
        "placetype": [
          "aat:300008347"
        ],
        "id": 7372277,
        "name:xx": "La Noria"
      }
    },
    {
      "geometry": {
        "type": "Point",
        "coordinates": [
          -105.683333,
          26.816667
        ]
      },
      "type": "Feature",
      "properties": {
        "hierarchy": [
          "tgn:7372278",
          "tgn:7005581",
          "tgn:1000001",
          "tgn:7005560",
          "tgn:7029392"
        ],
        "placetype": [
          "aat:300008347"
        ],
        "id": 7372278,
        "name:xx": "La Noria"
      }
    },
    {
      "geometry": {
        "type": "Point",
        "coordinates": [
          -108.483333,
          25.7
        ]
      },
      "type": "Feature",
      "properties": {
        "hierarchy": [
          "tgn:7372279",
          "tgn:1000001",
          "tgn:7005595",
          "tgn:7005560",
          "tgn:7029392"
        ],
        "placetype": [
          "aat:300008347"
        ],
        "id": 7372279,
        "name:xx": "La Noria"
      }
    }
  ]
}
