{
  "geometry": {
    "type": "Point",
    "coordinates": [
      -83.7667,
      38.8833
    ]
  },
  "type": "Feature",
  "properties": {
    "hierarchy": [
      "tgn:2634403",
      "tgn:1000001",
      "tgn:1002210",
      "tgn:7012149",
      "tgn:7007706",
      "tgn:7029392"
    ],
    "placetype": [
      "aat:300006191"
    ],
    "id": 2634403,
    "name:xx": "Russellville Watersupply Reservoir"
  }
}
