{
  "type": "FeatureCollection",
  "features": [
    {
      "geometry": {
        "type": "Point",
        "coordinates": [
          -157.8,
          21.2667
        ]
      },
      "type": "Feature",
      "properties": {
        "hierarchy": [
          "tgn:2024921",
          "tgn:1002483",
          "tgn:7019080",
          "tgn:1000001",
          "tgn:7013718",
          "tgn:7012149",
          "tgn:7007249",
          "tgn:7029392"
        ],
        "placetype": [
          "aat:300000745"
        ],
        "id": 2024921,
        "name:xx": "Kaimuki"
      }
    },
    {
      "geometry": {
        "type": "Point",
        "coordinates": [
          -157.8667,
          21.3333
        ]
      },
      "type": "Feature",
      "properties": {
        "hierarchy": [
          "tgn:2024922",
          "tgn:1002483",
          "tgn:7019080",
          "tgn:1000001",
          "tgn:7013718",
          "tgn:7012149",
          "tgn:7007249",
          "tgn:7029392"
        ],
        "placetype": [
          "aat:300000745"
        ],
        "id": 2024922,
        "name:xx": "Kalihi"
      }
    },
    {
      "geometry": {
        "type": "Point",
        "coordinates": [
          -157.85,
          21.3333
        ]
      },
      "type": "Feature",
      "properties": {
        "hierarchy": [
          "tgn:2024925",
          "tgn:1002483",
          "tgn:7019080",
          "tgn:1000001",
          "tgn:7013718",
          "tgn:7012149",
          "tgn:7007249",
          "tgn:7029392"
        ],
        "placetype": [
          "aat:300000745"
        ],
        "id": 2024925,
        "name:xx": "Kamehameha Heights"
      }
    }
  ]
}
