{
  "geometry": {
    "type": "Point",
    "coordinates": [
      -123.1167,
      45.95
    ]
  },
  "type": "Feature",
  "properties": {
    "hierarchy": [
      "tgn:2318216",
      "tgn:1000001",
      "tgn:1002293",
      "tgn:7012149",
      "tgn:7007708",
      "tgn:7029392"
    ],
    "placetype": [
      "aat:300008798"
    ],
    "id": 2318216,
    "name:xx": "Enterprise Point"
  }
}
