{
  "geometry": {
    "type": "Point",
    "coordinates": [
      82.483333,
      18.55
    ]
  },
  "type": "Feature",
  "properties": {
    "hierarchy": [
      "tgn:7574604",
      "tgn:1000004",
      "tgn:7000198",
      "tgn:7016694",
      "tgn:7029392"
    ],
    "placetype": [
      "aat:300006191"
    ],
    "name:en": "Māchhakund Reservoir",
    "id": 7574604
  }
}
