{
  "geometry": {
    "type": "Point",
    "coordinates": [
      -92.45,
      30.3167
    ]
  },
  "type": "Feature",
  "properties": {
    "hierarchy": [
      "tgn:2589913",
      "tgn:2000854",
      "tgn:1000001",
      "tgn:7012149",
      "tgn:7007256",
      "tgn:7029392"
    ],
    "placetype": [
      "aat:300008699"
    ],
    "id": 2589913,
    "name:xx": "Pointe Aux Loups, Bayou"
  }
}
