{
  "geometry": {
    "type": "Point",
    "coordinates": [
      -80.25,
      34.6333
    ]
  },
  "type": "Feature",
  "properties": {
    "hierarchy": [
      "tgn:2608135",
      "tgn:1000001",
      "tgn:2001737",
      "tgn:7012149",
      "tgn:7007712",
      "tgn:7029392"
    ],
    "placetype": [
      "aat:300008699"
    ],
    "id": 2608135,
    "name:xx": "Rattlesnake Branch"
  }
}
