{
  "geometry": {
    "type": "Point",
    "coordinates": [
      -75.7667,
      38.2833
    ]
  },
  "type": "Feature",
  "properties": {
    "hierarchy": [
      "tgn:2450135",
      "tgn:1000001",
      "tgn:1003023",
      "tgn:7012149",
      "tgn:7007516",
      "tgn:7029392"
    ],
    "placetype": [
      "aat:300008706"
    ],
    "id": 2450135,
    "name:xx": "Line Creek"
  }
}
