{
  "geometry": {
    "type": "Point",
    "coordinates": [
      -92.3833,
      35.1833
    ]
  },
  "type": "Feature",
  "properties": {
    "hierarchy": [
      "tgn:2009552",
      "tgn:1000001",
      "tgn:7016172",
      "tgn:7012149",
      "tgn:2000127",
      "tgn:7029392"
    ],
    "placetype": [
      "aat:300008347"
    ],
    "id": 2009552,
    "name:xx": "Springhill"
  }
}
