{
  "geometry": {
    "type": "Point",
    "coordinates": [
      -112.6667,
      34.6167
    ]
  },
  "type": "Feature",
  "properties": {
    "hierarchy": [
      "tgn:2725267",
      "tgn:1000001",
      "tgn:7006451",
      "tgn:7012149",
      "tgn:2000103",
      "tgn:7029392"
    ],
    "placetype": [
      "aat:300008798"
    ],
    "id": 2725267,
    "name:xx": "Tonto Mountain"
  }
}
