{
  "geometry": {
    "type": "Point",
    "coordinates": [
      -112.65,
      42.8667
    ]
  },
  "type": "Feature",
  "properties": {
    "hierarchy": [
      "tgn:2026110",
      "tgn:1000001",
      "tgn:7012149",
      "tgn:2000490",
      "tgn:7007250",
      "tgn:7029392"
    ],
    "placetype": [
      "aat:300387016"
    ],
    "id": 2026110,
    "name:xx": "Schiller"
  }
}
