{
  "geometry": {
    "type": "Point",
    "coordinates": [
      -73.7667,
      44.1167
    ]
  },
  "type": "Feature",
  "properties": {
    "hierarchy": [
      "tgn:2409295",
      "tgn:1000001",
      "tgn:7012149",
      "tgn:2001461",
      "tgn:7007568",
      "tgn:7029392"
    ],
    "placetype": [
      "aat:300008699"
    ],
    "id": 2409295,
    "name:xx": "Icy Brook"
  }
}
