{
  "geometry": {
    "type": "Point",
    "coordinates": [
      -91.8667,
      35.3333
    ]
  },
  "type": "Feature",
  "properties": {
    "hierarchy": [
      "tgn:2009221",
      "tgn:1000001",
      "tgn:7016172",
      "tgn:7012149",
      "tgn:2000177",
      "tgn:7029392"
    ],
    "placetype": [
      "aat:300008347",
      "aat:300387210"
    ],
    "id": 2009221,
    "name:xx": "Pickens"
  }
}
