{
  "geometry": {
    "type": "Point",
    "coordinates": [
      -1.75,
      40.55
    ]
  },
  "type": "Feature",
  "properties": {
    "hierarchy": [
      "tgn:7301672",
      "tgn:7002759",
      "tgn:7002843",
      "tgn:1000003",
      "tgn:1000095",
      "tgn:7029392"
    ],
    "placetype": [
      "aat:300008697"
    ],
    "id": 7301672,
    "name:xx": "Minillas, Fuente de las"
  }
}
