{
  "geometry": {
    "type": "Point",
    "coordinates": [
      -9.03,
      38.625
    ]
  },
  "type": "Feature",
  "properties": {
    "hierarchy": [
      "tgn:1049927",
      "tgn:1000003",
      "tgn:1000929",
      "tgn:1000090",
      "tgn:7029392"
    ],
    "placetype": [
      "aat:300008347"
    ],
    "id": 1049927,
    "name:xx": "Santo António da Charneca"
  }
}
