{
  "geometry": {
    "type": "Point",
    "coordinates": [
      -106.7667,
      43.9167
    ]
  },
  "type": "Feature",
  "properties": {
    "hierarchy": [
      "tgn:2476848",
      "tgn:1000001",
      "tgn:7012149",
      "tgn:2002374",
      "tgn:7007923",
      "tgn:7029392"
    ],
    "placetype": [
      "aat:300006191"
    ],
    "id": 2476848,
    "name:xx": "Lyle Reservoir"
  }
}
