{
  "type": "FeatureCollection",
  "features": [
    {
      "geometry": {
        "type": "Point",
        "coordinates": [
          -74.4,
          40.5667
        ]
      },
      "type": "Feature",
      "properties": {
        "hierarchy": [
          "tgn:2066220",
          "tgn:1000001",
          "tgn:1002666",
          "tgn:7012149",
          "tgn:7007565",
          "tgn:7029392"
        ],
        "placetype": [
          "aat:300008347"
        ],
        "id": 2066220,
        "name:xx": "South Plainfield"
      }
    },
    {
      "geometry": {
        "type": "Point",
        "coordinates": [
          -74.3833,
          40.4333
        ]
      },
      "type": "Feature",
      "properties": {
        "hierarchy": [
          "tgn:2066221",
          "tgn:1000001",
          "tgn:1002666",
          "tgn:7012149",
          "tgn:7007565",
          "tgn:7029392"
        ],
        "placetype": [
          "aat:300008347"
        ],
        "id": 2066221,
        "name:xx": "South River"
      }
    },
    {
      "geometry": {
        "type": "Point",
        "coordinates": [
          -74.0667,
          39.9
        ]
      },
      "type": "Feature",
      "properties": {
        "hierarchy": [
          "tgn:2066222",
          "tgn:1000001",
          "tgn:1002738",
          "tgn:7012149",
          "tgn:7007565",
          "tgn:7029392"
        ],
        "placetype": [
          "aat:300008347"
        ],
        "id": 2066222,
        "name:xx": "South Seaside Park"
      }
    },
    {
      "geometry": {
        "type": "Point",
        "coordinates": [
          -74.75,
          39.1667
        ]
      },
      "type": "Feature",
      "properties": {
        "hierarchy": [
          "tgn:2066223",
          "tgn:1002232",
          "tgn:1000001",
          "tgn:7012149",
          "tgn:7007565",
          "tgn:7029392"
        ],
        "placetype": [
          "aat:300008347"
        ],
        "id": 2066223,
        "name:xx": "South Seaville"
      }
    },
    {
      "geometry": {
        "type": "Point",
        "coordinates": [
          -74.2,
          39.9333
        ]
      },
      "type": "Feature",
      "properties": {
        "hierarchy": [
          "tgn:2066224",
          "tgn:1000001",
          "tgn:1002738",
          "tgn:7012149",
          "tgn:7007565",
          "tgn:7029392"
        ],
        "placetype": [
          "aat:300008347"
        ],
        "id": 2066224,
        "name:xx": "South Toms River"
      }
    },
    {
      "geometry": {
        "type": "Point",
        "coordinates": [
          -74.35,
          40.4
        ]
      },
      "type": "Feature",
      "properties": {
        "hierarchy": [
          "tgn:2066226",
          "tgn:1000001",
          "tgn:1002666",
          "tgn:7012149",
          "tgn:7007565",
          "tgn:7029392"
        ],
        "placetype": [
          "aat:300008347"
        ],
        "id": 2066226,
        "name:xx": "South Old Bridge"
      }
    },
    {
      "geometry": {
        "type": "Point",
        "coordinates": [
          -74.6333,
          41.0333
        ]
      },
      "type": "Feature",
      "properties": {
        "hierarchy": [
          "tgn:2066227",
          "tgn:1000001",
          "tgn:1002934",
          "tgn:7012149",
          "tgn:7007565",
          "tgn:7029392"
        ],
        "placetype": [
          "aat:300008347"
        ],
        "id": 2066227,
        "name:xx": "Sparta"
      }
    }
  ]
}
