{
  "geometry": {
    "type": "Point",
    "coordinates": [
      -70.0667,
      -51.5333
    ]
  },
  "type": "Feature",
  "properties": {
    "hierarchy": [
      "tgn:1122204",
      "tgn:7006477",
      "tgn:1001522",
      "tgn:1000002",
      "tgn:7029392"
    ],
    "placetype": [
      "aat:300008707"
    ],
    "id": 1122204,
    "name:xx": "Brazo Sur del Rio Coig"
  }
}
