{
  "geometry": {
    "type": "Point",
    "coordinates": [
      24.3667,
      -29.4167
    ]
  },
  "type": "Feature",
  "properties": {
    "hierarchy": [
      "tgn:1092864",
      "tgn:7001242",
      "tgn:7017582",
      "tgn:1000193",
      "tgn:7029392"
    ],
    "placetype": [
      "aat:300008347"
    ],
    "id": 1092864,
    "name:xx": "Belmont"
  }
}
