{
  "geometry": {
    "type": "Point",
    "coordinates": [
      -121.8667,
      37.8167
    ]
  },
  "type": "Feature",
  "properties": {
    "hierarchy": [
      "tgn:1132233",
      "tgn:1000001",
      "tgn:7012149",
      "tgn:7007157",
      "tgn:7029392"
    ],
    "placetype": [
      "aat:300008706"
    ],
    "id": 1132233,
    "name:xx": "Alamo Creek"
  }
}
