{
  "geometry": {
    "type": "Point",
    "coordinates": [
      -83.6833,
      42.7833
    ]
  },
  "type": "Feature",
  "properties": {
    "hierarchy": [
      "tgn:2762954",
      "tgn:1000001",
      "tgn:7012149",
      "tgn:1002406",
      "tgn:7007520",
      "tgn:7029392"
    ],
    "placetype": [
      "aat:300008680"
    ],
    "id": 2762954,
    "name:xx": "Westman Lake"
  }
}
