{
  "geometry": {
    "type": "Point",
    "coordinates": [
      -111.65,
      41.7667
    ]
  },
  "type": "Feature",
  "properties": {
    "hierarchy": [
      "tgn:2238467",
      "tgn:1000001",
      "tgn:2002103",
      "tgn:7012149",
      "tgn:7007827",
      "tgn:7029392"
    ],
    "placetype": [
      "aat:300008347"
    ],
    "id": 2238467,
    "name:xx": "Chokecherry Summer Home Area"
  }
}
