{
  "geometry": {
    "type": "Point",
    "coordinates": [
      -93.0833,
      43.8333
    ]
  },
  "type": "Feature",
  "properties": {
    "hierarchy": [
      "tgn:2281685",
      "tgn:1000001",
      "tgn:2001022",
      "tgn:7012149",
      "tgn:7007521",
      "tgn:7029392"
    ],
    "placetype": [
      "aat:300008706"
    ],
    "id": 2281685,
    "name:xx": "Deer Creek"
  }
}
