{
  "geometry": {
    "type": "Point",
    "coordinates": [
      -118.5333,
      35.6833
    ]
  },
  "type": "Feature",
  "properties": {
    "hierarchy": [
      "tgn:2148333",
      "tgn:1000001",
      "tgn:7012149",
      "tgn:1002545",
      "tgn:7007157",
      "tgn:7029392"
    ],
    "placetype": [
      "aat:300008761"
    ],
    "id": 2148333,
    "name:xx": "Barn Canyon"
  }
}
