{
  "geometry": {
    "type": "Point",
    "coordinates": [
      -85.9333,
      30.85
    ]
  },
  "type": "Feature",
  "properties": {
    "hierarchy": [
      "tgn:2152195",
      "tgn:1000001",
      "tgn:2000272",
      "tgn:7012149",
      "tgn:7007240",
      "tgn:7029392"
    ],
    "placetype": [
      "aat:300008699"
    ],
    "id": 2152195,
    "name:xx": "Bay Branch"
  }
}
