{
  "geometry": {
    "type": "Point",
    "coordinates": [
      34.46481,
      28.96919
    ]
  },
  "type": "Feature",
  "properties": {
    "hierarchy": [
      "tgn:7536866",
      "tgn:7001242",
      "tgn:7016833",
      "tgn:7001336",
      "tgn:7029392"
    ],
    "placetype": [
      "aat:300379998"
    ],
    "name:en": "Judayrah, Wādī",
    "id": 7536866
  }
}
