{
  "geometry": {
    "type": "Point",
    "coordinates": [
      -108.5667,
      43.6667
    ]
  },
  "type": "Feature",
  "properties": {
    "hierarchy": [
      "tgn:2472611",
      "tgn:1000001",
      "tgn:7012149",
      "tgn:2002373",
      "tgn:7007923",
      "tgn:7029392"
    ],
    "placetype": [
      "aat:300008697"
    ],
    "id": 2472611,
    "name:xx": "Love Spring"
  }
}
