{
  "geometry": {
    "type": "Point",
    "coordinates": [
      -79.9333,
      40.8833
    ]
  },
  "type": "Feature",
  "properties": {
    "hierarchy": [
      "tgn:2702397",
      "tgn:1000001",
      "tgn:1002217",
      "tgn:7012149",
      "tgn:7007710",
      "tgn:7029392"
    ],
    "placetype": [
      "aat:300008699"
    ],
    "id": 2702397,
    "name:xx": "Sullivan Run"
  }
}
