{
  "geometry": {
    "type": "Point",
    "coordinates": [
      175.45,
      -36.85
    ]
  },
  "type": "Feature",
  "properties": {
    "hierarchy": [
      "tgn:7517544",
      "tgn:1008380",
      "tgn:1000226",
      "tgn:7018426",
      "tgn:1000006",
      "tgn:7029392"
    ],
    "placetype": [
      "aat:300008678"
    ],
    "name:en": "Manaia Harbour",
    "id": 7517544
  }
}
