{
  "geometry": {
    "type": "Point",
    "coordinates": [
      72.6167,
      40.7667
    ]
  },
  "type": "Feature",
  "properties": {
    "hierarchy": [
      "tgn:1054765",
      "tgn:7012245",
      "tgn:1000004",
      "tgn:7006661",
      "tgn:7029392"
    ],
    "placetype": [
      "aat:300008347"
    ],
    "id": 1054765,
    "name:xx": "Yuzhnyy Alamyshik"
  }
}
