{
  "geometry": {
    "type": "Point",
    "coordinates": [
      -110.7167,
      32.5833
    ]
  },
  "type": "Feature",
  "properties": {
    "hierarchy": [
      "tgn:2609398",
      "tgn:1000001",
      "tgn:7006451",
      "tgn:7012149",
      "tgn:2000101",
      "tgn:7029392"
    ],
    "placetype": [
      "aat:300008697"
    ],
    "id": 2609398,
    "name:xx": "Ray Spring"
  }
}
