{
  "geometry": {
    "type": "Point",
    "coordinates": [
      13.455,
      46.476389
    ]
  },
  "type": "Feature",
  "properties": {
    "hierarchy": [
      "tgn:7036364",
      "tgn:1003506",
      "tgn:1000003",
      "tgn:7002993",
      "tgn:1000080",
      "tgn:7029392"
    ],
    "placetype": [
      "aat:300008795"
    ],
    "id": 7036364,
    "name:xx": "Jôf di Miezegnot"
  }
}
