{
  "type": "FeatureCollection",
  "features": [
    {
      "geometry": {
        "type": "Point",
        "coordinates": [
          40.8333,
          13.5
        ]
      },
      "type": "Feature",
      "properties": {
        "hierarchy": [
          "tgn:1001570",
          "tgn:7001242",
          "tgn:7000489",
          "tgn:7029392"
        ],
        "placetype": [
          "aat:300387064",
          "aat:300236112"
        ],
        "id": 1001570,
        "name:xx": "Tigray Kifle Håger"
      }
    },
    {
      "geometry": {
        "type": "Point",
        "coordinates": [
          -9.5,
          29.5833
        ]
      },
      "type": "Feature",
      "properties": {
        "hierarchy": [
          "tgn:1001572",
          "tgn:7001242",
          "tgn:1000179",
          "tgn:7593686",
          "tgn:7029392"
        ],
        "placetype": [
          "aat:300387064",
          "aat:300387145",
          "aat:300000774"
        ],
        "id": 1001572,
        "name:xx": "Tiznit, Province de"
      }
    },
    {
      "geometry": {
        "type": "Point",
        "coordinates": [
          49,
          -18
        ]
      },
      "type": "Feature",
      "properties": {
        "hierarchy": [
          "tgn:1001573",
          "tgn:7001242",
          "tgn:1000173",
          "tgn:7029392"
        ],
        "placetype": [
          "aat:300387064",
          "aat:300000774"
        ],
        "id": 1001573,
        "name:xx": "Toamasina, Faritanin' i"
      }
    },
    {
      "geometry": {
        "type": "Point",
        "coordinates": [
          36.5833,
          40.4167
        ]
      },
      "type": "Feature",
      "properties": {
        "hierarchy": [
          "tgn:1001574",
          "tgn:1000004",
          "tgn:7018454",
          "tgn:1000144",
          "tgn:7029392"
        ],
        "placetype": [
          "aat:300387064",
          "aat:300000774"
        ],
        "id": 1001574,
        "name:xx": "Tokat"
      }
    },
    {
      "geometry": {
        "type": "Point",
        "coordinates": [
          45,
          -21
        ]
      },
      "type": "Feature",
      "properties": {
        "hierarchy": [
          "tgn:1001575",
          "tgn:7001242",
          "tgn:1000173",
          "tgn:7029392"
        ],
        "placetype": [
          "aat:300387064",
          "aat:300000774"
        ],
        "id": 1001575,
        "name:xx": "Toliara, Faritanin' i"
      }
    },
    {
      "geometry": {
        "type": "Point",
        "coordinates": [
          39.812,
          40.869
        ]
      },
      "type": "Feature",
      "properties": {
        "hierarchy": [
          "tgn:1001576",
          "tgn:1000004",
          "tgn:7018454",
          "tgn:1000144",
          "tgn:7029392"
        ],
        "placetype": [
          "aat:300387064",
          "aat:300000774"
        ],
        "id": 1001576,
        "name:xx": "Trabzon"
      }
    },
    {
      "geometry": {
        "type": "Point",
        "coordinates": [
          92,
          24
        ]
      },
      "type": "Feature",
      "properties": {
        "hierarchy": [
          "tgn:1001578",
          "tgn:1000004",
          "tgn:7000198",
          "tgn:7029392"
        ],
        "placetype": [
          "aat:300387064",
          "aat:300000776",
          "aat:300387122"
        ],
        "id": 1001578,
        "name:xx": "Tripura"
      }
    },
    {
      "geometry": {
        "type": "Point",
        "coordinates": [
          -65.5,
          -27
        ]
      },
      "type": "Feature",
      "properties": {
        "hierarchy": [
          "tgn:1001579",
          "tgn:7006477",
          "tgn:1000002",
          "tgn:7029392"
        ],
        "placetype": [
          "aat:300387064",
          "aat:300000774"
        ],
        "id": 1001579,
        "name:xx": "Tucumán"
      }
    }
  ]
}
