{
  "geometry": {
    "type": "Point",
    "coordinates": [
      2.55,
      45.65
    ]
  },
  "type": "Feature",
  "properties": {
    "hierarchy": [
      "tgn:1032257",
      "tgn:7002871",
      "tgn:1000003",
      "tgn:1000070",
      "tgn:7029392"
    ],
    "placetype": [
      "aat:300008347"
    ],
    "id": 1032257,
    "name:xx": "Bourg-Lastic"
  }
}
