{
  "geometry": {
    "type": "Point",
    "coordinates": [
      -98.6833,
      33.7333
    ]
  },
  "type": "Feature",
  "properties": {
    "hierarchy": [
      "tgn:2273876",
      "tgn:2001934",
      "tgn:1000001",
      "tgn:7012149",
      "tgn:7007826",
      "tgn:7029392"
    ],
    "placetype": [
      "aat:300008347"
    ],
    "id": 2273876,
    "name:xx": "Dads Corner"
  }
}
