{
  "geometry": {
    "type": "Point",
    "coordinates": [
      -112.1667,
      40.55
    ]
  },
  "type": "Feature",
  "properties": {
    "hierarchy": [
      "tgn:2339910",
      "tgn:1000001",
      "tgn:7012149",
      "tgn:2002118",
      "tgn:7007827",
      "tgn:7029392"
    ],
    "placetype": [
      "aat:300008798"
    ],
    "id": 2339910,
    "name:xx": "Freeman Peak"
  }
}
