{
  "type": "FeatureCollection",
  "features": [
    {
      "geometry": {
        "type": "Point",
        "coordinates": [
          6.1333,
          46.8
        ]
      },
      "type": "Feature",
      "properties": {
        "hierarchy": [
          "tgn:1034380",
          "tgn:1000003",
          "tgn:7002881",
          "tgn:1000070",
          "tgn:7029392"
        ],
        "placetype": [
          "aat:300008347"
        ],
        "id": 1034380,
        "name:xx": "Mignovillard"
      }
    },
    {
      "geometry": {
        "type": "Point",
        "coordinates": [
          6,
          46.3667
        ]
      },
      "type": "Feature",
      "properties": {
        "hierarchy": [
          "tgn:1034381",
          "tgn:1000003",
          "tgn:1000070",
          "tgn:7002897",
          "tgn:7029392"
        ],
        "placetype": [
          "aat:300008347"
        ],
        "id": 1034381,
        "name:xx": "Mijoux"
      }
    },
    {
      "geometry": {
        "type": "Point",
        "coordinates": [
          4.3,
          43.7833
        ]
      },
      "type": "Feature",
      "properties": {
        "hierarchy": [
          "tgn:1034382",
          "tgn:1000003",
          "tgn:7002885",
          "tgn:1000070",
          "tgn:7029392"
        ],
        "placetype": [
          "aat:300008347"
        ],
        "id": 1034382,
        "name:xx": "Milhaud"
      }
    },
    {
      "geometry": {
        "type": "Point",
        "coordinates": [
          1.7333,
          48.8
        ]
      },
      "type": "Feature",
      "properties": {
        "hierarchy": [
          "tgn:1034384",
          "tgn:1000003",
          "tgn:7002883",
          "tgn:1000070",
          "tgn:7029392"
        ],
        "placetype": [
          "aat:300008347"
        ],
        "id": 1034384,
        "name:xx": "Millemont"
      }
    },
    {
      "geometry": {
        "type": "Point",
        "coordinates": [
          4.7,
          46.35
        ]
      },
      "type": "Feature",
      "properties": {
        "hierarchy": [
          "tgn:1034385",
          "tgn:1000003",
          "tgn:7002875",
          "tgn:1000070",
          "tgn:7029392"
        ],
        "placetype": [
          "aat:300008347"
        ],
        "id": 1034385,
        "name:xx": "Milly-Lamartine"
      }
    },
    {
      "geometry": {
        "type": "Point",
        "coordinates": [
          2.05,
          48.7333
        ]
      },
      "type": "Feature",
      "properties": {
        "hierarchy": [
          "tgn:1034387",
          "tgn:1000003",
          "tgn:7002883",
          "tgn:1000070",
          "tgn:7029392"
        ],
        "placetype": [
          "aat:300008347"
        ],
        "id": 1034387,
        "name:xx": "Milon-la-Chapelle"
      }
    },
    {
      "geometry": {
        "type": "Point",
        "coordinates": [
          -1.2333,
          44.2
        ]
      },
      "type": "Feature",
      "properties": {
        "hierarchy": [
          "tgn:1034388",
          "tgn:7002878",
          "tgn:1000003",
          "tgn:1000070",
          "tgn:7029392"
        ],
        "placetype": [
          "aat:300008347"
        ],
        "id": 1034388,
        "name:xx": "Mimizan"
      }
    },
    {
      "geometry": {
        "type": "Point",
        "coordinates": [
          5.6333,
          43.7
        ]
      },
      "type": "Feature",
      "properties": {
        "hierarchy": [
          "tgn:1034389",
          "tgn:1000003",
          "tgn:1000070",
          "tgn:7002895",
          "tgn:7029392"
        ],
        "placetype": [
          "aat:300008347"
        ],
        "id": 1034389,
        "name:xx": "Mirabeau"
      }
    }
  ]
}
