{
  "geometry": {
    "type": "Point",
    "coordinates": [
      -101.6833,
      33.5333
    ]
  },
  "type": "Feature",
  "properties": {
    "hierarchy": [
      "tgn:2204819",
      "tgn:1000001",
      "tgn:7012149",
      "tgn:2002032",
      "tgn:7007826",
      "tgn:7029392"
    ],
    "placetype": [
      "aat:300008680"
    ],
    "id": 2204819,
    "name:xx": "Buffalo Springs Lake"
  }
}
