{
  "type": "FeatureCollection",
  "features": [
    {
      "geometry": {
        "type": "Point",
        "coordinates": [
          23.9,
          43.1333
        ]
      },
      "type": "Feature",
      "properties": {
        "hierarchy": [
          "tgn:1026950",
          "tgn:7593877",
          "tgn:1000003",
          "tgn:7006413",
          "tgn:7029392"
        ],
        "placetype": [
          "aat:300008347"
        ],
        "id": 1026950,
        "name:xx": "Roman"
      }
    },
    {
      "geometry": {
        "type": "Point",
        "coordinates": [
          23.5667,
          42.3167
        ]
      },
      "type": "Feature",
      "properties": {
        "hierarchy": [
          "tgn:1026952",
          "tgn:7018763",
          "tgn:1000003",
          "tgn:7006413",
          "tgn:7029392"
        ],
        "placetype": [
          "aat:300008347"
        ],
        "id": 1026952,
        "name:xx": "Samokov"
      }
    },
    {
      "geometry": {
        "type": "Point",
        "coordinates": [
          23.2667,
          42.5833
        ]
      },
      "type": "Feature",
      "properties": {
        "hierarchy": [
          "tgn:1026953",
          "tgn:7593860",
          "tgn:1000003",
          "tgn:7006413",
          "tgn:7029392"
        ],
        "placetype": [
          "aat:300008347"
        ],
        "id": 1026953,
        "name:xx": "Sandanski"
      }
    },
    {
      "geometry": {
        "type": "Point",
        "coordinates": [
          27.1167,
          43
        ]
      },
      "type": "Feature",
      "properties": {
        "hierarchy": [
          "tgn:1026954",
          "tgn:7593862",
          "tgn:1000003",
          "tgn:7006413",
          "tgn:7029392"
        ],
        "placetype": [
          "aat:300008347"
        ],
        "id": 1026954,
        "name:xx": "Sevlievo"
      }
    },
    {
      "geometry": {
        "type": "Point",
        "coordinates": [
          26.3167,
          42.6667
        ]
      },
      "type": "Feature",
      "properties": {
        "hierarchy": [
          "tgn:1026956",
          "tgn:7593871",
          "tgn:1000003",
          "tgn:7006413",
          "tgn:7029392"
        ],
        "placetype": [
          "aat:300387277",
          "aat:300008347",
          "aat:300008389",
          "aat:300005135",
          "aat:300387223",
          "aat:300387235",
          "aat:300387270",
          "aat:300387302"
        ],
        "id": 1026956,
        "name:xx": "Sliven"
      }
    },
    {
      "geometry": {
        "type": "Point",
        "coordinates": [
          23,
          42.8333
        ]
      },
      "type": "Feature",
      "properties": {
        "hierarchy": [
          "tgn:1026957",
          "tgn:7018763",
          "tgn:1000003",
          "tgn:7006413",
          "tgn:7029392"
        ],
        "placetype": [
          "aat:300008347"
        ],
        "id": 1026957,
        "name:xx": "Slivnitsa"
      }
    },
    {
      "geometry": {
        "type": "Point",
        "coordinates": [
          24.7,
          41.5667
        ]
      },
      "type": "Feature",
      "properties": {
        "hierarchy": [
          "tgn:1026958",
          "tgn:7593872",
          "tgn:1000003",
          "tgn:7006413",
          "tgn:7029392"
        ],
        "placetype": [
          "aat:300387277",
          "aat:300008347",
          "aat:300387223",
          "aat:300387305",
          "aat:300008375",
          "aat:300387280"
        ],
        "name:bg": "Smolyan",
        "id": 1026958
      }
    }
  ]
}
