{
  "geometry": {
    "type": "Point",
    "coordinates": [
      -94.8833,
      38.8167
    ]
  },
  "type": "Feature",
  "properties": {
    "hierarchy": [
      "tgn:2452776",
      "tgn:1000001",
      "tgn:7012149",
      "tgn:7007254",
      "tgn:7029392"
    ],
    "placetype": [
      "aat:300008706"
    ],
    "id": 2452776,
    "name:xx": "Little Bull Creek"
  }
}
