{
  "geometry": {
    "type": "Point",
    "coordinates": [
      -123.3333,
      44.7833
    ]
  },
  "type": "Feature",
  "properties": {
    "hierarchy": [
      "tgn:2608918",
      "tgn:1000001",
      "tgn:7012149",
      "tgn:1002794",
      "tgn:7007708",
      "tgn:7029392"
    ],
    "placetype": [
      "aat:300006191"
    ],
    "id": 2608918,
    "name:xx": "Ratzlaff Reservoir"
  }
}
