{
  "type": "FeatureCollection",
  "features": [
    {
      "geometry": {
        "type": "Point",
        "coordinates": [
          -3.033333,
          58.616667
        ]
      },
      "type": "Feature",
      "properties": {
        "hierarchy": [
          "tgn:7442400",
          "tgn:7002444",
          "tgn:1000003",
          "tgn:7008082",
          "tgn:7008591",
          "tgn:7029392"
        ],
        "placetype": [
          "aat:300132316"
        ],
        "name:en": "Wife Geo",
        "id": 7442400
      }
    },
    {
      "geometry": {
        "type": "Point",
        "coordinates": [
          -1.1,
          51.133333
        ]
      },
      "type": "Feature",
      "properties": {
        "hierarchy": [
          "tgn:7442401",
          "tgn:7002445",
          "tgn:1000003",
          "tgn:7008139",
          "tgn:7008591",
          "tgn:7029392"
        ],
        "placetype": [
          "aat:300008347"
        ],
        "name:en": "Wield",
        "id": 7442401
      }
    },
    {
      "geometry": {
        "type": "Point",
        "coordinates": [
          -5.883333,
          54.183333
        ]
      },
      "type": "Feature",
      "properties": {
        "hierarchy": [
          "tgn:7442403",
          "tgn:7002448",
          "tgn:7008698",
          "tgn:1000003",
          "tgn:7008591",
          "tgn:7029392"
        ],
        "placetype": [
          "aat:300008347"
        ],
        "name:en": "Widows Row",
        "id": 7442403
      }
    },
    {
      "geometry": {
        "type": "Point",
        "coordinates": [
          -1.766667,
          52.383333
        ]
      },
      "type": "Feature",
      "properties": {
        "hierarchy": [
          "tgn:7442404",
          "tgn:7002445",
          "tgn:7019027",
          "tgn:1000003",
          "tgn:7029506",
          "tgn:7008591",
          "tgn:7029392"
        ],
        "placetype": [
          "aat:300007783"
        ],
        "name:en": "Widney Manor Station",
        "id": 7442404
      }
    }
  ]
}
