{
  "geometry": {
    "type": "Point",
    "coordinates": [
      14.7167,
      -11.55
    ]
  },
  "type": "Feature",
  "properties": {
    "hierarchy": [
      "tgn:1087618",
      "tgn:7001242",
      "tgn:1000149",
      "tgn:1000835",
      "tgn:7029392"
    ],
    "placetype": [
      "aat:300008347"
    ],
    "id": 1087618,
    "name:xx": "Amboíva"
  }
}
