{
  "geometry": {
    "type": "Point",
    "coordinates": [
      -52.1833,
      -21.8167
    ]
  },
  "type": "Feature",
  "properties": {
    "hierarchy": [
      "tgn:1129662",
      "tgn:1001945",
      "tgn:1000047",
      "tgn:7002457",
      "tgn:1000002",
      "tgn:7029392"
    ],
    "placetype": [
      "aat:300008707"
    ],
    "id": 1129662,
    "name:xx": "Santo Anastácio"
  }
}
