{
  "geometry": {
    "type": "Point",
    "coordinates": [
      -81.5667,
      33.0167
    ]
  },
  "type": "Feature",
  "properties": {
    "hierarchy": [
      "tgn:2623951",
      "tgn:1000001",
      "tgn:2000308",
      "tgn:7012149",
      "tgn:7007248",
      "tgn:7029392"
    ],
    "placetype": [
      "aat:300008347"
    ],
    "id": 2623951,
    "name:xx": "Rock Fence Crossroads"
  }
}
