{
  "geometry": {
    "type": "Point",
    "coordinates": [
      -76.6333,
      35.1833
    ]
  },
  "type": "Feature",
  "properties": {
    "hierarchy": [
      "tgn:2163079",
      "tgn:1000001",
      "tgn:7012149",
      "tgn:2001526",
      "tgn:7007709",
      "tgn:7029392"
    ],
    "placetype": [
      "aat:300008706"
    ],
    "id": 2163079,
    "name:xx": "Bennett Creek"
  }
}
