{
  "geometry": {
    "type": "Point",
    "coordinates": [
      -91.6667,
      30.8833
    ]
  },
  "type": "Feature",
  "properties": {
    "hierarchy": [
      "tgn:2773311",
      "tgn:1000001",
      "tgn:7012149",
      "tgn:2000892",
      "tgn:7007256",
      "tgn:7029392"
    ],
    "placetype": [
      "aat:300008347"
    ],
    "id": 2773311,
    "name:xx": "Williamsport"
  }
}
