{
  "geometry": {
    "type": "Point",
    "coordinates": [
      -71.8167,
      43.4333
    ]
  },
  "type": "Feature",
  "properties": {
    "hierarchy": [
      "tgn:2605299",
      "tgn:1000001",
      "tgn:2001425",
      "tgn:7012149",
      "tgn:7007564",
      "tgn:7029392"
    ],
    "placetype": [
      "aat:300008863"
    ],
    "id": 2605299,
    "name:xx": "Ragged Mountain State Forest"
  }
}
