{
  "geometry": {
    "type": "Point",
    "coordinates": [
      -83.5667,
      35.5167
    ]
  },
  "type": "Feature",
  "properties": {
    "hierarchy": [
      "tgn:2646843",
      "tgn:1000001",
      "tgn:7012149",
      "tgn:2001543",
      "tgn:7007709",
      "tgn:7029392"
    ],
    "placetype": [
      "aat:300266640"
    ],
    "id": 2646843,
    "name:xx": "Scarlet Ridge"
  }
}
