{
  "geometry": {
    "type": "Point",
    "coordinates": [
      -111.4667,
      41.9167
    ]
  },
  "type": "Feature",
  "properties": {
    "hierarchy": [
      "tgn:2510421",
      "tgn:1000001",
      "tgn:2002103",
      "tgn:7012149",
      "tgn:7007827",
      "tgn:7029392"
    ],
    "placetype": [
      "aat:300386845"
    ],
    "id": 2510421,
    "name:xx": "Middle Sink"
  }
}
