{
  "geometry": {
    "type": "Point",
    "coordinates": [
      -74.5667,
      39.9667
    ]
  },
  "type": "Feature",
  "properties": {
    "hierarchy": [
      "tgn:2544290",
      "tgn:1000001",
      "tgn:7012149",
      "tgn:7007565",
      "tgn:7029392"
    ],
    "placetype": [
      "aat:300008706"
    ],
    "id": 2544290,
    "name:xx": "North Branch Rancocas Creek"
  }
}
