{
  "geometry": {
    "type": "Point",
    "coordinates": [
      -92.0333,
      35.7333
    ]
  },
  "type": "Feature",
  "properties": {
    "hierarchy": [
      "tgn:2387228",
      "tgn:1000001",
      "tgn:7016172",
      "tgn:7012149",
      "tgn:2000173",
      "tgn:7029392"
    ],
    "placetype": [
      "aat:300008761"
    ],
    "id": 2387228,
    "name:xx": "Hess Hollow"
  }
}
