{
  "type": "FeatureCollection",
  "features": [
    {
      "geometry": {
        "type": "Point",
        "coordinates": [
          7.1333,
          58.1667
        ]
      },
      "type": "Feature",
      "properties": {
        "hierarchy": [
          "tgn:1048650",
          "tgn:7003656",
          "tgn:1000003",
          "tgn:1000088",
          "tgn:7029392"
        ],
        "placetype": [
          "aat:300008347"
        ],
        "id": 1048650,
        "name:xx": "Lyngdal"
      }
    },
    {
      "geometry": {
        "type": "Point",
        "coordinates": [
          20.1667,
          69.6
        ]
      },
      "type": "Feature",
      "properties": {
        "hierarchy": [
          "tgn:1048651",
          "tgn:7003655",
          "tgn:1000003",
          "tgn:1000088",
          "tgn:7029392"
        ],
        "placetype": [
          "aat:300008347"
        ],
        "id": 1048651,
        "name:xx": "Lyngen"
      }
    },
    {
      "geometry": {
        "type": "Point",
        "coordinates": [
          10.6,
          59.9
        ]
      },
      "type": "Feature",
      "properties": {
        "hierarchy": [
          "tgn:1048652",
          "tgn:7003659",
          "tgn:1000003",
          "tgn:1000088",
          "tgn:7029392"
        ],
        "placetype": [
          "aat:300008347"
        ],
        "id": 1048652,
        "name:xx": "Lysaker"
      }
    },
    {
      "geometry": {
        "type": "Point",
        "coordinates": [
          5.1,
          61.95
        ]
      },
      "type": "Feature",
      "properties": {
        "hierarchy": [
          "tgn:1048653",
          "tgn:7003653",
          "tgn:1000003",
          "tgn:1000088",
          "tgn:7029392"
        ],
        "placetype": [
          "aat:300008347"
        ],
        "id": 1048653,
        "name:xx": "Måløy"
      }
    },
    {
      "geometry": {
        "type": "Point",
        "coordinates": [
          12.2,
          59.95
        ]
      },
      "type": "Feature",
      "properties": {
        "hierarchy": [
          "tgn:1048654",
          "tgn:7003643",
          "tgn:1000003",
          "tgn:1000088",
          "tgn:7029392"
        ],
        "placetype": [
          "aat:300008347"
        ],
        "id": 1048654,
        "name:xx": "Magnor"
      }
    },
    {
      "geometry": {
        "type": "Point",
        "coordinates": [
          11.2,
          64.0667
        ]
      },
      "type": "Feature",
      "properties": {
        "hierarchy": [
          "tgn:1048655",
          "tgn:7003645",
          "tgn:1000003",
          "tgn:1000088",
          "tgn:7029392"
        ],
        "placetype": [
          "aat:300008347"
        ],
        "id": 1048655,
        "name:xx": "Malm"
      }
    },
    {
      "geometry": {
        "type": "Point",
        "coordinates": [
          7.5,
          58.0333
        ]
      },
      "type": "Feature",
      "properties": {
        "hierarchy": [
          "tgn:1048656",
          "tgn:7003656",
          "tgn:1000003",
          "tgn:1000088",
          "tgn:7029392"
        ],
        "placetype": [
          "aat:300008347"
        ],
        "id": 1048656,
        "name:xx": "Mandal"
      }
    },
    {
      "geometry": {
        "type": "Point",
        "coordinates": [
          10.2667,
          63.2833
        ]
      },
      "type": "Feature",
      "properties": {
        "hierarchy": [
          "tgn:1048657",
          "tgn:1000440",
          "tgn:1000003",
          "tgn:1000088",
          "tgn:7029392"
        ],
        "placetype": [
          "aat:300008347"
        ],
        "id": 1048657,
        "name:xx": "Melhus"
      }
    },
    {
      "geometry": {
        "type": "Point",
        "coordinates": [
          11.8,
          63.4333
        ]
      },
      "type": "Feature",
      "properties": {
        "hierarchy": [
          "tgn:1048658",
          "tgn:7003645",
          "tgn:1000003",
          "tgn:1000088",
          "tgn:7029392"
        ],
        "placetype": [
          "aat:300008347"
        ],
        "id": 1048658,
        "name:xx": "Meråker"
      }
    },
    {
      "geometry": {
        "type": "Point",
        "coordinates": [
          10.0167,
          59.75
        ]
      },
      "type": "Feature",
      "properties": {
        "hierarchy": [
          "tgn:1048659",
          "tgn:7003641",
          "tgn:1000003",
          "tgn:1000088",
          "tgn:7029392"
        ],
        "placetype": [
          "aat:300008347"
        ],
        "id": 1048659,
        "name:xx": "Mjøndalen"
      }
    }
  ]
}
