{
  "type": "FeatureCollection",
  "features": [
    {
      "geometry": {
        "type": "Point",
        "coordinates": [
          -71.0167,
          42.3333
        ]
      },
      "type": "Feature",
      "properties": {
        "hierarchy": [
          "tgn:2049450",
          "tgn:7013445",
          "tgn:1000001",
          "tgn:1002923",
          "tgn:7012149",
          "tgn:7007517",
          "tgn:7029392"
        ],
        "placetype": [
          "aat:300000745"
        ],
        "id": 2049450,
        "name:xx": "City Point"
      }
    },
    {
      "geometry": {
        "type": "Point",
        "coordinates": [
          -71.0667,
          42.2833
        ]
      },
      "type": "Feature",
      "properties": {
        "hierarchy": [
          "tgn:2049455",
          "tgn:7013445",
          "tgn:1000001",
          "tgn:1002923",
          "tgn:7012149",
          "tgn:7007517",
          "tgn:7029392"
        ],
        "placetype": [
          "aat:300000745"
        ],
        "id": 2049455,
        "name:xx": "Dorchester Center"
      }
    }
  ]
}
