{
  "geometry": {
    "type": "Point",
    "coordinates": [
      36.1333,
      32.75
    ]
  },
  "type": "Feature",
  "properties": {
    "hierarchy": [
      "tgn:1085128",
      "tgn:1002074",
      "tgn:1000004",
      "tgn:1000140",
      "tgn:7029392"
    ],
    "placetype": [
      "aat:300008347"
    ],
    "id": 1085128,
    "name:xx": "Dāʻīl"
  }
}
