{
  "geometry": {
    "type": "Point",
    "coordinates": [
      -88.8333,
      36.5333
    ]
  },
  "type": "Feature",
  "properties": {
    "hierarchy": [
      "tgn:2378110",
      "tgn:1000001",
      "tgn:7012149",
      "tgn:7029392"
    ],
    "placetype": [
      "aat:300008706"
    ],
    "id": 2378110,
    "name:xx": "Harris Fork Creek"
  }
}
