{
  "geometry": {
    "type": "Point",
    "coordinates": [
      -88.3333,
      34.9167
    ]
  },
  "type": "Feature",
  "properties": {
    "hierarchy": [
      "tgn:2466564",
      "tgn:1000001",
      "tgn:7012149",
      "tgn:2001156",
      "tgn:7007522",
      "tgn:7029392"
    ],
    "placetype": [
      "aat:300008699"
    ],
    "id": 2466564,
    "name:xx": "Long Branch"
  }
}
