{
  "geometry": {
    "type": "Point",
    "coordinates": [
      -115.6333,
      36.2833
    ]
  },
  "type": "Feature",
  "properties": {
    "hierarchy": [
      "tgn:2532023",
      "tgn:1000001",
      "tgn:2001410",
      "tgn:7012149",
      "tgn:7007526",
      "tgn:7029392"
    ],
    "placetype": [
      "aat:300008697"
    ],
    "id": 2532023,
    "name:xx": "Mummy Spring"
  }
}
