{
  "geometry": {
    "type": "Point",
    "coordinates": [
      15.4833,
      49.2833
    ]
  },
  "type": "Feature",
  "properties": {
    "hierarchy": [
      "tgn:1027574",
      "tgn:7593921",
      "tgn:1000003",
      "tgn:1001780",
      "tgn:7029392"
    ],
    "placetype": [
      "aat:300008347"
    ],
    "id": 1027574,
    "name:xx": "Třešt"
  }
}
