{
  "geometry": {
    "type": "Point",
    "coordinates": [
      -72.45,
      43.25
    ]
  },
  "type": "Feature",
  "properties": {
    "hierarchy": [
      "tgn:2361166",
      "tgn:1000001",
      "tgn:2002136",
      "tgn:7012149",
      "tgn:7007828",
      "tgn:7029392"
    ],
    "placetype": [
      "aat:300008699"
    ],
    "id": 2361166,
    "name:xx": "Gravel Brook"
  }
}
