{
  "type": "FeatureCollection",
  "features": [
    {
      "geometry": {
        "type": "Point",
        "coordinates": [
          -77.0333,
          41.2167
        ]
      },
      "type": "Feature",
      "properties": {
        "hierarchy": [
          "tgn:2087905",
          "tgn:1000001",
          "tgn:7012149",
          "tgn:1002613",
          "tgn:7007710",
          "tgn:7029392"
        ],
        "placetype": [
          "aat:300008347"
        ],
        "id": 2087905,
        "name:xx": "Duboistown"
      }
    },
    {
      "geometry": {
        "type": "Point",
        "coordinates": [
          -78.1667,
          40.2
        ]
      },
      "type": "Feature",
      "properties": {
        "hierarchy": [
          "tgn:2087907",
          "tgn:1000001",
          "tgn:7012149",
          "tgn:1002494",
          "tgn:7007710",
          "tgn:7029392"
        ],
        "placetype": [
          "aat:300008347"
        ],
        "id": 2087907,
        "name:xx": "Dudley"
      }
    },
    {
      "geometry": {
        "type": "Point",
        "coordinates": [
          -77.5667,
          39.8833
        ]
      },
      "type": "Feature",
      "properties": {
        "hierarchy": [
          "tgn:2087908",
          "tgn:1000001",
          "tgn:7012149",
          "tgn:1002387",
          "tgn:7007710",
          "tgn:7029392"
        ],
        "placetype": [
          "aat:300008347"
        ],
        "id": 2087908,
        "name:xx": "Duffield"
      }
    }
  ]
}
