{
  "geometry": {
    "type": "Point",
    "coordinates": [
      -90.9833,
      43.0833
    ]
  },
  "type": "Feature",
  "properties": {
    "hierarchy": [
      "tgn:2302355",
      "tgn:1000001",
      "tgn:2002316",
      "tgn:7012149",
      "tgn:7007922",
      "tgn:7029392"
    ],
    "placetype": [
      "aat:300266640"
    ],
    "id": 2302355,
    "name:xx": "Dutch Ridge"
  }
}
