{
  "geometry": {
    "type": "Point",
    "coordinates": [
      31.060921,
      29.054176
    ]
  },
  "type": "Feature",
  "properties": {
    "hierarchy": [
      "tgn:1095744",
      "tgn:7001242",
      "tgn:7016833",
      "tgn:1001142",
      "tgn:7029392"
    ],
    "placetype": [
      "aat:300008347"
    ],
    "name:en": "Tizmant ash Sharqīyah",
    "id": 1095744
  }
}
