{
  "type": "FeatureCollection",
  "features": [
    {
      "geometry": {
        "type": "Point",
        "coordinates": [
          -1.75,
          54.083333
        ]
      },
      "type": "Feature",
      "properties": {
        "hierarchy": [
          "tgn:7011970",
          "tgn:7002445",
          "tgn:1000003",
          "tgn:7008166",
          "tgn:7008591",
          "tgn:7029392"
        ],
        "placetype": [
          "aat:300008347"
        ],
        "name:en": "Pateley Bridge",
        "id": 7011970
      }
    },
    {
      "geometry": {
        "type": "Point",
        "coordinates": [
          -1.833333,
          52.316667
        ]
      },
      "type": "Feature",
      "properties": {
        "hierarchy": [
          "tgn:7011972",
          "tgn:7002445",
          "tgn:1000003",
          "tgn:7008178",
          "tgn:7008591",
          "tgn:7029392"
        ],
        "placetype": [
          "aat:300008347"
        ],
        "id": 7011972,
        "name:xx": "Tanworth-in-Arden"
      }
    },
    {
      "geometry": {
        "type": "Point",
        "coordinates": [
          -0.033333,
          52.05
        ]
      },
      "type": "Feature",
      "properties": {
        "hierarchy": [
          "tgn:7011974",
          "tgn:7002445",
          "tgn:1000003",
          "tgn:7008145",
          "tgn:7008591",
          "tgn:7029392"
        ],
        "placetype": [
          "aat:300008347"
        ],
        "name:en": "Royston",
        "id": 7011974
      }
    },
    {
      "geometry": {
        "type": "Point",
        "coordinates": [
          -1,
          51.633333
        ]
      },
      "type": "Feature",
      "properties": {
        "hierarchy": [
          "tgn:7011975",
          "tgn:7002445",
          "tgn:1000003",
          "tgn:7008168",
          "tgn:7008591",
          "tgn:7029392"
        ],
        "placetype": [
          "aat:300008347",
          "aat:300008375"
        ],
        "name:en": "Watlington",
        "id": 7011975
      }
    },
    {
      "geometry": {
        "type": "Point",
        "coordinates": [
          -2.65,
          51.85
        ]
      },
      "type": "Feature",
      "properties": {
        "hierarchy": [
          "tgn:7011977",
          "tgn:7002445",
          "tgn:1000003",
          "tgn:7008143",
          "tgn:7008591",
          "tgn:7029392"
        ],
        "placetype": [
          "aat:300008347"
        ],
        "name:en": "Whitchurch",
        "id": 7011977
      }
    },
    {
      "geometry": {
        "type": "Point",
        "coordinates": [
          -2.033333,
          52.6
        ]
      },
      "type": "Feature",
      "properties": {
        "hierarchy": [
          "tgn:7011979",
          "tgn:7002445",
          "tgn:7019029",
          "tgn:1000003",
          "tgn:7029506",
          "tgn:7008591",
          "tgn:7029392"
        ],
        "placetype": [
          "aat:300008347"
        ],
        "name:en": "Willenhall",
        "id": 7011979
      }
    }
  ]
}
