{
  "type": "FeatureCollection",
  "features": [
    {
      "geometry": {
        "type": "Point",
        "coordinates": [
          -85.1,
          38.5833
        ]
      },
      "type": "Feature",
      "properties": {
        "hierarchy": [
          "tgn:2487241",
          "tgn:1000001",
          "tgn:1002237",
          "tgn:7012149",
          "tgn:7007255",
          "tgn:7029392"
        ],
        "placetype": [
          "aat:300008706"
        ],
        "id": 2487241,
        "name:xx": "Lees Creek"
      }
    },
    {
      "geometry": {
        "type": "Point",
        "coordinates": [
          -89.9167,
          30.7333
        ]
      },
      "type": "Feature",
      "properties": {
        "hierarchy": [
          "tgn:2487242",
          "tgn:1000001",
          "tgn:7012149",
          "tgn:2000912",
          "tgn:7007256",
          "tgn:7029392"
        ],
        "placetype": [
          "aat:300008706"
        ],
        "id": 2487242,
        "name:xx": "Lees Creek"
      }
    },
    {
      "geometry": {
        "type": "Point",
        "coordinates": [
          -117.85,
          40.5667
        ]
      },
      "type": "Feature",
      "properties": {
        "hierarchy": [
          "tgn:2487243",
          "tgn:1000001",
          "tgn:2001419",
          "tgn:7012149",
          "tgn:7007526",
          "tgn:7029392"
        ],
        "placetype": [
          "aat:300008706"
        ],
        "id": 2487243,
        "name:xx": "Lees Creek"
      }
    },
    {
      "geometry": {
        "type": "Point",
        "coordinates": [
          -75.05,
          44.0167
        ]
      },
      "type": "Feature",
      "properties": {
        "hierarchy": [
          "tgn:2487244",
          "tgn:1000001",
          "tgn:7012149",
          "tgn:1002472",
          "tgn:7007568",
          "tgn:7029392"
        ],
        "placetype": [
          "aat:300008706"
        ],
        "id": 2487244,
        "name:xx": "Lees Creek"
      }
    },
    {
      "geometry": {
        "type": "Point",
        "coordinates": [
          -77.6,
          36.4833
        ]
      },
      "type": "Feature",
      "properties": {
        "hierarchy": [
          "tgn:2487245",
          "tgn:1000001",
          "tgn:7012149",
          "tgn:1002728",
          "tgn:7007709",
          "tgn:7029392"
        ],
        "placetype": [
          "aat:300008706"
        ],
        "id": 2487245,
        "name:xx": "Lees Creek"
      }
    },
    {
      "geometry": {
        "type": "Point",
        "coordinates": [
          -123.1333,
          43.6667
        ]
      },
      "type": "Feature",
      "properties": {
        "hierarchy": [
          "tgn:2487247",
          "tgn:1000001",
          "tgn:7012149",
          "tgn:2001706",
          "tgn:7007708",
          "tgn:7029392"
        ],
        "placetype": [
          "aat:300008706"
        ],
        "id": 2487247,
        "name:xx": "Lees Creek"
      }
    },
    {
      "geometry": {
        "type": "Point",
        "coordinates": [
          -75.55,
          41.5667
        ]
      },
      "type": "Feature",
      "properties": {
        "hierarchy": [
          "tgn:2487248",
          "tgn:1000001",
          "tgn:7012149",
          "tgn:1002564",
          "tgn:7007710",
          "tgn:7029392"
        ],
        "placetype": [
          "aat:300008706"
        ],
        "id": 2487248,
        "name:xx": "Lees Creek"
      }
    },
    {
      "geometry": {
        "type": "Point",
        "coordinates": [
          -86.4833,
          35.0833
        ]
      },
      "type": "Feature",
      "properties": {
        "hierarchy": [
          "tgn:2487249",
          "tgn:1000001",
          "tgn:7012149",
          "tgn:2001888",
          "tgn:7007825",
          "tgn:7029392"
        ],
        "placetype": [
          "aat:300008706"
        ],
        "id": 2487249,
        "name:xx": "Lees Creek"
      }
    }
  ]
}
