{
  "geometry": {
    "type": "Point",
    "coordinates": [
      -104.15,
      46.25
    ]
  },
  "type": "Feature",
  "properties": {
    "hierarchy": [
      "tgn:2204727",
      "tgn:1000001",
      "tgn:7012149",
      "tgn:2001272",
      "tgn:7007524",
      "tgn:7029392"
    ],
    "placetype": [
      "aat:300006191"
    ],
    "id": 2204727,
    "name:xx": "Buffalo Reservoir"
  }
}
