{
  "type": "FeatureCollection",
  "features": [
    {
      "geometry": {
        "type": "Point",
        "coordinates": [
          31.593838,
          31.225803
        ]
      },
      "type": "Feature",
      "properties": {
        "hierarchy": [
          "tgn:7543580",
          "tgn:7001242",
          "tgn:1001059",
          "tgn:7016833",
          "tgn:7029392"
        ],
        "placetype": [
          "aat:300000206"
        ],
        "name:en": "'Izbat al 'Abd",
        "id": 7543580
      }
    },
    {
      "geometry": {
        "type": "Point",
        "coordinates": [
          31.566053,
          31.220164
        ]
      },
      "type": "Feature",
      "properties": {
        "hierarchy": [
          "tgn:7543581",
          "tgn:7001242",
          "tgn:1001059",
          "tgn:7016833",
          "tgn:7029392"
        ],
        "placetype": [
          "aat:300000206"
        ],
        "name:en": "'Izbat 'Abd al Malāk",
        "id": 7543581
      }
    },
    {
      "geometry": {
        "type": "Point",
        "coordinates": [
          31.57062,
          31.223184
        ]
      },
      "type": "Feature",
      "properties": {
        "hierarchy": [
          "tgn:7543582",
          "tgn:7001242",
          "tgn:1001059",
          "tgn:7016833",
          "tgn:7029392"
        ],
        "placetype": [
          "aat:300000206"
        ],
        "name:en": "'Izbat ad Duktūr Labīb",
        "id": 7543582
      }
    },
    {
      "geometry": {
        "type": "Point",
        "coordinates": [
          31.568157,
          31.22616
        ]
      },
      "type": "Feature",
      "properties": {
        "hierarchy": [
          "tgn:7543583",
          "tgn:7001242",
          "tgn:1001059",
          "tgn:7016833",
          "tgn:7029392"
        ],
        "placetype": [
          "aat:300000206"
        ],
        "name:en": "'Izbat Ţaha al Jūharī",
        "id": 7543583
      }
    },
    {
      "geometry": {
        "type": "Point",
        "coordinates": [
          31.554256,
          31.225598
        ]
      },
      "type": "Feature",
      "properties": {
        "hierarchy": [
          "tgn:7543584",
          "tgn:7001242",
          "tgn:1001059",
          "tgn:7016833",
          "tgn:7029392"
        ],
        "placetype": [
          "aat:300008347"
        ],
        "name:en": "'Izbat Ramzī Astīnū",
        "id": 7543584
      }
    },
    {
      "geometry": {
        "type": "Point",
        "coordinates": [
          31.550033,
          31.228017
        ]
      },
      "type": "Feature",
      "properties": {
        "hierarchy": [
          "tgn:7543585",
          "tgn:7001242",
          "tgn:1001059",
          "tgn:7016833",
          "tgn:7029392"
        ],
        "placetype": [
          "aat:300000206"
        ],
        "name:en": "'Izbat 'Awaḑ Allāh",
        "id": 7543585
      }
    },
    {
      "geometry": {
        "type": "Point",
        "coordinates": [
          31.530686,
          31.217787
        ]
      },
      "type": "Feature",
      "properties": {
        "hierarchy": [
          "tgn:7543586",
          "tgn:7001242",
          "tgn:1001059",
          "tgn:7016833",
          "tgn:7029392"
        ],
        "placetype": [
          "aat:300008347"
        ],
        "name:en": "'Izbat ad Duktūr Ibrāhīm Shawkat",
        "id": 7543586
      }
    },
    {
      "geometry": {
        "type": "Point",
        "coordinates": [
          31.536121,
          31.2309
        ]
      },
      "type": "Feature",
      "properties": {
        "hierarchy": [
          "tgn:7543587",
          "tgn:7001242",
          "tgn:1001059",
          "tgn:7016833",
          "tgn:7029392"
        ],
        "placetype": [
          "aat:300008347"
        ],
        "name:en": "'Izbat Muḩammad Muşbāḩ",
        "id": 7543587
      }
    },
    {
      "geometry": {
        "type": "Point",
        "coordinates": [
          31.535446,
          31.225514
        ]
      },
      "type": "Feature",
      "properties": {
        "hierarchy": [
          "tgn:7543588",
          "tgn:7001242",
          "tgn:1001059",
          "tgn:7016833",
          "tgn:7029392"
        ],
        "placetype": [
          "aat:300008347"
        ],
        "name:en": "'Izbat ad Daqq",
        "id": 7543588
      }
    },
    {
      "geometry": {
        "type": "Point",
        "coordinates": [
          31.512378,
          31.213159
        ]
      },
      "type": "Feature",
      "properties": {
        "hierarchy": [
          "tgn:7543589",
          "tgn:7001242",
          "tgn:1001059",
          "tgn:7016833",
          "tgn:7029392"
        ],
        "placetype": [
          "aat:300006075"
        ],
        "name:en": "Tir'at al Arba'ah",
        "id": 7543589
      }
    }
  ]
}
