{
  "geometry": {
    "type": "Point",
    "coordinates": [
      -89.4333,
      33.45
    ]
  },
  "type": "Feature",
  "properties": {
    "hierarchy": [
      "tgn:2057547",
      "tgn:1000001",
      "tgn:7012149",
      "tgn:2001163",
      "tgn:7007522",
      "tgn:7029392"
    ],
    "placetype": [
      "aat:300008347"
    ],
    "id": 2057547,
    "name:xx": "Stewart"
  }
}
