{
  "geometry": {
    "type": "Point",
    "coordinates": [
      -103.5333,
      36.35
    ]
  },
  "type": "Feature",
  "properties": {
    "hierarchy": [
      "tgn:2727054",
      "tgn:1000001",
      "tgn:7012149",
      "tgn:2001459",
      "tgn:7007566",
      "tgn:7029392"
    ],
    "placetype": [
      "aat:300008706"
    ],
    "id": 2727054,
    "name:xx": "Trabajo Creek"
  }
}
