{
  "geometry": {
    "type": "Point",
    "coordinates": [
      -109.9833,
      43.2333
    ]
  },
  "type": "Feature",
  "properties": {
    "hierarchy": [
      "tgn:2370270",
      "tgn:1000001",
      "tgn:7012149",
      "tgn:2002382",
      "tgn:7007923",
      "tgn:7029392"
    ],
    "placetype": [
      "aat:300008798"
    ],
    "id": 2370270,
    "name:xx": "Gypsum Hill"
  }
}
