{
  "geometry": {
    "type": "Point",
    "coordinates": [
      -87.6875,
      21.0625
    ]
  },
  "type": "Feature",
  "properties": {
    "hierarchy": [
      "tgn:7403151",
      "tgn:1000001",
      "tgn:7005600",
      "tgn:7005560",
      "tgn:7029392"
    ],
    "placetype": [
      "aat:300008347"
    ],
    "id": 7403151,
    "name:xx": "San José Montecristo"
  }
}
