{
  "geometry": {
    "type": "Point",
    "coordinates": [
      -114.6333,
      43.2167
    ]
  },
  "type": "Feature",
  "properties": {
    "hierarchy": [
      "tgn:2399424",
      "tgn:1000001",
      "tgn:2000464",
      "tgn:7012149",
      "tgn:7007250",
      "tgn:7029392"
    ],
    "placetype": [
      "aat:300008697"
    ],
    "id": 2399424,
    "name:xx": "Horn Spring"
  }
}
