{
  "geometry": {
    "type": "Point",
    "coordinates": [
      -99.1167,
      32.8333
    ]
  },
  "type": "Feature",
  "properties": {
    "hierarchy": [
      "tgn:2500705",
      "tgn:1000001",
      "tgn:7012149",
      "tgn:7007826",
      "tgn:7029392"
    ],
    "placetype": [
      "aat:300008706"
    ],
    "id": 2500705,
    "name:xx": "McDowell Creek"
  }
}
