{
  "geometry": {
    "type": "Point",
    "coordinates": [
      -116.0333,
      48.5667
    ]
  },
  "type": "Feature",
  "properties": {
    "hierarchy": [
      "tgn:2464750",
      "tgn:1000001",
      "tgn:7012149",
      "tgn:2001286",
      "tgn:7007524",
      "tgn:7029392"
    ],
    "placetype": [
      "aat:300008706"
    ],
    "id": 2464750,
    "name:xx": "Logan Creek"
  }
}
