{
  "geometry": {
    "type": "Point",
    "coordinates": [
      -111.7167,
      41.4333
    ]
  },
  "type": "Feature",
  "properties": {
    "hierarchy": [
      "tgn:2680021",
      "tgn:1000001",
      "tgn:2002103",
      "tgn:7012149",
      "tgn:7007827",
      "tgn:7029392"
    ],
    "placetype": [
      "aat:300008706"
    ],
    "id": 2680021,
    "name:xx": "South Fork Smith Creek"
  }
}
