{
  "geometry": {
    "type": "Point",
    "coordinates": [
      -74.3833,
      41.1833
    ]
  },
  "type": "Feature",
  "properties": {
    "hierarchy": [
      "tgn:2441676",
      "tgn:1000001",
      "tgn:1002934",
      "tgn:7012149",
      "tgn:7007565",
      "tgn:7029392"
    ],
    "placetype": [
      "aat:300006191"
    ],
    "id": 2441676,
    "name:xx": "Kohout Lake"
  }
}
