{
  "geometry": {
    "type": "Point",
    "coordinates": [
      -98.3667,
      39.3333
    ]
  },
  "type": "Feature",
  "properties": {
    "hierarchy": [
      "tgn:2749578",
      "tgn:1000001",
      "tgn:7012149",
      "tgn:2000721",
      "tgn:7007254",
      "tgn:7029392"
    ],
    "placetype": [
      "aat:300008706"
    ],
    "id": 2749578,
    "name:xx": "Walnut Creek"
  }
}
