{
  "geometry": {
    "type": "Point",
    "coordinates": [
      -95.25,
      41.8167
    ]
  },
  "type": "Feature",
  "properties": {
    "hierarchy": [
      "tgn:2436566",
      "tgn:1000001",
      "tgn:7012149",
      "tgn:2000643",
      "tgn:7007253",
      "tgn:7029392"
    ],
    "placetype": [
      "aat:300008706"
    ],
    "id": 2436566,
    "name:xx": "Kidds Creek"
  }
}
