{
  "type": "FeatureCollection",
  "features": [
    {
      "geometry": {
        "type": "Point",
        "coordinates": [
          -113.4,
          37.5
        ]
      },
      "type": "Feature",
      "properties": {
        "hierarchy": [
          "tgn:2614740",
          "tgn:1000001",
          "tgn:7012149",
          "tgn:2002127",
          "tgn:7007827",
          "tgn:7029392"
        ],
        "placetype": [
          "aat:300008798"
        ],
        "id": 2614740,
        "name:xx": "Rencher Peak"
      }
    },
    {
      "geometry": {
        "type": "Point",
        "coordinates": [
          -86.15,
          33.3167
        ]
      },
      "type": "Feature",
      "properties": {
        "hierarchy": [
          "tgn:2614741",
          "tgn:7002659",
          "tgn:1000001",
          "tgn:7012149",
          "tgn:2000060",
          "tgn:7029392"
        ],
        "placetype": [
          "aat:300008347"
        ],
        "id": 2614741,
        "name:xx": "Rendalia"
      }
    },
    {
      "geometry": {
        "type": "Point",
        "coordinates": [
          -86.9,
          37.3833
        ]
      },
      "type": "Feature",
      "properties": {
        "hierarchy": [
          "tgn:2614742",
          "tgn:1000001",
          "tgn:7012149",
          "tgn:2000834",
          "tgn:7007255",
          "tgn:7029392"
        ],
        "placetype": [
          "aat:300008706"
        ],
        "id": 2614742,
        "name:xx": "Render Creek"
      }
    },
    {
      "geometry": {
        "type": "Point",
        "coordinates": [
          -100.9667,
          32
        ]
      },
      "type": "Feature",
      "properties": {
        "hierarchy": [
          "tgn:2614743",
          "tgn:1000001",
          "tgn:7012149",
          "tgn:7007826",
          "tgn:7029392"
        ],
        "placetype": [
          "aat:300008706"
        ],
        "id": 2614743,
        "name:xx": "Renderbrook Creek"
      }
    },
    {
      "geometry": {
        "type": "Point",
        "coordinates": [
          -100.9667,
          32.1333
        ]
      },
      "type": "Feature",
      "properties": {
        "hierarchy": [
          "tgn:2614744",
          "tgn:1000001",
          "tgn:7012149",
          "tgn:2002043",
          "tgn:7007826",
          "tgn:7029392"
        ],
        "placetype": [
          "aat:300008697"
        ],
        "id": 2614744,
        "name:xx": "Renderbrook Spring"
      }
    },
    {
      "geometry": {
        "type": "Point",
        "coordinates": [
          -84.05,
          34.2667
        ]
      },
      "type": "Feature",
      "properties": {
        "hierarchy": [
          "tgn:2614745",
          "tgn:1000001",
          "tgn:7012149",
          "tgn:2000349",
          "tgn:7007248",
          "tgn:7029392"
        ],
        "placetype": [
          "aat:300006191"
        ],
        "id": 2614745,
        "name:xx": "Rendering Plant Lake"
      }
    },
    {
      "geometry": {
        "type": "Point",
        "coordinates": [
          -73.5,
          42.6167
        ]
      },
      "type": "Feature",
      "properties": {
        "hierarchy": [
          "tgn:2614746",
          "tgn:1000001",
          "tgn:7012149",
          "tgn:1002821",
          "tgn:7007568",
          "tgn:7029392"
        ],
        "placetype": [
          "aat:300008680"
        ],
        "id": 2614746,
        "name:xx": "Rendert Pond"
      }
    },
    {
      "geometry": {
        "type": "Point",
        "coordinates": [
          -120.3,
          48.5667
        ]
      },
      "type": "Feature",
      "properties": {
        "hierarchy": [
          "tgn:2614747",
          "tgn:1000001",
          "tgn:7012149",
          "tgn:1002742",
          "tgn:7007920",
          "tgn:7029392"
        ],
        "placetype": [
          "aat:300008798"
        ],
        "id": 2614747,
        "name:xx": "Rendevous Mountain"
      }
    },
    {
      "geometry": {
        "type": "Point",
        "coordinates": [
          -92.8167,
          33.5
        ]
      },
      "type": "Feature",
      "properties": {
        "hierarchy": [
          "tgn:2614748",
          "tgn:1000001",
          "tgn:7016172",
          "tgn:7012149",
          "tgn:2000156",
          "tgn:7029392"
        ],
        "placetype": [
          "aat:300008347"
        ],
        "id": 2614748,
        "name:xx": "Rendezvous"
      }
    },
    {
      "geometry": {
        "type": "Point",
        "coordinates": [
          -109.95,
          41.05
        ]
      },
      "type": "Feature",
      "properties": {
        "hierarchy": [
          "tgn:2614749",
          "tgn:1000001",
          "tgn:7012149",
          "tgn:2002383",
          "tgn:7007923",
          "tgn:7029392"
        ],
        "placetype": [
          "aat:300008347"
        ],
        "id": 2614749,
        "name:xx": "Rendezvous"
      }
    }
  ]
}
