{
  "geometry": {
    "type": "Point",
    "coordinates": [
      -35.3333,
      -5.8333
    ]
  },
  "type": "Feature",
  "properties": {
    "hierarchy": [
      "tgn:1021986",
      "tgn:7006257",
      "tgn:1000047",
      "tgn:7002455",
      "tgn:1000002",
      "tgn:7029392"
    ],
    "placetype": [
      "aat:300008347"
    ],
    "id": 1021986,
    "name:xx": "Macaíba"
  }
}
