{
  "geometry": {
    "type": "Point",
    "coordinates": [
      -121.5833,
      47.45
    ]
  },
  "type": "Feature",
  "properties": {
    "hierarchy": [
      "tgn:2718245",
      "tgn:1000001",
      "tgn:7012149",
      "tgn:7018871",
      "tgn:7007920",
      "tgn:7029392"
    ],
    "placetype": [
      "aat:300008706"
    ],
    "id": 2718245,
    "name:xx": "Thompson Creek"
  }
}
