{
  "type": "FeatureCollection",
  "features": [
    {
      "geometry": {
        "type": "Point",
        "coordinates": [
          -122.3833,
          47.3
        ]
      },
      "type": "Feature",
      "properties": {
        "hierarchy": [
          "tgn:2480110",
          "tgn:1000001",
          "tgn:7012149",
          "tgn:7018871",
          "tgn:7007920",
          "tgn:7029392"
        ],
        "placetype": [
          "aat:300006191"
        ],
        "id": 2480110,
        "name:xx": "Lake Loreene"
      }
    },
    {
      "geometry": {
        "type": "Point",
        "coordinates": [
          -121.0667,
          47.6667
        ]
      },
      "type": "Feature",
      "properties": {
        "hierarchy": [
          "tgn:2480111",
          "tgn:1000001",
          "tgn:1002260",
          "tgn:7012149",
          "tgn:7007920",
          "tgn:7029392"
        ],
        "placetype": [
          "aat:300008850"
        ],
        "id": 2480111,
        "name:xx": "Lake Lorraine Point"
      }
    },
    {
      "geometry": {
        "type": "Point",
        "coordinates": [
          -83.2667,
          34.6
        ]
      },
      "type": "Feature",
      "properties": {
        "hierarchy": [
          "tgn:2480115",
          "tgn:1000001",
          "tgn:7012149",
          "tgn:2000418",
          "tgn:7007248",
          "tgn:7029392"
        ],
        "placetype": [
          "aat:300006191"
        ],
        "id": 2480115,
        "name:xx": "Lake Louise Dam"
      }
    },
    {
      "geometry": {
        "type": "Point",
        "coordinates": [
          -106.0833,
          40.4
        ]
      },
      "type": "Feature",
      "properties": {
        "hierarchy": [
          "tgn:2480116",
          "tgn:1000001",
          "tgn:7012149",
          "tgn:2000226",
          "tgn:7007158",
          "tgn:7029392"
        ],
        "placetype": [
          "aat:300006191"
        ],
        "id": 2480116,
        "name:xx": "Lake Loveland"
      }
    },
    {
      "geometry": {
        "type": "Point",
        "coordinates": [
          -91.45,
          31.3167
        ]
      },
      "type": "Feature",
      "properties": {
        "hierarchy": [
          "tgn:2480117",
          "tgn:2001086",
          "tgn:1000001",
          "tgn:7012149",
          "tgn:7007522",
          "tgn:7029392"
        ],
        "placetype": [
          "aat:300008905"
        ],
        "id": 2480117,
        "name:xx": "Lake Lucile"
      }
    },
    {
      "geometry": {
        "type": "Point",
        "coordinates": [
          -123.0333,
          47.95
        ]
      },
      "type": "Feature",
      "properties": {
        "hierarchy": [
          "tgn:2480118",
          "tgn:1000001",
          "tgn:7012149",
          "tgn:1002942",
          "tgn:7007920",
          "tgn:7029392"
        ],
        "placetype": [
          "aat:300006191"
        ],
        "id": 2480118,
        "name:xx": "Lake Lucinda"
      }
    },
    {
      "geometry": {
        "type": "Point",
        "coordinates": [
          -71.5167,
          42.15
        ]
      },
      "type": "Feature",
      "properties": {
        "hierarchy": [
          "tgn:2480119",
          "tgn:1000001",
          "tgn:7012149",
          "tgn:1003038",
          "tgn:7007517",
          "tgn:7029392"
        ],
        "placetype": [
          "aat:300006191"
        ],
        "id": 2480119,
        "name:xx": "Lake Luisa Reservoir"
      }
    }
  ]
}
