{
  "geometry": {
    "type": "Point",
    "coordinates": [
      -93.0833,
      43.7833
    ]
  },
  "type": "Feature",
  "properties": {
    "hierarchy": [
      "tgn:2488195",
      "tgn:1000001",
      "tgn:2001022",
      "tgn:7012149",
      "tgn:7007521",
      "tgn:7029392"
    ],
    "placetype": [
      "aat:300006075"
    ],
    "id": 2488195,
    "name:xx": "Magnuson Ditch"
  }
}
