{
  "geometry": {
    "type": "Point",
    "coordinates": [
      -83.4167,
      37.35
    ]
  },
  "type": "Feature",
  "properties": {
    "hierarchy": [
      "tgn:2215581",
      "tgn:1000001",
      "tgn:7012149",
      "tgn:2000836",
      "tgn:7007255",
      "tgn:7029392"
    ],
    "placetype": [
      "aat:300008699"
    ],
    "id": 2215581,
    "name:xx": "Cam Johnson Branch"
  }
}
