{
  "geometry": {
    "type": "Point",
    "coordinates": [
      -111.35,
      40.9167
    ]
  },
  "type": "Feature",
  "properties": {
    "hierarchy": [
      "tgn:2548633",
      "tgn:1000001",
      "tgn:7012149",
      "tgn:2002122",
      "tgn:7007827",
      "tgn:7029392"
    ],
    "placetype": [
      "aat:300006075"
    ],
    "id": 2548633,
    "name:xx": "North Narrows Ditch"
  }
}
