{
  "geometry": {
    "type": "Point",
    "coordinates": [
      -88.6667,
      30.6833
    ]
  },
  "type": "Feature",
  "properties": {
    "hierarchy": [
      "tgn:2166363",
      "tgn:1000001",
      "tgn:7012149",
      "tgn:2001115",
      "tgn:7007522",
      "tgn:7029392"
    ],
    "placetype": [
      "aat:300008706"
    ],
    "id": 2166363,
    "name:xx": "Big Black Creek"
  }
}
