{
  "type": "FeatureCollection",
  "features": [
    {
      "geometry": {
        "type": "Point",
        "coordinates": [
          24.916667,
          35.1
        ]
      },
      "type": "Feature",
      "properties": {
        "hierarchy": [
          "tgn:7221990",
          "tgn:7002690",
          "tgn:7012056",
          "tgn:1000003",
          "tgn:1000074",
          "tgn:7029392"
        ],
        "placetype": [
          "aat:300008347"
        ],
        "id": 7221990,
        "name:xx": "Panayía"
      }
    },
    {
      "geometry": {
        "type": "Point",
        "coordinates": [
          25.066667,
          35
        ]
      },
      "type": "Feature",
      "properties": {
        "hierarchy": [
          "tgn:7221991",
          "tgn:7002690",
          "tgn:7012056",
          "tgn:1000003",
          "tgn:1000074",
          "tgn:7029392"
        ],
        "placetype": [
          "aat:300008347"
        ],
        "id": 7221991,
        "name:xx": "Panayía"
      }
    },
    {
      "geometry": {
        "type": "Point",
        "coordinates": [
          21.4,
          37.916667
        ]
      },
      "type": "Feature",
      "properties": {
        "hierarchy": [
          "tgn:7221992",
          "tgn:7002743",
          "tgn:7017076",
          "tgn:1000003",
          "tgn:1000074",
          "tgn:7029392"
        ],
        "placetype": [
          "aat:300008347"
        ],
        "id": 7221992,
        "name:xx": "Panayaíika"
      }
    },
    {
      "geometry": {
        "type": "Point",
        "coordinates": [
          24.983333,
          35.133333
        ]
      },
      "type": "Feature",
      "properties": {
        "hierarchy": [
          "tgn:7221993",
          "tgn:7002690",
          "tgn:7012056",
          "tgn:1000003",
          "tgn:1000074",
          "tgn:7029392"
        ],
        "placetype": [
          "aat:300008347"
        ],
        "id": 7221993,
        "name:xx": "Panasós"
      }
    },
    {
      "geometry": {
        "type": "Point",
        "coordinates": [
          22.816667,
          37.633333
        ]
      },
      "type": "Feature",
      "properties": {
        "hierarchy": [
          "tgn:7221994",
          "tgn:7002739",
          "tgn:7017076",
          "tgn:1000003",
          "tgn:1000074",
          "tgn:7029392"
        ],
        "placetype": [
          "aat:300008347"
        ],
        "id": 7221994,
        "name:xx": "Panarítis"
      }
    },
    {
      "geometry": {
        "type": "Point",
        "coordinates": [
          22.533333,
          38
        ]
      },
      "type": "Feature",
      "properties": {
        "hierarchy": [
          "tgn:7221995",
          "tgn:7002741",
          "tgn:7017076",
          "tgn:1000003",
          "tgn:1000074",
          "tgn:7029392"
        ],
        "placetype": [
          "aat:300008347"
        ],
        "id": 7221995,
        "name:xx": "Panarítion"
      }
    },
    {
      "geometry": {
        "type": "Point",
        "coordinates": [
          21.433333,
          40.25
        ]
      },
      "type": "Feature",
      "properties": {
        "hierarchy": [
          "tgn:7221996",
          "tgn:7002721",
          "tgn:7002715",
          "tgn:1000003",
          "tgn:1000074",
          "tgn:7029392"
        ],
        "placetype": [
          "aat:300008347"
        ],
        "id": 7221996,
        "name:xx": "Panaríti"
      }
    },
    {
      "geometry": {
        "type": "Point",
        "coordinates": [
          23.783333,
          35.4
        ]
      },
      "type": "Feature",
      "properties": {
        "hierarchy": [
          "tgn:7221997",
          "tgn:7002690",
          "tgn:7012056",
          "tgn:1000003",
          "tgn:1000074",
          "tgn:7029392"
        ],
        "placetype": [
          "aat:300008347"
        ],
        "id": 7221997,
        "name:xx": "Pananianá"
      }
    },
    {
      "geometry": {
        "type": "Point",
        "coordinates": [
          23.5,
          38.183333
        ]
      },
      "type": "Feature",
      "properties": {
        "hierarchy": [
          "tgn:7221998",
          "tgn:7002681",
          "tgn:7001395",
          "tgn:1000003",
          "tgn:1000074",
          "tgn:7029392"
        ],
        "placetype": [
          "aat:300008347"
        ],
        "id": 7221998,
        "name:xx": "Pánakton"
      }
    },
    {
      "geometry": {
        "type": "Point",
        "coordinates": [
          21.9,
          38.2
        ]
      },
      "type": "Feature",
      "properties": {
        "hierarchy": [
          "tgn:7221999",
          "tgn:7002680",
          "tgn:7001395",
          "tgn:1000003",
          "tgn:1000074",
          "tgn:7029392"
        ],
        "placetype": [
          "aat:300008795"
        ],
        "id": 7221999,
        "name:xx": "Panakhaïkón Óros"
      }
    }
  ]
}
