{
  "type": "FeatureCollection",
  "features": [
    {
      "geometry": {
        "type": "Point",
        "coordinates": [
          -72.7333,
          41.6167
        ]
      },
      "type": "Feature",
      "properties": {
        "hierarchy": [
          "tgn:2016600",
          "tgn:1000001",
          "tgn:1002461",
          "tgn:7012149",
          "tgn:7007159",
          "tgn:7029392"
        ],
        "placetype": [
          "aat:300008347"
        ],
        "id": 2016600,
        "name:xx": "Berlin"
      }
    },
    {
      "geometry": {
        "type": "Point",
        "coordinates": [
          -72.7333,
          41.5167
        ]
      },
      "type": "Feature",
      "properties": {
        "hierarchy": [
          "tgn:2016603",
          "tgn:1000001",
          "tgn:1002664",
          "tgn:7012149",
          "tgn:7007159",
          "tgn:7029392"
        ],
        "placetype": [
          "aat:300008347"
        ],
        "id": 2016603,
        "name:xx": "Beseck Lake"
      }
    },
    {
      "geometry": {
        "type": "Point",
        "coordinates": [
          -72.9833,
          41.4167
        ]
      },
      "type": "Feature",
      "properties": {
        "hierarchy": [
          "tgn:2016604",
          "tgn:1000001",
          "tgn:1002712",
          "tgn:7012149",
          "tgn:7007159",
          "tgn:7029392"
        ],
        "placetype": [
          "aat:300008347"
        ],
        "id": 2016604,
        "name:xx": "Bethany"
      }
    },
    {
      "geometry": {
        "type": "Point",
        "coordinates": [
          -73.4,
          41.3667
        ]
      },
      "type": "Feature",
      "properties": {
        "hierarchy": [
          "tgn:2016605",
          "tgn:1002366",
          "tgn:1000001",
          "tgn:7012149",
          "tgn:7007159",
          "tgn:7029392"
        ],
        "placetype": [
          "aat:300008347"
        ],
        "id": 2016605,
        "name:xx": "Bethel"
      }
    },
    {
      "geometry": {
        "type": "Point",
        "coordinates": [
          -73.2,
          41.6333
        ]
      },
      "type": "Feature",
      "properties": {
        "hierarchy": [
          "tgn:2016608",
          "tgn:1000001",
          "tgn:1002601",
          "tgn:7012149",
          "tgn:7007159",
          "tgn:7029392"
        ],
        "placetype": [
          "aat:300008347"
        ],
        "id": 2016608,
        "name:xx": "Bethlehem"
      }
    },
    {
      "geometry": {
        "type": "Point",
        "coordinates": [
          -73.4333,
          41.5333
        ]
      },
      "type": "Feature",
      "properties": {
        "hierarchy": [
          "tgn:2016609",
          "tgn:1000001",
          "tgn:1002601",
          "tgn:7012149",
          "tgn:7007159",
          "tgn:7029392"
        ],
        "placetype": [
          "aat:300008347"
        ],
        "id": 2016609,
        "name:xx": "Birch Groves"
      }
    }
  ]
}
