{
  "geometry": {
    "type": "Point",
    "coordinates": [
      -149.1333,
      64.7167
    ]
  },
  "type": "Feature",
  "properties": {
    "hierarchy": [
      "tgn:2645976",
      "tgn:7006450",
      "tgn:1000001",
      "tgn:7012149",
      "tgn:2000089",
      "tgn:7029392"
    ],
    "placetype": [
      "aat:300008791"
    ],
    "id": 2645976,
    "name:xx": "Sawmill Island"
  }
}
