{
  "type": "FeatureCollection",
  "features": [
    {
      "geometry": {
        "type": "Point",
        "coordinates": [
          5.966667,
          52.95
        ]
      },
      "type": "Feature",
      "properties": {
        "hierarchy": [
          "tgn:4008235",
          "tgn:7003616",
          "tgn:1000003",
          "tgn:7016845",
          "tgn:7029392"
        ],
        "placetype": [
          "aat:300008347"
        ],
        "name:nl": "Oranjewoud",
        "id": 4008235
      }
    },
    {
      "geometry": {
        "type": "Point",
        "coordinates": [
          -1.233333,
          42.983333
        ]
      },
      "type": "Feature",
      "properties": {
        "hierarchy": [
          "tgn:4008236",
          "tgn:7001155",
          "tgn:1000003",
          "tgn:7002790",
          "tgn:1000095",
          "tgn:7029392"
        ],
        "placetype": [
          "aat:300008347"
        ],
        "id": 4008236,
        "name:xx": "Orbaiceta"
      }
    }
  ]
}
