{
  "geometry": {
    "type": "Point",
    "coordinates": [
      -116.8833,
      46.1833
    ]
  },
  "type": "Feature",
  "properties": {
    "hierarchy": [
      "tgn:2204535",
      "tgn:1000001",
      "tgn:7012149",
      "tgn:2000486",
      "tgn:7007250",
      "tgn:7029392"
    ],
    "placetype": [
      "aat:300008761"
    ],
    "id": 2204535,
    "name:xx": "Buffalo Draw"
  }
}
