{
  "type": "FeatureCollection",
  "features": [
    {
      "geometry": {
        "type": "Point",
        "coordinates": [
          -1.283333,
          54.616667
        ]
      },
      "type": "Feature",
      "properties": {
        "hierarchy": [
          "tgn:7445241",
          "tgn:7002445",
          "tgn:1000003",
          "tgn:7019067",
          "tgn:7008591",
          "tgn:7029392"
        ],
        "placetype": [
          "aat:300008347"
        ],
        "name:en": "Wolviston",
        "id": 7445241
      }
    },
    {
      "geometry": {
        "type": "Point",
        "coordinates": [
          -1.366667,
          52.483333
        ]
      },
      "type": "Feature",
      "properties": {
        "hierarchy": [
          "tgn:7445242",
          "tgn:7002445",
          "tgn:1000003",
          "tgn:7008178",
          "tgn:7008591",
          "tgn:7029392"
        ],
        "placetype": [
          "aat:300008347"
        ],
        "name:en": "Wolvey",
        "id": 7445242
      }
    },
    {
      "geometry": {
        "type": "Point",
        "coordinates": [
          -2.789444,
          51.691389
        ]
      },
      "type": "Feature",
      "properties": {
        "hierarchy": [
          "tgn:7445243",
          "tgn:7002443",
          "tgn:1000003",
          "tgn:5000560",
          "tgn:7008591",
          "tgn:7029392"
        ],
        "placetype": [
          "aat:300008347"
        ],
        "name:en": "Wolvesnewton",
        "id": 7445243
      }
    },
    {
      "geometry": {
        "type": "Point",
        "coordinates": [
          -1.7,
          52.25
        ]
      },
      "type": "Feature",
      "properties": {
        "hierarchy": [
          "tgn:7445244",
          "tgn:7002445",
          "tgn:1000003",
          "tgn:7008178",
          "tgn:7008591",
          "tgn:7029392"
        ],
        "placetype": [
          "aat:300008347"
        ],
        "name:en": "Wolverton",
        "id": 7445244
      }
    },
    {
      "geometry": {
        "type": "Point",
        "coordinates": [
          -1.2,
          51.316667
        ]
      },
      "type": "Feature",
      "properties": {
        "hierarchy": [
          "tgn:7445246",
          "tgn:7002445",
          "tgn:1000003",
          "tgn:7008139",
          "tgn:7008591",
          "tgn:7029392"
        ],
        "placetype": [
          "aat:300008347"
        ],
        "name:en": "Wolverton",
        "id": 7445246
      }
    },
    {
      "geometry": {
        "type": "Point",
        "coordinates": [
          -1.383333,
          52.366667
        ]
      },
      "type": "Feature",
      "properties": {
        "hierarchy": [
          "tgn:7445249",
          "tgn:7002445",
          "tgn:1000003",
          "tgn:7008178",
          "tgn:7008591",
          "tgn:7029392"
        ],
        "placetype": [
          "aat:300008347"
        ],
        "name:en": "Wolston",
        "id": 7445249
      }
    }
  ]
}
