{
  "geometry": {
    "type": "Point",
    "coordinates": [
      -75.283333,
      -48.15
    ]
  },
  "type": "Feature",
  "properties": {
    "hierarchy": [
      "tgn:7276355",
      "tgn:1001623",
      "tgn:1000049",
      "tgn:1000002",
      "tgn:7029392"
    ],
    "placetype": [
      "aat:300387026"
    ],
    "id": 7276355,
    "name:xx": "Tomás, Paso"
  }
}
