{
  "type": "FeatureCollection",
  "features": [
    {
      "geometry": {
        "type": "Point",
        "coordinates": [
          8.366667,
          48.6
        ]
      },
      "type": "Feature",
      "properties": {
        "hierarchy": [
          "tgn:7094021",
          "tgn:7003692",
          "tgn:1000003",
          "tgn:7000084",
          "tgn:7029392"
        ],
        "placetype": [
          "aat:300008699"
        ],
        "id": 7094021,
        "name:xx": "Schönmünz"
      }
    },
    {
      "geometry": {
        "type": "Point",
        "coordinates": [
          8.3,
          48.566667
        ]
      },
      "type": "Feature",
      "properties": {
        "hierarchy": [
          "tgn:7094022",
          "tgn:7003692",
          "tgn:1000003",
          "tgn:7000084",
          "tgn:7029392"
        ],
        "placetype": [
          "aat:300000206"
        ],
        "id": 7094022,
        "name:xx": "Schönmünz"
      }
    },
    {
      "geometry": {
        "type": "Point",
        "coordinates": [
          10.133333,
          53.966667
        ]
      },
      "type": "Feature",
      "properties": {
        "hierarchy": [
          "tgn:7094023",
          "tgn:1000003",
          "tgn:7003688",
          "tgn:7000084",
          "tgn:7029392"
        ],
        "placetype": [
          "aat:300008347"
        ],
        "id": 7094023,
        "name:xx": "Schönmoor"
      }
    },
    {
      "geometry": {
        "type": "Point",
        "coordinates": [
          9.583333,
          53.8
        ]
      },
      "type": "Feature",
      "properties": {
        "hierarchy": [
          "tgn:7094024",
          "tgn:1000003",
          "tgn:7003688",
          "tgn:7000084",
          "tgn:7029392"
        ],
        "placetype": [
          "aat:300008347"
        ],
        "id": 7094024,
        "name:xx": "Schönmoor"
      }
    },
    {
      "geometry": {
        "type": "Point",
        "coordinates": [
          9.6,
          48.416667
        ]
      },
      "type": "Feature",
      "properties": {
        "hierarchy": [
          "tgn:7094025",
          "tgn:7003692",
          "tgn:1000003",
          "tgn:7000084",
          "tgn:7029392"
        ],
        "placetype": [
          "aat:300008795"
        ],
        "id": 7094025,
        "name:xx": "Schönmehl"
      }
    },
    {
      "geometry": {
        "type": "Point",
        "coordinates": [
          10.45,
          47.916667
        ]
      },
      "type": "Feature",
      "properties": {
        "hierarchy": [
          "tgn:7094026",
          "tgn:7003669",
          "tgn:1000003",
          "tgn:7000084",
          "tgn:7029392"
        ],
        "placetype": [
          "aat:300000206"
        ],
        "id": 7094026,
        "name:xx": "Schönlings"
      }
    },
    {
      "geometry": {
        "type": "Point",
        "coordinates": [
          12.3,
          50.3
        ]
      },
      "type": "Feature",
      "properties": {
        "hierarchy": [
          "tgn:7094027",
          "tgn:1000003",
          "tgn:7003685",
          "tgn:7000084",
          "tgn:7029392"
        ],
        "placetype": [
          "aat:300008863"
        ],
        "id": 7094027,
        "name:xx": "Schönlinder Wald"
      }
    },
    {
      "geometry": {
        "type": "Point",
        "coordinates": [
          12.516667,
          48.1
        ]
      },
      "type": "Feature",
      "properties": {
        "hierarchy": [
          "tgn:7094028",
          "tgn:7003669",
          "tgn:1000003",
          "tgn:7000084",
          "tgn:7029392"
        ],
        "placetype": [
          "aat:300000206"
        ],
        "id": 7094028,
        "name:xx": "Schönlinden"
      }
    },
    {
      "geometry": {
        "type": "Point",
        "coordinates": [
          12.983333,
          50.466667
        ]
      },
      "type": "Feature",
      "properties": {
        "hierarchy": [
          "tgn:7094029",
          "tgn:1000003",
          "tgn:7003685",
          "tgn:7000084",
          "tgn:7029392"
        ],
        "placetype": [
          "aat:300008347"
        ],
        "id": 7094029,
        "name:xx": "Schönlind"
      }
    }
  ]
}
