{
  "geometry": {
    "type": "Point",
    "coordinates": [
      -96.2667,
      41.9167
    ]
  },
  "type": "Feature",
  "properties": {
    "hierarchy": [
      "tgn:2663287",
      "tgn:1000001",
      "tgn:2001326",
      "tgn:7012149",
      "tgn:7007525",
      "tgn:7029392"
    ],
    "placetype": [
      "aat:300008706"
    ],
    "id": 2663287,
    "name:xx": "Silver Creek"
  }
}
