{
  "geometry": {
    "type": "Point",
    "coordinates": [
      -96.0333,
      29.9667
    ]
  },
  "type": "Feature",
  "properties": {
    "hierarchy": [
      "tgn:2414501",
      "tgn:1000001",
      "tgn:7012149",
      "tgn:1002981",
      "tgn:7007826",
      "tgn:7029392"
    ],
    "placetype": [
      "aat:300008706"
    ],
    "id": 2414501,
    "name:xx": "Irons Creek"
  }
}
