{
  "geometry": {
    "type": "Point",
    "coordinates": [
      -117.9167,
      42.9833
    ]
  },
  "type": "Feature",
  "properties": {
    "hierarchy": [
      "tgn:2722999",
      "tgn:1000001",
      "tgn:7012149",
      "tgn:2001718",
      "tgn:7007708",
      "tgn:7029392"
    ],
    "placetype": [
      "aat:300008746"
    ],
    "id": 2722999,
    "name:xx": "Tire Tube Cave"
  }
}
