{
  "geometry": {
    "type": "Point",
    "coordinates": [
      -82.9667,
      35.5667
    ]
  },
  "type": "Feature",
  "properties": {
    "hierarchy": [
      "tgn:2276982",
      "tgn:1000001",
      "tgn:7012149",
      "tgn:2001503",
      "tgn:7007709",
      "tgn:7029392"
    ],
    "placetype": [
      "aat:300008761"
    ],
    "id": 2276982,
    "name:xx": "Davis Cove"
  }
}
