{
  "geometry": {
    "type": "Point",
    "coordinates": [
      -87.0667,
      40.9333
    ]
  },
  "type": "Feature",
  "properties": {
    "hierarchy": [
      "tgn:2033326",
      "tgn:1000001",
      "tgn:7012149",
      "tgn:1002512",
      "tgn:7007252",
      "tgn:7029392"
    ],
    "placetype": [
      "aat:300387016"
    ],
    "id": 2033326,
    "name:xx": "Pleasant Ridge"
  }
}
