{
  "geometry": {
    "type": "Point",
    "coordinates": [
      -81.3667,
      30.0167
    ]
  },
  "type": "Feature",
  "properties": {
    "hierarchy": [
      "tgn:2493820",
      "tgn:1000001",
      "tgn:7012149",
      "tgn:2000283",
      "tgn:7007240",
      "tgn:7029392"
    ],
    "placetype": [
      "aat:300008706"
    ],
    "id": 2493820,
    "name:xx": "Marshall Creek"
  }
}
