{
  "geometry": {
    "type": "Point",
    "coordinates": [
      -64.6667,
      -15.2167
    ]
  },
  "type": "Feature",
  "properties": {
    "hierarchy": [
      "tgn:1020335",
      "tgn:1000525",
      "tgn:1000046",
      "tgn:1000002",
      "tgn:7029392"
    ],
    "placetype": [
      "aat:300008347"
    ],
    "id": 1020335,
    "name:xx": "Loreto"
  }
}
