{
  "geometry": {
    "type": "Point",
    "coordinates": [
      -71.4333,
      41.5333
    ]
  },
  "type": "Feature",
  "properties": {
    "hierarchy": [
      "tgn:2757125",
      "tgn:1002996",
      "tgn:1000001",
      "tgn:7012149",
      "tgn:7007711",
      "tgn:7029392"
    ],
    "placetype": [
      "aat:300006191"
    ],
    "id": 2757125,
    "name:xx": "Wertz And Viall Pond"
  }
}
