{
  "geometry": {
    "type": "Point",
    "coordinates": [
      -103.1167,
      45.1667
    ]
  },
  "type": "Feature",
  "properties": {
    "hierarchy": [
      "tgn:2327809",
      "tgn:1000001",
      "tgn:2001779",
      "tgn:7012149",
      "tgn:7007713",
      "tgn:7029392"
    ],
    "placetype": [
      "aat:300008761"
    ],
    "id": 2327809,
    "name:xx": "Fish Draw"
  }
}
