{
  "geometry": {
    "type": "Point",
    "coordinates": [
      43.1667,
      49.8833
    ]
  },
  "type": "Feature",
  "properties": {
    "hierarchy": [
      "tgn:1121294",
      "tgn:1000004",
      "tgn:7013207",
      "tgn:7018214",
      "tgn:7002435",
      "tgn:7029392"
    ],
    "placetype": [
      "aat:300008707"
    ],
    "id": 1121294,
    "name:xx": "Archeda"
  }
}
