{
  "geometry": {
    "type": "Point",
    "coordinates": [
      -80.5667,
      40.4667
    ]
  },
  "type": "Feature",
  "properties": {
    "hierarchy": [
      "tgn:2394765",
      "tgn:1000001",
      "tgn:7012149",
      "tgn:1002449",
      "tgn:7013961",
      "tgn:7029392"
    ],
    "placetype": [
      "aat:300008699"
    ],
    "id": 2394765,
    "name:xx": "Holbert Run"
  }
}
