{
  "geometry": {
    "type": "Point",
    "coordinates": [
      -108.55,
      40.0167
    ]
  },
  "type": "Feature",
  "properties": {
    "hierarchy": [
      "tgn:2611086",
      "tgn:1000001",
      "tgn:7012149",
      "tgn:7007158",
      "tgn:2000243",
      "tgn:7029392"
    ],
    "placetype": [
      "aat:300008761"
    ],
    "id": 2611086,
    "name:xx": "Red Hill Gulch"
  }
}
