{
  "geometry": {
    "type": "Point",
    "coordinates": [
      79.923,
      27.2097
    ]
  },
  "type": "Feature",
  "properties": {
    "hierarchy": [
      "tgn:7562121",
      "tgn:1000004",
      "tgn:7000198",
      "tgn:7016722",
      "tgn:7029392"
    ],
    "placetype": [
      "aat:300008347"
    ],
    "name:en": "Nunkhāra",
    "id": 7562121
  }
}
