{
  "geometry": {
    "type": "Point",
    "coordinates": [
      22.3333,
      65.85
    ]
  },
  "type": "Feature",
  "properties": {
    "hierarchy": [
      "tgn:1063492",
      "tgn:1000003",
      "tgn:7003774",
      "tgn:1000097",
      "tgn:7029392"
    ],
    "placetype": [
      "aat:300008347"
    ],
    "id": 1063492,
    "name:xx": "Råneå"
  }
}
