{
  "geometry": {
    "type": "Point",
    "coordinates": [
      -84.6833,
      38.5333
    ]
  },
  "type": "Feature",
  "properties": {
    "hierarchy": [
      "tgn:2270761",
      "tgn:1000001",
      "tgn:7012149",
      "tgn:1002763",
      "tgn:7007255",
      "tgn:7029392"
    ],
    "placetype": [
      "aat:300008699"
    ],
    "id": 2270761,
    "name:xx": "Cub Branch"
  }
}
