{
  "geometry": {
    "type": "Point",
    "coordinates": [
      -97.5333,
      41.1667
    ]
  },
  "type": "Feature",
  "properties": {
    "hierarchy": [
      "tgn:2062520",
      "tgn:1000001",
      "tgn:7012149",
      "tgn:2001387",
      "tgn:7007525",
      "tgn:7029392"
    ],
    "placetype": [
      "aat:300008347"
    ],
    "id": 2062520,
    "name:xx": "Osceola"
  }
}
