{
  "type": "FeatureCollection",
  "features": [
    {
      "geometry": {
        "type": "Point",
        "coordinates": [
          172.383333,
          -40.783333
        ]
      },
      "type": "Feature",
      "properties": {
        "hierarchy": [
          "tgn:7517360",
          "tgn:1009227",
          "tgn:1000226",
          "tgn:7520095",
          "tgn:1000006",
          "tgn:7029392"
        ],
        "placetype": [
          "aat:300008699"
        ],
        "name:en": "North Branch Anatori River",
        "id": 7517360
      }
    },
    {
      "geometry": {
        "type": "Point",
        "coordinates": [
          166.1,
          -50.783333
        ]
      },
      "type": "Feature",
      "properties": {
        "hierarchy": [
          "tgn:7517362",
          "tgn:1009227",
          "tgn:1000226",
          "tgn:7016822",
          "tgn:1000006",
          "tgn:7029392"
        ],
        "placetype": [
          "aat:300132316"
        ],
        "name:en": "North Arm",
        "id": 7517362
      }
    },
    {
      "geometry": {
        "type": "Point",
        "coordinates": [
          166.2,
          -50.733333
        ]
      },
      "type": "Feature",
      "properties": {
        "hierarchy": [
          "tgn:7517363",
          "tgn:1009227",
          "tgn:1000226",
          "tgn:7016822",
          "tgn:1000006",
          "tgn:7029392"
        ],
        "placetype": [
          "aat:300132316"
        ],
        "name:en": "North Arm",
        "id": 7517363
      }
    },
    {
      "geometry": {
        "type": "Point",
        "coordinates": [
          167.7,
          -47.166667
        ]
      },
      "type": "Feature",
      "properties": {
        "hierarchy": [
          "tgn:7517364",
          "tgn:1009227",
          "tgn:1000226",
          "tgn:7016822",
          "tgn:1000006",
          "tgn:7029392"
        ],
        "placetype": [
          "aat:300132316"
        ],
        "name:en": "North Arm",
        "id": 7517364
      }
    },
    {
      "geometry": {
        "type": "Point",
        "coordinates": [
          168.183333,
          -47.05
        ]
      },
      "type": "Feature",
      "properties": {
        "hierarchy": [
          "tgn:7517365",
          "tgn:1009227",
          "tgn:1000226",
          "tgn:7016822",
          "tgn:1000006",
          "tgn:7029392"
        ],
        "placetype": [
          "aat:300132316"
        ],
        "name:en": "North Arm",
        "id": 7517365
      }
    },
    {
      "geometry": {
        "type": "Point",
        "coordinates": [
          168.016667,
          -46.883333
        ]
      },
      "type": "Feature",
      "properties": {
        "hierarchy": [
          "tgn:7517366",
          "tgn:1009227",
          "tgn:1000226",
          "tgn:7016822",
          "tgn:1000006",
          "tgn:7029392"
        ],
        "placetype": [
          "aat:300132316"
        ],
        "name:en": "North Arm",
        "id": 7517366
      }
    },
    {
      "geometry": {
        "type": "Point",
        "coordinates": [
          167.366667,
          -45.483333
        ]
      },
      "type": "Feature",
      "properties": {
        "hierarchy": [
          "tgn:7517367",
          "tgn:1009227",
          "tgn:1000226",
          "tgn:7016822",
          "tgn:1000006",
          "tgn:7029392"
        ],
        "placetype": [
          "aat:300132316"
        ],
        "name:en": "North Arm",
        "id": 7517367
      }
    },
    {
      "geometry": {
        "type": "Point",
        "coordinates": [
          -177.916667,
          -29.216667
        ]
      },
      "type": "Feature",
      "properties": {
        "hierarchy": [
          "tgn:7517368",
          "tgn:1008380",
          "tgn:7000507",
          "tgn:1000226",
          "tgn:1000006",
          "tgn:7029392"
        ],
        "placetype": [
          "aat:300386968"
        ],
        "name:en": "North Anchorage",
        "id": 7517368
      }
    },
    {
      "geometry": {
        "type": "Point",
        "coordinates": [
          172.95,
          -42.3
        ]
      },
      "type": "Feature",
      "properties": {
        "hierarchy": [
          "tgn:7517369",
          "tgn:1009227",
          "tgn:7001866",
          "tgn:1000226",
          "tgn:1000006",
          "tgn:7029392"
        ],
        "placetype": [
          "aat:300008795"
        ],
        "name:en": "Northampton, Mount",
        "id": 7517369
      }
    }
  ]
}
