{
  "geometry": {
    "type": "Point",
    "coordinates": [
      -155.0833,
      19.3833
    ]
  },
  "type": "Feature",
  "properties": {
    "hierarchy": [
      "tgn:2373295",
      "tgn:7023902",
      "tgn:1000001",
      "tgn:7012149",
      "tgn:7007249",
      "tgn:7029392"
    ],
    "placetype": [
      "aat:300008798"
    ],
    "id": 2373295,
    "name:xx": "Halulu, Puu"
  }
}
