{
  "geometry": {
    "type": "Point",
    "coordinates": [
      128.2167,
      43.35
    ]
  },
  "type": "Feature",
  "properties": {
    "hierarchy": [
      "tgn:1067897",
      "tgn:1000004",
      "tgn:7002372",
      "tgn:1000111",
      "tgn:7029392"
    ],
    "placetype": [
      "aat:300008347"
    ],
    "id": 1067897,
    "name:xx": "Dunhua"
  }
}
