{
  "geometry": {
    "type": "Point",
    "coordinates": [
      -80.8833,
      35.1333
    ]
  },
  "type": "Feature",
  "properties": {
    "hierarchy": [
      "tgn:2195434",
      "tgn:1000001",
      "tgn:7012149",
      "tgn:7014021",
      "tgn:7007709",
      "tgn:7029392"
    ],
    "placetype": [
      "aat:300008347"
    ],
    "id": 2195434,
    "name:xx": "British Woods"
  }
}
