{
  "geometry": {
    "type": "Point",
    "coordinates": [
      -106.5333,
      35.6833
    ]
  },
  "type": "Feature",
  "properties": {
    "hierarchy": [
      "tgn:2155707",
      "tgn:1000001",
      "tgn:7012149",
      "tgn:2001451",
      "tgn:7007566",
      "tgn:7029392"
    ],
    "placetype": [
      "aat:300008761"
    ],
    "id": 2155707,
    "name:xx": "Bear Springs Canyon"
  }
}
