{
  "geometry": {
    "type": "Point",
    "coordinates": [
      91.9167,
      22.1333
    ]
  },
  "type": "Feature",
  "properties": {
    "hierarchy": [
      "tgn:1065637",
      "tgn:7000188",
      "tgn:1000004",
      "tgn:1000105",
      "tgn:7029392"
    ],
    "placetype": [
      "aat:300008347"
    ],
    "id": 1065637,
    "name:xx": "Chāndpur"
  }
}
