{
  "geometry": {
    "type": "Point",
    "coordinates": [
      -81.6167,
      36.6333
    ]
  },
  "type": "Feature",
  "properties": {
    "hierarchy": [
      "tgn:2700268",
      "tgn:1000001",
      "tgn:7012149",
      "tgn:7007919",
      "tgn:7029392"
    ],
    "placetype": [
      "aat:300008699"
    ],
    "id": 2700268,
    "name:xx": "Sturgill Branch"
  }
}
