{
  "type": "FeatureCollection",
  "features": [
    {
      "geometry": {
        "type": "Point",
        "coordinates": [
          -93.3167,
          44.3667
        ]
      },
      "type": "Feature",
      "properties": {
        "hierarchy": [
          "tgn:2779000",
          "tgn:1000001",
          "tgn:7012149",
          "tgn:2001064",
          "tgn:7007521",
          "tgn:7029392"
        ],
        "placetype": [
          "aat:300008706"
        ],
        "id": 2779000,
        "name:xx": "Wolf Creek"
      }
    },
    {
      "geometry": {
        "type": "Point",
        "coordinates": [
          -95.6167,
          46
        ]
      },
      "type": "Feature",
      "properties": {
        "hierarchy": [
          "tgn:2779001",
          "tgn:1000001",
          "tgn:2001019",
          "tgn:7012149",
          "tgn:7007521",
          "tgn:7029392"
        ],
        "placetype": [
          "aat:300008706"
        ],
        "id": 2779001,
        "name:xx": "Wolf Creek"
      }
    },
    {
      "geometry": {
        "type": "Point",
        "coordinates": [
          -94.15,
          46.1
        ]
      },
      "type": "Feature",
      "properties": {
        "hierarchy": [
          "tgn:2779002",
          "tgn:1000001",
          "tgn:7012149",
          "tgn:2001047",
          "tgn:7007521",
          "tgn:7029392"
        ],
        "placetype": [
          "aat:300008706"
        ],
        "id": 2779002,
        "name:xx": "Wolf Creek"
      }
    },
    {
      "geometry": {
        "type": "Point",
        "coordinates": [
          -88.8,
          31.8667
        ]
      },
      "type": "Feature",
      "properties": {
        "hierarchy": [
          "tgn:2779003",
          "tgn:1000001",
          "tgn:7012149",
          "tgn:7007522",
          "tgn:7029392"
        ],
        "placetype": [
          "aat:300008706"
        ],
        "id": 2779003,
        "name:xx": "Wolf Creek"
      }
    },
    {
      "geometry": {
        "type": "Point",
        "coordinates": [
          -90.2667,
          32.7
        ]
      },
      "type": "Feature",
      "properties": {
        "hierarchy": [
          "tgn:2779004",
          "tgn:1000001",
          "tgn:7012149",
          "tgn:2001167",
          "tgn:7007522",
          "tgn:7029392"
        ],
        "placetype": [
          "aat:300008706"
        ],
        "id": 2779004,
        "name:xx": "Wolf Creek"
      }
    },
    {
      "geometry": {
        "type": "Point",
        "coordinates": [
          -89.2167,
          32.7667
        ]
      },
      "type": "Feature",
      "properties": {
        "hierarchy": [
          "tgn:2779005",
          "tgn:1000001",
          "tgn:7012149",
          "tgn:2001135",
          "tgn:7007522",
          "tgn:7029392"
        ],
        "placetype": [
          "aat:300008706"
        ],
        "id": 2779005,
        "name:xx": "Wolf Creek"
      }
    },
    {
      "geometry": {
        "type": "Point",
        "coordinates": [
          -89.3,
          34.3
        ]
      },
      "type": "Feature",
      "properties": {
        "hierarchy": [
          "tgn:2779006",
          "tgn:1000001",
          "tgn:7012149",
          "tgn:2001121",
          "tgn:7007522",
          "tgn:7029392"
        ],
        "placetype": [
          "aat:300008706"
        ],
        "id": 2779006,
        "name:xx": "Wolf Creek"
      }
    },
    {
      "geometry": {
        "type": "Point",
        "coordinates": [
          -88.6167,
          34.0167
        ]
      },
      "type": "Feature",
      "properties": {
        "hierarchy": [
          "tgn:2779007",
          "tgn:1000001",
          "tgn:7012149",
          "tgn:2001133",
          "tgn:7007522",
          "tgn:7029392"
        ],
        "placetype": [
          "aat:300008706"
        ],
        "id": 2779007,
        "name:xx": "Wolf Creek"
      }
    },
    {
      "geometry": {
        "type": "Point",
        "coordinates": [
          -88.65,
          34.7
        ]
      },
      "type": "Feature",
      "properties": {
        "hierarchy": [
          "tgn:2779008",
          "tgn:1000001",
          "tgn:7012149",
          "tgn:2001144",
          "tgn:7007522",
          "tgn:7029392"
        ],
        "placetype": [
          "aat:300008706"
        ],
        "id": 2779008,
        "name:xx": "Wolf Creek"
      }
    },
    {
      "geometry": {
        "type": "Point",
        "coordinates": [
          -90.15,
          34.8167
        ]
      },
      "type": "Feature",
      "properties": {
        "hierarchy": [
          "tgn:2779009",
          "tgn:1000001",
          "tgn:2001102",
          "tgn:7012149",
          "tgn:7007522",
          "tgn:7029392"
        ],
        "placetype": [
          "aat:300008706"
        ],
        "id": 2779009,
        "name:xx": "Wolf Creek"
      }
    }
  ]
}
