{
  "geometry": {
    "type": "Point",
    "coordinates": [
      -117.6833,
      34.3167
    ]
  },
  "type": "Feature",
  "properties": {
    "hierarchy": [
      "tgn:2583355",
      "tgn:1000001",
      "tgn:7012149",
      "tgn:7007157",
      "tgn:1002608",
      "tgn:7029392"
    ],
    "placetype": [
      "aat:300266640"
    ],
    "id": 2583355,
    "name:xx": "Pine Mountain Ridge"
  }
}
