{
  "geometry": {
    "type": "Point",
    "coordinates": [
      23.0833,
      62.5667
    ]
  },
  "type": "Feature",
  "properties": {
    "hierarchy": [
      "tgn:1031500",
      "tgn:7024077",
      "tgn:1000003",
      "tgn:1000069",
      "tgn:7029392"
    ],
    "placetype": [
      "aat:300008347"
    ],
    "id": 1031500,
    "name:xx": "Peräseinäjoki"
  }
}
