{
  "geometry": {
    "type": "Point",
    "coordinates": [
      -85.7833,
      41.0833
    ]
  },
  "type": "Feature",
  "properties": {
    "hierarchy": [
      "tgn:2588678",
      "tgn:1000001",
      "tgn:7012149",
      "tgn:1002557",
      "tgn:7007252",
      "tgn:7029392"
    ],
    "placetype": [
      "aat:300008706"
    ],
    "id": 2588678,
    "name:xx": "Plunge Creek"
  }
}
