{
  "geometry": {
    "type": "Point",
    "coordinates": [
      8.9167,
      46.7167
    ]
  },
  "type": "Feature",
  "properties": {
    "hierarchy": [
      "tgn:1064421",
      "tgn:7003748",
      "tgn:1000003",
      "tgn:7011731",
      "tgn:7029392"
    ],
    "placetype": [
      "aat:300008347"
    ],
    "id": 1064421,
    "name:xx": "Somvix"
  }
}
