{
  "geometry": {
    "type": "Point",
    "coordinates": [
      -133.6333,
      55.45
    ]
  },
  "type": "Feature",
  "properties": {
    "hierarchy": [
      "tgn:2433636",
      "tgn:7006450",
      "tgn:1000001",
      "tgn:7012149",
      "tgn:2000082",
      "tgn:7029392"
    ],
    "placetype": [
      "aat:300132316"
    ],
    "id": 2433636,
    "name:xx": "Kelly Cove"
  }
}
