{
  "geometry": {
    "type": "Point",
    "coordinates": [
      -83.1667,
      35.6667
    ]
  },
  "type": "Feature",
  "properties": {
    "hierarchy": [
      "tgn:2146404",
      "tgn:1000001",
      "tgn:7012149",
      "tgn:7007709",
      "tgn:7029392"
    ],
    "placetype": [
      "aat:300008798"
    ],
    "id": 2146404,
    "name:xx": "Balsam Corner"
  }
}
