{
  "geometry": {
    "type": "Point",
    "coordinates": [
      -121.65,
      36.8167
    ]
  },
  "type": "Feature",
  "properties": {
    "hierarchy": [
      "tgn:2482289",
      "tgn:1000001",
      "tgn:7012149",
      "tgn:7007157",
      "tgn:1002684",
      "tgn:7029392"
    ],
    "placetype": [
      "aat:300008761"
    ],
    "id": 2482289,
    "name:xx": "Langley Canyon"
  }
}
