{
  "geometry": {
    "type": "Point",
    "coordinates": [
      31.15,
      29.316667
    ]
  },
  "type": "Feature",
  "properties": {
    "hierarchy": [
      "tgn:7534480",
      "tgn:7001242",
      "tgn:7001105",
      "tgn:7016833",
      "tgn:7029392"
    ],
    "placetype": [
      "aat:300343519"
    ],
    "name:en": "Majrūr Qushayshah, Ḩawḑ",
    "id": 7534480
  }
}
