{
  "geometry": {
    "type": "Point",
    "coordinates": [
      -123.15,
      46.2833
    ]
  },
  "type": "Feature",
  "properties": {
    "hierarchy": [
      "tgn:2318456",
      "tgn:1000001",
      "tgn:1002305",
      "tgn:7012149",
      "tgn:7007920",
      "tgn:7029392"
    ],
    "placetype": [
      "aat:300008706"
    ],
    "id": 2318456,
    "name:xx": "Erick Creek"
  }
}
