{
  "geometry": {
    "type": "Point",
    "coordinates": [
      -78.1833,
      38.7833
    ]
  },
  "type": "Feature",
  "properties": {
    "hierarchy": [
      "tgn:2671145",
      "tgn:1000001",
      "tgn:7012149",
      "tgn:2002193",
      "tgn:7007919",
      "tgn:7029392"
    ],
    "placetype": [
      "aat:300008706"
    ],
    "id": 2671145,
    "name:xx": "Smith Creek"
  }
}
