{
  "type": "FeatureCollection",
  "features": [
    {
      "geometry": {
        "type": "Point",
        "coordinates": [
          159.2,
          -9.0667
        ]
      },
      "type": "Feature",
      "properties": {
        "hierarchy": [
          "tgn:1010250",
          "tgn:1001188",
          "tgn:1000233",
          "tgn:1000006",
          "tgn:7029392"
        ],
        "placetype": [
          "aat:300386853"
        ],
        "id": 1010250,
        "name:xx": "Russell Islands"
      }
    },
    {
      "geometry": {
        "type": "Point",
        "coordinates": [
          -81.5833,
          24.6
        ]
      },
      "type": "Feature",
      "properties": {
        "hierarchy": [
          "tgn:1010251",
          "tgn:1000001",
          "tgn:7021534",
          "tgn:7012149",
          "tgn:1002676",
          "tgn:7007240",
          "tgn:7029392"
        ],
        "placetype": [
          "aat:300386853"
        ],
        "id": 1010251,
        "name:xx": "Saddlebunch Keys"
      }
    },
    {
      "geometry": {
        "type": "Point",
        "coordinates": [
          -64.8333,
          18.3167
        ]
      },
      "type": "Feature",
      "properties": {
        "hierarchy": [
          "tgn:1010253",
          "tgn:1000001",
          "tgn:7005118",
          "tgn:7029392"
        ],
        "placetype": [
          "aat:300386853"
        ],
        "id": 1010253,
        "name:xx": "Saint James Islands"
      }
    },
    {
      "geometry": {
        "type": "Point",
        "coordinates": [
          -82.7333,
          28.7833
        ]
      },
      "type": "Feature",
      "properties": {
        "hierarchy": [
          "tgn:1010254",
          "tgn:1000001",
          "tgn:1002269",
          "tgn:7012149",
          "tgn:7007240",
          "tgn:7029392"
        ],
        "placetype": [
          "aat:300386853"
        ],
        "id": 1010254,
        "name:xx": "Saint Martins Keys"
      }
    },
    {
      "geometry": {
        "type": "Point",
        "coordinates": [
          -1.15,
          49.5
        ]
      },
      "type": "Feature",
      "properties": {
        "hierarchy": [
          "tgn:1010256",
          "tgn:7002872",
          "tgn:1000003",
          "tgn:1000070",
          "tgn:7029392"
        ],
        "placetype": [
          "aat:300386853"
        ],
        "id": 1010256,
        "name:xx": "Saint-Marcouf, Iles"
      }
    },
    {
      "geometry": {
        "type": "Point",
        "coordinates": [
          -61.6167,
          15.8667
        ]
      },
      "type": "Feature",
      "properties": {
        "hierarchy": [
          "tgn:1010257",
          "tgn:7018312",
          "tgn:1000001",
          "tgn:7004545",
          "tgn:7029392"
        ],
        "placetype": [
          "aat:300386853"
        ],
        "id": 1010257,
        "name:xx": "Saintes, Îles des"
      }
    }
  ]
}
