{
  "geometry": {
    "type": "Point",
    "coordinates": [
      -78.05,
      39.3333
    ]
  },
  "type": "Feature",
  "properties": {
    "hierarchy": [
      "tgn:2117622",
      "tgn:1000001",
      "tgn:2002254",
      "tgn:7012149",
      "tgn:7013961",
      "tgn:7029392"
    ],
    "placetype": [
      "aat:300008347"
    ],
    "id": 2117622,
    "name:xx": "Bunker Hill"
  }
}
