{
  "geometry": {
    "type": "Point",
    "coordinates": [
      -88.3667,
      41.9167
    ]
  },
  "type": "Feature",
  "properties": {
    "hierarchy": [
      "tgn:2029789",
      "tgn:1000001",
      "tgn:7012149",
      "tgn:1002531",
      "tgn:7007251",
      "tgn:7029392"
    ],
    "placetype": [
      "aat:300008347"
    ],
    "id": 2029789,
    "name:xx": "Rainbow Hills"
  }
}
