{
  "geometry": {
    "type": "Point",
    "coordinates": [
      -85.8167,
      36.0833
    ]
  },
  "type": "Feature",
  "properties": {
    "hierarchy": [
      "tgn:2230491",
      "tgn:1000001",
      "tgn:7012149",
      "tgn:7007825",
      "tgn:7029392"
    ],
    "placetype": [
      "aat:300006191"
    ],
    "id": 2230491,
    "name:xx": "Center Hill Lake"
  }
}
