{
  "geometry": {
    "type": "Point",
    "coordinates": [
      -77.6833,
      42.55
    ]
  },
  "type": "Feature",
  "properties": {
    "hierarchy": [
      "tgn:2068772",
      "tgn:1000001",
      "tgn:7012149",
      "tgn:1002604",
      "tgn:7007568",
      "tgn:7029392"
    ],
    "placetype": [
      "aat:300008347"
    ],
    "id": 2068772,
    "name:xx": "Dansville"
  }
}
