{
  "geometry": {
    "type": "Point",
    "coordinates": [
      -84.4333,
      35.3667
    ]
  },
  "type": "Feature",
  "properties": {
    "hierarchy": [
      "tgn:2100079",
      "tgn:1000001",
      "tgn:7012149",
      "tgn:7022542",
      "tgn:7007825",
      "tgn:7029392"
    ],
    "placetype": [
      "aat:300008347",
      "aat:300387210"
    ],
    "id": 2100079,
    "name:xx": "Liberty Hill"
  }
}
