{
  "type": "FeatureCollection",
  "features": [
    {
      "geometry": {
        "type": "Point",
        "coordinates": [
          -72.2,
          43.15
        ]
      },
      "type": "Feature",
      "properties": {
        "hierarchy": [
          "tgn:2346750",
          "tgn:7019618",
          "tgn:1000001",
          "tgn:7012149",
          "tgn:7007564",
          "tgn:7029392"
        ],
        "placetype": [
          "aat:300008699"
        ],
        "id": 2346750,
        "name:xx": "Gee Brook"
      }
    },
    {
      "geometry": {
        "type": "Point",
        "coordinates": [
          -75.9167,
          42.5
        ]
      },
      "type": "Feature",
      "properties": {
        "hierarchy": [
          "tgn:2346751",
          "tgn:1000001",
          "tgn:1002302",
          "tgn:7012149",
          "tgn:7007568",
          "tgn:7029392"
        ],
        "placetype": [
          "aat:300008347"
        ],
        "id": 2346751,
        "name:xx": "Gee Brook"
      }
    },
    {
      "geometry": {
        "type": "Point",
        "coordinates": [
          -75.2167,
          41.9
        ]
      },
      "type": "Feature",
      "properties": {
        "hierarchy": [
          "tgn:2346752",
          "tgn:1000001",
          "tgn:1002328",
          "tgn:7012149",
          "tgn:7007568",
          "tgn:7029392"
        ],
        "placetype": [
          "aat:300008699"
        ],
        "id": 2346752,
        "name:xx": "Gee Brook"
      }
    },
    {
      "geometry": {
        "type": "Point",
        "coordinates": [
          -74.7667,
          41.9833
        ]
      },
      "type": "Feature",
      "properties": {
        "hierarchy": [
          "tgn:2346753",
          "tgn:1000001",
          "tgn:7012149",
          "tgn:1002926",
          "tgn:7007568",
          "tgn:7029392"
        ],
        "placetype": [
          "aat:300008699"
        ],
        "id": 2346753,
        "name:xx": "Gee Brook"
      }
    },
    {
      "geometry": {
        "type": "Point",
        "coordinates": [
          -76,
          42.5667
        ]
      },
      "type": "Feature",
      "properties": {
        "hierarchy": [
          "tgn:2346754",
          "tgn:1000001",
          "tgn:1002302",
          "tgn:7012149",
          "tgn:7007568",
          "tgn:7029392"
        ],
        "placetype": [
          "aat:300008699"
        ],
        "id": 2346754,
        "name:xx": "Gee Brook"
      }
    },
    {
      "geometry": {
        "type": "Point",
        "coordinates": [
          -84.5333,
          35.2333
        ]
      },
      "type": "Feature",
      "properties": {
        "hierarchy": [
          "tgn:2346755",
          "tgn:1000001",
          "tgn:7012149",
          "tgn:2001906",
          "tgn:7007825",
          "tgn:7029392"
        ],
        "placetype": [
          "aat:300008746"
        ],
        "id": 2346755,
        "name:xx": "Gee Cave"
      }
    },
    {
      "geometry": {
        "type": "Point",
        "coordinates": [
          -93.3,
          35.7
        ]
      },
      "type": "Feature",
      "properties": {
        "hierarchy": [
          "tgn:2346756",
          "tgn:1000001",
          "tgn:7016172",
          "tgn:7012149",
          "tgn:2000140",
          "tgn:7029392"
        ],
        "placetype": [
          "aat:300008706"
        ],
        "id": 2346756,
        "name:xx": "Gee Creek"
      }
    },
    {
      "geometry": {
        "type": "Point",
        "coordinates": [
          -81.3167,
          28.6833
        ]
      },
      "type": "Feature",
      "properties": {
        "hierarchy": [
          "tgn:2346757",
          "tgn:1000001",
          "tgn:7012149",
          "tgn:1002881",
          "tgn:7007240",
          "tgn:7029392"
        ],
        "placetype": [
          "aat:300008706"
        ],
        "id": 2346757,
        "name:xx": "Gee Creek"
      }
    },
    {
      "geometry": {
        "type": "Point",
        "coordinates": [
          -92.9,
          32.6667
        ]
      },
      "type": "Feature",
      "properties": {
        "hierarchy": [
          "tgn:2346758",
          "tgn:1000001",
          "tgn:7012149",
          "tgn:7007256",
          "tgn:7029392"
        ],
        "placetype": [
          "aat:300008706"
        ],
        "id": 2346758,
        "name:xx": "Gee Creek"
      }
    },
    {
      "geometry": {
        "type": "Point",
        "coordinates": [
          -92.9,
          32.8
        ]
      },
      "type": "Feature",
      "properties": {
        "hierarchy": [
          "tgn:2346759",
          "tgn:1000001",
          "tgn:2000867",
          "tgn:7012149",
          "tgn:7007256",
          "tgn:7029392"
        ],
        "placetype": [
          "aat:300008706"
        ],
        "id": 2346759,
        "name:xx": "Gee Creek"
      }
    }
  ]
}
