{
  "geometry": {
    "type": "Point",
    "coordinates": [
      77.881788,
      30.31246
    ]
  },
  "type": "Feature",
  "properties": {
    "hierarchy": [
      "tgn:7592108",
      "tgn:1000004",
      "tgn:7000198",
      "tgn:7031786",
      "tgn:7029392"
    ],
    "placetype": [
      "aat:300008699"
    ],
    "name:en": "Ogipāni Rao",
    "id": 7592108
  }
}
