{
  "type": "FeatureCollection",
  "features": [
    {
      "geometry": {
        "type": "Point",
        "coordinates": [
          -84.0333,
          35.4167
        ]
      },
      "type": "Feature",
      "properties": {
        "hierarchy": [
          "tgn:2626290",
          "tgn:1000001",
          "tgn:7012149",
          "tgn:2001898",
          "tgn:7007825",
          "tgn:7029392"
        ],
        "placetype": [
          "aat:300008699"
        ],
        "id": 2626290,
        "name:xx": "Rocky Flats Branch"
      }
    },
    {
      "geometry": {
        "type": "Point",
        "coordinates": [
          -87.8333,
          32.7
        ]
      },
      "type": "Feature",
      "properties": {
        "hierarchy": [
          "tgn:2626291",
          "tgn:7002659",
          "tgn:1000001",
          "tgn:7012149",
          "tgn:2000031",
          "tgn:7029392"
        ],
        "placetype": [
          "aat:300008347"
        ],
        "id": 2626291,
        "name:xx": "Rocky Ford"
      }
    },
    {
      "geometry": {
        "type": "Point",
        "coordinates": [
          -88.1667,
          39.3
        ]
      },
      "type": "Feature",
      "properties": {
        "hierarchy": [
          "tgn:2626292",
          "tgn:1000001",
          "tgn:2000502",
          "tgn:7012149",
          "tgn:7007251",
          "tgn:7029392"
        ],
        "placetype": [
          "aat:300008347"
        ],
        "id": 2626292,
        "name:xx": "Rocky Ford"
      }
    },
    {
      "geometry": {
        "type": "Point",
        "coordinates": [
          -87.3167,
          40.3833
        ]
      },
      "type": "Feature",
      "properties": {
        "hierarchy": [
          "tgn:2626293",
          "tgn:1000001",
          "tgn:7012149",
          "tgn:1002983",
          "tgn:7007252",
          "tgn:7029392"
        ],
        "placetype": [
          "aat:300008347"
        ],
        "id": 2626293,
        "name:xx": "Rocky Ford"
      }
    },
    {
      "geometry": {
        "type": "Point",
        "coordinates": [
          -96.05,
          37.8167
        ]
      },
      "type": "Feature",
      "properties": {
        "hierarchy": [
          "tgn:2626294",
          "tgn:1000001",
          "tgn:2000696",
          "tgn:7012149",
          "tgn:7007254",
          "tgn:7029392"
        ],
        "placetype": [
          "aat:300008347"
        ],
        "id": 2626294,
        "name:xx": "Rocky Ford"
      }
    },
    {
      "geometry": {
        "type": "Point",
        "coordinates": [
          -89.1,
          34.3667
        ]
      },
      "type": "Feature",
      "properties": {
        "hierarchy": [
          "tgn:2626295",
          "tgn:1000001",
          "tgn:7012149",
          "tgn:2001143",
          "tgn:7007522",
          "tgn:7029392"
        ],
        "placetype": [
          "aat:300008347"
        ],
        "id": 2626295,
        "name:xx": "Rocky Ford"
      }
    },
    {
      "geometry": {
        "type": "Point",
        "coordinates": [
          -94.1833,
          38.0333
        ]
      },
      "type": "Feature",
      "properties": {
        "hierarchy": [
          "tgn:2626296",
          "tgn:1000001",
          "tgn:7012149",
          "tgn:2001253",
          "tgn:7007523",
          "tgn:7029392"
        ],
        "placetype": [
          "aat:300008347"
        ],
        "id": 2626296,
        "name:xx": "Rocky Ford"
      }
    },
    {
      "geometry": {
        "type": "Point",
        "coordinates": [
          -83.55,
          41.0833
        ]
      },
      "type": "Feature",
      "properties": {
        "hierarchy": [
          "tgn:2626297",
          "tgn:1000001",
          "tgn:7012149",
          "tgn:7007706",
          "tgn:7029392"
        ],
        "placetype": [
          "aat:300008699"
        ],
        "id": 2626297,
        "name:xx": "Rocky Ford"
      }
    },
    {
      "geometry": {
        "type": "Point",
        "coordinates": [
          -98.0667,
          34.8333
        ]
      },
      "type": "Feature",
      "properties": {
        "hierarchy": [
          "tgn:2626299",
          "tgn:1000001",
          "tgn:2001638",
          "tgn:7012149",
          "tgn:7007707",
          "tgn:7029392"
        ],
        "placetype": [
          "aat:300008347"
        ],
        "id": 2626299,
        "name:xx": "Rocky Ford"
      }
    }
  ]
}
