{
  "geometry": {
    "type": "Point",
    "coordinates": [
      -91.55,
      34.7167
    ]
  },
  "type": "Feature",
  "properties": {
    "hierarchy": [
      "tgn:2662347",
      "tgn:1000001",
      "tgn:7016172",
      "tgn:7012149",
      "tgn:2000163",
      "tgn:7029392"
    ],
    "placetype": [
      "aat:300008347"
    ],
    "id": 2662347,
    "name:xx": "Siedenstricker"
  }
}
