{
  "geometry": {
    "type": "Point",
    "coordinates": [
      -80.8167,
      26.1833
    ]
  },
  "type": "Feature",
  "properties": {
    "hierarchy": [
      "tgn:2465586",
      "tgn:1000001",
      "tgn:1002207",
      "tgn:7012149",
      "tgn:7007240",
      "tgn:7029392"
    ],
    "placetype": [
      "aat:300008791"
    ],
    "id": 2465586,
    "name:xx": "Lone Palm Head"
  }
}
