{
  "geometry": {
    "type": "Point",
    "coordinates": [
      -81.7333,
      38.1667
    ]
  },
  "type": "Feature",
  "properties": {
    "hierarchy": [
      "tgn:7021049",
      "tgn:1000001",
      "tgn:2002255",
      "tgn:7012149",
      "tgn:7013961",
      "tgn:7029392"
    ],
    "placetype": [
      "aat:300008699"
    ],
    "id": 7021049,
    "name:xx": "White Oak Branch"
  }
}
