{
  "geometry": {
    "type": "Point",
    "coordinates": [
      -96.3167,
      33.2667
    ]
  },
  "type": "Feature",
  "properties": {
    "hierarchy": [
      "tgn:2137532",
      "tgn:1000001",
      "tgn:7012149",
      "tgn:1002290",
      "tgn:7007826",
      "tgn:7029392"
    ],
    "placetype": [
      "aat:300008347"
    ],
    "id": 2137532,
    "name:xx": "Arnold"
  }
}
