{
  "geometry": {
    "type": "Point",
    "coordinates": [
      -109.0833,
      33.3167
    ]
  },
  "type": "Feature",
  "properties": {
    "hierarchy": [
      "tgn:2206221",
      "tgn:1000001",
      "tgn:7012149",
      "tgn:7029392"
    ],
    "placetype": [
      "aat:300008761"
    ],
    "id": 2206221,
    "name:xx": "Bullard Canyon"
  }
}
