{
  "geometry": {
    "type": "Point",
    "coordinates": [
      78.6261,
      29.713044
    ]
  },
  "type": "Feature",
  "properties": {
    "hierarchy": [
      "tgn:7568116",
      "tgn:1000004",
      "tgn:7000198",
      "tgn:7031786",
      "tgn:7029392"
    ],
    "placetype": [
      "aat:300008699"
    ],
    "name:en": "Bīr Gād",
    "id": 7568116
  }
}
