{
  "geometry": {
    "type": "Point",
    "coordinates": [
      -73.0333,
      42.8167
    ]
  },
  "type": "Feature",
  "properties": {
    "hierarchy": [
      "tgn:2529809",
      "tgn:1002176",
      "tgn:1000001",
      "tgn:7012149",
      "tgn:7007828",
      "tgn:7029392"
    ],
    "placetype": [
      "aat:300008680"
    ],
    "id": 2529809,
    "name:xx": "Mud Pond"
  }
}
