{
  "type": "FeatureCollection",
  "features": [
    {
      "geometry": {
        "type": "Point",
        "coordinates": [
          13.316667,
          48.45
        ]
      },
      "type": "Feature",
      "properties": {
        "hierarchy": [
          "tgn:7156560",
          "tgn:7003669",
          "tgn:1000003",
          "tgn:7000084",
          "tgn:7029392"
        ],
        "placetype": [
          "aat:300008347"
        ],
        "id": 7156560,
        "name:xx": "Kleeberg"
      }
    },
    {
      "geometry": {
        "type": "Point",
        "coordinates": [
          12.644444,
          49.44
        ]
      },
      "type": "Feature",
      "properties": {
        "hierarchy": [
          "tgn:7156561",
          "tgn:7003669",
          "tgn:1000003",
          "tgn:7000084",
          "tgn:7029392"
        ],
        "placetype": [
          "aat:300008795"
        ],
        "id": 7156561,
        "name:xx": "Kleeberg"
      }
    },
    {
      "geometry": {
        "type": "Point",
        "coordinates": [
          12.816667,
          53.383333
        ]
      },
      "type": "Feature",
      "properties": {
        "hierarchy": [
          "tgn:7156562",
          "tgn:1000003",
          "tgn:7000094",
          "tgn:7000084",
          "tgn:7029392"
        ],
        "placetype": [
          "aat:300008777"
        ],
        "id": 7156562,
        "name:xx": "Klee Berg"
      }
    },
    {
      "geometry": {
        "type": "Point",
        "coordinates": [
          8.1,
          52.316667
        ]
      },
      "type": "Feature",
      "properties": {
        "hierarchy": [
          "tgn:7156563",
          "tgn:1000003",
          "tgn:7003676",
          "tgn:7000084",
          "tgn:7029392"
        ],
        "placetype": [
          "aat:300008777"
        ],
        "id": 7156563,
        "name:xx": "Klee-Berg"
      }
    },
    {
      "geometry": {
        "type": "Point",
        "coordinates": [
          7.85,
          52.2
        ]
      },
      "type": "Feature",
      "properties": {
        "hierarchy": [
          "tgn:7156564",
          "tgn:1000003",
          "tgn:7003677",
          "tgn:7000084",
          "tgn:7029392"
        ],
        "placetype": [
          "aat:300008777"
        ],
        "id": 7156564,
        "name:xx": "Klee-Berg"
      }
    },
    {
      "geometry": {
        "type": "Point",
        "coordinates": [
          8.983333,
          52.066667
        ]
      },
      "type": "Feature",
      "properties": {
        "hierarchy": [
          "tgn:7156565",
          "tgn:1000003",
          "tgn:7003677",
          "tgn:7000084",
          "tgn:7029392"
        ],
        "placetype": [
          "aat:300008777"
        ],
        "id": 7156565,
        "name:xx": "Klee-Berg"
      }
    },
    {
      "geometry": {
        "type": "Point",
        "coordinates": [
          9.516667,
          51.433333
        ]
      },
      "type": "Feature",
      "properties": {
        "hierarchy": [
          "tgn:7156566",
          "tgn:1000003",
          "tgn:7003678",
          "tgn:7000084",
          "tgn:7029392"
        ],
        "placetype": [
          "aat:300008777"
        ],
        "id": 7156566,
        "name:xx": "Klee-Berg"
      }
    },
    {
      "geometry": {
        "type": "Point",
        "coordinates": [
          8.833333,
          50.983333
        ]
      },
      "type": "Feature",
      "properties": {
        "hierarchy": [
          "tgn:7156567",
          "tgn:1000003",
          "tgn:7003678",
          "tgn:7000084",
          "tgn:7029392"
        ],
        "placetype": [
          "aat:300008777"
        ],
        "id": 7156567,
        "name:xx": "Klee-Berg"
      }
    },
    {
      "geometry": {
        "type": "Point",
        "coordinates": [
          8.5,
          50.916667
        ]
      },
      "type": "Feature",
      "properties": {
        "hierarchy": [
          "tgn:7156568",
          "tgn:1000003",
          "tgn:7003678",
          "tgn:7000084",
          "tgn:7029392"
        ],
        "placetype": [
          "aat:300008777"
        ],
        "id": 7156568,
        "name:xx": "Klee-Berg"
      }
    },
    {
      "geometry": {
        "type": "Point",
        "coordinates": [
          10.616667,
          50.4
        ]
      },
      "type": "Feature",
      "properties": {
        "hierarchy": [
          "tgn:7156569",
          "tgn:1000003",
          "tgn:7003689",
          "tgn:7000084",
          "tgn:7029392"
        ],
        "placetype": [
          "aat:300008777"
        ],
        "id": 7156569,
        "name:xx": "Klee-Berg"
      }
    }
  ]
}
