{
  "geometry": {
    "type": "Point",
    "coordinates": [
      -118.15,
      45.1667
    ]
  },
  "type": "Feature",
  "properties": {
    "hierarchy": [
      "tgn:2459978",
      "tgn:1000001",
      "tgn:7012149",
      "tgn:2001721",
      "tgn:7007708",
      "tgn:7029392"
    ],
    "placetype": [
      "aat:300008706"
    ],
    "id": 2459978,
    "name:xx": "Little Rock Creek"
  }
}
