{
  "geometry": {
    "type": "Point",
    "coordinates": [
      -99.1167,
      45.1667
    ]
  },
  "type": "Feature",
  "properties": {
    "hierarchy": [
      "tgn:2097639",
      "tgn:1000001",
      "tgn:2001794",
      "tgn:7012149",
      "tgn:7007713",
      "tgn:7029392"
    ],
    "placetype": [
      "aat:300008347"
    ],
    "id": 2097639,
    "name:xx": "Wecota"
  }
}
