{
  "type": "FeatureCollection",
  "features": [
    {
      "geometry": {
        "type": "Point",
        "coordinates": [
          11.4667,
          9.8333
        ]
      },
      "type": "Feature",
      "properties": {
        "hierarchy": [
          "tgn:1092280",
          "tgn:7001242",
          "tgn:1001838",
          "tgn:1000182",
          "tgn:7029392"
        ],
        "placetype": [
          "aat:300008347"
        ],
        "id": 1092280,
        "name:xx": "Tula"
      }
    },
    {
      "geometry": {
        "type": "Point",
        "coordinates": [
          9.3167,
          8
        ]
      },
      "type": "Feature",
      "properties": {
        "hierarchy": [
          "tgn:1092281",
          "tgn:7001242",
          "tgn:1001841",
          "tgn:1000182",
          "tgn:7029392"
        ],
        "placetype": [
          "aat:300008347"
        ],
        "id": 1092281,
        "name:xx": "Tunga"
      }
    },
    {
      "geometry": {
        "type": "Point",
        "coordinates": [
          6.3833,
          6.65
        ]
      },
      "type": "Feature",
      "properties": {
        "hierarchy": [
          "tgn:1092282",
          "tgn:7001242",
          "tgn:7015576",
          "tgn:1000182",
          "tgn:7029392"
        ],
        "placetype": [
          "aat:300008347"
        ],
        "id": 1092282,
        "name:xx": "Ubiaja"
      }
    },
    {
      "geometry": {
        "type": "Point",
        "coordinates": [
          7.4,
          6.25
        ]
      },
      "type": "Feature",
      "properties": {
        "hierarchy": [
          "tgn:1092283",
          "tgn:7001242",
          "tgn:7015579",
          "tgn:1000182",
          "tgn:7029392"
        ],
        "placetype": [
          "aat:300008347"
        ],
        "id": 1092283,
        "name:xx": "Udi"
      }
    },
    {
      "geometry": {
        "type": "Point",
        "coordinates": [
          10.5833,
          11.8667
        ]
      },
      "type": "Feature",
      "properties": {
        "hierarchy": [
          "tgn:1092284",
          "tgn:7001242",
          "tgn:1001838",
          "tgn:1000182",
          "tgn:7029392"
        ],
        "placetype": [
          "aat:300008347"
        ],
        "id": 1092284,
        "name:xx": "Ubudo"
      }
    },
    {
      "geometry": {
        "type": "Point",
        "coordinates": [
          8.0833,
          5.8
        ]
      },
      "type": "Feature",
      "properties": {
        "hierarchy": [
          "tgn:1092285",
          "tgn:7001242",
          "tgn:1001856",
          "tgn:1000182",
          "tgn:7029392"
        ],
        "placetype": [
          "aat:300008347"
        ],
        "id": 1092285,
        "name:xx": "Ugep"
      }
    },
    {
      "geometry": {
        "type": "Point",
        "coordinates": [
          6,
          5.55
        ]
      },
      "type": "Feature",
      "properties": {
        "hierarchy": [
          "tgn:1092286",
          "tgn:7001242",
          "tgn:7015044",
          "tgn:1000182",
          "tgn:7029392"
        ],
        "placetype": [
          "aat:300008347"
        ],
        "id": 1092286,
        "name:xx": "Ughelli"
      }
    },
    {
      "geometry": {
        "type": "Point",
        "coordinates": [
          7.6,
          5.5167
        ]
      },
      "type": "Feature",
      "properties": {
        "hierarchy": [
          "tgn:1092287",
          "tgn:7015042",
          "tgn:7001242",
          "tgn:1000182",
          "tgn:7029392"
        ],
        "placetype": [
          "aat:300387277",
          "aat:300008347",
          "aat:300387221",
          "aat:300008375",
          "aat:300387285"
        ],
        "id": 1092287,
        "name:xx": "Umuahia"
      }
    },
    {
      "geometry": {
        "type": "Point",
        "coordinates": [
          6.3333,
          6.7
        ]
      },
      "type": "Feature",
      "properties": {
        "hierarchy": [
          "tgn:1092288",
          "tgn:7001242",
          "tgn:7015576",
          "tgn:1000182",
          "tgn:7029392"
        ],
        "placetype": [
          "aat:300008347"
        ],
        "id": 1092288,
        "name:xx": "Uromi"
      }
    },
    {
      "geometry": {
        "type": "Point",
        "coordinates": [
          6.2167,
          5.5333
        ]
      },
      "type": "Feature",
      "properties": {
        "hierarchy": [
          "tgn:1092289",
          "tgn:7001242",
          "tgn:7015044",
          "tgn:1000182",
          "tgn:7029392"
        ],
        "placetype": [
          "aat:300008347"
        ],
        "id": 1092289,
        "name:xx": "Usoro"
      }
    }
  ]
}
