{
  "geometry": {
    "type": "Point",
    "coordinates": [
      -41.5167,
      -17.8667
    ]
  },
  "type": "Feature",
  "properties": {
    "hierarchy": [
      "tgn:1023165",
      "tgn:7006237",
      "tgn:1000047",
      "tgn:7002457",
      "tgn:1000002",
      "tgn:7029392"
    ],
    "placetype": [
      "aat:300387277",
      "aat:300008347",
      "aat:300008389",
      "aat:300387305"
    ],
    "id": 1023165,
    "name:xx": "Teófilo Otôni"
  }
}
