{
  "geometry": {
    "type": "Point",
    "coordinates": [
      6.2833,
      49.8333
    ]
  },
  "type": "Feature",
  "properties": {
    "hierarchy": [
      "tgn:1047540",
      "tgn:7003533",
      "tgn:1000003",
      "tgn:7003514",
      "tgn:7029392"
    ],
    "placetype": [
      "aat:300008347"
    ],
    "id": 1047540,
    "name:xx": "Beaufort"
  }
}
