{
  "geometry": {
    "type": "Point",
    "coordinates": [
      -77.1833,
      -12.1167
    ]
  },
  "type": "Feature",
  "properties": {
    "hierarchy": [
      "tgn:1007136",
      "tgn:1001172",
      "tgn:1000002",
      "tgn:1000056",
      "tgn:7029392"
    ],
    "placetype": [
      "aat:300008791"
    ],
    "id": 1007136,
    "name:xx": "Frontón, Isla"
  }
}
