{
  "geometry": {
    "type": "Point",
    "coordinates": [
      -121.9167,
      40.5833
    ]
  },
  "type": "Feature",
  "properties": {
    "hierarchy": [
      "tgn:2332906",
      "tgn:1000001",
      "tgn:7012149",
      "tgn:7007157",
      "tgn:2000188",
      "tgn:7029392"
    ],
    "placetype": [
      "aat:300386845"
    ],
    "id": 2332906,
    "name:xx": "Fluhart Basin"
  }
}
