{
  "type": "FeatureCollection",
  "features": [
    {
      "geometry": {
        "type": "Point",
        "coordinates": [
          141.95,
          39.4167
        ]
      },
      "type": "Feature",
      "properties": {
        "hierarchy": [
          "tgn:1101820",
          "tgn:7016687",
          "tgn:1000004",
          "tgn:7000893",
          "tgn:1000120",
          "tgn:7029392"
        ],
        "placetype": [
          "aat:300008189"
        ],
        "id": 1101820,
        "name:xx": "Rikuchū-kaigan-kokuritsu-kōen"
      }
    },
    {
      "geometry": {
        "type": "Point",
        "coordinates": [
          141.5833,
          45.1667
        ]
      },
      "type": "Feature",
      "properties": {
        "hierarchy": [
          "tgn:1101821",
          "tgn:1000985",
          "tgn:7016529",
          "tgn:7016531",
          "tgn:1000004",
          "tgn:1000120",
          "tgn:7029392"
        ],
        "placetype": [
          "aat:300008189"
        ],
        "id": 1101821,
        "name:xx": "Rishiri-Rebun-Sarobetsu-kokuritsu-kōen"
      }
    },
    {
      "geometry": {
        "type": "Point",
        "coordinates": [
          149.1667,
          -25.25
        ]
      },
      "type": "Feature",
      "properties": {
        "hierarchy": [
          "tgn:1101822",
          "tgn:7000490",
          "tgn:1000006",
          "tgn:7001830",
          "tgn:7029392"
        ],
        "placetype": [
          "aat:300008189"
        ],
        "id": 1101822,
        "name:xx": "Robinson Gorge National Park"
      }
    },
    {
      "geometry": {
        "type": "Point",
        "coordinates": [
          -105.7,
          40.3333
        ]
      },
      "type": "Feature",
      "properties": {
        "hierarchy": [
          "tgn:1101823",
          "tgn:1000001",
          "tgn:7012149",
          "tgn:7007158",
          "tgn:7029392"
        ],
        "placetype": [
          "aat:300008189"
        ],
        "id": 1101823,
        "name:xx": "Rocky Mountain National Park"
      }
    },
    {
      "geometry": {
        "type": "Point",
        "coordinates": [
          142.9167,
          -13.6667
        ]
      },
      "type": "Feature",
      "properties": {
        "hierarchy": [
          "tgn:1101824",
          "tgn:7000490",
          "tgn:1000006",
          "tgn:7001830",
          "tgn:7029392"
        ],
        "placetype": [
          "aat:300008189"
        ],
        "id": 1101824,
        "name:xx": "Rokeby National Park"
      }
    },
    {
      "geometry": {
        "type": "Point",
        "coordinates": [
          69.3333,
          38.8
        ]
      },
      "type": "Feature",
      "properties": {
        "hierarchy": [
          "tgn:1101827",
          "tgn:7011627",
          "tgn:1000004",
          "tgn:7014835",
          "tgn:7029392"
        ],
        "placetype": [
          "aat:300008189"
        ],
        "id": 1101827,
        "name:xx": "Ramit, Zapovednik"
      }
    }
  ]
}
