{
  "geometry": {
    "type": "Point",
    "coordinates": [
      24.4833,
      54.85
    ]
  },
  "type": "Feature",
  "properties": {
    "hierarchy": [
      "tgn:1054867",
      "tgn:7006561",
      "tgn:1000003",
      "tgn:7006542",
      "tgn:7029392"
    ],
    "placetype": [
      "aat:300008347",
      "aat:300387222"
    ],
    "id": 1054867,
    "name:xx": "Kaisiadorys"
  }
}
