{
  "geometry": {
    "type": "Point",
    "coordinates": [
      -83.1333,
      39.2667
    ]
  },
  "type": "Feature",
  "properties": {
    "hierarchy": [
      "tgn:2688414",
      "tgn:1000001",
      "tgn:7012149",
      "tgn:1002835",
      "tgn:7007706",
      "tgn:7029392"
    ],
    "placetype": [
      "aat:300266640"
    ],
    "id": 2688414,
    "name:xx": "Spruce Hill"
  }
}
