{
  "geometry": {
    "type": "Point",
    "coordinates": [
      -108.4333,
      42.6833
    ]
  },
  "type": "Feature",
  "properties": {
    "hierarchy": [
      "tgn:2289822",
      "tgn:1000001",
      "tgn:7012149",
      "tgn:2002371",
      "tgn:7007923",
      "tgn:7029392"
    ],
    "placetype": [
      "aat:300006191"
    ],
    "id": 2289822,
    "name:xx": "Dobe Reservoir"
  }
}
