{
  "geometry": {
    "type": "Point",
    "coordinates": [
      -10.5333,
      7.05
    ]
  },
  "type": "Feature",
  "properties": {
    "hierarchy": [
      "tgn:1090584",
      "tgn:7001242",
      "tgn:1000409",
      "tgn:1000171",
      "tgn:7029392"
    ],
    "placetype": [
      "aat:300008347"
    ],
    "id": 1090584,
    "name:xx": "Bopolu"
  }
}
