{
  "type": "FeatureCollection",
  "features": [
    {
      "geometry": {
        "type": "Point",
        "coordinates": [
          1.216667,
          53.366667
        ]
      },
      "type": "Feature",
      "properties": {
        "hierarchy": [
          "tgn:7449100",
          "tgn:7002445",
          "tgn:1000003",
          "tgn:7008160",
          "tgn:7008591",
          "tgn:7029392"
        ],
        "placetype": [
          "aat:300387036"
        ],
        "name:en": "South Outer Dowsing",
        "id": 7449100
      }
    },
    {
      "geometry": {
        "type": "Point",
        "coordinates": [
          -1.416667,
          54.283333
        ]
      },
      "type": "Feature",
      "properties": {
        "hierarchy": [
          "tgn:7449101",
          "tgn:7002445",
          "tgn:1000003",
          "tgn:7008166",
          "tgn:7008591",
          "tgn:7029392"
        ],
        "placetype": [
          "aat:300008347"
        ],
        "name:en": "South Otterington",
        "id": 7449101
      }
    },
    {
      "geometry": {
        "type": "Point",
        "coordinates": [
          -0.4,
          52.6
        ]
      },
      "type": "Feature",
      "properties": {
        "hierarchy": [
          "tgn:7449102",
          "tgn:7002445",
          "tgn:1000003",
          "tgn:7026520",
          "tgn:7008591",
          "tgn:7029392"
        ],
        "placetype": [
          "aat:300008347"
        ],
        "name:en": "Southorpe",
        "id": 7449102
      }
    },
    {
      "geometry": {
        "type": "Point",
        "coordinates": [
          -0.133333,
          51.016667
        ]
      },
      "type": "Feature",
      "properties": {
        "hierarchy": [
          "tgn:7449105",
          "tgn:7002445",
          "tgn:1000003",
          "tgn:7008134",
          "tgn:7008591",
          "tgn:7029392"
        ],
        "placetype": [
          "aat:300008347"
        ],
        "name:en": "South Nutfield",
        "id": 7449105
      }
    },
    {
      "geometry": {
        "type": "Point",
        "coordinates": [
          -1.866667,
          51.1
        ]
      },
      "type": "Feature",
      "properties": {
        "hierarchy": [
          "tgn:7449108",
          "tgn:7002445",
          "tgn:1000003",
          "tgn:7008180",
          "tgn:7008591",
          "tgn:7029392"
        ],
        "placetype": [
          "aat:300008347"
        ],
        "name:en": "South Newton",
        "id": 7449108
      }
    }
  ]
}
