{
  "geometry": {
    "type": "Point",
    "coordinates": [
      -114.8333,
      48.5833
    ]
  },
  "type": "Feature",
  "properties": {
    "hierarchy": [
      "tgn:2694502",
      "tgn:1000001",
      "tgn:7012149",
      "tgn:7007524",
      "tgn:7029392"
    ],
    "placetype": [
      "aat:300008706"
    ],
    "id": 2694502,
    "name:xx": "Stewart Creek"
  }
}
