{
  "geometry": {
    "type": "Point",
    "coordinates": [
      -153.3833,
      59.7833
    ]
  },
  "type": "Feature",
  "properties": {
    "hierarchy": [
      "tgn:2628847",
      "tgn:7006450",
      "tgn:1000001",
      "tgn:7019698",
      "tgn:7012149",
      "tgn:7029392"
    ],
    "placetype": [
      "aat:300008706"
    ],
    "id": 2628847,
    "name:xx": "Roscoe Creek"
  }
}
