{
  "geometry": {
    "type": "Point",
    "coordinates": [
      -89.3333,
      35.7167
    ]
  },
  "type": "Feature",
  "properties": {
    "hierarchy": [
      "tgn:2655850",
      "tgn:1000001",
      "tgn:7012149",
      "tgn:2001874",
      "tgn:7007825",
      "tgn:7029392"
    ],
    "placetype": [
      "aat:300008347"
    ],
    "id": 2655850,
    "name:xx": "Shaw"
  }
}
