{
  "geometry": {
    "type": "Point",
    "coordinates": [
      -123.9167,
      40.3167
    ]
  },
  "type": "Feature",
  "properties": {
    "hierarchy": [
      "tgn:2535983",
      "tgn:1000001",
      "tgn:7012149",
      "tgn:2000181",
      "tgn:7007157",
      "tgn:7029392"
    ],
    "placetype": [
      "aat:300055621"
    ],
    "id": 2535983,
    "name:xx": "Native Daughters Of The Golden West Grove"
  }
}
