{
  "geometry": {
    "type": "Point",
    "coordinates": [
      -73.6167,
      40.8167
    ]
  },
  "type": "Feature",
  "properties": {
    "hierarchy": [
      "tgn:2071425",
      "tgn:1000001",
      "tgn:7012149",
      "tgn:1002708",
      "tgn:7007568",
      "tgn:7029392"
    ],
    "placetype": [
      "aat:300008347"
    ],
    "id": 2071425,
    "name:xx": "Old Brookville"
  }
}
