{
  "geometry": {
    "type": "Point",
    "coordinates": [
      132.8667,
      35.4333
    ]
  },
  "type": "Feature",
  "properties": {
    "hierarchy": [
      "tgn:1124631",
      "tgn:7016808",
      "tgn:7000897",
      "tgn:1000004",
      "tgn:1000120",
      "tgn:7029392"
    ],
    "placetype": [
      "aat:300008707"
    ],
    "id": 1124631,
    "name:xx": "Hii-kawa"
  }
}
