{
  "type": "FeatureCollection",
  "features": [
    {
      "geometry": {
        "type": "Point",
        "coordinates": [
          -99.6,
          23.833333
        ]
      },
      "type": "Feature",
      "properties": {
        "hierarchy": [
          "tgn:7388041",
          "tgn:1000001",
          "tgn:7005589",
          "tgn:7005560",
          "tgn:7029392"
        ],
        "placetype": [
          "aat:300008347"
        ],
        "id": 7388041,
        "name:xx": "Puerto del Aire"
      }
    },
    {
      "geometry": {
        "type": "Point",
        "coordinates": [
          -100.45,
          23.366667
        ]
      },
      "type": "Feature",
      "properties": {
        "hierarchy": [
          "tgn:7388042",
          "tgn:1000001",
          "tgn:7005589",
          "tgn:7005560",
          "tgn:7029392"
        ],
        "placetype": [
          "aat:300008347"
        ],
        "id": 7388042,
        "name:xx": "Puerto del Aire"
      }
    },
    {
      "geometry": {
        "type": "Point",
        "coordinates": [
          -107.666667,
          26.85
        ]
      },
      "type": "Feature",
      "properties": {
        "hierarchy": [
          "tgn:7388043",
          "tgn:7005581",
          "tgn:1000001",
          "tgn:7005560",
          "tgn:7029392"
        ],
        "placetype": [
          "aat:300008795"
        ],
        "id": 7388043,
        "name:xx": "Puerto de la Higuera, Pico del"
      }
    },
    {
      "geometry": {
        "type": "Point",
        "coordinates": [
          -99.433333,
          25.7
        ]
      },
      "type": "Feature",
      "properties": {
        "hierarchy": [
          "tgn:7388044",
          "tgn:1000001",
          "tgn:7005589",
          "tgn:7005560",
          "tgn:7029392"
        ],
        "placetype": [
          "aat:300008347"
        ],
        "id": 7388044,
        "name:xx": "Puerto del Agua"
      }
    },
    {
      "geometry": {
        "type": "Point",
        "coordinates": [
          -102.133333,
          22.2
        ]
      },
      "type": "Feature",
      "properties": {
        "hierarchy": [
          "tgn:7388045",
          "tgn:7005579",
          "tgn:1000001",
          "tgn:7005560",
          "tgn:7029392"
        ],
        "placetype": [
          "aat:300008347"
        ],
        "id": 7388045,
        "name:xx": "Puerto de la Concepción"
      }
    },
    {
      "geometry": {
        "type": "Point",
        "coordinates": [
          -100.466667,
          23.566667
        ]
      },
      "type": "Feature",
      "properties": {
        "hierarchy": [
          "tgn:7388046",
          "tgn:1000001",
          "tgn:7005589",
          "tgn:7005560",
          "tgn:7029392"
        ],
        "placetype": [
          "aat:300008347"
        ],
        "id": 7388046,
        "name:xx": "Puerto de la Carne"
      }
    },
    {
      "geometry": {
        "type": "Point",
        "coordinates": [
          -102.566667,
          22.616667
        ]
      },
      "type": "Feature",
      "properties": {
        "hierarchy": [
          "tgn:7388047",
          "tgn:1000001",
          "tgn:7005601",
          "tgn:7005560",
          "tgn:7029392"
        ],
        "placetype": [
          "aat:300008347"
        ],
        "id": 7388047,
        "name:xx": "Puerto de la Cañada"
      }
    },
    {
      "geometry": {
        "type": "Point",
        "coordinates": [
          -98.75,
          22.8
        ]
      },
      "type": "Feature",
      "properties": {
        "hierarchy": [
          "tgn:7388048",
          "tgn:1000001",
          "tgn:7005597",
          "tgn:7005560",
          "tgn:7029392"
        ],
        "placetype": [
          "aat:300008347"
        ],
        "id": 7388048,
        "name:xx": "Potrero"
      }
    },
    {
      "geometry": {
        "type": "Point",
        "coordinates": [
          -102.833333,
          22.1
        ]
      },
      "type": "Feature",
      "properties": {
        "hierarchy": [
          "tgn:7388049",
          "tgn:1000001",
          "tgn:7005601",
          "tgn:7005560",
          "tgn:7029392"
        ],
        "placetype": [
          "aat:300008347"
        ],
        "id": 7388049,
        "name:xx": "Potrero"
      }
    }
  ]
}
