{
  "geometry": {
    "type": "Point",
    "coordinates": [
      -80.5667,
      39.0667
    ]
  },
  "type": "Feature",
  "properties": {
    "hierarchy": [
      "tgn:2297506",
      "tgn:1000001",
      "tgn:7012149",
      "tgn:2002271",
      "tgn:7013961",
      "tgn:7029392"
    ],
    "placetype": [
      "aat:300008699"
    ],
    "id": 2297506,
    "name:xx": "Dry Fork"
  }
}
