{
  "type": "FeatureCollection",
  "features": [
    {
      "geometry": {
        "type": "Point",
        "coordinates": [
          12.028889,
          44.796944
        ]
      },
      "type": "Feature",
      "properties": {
        "hierarchy": [
          "tgn:1045301",
          "tgn:7003128",
          "tgn:1000003",
          "tgn:7008516",
          "tgn:1000080",
          "tgn:7029392"
        ],
        "placetype": [
          "aat:300008347"
        ],
        "id": 1045301,
        "name:xx": "Massa Fiscaglia"
      }
    },
    {
      "geometry": {
        "type": "Point",
        "coordinates": [
          17.115278,
          40.591944
        ]
      },
      "type": "Feature",
      "properties": {
        "hierarchy": [
          "tgn:1045306",
          "tgn:1003500",
          "tgn:1000003",
          "tgn:7010380",
          "tgn:1000080",
          "tgn:7029392"
        ],
        "placetype": [
          "aat:300008347"
        ],
        "id": 1045306,
        "name:xx": "Massafra"
      }
    },
    {
      "geometry": {
        "type": "Point",
        "coordinates": [
          10.333333,
          43.866667
        ]
      },
      "type": "Feature",
      "properties": {
        "hierarchy": [
          "tgn:1045307",
          "tgn:7003165",
          "tgn:1000003",
          "tgn:7009760",
          "tgn:1000080",
          "tgn:7029392"
        ],
        "placetype": [
          "aat:300008347"
        ],
        "id": 1045307,
        "name:xx": "Massarosa"
      }
    },
    {
      "geometry": {
        "type": "Point",
        "coordinates": [
          7.066667,
          44.95
        ]
      },
      "type": "Feature",
      "properties": {
        "hierarchy": [
          "tgn:1045308",
          "tgn:7003154",
          "tgn:1000003",
          "tgn:7003120",
          "tgn:1000080",
          "tgn:7029392"
        ],
        "placetype": [
          "aat:300008347"
        ],
        "id": 1045308,
        "name:xx": "Massello"
      }
    }
  ]
}
