{
  "geometry": {
    "type": "Point",
    "coordinates": [
      -122.4167,
      48.8333
    ]
  },
  "type": "Feature",
  "properties": {
    "hierarchy": [
      "tgn:2383674",
      "tgn:1000001",
      "tgn:7012149",
      "tgn:1003020",
      "tgn:7007920",
      "tgn:7029392"
    ],
    "placetype": [
      "aat:300006191"
    ],
    "id": 2383674,
    "name:xx": "Heavens-Lass Lagoon"
  }
}
