{
  "geometry": {
    "type": "Point",
    "coordinates": [
      28.9833,
      41.1833
    ]
  },
  "type": "Feature",
  "properties": {
    "hierarchy": [
      "tgn:1086047",
      "tgn:1001052",
      "tgn:1000004",
      "tgn:7018450",
      "tgn:1000144",
      "tgn:7029392"
    ],
    "placetype": [
      "aat:300008347"
    ],
    "id": 1086047,
    "name:xx": "Bahçeköy"
  }
}
