{
  "type": "FeatureCollection",
  "features": [
    {
      "geometry": {
        "type": "Point",
        "coordinates": [
          -86.6,
          34.5
        ]
      },
      "type": "Feature",
      "properties": {
        "hierarchy": [
          "tgn:2172320",
          "tgn:7002659",
          "tgn:1000001",
          "tgn:7012149",
          "tgn:2000051",
          "tgn:7029392"
        ],
        "placetype": [
          "aat:300008746"
        ],
        "id": 2172320,
        "name:xx": "Bill Blacks Cave"
      }
    },
    {
      "geometry": {
        "type": "Point",
        "coordinates": [
          -91.9667,
          31.2333
        ]
      },
      "type": "Feature",
      "properties": {
        "hierarchy": [
          "tgn:2172321",
          "tgn:1000001",
          "tgn:2000866",
          "tgn:7012149",
          "tgn:7007256",
          "tgn:7029392"
        ],
        "placetype": [
          "aat:300008905"
        ],
        "id": 2172321,
        "name:xx": "Bill Book Lake"
      }
    },
    {
      "geometry": {
        "type": "Point",
        "coordinates": [
          -110.5833,
          46.25
        ]
      },
      "type": "Feature",
      "properties": {
        "hierarchy": [
          "tgn:2172322",
          "tgn:1000001",
          "tgn:7012149",
          "tgn:2001289",
          "tgn:7007524",
          "tgn:7029392"
        ],
        "placetype": [
          "aat:300008347"
        ],
        "id": 2172322,
        "name:xx": "Bill Bracket Place"
      }
    },
    {
      "geometry": {
        "type": "Point",
        "coordinates": [
          -82.2833,
          30.3667
        ]
      },
      "type": "Feature",
      "properties": {
        "hierarchy": [
          "tgn:2172323",
          "tgn:2000257",
          "tgn:1000001",
          "tgn:7012149",
          "tgn:7007240",
          "tgn:7029392"
        ],
        "placetype": [
          "aat:300008699"
        ],
        "id": 2172323,
        "name:xx": "Bill Branch"
      }
    },
    {
      "geometry": {
        "type": "Point",
        "coordinates": [
          -83,
          30.7667
        ]
      },
      "type": "Feature",
      "properties": {
        "hierarchy": [
          "tgn:2172324",
          "tgn:1000001",
          "tgn:7012149",
          "tgn:2000341",
          "tgn:7007248",
          "tgn:7029392"
        ],
        "placetype": [
          "aat:300008699"
        ],
        "id": 2172324,
        "name:xx": "Bill Branch"
      }
    },
    {
      "geometry": {
        "type": "Point",
        "coordinates": [
          -83.3,
          36.9167
        ]
      },
      "type": "Feature",
      "properties": {
        "hierarchy": [
          "tgn:2172325",
          "tgn:1000001",
          "tgn:7012149",
          "tgn:2000797",
          "tgn:7007255",
          "tgn:7029392"
        ],
        "placetype": [
          "aat:300008699"
        ],
        "id": 2172325,
        "name:xx": "Bill Branch"
      }
    },
    {
      "geometry": {
        "type": "Point",
        "coordinates": [
          -83.0167,
          38.05
        ]
      },
      "type": "Feature",
      "properties": {
        "hierarchy": [
          "tgn:2172326",
          "tgn:1000001",
          "tgn:7012149",
          "tgn:1002354",
          "tgn:7007255",
          "tgn:7029392"
        ],
        "placetype": [
          "aat:300008699"
        ],
        "id": 2172326,
        "name:xx": "Bill Branch"
      }
    },
    {
      "geometry": {
        "type": "Point",
        "coordinates": [
          -76.7167,
          39.2333
        ]
      },
      "type": "Feature",
      "properties": {
        "hierarchy": [
          "tgn:2172327",
          "tgn:7016099",
          "tgn:1000001",
          "tgn:7012149",
          "tgn:7007516",
          "tgn:7029392"
        ],
        "placetype": [
          "aat:300008699"
        ],
        "id": 2172327,
        "name:xx": "Bill Branch"
      }
    },
    {
      "geometry": {
        "type": "Point",
        "coordinates": [
          -80.4333,
          35.1833
        ]
      },
      "type": "Feature",
      "properties": {
        "hierarchy": [
          "tgn:2172328",
          "tgn:1000001",
          "tgn:7012149",
          "tgn:2001540",
          "tgn:7007709",
          "tgn:7029392"
        ],
        "placetype": [
          "aat:300008699"
        ],
        "id": 2172328,
        "name:xx": "Bill Branch"
      }
    },
    {
      "geometry": {
        "type": "Point",
        "coordinates": [
          -80.3667,
          36.1333
        ]
      },
      "type": "Feature",
      "properties": {
        "hierarchy": [
          "tgn:2172329",
          "tgn:1000001",
          "tgn:7012149",
          "tgn:2001494",
          "tgn:7007709",
          "tgn:7029392"
        ],
        "placetype": [
          "aat:300008699"
        ],
        "id": 2172329,
        "name:xx": "Bill Branch"
      }
    }
  ]
}
