{
  "geometry": {
    "type": "Point",
    "coordinates": [
      84.03076,
      21.415705
    ]
  },
  "type": "Feature",
  "properties": {
    "hierarchy": [
      "tgn:7555768",
      "tgn:1000004",
      "tgn:7000198",
      "tgn:7016694",
      "tgn:7029392"
    ],
    "placetype": [
      "aat:300008347"
    ],
    "name:en": "Mānesar",
    "id": 7555768
  }
}
