{
  "geometry": {
    "type": "Point",
    "coordinates": [
      16.25,
      60.1167
    ]
  },
  "type": "Feature",
  "properties": {
    "hierarchy": [
      "tgn:1063254",
      "tgn:1000403",
      "tgn:1000003",
      "tgn:1000097",
      "tgn:7029392"
    ],
    "placetype": [
      "aat:300008347"
    ],
    "id": 1063254,
    "name:xx": "Krylbo"
  }
}
