{
  "type": "FeatureCollection",
  "features": [
    {
      "geometry": {
        "type": "Point",
        "coordinates": [
          14.6,
          41.25
        ]
      },
      "type": "Feature",
      "properties": {
        "hierarchy": [
          "tgn:7004510",
          "tgn:7004595",
          "tgn:7003005",
          "tgn:1000003",
          "tgn:1000080",
          "tgn:7029392"
        ],
        "placetype": [
          "aat:300008347"
        ],
        "id": 7004510,
        "name:xx": "Guardia Sanframondi"
      }
    },
    {
      "geometry": {
        "type": "Point",
        "coordinates": [
          57.333,
          22.5
        ]
      },
      "type": "Feature",
      "properties": {
        "hierarchy": [
          "tgn:7004512",
          "tgn:1000004",
          "tgn:1000131",
          "tgn:7029392"
        ],
        "placetype": [
          "aat:300387064",
          "aat:300235093",
          "aat:300236112"
        ],
        "id": 7004512,
        "name:xx": "Ad D훮khil카yah"
      }
    },
    {
      "geometry": {
        "type": "Point",
        "coordinates": [
          54,
          17
        ]
      },
      "type": "Feature",
      "properties": {
        "hierarchy": [
          "tgn:7004513",
          "tgn:1000004",
          "tgn:1000131",
          "tgn:7029392"
        ],
        "placetype": [
          "aat:300387179",
          "aat:300387064",
          "aat:300236112"
        ],
        "id": 7004513,
        "name:xx": "al-Jan큰b카yah"
      }
    },
    {
      "geometry": {
        "type": "Point",
        "coordinates": [
          14.066667,
          40.816667
        ]
      },
      "type": "Feature",
      "properties": {
        "hierarchy": [
          "tgn:7004516",
          "tgn:7003013",
          "tgn:7003005",
          "tgn:1000003",
          "tgn:1000080",
          "tgn:7029392"
        ],
        "placetype": [
          "aat:300008347",
          "aat:300000810",
          "aat:300008375",
          "aat:300387292"
        ],
        "id": 7004516,
        "name:xx": "Baia"
      }
    },
    {
      "geometry": {
        "type": "Point",
        "coordinates": [
          14.5,
          41.016667
        ]
      },
      "type": "Feature",
      "properties": {
        "hierarchy": [
          "tgn:7004517",
          "tgn:7003011",
          "tgn:7003005",
          "tgn:1000003",
          "tgn:1000080",
          "tgn:7029392"
        ],
        "placetype": [
          "aat:300008347"
        ],
        "id": 7004517,
        "name:xx": "Arienzo"
      }
    },
    {
      "geometry": {
        "type": "Point",
        "coordinates": [
          14.2,
          40.966667
        ]
      },
      "type": "Feature",
      "properties": {
        "hierarchy": [
          "tgn:7004518",
          "tgn:7003011",
          "tgn:7003005",
          "tgn:1000003",
          "tgn:1000080",
          "tgn:7029392"
        ],
        "placetype": [
          "aat:300008347"
        ],
        "id": 7004518,
        "name:xx": "Aversa"
      }
    },
    {
      "geometry": {
        "type": "Point",
        "coordinates": [
          14.25,
          41.116667
        ]
      },
      "type": "Feature",
      "properties": {
        "hierarchy": [
          "tgn:7004519",
          "tgn:7003011",
          "tgn:7003005",
          "tgn:1000003",
          "tgn:1000080",
          "tgn:7029392"
        ],
        "placetype": [
          "aat:300008347"
        ],
        "id": 7004519,
        "name:xx": "Sant'Angelo in Formis"
      }
    }
  ]
}
