{
  "geometry": {
    "type": "Point",
    "coordinates": [
      -98.1167,
      47.4333
    ]
  },
  "type": "Feature",
  "properties": {
    "hierarchy": [
      "tgn:2077509",
      "tgn:1000001",
      "tgn:2001576",
      "tgn:7012149",
      "tgn:7007705",
      "tgn:7029392"
    ],
    "placetype": [
      "aat:300008347"
    ],
    "id": 2077509,
    "name:xx": "Cooperstown"
  }
}
