{
  "geometry": {
    "type": "Point",
    "coordinates": [
      -152.9333,
      61.8333
    ]
  },
  "type": "Feature",
  "properties": {
    "hierarchy": [
      "tgn:2721753",
      "tgn:7006450",
      "tgn:1000001",
      "tgn:7012149",
      "tgn:7029392"
    ],
    "placetype": [
      "aat:300008706"
    ],
    "id": 2721753,
    "name:xx": "Timber Creek"
  }
}
