{
  "geometry": {
    "type": "Point",
    "coordinates": [
      -112.3167,
      45.8167
    ]
  },
  "type": "Feature",
  "properties": {
    "hierarchy": [
      "tgn:7020489",
      "tgn:1000001",
      "tgn:7012149",
      "tgn:2001281",
      "tgn:7007524",
      "tgn:7029392"
    ],
    "placetype": [
      "aat:300008697"
    ],
    "id": 7020489,
    "name:xx": "Mud Springs"
  }
}
