{
  "geometry": {
    "type": "Point",
    "coordinates": [
      106.5333,
      23.9167
    ]
  },
  "type": "Feature",
  "properties": {
    "hierarchy": [
      "tgn:1066941",
      "tgn:1000004",
      "tgn:1001678",
      "tgn:1000111",
      "tgn:7029392"
    ],
    "placetype": [
      "aat:300008347"
    ],
    "id": 1066941,
    "name:xx": "Bose"
  }
}
