{
  "geometry": {
    "type": "Point",
    "coordinates": [
      -99.2333,
      39.8667
    ]
  },
  "type": "Feature",
  "properties": {
    "hierarchy": [
      "tgn:2200206",
      "tgn:1000001",
      "tgn:7012149",
      "tgn:2000733",
      "tgn:7007254",
      "tgn:7029392"
    ],
    "placetype": [
      "aat:300008761"
    ],
    "id": 2200206,
    "name:xx": "Brushy Draw"
  }
}
