{
  "geometry": {
    "type": "Point",
    "coordinates": [
      -84.0833,
      37.9167
    ]
  },
  "type": "Feature",
  "properties": {
    "hierarchy": [
      "tgn:2438345",
      "tgn:1000001",
      "tgn:2000781",
      "tgn:7012149",
      "tgn:7007255",
      "tgn:7029392"
    ],
    "placetype": [
      "aat:300008699"
    ],
    "id": 2438345,
    "name:xx": "Kings Fork"
  }
}
