{
  "geometry": {
    "type": "Point",
    "coordinates": [
      -85.4333,
      41.1667
    ]
  },
  "type": "Feature",
  "properties": {
    "hierarchy": [
      "tgn:2514452",
      "tgn:1000001",
      "tgn:7012149",
      "tgn:1003022",
      "tgn:7007252",
      "tgn:7029392"
    ],
    "placetype": [
      "aat:300006075"
    ],
    "id": 2514452,
    "name:xx": "Miller Ditch"
  }
}
