{
  "type": "FeatureCollection",
  "features": [
    {
      "geometry": {
        "type": "Point",
        "coordinates": [
          -79.85,
          40.5333
        ]
      },
      "type": "Feature",
      "properties": {
        "hierarchy": [
          "tgn:2350820",
          "tgn:7013272",
          "tgn:1000001",
          "tgn:7012149",
          "tgn:7007710",
          "tgn:7029392"
        ],
        "placetype": [
          "aat:300008699"
        ],
        "id": 2350820,
        "name:xx": "Glade Run"
      }
    },
    {
      "geometry": {
        "type": "Point",
        "coordinates": [
          -79.5667,
          40.9
        ]
      },
      "type": "Feature",
      "properties": {
        "hierarchy": [
          "tgn:2350821",
          "tgn:1002153",
          "tgn:1000001",
          "tgn:7012149",
          "tgn:7007710",
          "tgn:7029392"
        ],
        "placetype": [
          "aat:300008699"
        ],
        "id": 2350821,
        "name:xx": "Glade Run"
      }
    },
    {
      "geometry": {
        "type": "Point",
        "coordinates": [
          -79.3167,
          41.0833
        ]
      },
      "type": "Feature",
      "properties": {
        "hierarchy": [
          "tgn:2350822",
          "tgn:1000001",
          "tgn:1002272",
          "tgn:7012149",
          "tgn:7007710",
          "tgn:7029392"
        ],
        "placetype": [
          "aat:300008699"
        ],
        "id": 2350822,
        "name:xx": "Glade Run"
      }
    },
    {
      "geometry": {
        "type": "Point",
        "coordinates": [
          -80.35,
          38.2
        ]
      },
      "type": "Feature",
      "properties": {
        "hierarchy": [
          "tgn:2350823",
          "tgn:1000001",
          "tgn:7012149",
          "tgn:2002287",
          "tgn:7013961",
          "tgn:7029392"
        ],
        "placetype": [
          "aat:300008699"
        ],
        "id": 2350823,
        "name:xx": "Glade Run"
      }
    },
    {
      "geometry": {
        "type": "Point",
        "coordinates": [
          -80.5,
          38.3
        ]
      },
      "type": "Feature",
      "properties": {
        "hierarchy": [
          "tgn:2350824",
          "tgn:1000001",
          "tgn:7012149",
          "tgn:7013961",
          "tgn:7029392"
        ],
        "placetype": [
          "aat:300008699"
        ],
        "id": 2350824,
        "name:xx": "Glade Run"
      }
    },
    {
      "geometry": {
        "type": "Point",
        "coordinates": [
          -80.55,
          38.45
        ]
      },
      "type": "Feature",
      "properties": {
        "hierarchy": [
          "tgn:2350825",
          "tgn:1000001",
          "tgn:7012149",
          "tgn:2002300",
          "tgn:7013961",
          "tgn:7029392"
        ],
        "placetype": [
          "aat:300008699"
        ],
        "id": 2350825,
        "name:xx": "Glade Run"
      }
    },
    {
      "geometry": {
        "type": "Point",
        "coordinates": [
          -79.8333,
          38.6333
        ]
      },
      "type": "Feature",
      "properties": {
        "hierarchy": [
          "tgn:2350826",
          "tgn:1000001",
          "tgn:7012149",
          "tgn:2002291",
          "tgn:7013961",
          "tgn:7029392"
        ],
        "placetype": [
          "aat:300008699"
        ],
        "id": 2350826,
        "name:xx": "Glade Run"
      }
    },
    {
      "geometry": {
        "type": "Point",
        "coordinates": [
          -79.9333,
          39.15
        ]
      },
      "type": "Feature",
      "properties": {
        "hierarchy": [
          "tgn:2350827",
          "tgn:2002253",
          "tgn:1000001",
          "tgn:7012149",
          "tgn:7013961",
          "tgn:7029392"
        ],
        "placetype": [
          "aat:300008699"
        ],
        "id": 2350827,
        "name:xx": "Glade Run"
      }
    },
    {
      "geometry": {
        "type": "Point",
        "coordinates": [
          -80.1833,
          39.2167
        ]
      },
      "type": "Feature",
      "properties": {
        "hierarchy": [
          "tgn:2350828",
          "tgn:1000001",
          "tgn:7012149",
          "tgn:2002267",
          "tgn:7013961",
          "tgn:7029392"
        ],
        "placetype": [
          "aat:300008699"
        ],
        "id": 2350828,
        "name:xx": "Glade Run"
      }
    },
    {
      "geometry": {
        "type": "Point",
        "coordinates": [
          -79.9167,
          39.3167
        ]
      },
      "type": "Feature",
      "properties": {
        "hierarchy": [
          "tgn:2350829",
          "tgn:1000001",
          "tgn:7012149",
          "tgn:2002295",
          "tgn:7013961",
          "tgn:7029392"
        ],
        "placetype": [
          "aat:300008699"
        ],
        "id": 2350829,
        "name:xx": "Glade Run"
      }
    }
  ]
}
