{
  "geometry": {
    "type": "Point",
    "coordinates": [
      -86.3333,
      34.6167
    ]
  },
  "type": "Feature",
  "properties": {
    "hierarchy": [
      "tgn:2670383",
      "tgn:7002659",
      "tgn:1000001",
      "tgn:7012149",
      "tgn:2000035",
      "tgn:7029392"
    ],
    "placetype": [
      "aat:300008746"
    ],
    "id": 2670383,
    "name:xx": "Small Spring Cave"
  }
}
