{
  "type": "FeatureCollection",
  "features": [
    {
      "geometry": {
        "type": "Point",
        "coordinates": [
          -112.3167,
          36.45
        ]
      },
      "type": "Feature",
      "properties": {
        "hierarchy": [
          "tgn:2159610",
          "tgn:1000001",
          "tgn:7006451",
          "tgn:2000092",
          "tgn:7012149",
          "tgn:7029392"
        ],
        "placetype": [
          "aat:300008697"
        ],
        "id": 2159610,
        "name:xx": "Bee Spring"
      }
    },
    {
      "geometry": {
        "type": "Point",
        "coordinates": [
          -107.2,
          36.5333
        ]
      },
      "type": "Feature",
      "properties": {
        "hierarchy": [
          "tgn:2159611",
          "tgn:1000001",
          "tgn:7012149",
          "tgn:2001449",
          "tgn:7007566",
          "tgn:7029392"
        ],
        "placetype": [
          "aat:300008697"
        ],
        "id": 2159611,
        "name:xx": "Bee Spring"
      }
    },
    {
      "geometry": {
        "type": "Point",
        "coordinates": [
          -120.5833,
          42.1
        ]
      },
      "type": "Feature",
      "properties": {
        "hierarchy": [
          "tgn:2159612",
          "tgn:1000001",
          "tgn:7012149",
          "tgn:2001715",
          "tgn:7007708",
          "tgn:7029392"
        ],
        "placetype": [
          "aat:300008697"
        ],
        "id": 2159612,
        "name:xx": "Bee Spring"
      }
    },
    {
      "geometry": {
        "type": "Point",
        "coordinates": [
          -86.8333,
          35.1167
        ]
      },
      "type": "Feature",
      "properties": {
        "hierarchy": [
          "tgn:2159613",
          "tgn:1000001",
          "tgn:7012149",
          "tgn:2001864",
          "tgn:7007825",
          "tgn:7029392"
        ],
        "placetype": [
          "aat:300008697"
        ],
        "id": 2159613,
        "name:xx": "Bee Spring"
      }
    },
    {
      "geometry": {
        "type": "Point",
        "coordinates": [
          -87.4667,
          33.65
        ]
      },
      "type": "Feature",
      "properties": {
        "hierarchy": [
          "tgn:2159614",
          "tgn:7002659",
          "tgn:1000001",
          "tgn:7012149",
          "tgn:2000028",
          "tgn:7029392"
        ],
        "placetype": [
          "aat:300008699"
        ],
        "id": 2159614,
        "name:xx": "Bee Spring Branch"
      }
    },
    {
      "geometry": {
        "type": "Point",
        "coordinates": [
          -86.8333,
          35.1167
        ]
      },
      "type": "Feature",
      "properties": {
        "hierarchy": [
          "tgn:2159615",
          "tgn:1000001",
          "tgn:7012149",
          "tgn:2001864",
          "tgn:7007825",
          "tgn:7029392"
        ],
        "placetype": [
          "aat:300008699"
        ],
        "id": 2159615,
        "name:xx": "Bee Spring Branch"
      }
    },
    {
      "geometry": {
        "type": "Point",
        "coordinates": [
          -86.8333,
          35.1167
        ]
      },
      "type": "Feature",
      "properties": {
        "hierarchy": [
          "tgn:2159616",
          "tgn:1000001",
          "tgn:7012149",
          "tgn:2001864",
          "tgn:7007825",
          "tgn:7029392"
        ],
        "placetype": [
          "aat:300008798"
        ],
        "id": 2159616,
        "name:xx": "Bee Spring Hill"
      }
    },
    {
      "geometry": {
        "type": "Point",
        "coordinates": [
          -113.9,
          34.8833
        ]
      },
      "type": "Feature",
      "properties": {
        "hierarchy": [
          "tgn:2159617",
          "tgn:1000001",
          "tgn:7006451",
          "tgn:7012149",
          "tgn:2000098",
          "tgn:7029392"
        ],
        "placetype": [
          "aat:300008697"
        ],
        "id": 2159617,
        "name:xx": "Bee Springs"
      }
    },
    {
      "geometry": {
        "type": "Point",
        "coordinates": [
          -118.05,
          36.8
        ]
      },
      "type": "Feature",
      "properties": {
        "hierarchy": [
          "tgn:2159618",
          "tgn:1000001",
          "tgn:7012149",
          "tgn:2000183",
          "tgn:7007157",
          "tgn:7029392"
        ],
        "placetype": [
          "aat:300008697"
        ],
        "id": 2159618,
        "name:xx": "Bee Springs"
      }
    },
    {
      "geometry": {
        "type": "Point",
        "coordinates": [
          -118,
          36.8
        ]
      },
      "type": "Feature",
      "properties": {
        "hierarchy": [
          "tgn:2159619",
          "tgn:1000001",
          "tgn:7012149",
          "tgn:2000183",
          "tgn:7007157",
          "tgn:7029392"
        ],
        "placetype": [
          "aat:300008761"
        ],
        "id": 2159619,
        "name:xx": "Bee Springs Canyon"
      }
    }
  ]
}
