{
  "geometry": {
    "type": "Point",
    "coordinates": [
      -108.65,
      44.2833
    ]
  },
  "type": "Feature",
  "properties": {
    "hierarchy": [
      "tgn:2501147",
      "tgn:1000001",
      "tgn:7012149",
      "tgn:2002379",
      "tgn:7007923",
      "tgn:7029392"
    ],
    "placetype": [
      "aat:300006191"
    ],
    "id": 2501147,
    "name:xx": "McGee Reservoir"
  }
}
