{
  "type": "FeatureCollection",
  "features": [
    {
      "geometry": {
        "type": "Point",
        "coordinates": [
          -102.057,
          17.965
        ]
      },
      "type": "Feature",
      "properties": {
        "hierarchy": [
          "tgn:1113610",
          "tgn:1000001",
          "tgn:7005560",
          "tgn:7029392"
        ],
        "placetype": [
          "aat:300132316"
        ],
        "id": 1113610,
        "name:xx": "Petacalco, Bahía"
      }
    },
    {
      "geometry": {
        "type": "Point",
        "coordinates": [
          24.083333,
          38
        ]
      },
      "type": "Feature",
      "properties": {
        "hierarchy": [
          "tgn:1113611",
          "tgn:7001395",
          "tgn:1000003",
          "tgn:1000074",
          "tgn:7029392"
        ],
        "placetype": [
          "aat:300132316"
        ],
        "id": 1113611,
        "name:xx": "Petalión, Kólpos"
      }
    },
    {
      "geometry": {
        "type": "Point",
        "coordinates": [
          -61.55,
          16.2
        ]
      },
      "type": "Feature",
      "properties": {
        "hierarchy": [
          "tgn:1113612",
          "tgn:1000001",
          "tgn:7004545",
          "tgn:7029392"
        ],
        "placetype": [
          "aat:300132316"
        ],
        "id": 1113612,
        "name:xx": "Petit Cul de Sac Marin"
      }
    },
    {
      "geometry": {
        "type": "Point",
        "coordinates": [
          -149.35,
          -17.7333
        ]
      },
      "type": "Feature",
      "properties": {
        "hierarchy": [
          "tgn:1113614",
          "tgn:7006218",
          "tgn:7006211",
          "tgn:1000216",
          "tgn:1000006",
          "tgn:7029392"
        ],
        "placetype": [
          "aat:300132316"
        ],
        "id": 1113614,
        "name:xx": "Phaéton, Port"
      }
    },
    {
      "geometry": {
        "type": "Point",
        "coordinates": [
          -77.1333,
          44.05
        ]
      },
      "type": "Feature",
      "properties": {
        "hierarchy": [
          "tgn:1113615",
          "tgn:7005685",
          "tgn:1000001",
          "tgn:7013154",
          "tgn:7029392"
        ],
        "placetype": [
          "aat:300132316"
        ],
        "id": 1113615,
        "name:xx": "Picton Bay"
      }
    },
    {
      "geometry": {
        "type": "Point",
        "coordinates": [
          123,
          11.5667
        ]
      },
      "type": "Feature",
      "properties": {
        "hierarchy": [
          "tgn:1113618",
          "tgn:1000004",
          "tgn:1001178",
          "tgn:1000135",
          "tgn:7029392"
        ],
        "placetype": [
          "aat:300132316"
        ],
        "id": 1113618,
        "name:xx": "Pilar Bay"
      }
    },
    {
      "geometry": {
        "type": "Point",
        "coordinates": [
          -102.0833,
          -74.8333
        ]
      },
      "type": "Feature",
      "properties": {
        "hierarchy": [
          "tgn:1113619",
          "tgn:1000007",
          "tgn:7029392"
        ],
        "placetype": [
          "aat:300132316"
        ],
        "id": 1113619,
        "name:xx": "Pine Island Bay"
      }
    }
  ]
}
