{
  "geometry": {
    "type": "Point",
    "coordinates": [
      -84.1167,
      43.6667
    ]
  },
  "type": "Feature",
  "properties": {
    "hierarchy": [
      "tgn:2659411",
      "tgn:2000948",
      "tgn:1000001",
      "tgn:7012149",
      "tgn:7007520",
      "tgn:7029392"
    ],
    "placetype": [
      "aat:300006075"
    ],
    "id": 2659411,
    "name:xx": "Shinbines Drain"
  }
}
