{
  "type": "FeatureCollection",
  "features": [
    {
      "geometry": {
        "type": "Point",
        "coordinates": [
          -1.283333,
          41.6
        ]
      },
      "type": "Feature",
      "properties": {
        "hierarchy": [
          "tgn:1061690",
          "tgn:7002759",
          "tgn:7002845",
          "tgn:1000003",
          "tgn:1000095",
          "tgn:7029392"
        ],
        "placetype": [
          "aat:300008347"
        ],
        "id": 1061690,
        "name:xx": "Épila"
      }
    },
    {
      "geometry": {
        "type": "Point",
        "coordinates": [
          -2.783333,
          41.8
        ]
      },
      "type": "Feature",
      "properties": {
        "hierarchy": [
          "tgn:1061692",
          "tgn:7002842",
          "tgn:7001158",
          "tgn:1000003",
          "tgn:1000095",
          "tgn:7029392"
        ],
        "placetype": [
          "aat:300008347"
        ],
        "id": 1061692,
        "name:xx": "Abéjar"
      }
    },
    {
      "geometry": {
        "type": "Point",
        "coordinates": [
          -4.35,
          38.883333
        ]
      },
      "type": "Feature",
      "properties": {
        "hierarchy": [
          "tgn:1061693",
          "tgn:7002816",
          "tgn:1001647",
          "tgn:1000003",
          "tgn:1000095",
          "tgn:7029392"
        ],
        "placetype": [
          "aat:300008347"
        ],
        "id": 1061693,
        "name:xx": "Abenójar"
      }
    },
    {
      "geometry": {
        "type": "Point",
        "coordinates": [
          -4.6,
          40.933333
        ]
      },
      "type": "Feature",
      "properties": {
        "hierarchy": [
          "tgn:1061694",
          "tgn:7002806",
          "tgn:7001158",
          "tgn:1000003",
          "tgn:1000095",
          "tgn:7029392"
        ],
        "placetype": [
          "aat:300008347"
        ],
        "id": 1061694,
        "name:xx": "Adanero"
      }
    },
    {
      "geometry": {
        "type": "Point",
        "coordinates": [
          -3.016667,
          36.733333
        ]
      },
      "type": "Feature",
      "properties": {
        "hierarchy": [
          "tgn:1061695",
          "tgn:7002805",
          "tgn:7002758",
          "tgn:1000003",
          "tgn:1000095",
          "tgn:7029392"
        ],
        "placetype": [
          "aat:300008347",
          "aat:300387511",
          "aat:300008375"
        ],
        "id": 1061695,
        "name:xx": "Adra"
      }
    },
    {
      "geometry": {
        "type": "Point",
        "coordinates": [
          -3.483333,
          40.533333
        ]
      },
      "type": "Feature",
      "properties": {
        "hierarchy": [
          "tgn:1061697",
          "tgn:7010420",
          "tgn:1000003",
          "tgn:7002795",
          "tgn:1000095",
          "tgn:7029392"
        ],
        "placetype": [
          "aat:300008347"
        ],
        "id": 1061697,
        "name:xx": "Ajalvir"
      }
    },
    {
      "geometry": {
        "type": "Point",
        "coordinates": [
          -5.216667,
          39.45
        ]
      },
      "type": "Feature",
      "properties": {
        "hierarchy": [
          "tgn:1061698",
          "tgn:7002811",
          "tgn:1000003",
          "tgn:7003837",
          "tgn:1000095",
          "tgn:7029392"
        ],
        "placetype": [
          "aat:300008347"
        ],
        "id": 1061698,
        "name:xx": "Alía"
      }
    }
  ]
}
