{
  "geometry": {
    "type": "Point",
    "coordinates": [
      83.35,
      26.75
    ]
  },
  "type": "Feature",
  "properties": {
    "hierarchy": [
      "tgn:7546819",
      "tgn:1000004",
      "tgn:7000198",
      "tgn:7016722",
      "tgn:7029392"
    ],
    "placetype": [
      "aat:300008699"
    ],
    "name:en": "Rohini Nadī",
    "id": 7546819
  }
}
