{
  "geometry": {
    "type": "Point",
    "coordinates": [
      -108.0833,
      37.9167
    ]
  },
  "type": "Feature",
  "properties": {
    "hierarchy": [
      "tgn:2453591",
      "tgn:1000001",
      "tgn:7012149",
      "tgn:7007158",
      "tgn:2000248",
      "tgn:7029392"
    ],
    "placetype": [
      "aat:300008798"
    ],
    "id": 2453591,
    "name:xx": "Little Cone"
  }
}
