{
  "geometry": {
    "type": "Point",
    "coordinates": [
      -76.4667,
      36.5167
    ]
  },
  "type": "Feature",
  "properties": {
    "hierarchy": [
      "tgn:2334458",
      "tgn:1000001",
      "tgn:1002228",
      "tgn:7012149",
      "tgn:7007709",
      "tgn:7029392"
    ],
    "placetype": [
      "aat:300006075"
    ],
    "id": 2334458,
    "name:xx": "Forest Line Ditch"
  }
}
