{
  "type": "FeatureCollection",
  "features": [
    {
      "geometry": {
        "type": "Point",
        "coordinates": [
          118.9833,
          31.1667
        ]
      },
      "type": "Feature",
      "properties": {
        "hierarchy": [
          "tgn:1125963",
          "tgn:7002075",
          "tgn:1000004",
          "tgn:1000111",
          "tgn:7029392"
        ],
        "placetype": [
          "aat:300008707"
        ],
        "id": 1125963,
        "name:xx": "Langxi"
      }
    },
    {
      "geometry": {
        "type": "Point",
        "coordinates": [
          6.0833,
          47.75
        ]
      },
      "type": "Feature",
      "properties": {
        "hierarchy": [
          "tgn:1125964",
          "tgn:1000003",
          "tgn:1000070",
          "tgn:7029392"
        ],
        "placetype": [
          "aat:300008707"
        ],
        "id": 1125964,
        "name:xx": "Lanterne"
      }
    },
    {
      "geometry": {
        "type": "Point",
        "coordinates": [
          15.8,
          39.7833
        ]
      },
      "type": "Feature",
      "properties": {
        "hierarchy": [
          "tgn:1125965",
          "tgn:1003450",
          "tgn:7007850",
          "tgn:1000003",
          "tgn:1000080",
          "tgn:7029392"
        ],
        "placetype": [
          "aat:300008707",
          "aat:300008699"
        ],
        "id": 1125965,
        "name:it": "Lao"
      }
    },
    {
      "geometry": {
        "type": "Point",
        "coordinates": [
          116,
          29.1833
        ]
      },
      "type": "Feature",
      "properties": {
        "hierarchy": [
          "tgn:1125966",
          "tgn:1000004",
          "tgn:7002082",
          "tgn:1000111",
          "tgn:7029392"
        ],
        "placetype": [
          "aat:300008707"
        ],
        "id": 1125966,
        "name:xx": "Lao"
      }
    },
    {
      "geometry": {
        "type": "Point",
        "coordinates": [
          120.6,
          18.2
        ]
      },
      "type": "Feature",
      "properties": {
        "hierarchy": [
          "tgn:1125968",
          "tgn:1000004",
          "tgn:1001305",
          "tgn:1000135",
          "tgn:7029392"
        ],
        "placetype": [
          "aat:300008707"
        ],
        "id": 1125968,
        "name:xx": "Laoag"
      }
    },
    {
      "geometry": {
        "type": "Point",
        "coordinates": [
          112.9833,
          28.3
        ]
      },
      "type": "Feature",
      "properties": {
        "hierarchy": [
          "tgn:1125969",
          "tgn:1000004",
          "tgn:7002079",
          "tgn:1000111",
          "tgn:7029392"
        ],
        "placetype": [
          "aat:300008707"
        ],
        "id": 1125969,
        "name:xx": "Laodao"
      }
    }
  ]
}
