{
  "geometry": {
    "type": "Point",
    "coordinates": [
      -97.7167,
      44.65
    ]
  },
  "type": "Feature",
  "properties": {
    "hierarchy": [
      "tgn:1134137",
      "tgn:1000001",
      "tgn:7012149",
      "tgn:7007713",
      "tgn:7029392"
    ],
    "placetype": [
      "aat:300008706"
    ],
    "id": 1134137,
    "name:xx": "Pearl Creek"
  }
}
