{
  "geometry": {
    "type": "Point",
    "coordinates": [
      -122.45,
      42.4333
    ]
  },
  "type": "Feature",
  "properties": {
    "hierarchy": [
      "tgn:2747896",
      "tgn:1000001",
      "tgn:7012149",
      "tgn:2001711",
      "tgn:7007708",
      "tgn:7029392"
    ],
    "placetype": [
      "aat:300008706"
    ],
    "id": 2747896,
    "name:xx": "Walch Creek"
  }
}
