{
  "geometry": {
    "type": "Point",
    "coordinates": [
      79.239629,
      24.828651
    ]
  },
  "type": "Feature",
  "properties": {
    "hierarchy": [
      "tgn:7565095",
      "tgn:1000004",
      "tgn:7000198",
      "tgn:1001894",
      "tgn:7029392"
    ],
    "placetype": [
      "aat:300008347"
    ],
    "name:en": "Kurīla",
    "id": 7565095
  }
}
