{
  "geometry": {
    "type": "Point",
    "coordinates": [
      -86.7833,
      33.9833
    ]
  },
  "type": "Feature",
  "properties": {
    "hierarchy": [
      "tgn:2147781",
      "tgn:7002659",
      "tgn:1000001",
      "tgn:7012149",
      "tgn:2000021",
      "tgn:7029392"
    ],
    "placetype": [
      "aat:300008798"
    ],
    "id": 2147781,
    "name:xx": "Barefoot Mountain"
  }
}
