{
  "geometry": {
    "type": "Point",
    "coordinates": [
      72.1667,
      31.1667
    ]
  },
  "type": "Feature",
  "properties": {
    "hierarchy": [
      "tgn:1125173",
      "tgn:1000004",
      "tgn:7029392"
    ],
    "placetype": [
      "aat:300008707"
    ],
    "id": 1125173,
    "name:xx": "Jhelum"
  }
}
