{
  "geometry": {
    "type": "Point",
    "coordinates": [
      -90.4333,
      35.35
    ]
  },
  "type": "Feature",
  "properties": {
    "hierarchy": [
      "tgn:2156943",
      "tgn:1000001",
      "tgn:7016172",
      "tgn:2000122",
      "tgn:7012149",
      "tgn:7029392"
    ],
    "placetype": [
      "aat:300008680"
    ],
    "id": 2156943,
    "name:xx": "Beautiful Lake"
  }
}
