{
  "geometry": {
    "type": "Point",
    "coordinates": [
      -120.8667,
      36.4667
    ]
  },
  "type": "Feature",
  "properties": {
    "hierarchy": [
      "tgn:2424415",
      "tgn:1000001",
      "tgn:7012149",
      "tgn:7007157",
      "tgn:1002856",
      "tgn:7029392"
    ],
    "placetype": [
      "aat:300008761"
    ],
    "id": 2424415,
    "name:xx": "Johnson Canyon"
  }
}
