{
  "geometry": {
    "type": "Point",
    "coordinates": [
      -80.1667,
      26.2333
    ]
  },
  "type": "Feature",
  "properties": {
    "hierarchy": [
      "tgn:2247134",
      "tgn:1000001",
      "tgn:1002207",
      "tgn:7012149",
      "tgn:7007240",
      "tgn:7029392"
    ],
    "placetype": [
      "aat:300008347"
    ],
    "id": 2247134,
    "name:xx": "Coconut Creek Park"
  }
}
