{
  "geometry": {
    "type": "Point",
    "coordinates": [
      30.55,
      25.183333
    ]
  },
  "type": "Feature",
  "properties": {
    "hierarchy": [
      "tgn:7540117",
      "tgn:7001242",
      "tgn:7016833",
      "tgn:7001334",
      "tgn:7029392"
    ],
    "placetype": [
      "aat:300008777"
    ],
    "name:en": "Qaşr 'Awaḑīyah, Tall",
    "id": 7540117
  }
}
