{
  "geometry": {
    "type": "Point",
    "coordinates": [
      -113.8833,
      45.8833
    ]
  },
  "type": "Feature",
  "properties": {
    "hierarchy": [
      "tgn:2207016",
      "tgn:1000001",
      "tgn:7012149",
      "tgn:2001300",
      "tgn:7007524",
      "tgn:7029392"
    ],
    "placetype": [
      "aat:300008761"
    ],
    "id": 2207016,
    "name:xx": "Bunch Gulch"
  }
}
