{
  "type": "FeatureCollection",
  "features": [
    {
      "geometry": {
        "type": "Point",
        "coordinates": [
          -111.8333,
          33.5833
        ]
      },
      "type": "Feature",
      "properties": {
        "hierarchy": [
          "tgn:2659310",
          "tgn:1000001",
          "tgn:7006451",
          "tgn:7012149",
          "tgn:2000097",
          "tgn:7029392"
        ],
        "placetype": [
          "aat:300008347"
        ],
        "id": 2659310,
        "name:xx": "Shiloh Canyon"
      }
    },
    {
      "geometry": {
        "type": "Point",
        "coordinates": [
          -86.5667,
          38.8667
        ]
      },
      "type": "Feature",
      "properties": {
        "hierarchy": [
          "tgn:2659311",
          "tgn:1000001",
          "tgn:7012149",
          "tgn:1002579",
          "tgn:7007252",
          "tgn:7029392"
        ],
        "placetype": [
          "aat:300008746"
        ],
        "id": 2659311,
        "name:xx": "Shiloh Cave"
      }
    },
    {
      "geometry": {
        "type": "Point",
        "coordinates": [
          -85.5667,
          34.8167
        ]
      },
      "type": "Feature",
      "properties": {
        "hierarchy": [
          "tgn:2659312",
          "tgn:1000001",
          "tgn:7012149",
          "tgn:7029392"
        ],
        "placetype": [
          "aat:300008706"
        ],
        "id": 2659312,
        "name:xx": "Shiloh Creek"
      }
    },
    {
      "geometry": {
        "type": "Point",
        "coordinates": [
          -92.1333,
          35.5667
        ]
      },
      "type": "Feature",
      "properties": {
        "hierarchy": [
          "tgn:2659313",
          "tgn:1000001",
          "tgn:7016172",
          "tgn:2000116",
          "tgn:7012149",
          "tgn:7029392"
        ],
        "placetype": [
          "aat:300008706"
        ],
        "id": 2659313,
        "name:xx": "Shiloh Creek"
      }
    },
    {
      "geometry": {
        "type": "Point",
        "coordinates": [
          -93.0667,
          35.3
        ]
      },
      "type": "Feature",
      "properties": {
        "hierarchy": [
          "tgn:2659314",
          "tgn:1000001",
          "tgn:7016172",
          "tgn:7012149",
          "tgn:2000162",
          "tgn:7029392"
        ],
        "placetype": [
          "aat:300008706"
        ],
        "id": 2659314,
        "name:xx": "Shiloh Creek"
      }
    },
    {
      "geometry": {
        "type": "Point",
        "coordinates": [
          -83.2167,
          34.2167
        ]
      },
      "type": "Feature",
      "properties": {
        "hierarchy": [
          "tgn:2659315",
          "tgn:1000001",
          "tgn:7012149",
          "tgn:2000388",
          "tgn:7007248",
          "tgn:7029392"
        ],
        "placetype": [
          "aat:300008706"
        ],
        "id": 2659315,
        "name:xx": "Shiloh Creek"
      }
    },
    {
      "geometry": {
        "type": "Point",
        "coordinates": [
          -86.3333,
          39.7667
        ]
      },
      "type": "Feature",
      "properties": {
        "hierarchy": [
          "tgn:2659316",
          "tgn:1000001",
          "tgn:7012149",
          "tgn:7007252",
          "tgn:7029392"
        ],
        "placetype": [
          "aat:300008706"
        ],
        "id": 2659316,
        "name:xx": "Shiloh Creek"
      }
    },
    {
      "geometry": {
        "type": "Point",
        "coordinates": [
          -84.7833,
          36.8333
        ]
      },
      "type": "Feature",
      "properties": {
        "hierarchy": [
          "tgn:2659317",
          "tgn:1000001",
          "tgn:7012149",
          "tgn:2000850",
          "tgn:7007255",
          "tgn:7029392"
        ],
        "placetype": [
          "aat:300008706"
        ],
        "id": 2659317,
        "name:xx": "Shiloh Creek"
      }
    },
    {
      "geometry": {
        "type": "Point",
        "coordinates": [
          -89.2833,
          34.3167
        ]
      },
      "type": "Feature",
      "properties": {
        "hierarchy": [
          "tgn:2659318",
          "tgn:1000001",
          "tgn:7012149",
          "tgn:2001121",
          "tgn:7007522",
          "tgn:7029392"
        ],
        "placetype": [
          "aat:300008706"
        ],
        "id": 2659318,
        "name:xx": "Shiloh Creek"
      }
    },
    {
      "geometry": {
        "type": "Point",
        "coordinates": [
          -90.5833,
          32.35
        ]
      },
      "type": "Feature",
      "properties": {
        "hierarchy": [
          "tgn:2659319",
          "tgn:1000001",
          "tgn:7012149",
          "tgn:2001110",
          "tgn:7007522",
          "tgn:7029392"
        ],
        "placetype": [
          "aat:300008706"
        ],
        "id": 2659319,
        "name:xx": "Shiloh Creek"
      }
    }
  ]
}
