{
  "geometry": {
    "type": "Point",
    "coordinates": [
      21.7167,
      5.3333
    ]
  },
  "type": "Feature",
  "properties": {
    "hierarchy": [
      "tgn:1088380",
      "tgn:1000965",
      "tgn:7001242",
      "tgn:1000155",
      "tgn:7029392"
    ],
    "placetype": [
      "aat:300008347"
    ],
    "id": 1088380,
    "name:xx": "Kabou"
  }
}
