{
  "geometry": {
    "type": "Point",
    "coordinates": [
      -113.9667,
      45.5833
    ]
  },
  "type": "Feature",
  "properties": {
    "hierarchy": [
      "tgn:2454490",
      "tgn:1000001",
      "tgn:7012149",
      "tgn:2000481",
      "tgn:7007250",
      "tgn:7029392"
    ],
    "placetype": [
      "aat:300008706"
    ],
    "id": 2454490,
    "name:xx": "Little Deep Creek"
  }
}
