{
  "geometry": {
    "type": "Point",
    "coordinates": [
      -85.0333,
      36.5833
    ]
  },
  "type": "Feature",
  "properties": {
    "hierarchy": [
      "tgn:2394764",
      "tgn:1000001",
      "tgn:7012149",
      "tgn:7007825",
      "tgn:7029392"
    ],
    "placetype": [
      "aat:300008706"
    ],
    "id": 2394764,
    "name:xx": "Holbert Creek"
  }
}
