{
  "geometry": {
    "type": "Point",
    "coordinates": [
      -90.5833,
      38.6167
    ]
  },
  "type": "Feature",
  "properties": {
    "hierarchy": [
      "tgn:2058368",
      "tgn:1000001",
      "tgn:7012149",
      "tgn:7016167",
      "tgn:7007523",
      "tgn:7029392"
    ],
    "placetype": [
      "aat:300008347"
    ],
    "id": 2058368,
    "name:xx": "Clarkson Valley"
  }
}
