{
  "type": "FeatureCollection",
  "features": [
    {
      "geometry": {
        "type": "Point",
        "coordinates": [
          -106.3,
          25.55
        ]
      },
      "type": "Feature",
      "properties": {
        "hierarchy": [
          "tgn:7376520",
          "tgn:7005583",
          "tgn:1000001",
          "tgn:7005560",
          "tgn:7029392"
        ],
        "placetype": [
          "aat:300000241"
        ],
        "id": 7376520,
        "name:xx": "Rancho Las Lajas"
      }
    },
    {
      "geometry": {
        "type": "Point",
        "coordinates": [
          -99.972778,
          24.99
        ]
      },
      "type": "Feature",
      "properties": {
        "hierarchy": [
          "tgn:7376521",
          "tgn:1000001",
          "tgn:7005589",
          "tgn:7005560",
          "tgn:7029392"
        ],
        "placetype": [
          "aat:300000241"
        ],
        "id": 7376521,
        "name:xx": "Rancho Las Lajas"
      }
    },
    {
      "geometry": {
        "type": "Point",
        "coordinates": [
          -109.85,
          29.65
        ]
      },
      "type": "Feature",
      "properties": {
        "hierarchy": [
          "tgn:7376522",
          "tgn:1000001",
          "tgn:1001960",
          "tgn:7005560",
          "tgn:7029392"
        ],
        "placetype": [
          "aat:300266554",
          "aat:300008699"
        ],
        "id": 7376522,
        "name:xx": "Las Lajas, Arroyo"
      }
    },
    {
      "geometry": {
        "type": "Point",
        "coordinates": [
          -109.35,
          27.233333
        ]
      },
      "type": "Feature",
      "properties": {
        "hierarchy": [
          "tgn:7376523",
          "tgn:1000001",
          "tgn:1001960",
          "tgn:7005560",
          "tgn:7029392"
        ],
        "placetype": [
          "aat:300008699"
        ],
        "id": 7376523,
        "name:xx": "Las Lajas, Arroyo"
      }
    },
    {
      "geometry": {
        "type": "Point",
        "coordinates": [
          -98.483333,
          20.033333
        ]
      },
      "type": "Feature",
      "properties": {
        "hierarchy": [
          "tgn:7376525",
          "tgn:7005587",
          "tgn:1000001",
          "tgn:7005560",
          "tgn:7029392"
        ],
        "placetype": [
          "aat:300007783"
        ],
        "id": 7376525,
        "name:xx": "Las Lajas"
      }
    },
    {
      "geometry": {
        "type": "Point",
        "coordinates": [
          -107.083333,
          29.883333
        ]
      },
      "type": "Feature",
      "properties": {
        "hierarchy": [
          "tgn:7376526",
          "tgn:7005581",
          "tgn:1000001",
          "tgn:7005560",
          "tgn:7029392"
        ],
        "placetype": [
          "aat:300008347"
        ],
        "id": 7376526,
        "name:xx": "Las Lajas"
      }
    },
    {
      "geometry": {
        "type": "Point",
        "coordinates": [
          -109.9,
          29.7
        ]
      },
      "type": "Feature",
      "properties": {
        "hierarchy": [
          "tgn:7376527",
          "tgn:1000001",
          "tgn:1001960",
          "tgn:7005560",
          "tgn:7029392"
        ],
        "placetype": [
          "aat:300008347"
        ],
        "id": 7376527,
        "name:xx": "Las Lajas"
      }
    },
    {
      "geometry": {
        "type": "Point",
        "coordinates": [
          -109.833333,
          28.683333
        ]
      },
      "type": "Feature",
      "properties": {
        "hierarchy": [
          "tgn:7376528",
          "tgn:1000001",
          "tgn:1001960",
          "tgn:7005560",
          "tgn:7029392"
        ],
        "placetype": [
          "aat:300008347"
        ],
        "id": 7376528,
        "name:xx": "Las Lajas"
      }
    },
    {
      "geometry": {
        "type": "Point",
        "coordinates": [
          -109.383333,
          27.266667
        ]
      },
      "type": "Feature",
      "properties": {
        "hierarchy": [
          "tgn:7376529",
          "tgn:1000001",
          "tgn:1001960",
          "tgn:7005560",
          "tgn:7029392"
        ],
        "placetype": [
          "aat:300008347"
        ],
        "id": 7376529,
        "name:xx": "Las Lajas"
      }
    }
  ]
}
