{
  "type": "FeatureCollection",
  "features": [
    {
      "geometry": {
        "type": "Point",
        "coordinates": [
          -147.1833,
          65.5333
        ]
      },
      "type": "Feature",
      "properties": {
        "hierarchy": [
          "tgn:2335910",
          "tgn:7006450",
          "tgn:1000001",
          "tgn:7012149",
          "tgn:2000089",
          "tgn:7029392"
        ],
        "placetype": [
          "aat:300008706"
        ],
        "id": 2335910,
        "name:xx": "Fossil Creek"
      }
    },
    {
      "geometry": {
        "type": "Point",
        "coordinates": [
          -111.5,
          34.4333
        ]
      },
      "type": "Feature",
      "properties": {
        "hierarchy": [
          "tgn:2335911",
          "tgn:1000001",
          "tgn:7006451",
          "tgn:7012149",
          "tgn:7029392"
        ],
        "placetype": [
          "aat:300008706"
        ],
        "id": 2335911,
        "name:xx": "Fossil Creek"
      }
    },
    {
      "geometry": {
        "type": "Point",
        "coordinates": [
          -123.0667,
          39.9167
        ]
      },
      "type": "Feature",
      "properties": {
        "hierarchy": [
          "tgn:2335912",
          "tgn:1000001",
          "tgn:7012149",
          "tgn:7007157",
          "tgn:2000185",
          "tgn:7029392"
        ],
        "placetype": [
          "aat:300008706"
        ],
        "id": 2335912,
        "name:xx": "Fossil Creek"
      }
    },
    {
      "geometry": {
        "type": "Point",
        "coordinates": [
          -105.1333,
          40.5
        ]
      },
      "type": "Feature",
      "properties": {
        "hierarchy": [
          "tgn:2335913",
          "tgn:1000001",
          "tgn:7012149",
          "tgn:2000226",
          "tgn:7007158",
          "tgn:7029392"
        ],
        "placetype": [
          "aat:300008706"
        ],
        "id": 2335913,
        "name:xx": "Fossil Creek"
      }
    },
    {
      "geometry": {
        "type": "Point",
        "coordinates": [
          -116.6,
          43
        ]
      },
      "type": "Feature",
      "properties": {
        "hierarchy": [
          "tgn:2335914",
          "tgn:1000001",
          "tgn:7012149",
          "tgn:2000488",
          "tgn:7007250",
          "tgn:7029392"
        ],
        "placetype": [
          "aat:300008706"
        ],
        "id": 2335914,
        "name:xx": "Fossil Creek"
      }
    },
    {
      "geometry": {
        "type": "Point",
        "coordinates": [
          -98.95,
          38.8833
        ]
      },
      "type": "Feature",
      "properties": {
        "hierarchy": [
          "tgn:2335915",
          "tgn:1000001",
          "tgn:7012149",
          "tgn:2000743",
          "tgn:7007254",
          "tgn:7029392"
        ],
        "placetype": [
          "aat:300008706"
        ],
        "id": 2335915,
        "name:xx": "Fossil Creek"
      }
    },
    {
      "geometry": {
        "type": "Point",
        "coordinates": [
          -111.8333,
          44.8167
        ]
      },
      "type": "Feature",
      "properties": {
        "hierarchy": [
          "tgn:2335916",
          "tgn:1000001",
          "tgn:7012149",
          "tgn:7007524",
          "tgn:7029392"
        ],
        "placetype": [
          "aat:300008706"
        ],
        "id": 2335916,
        "name:xx": "Fossil Creek"
      }
    },
    {
      "geometry": {
        "type": "Point",
        "coordinates": [
          -119.6167,
          44.7
        ]
      },
      "type": "Feature",
      "properties": {
        "hierarchy": [
          "tgn:2335917",
          "tgn:1000001",
          "tgn:7012149",
          "tgn:2001708",
          "tgn:7007708",
          "tgn:7029392"
        ],
        "placetype": [
          "aat:300008706"
        ],
        "id": 2335917,
        "name:xx": "Fossil Creek"
      }
    },
    {
      "geometry": {
        "type": "Point",
        "coordinates": [
          -121.8333,
          48.9167
        ]
      },
      "type": "Feature",
      "properties": {
        "hierarchy": [
          "tgn:2335918",
          "tgn:1000001",
          "tgn:7012149",
          "tgn:1003020",
          "tgn:7007920",
          "tgn:7029392"
        ],
        "placetype": [
          "aat:300008706"
        ],
        "id": 2335918,
        "name:xx": "Fossil Creek"
      }
    },
    {
      "geometry": {
        "type": "Point",
        "coordinates": [
          -124.3833,
          47.7667
        ]
      },
      "type": "Feature",
      "properties": {
        "hierarchy": [
          "tgn:2335919",
          "tgn:1000001",
          "tgn:7012149",
          "tgn:1002521",
          "tgn:7007920",
          "tgn:7029392"
        ],
        "placetype": [
          "aat:300008706"
        ],
        "id": 2335919,
        "name:xx": "Fossil Creek"
      }
    }
  ]
}
