{
  "type": "FeatureCollection",
  "features": [
    {
      "geometry": {
        "type": "Point",
        "coordinates": [
          68.4667,
          38.0167
        ]
      },
      "type": "Feature",
      "properties": {
        "hierarchy": [
          "tgn:1105730",
          "tgn:7011631",
          "tgn:1000004",
          "tgn:7014835",
          "tgn:7029392"
        ],
        "placetype": [
          "aat:300008795"
        ],
        "id": 1105730,
        "name:xx": "Mundytau, Gora"
      }
    },
    {
      "geometry": {
        "type": "Point",
        "coordinates": [
          100.5,
          51.8
        ]
      },
      "type": "Feature",
      "properties": {
        "hierarchy": [
          "tgn:1105732",
          "tgn:1000004",
          "tgn:7029392"
        ],
        "placetype": [
          "aat:300008795"
        ],
        "id": 1105732,
        "name:xx": "Munki-Sardyk, Gora"
      }
    },
    {
      "geometry": {
        "type": "Point",
        "coordinates": [
          27.7,
          13.6333
        ]
      },
      "type": "Feature",
      "properties": {
        "hierarchy": [
          "tgn:1105735",
          "tgn:7001242",
          "tgn:1000201",
          "tgn:1001368",
          "tgn:7029392"
        ],
        "placetype": [
          "aat:300008795"
        ],
        "id": 1105735,
        "name:xx": "Muqsam, Jabal"
      }
    },
    {
      "geometry": {
        "type": "Point",
        "coordinates": [
          -73.4333,
          -49.8
        ]
      },
      "type": "Feature",
      "properties": {
        "hierarchy": [
          "tgn:1105736",
          "tgn:1000002",
          "tgn:7029392"
        ],
        "placetype": [
          "aat:300008795"
        ],
        "id": 1105736,
        "name:xx": "Murallón, Cerro"
      }
    },
    {
      "geometry": {
        "type": "Point",
        "coordinates": [
          171.366667,
          -43.016667
        ]
      },
      "type": "Feature",
      "properties": {
        "hierarchy": [
          "tgn:1105739",
          "tgn:1009227",
          "tgn:7001866",
          "tgn:1000226",
          "tgn:1000006",
          "tgn:7029392"
        ],
        "placetype": [
          "aat:300008795"
        ],
        "name:en": "Murchison, Mount",
        "id": 1105739
      }
    }
  ]
}
