{
  "type": "FeatureCollection",
  "features": [
    {
      "geometry": {
        "type": "Point",
        "coordinates": [
          -103.016667,
          19.7
        ]
      },
      "type": "Feature",
      "properties": {
        "hierarchy": [
          "tgn:7364550",
          "tgn:7005586",
          "tgn:1000001",
          "tgn:7005560",
          "tgn:7029392"
        ],
        "placetype": [
          "aat:300000241"
        ],
        "id": 7364550,
        "name:xx": "El Pozole"
      }
    },
    {
      "geometry": {
        "type": "Point",
        "coordinates": [
          -109.333333,
          25.866667
        ]
      },
      "type": "Feature",
      "properties": {
        "hierarchy": [
          "tgn:7364551",
          "tgn:1000001",
          "tgn:7005595",
          "tgn:7005560",
          "tgn:7029392"
        ],
        "placetype": [
          "aat:300008347"
        ],
        "id": 7364551,
        "name:xx": "El Pozole"
      }
    },
    {
      "geometry": {
        "type": "Point",
        "coordinates": [
          -104.766667,
          24.566667
        ]
      },
      "type": "Feature",
      "properties": {
        "hierarchy": [
          "tgn:7364552",
          "tgn:7005583",
          "tgn:1000001",
          "tgn:7005560",
          "tgn:7029392"
        ],
        "placetype": [
          "aat:300008347"
        ],
        "id": 7364552,
        "name:xx": "El Pozole"
      }
    },
    {
      "geometry": {
        "type": "Point",
        "coordinates": [
          -106.233333,
          23.183333
        ]
      },
      "type": "Feature",
      "properties": {
        "hierarchy": [
          "tgn:7364553",
          "tgn:1000001",
          "tgn:7005595",
          "tgn:7005560",
          "tgn:7029392"
        ],
        "placetype": [
          "aat:300008347"
        ],
        "id": 7364553,
        "name:xx": "El Pozole"
      }
    },
    {
      "geometry": {
        "type": "Point",
        "coordinates": [
          -105.383333,
          21.7
        ]
      },
      "type": "Feature",
      "properties": {
        "hierarchy": [
          "tgn:7364554",
          "tgn:1000001",
          "tgn:1001906",
          "tgn:7005560",
          "tgn:7029392"
        ],
        "placetype": [
          "aat:300008347"
        ],
        "id": 7364554,
        "name:xx": "El Pozole"
      }
    },
    {
      "geometry": {
        "type": "Point",
        "coordinates": [
          -110.733333,
          28.333333
        ]
      },
      "type": "Feature",
      "properties": {
        "hierarchy": [
          "tgn:7364555",
          "tgn:1000001",
          "tgn:1001960",
          "tgn:7005560",
          "tgn:7029392"
        ],
        "placetype": [
          "aat:300000241"
        ],
        "id": 7364555,
        "name:xx": "Rancho El Pozo de Obregón"
      }
    },
    {
      "geometry": {
        "type": "Point",
        "coordinates": [
          -110.966667,
          30.966667
        ]
      },
      "type": "Feature",
      "properties": {
        "hierarchy": [
          "tgn:7364556",
          "tgn:1000001",
          "tgn:1001960",
          "tgn:7005560",
          "tgn:7029392"
        ],
        "placetype": [
          "aat:300008347"
        ],
        "id": 7364556,
        "name:xx": "El Pozo"
      }
    },
    {
      "geometry": {
        "type": "Point",
        "coordinates": [
          -110.083333,
          30.9
        ]
      },
      "type": "Feature",
      "properties": {
        "hierarchy": [
          "tgn:7364557",
          "tgn:1000001",
          "tgn:1001960",
          "tgn:7005560",
          "tgn:7029392"
        ],
        "placetype": [
          "aat:300000241"
        ],
        "id": 7364557,
        "name:xx": "Rancho El Pozo"
      }
    },
    {
      "geometry": {
        "type": "Point",
        "coordinates": [
          -109.55,
          30.65
        ]
      },
      "type": "Feature",
      "properties": {
        "hierarchy": [
          "tgn:7364558",
          "tgn:1000001",
          "tgn:1001960",
          "tgn:7005560",
          "tgn:7029392"
        ],
        "placetype": [
          "aat:300000241"
        ],
        "id": 7364558,
        "name:xx": "Rancho El Pozo"
      }
    }
  ]
}
