{
  "geometry": {
    "type": "Point",
    "coordinates": [
      -106.55,
      35.2833
    ]
  },
  "type": "Feature",
  "properties": {
    "hierarchy": [
      "tgn:2188213",
      "tgn:1000001",
      "tgn:7012149",
      "tgn:2001451",
      "tgn:7007566",
      "tgn:7029392"
    ],
    "placetype": [
      "aat:300006075"
    ],
    "id": 2188213,
    "name:xx": "Bosque Lateral Number Two"
  }
}
