{
  "type": "FeatureCollection",
  "features": [
    {
      "geometry": {
        "type": "Point",
        "coordinates": [
          -85.8,
          35.45
        ]
      },
      "type": "Feature",
      "properties": {
        "hierarchy": [
          "tgn:2228970",
          "tgn:1000001",
          "tgn:7012149",
          "tgn:2001867",
          "tgn:7007825",
          "tgn:7029392"
        ],
        "placetype": [
          "aat:300008761"
        ],
        "id": 2228970,
        "name:xx": "Cedar Hollow"
      }
    },
    {
      "geometry": {
        "type": "Point",
        "coordinates": [
          -88.05,
          36.0667
        ]
      },
      "type": "Feature",
      "properties": {
        "hierarchy": [
          "tgn:2228971",
          "tgn:1000001",
          "tgn:2001839",
          "tgn:7012149",
          "tgn:7007825",
          "tgn:7029392"
        ],
        "placetype": [
          "aat:300008761"
        ],
        "id": 2228971,
        "name:xx": "Cedar Hollow"
      }
    },
    {
      "geometry": {
        "type": "Point",
        "coordinates": [
          -99.2167,
          29.6833
        ]
      },
      "type": "Feature",
      "properties": {
        "hierarchy": [
          "tgn:2228972",
          "tgn:1000001",
          "tgn:2001938",
          "tgn:7012149",
          "tgn:7007826",
          "tgn:7029392"
        ],
        "placetype": [
          "aat:300008761"
        ],
        "id": 2228972,
        "name:xx": "Cedar Hollow"
      }
    },
    {
      "geometry": {
        "type": "Point",
        "coordinates": [
          -99.8167,
          29.7167
        ]
      },
      "type": "Feature",
      "properties": {
        "hierarchy": [
          "tgn:2228973",
          "tgn:1000001",
          "tgn:7012149",
          "tgn:2002060",
          "tgn:7007826",
          "tgn:7029392"
        ],
        "placetype": [
          "aat:300008761"
        ],
        "id": 2228973,
        "name:xx": "Cedar Hollow"
      }
    },
    {
      "geometry": {
        "type": "Point",
        "coordinates": [
          -97.9333,
          30.3
        ]
      },
      "type": "Feature",
      "properties": {
        "hierarchy": [
          "tgn:2228974",
          "tgn:1000001",
          "tgn:7012149",
          "tgn:1002952",
          "tgn:7007826",
          "tgn:7029392"
        ],
        "placetype": [
          "aat:300008761"
        ],
        "id": 2228974,
        "name:xx": "Cedar Hollow"
      }
    },
    {
      "geometry": {
        "type": "Point",
        "coordinates": [
          -98.55,
          31.1833
        ]
      },
      "type": "Feature",
      "properties": {
        "hierarchy": [
          "tgn:2228975",
          "tgn:1000001",
          "tgn:7012149",
          "tgn:2002069",
          "tgn:7007826",
          "tgn:7029392"
        ],
        "placetype": [
          "aat:300386845"
        ],
        "id": 2228975,
        "name:xx": "Cedar Hollow"
      }
    },
    {
      "geometry": {
        "type": "Point",
        "coordinates": [
          -99.0333,
          30.5167
        ]
      },
      "type": "Feature",
      "properties": {
        "hierarchy": [
          "tgn:2228976",
          "tgn:1000001",
          "tgn:7012149",
          "tgn:2002037",
          "tgn:7007826",
          "tgn:7029392"
        ],
        "placetype": [
          "aat:300008761"
        ],
        "id": 2228976,
        "name:xx": "Cedar Hollow"
      }
    },
    {
      "geometry": {
        "type": "Point",
        "coordinates": [
          -97.7667,
          30.65
        ]
      },
      "type": "Feature",
      "properties": {
        "hierarchy": [
          "tgn:2228977",
          "tgn:1000001",
          "tgn:7012149",
          "tgn:1003026",
          "tgn:7007826",
          "tgn:7029392"
        ],
        "placetype": [
          "aat:300008761"
        ],
        "id": 2228977,
        "name:xx": "Cedar Hollow"
      }
    },
    {
      "geometry": {
        "type": "Point",
        "coordinates": [
          -99.65,
          30.65
        ]
      },
      "type": "Feature",
      "properties": {
        "hierarchy": [
          "tgn:2228978",
          "tgn:1000001",
          "tgn:7012149",
          "tgn:2002019",
          "tgn:7007826",
          "tgn:7029392"
        ],
        "placetype": [
          "aat:300008761"
        ],
        "id": 2228978,
        "name:xx": "Cedar Hollow"
      }
    },
    {
      "geometry": {
        "type": "Point",
        "coordinates": [
          -99.55,
          30.9333
        ]
      },
      "type": "Feature",
      "properties": {
        "hierarchy": [
          "tgn:2228979",
          "tgn:1000001",
          "tgn:7012149",
          "tgn:2002040",
          "tgn:7007826",
          "tgn:7029392"
        ],
        "placetype": [
          "aat:300008761"
        ],
        "id": 2228979,
        "name:xx": "Cedar Hollow"
      }
    }
  ]
}
