{
  "geometry": {
    "type": "Point",
    "coordinates": [
      77.839033,
      30.351316
    ]
  },
  "type": "Feature",
  "properties": {
    "hierarchy": [
      "tgn:7591849",
      "tgn:1000004",
      "tgn:7000198",
      "tgn:7031786",
      "tgn:7029392"
    ],
    "placetype": [
      "aat:300008699"
    ],
    "name:en": "Bhātūwāla Rao",
    "id": 7591849
  }
}
