{
  "geometry": {
    "type": "Point",
    "coordinates": [
      -80.6333,
      39.8667
    ]
  },
  "type": "Feature",
  "properties": {
    "hierarchy": [
      "tgn:2334823",
      "tgn:1000001",
      "tgn:7012149",
      "tgn:2002276",
      "tgn:7013961",
      "tgn:7029392"
    ],
    "placetype": [
      "aat:300266640"
    ],
    "id": 2334823,
    "name:xx": "Fork Ridge"
  }
}
