{
  "geometry": {
    "type": "Point",
    "coordinates": [
      30.049167,
      30.709167
    ]
  },
  "type": "Feature",
  "properties": {
    "hierarchy": [
      "tgn:7529491",
      "tgn:7001242",
      "tgn:1001075",
      "tgn:7016833",
      "tgn:7029392"
    ],
    "placetype": [
      "aat:300007558"
    ],
    "name:en": "Ḍarîḥ Tammâmîya",
    "id": 7529491
  }
}
