{
  "type": "FeatureCollection",
  "features": [
    {
      "geometry": {
        "type": "Point",
        "coordinates": [
          7.266667,
          51.95
        ]
      },
      "type": "Feature",
      "properties": {
        "hierarchy": [
          "tgn:7216510",
          "tgn:1000003",
          "tgn:7003677",
          "tgn:7000084",
          "tgn:7029392"
        ],
        "placetype": [
          "aat:300387200"
        ],
        "id": 7216510,
        "name:xx": "Alstätte"
      }
    },
    {
      "geometry": {
        "type": "Point",
        "coordinates": [
          7.783333,
          51.85
        ]
      },
      "type": "Feature",
      "properties": {
        "hierarchy": [
          "tgn:7216514",
          "tgn:1000003",
          "tgn:7003677",
          "tgn:7000084",
          "tgn:7029392"
        ],
        "placetype": [
          "aat:300007783"
        ],
        "id": 7216514,
        "name:xx": "Haltepunkt Alst"
      }
    },
    {
      "geometry": {
        "type": "Point",
        "coordinates": [
          7.766667,
          51.85
        ]
      },
      "type": "Feature",
      "properties": {
        "hierarchy": [
          "tgn:7216515",
          "tgn:1000003",
          "tgn:7003677",
          "tgn:7000084",
          "tgn:7029392"
        ],
        "placetype": [
          "aat:300387200"
        ],
        "id": 7216515,
        "name:xx": "Alst"
      }
    },
    {
      "geometry": {
        "type": "Point",
        "coordinates": [
          7.316667,
          52.1
        ]
      },
      "type": "Feature",
      "properties": {
        "hierarchy": [
          "tgn:7216516",
          "tgn:1000003",
          "tgn:7003677",
          "tgn:7000084",
          "tgn:7029392"
        ],
        "placetype": [
          "aat:300008347"
        ],
        "id": 7216516,
        "name:xx": "Alst"
      }
    },
    {
      "geometry": {
        "type": "Point",
        "coordinates": [
          6.2,
          51.266667
        ]
      },
      "type": "Feature",
      "properties": {
        "hierarchy": [
          "tgn:7216517",
          "tgn:1000003",
          "tgn:7003677",
          "tgn:7000084",
          "tgn:7029392"
        ],
        "placetype": [
          "aat:300008347"
        ],
        "id": 7216517,
        "name:xx": "Alst"
      }
    },
    {
      "geometry": {
        "type": "Point",
        "coordinates": [
          11.033333,
          48.516667
        ]
      },
      "type": "Feature",
      "properties": {
        "hierarchy": [
          "tgn:7216518",
          "tgn:7003669",
          "tgn:1000003",
          "tgn:7000084",
          "tgn:7029392"
        ],
        "placetype": [
          "aat:300008347"
        ],
        "id": 7216518,
        "name:xx": "Alsmoos"
      }
    },
    {
      "geometry": {
        "type": "Point",
        "coordinates": [
          11.8,
          50.75
        ]
      },
      "type": "Feature",
      "properties": {
        "hierarchy": [
          "tgn:7216519",
          "tgn:1000003",
          "tgn:7003689",
          "tgn:7000084",
          "tgn:7029392"
        ],
        "placetype": [
          "aat:300008347"
        ],
        "id": 7216519,
        "name:xx": "Alsmannsdorf"
      }
    }
  ]
}
