{
  "geometry": {
    "type": "Point",
    "coordinates": [
      -80.0833,
      37.25
    ]
  },
  "type": "Feature",
  "properties": {
    "hierarchy": [
      "tgn:2513039",
      "tgn:1000001",
      "tgn:7012149",
      "tgn:7014344",
      "tgn:7007919",
      "tgn:7029392"
    ],
    "placetype": [
      "aat:300008706"
    ],
    "id": 2513039,
    "name:xx": "Mill Creek"
  }
}
