{
  "geometry": {
    "type": "Point",
    "coordinates": [
      -99.875,
      17.0625
    ]
  },
  "type": "Feature",
  "properties": {
    "hierarchy": [
      "tgn:7404615",
      "tgn:7005585",
      "tgn:1000001",
      "tgn:7005560",
      "tgn:7029392"
    ],
    "placetype": [
      "aat:300008795"
    ],
    "id": 7404615,
    "name:xx": "La Lima, Cerro"
  }
}
