{
  "geometry": {
    "type": "Point",
    "coordinates": [
      33.25,
      8.1667
    ]
  },
  "type": "Feature",
  "properties": {
    "hierarchy": [
      "tgn:1124189",
      "tgn:7001242",
      "tgn:1001308",
      "tgn:7000489",
      "tgn:7029392"
    ],
    "placetype": [
      "aat:300008707"
    ],
    "id": 1124189,
    "name:xx": "Gīlo Wenz"
  }
}
