{
  "geometry": {
    "type": "Point",
    "coordinates": [
      79.9414,
      27.0191
    ]
  },
  "type": "Feature",
  "properties": {
    "hierarchy": [
      "tgn:7559609",
      "tgn:1000004",
      "tgn:7000198",
      "tgn:7016722",
      "tgn:7029392"
    ],
    "placetype": [
      "aat:300008347"
    ],
    "name:en": "Balai",
    "id": 7559609
  }
}
