{
  "geometry": {
    "type": "Point",
    "coordinates": [
      -78.6833,
      38.4667
    ]
  },
  "type": "Feature",
  "properties": {
    "hierarchy": [
      "tgn:1135505",
      "tgn:1000001",
      "tgn:7012149",
      "tgn:7007919",
      "tgn:7029392"
    ],
    "placetype": [
      "aat:300387045"
    ],
    "id": 1135505,
    "name:xx": "Cub Run"
  }
}
