{
  "geometry": {
    "type": "Point",
    "coordinates": [
      -141.8833,
      68.4667
    ]
  },
  "type": "Feature",
  "properties": {
    "hierarchy": [
      "tgn:2327484",
      "tgn:7006450",
      "tgn:1000001",
      "tgn:7012149",
      "tgn:7029392"
    ],
    "placetype": [
      "aat:300008707"
    ],
    "id": 2327484,
    "name:xx": "Firth River"
  }
}
