{
  "geometry": {
    "type": "Point",
    "coordinates": [
      -123.8333,
      46.4833
    ]
  },
  "type": "Feature",
  "properties": {
    "hierarchy": [
      "tgn:2340752",
      "tgn:1000001",
      "tgn:7012149",
      "tgn:1002767",
      "tgn:7007920",
      "tgn:7029392"
    ],
    "placetype": [
      "aat:300008706"
    ],
    "id": 2340752,
    "name:xx": "Freshwater Creek"
  }
}
