{
  "geometry": {
    "type": "Point",
    "coordinates": [
      -75.45,
      40.0833
    ]
  },
  "type": "Feature",
  "properties": {
    "hierarchy": [
      "tgn:2427917",
      "tgn:1000001",
      "tgn:7012149",
      "tgn:1002690",
      "tgn:7007710",
      "tgn:7029392"
    ],
    "placetype": [
      "aat:300008798"
    ],
    "id": 2427917,
    "name:xx": "Joy, Mount"
  }
}
