{
  "type": "FeatureCollection",
  "features": [
    {
      "geometry": {
        "type": "Point",
        "coordinates": [
          -96.466667,
          16.083333
        ]
      },
      "type": "Feature",
      "properties": {
        "hierarchy": [
          "tgn:7397281",
          "tgn:1000001",
          "tgn:7005591",
          "tgn:7005560",
          "tgn:7029392"
        ],
        "placetype": [
          "aat:300008347"
        ],
        "id": 7397281,
        "name:xx": "San Miguel Suchixtepec"
      }
    },
    {
      "geometry": {
        "type": "Point",
        "coordinates": [
          -95.95,
          16.2
        ]
      },
      "type": "Feature",
      "properties": {
        "hierarchy": [
          "tgn:7397282",
          "tgn:1000001",
          "tgn:7005591",
          "tgn:7005560",
          "tgn:7029392"
        ],
        "placetype": [
          "aat:300008347"
        ],
        "id": 7397282,
        "name:xx": "San Miguel Suchiltepec"
      }
    },
    {
      "geometry": {
        "type": "Point",
        "coordinates": [
          -91.1,
          17.633333
        ]
      },
      "type": "Feature",
      "properties": {
        "hierarchy": [
          "tgn:7397284",
          "tgn:1000001",
          "tgn:7005596",
          "tgn:7005560",
          "tgn:7029392"
        ],
        "placetype": [
          "aat:300008347"
        ],
        "id": 7397284,
        "name:xx": "San Miguel Sacaola"
      }
    },
    {
      "geometry": {
        "type": "Point",
        "coordinates": [
          -107.883333,
          28.583333
        ]
      },
      "type": "Feature",
      "properties": {
        "hierarchy": [
          "tgn:7397285",
          "tgn:7005581",
          "tgn:1000001",
          "tgn:7005560",
          "tgn:7029392"
        ],
        "placetype": [
          "aat:300008347"
        ],
        "id": 7397285,
        "name:xx": "San Miguel Río Verde"
      }
    },
    {
      "geometry": {
        "type": "Point",
        "coordinates": [
          -97.9,
          16.916667
        ]
      },
      "type": "Feature",
      "properties": {
        "hierarchy": [
          "tgn:7397286",
          "tgn:1000001",
          "tgn:7005591",
          "tgn:7005560",
          "tgn:7029392"
        ],
        "placetype": [
          "aat:300008347"
        ],
        "id": 7397286,
        "name:xx": "San Miguel Reyes"
      }
    },
    {
      "geometry": {
        "type": "Point",
        "coordinates": [
          -98.566667,
          20.216667
        ]
      },
      "type": "Feature",
      "properties": {
        "hierarchy": [
          "tgn:7397287",
          "tgn:7005587",
          "tgn:1000001",
          "tgn:7005560",
          "tgn:7029392"
        ],
        "placetype": [
          "aat:300008347"
        ],
        "id": 7397287,
        "name:xx": "San Miguel Regla"
      }
    },
    {
      "geometry": {
        "type": "Point",
        "coordinates": [
          -96.216667,
          17.5
        ]
      },
      "type": "Feature",
      "properties": {
        "hierarchy": [
          "tgn:7397288",
          "tgn:1000001",
          "tgn:7005591",
          "tgn:7005560",
          "tgn:7029392"
        ],
        "placetype": [
          "aat:300008347"
        ],
        "id": 7397288,
        "name:xx": "San Miguel Reagui"
      }
    },
    {
      "geometry": {
        "type": "Point",
        "coordinates": [
          -95.816667,
          16.966667
        ]
      },
      "type": "Feature",
      "properties": {
        "hierarchy": [
          "tgn:7397289",
          "tgn:1000001",
          "tgn:7005591",
          "tgn:7005560",
          "tgn:7029392"
        ],
        "placetype": [
          "aat:300008347"
        ],
        "id": 7397289,
        "name:xx": "San Miguel Quetzaltepec"
      }
    }
  ]
}
