{
  "geometry": {
    "type": "Point",
    "coordinates": [
      -108.2833,
      40.9667
    ]
  },
  "type": "Feature",
  "properties": {
    "hierarchy": [
      "tgn:2547082",
      "tgn:1000001",
      "tgn:7012149",
      "tgn:7029392"
    ],
    "placetype": [
      "aat:300008761"
    ],
    "id": 2547082,
    "name:xx": "North Fork Powder Wash"
  }
}
