{
  "geometry": {
    "type": "Point",
    "coordinates": [
      -105.9833,
      33.4333
    ]
  },
  "type": "Feature",
  "properties": {
    "hierarchy": [
      "tgn:2417728",
      "tgn:1000001",
      "tgn:7012149",
      "tgn:2001442",
      "tgn:7007566",
      "tgn:7029392"
    ],
    "placetype": [
      "aat:300008701"
    ],
    "id": 2417728,
    "name:xx": "Jackson Draw"
  }
}
