{
  "type": "FeatureCollection",
  "features": [
    {
      "geometry": {
        "type": "Point",
        "coordinates": [
          -111.1833,
          43.7333
        ]
      },
      "type": "Feature",
      "properties": {
        "hierarchy": [
          "tgn:2719500",
          "tgn:1000001",
          "tgn:7012149",
          "tgn:2000492",
          "tgn:7007250",
          "tgn:7029392"
        ],
        "placetype": [
          "aat:300055621"
        ],
        "id": 2719500,
        "name:xx": "Three Forks"
      }
    },
    {
      "geometry": {
        "type": "Point",
        "coordinates": [
          -116.0167,
          42.0833
        ]
      },
      "type": "Feature",
      "properties": {
        "hierarchy": [
          "tgn:2719501",
          "tgn:1000001",
          "tgn:7012149",
          "tgn:2000488",
          "tgn:7007250",
          "tgn:7029392"
        ],
        "placetype": [
          "aat:300055621"
        ],
        "id": 2719501,
        "name:xx": "Three Forks"
      }
    },
    {
      "geometry": {
        "type": "Point",
        "coordinates": [
          -115.8333,
          42.1
        ]
      },
      "type": "Feature",
      "properties": {
        "hierarchy": [
          "tgn:2719502",
          "tgn:1000001",
          "tgn:7012149",
          "tgn:2000488",
          "tgn:7007250",
          "tgn:7029392"
        ],
        "placetype": [
          "aat:300008347"
        ],
        "id": 2719502,
        "name:xx": "Three Forks"
      }
    },
    {
      "geometry": {
        "type": "Point",
        "coordinates": [
          -115.1833,
          43.7
        ]
      },
      "type": "Feature",
      "properties": {
        "hierarchy": [
          "tgn:2719503",
          "tgn:1000001",
          "tgn:7012149",
          "tgn:2000471",
          "tgn:7007250",
          "tgn:7029392"
        ],
        "placetype": [
          "aat:300008699"
        ],
        "id": 2719503,
        "name:xx": "Three Forks"
      }
    },
    {
      "geometry": {
        "type": "Point",
        "coordinates": [
          -84.5667,
          37.6833
        ]
      },
      "type": "Feature",
      "properties": {
        "hierarchy": [
          "tgn:2719504",
          "tgn:1000001",
          "tgn:7012149",
          "tgn:2000791",
          "tgn:7007255",
          "tgn:7029392"
        ],
        "placetype": [
          "aat:300008347"
        ],
        "id": 2719504,
        "name:xx": "Three Forks"
      }
    },
    {
      "geometry": {
        "type": "Point",
        "coordinates": [
          -111.0833,
          47.2667
        ]
      },
      "type": "Feature",
      "properties": {
        "hierarchy": [
          "tgn:2719505",
          "tgn:1000001",
          "tgn:2001266",
          "tgn:7012149",
          "tgn:7007524",
          "tgn:7029392"
        ],
        "placetype": [
          "aat:300008347"
        ],
        "id": 2719505,
        "name:xx": "Three Forks"
      }
    },
    {
      "geometry": {
        "type": "Point",
        "coordinates": [
          -113.3,
          48.1
        ]
      },
      "type": "Feature",
      "properties": {
        "hierarchy": [
          "tgn:2719506",
          "tgn:1000001",
          "tgn:7012149",
          "tgn:2001274",
          "tgn:7007524",
          "tgn:7029392"
        ],
        "placetype": [
          "aat:300008347"
        ],
        "id": 2719506,
        "name:xx": "Three Forks"
      }
    },
    {
      "geometry": {
        "type": "Point",
        "coordinates": [
          -106.2833,
          48.45
        ]
      },
      "type": "Feature",
      "properties": {
        "hierarchy": [
          "tgn:2719507",
          "tgn:1000001",
          "tgn:7012149",
          "tgn:2001312",
          "tgn:7007524",
          "tgn:7029392"
        ],
        "placetype": [
          "aat:300055621"
        ],
        "id": 2719507,
        "name:xx": "Three Forks"
      }
    },
    {
      "geometry": {
        "type": "Point",
        "coordinates": [
          -104.7667,
          32.35
        ]
      },
      "type": "Feature",
      "properties": {
        "hierarchy": [
          "tgn:2719508",
          "tgn:1000001",
          "tgn:2001436",
          "tgn:7012149",
          "tgn:7007566",
          "tgn:7029392"
        ],
        "placetype": [
          "aat:300008347"
        ],
        "id": 2719508,
        "name:xx": "Three Forks"
      }
    },
    {
      "geometry": {
        "type": "Point",
        "coordinates": [
          -83.25,
          35.6333
        ]
      },
      "type": "Feature",
      "properties": {
        "hierarchy": [
          "tgn:2719509",
          "tgn:1000001",
          "tgn:7012149",
          "tgn:2001543",
          "tgn:7007709",
          "tgn:7029392"
        ],
        "placetype": [
          "aat:300008347"
        ],
        "id": 2719509,
        "name:xx": "Three Forks"
      }
    }
  ]
}
