{
  "geometry": {
    "type": "Point",
    "coordinates": [
      -80.1833,
      37.6167
    ]
  },
  "type": "Feature",
  "properties": {
    "hierarchy": [
      "tgn:2596160",
      "tgn:2002138",
      "tgn:1000001",
      "tgn:7012149",
      "tgn:7007919",
      "tgn:7029392"
    ],
    "placetype": [
      "aat:300008347"
    ],
    "id": 2596160,
    "name:xx": "Potts Creek"
  }
}
