{
  "type": "FeatureCollection",
  "features": [
    {
      "geometry": {
        "type": "Point",
        "coordinates": [
          -3.316667,
          54.183333
        ]
      },
      "type": "Feature",
      "properties": {
        "hierarchy": [
          "tgn:7452271",
          "tgn:7002445",
          "tgn:1000003",
          "tgn:7008117",
          "tgn:7008591",
          "tgn:7029392"
        ],
        "placetype": [
          "aat:300386846"
        ],
        "name:en": "Haverigg Point",
        "id": 7452271
      }
    },
    {
      "geometry": {
        "type": "Point",
        "coordinates": [
          -1.2,
          50.716667
        ]
      },
      "type": "Feature",
      "properties": {
        "hierarchy": [
          "tgn:7452275",
          "tgn:7002445",
          "tgn:1000003",
          "tgn:7011430",
          "tgn:7008591",
          "tgn:7029392"
        ],
        "placetype": [
          "aat:300008347"
        ],
        "name:en": "Haven Street",
        "id": 7452275
      }
    },
    {
      "geometry": {
        "type": "Point",
        "coordinates": [
          0.266667,
          53.1
        ]
      },
      "type": "Feature",
      "properties": {
        "hierarchy": [
          "tgn:7452276",
          "tgn:7002445",
          "tgn:1000003",
          "tgn:7008157",
          "tgn:7008591",
          "tgn:7029392"
        ],
        "placetype": [
          "aat:300007783"
        ],
        "name:en": "Havenhouse Station",
        "id": 7452276
      }
    },
    {
      "geometry": {
        "type": "Point",
        "coordinates": [
          0.85,
          51.566667
        ]
      },
      "type": "Feature",
      "properties": {
        "hierarchy": [
          "tgn:7452277",
          "tgn:7002445",
          "tgn:1000003",
          "tgn:7008131",
          "tgn:7008591",
          "tgn:7029392"
        ],
        "placetype": [
          "aat:300008791"
        ],
        "name:en": "Havengore Island",
        "id": 7452277
      }
    },
    {
      "geometry": {
        "type": "Point",
        "coordinates": [
          -3.05,
          58.75
        ]
      },
      "type": "Feature",
      "properties": {
        "hierarchy": [
          "tgn:7452278",
          "tgn:7002444",
          "tgn:1000003",
          "tgn:7009907",
          "tgn:7008591",
          "tgn:7029392"
        ],
        "placetype": [
          "aat:300132316"
        ],
        "name:en": "Haven, The",
        "id": 7452278
      }
    },
    {
      "geometry": {
        "type": "Point",
        "coordinates": [
          -1.083333,
          60.266667
        ]
      },
      "type": "Feature",
      "properties": {
        "hierarchy": [
          "tgn:7452279",
          "tgn:7002444",
          "tgn:1000003",
          "tgn:7029508",
          "tgn:7008591",
          "tgn:7029392"
        ],
        "placetype": [
          "aat:300011692"
        ],
        "name:en": "Hevda Skerry",
        "id": 7452279
      }
    }
  ]
}
