{
  "geometry": {
    "type": "Point",
    "coordinates": [
      6.9167,
      45.9667
    ]
  },
  "type": "Feature",
  "properties": {
    "hierarchy": [
      "tgn:1031841",
      "tgn:1000003",
      "tgn:1000070",
      "tgn:7002897",
      "tgn:7029392"
    ],
    "placetype": [
      "aat:300008347"
    ],
    "id": 1031841,
    "name:xx": "Argentière"
  }
}
