{
  "geometry": {
    "type": "Point",
    "coordinates": [
      -160.25,
      67.2833
    ]
  },
  "type": "Feature",
  "properties": {
    "hierarchy": [
      "tgn:2353848",
      "tgn:7006450",
      "tgn:1000001",
      "tgn:7012149",
      "tgn:2124014",
      "tgn:7029392"
    ],
    "placetype": [
      "aat:300008706"
    ],
    "id": 2353848,
    "name:xx": "Gold Run Creek"
  }
}
