{
  "geometry": {
    "type": "Point",
    "coordinates": [
      -93.3333,
      36.4833
    ]
  },
  "type": "Feature",
  "properties": {
    "hierarchy": [
      "tgn:2678206",
      "tgn:1000001",
      "tgn:7012149",
      "tgn:7029392"
    ],
    "placetype": [
      "aat:300008706"
    ],
    "id": 2678206,
    "name:xx": "South Fork Brush Creek"
  }
}
