{
  "geometry": {
    "type": "Point",
    "coordinates": [
      -85.1167,
      40.95
    ]
  },
  "type": "Feature",
  "properties": {
    "hierarchy": [
      "tgn:2674490",
      "tgn:1002143",
      "tgn:1000001",
      "tgn:7012149",
      "tgn:7007252",
      "tgn:7029392"
    ],
    "placetype": [
      "aat:300006075"
    ],
    "id": 2674490,
    "name:xx": "Snyder Ditch"
  }
}
