{
  "geometry": {
    "type": "Point",
    "coordinates": [
      -106.1667,
      33.85
    ]
  },
  "type": "Feature",
  "properties": {
    "hierarchy": [
      "tgn:2426739",
      "tgn:1000001",
      "tgn:7012149",
      "tgn:2001456",
      "tgn:7007566",
      "tgn:7029392"
    ],
    "placetype": [
      "aat:300000390"
    ],
    "id": 2426739,
    "name:xx": "Jones Magnatite"
  }
}
