{
  "geometry": {
    "type": "Point",
    "coordinates": [
      -85.8167,
      39.65
    ]
  },
  "type": "Feature",
  "properties": {
    "hierarchy": [
      "tgn:2373667",
      "tgn:1000001",
      "tgn:7012149",
      "tgn:1002886",
      "tgn:7007252",
      "tgn:7029392"
    ],
    "placetype": [
      "aat:300006075"
    ],
    "id": 2373667,
    "name:xx": "Hamilton Ditch"
  }
}
