{
  "geometry": {
    "type": "Point",
    "coordinates": [
      14.6667,
      46.9167
    ]
  },
  "type": "Feature",
  "properties": {
    "hierarchy": [
      "tgn:1109595",
      "tgn:7003024",
      "tgn:1000003",
      "tgn:1000062",
      "tgn:7029392"
    ],
    "placetype": [
      "aat:300008795"
    ],
    "id": 1109595,
    "name:xx": "Saulape"
  }
}
