{
  "type": "FeatureCollection",
  "features": [
    {
      "geometry": {
        "type": "Point",
        "coordinates": [
          -156.4,
          20.8833
        ]
      },
      "type": "Feature",
      "properties": {
        "hierarchy": [
          "tgn:2025252",
          "tgn:1002648",
          "tgn:1000001",
          "tgn:7019158",
          "tgn:7012149",
          "tgn:7007249",
          "tgn:7029392"
        ],
        "placetype": [
          "aat:300008347"
        ],
        "id": 2025252,
        "name:xx": "Spreckelsville"
      }
    },
    {
      "geometry": {
        "type": "Point",
        "coordinates": [
          -158.0333,
          21.6667
        ]
      },
      "type": "Feature",
      "properties": {
        "hierarchy": [
          "tgn:2025253",
          "tgn:1002483",
          "tgn:7019080",
          "tgn:1000001",
          "tgn:7012149",
          "tgn:7007249",
          "tgn:7029392"
        ],
        "placetype": [
          "aat:300008347"
        ],
        "id": 2025253,
        "name:xx": "Sunset Beach"
      }
    },
    {
      "geometry": {
        "type": "Point",
        "coordinates": [
          -156.8167,
          21.05
        ]
      },
      "type": "Feature",
      "properties": {
        "hierarchy": [
          "tgn:2025256",
          "tgn:1002648",
          "tgn:1000001",
          "tgn:1008191",
          "tgn:7012149",
          "tgn:7007249",
          "tgn:7029392"
        ],
        "placetype": [
          "aat:300008347",
          "aat:300387210"
        ],
        "id": 2025256,
        "name:xx": "Ualapue"
      }
    },
    {
      "geometry": {
        "type": "Point",
        "coordinates": [
          -156.2833,
          20.9
        ]
      },
      "type": "Feature",
      "properties": {
        "hierarchy": [
          "tgn:2025257",
          "tgn:1002648",
          "tgn:1000001",
          "tgn:7019158",
          "tgn:7012149",
          "tgn:7007249",
          "tgn:7029392"
        ],
        "placetype": [
          "aat:300008347",
          "aat:300387210"
        ],
        "id": 2025257,
        "name:xx": "Ulumalu"
      }
    },
    {
      "geometry": {
        "type": "Point",
        "coordinates": [
          -155.3833,
          19.9667
        ]
      },
      "type": "Feature",
      "properties": {
        "hierarchy": [
          "tgn:2025259",
          "tgn:7023902",
          "tgn:1000001",
          "tgn:7012149",
          "tgn:7007249",
          "tgn:7029392"
        ],
        "placetype": [
          "aat:300008347"
        ],
        "id": 2025259,
        "name:xx": "Umikoa"
      }
    }
  ]
}
