{
  "type": "FeatureCollection",
  "features": [
    {
      "geometry": {
        "type": "Point",
        "coordinates": [
          -76.55,
          37.2833
        ]
      },
      "type": "Feature",
      "properties": {
        "hierarchy": [
          "tgn:2226550",
          "tgn:1000001",
          "tgn:7012149",
          "tgn:1002411",
          "tgn:7007919",
          "tgn:7029392"
        ],
        "placetype": [
          "aat:300386853"
        ],
        "id": 2226550,
        "name:xx": "Catlett Islands"
      }
    },
    {
      "geometry": {
        "type": "Point",
        "coordinates": [
          -78.2167,
          38.9
        ]
      },
      "type": "Feature",
      "properties": {
        "hierarchy": [
          "tgn:2226551",
          "tgn:1000001",
          "tgn:7012149",
          "tgn:2002193",
          "tgn:7007919",
          "tgn:7029392"
        ],
        "placetype": [
          "aat:300008798"
        ],
        "id": 2226551,
        "name:xx": "Catlett Mountain"
      }
    },
    {
      "geometry": {
        "type": "Point",
        "coordinates": [
          -78.3,
          38.6
        ]
      },
      "type": "Feature",
      "properties": {
        "hierarchy": [
          "tgn:2226552",
          "tgn:1000001",
          "tgn:7012149",
          "tgn:2002184",
          "tgn:7007919",
          "tgn:7029392"
        ],
        "placetype": [
          "aat:300008798"
        ],
        "id": 2226552,
        "name:xx": "Catlett Mountain"
      }
    },
    {
      "geometry": {
        "type": "Point",
        "coordinates": [
          -78.2833,
          39
        ]
      },
      "type": "Feature",
      "properties": {
        "hierarchy": [
          "tgn:2226553",
          "tgn:1000001",
          "tgn:7012149",
          "tgn:7007919",
          "tgn:7029392"
        ],
        "placetype": [
          "aat:300008699"
        ],
        "id": 2226553,
        "name:xx": "Catlett Run"
      }
    },
    {
      "geometry": {
        "type": "Point",
        "coordinates": [
          -77.7,
          38.85
        ]
      },
      "type": "Feature",
      "properties": {
        "hierarchy": [
          "tgn:2226554",
          "tgn:1000001",
          "tgn:7012149",
          "tgn:7015778",
          "tgn:7007919",
          "tgn:7029392"
        ],
        "placetype": [
          "aat:300008699"
        ],
        "id": 2226554,
        "name:xx": "Catletts Branch"
      }
    },
    {
      "geometry": {
        "type": "Point",
        "coordinates": [
          -82.65,
          38.4
        ]
      },
      "type": "Feature",
      "properties": {
        "hierarchy": [
          "tgn:2226555",
          "tgn:1000001",
          "tgn:2000770",
          "tgn:7012149",
          "tgn:7007255",
          "tgn:7029392"
        ],
        "placetype": [
          "aat:300008706"
        ],
        "id": 2226555,
        "name:xx": "Catletts Creek"
      }
    },
    {
      "geometry": {
        "type": "Point",
        "coordinates": [
          -82.8167,
          32.5
        ]
      },
      "type": "Feature",
      "properties": {
        "hierarchy": [
          "tgn:2226556",
          "tgn:1000001",
          "tgn:7012149",
          "tgn:2000378",
          "tgn:7007248",
          "tgn:7029392"
        ],
        "placetype": [
          "aat:300008347"
        ],
        "id": 2226556,
        "name:xx": "Catlin"
      }
    },
    {
      "geometry": {
        "type": "Point",
        "coordinates": [
          -72.7667,
          41.4833
        ]
      },
      "type": "Feature",
      "properties": {
        "hierarchy": [
          "tgn:2226557",
          "tgn:1000001",
          "tgn:1002712",
          "tgn:7012149",
          "tgn:7007159",
          "tgn:7029392"
        ],
        "placetype": [
          "aat:300008699"
        ],
        "id": 2226557,
        "name:xx": "Catlin Brook"
      }
    },
    {
      "geometry": {
        "type": "Point",
        "coordinates": [
          -73.0833,
          41.7833
        ]
      },
      "type": "Feature",
      "properties": {
        "hierarchy": [
          "tgn:2226558",
          "tgn:1000001",
          "tgn:1002601",
          "tgn:7012149",
          "tgn:7007159",
          "tgn:7029392"
        ],
        "placetype": [
          "aat:300008699"
        ],
        "id": 2226558,
        "name:xx": "Catlin Brook"
      }
    },
    {
      "geometry": {
        "type": "Point",
        "coordinates": [
          -76.2,
          41.5
        ]
      },
      "type": "Feature",
      "properties": {
        "hierarchy": [
          "tgn:2226559",
          "tgn:1000001",
          "tgn:7012149",
          "tgn:1003041",
          "tgn:7007710",
          "tgn:7029392"
        ],
        "placetype": [
          "aat:300008699"
        ],
        "id": 2226559,
        "name:xx": "Catlin Brook"
      }
    }
  ]
}
