{
  "geometry": {
    "type": "Point",
    "coordinates": [
      -108.5333,
      46.6333
    ]
  },
  "type": "Feature",
  "properties": {
    "hierarchy": [
      "tgn:2285167",
      "tgn:1000001",
      "tgn:7012149",
      "tgn:2001292",
      "tgn:7007524",
      "tgn:7029392"
    ],
    "placetype": [
      "aat:300386845"
    ],
    "id": 2285167,
    "name:xx": "Devils Basin"
  }
}
