{
  "geometry": {
    "type": "Point",
    "coordinates": [
      -105.2667,
      38.85
    ]
  },
  "type": "Feature",
  "properties": {
    "hierarchy": [
      "tgn:2427418",
      "tgn:1000001",
      "tgn:7012149",
      "tgn:7007158",
      "tgn:2000251",
      "tgn:7029392"
    ],
    "placetype": [
      "aat:300006191"
    ],
    "id": 2427418,
    "name:xx": "Jordan Number 1 Reservoir"
  }
}
