{
  "geometry": {
    "type": "Point",
    "coordinates": [
      -80.75,
      37.8833
    ]
  },
  "type": "Feature",
  "properties": {
    "hierarchy": [
      "tgn:2656239",
      "tgn:1000001",
      "tgn:2002261",
      "tgn:7012149",
      "tgn:7013961",
      "tgn:7029392"
    ],
    "placetype": [
      "aat:300008347"
    ],
    "id": 2656239,
    "name:xx": "Shawver"
  }
}
