{
  "type": "FeatureCollection",
  "features": [
    {
      "geometry": {
        "type": "Point",
        "coordinates": [
          -101.633333,
          25.4
        ]
      },
      "type": "Feature",
      "properties": {
        "hierarchy": [
          "tgn:7374490",
          "tgn:1001853",
          "tgn:1000001",
          "tgn:7005560",
          "tgn:7029392"
        ],
        "placetype": [
          "aat:300266554",
          "aat:300008699"
        ],
        "id": 7374490,
        "name:xx": "La Boca, Arroyo de"
      }
    },
    {
      "geometry": {
        "type": "Point",
        "coordinates": [
          -107.4,
          29.783333
        ]
      },
      "type": "Feature",
      "properties": {
        "hierarchy": [
          "tgn:7374491",
          "tgn:7005581",
          "tgn:1000001",
          "tgn:7005560",
          "tgn:7029392"
        ],
        "placetype": [
          "aat:300008347"
        ],
        "id": 7374491,
        "name:xx": "La Boca"
      }
    },
    {
      "geometry": {
        "type": "Point",
        "coordinates": [
          -105.916667,
          27.6
        ]
      },
      "type": "Feature",
      "properties": {
        "hierarchy": [
          "tgn:7374492",
          "tgn:7005581",
          "tgn:1000001",
          "tgn:7005560",
          "tgn:7029392"
        ],
        "placetype": [
          "aat:300008347"
        ],
        "id": 7374492,
        "name:xx": "La Boca"
      }
    },
    {
      "geometry": {
        "type": "Point",
        "coordinates": [
          -99.933333,
          26.366667
        ]
      },
      "type": "Feature",
      "properties": {
        "hierarchy": [
          "tgn:7374493",
          "tgn:1000001",
          "tgn:7005589",
          "tgn:7005560",
          "tgn:7029392"
        ],
        "placetype": [
          "aat:300008347"
        ],
        "id": 7374493,
        "name:xx": "La Boca"
      }
    },
    {
      "geometry": {
        "type": "Point",
        "coordinates": [
          -100.083333,
          25.466667
        ]
      },
      "type": "Feature",
      "properties": {
        "hierarchy": [
          "tgn:7374494",
          "tgn:1000001",
          "tgn:7005589",
          "tgn:7005560",
          "tgn:7029392"
        ],
        "placetype": [
          "aat:300008347"
        ],
        "id": 7374494,
        "name:xx": "La Boca"
      }
    },
    {
      "geometry": {
        "type": "Point",
        "coordinates": [
          -107.416667,
          24.933333
        ]
      },
      "type": "Feature",
      "properties": {
        "hierarchy": [
          "tgn:7374495",
          "tgn:1000001",
          "tgn:7005595",
          "tgn:7005560",
          "tgn:7029392"
        ],
        "placetype": [
          "aat:300008347"
        ],
        "id": 7374495,
        "name:xx": "La Boca"
      }
    },
    {
      "geometry": {
        "type": "Point",
        "coordinates": [
          -107.684722,
          24.685833
        ]
      },
      "type": "Feature",
      "properties": {
        "hierarchy": [
          "tgn:7374496",
          "tgn:1000001",
          "tgn:7005595",
          "tgn:7005560",
          "tgn:7029392"
        ],
        "placetype": [
          "aat:300008347"
        ],
        "id": 7374496,
        "name:xx": "La Boca"
      }
    },
    {
      "geometry": {
        "type": "Point",
        "coordinates": [
          -107.416111,
          24.245833
        ]
      },
      "type": "Feature",
      "properties": {
        "hierarchy": [
          "tgn:7374497",
          "tgn:1000001",
          "tgn:7005595",
          "tgn:7005560",
          "tgn:7029392"
        ],
        "placetype": [
          "aat:300008347"
        ],
        "id": 7374497,
        "name:xx": "La Boca"
      }
    },
    {
      "geometry": {
        "type": "Point",
        "coordinates": [
          -100.733333,
          23.666667
        ]
      },
      "type": "Feature",
      "properties": {
        "hierarchy": [
          "tgn:7374499",
          "tgn:1000001",
          "tgn:7005594",
          "tgn:7005560",
          "tgn:7029392"
        ],
        "placetype": [
          "aat:300008347"
        ],
        "id": 7374499,
        "name:xx": "La Boca"
      }
    }
  ]
}
