{
  "type": "FeatureCollection",
  "features": [
    {
      "geometry": {
        "type": "Point",
        "coordinates": [
          -90.469,
          0.328
        ]
      },
      "type": "Feature",
      "properties": {
        "hierarchy": [
          "tgn:1008051",
          "tgn:1001259",
          "tgn:1009942",
          "tgn:7002563",
          "tgn:1000051",
          "tgn:1000002",
          "tgn:7029392"
        ],
        "placetype": [
          "aat:300008791"
        ],
        "id": 1008051,
        "name:xx": "Isla Marchena"
      }
    },
    {
      "geometry": {
        "type": "Point",
        "coordinates": [
          -81.7167,
          25.9333
        ]
      },
      "type": "Feature",
      "properties": {
        "hierarchy": [
          "tgn:1008053",
          "tgn:1000001",
          "tgn:1002289",
          "tgn:7012149",
          "tgn:7007240",
          "tgn:7029392"
        ],
        "placetype": [
          "aat:300008791"
        ],
        "id": 1008053,
        "name:xx": "Marco Island"
      }
    },
    {
      "geometry": {
        "type": "Point",
        "coordinates": [
          12.05,
          37.966667
        ]
      },
      "type": "Feature",
      "properties": {
        "hierarchy": [
          "tgn:1008056",
          "tgn:1000003",
          "tgn:7003122",
          "tgn:1001762",
          "tgn:1000080",
          "tgn:7029392"
        ],
        "placetype": [
          "aat:300008791"
        ],
        "id": 1008056,
        "name:xx": "Marettimo, Isola"
      }
    },
    {
      "geometry": {
        "type": "Point",
        "coordinates": [
          -74.5,
          9.0833
        ]
      },
      "type": "Feature",
      "properties": {
        "hierarchy": [
          "tgn:1008057",
          "tgn:1000529",
          "tgn:1000050",
          "tgn:1000002",
          "tgn:7029392"
        ],
        "placetype": [
          "aat:300008791"
        ],
        "id": 1008057,
        "name:xx": "Margarita, Isla"
      }
    },
    {
      "geometry": {
        "type": "Point",
        "coordinates": [
          -63.935,
          10.986
        ]
      },
      "type": "Feature",
      "properties": {
        "hierarchy": [
          "tgn:1008058",
          "tgn:1001914",
          "tgn:1000002",
          "tgn:1000059",
          "tgn:7029392"
        ],
        "placetype": [
          "aat:300008791"
        ],
        "id": 1008058,
        "name:xx": "Isla de Margarita"
      }
    }
  ]
}
