{
  "geometry": {
    "type": "Point",
    "coordinates": [
      -88.3667,
      42.9667
    ]
  },
  "type": "Feature",
  "properties": {
    "hierarchy": [
      "tgn:2544057",
      "tgn:1000001",
      "tgn:7012149",
      "tgn:1003002",
      "tgn:7007922",
      "tgn:7029392"
    ],
    "placetype": [
      "aat:300008706"
    ],
    "id": 2544057,
    "name:xx": "North Branch Genesee Creek"
  }
}
