{
  "geometry": {
    "type": "Point",
    "coordinates": [
      36.3667,
      32.3333
    ]
  },
  "type": "Feature",
  "properties": {
    "hierarchy": [
      "tgn:7017527",
      "tgn:7018394",
      "tgn:1000004",
      "tgn:1000121",
      "tgn:7029392"
    ],
    "placetype": [
      "aat:300008347",
      "aat:300167671"
    ],
    "id": 7017527,
    "name:xx": "Umm Al-Jimāl, Khirbat"
  }
}
