{
  "geometry": {
    "type": "Point",
    "coordinates": [
      -96.816667,
      17.05
    ]
  },
  "type": "Feature",
  "properties": {
    "hierarchy": [
      "tgn:7395357",
      "tgn:1000001",
      "tgn:7005591",
      "tgn:7005560",
      "tgn:7029392"
    ],
    "placetype": [
      "aat:300008347"
    ],
    "id": 7395357,
    "name:xx": "San Andrés Ixtlahuaca"
  }
}
