{
  "type": "FeatureCollection",
  "features": [
    {
      "geometry": {
        "type": "Point",
        "coordinates": [
          -98.6667,
          29.8
        ]
      },
      "type": "Feature",
      "properties": {
        "hierarchy": [
          "tgn:2198350",
          "tgn:1000001",
          "tgn:7012149",
          "tgn:2002015",
          "tgn:7007826",
          "tgn:7029392"
        ],
        "placetype": [
          "aat:300008706"
        ],
        "id": 2198350,
        "name:xx": "Browns Creek"
      }
    },
    {
      "geometry": {
        "type": "Point",
        "coordinates": [
          -98.35,
          31.1333
        ]
      },
      "type": "Feature",
      "properties": {
        "hierarchy": [
          "tgn:2198351",
          "tgn:1000001",
          "tgn:7012149",
          "tgn:2002026",
          "tgn:7007826",
          "tgn:7029392"
        ],
        "placetype": [
          "aat:300008706"
        ],
        "id": 2198351,
        "name:xx": "Browns Creek"
      }
    },
    {
      "geometry": {
        "type": "Point",
        "coordinates": [
          -97.8,
          31.3
        ]
      },
      "type": "Feature",
      "properties": {
        "hierarchy": [
          "tgn:2198352",
          "tgn:1000001",
          "tgn:7012149",
          "tgn:1002303",
          "tgn:7007826",
          "tgn:7029392"
        ],
        "placetype": [
          "aat:300008706"
        ],
        "id": 2198352,
        "name:xx": "Browns Creek"
      }
    },
    {
      "geometry": {
        "type": "Point",
        "coordinates": [
          -98.55,
          31.6
        ]
      },
      "type": "Feature",
      "properties": {
        "hierarchy": [
          "tgn:2198353",
          "tgn:1000001",
          "tgn:7012149",
          "tgn:2002042",
          "tgn:7007826",
          "tgn:7029392"
        ],
        "placetype": [
          "aat:300008706"
        ],
        "id": 2198353,
        "name:xx": "Browns Creek"
      }
    },
    {
      "geometry": {
        "type": "Point",
        "coordinates": [
          -94.55,
          31.7
        ]
      },
      "type": "Feature",
      "properties": {
        "hierarchy": [
          "tgn:2198354",
          "tgn:1000001",
          "tgn:7012149",
          "tgn:1002703",
          "tgn:7007826",
          "tgn:7029392"
        ],
        "placetype": [
          "aat:300008706"
        ],
        "id": 2198354,
        "name:xx": "Browns Creek"
      }
    },
    {
      "geometry": {
        "type": "Point",
        "coordinates": [
          -95.2833,
          30.8333
        ]
      },
      "type": "Feature",
      "properties": {
        "hierarchy": [
          "tgn:2198355",
          "tgn:1000001",
          "tgn:7012149",
          "tgn:1002860",
          "tgn:7007826",
          "tgn:7029392"
        ],
        "placetype": [
          "aat:300008706"
        ],
        "id": 2198355,
        "name:xx": "Browns Creek"
      }
    },
    {
      "geometry": {
        "type": "Point",
        "coordinates": [
          -96.1167,
          31.5833
        ]
      },
      "type": "Feature",
      "properties": {
        "hierarchy": [
          "tgn:2198356",
          "tgn:1000001",
          "tgn:7012149",
          "tgn:7007826",
          "tgn:7029392"
        ],
        "placetype": [
          "aat:300008706"
        ],
        "id": 2198356,
        "name:xx": "Browns Creek"
      }
    },
    {
      "geometry": {
        "type": "Point",
        "coordinates": [
          -110.75,
          37.9333
        ]
      },
      "type": "Feature",
      "properties": {
        "hierarchy": [
          "tgn:2198357",
          "tgn:1000001",
          "tgn:2002109",
          "tgn:7012149",
          "tgn:7007827",
          "tgn:7029392"
        ],
        "placetype": [
          "aat:300008706"
        ],
        "id": 2198357,
        "name:xx": "Browns Creek"
      }
    },
    {
      "geometry": {
        "type": "Point",
        "coordinates": [
          -79.3333,
          37.65
        ]
      },
      "type": "Feature",
      "properties": {
        "hierarchy": [
          "tgn:2198358",
          "tgn:2002140",
          "tgn:1000001",
          "tgn:7012149",
          "tgn:7007919",
          "tgn:7029392"
        ],
        "placetype": [
          "aat:300008706"
        ],
        "id": 2198358,
        "name:xx": "Browns Creek"
      }
    },
    {
      "geometry": {
        "type": "Point",
        "coordinates": [
          -76.45,
          37.75
        ]
      },
      "type": "Feature",
      "properties": {
        "hierarchy": [
          "tgn:2198359",
          "tgn:1000001",
          "tgn:7012149",
          "tgn:1002575",
          "tgn:7007919",
          "tgn:7029392"
        ],
        "placetype": [
          "aat:300008706"
        ],
        "id": 2198359,
        "name:xx": "Browns Creek"
      }
    }
  ]
}
