{
  "geometry": {
    "type": "Point",
    "coordinates": [
      116.2833,
      23.6333
    ]
  },
  "type": "Feature",
  "properties": {
    "hierarchy": [
      "tgn:1073080",
      "tgn:1000004",
      "tgn:7005232",
      "tgn:1000111",
      "tgn:7029392"
    ],
    "placetype": [
      "aat:300008347"
    ],
    "id": 1073080,
    "name:xx": "Xinheng"
  }
}
