{
  "geometry": {
    "type": "Point",
    "coordinates": [
      -80.9333,
      40.4833
    ]
  },
  "type": "Feature",
  "properties": {
    "hierarchy": [
      "tgn:2580624",
      "tgn:1000001",
      "tgn:1002239",
      "tgn:7012149",
      "tgn:7007706",
      "tgn:7029392"
    ],
    "placetype": [
      "aat:300266640"
    ],
    "id": 2580624,
    "name:xx": "Pigeon Ridge"
  }
}
