{
  "geometry": {
    "type": "Point",
    "coordinates": [
      -80.2167,
      39.95
    ]
  },
  "type": "Feature",
  "properties": {
    "hierarchy": [
      "tgn:2778214",
      "tgn:1000001",
      "tgn:7012149",
      "tgn:2001724",
      "tgn:7007710",
      "tgn:7029392"
    ],
    "placetype": [
      "aat:300008699"
    ],
    "id": 2778214,
    "name:xx": "Wisecarver Run"
  }
}
