{
  "geometry": {
    "type": "Point",
    "coordinates": [
      31.1167,
      30.1833
    ]
  },
  "type": "Feature",
  "properties": {
    "hierarchy": [
      "tgn:1135822",
      "tgn:7001242",
      "tgn:7016833",
      "tgn:7029392"
    ],
    "placetype": [
      "aat:300006075"
    ],
    "id": 1135822,
    "name:xx": "Ar-Rayyaāḥ at-Tawfīqī"
  }
}
