{
  "geometry": {
    "type": "Point",
    "coordinates": [
      -70.9833,
      -28.9667
    ]
  },
  "type": "Feature",
  "properties": {
    "hierarchy": [
      "tgn:1023446",
      "tgn:1001630",
      "tgn:1000049",
      "tgn:1000002",
      "tgn:7029392"
    ],
    "placetype": [
      "aat:300008347"
    ],
    "id": 1023446,
    "name:xx": "Domeyko"
  }
}
