{
  "geometry": {
    "type": "Point",
    "coordinates": [
      -85.7333,
      38.0833
    ]
  },
  "type": "Feature",
  "properties": {
    "hierarchy": [
      "tgn:2396434",
      "tgn:1000001",
      "tgn:7012149",
      "tgn:1002516",
      "tgn:7007255",
      "tgn:7029392"
    ],
    "placetype": [
      "aat:300008798"
    ],
    "id": 2396434,
    "name:xx": "Holsclaw Hill"
  }
}
