{
  "geometry": {
    "type": "Point",
    "coordinates": [
      -83.0667,
      35.5167
    ]
  },
  "type": "Feature",
  "properties": {
    "hierarchy": [
      "tgn:2437022",
      "tgn:1000001",
      "tgn:7012149",
      "tgn:2001503",
      "tgn:7007709",
      "tgn:7029392"
    ],
    "placetype": [
      "aat:300008798"
    ],
    "id": 2437022,
    "name:xx": "Killian Knob"
  }
}
