{
  "geometry": {
    "type": "Point",
    "coordinates": [
      77.151853,
      26.35709
    ]
  },
  "type": "Feature",
  "properties": {
    "hierarchy": [
      "tgn:7580871",
      "tgn:1000004",
      "tgn:7000198",
      "tgn:7016788",
      "tgn:7029392"
    ],
    "placetype": [
      "aat:300008347"
    ],
    "name:en": "Shāmpur",
    "id": 7580871
  }
}
