{
  "geometry": {
    "type": "Point",
    "coordinates": [
      -88.8333,
      42.9167
    ]
  },
  "type": "Feature",
  "properties": {
    "hierarchy": [
      "tgn:2121219",
      "tgn:1000001",
      "tgn:7012149",
      "tgn:1002522",
      "tgn:7007922",
      "tgn:7029392"
    ],
    "placetype": [
      "aat:300008347"
    ],
    "id": 2121219,
    "name:xx": "Fort Atkinson"
  }
}
