{
  "geometry": {
    "type": "Point",
    "coordinates": [
      -73.6833,
      40.95
    ]
  },
  "type": "Feature",
  "properties": {
    "hierarchy": [
      "tgn:2515871",
      "tgn:1000001",
      "tgn:7012149",
      "tgn:7014612",
      "tgn:7007568",
      "tgn:7029392"
    ],
    "placetype": [
      "aat:300008347"
    ],
    "id": 2515871,
    "name:xx": "Milton"
  }
}
