{
  "geometry": {
    "type": "Point",
    "coordinates": [
      120.3167,
      16.65
    ]
  },
  "type": "Feature",
  "properties": {
    "hierarchy": [
      "tgn:1084608",
      "tgn:1000004",
      "tgn:1009446",
      "tgn:1001419",
      "tgn:1000135",
      "tgn:7029392"
    ],
    "placetype": [
      "aat:300008347"
    ],
    "id": 1084608,
    "name:xx": "San Fernando"
  }
}
