{
  "geometry": {
    "type": "Point",
    "coordinates": [
      -44.9167,
      -13.9333
    ]
  },
  "type": "Feature",
  "properties": {
    "hierarchy": [
      "tgn:1128823",
      "tgn:1001834",
      "tgn:1000047",
      "tgn:7002455",
      "tgn:1000002",
      "tgn:7029392"
    ],
    "placetype": [
      "aat:300008707"
    ],
    "id": 1128823,
    "name:xx": "Pratudão"
  }
}
