{
  "geometry": {
    "type": "Point",
    "coordinates": [
      -110.9333,
      46.6333
    ]
  },
  "type": "Feature",
  "properties": {
    "hierarchy": [
      "tgn:2540215",
      "tgn:1000001",
      "tgn:7012149",
      "tgn:2001289",
      "tgn:7007524",
      "tgn:7029392"
    ],
    "placetype": [
      "aat:300006191"
    ],
    "id": 2540215,
    "name:xx": "Newlan Creek Reservoir"
  }
}
