{
  "geometry": {
    "type": "Point",
    "coordinates": [
      -107.25,
      28.65
    ]
  },
  "type": "Feature",
  "properties": {
    "hierarchy": [
      "tgn:7435985",
      "tgn:7005581",
      "tgn:1000001",
      "tgn:7005560",
      "tgn:7029392"
    ],
    "placetype": [
      "aat:300008347"
    ],
    "id": 7435985,
    "name:xx": "Téchore"
  }
}
