{
  "geometry": {
    "type": "Point",
    "coordinates": [
      -95.9333,
      32.8833
    ]
  },
  "type": "Feature",
  "properties": {
    "hierarchy": [
      "tgn:2553451",
      "tgn:1000001",
      "tgn:7012149",
      "tgn:1002816",
      "tgn:7007826",
      "tgn:7029392"
    ],
    "placetype": [
      "aat:300132316"
    ],
    "id": 2553451,
    "name:xx": "Oak Cove"
  }
}
