{
  "geometry": {
    "type": "Point",
    "coordinates": [
      -81.3833,
      41.6833
    ]
  },
  "type": "Feature",
  "properties": {
    "hierarchy": [
      "tgn:2137920",
      "tgn:1000001",
      "tgn:7012149",
      "tgn:1002570",
      "tgn:7007706",
      "tgn:7029392"
    ],
    "placetype": [
      "aat:300008347"
    ],
    "id": 2137920,
    "name:xx": "Arrowhead Beach"
  }
}
