{
  "type": "FeatureCollection",
  "features": [
    {
      "geometry": {
        "type": "Point",
        "coordinates": [
          32.866667,
          24.866667
        ]
      },
      "type": "Feature",
      "properties": {
        "hierarchy": [
          "tgn:7539610",
          "tgn:7001242",
          "tgn:7016833",
          "tgn:7000122",
          "tgn:7029392"
        ],
        "placetype": [
          "aat:300008347"
        ],
        "name:en": "Nag' Ammâr",
        "id": 7539610
      }
    },
    {
      "geometry": {
        "type": "Point",
        "coordinates": [
          30.616667,
          28.216667
        ]
      },
      "type": "Feature",
      "properties": {
        "hierarchy": [
          "tgn:7539611",
          "tgn:7001242",
          "tgn:7016833",
          "tgn:1001088",
          "tgn:7029392"
        ],
        "placetype": [
          "aat:300008347"
        ],
        "name:en": "Nag' 'Ali' Abd el-Hâdi",
        "id": 7539611
      }
    },
    {
      "geometry": {
        "type": "Point",
        "coordinates": [
          32.633333,
          25.65
        ]
      },
      "type": "Feature",
      "properties": {
        "hierarchy": [
          "tgn:7539612",
          "tgn:7001242",
          "tgn:7016833",
          "tgn:7000123",
          "tgn:7029392"
        ],
        "placetype": [
          "aat:300008347"
        ],
        "name:en": "Nag' Aḥmad Oṣman",
        "id": 7539612
      }
    },
    {
      "geometry": {
        "type": "Point",
        "coordinates": [
          32.816667,
          25.833333
        ]
      },
      "type": "Feature",
      "properties": {
        "hierarchy": [
          "tgn:7539613",
          "tgn:7001242",
          "tgn:7016833",
          "tgn:7000123",
          "tgn:7029392"
        ],
        "placetype": [
          "aat:300008347"
        ],
        "name:en": "Nag' Abu Zinâd",
        "id": 7539613
      }
    },
    {
      "geometry": {
        "type": "Point",
        "coordinates": [
          30.633333,
          28.133333
        ]
      },
      "type": "Feature",
      "properties": {
        "hierarchy": [
          "tgn:7539614",
          "tgn:7001242",
          "tgn:7016833",
          "tgn:1001088",
          "tgn:7029392"
        ],
        "placetype": [
          "aat:300008347"
        ],
        "name:en": "Nag' Abû Shinâf",
        "id": 7539614
      }
    },
    {
      "geometry": {
        "type": "Point",
        "coordinates": [
          32.833333,
          25.9
        ]
      },
      "type": "Feature",
      "properties": {
        "hierarchy": [
          "tgn:7539615",
          "tgn:7001242",
          "tgn:7016833",
          "tgn:7000123",
          "tgn:7029392"
        ],
        "placetype": [
          "aat:300008347"
        ],
        "name:en": "Nag' Abu Sandal",
        "id": 7539615
      }
    },
    {
      "geometry": {
        "type": "Point",
        "coordinates": [
          32.083333,
          26.1
        ]
      },
      "type": "Feature",
      "properties": {
        "hierarchy": [
          "tgn:7539616",
          "tgn:7001242",
          "tgn:7016833",
          "tgn:7000123",
          "tgn:7029392"
        ],
        "placetype": [
          "aat:300008347"
        ],
        "name:en": "Nag' Abu Salim",
        "id": 7539616
      }
    },
    {
      "geometry": {
        "type": "Point",
        "coordinates": [
          31.430265,
          26.734358
        ]
      },
      "type": "Feature",
      "properties": {
        "hierarchy": [
          "tgn:7539617",
          "tgn:7001242",
          "tgn:7016833",
          "tgn:7000124",
          "tgn:7029392"
        ],
        "placetype": [
          "aat:300008347"
        ],
        "name:en": "Naj' Abū Laylah",
        "id": 7539617
      }
    },
    {
      "geometry": {
        "type": "Point",
        "coordinates": [
          32.466667,
          25.5
        ]
      },
      "type": "Feature",
      "properties": {
        "hierarchy": [
          "tgn:7539618",
          "tgn:7001242",
          "tgn:7016833",
          "tgn:7000123",
          "tgn:7029392"
        ],
        "placetype": [
          "aat:300008347"
        ],
        "name:en": "Nag' Abu Hummuṣî",
        "id": 7539618
      }
    },
    {
      "geometry": {
        "type": "Point",
        "coordinates": [
          32.7,
          25.766667
        ]
      },
      "type": "Feature",
      "properties": {
        "hierarchy": [
          "tgn:7539619",
          "tgn:7001242",
          "tgn:7016833",
          "tgn:7000123",
          "tgn:7029392"
        ],
        "placetype": [
          "aat:300008347"
        ],
        "name:en": "Nag' Abu Hammâd",
        "id": 7539619
      }
    }
  ]
}
