{
  "geometry": {
    "type": "Point",
    "coordinates": [
      13.2167,
      52.5333
    ]
  },
  "type": "Feature",
  "properties": {
    "hierarchy": [
      "tgn:1130266",
      "tgn:1000003",
      "tgn:7000084",
      "tgn:7029392"
    ],
    "placetype": [
      "aat:300008707"
    ],
    "id": 1130266,
    "name:xx": "Spree"
  }
}
