{
  "type": "FeatureCollection",
  "features": [
    {
      "geometry": {
        "type": "Point",
        "coordinates": [
          -106.05,
          28.533333
        ]
      },
      "type": "Feature",
      "properties": {
        "hierarchy": [
          "tgn:7383190",
          "tgn:7005581",
          "tgn:1000001",
          "tgn:7005560",
          "tgn:7029392"
        ],
        "placetype": [
          "aat:300000241"
        ],
        "id": 7383190,
        "name:xx": "Rancho de Orizaba"
      }
    },
    {
      "geometry": {
        "type": "Point",
        "coordinates": [
          -98.65,
          24.433333
        ]
      },
      "type": "Feature",
      "properties": {
        "hierarchy": [
          "tgn:7383191",
          "tgn:1000001",
          "tgn:7005597",
          "tgn:7005560",
          "tgn:7029392"
        ],
        "placetype": [
          "aat:300000241"
        ],
        "id": 7383191,
        "name:xx": "Rancho Orizaba"
      }
    },
    {
      "geometry": {
        "type": "Point",
        "coordinates": [
          -97.1,
          18.833333
        ]
      },
      "type": "Feature",
      "properties": {
        "hierarchy": [
          "tgn:7383192",
          "tgn:1000001",
          "tgn:7005599",
          "tgn:7005560",
          "tgn:7029392"
        ],
        "placetype": [
          "aat:300007783"
        ],
        "id": 7383192,
        "name:xx": "Orizaba"
      }
    },
    {
      "geometry": {
        "type": "Point",
        "coordinates": [
          -90.316667,
          20.1
        ]
      },
      "type": "Feature",
      "properties": {
        "hierarchy": [
          "tgn:7383193",
          "tgn:7005578",
          "tgn:1000001",
          "tgn:7005560",
          "tgn:7029392"
        ],
        "placetype": [
          "aat:300008347"
        ],
        "id": 7383193,
        "name:xx": "Orizaba"
      }
    },
    {
      "geometry": {
        "type": "Point",
        "coordinates": [
          -92.116667,
          18.233333
        ]
      },
      "type": "Feature",
      "properties": {
        "hierarchy": [
          "tgn:7383195",
          "tgn:7005578",
          "tgn:1000001",
          "tgn:7005560",
          "tgn:7029392"
        ],
        "placetype": [
          "aat:300008347"
        ],
        "id": 7383195,
        "name:xx": "Orizaba"
      }
    },
    {
      "geometry": {
        "type": "Point",
        "coordinates": [
          -93.4,
          16.7
        ]
      },
      "type": "Feature",
      "properties": {
        "hierarchy": [
          "tgn:7383196",
          "tgn:7005580",
          "tgn:1000001",
          "tgn:7005560",
          "tgn:7029392"
        ],
        "placetype": [
          "aat:300008347"
        ],
        "id": 7383196,
        "name:xx": "Orizaba"
      }
    },
    {
      "geometry": {
        "type": "Point",
        "coordinates": [
          -94.083333,
          16.483333
        ]
      },
      "type": "Feature",
      "properties": {
        "hierarchy": [
          "tgn:7383197",
          "tgn:7005580",
          "tgn:1000001",
          "tgn:7005560",
          "tgn:7029392"
        ],
        "placetype": [
          "aat:300008347"
        ],
        "id": 7383197,
        "name:xx": "Orizaba"
      }
    },
    {
      "geometry": {
        "type": "Point",
        "coordinates": [
          -93.216667,
          16.25
        ]
      },
      "type": "Feature",
      "properties": {
        "hierarchy": [
          "tgn:7383198",
          "tgn:7005580",
          "tgn:1000001",
          "tgn:7005560",
          "tgn:7029392"
        ],
        "placetype": [
          "aat:300008347"
        ],
        "id": 7383198,
        "name:xx": "Orizaba"
      }
    },
    {
      "geometry": {
        "type": "Point",
        "coordinates": [
          -103.95,
          19.633333
        ]
      },
      "type": "Feature",
      "properties": {
        "hierarchy": [
          "tgn:7383199",
          "tgn:7005586",
          "tgn:1000001",
          "tgn:7005560",
          "tgn:7029392"
        ],
        "placetype": [
          "aat:300008777"
        ],
        "id": 7383199,
        "name:xx": "Oriz, Cerro"
      }
    }
  ]
}
