{
  "geometry": {
    "type": "Point",
    "coordinates": [
      -75.5667,
      44.5167
    ]
  },
  "type": "Feature",
  "properties": {
    "hierarchy": [
      "tgn:2518423",
      "tgn:1000001",
      "tgn:7012149",
      "tgn:7016021",
      "tgn:7007568",
      "tgn:7029392"
    ],
    "placetype": [
      "aat:300132316"
    ],
    "id": 2518423,
    "name:xx": "Mitchell Bay"
  }
}
