{
  "geometry": {
    "type": "Point",
    "coordinates": [
      -81.3167,
      40.7833
    ]
  },
  "type": "Feature",
  "properties": {
    "hierarchy": [
      "tgn:2243337",
      "tgn:1000001",
      "tgn:7012149",
      "tgn:1002917",
      "tgn:7007706",
      "tgn:7029392"
    ],
    "placetype": [
      "aat:300008347"
    ],
    "id": 2243337,
    "name:xx": "Clear View Heights"
  }
}
