{
  "geometry": {
    "type": "Point",
    "coordinates": [
      13.55,
      53.15
    ]
  },
  "type": "Feature",
  "properties": {
    "hierarchy": [
      "tgn:7206903",
      "tgn:7000096",
      "tgn:1000003",
      "tgn:7000084",
      "tgn:7029392"
    ],
    "placetype": [
      "aat:300386887"
    ],
    "id": 7206903,
    "name:xx": "Bürgerheide"
  }
}
