{
  "geometry": {
    "type": "Point",
    "coordinates": [
      -88.6833,
      32.5667
    ]
  },
  "type": "Feature",
  "properties": {
    "hierarchy": [
      "tgn:2143971",
      "tgn:1000001",
      "tgn:7012149",
      "tgn:2001123",
      "tgn:7007522",
      "tgn:7029392"
    ],
    "placetype": [
      "aat:300008706"
    ],
    "id": 2143971,
    "name:xx": "Baker Creek"
  }
}
