{
  "type": "FeatureCollection",
  "features": [
    {
      "geometry": {
        "type": "Point",
        "coordinates": [
          9.1,
          52.966667
        ]
      },
      "type": "Feature",
      "properties": {
        "hierarchy": [
          "tgn:7128481",
          "tgn:1000003",
          "tgn:7003676",
          "tgn:7000084",
          "tgn:7029392"
        ],
        "placetype": [
          "aat:300008347"
        ],
        "id": 7128481,
        "name:xx": "Nottorf"
      }
    },
    {
      "geometry": {
        "type": "Point",
        "coordinates": [
          9.8,
          52.95
        ]
      },
      "type": "Feature",
      "properties": {
        "hierarchy": [
          "tgn:7128482",
          "tgn:1000003",
          "tgn:7003676",
          "tgn:7000084",
          "tgn:7029392"
        ],
        "placetype": [
          "aat:300008347"
        ],
        "id": 7128482,
        "name:xx": "Nottorf"
      }
    },
    {
      "geometry": {
        "type": "Point",
        "coordinates": [
          8.566667,
          48.933333
        ]
      },
      "type": "Feature",
      "properties": {
        "hierarchy": [
          "tgn:7128484",
          "tgn:7003692",
          "tgn:1000003",
          "tgn:7000084",
          "tgn:7029392"
        ],
        "placetype": [
          "aat:300008347"
        ],
        "id": 7128484,
        "name:xx": "Nöttingen"
      }
    },
    {
      "geometry": {
        "type": "Point",
        "coordinates": [
          11.616667,
          48.7
        ]
      },
      "type": "Feature",
      "properties": {
        "hierarchy": [
          "tgn:7128485",
          "tgn:7003669",
          "tgn:1000003",
          "tgn:7000084",
          "tgn:7029392"
        ],
        "placetype": [
          "aat:300008347"
        ],
        "id": 7128485,
        "name:xx": "Nötting"
      }
    },
    {
      "geometry": {
        "type": "Point",
        "coordinates": [
          9.766667,
          54.616667
        ]
      },
      "type": "Feature",
      "properties": {
        "hierarchy": [
          "tgn:7128486",
          "tgn:1000003",
          "tgn:7003688",
          "tgn:7000084",
          "tgn:7029392"
        ],
        "placetype": [
          "aat:300008347"
        ],
        "id": 7128486,
        "name:xx": "Nottfeld"
      }
    },
    {
      "geometry": {
        "type": "Point",
        "coordinates": [
          12.116667,
          49.816667
        ]
      },
      "type": "Feature",
      "properties": {
        "hierarchy": [
          "tgn:7128487",
          "tgn:7003669",
          "tgn:1000003",
          "tgn:7000084",
          "tgn:7029392"
        ],
        "placetype": [
          "aat:300008347"
        ],
        "id": 7128487,
        "name:xx": "Nottersdorf"
      }
    },
    {
      "geometry": {
        "type": "Point",
        "coordinates": [
          12.366667,
          49.433333
        ]
      },
      "type": "Feature",
      "properties": {
        "hierarchy": [
          "tgn:7128488",
          "tgn:7003669",
          "tgn:1000003",
          "tgn:7000084",
          "tgn:7029392"
        ],
        "placetype": [
          "aat:300008347"
        ],
        "id": 7128488,
        "name:xx": "Nottersdorf"
      }
    },
    {
      "geometry": {
        "type": "Point",
        "coordinates": [
          10.516667,
          51.2
        ]
      },
      "type": "Feature",
      "properties": {
        "hierarchy": [
          "tgn:7128489",
          "tgn:1000003",
          "tgn:7003689",
          "tgn:7000084",
          "tgn:7029392"
        ],
        "placetype": [
          "aat:300008699"
        ],
        "id": 7128489,
        "name:xx": "Notter"
      }
    }
  ]
}
