{
  "geometry": {
    "type": "Point",
    "coordinates": [
      1.8667,
      46.1667
    ]
  },
  "type": "Feature",
  "properties": {
    "hierarchy": [
      "tgn:7009223",
      "tgn:1000003",
      "tgn:7001095",
      "tgn:1000070",
      "tgn:7029392"
    ],
    "placetype": [
      "aat:300008347"
    ],
    "id": 7009223,
    "name:xx": "Guéret"
  }
}
