{
  "type": "FeatureCollection",
  "features": [
    {
      "geometry": {
        "type": "Point",
        "coordinates": [
          -94.7333,
          34.3
        ]
      },
      "type": "Feature",
      "properties": {
        "hierarchy": [
          "tgn:2344540",
          "tgn:1000001",
          "tgn:7012149",
          "tgn:2001667",
          "tgn:7007707",
          "tgn:7029392"
        ],
        "placetype": [
          "aat:300008706"
        ],
        "id": 2344540,
        "name:xx": "Gar Creek"
      }
    },
    {
      "geometry": {
        "type": "Point",
        "coordinates": [
          -95.7833,
          35.3
        ]
      },
      "type": "Feature",
      "properties": {
        "hierarchy": [
          "tgn:2344541",
          "tgn:1000001",
          "tgn:7012149",
          "tgn:7021277",
          "tgn:7007707",
          "tgn:7029392"
        ],
        "placetype": [
          "aat:300008706"
        ],
        "id": 2344541,
        "name:xx": "Gar Creek"
      }
    },
    {
      "geometry": {
        "type": "Point",
        "coordinates": [
          -97.5667,
          35.8167
        ]
      },
      "type": "Feature",
      "properties": {
        "hierarchy": [
          "tgn:2344542",
          "tgn:1000001",
          "tgn:7012149",
          "tgn:2001664",
          "tgn:7007707",
          "tgn:7029392"
        ],
        "placetype": [
          "aat:300008706"
        ],
        "id": 2344542,
        "name:xx": "Gar Creek"
      }
    },
    {
      "geometry": {
        "type": "Point",
        "coordinates": [
          -96.5167,
          35.2667
        ]
      },
      "type": "Feature",
      "properties": {
        "hierarchy": [
          "tgn:2344543",
          "tgn:1000001",
          "tgn:7012149",
          "tgn:7007707",
          "tgn:7029392"
        ],
        "placetype": [
          "aat:300008706"
        ],
        "id": 2344543,
        "name:xx": "Gar Creek"
      }
    },
    {
      "geometry": {
        "type": "Point",
        "coordinates": [
          -95.55,
          35.8667
        ]
      },
      "type": "Feature",
      "properties": {
        "hierarchy": [
          "tgn:2344544",
          "tgn:1000001",
          "tgn:7012149",
          "tgn:2001695",
          "tgn:7007707",
          "tgn:7029392"
        ],
        "placetype": [
          "aat:300008706"
        ],
        "id": 2344544,
        "name:xx": "Gar Creek"
      }
    },
    {
      "geometry": {
        "type": "Point",
        "coordinates": [
          -80.8,
          34.5667
        ]
      },
      "type": "Feature",
      "properties": {
        "hierarchy": [
          "tgn:2344545",
          "tgn:1000001",
          "tgn:7012149",
          "tgn:2001753",
          "tgn:7007712",
          "tgn:7029392"
        ],
        "placetype": [
          "aat:300008706"
        ],
        "id": 2344545,
        "name:xx": "Gar Creek"
      }
    },
    {
      "geometry": {
        "type": "Point",
        "coordinates": [
          -87.9,
          41.0833
        ]
      },
      "type": "Feature",
      "properties": {
        "hierarchy": [
          "tgn:2344546",
          "tgn:1000001",
          "tgn:7012149",
          "tgn:1002532",
          "tgn:7007251",
          "tgn:7029392"
        ],
        "placetype": [
          "aat:300006075"
        ],
        "id": 2344546,
        "name:xx": "Gar Creek Ditch"
      }
    },
    {
      "geometry": {
        "type": "Point",
        "coordinates": [
          -83.65,
          37.3333
        ]
      },
      "type": "Feature",
      "properties": {
        "hierarchy": [
          "tgn:2344548",
          "tgn:1000001",
          "tgn:2000782",
          "tgn:7012149",
          "tgn:7007255",
          "tgn:7029392"
        ],
        "placetype": [
          "aat:300008699"
        ],
        "id": 2344548,
        "name:xx": "Gar Hole Branch"
      }
    },
    {
      "geometry": {
        "type": "Point",
        "coordinates": [
          -85.6667,
          35.8167
        ]
      },
      "type": "Feature",
      "properties": {
        "hierarchy": [
          "tgn:2344549",
          "tgn:1000001",
          "tgn:7012149",
          "tgn:2001929",
          "tgn:7007825",
          "tgn:7029392"
        ],
        "placetype": [
          "aat:300008791"
        ],
        "id": 2344549,
        "name:xx": "Gar Island"
      }
    }
  ]
}
