{
  "geometry": {
    "type": "Point",
    "coordinates": [
      -85.0667,
      33.05
    ]
  },
  "type": "Feature",
  "properties": {
    "hierarchy": [
      "tgn:2215314",
      "tgn:1000001",
      "tgn:7012149",
      "tgn:2000432",
      "tgn:7007248",
      "tgn:7029392"
    ],
    "placetype": [
      "aat:300006191"
    ],
    "id": 2215314,
    "name:xx": "Callaway Lake"
  }
}
