{
  "geometry": {
    "type": "Point",
    "coordinates": [
      -76.4167,
      40.9667
    ]
  },
  "type": "Feature",
  "properties": {
    "hierarchy": [
      "tgn:2193319",
      "tgn:1000001",
      "tgn:1002294",
      "tgn:7012149",
      "tgn:7007710",
      "tgn:7029392"
    ],
    "placetype": [
      "aat:300008347"
    ],
    "id": 2193319,
    "name:xx": "Breezy Acres"
  }
}
