{
  "geometry": {
    "type": "Point",
    "coordinates": [
      -104.0333,
      35.8167
    ]
  },
  "type": "Feature",
  "properties": {
    "hierarchy": [
      "tgn:2354913",
      "tgn:1000001",
      "tgn:7012149",
      "tgn:2001439",
      "tgn:7007566",
      "tgn:7029392"
    ],
    "placetype": [
      "aat:300008680"
    ],
    "id": 2354913,
    "name:xx": "Goodhue Lake"
  }
}
