{
  "type": "FeatureCollection",
  "features": [
    {
      "geometry": {
        "type": "Point",
        "coordinates": [
          -80.1167,
          33.1167
        ]
      },
      "type": "Feature",
      "properties": {
        "hierarchy": [
          "tgn:2643680",
          "tgn:2001732",
          "tgn:1000001",
          "tgn:7012149",
          "tgn:7007712",
          "tgn:7029392"
        ],
        "placetype": [
          "aat:300008699"
        ],
        "id": 2643680,
        "name:xx": "Sandy Run"
      }
    },
    {
      "geometry": {
        "type": "Point",
        "coordinates": [
          -81.0833,
          33.8
        ]
      },
      "type": "Feature",
      "properties": {
        "hierarchy": [
          "tgn:2643681",
          "tgn:1000001",
          "tgn:2001733",
          "tgn:7012149",
          "tgn:7007712",
          "tgn:7029392"
        ],
        "placetype": [
          "aat:300008699"
        ],
        "id": 2643681,
        "name:xx": "Sandy Run"
      }
    },
    {
      "geometry": {
        "type": "Point",
        "coordinates": [
          -80.1667,
          33.1167
        ]
      },
      "type": "Feature",
      "properties": {
        "hierarchy": [
          "tgn:2643682",
          "tgn:2001732",
          "tgn:1000001",
          "tgn:7012149",
          "tgn:7007712",
          "tgn:7029392"
        ],
        "placetype": [
          "aat:300008347"
        ],
        "id": 2643682,
        "name:xx": "Sandy Run"
      }
    },
    {
      "geometry": {
        "type": "Point",
        "coordinates": [
          -87,
          36.25
        ]
      },
      "type": "Feature",
      "properties": {
        "hierarchy": [
          "tgn:2643683",
          "tgn:1000001",
          "tgn:7012149",
          "tgn:2001847",
          "tgn:7007825",
          "tgn:7029392"
        ],
        "placetype": [
          "aat:300008699"
        ],
        "id": 2643683,
        "name:xx": "Sandy Run"
      }
    },
    {
      "geometry": {
        "type": "Point",
        "coordinates": [
          -77.3167,
          38.7667
        ]
      },
      "type": "Feature",
      "properties": {
        "hierarchy": [
          "tgn:2643684",
          "tgn:1000001",
          "tgn:7012149",
          "tgn:7014160",
          "tgn:7007919",
          "tgn:7029392"
        ],
        "placetype": [
          "aat:300008699"
        ],
        "id": 2643684,
        "name:xx": "Sandy Run"
      }
    },
    {
      "geometry": {
        "type": "Point",
        "coordinates": [
          -80.4,
          38.45
        ]
      },
      "type": "Feature",
      "properties": {
        "hierarchy": [
          "tgn:2643685",
          "tgn:1000001",
          "tgn:7012149",
          "tgn:2002300",
          "tgn:7013961",
          "tgn:7029392"
        ],
        "placetype": [
          "aat:300008699"
        ],
        "id": 2643685,
        "name:xx": "Sandy Run"
      }
    },
    {
      "geometry": {
        "type": "Point",
        "coordinates": [
          -81.5167,
          39.0167
        ]
      },
      "type": "Feature",
      "properties": {
        "hierarchy": [
          "tgn:2643686",
          "tgn:1000001",
          "tgn:7012149",
          "tgn:7013961",
          "tgn:7029392"
        ],
        "placetype": [
          "aat:300008699"
        ],
        "id": 2643686,
        "name:xx": "Sandy Run"
      }
    },
    {
      "geometry": {
        "type": "Point",
        "coordinates": [
          -91.5333,
          46.55
        ]
      },
      "type": "Feature",
      "properties": {
        "hierarchy": [
          "tgn:2643687",
          "tgn:1000001",
          "tgn:7012149",
          "tgn:7007922",
          "tgn:7029392"
        ],
        "placetype": [
          "aat:300008699"
        ],
        "id": 2643687,
        "name:xx": "Sandy Run"
      }
    },
    {
      "geometry": {
        "type": "Point",
        "coordinates": [
          -77.3667,
          34.7667
        ]
      },
      "type": "Feature",
      "properties": {
        "hierarchy": [
          "tgn:2643688",
          "tgn:1000001",
          "tgn:7012149",
          "tgn:2001524",
          "tgn:7007709",
          "tgn:7029392"
        ],
        "placetype": [
          "aat:300008699"
        ],
        "id": 2643688,
        "name:xx": "Sandy Run Branch"
      }
    },
    {
      "geometry": {
        "type": "Point",
        "coordinates": [
          -85.8,
          31.75
        ]
      },
      "type": "Feature",
      "properties": {
        "hierarchy": [
          "tgn:2643689",
          "tgn:7002659",
          "tgn:1000001",
          "tgn:7012149",
          "tgn:2000054",
          "tgn:7029392"
        ],
        "placetype": [
          "aat:300008706"
        ],
        "id": 2643689,
        "name:xx": "Sandy Run Creek"
      }
    }
  ]
}
