{
  "geometry": {
    "type": "Point",
    "coordinates": [
      -105.7167,
      44.05
    ]
  },
  "type": "Feature",
  "properties": {
    "hierarchy": [
      "tgn:2681517",
      "tgn:1000001",
      "tgn:2002367",
      "tgn:7012149",
      "tgn:7007923",
      "tgn:7029392"
    ],
    "placetype": [
      "aat:300008706"
    ],
    "id": 2681517,
    "name:xx": "South Prong Caballo Creek"
  }
}
