{
  "geometry": {
    "type": "Point",
    "coordinates": [
      -77.15,
      37.2333
    ]
  },
  "type": "Feature",
  "properties": {
    "hierarchy": [
      "tgn:2111895",
      "tgn:1000001",
      "tgn:7012149",
      "tgn:1002805",
      "tgn:7007919",
      "tgn:7029392"
    ],
    "placetype": [
      "aat:300008347"
    ],
    "id": 2111895,
    "name:xx": "Garysville"
  }
}
