{
  "geometry": {
    "type": "Point",
    "coordinates": [
      -116.0833,
      42.25
    ]
  },
  "type": "Feature",
  "properties": {
    "hierarchy": [
      "tgn:2571923",
      "tgn:1000001",
      "tgn:7012149",
      "tgn:2000488",
      "tgn:7007250",
      "tgn:7029392"
    ],
    "placetype": [
      "aat:300006191"
    ],
    "id": 2571923,
    "name:xx": "Payne Creek Reservoir"
  }
}
