{
  "type": "FeatureCollection",
  "features": [
    {
      "geometry": {
        "type": "Point",
        "coordinates": [
          113.5333,
          28.4167
        ]
      },
      "type": "Feature",
      "properties": {
        "hierarchy": [
          "tgn:1072770",
          "tgn:1000004",
          "tgn:7002079",
          "tgn:1000111",
          "tgn:7029392"
        ],
        "placetype": [
          "aat:300008347"
        ],
        "id": 1072770,
        "name:xx": "Xianggongshi"
      }
    },
    {
      "geometry": {
        "type": "Point",
        "coordinates": [
          118.3167,
          39.8
        ]
      },
      "type": "Feature",
      "properties": {
        "hierarchy": [
          "tgn:1072771",
          "tgn:1000004",
          "tgn:7002077",
          "tgn:1000111",
          "tgn:7029392"
        ],
        "placetype": [
          "aat:300008347"
        ],
        "id": 1072771,
        "name:xx": "Xianggongzhuang"
      }
    },
    {
      "geometry": {
        "type": "Point",
        "coordinates": [
          117.0167,
          39.7833
        ]
      },
      "type": "Feature",
      "properties": {
        "hierarchy": [
          "tgn:1072772",
          "tgn:1000004",
          "tgn:7002077",
          "tgn:1000111",
          "tgn:7029392"
        ],
        "placetype": [
          "aat:300008347"
        ],
        "id": 1072772,
        "name:xx": "Xianghe"
      }
    },
    {
      "geometry": {
        "type": "Point",
        "coordinates": [
          113.4333,
          33.1
        ]
      },
      "type": "Feature",
      "properties": {
        "hierarchy": [
          "tgn:1072773",
          "tgn:1000004",
          "tgn:7016672",
          "tgn:1000111",
          "tgn:7029392"
        ],
        "placetype": [
          "aat:300008347"
        ],
        "id": 1072773,
        "name:xx": "Xiangheguan"
      }
    },
    {
      "geometry": {
        "type": "Point",
        "coordinates": [
          121.7167,
          31.5167
        ]
      },
      "type": "Feature",
      "properties": {
        "hierarchy": [
          "tgn:1072774",
          "tgn:1000004",
          "tgn:1000958",
          "tgn:1000111",
          "tgn:7029392"
        ],
        "placetype": [
          "aat:300008347"
        ],
        "id": 1072774,
        "name:xx": "Xianghuazhen"
      }
    },
    {
      "geometry": {
        "type": "Point",
        "coordinates": [
          104.3,
          30.1333
        ]
      },
      "type": "Feature",
      "properties": {
        "hierarchy": [
          "tgn:1072776",
          "tgn:1000004",
          "tgn:7002087",
          "tgn:1000111",
          "tgn:7029392"
        ],
        "placetype": [
          "aat:300008347"
        ],
        "id": 1072776,
        "name:xx": "Xiangjiachang"
      }
    },
    {
      "geometry": {
        "type": "Point",
        "coordinates": [
          110.85,
          36
        ]
      },
      "type": "Feature",
      "properties": {
        "hierarchy": [
          "tgn:1072777",
          "tgn:1000004",
          "tgn:7002086",
          "tgn:1000111",
          "tgn:7029392"
        ],
        "placetype": [
          "aat:300008347"
        ],
        "id": 1072777,
        "name:xx": "Xiangning"
      }
    },
    {
      "geometry": {
        "type": "Point",
        "coordinates": [
          97.8667,
          36
        ]
      },
      "type": "Feature",
      "properties": {
        "hierarchy": [
          "tgn:1072778",
          "tgn:1000004",
          "tgn:7002088",
          "tgn:1000111",
          "tgn:7029392"
        ],
        "placetype": [
          "aat:300008347"
        ],
        "id": 1072778,
        "name:xx": "Xiangride"
      }
    },
    {
      "geometry": {
        "type": "Point",
        "coordinates": [
          121.85,
          29.4833
        ]
      },
      "type": "Feature",
      "properties": {
        "hierarchy": [
          "tgn:1072779",
          "tgn:1000004",
          "tgn:7002076",
          "tgn:1000111",
          "tgn:7029392"
        ],
        "placetype": [
          "aat:300008347"
        ],
        "id": 1072779,
        "name:xx": "Xiangshan"
      }
    }
  ]
}
