{
  "geometry": {
    "type": "Point",
    "coordinates": [
      36.5833,
      33.0167
    ]
  },
  "type": "Feature",
  "properties": {
    "hierarchy": [
      "tgn:1085228",
      "tgn:1002066",
      "tgn:1000004",
      "tgn:1000140",
      "tgn:7029392"
    ],
    "placetype": [
      "aat:300008347"
    ],
    "id": 1085228,
    "name:xx": "Ruḍaymah Lioûa"
  }
}
