{
  "geometry": {
    "type": "Point",
    "coordinates": [
      76.29306,
      17.457577
    ]
  },
  "type": "Feature",
  "properties": {
    "hierarchy": [
      "tgn:7554834",
      "tgn:1000004",
      "tgn:7000198",
      "tgn:1001895",
      "tgn:7029392"
    ],
    "placetype": [
      "aat:300008347"
    ],
    "name:en": "Maindargi",
    "id": 7554834
  }
}
