{
  "geometry": {
    "type": "Point",
    "coordinates": [
      -73.5833,
      43.1833
    ]
  },
  "type": "Feature",
  "properties": {
    "hierarchy": [
      "tgn:2718410",
      "tgn:1000001",
      "tgn:7012149",
      "tgn:1002871",
      "tgn:7007568",
      "tgn:7029392"
    ],
    "placetype": [
      "aat:300008791"
    ],
    "id": 2718410,
    "name:xx": "Thompson Island"
  }
}
