{
  "geometry": {
    "type": "Point",
    "coordinates": [
      -99.65,
      26.033333
    ]
  },
  "type": "Feature",
  "properties": {
    "hierarchy": [
      "tgn:7354324",
      "tgn:1000001",
      "tgn:7005589",
      "tgn:7005560",
      "tgn:7029392"
    ],
    "placetype": [
      "aat:300008347"
    ],
    "id": 7354324,
    "name:xx": "Cañada Honda"
  }
}
