{
  "geometry": {
    "type": "Point",
    "coordinates": [
      -89.0333,
      38.9167
    ]
  },
  "type": "Feature",
  "properties": {
    "hierarchy": [
      "tgn:2557122",
      "tgn:1000001",
      "tgn:1002369",
      "tgn:7012149",
      "tgn:7007251",
      "tgn:7029392"
    ],
    "placetype": [
      "aat:300008706"
    ],
    "id": 2557122,
    "name:xx": "Old Hickory Creek"
  }
}
