{
  "geometry": {
    "type": "Point",
    "coordinates": [
      -119.9333,
      37.8167
    ]
  },
  "type": "Feature",
  "properties": {
    "hierarchy": [
      "tgn:2646007",
      "tgn:1000001",
      "tgn:7012149",
      "tgn:7007157",
      "tgn:1002957",
      "tgn:7029392"
    ],
    "placetype": [
      "aat:300008798"
    ],
    "id": 2646007,
    "name:xx": "Sawmill Mountain"
  }
}
