{
  "geometry": {
    "type": "Point",
    "coordinates": [
      -123.2333,
      47.4333
    ]
  },
  "type": "Feature",
  "properties": {
    "hierarchy": [
      "tgn:2272630",
      "tgn:1000001",
      "tgn:7012149",
      "tgn:1002645",
      "tgn:7007920",
      "tgn:7029392"
    ],
    "placetype": [
      "aat:300008798"
    ],
    "id": 2272630,
    "name:xx": "Cushman Hill"
  }
}
