{
  "geometry": {
    "type": "Point",
    "coordinates": [
      102.75,
      16.05
    ]
  },
  "type": "Feature",
  "properties": {
    "hierarchy": [
      "tgn:1085470",
      "tgn:7005193",
      "tgn:7000922",
      "tgn:1000004",
      "tgn:1000142",
      "tgn:7029392"
    ],
    "placetype": [
      "aat:300008347"
    ],
    "id": 1085470,
    "name:xx": "Ban Phai"
  }
}
