{
  "geometry": {
    "type": "Point",
    "coordinates": [
      -90.3333,
      46.25
    ]
  },
  "type": "Feature",
  "properties": {
    "hierarchy": [
      "tgn:2587553",
      "tgn:1000001",
      "tgn:7012149",
      "tgn:2002327",
      "tgn:7007922",
      "tgn:7029392"
    ],
    "placetype": [
      "aat:300008699"
    ],
    "id": 2587553,
    "name:xx": "Pleasant Lake Outlet"
  }
}
