{
  "geometry": {
    "type": "Point",
    "coordinates": [
      15.5667,
      -14.3333
    ]
  },
  "type": "Feature",
  "properties": {
    "hierarchy": [
      "tgn:1123240",
      "tgn:7001242",
      "tgn:1000149",
      "tgn:1000867",
      "tgn:7029392"
    ],
    "placetype": [
      "aat:300008707"
    ],
    "id": 1123240,
    "name:xx": "Cusso"
  }
}
