{
  "geometry": {
    "type": "Point",
    "coordinates": [
      116.25,
      50.5333
    ]
  },
  "type": "Feature",
  "properties": {
    "hierarchy": [
      "tgn:1051630",
      "tgn:1003351",
      "tgn:1000004",
      "tgn:7018214",
      "tgn:7002435",
      "tgn:7029392"
    ],
    "placetype": [
      "aat:300008347"
    ],
    "id": 1051630,
    "name:xx": "Sherlovaya Gora"
  }
}
