{
  "geometry": {
    "type": "Point",
    "coordinates": [
      -118.9833,
      37.25
    ]
  },
  "type": "Feature",
  "properties": {
    "hierarchy": [
      "tgn:2302286",
      "tgn:1000001",
      "tgn:7012149",
      "tgn:1002392",
      "tgn:7007157",
      "tgn:7029392"
    ],
    "placetype": [
      "aat:300008680"
    ],
    "id": 2302286,
    "name:xx": "Dutch Lake"
  }
}
