{
  "geometry": {
    "type": "Point",
    "coordinates": [
      -76.7833,
      34.8833
    ]
  },
  "type": "Feature",
  "properties": {
    "hierarchy": [
      "tgn:2672840",
      "tgn:1000001",
      "tgn:7012149",
      "tgn:2001486",
      "tgn:7007709",
      "tgn:7029392"
    ],
    "placetype": [
      "aat:300008699"
    ],
    "id": 2672840,
    "name:xx": "Snake Branch"
  }
}
