{
  "geometry": {
    "type": "Point",
    "coordinates": [
      -111.1333,
      31.5833
    ]
  },
  "type": "Feature",
  "properties": {
    "hierarchy": [
      "tgn:2411485",
      "tgn:1000001",
      "tgn:7006451",
      "tgn:7012149",
      "tgn:2000102",
      "tgn:7029392"
    ],
    "placetype": [
      "aat:300006191"
    ],
    "id": 2411485,
    "name:xx": "Indian Hills Tank"
  }
}
