{
  "geometry": {
    "type": "Point",
    "coordinates": [
      12.4833,
      46.1167
    ]
  },
  "type": "Feature",
  "properties": {
    "hierarchy": [
      "tgn:1104178",
      "tgn:1000003",
      "tgn:1000080",
      "tgn:7029392"
    ],
    "placetype": [
      "aat:300008795"
    ],
    "id": 1104178,
    "name:it": "Cavallo, Monte"
  }
}
