{
  "geometry": {
    "type": "Point",
    "coordinates": [
      -104.9333,
      39.6667
    ]
  },
  "type": "Feature",
  "properties": {
    "hierarchy": [
      "tgn:2379291",
      "tgn:1000001",
      "tgn:7012149",
      "tgn:2000207",
      "tgn:7007158",
      "tgn:7029392"
    ],
    "placetype": [
      "aat:300008761"
    ],
    "id": 2379291,
    "name:xx": "Harvard Gulch"
  }
}
