{
  "geometry": {
    "type": "Point",
    "coordinates": [
      88.554,
      23.527
    ]
  },
  "type": "Feature",
  "properties": {
    "hierarchy": [
      "tgn:1074923",
      "tgn:1000004",
      "tgn:7000198",
      "tgn:1001977",
      "tgn:7029392"
    ],
    "placetype": [
      "aat:300008347"
    ],
    "name:en": "Chāprā",
    "id": 1074923
  }
}
