{
  "geometry": {
    "type": "Point",
    "coordinates": [
      79.466092,
      26.48267
    ]
  },
  "type": "Feature",
  "properties": {
    "hierarchy": [
      "tgn:7565220",
      "tgn:1000004",
      "tgn:7000198",
      "tgn:7016722",
      "tgn:7029392"
    ],
    "placetype": [
      "aat:300008347"
    ],
    "name:en": "Chirhūli",
    "id": 7565220
  }
}
