{
  "geometry": {
    "type": "Point",
    "coordinates": [
      -3.4167,
      12.75
    ]
  },
  "type": "Feature",
  "properties": {
    "hierarchy": [
      "tgn:1130206",
      "tgn:7001242",
      "tgn:7029392"
    ],
    "placetype": [
      "aat:300008707"
    ],
    "id": 1130206,
    "name:xx": "Sourou"
  }
}
