{
  "geometry": {
    "type": "Point",
    "coordinates": [
      -121.0167,
      40.2833
    ]
  },
  "type": "Feature",
  "properties": {
    "hierarchy": [
      "tgn:2527957",
      "tgn:1000001",
      "tgn:7012149",
      "tgn:7007157",
      "tgn:2000184",
      "tgn:7029392"
    ],
    "placetype": [
      "aat:300006191"
    ],
    "id": 2527957,
    "name:xx": "Mountain Meadows Reservoir"
  }
}
