{
  "geometry": {
    "type": "Point",
    "coordinates": [
      -120.6667,
      39.6833
    ]
  },
  "type": "Feature",
  "properties": {
    "hierarchy": [
      "tgn:2480629",
      "tgn:1000001",
      "tgn:7012149",
      "tgn:7007157",
      "tgn:2000187",
      "tgn:7029392"
    ],
    "placetype": [
      "aat:300386845"
    ],
    "id": 2480629,
    "name:xx": "Lakes Basin"
  }
}
