{
  "geometry": {
    "type": "Point",
    "coordinates": [
      -111.3333,
      34.4167
    ]
  },
  "type": "Feature",
  "properties": {
    "hierarchy": [
      "tgn:2755269",
      "tgn:1000001",
      "tgn:7006451",
      "tgn:7012149",
      "tgn:7029392"
    ],
    "placetype": [
      "aat:300008706"
    ],
    "id": 2755269,
    "name:xx": "Webber Creek"
  }
}
