{
  "type": "FeatureCollection",
  "features": [
    {
      "geometry": {
        "type": "Point",
        "coordinates": [
          -84.9833,
          38.8667
        ]
      },
      "type": "Feature",
      "properties": {
        "hierarchy": [
          "tgn:2031675",
          "tgn:1000001",
          "tgn:7012149",
          "tgn:1002938",
          "tgn:7007252",
          "tgn:7029392"
        ],
        "placetype": [
          "aat:300008347"
        ],
        "id": 2031675,
        "name:xx": "East Enterprise"
      }
    },
    {
      "geometry": {
        "type": "Point",
        "coordinates": [
          -87.2833,
          39.4833
        ]
      },
      "type": "Feature",
      "properties": {
        "hierarchy": [
          "tgn:2031677",
          "tgn:1000001",
          "tgn:7012149",
          "tgn:2000559",
          "tgn:7007252",
          "tgn:7029392"
        ],
        "placetype": [
          "aat:300008347"
        ],
        "id": 2031677,
        "name:xx": "East Glenn"
      }
    },
    {
      "geometry": {
        "type": "Point",
        "coordinates": [
          -86.75,
          40.7333
        ]
      },
      "type": "Feature",
      "properties": {
        "hierarchy": [
          "tgn:2031678",
          "tgn:1000001",
          "tgn:7012149",
          "tgn:1003021",
          "tgn:7007252",
          "tgn:7029392"
        ],
        "placetype": [
          "aat:300008347"
        ],
        "id": 2031678,
        "name:xx": "East Monticello"
      }
    },
    {
      "geometry": {
        "type": "Point",
        "coordinates": [
          -87.7333,
          38.3833
        ]
      },
      "type": "Feature",
      "properties": {
        "hierarchy": [
          "tgn:2031679",
          "tgn:1000001",
          "tgn:7012149",
          "tgn:2000543",
          "tgn:7007252",
          "tgn:7029392"
        ],
        "placetype": [
          "aat:300008347",
          "aat:300387210"
        ],
        "id": 2031679,
        "name:xx": "East Mount Carmel"
      }
    }
  ]
}
