{
  "type": "FeatureCollection",
  "features": [
    {
      "geometry": {
        "type": "Point",
        "coordinates": [
          32.7,
          25.15
        ]
      },
      "type": "Feature",
      "properties": {
        "hierarchy": [
          "tgn:7524830",
          "tgn:7001242",
          "tgn:7016833",
          "tgn:7000122",
          "tgn:7029392"
        ],
        "placetype": [
          "aat:300008777"
        ],
        "name:en": "'Ayyāţ, Jabal al",
        "id": 7524830
      }
    },
    {
      "geometry": {
        "type": "Point",
        "coordinates": [
          29.783611,
          31.146944
        ]
      },
      "type": "Feature",
      "properties": {
        "hierarchy": [
          "tgn:7524831",
          "tgn:7001242",
          "tgn:7016833",
          "tgn:1001079",
          "tgn:7029392"
        ],
        "placetype": [
          "aat:300006909"
        ],
        "name:en": "Ţābiyat al 'Ayyānah",
        "id": 7524831
      }
    },
    {
      "geometry": {
        "type": "Point",
        "coordinates": [
          34.027753,
          28.91866
        ]
      },
      "type": "Feature",
      "properties": {
        "hierarchy": [
          "tgn:7524832",
          "tgn:7001242",
          "tgn:7016833",
          "tgn:7001336",
          "tgn:7029392"
        ],
        "placetype": [
          "aat:300006207"
        ],
        "name:en": "Bi'r 'Ayyānah",
        "id": 7524832
      }
    },
    {
      "geometry": {
        "type": "Point",
        "coordinates": [
          31.216667,
          28.8
        ]
      },
      "type": "Feature",
      "properties": {
        "hierarchy": [
          "tgn:7524833",
          "tgn:7001242",
          "tgn:7001311",
          "tgn:7016833",
          "tgn:7029392"
        ],
        "placetype": [
          "aat:300379998"
        ],
        "name:en": "'Ayyān, Wādī al",
        "id": 7524833
      }
    },
    {
      "geometry": {
        "type": "Point",
        "coordinates": [
          34.496468,
          23.111434
        ]
      },
      "type": "Feature",
      "properties": {
        "hierarchy": [
          "tgn:7524834",
          "tgn:7001242",
          "tgn:7001311",
          "tgn:7016833",
          "tgn:7029392"
        ],
        "placetype": [
          "aat:300008795"
        ],
        "name:en": "Aytūs, Jabal",
        "id": 7524834
      }
    },
    {
      "geometry": {
        "type": "Point",
        "coordinates": [
          29.276179,
          30.765031
        ]
      },
      "type": "Feature",
      "properties": {
        "hierarchy": [
          "tgn:7524835",
          "tgn:7001242",
          "tgn:7016833",
          "tgn:1001418",
          "tgn:7029392"
        ],
        "placetype": [
          "aat:300008777"
        ],
        "name:en": "'Aysh, Khashm al",
        "id": 7524835
      }
    },
    {
      "geometry": {
        "type": "Point",
        "coordinates": [
          33.866667,
          30.885278
        ]
      },
      "type": "Feature",
      "properties": {
        "hierarchy": [
          "tgn:7524836",
          "tgn:7001242",
          "tgn:7016833",
          "tgn:7001335",
          "tgn:7029392"
        ],
        "placetype": [
          "aat:300008750"
        ],
        "id": 7524836,
        "name:xx": "'Ayr, Kathīb al"
      }
    },
    {
      "geometry": {
        "type": "Point",
        "coordinates": [
          35.042448,
          24.047533
        ]
      },
      "type": "Feature",
      "properties": {
        "hierarchy": [
          "tgn:7524837",
          "tgn:7001242",
          "tgn:7001311",
          "tgn:7016833",
          "tgn:7029392"
        ],
        "placetype": [
          "aat:300008795"
        ],
        "name:en": "Ayqāt, Jabal",
        "id": 7524837
      }
    },
    {
      "geometry": {
        "type": "Point",
        "coordinates": [
          32.335965,
          29.589017
        ]
      },
      "type": "Feature",
      "properties": {
        "hierarchy": [
          "tgn:7524838",
          "tgn:7001242",
          "tgn:7016833",
          "tgn:1001110",
          "tgn:7029392"
        ],
        "placetype": [
          "aat:300006207"
        ],
        "name:en": "Al 'Ayn as Sukhnah",
        "id": 7524838
      }
    },
    {
      "geometry": {
        "type": "Point",
        "coordinates": [
          31.319113,
          30.130998
        ]
      },
      "type": "Feature",
      "properties": {
        "hierarchy": [
          "tgn:7524839",
          "tgn:7001242",
          "tgn:7016833",
          "tgn:1001091",
          "tgn:7029392"
        ],
        "placetype": [
          "aat:300007780"
        ],
        "id": 7524839,
        "name:xx": "'Ayn Shams"
      }
    }
  ]
}
