{
  "geometry": {
    "type": "Point",
    "coordinates": [
      -87.0833,
      37.3667
    ]
  },
  "type": "Feature",
  "properties": {
    "hierarchy": [
      "tgn:2670417",
      "tgn:1000001",
      "tgn:7012149",
      "tgn:2000834",
      "tgn:7007255",
      "tgn:7029392"
    ],
    "placetype": [
      "aat:300008347"
    ],
    "id": 2670417,
    "name:xx": "Smallhous"
  }
}
