{
  "type": "FeatureCollection",
  "features": [
    {
      "geometry": {
        "type": "Point",
        "coordinates": [
          -0.45,
          53.7
        ]
      },
      "type": "Feature",
      "properties": {
        "hierarchy": [
          "tgn:1101000",
          "tgn:7002445",
          "tgn:1000003",
          "tgn:7019057",
          "tgn:7008591",
          "tgn:7029392"
        ],
        "placetype": [
          "aat:300007836"
        ],
        "id": 1101000,
        "name:xx": "Humber Bridge"
      }
    },
    {
      "geometry": {
        "type": "Point",
        "coordinates": [
          -76.4833,
          36.9833
        ]
      },
      "type": "Feature",
      "properties": {
        "hierarchy": [
          "tgn:1101002",
          "tgn:1000001",
          "tgn:7012149",
          "tgn:7594201",
          "tgn:7007919",
          "tgn:7029392"
        ],
        "placetype": [
          "aat:300007836"
        ],
        "id": 1101002,
        "name:xx": "James River Bridge"
      }
    },
    {
      "geometry": {
        "type": "Point",
        "coordinates": [
          6.9,
          51.3833
        ]
      },
      "type": "Feature",
      "properties": {
        "hierarchy": [
          "tgn:1101005",
          "tgn:1000003",
          "tgn:7003677",
          "tgn:7000084",
          "tgn:7029392"
        ],
        "placetype": [
          "aat:300007836"
        ],
        "id": 1101005,
        "name:xx": "Mülheimer Ruhrtalbrüke"
      }
    }
  ]
}
