{
  "geometry": {
    "type": "Point",
    "coordinates": [
      -91.3167,
      45.85
    ]
  },
  "type": "Feature",
  "properties": {
    "hierarchy": [
      "tgn:2285376",
      "tgn:1000001",
      "tgn:7012149",
      "tgn:2002353",
      "tgn:7007922",
      "tgn:7029392"
    ],
    "placetype": [
      "aat:300008706"
    ],
    "id": 2285376,
    "name:xx": "Devils Creek"
  }
}
