{
  "geometry": {
    "type": "Point",
    "coordinates": [
      117.7333,
      5.4167
    ]
  },
  "type": "Feature",
  "properties": {
    "hierarchy": [
      "tgn:1082916",
      "tgn:7018970",
      "tgn:7000316",
      "tgn:1000004",
      "tgn:1000128",
      "tgn:7029392"
    ],
    "placetype": [
      "aat:300008347"
    ],
    "id": 1082916,
    "name:xx": "Pintasan"
  }
}
