{
  "geometry": {
    "type": "Point",
    "coordinates": [
      -106.75,
      44.3167
    ]
  },
  "type": "Feature",
  "properties": {
    "hierarchy": [
      "tgn:2424480",
      "tgn:1000001",
      "tgn:7012149",
      "tgn:2002374",
      "tgn:7007923",
      "tgn:7029392"
    ],
    "placetype": [
      "aat:300006075"
    ],
    "id": 2424480,
    "name:xx": "Johnson County Ditch"
  }
}
