{
  "geometry": {
    "type": "Point",
    "coordinates": [
      -102.15,
      41.75
    ]
  },
  "type": "Feature",
  "properties": {
    "hierarchy": [
      "tgn:2621677",
      "tgn:1000001",
      "tgn:2001350",
      "tgn:7012149",
      "tgn:7007525",
      "tgn:7029392"
    ],
    "placetype": [
      "aat:300386845"
    ],
    "id": 2621677,
    "name:xx": "Robb Valley"
  }
}
