{
  "geometry": {
    "type": "Point",
    "coordinates": [
      -82.3167,
      29.8333
    ]
  },
  "type": "Feature",
  "properties": {
    "hierarchy": [
      "tgn:2705075",
      "tgn:2000256",
      "tgn:1000001",
      "tgn:7012149",
      "tgn:7007240",
      "tgn:7029392"
    ],
    "placetype": [
      "aat:300008680"
    ],
    "id": 2705075,
    "name:xx": "Sunshine Lake"
  }
}
