{
  "geometry": {
    "type": "Point",
    "coordinates": [
      35.440296,
      23.591246
    ]
  },
  "type": "Feature",
  "properties": {
    "hierarchy": [
      "tgn:7527904",
      "tgn:7001242",
      "tgn:7001311",
      "tgn:7016833",
      "tgn:7029392"
    ],
    "placetype": [
      "aat:300379998"
    ],
    "name:en": "Um Markh, Wâdi",
    "id": 7527904
  }
}
