{
  "geometry": {
    "type": "Point",
    "coordinates": [
      13.45,
      51.05
    ]
  },
  "type": "Feature",
  "properties": {
    "hierarchy": [
      "tgn:7171286",
      "tgn:1000003",
      "tgn:7003685",
      "tgn:7000084",
      "tgn:7029392"
    ],
    "placetype": [
      "aat:300008777"
    ],
    "id": 7171286,
    "name:xx": "Hirschel-Berg"
  }
}
