{
  "geometry": {
    "type": "Point",
    "coordinates": [
      -80.3333,
      38.6167
    ]
  },
  "type": "Feature",
  "properties": {
    "hierarchy": [
      "tgn:7021469",
      "tgn:1000001",
      "tgn:7012149",
      "tgn:2002300",
      "tgn:7013961",
      "tgn:7029392"
    ],
    "placetype": [
      "aat:300008699"
    ],
    "id": 7021469,
    "name:xx": "Big Lick Fork"
  }
}
