{
  "geometry": {
    "type": "Point",
    "coordinates": [
      33.487112,
      29.413409
    ]
  },
  "type": "Feature",
  "properties": {
    "hierarchy": [
      "tgn:7542279",
      "tgn:7001242",
      "tgn:7016833",
      "tgn:7001336",
      "tgn:7029392"
    ],
    "placetype": [
      "aat:300379998"
    ],
    "name:en": "Ḩuwayshīyah, Wādī al",
    "id": 7542279
  }
}
