{
  "geometry": {
    "type": "Point",
    "coordinates": [
      -114.5833,
      37.95
    ]
  },
  "type": "Feature",
  "properties": {
    "hierarchy": [
      "tgn:2475587",
      "tgn:1000001",
      "tgn:2001416",
      "tgn:7012149",
      "tgn:7007526",
      "tgn:7029392"
    ],
    "placetype": [
      "aat:300000390"
    ],
    "id": 2475587,
    "name:xx": "Lucky Boy Shaft"
  }
}
