{
  "geometry": {
    "type": "Point",
    "coordinates": [
      -90.4167,
      43.1833
    ]
  },
  "type": "Feature",
  "properties": {
    "hierarchy": [
      "tgn:2533136",
      "tgn:1000001",
      "tgn:7012149",
      "tgn:2002326",
      "tgn:7007922",
      "tgn:7029392"
    ],
    "placetype": [
      "aat:300008791"
    ],
    "id": 2533136,
    "name:xx": "Muscoda Island"
  }
}
