{
  "geometry": {
    "type": "Point",
    "coordinates": [
      -116.4167,
      41.8167
    ]
  },
  "type": "Feature",
  "properties": {
    "hierarchy": [
      "tgn:2577689",
      "tgn:1000001",
      "tgn:2001411",
      "tgn:7012149",
      "tgn:7007526",
      "tgn:7029392"
    ],
    "placetype": [
      "aat:300008798"
    ],
    "id": 2577689,
    "name:xx": "Peterson Table"
  }
}
