{
  "geometry": {
    "type": "Point",
    "coordinates": [
      -112.3167,
      34.15
    ]
  },
  "type": "Feature",
  "properties": {
    "hierarchy": [
      "tgn:2150006",
      "tgn:1000001",
      "tgn:7006451",
      "tgn:7012149",
      "tgn:2000103",
      "tgn:7029392"
    ],
    "placetype": [
      "aat:300008697"
    ],
    "id": 2150006,
    "name:xx": "Bartol Spring"
  }
}
