{
  "geometry": {
    "type": "Point",
    "coordinates": [
      103.1167,
      14.4167
    ]
  },
  "type": "Feature",
  "properties": {
    "hierarchy": [
      "tgn:1085450",
      "tgn:7000910",
      "tgn:7005193",
      "tgn:1000004",
      "tgn:1000142",
      "tgn:7029392"
    ],
    "placetype": [
      "aat:300008347"
    ],
    "id": 1085450,
    "name:xx": "Ban Kruat"
  }
}
