{
  "geometry": {
    "type": "Point",
    "coordinates": [
      -105.2167,
      36.5167
    ]
  },
  "type": "Feature",
  "properties": {
    "hierarchy": [
      "tgn:1122868",
      "tgn:1000001",
      "tgn:2001432",
      "tgn:7012149",
      "tgn:7007566",
      "tgn:7029392"
    ],
    "placetype": [
      "aat:300008707"
    ],
    "id": 1122868,
    "name:xx": "Cimarron"
  }
}
