{
  "geometry": {
    "type": "Point",
    "coordinates": [
      -84.6833,
      44.7167
    ]
  },
  "type": "Feature",
  "properties": {
    "hierarchy": [
      "tgn:2194950",
      "tgn:1000001",
      "tgn:2000954",
      "tgn:7012149",
      "tgn:7007520",
      "tgn:7029392"
    ],
    "placetype": [
      "aat:300008680"
    ],
    "id": 2194950,
    "name:xx": "Bright Lake"
  }
}
