{
  "geometry": {
    "type": "Point",
    "coordinates": [
      -91.6667,
      47.7167
    ]
  },
  "type": "Feature",
  "properties": {
    "hierarchy": [
      "tgn:2283843",
      "tgn:1000001",
      "tgn:7012149",
      "tgn:2001036",
      "tgn:7007521",
      "tgn:7029392"
    ],
    "placetype": [
      "aat:300008680"
    ],
    "id": 2283843,
    "name:xx": "Denley Lake"
  }
}
