{
  "geometry": {
    "type": "Point",
    "coordinates": [
      -108.0833,
      37.4333
    ]
  },
  "type": "Feature",
  "properties": {
    "hierarchy": [
      "tgn:2680366",
      "tgn:1000001",
      "tgn:7012149",
      "tgn:2000233",
      "tgn:7007158",
      "tgn:7029392"
    ],
    "placetype": [
      "aat:300008707"
    ],
    "id": 2680366,
    "name:xx": "South Fork West Mancos River"
  }
}
