{
  "geometry": {
    "type": "Point",
    "coordinates": [
      -109.0167,
      45.45
    ]
  },
  "type": "Feature",
  "properties": {
    "hierarchy": [
      "tgn:2221102",
      "tgn:1000001",
      "tgn:2001264",
      "tgn:7012149",
      "tgn:7007524",
      "tgn:7029392"
    ],
    "placetype": [
      "aat:300006075"
    ],
    "id": 2221102,
    "name:xx": "Carbonado Ditch"
  }
}
