{
  "geometry": {
    "type": "Point",
    "coordinates": [
      85.407224,
      19.94307
    ]
  },
  "type": "Feature",
  "properties": {
    "hierarchy": [
      "tgn:7550091",
      "tgn:1000004",
      "tgn:7000198",
      "tgn:7016694",
      "tgn:7029392"
    ],
    "placetype": [
      "aat:300008347"
    ],
    "name:en": "Chāndpur",
    "id": 7550091
  }
}
