{
  "geometry": {
    "type": "Point",
    "coordinates": [
      61.1167,
      35.95
    ]
  },
  "type": "Feature",
  "properties": {
    "hierarchy": [
      "tgn:1058751",
      "tgn:7012221",
      "tgn:1000004",
      "tgn:7006659",
      "tgn:7029392"
    ],
    "placetype": [
      "aat:300008347"
    ],
    "id": 1058751,
    "name:xx": "Pulichatum"
  }
}
