{
  "geometry": {
    "type": "Point",
    "coordinates": [
      -73.0333,
      43.45
    ]
  },
  "type": "Feature",
  "properties": {
    "hierarchy": [
      "tgn:2722659",
      "tgn:1000001",
      "tgn:1002840",
      "tgn:7012149",
      "tgn:7007828",
      "tgn:7029392"
    ],
    "placetype": [
      "aat:300006075"
    ],
    "id": 2722659,
    "name:xx": "Tinmouth Channel"
  }
}
