{
  "geometry": {
    "type": "Point",
    "coordinates": [
      -9.204,
      38.823
    ]
  },
  "type": "Feature",
  "properties": {
    "hierarchy": [
      "tgn:1105683",
      "tgn:1000882",
      "tgn:1000003",
      "tgn:1000090",
      "tgn:7029392"
    ],
    "placetype": [
      "aat:300008795"
    ],
    "id": 1105683,
    "name:xx": "Montemor"
  }
}
