{
  "geometry": {
    "type": "Point",
    "coordinates": [
      -81.6833,
      32.9333
    ]
  },
  "type": "Feature",
  "properties": {
    "hierarchy": [
      "tgn:2515212",
      "tgn:1000001",
      "tgn:7012149",
      "tgn:2000415",
      "tgn:7007248",
      "tgn:7029392"
    ],
    "placetype": [
      "aat:300006191"
    ],
    "id": 2515212,
    "name:xx": "Millhaven Lake Number Two"
  }
}
