{
  "geometry": {
    "type": "Point",
    "coordinates": [
      -106.9667,
      38.6167
    ]
  },
  "type": "Feature",
  "properties": {
    "hierarchy": [
      "tgn:2487945",
      "tgn:1000001",
      "tgn:7012149",
      "tgn:2000217",
      "tgn:7007158",
      "tgn:7029392"
    ],
    "placetype": [
      "aat:300008761"
    ],
    "id": 2487945,
    "name:xx": "Maggie Gulch"
  }
}
