{
  "geometry": {
    "type": "Point",
    "coordinates": [
      120.571,
      23.8592
    ]
  },
  "type": "Feature",
  "properties": {
    "hierarchy": [
      "tgn:7491360",
      "tgn:1000004",
      "tgn:7467799",
      "tgn:1000141",
      "tgn:7029392"
    ],
    "placetype": [
      "aat:300387173"
    ],
    "id": 7491360,
    "name:xx": "Sanmin Li"
  }
}
