{
  "geometry": {
    "type": "Point",
    "coordinates": [
      23.116667,
      38.85
    ]
  },
  "type": "Feature",
  "properties": {
    "hierarchy": [
      "tgn:7236574",
      "tgn:7002751",
      "tgn:7001399",
      "tgn:1000003",
      "tgn:1000074",
      "tgn:7029392"
    ],
    "placetype": [
      "aat:300000745"
    ],
    "id": 7236574,
    "name:xx": "Áno Ília"
  }
}
