{
  "type": "FeatureCollection",
  "features": [
    {
      "geometry": {
        "type": "Point",
        "coordinates": [
          11.933333,
          48.166667
        ]
      },
      "type": "Feature",
      "properties": {
        "hierarchy": [
          "tgn:7215901",
          "tgn:7003669",
          "tgn:1000003",
          "tgn:7000084",
          "tgn:7029392"
        ],
        "placetype": [
          "aat:300008347"
        ],
        "id": 7215901,
        "name:xx": "Aitersteinering"
      }
    },
    {
      "geometry": {
        "type": "Point",
        "coordinates": [
          7.9,
          47.8
        ]
      },
      "type": "Feature",
      "properties": {
        "hierarchy": [
          "tgn:7215902",
          "tgn:7003692",
          "tgn:1000003",
          "tgn:7000084",
          "tgn:7029392"
        ],
        "placetype": [
          "aat:300008699"
        ],
        "id": 7215902,
        "name:xx": "Aiternbach"
      }
    },
    {
      "geometry": {
        "type": "Point",
        "coordinates": [
          7.9,
          47.8
        ]
      },
      "type": "Feature",
      "properties": {
        "hierarchy": [
          "tgn:7215903",
          "tgn:7003692",
          "tgn:1000003",
          "tgn:7000084",
          "tgn:7029392"
        ],
        "placetype": [
          "aat:300008347"
        ],
        "id": 7215903,
        "name:xx": "Aitern"
      }
    },
    {
      "geometry": {
        "type": "Point",
        "coordinates": [
          8.3,
          48.533333
        ]
      },
      "type": "Feature",
      "properties": {
        "hierarchy": [
          "tgn:7215905",
          "tgn:7003692",
          "tgn:1000003",
          "tgn:7000084",
          "tgn:7029392"
        ],
        "placetype": [
          "aat:300000206"
        ],
        "id": 7215905,
        "name:xx": "Aiterbächle"
      }
    },
    {
      "geometry": {
        "type": "Point",
        "coordinates": [
          7.066667,
          52.283333
        ]
      },
      "type": "Feature",
      "properties": {
        "hierarchy": [
          "tgn:7215906",
          "tgn:1000003",
          "tgn:7003676",
          "tgn:7000084",
          "tgn:7029392"
        ],
        "placetype": [
          "aat:300008347"
        ],
        "id": 7215906,
        "name:xx": "Achterberg"
      }
    },
    {
      "geometry": {
        "type": "Point",
        "coordinates": [
          6.516667,
          51.4
        ]
      },
      "type": "Feature",
      "properties": {
        "hierarchy": [
          "tgn:7215907",
          "tgn:1000003",
          "tgn:7003677",
          "tgn:7000084",
          "tgn:7029392"
        ],
        "placetype": [
          "aat:300008777"
        ],
        "id": 7215907,
        "name:xx": "Achter-Berg"
      }
    },
    {
      "geometry": {
        "type": "Point",
        "coordinates": [
          11.9,
          54.133333
        ]
      },
      "type": "Feature",
      "properties": {
        "hierarchy": [
          "tgn:7215908",
          "tgn:1000003",
          "tgn:7000094",
          "tgn:7000084",
          "tgn:7029392"
        ],
        "placetype": [
          "aat:300008699"
        ],
        "id": 7215908,
        "name:xx": "Achterbeek"
      }
    },
    {
      "geometry": {
        "type": "Point",
        "coordinates": [
          7.1,
          50.35
        ]
      },
      "type": "Feature",
      "properties": {
        "hierarchy": [
          "tgn:7215909",
          "tgn:1000003",
          "tgn:7003682",
          "tgn:7000084",
          "tgn:7029392"
        ],
        "placetype": [
          "aat:300008699"
        ],
        "id": 7215909,
        "name:xx": "Achter Bach"
      }
    }
  ]
}
