{
  "geometry": {
    "type": "Point",
    "coordinates": [
      -72.4333,
      42.2167
    ]
  },
  "type": "Feature",
  "properties": {
    "hierarchy": [
      "tgn:2390260",
      "tgn:1000001",
      "tgn:7012149",
      "tgn:7007517",
      "tgn:7029392"
    ],
    "placetype": [
      "aat:300008699"
    ],
    "id": 2390260,
    "name:xx": "Higher Brook"
  }
}
