{
  "type": "FeatureCollection",
  "features": [
    {
      "geometry": {
        "type": "Point",
        "coordinates": [
          -78.0333,
          34.0167
        ]
      },
      "type": "Feature",
      "properties": {
        "hierarchy": [
          "tgn:2782020",
          "tgn:1000001",
          "tgn:2001472",
          "tgn:7012149",
          "tgn:7007709",
          "tgn:7029392"
        ],
        "placetype": [
          "aat:300008680"
        ],
        "id": 2782020,
        "name:xx": "Woods Ponds"
      }
    },
    {
      "geometry": {
        "type": "Point",
        "coordinates": [
          -83.8,
          36.3667
        ]
      },
      "type": "Feature",
      "properties": {
        "hierarchy": [
          "tgn:2782021",
          "tgn:1000001",
          "tgn:7012149",
          "tgn:2001923",
          "tgn:7007825",
          "tgn:7029392"
        ],
        "placetype": [
          "aat:300000390"
        ],
        "id": 2782021,
        "name:xx": "Woods Prospect"
      }
    },
    {
      "geometry": {
        "type": "Point",
        "coordinates": [
          -104.55,
          42.65
        ]
      },
      "type": "Feature",
      "properties": {
        "hierarchy": [
          "tgn:2782022",
          "tgn:1000001",
          "tgn:7012149",
          "tgn:2002378",
          "tgn:7007923",
          "tgn:7029392"
        ],
        "placetype": [
          "aat:300008761"
        ],
        "id": 2782022,
        "name:xx": "Woods Ranch Draw"
      }
    },
    {
      "geometry": {
        "type": "Point",
        "coordinates": [
          -106.6667,
          39.3667
        ]
      },
      "type": "Feature",
      "properties": {
        "hierarchy": [
          "tgn:2782023",
          "tgn:1000001",
          "tgn:7012149",
          "tgn:2000210",
          "tgn:7007158",
          "tgn:7029392"
        ],
        "placetype": [
          "aat:300006191"
        ],
        "id": 2782023,
        "name:xx": "Woods Reservoir"
      }
    },
    {
      "geometry": {
        "type": "Point",
        "coordinates": [
          -106.5,
          40.2333
        ]
      },
      "type": "Feature",
      "properties": {
        "hierarchy": [
          "tgn:2782024",
          "tgn:1000001",
          "tgn:7012149",
          "tgn:2000216",
          "tgn:7007158",
          "tgn:7029392"
        ],
        "placetype": [
          "aat:300006191"
        ],
        "id": 2782024,
        "name:xx": "Woods Reservoir"
      }
    },
    {
      "geometry": {
        "type": "Point",
        "coordinates": [
          -116.6333,
          39.4667
        ]
      },
      "type": "Feature",
      "properties": {
        "hierarchy": [
          "tgn:2782025",
          "tgn:1000001",
          "tgn:2001415",
          "tgn:7012149",
          "tgn:7007526",
          "tgn:7029392"
        ],
        "placetype": [
          "aat:300006191"
        ],
        "id": 2782025,
        "name:xx": "Woods Reservoir"
      }
    },
    {
      "geometry": {
        "type": "Point",
        "coordinates": [
          -123.0833,
          45.2333
        ]
      },
      "type": "Feature",
      "properties": {
        "hierarchy": [
          "tgn:2782026",
          "tgn:1000001",
          "tgn:7012149",
          "tgn:1003044",
          "tgn:7007708",
          "tgn:7029392"
        ],
        "placetype": [
          "aat:300006191"
        ],
        "id": 2782026,
        "name:xx": "Woods Reservoir"
      }
    },
    {
      "geometry": {
        "type": "Point",
        "coordinates": [
          -86.0833,
          35.2833
        ]
      },
      "type": "Feature",
      "properties": {
        "hierarchy": [
          "tgn:2782027",
          "tgn:1000001",
          "tgn:7012149",
          "tgn:7007825",
          "tgn:7029392"
        ],
        "placetype": [
          "aat:300006191"
        ],
        "id": 2782027,
        "name:xx": "Woods Reservoir"
      }
    },
    {
      "geometry": {
        "type": "Point",
        "coordinates": [
          -113.6667,
          38.35
        ]
      },
      "type": "Feature",
      "properties": {
        "hierarchy": [
          "tgn:2782028",
          "tgn:2002101",
          "tgn:1000001",
          "tgn:7012149",
          "tgn:7007827",
          "tgn:7029392"
        ],
        "placetype": [
          "aat:300006191"
        ],
        "id": 2782028,
        "name:xx": "Woods Reservoir"
      }
    },
    {
      "geometry": {
        "type": "Point",
        "coordinates": [
          -123.1,
          48.5167
        ]
      },
      "type": "Feature",
      "properties": {
        "hierarchy": [
          "tgn:2782029",
          "tgn:1000001",
          "tgn:7012149",
          "tgn:1002862",
          "tgn:7007920",
          "tgn:7029392"
        ],
        "placetype": [
          "aat:300006191"
        ],
        "id": 2782029,
        "name:xx": "Woods Reservoir"
      }
    }
  ]
}
