{
  "geometry": {
    "type": "Point",
    "coordinates": [
      75.530992,
      25.06143
    ]
  },
  "type": "Feature",
  "properties": {
    "hierarchy": [
      "tgn:7568257",
      "tgn:1000004",
      "tgn:7000198",
      "tgn:7016788",
      "tgn:7029392"
    ],
    "placetype": [
      "aat:300008347"
    ],
    "name:en": "Dasāliya",
    "id": 7568257
  }
}
