{
  "geometry": {
    "type": "Point",
    "coordinates": [
      -94.4667,
      31.1667
    ]
  },
  "type": "Feature",
  "properties": {
    "hierarchy": [
      "tgn:2685873",
      "tgn:1002149",
      "tgn:1000001",
      "tgn:7012149",
      "tgn:7007826",
      "tgn:7029392"
    ],
    "placetype": [
      "aat:300008699"
    ],
    "id": 2685873,
    "name:xx": "Spring Branch"
  }
}
