{
  "geometry": {
    "type": "Point",
    "coordinates": [
      -76.9167,
      43.1333
    ]
  },
  "type": "Feature",
  "properties": {
    "hierarchy": [
      "tgn:2505526",
      "tgn:1000001",
      "tgn:7012149",
      "tgn:7014600",
      "tgn:7007568",
      "tgn:7029392"
    ],
    "placetype": [
      "aat:300008699"
    ],
    "id": 2505526,
    "name:xx": "Melvin Brook"
  }
}
