{
  "geometry": {
    "type": "Point",
    "coordinates": [
      -80.7667,
      37.3833
    ]
  },
  "type": "Feature",
  "properties": {
    "hierarchy": [
      "tgn:2612336",
      "tgn:1000001",
      "tgn:7012149",
      "tgn:2002282",
      "tgn:7013961",
      "tgn:7029392"
    ],
    "placetype": [
      "aat:300008697"
    ],
    "id": 2612336,
    "name:xx": "Red Sulphur Spring"
  }
}
