{
  "type": "FeatureCollection",
  "features": [
    {
      "geometry": {
        "type": "Point",
        "coordinates": [
          -71.0667,
          43.25
        ]
      },
      "type": "Feature",
      "properties": {
        "hierarchy": [
          "tgn:2468620",
          "tgn:1000001",
          "tgn:2001426",
          "tgn:7012149",
          "tgn:7007564",
          "tgn:7029392"
        ],
        "placetype": [
          "aat:300008680"
        ],
        "id": 2468620,
        "name:xx": "Long Pond"
      }
    },
    {
      "geometry": {
        "type": "Point",
        "coordinates": [
          -71.0667,
          43.8833
        ]
      },
      "type": "Feature",
      "properties": {
        "hierarchy": [
          "tgn:2468621",
          "tgn:2001423",
          "tgn:1000001",
          "tgn:7012149",
          "tgn:7007564",
          "tgn:7029392"
        ],
        "placetype": [
          "aat:300008680"
        ],
        "id": 2468621,
        "name:xx": "Long Pond"
      }
    },
    {
      "geometry": {
        "type": "Point",
        "coordinates": [
          -71.8833,
          44.05
        ]
      },
      "type": "Feature",
      "properties": {
        "hierarchy": [
          "tgn:2468622",
          "tgn:1000001",
          "tgn:2001424",
          "tgn:7012149",
          "tgn:7007564",
          "tgn:7029392"
        ],
        "placetype": [
          "aat:300008680"
        ],
        "id": 2468622,
        "name:xx": "Long Pond"
      }
    },
    {
      "geometry": {
        "type": "Point",
        "coordinates": [
          -71.2333,
          44.75
        ]
      },
      "type": "Feature",
      "properties": {
        "hierarchy": [
          "tgn:2468623",
          "tgn:1002300",
          "tgn:1000001",
          "tgn:7012149",
          "tgn:7007564",
          "tgn:7029392"
        ],
        "placetype": [
          "aat:300008680"
        ],
        "id": 2468623,
        "name:xx": "Long Pond"
      }
    },
    {
      "geometry": {
        "type": "Point",
        "coordinates": [
          -71.2333,
          43.2333
        ]
      },
      "type": "Feature",
      "properties": {
        "hierarchy": [
          "tgn:2468624",
          "tgn:1000001",
          "tgn:7014352",
          "tgn:7012149",
          "tgn:7007564",
          "tgn:7029392"
        ],
        "placetype": [
          "aat:300006191"
        ],
        "id": 2468624,
        "name:xx": "Long Pond"
      }
    },
    {
      "geometry": {
        "type": "Point",
        "coordinates": [
          -75.4667,
          39.45
        ]
      },
      "type": "Feature",
      "properties": {
        "hierarchy": [
          "tgn:2468625",
          "tgn:1000001",
          "tgn:7014449",
          "tgn:7012149",
          "tgn:7007565",
          "tgn:7029392"
        ],
        "placetype": [
          "aat:300008680"
        ],
        "id": 2468625,
        "name:xx": "Long Pond"
      }
    },
    {
      "geometry": {
        "type": "Point",
        "coordinates": [
          -72.3167,
          40.9333
        ]
      },
      "type": "Feature",
      "properties": {
        "hierarchy": [
          "tgn:2468626",
          "tgn:1000001",
          "tgn:7012149",
          "tgn:1002924",
          "tgn:7007568",
          "tgn:7029392"
        ],
        "placetype": [
          "aat:300008680"
        ],
        "id": 2468626,
        "name:xx": "Long Pond"
      }
    },
    {
      "geometry": {
        "type": "Point",
        "coordinates": [
          -73.6667,
          41.1333
        ]
      },
      "type": "Feature",
      "properties": {
        "hierarchy": [
          "tgn:2468627",
          "tgn:1000001",
          "tgn:7012149",
          "tgn:7014612",
          "tgn:7007568",
          "tgn:7029392"
        ],
        "placetype": [
          "aat:300008680"
        ],
        "id": 2468627,
        "name:xx": "Long Pond"
      }
    },
    {
      "geometry": {
        "type": "Point",
        "coordinates": [
          -74.0167,
          41.3667
        ]
      },
      "type": "Feature",
      "properties": {
        "hierarchy": [
          "tgn:2468628",
          "tgn:1000001",
          "tgn:7012149",
          "tgn:1002751",
          "tgn:7007568",
          "tgn:7029392"
        ],
        "placetype": [
          "aat:300008680"
        ],
        "id": 2468628,
        "name:xx": "Long Pond"
      }
    },
    {
      "geometry": {
        "type": "Point",
        "coordinates": [
          -73.7333,
          41.4
        ]
      },
      "type": "Feature",
      "properties": {
        "hierarchy": [
          "tgn:2468629",
          "tgn:1000001",
          "tgn:7012149",
          "tgn:1002810",
          "tgn:7007568",
          "tgn:7029392"
        ],
        "placetype": [
          "aat:300008680"
        ],
        "id": 2468629,
        "name:xx": "Long Pond"
      }
    }
  ]
}
