{
  "geometry": {
    "type": "Point",
    "coordinates": [
      -84.7167,
      42.8833
    ]
  },
  "type": "Feature",
  "properties": {
    "hierarchy": [
      "tgn:2533363",
      "tgn:1000001",
      "tgn:1002283",
      "tgn:7012149",
      "tgn:7007520",
      "tgn:7029392"
    ],
    "placetype": [
      "aat:300008706"
    ],
    "id": 2533363,
    "name:xx": "Muskrat Creek"
  }
}
