{
  "geometry": {
    "type": "Point",
    "coordinates": [
      32.618878,
      26.222336
    ]
  },
  "type": "Feature",
  "properties": {
    "hierarchy": [
      "tgn:7534475",
      "tgn:7001242",
      "tgn:7001311",
      "tgn:7016833",
      "tgn:7029392"
    ],
    "placetype": [
      "aat:300379998"
    ],
    "name:en": "Makhādimah, Wādī al",
    "id": 7534475
  }
}
