{
  "type": "FeatureCollection",
  "features": [
    {
      "geometry": {
        "type": "Point",
        "coordinates": [
          12.35,
          45.433333
        ]
      },
      "type": "Feature",
      "properties": {
        "hierarchy": [
          "tgn:7041691",
          "tgn:7003006",
          "tgn:1000003",
          "tgn:7002997",
          "tgn:1000080",
          "tgn:7029392"
        ],
        "placetype": [
          "aat:300007466"
        ],
        "id": 7041691,
        "name:xx": "San Giorgio Maggiore"
      }
    },
    {
      "geometry": {
        "type": "Point",
        "coordinates": [
          10.783333,
          45.416667
        ]
      },
      "type": "Feature",
      "properties": {
        "hierarchy": [
          "tgn:7041695",
          "tgn:7003007",
          "tgn:1000003",
          "tgn:7002997",
          "tgn:1000080",
          "tgn:7029392"
        ],
        "placetype": [
          "aat:300008347"
        ],
        "id": 7041695,
        "name:xx": "San Giorgio in Salici"
      }
    },
    {
      "geometry": {
        "type": "Point",
        "coordinates": [
          11.75,
          45.6
        ]
      },
      "type": "Feature",
      "properties": {
        "hierarchy": [
          "tgn:7041696",
          "tgn:7002994",
          "tgn:1000003",
          "tgn:7002997",
          "tgn:1000080",
          "tgn:7029392"
        ],
        "placetype": [
          "aat:300008347"
        ],
        "id": 7041696,
        "name:xx": "San Giorgio in Brenta"
      }
    },
    {
      "geometry": {
        "type": "Point",
        "coordinates": [
          11.8,
          45.583333
        ]
      },
      "type": "Feature",
      "properties": {
        "hierarchy": [
          "tgn:7041697",
          "tgn:7002994",
          "tgn:1000003",
          "tgn:7002997",
          "tgn:1000080",
          "tgn:7029392"
        ],
        "placetype": [
          "aat:300008347"
        ],
        "id": 7041697,
        "name:xx": "San Giorgio in Bosco"
      }
    },
    {
      "geometry": {
        "type": "Point",
        "coordinates": [
          12.283333,
          45.416667
        ]
      },
      "type": "Feature",
      "properties": {
        "hierarchy": [
          "tgn:7041698",
          "tgn:7003006",
          "tgn:1000003",
          "tgn:7002997",
          "tgn:1000080",
          "tgn:7029392"
        ],
        "placetype": [
          "aat:300008791"
        ],
        "id": 7041698,
        "name:xx": "San Giorgio in Alga"
      }
    }
  ]
}
