{
  "geometry": {
    "type": "Point",
    "coordinates": [
      -118.5833,
      44.7333
    ]
  },
  "type": "Feature",
  "properties": {
    "hierarchy": [
      "tgn:2162443",
      "tgn:1000001",
      "tgn:7012149",
      "tgn:2001708",
      "tgn:7007708",
      "tgn:7029392"
    ],
    "placetype": [
      "aat:300008798"
    ],
    "id": 2162443,
    "name:xx": "Ben Harrison Peak"
  }
}
