{
  "geometry": {
    "type": "Point",
    "coordinates": [
      -108.9333,
      37.6833
    ]
  },
  "type": "Feature",
  "properties": {
    "hierarchy": [
      "tgn:2689219",
      "tgn:1000001",
      "tgn:7012149",
      "tgn:7029392"
    ],
    "placetype": [
      "aat:300008761"
    ],
    "id": 2689219,
    "name:xx": "Squaw Canyon"
  }
}
