{
  "geometry": {
    "type": "Point",
    "coordinates": [
      86.9167,
      47.6667
    ]
  },
  "type": "Feature",
  "properties": {
    "hierarchy": [
      "tgn:1122320",
      "tgn:1000004",
      "tgn:7001745",
      "tgn:1000111",
      "tgn:7029392"
    ],
    "placetype": [
      "aat:300008707"
    ],
    "id": 1122320,
    "name:xx": "Burqin He"
  }
}
