{
  "geometry": {
    "type": "Point",
    "coordinates": [
      -74.0167,
      41.5167
    ]
  },
  "type": "Feature",
  "properties": {
    "hierarchy": [
      "tgn:2444906",
      "tgn:1000001",
      "tgn:7012149",
      "tgn:1002751",
      "tgn:7007568",
      "tgn:7029392"
    ],
    "placetype": [
      "aat:300008680"
    ],
    "id": 2444906,
    "name:xx": "Leighfs Pond"
  }
}
