{
  "type": "FeatureCollection",
  "features": [
    {
      "geometry": {
        "type": "Point",
        "coordinates": [
          -4.716667,
          55.816667
        ]
      },
      "type": "Feature",
      "properties": {
        "hierarchy": [
          "tgn:7458392",
          "tgn:7002444",
          "tgn:1000003",
          "tgn:7019095",
          "tgn:7008591",
          "tgn:7029392"
        ],
        "placetype": [
          "aat:300008795"
        ],
        "name:en": "Misty Law",
        "id": 7458392
      }
    },
    {
      "geometry": {
        "type": "Point",
        "coordinates": [
          -4.966667,
          57.416667
        ]
      },
      "type": "Feature",
      "properties": {
        "hierarchy": [
          "tgn:7458397",
          "tgn:7002444",
          "tgn:1000003",
          "tgn:7008082",
          "tgn:7008591",
          "tgn:7029392"
        ],
        "placetype": [
          "aat:300008699"
        ],
        "name:en": "Misgeach, Visge",
        "id": 7458397
      }
    },
    {
      "geometry": {
        "type": "Point",
        "coordinates": [
          -2.8,
          58.95
        ]
      },
      "type": "Feature",
      "properties": {
        "hierarchy": [
          "tgn:7458399",
          "tgn:7002444",
          "tgn:1000003",
          "tgn:7009907",
          "tgn:7008591",
          "tgn:7029392"
        ],
        "placetype": [
          "aat:300386846"
        ],
        "name:en": "Mirkady Point",
        "id": 7458399
      }
    }
  ]
}
