{
  "geometry": {
    "type": "Point",
    "coordinates": [
      101.6167,
      3.5833
    ]
  },
  "type": "Feature",
  "properties": {
    "hierarchy": [
      "tgn:1082816",
      "tgn:7000317",
      "tgn:1000004",
      "tgn:7016804",
      "tgn:1000128",
      "tgn:7029392"
    ],
    "placetype": [
      "aat:300008347"
    ],
    "id": 1082816,
    "name:xx": "Kuala Kubu Baharu"
  }
}
