{
  "type": "FeatureCollection",
  "features": [
    {
      "geometry": {
        "type": "Point",
        "coordinates": [
          -104.5833,
          59.9167
        ]
      },
      "type": "Feature",
      "properties": {
        "hierarchy": [
          "tgn:1118090",
          "tgn:7005685",
          "tgn:1000001",
          "tgn:7029392"
        ],
        "placetype": [
          "aat:300008680"
        ],
        "id": 1118090,
        "name:xx": "Selwyn Lake"
      }
    },
    {
      "geometry": {
        "type": "Point",
        "coordinates": [
          -94.1833,
          55.05
        ]
      },
      "type": "Feature",
      "properties": {
        "hierarchy": [
          "tgn:1118092",
          "tgn:7005685",
          "tgn:1000001",
          "tgn:7005734",
          "tgn:7029392"
        ],
        "placetype": [
          "aat:300008680"
        ],
        "id": 1118092,
        "name:xx": "Semmens Lake"
      }
    },
    {
      "geometry": {
        "type": "Point",
        "coordinates": [
          -95.65,
          55.0333
        ]
      },
      "type": "Feature",
      "properties": {
        "hierarchy": [
          "tgn:1118094",
          "tgn:7005685",
          "tgn:1000001",
          "tgn:7005734",
          "tgn:7029392"
        ],
        "placetype": [
          "aat:300008680"
        ],
        "id": 1118094,
        "name:xx": "Semple Lake"
      }
    },
    {
      "geometry": {
        "type": "Point",
        "coordinates": [
          -76.8667,
          42.6333
        ]
      },
      "type": "Feature",
      "properties": {
        "hierarchy": [
          "tgn:1118096",
          "tgn:1000001",
          "tgn:7012149",
          "tgn:7007568",
          "tgn:7029392"
        ],
        "placetype": [
          "aat:300008680"
        ],
        "id": 1118096,
        "name:xx": "Seneca Lake"
      }
    }
  ]
}
