{
  "geometry": {
    "type": "Point",
    "coordinates": [
      -92.55,
      39.9333
    ]
  },
  "type": "Feature",
  "properties": {
    "hierarchy": [
      "tgn:2447429",
      "tgn:1000001",
      "tgn:7012149",
      "tgn:1002619",
      "tgn:7007523",
      "tgn:7029392"
    ],
    "placetype": [
      "aat:300008706"
    ],
    "id": 2447429,
    "name:xx": "Lick Creek"
  }
}
