{
  "geometry": {
    "type": "Point",
    "coordinates": [
      -83.2333,
      35.75
    ]
  },
  "type": "Feature",
  "properties": {
    "hierarchy": [
      "tgn:2343125",
      "tgn:1000001",
      "tgn:7012149",
      "tgn:2001851",
      "tgn:7007825",
      "tgn:7029392"
    ],
    "placetype": [
      "aat:300008798"
    ],
    "id": 2343125,
    "name:xx": "Gabes Mountain"
  }
}
