{
  "geometry": {
    "type": "Point",
    "coordinates": [
      31.6667,
      48.4833
    ]
  },
  "type": "Feature",
  "properties": {
    "hierarchy": [
      "tgn:1058445",
      "tgn:1000003",
      "tgn:7011662",
      "tgn:7006660",
      "tgn:7029392"
    ],
    "placetype": [
      "aat:300008347"
    ],
    "id": 1058445,
    "name:xx": "Pletnyy Tashlyk"
  }
}
