{
  "geometry": {
    "type": "Point",
    "coordinates": [
      -82.7333,
      28.7667
    ]
  },
  "type": "Feature",
  "properties": {
    "hierarchy": [
      "tgn:2397172",
      "tgn:1000001",
      "tgn:1002269",
      "tgn:7012149",
      "tgn:7007240",
      "tgn:7029392"
    ],
    "placetype": [
      "aat:300008850"
    ],
    "id": 2397172,
    "name:xx": "Homosassa Point"
  }
}
