{
  "geometry": {
    "type": "Point",
    "coordinates": [
      -83.8333,
      35.5167
    ]
  },
  "type": "Feature",
  "properties": {
    "hierarchy": [
      "tgn:2735098",
      "tgn:1000001",
      "tgn:7012149",
      "tgn:2001543",
      "tgn:7007709",
      "tgn:7029392"
    ],
    "placetype": [
      "aat:300008706"
    ],
    "id": 2735098,
    "name:xx": "Twentymile Creek"
  }
}
