{
  "geometry": {
    "type": "Point",
    "coordinates": [
      -172.9167,
      52.0833
    ]
  },
  "type": "Feature",
  "properties": {
    "hierarchy": [
      "tgn:2126745",
      "tgn:7030516",
      "tgn:7006450",
      "tgn:1000001",
      "tgn:7012149",
      "tgn:7029392"
    ],
    "placetype": [
      "aat:300132348"
    ],
    "id": 2126745,
    "name:xx": "Agligadak Reefs"
  }
}
