{
  "geometry": {
    "type": "Point",
    "coordinates": [
      75.64042,
      18.195019
    ]
  },
  "type": "Feature",
  "properties": {
    "hierarchy": [
      "tgn:7579768",
      "tgn:1000004",
      "tgn:7000198",
      "tgn:1001895",
      "tgn:7029392"
    ],
    "placetype": [
      "aat:300007783"
    ],
    "name:en": "Uplāi",
    "id": 7579768
  }
}
