{
  "geometry": {
    "type": "Point",
    "coordinates": [
      -87.6833,
      36.9167
    ]
  },
  "type": "Feature",
  "properties": {
    "hierarchy": [
      "tgn:2204627",
      "tgn:1000001",
      "tgn:7012149",
      "tgn:2000846",
      "tgn:7007255",
      "tgn:7029392"
    ],
    "placetype": [
      "aat:300008798"
    ],
    "id": 2204627,
    "name:xx": "Buffalo Knob"
  }
}
