{
  "geometry": {
    "type": "Point",
    "coordinates": [
      -78.5667,
      37.1667
    ]
  },
  "type": "Feature",
  "properties": {
    "hierarchy": [
      "tgn:2204654",
      "tgn:1000001",
      "tgn:7012149",
      "tgn:2002182",
      "tgn:7007919",
      "tgn:7029392"
    ],
    "placetype": [
      "aat:300006191"
    ],
    "id": 2204654,
    "name:xx": "Buffalo Lake"
  }
}
