{
  "geometry": {
    "type": "Point",
    "coordinates": [
      -154.85,
      59.9333
    ]
  },
  "type": "Feature",
  "properties": {
    "hierarchy": [
      "tgn:2328221",
      "tgn:7006450",
      "tgn:1000001",
      "tgn:7030517",
      "tgn:7012149",
      "tgn:7029392"
    ],
    "placetype": [
      "aat:300008347"
    ],
    "id": 2328221,
    "name:xx": "Fish Village"
  }
}
