{
  "geometry": {
    "type": "Point",
    "coordinates": [
      -9.3333,
      38.683
    ]
  },
  "type": "Feature",
  "properties": {
    "hierarchy": [
      "tgn:1049908",
      "tgn:1000003",
      "tgn:1000929",
      "tgn:1000090",
      "tgn:7029392"
    ],
    "placetype": [
      "aat:300008347"
    ],
    "id": 1049908,
    "name:xx": "São Julião da Barra"
  }
}
