{
  "type": "FeatureCollection",
  "features": [
    {
      "geometry": {
        "type": "Point",
        "coordinates": [
          -89.0333,
          34.6
        ]
      },
      "type": "Feature",
      "properties": {
        "hierarchy": [
          "tgn:2420830",
          "tgn:1000001",
          "tgn:7012149",
          "tgn:7007522",
          "tgn:7029392"
        ],
        "placetype": [
          "aat:300008699"
        ],
        "id": 2420830,
        "name:xx": "Jenny Branch"
      }
    },
    {
      "geometry": {
        "type": "Point",
        "coordinates": [
          -83.5833,
          35.4667
        ]
      },
      "type": "Feature",
      "properties": {
        "hierarchy": [
          "tgn:2420831",
          "tgn:1000001",
          "tgn:7012149",
          "tgn:2001543",
          "tgn:7007709",
          "tgn:7029392"
        ],
        "placetype": [
          "aat:300008699"
        ],
        "id": 2420831,
        "name:xx": "Jenny Branch"
      }
    },
    {
      "geometry": {
        "type": "Point",
        "coordinates": [
          -81.9,
          36.0167
        ]
      },
      "type": "Feature",
      "properties": {
        "hierarchy": [
          "tgn:2420832",
          "tgn:2001468",
          "tgn:1000001",
          "tgn:7012149",
          "tgn:7007709",
          "tgn:7029392"
        ],
        "placetype": [
          "aat:300008699"
        ],
        "id": 2420832,
        "name:xx": "Jenny Branch"
      }
    },
    {
      "geometry": {
        "type": "Point",
        "coordinates": [
          -79.8667,
          36
        ]
      },
      "type": "Feature",
      "properties": {
        "hierarchy": [
          "tgn:2420833",
          "tgn:1000001",
          "tgn:7012149",
          "tgn:2001500",
          "tgn:7007709",
          "tgn:7029392"
        ],
        "placetype": [
          "aat:300008699"
        ],
        "id": 2420833,
        "name:xx": "Jenny Branch"
      }
    },
    {
      "geometry": {
        "type": "Point",
        "coordinates": [
          -86.3,
          35
        ]
      },
      "type": "Feature",
      "properties": {
        "hierarchy": [
          "tgn:2420834",
          "tgn:1000001",
          "tgn:7012149",
          "tgn:2001862",
          "tgn:7007825",
          "tgn:7029392"
        ],
        "placetype": [
          "aat:300008699"
        ],
        "id": 2420834,
        "name:xx": "Jenny Branch"
      }
    },
    {
      "geometry": {
        "type": "Point",
        "coordinates": [
          -81.4833,
          37.5167
        ]
      },
      "type": "Feature",
      "properties": {
        "hierarchy": [
          "tgn:2420835",
          "tgn:1000001",
          "tgn:7012149",
          "tgn:2002304",
          "tgn:7013961",
          "tgn:7029392"
        ],
        "placetype": [
          "aat:300008699"
        ],
        "id": 2420835,
        "name:xx": "Jenny Branch"
      }
    },
    {
      "geometry": {
        "type": "Point",
        "coordinates": [
          -81.5833,
          37.4833
        ]
      },
      "type": "Feature",
      "properties": {
        "hierarchy": [
          "tgn:2420836",
          "tgn:1000001",
          "tgn:7012149",
          "tgn:2002274",
          "tgn:7013961",
          "tgn:7029392"
        ],
        "placetype": [
          "aat:300008699"
        ],
        "id": 2420836,
        "name:xx": "Jenny Branch"
      }
    },
    {
      "geometry": {
        "type": "Point",
        "coordinates": [
          -110.2,
          39.1667
        ]
      },
      "type": "Feature",
      "properties": {
        "hierarchy": [
          "tgn:2420837",
          "tgn:1000001",
          "tgn:2002108",
          "tgn:7012149",
          "tgn:7007827",
          "tgn:7029392"
        ],
        "placetype": [
          "aat:300008761"
        ],
        "id": 2420837,
        "name:xx": "Jenny Canyon"
      }
    },
    {
      "geometry": {
        "type": "Point",
        "coordinates": [
          -72.85,
          43.3333
        ]
      },
      "type": "Feature",
      "properties": {
        "hierarchy": [
          "tgn:2420838",
          "tgn:1000001",
          "tgn:2002136",
          "tgn:7012149",
          "tgn:7007828",
          "tgn:7029392"
        ],
        "placetype": [
          "aat:300008699"
        ],
        "id": 2420838,
        "name:xx": "Jenny Coolidge Brook"
      }
    },
    {
      "geometry": {
        "type": "Point",
        "coordinates": [
          -116.95,
          45.9667
        ]
      },
      "type": "Feature",
      "properties": {
        "hierarchy": [
          "tgn:2420839",
          "tgn:1000001",
          "tgn:7012149",
          "tgn:2001722",
          "tgn:7007708",
          "tgn:7029392"
        ],
        "placetype": [
          "aat:300008761"
        ],
        "id": 2420839,
        "name:xx": "Jenny Corral Gulch"
      }
    }
  ]
}
