{
  "geometry": {
    "type": "Point",
    "coordinates": [
      -102.1167,
      29.8667
    ]
  },
  "type": "Feature",
  "properties": {
    "hierarchy": [
      "tgn:2416336",
      "tgn:1000001",
      "tgn:7012149",
      "tgn:2002082",
      "tgn:7007826",
      "tgn:7029392"
    ],
    "placetype": [
      "aat:300008761"
    ],
    "id": 2416336,
    "name:xx": "Jabalina Canyon"
  }
}
