{
  "geometry": {
    "type": "Point",
    "coordinates": [
      -103.9333,
      42.1333
    ]
  },
  "type": "Feature",
  "properties": {
    "hierarchy": [
      "tgn:2298588",
      "tgn:1000001",
      "tgn:7012149",
      "tgn:7007525",
      "tgn:7029392"
    ],
    "placetype": [
      "aat:300008706"
    ],
    "id": 2298588,
    "name:xx": "Dry Sheep Creek"
  }
}
