{
  "geometry": {
    "type": "Point",
    "coordinates": [
      -122.65,
      47.0667
    ]
  },
  "type": "Feature",
  "properties": {
    "hierarchy": [
      "tgn:2176197",
      "tgn:1000001",
      "tgn:7012149",
      "tgn:1002785",
      "tgn:7007920",
      "tgn:7029392"
    ],
    "placetype": [
      "aat:300008798"
    ],
    "id": 2176197,
    "name:xx": "Black Hill"
  }
}
