{
  "geometry": {
    "type": "Point",
    "coordinates": [
      -119.0667,
      35.3667
    ]
  },
  "type": "Feature",
  "properties": {
    "hierarchy": [
      "tgn:2011930",
      "tgn:1000001",
      "tgn:7012149",
      "tgn:1002545",
      "tgn:7007157",
      "tgn:7029392"
    ],
    "placetype": [
      "aat:300387016"
    ],
    "id": 2011930,
    "name:xx": "Jastro"
  }
}
