{
  "geometry": {
    "type": "Point",
    "coordinates": [
      -69.7333,
      46.5333
    ]
  },
  "type": "Feature",
  "properties": {
    "hierarchy": [
      "tgn:2333623",
      "tgn:1000001",
      "tgn:7012149",
      "tgn:7007515",
      "tgn:7029392"
    ],
    "placetype": [
      "aat:300008699"
    ],
    "id": 2333623,
    "name:xx": "Fool Brook"
  }
}
