{
  "geometry": {
    "type": "Point",
    "coordinates": [
      -115.9167,
      33.6167
    ]
  },
  "type": "Feature",
  "properties": {
    "hierarchy": [
      "tgn:2179227",
      "tgn:1000001",
      "tgn:7012149",
      "tgn:7007157",
      "tgn:1002857",
      "tgn:7029392"
    ],
    "placetype": [
      "aat:300008798"
    ],
    "id": 2179227,
    "name:xx": "Blake Hill"
  }
}
