{
  "type": "FeatureCollection",
  "features": [
    {
      "geometry": {
        "type": "Point",
        "coordinates": [
          -4.066667,
          54.8
        ]
      },
      "type": "Feature",
      "properties": {
        "hierarchy": [
          "tgn:7447350",
          "tgn:7002444",
          "tgn:7008074",
          "tgn:1000003",
          "tgn:7008591",
          "tgn:7029392"
        ],
        "placetype": [
          "aat:300008804"
        ],
        "name:en": "Saint Marys Isle",
        "id": 7447350
      }
    },
    {
      "geometry": {
        "type": "Point",
        "coordinates": [
          -3.5,
          50.383333
        ]
      },
      "type": "Feature",
      "properties": {
        "hierarchy": [
          "tgn:7447353",
          "tgn:7002445",
          "tgn:1000003",
          "tgn:7012077",
          "tgn:7008591",
          "tgn:7029392"
        ],
        "placetype": [
          "aat:300132316"
        ],
        "name:en": "Saint Marys Bay",
        "id": 7447353
      }
    },
    {
      "geometry": {
        "type": "Point",
        "coordinates": [
          -2.916667,
          58.9
        ]
      },
      "type": "Feature",
      "properties": {
        "hierarchy": [
          "tgn:7447354",
          "tgn:7002444",
          "tgn:1000003",
          "tgn:7009907",
          "tgn:7008591",
          "tgn:7029392"
        ],
        "placetype": [
          "aat:300008347"
        ],
        "name:en": "Saint Marys",
        "id": 7447354
      }
    },
    {
      "geometry": {
        "type": "Point",
        "coordinates": [
          -5.166667,
          50.066667
        ]
      },
      "type": "Feature",
      "properties": {
        "hierarchy": [
          "tgn:7447359",
          "tgn:7002445",
          "tgn:7008116",
          "tgn:1000003",
          "tgn:7008591",
          "tgn:7029392"
        ],
        "placetype": [
          "aat:300008347"
        ],
        "name:en": "Saint Martins Green",
        "id": 7447359
      }
    }
  ]
}
