{
  "geometry": {
    "type": "Point",
    "coordinates": [
      -79.9167,
      43.6667
    ]
  },
  "type": "Feature",
  "properties": {
    "hierarchy": [
      "tgn:1014788",
      "tgn:7005685",
      "tgn:1000001",
      "tgn:7013154",
      "tgn:7029392"
    ],
    "placetype": [
      "aat:300008347"
    ],
    "id": 1014788,
    "name:xx": "Glen Williams"
  }
}
