{
  "type": "FeatureCollection",
  "features": [
    {
      "geometry": {
        "type": "Point",
        "coordinates": [
          139.9,
          34.9
        ]
      },
      "type": "Feature",
      "properties": {
        "hierarchy": [
          "tgn:1010985",
          "tgn:1000971",
          "tgn:1000004",
          "tgn:7000894",
          "tgn:1000120",
          "tgn:7029392"
        ],
        "placetype": [
          "aat:300008850"
        ],
        "id": 1010985,
        "name:xx": "Nojima-zaki"
      }
    },
    {
      "geometry": {
        "type": "Point",
        "coordinates": [
          8.416667,
          44.2
        ]
      },
      "type": "Feature",
      "properties": {
        "hierarchy": [
          "tgn:1010986",
          "tgn:1000003",
          "tgn:7003236",
          "tgn:7003144",
          "tgn:1000080",
          "tgn:7029392"
        ],
        "placetype": [
          "aat:300008850"
        ],
        "id": 1010986,
        "name:xx": "Noli, Capo di"
      }
    },
    {
      "geometry": {
        "type": "Point",
        "coordinates": [
          -12.1333,
          81.5167
        ]
      },
      "type": "Feature",
      "properties": {
        "hierarchy": [
          "tgn:1010988",
          "tgn:1000001",
          "tgn:7024573",
          "tgn:7029392"
        ],
        "placetype": [
          "aat:300008850"
        ],
        "id": 1010988,
        "name:xx": "Nordostrundingen"
      }
    },
    {
      "geometry": {
        "type": "Point",
        "coordinates": [
          -49.9167,
          1.7167
        ]
      },
      "type": "Feature",
      "properties": {
        "hierarchy": [
          "tgn:1010989",
          "tgn:1001986",
          "tgn:1000047",
          "tgn:7002456",
          "tgn:1000002",
          "tgn:7029392"
        ],
        "placetype": [
          "aat:300008850"
        ],
        "id": 1010989,
        "name:xx": "Norte, Cabo"
      }
    }
  ]
}
