{
  "geometry": {
    "type": "Point",
    "coordinates": [
      86.197916,
      23.903812
    ]
  },
  "type": "Feature",
  "properties": {
    "hierarchy": [
      "tgn:1077201",
      "tgn:1000004",
      "tgn:7000198",
      "tgn:7031783",
      "tgn:7029392"
    ],
    "placetype": [
      "aat:300008347"
    ],
    "name:en": "Topchānchi",
    "id": 1077201
  }
}
