{
  "type": "FeatureCollection",
  "features": [
    {
      "geometry": {
        "type": "Point",
        "coordinates": [
          -75.35,
          40.6333
        ]
      },
      "type": "Feature",
      "properties": {
        "hierarchy": [
          "tgn:2086400",
          "tgn:7013416",
          "tgn:1000001",
          "tgn:7012149",
          "tgn:1002729",
          "tgn:7007710",
          "tgn:7029392"
        ],
        "placetype": [
          "aat:300387331"
        ],
        "id": 2086400,
        "name:xx": "Bethlehem View"
      }
    },
    {
      "geometry": {
        "type": "Point",
        "coordinates": [
          -75.3333,
          40.65
        ]
      },
      "type": "Feature",
      "properties": {
        "hierarchy": [
          "tgn:2086401",
          "tgn:7013416",
          "tgn:1000001",
          "tgn:7012149",
          "tgn:1002729",
          "tgn:7007710",
          "tgn:7029392"
        ],
        "placetype": [
          "aat:300387331"
        ],
        "id": 2086401,
        "name:xx": "East Hills"
      }
    },
    {
      "geometry": {
        "type": "Point",
        "coordinates": [
          -75.4,
          40.6333
        ]
      },
      "type": "Feature",
      "properties": {
        "hierarchy": [
          "tgn:2086404",
          "tgn:7013416",
          "tgn:1000001",
          "tgn:7012149",
          "tgn:1002729",
          "tgn:7007710",
          "tgn:7029392"
        ],
        "placetype": [
          "aat:300387331"
        ],
        "id": 2086404,
        "name:xx": "Kaywin"
      }
    },
    {
      "geometry": {
        "type": "Point",
        "coordinates": [
          -75.3667,
          40.6
        ]
      },
      "type": "Feature",
      "properties": {
        "hierarchy": [
          "tgn:2086405",
          "tgn:7013416",
          "tgn:1000001",
          "tgn:7012149",
          "tgn:1002729",
          "tgn:7007710",
          "tgn:7029392"
        ],
        "placetype": [
          "aat:300006495"
        ],
        "id": 2086405,
        "name:xx": "Lehigh University"
      }
    },
    {
      "geometry": {
        "type": "Point",
        "coordinates": [
          -75.35,
          40.6333
        ]
      },
      "type": "Feature",
      "properties": {
        "hierarchy": [
          "tgn:2086406",
          "tgn:7013416",
          "tgn:1000001",
          "tgn:7012149",
          "tgn:1002729",
          "tgn:7007710",
          "tgn:7029392"
        ],
        "placetype": [
          "aat:300387331"
        ],
        "id": 2086406,
        "name:xx": "Lincoln Park"
      }
    },
    {
      "geometry": {
        "type": "Point",
        "coordinates": [
          -75.35,
          40.65
        ]
      },
      "type": "Feature",
      "properties": {
        "hierarchy": [
          "tgn:2086407",
          "tgn:7013416",
          "tgn:1000001",
          "tgn:7012149",
          "tgn:1002729",
          "tgn:7007710",
          "tgn:7029392"
        ],
        "placetype": [
          "aat:300387331"
        ],
        "id": 2086407,
        "name:xx": "Macada"
      }
    },
    {
      "geometry": {
        "type": "Point",
        "coordinates": [
          -75.3667,
          40.6167
        ]
      },
      "type": "Feature",
      "properties": {
        "hierarchy": [
          "tgn:2086408",
          "tgn:7013416",
          "tgn:1000001",
          "tgn:7012149",
          "tgn:1002729",
          "tgn:7007710",
          "tgn:7029392"
        ],
        "placetype": [
          "aat:300266755"
        ],
        "id": 2086408,
        "name:xx": "Moravian"
      }
    },
    {
      "geometry": {
        "type": "Point",
        "coordinates": [
          -75.2,
          40.6833
        ]
      },
      "type": "Feature",
      "properties": {
        "hierarchy": [
          "tgn:2086409",
          "tgn:7013416",
          "tgn:1000001",
          "tgn:7012149",
          "tgn:1002729",
          "tgn:7007710",
          "tgn:7029392"
        ],
        "placetype": [
          "aat:300008187"
        ],
        "id": 2086409,
        "name:xx": "Riverside"
      }
    }
  ]
}
