{
  "type": "FeatureCollection",
  "features": [
    {
      "geometry": {
        "type": "Point",
        "coordinates": [
          77.433333,
          12.066667
        ]
      },
      "type": "Feature",
      "properties": {
        "hierarchy": [
          "tgn:7577090",
          "tgn:1000004",
          "tgn:7000198",
          "tgn:1001882",
          "tgn:7029392"
        ],
        "placetype": [
          "aat:300008347"
        ],
        "name:en": "Kowdhalli",
        "id": 7577090
      }
    },
    {
      "geometry": {
        "type": "Point",
        "coordinates": [
          80,
          14.766667
        ]
      },
      "type": "Feature",
      "properties": {
        "hierarchy": [
          "tgn:7577093",
          "tgn:1001828",
          "tgn:1000004",
          "tgn:7000198",
          "tgn:7029392"
        ],
        "placetype": [
          "aat:300008347"
        ],
        "name:en": "Kov큰rupalle",
        "id": 7577093
      }
    },
    {
      "geometry": {
        "type": "Point",
        "coordinates": [
          78.083333,
          10.6
        ]
      },
      "type": "Feature",
      "properties": {
        "hierarchy": [
          "tgn:7577095",
          "tgn:1000004",
          "tgn:7000198",
          "tgn:7001797",
          "tgn:7029392"
        ],
        "placetype": [
          "aat:300008347"
        ],
        "name:en": "Kovil큰r",
        "id": 7577095
      }
    },
    {
      "geometry": {
        "type": "Point",
        "coordinates": [
          78.75,
          10.083333
        ]
      },
      "type": "Feature",
      "properties": {
        "hierarchy": [
          "tgn:7577096",
          "tgn:1000004",
          "tgn:7000198",
          "tgn:7001797",
          "tgn:7029392"
        ],
        "placetype": [
          "aat:300008347"
        ],
        "name:en": "Kovil큰r",
        "id": 7577096
      }
    },
    {
      "geometry": {
        "type": "Point",
        "coordinates": [
          77.016667,
          10.733333
        ]
      },
      "type": "Feature",
      "properties": {
        "hierarchy": [
          "tgn:7577098",
          "tgn:1000004",
          "tgn:7000198",
          "tgn:7001797",
          "tgn:7029392"
        ],
        "placetype": [
          "aat:300007783"
        ],
        "name:en": "Kovilp훮laiyam",
        "id": 7577098
      }
    },
    {
      "geometry": {
        "type": "Point",
        "coordinates": [
          77.466667,
          11.716667
        ]
      },
      "type": "Feature",
      "properties": {
        "hierarchy": [
          "tgn:7577099",
          "tgn:1000004",
          "tgn:7000198",
          "tgn:7001797",
          "tgn:7029392"
        ],
        "placetype": [
          "aat:300008347"
        ],
        "name:en": "Kovilnattam",
        "id": 7577099
      }
    }
  ]
}
