{
  "geometry": {
    "type": "Point",
    "coordinates": [
      -105.8833,
      38.35
    ]
  },
  "type": "Feature",
  "properties": {
    "hierarchy": [
      "tgn:2697982",
      "tgn:1000001",
      "tgn:7012149",
      "tgn:2000213",
      "tgn:7007158",
      "tgn:7029392"
    ],
    "placetype": [
      "aat:300008706"
    ],
    "id": 2697982,
    "name:xx": "Stout Creek"
  }
}
