{
  "geometry": {
    "type": "Point",
    "coordinates": [
      -71.8167,
      41.8167
    ]
  },
  "type": "Feature",
  "properties": {
    "hierarchy": [
      "tgn:2668716",
      "tgn:1000001",
      "tgn:1003028",
      "tgn:7012149",
      "tgn:7007159",
      "tgn:7029392"
    ],
    "placetype": [
      "aat:300008798"
    ],
    "id": 2668716,
    "name:xx": "Slater Hill"
  }
}
