{
  "geometry": {
    "type": "Point",
    "coordinates": [
      -112.3333,
      39.85
    ]
  },
  "type": "Feature",
  "properties": {
    "hierarchy": [
      "tgn:2234858",
      "tgn:1000001",
      "tgn:7012149",
      "tgn:2002112",
      "tgn:7007827",
      "tgn:7029392"
    ],
    "placetype": [
      "aat:300006191"
    ],
    "id": 2234858,
    "name:xx": "Cherry Creek Reservoir"
  }
}
