{
  "geometry": {
    "type": "Point",
    "coordinates": [
      -74.3833,
      42.45
    ]
  },
  "type": "Feature",
  "properties": {
    "hierarchy": [
      "tgn:2587225",
      "tgn:1000001",
      "tgn:7012149",
      "tgn:1002873",
      "tgn:7007568",
      "tgn:7029392"
    ],
    "placetype": [
      "aat:300008699"
    ],
    "id": 2587225,
    "name:xx": "Platter Kill"
  }
}
