{
  "type": "FeatureCollection",
  "features": [
    {
      "geometry": {
        "type": "Point",
        "coordinates": [
          -94.7667,
          46.3333
        ]
      },
      "type": "Feature",
      "properties": {
        "hierarchy": [
          "tgn:2381820",
          "tgn:1000001",
          "tgn:7012149",
          "tgn:2001075",
          "tgn:7007521",
          "tgn:7029392"
        ],
        "placetype": [
          "aat:300008680"
        ],
        "id": 2381820,
        "name:xx": "Hayden Lake"
      }
    },
    {
      "geometry": {
        "type": "Point",
        "coordinates": [
          -94.7667,
          40.35
        ]
      },
      "type": "Feature",
      "properties": {
        "hierarchy": [
          "tgn:2381821",
          "tgn:1000001",
          "tgn:7012149",
          "tgn:2001224",
          "tgn:7007523",
          "tgn:7029392"
        ],
        "placetype": [
          "aat:300006191"
        ],
        "id": 2381821,
        "name:xx": "Hayden Lake"
      }
    },
    {
      "geometry": {
        "type": "Point",
        "coordinates": [
          -106.85,
          36.6167
        ]
      },
      "type": "Feature",
      "properties": {
        "hierarchy": [
          "tgn:2381822",
          "tgn:1000001",
          "tgn:7012149",
          "tgn:2001449",
          "tgn:7007566",
          "tgn:7029392"
        ],
        "placetype": [
          "aat:300006191"
        ],
        "id": 2381822,
        "name:xx": "Hayden Lake"
      }
    },
    {
      "geometry": {
        "type": "Point",
        "coordinates": [
          -123.1333,
          44.9
        ]
      },
      "type": "Feature",
      "properties": {
        "hierarchy": [
          "tgn:2381823",
          "tgn:1000001",
          "tgn:7012149",
          "tgn:1002794",
          "tgn:7007708",
          "tgn:7029392"
        ],
        "placetype": [
          "aat:300008680"
        ],
        "id": 2381823,
        "name:xx": "Hayden Lake"
      }
    },
    {
      "geometry": {
        "type": "Point",
        "coordinates": [
          -117.0667,
          45.3833
        ]
      },
      "type": "Feature",
      "properties": {
        "hierarchy": [
          "tgn:2381824",
          "tgn:1000001",
          "tgn:7012149",
          "tgn:2001722",
          "tgn:7007708",
          "tgn:7029392"
        ],
        "placetype": [
          "aat:300008680"
        ],
        "id": 2381824,
        "name:xx": "Hayden Lake"
      }
    },
    {
      "geometry": {
        "type": "Point",
        "coordinates": [
          -96,
          31.1667
        ]
      },
      "type": "Feature",
      "properties": {
        "hierarchy": [
          "tgn:2381825",
          "tgn:1000001",
          "tgn:7012149",
          "tgn:1002590",
          "tgn:7007826",
          "tgn:7029392"
        ],
        "placetype": [
          "aat:300008680"
        ],
        "id": 2381825,
        "name:xx": "Hayden Lake"
      }
    },
    {
      "geometry": {
        "type": "Point",
        "coordinates": [
          -110.8833,
          40.7167
        ]
      },
      "type": "Feature",
      "properties": {
        "hierarchy": [
          "tgn:2381826",
          "tgn:1000001",
          "tgn:7012149",
          "tgn:2002122",
          "tgn:7007827",
          "tgn:7029392"
        ],
        "placetype": [
          "aat:300008680"
        ],
        "id": 2381826,
        "name:xx": "Hayden Lake"
      }
    },
    {
      "geometry": {
        "type": "Point",
        "coordinates": [
          -92.35,
          45.9667
        ]
      },
      "type": "Feature",
      "properties": {
        "hierarchy": [
          "tgn:2381827",
          "tgn:1000001",
          "tgn:2002311",
          "tgn:7012149",
          "tgn:7007922",
          "tgn:7029392"
        ],
        "placetype": [
          "aat:300008680"
        ],
        "id": 2381827,
        "name:xx": "Hayden Lake"
      }
    },
    {
      "geometry": {
        "type": "Point",
        "coordinates": [
          -70.1667,
          45.3
        ]
      },
      "type": "Feature",
      "properties": {
        "hierarchy": [
          "tgn:2381828",
          "tgn:1000001",
          "tgn:7012149",
          "tgn:2000930",
          "tgn:7007515",
          "tgn:7029392"
        ],
        "placetype": [
          "aat:300008347"
        ],
        "id": 2381828,
        "name:xx": "Hayden Landing"
      }
    },
    {
      "geometry": {
        "type": "Point",
        "coordinates": [
          -114.6833,
          32.6167
        ]
      },
      "type": "Feature",
      "properties": {
        "hierarchy": [
          "tgn:2381829",
          "tgn:1000001",
          "tgn:7006451",
          "tgn:7012149",
          "tgn:2000104",
          "tgn:7029392"
        ],
        "placetype": [
          "aat:300006075"
        ],
        "id": 2381829,
        "name:xx": "Hayden Lateral"
      }
    }
  ]
}
