{
  "geometry": {
    "type": "Point",
    "coordinates": [
      -111.85,
      33.9667
    ]
  },
  "type": "Feature",
  "properties": {
    "hierarchy": [
      "tgn:2495647",
      "tgn:1000001",
      "tgn:7006451",
      "tgn:7012149",
      "tgn:2000097",
      "tgn:7029392"
    ],
    "placetype": [
      "aat:300008697"
    ],
    "id": 2495647,
    "name:xx": "Mashakattee Spring"
  }
}
