{
  "geometry": {
    "type": "Point",
    "coordinates": [
      -114.2333,
      47.6667
    ]
  },
  "type": "Feature",
  "properties": {
    "hierarchy": [
      "tgn:2745839",
      "tgn:1000001",
      "tgn:7012149",
      "tgn:2001283",
      "tgn:7007524",
      "tgn:7029392"
    ],
    "placetype": [
      "aat:300008850"
    ],
    "id": 2745839,
    "name:xx": "Vista Point"
  }
}
