{
  "geometry": {
    "type": "Point",
    "coordinates": [
      -166.4667,
      64.7833
    ]
  },
  "type": "Feature",
  "properties": {
    "hierarchy": [
      "tgn:2220629",
      "tgn:7006450",
      "tgn:1000001",
      "tgn:7012149",
      "tgn:2000079",
      "tgn:7029392"
    ],
    "placetype": [
      "aat:300008850"
    ],
    "id": 2220629,
    "name:xx": "Cape Woolley"
  }
}
