{
  "geometry": {
    "type": "Point",
    "coordinates": [
      -119.4833,
      45.0167
    ]
  },
  "type": "Feature",
  "properties": {
    "hierarchy": [
      "tgn:2524869",
      "tgn:1000001",
      "tgn:7012149",
      "tgn:2001719",
      "tgn:7007708",
      "tgn:7029392"
    ],
    "placetype": [
      "aat:300008761"
    ],
    "id": 2524869,
    "name:xx": "Morphine Canyon"
  }
}
