{
  "geometry": {
    "type": "Point",
    "coordinates": [
      -91.8833,
      31.25
    ]
  },
  "type": "Feature",
  "properties": {
    "hierarchy": [
      "tgn:2715490",
      "tgn:2000858",
      "tgn:1000001",
      "tgn:7012149",
      "tgn:7007256",
      "tgn:7029392"
    ],
    "placetype": [
      "aat:300266640"
    ],
    "id": 2715490,
    "name:xx": "Terre Chene Blanc"
  }
}
