{
  "geometry": {
    "type": "Point",
    "coordinates": [
      117.3333,
      8.4167
    ]
  },
  "type": "Feature",
  "properties": {
    "hierarchy": [
      "tgn:1112851",
      "tgn:1000004",
      "tgn:1001481",
      "tgn:1000135",
      "tgn:7029392"
    ],
    "placetype": [
      "aat:300132316"
    ],
    "id": 1112851,
    "name:xx": "Coral Bay"
  }
}
