{
  "geometry": {
    "type": "Point",
    "coordinates": [
      -87.8333,
      45.95
    ]
  },
  "type": "Feature",
  "properties": {
    "hierarchy": [
      "tgn:2215470",
      "tgn:1000001",
      "tgn:2000956",
      "tgn:7012149",
      "tgn:7007520",
      "tgn:7029392"
    ],
    "placetype": [
      "aat:300000390"
    ],
    "id": 2215470,
    "name:xx": "Calumet Mine"
  }
}
