{
  "geometry": {
    "type": "Point",
    "coordinates": [
      -70.8167,
      42.7333
    ]
  },
  "type": "Feature",
  "properties": {
    "hierarchy": [
      "tgn:2393828",
      "tgn:1000001",
      "tgn:1002359",
      "tgn:7012149",
      "tgn:7007517",
      "tgn:7029392"
    ],
    "placetype": [
      "aat:300386853"
    ],
    "id": 2393828,
    "name:xx": "Hog Islands"
  }
}
