{
  "geometry": {
    "type": "Point",
    "coordinates": [
      -112.0833,
      41.5167
    ]
  },
  "type": "Feature",
  "properties": {
    "hierarchy": [
      "tgn:2402078",
      "tgn:1000001",
      "tgn:2002102",
      "tgn:7012149",
      "tgn:7007827",
      "tgn:7029392"
    ],
    "placetype": [
      "aat:300008680"
    ],
    "id": 2402078,
    "name:xx": "Horseshoe Sloughs"
  }
}
