{
  "geometry": {
    "type": "Point",
    "coordinates": [
      10.65,
      47.95
    ]
  },
  "type": "Feature",
  "properties": {
    "hierarchy": [
      "tgn:7143093",
      "tgn:7003669",
      "tgn:1000003",
      "tgn:7000084",
      "tgn:7029392"
    ],
    "placetype": [
      "aat:300008777"
    ],
    "id": 7143093,
    "name:xx": "Linden Berg"
  }
}
