{
  "geometry": {
    "type": "Point",
    "coordinates": [
      -135.35,
      56.8833
    ]
  },
  "type": "Feature",
  "properties": {
    "hierarchy": [
      "tgn:2431062",
      "tgn:7006450",
      "tgn:1000001",
      "tgn:7012149",
      "tgn:2124002",
      "tgn:7029392"
    ],
    "placetype": [
      "aat:300132316"
    ],
    "id": 2431062,
    "name:xx": "Kanga Bay"
  }
}
