{
  "geometry": {
    "type": "Point",
    "coordinates": [
      -113.1167,
      37.15
    ]
  },
  "type": "Feature",
  "properties": {
    "hierarchy": [
      "tgn:2570191",
      "tgn:1000001",
      "tgn:7012149",
      "tgn:2002127",
      "tgn:7007827",
      "tgn:7029392"
    ],
    "placetype": [
      "aat:300266640"
    ],
    "id": 2570191,
    "name:xx": "Pastry Ridge"
  }
}
