{
  "type": "FeatureCollection",
  "features": [
    {
      "geometry": {
        "type": "Point",
        "coordinates": [
          135.4667,
          34.6
        ]
      },
      "type": "Feature",
      "properties": {
        "hierarchy": [
          "tgn:1005680",
          "tgn:1000004",
          "tgn:1000962",
          "tgn:7000896",
          "tgn:7004756",
          "tgn:1000120",
          "tgn:7029392"
        ],
        "placetype": [
          "aat:300000745"
        ],
        "id": 1005680,
        "name:xx": "Suminoe"
      }
    },
    {
      "geometry": {
        "type": "Point",
        "coordinates": [
          135.5,
          34.6167
        ]
      },
      "type": "Feature",
      "properties": {
        "hierarchy": [
          "tgn:1005681",
          "tgn:1000004",
          "tgn:1000962",
          "tgn:7000896",
          "tgn:7004756",
          "tgn:1000120",
          "tgn:7029392"
        ],
        "placetype": [
          "aat:300000745"
        ],
        "id": 1005681,
        "name:xx": "Sumiyoshi"
      }
    },
    {
      "geometry": {
        "type": "Point",
        "coordinates": [
          106.9,
          -6.15
        ]
      },
      "type": "Feature",
      "properties": {
        "hierarchy": [
          "tgn:1005685",
          "tgn:7002854",
          "tgn:1001318",
          "tgn:1000004",
          "tgn:1000116",
          "tgn:7029392"
        ],
        "placetype": [
          "aat:300000745"
        ],
        "id": 1005685,
        "name:xx": "Sunter"
      }
    },
    {
      "geometry": {
        "type": "Point",
        "coordinates": [
          88.4167,
          22.55
        ]
      },
      "type": "Feature",
      "properties": {
        "hierarchy": [
          "tgn:1005686",
          "tgn:1000004",
          "tgn:7000198",
          "tgn:1001977",
          "tgn:7030776",
          "tgn:7029392"
        ],
        "placetype": [
          "aat:300000745"
        ],
        "id": 1005686,
        "name:xx": "Sura"
      }
    },
    {
      "geometry": {
        "type": "Point",
        "coordinates": [
          -0.3,
          51.3833
        ]
      },
      "type": "Feature",
      "properties": {
        "hierarchy": [
          "tgn:1005687",
          "tgn:7002445",
          "tgn:7018901",
          "tgn:1000003",
          "tgn:7008136",
          "tgn:7008591",
          "tgn:7029392"
        ],
        "placetype": [
          "aat:300008347",
          "aat:300000745"
        ],
        "name:en": "Surbiton",
        "id": 1005687
      }
    },
    {
      "geometry": {
        "type": "Point",
        "coordinates": [
          3.35,
          6.5
        ]
      },
      "type": "Feature",
      "properties": {
        "hierarchy": [
          "tgn:1005688",
          "tgn:7001242",
          "tgn:1001889",
          "tgn:7000497",
          "tgn:1000182",
          "tgn:7029392"
        ],
        "placetype": [
          "aat:300000745"
        ],
        "id": 1005688,
        "name:xx": "Suru Lere"
      }
    }
  ]
}
