{
  "geometry": {
    "type": "Point",
    "coordinates": [
      72.924848,
      27.735
    ]
  },
  "type": "Feature",
  "properties": {
    "hierarchy": [
      "tgn:7583259",
      "tgn:1000004",
      "tgn:7000198",
      "tgn:7016788",
      "tgn:7029392"
    ],
    "placetype": [
      "aat:300008347"
    ],
    "name:en": "Khetolāi Mūlvān",
    "id": 7583259
  }
}
