{
  "geometry": {
    "type": "Point",
    "coordinates": [
      75.1618,
      28.4102
    ]
  },
  "type": "Feature",
  "properties": {
    "hierarchy": [
      "tgn:7584173",
      "tgn:1000004",
      "tgn:7000198",
      "tgn:7016788",
      "tgn:7029392"
    ],
    "placetype": [
      "aat:300008688"
    ],
    "name:en": "Pīpāna Johra",
    "id": 7584173
  }
}
