{
  "geometry": {
    "type": "Point",
    "coordinates": [
      -72.9667,
      44.9667
    ]
  },
  "type": "Feature",
  "properties": {
    "hierarchy": [
      "tgn:2198283",
      "tgn:1000001",
      "tgn:1002389",
      "tgn:7012149",
      "tgn:7007828",
      "tgn:7029392"
    ],
    "placetype": [
      "aat:300008347"
    ],
    "id": 2198283,
    "name:xx": "Browns Corners"
  }
}
