{
  "geometry": {
    "type": "Point",
    "coordinates": [
      -4.283333,
      42.05
    ]
  },
  "type": "Feature",
  "properties": {
    "hierarchy": [
      "tgn:7346199",
      "tgn:7002832",
      "tgn:7001158",
      "tgn:1000003",
      "tgn:1000095",
      "tgn:7029392"
    ],
    "placetype": [
      "aat:300008699"
    ],
    "id": 7346199,
    "name:xx": "Arlanzón, Río"
  }
}
