{
  "geometry": {
    "type": "Point",
    "coordinates": [
      137.6833,
      35.3667
    ]
  },
  "type": "Feature",
  "properties": {
    "hierarchy": [
      "tgn:1080960",
      "tgn:7000895",
      "tgn:1000004",
      "tgn:1001010",
      "tgn:1000120",
      "tgn:7029392"
    ],
    "placetype": [
      "aat:300008347"
    ],
    "id": 1080960,
    "name:xx": "Namiai"
  }
}
