{
  "geometry": {
    "type": "Point",
    "coordinates": [
      -87.5667,
      37.2833
    ]
  },
  "type": "Feature",
  "properties": {
    "hierarchy": [
      "tgn:2040627",
      "tgn:1000001",
      "tgn:7012149",
      "tgn:2000801",
      "tgn:7007255",
      "tgn:7029392"
    ],
    "placetype": [
      "aat:300387016"
    ],
    "id": 2040627,
    "name:xx": "Oriole"
  }
}
