{
  "geometry": {
    "type": "Point",
    "coordinates": [
      -105.59,
      24.15
    ]
  },
  "type": "Feature",
  "properties": {
    "hierarchy": [
      "tgn:7358591",
      "tgn:7005583",
      "tgn:1000001",
      "tgn:7005560",
      "tgn:7029392"
    ],
    "placetype": [
      "aat:300000241"
    ],
    "id": 7358591,
    "name:xx": "Rancho El Aceteado"
  }
}
