{
  "geometry": {
    "type": "Point",
    "coordinates": [
      7.4333,
      6.0833
    ]
  },
  "type": "Feature",
  "properties": {
    "hierarchy": [
      "tgn:1091877",
      "tgn:7001242",
      "tgn:1001874",
      "tgn:1000182",
      "tgn:7029392"
    ],
    "placetype": [
      "aat:300008347"
    ],
    "id": 1091877,
    "name:xx": "Awgu"
  }
}
