{
  "geometry": {
    "type": "Point",
    "coordinates": [
      -82.45,
      39.05
    ]
  },
  "type": "Feature",
  "properties": {
    "hierarchy": [
      "tgn:2202802",
      "tgn:1000001",
      "tgn:7012149",
      "tgn:2001614",
      "tgn:7007706",
      "tgn:7029392"
    ],
    "placetype": [
      "aat:300008347"
    ],
    "id": 2202802,
    "name:xx": "Buckeye"
  }
}
