{
  "geometry": {
    "type": "Point",
    "coordinates": [
      121.5228,
      25.0258
    ]
  },
  "type": "Feature",
  "properties": {
    "hierarchy": [
      "tgn:7499996",
      "tgn:1000004",
      "tgn:1000959",
      "tgn:1000141",
      "tgn:7029392"
    ],
    "placetype": [
      "aat:300007783"
    ],
    "id": 7499996,
    "name:xx": "Guting Zhan"
  }
}
