{
  "geometry": {
    "type": "Point",
    "coordinates": [
      120.2323,
      23.4692
    ]
  },
  "type": "Feature",
  "properties": {
    "hierarchy": [
      "tgn:7480474",
      "tgn:7468018",
      "tgn:1000004",
      "tgn:1000141",
      "tgn:7029392"
    ],
    "placetype": [
      "aat:300008347"
    ],
    "id": 7480474,
    "name:xx": "Yanbuzi"
  }
}
