{
  "geometry": {
    "type": "Point",
    "coordinates": [
      -83.45,
      43.7167
    ]
  },
  "type": "Feature",
  "properties": {
    "hierarchy": [
      "tgn:2757531",
      "tgn:1000001",
      "tgn:7012149",
      "tgn:7007520",
      "tgn:7029392"
    ],
    "placetype": [
      "aat:300006075"
    ],
    "id": 2757531,
    "name:xx": "West Branch"
  }
}
