{
  "geometry": {
    "type": "Point",
    "coordinates": [
      -85.6833,
      34.95
    ]
  },
  "type": "Feature",
  "properties": {
    "hierarchy": [
      "tgn:2467654",
      "tgn:7002659",
      "tgn:1000001",
      "tgn:7012149",
      "tgn:2000035",
      "tgn:7029392"
    ],
    "placetype": [
      "aat:300008791"
    ],
    "id": 2467654,
    "name:xx": "Long Island"
  }
}
