{
  "geometry": {
    "type": "Point",
    "coordinates": [
      -89.2833,
      34.3667
    ]
  },
  "type": "Feature",
  "properties": {
    "hierarchy": [
      "tgn:2447001",
      "tgn:1000001",
      "tgn:7012149",
      "tgn:2001121",
      "tgn:7007522",
      "tgn:7029392"
    ],
    "placetype": [
      "aat:300008798"
    ],
    "id": 2447001,
    "name:xx": "Liberty Hill"
  }
}
