{
  "geometry": {
    "type": "Point",
    "coordinates": [
      -91.0333,
      31.4333
    ]
  },
  "type": "Feature",
  "properties": {
    "hierarchy": [
      "tgn:2625811",
      "tgn:1000001",
      "tgn:7012149",
      "tgn:2001104",
      "tgn:7007522",
      "tgn:7029392"
    ],
    "placetype": [
      "aat:300008699"
    ],
    "id": 2625811,
    "name:xx": "Rocky Branch"
  }
}
