{
  "type": "FeatureCollection",
  "features": [
    {
      "geometry": {
        "type": "Point",
        "coordinates": [
          -66.5833,
          18.1667
        ]
      },
      "type": "Feature",
      "properties": {
        "hierarchy": [
          "tgn:1108880",
          "tgn:7005666",
          "tgn:1000001",
          "tgn:7004643",
          "tgn:7029392"
        ],
        "placetype": [
          "aat:300386831"
        ],
        "id": 1108880,
        "name:xx": "Central, Cordillera"
      }
    },
    {
      "geometry": {
        "type": "Point",
        "coordinates": [
          -75,
          5
        ]
      },
      "type": "Feature",
      "properties": {
        "hierarchy": [
          "tgn:1108881",
          "tgn:1000050",
          "tgn:1000002",
          "tgn:7029392"
        ],
        "placetype": [
          "aat:300386831"
        ],
        "id": 1108881,
        "name:xx": "Cordillera Central"
      }
    },
    {
      "geometry": {
        "type": "Point",
        "coordinates": [
          -76.5,
          -8.5
        ]
      },
      "type": "Feature",
      "properties": {
        "hierarchy": [
          "tgn:1108882",
          "tgn:1000002",
          "tgn:1000056",
          "tgn:7029392"
        ],
        "placetype": [
          "aat:300386831"
        ],
        "id": 1108882,
        "name:xx": "Central, Cordillera"
      }
    },
    {
      "geometry": {
        "type": "Point",
        "coordinates": [
          120.95,
          17.3333
        ]
      },
      "type": "Feature",
      "properties": {
        "hierarchy": [
          "tgn:1108883",
          "tgn:1000004",
          "tgn:7016720",
          "tgn:1000135",
          "tgn:7029392"
        ],
        "placetype": [
          "aat:300386831"
        ],
        "id": 1108883,
        "name:xx": "Central, Cordillera"
      }
    },
    {
      "geometry": {
        "type": "Point",
        "coordinates": [
          134,
          35.25
        ]
      },
      "type": "Feature",
      "properties": {
        "hierarchy": [
          "tgn:1108887",
          "tgn:7016674",
          "tgn:1000004",
          "tgn:1000120",
          "tgn:7029392"
        ],
        "placetype": [
          "aat:300008795"
        ],
        "id": 1108887,
        "name:xx": "Chugoku-sanchi"
      }
    },
    {
      "geometry": {
        "type": "Point",
        "coordinates": [
          -99.25,
          22.75
        ]
      },
      "type": "Feature",
      "properties": {
        "hierarchy": [
          "tgn:1108888",
          "tgn:1000001",
          "tgn:7005597",
          "tgn:7005560",
          "tgn:7029392"
        ],
        "placetype": [
          "aat:300008795"
        ],
        "id": 1108888,
        "name:xx": "Chamal, Sierra"
      }
    },
    {
      "geometry": {
        "type": "Point",
        "coordinates": [
          100,
          47.5
        ]
      },
      "type": "Feature",
      "properties": {
        "hierarchy": [
          "tgn:1108889",
          "tgn:1000004",
          "tgn:7029379",
          "tgn:7029392"
        ],
        "placetype": [
          "aat:300386831"
        ],
        "id": 1108889,
        "name:xx": "Hangayn Nuruu"
      }
    }
  ]
}
