{
  "geometry": {
    "type": "Point",
    "coordinates": [
      16.8333,
      -27.1667
    ]
  },
  "type": "Feature",
  "properties": {
    "hierarchy": [
      "tgn:1110300",
      "tgn:7001242",
      "tgn:1000198",
      "tgn:7029392"
    ],
    "placetype": [
      "aat:300132339"
    ],
    "id": 1110300,
    "name:xx": "Huib-Hoch Plateau"
  }
}
