{
  "geometry": {
    "type": "Point",
    "coordinates": [
      -122.3167,
      37.2667
    ]
  },
  "type": "Feature",
  "properties": {
    "hierarchy": [
      "tgn:2352389",
      "tgn:1000001",
      "tgn:7012149",
      "tgn:7007157",
      "tgn:1002864",
      "tgn:7029392"
    ],
    "placetype": [
      "aat:300008798"
    ],
    "id": 2352389,
    "name:xx": "Goat Hill"
  }
}
