{
  "geometry": {
    "type": "Point",
    "coordinates": [
      -105.8333,
      44.9167
    ]
  },
  "type": "Feature",
  "properties": {
    "hierarchy": [
      "tgn:2266951",
      "tgn:1000001",
      "tgn:2002367",
      "tgn:7012149",
      "tgn:7007923",
      "tgn:7029392"
    ],
    "placetype": [
      "aat:300008761"
    ],
    "id": 2266951,
    "name:xx": "Cresswell Draw"
  }
}
