{
  "geometry": {
    "type": "Point",
    "coordinates": [
      -98.3667,
      44.0333
    ]
  },
  "type": "Feature",
  "properties": {
    "hierarchy": [
      "tgn:2298500",
      "tgn:1000001",
      "tgn:7012149",
      "tgn:7007713",
      "tgn:7029392"
    ],
    "placetype": [
      "aat:300008699"
    ],
    "id": 2298500,
    "name:xx": "Dry Run"
  }
}
