{
  "type": "FeatureCollection",
  "features": [
    {
      "geometry": {
        "type": "Point",
        "coordinates": [
          8.566667,
          54.566667
        ]
      },
      "type": "Feature",
      "properties": {
        "hierarchy": [
          "tgn:1007432",
          "tgn:1000003",
          "tgn:7003688",
          "tgn:7000084",
          "tgn:7029392"
        ],
        "placetype": [
          "aat:300008791"
        ],
        "id": 1007432,
        "name:xx": "Hooge"
      }
    },
    {
      "geometry": {
        "type": "Point",
        "coordinates": [
          -127.9167,
          50.9167
        ]
      },
      "type": "Feature",
      "properties": {
        "hierarchy": [
          "tgn:1007434",
          "tgn:7005735",
          "tgn:7005685",
          "tgn:1000001",
          "tgn:7029392"
        ],
        "placetype": [
          "aat:300008791"
        ],
        "id": 1007434,
        "name:xx": "Hope Island"
      }
    },
    {
      "geometry": {
        "type": "Point",
        "coordinates": [
          -80.2,
          44.9167
        ]
      },
      "type": "Feature",
      "properties": {
        "hierarchy": [
          "tgn:1007435",
          "tgn:7005685",
          "tgn:1000001",
          "tgn:7013154",
          "tgn:7029392"
        ],
        "placetype": [
          "aat:300008791"
        ],
        "id": 1007435,
        "name:xx": "Hope Island"
      }
    },
    {
      "geometry": {
        "type": "Point",
        "coordinates": [
          -88.6833,
          30.2333
        ]
      },
      "type": "Feature",
      "properties": {
        "hierarchy": [
          "tgn:1007437",
          "tgn:1000001",
          "tgn:7012149",
          "tgn:2001115",
          "tgn:7007522",
          "tgn:7029392"
        ],
        "placetype": [
          "aat:300008791"
        ],
        "id": 1007437,
        "name:xx": "Horn Island"
      }
    },
    {
      "geometry": {
        "type": "Point",
        "coordinates": [
          -67.283333,
          -55.95
        ]
      },
      "type": "Feature",
      "properties": {
        "hierarchy": [
          "tgn:1007439",
          "tgn:1001702",
          "tgn:1000049",
          "tgn:1000002",
          "tgn:1010391",
          "tgn:7029392"
        ],
        "placetype": [
          "aat:300008791"
        ],
        "id": 1007439,
        "name:xx": "Hornos, Isla"
      }
    }
  ]
}
