{
  "type": "FeatureCollection",
  "features": [
    {
      "geometry": {
        "type": "Point",
        "coordinates": [
          -96.05,
          29.6333
        ]
      },
      "type": "Feature",
      "properties": {
        "hierarchy": [
          "tgn:2316140",
          "tgn:1000001",
          "tgn:7012149",
          "tgn:7007826",
          "tgn:7029392"
        ],
        "placetype": [
          "aat:300008699"
        ],
        "id": 2316140,
        "name:xx": "Elm Slough"
      }
    },
    {
      "geometry": {
        "type": "Point",
        "coordinates": [
          -99.8,
          30.5833
        ]
      },
      "type": "Feature",
      "properties": {
        "hierarchy": [
          "tgn:2316141",
          "tgn:1000001",
          "tgn:7012149",
          "tgn:2002019",
          "tgn:7007826",
          "tgn:7029392"
        ],
        "placetype": [
          "aat:300008699"
        ],
        "id": 2316141,
        "name:xx": "Elm Slough"
      }
    },
    {
      "geometry": {
        "type": "Point",
        "coordinates": [
          -99.1667,
          29.3667
        ]
      },
      "type": "Feature",
      "properties": {
        "hierarchy": [
          "tgn:2316142",
          "tgn:1000001",
          "tgn:7012149",
          "tgn:2002039",
          "tgn:7007826",
          "tgn:7029392"
        ],
        "placetype": [
          "aat:300008699"
        ],
        "id": 2316142,
        "name:xx": "Elm Slough"
      }
    },
    {
      "geometry": {
        "type": "Point",
        "coordinates": [
          -99.9167,
          29.3667
        ]
      },
      "type": "Feature",
      "properties": {
        "hierarchy": [
          "tgn:2316143",
          "tgn:1000001",
          "tgn:7012149",
          "tgn:2002087",
          "tgn:7007826",
          "tgn:7029392"
        ],
        "placetype": [
          "aat:300008699"
        ],
        "id": 2316143,
        "name:xx": "Elm Slough"
      }
    },
    {
      "geometry": {
        "type": "Point",
        "coordinates": [
          -98.6333,
          28.2167
        ]
      },
      "type": "Feature",
      "properties": {
        "hierarchy": [
          "tgn:2316144",
          "tgn:1000001",
          "tgn:7012149",
          "tgn:2002035",
          "tgn:7007826",
          "tgn:7029392"
        ],
        "placetype": [
          "aat:300008699"
        ],
        "id": 2316144,
        "name:xx": "Elm Slue"
      }
    },
    {
      "geometry": {
        "type": "Point",
        "coordinates": [
          -93.6667,
          36.1167
        ]
      },
      "type": "Feature",
      "properties": {
        "hierarchy": [
          "tgn:2316145",
          "tgn:1000001",
          "tgn:7016172",
          "tgn:7012149",
          "tgn:2000148",
          "tgn:7029392"
        ],
        "placetype": [
          "aat:300008697"
        ],
        "id": 2316145,
        "name:xx": "Elm Spring"
      }
    },
    {
      "geometry": {
        "type": "Point",
        "coordinates": [
          -96.4833,
          43.3
        ]
      },
      "type": "Feature",
      "properties": {
        "hierarchy": [
          "tgn:2316146",
          "tgn:1000001",
          "tgn:7012149",
          "tgn:2000644",
          "tgn:7007253",
          "tgn:7029392"
        ],
        "placetype": [
          "aat:300008347"
        ],
        "id": 2316146,
        "name:xx": "Elm Spring"
      }
    },
    {
      "geometry": {
        "type": "Point",
        "coordinates": [
          -94.3167,
          36.8
        ]
      },
      "type": "Feature",
      "properties": {
        "hierarchy": [
          "tgn:2316147",
          "tgn:1000001",
          "tgn:7012149",
          "tgn:2001223",
          "tgn:7007523",
          "tgn:7029392"
        ],
        "placetype": [
          "aat:300008697"
        ],
        "id": 2316147,
        "name:xx": "Elm Spring"
      }
    },
    {
      "geometry": {
        "type": "Point",
        "coordinates": [
          -93.6,
          36.95
        ]
      },
      "type": "Feature",
      "properties": {
        "hierarchy": [
          "tgn:2316148",
          "tgn:1000001",
          "tgn:7012149",
          "tgn:7007523",
          "tgn:7029392"
        ],
        "placetype": [
          "aat:300008697"
        ],
        "id": 2316148,
        "name:xx": "Elm Spring"
      }
    },
    {
      "geometry": {
        "type": "Point",
        "coordinates": [
          -93.1833,
          37.3333
        ]
      },
      "type": "Feature",
      "properties": {
        "hierarchy": [
          "tgn:2316149",
          "tgn:1000001",
          "tgn:7012149",
          "tgn:2001199",
          "tgn:7007523",
          "tgn:7029392"
        ],
        "placetype": [
          "aat:300008697"
        ],
        "id": 2316149,
        "name:xx": "Elm Spring"
      }
    }
  ]
}
