{
  "geometry": {
    "type": "Point",
    "coordinates": [
      -110.0667,
      32.7333
    ]
  },
  "type": "Feature",
  "properties": {
    "hierarchy": [
      "tgn:2375411",
      "tgn:1000001",
      "tgn:7006451",
      "tgn:2000094",
      "tgn:7012149",
      "tgn:7029392"
    ],
    "placetype": [
      "aat:300008761"
    ],
    "id": 2375411,
    "name:xx": "Hansen Canyon"
  }
}
