{
  "type": "FeatureCollection",
  "features": [
    {
      "geometry": {
        "type": "Point",
        "coordinates": [
          -113.6,
          48.5
        ]
      },
      "type": "Feature",
      "properties": {
        "hierarchy": [
          "tgn:1106571",
          "tgn:1000001",
          "tgn:7012149",
          "tgn:2001274",
          "tgn:7007524",
          "tgn:7029392"
        ],
        "placetype": [
          "aat:300008795"
        ],
        "id": 1106571,
        "name:xx": "Stimson, Mount"
      }
    },
    {
      "geometry": {
        "type": "Point",
        "coordinates": [
          -113.1,
          45.7167
        ]
      },
      "type": "Feature",
      "properties": {
        "hierarchy": [
          "tgn:1106572",
          "tgn:1000001",
          "tgn:2001260",
          "tgn:7012149",
          "tgn:7007524",
          "tgn:7029392"
        ],
        "placetype": [
          "aat:300008795"
        ],
        "id": 1106572,
        "name:xx": "Stine Mountain"
      }
    },
    {
      "geometry": {
        "type": "Point",
        "coordinates": [
          -2.9333,
          52.5833
        ]
      },
      "type": "Feature",
      "properties": {
        "hierarchy": [
          "tgn:1106573",
          "tgn:7002445",
          "tgn:1000003",
          "tgn:7012034",
          "tgn:7008591",
          "tgn:7029392"
        ],
        "placetype": [
          "aat:300008795"
        ],
        "id": 1106573,
        "name:xx": "Stiperstones"
      }
    },
    {
      "geometry": {
        "type": "Point",
        "coordinates": [
          -73.6833,
          41.95
        ]
      },
      "type": "Feature",
      "properties": {
        "hierarchy": [
          "tgn:1106575",
          "tgn:1000001",
          "tgn:1002347",
          "tgn:7012149",
          "tgn:7007568",
          "tgn:7029392"
        ],
        "placetype": [
          "aat:300008795"
        ],
        "id": 1106575,
        "name:xx": "Stissing Mountain"
      }
    },
    {
      "geometry": {
        "type": "Point",
        "coordinates": [
          -117.1167,
          34.6833
        ]
      },
      "type": "Feature",
      "properties": {
        "hierarchy": [
          "tgn:1106576",
          "tgn:1000001",
          "tgn:7012149",
          "tgn:7007157",
          "tgn:1002857",
          "tgn:7029392"
        ],
        "placetype": [
          "aat:300008795"
        ],
        "id": 1106576,
        "name:xx": "Stoddard Mountain"
      }
    },
    {
      "geometry": {
        "type": "Point",
        "coordinates": [
          174.1,
          -41.1
        ]
      },
      "type": "Feature",
      "properties": {
        "hierarchy": [
          "tgn:1106578",
          "tgn:1009227",
          "tgn:1000226",
          "tgn:7016729",
          "tgn:1000006",
          "tgn:7029392"
        ],
        "placetype": [
          "aat:300008795"
        ],
        "name:en": "Stokes, Mount",
        "id": 1106578
      }
    },
    {
      "geometry": {
        "type": "Point",
        "coordinates": [
          22.2333,
          44.2167
        ]
      },
      "type": "Feature",
      "properties": {
        "hierarchy": [
          "tgn:1106579",
          "tgn:1000003",
          "tgn:7006669",
          "tgn:7029392"
        ],
        "placetype": [
          "aat:300008795"
        ],
        "id": 1106579,
        "name:xx": "Stol"
      }
    }
  ]
}
