{
  "geometry": {
    "type": "Point",
    "coordinates": [
      -110.1667,
      38.25
    ]
  },
  "type": "Feature",
  "properties": {
    "hierarchy": [
      "tgn:2688806",
      "tgn:1000001",
      "tgn:7012149",
      "tgn:2002128",
      "tgn:7007827",
      "tgn:7029392"
    ],
    "placetype": [
      "aat:300008761"
    ],
    "id": 2688806,
    "name:xx": "Spur Fork"
  }
}
