{
  "geometry": {
    "type": "Point",
    "coordinates": [
      -141.8667,
      63.1167
    ]
  },
  "type": "Feature",
  "properties": {
    "hierarchy": [
      "tgn:2679164",
      "tgn:7006450",
      "tgn:1000001",
      "tgn:7012149",
      "tgn:2000085",
      "tgn:7029392"
    ],
    "placetype": [
      "aat:300008707"
    ],
    "id": 2679164,
    "name:xx": "South Fork Ladue River"
  }
}
