{
  "geometry": {
    "type": "Point",
    "coordinates": [
      -81.7167,
      38.1833
    ]
  },
  "type": "Feature",
  "properties": {
    "hierarchy": [
      "tgn:2117970",
      "tgn:1000001",
      "tgn:2002255",
      "tgn:7012149",
      "tgn:7013961",
      "tgn:7029392"
    ],
    "placetype": [
      "aat:300008347",
      "aat:300387210"
    ],
    "id": 2117970,
    "name:xx": "Dartmont"
  }
}
