{
  "geometry": {
    "type": "Point",
    "coordinates": [
      -86.95,
      36.4167
    ]
  },
  "type": "Feature",
  "properties": {
    "hierarchy": [
      "tgn:2214626",
      "tgn:1000001",
      "tgn:7012149",
      "tgn:2001910",
      "tgn:7007825",
      "tgn:7029392"
    ],
    "placetype": [
      "aat:300008706"
    ],
    "id": 2214626,
    "name:xx": "Calebs Creek"
  }
}
