{
  "geometry": {
    "type": "Point",
    "coordinates": [
      75.75,
      43.5167
    ]
  },
  "type": "Feature",
  "properties": {
    "hierarchy": [
      "tgn:1055602",
      "tgn:1003353",
      "tgn:1000004",
      "tgn:7014786",
      "tgn:7029392"
    ],
    "placetype": [
      "aat:300008347"
    ],
    "id": 1055602,
    "name:xx": "Kopa"
  }
}
