{
  "geometry": {
    "type": "Point",
    "coordinates": [
      -72.5167,
      40.8333
    ]
  },
  "type": "Feature",
  "properties": {
    "hierarchy": [
      "tgn:2482077",
      "tgn:1000001",
      "tgn:7012149",
      "tgn:1002924",
      "tgn:7007568",
      "tgn:7029392"
    ],
    "placetype": [
      "aat:300008791"
    ],
    "id": 2482077,
    "name:xx": "Lanes Island"
  }
}
