{
  "type": "FeatureCollection",
  "features": [
    {
      "geometry": {
        "type": "Point",
        "coordinates": [
          8.333333,
          44.833333
        ]
      },
      "type": "Feature",
      "properties": {
        "hierarchy": [
          "tgn:7054470",
          "tgn:1003428",
          "tgn:1000003",
          "tgn:7003120",
          "tgn:1000080",
          "tgn:7029392"
        ],
        "placetype": [
          "aat:300386856"
        ],
        "id": 7054470,
        "name:xx": "Monferrato, Alto"
      }
    },
    {
      "geometry": {
        "type": "Point",
        "coordinates": [
          9.433333,
          41.216667
        ]
      },
      "type": "Feature",
      "properties": {
        "hierarchy": [
          "tgn:7054473",
          "tgn:7015163",
          "tgn:1000003",
          "tgn:7003121",
          "tgn:1000080",
          "tgn:7029392"
        ],
        "placetype": [
          "aat:300386846"
        ],
        "id": 7054473,
        "name:xx": "Moneta, Punta"
      }
    },
    {
      "geometry": {
        "type": "Point",
        "coordinates": [
          9.433333,
          41.216667
        ]
      },
      "type": "Feature",
      "properties": {
        "hierarchy": [
          "tgn:7054474",
          "tgn:7015163",
          "tgn:1000003",
          "tgn:7003121",
          "tgn:1000080",
          "tgn:7029392"
        ],
        "placetype": [
          "aat:300266559"
        ],
        "id": 7054474,
        "name:xx": "Moneta, Passo della"
      }
    },
    {
      "geometry": {
        "type": "Point",
        "coordinates": [
          13.5,
          41.25
        ]
      },
      "type": "Feature",
      "properties": {
        "hierarchy": [
          "tgn:7054475",
          "tgn:7003136",
          "tgn:1000003",
          "tgn:7003080",
          "tgn:1000080",
          "tgn:7029392"
        ],
        "placetype": [
          "aat:300008795"
        ],
        "id": 7054475,
        "name:xx": "Moneta, Monte"
      }
    },
    {
      "geometry": {
        "type": "Point",
        "coordinates": [
          11.683333,
          44.733333
        ]
      },
      "type": "Feature",
      "properties": {
        "hierarchy": [
          "tgn:7054476",
          "tgn:7003128",
          "tgn:1000003",
          "tgn:7008516",
          "tgn:1000080",
          "tgn:7029392"
        ],
        "placetype": [
          "aat:300008347"
        ],
        "id": 7054476,
        "name:xx": "Monestirolo"
      }
    }
  ]
}
