{
  "geometry": {
    "type": "Point",
    "coordinates": [
      -110.0333,
      34.0167
    ]
  },
  "type": "Feature",
  "properties": {
    "hierarchy": [
      "tgn:2480276",
      "tgn:1000001",
      "tgn:7006451",
      "tgn:7012149",
      "tgn:7029392"
    ],
    "placetype": [
      "aat:300266640"
    ],
    "id": 2480276,
    "name:xx": "Lake Ridge"
  }
}
