{
  "geometry": {
    "type": "Point",
    "coordinates": [
      -82.0333,
      37.9333
    ]
  },
  "type": "Feature",
  "properties": {
    "hierarchy": [
      "tgn:2408035",
      "tgn:1000001",
      "tgn:7012149",
      "tgn:2002273",
      "tgn:7013961",
      "tgn:7029392"
    ],
    "placetype": [
      "aat:300008699"
    ],
    "id": 2408035,
    "name:xx": "Hurricane Fork"
  }
}
