{
  "geometry": {
    "type": "Point",
    "coordinates": [
      -95.0833,
      44.55
    ]
  },
  "type": "Feature",
  "properties": {
    "hierarchy": [
      "tgn:2055140",
      "tgn:1000001",
      "tgn:7012149",
      "tgn:2001062",
      "tgn:7007521",
      "tgn:7029392"
    ],
    "placetype": [
      "aat:300008347"
    ],
    "id": 2055140,
    "name:xx": "North Redwood"
  }
}
