{
  "geometry": {
    "type": "Point",
    "coordinates": [
      -114.4833,
      37.9167
    ]
  },
  "type": "Feature",
  "properties": {
    "hierarchy": [
      "tgn:2062835",
      "tgn:1000001",
      "tgn:2001416",
      "tgn:7012149",
      "tgn:7007526",
      "tgn:7029392"
    ],
    "placetype": [
      "aat:300008347"
    ],
    "id": 2062835,
    "name:xx": "Caselton"
  }
}
