{
  "geometry": {
    "type": "Point",
    "coordinates": [
      -117.7833,
      44.5167
    ]
  },
  "type": "Feature",
  "properties": {
    "hierarchy": [
      "tgn:2651862",
      "tgn:7013349",
      "tgn:1000001",
      "tgn:7012149",
      "tgn:7007708",
      "tgn:7029392"
    ],
    "placetype": [
      "aat:300008697"
    ],
    "id": 2651862,
    "name:xx": "Segundo Spring"
  }
}
