{
  "geometry": {
    "type": "Point",
    "coordinates": [
      76.991049,
      29.96965
    ]
  },
  "type": "Feature",
  "properties": {
    "hierarchy": [
      "tgn:7589918",
      "tgn:1000004",
      "tgn:1001871",
      "tgn:7000198",
      "tgn:7029392"
    ],
    "placetype": [
      "aat:300008347"
    ],
    "name:en": "Dūdhi",
    "id": 7589918
  }
}
