{
  "geometry": {
    "type": "Point",
    "coordinates": [
      -43.5833,
      -3.35
    ]
  },
  "type": "Feature",
  "properties": {
    "hierarchy": [
      "tgn:1022754",
      "tgn:7006246",
      "tgn:1000047",
      "tgn:7002455",
      "tgn:1000002",
      "tgn:7029392"
    ],
    "placetype": [
      "aat:300008347"
    ],
    "id": 1022754,
    "name:xx": "São Benedito do Rio Prêto"
  }
}
