{
  "geometry": {
    "type": "Point",
    "coordinates": [
      -97.0333,
      43.2833
    ]
  },
  "type": "Feature",
  "properties": {
    "hierarchy": [
      "tgn:2529519",
      "tgn:1000001",
      "tgn:7012149",
      "tgn:2001832",
      "tgn:7007713",
      "tgn:7029392"
    ],
    "placetype": [
      "aat:300008680"
    ],
    "id": 2529519,
    "name:xx": "Mud Lake"
  }
}
