{
  "geometry": {
    "type": "Point",
    "coordinates": [
      -121.0667,
      41.3167
    ]
  },
  "type": "Feature",
  "properties": {
    "hierarchy": [
      "tgn:2261796",
      "tgn:1000001",
      "tgn:7012149",
      "tgn:7007157",
      "tgn:2000186",
      "tgn:7029392"
    ],
    "placetype": [
      "aat:300008697"
    ],
    "id": 2261796,
    "name:xx": "Cove Spring"
  }
}
