{
  "geometry": {
    "type": "Point",
    "coordinates": [
      -116.7833,
      39.0333
    ]
  },
  "type": "Feature",
  "properties": {
    "hierarchy": [
      "tgn:2409685",
      "tgn:1000001",
      "tgn:2001418",
      "tgn:7012149",
      "tgn:7007526",
      "tgn:7029392"
    ],
    "placetype": [
      "aat:300008761"
    ],
    "id": 2409685,
    "name:xx": "Ikes Canyon"
  }
}
