{
  "geometry": {
    "type": "Point",
    "coordinates": [
      -75.4833,
      39.5667
    ]
  },
  "type": "Feature",
  "properties": {
    "hierarchy": [
      "tgn:2066184",
      "tgn:1000001",
      "tgn:7014449",
      "tgn:7012149",
      "tgn:7007565",
      "tgn:7029392"
    ],
    "placetype": [
      "aat:300008347"
    ],
    "id": 2066184,
    "name:xx": "Sinnickson Landing"
  }
}
