{
  "type": "FeatureCollection",
  "features": [
    {
      "geometry": {
        "type": "Point",
        "coordinates": [
          12.8,
          42.533333
        ]
      },
      "type": "Feature",
      "properties": {
        "hierarchy": [
          "tgn:5002340",
          "tgn:7003137",
          "tgn:1000003",
          "tgn:7003080",
          "tgn:1000080",
          "tgn:7029392"
        ],
        "placetype": [
          "aat:300008347"
        ],
        "id": 5002340,
        "name:xx": "Labro"
      }
    },
    {
      "geometry": {
        "type": "Point",
        "coordinates": [
          12.683333,
          42.3
        ]
      },
      "type": "Feature",
      "properties": {
        "hierarchy": [
          "tgn:5002342",
          "tgn:7003137",
          "tgn:1000003",
          "tgn:7003080",
          "tgn:1000080",
          "tgn:7029392"
        ],
        "placetype": [
          "aat:300008347"
        ],
        "id": 5002342,
        "name:xx": "Poggio Catino"
      }
    },
    {
      "geometry": {
        "type": "Point",
        "coordinates": [
          12.8,
          42.216667
        ]
      },
      "type": "Feature",
      "properties": {
        "hierarchy": [
          "tgn:5002344",
          "tgn:7003137",
          "tgn:1000003",
          "tgn:7003080",
          "tgn:1000080",
          "tgn:7029392"
        ],
        "placetype": [
          "aat:300008347"
        ],
        "id": 5002344,
        "name:xx": "Poggio Nativo"
      }
    },
    {
      "geometry": {
        "type": "Point",
        "coordinates": [
          11.65,
          44.316667
        ]
      },
      "type": "Feature",
      "properties": {
        "hierarchy": [
          "tgn:5002345",
          "tgn:7003137",
          "tgn:1000003",
          "tgn:7003080",
          "tgn:1000080",
          "tgn:7029392"
        ],
        "placetype": [
          "aat:300008347"
        ],
        "id": 5002345,
        "name:xx": "Ponticelli"
      }
    },
    {
      "geometry": {
        "type": "Point",
        "coordinates": [
          12.683333,
          42.316667
        ]
      },
      "type": "Feature",
      "properties": {
        "hierarchy": [
          "tgn:5002348",
          "tgn:7003137",
          "tgn:1000003",
          "tgn:7003080",
          "tgn:1000080",
          "tgn:7029392"
        ],
        "placetype": [
          "aat:300008347"
        ],
        "id": 5002348,
        "name:xx": "Roccantica"
      }
    },
    {
      "geometry": {
        "type": "Point",
        "coordinates": [
          12.833333,
          42.166667
        ]
      },
      "type": "Feature",
      "properties": {
        "hierarchy": [
          "tgn:5002349",
          "tgn:7003137",
          "tgn:1000003",
          "tgn:7003080",
          "tgn:1000080",
          "tgn:7029392"
        ],
        "placetype": [
          "aat:300008347"
        ],
        "id": 5002349,
        "name:xx": "Scandriglia"
      }
    }
  ]
}
