{
  "geometry": {
    "type": "Point",
    "coordinates": [
      -110.7833,
      37.95
    ]
  },
  "type": "Feature",
  "properties": {
    "hierarchy": [
      "tgn:2575061",
      "tgn:1000001",
      "tgn:2002109",
      "tgn:7012149",
      "tgn:7007827",
      "tgn:7029392"
    ],
    "placetype": [
      "aat:300008798"
    ],
    "id": 2575061,
    "name:xx": "Pennell, Mount"
  }
}
