{
  "type": "FeatureCollection",
  "features": [
    {
      "geometry": {
        "type": "Point",
        "coordinates": [
          31.502755,
          30.409162
        ]
      },
      "type": "Feature",
      "properties": {
        "hierarchy": [
          "tgn:7531000",
          "tgn:7001242",
          "tgn:7016833",
          "tgn:1001113",
          "tgn:7029392"
        ],
        "placetype": [
          "aat:300008347"
        ],
        "id": 7531000,
        "name:xx": "'Izbat Abū 'Utmān"
      }
    },
    {
      "geometry": {
        "type": "Point",
        "coordinates": [
          31.521851,
          30.424625
        ]
      },
      "type": "Feature",
      "properties": {
        "hierarchy": [
          "tgn:7531001",
          "tgn:7001242",
          "tgn:7016833",
          "tgn:1001113",
          "tgn:7029392"
        ],
        "placetype": [
          "aat:300008347"
        ],
        "id": 7531001,
        "name:xx": "'Izbat Hārūn"
      }
    },
    {
      "geometry": {
        "type": "Point",
        "coordinates": [
          31.516465,
          30.434467
        ]
      },
      "type": "Feature",
      "properties": {
        "hierarchy": [
          "tgn:7531002",
          "tgn:7001242",
          "tgn:7016833",
          "tgn:1001113",
          "tgn:7029392"
        ],
        "placetype": [
          "aat:300008347"
        ],
        "id": 7531002,
        "name:xx": "'Izbat al 'Arab"
      }
    },
    {
      "geometry": {
        "type": "Point",
        "coordinates": [
          31.592987,
          30.499448
        ]
      },
      "type": "Feature",
      "properties": {
        "hierarchy": [
          "tgn:7531003",
          "tgn:7001242",
          "tgn:7016833",
          "tgn:1001113",
          "tgn:7029392"
        ],
        "placetype": [
          "aat:300008347"
        ],
        "id": 7531003,
        "name:xx": "'Izbat al Malākah"
      }
    },
    {
      "geometry": {
        "type": "Point",
        "coordinates": [
          31.59806,
          30.492468
        ]
      },
      "type": "Feature",
      "properties": {
        "hierarchy": [
          "tgn:7531004",
          "tgn:7001242",
          "tgn:7016833",
          "tgn:1001113",
          "tgn:7029392"
        ],
        "placetype": [
          "aat:300008347"
        ],
        "id": 7531004,
        "name:xx": "'Izbat Ibrāhīm Yakan Fahmī"
      }
    },
    {
      "geometry": {
        "type": "Point",
        "coordinates": [
          31.201261,
          30.3331
        ]
      },
      "type": "Feature",
      "properties": {
        "hierarchy": [
          "tgn:7531005",
          "tgn:7001242",
          "tgn:7016833",
          "tgn:1001092",
          "tgn:7029392"
        ],
        "placetype": [
          "aat:300006075"
        ],
        "id": 7531005,
        "name:xx": "Tur'at Mughţāh"
      }
    },
    {
      "geometry": {
        "type": "Point",
        "coordinates": [
          31.120189,
          30.190599
        ]
      },
      "type": "Feature",
      "properties": {
        "hierarchy": [
          "tgn:7531006",
          "tgn:7001242",
          "tgn:7016833",
          "tgn:1001087",
          "tgn:7029392"
        ],
        "placetype": [
          "aat:300006075"
        ],
        "id": 7531006,
        "name:xx": "Ar Rayyāh al Minūfī"
      }
    },
    {
      "geometry": {
        "type": "Point",
        "coordinates": [
          31.227547,
          30.204903
        ]
      },
      "type": "Feature",
      "properties": {
        "hierarchy": [
          "tgn:7531007",
          "tgn:7001242",
          "tgn:7016833",
          "tgn:1001092",
          "tgn:7029392"
        ],
        "placetype": [
          "aat:300006075"
        ],
        "id": 7531007,
        "name:xx": "Khalīj ash Shāmī"
      }
    },
    {
      "geometry": {
        "type": "Point",
        "coordinates": [
          31.247651,
          30.217783
        ]
      },
      "type": "Feature",
      "properties": {
        "hierarchy": [
          "tgn:7531008",
          "tgn:7001242",
          "tgn:7016833",
          "tgn:1001092",
          "tgn:7029392"
        ],
        "placetype": [
          "aat:300006075"
        ],
        "id": 7531008,
        "name:xx": "Tur'at Fāḑil"
      }
    },
    {
      "geometry": {
        "type": "Point",
        "coordinates": [
          31.174241,
          30.426113
        ]
      },
      "type": "Feature",
      "properties": {
        "hierarchy": [
          "tgn:7531009",
          "tgn:7001242",
          "tgn:7016833",
          "tgn:1001092",
          "tgn:7029392"
        ],
        "placetype": [
          "aat:300006075"
        ],
        "id": 7531009,
        "name:xx": "Tur'at al Falfilah al Mustajaddah"
      }
    }
  ]
}
