{
  "type": "FeatureCollection",
  "features": [
    {
      "geometry": {
        "type": "Point",
        "coordinates": [
          7.866667,
          49.55
        ]
      },
      "type": "Feature",
      "properties": {
        "hierarchy": [
          "tgn:7169770",
          "tgn:1000003",
          "tgn:7003682",
          "tgn:7000084",
          "tgn:7029392"
        ],
        "placetype": [
          "aat:300008777"
        ],
        "id": 7169770,
        "name:xx": "Heuberg"
      }
    },
    {
      "geometry": {
        "type": "Point",
        "coordinates": [
          8.95,
          49.233333
        ]
      },
      "type": "Feature",
      "properties": {
        "hierarchy": [
          "tgn:7169771",
          "tgn:7003692",
          "tgn:1000003",
          "tgn:7000084",
          "tgn:7029392"
        ],
        "placetype": [
          "aat:300008777"
        ],
        "id": 7169771,
        "name:xx": "Heuberg"
      }
    },
    {
      "geometry": {
        "type": "Point",
        "coordinates": [
          8.65,
          48.983333
        ]
      },
      "type": "Feature",
      "properties": {
        "hierarchy": [
          "tgn:7169772",
          "tgn:7003692",
          "tgn:1000003",
          "tgn:7000084",
          "tgn:7029392"
        ],
        "placetype": [
          "aat:300008777"
        ],
        "id": 7169772,
        "name:xx": "Heuberg"
      }
    },
    {
      "geometry": {
        "type": "Point",
        "coordinates": [
          11.55,
          48.9
        ]
      },
      "type": "Feature",
      "properties": {
        "hierarchy": [
          "tgn:7169773",
          "tgn:7003669",
          "tgn:1000003",
          "tgn:7000084",
          "tgn:7029392"
        ],
        "placetype": [
          "aat:300008777"
        ],
        "id": 7169773,
        "name:xx": "Heuberg"
      }
    },
    {
      "geometry": {
        "type": "Point",
        "coordinates": [
          8.9,
          48.866667
        ]
      },
      "type": "Feature",
      "properties": {
        "hierarchy": [
          "tgn:7169774",
          "tgn:7003692",
          "tgn:1000003",
          "tgn:7000084",
          "tgn:7029392"
        ],
        "placetype": [
          "aat:300008777"
        ],
        "id": 7169774,
        "name:xx": "Heuberg"
      }
    },
    {
      "geometry": {
        "type": "Point",
        "coordinates": [
          9.633333,
          48.833333
        ]
      },
      "type": "Feature",
      "properties": {
        "hierarchy": [
          "tgn:7169775",
          "tgn:7003692",
          "tgn:1000003",
          "tgn:7000084",
          "tgn:7029392"
        ],
        "placetype": [
          "aat:300008777"
        ],
        "id": 7169775,
        "name:xx": "Heuberg"
      }
    },
    {
      "geometry": {
        "type": "Point",
        "coordinates": [
          9.583333,
          48.5
        ]
      },
      "type": "Feature",
      "properties": {
        "hierarchy": [
          "tgn:7169776",
          "tgn:7003692",
          "tgn:1000003",
          "tgn:7000084",
          "tgn:7029392"
        ],
        "placetype": [
          "aat:300008777"
        ],
        "id": 7169776,
        "name:xx": "Heuberg"
      }
    },
    {
      "geometry": {
        "type": "Point",
        "coordinates": [
          8.9,
          48.5
        ]
      },
      "type": "Feature",
      "properties": {
        "hierarchy": [
          "tgn:7169777",
          "tgn:7003692",
          "tgn:1000003",
          "tgn:7000084",
          "tgn:7029392"
        ],
        "placetype": [
          "aat:300008777"
        ],
        "id": 7169777,
        "name:xx": "Heuberg"
      }
    },
    {
      "geometry": {
        "type": "Point",
        "coordinates": [
          8.35,
          48.5
        ]
      },
      "type": "Feature",
      "properties": {
        "hierarchy": [
          "tgn:7169778",
          "tgn:7003692",
          "tgn:1000003",
          "tgn:7000084",
          "tgn:7029392"
        ],
        "placetype": [
          "aat:300008777"
        ],
        "id": 7169778,
        "name:xx": "Heuberg"
      }
    },
    {
      "geometry": {
        "type": "Point",
        "coordinates": [
          10.666667,
          48.483333
        ]
      },
      "type": "Feature",
      "properties": {
        "hierarchy": [
          "tgn:7169779",
          "tgn:7003669",
          "tgn:1000003",
          "tgn:7000084",
          "tgn:7029392"
        ],
        "placetype": [
          "aat:300008777"
        ],
        "id": 7169779,
        "name:xx": "Heuberg"
      }
    }
  ]
}
