{
  "geometry": {
    "type": "Point",
    "coordinates": [
      -76.1333,
      38.8667
    ]
  },
  "type": "Feature",
  "properties": {
    "hierarchy": [
      "tgn:2603119",
      "tgn:1000001",
      "tgn:2000939",
      "tgn:7012149",
      "tgn:7007516",
      "tgn:7029392"
    ],
    "placetype": [
      "aat:300132316"
    ],
    "id": 2603119,
    "name:xx": "Quarter Cove"
  }
}
