{
  "geometry": {
    "type": "Point",
    "coordinates": [
      -83.55,
      42.15
    ]
  },
  "type": "Feature",
  "properties": {
    "hierarchy": [
      "tgn:2053738",
      "tgn:1000001",
      "tgn:7012149",
      "tgn:1003000",
      "tgn:7007520",
      "tgn:7029392"
    ],
    "placetype": [
      "aat:300008347"
    ],
    "id": 2053738,
    "name:xx": "Willis"
  }
}
