{
  "geometry": {
    "type": "Point",
    "coordinates": [
      -171.75,
      63.6833
    ]
  },
  "type": "Feature",
  "properties": {
    "hierarchy": [
      "tgn:2537760",
      "tgn:7006450",
      "tgn:1000001",
      "tgn:7012149",
      "tgn:2000079",
      "tgn:7029392"
    ],
    "placetype": [
      "aat:300008850"
    ],
    "id": 2537760,
    "name:xx": "Nekeelit Point"
  }
}
