{
  "geometry": {
    "type": "Point",
    "coordinates": [
      -90.6667,
      46.1833
    ]
  },
  "type": "Feature",
  "properties": {
    "hierarchy": [
      "tgn:2684578",
      "tgn:2002306",
      "tgn:1000001",
      "tgn:7012149",
      "tgn:7007922",
      "tgn:7029392"
    ],
    "placetype": [
      "aat:300008680"
    ],
    "id": 2684578,
    "name:xx": "Spillerberg Lake"
  }
}
