{
  "geometry": {
    "type": "Point",
    "coordinates": [
      34.50352,
      29.376064
    ]
  },
  "type": "Feature",
  "properties": {
    "hierarchy": [
      "tgn:7529759",
      "tgn:7001242",
      "tgn:7016833",
      "tgn:7001336",
      "tgn:7029392"
    ],
    "placetype": [
      "aat:300379998"
    ],
    "name:en": "Rumaythī, Wādī ar",
    "id": 7529759
  }
}
