{
  "geometry": {
    "type": "Point",
    "coordinates": [
      -116.6333,
      33.0833
    ]
  },
  "type": "Feature",
  "properties": {
    "hierarchy": [
      "tgn:2602956",
      "tgn:1000001",
      "tgn:7012149",
      "tgn:7007157",
      "tgn:1002858",
      "tgn:7029392"
    ],
    "placetype": [
      "aat:300008761"
    ],
    "id": 2602956,
    "name:xx": "Quanai Canyon"
  }
}
