{
  "geometry": {
    "type": "Point",
    "coordinates": [
      -155.3667,
      64.7833
    ]
  },
  "type": "Feature",
  "properties": {
    "hierarchy": [
      "tgn:2698468",
      "tgn:7006450",
      "tgn:1000001",
      "tgn:7012149",
      "tgn:2000089",
      "tgn:7029392"
    ],
    "placetype": [
      "aat:300008791"
    ],
    "id": 2698468,
    "name:xx": "Straight Island"
  }
}
