{
  "type": "FeatureCollection",
  "features": [
    {
      "geometry": {
        "type": "Point",
        "coordinates": [
          -102.291667,
          21.791667
        ]
      },
      "type": "Feature",
      "properties": {
        "hierarchy": [
          "tgn:7420440",
          "tgn:7005579",
          "tgn:1000001",
          "tgn:7005560",
          "tgn:7029392"
        ],
        "placetype": [
          "aat:300008347"
        ],
        "id": 7420440,
        "name:xx": "El Gigante"
      }
    },
    {
      "geometry": {
        "type": "Point",
        "coordinates": [
          -102.295833,
          22.0375
        ]
      },
      "type": "Feature",
      "properties": {
        "hierarchy": [
          "tgn:7420441",
          "tgn:7005579",
          "tgn:1000001",
          "tgn:7005560",
          "tgn:7029392"
        ],
        "placetype": [
          "aat:300008347"
        ],
        "id": 7420441,
        "name:xx": "La Máquina"
      }
    },
    {
      "geometry": {
        "type": "Point",
        "coordinates": [
          -102.295833,
          22.016667
        ]
      },
      "type": "Feature",
      "properties": {
        "hierarchy": [
          "tgn:7420442",
          "tgn:7005579",
          "tgn:1000001",
          "tgn:7005560",
          "tgn:7029392"
        ],
        "placetype": [
          "aat:300008347"
        ],
        "id": 7420442,
        "name:xx": "El Cortijo"
      }
    },
    {
      "geometry": {
        "type": "Point",
        "coordinates": [
          -102.295833,
          22
        ]
      },
      "type": "Feature",
      "properties": {
        "hierarchy": [
          "tgn:7420444",
          "tgn:7005579",
          "tgn:1000001",
          "tgn:7005560",
          "tgn:7029392"
        ],
        "placetype": [
          "aat:300008347"
        ],
        "id": 7420444,
        "name:xx": "Jesús Gómez Portugal"
      }
    },
    {
      "geometry": {
        "type": "Point",
        "coordinates": [
          -102.3,
          22.366667
        ]
      },
      "type": "Feature",
      "properties": {
        "hierarchy": [
          "tgn:7420445",
          "tgn:7005579",
          "tgn:1000001",
          "tgn:7005560",
          "tgn:7029392"
        ],
        "placetype": [
          "aat:300008347"
        ],
        "id": 7420445,
        "name:xx": "Coso"
      }
    },
    {
      "geometry": {
        "type": "Point",
        "coordinates": [
          -102.3,
          22.333333
        ]
      },
      "type": "Feature",
      "properties": {
        "hierarchy": [
          "tgn:7420447",
          "tgn:7005579",
          "tgn:1000001",
          "tgn:7005560",
          "tgn:7029392"
        ],
        "placetype": [
          "aat:300008347"
        ],
        "id": 7420447,
        "name:xx": "La Punta"
      }
    },
    {
      "geometry": {
        "type": "Point",
        "coordinates": [
          -102.3,
          22.291667
        ]
      },
      "type": "Feature",
      "properties": {
        "hierarchy": [
          "tgn:7420448",
          "tgn:7005579",
          "tgn:1000001",
          "tgn:7005560",
          "tgn:7029392"
        ],
        "placetype": [
          "aat:300008347"
        ],
        "id": 7420448,
        "name:xx": "Santa Fe"
      }
    },
    {
      "geometry": {
        "type": "Point",
        "coordinates": [
          -102.3,
          22.291667
        ]
      },
      "type": "Feature",
      "properties": {
        "hierarchy": [
          "tgn:7420449",
          "tgn:7005579",
          "tgn:1000001",
          "tgn:7005560",
          "tgn:7029392"
        ],
        "placetype": [
          "aat:300008347"
        ],
        "id": 7420449,
        "name:xx": "La Represa"
      }
    }
  ]
}
