{
  "geometry": {
    "type": "Point",
    "coordinates": [
      -80.75,
      40.0833
    ]
  },
  "type": "Feature",
  "properties": {
    "hierarchy": [
      "tgn:2275070",
      "tgn:1002175",
      "tgn:1000001",
      "tgn:7012149",
      "tgn:7007706",
      "tgn:7029392"
    ],
    "placetype": [
      "aat:300008761"
    ],
    "id": 2275070,
    "name:xx": "Dandelion Hollow"
  }
}
