{
  "type": "FeatureCollection",
  "features": [
    {
      "geometry": {
        "type": "Point",
        "coordinates": [
          -77.3167,
          42.6833
        ]
      },
      "type": "Feature",
      "properties": {
        "hierarchy": [
          "tgn:2680680",
          "tgn:1000001",
          "tgn:7012149",
          "tgn:1003045",
          "tgn:7007568",
          "tgn:7029392"
        ],
        "placetype": [
          "aat:300008798"
        ],
        "id": 2680680,
        "name:xx": "South Hill"
      }
    },
    {
      "geometry": {
        "type": "Point",
        "coordinates": [
          -75.8667,
          42.7333
        ]
      },
      "type": "Feature",
      "properties": {
        "hierarchy": [
          "tgn:2680681",
          "tgn:1000001",
          "tgn:7012149",
          "tgn:1002624",
          "tgn:7007568",
          "tgn:7029392"
        ],
        "placetype": [
          "aat:300008798"
        ],
        "id": 2680681,
        "name:xx": "South Hill"
      }
    },
    {
      "geometry": {
        "type": "Point",
        "coordinates": [
          -75.2833,
          43.2667
        ]
      },
      "type": "Feature",
      "properties": {
        "hierarchy": [
          "tgn:2680682",
          "tgn:1000001",
          "tgn:7012149",
          "tgn:7014287",
          "tgn:7007568",
          "tgn:7029392"
        ],
        "placetype": [
          "aat:300008798"
        ],
        "id": 2680682,
        "name:xx": "South Hill"
      }
    },
    {
      "geometry": {
        "type": "Point",
        "coordinates": [
          -78.65,
          42.5833
        ]
      },
      "type": "Feature",
      "properties": {
        "hierarchy": [
          "tgn:2680683",
          "tgn:1000001",
          "tgn:7012149",
          "tgn:1002356",
          "tgn:7007568",
          "tgn:7029392"
        ],
        "placetype": [
          "aat:300008798"
        ],
        "id": 2680683,
        "name:xx": "South Hill"
      }
    },
    {
      "geometry": {
        "type": "Point",
        "coordinates": [
          -74.7667,
          42.55
        ]
      },
      "type": "Feature",
      "properties": {
        "hierarchy": [
          "tgn:2680684",
          "tgn:1000001",
          "tgn:7012149",
          "tgn:7007568",
          "tgn:7029392"
        ],
        "placetype": [
          "aat:300008798"
        ],
        "id": 2680684,
        "name:xx": "South Hill"
      }
    },
    {
      "geometry": {
        "type": "Point",
        "coordinates": [
          -76.25,
          41.8333
        ]
      },
      "type": "Feature",
      "properties": {
        "hierarchy": [
          "tgn:2680686",
          "tgn:1000001",
          "tgn:1002194",
          "tgn:7012149",
          "tgn:7007710",
          "tgn:7029392"
        ],
        "placetype": [
          "aat:300008347"
        ],
        "id": 2680686,
        "name:xx": "South Hill"
      }
    },
    {
      "geometry": {
        "type": "Point",
        "coordinates": [
          -77.4167,
          41.8333
        ]
      },
      "type": "Feature",
      "properties": {
        "hierarchy": [
          "tgn:2680687",
          "tgn:1000001",
          "tgn:7012149",
          "tgn:1002945",
          "tgn:7007710",
          "tgn:7029392"
        ],
        "placetype": [
          "aat:300008798"
        ],
        "id": 2680687,
        "name:xx": "South Hill"
      }
    },
    {
      "geometry": {
        "type": "Point",
        "coordinates": [
          -72.8,
          43.7333
        ]
      },
      "type": "Feature",
      "properties": {
        "hierarchy": [
          "tgn:2680688",
          "tgn:1000001",
          "tgn:7012149",
          "tgn:7007828",
          "tgn:7029392"
        ],
        "placetype": [
          "aat:300008798"
        ],
        "id": 2680688,
        "name:xx": "South Hill"
      }
    },
    {
      "geometry": {
        "type": "Point",
        "coordinates": [
          -72.7833,
          43.75
        ]
      },
      "type": "Feature",
      "properties": {
        "hierarchy": [
          "tgn:2680689",
          "tgn:1000001",
          "tgn:2002136",
          "tgn:7012149",
          "tgn:7007828",
          "tgn:7029392"
        ],
        "placetype": [
          "aat:300008798"
        ],
        "id": 2680689,
        "name:xx": "South Hill"
      }
    }
  ]
}
