{
  "geometry": {
    "type": "Point",
    "coordinates": [
      -82.25,
      33.2667
    ]
  },
  "type": "Feature",
  "properties": {
    "hierarchy": [
      "tgn:2319575",
      "tgn:1000001",
      "tgn:7012149",
      "tgn:2000412",
      "tgn:7007248",
      "tgn:7029392"
    ],
    "placetype": [
      "aat:300006191"
    ],
    "id": 2319575,
    "name:xx": "Euclid Claussen Pond"
  }
}
