{
  "type": "FeatureCollection",
  "features": [
    {
      "geometry": {
        "type": "Point",
        "coordinates": [
          -72.083333,
          -44.45
        ]
      },
      "type": "Feature",
      "properties": {
        "hierarchy": [
          "tgn:7310880",
          "tgn:1001623",
          "tgn:1000049",
          "tgn:1000002",
          "tgn:7029392"
        ],
        "placetype": [
          "aat:300259572"
        ],
        "id": 7310880,
        "name:xx": "Negro, Portezuelo"
      }
    },
    {
      "geometry": {
        "type": "Point",
        "coordinates": [
          -68.55,
          -21.266667
        ]
      },
      "type": "Feature",
      "properties": {
        "hierarchy": [
          "tgn:7310881",
          "tgn:7016598",
          "tgn:1000049",
          "tgn:1000002",
          "tgn:7029392"
        ],
        "placetype": [
          "aat:300008697"
        ],
        "id": 7310881,
        "name:xx": "Negro, Ojo"
      }
    },
    {
      "geometry": {
        "type": "Point",
        "coordinates": [
          -70.633333,
          -32.683333
        ]
      },
      "type": "Feature",
      "properties": {
        "hierarchy": [
          "tgn:7310882",
          "tgn:1001768",
          "tgn:1000049",
          "tgn:1000002",
          "tgn:7029392"
        ],
        "placetype": [
          "aat:300008798"
        ],
        "id": 7310882,
        "name:xx": "Negro, Morro"
      }
    },
    {
      "geometry": {
        "type": "Point",
        "coordinates": [
          -70.6,
          -32.55
        ]
      },
      "type": "Feature",
      "properties": {
        "hierarchy": [
          "tgn:7310883",
          "tgn:1001768",
          "tgn:1000049",
          "tgn:1000002",
          "tgn:7029392"
        ],
        "placetype": [
          "aat:300008798"
        ],
        "id": 7310883,
        "name:xx": "Negro, Morro"
      }
    },
    {
      "geometry": {
        "type": "Point",
        "coordinates": [
          -71.266667,
          -34.483333
        ]
      },
      "type": "Feature",
      "properties": {
        "hierarchy": [
          "tgn:7310884",
          "tgn:1001695",
          "tgn:1000049",
          "tgn:1000002",
          "tgn:7029392"
        ],
        "placetype": [
          "aat:300008795"
        ],
        "id": 7310884,
        "name:xx": "Negro, Morro"
      }
    },
    {
      "geometry": {
        "type": "Point",
        "coordinates": [
          -70.533333,
          -33.833333
        ]
      },
      "type": "Feature",
      "properties": {
        "hierarchy": [
          "tgn:7310885",
          "tgn:1001708",
          "tgn:1000049",
          "tgn:1000002",
          "tgn:7029392"
        ],
        "placetype": [
          "aat:300008795"
        ],
        "id": 7310885,
        "name:xx": "Negro, Morro"
      }
    },
    {
      "geometry": {
        "type": "Point",
        "coordinates": [
          -71,
          -33.3
        ]
      },
      "type": "Feature",
      "properties": {
        "hierarchy": [
          "tgn:7310886",
          "tgn:1001708",
          "tgn:1000049",
          "tgn:1000002",
          "tgn:7029392"
        ],
        "placetype": [
          "aat:300008795"
        ],
        "id": 7310886,
        "name:xx": "Negro, Morro"
      }
    },
    {
      "geometry": {
        "type": "Point",
        "coordinates": [
          -71.05,
          -32.65
        ]
      },
      "type": "Feature",
      "properties": {
        "hierarchy": [
          "tgn:7310887",
          "tgn:1001768",
          "tgn:1000049",
          "tgn:1000002",
          "tgn:7029392"
        ],
        "placetype": [
          "aat:300008795"
        ],
        "id": 7310887,
        "name:xx": "Negro, Morro"
      }
    },
    {
      "geometry": {
        "type": "Point",
        "coordinates": [
          -69.866667,
          -28.683333
        ]
      },
      "type": "Feature",
      "properties": {
        "hierarchy": [
          "tgn:7310888",
          "tgn:1001630",
          "tgn:1000049",
          "tgn:1000002",
          "tgn:7029392"
        ],
        "placetype": [
          "aat:300008795"
        ],
        "id": 7310888,
        "name:xx": "Negro, Morro"
      }
    },
    {
      "geometry": {
        "type": "Point",
        "coordinates": [
          -69.416667,
          -22.216667
        ]
      },
      "type": "Feature",
      "properties": {
        "hierarchy": [
          "tgn:7310889",
          "tgn:7016598",
          "tgn:1000049",
          "tgn:1000002",
          "tgn:7029392"
        ],
        "placetype": [
          "aat:300008795"
        ],
        "id": 7310889,
        "name:xx": "Negro, Morro"
      }
    }
  ]
}
