{
  "geometry": {
    "type": "Point",
    "coordinates": [
      -121.55,
      44.55
    ]
  },
  "type": "Feature",
  "properties": {
    "hierarchy": [
      "tgn:2680089",
      "tgn:1000001",
      "tgn:7012149",
      "tgn:2001712",
      "tgn:7007708",
      "tgn:7029392"
    ],
    "placetype": [
      "aat:300008706"
    ],
    "id": 2680089,
    "name:xx": "South Fork Spring Creek"
  }
}
