{
  "geometry": {
    "type": "Point",
    "coordinates": [
      -121.0167,
      41.9333
    ]
  },
  "type": "Feature",
  "properties": {
    "hierarchy": [
      "tgn:2619430",
      "tgn:1000001",
      "tgn:7012149",
      "tgn:7007157",
      "tgn:2000186",
      "tgn:7029392"
    ],
    "placetype": [
      "aat:300008697"
    ],
    "id": 2619430,
    "name:xx": "Rimrock Spring"
  }
}
