{
  "geometry": {
    "type": "Point",
    "coordinates": [
      -113.5167,
      43.4333
    ]
  },
  "type": "Feature",
  "properties": {
    "hierarchy": [
      "tgn:2286085",
      "tgn:1000001",
      "tgn:2000463",
      "tgn:7012149",
      "tgn:7007250",
      "tgn:7029392"
    ],
    "placetype": [
      "aat:300008746"
    ],
    "id": 2286085,
    "name:xx": "Dewdrop Cave"
  }
}
