{
  "type": "FeatureCollection",
  "features": [
    {
      "geometry": {
        "type": "Point",
        "coordinates": [
          -105.2333,
          37.6167
        ]
      },
      "type": "Feature",
      "properties": {
        "hierarchy": [
          "tgn:2570040",
          "tgn:1000001",
          "tgn:7012149",
          "tgn:2000219",
          "tgn:7007158",
          "tgn:7029392"
        ],
        "placetype": [
          "aat:300008706"
        ],
        "id": 2570040,
        "name:xx": "Pass Creek"
      }
    },
    {
      "geometry": {
        "type": "Point",
        "coordinates": [
          -103,
          39.0333
        ]
      },
      "type": "Feature",
      "properties": {
        "hierarchy": [
          "tgn:2570041",
          "tgn:1000001",
          "tgn:2000200",
          "tgn:7012149",
          "tgn:7007158",
          "tgn:7029392"
        ],
        "placetype": [
          "aat:300008706"
        ],
        "id": 2570041,
        "name:xx": "Pass Creek"
      }
    },
    {
      "geometry": {
        "type": "Point",
        "coordinates": [
          -114.75,
          44.0333
        ]
      },
      "type": "Feature",
      "properties": {
        "hierarchy": [
          "tgn:2570042",
          "tgn:1000001",
          "tgn:2000470",
          "tgn:7012149",
          "tgn:7007250",
          "tgn:7029392"
        ],
        "placetype": [
          "aat:300008706"
        ],
        "id": 2570042,
        "name:xx": "Pass Creek"
      }
    },
    {
      "geometry": {
        "type": "Point",
        "coordinates": [
          -112.9833,
          44.1333
        ]
      },
      "type": "Feature",
      "properties": {
        "hierarchy": [
          "tgn:2570043",
          "tgn:1000001",
          "tgn:2000468",
          "tgn:7012149",
          "tgn:7007250",
          "tgn:7029392"
        ],
        "placetype": [
          "aat:300008706"
        ],
        "id": 2570043,
        "name:xx": "Pass Creek"
      }
    },
    {
      "geometry": {
        "type": "Point",
        "coordinates": [
          -115.35,
          44.2833
        ]
      },
      "type": "Feature",
      "properties": {
        "hierarchy": [
          "tgn:2570044",
          "tgn:1000001",
          "tgn:2000459",
          "tgn:7012149",
          "tgn:7007250",
          "tgn:7029392"
        ],
        "placetype": [
          "aat:300008706"
        ],
        "id": 2570044,
        "name:xx": "Pass Creek"
      }
    },
    {
      "geometry": {
        "type": "Point",
        "coordinates": [
          -113.0167,
          44.4833
        ]
      },
      "type": "Feature",
      "properties": {
        "hierarchy": [
          "tgn:2570045",
          "tgn:1000001",
          "tgn:7012149",
          "tgn:2000481",
          "tgn:7007250",
          "tgn:7029392"
        ],
        "placetype": [
          "aat:300008706"
        ],
        "id": 2570045,
        "name:xx": "Pass Creek"
      }
    },
    {
      "geometry": {
        "type": "Point",
        "coordinates": [
          -115.35,
          46.95
        ]
      },
      "type": "Feature",
      "properties": {
        "hierarchy": [
          "tgn:2570046",
          "tgn:1000001",
          "tgn:7012149",
          "tgn:2000491",
          "tgn:7007250",
          "tgn:7029392"
        ],
        "placetype": [
          "aat:300008706"
        ],
        "id": 2570046,
        "name:xx": "Pass Creek"
      }
    },
    {
      "geometry": {
        "type": "Point",
        "coordinates": [
          -113.45,
          44.0167
        ]
      },
      "type": "Feature",
      "properties": {
        "hierarchy": [
          "tgn:2570047",
          "tgn:1000001",
          "tgn:7012149",
          "tgn:7007250",
          "tgn:7029392"
        ],
        "placetype": [
          "aat:300008706"
        ],
        "id": 2570047,
        "name:xx": "Pass Creek"
      }
    },
    {
      "geometry": {
        "type": "Point",
        "coordinates": [
          -115.25,
          46.3333
        ]
      },
      "type": "Feature",
      "properties": {
        "hierarchy": [
          "tgn:2570048",
          "tgn:1000001",
          "tgn:7012149",
          "tgn:2000476",
          "tgn:7007250",
          "tgn:7029392"
        ],
        "placetype": [
          "aat:300008706"
        ],
        "id": 2570048,
        "name:xx": "Pass Creek"
      }
    },
    {
      "geometry": {
        "type": "Point",
        "coordinates": [
          -88.5833,
          46.3333
        ]
      },
      "type": "Feature",
      "properties": {
        "hierarchy": [
          "tgn:2570049",
          "tgn:1000001",
          "tgn:7012149",
          "tgn:2000966",
          "tgn:7007520",
          "tgn:7029392"
        ],
        "placetype": [
          "aat:300008706"
        ],
        "id": 2570049,
        "name:xx": "Pass Creek"
      }
    }
  ]
}
