{
  "geometry": {
    "type": "Point",
    "coordinates": [
      34.864616,
      24.17133
    ]
  },
  "type": "Feature",
  "properties": {
    "hierarchy": [
      "tgn:7527881",
      "tgn:7001242",
      "tgn:7001311",
      "tgn:7016833",
      "tgn:7029392"
    ],
    "placetype": [
      "aat:300008795"
    ],
    "name:en": "Umm aţ Ţuyūr, Jabal",
    "id": 7527881
  }
}
