{
  "type": "FeatureCollection",
  "features": [
    {
      "geometry": {
        "type": "Point",
        "coordinates": [
          -90.9667,
          41.2833
        ]
      },
      "type": "Feature",
      "properties": {
        "hierarchy": [
          "tgn:2027700",
          "tgn:1000001",
          "tgn:7012149",
          "tgn:2000520",
          "tgn:7007251",
          "tgn:7029392"
        ],
        "placetype": [
          "aat:300008347"
        ],
        "id": 2027700,
        "name:xx": "Eliza"
      }
    },
    {
      "geometry": {
        "type": "Point",
        "coordinates": [
          -90.2167,
          42.3167
        ]
      },
      "type": "Feature",
      "properties": {
        "hierarchy": [
          "tgn:2027701",
          "tgn:1000001",
          "tgn:7012149",
          "tgn:2000514",
          "tgn:7007251",
          "tgn:7029392"
        ],
        "placetype": [
          "aat:300008347"
        ],
        "id": 2027701,
        "name:xx": "Elizabeth"
      }
    },
    {
      "geometry": {
        "type": "Point",
        "coordinates": [
          -88.3,
          37.4333
        ]
      },
      "type": "Feature",
      "properties": {
        "hierarchy": [
          "tgn:2027702",
          "tgn:1000001",
          "tgn:7012149",
          "tgn:2000509",
          "tgn:7007251",
          "tgn:7029392"
        ],
        "placetype": [
          "aat:300008347"
        ],
        "id": 2027702,
        "name:xx": "Elizabethtown"
      }
    },
    {
      "geometry": {
        "type": "Point",
        "coordinates": [
          -88,
          41.9833
        ]
      },
      "type": "Feature",
      "properties": {
        "hierarchy": [
          "tgn:2027703",
          "tgn:1000001",
          "tgn:7013649",
          "tgn:7012149",
          "tgn:7007251",
          "tgn:7029392"
        ],
        "placetype": [
          "aat:300008347"
        ],
        "id": 2027703,
        "name:xx": "Elk Grove Village"
      }
    },
    {
      "geometry": {
        "type": "Point",
        "coordinates": [
          -89.4667,
          40.0167
        ]
      },
      "type": "Feature",
      "properties": {
        "hierarchy": [
          "tgn:2027707",
          "tgn:1000001",
          "tgn:7012149",
          "tgn:1002605",
          "tgn:7007251",
          "tgn:7029392"
        ],
        "placetype": [
          "aat:300008347"
        ],
        "id": 2027707,
        "name:xx": "Elkhart"
      }
    },
    {
      "geometry": {
        "type": "Point",
        "coordinates": [
          -89.55,
          38.2833
        ]
      },
      "type": "Feature",
      "properties": {
        "hierarchy": [
          "tgn:2027708",
          "tgn:1000001",
          "tgn:7012149",
          "tgn:1002991",
          "tgn:7007251",
          "tgn:7029392"
        ],
        "placetype": [
          "aat:300008347",
          "aat:300387210"
        ],
        "id": 2027708,
        "name:xx": "Elkton"
      }
    },
    {
      "geometry": {
        "type": "Point",
        "coordinates": [
          -89.2333,
          37.9
        ]
      },
      "type": "Feature",
      "properties": {
        "hierarchy": [
          "tgn:2027709",
          "tgn:1000001",
          "tgn:7012149",
          "tgn:2000512",
          "tgn:7007251",
          "tgn:7029392"
        ],
        "placetype": [
          "aat:300008347"
        ],
        "id": 2027709,
        "name:xx": "Elkville"
      }
    }
  ]
}
