{
  "geometry": {
    "type": "Point",
    "coordinates": [
      -118.6667,
      37.75
    ]
  },
  "type": "Feature",
  "properties": {
    "hierarchy": [
      "tgn:2763285",
      "tgn:1000001",
      "tgn:7012149",
      "tgn:7007157",
      "tgn:1002675",
      "tgn:7029392"
    ],
    "placetype": [
      "aat:300008699"
    ],
    "id": 2763285,
    "name:xx": "Wet Fork"
  }
}
