{
  "geometry": {
    "type": "Point",
    "coordinates": [
      -76.1333,
      38.2667
    ]
  },
  "type": "Feature",
  "properties": {
    "hierarchy": [
      "tgn:2776667",
      "tgn:1002338",
      "tgn:1000001",
      "tgn:7012149",
      "tgn:7007516",
      "tgn:7029392"
    ],
    "placetype": [
      "aat:300132316"
    ],
    "id": 2776667,
    "name:xx": "Windmill Cove"
  }
}
