{
  "type": "FeatureCollection",
  "features": [
    {
      "geometry": {
        "type": "Point",
        "coordinates": [
          10.633333,
          52.866667
        ]
      },
      "type": "Feature",
      "properties": {
        "hierarchy": [
          "tgn:7161630",
          "tgn:1000003",
          "tgn:7003676",
          "tgn:7000084",
          "tgn:7029392"
        ],
        "placetype": [
          "aat:300008777"
        ],
        "id": 7161630,
        "name:xx": "Hoher Berg"
      }
    },
    {
      "geometry": {
        "type": "Point",
        "coordinates": [
          8.783333,
          52.933333
        ]
      },
      "type": "Feature",
      "properties": {
        "hierarchy": [
          "tgn:7161631",
          "tgn:1000003",
          "tgn:7003676",
          "tgn:7000084",
          "tgn:7029392"
        ],
        "placetype": [
          "aat:300008777"
        ],
        "id": 7161631,
        "name:xx": "Hoher Berg"
      }
    },
    {
      "geometry": {
        "type": "Point",
        "coordinates": [
          12.733333,
          52.85
        ]
      },
      "type": "Feature",
      "properties": {
        "hierarchy": [
          "tgn:7161633",
          "tgn:7000096",
          "tgn:1000003",
          "tgn:7000084",
          "tgn:7029392"
        ],
        "placetype": [
          "aat:300008777"
        ],
        "id": 7161633,
        "name:xx": "Hoher Berg"
      }
    },
    {
      "geometry": {
        "type": "Point",
        "coordinates": [
          13.1,
          52.25
        ]
      },
      "type": "Feature",
      "properties": {
        "hierarchy": [
          "tgn:7161634",
          "tgn:7000096",
          "tgn:1000003",
          "tgn:7000084",
          "tgn:7029392"
        ],
        "placetype": [
          "aat:300008777"
        ],
        "id": 7161634,
        "name:xx": "Hoher Berg"
      }
    },
    {
      "geometry": {
        "type": "Point",
        "coordinates": [
          10.883333,
          51.7
        ]
      },
      "type": "Feature",
      "properties": {
        "hierarchy": [
          "tgn:7161635",
          "tgn:1000003",
          "tgn:7003687",
          "tgn:7000084",
          "tgn:7029392"
        ],
        "placetype": [
          "aat:300008777"
        ],
        "id": 7161635,
        "name:xx": "Hoher-Berg"
      }
    },
    {
      "geometry": {
        "type": "Point",
        "coordinates": [
          11.533333,
          51.633333
        ]
      },
      "type": "Feature",
      "properties": {
        "hierarchy": [
          "tgn:7161636",
          "tgn:1000003",
          "tgn:7003687",
          "tgn:7000084",
          "tgn:7029392"
        ],
        "placetype": [
          "aat:300008777"
        ],
        "id": 7161636,
        "name:xx": "Hoher Berg"
      }
    },
    {
      "geometry": {
        "type": "Point",
        "coordinates": [
          14.583333,
          51.616667
        ]
      },
      "type": "Feature",
      "properties": {
        "hierarchy": [
          "tgn:7161637",
          "tgn:7000096",
          "tgn:1000003",
          "tgn:7000084",
          "tgn:7029392"
        ],
        "placetype": [
          "aat:300008777"
        ],
        "id": 7161637,
        "name:xx": "Hoher Berg"
      }
    },
    {
      "geometry": {
        "type": "Point",
        "coordinates": [
          10.15,
          51.6
        ]
      },
      "type": "Feature",
      "properties": {
        "hierarchy": [
          "tgn:7161638",
          "tgn:1000003",
          "tgn:7003676",
          "tgn:7000084",
          "tgn:7029392"
        ],
        "placetype": [
          "aat:300008777"
        ],
        "id": 7161638,
        "name:xx": "Höher Berg"
      }
    },
    {
      "geometry": {
        "type": "Point",
        "coordinates": [
          9.35,
          51.566667
        ]
      },
      "type": "Feature",
      "properties": {
        "hierarchy": [
          "tgn:7161639",
          "tgn:1000003",
          "tgn:7003677",
          "tgn:7000084",
          "tgn:7029392"
        ],
        "placetype": [
          "aat:300008777"
        ],
        "id": 7161639,
        "name:xx": "Hohe-Berg"
      }
    }
  ]
}
