{
  "type": "FeatureCollection",
  "features": [
    {
      "geometry": {
        "type": "Point",
        "coordinates": [
          -83.35,
          38.45
        ]
      },
      "type": "Feature",
      "properties": {
        "hierarchy": [
          "tgn:2433560",
          "tgn:1000001",
          "tgn:7012149",
          "tgn:1002591",
          "tgn:7007255",
          "tgn:7029392"
        ],
        "placetype": [
          "aat:300008699"
        ],
        "id": 2433560,
        "name:xx": "Kelly Branch"
      }
    },
    {
      "geometry": {
        "type": "Point",
        "coordinates": [
          -88.9833,
          37.1833
        ]
      },
      "type": "Feature",
      "properties": {
        "hierarchy": [
          "tgn:2433561",
          "tgn:2000767",
          "tgn:1000001",
          "tgn:7012149",
          "tgn:7007255",
          "tgn:7029392"
        ],
        "placetype": [
          "aat:300008699"
        ],
        "id": 2433561,
        "name:xx": "Kelly Branch"
      }
    },
    {
      "geometry": {
        "type": "Point",
        "coordinates": [
          -83.95,
          37.2667
        ]
      },
      "type": "Feature",
      "properties": {
        "hierarchy": [
          "tgn:2433562",
          "tgn:1000001",
          "tgn:7012149",
          "tgn:7007255",
          "tgn:7029392"
        ],
        "placetype": [
          "aat:300008699"
        ],
        "id": 2433562,
        "name:xx": "Kelly Branch"
      }
    },
    {
      "geometry": {
        "type": "Point",
        "coordinates": [
          -76.6167,
          39.45
        ]
      },
      "type": "Feature",
      "properties": {
        "hierarchy": [
          "tgn:2433563",
          "tgn:7016099",
          "tgn:1000001",
          "tgn:7012149",
          "tgn:7007516",
          "tgn:7029392"
        ],
        "placetype": [
          "aat:300008699"
        ],
        "id": 2433563,
        "name:xx": "Kelly Branch"
      }
    },
    {
      "geometry": {
        "type": "Point",
        "coordinates": [
          -83.2333,
          43.5333
        ]
      },
      "type": "Feature",
      "properties": {
        "hierarchy": [
          "tgn:2433564",
          "tgn:1000001",
          "tgn:7012149",
          "tgn:2000997",
          "tgn:7007520",
          "tgn:7029392"
        ],
        "placetype": [
          "aat:300006075"
        ],
        "id": 2433564,
        "name:xx": "Kelly Branch"
      }
    },
    {
      "geometry": {
        "type": "Point",
        "coordinates": [
          -90.8833,
          31.2
        ]
      },
      "type": "Feature",
      "properties": {
        "hierarchy": [
          "tgn:2433565",
          "tgn:2001088",
          "tgn:1000001",
          "tgn:7012149",
          "tgn:7007522",
          "tgn:7029392"
        ],
        "placetype": [
          "aat:300008699"
        ],
        "id": 2433565,
        "name:xx": "Kelly Branch"
      }
    },
    {
      "geometry": {
        "type": "Point",
        "coordinates": [
          -92,
          38.7167
        ]
      },
      "type": "Feature",
      "properties": {
        "hierarchy": [
          "tgn:2433566",
          "tgn:1000001",
          "tgn:1002223",
          "tgn:7012149",
          "tgn:7007523",
          "tgn:7029392"
        ],
        "placetype": [
          "aat:300008699"
        ],
        "id": 2433566,
        "name:xx": "Kelly Branch"
      }
    },
    {
      "geometry": {
        "type": "Point",
        "coordinates": [
          -93.5167,
          37.3
        ]
      },
      "type": "Feature",
      "properties": {
        "hierarchy": [
          "tgn:2433567",
          "tgn:1000001",
          "tgn:7012149",
          "tgn:2001199",
          "tgn:7007523",
          "tgn:7029392"
        ],
        "placetype": [
          "aat:300008699"
        ],
        "id": 2433567,
        "name:xx": "Kelly Branch"
      }
    },
    {
      "geometry": {
        "type": "Point",
        "coordinates": [
          -91.2,
          38.0333
        ]
      },
      "type": "Feature",
      "properties": {
        "hierarchy": [
          "tgn:2433568",
          "tgn:1000001",
          "tgn:7012149",
          "tgn:2001190",
          "tgn:7007523",
          "tgn:7029392"
        ],
        "placetype": [
          "aat:300008699"
        ],
        "id": 2433568,
        "name:xx": "Kelly Branch"
      }
    },
    {
      "geometry": {
        "type": "Point",
        "coordinates": [
          -80.2667,
          34.9833
        ]
      },
      "type": "Feature",
      "properties": {
        "hierarchy": [
          "tgn:2433569",
          "tgn:2001466",
          "tgn:1000001",
          "tgn:7012149",
          "tgn:7007709",
          "tgn:7029392"
        ],
        "placetype": [
          "aat:300008699"
        ],
        "id": 2433569,
        "name:xx": "Kelly Branch"
      }
    }
  ]
}
