{
  "geometry": {
    "type": "Point",
    "coordinates": [
      -106.4167,
      37.2333
    ]
  },
  "type": "Feature",
  "properties": {
    "hierarchy": [
      "tgn:2471348",
      "tgn:1000001",
      "tgn:2000202",
      "tgn:7012149",
      "tgn:7007158",
      "tgn:7029392"
    ],
    "placetype": [
      "aat:300008680"
    ],
    "id": 2471348,
    "name:xx": "Lost Lake"
  }
}
