{
  "geometry": {
    "type": "Point",
    "coordinates": [
      -90.9167,
      36.3833
    ]
  },
  "type": "Feature",
  "properties": {
    "hierarchy": [
      "tgn:2446293",
      "tgn:1000001",
      "tgn:7016172",
      "tgn:7012149",
      "tgn:2000165",
      "tgn:7029392"
    ],
    "placetype": [
      "aat:300008706"
    ],
    "id": 2446293,
    "name:xx": "Lewis Creek"
  }
}
