{
  "geometry": {
    "type": "Point",
    "coordinates": [
      -93.1333,
      37.4833
    ]
  },
  "type": "Feature",
  "properties": {
    "hierarchy": [
      "tgn:2390010",
      "tgn:1000001",
      "tgn:7012149",
      "tgn:2001192",
      "tgn:7007523",
      "tgn:7029392"
    ],
    "placetype": [
      "aat:300055621"
    ],
    "id": 2390010,
    "name:xx": "High Prairie"
  }
}
