{
  "type": "FeatureCollection",
  "features": [
    {
      "geometry": {
        "type": "Point",
        "coordinates": [
          121.6,
          49.9833
        ]
      },
      "type": "Feature",
      "properties": {
        "hierarchy": [
          "tgn:1069000",
          "tgn:1000004",
          "tgn:7001838",
          "tgn:1000111",
          "tgn:7029392"
        ],
        "placetype": [
          "aat:300008347"
        ],
        "id": 1069000,
        "name:xx": "Huder"
      }
    },
    {
      "geometry": {
        "type": "Point",
        "coordinates": [
          115.9333,
          22.8167
        ]
      },
      "type": "Feature",
      "properties": {
        "hierarchy": [
          "tgn:1069001",
          "tgn:1000004",
          "tgn:7005232",
          "tgn:1000111",
          "tgn:7029392"
        ],
        "placetype": [
          "aat:300008347"
        ],
        "id": 1069001,
        "name:xx": "Hudong"
      }
    },
    {
      "geometry": {
        "type": "Point",
        "coordinates": [
          90,
          32.75
        ]
      },
      "type": "Feature",
      "properties": {
        "hierarchy": [
          "tgn:1069002",
          "tgn:1000004",
          "tgn:7001319",
          "tgn:1000111",
          "tgn:7029392"
        ],
        "placetype": [
          "aat:300008347"
        ],
        "id": 1069002,
        "name:xx": "Huerlumada"
      }
    },
    {
      "geometry": {
        "type": "Point",
        "coordinates": [
          106.1,
          29.7167
        ]
      },
      "type": "Feature",
      "properties": {
        "hierarchy": [
          "tgn:1069003",
          "tgn:1000004",
          "tgn:7002087",
          "tgn:1000111",
          "tgn:7029392"
        ],
        "placetype": [
          "aat:300008347"
        ],
        "id": 1069003,
        "name:xx": "Hufengchang"
      }
    },
    {
      "geometry": {
        "type": "Point",
        "coordinates": [
          119.8,
          31.2333
        ]
      },
      "type": "Feature",
      "properties": {
        "hierarchy": [
          "tgn:1069004",
          "tgn:1000004",
          "tgn:7002081",
          "tgn:1000111",
          "tgn:7029392"
        ],
        "placetype": [
          "aat:300008347"
        ],
        "id": 1069004,
        "name:xx": "Hufu"
      }
    },
    {
      "geometry": {
        "type": "Point",
        "coordinates": [
          117.1333,
          33.35
        ]
      },
      "type": "Feature",
      "properties": {
        "hierarchy": [
          "tgn:1069005",
          "tgn:7002075",
          "tgn:1000004",
          "tgn:1000111",
          "tgn:7029392"
        ],
        "placetype": [
          "aat:300008347"
        ],
        "id": 1069005,
        "name:xx": "Hugou"
      }
    },
    {
      "geometry": {
        "type": "Point",
        "coordinates": [
          118.8,
          25.0333
        ]
      },
      "type": "Feature",
      "properties": {
        "hierarchy": [
          "tgn:1069006",
          "tgn:1000004",
          "tgn:7001796",
          "tgn:1000111",
          "tgn:7029392"
        ],
        "placetype": [
          "aat:300008347"
        ],
        "id": 1069006,
        "name:xx": "Hui'an"
      }
    },
    {
      "geometry": {
        "type": "Point",
        "coordinates": [
          121.75,
          31.7833
        ]
      },
      "type": "Feature",
      "properties": {
        "hierarchy": [
          "tgn:1069007",
          "tgn:1000004",
          "tgn:7002081",
          "tgn:1000111",
          "tgn:7029392"
        ],
        "placetype": [
          "aat:300008347"
        ],
        "id": 1069007,
        "name:xx": "Hui-an"
      }
    },
    {
      "geometry": {
        "type": "Point",
        "coordinates": [
          115.25,
          28.3
        ]
      },
      "type": "Feature",
      "properties": {
        "hierarchy": [
          "tgn:1069008",
          "tgn:1000004",
          "tgn:7002082",
          "tgn:1000111",
          "tgn:7029392"
        ],
        "placetype": [
          "aat:300008347"
        ],
        "id": 1069008,
        "name:xx": "Huibu"
      }
    },
    {
      "geometry": {
        "type": "Point",
        "coordinates": [
          115.75,
          25.5333
        ]
      },
      "type": "Feature",
      "properties": {
        "hierarchy": [
          "tgn:1069009",
          "tgn:1000004",
          "tgn:7002082",
          "tgn:1000111",
          "tgn:7029392"
        ],
        "placetype": [
          "aat:300008347"
        ],
        "id": 1069009,
        "name:xx": "Huichang"
      }
    }
  ]
}
