{
  "geometry": {
    "type": "Point",
    "coordinates": [
      78.366667,
      12.55
    ]
  },
  "type": "Feature",
  "properties": {
    "hierarchy": [
      "tgn:7545192",
      "tgn:1000004",
      "tgn:7000198",
      "tgn:7001797",
      "tgn:7029392"
    ],
    "placetype": [
      "aat:300008347"
    ],
    "name:en": "Bargūru",
    "id": 7545192
  }
}
