{
  "type": "FeatureCollection",
  "features": [
    {
      "geometry": {
        "type": "Point",
        "coordinates": [
          -8.486,
          39.404
        ]
      },
      "type": "Feature",
      "properties": {
        "hierarchy": [
          "tgn:4004411",
          "tgn:1000003",
          "tgn:1000926",
          "tgn:1000090",
          "tgn:7029392"
        ],
        "placetype": [
          "aat:300008347"
        ],
        "id": 4004411,
        "name:xx": "Golegã"
      }
    },
    {
      "geometry": {
        "type": "Point",
        "coordinates": [
          9.283333,
          44.3
        ]
      },
      "type": "Feature",
      "properties": {
        "hierarchy": [
          "tgn:4004412",
          "tgn:1000003",
          "tgn:7003142",
          "tgn:7003236",
          "tgn:1000080",
          "tgn:7029392"
        ],
        "placetype": [
          "aat:300132315"
        ],
        "id": 4004412,
        "name:xx": "Golfo di Tigullio"
      }
    },
    {
      "geometry": {
        "type": "Point",
        "coordinates": [
          10.2,
          49.566667
        ]
      },
      "type": "Feature",
      "properties": {
        "hierarchy": [
          "tgn:4004413",
          "tgn:7003669",
          "tgn:1000003",
          "tgn:7000084",
          "tgn:7029392"
        ],
        "placetype": [
          "aat:300008347"
        ],
        "id": 4004413,
        "name:xx": "Gollhofen"
      }
    },
    {
      "geometry": {
        "type": "Point",
        "coordinates": [
          6.616667,
          49.966667
        ]
      },
      "type": "Feature",
      "properties": {
        "hierarchy": [
          "tgn:4004419",
          "tgn:1000003",
          "tgn:7003682",
          "tgn:7000084",
          "tgn:7029392"
        ],
        "placetype": [
          "aat:300008347"
        ],
        "id": 4004419,
        "name:xx": "Gondorf"
      }
    }
  ]
}
