{
  "geometry": {
    "type": "Point",
    "coordinates": [
      94.20013,
      26.843714
    ]
  },
  "type": "Feature",
  "properties": {
    "hierarchy": [
      "tgn:7571818",
      "tgn:1000004",
      "tgn:1001832",
      "tgn:7000198",
      "tgn:7029392"
    ],
    "placetype": [
      "aat:300008347"
    ],
    "name:en": "Gohāingaon",
    "id": 7571818
  }
}
