{
  "geometry": {
    "type": "Point",
    "coordinates": [
      -92.05,
      35.6833
    ]
  },
  "type": "Feature",
  "properties": {
    "hierarchy": [
      "tgn:2699786",
      "tgn:1000001",
      "tgn:7016172",
      "tgn:2000116",
      "tgn:7012149",
      "tgn:7029392"
    ],
    "placetype": [
      "aat:300008850"
    ],
    "id": 2699786,
    "name:xx": "Stubbs Point"
  }
}
