{
  "geometry": {
    "type": "Point",
    "coordinates": [
      28.5167,
      50.1167
    ]
  },
  "type": "Feature",
  "properties": {
    "hierarchy": [
      "tgn:1060446",
      "tgn:1000003",
      "tgn:7011671",
      "tgn:7006660",
      "tgn:7029392"
    ],
    "placetype": [
      "aat:300008347"
    ],
    "id": 1060446,
    "name:xx": "Troyaniv"
  }
}
