{
  "type": "FeatureCollection",
  "features": [
    {
      "geometry": {
        "type": "Point",
        "coordinates": [
          -112.4,
          34.45
        ]
      },
      "type": "Feature",
      "properties": {
        "hierarchy": [
          "tgn:1106550",
          "tgn:1000001",
          "tgn:7006451",
          "tgn:7012149",
          "tgn:2000103",
          "tgn:7029392"
        ],
        "placetype": [
          "aat:300008795"
        ],
        "id": 1106550,
        "name:xx": "Spruce Mountain"
      }
    },
    {
      "geometry": {
        "type": "Point",
        "coordinates": [
          -114.8167,
          40.55
        ]
      },
      "type": "Feature",
      "properties": {
        "hierarchy": [
          "tgn:1106551",
          "tgn:1000001",
          "tgn:2001411",
          "tgn:7012149",
          "tgn:7007526",
          "tgn:7029392"
        ],
        "placetype": [
          "aat:300008795"
        ],
        "id": 1106551,
        "name:xx": "Spruce Mountain"
      }
    },
    {
      "geometry": {
        "type": "Point",
        "coordinates": [
          -152.25,
          61.2833
        ]
      },
      "type": "Feature",
      "properties": {
        "hierarchy": [
          "tgn:1106552",
          "tgn:7006450",
          "tgn:1000001",
          "tgn:7019698",
          "tgn:7012149",
          "tgn:7029392"
        ],
        "placetype": [
          "aat:300008795"
        ],
        "id": 1106552,
        "name:xx": "Spurr, Mount"
      }
    },
    {
      "geometry": {
        "type": "Point",
        "coordinates": [
          -66.8833,
          47.8833
        ]
      },
      "type": "Feature",
      "properties": {
        "hierarchy": [
          "tgn:1106553",
          "tgn:7005685",
          "tgn:1000001",
          "tgn:7005799",
          "tgn:7029392"
        ],
        "placetype": [
          "aat:300008795"
        ],
        "id": 1106553,
        "name:xx": "Squaw Cap Mountain"
      }
    },
    {
      "geometry": {
        "type": "Point",
        "coordinates": [
          -105.0167,
          41.8
        ]
      },
      "type": "Feature",
      "properties": {
        "hierarchy": [
          "tgn:1106554",
          "tgn:1000001",
          "tgn:7012149",
          "tgn:2002380",
          "tgn:7007923",
          "tgn:7029392"
        ],
        "placetype": [
          "aat:300008795"
        ],
        "id": 1106554,
        "name:xx": "Squaw Hill"
      }
    },
    {
      "geometry": {
        "type": "Point",
        "coordinates": [
          13.566,
          49.4
        ]
      },
      "type": "Feature",
      "properties": {
        "hierarchy": [
          "tgn:1106557",
          "tgn:7593919",
          "tgn:1000003",
          "tgn:1001780",
          "tgn:7029392"
        ],
        "placetype": [
          "aat:300008795"
        ],
        "id": 1106557,
        "name:xx": "Stírka"
      }
    },
    {
      "geometry": {
        "type": "Point",
        "coordinates": [
          10.566667,
          51.65
        ]
      },
      "type": "Feature",
      "properties": {
        "hierarchy": [
          "tgn:1106559",
          "tgn:1000003",
          "tgn:7003676",
          "tgn:7000084",
          "tgn:7029392"
        ],
        "placetype": [
          "aat:300008777",
          "aat:300008795"
        ],
        "id": 1106559,
        "name:xx": "Stöberhai"
      }
    }
  ]
}
