{
  "geometry": {
    "type": "Point",
    "coordinates": [
      121.8099,
      24.6396
    ]
  },
  "type": "Feature",
  "properties": {
    "hierarchy": [
      "tgn:7490446",
      "tgn:1000004",
      "tgn:7489179",
      "tgn:1000141",
      "tgn:7029392"
    ],
    "placetype": [
      "aat:300387173"
    ],
    "id": 7490446,
    "name:xx": "Sanqi Cun"
  }
}
