{
  "geometry": {
    "type": "Point",
    "coordinates": [
      -54.3333,
      -4.75
    ]
  },
  "type": "Feature",
  "properties": {
    "hierarchy": [
      "tgn:1122519",
      "tgn:7006247",
      "tgn:1000047",
      "tgn:7002456",
      "tgn:1000002",
      "tgn:7029392"
    ],
    "placetype": [
      "aat:300008707"
    ],
    "id": 1122519,
    "name:xx": "Carajari"
  }
}
