{
  "geometry": {
    "type": "Point",
    "coordinates": [
      -90.2833,
      31.4667
    ]
  },
  "type": "Feature",
  "properties": {
    "hierarchy": [
      "tgn:2762338",
      "tgn:1000001",
      "tgn:7012149",
      "tgn:7007522",
      "tgn:7029392"
    ],
    "placetype": [
      "aat:300008706"
    ],
    "id": 2762338,
    "name:xx": "West Topisaw Creek"
  }
}
