{
  "geometry": {
    "type": "Point",
    "coordinates": [
      -84.8333,
      35.2167
    ]
  },
  "type": "Feature",
  "properties": {
    "hierarchy": [
      "tgn:2681013",
      "tgn:1000001",
      "tgn:2001842",
      "tgn:7012149",
      "tgn:7007825",
      "tgn:7029392"
    ],
    "placetype": [
      "aat:300008347"
    ],
    "id": 2681013,
    "name:xx": "South Mapleton Hills"
  }
}
