{
  "type": "FeatureCollection",
  "features": [
    {
      "geometry": {
        "type": "Point",
        "coordinates": [
          -82.6167,
          27.5
        ]
      },
      "type": "Feature",
      "properties": {
        "hierarchy": [
          "tgn:2020740",
          "tgn:1000001",
          "tgn:7012149",
          "tgn:1002628",
          "tgn:7007240",
          "tgn:7029392"
        ],
        "placetype": [
          "aat:300008347"
        ],
        "id": 2020740,
        "name:xx": "Palma Sola"
      }
    },
    {
      "geometry": {
        "type": "Point",
        "coordinates": [
          -80.5833,
          28.0333
        ]
      },
      "type": "Feature",
      "properties": {
        "hierarchy": [
          "tgn:2020743",
          "tgn:1000001",
          "tgn:1002200",
          "tgn:7012149",
          "tgn:7007240",
          "tgn:7029392"
        ],
        "placetype": [
          "aat:300008347"
        ],
        "id": 2020743,
        "name:xx": "Palm Bay"
      }
    },
    {
      "geometry": {
        "type": "Point",
        "coordinates": [
          -80.1333,
          26.8167
        ]
      },
      "type": "Feature",
      "properties": {
        "hierarchy": [
          "tgn:2020747",
          "tgn:1000001",
          "tgn:7012149",
          "tgn:1002768",
          "tgn:7007240",
          "tgn:7029392"
        ],
        "placetype": [
          "aat:300008347"
        ],
        "id": 2020747,
        "name:xx": "Palm Beach Gardens"
      }
    },
    {
      "geometry": {
        "type": "Point",
        "coordinates": [
          -80.0333,
          26.7667
        ]
      },
      "type": "Feature",
      "properties": {
        "hierarchy": [
          "tgn:2020748",
          "tgn:1000001",
          "tgn:7012149",
          "tgn:1002768",
          "tgn:7007240",
          "tgn:7029392"
        ],
        "placetype": [
          "aat:300008347"
        ],
        "id": 2020748,
        "name:xx": "Palm Beach Shores"
      }
    },
    {
      "geometry": {
        "type": "Point",
        "coordinates": [
          -80.25,
          27.1667
        ]
      },
      "type": "Feature",
      "properties": {
        "hierarchy": [
          "tgn:2020749",
          "tgn:1000001",
          "tgn:7012149",
          "tgn:1002641",
          "tgn:7007240",
          "tgn:7029392"
        ],
        "placetype": [
          "aat:300008347"
        ],
        "id": 2020749,
        "name:xx": "Palm City"
      }
    }
  ]
}
