{
  "geometry": {
    "type": "Point",
    "coordinates": [
      -87.1833,
      34.8333
    ]
  },
  "type": "Feature",
  "properties": {
    "hierarchy": [
      "tgn:2219416",
      "tgn:7002659",
      "tgn:1000001",
      "tgn:7012149",
      "tgn:2000041",
      "tgn:7029392"
    ],
    "placetype": [
      "aat:300008761"
    ],
    "id": 2219416,
    "name:xx": "Cannon Hollow"
  }
}
