{
  "geometry": {
    "type": "Point",
    "coordinates": [
      27.8167,
      48.4833
    ]
  },
  "type": "Feature",
  "properties": {
    "hierarchy": [
      "tgn:1057068",
      "tgn:1000003",
      "tgn:7011999",
      "tgn:7006660",
      "tgn:7029392"
    ],
    "placetype": [
      "aat:300008347"
    ],
    "id": 1057068,
    "name:xx": "Mogilev-Podolskiy"
  }
}
