{
  "geometry": {
    "type": "Point",
    "coordinates": [
      -122.8667,
      38.0333
    ]
  },
  "type": "Feature",
  "properties": {
    "hierarchy": [
      "tgn:2530672",
      "tgn:1000001",
      "tgn:7012149",
      "tgn:7007157",
      "tgn:7014005",
      "tgn:7029392"
    ],
    "placetype": [
      "aat:300386845"
    ],
    "id": 2530672,
    "name:xx": "Muddy Hollow"
  }
}
