{
  "geometry": {
    "type": "Point",
    "coordinates": [
      -75.8333,
      35.1833
    ]
  },
  "type": "Feature",
  "properties": {
    "hierarchy": [
      "tgn:2444692",
      "tgn:1000001",
      "tgn:7012149",
      "tgn:2001506",
      "tgn:7007709",
      "tgn:7029392"
    ],
    "placetype": [
      "aat:300132348"
    ],
    "id": 2444692,
    "name:xx": "Legged Lump"
  }
}
