{
  "geometry": {
    "type": "Point",
    "coordinates": [
      -81.0667,
      41.3667
    ]
  },
  "type": "Feature",
  "properties": {
    "hierarchy": [
      "tgn:2319159",
      "tgn:1000001",
      "tgn:7012149",
      "tgn:7021516",
      "tgn:7007706",
      "tgn:7029392"
    ],
    "placetype": [
      "aat:300008680"
    ],
    "id": 2319159,
    "name:xx": "Estabrook, Lake"
  }
}
