{
  "type": "FeatureCollection",
  "features": [
    {
      "geometry": {
        "type": "Point",
        "coordinates": [
          -89.5667,
          41.1833
        ]
      },
      "type": "Feature",
      "properties": {
        "hierarchy": [
          "tgn:2515820",
          "tgn:1000001",
          "tgn:2000497",
          "tgn:7012149",
          "tgn:7007251",
          "tgn:7029392"
        ],
        "placetype": [
          "aat:300008347"
        ],
        "id": 2515820,
        "name:xx": "Milo"
      }
    },
    {
      "geometry": {
        "type": "Point",
        "coordinates": [
          -97.9667,
          39.1667
        ]
      },
      "type": "Feature",
      "properties": {
        "hierarchy": [
          "tgn:2515821",
          "tgn:1000001",
          "tgn:7012149",
          "tgn:2000712",
          "tgn:7007254",
          "tgn:7029392"
        ],
        "placetype": [
          "aat:300008347"
        ],
        "id": 2515821,
        "name:xx": "Milo"
      }
    },
    {
      "geometry": {
        "type": "Point",
        "coordinates": [
          -82.9833,
          39.9833
        ]
      },
      "type": "Feature",
      "properties": {
        "hierarchy": [
          "tgn:2515822",
          "tgn:1000001",
          "tgn:7012149",
          "tgn:1002386",
          "tgn:7007706",
          "tgn:7029392"
        ],
        "placetype": [
          "aat:300008347"
        ],
        "id": 2515822,
        "name:xx": "Milo"
      }
    },
    {
      "geometry": {
        "type": "Point",
        "coordinates": [
          -111.8167,
          40.65
        ]
      },
      "type": "Feature",
      "properties": {
        "hierarchy": [
          "tgn:2515824",
          "tgn:1000001",
          "tgn:7012149",
          "tgn:2002118",
          "tgn:7007827",
          "tgn:7029392"
        ],
        "placetype": [
          "aat:300008347"
        ],
        "id": 2515824,
        "name:xx": "Milo"
      }
    },
    {
      "geometry": {
        "type": "Point",
        "coordinates": [
          -106.4167,
          41.6167
        ]
      },
      "type": "Feature",
      "properties": {
        "hierarchy": [
          "tgn:2515825",
          "tgn:1000001",
          "tgn:2002368",
          "tgn:7012149",
          "tgn:7007923",
          "tgn:7029392"
        ],
        "placetype": [
          "aat:300008347"
        ],
        "id": 2515825,
        "name:xx": "Milo"
      }
    },
    {
      "geometry": {
        "type": "Point",
        "coordinates": [
          -112.95,
          44.4167
        ]
      },
      "type": "Feature",
      "properties": {
        "hierarchy": [
          "tgn:2515826",
          "tgn:1000001",
          "tgn:7012149",
          "tgn:2000481",
          "tgn:7007250",
          "tgn:7029392"
        ],
        "placetype": [
          "aat:300008761"
        ],
        "id": 2515826,
        "name:xx": "Milo Canyon"
      }
    },
    {
      "geometry": {
        "type": "Point",
        "coordinates": [
          -107.4167,
          33.5667
        ]
      },
      "type": "Feature",
      "properties": {
        "hierarchy": [
          "tgn:2515827",
          "tgn:1000001",
          "tgn:7012149",
          "tgn:2001456",
          "tgn:7007566",
          "tgn:7029392"
        ],
        "placetype": [
          "aat:300008761"
        ],
        "id": 2515827,
        "name:xx": "Milo Canyon"
      }
    },
    {
      "geometry": {
        "type": "Point",
        "coordinates": [
          -102.4,
          34.9667
        ]
      },
      "type": "Feature",
      "properties": {
        "hierarchy": [
          "tgn:2515828",
          "tgn:1000001",
          "tgn:7012149",
          "tgn:2001972",
          "tgn:7007826",
          "tgn:7029392"
        ],
        "placetype": [
          "aat:300008347"
        ],
        "id": 2515828,
        "name:xx": "Milo Center"
      }
    },
    {
      "geometry": {
        "type": "Point",
        "coordinates": [
          -158.1167,
          21.3333
        ]
      },
      "type": "Feature",
      "properties": {
        "hierarchy": [
          "tgn:2515829",
          "tgn:1002483",
          "tgn:7019080",
          "tgn:1000001",
          "tgn:7012149",
          "tgn:7007249",
          "tgn:7029392"
        ],
        "placetype": [
          "aat:300132316"
        ],
        "id": 2515829,
        "name:xx": "Milo Cove"
      }
    }
  ]
}
