{
  "geometry": {
    "type": "Point",
    "coordinates": [
      -93.2833,
      31.45
    ]
  },
  "type": "Feature",
  "properties": {
    "hierarchy": [
      "tgn:2685738",
      "tgn:1000001",
      "tgn:7012149",
      "tgn:2000896",
      "tgn:7007256",
      "tgn:7029392"
    ],
    "placetype": [
      "aat:300008699"
    ],
    "id": 2685738,
    "name:xx": "Spring Branch"
  }
}
