{
  "geometry": {
    "type": "Point",
    "coordinates": [
      -108.45,
      35.3667
    ]
  },
  "type": "Feature",
  "properties": {
    "hierarchy": [
      "tgn:2150271",
      "tgn:1000001",
      "tgn:7012149",
      "tgn:7019676",
      "tgn:7007566",
      "tgn:7029392"
    ],
    "placetype": [
      "aat:300006191"
    ],
    "id": 2150271,
    "name:xx": "Basgal Tank"
  }
}
