{
  "type": "FeatureCollection",
  "features": [
    {
      "geometry": {
        "type": "Point",
        "coordinates": [
          5.783333,
          50.416667
        ]
      },
      "type": "Feature",
      "properties": {
        "hierarchy": [
          "tgn:7241491",
          "tgn:7003460",
          "tgn:1000003",
          "tgn:1000063",
          "tgn:4012014",
          "tgn:7029392"
        ],
        "placetype": [
          "aat:300008699"
        ],
        "id": 7241491,
        "name:xx": "Lienne"
      }
    },
    {
      "geometry": {
        "type": "Point",
        "coordinates": [
          5.087431,
          50.307856
        ]
      },
      "type": "Feature",
      "properties": {
        "hierarchy": [
          "tgn:7241492",
          "tgn:7003466",
          "tgn:1000003",
          "tgn:1000063",
          "tgn:4012014",
          "tgn:7029392"
        ],
        "placetype": [
          "aat:300008347"
        ],
        "id": 7241492,
        "name:xx": "Lienne"
      }
    },
    {
      "geometry": {
        "type": "Point",
        "coordinates": [
          5.283333,
          50.3
        ]
      },
      "type": "Feature",
      "properties": {
        "hierarchy": [
          "tgn:7241493",
          "tgn:7003466",
          "tgn:1000003",
          "tgn:1000063",
          "tgn:4012014",
          "tgn:7029392"
        ],
        "placetype": [
          "aat:300008347"
        ],
        "id": 7241493,
        "name:xx": "Liéneux"
      }
    },
    {
      "geometry": {
        "type": "Point",
        "coordinates": [
          3.783333,
          50.666667
        ]
      },
      "type": "Feature",
      "properties": {
        "hierarchy": [
          "tgn:7241494",
          "tgn:7007877",
          "tgn:1000003",
          "tgn:1000063",
          "tgn:4012014",
          "tgn:7029392"
        ],
        "placetype": [
          "aat:300000206"
        ],
        "id": 7241494,
        "name:xx": "Liénart"
      }
    },
    {
      "geometry": {
        "type": "Point",
        "coordinates": [
          5.033333,
          50.916667
        ]
      },
      "type": "Feature",
      "properties": {
        "hierarchy": [
          "tgn:7241499",
          "tgn:7003461",
          "tgn:1000003",
          "tgn:1000063",
          "tgn:7018236",
          "tgn:7029392"
        ],
        "placetype": [
          "aat:300000206"
        ],
        "id": 7241499,
        "name:xx": "Liefkensrode"
      }
    }
  ]
}
