{
  "geometry": {
    "type": "Point",
    "coordinates": [
      29.319192,
      30.858757
    ]
  },
  "type": "Feature",
  "properties": {
    "hierarchy": [
      "tgn:7526223",
      "tgn:7001242",
      "tgn:7016833",
      "tgn:1001418",
      "tgn:7029392"
    ],
    "placetype": [
      "aat:300005926"
    ],
    "name:en": "Man훮mat S카d카 Khal카fah",
    "id": 7526223
  }
}
