{
  "geometry": {
    "type": "Point",
    "coordinates": [
      -113.0833,
      37.4833
    ]
  },
  "type": "Feature",
  "properties": {
    "hierarchy": [
      "tgn:2530055",
      "tgn:1000001",
      "tgn:7012149",
      "tgn:2002111",
      "tgn:7007827",
      "tgn:7029392"
    ],
    "placetype": [
      "aat:300008697"
    ],
    "id": 2530055,
    "name:xx": "Mud Spring"
  }
}
