{
  "geometry": {
    "type": "Point",
    "coordinates": [
      -93.2833,
      31.3833
    ]
  },
  "type": "Feature",
  "properties": {
    "hierarchy": [
      "tgn:2436347",
      "tgn:1000001",
      "tgn:7012149",
      "tgn:2000896",
      "tgn:7007256",
      "tgn:7029392"
    ],
    "placetype": [
      "aat:300008699"
    ],
    "id": 2436347,
    "name:xx": "Kib Bayou"
  }
}
