{
  "geometry": {
    "type": "Point",
    "coordinates": [
      -94.8333,
      31.15
    ]
  },
  "type": "Feature",
  "properties": {
    "hierarchy": [
      "tgn:2554406",
      "tgn:1002149",
      "tgn:1000001",
      "tgn:7012149",
      "tgn:7007826",
      "tgn:7029392"
    ],
    "placetype": [
      "aat:300266640"
    ],
    "id": 2554406,
    "name:xx": "Oakey Ridge"
  }
}
