{
  "geometry": {
    "type": "Point",
    "coordinates": [
      -93.7167,
      42.5167
    ]
  },
  "type": "Feature",
  "properties": {
    "hierarchy": [
      "tgn:2477436",
      "tgn:1000001",
      "tgn:2000600",
      "tgn:7012149",
      "tgn:7007253",
      "tgn:7029392"
    ],
    "placetype": [
      "aat:300008706"
    ],
    "id": 2477436,
    "name:xx": "Lyons Creek"
  }
}
