{
  "geometry": {
    "type": "Point",
    "coordinates": [
      116.35,
      38.8833
    ]
  },
  "type": "Feature",
  "properties": {
    "hierarchy": [
      "tgn:1067585",
      "tgn:1000004",
      "tgn:7002077",
      "tgn:1000111",
      "tgn:7029392"
    ],
    "placetype": [
      "aat:300008347"
    ],
    "id": 1067585,
    "name:xx": "Dawangdong"
  }
}
