{
  "geometry": {
    "type": "Point",
    "coordinates": [
      -85.1667,
      34.1833
    ]
  },
  "type": "Feature",
  "properties": {
    "hierarchy": [
      "tgn:2023404",
      "tgn:1000001",
      "tgn:7012149",
      "tgn:2000348",
      "tgn:7007248",
      "tgn:7029392"
    ],
    "placetype": [
      "aat:300008347"
    ],
    "id": 2023404,
    "name:xx": "Lindale"
  }
}
