{
  "geometry": {
    "type": "Point",
    "coordinates": [
      26.355556,
      41.6675
    ]
  },
  "type": "Feature",
  "properties": {
    "hierarchy": [
      "tgn:7230445",
      "tgn:7011163",
      "tgn:7002674",
      "tgn:1000003",
      "tgn:1000074",
      "tgn:7029392"
    ],
    "placetype": [
      "aat:300008347"
    ],
    "id": 7230445,
    "name:xx": "Kriós"
  }
}
