{
  "geometry": {
    "type": "Point",
    "coordinates": [
      -76.9833,
      38.9167
    ]
  },
  "type": "Feature",
  "properties": {
    "hierarchy": [
      "tgn:1004176",
      "tgn:7013962",
      "tgn:1000001",
      "tgn:7012149",
      "tgn:7015717",
      "tgn:7029392"
    ],
    "placetype": [
      "aat:300000745"
    ],
    "id": 1004176,
    "name:xx": "Brookland"
  }
}
