{
  "geometry": {
    "type": "Point",
    "coordinates": [
      38.5167,
      17.35
    ]
  },
  "type": "Feature",
  "properties": {
    "hierarchy": [
      "tgn:1089702",
      "tgn:7001242",
      "tgn:7017564",
      "tgn:7001658",
      "tgn:7029392"
    ],
    "placetype": [
      "aat:300008347"
    ],
    "id": 1089702,
    "name:xx": "Algena"
  }
}
