{
  "geometry": {
    "type": "Point",
    "coordinates": [
      120.6607,
      24.2005
    ]
  },
  "type": "Feature",
  "properties": {
    "hierarchy": [
      "tgn:7497519",
      "tgn:1000004",
      "tgn:7001009",
      "tgn:1000141",
      "tgn:7029392"
    ],
    "placetype": [
      "aat:300007836"
    ],
    "id": 7497519,
    "name:xx": "Taiyu Qiao"
  }
}
