{
  "type": "FeatureCollection",
  "features": [
    {
      "geometry": {
        "type": "Point",
        "coordinates": [
          47,
          33.1667
        ]
      },
      "type": "Feature",
      "properties": {
        "hierarchy": [
          "tgn:7000227",
          "tgn:1000004",
          "tgn:7000231",
          "tgn:7029392"
        ],
        "placetype": [
          "aat:300387064",
          "aat:300000774"
        ],
        "id": 7000227,
        "name:xx": "Īlām"
      }
    },
    {
      "geometry": {
        "type": "Point",
        "coordinates": [
          56,
          26.75
        ]
      },
      "type": "Feature",
      "properties": {
        "hierarchy": [
          "tgn:7000228",
          "tgn:1000004",
          "tgn:7000231",
          "tgn:7029392"
        ],
        "placetype": [
          "aat:300387064",
          "aat:300000774"
        ],
        "id": 7000228,
        "name:xx": "Hormozgān"
      }
    },
    {
      "geometry": {
        "type": "Point",
        "coordinates": [
          72.683333,
          23.216667
        ]
      },
      "type": "Feature",
      "properties": {
        "hierarchy": [
          "tgn:7000229",
          "tgn:1000004",
          "tgn:1001869",
          "tgn:7000198",
          "tgn:7029392"
        ],
        "placetype": [
          "aat:300008347",
          "aat:300387220",
          "aat:300387221",
          "aat:300008375"
        ],
        "name:en": "Gāndhīnagar",
        "id": 7000229
      }
    }
  ]
}
