{
  "geometry": {
    "type": "Point",
    "coordinates": [
      -115.7167,
      45.1667
    ]
  },
  "type": "Feature",
  "properties": {
    "hierarchy": [
      "tgn:2692460",
      "tgn:1000001",
      "tgn:7012149",
      "tgn:7007250",
      "tgn:7029392"
    ],
    "placetype": [
      "aat:300008706"
    ],
    "id": 2692460,
    "name:xx": "Steamboat Creek"
  }
}
