{
  "geometry": {
    "type": "Point",
    "coordinates": [
      -85.9667,
      32.9833
    ]
  },
  "type": "Feature",
  "properties": {
    "hierarchy": [
      "tgn:2573081",
      "tgn:7002659",
      "tgn:1000001",
      "tgn:7012149",
      "tgn:2000061",
      "tgn:7029392"
    ],
    "placetype": [
      "aat:300008347"
    ],
    "id": 2573081,
    "name:xx": "Pearson Chapel"
  }
}
