{
  "geometry": {
    "type": "Point",
    "coordinates": [
      -109.45,
      33.1833
    ]
  },
  "type": "Feature",
  "properties": {
    "hierarchy": [
      "tgn:2240325",
      "tgn:1000001",
      "tgn:7006451",
      "tgn:2000095",
      "tgn:7012149",
      "tgn:7029392"
    ],
    "placetype": [
      "aat:300006191"
    ],
    "id": 2240325,
    "name:xx": "Cistern Tank"
  }
}
