{
  "type": "FeatureCollection",
  "features": [
    {
      "geometry": {
        "type": "Point",
        "coordinates": [
          13.526944,
          46.481389
        ]
      },
      "type": "Feature",
      "properties": {
        "hierarchy": [
          "tgn:7052801",
          "tgn:1003506",
          "tgn:1000003",
          "tgn:7002993",
          "tgn:1000080",
          "tgn:7029392"
        ],
        "placetype": [
          "aat:300008347"
        ],
        "id": 7052801,
        "name:xx": "Montesanto di Lussari"
      }
    },
    {
      "geometry": {
        "type": "Point",
        "coordinates": [
          12.933333,
          42.9
        ]
      },
      "type": "Feature",
      "properties": {
        "hierarchy": [
          "tgn:7052803",
          "tgn:7003170",
          "tgn:1000003",
          "tgn:7003125",
          "tgn:1000080",
          "tgn:7029392"
        ],
        "placetype": [
          "aat:300008347"
        ],
        "id": 7052803,
        "name:xx": "Montesanto"
      }
    },
    {
      "geometry": {
        "type": "Point",
        "coordinates": [
          12.766667,
          42.216667
        ]
      },
      "type": "Feature",
      "properties": {
        "hierarchy": [
          "tgn:7052806",
          "tgn:7003137",
          "tgn:1000003",
          "tgn:7003080",
          "tgn:1000080",
          "tgn:7029392"
        ],
        "placetype": [
          "aat:300008347"
        ],
        "id": 7052806,
        "name:xx": "Monte Santa Maria"
      }
    },
    {
      "geometry": {
        "type": "Point",
        "coordinates": [
          11.133333,
          44.433333
        ]
      },
      "type": "Feature",
      "properties": {
        "hierarchy": [
          "tgn:7052808",
          "tgn:7003127",
          "tgn:1000003",
          "tgn:7008516",
          "tgn:1000080",
          "tgn:7029392"
        ],
        "placetype": [
          "aat:300008347"
        ],
        "id": 7052808,
        "name:xx": "Monte San Pietro"
      }
    },
    {
      "geometry": {
        "type": "Point",
        "coordinates": [
          13.566667,
          43.183333
        ]
      },
      "type": "Feature",
      "properties": {
        "hierarchy": [
          "tgn:7052809",
          "tgn:1003471",
          "tgn:1000003",
          "tgn:7003240",
          "tgn:1000080",
          "tgn:7029392"
        ],
        "placetype": [
          "aat:300008347"
        ],
        "id": 7052809,
        "name:xx": "Monte San Pietrangeli"
      }
    }
  ]
}
