{
  "geometry": {
    "type": "Point",
    "coordinates": [
      -118.6667,
      45.3167
    ]
  },
  "type": "Feature",
  "properties": {
    "hierarchy": [
      "tgn:2677417",
      "tgn:1000001",
      "tgn:7012149",
      "tgn:7007708",
      "tgn:7029392"
    ],
    "placetype": [
      "aat:300008761"
    ],
    "id": 2677417,
    "name:xx": "South Canyon"
  }
}
