{
  "geometry": {
    "type": "Point",
    "coordinates": [
      -110.2833,
      38.3333
    ]
  },
  "type": "Feature",
  "properties": {
    "hierarchy": [
      "tgn:2358166",
      "tgn:1000001",
      "tgn:7012149",
      "tgn:2002128",
      "tgn:7007827",
      "tgn:7029392"
    ],
    "placetype": [
      "aat:300008697"
    ],
    "id": 2358166,
    "name:xx": "Granary Spring"
  }
}
