{
  "geometry": {
    "type": "Point",
    "coordinates": [
      -71.1167,
      -17.8167
    ]
  },
  "type": "Feature",
  "properties": {
    "hierarchy": [
      "tgn:7026150",
      "tgn:1000773",
      "tgn:1000002",
      "tgn:1000056",
      "tgn:7029392"
    ],
    "placetype": [
      "aat:300266554"
    ],
    "id": 7026150,
    "name:xx": "Tacahuay, Quebrada"
  }
}
