{
  "type": "FeatureCollection",
  "features": [
    {
      "geometry": {
        "type": "Point",
        "coordinates": [
          76.940687,
          33.687702
        ]
      },
      "type": "Feature",
      "properties": {
        "hierarchy": [
          "tgn:7572400",
          "tgn:1000004",
          "tgn:7000198",
          "tgn:7000799",
          "tgn:7029392"
        ],
        "placetype": [
          "aat:300008347"
        ],
        "name:en": "Honia",
        "id": 7572400
      }
    },
    {
      "geometry": {
        "type": "Point",
        "coordinates": [
          77.933333,
          13.4
        ]
      },
      "type": "Feature",
      "properties": {
        "hierarchy": [
          "tgn:7572401",
          "tgn:1000004",
          "tgn:7000198",
          "tgn:1001882",
          "tgn:7029392"
        ],
        "placetype": [
          "aat:300007783"
        ],
        "name:en": "Hongashenhalli",
        "id": 7572401
      }
    },
    {
      "geometry": {
        "type": "Point",
        "coordinates": [
          77.233333,
          12.6
        ]
      },
      "type": "Feature",
      "properties": {
        "hierarchy": [
          "tgn:7572402",
          "tgn:1000004",
          "tgn:7000198",
          "tgn:1001882",
          "tgn:7029392"
        ],
        "placetype": [
          "aat:300008347"
        ],
        "name:en": "Honganūr",
        "id": 7572402
      }
    },
    {
      "geometry": {
        "type": "Point",
        "coordinates": [
          77.05,
          11.983333
        ]
      },
      "type": "Feature",
      "properties": {
        "hierarchy": [
          "tgn:7572403",
          "tgn:1000004",
          "tgn:7000198",
          "tgn:1001882",
          "tgn:7029392"
        ],
        "placetype": [
          "aat:300008347"
        ],
        "name:en": "Honganūr",
        "id": 7572403
      }
    },
    {
      "geometry": {
        "type": "Point",
        "coordinates": [
          93.849496,
          27.559219
        ]
      },
      "type": "Feature",
      "properties": {
        "hierarchy": [
          "tgn:7572404",
          "tgn:7001819",
          "tgn:1000004",
          "tgn:7000198",
          "tgn:7029392"
        ],
        "placetype": [
          "aat:300008347"
        ],
        "name:en": "Hong",
        "id": 7572404
      }
    },
    {
      "geometry": {
        "type": "Point",
        "coordinates": [
          76.7,
          12.7
        ]
      },
      "type": "Feature",
      "properties": {
        "hierarchy": [
          "tgn:7572406",
          "tgn:1000004",
          "tgn:7000198",
          "tgn:1001882",
          "tgn:7029392"
        ],
        "placetype": [
          "aat:300008347"
        ],
        "name:en": "Honakere",
        "id": 7572406
      }
    },
    {
      "geometry": {
        "type": "Point",
        "coordinates": [
          78.230894,
          31.744528
        ]
      },
      "type": "Feature",
      "properties": {
        "hierarchy": [
          "tgn:7572407",
          "tgn:1000004",
          "tgn:7000198",
          "tgn:1001996",
          "tgn:7029392"
        ],
        "placetype": [
          "aat:300008347"
        ],
        "name:en": "Homtich Thāch",
        "id": 7572407
      }
    },
    {
      "geometry": {
        "type": "Point",
        "coordinates": [
          92.866667,
          12.3
        ]
      },
      "type": "Feature",
      "properties": {
        "hierarchy": [
          "tgn:7572409",
          "tgn:1009838",
          "tgn:7000204",
          "tgn:1000004",
          "tgn:7000198",
          "tgn:7029392"
        ],
        "placetype": [
          "aat:300266559"
        ],
        "name:en": "Homfray Strait",
        "id": 7572409
      }
    }
  ]
}
