{
  "type": "FeatureCollection",
  "features": [
    {
      "geometry": {
        "type": "Point",
        "coordinates": [
          -156.2667,
          61.5
        ]
      },
      "type": "Feature",
      "properties": {
        "hierarchy": [
          "tgn:2175640",
          "tgn:7006450",
          "tgn:2000069",
          "tgn:1000001",
          "tgn:7012149",
          "tgn:7029392"
        ],
        "placetype": [
          "aat:300008706"
        ],
        "id": 2175640,
        "name:xx": "Black Creek"
      }
    },
    {
      "geometry": {
        "type": "Point",
        "coordinates": [
          -150.95,
          62.3833
        ]
      },
      "type": "Feature",
      "properties": {
        "hierarchy": [
          "tgn:2175641",
          "tgn:7006450",
          "tgn:1000001",
          "tgn:2124053",
          "tgn:7012149",
          "tgn:7029392"
        ],
        "placetype": [
          "aat:300008706"
        ],
        "id": 2175641,
        "name:xx": "Black Creek"
      }
    },
    {
      "geometry": {
        "type": "Point",
        "coordinates": [
          -157.9667,
          62.4167
        ]
      },
      "type": "Feature",
      "properties": {
        "hierarchy": [
          "tgn:2175642",
          "tgn:7006450",
          "tgn:1000001",
          "tgn:7012149",
          "tgn:2000089",
          "tgn:7029392"
        ],
        "placetype": [
          "aat:300008706"
        ],
        "id": 2175642,
        "name:xx": "Black Creek"
      }
    },
    {
      "geometry": {
        "type": "Point",
        "coordinates": [
          -164.2,
          65.5167
        ]
      },
      "type": "Feature",
      "properties": {
        "hierarchy": [
          "tgn:2175643",
          "tgn:7006450",
          "tgn:1000001",
          "tgn:7012149",
          "tgn:2000079",
          "tgn:7029392"
        ],
        "placetype": [
          "aat:300008706"
        ],
        "id": 2175643,
        "name:xx": "Black Creek"
      }
    },
    {
      "geometry": {
        "type": "Point",
        "coordinates": [
          -168.6167,
          53.0833
        ]
      },
      "type": "Feature",
      "properties": {
        "hierarchy": [
          "tgn:2175644",
          "tgn:7030516",
          "tgn:7006450",
          "tgn:1000001",
          "tgn:7012149",
          "tgn:7029392"
        ],
        "placetype": [
          "aat:300008706"
        ],
        "id": 2175644,
        "name:xx": "Black Creek"
      }
    },
    {
      "geometry": {
        "type": "Point",
        "coordinates": [
          -93.1667,
          33.5
        ]
      },
      "type": "Feature",
      "properties": {
        "hierarchy": [
          "tgn:2175645",
          "tgn:1000001",
          "tgn:7016172",
          "tgn:7012149",
          "tgn:2000154",
          "tgn:7029392"
        ],
        "placetype": [
          "aat:300008706"
        ],
        "id": 2175645,
        "name:xx": "Black Creek"
      }
    },
    {
      "geometry": {
        "type": "Point",
        "coordinates": [
          -91.65,
          35.2
        ]
      },
      "type": "Feature",
      "properties": {
        "hierarchy": [
          "tgn:2175646",
          "tgn:1000001",
          "tgn:7016172",
          "tgn:7012149",
          "tgn:2000177",
          "tgn:7029392"
        ],
        "placetype": [
          "aat:300008706"
        ],
        "id": 2175646,
        "name:xx": "Black Creek"
      }
    },
    {
      "geometry": {
        "type": "Point",
        "coordinates": [
          -120.5667,
          37.9667
        ]
      },
      "type": "Feature",
      "properties": {
        "hierarchy": [
          "tgn:2175647",
          "tgn:1000001",
          "tgn:1002219",
          "tgn:7012149",
          "tgn:7007157",
          "tgn:7029392"
        ],
        "placetype": [
          "aat:300008706"
        ],
        "id": 2175647,
        "name:xx": "Black Creek"
      }
    },
    {
      "geometry": {
        "type": "Point",
        "coordinates": [
          -123.5833,
          41.9167
        ]
      },
      "type": "Feature",
      "properties": {
        "hierarchy": [
          "tgn:2175648",
          "tgn:1000001",
          "tgn:7012149",
          "tgn:2000180",
          "tgn:7007157",
          "tgn:7029392"
        ],
        "placetype": [
          "aat:300008706"
        ],
        "id": 2175648,
        "name:xx": "Black Creek"
      }
    },
    {
      "geometry": {
        "type": "Point",
        "coordinates": [
          -122,
          37.1833
        ]
      },
      "type": "Feature",
      "properties": {
        "hierarchy": [
          "tgn:2175649",
          "tgn:1000001",
          "tgn:7012149",
          "tgn:7007157",
          "tgn:7014475",
          "tgn:7029392"
        ],
        "placetype": [
          "aat:300008706"
        ],
        "id": 2175649,
        "name:xx": "Black Creek"
      }
    }
  ]
}
