{
  "geometry": {
    "type": "Point",
    "coordinates": [
      -79.8667,
      36.0167
    ]
  },
  "type": "Feature",
  "properties": {
    "hierarchy": [
      "tgn:2651496",
      "tgn:1000001",
      "tgn:7012149",
      "tgn:2001500",
      "tgn:7007709",
      "tgn:7029392"
    ],
    "placetype": [
      "aat:300008347"
    ],
    "id": 2651496,
    "name:xx": "Sedge-Town"
  }
}
