{
  "geometry": {
    "type": "Point",
    "coordinates": [
      -121.7167,
      48.7167
    ]
  },
  "type": "Feature",
  "properties": {
    "hierarchy": [
      "tgn:2460531",
      "tgn:1000001",
      "tgn:7012149",
      "tgn:1003020",
      "tgn:7007920",
      "tgn:7029392"
    ],
    "placetype": [
      "aat:300008706"
    ],
    "id": 2460531,
    "name:xx": "Little Sandy Creek"
  }
}
