{
  "geometry": {
    "type": "Point",
    "coordinates": [
      -105.9167,
      38.6167
    ]
  },
  "type": "Feature",
  "properties": {
    "hierarchy": [
      "tgn:2647768",
      "tgn:1000001",
      "tgn:2000199",
      "tgn:7012149",
      "tgn:7007158",
      "tgn:7029392"
    ],
    "placetype": [
      "aat:300008697"
    ],
    "id": 2647768,
    "name:xx": "School Section Spring"
  }
}
