{
  "type": "FeatureCollection",
  "features": [
    {
      "geometry": {
        "type": "Point",
        "coordinates": [
          6.366667,
          53.266667
        ]
      },
      "type": "Feature",
      "properties": {
        "hierarchy": [
          "tgn:7270430",
          "tgn:1000003",
          "tgn:7003613",
          "tgn:7016845",
          "tgn:7029392"
        ],
        "placetype": [
          "aat:300008347"
        ],
        "name:nl": "Okswerd",
        "id": 7270430
      }
    },
    {
      "geometry": {
        "type": "Point",
        "coordinates": [
          6.316667,
          52.3
        ]
      },
      "type": "Feature",
      "properties": {
        "hierarchy": [
          "tgn:7270431",
          "tgn:1000003",
          "tgn:7003626",
          "tgn:7016845",
          "tgn:7029392"
        ],
        "placetype": [
          "aat:300008347"
        ],
        "name:nl": "Okkenbroek",
        "id": 7270431
      }
    },
    {
      "geometry": {
        "type": "Point",
        "coordinates": [
          5.216667,
          51.566667
        ]
      },
      "type": "Feature",
      "properties": {
        "hierarchy": [
          "tgn:7270432",
          "tgn:1000003",
          "tgn:7003624",
          "tgn:7016845",
          "tgn:7029392"
        ],
        "placetype": [
          "aat:300008680"
        ],
        "name:nl": "Oisterwijkse Vennen",
        "id": 7270432
      }
    },
    {
      "geometry": {
        "type": "Point",
        "coordinates": [
          5.166667,
          51.566667
        ]
      },
      "type": "Feature",
      "properties": {
        "hierarchy": [
          "tgn:7270433",
          "tgn:1000003",
          "tgn:7003624",
          "tgn:7016845",
          "tgn:7029392"
        ],
        "placetype": [
          "aat:300000206"
        ],
        "name:nl": "Oisterwijkse Hoeven",
        "id": 7270433
      }
    },
    {
      "geometry": {
        "type": "Point",
        "coordinates": [
          5.216667,
          51.566667
        ]
      },
      "type": "Feature",
      "properties": {
        "hierarchy": [
          "tgn:7270434",
          "tgn:1000003",
          "tgn:7003624",
          "tgn:7016845",
          "tgn:7029392"
        ],
        "placetype": [
          "aat:300386887"
        ],
        "name:nl": "Oisterwijkse Heide",
        "id": 7270434
      }
    },
    {
      "geometry": {
        "type": "Point",
        "coordinates": [
          5.35,
          51.483333
        ]
      },
      "type": "Feature",
      "properties": {
        "hierarchy": [
          "tgn:7270437",
          "tgn:1000003",
          "tgn:7003624",
          "tgn:7016845",
          "tgn:7029392"
        ],
        "placetype": [
          "aat:300386887"
        ],
        "name:nl": "Oirschotse Heide",
        "id": 7270437
      }
    }
  ]
}
