{
  "geometry": {
    "type": "Point",
    "coordinates": [
      -105.3333,
      40.3167
    ]
  },
  "type": "Feature",
  "properties": {
    "hierarchy": [
      "tgn:2403635",
      "tgn:1000001",
      "tgn:7012149",
      "tgn:2000226",
      "tgn:7007158",
      "tgn:7029392"
    ],
    "placetype": [
      "aat:300008761"
    ],
    "id": 2403635,
    "name:xx": "Howard Gulch"
  }
}
