{
  "geometry": {
    "type": "Point",
    "coordinates": [
      -72.35,
      41.35
    ]
  },
  "type": "Feature",
  "properties": {
    "hierarchy": [
      "tgn:2470245",
      "tgn:1000001",
      "tgn:1002714",
      "tgn:7012149",
      "tgn:7007159",
      "tgn:7029392"
    ],
    "placetype": [
      "aat:300008706"
    ],
    "id": 2470245,
    "name:xx": "Lord Creek"
  }
}
