{
  "geometry": {
    "type": "Point",
    "coordinates": [
      -70.8833,
      41.5667
    ]
  },
  "type": "Feature",
  "properties": {
    "hierarchy": [
      "tgn:2548400",
      "tgn:1002201",
      "tgn:1000001",
      "tgn:7012149",
      "tgn:7007517",
      "tgn:7029392"
    ],
    "placetype": [
      "aat:300011692"
    ],
    "id": 2548400,
    "name:xx": "North Ledge"
  }
}
