{
  "geometry": {
    "type": "Point",
    "coordinates": [
      -105.9833,
      41.9667
    ]
  },
  "type": "Feature",
  "properties": {
    "hierarchy": [
      "tgn:2298111",
      "tgn:2002365",
      "tgn:1000001",
      "tgn:7012149",
      "tgn:7007923",
      "tgn:7029392"
    ],
    "placetype": [
      "aat:300008680"
    ],
    "id": 2298111,
    "name:xx": "Dry Lake"
  }
}
