{
  "geometry": {
    "type": "Point",
    "coordinates": [
      -163.1833,
      61.45
    ]
  },
  "type": "Feature",
  "properties": {
    "hierarchy": [
      "tgn:2231379",
      "tgn:7006450",
      "tgn:1000001",
      "tgn:7012149",
      "tgn:2000087",
      "tgn:7029392"
    ],
    "placetype": [
      "aat:300008706"
    ],
    "id": 2231379,
    "name:xx": "Chakaktolik Creek"
  }
}
