{
  "geometry": {
    "type": "Point",
    "coordinates": [
      -78.4667,
      39.7833
    ]
  },
  "type": "Feature",
  "properties": {
    "hierarchy": [
      "tgn:2583580",
      "tgn:1002172",
      "tgn:1000001",
      "tgn:7012149",
      "tgn:7007710",
      "tgn:7029392"
    ],
    "placetype": [
      "aat:300055621"
    ],
    "id": 2583580,
    "name:xx": "Pine Ridge Natural Area"
  }
}
