{
  "geometry": {
    "type": "Point",
    "coordinates": [
      -70.9333,
      43.0333
    ]
  },
  "type": "Feature",
  "properties": {
    "hierarchy": [
      "tgn:2063640",
      "tgn:1000001",
      "tgn:7014352",
      "tgn:7012149",
      "tgn:7007564",
      "tgn:7029392"
    ],
    "placetype": [
      "aat:300008347"
    ],
    "id": 2063640,
    "name:xx": "Newfields"
  }
}
