{
  "geometry": {
    "type": "Point",
    "coordinates": [
      -74.5833,
      42.1333
    ]
  },
  "type": "Feature",
  "properties": {
    "hierarchy": [
      "tgn:2503624",
      "tgn:1000001",
      "tgn:1002328",
      "tgn:7012149",
      "tgn:7007568",
      "tgn:7029392"
    ],
    "placetype": [
      "aat:300008798"
    ],
    "id": 2503624,
    "name:xx": "Meade Hill"
  }
}
