{
  "geometry": {
    "type": "Point",
    "coordinates": [
      -72.2833,
      41.9333
    ]
  },
  "type": "Feature",
  "properties": {
    "hierarchy": [
      "tgn:2745131",
      "tgn:1000001",
      "tgn:1002949",
      "tgn:7012149",
      "tgn:7007159",
      "tgn:7029392"
    ],
    "placetype": [
      "aat:300008798"
    ],
    "id": 2745131,
    "name:xx": "Village Hill"
  }
}
