{
  "geometry": {
    "type": "Point",
    "coordinates": [
      31.85,
      29.266667
    ]
  },
  "type": "Feature",
  "properties": {
    "hierarchy": [
      "tgn:7534374",
      "tgn:7001242",
      "tgn:7016833",
      "tgn:1001083",
      "tgn:7029392"
    ],
    "placetype": [
      "aat:300008777"
    ],
    "name:en": "Ḥayîya, Farsh",
    "id": 7534374
  }
}
