{
  "geometry": {
    "type": "Point",
    "coordinates": [
      -89.8667,
      38.7167
    ]
  },
  "type": "Feature",
  "properties": {
    "hierarchy": [
      "tgn:2030439",
      "tgn:1000001",
      "tgn:7012149",
      "tgn:1002622",
      "tgn:7007251",
      "tgn:7029392"
    ],
    "placetype": [
      "aat:300008347"
    ],
    "id": 2030439,
    "name:xx": "Troy"
  }
}
