{
  "geometry": {
    "type": "Point",
    "coordinates": [
      -94.5333,
      33.9667
    ]
  },
  "type": "Feature",
  "properties": {
    "hierarchy": [
      "tgn:2334895",
      "tgn:1000001",
      "tgn:7012149",
      "tgn:2001667",
      "tgn:7007707",
      "tgn:7029392"
    ],
    "placetype": [
      "aat:300008680"
    ],
    "id": 2334895,
    "name:xx": "Forked Lake"
  }
}
