{
  "geometry": {
    "type": "Point",
    "coordinates": [
      -91.8667,
      42.1833
    ]
  },
  "type": "Feature",
  "properties": {
    "hierarchy": [
      "tgn:2409138",
      "tgn:2000566",
      "tgn:1000001",
      "tgn:7012149",
      "tgn:7007253",
      "tgn:7029392"
    ],
    "placetype": [
      "aat:300008680"
    ],
    "id": 2409138,
    "name:xx": "Ice House Lake"
  }
}
