{
  "type": "FeatureCollection",
  "features": [
    {
      "geometry": {
        "type": "Point",
        "coordinates": [
          -106.683333,
          27.883333
        ]
      },
      "type": "Feature",
      "properties": {
        "hierarchy": [
          "tgn:7359210",
          "tgn:7005581",
          "tgn:1000001",
          "tgn:7005560",
          "tgn:7029392"
        ],
        "placetype": [
          "aat:300008699"
        ],
        "id": 7359210,
        "name:xx": "Cieneguita, Arroyo"
      }
    },
    {
      "geometry": {
        "type": "Point",
        "coordinates": [
          -111.166667,
          30.533333
        ]
      },
      "type": "Feature",
      "properties": {
        "hierarchy": [
          "tgn:7359211",
          "tgn:1000001",
          "tgn:1001960",
          "tgn:7005560",
          "tgn:7029392"
        ],
        "placetype": [
          "aat:300008347"
        ],
        "id": 7359211,
        "name:xx": "Cieneguita"
      }
    },
    {
      "geometry": {
        "type": "Point",
        "coordinates": [
          -110.7,
          29.866667
        ]
      },
      "type": "Feature",
      "properties": {
        "hierarchy": [
          "tgn:7359212",
          "tgn:1000001",
          "tgn:1001960",
          "tgn:7005560",
          "tgn:7029392"
        ],
        "placetype": [
          "aat:300008347"
        ],
        "id": 7359212,
        "name:xx": "Cieneguita"
      }
    },
    {
      "geometry": {
        "type": "Point",
        "coordinates": [
          -110.083333,
          29.7
        ]
      },
      "type": "Feature",
      "properties": {
        "hierarchy": [
          "tgn:7359213",
          "tgn:1000001",
          "tgn:1001960",
          "tgn:7005560",
          "tgn:7029392"
        ],
        "placetype": [
          "aat:300008347"
        ],
        "id": 7359213,
        "name:xx": "Cieneguita"
      }
    },
    {
      "geometry": {
        "type": "Point",
        "coordinates": [
          -110.416667,
          29.4
        ]
      },
      "type": "Feature",
      "properties": {
        "hierarchy": [
          "tgn:7359214",
          "tgn:1000001",
          "tgn:1001960",
          "tgn:7005560",
          "tgn:7029392"
        ],
        "placetype": [
          "aat:300008347"
        ],
        "id": 7359214,
        "name:xx": "Cieneguita"
      }
    },
    {
      "geometry": {
        "type": "Point",
        "coordinates": [
          -108.9,
          28.766667
        ]
      },
      "type": "Feature",
      "properties": {
        "hierarchy": [
          "tgn:7359215",
          "tgn:1000001",
          "tgn:1001960",
          "tgn:7005560",
          "tgn:7029392"
        ],
        "placetype": [
          "aat:300008347"
        ],
        "id": 7359215,
        "name:xx": "Cieneguita"
      }
    },
    {
      "geometry": {
        "type": "Point",
        "coordinates": [
          -104.216667,
          28.733333
        ]
      },
      "type": "Feature",
      "properties": {
        "hierarchy": [
          "tgn:7359216",
          "tgn:7005581",
          "tgn:1000001",
          "tgn:7005560",
          "tgn:7029392"
        ],
        "placetype": [
          "aat:300008347"
        ],
        "id": 7359216,
        "name:xx": "Cieneguita"
      }
    },
    {
      "geometry": {
        "type": "Point",
        "coordinates": [
          -110.266667,
          28.6
        ]
      },
      "type": "Feature",
      "properties": {
        "hierarchy": [
          "tgn:7359217",
          "tgn:1000001",
          "tgn:1001960",
          "tgn:7005560",
          "tgn:7029392"
        ],
        "placetype": [
          "aat:300008347"
        ],
        "id": 7359217,
        "name:xx": "Cieneguita"
      }
    },
    {
      "geometry": {
        "type": "Point",
        "coordinates": [
          -111.083333,
          28.4
        ]
      },
      "type": "Feature",
      "properties": {
        "hierarchy": [
          "tgn:7359218",
          "tgn:1000001",
          "tgn:1001960",
          "tgn:7005560",
          "tgn:7029392"
        ],
        "placetype": [
          "aat:300008347"
        ],
        "id": 7359218,
        "name:xx": "Cieneguita"
      }
    },
    {
      "geometry": {
        "type": "Point",
        "coordinates": [
          -109.966667,
          28.183333
        ]
      },
      "type": "Feature",
      "properties": {
        "hierarchy": [
          "tgn:7359219",
          "tgn:1000001",
          "tgn:1001960",
          "tgn:7005560",
          "tgn:7029392"
        ],
        "placetype": [
          "aat:300008347"
        ],
        "id": 7359219,
        "name:xx": "Cieneguita"
      }
    }
  ]
}
