{
  "geometry": {
    "type": "Point",
    "coordinates": [
      -104.6833,
      35.7833
    ]
  },
  "type": "Feature",
  "properties": {
    "hierarchy": [
      "tgn:2585293",
      "tgn:1000001",
      "tgn:7012149",
      "tgn:2001446",
      "tgn:7007566",
      "tgn:7029392"
    ],
    "placetype": [
      "aat:300055621"
    ],
    "id": 2585293,
    "name:xx": "Pinos Altos"
  }
}
