{
  "geometry": {
    "type": "Point",
    "coordinates": [
      -97.4333,
      31.4833
    ]
  },
  "type": "Feature",
  "properties": {
    "hierarchy": [
      "tgn:2316002",
      "tgn:1000001",
      "tgn:7012149",
      "tgn:7021748",
      "tgn:7007826",
      "tgn:7029392"
    ],
    "placetype": [
      "aat:300008706"
    ],
    "id": 2316002,
    "name:xx": "Elm Creek"
  }
}
