{
  "geometry": {
    "type": "Point",
    "coordinates": [
      -2.45,
      37.35
    ]
  },
  "type": "Feature",
  "properties": {
    "hierarchy": [
      "tgn:7345877",
      "tgn:7002805",
      "tgn:7002758",
      "tgn:1000003",
      "tgn:1000095",
      "tgn:7029392"
    ],
    "placetype": [
      "aat:300008699"
    ],
    "id": 7345877,
    "name:xx": "Bacarés, Río de"
  }
}
