{
  "type": "FeatureCollection",
  "features": [
    {
      "geometry": {
        "type": "Point",
        "coordinates": [
          -76.45,
          39.1
        ]
      },
      "type": "Feature",
      "properties": {
        "hierarchy": [
          "tgn:2048000",
          "tgn:7014651",
          "tgn:1000001",
          "tgn:7012149",
          "tgn:7007516",
          "tgn:7029392"
        ],
        "placetype": [
          "aat:300008347",
          "aat:300387210"
        ],
        "id": 2048000,
        "name:xx": "Mount Carmel"
      }
    },
    {
      "geometry": {
        "type": "Point",
        "coordinates": [
          -76.6,
          38.6833
        ]
      },
      "type": "Feature",
      "properties": {
        "hierarchy": [
          "tgn:2048001",
          "tgn:1002224",
          "tgn:1000001",
          "tgn:7012149",
          "tgn:7007516",
          "tgn:7029392"
        ],
        "placetype": [
          "aat:300008347",
          "aat:300387210"
        ],
        "id": 2048001,
        "name:xx": "Mount Harmony"
      }
    },
    {
      "geometry": {
        "type": "Point",
        "coordinates": [
          -75.5167,
          38.35
        ]
      },
      "type": "Feature",
      "properties": {
        "hierarchy": [
          "tgn:2048003",
          "tgn:1000001",
          "tgn:1003023",
          "tgn:7012149",
          "tgn:7007516",
          "tgn:7029392"
        ],
        "placetype": [
          "aat:300008347"
        ],
        "id": 2048003,
        "name:xx": "Mount Hermon"
      }
    },
    {
      "geometry": {
        "type": "Point",
        "coordinates": [
          -77.6167,
          39.55
        ]
      },
      "type": "Feature",
      "properties": {
        "hierarchy": [
          "tgn:2048004",
          "tgn:1000001",
          "tgn:7016106",
          "tgn:7012149",
          "tgn:7007516",
          "tgn:7029392"
        ],
        "placetype": [
          "aat:300008347"
        ],
        "id": 2048004,
        "name:xx": "Mount Lena"
      }
    },
    {
      "geometry": {
        "type": "Point",
        "coordinates": [
          -75.3333,
          38.35
        ]
      },
      "type": "Feature",
      "properties": {
        "hierarchy": [
          "tgn:2048008",
          "tgn:1000001",
          "tgn:1003023",
          "tgn:7012149",
          "tgn:7007516",
          "tgn:7029392"
        ],
        "placetype": [
          "aat:300008347",
          "aat:300387210"
        ],
        "id": 2048008,
        "name:xx": "Mount Pleasant"
      }
    },
    {
      "geometry": {
        "type": "Point",
        "coordinates": [
          -77.3167,
          39.45
        ]
      },
      "type": "Feature",
      "properties": {
        "hierarchy": [
          "tgn:2048009",
          "tgn:1000001",
          "tgn:7016101",
          "tgn:7012149",
          "tgn:7007516",
          "tgn:7029392"
        ],
        "placetype": [
          "aat:300008347"
        ],
        "id": 2048009,
        "name:xx": "Mount Pleasant"
      }
    }
  ]
}
