{
  "geometry": {
    "type": "Point",
    "coordinates": [
      -95.5167,
      30.65
    ]
  },
  "type": "Feature",
  "properties": {
    "hierarchy": [
      "tgn:2314985",
      "tgn:1000001",
      "tgn:7012149",
      "tgn:1002980",
      "tgn:7007826",
      "tgn:7029392"
    ],
    "placetype": [
      "aat:300006191"
    ],
    "id": 2314985,
    "name:xx": "Elkins Lake"
  }
}
