{
  "geometry": {
    "type": "Point",
    "coordinates": [
      66.25,
      60.4333
    ]
  },
  "type": "Feature",
  "properties": {
    "hierarchy": [
      "tgn:1056425",
      "tgn:1000004",
      "tgn:7011606",
      "tgn:7018214",
      "tgn:7002435",
      "tgn:7029392"
    ],
    "placetype": [
      "aat:300008347"
    ],
    "id": 1056425,
    "name:xx": "Levdym"
  }
}
