{
  "geometry": {
    "type": "Point",
    "coordinates": [
      -91.65,
      31.1833
    ]
  },
  "type": "Feature",
  "properties": {
    "hierarchy": [
      "tgn:2454367",
      "tgn:1000001",
      "tgn:2000868",
      "tgn:7012149",
      "tgn:7007256",
      "tgn:7029392"
    ],
    "placetype": [
      "aat:300008699"
    ],
    "id": 2454367,
    "name:xx": "Little Cutoff"
  }
}
