{
  "geometry": {
    "type": "Point",
    "coordinates": [
      -87.6167,
      30.35
    ]
  },
  "type": "Feature",
  "properties": {
    "hierarchy": [
      "tgn:2531046",
      "tgn:2000001",
      "tgn:7002659",
      "tgn:1000001",
      "tgn:7012149",
      "tgn:7029392"
    ],
    "placetype": [
      "aat:300006191"
    ],
    "id": 2531046,
    "name:xx": "Muiel Lake"
  }
}
