{
  "type": "FeatureCollection",
  "features": [
    {
      "geometry": {
        "type": "Point",
        "coordinates": [
          -105.1,
          22.866667
        ]
      },
      "type": "Feature",
      "properties": {
        "hierarchy": [
          "tgn:7394010",
          "tgn:1000001",
          "tgn:1001906",
          "tgn:7005560",
          "tgn:7029392"
        ],
        "placetype": [
          "aat:300008347"
        ],
        "id": 7394010,
        "name:xx": "San Blas"
      }
    },
    {
      "geometry": {
        "type": "Point",
        "coordinates": [
          -98.7,
          22.5
        ]
      },
      "type": "Feature",
      "properties": {
        "hierarchy": [
          "tgn:7394011",
          "tgn:1000001",
          "tgn:7005597",
          "tgn:7005560",
          "tgn:7029392"
        ],
        "placetype": [
          "aat:300008347"
        ],
        "id": 7394011,
        "name:xx": "San Blas"
      }
    },
    {
      "geometry": {
        "type": "Point",
        "coordinates": [
          -105.083333,
          19.7
        ]
      },
      "type": "Feature",
      "properties": {
        "hierarchy": [
          "tgn:7394013",
          "tgn:7005586",
          "tgn:1000001",
          "tgn:7005560",
          "tgn:7029392"
        ],
        "placetype": [
          "aat:300008347"
        ],
        "id": 7394013,
        "name:xx": "San Blas"
      }
    },
    {
      "geometry": {
        "type": "Point",
        "coordinates": [
          -98.4,
          19.533333
        ]
      },
      "type": "Feature",
      "properties": {
        "hierarchy": [
          "tgn:7394014",
          "tgn:1000001",
          "tgn:7005598",
          "tgn:7005560",
          "tgn:7029392"
        ],
        "placetype": [
          "aat:300008347"
        ],
        "id": 7394014,
        "name:xx": "San Blas"
      }
    },
    {
      "geometry": {
        "type": "Point",
        "coordinates": [
          -96.8,
          17.383333
        ]
      },
      "type": "Feature",
      "properties": {
        "hierarchy": [
          "tgn:7394015",
          "tgn:1000001",
          "tgn:7005591",
          "tgn:7005560",
          "tgn:7029392"
        ],
        "placetype": [
          "aat:300008347"
        ],
        "id": 7394015,
        "name:xx": "San Blas"
      }
    },
    {
      "geometry": {
        "type": "Point",
        "coordinates": [
          -106.1,
          29.6
        ]
      },
      "type": "Feature",
      "properties": {
        "hierarchy": [
          "tgn:7394017",
          "tgn:7005581",
          "tgn:1000001",
          "tgn:7005560",
          "tgn:7029392"
        ],
        "placetype": [
          "aat:300008697"
        ],
        "id": 7394017,
        "name:xx": "San Bernardo, Ojo de"
      }
    },
    {
      "geometry": {
        "type": "Point",
        "coordinates": [
          -95.316667,
          18.166667
        ]
      },
      "type": "Feature",
      "properties": {
        "hierarchy": [
          "tgn:7394018",
          "tgn:1000001",
          "tgn:7005599",
          "tgn:7005560",
          "tgn:7029392"
        ],
        "placetype": [
          "aat:300008680"
        ],
        "id": 7394018,
        "name:xx": "San Bernardo, Laguna"
      }
    },
    {
      "geometry": {
        "type": "Point",
        "coordinates": [
          -100.383333,
          28.333333
        ]
      },
      "type": "Feature",
      "properties": {
        "hierarchy": [
          "tgn:7394019",
          "tgn:1001853",
          "tgn:1000001",
          "tgn:7005560",
          "tgn:7029392"
        ],
        "placetype": [
          "aat:300008347"
        ],
        "id": 7394019,
        "name:xx": "San Bernardo"
      }
    }
  ]
}
