{
  "geometry": {
    "type": "Point",
    "coordinates": [
      75.63503,
      28.052291
    ]
  },
  "type": "Feature",
  "properties": {
    "hierarchy": [
      "tgn:7583094",
      "tgn:1000004",
      "tgn:7000198",
      "tgn:7016788",
      "tgn:7029392"
    ],
    "placetype": [
      "aat:300008347"
    ],
    "name:en": "Sunārli ki Dhāni",
    "id": 7583094
  }
}
