{
  "geometry": {
    "type": "Point",
    "coordinates": [
      -111.8333,
      54.7167
    ]
  },
  "type": "Feature",
  "properties": {
    "hierarchy": [
      "tgn:1115565",
      "tgn:7005694",
      "tgn:7005685",
      "tgn:1000001",
      "tgn:7029392"
    ],
    "placetype": [
      "aat:300008680"
    ],
    "id": 1115565,
    "name:xx": "Beaver Lake"
  }
}
