{
  "geometry": {
    "type": "Point",
    "coordinates": [
      -116.7667,
      43.0833
    ]
  },
  "type": "Feature",
  "properties": {
    "hierarchy": [
      "tgn:2615833",
      "tgn:1000001",
      "tgn:7012149",
      "tgn:2000488",
      "tgn:7007250",
      "tgn:7029392"
    ],
    "placetype": [
      "aat:300008706"
    ],
    "id": 2615833,
    "name:xx": "Reynolds Creek"
  }
}
