{
  "geometry": {
    "type": "Point",
    "coordinates": [
      24.7333,
      49.05
    ]
  },
  "type": "Feature",
  "properties": {
    "hierarchy": [
      "tgn:1137120",
      "tgn:7011650",
      "tgn:1000003",
      "tgn:7006660",
      "tgn:7029392"
    ],
    "placetype": [
      "aat:300008347"
    ],
    "id": 1137120,
    "name:xx": "Zhovten"
  }
}
