{
  "geometry": {
    "type": "Point",
    "coordinates": [
      -88.9667,
      34.0333
    ]
  },
  "type": "Feature",
  "properties": {
    "hierarchy": [
      "tgn:2277052",
      "tgn:1000001",
      "tgn:2001094",
      "tgn:7012149",
      "tgn:7007522",
      "tgn:7029392"
    ],
    "placetype": [
      "aat:300008706"
    ],
    "id": 2277052,
    "name:xx": "Davis Creek"
  }
}
