{
  "geometry": {
    "type": "Point",
    "coordinates": [
      120.0833,
      31.8667
    ]
  },
  "type": "Feature",
  "properties": {
    "hierarchy": [
      "tgn:1073175",
      "tgn:1000004",
      "tgn:7002081",
      "tgn:1000111",
      "tgn:7029392"
    ],
    "placetype": [
      "aat:300008347"
    ],
    "id": 1073175,
    "name:xx": "Xishiqiao"
  }
}
