{
  "geometry": {
    "type": "Point",
    "coordinates": [
      -105.1833,
      35.35
    ]
  },
  "type": "Feature",
  "properties": {
    "hierarchy": [
      "tgn:2509855",
      "tgn:1000001",
      "tgn:7012149",
      "tgn:2001453",
      "tgn:7007566",
      "tgn:7029392"
    ],
    "placetype": [
      "aat:300008798"
    ],
    "id": 2509855,
    "name:xx": "Middle Mesa"
  }
}
