{
  "type": "FeatureCollection",
  "features": [
    {
      "geometry": {
        "type": "Point",
        "coordinates": [
          -82.7667,
          33.6333
        ]
      },
      "type": "Feature",
      "properties": {
        "hierarchy": [
          "tgn:2022871",
          "tgn:1000001",
          "tgn:7012149",
          "tgn:2000448",
          "tgn:7007248",
          "tgn:7029392"
        ],
        "placetype": [
          "aat:300008347",
          "aat:300387210"
        ],
        "id": 2022871,
        "name:xx": "Ficklin"
      }
    },
    {
      "geometry": {
        "type": "Point",
        "coordinates": [
          -83.9833,
          32.2667
        ]
      },
      "type": "Feature",
      "properties": {
        "hierarchy": [
          "tgn:2022874",
          "tgn:1000001",
          "tgn:7012149",
          "tgn:2000387",
          "tgn:7007248",
          "tgn:7029392"
        ],
        "placetype": [
          "aat:300387016"
        ],
        "id": 2022874,
        "name:xx": "Fields"
      }
    },
    {
      "geometry": {
        "type": "Point",
        "coordinates": [
          -84.5333,
          33.5333
        ]
      },
      "type": "Feature",
      "properties": {
        "hierarchy": [
          "tgn:2022875",
          "tgn:1000001",
          "tgn:7012149",
          "tgn:2000351",
          "tgn:7007248",
          "tgn:7029392"
        ],
        "placetype": [
          "aat:300008347",
          "aat:300387210"
        ],
        "id": 2022875,
        "name:xx": "Fife"
      }
    },
    {
      "geometry": {
        "type": "Point",
        "coordinates": [
          -83.95,
          33.4
        ]
      },
      "type": "Feature",
      "properties": {
        "hierarchy": [
          "tgn:2022876",
          "tgn:1000001",
          "tgn:2000309",
          "tgn:7012149",
          "tgn:7007248",
          "tgn:7029392"
        ],
        "placetype": [
          "aat:300008347",
          "aat:300387210"
        ],
        "id": 2022876,
        "name:xx": "Fincherville"
      }
    },
    {
      "geometry": {
        "type": "Point",
        "coordinates": [
          -83.7667,
          32.15
        ]
      },
      "type": "Feature",
      "properties": {
        "hierarchy": [
          "tgn:2022877",
          "tgn:1000001",
          "tgn:7012149",
          "tgn:2000337",
          "tgn:7007248",
          "tgn:7029392"
        ],
        "placetype": [
          "aat:300008347"
        ],
        "id": 2022877,
        "name:xx": "Findlay"
      }
    },
    {
      "geometry": {
        "type": "Point",
        "coordinates": [
          -83.5,
          32.1167
        ]
      },
      "type": "Feature",
      "properties": {
        "hierarchy": [
          "tgn:2022878",
          "tgn:1000001",
          "tgn:7012149",
          "tgn:2000407",
          "tgn:7007248",
          "tgn:7029392"
        ],
        "placetype": [
          "aat:300008347"
        ],
        "id": 2022878,
        "name:xx": "Finleyson"
      }
    }
  ]
}
