{
  "type": "FeatureCollection",
  "features": [
    {
      "geometry": {
        "type": "Point",
        "coordinates": [
          5.633333,
          50.166667
        ]
      },
      "type": "Feature",
      "properties": {
        "hierarchy": [
          "tgn:7243290",
          "tgn:7003465",
          "tgn:1000003",
          "tgn:1000063",
          "tgn:4012014",
          "tgn:7029392"
        ],
        "placetype": [
          "aat:300008699"
        ],
        "id": 7243290,
        "name:xx": "Maboge"
      }
    },
    {
      "geometry": {
        "type": "Point",
        "coordinates": [
          5.633333,
          50.166667
        ]
      },
      "type": "Feature",
      "properties": {
        "hierarchy": [
          "tgn:7243291",
          "tgn:7003465",
          "tgn:1000003",
          "tgn:1000063",
          "tgn:4012014",
          "tgn:7029392"
        ],
        "placetype": [
          "aat:300008347"
        ],
        "id": 7243291,
        "name:xx": "Maboge"
      }
    },
    {
      "geometry": {
        "type": "Point",
        "coordinates": [
          5.483333,
          51.066667
        ]
      },
      "type": "Feature",
      "properties": {
        "hierarchy": [
          "tgn:7243292",
          "tgn:7003461",
          "tgn:1000003",
          "tgn:1000063",
          "tgn:7018236",
          "tgn:7029392"
        ],
        "placetype": [
          "aat:300008347"
        ],
        "id": 7243292,
        "name:xx": "Maastrichterheide"
      }
    },
    {
      "geometry": {
        "type": "Point",
        "coordinates": [
          4.583333,
          51.133333
        ]
      },
      "type": "Feature",
      "properties": {
        "hierarchy": [
          "tgn:7243294",
          "tgn:7003456",
          "tgn:1000003",
          "tgn:1000063",
          "tgn:7018236",
          "tgn:7029392"
        ],
        "placetype": [
          "aat:300008699"
        ],
        "id": 7243294,
        "name:xx": "Maasfortbeek"
      }
    },
    {
      "geometry": {
        "type": "Point",
        "coordinates": [
          4.249078,
          50.710855
        ]
      },
      "type": "Feature",
      "properties": {
        "hierarchy": [
          "tgn:7243298",
          "tgn:7018239",
          "tgn:1000003",
          "tgn:1000063",
          "tgn:7018236",
          "tgn:7029392"
        ],
        "placetype": [
          "aat:300008347"
        ],
        "id": 7243298,
        "name:xx": "Maasdal"
      }
    },
    {
      "geometry": {
        "type": "Point",
        "coordinates": [
          4.9,
          49.833333
        ]
      },
      "type": "Feature",
      "properties": {
        "hierarchy": [
          "tgn:7243299",
          "tgn:7003465",
          "tgn:1000003",
          "tgn:1000063",
          "tgn:4012014",
          "tgn:7029392"
        ],
        "placetype": [
          "aat:300008347"
        ],
        "id": 7243299,
        "name:xx": "Les Quatre Bornes"
      }
    }
  ]
}
