{
  "geometry": {
    "type": "Point",
    "coordinates": [
      113.558,
      22.193
    ]
  },
  "type": "Feature",
  "properties": {
    "hierarchy": [
      "tgn:7031920",
      "tgn:1000004",
      "tgn:7005019",
      "tgn:7029392"
    ],
    "placetype": [
      "aat:300008678"
    ],
    "id": 7031920,
    "name:xx": "Exterior, Porto"
  }
}
