{
  "type": "FeatureCollection",
  "features": [
    {
      "geometry": {
        "type": "Point",
        "coordinates": [
          -71.833333,
          -54.583333
        ]
      },
      "type": "Feature",
      "properties": {
        "hierarchy": [
          "tgn:7321740",
          "tgn:1001702",
          "tgn:1000049",
          "tgn:1000002",
          "tgn:7029392"
        ],
        "placetype": [
          "aat:300008804"
        ],
        "id": 7321740,
        "name:xx": "Brecknock, Península"
      }
    },
    {
      "geometry": {
        "type": "Point",
        "coordinates": [
          -71.916667,
          -54.666667
        ]
      },
      "type": "Feature",
      "properties": {
        "hierarchy": [
          "tgn:7321741",
          "tgn:1001702",
          "tgn:1000049",
          "tgn:1000002",
          "tgn:7029392"
        ],
        "placetype": [
          "aat:300387026"
        ],
        "id": 7321741,
        "name:xx": "Brecknock, Canal"
      }
    },
    {
      "geometry": {
        "type": "Point",
        "coordinates": [
          -71.55,
          -54.666667
        ]
      },
      "type": "Feature",
      "properties": {
        "hierarchy": [
          "tgn:7321742",
          "tgn:1001702",
          "tgn:1000049",
          "tgn:1000002",
          "tgn:7029392"
        ],
        "placetype": [
          "aat:300008791"
        ],
        "id": 7321742,
        "name:xx": "Brecknock, Isla"
      }
    },
    {
      "geometry": {
        "type": "Point",
        "coordinates": [
          -70.7,
          -29.483333
        ]
      },
      "type": "Feature",
      "properties": {
        "hierarchy": [
          "tgn:7321743",
          "tgn:1001657",
          "tgn:1000049",
          "tgn:1000002",
          "tgn:7029392"
        ],
        "placetype": [
          "aat:300266554",
          "aat:300008699"
        ],
        "id": 7321743,
        "name:xx": "Breas de La Junta, Quebrada"
      }
    },
    {
      "geometry": {
        "type": "Point",
        "coordinates": [
          -69.866667,
          -27.416667
        ]
      },
      "type": "Feature",
      "properties": {
        "hierarchy": [
          "tgn:7321744",
          "tgn:1001630",
          "tgn:1000049",
          "tgn:1000002",
          "tgn:7029392"
        ],
        "placetype": [
          "aat:300266554",
          "aat:300008699"
        ],
        "id": 7321744,
        "name:xx": "Breas, Quebrada de"
      }
    },
    {
      "geometry": {
        "type": "Point",
        "coordinates": [
          -70.916667,
          -28.883333
        ]
      },
      "type": "Feature",
      "properties": {
        "hierarchy": [
          "tgn:7321745",
          "tgn:1001630",
          "tgn:1000049",
          "tgn:1000002",
          "tgn:7029392"
        ],
        "placetype": [
          "aat:300266554",
          "aat:300008699"
        ],
        "id": 7321745,
        "name:xx": "Breas, Quebrada"
      }
    },
    {
      "geometry": {
        "type": "Point",
        "coordinates": [
          -70.4,
          -25.5
        ]
      },
      "type": "Feature",
      "properties": {
        "hierarchy": [
          "tgn:7321747",
          "tgn:7016598",
          "tgn:1000049",
          "tgn:1000002",
          "tgn:7029392"
        ],
        "placetype": [
          "aat:300007783"
        ],
        "id": 7321747,
        "name:xx": "Estación Breas"
      }
    },
    {
      "geometry": {
        "type": "Point",
        "coordinates": [
          -70.45,
          -25.433333
        ]
      },
      "type": "Feature",
      "properties": {
        "hierarchy": [
          "tgn:7321748",
          "tgn:7016598",
          "tgn:1000049",
          "tgn:1000002",
          "tgn:7029392"
        ],
        "placetype": [
          "aat:300008777"
        ],
        "id": 7321748,
        "name:xx": "Breas, Cerro"
      }
    },
    {
      "geometry": {
        "type": "Point",
        "coordinates": [
          -69.183333,
          -24.966667
        ]
      },
      "type": "Feature",
      "properties": {
        "hierarchy": [
          "tgn:7321749",
          "tgn:7016598",
          "tgn:1000049",
          "tgn:1000002",
          "tgn:7029392"
        ],
        "placetype": [
          "aat:300008697"
        ],
        "id": 7321749,
        "name:xx": "Breas, Aguada de"
      }
    }
  ]
}
