{
  "geometry": {
    "type": "Point",
    "coordinates": [
      -79.5667,
      33.4667
    ]
  },
  "type": "Feature",
  "properties": {
    "hierarchy": [
      "tgn:2400772",
      "tgn:1000001",
      "tgn:7012149",
      "tgn:7007712",
      "tgn:7029392"
    ],
    "placetype": [
      "aat:300008699"
    ],
    "id": 2400772,
    "name:xx": "Horse Pen Swamp"
  }
}
