{
  "geometry": {
    "type": "Point",
    "coordinates": [
      -73.8833,
      44.3833
    ]
  },
  "type": "Feature",
  "properties": {
    "hierarchy": [
      "tgn:2319311",
      "tgn:1000001",
      "tgn:7012149",
      "tgn:2001461",
      "tgn:7007568",
      "tgn:7029392"
    ],
    "placetype": [
      "aat:300008798"
    ],
    "id": 2319311,
    "name:xx": "Esther Mountain"
  }
}
