{
  "geometry": {
    "type": "Point",
    "coordinates": [
      -72.766,
      18.426
    ]
  },
  "type": "Feature",
  "properties": {
    "hierarchy": [
      "tgn:7593648",
      "tgn:7005518",
      "tgn:1000001",
      "tgn:7005502",
      "tgn:7029392"
    ],
    "placetype": [
      "aat:300008347"
    ],
    "id": 7593648,
    "name:xx": "Grand Goâve"
  }
}
