{
  "geometry": {
    "type": "Point",
    "coordinates": [
      -122.1667,
      41.25
    ]
  },
  "type": "Feature",
  "properties": {
    "hierarchy": [
      "tgn:2398342",
      "tgn:1000001",
      "tgn:7012149",
      "tgn:7007157",
      "tgn:2000189",
      "tgn:7029392"
    ],
    "placetype": [
      "aat:300008697"
    ],
    "id": 2398342,
    "name:xx": "Hooper Spring"
  }
}
