{
  "geometry": {
    "type": "Point",
    "coordinates": [
      -84.3833,
      43.0833
    ]
  },
  "type": "Feature",
  "properties": {
    "hierarchy": [
      "tgn:2051840",
      "tgn:1000001",
      "tgn:1002283",
      "tgn:7012149",
      "tgn:7007520",
      "tgn:7029392"
    ],
    "placetype": [
      "aat:300008347"
    ],
    "id": 2051840,
    "name:xx": "Elsie"
  }
}
