{
  "geometry": {
    "type": "Point",
    "coordinates": [
      -70.8333,
      42.8667
    ]
  },
  "type": "Feature",
  "properties": {
    "hierarchy": [
      "tgn:2512783",
      "tgn:1000001",
      "tgn:7014352",
      "tgn:7012149",
      "tgn:7007564",
      "tgn:7029392"
    ],
    "placetype": [
      "aat:300008706"
    ],
    "id": 2512783,
    "name:xx": "Mill Creek"
  }
}
