{
  "type": "FeatureCollection",
  "features": [
    {
      "geometry": {
        "type": "Point",
        "coordinates": [
          -89.3333,
          30.9833
        ]
      },
      "type": "Feature",
      "properties": {
        "hierarchy": [
          "tgn:2296830",
          "tgn:1000001",
          "tgn:7012149",
          "tgn:7007522",
          "tgn:7029392"
        ],
        "placetype": [
          "aat:300008706"
        ],
        "id": 2296830,
        "name:xx": "Dry Creek"
      }
    },
    {
      "geometry": {
        "type": "Point",
        "coordinates": [
          -91.3667,
          31.1333
        ]
      },
      "type": "Feature",
      "properties": {
        "hierarchy": [
          "tgn:2296831",
          "tgn:1000001",
          "tgn:7012149",
          "tgn:2001164",
          "tgn:7007522",
          "tgn:7029392"
        ],
        "placetype": [
          "aat:300008706"
        ],
        "id": 2296831,
        "name:xx": "Dry Creek"
      }
    },
    {
      "geometry": {
        "type": "Point",
        "coordinates": [
          -89.7833,
          31.2833
        ]
      },
      "type": "Feature",
      "properties": {
        "hierarchy": [
          "tgn:2296832",
          "tgn:1000001",
          "tgn:7012149",
          "tgn:2001131",
          "tgn:7007522",
          "tgn:7029392"
        ],
        "placetype": [
          "aat:300008706"
        ],
        "id": 2296832,
        "name:xx": "Dry Creek"
      }
    },
    {
      "geometry": {
        "type": "Point",
        "coordinates": [
          -88.65,
          31.6
        ]
      },
      "type": "Feature",
      "properties": {
        "hierarchy": [
          "tgn:2296833",
          "tgn:1000001",
          "tgn:7012149",
          "tgn:2001162",
          "tgn:7007522",
          "tgn:7029392"
        ],
        "placetype": [
          "aat:300008706"
        ],
        "id": 2296833,
        "name:xx": "Dry Creek"
      }
    },
    {
      "geometry": {
        "type": "Point",
        "coordinates": [
          -90.2333,
          31.8833
        ]
      },
      "type": "Feature",
      "properties": {
        "hierarchy": [
          "tgn:2296834",
          "tgn:1000001",
          "tgn:2001100",
          "tgn:7012149",
          "tgn:7007522",
          "tgn:7029392"
        ],
        "placetype": [
          "aat:300008706"
        ],
        "id": 2296834,
        "name:xx": "Dry Creek"
      }
    },
    {
      "geometry": {
        "type": "Point",
        "coordinates": [
          -89.6667,
          31.9833
        ]
      },
      "type": "Feature",
      "properties": {
        "hierarchy": [
          "tgn:2296835",
          "tgn:1000001",
          "tgn:7012149",
          "tgn:2001149",
          "tgn:7007522",
          "tgn:7029392"
        ],
        "placetype": [
          "aat:300008706"
        ],
        "id": 2296835,
        "name:xx": "Dry Creek"
      }
    },
    {
      "geometry": {
        "type": "Point",
        "coordinates": [
          -89.7333,
          33.3667
        ]
      },
      "type": "Feature",
      "properties": {
        "hierarchy": [
          "tgn:2296836",
          "tgn:1000001",
          "tgn:2001093",
          "tgn:7012149",
          "tgn:7007522",
          "tgn:7029392"
        ],
        "placetype": [
          "aat:300008706"
        ],
        "id": 2296836,
        "name:xx": "Dry Creek"
      }
    },
    {
      "geometry": {
        "type": "Point",
        "coordinates": [
          -89.35,
          33.3
        ]
      },
      "type": "Feature",
      "properties": {
        "hierarchy": [
          "tgn:2296837",
          "tgn:1000001",
          "tgn:2001095",
          "tgn:7012149",
          "tgn:7007522",
          "tgn:7029392"
        ],
        "placetype": [
          "aat:300008706"
        ],
        "id": 2296837,
        "name:xx": "Dry Creek"
      }
    },
    {
      "geometry": {
        "type": "Point",
        "coordinates": [
          -89.2167,
          33.9333
        ]
      },
      "type": "Feature",
      "properties": {
        "hierarchy": [
          "tgn:2296838",
          "tgn:1000001",
          "tgn:2001092",
          "tgn:7012149",
          "tgn:7007522",
          "tgn:7029392"
        ],
        "placetype": [
          "aat:300008706"
        ],
        "id": 2296838,
        "name:xx": "Dry Creek"
      }
    },
    {
      "geometry": {
        "type": "Point",
        "coordinates": [
          -88.1667,
          34.5
        ]
      },
      "type": "Feature",
      "properties": {
        "hierarchy": [
          "tgn:2296839",
          "tgn:1000001",
          "tgn:7012149",
          "tgn:2001156",
          "tgn:7007522",
          "tgn:7029392"
        ],
        "placetype": [
          "aat:300008706"
        ],
        "id": 2296839,
        "name:xx": "Dry Creek"
      }
    }
  ]
}
