{
  "geometry": {
    "type": "Point",
    "coordinates": [
      -118.9667,
      34.4333
    ]
  },
  "type": "Feature",
  "properties": {
    "hierarchy": [
      "tgn:2673690",
      "tgn:1000001",
      "tgn:7012149",
      "tgn:7007157",
      "tgn:1002972",
      "tgn:7029392"
    ],
    "placetype": [
      "aat:300008761"
    ],
    "id": 2673690,
    "name:xx": "Snow Canyon"
  }
}
