{
  "geometry": {
    "type": "Point",
    "coordinates": [
      -100.6833,
      44.6833
    ]
  },
  "type": "Feature",
  "properties": {
    "hierarchy": [
      "tgn:2414311",
      "tgn:1000001",
      "tgn:7012149",
      "tgn:2001828",
      "tgn:7007713",
      "tgn:7029392"
    ],
    "placetype": [
      "aat:300386831"
    ],
    "id": 2414311,
    "name:xx": "Iron Post Buttes"
  }
}
