{
  "type": "FeatureCollection",
  "features": [
    {
      "geometry": {
        "type": "Point",
        "coordinates": [
          -78.6167,
          38.6
        ]
      },
      "type": "Feature",
      "properties": {
        "hierarchy": [
          "tgn:2586470",
          "tgn:1000001",
          "tgn:7012149",
          "tgn:2002178",
          "tgn:7007919",
          "tgn:7029392"
        ],
        "placetype": [
          "aat:300008699"
        ],
        "id": 2586470,
        "name:xx": "Pitt Spring Run"
      }
    },
    {
      "geometry": {
        "type": "Point",
        "coordinates": [
          -112.3,
          35.55
        ]
      },
      "type": "Feature",
      "properties": {
        "hierarchy": [
          "tgn:2586471",
          "tgn:1000001",
          "tgn:7006451",
          "tgn:2000092",
          "tgn:7012149",
          "tgn:7029392"
        ],
        "placetype": [
          "aat:300006191"
        ],
        "id": 2586471,
        "name:xx": "Pitt Tank"
      }
    },
    {
      "geometry": {
        "type": "Point",
        "coordinates": [
          -118.3,
          40.6
        ]
      },
      "type": "Feature",
      "properties": {
        "hierarchy": [
          "tgn:2586472",
          "tgn:1000001",
          "tgn:2001419",
          "tgn:7012149",
          "tgn:7007526",
          "tgn:7029392"
        ],
        "placetype": [
          "aat:300132316"
        ],
        "id": 2586472,
        "name:xx": "Pitt-Taylor Cove"
      }
    },
    {
      "geometry": {
        "type": "Point",
        "coordinates": [
          -118.1667,
          40.6667
        ]
      },
      "type": "Feature",
      "properties": {
        "hierarchy": [
          "tgn:2586473",
          "tgn:1000001",
          "tgn:2001419",
          "tgn:7012149",
          "tgn:7007526",
          "tgn:7029392"
        ],
        "placetype": [
          "aat:300006075"
        ],
        "id": 2586473,
        "name:xx": "Pitt-Taylor Diversion Canal"
      }
    },
    {
      "geometry": {
        "type": "Point",
        "coordinates": [
          -155.3667,
          70.8167
        ]
      },
      "type": "Feature",
      "properties": {
        "hierarchy": [
          "tgn:2586474",
          "tgn:7006450",
          "tgn:1000001",
          "tgn:7012149",
          "tgn:2124005",
          "tgn:7029392"
        ],
        "placetype": [
          "aat:300008680"
        ],
        "id": 2586474,
        "name:xx": "Pittalukruak Lake"
      }
    },
    {
      "geometry": {
        "type": "Point",
        "coordinates": [
          -87.1,
          35.1667
        ]
      },
      "type": "Feature",
      "properties": {
        "hierarchy": [
          "tgn:2586475",
          "tgn:1000001",
          "tgn:7012149",
          "tgn:2001864",
          "tgn:7007825",
          "tgn:7029392"
        ],
        "placetype": [
          "aat:300008746"
        ],
        "id": 2586475,
        "name:xx": "Pittard Cave"
      }
    },
    {
      "geometry": {
        "type": "Point",
        "coordinates": [
          -123.5333,
          43.9667
        ]
      },
      "type": "Feature",
      "properties": {
        "hierarchy": [
          "tgn:2586476",
          "tgn:1000001",
          "tgn:7012149",
          "tgn:2001716",
          "tgn:7007708",
          "tgn:7029392"
        ],
        "placetype": [
          "aat:300008706"
        ],
        "id": 2586476,
        "name:xx": "Pittenger Creek"
      }
    },
    {
      "geometry": {
        "type": "Point",
        "coordinates": [
          -90.9833,
          35.4333
        ]
      },
      "type": "Feature",
      "properties": {
        "hierarchy": [
          "tgn:2586478",
          "tgn:1000001",
          "tgn:7016172",
          "tgn:2000123",
          "tgn:7012149",
          "tgn:7029392"
        ],
        "placetype": [
          "aat:300008347"
        ],
        "id": 2586478,
        "name:xx": "Pittinger"
      }
    },
    {
      "geometry": {
        "type": "Point",
        "coordinates": [
          -90.7,
          36.4833
        ]
      },
      "type": "Feature",
      "properties": {
        "hierarchy": [
          "tgn:2586479",
          "tgn:1000001",
          "tgn:7016172",
          "tgn:2000115",
          "tgn:7012149",
          "tgn:7029392"
        ],
        "placetype": [
          "aat:300008347"
        ],
        "id": 2586479,
        "name:xx": "Pittman"
      }
    }
  ]
}
