{
  "geometry": {
    "type": "Point",
    "coordinates": [
      79.9526,
      27.0313
    ]
  },
  "type": "Feature",
  "properties": {
    "hierarchy": [
      "tgn:7563274",
      "tgn:1000004",
      "tgn:7000198",
      "tgn:7016722",
      "tgn:7029392"
    ],
    "placetype": [
      "aat:300008347"
    ],
    "name:en": "Salempur Tāra",
    "id": 7563274
  }
}
