{
  "geometry": {
    "type": "Point",
    "coordinates": [
      22.5667,
      56.2167
    ]
  },
  "type": "Feature",
  "properties": {
    "hierarchy": [
      "tgn:1131493",
      "tgn:1000003",
      "tgn:7006542",
      "tgn:7029392"
    ],
    "placetype": [
      "aat:300008707"
    ],
    "id": 1131493,
    "name:xx": "Virvyčia"
  }
}
