{
  "geometry": {
    "type": "Point",
    "coordinates": [
      -83.25,
      38.1167
    ]
  },
  "type": "Feature",
  "properties": {
    "hierarchy": [
      "tgn:2197528",
      "tgn:1000001",
      "tgn:7012149",
      "tgn:7007255",
      "tgn:7029392"
    ],
    "placetype": [
      "aat:300008699"
    ],
    "id": 2197528,
    "name:xx": "Brown Fork"
  }
}
