{
  "geometry": {
    "type": "Point",
    "coordinates": [
      -82.65,
      42.6667
    ]
  },
  "type": "Feature",
  "properties": {
    "hierarchy": [
      "tgn:2051871",
      "tgn:1000001",
      "tgn:7012149",
      "tgn:7016056",
      "tgn:7007520",
      "tgn:7029392"
    ],
    "placetype": [
      "aat:300008347"
    ],
    "id": 2051871,
    "name:xx": "Fair Haven"
  }
}
