{
  "geometry": {
    "type": "Point",
    "coordinates": [
      -83.8833,
      42.9667
    ]
  },
  "type": "Feature",
  "properties": {
    "hierarchy": [
      "tgn:2518352",
      "tgn:1000001",
      "tgn:7012149",
      "tgn:7007520",
      "tgn:7029392"
    ],
    "placetype": [
      "aat:300008706"
    ],
    "id": 2518352,
    "name:xx": "Misteguay Creek"
  }
}
