{
  "geometry": {
    "type": "Point",
    "coordinates": [
      79.360013,
      27.16191
    ]
  },
  "type": "Feature",
  "properties": {
    "hierarchy": [
      "tgn:7561504",
      "tgn:1000004",
      "tgn:7000198",
      "tgn:7016722",
      "tgn:7029392"
    ],
    "placetype": [
      "aat:300008347"
    ],
    "name:en": "Manīrāmpur",
    "id": 7561504
  }
}
