{
  "geometry": {
    "type": "Point",
    "coordinates": [
      -98.5833,
      30.1667
    ]
  },
  "type": "Feature",
  "properties": {
    "hierarchy": [
      "tgn:2772680",
      "tgn:1000001",
      "tgn:7012149",
      "tgn:7007826",
      "tgn:7029392"
    ],
    "placetype": [
      "aat:300008706"
    ],
    "id": 2772680,
    "name:xx": "Williams Creek"
  }
}
