{
  "type": "FeatureCollection",
  "features": [
    {
      "geometry": {
        "type": "Point",
        "coordinates": [
          -70.033333,
          -20.883333
        ]
      },
      "type": "Feature",
      "properties": {
        "hierarchy": [
          "tgn:7287100",
          "tgn:7002464",
          "tgn:1000049",
          "tgn:1000002",
          "tgn:7029392"
        ],
        "placetype": [
          "aat:300386871"
        ],
        "id": 7287100,
        "name:xx": "Grande, Salar"
      }
    },
    {
      "geometry": {
        "type": "Point",
        "coordinates": [
          -70.1,
          -53.966667
        ]
      },
      "type": "Feature",
      "properties": {
        "hierarchy": [
          "tgn:7287102",
          "tgn:1001702",
          "tgn:1000049",
          "tgn:1000002",
          "tgn:7029392"
        ],
        "placetype": [
          "aat:300008699"
        ],
        "id": 7287102,
        "name:xx": "Grande, Río"
      }
    },
    {
      "geometry": {
        "type": "Point",
        "coordinates": [
          -71.333333,
          -53.083333
        ]
      },
      "type": "Feature",
      "properties": {
        "hierarchy": [
          "tgn:7287103",
          "tgn:1001702",
          "tgn:1000049",
          "tgn:1000002",
          "tgn:7029392"
        ],
        "placetype": [
          "aat:300008699"
        ],
        "id": 7287103,
        "name:xx": "Grande, Río"
      }
    },
    {
      "geometry": {
        "type": "Point",
        "coordinates": [
          -71.883333,
          -53
        ]
      },
      "type": "Feature",
      "properties": {
        "hierarchy": [
          "tgn:7287104",
          "tgn:1001702",
          "tgn:1000049",
          "tgn:1000002",
          "tgn:7029392"
        ],
        "placetype": [
          "aat:300008699"
        ],
        "id": 7287104,
        "name:xx": "Grande, Río"
      }
    },
    {
      "geometry": {
        "type": "Point",
        "coordinates": [
          -71.916667,
          -46.766667
        ]
      },
      "type": "Feature",
      "properties": {
        "hierarchy": [
          "tgn:7287105",
          "tgn:1001623",
          "tgn:1000049",
          "tgn:1000002",
          "tgn:7029392"
        ],
        "placetype": [
          "aat:300008699"
        ],
        "id": 7287105,
        "name:xx": "Grande, Río"
      }
    },
    {
      "geometry": {
        "type": "Point",
        "coordinates": [
          -72.3,
          -44.666667
        ]
      },
      "type": "Feature",
      "properties": {
        "hierarchy": [
          "tgn:7287106",
          "tgn:1001623",
          "tgn:1000049",
          "tgn:1000002",
          "tgn:7029392"
        ],
        "placetype": [
          "aat:300008699"
        ],
        "id": 7287106,
        "name:xx": "Grande, Río"
      }
    },
    {
      "geometry": {
        "type": "Point",
        "coordinates": [
          -73.978611,
          -42.040278
        ]
      },
      "type": "Feature",
      "properties": {
        "hierarchy": [
          "tgn:7287107",
          "tgn:1001699",
          "tgn:1000049",
          "tgn:1000002",
          "tgn:7029392"
        ],
        "placetype": [
          "aat:300008699"
        ],
        "id": 7287107,
        "name:xx": "Río Grande"
      }
    },
    {
      "geometry": {
        "type": "Point",
        "coordinates": [
          -72.066667,
          -39.3
        ]
      },
      "type": "Feature",
      "properties": {
        "hierarchy": [
          "tgn:7287108",
          "tgn:1001692",
          "tgn:1000049",
          "tgn:1000002",
          "tgn:7029392"
        ],
        "placetype": [
          "aat:300008699"
        ],
        "id": 7287108,
        "name:xx": "Grande, Río"
      }
    },
    {
      "geometry": {
        "type": "Point",
        "coordinates": [
          -73.466667,
          -38.283333
        ]
      },
      "type": "Feature",
      "properties": {
        "hierarchy": [
          "tgn:7287109",
          "tgn:1001637",
          "tgn:1000049",
          "tgn:1000002",
          "tgn:7029392"
        ],
        "placetype": [
          "aat:300008699"
        ],
        "id": 7287109,
        "name:xx": "Grande, Río"
      }
    }
  ]
}
