{
  "geometry": {
    "type": "Point",
    "coordinates": [
      -70.7333,
      41.4833
    ]
  },
  "type": "Feature",
  "properties": {
    "hierarchy": [
      "tgn:2265519",
      "tgn:1008304",
      "tgn:1009982",
      "tgn:1000001",
      "tgn:1002344",
      "tgn:7012149",
      "tgn:7007517",
      "tgn:7029392"
    ],
    "placetype": [
      "aat:300008680"
    ],
    "id": 2265519,
    "name:xx": "Crane Pond"
  }
}
