{
  "geometry": {
    "type": "Point",
    "coordinates": [
      84.466667,
      18.75
    ]
  },
  "type": "Feature",
  "properties": {
    "hierarchy": [
      "tgn:7546378",
      "tgn:1001828",
      "tgn:1000004",
      "tgn:7000198",
      "tgn:7029392"
    ],
    "placetype": [
      "aat:300008777"
    ],
    "name:en": "Bātupuram",
    "id": 7546378
  }
}
