{
  "geometry": {
    "type": "Point",
    "coordinates": [
      -69.5667,
      44.3333
    ]
  },
  "type": "Feature",
  "properties": {
    "hierarchy": [
      "tgn:2045299",
      "tgn:1000001",
      "tgn:2000923",
      "tgn:7012149",
      "tgn:7007515",
      "tgn:7029392"
    ],
    "placetype": [
      "aat:300008347",
      "aat:300387210"
    ],
    "id": 2045299,
    "name:xx": "North Windsor"
  }
}
