{
  "geometry": {
    "type": "Point",
    "coordinates": [
      -75.1667,
      44.1667
    ]
  },
  "type": "Feature",
  "properties": {
    "hierarchy": [
      "tgn:2684465",
      "tgn:1000001",
      "tgn:7012149",
      "tgn:7016021",
      "tgn:7007568",
      "tgn:7029392"
    ],
    "placetype": [
      "aat:300008680"
    ],
    "id": 2684465,
    "name:xx": "Spider Pond"
  }
}
