{
  "geometry": {
    "type": "Point",
    "coordinates": [
      -104.4667,
      50.4833
    ]
  },
  "type": "Feature",
  "properties": {
    "hierarchy": [
      "tgn:1016067",
      "tgn:7005685",
      "tgn:1000001",
      "tgn:7005805",
      "tgn:7029392"
    ],
    "placetype": [
      "aat:300008347"
    ],
    "id": 1016067,
    "name:xx": "Pilot Butte"
  }
}
