{
  "geometry": {
    "type": "Point",
    "coordinates": [
      -85.0833,
      42.7833
    ]
  },
  "type": "Feature",
  "properties": {
    "hierarchy": [
      "tgn:2140227",
      "tgn:1000001",
      "tgn:7012149",
      "tgn:1002503",
      "tgn:7007520",
      "tgn:7029392"
    ],
    "placetype": [
      "aat:300008680"
    ],
    "id": 2140227,
    "name:xx": "Augst Lake"
  }
}
