{
  "geometry": {
    "type": "Point",
    "coordinates": [
      -94.8667,
      33.7667
    ]
  },
  "type": "Feature",
  "properties": {
    "hierarchy": [
      "tgn:2247944",
      "tgn:1000001",
      "tgn:7012149",
      "tgn:2001667",
      "tgn:7007707",
      "tgn:7029392"
    ],
    "placetype": [
      "aat:300008680"
    ],
    "id": 2247944,
    "name:xx": "Colbert Lake"
  }
}
