{
  "geometry": {
    "type": "Point",
    "coordinates": [
      -75.8333,
      37.1667
    ]
  },
  "type": "Feature",
  "properties": {
    "hierarchy": [
      "tgn:2517075",
      "tgn:1000001",
      "tgn:7012149",
      "tgn:1002730",
      "tgn:7007919",
      "tgn:7029392"
    ],
    "placetype": [
      "aat:300132316"
    ],
    "id": 2517075,
    "name:xx": "Mink Island Bay"
  }
}
