{
  "geometry": {
    "type": "Point",
    "coordinates": [
      -83.3333,
      38.3167
    ]
  },
  "type": "Feature",
  "properties": {
    "hierarchy": [
      "tgn:2038844",
      "tgn:1000001",
      "tgn:1002240",
      "tgn:7012149",
      "tgn:7007255",
      "tgn:7029392"
    ],
    "placetype": [
      "aat:300008347",
      "aat:300387210"
    ],
    "id": 2038844,
    "name:xx": "Fitch"
  }
}
