{
  "geometry": {
    "type": "Point",
    "coordinates": [
      -77.6833,
      38.5167
    ]
  },
  "type": "Feature",
  "properties": {
    "hierarchy": [
      "tgn:2377654",
      "tgn:1000001",
      "tgn:7012149",
      "tgn:1002368",
      "tgn:7007919",
      "tgn:7029392"
    ],
    "placetype": [
      "aat:300008699"
    ],
    "id": 2377654,
    "name:xx": "Harpers Run"
  }
}
