{
  "geometry": {
    "type": "Point",
    "coordinates": [
      -90.7167,
      39.9667
    ]
  },
  "type": "Feature",
  "properties": {
    "hierarchy": [
      "tgn:2373570",
      "tgn:1000001",
      "tgn:1002208",
      "tgn:7012149",
      "tgn:7007251",
      "tgn:7029392"
    ],
    "placetype": [
      "aat:300008699"
    ],
    "id": 2373570,
    "name:xx": "Hamilton Branch"
  }
}
