{
  "geometry": {
    "type": "Point",
    "coordinates": [
      -168.3333,
      53.2667
    ]
  },
  "type": "Feature",
  "properties": {
    "hierarchy": [
      "tgn:2693172",
      "tgn:7030516",
      "tgn:7006450",
      "tgn:1000001",
      "tgn:7012149",
      "tgn:7029392"
    ],
    "placetype": [
      "aat:300008850"
    ],
    "id": 2693172,
    "name:xx": "Steeple Point"
  }
}
