{
  "geometry": {
    "type": "Point",
    "coordinates": [
      -111.2167,
      42.3667
    ]
  },
  "type": "Feature",
  "properties": {
    "hierarchy": [
      "tgn:2338283",
      "tgn:2000455",
      "tgn:1000001",
      "tgn:7012149",
      "tgn:7007250",
      "tgn:7029392"
    ],
    "placetype": [
      "aat:300008697"
    ],
    "id": 2338283,
    "name:xx": "Fox Spring"
  }
}
