{
  "geometry": {
    "type": "Point",
    "coordinates": [
      78.185278,
      17.797778
    ]
  },
  "type": "Feature",
  "properties": {
    "hierarchy": [
      "tgn:7566746",
      "tgn:1001828",
      "tgn:1000004",
      "tgn:7000198",
      "tgn:7029392"
    ],
    "placetype": [
      "aat:300008347"
    ],
    "name:en": "Ibrahimābād",
    "id": 7566746
  }
}
