{
  "geometry": {
    "type": "Point",
    "coordinates": [
      -107.8333,
      33.1167
    ]
  },
  "type": "Feature",
  "properties": {
    "hierarchy": [
      "tgn:2774691",
      "tgn:1000001",
      "tgn:7012149",
      "tgn:2001455",
      "tgn:7007566",
      "tgn:7029392"
    ],
    "placetype": [
      "aat:300008697"
    ],
    "id": 2774691,
    "name:xx": "Willow Spring"
  }
}
