{
  "geometry": {
    "type": "Point",
    "coordinates": [
      -113.35,
      45.15
    ]
  },
  "type": "Feature",
  "properties": {
    "hierarchy": [
      "tgn:2652249",
      "tgn:1000001",
      "tgn:2001260",
      "tgn:7012149",
      "tgn:7007524",
      "tgn:7029392"
    ],
    "placetype": [
      "aat:300008680"
    ],
    "id": 2652249,
    "name:xx": "Selway Lake"
  }
}
