{
  "type": "FeatureCollection",
  "features": [
    {
      "geometry": {
        "type": "Point",
        "coordinates": [
          -85.25,
          34.3167
        ]
      },
      "type": "Feature",
      "properties": {
        "hierarchy": [
          "tgn:2159810",
          "tgn:1000001",
          "tgn:7012149",
          "tgn:2000348",
          "tgn:7007248",
          "tgn:7029392"
        ],
        "placetype": [
          "aat:300008706"
        ],
        "id": 2159810,
        "name:xx": "Beech Creek"
      }
    },
    {
      "geometry": {
        "type": "Point",
        "coordinates": [
          -83.55,
          34.9833
        ]
      },
      "type": "Feature",
      "properties": {
        "hierarchy": [
          "tgn:2159811",
          "tgn:1000001",
          "tgn:7012149",
          "tgn:7029392"
        ],
        "placetype": [
          "aat:300008706"
        ],
        "id": 2159811,
        "name:xx": "Beech Creek"
      }
    },
    {
      "geometry": {
        "type": "Point",
        "coordinates": [
          -86.7833,
          38.7
        ]
      },
      "type": "Feature",
      "properties": {
        "hierarchy": [
          "tgn:2159812",
          "tgn:1000001",
          "tgn:7012149",
          "tgn:2000546",
          "tgn:7007252",
          "tgn:7029392"
        ],
        "placetype": [
          "aat:300008706"
        ],
        "id": 2159812,
        "name:xx": "Beech Creek"
      }
    },
    {
      "geometry": {
        "type": "Point",
        "coordinates": [
          -86.9333,
          39.2333
        ]
      },
      "type": "Feature",
      "properties": {
        "hierarchy": [
          "tgn:2159813",
          "tgn:1000001",
          "tgn:7012149",
          "tgn:2000548",
          "tgn:7007252",
          "tgn:7029392"
        ],
        "placetype": [
          "aat:300008706"
        ],
        "id": 2159813,
        "name:xx": "Beech Creek"
      }
    },
    {
      "geometry": {
        "type": "Point",
        "coordinates": [
          -86.05,
          39.7167
        ]
      },
      "type": "Feature",
      "properties": {
        "hierarchy": [
          "tgn:2159814",
          "tgn:1000001",
          "tgn:7012149",
          "tgn:1002633",
          "tgn:7007252",
          "tgn:7029392"
        ],
        "placetype": [
          "aat:300008706"
        ],
        "id": 2159814,
        "name:xx": "Beech Creek"
      }
    },
    {
      "geometry": {
        "type": "Point",
        "coordinates": [
          -87.1333,
          38.4667
        ]
      },
      "type": "Feature",
      "properties": {
        "hierarchy": [
          "tgn:2159815",
          "tgn:1000001",
          "tgn:7012149",
          "tgn:2000551",
          "tgn:7007252",
          "tgn:7029392"
        ],
        "placetype": [
          "aat:300008706"
        ],
        "id": 2159815,
        "name:xx": "Beech Creek"
      }
    },
    {
      "geometry": {
        "type": "Point",
        "coordinates": [
          -86.6833,
          39.0833
        ]
      },
      "type": "Feature",
      "properties": {
        "hierarchy": [
          "tgn:2159816",
          "tgn:1000001",
          "tgn:7012149",
          "tgn:2000544",
          "tgn:7007252",
          "tgn:7029392"
        ],
        "placetype": [
          "aat:300008706"
        ],
        "id": 2159816,
        "name:xx": "Beech Creek"
      }
    },
    {
      "geometry": {
        "type": "Point",
        "coordinates": [
          -84.3667,
          37.05
        ]
      },
      "type": "Feature",
      "properties": {
        "hierarchy": [
          "tgn:2159817",
          "tgn:1000001",
          "tgn:7012149",
          "tgn:2000839",
          "tgn:7007255",
          "tgn:7029392"
        ],
        "placetype": [
          "aat:300008706"
        ],
        "id": 2159817,
        "name:xx": "Beech Creek"
      }
    },
    {
      "geometry": {
        "type": "Point",
        "coordinates": [
          -87.0333,
          37.1667
        ]
      },
      "type": "Feature",
      "properties": {
        "hierarchy": [
          "tgn:2159818",
          "tgn:1000001",
          "tgn:7012149",
          "tgn:2000832",
          "tgn:7007255",
          "tgn:7029392"
        ],
        "placetype": [
          "aat:300008706"
        ],
        "id": 2159818,
        "name:xx": "Beech Creek"
      }
    },
    {
      "geometry": {
        "type": "Point",
        "coordinates": [
          -83.6833,
          37.1333
        ]
      },
      "type": "Feature",
      "properties": {
        "hierarchy": [
          "tgn:2159819",
          "tgn:1000001",
          "tgn:2000782",
          "tgn:7012149",
          "tgn:7007255",
          "tgn:7029392"
        ],
        "placetype": [
          "aat:300008706"
        ],
        "id": 2159819,
        "name:xx": "Beech Creek"
      }
    }
  ]
}
