{
  "type": "FeatureCollection",
  "features": [
    {
      "geometry": {
        "type": "Point",
        "coordinates": [
          -122.251,
          49.151
        ]
      },
      "type": "Feature",
      "properties": {
        "hierarchy": [
          "tgn:7032631",
          "tgn:7005735",
          "tgn:7005685",
          "tgn:1000001",
          "tgn:7029392"
        ],
        "placetype": [
          "aat:300008347",
          "aat:300000810",
          "aat:300167671",
          "aat:300017437",
          "aat:300387004",
          "aat:300008372"
        ],
        "id": 7032631,
        "name:xx": "Xá:ytem"
      }
    },
    {
      "geometry": {
        "type": "Point",
        "coordinates": [
          17.0167,
          49.7
        ]
      },
      "type": "Feature",
      "properties": {
        "hierarchy": [
          "tgn:7032632",
          "tgn:7593917",
          "tgn:1000003",
          "tgn:1001780",
          "tgn:7029392"
        ],
        "placetype": [
          "aat:300386972",
          "aat:300000810",
          "aat:300048808",
          "aat:300391483",
          "aat:300387247",
          "aat:300266152",
          "aat:300387006"
        ],
        "name:en": "Mladeč Caves",
        "id": 7032632
      }
    },
    {
      "geometry": {
        "type": "Point",
        "coordinates": [
          16.65,
          48.8833
        ]
      },
      "type": "Feature",
      "properties": {
        "hierarchy": [
          "tgn:7032633",
          "tgn:1003523",
          "tgn:1000003",
          "tgn:1001780",
          "tgn:7029392"
        ],
        "placetype": [
          "aat:300019258",
          "aat:300008347",
          "aat:300000810",
          "aat:300167671",
          "aat:300387004"
        ],
        "name:en": "Dolní Věstonice",
        "name:cs": "Dolní Věstonice",
        "id": 7032633
      }
    },
    {
      "geometry": {
        "type": "Point",
        "coordinates": [
          -1.3,
          54.366667
        ]
      },
      "type": "Feature",
      "properties": {
        "hierarchy": [
          "tgn:7032636",
          "tgn:7002445",
          "tgn:1000003",
          "tgn:7008166",
          "tgn:7008591",
          "tgn:7029392"
        ],
        "placetype": [
          "aat:300008347",
          "aat:300387007",
          "aat:300000810",
          "aat:300167671",
          "aat:300000645",
          "aat:300000641",
          "aat:300008057",
          "aat:300000833"
        ],
        "name:en": "Mount Grace Priory",
        "id": 7032636
      }
    },
    {
      "geometry": {
        "type": "Point",
        "coordinates": [
          0.186,
          52.293
        ]
      },
      "type": "Feature",
      "properties": {
        "hierarchy": [
          "tgn:7032637",
          "tgn:7002445",
          "tgn:7011980",
          "tgn:1000003",
          "tgn:7008591",
          "tgn:7029392"
        ],
        "placetype": [
          "aat:300008347",
          "aat:300000642",
          "aat:300005433",
          "aat:300167671",
          "aat:300000206",
          "aat:300386960",
          "aat:300000641",
          "aat:300007423",
          "aat:300000833"
        ],
        "id": 7032637,
        "name:xx": "Denny Abbey"
      }
    },
    {
      "geometry": {
        "type": "Point",
        "coordinates": [
          -109.442,
          -27.189
        ]
      },
      "type": "Feature",
      "properties": {
        "hierarchy": [
          "tgn:7032638",
          "tgn:1001768",
          "tgn:1000049",
          "tgn:1000002",
          "tgn:1008543",
          "tgn:7029392"
        ],
        "placetype": [
          "aat:300008347",
          "aat:300000810",
          "aat:300167671",
          "aat:300387272"
        ],
        "id": 7032638,
        "name:xx": "Orongo"
      }
    },
    {
      "geometry": {
        "type": "Point",
        "coordinates": [
          -98.666,
          33
        ]
      },
      "type": "Feature",
      "properties": {
        "hierarchy": [
          "tgn:7032639",
          "tgn:1000001",
          "tgn:7012149",
          "tgn:2002098",
          "tgn:7007826",
          "tgn:7029392"
        ],
        "placetype": [
          "aat:300008347",
          "aat:300000810",
          "aat:300167671"
        ],
        "id": 7032639,
        "name:xx": "Harrell"
      }
    }
  ]
}
