{
  "type": "FeatureCollection",
  "features": [
    {
      "geometry": {
        "type": "Point",
        "coordinates": [
          -84.0333,
          33.75
        ]
      },
      "type": "Feature",
      "properties": {
        "hierarchy": [
          "tgn:2543500",
          "tgn:1000001",
          "tgn:7012149",
          "tgn:2124023",
          "tgn:7007248",
          "tgn:7029392"
        ],
        "placetype": [
          "aat:300006191"
        ],
        "id": 2543500,
        "name:xx": "Norris Lake"
      }
    },
    {
      "geometry": {
        "type": "Point",
        "coordinates": [
          -93.3833,
          45.3667
        ]
      },
      "type": "Feature",
      "properties": {
        "hierarchy": [
          "tgn:2543501",
          "tgn:2001000",
          "tgn:1000001",
          "tgn:7012149",
          "tgn:7007521",
          "tgn:7029392"
        ],
        "placetype": [
          "aat:300008680"
        ],
        "id": 2543501,
        "name:xx": "Norris Lake"
      }
    },
    {
      "geometry": {
        "type": "Point",
        "coordinates": [
          -95.55,
          47.25
        ]
      },
      "type": "Feature",
      "properties": {
        "hierarchy": [
          "tgn:2543502",
          "tgn:1000001",
          "tgn:7012149",
          "tgn:2001042",
          "tgn:7007521",
          "tgn:7029392"
        ],
        "placetype": [
          "aat:300008680"
        ],
        "id": 2543502,
        "name:xx": "Norris Lake"
      }
    },
    {
      "geometry": {
        "type": "Point",
        "coordinates": [
          -88.4,
          33.4667
        ]
      },
      "type": "Feature",
      "properties": {
        "hierarchy": [
          "tgn:2543503",
          "tgn:1000001",
          "tgn:7012149",
          "tgn:2001129",
          "tgn:7007522",
          "tgn:7029392"
        ],
        "placetype": [
          "aat:300006191"
        ],
        "id": 2543503,
        "name:xx": "Norris Lake"
      }
    },
    {
      "geometry": {
        "type": "Point",
        "coordinates": [
          -102.85,
          41.45
        ]
      },
      "type": "Feature",
      "properties": {
        "hierarchy": [
          "tgn:2543504",
          "tgn:1000001",
          "tgn:7012149",
          "tgn:2001377",
          "tgn:7007525",
          "tgn:7029392"
        ],
        "placetype": [
          "aat:300008680"
        ],
        "id": 2543504,
        "name:xx": "Norris Lake"
      }
    },
    {
      "geometry": {
        "type": "Point",
        "coordinates": [
          -84.0833,
          36.2167
        ]
      },
      "type": "Feature",
      "properties": {
        "hierarchy": [
          "tgn:2543505",
          "tgn:1000001",
          "tgn:7012149",
          "tgn:7007825",
          "tgn:7029392"
        ],
        "placetype": [
          "aat:300006191"
        ],
        "id": 2543505,
        "name:xx": "Norris Lake"
      }
    },
    {
      "geometry": {
        "type": "Point",
        "coordinates": [
          -116.7667,
          43.5333
        ]
      },
      "type": "Feature",
      "properties": {
        "hierarchy": [
          "tgn:2543506",
          "tgn:1000001",
          "tgn:2000465",
          "tgn:7012149",
          "tgn:7007250",
          "tgn:7029392"
        ],
        "placetype": [
          "aat:300006075"
        ],
        "id": 2543506,
        "name:xx": "Norris Lateral"
      }
    },
    {
      "geometry": {
        "type": "Point",
        "coordinates": [
          -134.1333,
          58.4333
        ]
      },
      "type": "Feature",
      "properties": {
        "hierarchy": [
          "tgn:2543508",
          "tgn:7006450",
          "tgn:1000001",
          "tgn:2124089",
          "tgn:7012149",
          "tgn:7029392"
        ],
        "placetype": [
          "aat:300008798"
        ],
        "id": 2543508,
        "name:xx": "Norris Mountain"
      }
    },
    {
      "geometry": {
        "type": "Point",
        "coordinates": [
          -113.5167,
          48.5667
        ]
      },
      "type": "Feature",
      "properties": {
        "hierarchy": [
          "tgn:2543509",
          "tgn:1000001",
          "tgn:7012149",
          "tgn:7007524",
          "tgn:7029392"
        ],
        "placetype": [
          "aat:300008798"
        ],
        "id": 2543509,
        "name:xx": "Norris Mountain"
      }
    }
  ]
}
