{
  "geometry": {
    "type": "Point",
    "coordinates": [
      -82.4333,
      35.2333
    ]
  },
  "type": "Feature",
  "properties": {
    "hierarchy": [
      "tgn:2498560",
      "tgn:1000001",
      "tgn:7012149",
      "tgn:2001504",
      "tgn:7007709",
      "tgn:7029392"
    ],
    "placetype": [
      "aat:300008798"
    ],
    "id": 2498560,
    "name:xx": "McAlpine Mountain"
  }
}
