{
  "geometry": {
    "type": "Point",
    "coordinates": [
      -83.85,
      30.4833
    ]
  },
  "type": "Feature",
  "properties": {
    "hierarchy": [
      "tgn:2205033",
      "tgn:1000001",
      "tgn:2000274",
      "tgn:7012149",
      "tgn:7007240",
      "tgn:7029392"
    ],
    "placetype": [
      "aat:300008706"
    ],
    "id": 2205033,
    "name:xx": "Buggs Creek"
  }
}
