{
  "geometry": {
    "type": "Point",
    "coordinates": [
      -109.2667,
      38.4167
    ]
  },
  "type": "Feature",
  "properties": {
    "hierarchy": [
      "tgn:2444108",
      "tgn:1000001",
      "tgn:7012149",
      "tgn:2002119",
      "tgn:7007827",
      "tgn:7029392"
    ],
    "placetype": [
      "aat:300000390"
    ],
    "id": 2444108,
    "name:xx": "LaSal Pass Mine"
  }
}
