{
  "type": "FeatureCollection",
  "features": [
    {
      "geometry": {
        "type": "Point",
        "coordinates": [
          18.5,
          40.15
        ]
      },
      "type": "Feature",
      "properties": {
        "hierarchy": [
          "tgn:7041270",
          "tgn:1003468",
          "tgn:1000003",
          "tgn:7010380",
          "tgn:1000080",
          "tgn:7029392"
        ],
        "placetype": [
          "aat:300386846"
        ],
        "id": 7041270,
        "name:xx": "San Nicola, Punta"
      }
    },
    {
      "geometry": {
        "type": "Point",
        "coordinates": [
          13.65,
          42.116667
        ]
      },
      "type": "Feature",
      "properties": {
        "hierarchy": [
          "tgn:7041271",
          "tgn:7009084",
          "tgn:7004154",
          "tgn:1000003",
          "tgn:1000080",
          "tgn:7029392"
        ],
        "placetype": [
          "aat:300008795"
        ],
        "id": 7041271,
        "name:xx": "San Nicola, Monte"
      }
    },
    {
      "geometry": {
        "type": "Point",
        "coordinates": [
          13.3,
          42.066667
        ]
      },
      "type": "Feature",
      "properties": {
        "hierarchy": [
          "tgn:7041272",
          "tgn:7009084",
          "tgn:7004154",
          "tgn:1000003",
          "tgn:1000080",
          "tgn:7029392"
        ],
        "placetype": [
          "aat:300008795"
        ],
        "id": 7041272,
        "name:xx": "San Nicola, Monte"
      }
    },
    {
      "geometry": {
        "type": "Point",
        "coordinates": [
          14.183333,
          41.35
        ]
      },
      "type": "Feature",
      "properties": {
        "hierarchy": [
          "tgn:7041273",
          "tgn:7003011",
          "tgn:7003005",
          "tgn:1000003",
          "tgn:1000080",
          "tgn:7029392"
        ],
        "placetype": [
          "aat:300008795"
        ],
        "id": 7041273,
        "name:xx": "San Nicola, Monte"
      }
    },
    {
      "geometry": {
        "type": "Point",
        "coordinates": [
          12.35,
          41.916667
        ]
      },
      "type": "Feature",
      "properties": {
        "hierarchy": [
          "tgn:7041275",
          "tgn:7003138",
          "tgn:1000003",
          "tgn:7003080",
          "tgn:1000080",
          "tgn:7029392"
        ],
        "placetype": [
          "aat:300008699"
        ],
        "id": 7041275,
        "name:xx": "San Nicola, Fosso"
      }
    },
    {
      "geometry": {
        "type": "Point",
        "coordinates": [
          13.266667,
          42.3
        ]
      },
      "type": "Feature",
      "properties": {
        "hierarchy": [
          "tgn:7041276",
          "tgn:7009084",
          "tgn:7004154",
          "tgn:1000003",
          "tgn:1000080",
          "tgn:7029392"
        ],
        "placetype": [
          "aat:300008347"
        ],
        "id": 7041276,
        "name:xx": "San Nicola"
      }
    },
    {
      "geometry": {
        "type": "Point",
        "coordinates": [
          15.516667,
          42.116667
        ]
      },
      "type": "Feature",
      "properties": {
        "hierarchy": [
          "tgn:7041277",
          "tgn:1003455",
          "tgn:1000003",
          "tgn:7010380",
          "tgn:1000080",
          "tgn:7029392"
        ],
        "placetype": [
          "aat:300008347"
        ],
        "id": 7041277,
        "name:xx": "San Nicola"
      }
    },
    {
      "geometry": {
        "type": "Point",
        "coordinates": [
          15.283333,
          40.1
        ]
      },
      "type": "Feature",
      "properties": {
        "hierarchy": [
          "tgn:7041278",
          "tgn:7003005",
          "tgn:7003014",
          "tgn:1000003",
          "tgn:1000080",
          "tgn:7029392"
        ],
        "placetype": [
          "aat:300008347"
        ],
        "id": 7041278,
        "name:xx": "San Nicola"
      }
    }
  ]
}
