{
  "type": "FeatureCollection",
  "features": [
    {
      "geometry": {
        "type": "Point",
        "coordinates": [
          81.5,
          29
        ]
      },
      "type": "Feature",
      "properties": {
        "hierarchy": [
          "tgn:7001420",
          "tgn:1000004",
          "tgn:1000132",
          "tgn:7029392"
        ],
        "placetype": [
          "aat:300387064",
          "aat:300236112"
        ],
        "id": 7001420,
        "name:xx": "Far-western"
      }
    },
    {
      "geometry": {
        "type": "Point",
        "coordinates": [
          87.9167,
          27.1667
        ]
      },
      "type": "Feature",
      "properties": {
        "hierarchy": [
          "tgn:7001421",
          "tgn:7001416",
          "tgn:1000004",
          "tgn:1000132",
          "tgn:7029392"
        ],
        "placetype": [
          "aat:300387145",
          "aat:300000853"
        ],
        "id": 7001421,
        "name:xx": "Mechi"
      }
    },
    {
      "geometry": {
        "type": "Point",
        "coordinates": [
          87.4167,
          27.1667
        ]
      },
      "type": "Feature",
      "properties": {
        "hierarchy": [
          "tgn:7001422",
          "tgn:7001416",
          "tgn:1000004",
          "tgn:1000132",
          "tgn:7029392"
        ],
        "placetype": [
          "aat:300387145",
          "aat:300000853"
        ],
        "id": 7001422,
        "name:xx": "Kosi"
      }
    },
    {
      "geometry": {
        "type": "Point",
        "coordinates": [
          86.6667,
          27.3333
        ]
      },
      "type": "Feature",
      "properties": {
        "hierarchy": [
          "tgn:7001423",
          "tgn:7001416",
          "tgn:1000004",
          "tgn:1000132",
          "tgn:7029392"
        ],
        "placetype": [
          "aat:300387145",
          "aat:300000853"
        ],
        "id": 7001423,
        "name:xx": "Sagarmatha"
      }
    },
    {
      "geometry": {
        "type": "Point",
        "coordinates": [
          85.9167,
          27.1667
        ]
      },
      "type": "Feature",
      "properties": {
        "hierarchy": [
          "tgn:7001424",
          "tgn:7001417",
          "tgn:1000004",
          "tgn:1000132",
          "tgn:7029392"
        ],
        "placetype": [
          "aat:300387145",
          "aat:300000853"
        ],
        "id": 7001424,
        "name:xx": "Janakpur"
      }
    },
    {
      "geometry": {
        "type": "Point",
        "coordinates": [
          85.4167,
          28
        ]
      },
      "type": "Feature",
      "properties": {
        "hierarchy": [
          "tgn:7001425",
          "tgn:7001417",
          "tgn:1000004",
          "tgn:1000132",
          "tgn:7029392"
        ],
        "placetype": [
          "aat:300387145",
          "aat:300000853"
        ],
        "id": 7001425,
        "name:xx": "B훮gmat카"
      }
    },
    {
      "geometry": {
        "type": "Point",
        "coordinates": [
          85,
          27.4167
        ]
      },
      "type": "Feature",
      "properties": {
        "hierarchy": [
          "tgn:7001426",
          "tgn:7001417",
          "tgn:1000004",
          "tgn:1000132",
          "tgn:7029392"
        ],
        "placetype": [
          "aat:300387145",
          "aat:300000853"
        ],
        "id": 7001426,
        "name:xx": "N훮r훮yani"
      }
    },
    {
      "geometry": {
        "type": "Point",
        "coordinates": [
          83.5,
          28.8333
        ]
      },
      "type": "Feature",
      "properties": {
        "hierarchy": [
          "tgn:7001427",
          "tgn:1000004",
          "tgn:7001418",
          "tgn:1000132",
          "tgn:7029392"
        ],
        "placetype": [
          "aat:300387145",
          "aat:300000853"
        ],
        "id": 7001427,
        "name:xx": "Dhaulagiri"
      }
    },
    {
      "geometry": {
        "type": "Point",
        "coordinates": [
          83.5,
          27.75
        ]
      },
      "type": "Feature",
      "properties": {
        "hierarchy": [
          "tgn:7001428",
          "tgn:1000004",
          "tgn:7001418",
          "tgn:1000132",
          "tgn:7029392"
        ],
        "placetype": [
          "aat:300387145",
          "aat:300000853"
        ],
        "id": 7001428,
        "name:xx": "Lumbini"
      }
    },
    {
      "geometry": {
        "type": "Point",
        "coordinates": [
          84.5,
          28.1667
        ]
      },
      "type": "Feature",
      "properties": {
        "hierarchy": [
          "tgn:7001429",
          "tgn:1000004",
          "tgn:7001418",
          "tgn:1000132",
          "tgn:7029392"
        ],
        "placetype": [
          "aat:300387145",
          "aat:300000853"
        ],
        "id": 7001429,
        "name:xx": "Gandaki"
      }
    }
  ]
}
