{
  "geometry": {
    "type": "Point",
    "coordinates": [
      4.6667,
      45.85
    ]
  },
  "type": "Feature",
  "properties": {
    "hierarchy": [
      "tgn:1122182",
      "tgn:1000003",
      "tgn:1000070",
      "tgn:7002897",
      "tgn:7029392"
    ],
    "placetype": [
      "aat:300008707"
    ],
    "id": 1122182,
    "name:xx": "Brévenne"
  }
}
