{
  "geometry": {
    "type": "Point",
    "coordinates": [
      14.6667,
      58.2167
    ]
  },
  "type": "Feature",
  "properties": {
    "hierarchy": [
      "tgn:1062690",
      "tgn:1000003",
      "tgn:7003775",
      "tgn:1000097",
      "tgn:7029392"
    ],
    "placetype": [
      "aat:300008347"
    ],
    "id": 1062690,
    "name:xx": "Ödeshög"
  }
}
