{
  "geometry": {
    "type": "Point",
    "coordinates": [
      -95.85,
      42.1833
    ]
  },
  "type": "Feature",
  "properties": {
    "hierarchy": [
      "tgn:2600972",
      "tgn:1000001",
      "tgn:7012149",
      "tgn:2000627",
      "tgn:7007253",
      "tgn:7029392"
    ],
    "placetype": [
      "aat:300008699"
    ],
    "id": 2600972,
    "name:xx": "Pumpkin Run"
  }
}
