{
  "geometry": {
    "type": "Point",
    "coordinates": [
      -80.6667,
      40.4833
    ]
  },
  "type": "Feature",
  "properties": {
    "hierarchy": [
      "tgn:2395793",
      "tgn:1000001",
      "tgn:7012149",
      "tgn:1002519",
      "tgn:7007706",
      "tgn:7029392"
    ],
    "placetype": [
      "aat:300008699"
    ],
    "id": 2395793,
    "name:xx": "Hollow Rock Run"
  }
}
