{
  "geometry": {
    "type": "Point",
    "coordinates": [
      -76.9167,
      40.3667
    ]
  },
  "type": "Feature",
  "properties": {
    "hierarchy": [
      "tgn:2087701",
      "tgn:1000001",
      "tgn:1002318",
      "tgn:7012149",
      "tgn:7007710",
      "tgn:7029392"
    ],
    "placetype": [
      "aat:300008347"
    ],
    "id": 2087701,
    "name:xx": "Dauphin"
  }
}
