{
  "type": "FeatureCollection",
  "features": [
    {
      "geometry": {
        "type": "Point",
        "coordinates": [
          -0.766667,
          54.516667
        ]
      },
      "type": "Feature",
      "properties": {
        "hierarchy": [
          "tgn:7452695",
          "tgn:7002445",
          "tgn:1000003",
          "tgn:7008166",
          "tgn:7008591",
          "tgn:7029392"
        ],
        "placetype": [
          "aat:300008347"
        ],
        "name:en": "Ellerby",
        "id": 7452695
      }
    },
    {
      "geometry": {
        "type": "Point",
        "coordinates": [
          -4.433333,
          56.233333
        ]
      },
      "type": "Feature",
      "properties": {
        "hierarchy": [
          "tgn:7452696",
          "tgn:7002444",
          "tgn:1000003",
          "tgn:5000460",
          "tgn:7008591",
          "tgn:7029392"
        ],
        "placetype": [
          "aat:300008791"
        ],
        "name:en": "Molach, Eilean",
        "id": 7452696
      }
    },
    {
      "geometry": {
        "type": "Point",
        "coordinates": [
          -2.233333,
          52.833333
        ]
      },
      "type": "Feature",
      "properties": {
        "hierarchy": [
          "tgn:7452697",
          "tgn:7002445",
          "tgn:1000003",
          "tgn:7008174",
          "tgn:7008591",
          "tgn:7029392"
        ],
        "placetype": [
          "aat:300008347"
        ],
        "name:en": "Ellenhall",
        "id": 7452697
      }
    },
    {
      "geometry": {
        "type": "Point",
        "coordinates": [
          -2.416667,
          53.516667
        ]
      },
      "type": "Feature",
      "properties": {
        "hierarchy": [
          "tgn:7452698",
          "tgn:7002445",
          "tgn:1003640",
          "tgn:1000003",
          "tgn:7026570",
          "tgn:7008591",
          "tgn:7029392"
        ],
        "placetype": [
          "aat:300008347"
        ],
        "name:en": "Ellenbrook",
        "id": 7452698
      }
    },
    {
      "geometry": {
        "type": "Point",
        "coordinates": [
          -3.483333,
          54.7
        ]
      },
      "type": "Feature",
      "properties": {
        "hierarchy": [
          "tgn:7452699",
          "tgn:7002445",
          "tgn:1000003",
          "tgn:7008117",
          "tgn:7008591",
          "tgn:7029392"
        ],
        "placetype": [
          "aat:300008347"
        ],
        "name:en": "Ellenborough",
        "id": 7452699
      }
    }
  ]
}
