{
  "geometry": {
    "type": "Point",
    "coordinates": [
      -115.5167,
      35.4667
    ]
  },
  "type": "Feature",
  "properties": {
    "hierarchy": [
      "tgn:2702460",
      "tgn:1000001",
      "tgn:7012149",
      "tgn:7007157",
      "tgn:1002857",
      "tgn:7029392"
    ],
    "placetype": [
      "aat:300000390"
    ],
    "id": 2702460,
    "name:xx": "Sulphide Queen Mine"
  }
}
