{
  "geometry": {
    "type": "Point",
    "coordinates": [
      -111.2333,
      45.3333
    ]
  },
  "type": "Feature",
  "properties": {
    "hierarchy": [
      "tgn:2138390",
      "tgn:1000001",
      "tgn:7012149",
      "tgn:2001275",
      "tgn:7007524",
      "tgn:7029392"
    ],
    "placetype": [
      "aat:300008706"
    ],
    "id": 2138390,
    "name:xx": "Asbestos Creek"
  }
}
