{
  "type": "FeatureCollection",
  "features": [
    {
      "geometry": {
        "type": "Point",
        "coordinates": [
          -68.8333,
          61.0833
        ]
      },
      "type": "Feature",
      "properties": {
        "hierarchy": [
          "tgn:7013570",
          "tgn:1000004",
          "tgn:7029392"
        ],
        "placetype": [
          "aat:300008707"
        ],
        "id": 7013570,
        "name:xx": "Irtysh"
      }
    },
    {
      "geometry": {
        "type": "Point",
        "coordinates": [
          64,
          66.5
        ]
      },
      "type": "Feature",
      "properties": {
        "hierarchy": [
          "tgn:7013571",
          "tgn:1000004",
          "tgn:7018214",
          "tgn:7002435",
          "tgn:7029392"
        ],
        "placetype": [
          "aat:300387145",
          "aat:300387080"
        ],
        "id": 7013571,
        "name:xx": "Yamalo-Nenetskiy Avtonomnyy Okrug"
      }
    },
    {
      "geometry": {
        "type": "Point",
        "coordinates": [
          -73.8667,
          41
        ]
      },
      "type": "Feature",
      "properties": {
        "hierarchy": [
          "tgn:7013572",
          "tgn:1000001",
          "tgn:7012149",
          "tgn:7014612",
          "tgn:7007568",
          "tgn:7029392"
        ],
        "placetype": [
          "aat:300008347"
        ],
        "id": 7013572,
        "name:xx": "Dobbs Ferry"
      }
    },
    {
      "geometry": {
        "type": "Point",
        "coordinates": [
          -100.0167,
          37.75
        ]
      },
      "type": "Feature",
      "properties": {
        "hierarchy": [
          "tgn:7013573",
          "tgn:1000001",
          "tgn:2000688",
          "tgn:7012149",
          "tgn:7007254",
          "tgn:7029392"
        ],
        "placetype": [
          "aat:300008347",
          "aat:300387233",
          "aat:300008375"
        ],
        "id": 7013573,
        "name:xx": "Dodge City"
      }
    },
    {
      "geometry": {
        "type": "Point",
        "coordinates": [
          -120.3167,
          39.3167
        ]
      },
      "type": "Feature",
      "properties": {
        "hierarchy": [
          "tgn:7013574",
          "tgn:1000001",
          "tgn:7012149",
          "tgn:7007157",
          "tgn:1002791",
          "tgn:7029392"
        ],
        "placetype": [
          "aat:300259572"
        ],
        "id": 7013574,
        "name:xx": "Donner Pass"
      }
    },
    {
      "geometry": {
        "type": "Point",
        "coordinates": [
          -71.0667,
          42.2833
        ]
      },
      "type": "Feature",
      "properties": {
        "hierarchy": [
          "tgn:7013575",
          "tgn:7013445",
          "tgn:1000001",
          "tgn:1002923",
          "tgn:7012149",
          "tgn:7007517",
          "tgn:7029392"
        ],
        "placetype": [
          "aat:300000745"
        ],
        "id": 7013575,
        "name:xx": "Dorchester"
      }
    },
    {
      "geometry": {
        "type": "Point",
        "coordinates": [
          -88.2333,
          40.1
        ]
      },
      "type": "Feature",
      "properties": {
        "hierarchy": [
          "tgn:7013576",
          "tgn:1000001",
          "tgn:1002253",
          "tgn:7012149",
          "tgn:7007251",
          "tgn:7029392"
        ],
        "placetype": [
          "aat:300008347"
        ],
        "id": 7013576,
        "name:xx": "Champaign"
      }
    },
    {
      "geometry": {
        "type": "Point",
        "coordinates": [
          -79.05,
          35.9
        ]
      },
      "type": "Feature",
      "properties": {
        "hierarchy": [
          "tgn:7013578",
          "tgn:1000001",
          "tgn:7012149",
          "tgn:2001525",
          "tgn:7007709",
          "tgn:7029392"
        ],
        "placetype": [
          "aat:300008347"
        ],
        "id": 7013578,
        "name:xx": "Chapel Hill"
      }
    }
  ]
}
