{
  "geometry": {
    "type": "Point",
    "coordinates": [
      55.9167,
      53.35
    ]
  },
  "type": "Feature",
  "properties": {
    "hierarchy": [
      "tgn:1059135",
      "tgn:1000004",
      "tgn:7011498",
      "tgn:7002435",
      "tgn:7029392"
    ],
    "placetype": [
      "aat:300008347"
    ],
    "id": 1059135,
    "name:xx": "Salavat"
  }
}
