{
  "geometry": {
    "type": "Point",
    "coordinates": [
      106.7833,
      10.8333
    ]
  },
  "type": "Feature",
  "properties": {
    "hierarchy": [
      "tgn:1087242",
      "tgn:1000004",
      "tgn:7001063",
      "tgn:1000145",
      "tgn:7029392"
    ],
    "placetype": [
      "aat:300008347"
    ],
    "id": 1087242,
    "name:xx": "Tǎng Nho'n Phú"
  }
}
