{
  "geometry": {
    "type": "Point",
    "coordinates": [
      -104.55,
      31.1833
    ]
  },
  "type": "Feature",
  "properties": {
    "hierarchy": [
      "tgn:2720239",
      "tgn:1000001",
      "tgn:7012149",
      "tgn:2001969",
      "tgn:7007826",
      "tgn:7029392"
    ],
    "placetype": [
      "aat:300006191"
    ],
    "id": 2720239,
    "name:xx": "Threemile Tank"
  }
}
