{
  "geometry": {
    "type": "Point",
    "coordinates": [
      6.6167,
      44.1667
    ]
  },
  "type": "Feature",
  "properties": {
    "hierarchy": [
      "tgn:1036127",
      "tgn:1000003",
      "tgn:1000070",
      "tgn:7002895",
      "tgn:7029392"
    ],
    "placetype": [
      "aat:300008347"
    ],
    "id": 1036127,
    "name:xx": "Villars-Colmars"
  }
}
