{
  "geometry": {
    "type": "Point",
    "coordinates": [
      -77.2167,
      40.5833
    ]
  },
  "type": "Feature",
  "properties": {
    "hierarchy": [
      "tgn:2286159",
      "tgn:1000001",
      "tgn:7012149",
      "tgn:1002528",
      "tgn:7007710",
      "tgn:7029392"
    ],
    "placetype": [
      "aat:300008798"
    ],
    "id": 2286159,
    "name:xx": "Dewey Hill"
  }
}
