{
  "geometry": {
    "type": "Point",
    "coordinates": [
      -84.9667,
      36.5833
    ]
  },
  "type": "Feature",
  "properties": {
    "hierarchy": [
      "tgn:2355029",
      "tgn:1000001",
      "tgn:7012149",
      "tgn:2001905",
      "tgn:7007825",
      "tgn:7029392"
    ],
    "placetype": [
      "aat:300266640"
    ],
    "id": 2355029,
    "name:xx": "Goodman Ridge"
  }
}
