{
  "geometry": {
    "type": "Point",
    "coordinates": [
      -109.35,
      48.6667
    ]
  },
  "type": "Feature",
  "properties": {
    "hierarchy": [
      "tgn:2716894",
      "tgn:1000001",
      "tgn:2001262",
      "tgn:7012149",
      "tgn:7007524",
      "tgn:7029392"
    ],
    "placetype": [
      "aat:300008761"
    ],
    "id": 2716894,
    "name:xx": "Thibadeau Coulee"
  }
}
