{
  "geometry": {
    "type": "Point",
    "coordinates": [
      35.65,
      33.05
    ]
  },
  "type": "Feature",
  "properties": {
    "hierarchy": [
      "tgn:1079477",
      "tgn:7000249",
      "tgn:1000004",
      "tgn:1000119",
      "tgn:7029392"
    ],
    "placetype": [
      "aat:300008347"
    ],
    "id": 1079477,
    "name:xx": "Ashmura"
  }
}
