{
  "geometry": {
    "type": "Point",
    "coordinates": [
      -79.2667,
      41.3833
    ]
  },
  "type": "Feature",
  "properties": {
    "hierarchy": [
      "tgn:2723443",
      "tgn:1000001",
      "tgn:1002272",
      "tgn:7012149",
      "tgn:7007710",
      "tgn:7029392"
    ],
    "placetype": [
      "aat:300008706"
    ],
    "id": 2723443,
    "name:xx": "Toby Creek"
  }
}
