{
  "geometry": {
    "type": "Point",
    "coordinates": [
      -108.85,
      39.0333
    ]
  },
  "type": "Feature",
  "properties": {
    "hierarchy": [
      "tgn:2151873",
      "tgn:1000001",
      "tgn:7012149",
      "tgn:2000230",
      "tgn:7007158",
      "tgn:7029392"
    ],
    "placetype": [
      "aat:300008798"
    ],
    "id": 2151873,
    "name:xx": "Battleship Rock"
  }
}
