{
  "geometry": {
    "type": "Point",
    "coordinates": [
      -91.7833,
      46.2167
    ]
  },
  "type": "Feature",
  "properties": {
    "hierarchy": [
      "tgn:2377775",
      "tgn:1000001",
      "tgn:2002318",
      "tgn:7012149",
      "tgn:7007922",
      "tgn:7029392"
    ],
    "placetype": [
      "aat:300008680"
    ],
    "id": 2377775,
    "name:xx": "Harriet Lake"
  }
}
