{
  "geometry": {
    "type": "Point",
    "coordinates": [
      -79.4333,
      38.5167
    ]
  },
  "type": "Feature",
  "properties": {
    "hierarchy": [
      "tgn:2447077",
      "tgn:1000001",
      "tgn:7012149",
      "tgn:7014398",
      "tgn:7013961",
      "tgn:7029392"
    ],
    "placetype": [
      "aat:300008699"
    ],
    "id": 2447077,
    "name:xx": "Liberty Run"
  }
}
