{
  "type": "FeatureCollection",
  "features": [
    {
      "geometry": {
        "type": "Point",
        "coordinates": [
          -1.3,
          54.266667
        ]
      },
      "type": "Feature",
      "properties": {
        "hierarchy": [
          "tgn:7443720",
          "tgn:7002445",
          "tgn:1000003",
          "tgn:7008166",
          "tgn:7008591",
          "tgn:7029392"
        ],
        "placetype": [
          "aat:300008347"
        ],
        "name:en": "Upsall",
        "id": 7443720
      }
    },
    {
      "geometry": {
        "type": "Point",
        "coordinates": [
          -1.766667,
          51.583333
        ]
      },
      "type": "Feature",
      "properties": {
        "hierarchy": [
          "tgn:7443725",
          "tgn:7002445",
          "tgn:1000003",
          "tgn:7026532",
          "tgn:7008591",
          "tgn:7029392"
        ],
        "placetype": [
          "aat:300008347"
        ],
        "name:en": "Upper Stratton",
        "id": 7443725
      }
    },
    {
      "geometry": {
        "type": "Point",
        "coordinates": [
          -1.9,
          52.616667
        ]
      },
      "type": "Feature",
      "properties": {
        "hierarchy": [
          "tgn:7443727",
          "tgn:7002445",
          "tgn:7019031",
          "tgn:1000003",
          "tgn:7029506",
          "tgn:7008591",
          "tgn:7029392"
        ],
        "placetype": [
          "aat:300008347"
        ],
        "name:en": "Upper Stonnall",
        "id": 7443727
      }
    },
    {
      "geometry": {
        "type": "Point",
        "coordinates": [
          -1.433333,
          51.083333
        ]
      },
      "type": "Feature",
      "properties": {
        "hierarchy": [
          "tgn:7443728",
          "tgn:7002445",
          "tgn:1000003",
          "tgn:7008139",
          "tgn:7008591",
          "tgn:7029392"
        ],
        "placetype": [
          "aat:300008347"
        ],
        "name:en": "Upper Somborne",
        "id": 7443728
      }
    }
  ]
}
