{
  "geometry": {
    "type": "Point",
    "coordinates": [
      -44.5667,
      -22.9667
    ]
  },
  "type": "Feature",
  "properties": {
    "hierarchy": [
      "tgn:1124046",
      "tgn:1001945",
      "tgn:1000047",
      "tgn:7002457",
      "tgn:1000002",
      "tgn:7029392"
    ],
    "placetype": [
      "aat:300008707"
    ],
    "id": 1124046,
    "name:xx": "Funil, Rio do"
  }
}
