{
  "type": "FeatureCollection",
  "features": [
    {
      "geometry": {
        "type": "Point",
        "coordinates": [
          -1.666667,
          54.566667
        ]
      },
      "type": "Feature",
      "properties": {
        "hierarchy": [
          "tgn:7454060",
          "tgn:7002445",
          "tgn:1000003",
          "tgn:7026514",
          "tgn:7008591",
          "tgn:7029392"
        ],
        "placetype": [
          "aat:300008347"
        ],
        "name:en": "Denton",
        "id": 7454060
      }
    },
    {
      "geometry": {
        "type": "Point",
        "coordinates": [
          0.066667,
          50.783333
        ]
      },
      "type": "Feature",
      "properties": {
        "hierarchy": [
          "tgn:7454066",
          "tgn:7002445",
          "tgn:1000003",
          "tgn:7008129",
          "tgn:7008591",
          "tgn:7029392"
        ],
        "placetype": [
          "aat:300008347"
        ],
        "name:en": "Denton",
        "id": 7454066
      }
    },
    {
      "geometry": {
        "type": "Point",
        "coordinates": [
          -2.45,
          54.266667
        ]
      },
      "type": "Feature",
      "properties": {
        "hierarchy": [
          "tgn:7454067",
          "tgn:7002445",
          "tgn:1000003",
          "tgn:7008117",
          "tgn:7008591",
          "tgn:7029392"
        ],
        "placetype": [
          "aat:300008347"
        ],
        "name:en": "Dent",
        "id": 7454067
      }
    },
    {
      "geometry": {
        "type": "Point",
        "coordinates": [
          -1.85,
          52.966667
        ]
      },
      "type": "Feature",
      "properties": {
        "hierarchy": [
          "tgn:7454068",
          "tgn:7002445",
          "tgn:1000003",
          "tgn:7008174",
          "tgn:7008591",
          "tgn:7029392"
        ],
        "placetype": [
          "aat:300008347"
        ],
        "name:en": "Denstone",
        "id": 7454068
      }
    },
    {
      "geometry": {
        "type": "Point",
        "coordinates": [
          0.566667,
          52.15
        ]
      },
      "type": "Feature",
      "properties": {
        "hierarchy": [
          "tgn:7454069",
          "tgn:7002445",
          "tgn:1000003",
          "tgn:7008185",
          "tgn:7008591",
          "tgn:7029392"
        ],
        "placetype": [
          "aat:300008347"
        ],
        "name:en": "Denston",
        "id": 7454069
      }
    }
  ]
}
