{
  "geometry": {
    "type": "Point",
    "coordinates": [
      -92.6667,
      34.8167
    ]
  },
  "type": "Feature",
  "properties": {
    "hierarchy": [
      "tgn:1105706",
      "tgn:1000001",
      "tgn:7016172",
      "tgn:7012149",
      "tgn:2000167",
      "tgn:7029392"
    ],
    "placetype": [
      "aat:300008795"
    ],
    "id": 1105706,
    "name:xx": "Moss Mountain"
  }
}
