{
  "type": "FeatureCollection",
  "features": [
    {
      "geometry": {
        "type": "Point",
        "coordinates": [
          3.833333,
          50.85
        ]
      },
      "type": "Feature",
      "properties": {
        "hierarchy": [
          "tgn:7239100",
          "tgn:7003457",
          "tgn:1000003",
          "tgn:1000063",
          "tgn:7018236",
          "tgn:7029392"
        ],
        "placetype": [
          "aat:300008347"
        ],
        "id": 7239100,
        "name:xx": "Groenstraat"
      }
    },
    {
      "geometry": {
        "type": "Point",
        "coordinates": [
          3.3,
          51.35
        ]
      },
      "type": "Feature",
      "properties": {
        "hierarchy": [
          "tgn:7239101",
          "tgn:7003458",
          "tgn:1000003",
          "tgn:1000063",
          "tgn:7018236",
          "tgn:7029392"
        ],
        "placetype": [
          "aat:300008347"
        ],
        "id": 7239101,
        "name:xx": "Groenplein"
      }
    },
    {
      "geometry": {
        "type": "Point",
        "coordinates": [
          5.5,
          51
        ]
      },
      "type": "Feature",
      "properties": {
        "hierarchy": [
          "tgn:7239102",
          "tgn:7003461",
          "tgn:1000003",
          "tgn:1000063",
          "tgn:7018236",
          "tgn:7029392"
        ],
        "placetype": [
          "aat:300008347"
        ],
        "id": 7239102,
        "name:xx": "Hoevenzavel"
      }
    },
    {
      "geometry": {
        "type": "Point",
        "coordinates": [
          4.402035,
          51.306042
        ]
      },
      "type": "Feature",
      "properties": {
        "hierarchy": [
          "tgn:7239103",
          "tgn:7003456",
          "tgn:1000003",
          "tgn:1000063",
          "tgn:7018236",
          "tgn:7029392"
        ],
        "placetype": [
          "aat:300008347"
        ],
        "id": 7239103,
        "name:xx": "Hoevenen"
      }
    },
    {
      "geometry": {
        "type": "Point",
        "coordinates": [
          5.216667,
          50.933333
        ]
      },
      "type": "Feature",
      "properties": {
        "hierarchy": [
          "tgn:7239105",
          "tgn:7003461",
          "tgn:1000003",
          "tgn:1000063",
          "tgn:7018236",
          "tgn:7029392"
        ],
        "placetype": [
          "aat:300008699"
        ],
        "id": 7239105,
        "name:xx": "Hoevenbeek"
      }
    },
    {
      "geometry": {
        "type": "Point",
        "coordinates": [
          5.4,
          51.183333
        ]
      },
      "type": "Feature",
      "properties": {
        "hierarchy": [
          "tgn:7239106",
          "tgn:7003461",
          "tgn:1000003",
          "tgn:1000063",
          "tgn:7018236",
          "tgn:7029392"
        ],
        "placetype": [
          "aat:300008347"
        ],
        "id": 7239106,
        "name:xx": "Hoeven"
      }
    },
    {
      "geometry": {
        "type": "Point",
        "coordinates": [
          4.840328,
          51.216667
        ]
      },
      "type": "Feature",
      "properties": {
        "hierarchy": [
          "tgn:7239107",
          "tgn:7003456",
          "tgn:1000003",
          "tgn:1000063",
          "tgn:7018236",
          "tgn:7029392"
        ],
        "placetype": [
          "aat:300008347"
        ],
        "id": 7239107,
        "name:xx": "Hoeven"
      }
    },
    {
      "geometry": {
        "type": "Point",
        "coordinates": [
          5.1,
          51.083333
        ]
      },
      "type": "Feature",
      "properties": {
        "hierarchy": [
          "tgn:7239109",
          "tgn:7003461",
          "tgn:1000003",
          "tgn:1000063",
          "tgn:7018236",
          "tgn:7029392"
        ],
        "placetype": [
          "aat:300008347"
        ],
        "id": 7239109,
        "name:xx": "Hoeven"
      }
    }
  ]
}
