{
  "type": "FeatureCollection",
  "features": [
    {
      "geometry": {
        "type": "Point",
        "coordinates": [
          -111.1667,
          39.9833
        ]
      },
      "type": "Feature",
      "properties": {
        "hierarchy": [
          "tgn:2529210",
          "tgn:1000001",
          "tgn:7012149",
          "tgn:2002125",
          "tgn:7007827",
          "tgn:7029392"
        ],
        "placetype": [
          "aat:300008761"
        ],
        "id": 2529210,
        "name:xx": "Mud Hollow"
      }
    },
    {
      "geometry": {
        "type": "Point",
        "coordinates": [
          -71.9333,
          44.4833
        ]
      },
      "type": "Feature",
      "properties": {
        "hierarchy": [
          "tgn:2529211",
          "tgn:2002131",
          "tgn:1000001",
          "tgn:7012149",
          "tgn:7007828",
          "tgn:7029392"
        ],
        "placetype": [
          "aat:300008761"
        ],
        "id": 2529211,
        "name:xx": "Mud Hollow"
      }
    },
    {
      "geometry": {
        "type": "Point",
        "coordinates": [
          -82.0667,
          36.6
        ]
      },
      "type": "Feature",
      "properties": {
        "hierarchy": [
          "tgn:2529212",
          "tgn:1000001",
          "tgn:7012149",
          "tgn:2002194",
          "tgn:7007919",
          "tgn:7029392"
        ],
        "placetype": [
          "aat:300008761"
        ],
        "id": 2529212,
        "name:xx": "Mud Hollow"
      }
    },
    {
      "geometry": {
        "type": "Point",
        "coordinates": [
          -110.85,
          42.6667
        ]
      },
      "type": "Feature",
      "properties": {
        "hierarchy": [
          "tgn:2529213",
          "tgn:1000001",
          "tgn:7012149",
          "tgn:2002376",
          "tgn:7007923",
          "tgn:7029392"
        ],
        "placetype": [
          "aat:300008761"
        ],
        "id": 2529213,
        "name:xx": "Mud Hollow"
      }
    },
    {
      "geometry": {
        "type": "Point",
        "coordinates": [
          -73.2,
          44.2833
        ]
      },
      "type": "Feature",
      "properties": {
        "hierarchy": [
          "tgn:2529214",
          "tgn:1000001",
          "tgn:2002132",
          "tgn:7012149",
          "tgn:7007828",
          "tgn:7029392"
        ],
        "placetype": [
          "aat:300008699"
        ],
        "id": 2529214,
        "name:xx": "Mud Hollow Brook"
      }
    },
    {
      "geometry": {
        "type": "Point",
        "coordinates": [
          -109.8333,
          32.85
        ]
      },
      "type": "Feature",
      "properties": {
        "hierarchy": [
          "tgn:2529215",
          "tgn:1000001",
          "tgn:7006451",
          "tgn:2000094",
          "tgn:7012149",
          "tgn:7029392"
        ],
        "placetype": [
          "aat:300006191"
        ],
        "id": 2529215,
        "name:xx": "Mud Hollow Tank"
      }
    },
    {
      "geometry": {
        "type": "Point",
        "coordinates": [
          -86.2833,
          32.4667
        ]
      },
      "type": "Feature",
      "properties": {
        "hierarchy": [
          "tgn:2529216",
          "tgn:7002659",
          "tgn:1000001",
          "tgn:7012149",
          "tgn:2000025",
          "tgn:7029392"
        ],
        "placetype": [
          "aat:300008791"
        ],
        "id": 2529216,
        "name:xx": "Mud Island"
      }
    },
    {
      "geometry": {
        "type": "Point",
        "coordinates": [
          -91.0333,
          33.6833
        ]
      },
      "type": "Feature",
      "properties": {
        "hierarchy": [
          "tgn:2529217",
          "tgn:1000001",
          "tgn:7016172",
          "tgn:7012149",
          "tgn:2000125",
          "tgn:7029392"
        ],
        "placetype": [
          "aat:300008791"
        ],
        "id": 2529217,
        "name:xx": "Mud Island"
      }
    },
    {
      "geometry": {
        "type": "Point",
        "coordinates": [
          -80.95,
          31.9667
        ]
      },
      "type": "Feature",
      "properties": {
        "hierarchy": [
          "tgn:2529218",
          "tgn:1000001",
          "tgn:2000316",
          "tgn:7012149",
          "tgn:7007248",
          "tgn:7029392"
        ],
        "placetype": [
          "aat:300008791"
        ],
        "id": 2529218,
        "name:xx": "Mud Island"
      }
    },
    {
      "geometry": {
        "type": "Point",
        "coordinates": [
          -91.4833,
          40.1833
        ]
      },
      "type": "Feature",
      "properties": {
        "hierarchy": [
          "tgn:2529219",
          "tgn:1002134",
          "tgn:1000001",
          "tgn:7012149",
          "tgn:7007251",
          "tgn:7029392"
        ],
        "placetype": [
          "aat:300008791"
        ],
        "id": 2529219,
        "name:xx": "Mud Island"
      }
    }
  ]
}
