{
  "geometry": {
    "type": "Point",
    "coordinates": [
      115.4833,
      33.85
    ]
  },
  "type": "Feature",
  "properties": {
    "hierarchy": [
      "tgn:1070250",
      "tgn:1000004",
      "tgn:7016672",
      "tgn:1000111",
      "tgn:7029392"
    ],
    "placetype": [
      "aat:300008347"
    ],
    "id": 1070250,
    "name:xx": "Luyi"
  }
}
