{
  "geometry": {
    "type": "Point",
    "coordinates": [
      -114.85,
      44.35
    ]
  },
  "type": "Feature",
  "properties": {
    "hierarchy": [
      "tgn:2299958",
      "tgn:1000001",
      "tgn:2000470",
      "tgn:7012149",
      "tgn:7007250",
      "tgn:7029392"
    ],
    "placetype": [
      "aat:300008706"
    ],
    "id": 2299958,
    "name:xx": "Duffy Creek"
  }
}
