{
  "geometry": {
    "type": "Point",
    "coordinates": [
      27.271,
      59.398
    ]
  },
  "type": "Feature",
  "properties": {
    "hierarchy": [
      "tgn:1055464",
      "tgn:7006633",
      "tgn:1000003",
      "tgn:7006540",
      "tgn:7029392"
    ],
    "placetype": [
      "aat:300008347",
      "aat:300008389",
      "aat:300387270",
      "aat:300387302"
    ],
    "id": 1055464,
    "name:xx": "Kohtla-Järve"
  }
}
