{
  "geometry": {
    "type": "Point",
    "coordinates": [
      -86.3833,
      31.3667
    ]
  },
  "type": "Feature",
  "properties": {
    "hierarchy": [
      "tgn:2605070",
      "tgn:7002659",
      "tgn:1000001",
      "tgn:2000019",
      "tgn:7012149",
      "tgn:7029392"
    ],
    "placetype": [
      "aat:300006191"
    ],
    "id": 2605070,
    "name:xx": "Radford Ponds"
  }
}
