{
  "geometry": {
    "type": "Point",
    "coordinates": [
      -72.0333,
      42.0667
    ]
  },
  "type": "Feature",
  "properties": {
    "hierarchy": [
      "tgn:2050617",
      "tgn:1000001",
      "tgn:7012149",
      "tgn:1003038",
      "tgn:7007517",
      "tgn:7029392"
    ],
    "placetype": [
      "aat:300008347"
    ],
    "id": 2050617,
    "name:xx": "Southbridge"
  }
}
