{
  "geometry": {
    "type": "Point",
    "coordinates": [
      121.95,
      10.4667
    ]
  },
  "type": "Feature",
  "properties": {
    "hierarchy": [
      "tgn:1084169",
      "tgn:1001104",
      "tgn:1000004",
      "tgn:1000135",
      "tgn:7029392"
    ],
    "placetype": [
      "aat:300008347"
    ],
    "id": 1084169,
    "name:xx": "Dao"
  }
}
