{
  "geometry": {
    "type": "Point",
    "coordinates": [
      77.603695,
      23.192808
    ]
  },
  "type": "Feature",
  "properties": {
    "hierarchy": [
      "tgn:7579513",
      "tgn:1000004",
      "tgn:7000198",
      "tgn:1001894",
      "tgn:7029392"
    ],
    "placetype": [
      "aat:300008347"
    ],
    "name:en": "Umrāoganj",
    "id": 7579513
  }
}
