{
  "geometry": {
    "type": "Point",
    "coordinates": [
      116.7167,
      39.15
    ]
  },
  "type": "Feature",
  "properties": {
    "hierarchy": [
      "tgn:1072103",
      "tgn:1000004",
      "tgn:7002077",
      "tgn:1000111",
      "tgn:7029392"
    ],
    "placetype": [
      "aat:300008347"
    ],
    "id": 1072103,
    "name:xx": "Tang'erli"
  }
}
