{
  "type": "FeatureCollection",
  "features": [
    {
      "geometry": {
        "type": "Point",
        "coordinates": [
          -90.8667,
          33.55
        ]
      },
      "type": "Feature",
      "properties": {
        "hierarchy": [
          "tgn:2672830",
          "tgn:1000001",
          "tgn:2001091",
          "tgn:7012149",
          "tgn:7007522",
          "tgn:7029392"
        ],
        "placetype": [
          "aat:300008699"
        ],
        "id": 2672830,
        "name:xx": "Snake Bayou"
      }
    },
    {
      "geometry": {
        "type": "Point",
        "coordinates": [
          -80.8667,
          25.1833
        ]
      },
      "type": "Feature",
      "properties": {
        "hierarchy": [
          "tgn:2672831",
          "tgn:1000001",
          "tgn:7012149",
          "tgn:1002676",
          "tgn:7007240",
          "tgn:7029392"
        ],
        "placetype": [
          "aat:300006075"
        ],
        "id": 2672831,
        "name:xx": "Snake Bight Canal"
      }
    },
    {
      "geometry": {
        "type": "Point",
        "coordinates": [
          -69.15,
          46.2833
        ]
      },
      "type": "Feature",
      "properties": {
        "hierarchy": [
          "tgn:2672832",
          "tgn:1000001",
          "tgn:7012149",
          "tgn:2000928",
          "tgn:7007515",
          "tgn:7029392"
        ],
        "placetype": [
          "aat:300008905"
        ],
        "id": 2672832,
        "name:xx": "Snake Bog"
      }
    },
    {
      "geometry": {
        "type": "Point",
        "coordinates": [
          -86.0667,
          31.15
        ]
      },
      "type": "Feature",
      "properties": {
        "hierarchy": [
          "tgn:2672833",
          "tgn:7002659",
          "tgn:1000001",
          "tgn:7012149",
          "tgn:2000030",
          "tgn:7029392"
        ],
        "placetype": [
          "aat:300008699"
        ],
        "id": 2672833,
        "name:xx": "Snake Branch"
      }
    },
    {
      "geometry": {
        "type": "Point",
        "coordinates": [
          -93.3667,
          35.1667
        ]
      },
      "type": "Feature",
      "properties": {
        "hierarchy": [
          "tgn:2672834",
          "tgn:1000001",
          "tgn:7016172",
          "tgn:7012149",
          "tgn:2000179",
          "tgn:7029392"
        ],
        "placetype": [
          "aat:300008699"
        ],
        "id": 2672834,
        "name:xx": "Snake Branch"
      }
    },
    {
      "geometry": {
        "type": "Point",
        "coordinates": [
          -83.65,
          34.7667
        ]
      },
      "type": "Feature",
      "properties": {
        "hierarchy": [
          "tgn:2672835",
          "tgn:1000001",
          "tgn:7012149",
          "tgn:2000445",
          "tgn:7007248",
          "tgn:7029392"
        ],
        "placetype": [
          "aat:300008699"
        ],
        "id": 2672835,
        "name:xx": "Snake Branch"
      }
    },
    {
      "geometry": {
        "type": "Point",
        "coordinates": [
          -86.6,
          38.1
        ]
      },
      "type": "Feature",
      "properties": {
        "hierarchy": [
          "tgn:2672836",
          "tgn:1000001",
          "tgn:7012149",
          "tgn:2000550",
          "tgn:7007252",
          "tgn:7029392"
        ],
        "placetype": [
          "aat:300008699"
        ],
        "id": 2672836,
        "name:xx": "Snake Branch"
      }
    },
    {
      "geometry": {
        "type": "Point",
        "coordinates": [
          -85.4667,
          37.1333
        ]
      },
      "type": "Feature",
      "properties": {
        "hierarchy": [
          "tgn:2672837",
          "tgn:1000001",
          "tgn:7012149",
          "tgn:2000794",
          "tgn:7007255",
          "tgn:7029392"
        ],
        "placetype": [
          "aat:300008699"
        ],
        "id": 2672837,
        "name:xx": "Snake Branch"
      }
    },
    {
      "geometry": {
        "type": "Point",
        "coordinates": [
          -82.45,
          37.35
        ]
      },
      "type": "Feature",
      "properties": {
        "hierarchy": [
          "tgn:2672838",
          "tgn:1000001",
          "tgn:7012149",
          "tgn:2000837",
          "tgn:7007255",
          "tgn:7029392"
        ],
        "placetype": [
          "aat:300008699"
        ],
        "id": 2672838,
        "name:xx": "Snake Branch"
      }
    },
    {
      "geometry": {
        "type": "Point",
        "coordinates": [
          -83.5167,
          37.4833
        ]
      },
      "type": "Feature",
      "properties": {
        "hierarchy": [
          "tgn:2672839",
          "tgn:1000001",
          "tgn:2000772",
          "tgn:7012149",
          "tgn:7007255",
          "tgn:7029392"
        ],
        "placetype": [
          "aat:300008699"
        ],
        "id": 2672839,
        "name:xx": "Snake Branch"
      }
    }
  ]
}
