{
  "type": "FeatureCollection",
  "features": [
    {
      "geometry": {
        "type": "Point",
        "coordinates": [
          -94.4333,
          29.8333
        ]
      },
      "type": "Feature",
      "properties": {
        "hierarchy": [
          "tgn:2633760",
          "tgn:1000001",
          "tgn:7012149",
          "tgn:1002456",
          "tgn:7007826",
          "tgn:7029392"
        ],
        "placetype": [
          "aat:300006075"
        ],
        "id": 2633760,
        "name:xx": "Rush Ditch"
      }
    },
    {
      "geometry": {
        "type": "Point",
        "coordinates": [
          -82.9667,
          43.7167
        ]
      },
      "type": "Feature",
      "properties": {
        "hierarchy": [
          "tgn:2633761",
          "tgn:1000001",
          "tgn:7012149",
          "tgn:2000964",
          "tgn:7007520",
          "tgn:7029392"
        ],
        "placetype": [
          "aat:300006075"
        ],
        "id": 2633761,
        "name:xx": "Rush Drain"
      }
    },
    {
      "geometry": {
        "type": "Point",
        "coordinates": [
          -93.2,
          34.3667
        ]
      },
      "type": "Feature",
      "properties": {
        "hierarchy": [
          "tgn:2633762",
          "tgn:1000001",
          "tgn:7016172",
          "tgn:7012149",
          "tgn:7029392"
        ],
        "placetype": [
          "aat:300008699"
        ],
        "id": 2633762,
        "name:xx": "Rush Fork"
      }
    },
    {
      "geometry": {
        "type": "Point",
        "coordinates": [
          -82.8167,
          37.8667
        ]
      },
      "type": "Feature",
      "properties": {
        "hierarchy": [
          "tgn:2633763",
          "tgn:1000001",
          "tgn:7012149",
          "tgn:2000804",
          "tgn:7007255",
          "tgn:7029392"
        ],
        "placetype": [
          "aat:300008699"
        ],
        "id": 2633763,
        "name:xx": "Rush Fork"
      }
    },
    {
      "geometry": {
        "type": "Point",
        "coordinates": [
          -82.65,
          37.9
        ]
      },
      "type": "Feature",
      "properties": {
        "hierarchy": [
          "tgn:2633764",
          "tgn:1000001",
          "tgn:7012149",
          "tgn:2000809",
          "tgn:7007255",
          "tgn:7029392"
        ],
        "placetype": [
          "aat:300008699"
        ],
        "id": 2633764,
        "name:xx": "Rush Fork"
      }
    },
    {
      "geometry": {
        "type": "Point",
        "coordinates": [
          -83.3667,
          37.6833
        ]
      },
      "type": "Feature",
      "properties": {
        "hierarchy": [
          "tgn:2633765",
          "tgn:1000001",
          "tgn:7012149",
          "tgn:2000853",
          "tgn:7007255",
          "tgn:7029392"
        ],
        "placetype": [
          "aat:300008699"
        ],
        "id": 2633765,
        "name:xx": "Rush Fork"
      }
    },
    {
      "geometry": {
        "type": "Point",
        "coordinates": [
          -82.9167,
          35.6333
        ]
      },
      "type": "Feature",
      "properties": {
        "hierarchy": [
          "tgn:2633766",
          "tgn:1000001",
          "tgn:7012149",
          "tgn:2001503",
          "tgn:7007709",
          "tgn:7029392"
        ],
        "placetype": [
          "aat:300008699"
        ],
        "id": 2633766,
        "name:xx": "Rush Fork"
      }
    },
    {
      "geometry": {
        "type": "Point",
        "coordinates": [
          -85.6333,
          36.2167
        ]
      },
      "type": "Feature",
      "properties": {
        "hierarchy": [
          "tgn:2633767",
          "tgn:1000001",
          "tgn:7012149",
          "tgn:2001880",
          "tgn:7007825",
          "tgn:7029392"
        ],
        "placetype": [
          "aat:300008699"
        ],
        "id": 2633767,
        "name:xx": "Rush Fork"
      }
    },
    {
      "geometry": {
        "type": "Point",
        "coordinates": [
          -80.4167,
          36.8167
        ]
      },
      "type": "Feature",
      "properties": {
        "hierarchy": [
          "tgn:2633768",
          "tgn:1000001",
          "tgn:7012149",
          "tgn:2002158",
          "tgn:7007919",
          "tgn:7029392"
        ],
        "placetype": [
          "aat:300008699"
        ],
        "id": 2633768,
        "name:xx": "Rush Fork"
      }
    },
    {
      "geometry": {
        "type": "Point",
        "coordinates": [
          -81.0833,
          38.5667
        ]
      },
      "type": "Feature",
      "properties": {
        "hierarchy": [
          "tgn:2633769",
          "tgn:1000001",
          "tgn:2002259",
          "tgn:7012149",
          "tgn:7013961",
          "tgn:7029392"
        ],
        "placetype": [
          "aat:300008699"
        ],
        "id": 2633769,
        "name:xx": "Rush Fork"
      }
    }
  ]
}
