{
  "geometry": {
    "type": "Point",
    "coordinates": [
      22.7833,
      -19.5833
    ]
  },
  "type": "Feature",
  "properties": {
    "hierarchy": [
      "tgn:1088103",
      "tgn:7001242",
      "tgn:1000905",
      "tgn:1000150",
      "tgn:7029392"
    ],
    "placetype": [
      "aat:300008347"
    ],
    "id": 1088103,
    "name:xx": "Ranwanalenaus"
  }
}
