{
  "type": "FeatureCollection",
  "features": [
    {
      "geometry": {
        "type": "Point",
        "coordinates": [
          -114.5,
          45.2333
        ]
      },
      "type": "Feature",
      "properties": {
        "hierarchy": [
          "tgn:2344730",
          "tgn:1000001",
          "tgn:7012149",
          "tgn:2000481",
          "tgn:7007250",
          "tgn:7029392"
        ],
        "placetype": [
          "aat:300008706"
        ],
        "id": 2344730,
        "name:xx": "Garden Creek"
      }
    },
    {
      "geometry": {
        "type": "Point",
        "coordinates": [
          -92.3167,
          32.05
        ]
      },
      "type": "Feature",
      "properties": {
        "hierarchy": [
          "tgn:2344731",
          "tgn:1000001",
          "tgn:7012149",
          "tgn:7007256",
          "tgn:7029392"
        ],
        "placetype": [
          "aat:300008706"
        ],
        "id": 2344731,
        "name:xx": "Garden Creek"
      }
    },
    {
      "geometry": {
        "type": "Point",
        "coordinates": [
          -86.5,
          45.7833
        ]
      },
      "type": "Feature",
      "properties": {
        "hierarchy": [
          "tgn:2344732",
          "tgn:1000001",
          "tgn:2000955",
          "tgn:7012149",
          "tgn:7007520",
          "tgn:7029392"
        ],
        "placetype": [
          "aat:300008706"
        ],
        "id": 2344732,
        "name:xx": "Garden Creek"
      }
    },
    {
      "geometry": {
        "type": "Point",
        "coordinates": [
          -111.2333,
          46.5833
        ]
      },
      "type": "Feature",
      "properties": {
        "hierarchy": [
          "tgn:2344733",
          "tgn:1000001",
          "tgn:7012149",
          "tgn:2001289",
          "tgn:7007524",
          "tgn:7029392"
        ],
        "placetype": [
          "aat:300008706"
        ],
        "id": 2344733,
        "name:xx": "Garden Creek"
      }
    },
    {
      "geometry": {
        "type": "Point",
        "coordinates": [
          -114.4667,
          46.85
        ]
      },
      "type": "Feature",
      "properties": {
        "hierarchy": [
          "tgn:2344734",
          "tgn:1000001",
          "tgn:7012149",
          "tgn:2001291",
          "tgn:7007524",
          "tgn:7029392"
        ],
        "placetype": [
          "aat:300008706"
        ],
        "id": 2344734,
        "name:xx": "Garden Creek"
      }
    },
    {
      "geometry": {
        "type": "Point",
        "coordinates": [
          -112.2333,
          45.2667
        ]
      },
      "type": "Feature",
      "properties": {
        "hierarchy": [
          "tgn:2344735",
          "tgn:1000001",
          "tgn:7012149",
          "tgn:2001288",
          "tgn:7007524",
          "tgn:7029392"
        ],
        "placetype": [
          "aat:300008706"
        ],
        "id": 2344735,
        "name:xx": "Garden Creek"
      }
    },
    {
      "geometry": {
        "type": "Point",
        "coordinates": [
          -106.0667,
          45.85
        ]
      },
      "type": "Feature",
      "properties": {
        "hierarchy": [
          "tgn:2344736",
          "tgn:1000001",
          "tgn:7012149",
          "tgn:7007524",
          "tgn:7029392"
        ],
        "placetype": [
          "aat:300008706"
        ],
        "id": 2344736,
        "name:xx": "Garden Creek"
      }
    },
    {
      "geometry": {
        "type": "Point",
        "coordinates": [
          -114.75,
          47.65
        ]
      },
      "type": "Feature",
      "properties": {
        "hierarchy": [
          "tgn:2344737",
          "tgn:1000001",
          "tgn:7012149",
          "tgn:2001304",
          "tgn:7007524",
          "tgn:7029392"
        ],
        "placetype": [
          "aat:300008706"
        ],
        "id": 2344737,
        "name:xx": "Garden Creek"
      }
    },
    {
      "geometry": {
        "type": "Point",
        "coordinates": [
          -99.95,
          42.75
        ]
      },
      "type": "Feature",
      "properties": {
        "hierarchy": [
          "tgn:2344738",
          "tgn:1000001",
          "tgn:2001324",
          "tgn:7012149",
          "tgn:7007525",
          "tgn:7029392"
        ],
        "placetype": [
          "aat:300008706"
        ],
        "id": 2344738,
        "name:xx": "Garden Creek"
      }
    },
    {
      "geometry": {
        "type": "Point",
        "coordinates": [
          -114.5667,
          39.45
        ]
      },
      "type": "Feature",
      "properties": {
        "hierarchy": [
          "tgn:2344739",
          "tgn:1000001",
          "tgn:7012149",
          "tgn:2001420",
          "tgn:7007526",
          "tgn:7029392"
        ],
        "placetype": [
          "aat:300008706"
        ],
        "id": 2344739,
        "name:xx": "Garden Creek"
      }
    }
  ]
}
