{
  "geometry": {
    "type": "Point",
    "coordinates": [
      -88.1333,
      45.8667
    ]
  },
  "type": "Feature",
  "properties": {
    "hierarchy": [
      "tgn:2122433",
      "tgn:1000001",
      "tgn:2002321",
      "tgn:7012149",
      "tgn:7007922",
      "tgn:7029392"
    ],
    "placetype": [
      "aat:300008347"
    ],
    "id": 2122433,
    "name:xx": "Spread Eagle"
  }
}
