{
  "type": "FeatureCollection",
  "features": [
    {
      "geometry": {
        "type": "Point",
        "coordinates": [
          5.816667,
          51.133333
        ]
      },
      "type": "Feature",
      "properties": {
        "hierarchy": [
          "tgn:7273770",
          "tgn:1000003",
          "tgn:7003622",
          "tgn:7016845",
          "tgn:7029392"
        ],
        "placetype": [
          "aat:300008057"
        ],
        "name:nl": "Walborg",
        "id": 7273770
      }
    },
    {
      "geometry": {
        "type": "Point",
        "coordinates": [
          6.2,
          51.516667
        ]
      },
      "type": "Feature",
      "properties": {
        "hierarchy": [
          "tgn:7273771",
          "tgn:1000003",
          "tgn:7003622",
          "tgn:7016845",
          "tgn:7029392"
        ],
        "placetype": [
          "aat:300386887"
        ],
        "name:nl": "Walbeckheide",
        "id": 7273771
      }
    },
    {
      "geometry": {
        "type": "Point",
        "coordinates": [
          5.883333,
          52.483333
        ]
      },
      "type": "Feature",
      "properties": {
        "hierarchy": [
          "tgn:7273772",
          "tgn:7003619",
          "tgn:1000003",
          "tgn:7016845",
          "tgn:7029392"
        ],
        "placetype": [
          "aat:300008688"
        ],
        "name:nl": "Wakolk",
        "id": 7273772
      }
    },
    {
      "geometry": {
        "type": "Point",
        "coordinates": [
          6.016667,
          51.266667
        ]
      },
      "type": "Feature",
      "properties": {
        "hierarchy": [
          "tgn:7273773",
          "tgn:1000003",
          "tgn:7003622",
          "tgn:7016845",
          "tgn:7029392"
        ],
        "placetype": [
          "aat:300008347"
        ],
        "name:nl": "Waije",
        "id": 7273773
      }
    },
    {
      "geometry": {
        "type": "Point",
        "coordinates": [
          6.016667,
          51.883333
        ]
      },
      "type": "Feature",
      "properties": {
        "hierarchy": [
          "tgn:7273774",
          "tgn:7003619",
          "tgn:1000003",
          "tgn:7016845",
          "tgn:7029392"
        ],
        "placetype": [
          "aat:300000206"
        ],
        "name:nl": "Waiboerhoeve",
        "id": 7273774
      }
    },
    {
      "geometry": {
        "type": "Point",
        "coordinates": [
          5.2,
          52.8
        ]
      },
      "type": "Feature",
      "properties": {
        "hierarchy": [
          "tgn:7273776",
          "tgn:1000003",
          "tgn:7006951",
          "tgn:7016845",
          "tgn:7029392"
        ],
        "placetype": [
          "aat:300387036"
        ],
        "name:nl": "Wagenpad",
        "id": 7273776
      }
    },
    {
      "geometry": {
        "type": "Point",
        "coordinates": [
          5.7,
          51.966667
        ]
      },
      "type": "Feature",
      "properties": {
        "hierarchy": [
          "tgn:7273777",
          "tgn:7003619",
          "tgn:1000003",
          "tgn:7016845",
          "tgn:7029392"
        ],
        "placetype": [
          "aat:300008777"
        ],
        "name:nl": "Wageningsche Berg",
        "id": 7273777
      }
    },
    {
      "geometry": {
        "type": "Point",
        "coordinates": [
          5.7,
          51.983333
        ]
      },
      "type": "Feature",
      "properties": {
        "hierarchy": [
          "tgn:7273778",
          "tgn:7003619",
          "tgn:1000003",
          "tgn:7016845",
          "tgn:7029392"
        ],
        "placetype": [
          "aat:300008347"
        ],
        "name:nl": "Wageningen-Hoog",
        "id": 7273778
      }
    }
  ]
}
