{
  "geometry": {
    "type": "Point",
    "coordinates": [
      -75.7833,
      41.7667
    ]
  },
  "type": "Feature",
  "properties": {
    "hierarchy": [
      "tgn:2296999",
      "tgn:1000001",
      "tgn:7012149",
      "tgn:1002932",
      "tgn:7007710",
      "tgn:7029392"
    ],
    "placetype": [
      "aat:300008706"
    ],
    "id": 2296999,
    "name:xx": "Dry Creek"
  }
}
