{
  "geometry": {
    "type": "Point",
    "coordinates": [
      -84.7833,
      37.35
    ]
  },
  "type": "Feature",
  "properties": {
    "hierarchy": [
      "tgn:2392472",
      "tgn:1000001",
      "tgn:2000779",
      "tgn:7012149",
      "tgn:7007255",
      "tgn:7029392"
    ],
    "placetype": [
      "aat:300008706"
    ],
    "id": 2392472,
    "name:xx": "Hites Creek"
  }
}
