{
  "geometry": {
    "type": "Point",
    "coordinates": [
      -119.7667,
      38.6167
    ]
  },
  "type": "Feature",
  "properties": {
    "hierarchy": [
      "tgn:2410642",
      "tgn:1002145",
      "tgn:1000001",
      "tgn:7012149",
      "tgn:7007157",
      "tgn:7029392"
    ],
    "placetype": [
      "aat:300008706"
    ],
    "id": 2410642,
    "name:xx": "Indian Creek"
  }
}
