{
  "type": "FeatureCollection",
  "features": [
    {
      "geometry": {
        "type": "Point",
        "coordinates": [
          -81.3,
          39.15
        ]
      },
      "type": "Feature",
      "properties": {
        "hierarchy": [
          "tgn:2338270",
          "tgn:1000001",
          "tgn:7012149",
          "tgn:7013961",
          "tgn:7029392"
        ],
        "placetype": [
          "aat:300008699"
        ],
        "id": 2338270,
        "name:xx": "Fox Run"
      }
    },
    {
      "geometry": {
        "type": "Point",
        "coordinates": [
          -79.7333,
          38.6833
        ]
      },
      "type": "Feature",
      "properties": {
        "hierarchy": [
          "tgn:2338271",
          "tgn:1000001",
          "tgn:7012149",
          "tgn:2002287",
          "tgn:7013961",
          "tgn:7029392"
        ],
        "placetype": [
          "aat:300008699"
        ],
        "id": 2338271,
        "name:xx": "Fox Run"
      }
    },
    {
      "geometry": {
        "type": "Point",
        "coordinates": [
          -78.7833,
          39.35
        ]
      },
      "type": "Feature",
      "properties": {
        "hierarchy": [
          "tgn:2338272",
          "tgn:1000001",
          "tgn:7012149",
          "tgn:2002265",
          "tgn:7013961",
          "tgn:7029392"
        ],
        "placetype": [
          "aat:300008699"
        ],
        "id": 2338272,
        "name:xx": "Fox Run"
      }
    },
    {
      "geometry": {
        "type": "Point",
        "coordinates": [
          -88.4167,
          33.5333
        ]
      },
      "type": "Feature",
      "properties": {
        "hierarchy": [
          "tgn:2338273",
          "tgn:1000001",
          "tgn:7012149",
          "tgn:2001129",
          "tgn:7007522",
          "tgn:7029392"
        ],
        "placetype": [
          "aat:300008347"
        ],
        "id": 2338273,
        "name:xx": "Fox Run Colony"
      }
    },
    {
      "geometry": {
        "type": "Point",
        "coordinates": [
          -112,
          40.7
        ]
      },
      "type": "Feature",
      "properties": {
        "hierarchy": [
          "tgn:2338274",
          "tgn:1000001",
          "tgn:7012149",
          "tgn:2002118",
          "tgn:7007827",
          "tgn:7029392"
        ],
        "placetype": [
          "aat:300008347"
        ],
        "id": 2338274,
        "name:xx": "Fox Shadow"
      }
    },
    {
      "geometry": {
        "type": "Point",
        "coordinates": [
          -147.6167,
          64.95
        ]
      },
      "type": "Feature",
      "properties": {
        "hierarchy": [
          "tgn:2338276",
          "tgn:7006450",
          "tgn:1000001",
          "tgn:7019674",
          "tgn:7012149",
          "tgn:7029392"
        ],
        "placetype": [
          "aat:300008697"
        ],
        "id": 2338276,
        "name:xx": "Fox Spring"
      }
    },
    {
      "geometry": {
        "type": "Point",
        "coordinates": [
          -110.45,
          33.95
        ]
      },
      "type": "Feature",
      "properties": {
        "hierarchy": [
          "tgn:2338277",
          "tgn:1000001",
          "tgn:7006451",
          "tgn:2000093",
          "tgn:7012149",
          "tgn:7029392"
        ],
        "placetype": [
          "aat:300008697"
        ],
        "id": 2338277,
        "name:xx": "Fox Spring"
      }
    },
    {
      "geometry": {
        "type": "Point",
        "coordinates": [
          -119.0667,
          36.7667
        ]
      },
      "type": "Feature",
      "properties": {
        "hierarchy": [
          "tgn:2338278",
          "tgn:1000001",
          "tgn:7012149",
          "tgn:1002392",
          "tgn:7007157",
          "tgn:7029392"
        ],
        "placetype": [
          "aat:300008697"
        ],
        "id": 2338278,
        "name:xx": "Fox Spring"
      }
    },
    {
      "geometry": {
        "type": "Point",
        "coordinates": [
          -124.0667,
          40.15
        ]
      },
      "type": "Feature",
      "properties": {
        "hierarchy": [
          "tgn:2338279",
          "tgn:1000001",
          "tgn:7012149",
          "tgn:2000181",
          "tgn:7007157",
          "tgn:7029392"
        ],
        "placetype": [
          "aat:300008697"
        ],
        "id": 2338279,
        "name:xx": "Fox Spring"
      }
    }
  ]
}
