{
  "geometry": {
    "type": "Point",
    "coordinates": [
      -112.7167,
      34.0167
    ]
  },
  "type": "Feature",
  "properties": {
    "hierarchy": [
      "tgn:2560923",
      "tgn:1000001",
      "tgn:7006451",
      "tgn:7012149",
      "tgn:2000103",
      "tgn:7029392"
    ],
    "placetype": [
      "aat:300000390"
    ],
    "id": 2560923,
    "name:xx": "Oro Grande Mine"
  }
}
