{
  "type": "FeatureCollection",
  "features": [
    {
      "geometry": {
        "type": "Point",
        "coordinates": [
          -1.266667,
          53.7
        ]
      },
      "type": "Feature",
      "properties": {
        "hierarchy": [
          "tgn:4003890",
          "tgn:7002445",
          "tgn:7019040",
          "tgn:1000003",
          "tgn:7029507",
          "tgn:7008591",
          "tgn:7029392"
        ],
        "placetype": [
          "aat:300008347",
          "aat:300008372"
        ],
        "name:en": "Ferrybridge",
        "id": 4003890
      }
    },
    {
      "geometry": {
        "type": "Point",
        "coordinates": [
          1.033333,
          52.4
        ]
      },
      "type": "Feature",
      "properties": {
        "hierarchy": [
          "tgn:4003891",
          "tgn:7002445",
          "tgn:1000003",
          "tgn:7008160",
          "tgn:7008591",
          "tgn:7029392"
        ],
        "placetype": [
          "aat:300008347",
          "aat:300008372"
        ],
        "id": 4003891,
        "name:xx": "Fersfield"
      }
    },
    {
      "geometry": {
        "type": "Point",
        "coordinates": [
          16.9167,
          47.5833
        ]
      },
      "type": "Feature",
      "properties": {
        "hierarchy": [
          "tgn:4003893",
          "tgn:7006350",
          "tgn:1000003",
          "tgn:7006278",
          "tgn:7029392"
        ],
        "placetype": [
          "aat:300008347"
        ],
        "id": 4003893,
        "name:xx": "Fertőszentmiklós"
      }
    },
    {
      "geometry": {
        "type": "Point",
        "coordinates": [
          5.833333,
          53.333333
        ]
      },
      "type": "Feature",
      "properties": {
        "hierarchy": [
          "tgn:4003894",
          "tgn:7003616",
          "tgn:1000003",
          "tgn:7016845",
          "tgn:7029392"
        ],
        "placetype": [
          "aat:300008347"
        ],
        "name:nl": "Ferwerd",
        "id": 4003894
      }
    }
  ]
}
