{
  "geometry": {
    "type": "Point",
    "coordinates": [
      31.183333,
      31.116667
    ]
  },
  "type": "Feature",
  "properties": {
    "hierarchy": [
      "tgn:7538700",
      "tgn:7001242",
      "tgn:7016833",
      "tgn:7001312",
      "tgn:7029392"
    ],
    "placetype": [
      "aat:300000745"
    ],
    "name:en": "Nişf Thānī Bashbīsh",
    "id": 7538700
  }
}
