{
  "type": "FeatureCollection",
  "features": [
    {
      "geometry": {
        "type": "Point",
        "coordinates": [
          12.583333,
          52.283333
        ]
      },
      "type": "Feature",
      "properties": {
        "hierarchy": [
          "tgn:7144120",
          "tgn:7000096",
          "tgn:1000003",
          "tgn:7000084",
          "tgn:7029392"
        ],
        "placetype": [
          "aat:300008347"
        ],
        "id": 7144120,
        "name:xx": "Königsberg"
      }
    },
    {
      "geometry": {
        "type": "Point",
        "coordinates": [
          8.866667,
          52.25
        ]
      },
      "type": "Feature",
      "properties": {
        "hierarchy": [
          "tgn:7144121",
          "tgn:1000003",
          "tgn:7003677",
          "tgn:7000084",
          "tgn:7029392"
        ],
        "placetype": [
          "aat:300008347"
        ],
        "id": 7144121,
        "name:xx": "Königsberg"
      }
    },
    {
      "geometry": {
        "type": "Point",
        "coordinates": [
          8.533333,
          50.65
        ]
      },
      "type": "Feature",
      "properties": {
        "hierarchy": [
          "tgn:7144122",
          "tgn:1000003",
          "tgn:7003678",
          "tgn:7000084",
          "tgn:7029392"
        ],
        "placetype": [
          "aat:300008347"
        ],
        "id": 7144122,
        "name:xx": "Königsberg"
      }
    },
    {
      "geometry": {
        "type": "Point",
        "coordinates": [
          10.466667,
          51.966667
        ]
      },
      "type": "Feature",
      "properties": {
        "hierarchy": [
          "tgn:7144123",
          "tgn:1000003",
          "tgn:7003676",
          "tgn:7000084",
          "tgn:7029392"
        ],
        "placetype": [
          "aat:300008777",
          "aat:300008795"
        ],
        "id": 7144123,
        "name:xx": "Königs-Berg"
      }
    },
    {
      "geometry": {
        "type": "Point",
        "coordinates": [
          7.583333,
          49.566667
        ]
      },
      "type": "Feature",
      "properties": {
        "hierarchy": [
          "tgn:7144124",
          "tgn:1000003",
          "tgn:7003682",
          "tgn:7000084",
          "tgn:7029392"
        ],
        "placetype": [
          "aat:300008795"
        ],
        "id": 7144124,
        "name:xx": "Königsberg"
      }
    },
    {
      "geometry": {
        "type": "Point",
        "coordinates": [
          9.75,
          54.3
        ]
      },
      "type": "Feature",
      "properties": {
        "hierarchy": [
          "tgn:7144125",
          "tgn:1000003",
          "tgn:7003688",
          "tgn:7000084",
          "tgn:7029392"
        ],
        "placetype": [
          "aat:300008777"
        ],
        "id": 7144125,
        "name:xx": "Königs-Berg"
      }
    },
    {
      "geometry": {
        "type": "Point",
        "coordinates": [
          12.783333,
          53.716667
        ]
      },
      "type": "Feature",
      "properties": {
        "hierarchy": [
          "tgn:7144126",
          "tgn:1000003",
          "tgn:7000094",
          "tgn:7000084",
          "tgn:7029392"
        ],
        "placetype": [
          "aat:300008777"
        ],
        "id": 7144126,
        "name:xx": "Königs Berg"
      }
    },
    {
      "geometry": {
        "type": "Point",
        "coordinates": [
          9.1,
          53.233333
        ]
      },
      "type": "Feature",
      "properties": {
        "hierarchy": [
          "tgn:7144127",
          "tgn:1000003",
          "tgn:7003676",
          "tgn:7000084",
          "tgn:7029392"
        ],
        "placetype": [
          "aat:300008777"
        ],
        "id": 7144127,
        "name:xx": "Königs-Berg"
      }
    },
    {
      "geometry": {
        "type": "Point",
        "coordinates": [
          10.733333,
          53
        ]
      },
      "type": "Feature",
      "properties": {
        "hierarchy": [
          "tgn:7144128",
          "tgn:1000003",
          "tgn:7003676",
          "tgn:7000084",
          "tgn:7029392"
        ],
        "placetype": [
          "aat:300008777"
        ],
        "id": 7144128,
        "name:xx": "Königs-Berg"
      }
    },
    {
      "geometry": {
        "type": "Point",
        "coordinates": [
          10.566667,
          52.933333
        ]
      },
      "type": "Feature",
      "properties": {
        "hierarchy": [
          "tgn:7144129",
          "tgn:1000003",
          "tgn:7003676",
          "tgn:7000084",
          "tgn:7029392"
        ],
        "placetype": [
          "aat:300008777"
        ],
        "id": 7144129,
        "name:xx": "Königs-Berg"
      }
    }
  ]
}
