{
  "geometry": {
    "type": "Point",
    "coordinates": [
      -117.85,
      43.8333
    ]
  },
  "type": "Feature",
  "properties": {
    "hierarchy": [
      "tgn:2678502",
      "tgn:1000001",
      "tgn:7012149",
      "tgn:2001718",
      "tgn:7007708",
      "tgn:7029392"
    ],
    "placetype": [
      "aat:300008706"
    ],
    "id": 2678502,
    "name:xx": "South Fork Cottonwood Creek"
  }
}
