{
  "geometry": {
    "type": "Point",
    "coordinates": [
      -93.7667,
      30.5333
    ]
  },
  "type": "Feature",
  "properties": {
    "hierarchy": [
      "tgn:2106496",
      "tgn:1000001",
      "tgn:7012149",
      "tgn:2002047",
      "tgn:7007826",
      "tgn:7029392"
    ],
    "placetype": [
      "aat:300008347",
      "aat:300387210"
    ],
    "id": 2106496,
    "name:xx": "Salem"
  }
}
