{
  "geometry": {
    "type": "Point",
    "coordinates": [
      8.45,
      47.95
    ]
  },
  "type": "Feature",
  "properties": {
    "hierarchy": [
      "tgn:7107149",
      "tgn:7003692",
      "tgn:1000003",
      "tgn:7000084",
      "tgn:7029392"
    ],
    "placetype": [
      "aat:300008777"
    ],
    "id": 7107149,
    "name:xx": "Schellenberg"
  }
}
