{
  "type": "FeatureCollection",
  "features": [
    {
      "geometry": {
        "type": "Point",
        "coordinates": [
          -100.616667,
          26.516667
        ]
      },
      "type": "Feature",
      "properties": {
        "hierarchy": [
          "tgn:7386700",
          "tgn:1000001",
          "tgn:7005589",
          "tgn:7005560",
          "tgn:7029392"
        ],
        "placetype": [
          "aat:300008347"
        ],
        "id": 7386700,
        "name:xx": "Ranchito"
      }
    },
    {
      "geometry": {
        "type": "Point",
        "coordinates": [
          -106.483333,
          26
        ]
      },
      "type": "Feature",
      "properties": {
        "hierarchy": [
          "tgn:7386701",
          "tgn:7005583",
          "tgn:1000001",
          "tgn:7005560",
          "tgn:7029392"
        ],
        "placetype": [
          "aat:300008347"
        ],
        "id": 7386701,
        "name:xx": "Ranchito"
      }
    },
    {
      "geometry": {
        "type": "Point",
        "coordinates": [
          -106.2,
          25.933333
        ]
      },
      "type": "Feature",
      "properties": {
        "hierarchy": [
          "tgn:7386702",
          "tgn:7005583",
          "tgn:1000001",
          "tgn:7005560",
          "tgn:7029392"
        ],
        "placetype": [
          "aat:300008347"
        ],
        "id": 7386702,
        "name:xx": "Ranchito"
      }
    },
    {
      "geometry": {
        "type": "Point",
        "coordinates": [
          -108.233333,
          25.75
        ]
      },
      "type": "Feature",
      "properties": {
        "hierarchy": [
          "tgn:7386703",
          "tgn:1000001",
          "tgn:7005595",
          "tgn:7005560",
          "tgn:7029392"
        ],
        "placetype": [
          "aat:300008347"
        ],
        "id": 7386703,
        "name:xx": "Ranchito"
      }
    },
    {
      "geometry": {
        "type": "Point",
        "coordinates": [
          -107.9,
          25.7
        ]
      },
      "type": "Feature",
      "properties": {
        "hierarchy": [
          "tgn:7386704",
          "tgn:1000001",
          "tgn:7005595",
          "tgn:7005560",
          "tgn:7029392"
        ],
        "placetype": [
          "aat:300008347"
        ],
        "id": 7386704,
        "name:xx": "Ranchito"
      }
    },
    {
      "geometry": {
        "type": "Point",
        "coordinates": [
          -107.076944,
          24.568889
        ]
      },
      "type": "Feature",
      "properties": {
        "hierarchy": [
          "tgn:7386705",
          "tgn:1000001",
          "tgn:7005595",
          "tgn:7005560",
          "tgn:7029392"
        ],
        "placetype": [
          "aat:300008347"
        ],
        "id": 7386705,
        "name:xx": "Ranchito"
      }
    },
    {
      "geometry": {
        "type": "Point",
        "coordinates": [
          -99.453333,
          24.531667
        ]
      },
      "type": "Feature",
      "properties": {
        "hierarchy": [
          "tgn:7386706",
          "tgn:1000001",
          "tgn:7005597",
          "tgn:7005560",
          "tgn:7029392"
        ],
        "placetype": [
          "aat:300008347"
        ],
        "id": 7386706,
        "name:xx": "Ranchito"
      }
    },
    {
      "geometry": {
        "type": "Point",
        "coordinates": [
          -103.85,
          23.766667
        ]
      },
      "type": "Feature",
      "properties": {
        "hierarchy": [
          "tgn:7386707",
          "tgn:1000001",
          "tgn:7005601",
          "tgn:7005560",
          "tgn:7029392"
        ],
        "placetype": [
          "aat:300008347"
        ],
        "id": 7386707,
        "name:xx": "Ranchito"
      }
    },
    {
      "geometry": {
        "type": "Point",
        "coordinates": [
          -102.75,
          22.4
        ]
      },
      "type": "Feature",
      "properties": {
        "hierarchy": [
          "tgn:7386708",
          "tgn:1000001",
          "tgn:7005601",
          "tgn:7005560",
          "tgn:7029392"
        ],
        "placetype": [
          "aat:300008347"
        ],
        "id": 7386708,
        "name:xx": "Ranchito"
      }
    },
    {
      "geometry": {
        "type": "Point",
        "coordinates": [
          -100.5,
          22.083333
        ]
      },
      "type": "Feature",
      "properties": {
        "hierarchy": [
          "tgn:7386709",
          "tgn:1000001",
          "tgn:7005594",
          "tgn:7005560",
          "tgn:7029392"
        ],
        "placetype": [
          "aat:300008347"
        ],
        "id": 7386709,
        "name:xx": "Ranchito"
      }
    }
  ]
}
