{
  "geometry": {
    "type": "Point",
    "coordinates": [
      -92.2833,
      48.1833
    ]
  },
  "type": "Feature",
  "properties": {
    "hierarchy": [
      "tgn:2779976",
      "tgn:1000001",
      "tgn:7012149",
      "tgn:2001067",
      "tgn:7007521",
      "tgn:7029392"
    ],
    "placetype": [
      "aat:300008680"
    ],
    "id": 2779976,
    "name:xx": "Wolfpack Lake"
  }
}
