{
  "type": "FeatureCollection",
  "features": [
    {
      "geometry": {
        "type": "Point",
        "coordinates": [
          -108.1,
          35.15
        ]
      },
      "type": "Feature",
      "properties": {
        "hierarchy": [
          "tgn:2287470",
          "tgn:1000001",
          "tgn:2001431",
          "tgn:7012149",
          "tgn:7007566",
          "tgn:7029392"
        ],
        "placetype": [
          "aat:300008761"
        ],
        "id": 2287470,
        "name:xx": "Diener Canyon"
      }
    },
    {
      "geometry": {
        "type": "Point",
        "coordinates": [
          -122.8,
          40.8833
        ]
      },
      "type": "Feature",
      "properties": {
        "hierarchy": [
          "tgn:2287471",
          "tgn:1000001",
          "tgn:7012149",
          "tgn:7007157",
          "tgn:2000191",
          "tgn:7029392"
        ],
        "placetype": [
          "aat:300006075"
        ],
        "id": 2287471,
        "name:xx": "Diener Ditch"
      }
    },
    {
      "geometry": {
        "type": "Point",
        "coordinates": [
          -86.85,
          40.75
        ]
      },
      "type": "Feature",
      "properties": {
        "hierarchy": [
          "tgn:2287472",
          "tgn:1000001",
          "tgn:7012149",
          "tgn:1003021",
          "tgn:7007252",
          "tgn:7029392"
        ],
        "placetype": [
          "aat:300006075"
        ],
        "id": 2287472,
        "name:xx": "Diener Ditch"
      }
    },
    {
      "geometry": {
        "type": "Point",
        "coordinates": [
          -122.7833,
          40.8667
        ]
      },
      "type": "Feature",
      "properties": {
        "hierarchy": [
          "tgn:2287473",
          "tgn:1000001",
          "tgn:7012149",
          "tgn:7007157",
          "tgn:2000191",
          "tgn:7029392"
        ],
        "placetype": [
          "aat:300000390"
        ],
        "id": 2287473,
        "name:xx": "Diener Mine"
      }
    },
    {
      "geometry": {
        "type": "Point",
        "coordinates": [
          -76.1667,
          40.7
        ]
      },
      "type": "Feature",
      "properties": {
        "hierarchy": [
          "tgn:2287474",
          "tgn:1000001",
          "tgn:7012149",
          "tgn:1002876",
          "tgn:7007710",
          "tgn:7029392"
        ],
        "placetype": [
          "aat:300008347"
        ],
        "id": 2287474,
        "name:xx": "Dieners Hill"
      }
    },
    {
      "geometry": {
        "type": "Point",
        "coordinates": [
          -99.0333,
          44.85
        ]
      },
      "type": "Feature",
      "properties": {
        "hierarchy": [
          "tgn:2287475",
          "tgn:1000001",
          "tgn:2001799",
          "tgn:7012149",
          "tgn:7007713",
          "tgn:7029392"
        ],
        "placetype": [
          "aat:300008680"
        ],
        "id": 2287475,
        "name:xx": "Dienslake Lake"
      }
    },
    {
      "geometry": {
        "type": "Point",
        "coordinates": [
          -93.6333,
          36.1
        ]
      },
      "type": "Feature",
      "properties": {
        "hierarchy": [
          "tgn:2287476",
          "tgn:1000001",
          "tgn:7016172",
          "tgn:7012149",
          "tgn:2000148",
          "tgn:7029392"
        ],
        "placetype": [
          "aat:300008798"
        ],
        "id": 2287476,
        "name:xx": "Diera Mountain"
      }
    },
    {
      "geometry": {
        "type": "Point",
        "coordinates": [
          -90.5,
          38.1
        ]
      },
      "type": "Feature",
      "properties": {
        "hierarchy": [
          "tgn:2287477",
          "tgn:1000001",
          "tgn:7012149",
          "tgn:1002517",
          "tgn:7007523",
          "tgn:7029392"
        ],
        "placetype": [
          "aat:300006191"
        ],
        "id": 2287477,
        "name:xx": "Dierberg Lake"
      }
    },
    {
      "geometry": {
        "type": "Point",
        "coordinates": [
          -108.8667,
          38.9
        ]
      },
      "type": "Feature",
      "properties": {
        "hierarchy": [
          "tgn:2287478",
          "tgn:1000001",
          "tgn:7012149",
          "tgn:2000230",
          "tgn:7007158",
          "tgn:7029392"
        ],
        "placetype": [
          "aat:300008706"
        ],
        "id": 2287478,
        "name:xx": "Dierich Creek"
      }
    },
    {
      "geometry": {
        "type": "Point",
        "coordinates": [
          -114.3833,
          42.5833
        ]
      },
      "type": "Feature",
      "properties": {
        "hierarchy": [
          "tgn:2287479",
          "tgn:1000001",
          "tgn:7012149",
          "tgn:2000493",
          "tgn:7007250",
          "tgn:7029392"
        ],
        "placetype": [
          "aat:300008680"
        ],
        "id": 2287479,
        "name:xx": "Dierkes Lake"
      }
    }
  ]
}
