{
  "type": "FeatureCollection",
  "features": [
    {
      "geometry": {
        "type": "Point",
        "coordinates": [
          -77.4333,
          36.2
        ]
      },
      "type": "Feature",
      "properties": {
        "hierarchy": [
          "tgn:2076752",
          "tgn:1000001",
          "tgn:7012149",
          "tgn:2001501",
          "tgn:7007709",
          "tgn:7029392"
        ],
        "placetype": [
          "aat:300008347",
          "aat:300387210"
        ],
        "id": 2076752,
        "name:xx": "Spring Hill"
      }
    },
    {
      "geometry": {
        "type": "Point",
        "coordinates": [
          -78.1,
          35.9333
        ]
      },
      "type": "Feature",
      "properties": {
        "hierarchy": [
          "tgn:2076753",
          "tgn:1000001",
          "tgn:7012149",
          "tgn:2001522",
          "tgn:7007709",
          "tgn:7029392"
        ],
        "placetype": [
          "aat:300008347"
        ],
        "id": 2076753,
        "name:xx": "Spring Hope"
      }
    },
    {
      "geometry": {
        "type": "Point",
        "coordinates": [
          -78.9667,
          35.1667
        ]
      },
      "type": "Feature",
      "properties": {
        "hierarchy": [
          "tgn:2076754",
          "tgn:1000001",
          "tgn:7012149",
          "tgn:2001487",
          "tgn:7007709",
          "tgn:7029392"
        ],
        "placetype": [
          "aat:300008347"
        ],
        "id": 2076754,
        "name:xx": "Spring Lake"
      }
    },
    {
      "geometry": {
        "type": "Point",
        "coordinates": [
          -81.05,
          35.2667
        ]
      },
      "type": "Feature",
      "properties": {
        "hierarchy": [
          "tgn:2076755",
          "tgn:1000001",
          "tgn:7012149",
          "tgn:2001496",
          "tgn:7007709",
          "tgn:7029392"
        ],
        "placetype": [
          "aat:300008347"
        ],
        "id": 2076755,
        "name:xx": "Springwood"
      }
    },
    {
      "geometry": {
        "type": "Point",
        "coordinates": [
          -82.05,
          35.9
        ]
      },
      "type": "Feature",
      "properties": {
        "hierarchy": [
          "tgn:2076756",
          "tgn:1000001",
          "tgn:7012149",
          "tgn:2001519",
          "tgn:7007709",
          "tgn:7029392"
        ],
        "placetype": [
          "aat:300008347"
        ],
        "id": 2076756,
        "name:xx": "Spruce Pine"
      }
    },
    {
      "geometry": {
        "type": "Point",
        "coordinates": [
          -82.7667,
          35.8667
        ]
      },
      "type": "Feature",
      "properties": {
        "hierarchy": [
          "tgn:2076758",
          "tgn:1000001",
          "tgn:7012149",
          "tgn:2001516",
          "tgn:7007709",
          "tgn:7029392"
        ],
        "placetype": [
          "aat:300008347",
          "aat:300387210"
        ],
        "id": 2076758,
        "name:xx": "Stackhouse"
      }
    },
    {
      "geometry": {
        "type": "Point",
        "coordinates": [
          -76.4,
          34.8333
        ]
      },
      "type": "Feature",
      "properties": {
        "hierarchy": [
          "tgn:2076759",
          "tgn:1000001",
          "tgn:2001477",
          "tgn:7012149",
          "tgn:7007709",
          "tgn:7029392"
        ],
        "placetype": [
          "aat:300008347"
        ],
        "id": 2076759,
        "name:xx": "Stacy"
      }
    }
  ]
}
