{
  "geometry": {
    "type": "Point",
    "coordinates": [
      -78.2833,
      34.4167
    ]
  },
  "type": "Feature",
  "properties": {
    "hierarchy": [
      "tgn:1131760",
      "tgn:1000001",
      "tgn:7012149",
      "tgn:7007709",
      "tgn:7029392"
    ],
    "placetype": [
      "aat:300008707"
    ],
    "id": 1131760,
    "name:xx": "White Oak"
  }
}
