{
  "type": "FeatureCollection",
  "features": [
    {
      "geometry": {
        "type": "Point",
        "coordinates": [
          -75.066667,
          -49.9
        ]
      },
      "type": "Feature",
      "properties": {
        "hierarchy": [
          "tgn:7320010",
          "tgn:1001702",
          "tgn:1000049",
          "tgn:1000002",
          "tgn:7029392"
        ],
        "placetype": [
          "aat:300386846"
        ],
        "id": 7320010,
        "name:xx": "Adelaida, Punta"
      }
    },
    {
      "geometry": {
        "type": "Point",
        "coordinates": [
          -71.95,
          -54.35
        ]
      },
      "type": "Feature",
      "properties": {
        "hierarchy": [
          "tgn:7320011",
          "tgn:1001702",
          "tgn:1000049",
          "tgn:1000002",
          "tgn:7029392"
        ],
        "placetype": [
          "aat:300387026"
        ],
        "id": 7320011,
        "name:xx": "Adelaida, Paso"
      }
    },
    {
      "geometry": {
        "type": "Point",
        "coordinates": [
          -71.366667,
          -30.116667
        ]
      },
      "type": "Feature",
      "properties": {
        "hierarchy": [
          "tgn:7320012",
          "tgn:1001657",
          "tgn:1000049",
          "tgn:1000002",
          "tgn:7029392"
        ],
        "placetype": [
          "aat:300008679"
        ],
        "id": 7320012,
        "name:xx": "Adelaida, Laguna"
      }
    },
    {
      "geometry": {
        "type": "Point",
        "coordinates": [
          -73.483333,
          -52.066667
        ]
      },
      "type": "Feature",
      "properties": {
        "hierarchy": [
          "tgn:7320013",
          "tgn:1001702",
          "tgn:1000049",
          "tgn:1000002",
          "tgn:7029392"
        ],
        "placetype": [
          "aat:300008680"
        ],
        "id": 7320013,
        "name:xx": "Adelaida, Lago"
      }
    },
    {
      "geometry": {
        "type": "Point",
        "coordinates": [
          -73.6,
          -53.1
        ]
      },
      "type": "Feature",
      "properties": {
        "hierarchy": [
          "tgn:7320014",
          "tgn:1001702",
          "tgn:1000049",
          "tgn:1000002",
          "tgn:7029392"
        ],
        "placetype": [
          "aat:300008791"
        ],
        "id": 7320014,
        "name:xx": "Adelaida, Islote"
      }
    },
    {
      "geometry": {
        "type": "Point",
        "coordinates": [
          -74.3,
          -49.783333
        ]
      },
      "type": "Feature",
      "properties": {
        "hierarchy": [
          "tgn:7320015",
          "tgn:1001702",
          "tgn:1000049",
          "tgn:1000002",
          "tgn:7029392"
        ],
        "placetype": [
          "aat:300008791"
        ],
        "id": 7320015,
        "name:xx": "Adelaida, Islote"
      }
    },
    {
      "geometry": {
        "type": "Point",
        "coordinates": [
          -73.633333,
          -52.533333
        ]
      },
      "type": "Feature",
      "properties": {
        "hierarchy": [
          "tgn:7320016",
          "tgn:1001702",
          "tgn:1000049",
          "tgn:1000002",
          "tgn:7029392"
        ],
        "placetype": [
          "aat:300008791"
        ],
        "id": 7320016,
        "name:xx": "Adelaida, Islas"
      }
    },
    {
      "geometry": {
        "type": "Point",
        "coordinates": [
          -72.1,
          -54.366667
        ]
      },
      "type": "Feature",
      "properties": {
        "hierarchy": [
          "tgn:7320017",
          "tgn:1001702",
          "tgn:1000049",
          "tgn:1000002",
          "tgn:7029392"
        ],
        "placetype": [
          "aat:300008791"
        ],
        "id": 7320017,
        "name:xx": "Adelaida, Isla"
      }
    },
    {
      "geometry": {
        "type": "Point",
        "coordinates": [
          -75.2,
          -49.416667
        ]
      },
      "type": "Feature",
      "properties": {
        "hierarchy": [
          "tgn:7320018",
          "tgn:1001702",
          "tgn:1000049",
          "tgn:1000002",
          "tgn:7029392"
        ],
        "placetype": [
          "aat:300008676"
        ],
        "id": 7320018,
        "name:xx": "Adelaida, Estero"
      }
    },
    {
      "geometry": {
        "type": "Point",
        "coordinates": [
          -73.633333,
          -52.55
        ]
      },
      "type": "Feature",
      "properties": {
        "hierarchy": [
          "tgn:7320019",
          "tgn:1001702",
          "tgn:1000049",
          "tgn:1000002",
          "tgn:7029392"
        ],
        "placetype": [
          "aat:300387036"
        ],
        "id": 7320019,
        "name:xx": "Adelaida, Bajo"
      }
    }
  ]
}
