{
  "geometry": {
    "type": "Point",
    "coordinates": [
      -114.0333,
      45.6667
    ]
  },
  "type": "Feature",
  "properties": {
    "hierarchy": [
      "tgn:2405508",
      "tgn:1000001",
      "tgn:7012149",
      "tgn:2001300",
      "tgn:7007524",
      "tgn:7029392"
    ],
    "placetype": [
      "aat:300008706"
    ],
    "id": 2405508,
    "name:xx": "Hughes Creek"
  }
}
