{
  "geometry": {
    "type": "Point",
    "coordinates": [
      -90.3167,
      32.35
    ]
  },
  "type": "Feature",
  "properties": {
    "hierarchy": [
      "tgn:2698408",
      "tgn:1000001",
      "tgn:7012149",
      "tgn:2001110",
      "tgn:7007522",
      "tgn:7029392"
    ],
    "placetype": [
      "aat:300008706"
    ],
    "id": 2698408,
    "name:xx": "Straight Fence Creek"
  }
}
