{
  "geometry": {
    "type": "Point",
    "coordinates": [
      -119.3167,
      48.3833
    ]
  },
  "type": "Feature",
  "properties": {
    "hierarchy": [
      "tgn:2356590",
      "tgn:1000001",
      "tgn:7012149",
      "tgn:1002742",
      "tgn:7007920",
      "tgn:7029392"
    ],
    "placetype": [
      "aat:300008697"
    ],
    "id": 2356590,
    "name:xx": "Gordon Spring"
  }
}
