{
  "geometry": {
    "type": "Point",
    "coordinates": [
      -114.8833,
      39.9667
    ]
  },
  "type": "Feature",
  "properties": {
    "hierarchy": [
      "tgn:2320712",
      "tgn:1000001",
      "tgn:7012149",
      "tgn:2001420",
      "tgn:7007526",
      "tgn:7029392"
    ],
    "placetype": [
      "aat:300008761"
    ],
    "id": 2320712,
    "name:xx": "Exchequer Canyon"
  }
}
