{
  "geometry": {
    "type": "Point",
    "coordinates": [
      -87.2333,
      39.1667
    ]
  },
  "type": "Feature",
  "properties": {
    "hierarchy": [
      "tgn:2445345",
      "tgn:1000001",
      "tgn:7012149",
      "tgn:2000544",
      "tgn:7007252",
      "tgn:7029392"
    ],
    "placetype": [
      "aat:300006191"
    ],
    "id": 2445345,
    "name:xx": "Lenape, Lake"
  }
}
