{
  "type": "FeatureCollection",
  "features": [
    {
      "geometry": {
        "type": "Point",
        "coordinates": [
          -98.9667,
          35.5
        ]
      },
      "type": "Feature",
      "properties": {
        "hierarchy": [
          "tgn:2083032",
          "tgn:1000001",
          "tgn:2001642",
          "tgn:7012149",
          "tgn:7007707",
          "tgn:7029392"
        ],
        "placetype": [
          "aat:300008347"
        ],
        "id": 2083032,
        "name:xx": "Clinton"
      }
    },
    {
      "geometry": {
        "type": "Point",
        "coordinates": [
          -98.8333,
          35.25
        ]
      },
      "type": "Feature",
      "properties": {
        "hierarchy": [
          "tgn:2083036",
          "tgn:1000001",
          "tgn:7012149",
          "tgn:2001697",
          "tgn:7007707",
          "tgn:7029392"
        ],
        "placetype": [
          "aat:300008347"
        ],
        "id": 2083036,
        "name:xx": "Cloud Chief"
      }
    },
    {
      "geometry": {
        "type": "Point",
        "coordinates": [
          -95.2667,
          34.3
        ]
      },
      "type": "Feature",
      "properties": {
        "hierarchy": [
          "tgn:2083037",
          "tgn:1000001",
          "tgn:7012149",
          "tgn:2001686",
          "tgn:7007707",
          "tgn:7029392"
        ],
        "placetype": [
          "aat:300008347"
        ],
        "id": 2083037,
        "name:xx": "Cloudy"
      }
    },
    {
      "geometry": {
        "type": "Point",
        "coordinates": [
          -97.8167,
          36.8333
        ]
      },
      "type": "Feature",
      "properties": {
        "hierarchy": [
          "tgn:2083038",
          "tgn:1000001",
          "tgn:2001649",
          "tgn:7012149",
          "tgn:7007707",
          "tgn:7029392"
        ],
        "placetype": [
          "aat:300008347",
          "aat:300387210"
        ],
        "id": 2083038,
        "name:xx": "Clyde"
      }
    },
    {
      "geometry": {
        "type": "Point",
        "coordinates": [
          -94.65,
          35.1833
        ]
      },
      "type": "Feature",
      "properties": {
        "hierarchy": [
          "tgn:2083039",
          "tgn:1000001",
          "tgn:7012149",
          "tgn:2001662",
          "tgn:7007707",
          "tgn:7029392"
        ],
        "placetype": [
          "aat:300387016"
        ],
        "id": 2083039,
        "name:xx": "Coal Creek"
      }
    }
  ]
}
