{
  "geometry": {
    "type": "Point",
    "coordinates": [
      -121.1333,
      45.4667
    ]
  },
  "type": "Feature",
  "properties": {
    "hierarchy": [
      "tgn:2691906",
      "tgn:1000001",
      "tgn:7012149",
      "tgn:1002990",
      "tgn:7007708",
      "tgn:7029392"
    ],
    "placetype": [
      "aat:300008706"
    ],
    "id": 2691906,
    "name:xx": "Starveout Creek"
  }
}
