{
  "type": "FeatureCollection",
  "features": [
    {
      "geometry": {
        "type": "Point",
        "coordinates": [
          -106.5,
          37.2667
        ]
      },
      "type": "Feature",
      "properties": {
        "hierarchy": [
          "tgn:2155040",
          "tgn:1000001",
          "tgn:2000202",
          "tgn:7012149",
          "tgn:7007158",
          "tgn:7029392"
        ],
        "placetype": [
          "aat:300008680"
        ],
        "id": 2155040,
        "name:xx": "Bear Lake"
      }
    },
    {
      "geometry": {
        "type": "Point",
        "coordinates": [
          -105.1333,
          37.3167
        ]
      },
      "type": "Feature",
      "properties": {
        "hierarchy": [
          "tgn:2155041",
          "tgn:1000001",
          "tgn:7012149",
          "tgn:2000219",
          "tgn:7007158",
          "tgn:7029392"
        ],
        "placetype": [
          "aat:300008680"
        ],
        "id": 2155041,
        "name:xx": "Bear Lake"
      }
    },
    {
      "geometry": {
        "type": "Point",
        "coordinates": [
          -104.8833,
          37.4167
        ]
      },
      "type": "Feature",
      "properties": {
        "hierarchy": [
          "tgn:2155042",
          "tgn:1000001",
          "tgn:7012149",
          "tgn:2000219",
          "tgn:7007158",
          "tgn:7029392"
        ],
        "placetype": [
          "aat:300006191"
        ],
        "id": 2155042,
        "name:xx": "Bear Lake"
      }
    },
    {
      "geometry": {
        "type": "Point",
        "coordinates": [
          -80.95,
          25.1667
        ]
      },
      "type": "Feature",
      "properties": {
        "hierarchy": [
          "tgn:2155043",
          "tgn:1000001",
          "tgn:7012149",
          "tgn:1002676",
          "tgn:7007240",
          "tgn:7029392"
        ],
        "placetype": [
          "aat:300008680"
        ],
        "id": 2155043,
        "name:xx": "Bear Lake"
      }
    },
    {
      "geometry": {
        "type": "Point",
        "coordinates": [
          -81.4333,
          28.65
        ]
      },
      "type": "Feature",
      "properties": {
        "hierarchy": [
          "tgn:2155044",
          "tgn:1000001",
          "tgn:7012149",
          "tgn:1002881",
          "tgn:7007240",
          "tgn:7029392"
        ],
        "placetype": [
          "aat:300008680"
        ],
        "id": 2155044,
        "name:xx": "Bear Lake"
      }
    },
    {
      "geometry": {
        "type": "Point",
        "coordinates": [
          -81.4333,
          28.9667
        ]
      },
      "type": "Feature",
      "properties": {
        "hierarchy": [
          "tgn:2155045",
          "tgn:1000001",
          "tgn:7012149",
          "tgn:1002567",
          "tgn:7007240",
          "tgn:7029392"
        ],
        "placetype": [
          "aat:300008680"
        ],
        "id": 2155045,
        "name:xx": "Bear Lake"
      }
    },
    {
      "geometry": {
        "type": "Point",
        "coordinates": [
          -86.8333,
          30.85
        ]
      },
      "type": "Feature",
      "properties": {
        "hierarchy": [
          "tgn:2155046",
          "tgn:1000001",
          "tgn:7012149",
          "tgn:2000285",
          "tgn:7007240",
          "tgn:7029392"
        ],
        "placetype": [
          "aat:300006191"
        ],
        "id": 2155046,
        "name:xx": "Bear Lake"
      }
    },
    {
      "geometry": {
        "type": "Point",
        "coordinates": [
          -82.15,
          30.95
        ]
      },
      "type": "Feature",
      "properties": {
        "hierarchy": [
          "tgn:2155047",
          "tgn:1000001",
          "tgn:2000315",
          "tgn:7012149",
          "tgn:7007248",
          "tgn:7029392"
        ],
        "placetype": [
          "aat:300008680"
        ],
        "id": 2155047,
        "name:xx": "Bear Lake"
      }
    },
    {
      "geometry": {
        "type": "Point",
        "coordinates": [
          -83.3,
          33.7
        ]
      },
      "type": "Feature",
      "properties": {
        "hierarchy": [
          "tgn:2155048",
          "tgn:1000001",
          "tgn:7012149",
          "tgn:2000357",
          "tgn:7007248",
          "tgn:7029392"
        ],
        "placetype": [
          "aat:300006191"
        ],
        "id": 2155048,
        "name:xx": "Bear Lake"
      }
    },
    {
      "geometry": {
        "type": "Point",
        "coordinates": [
          -111.1833,
          44.1167
        ]
      },
      "type": "Feature",
      "properties": {
        "hierarchy": [
          "tgn:2155049",
          "tgn:1000001",
          "tgn:7012149",
          "tgn:2000473",
          "tgn:7007250",
          "tgn:7029392"
        ],
        "placetype": [
          "aat:300008680"
        ],
        "id": 2155049,
        "name:xx": "Bear Lake"
      }
    }
  ]
}
