{
  "geometry": {
    "type": "Point",
    "coordinates": [
      -122.5833,
      38.7667
    ]
  },
  "type": "Feature",
  "properties": {
    "hierarchy": [
      "tgn:2266279",
      "tgn:1000001",
      "tgn:7012149",
      "tgn:7007157",
      "tgn:1002566",
      "tgn:7029392"
    ],
    "placetype": [
      "aat:300008706"
    ],
    "id": 2266279,
    "name:xx": "Crazy Creek"
  }
}
