{
  "geometry": {
    "type": "Point",
    "coordinates": [
      -6.25,
      41.45
    ]
  },
  "type": "Feature",
  "properties": {
    "hierarchy": [
      "tgn:7345857",
      "tgn:7001158",
      "tgn:7002850",
      "tgn:1000003",
      "tgn:1000095",
      "tgn:7029392"
    ],
    "placetype": [
      "aat:300008347"
    ],
    "id": 7345857,
    "name:xx": "Badilla"
  }
}
