{
  "geometry": {
    "type": "Point",
    "coordinates": [
      74.150512,
      28.90761
    ]
  },
  "type": "Feature",
  "properties": {
    "hierarchy": [
      "tgn:7563460",
      "tgn:1000004",
      "tgn:7000198",
      "tgn:7016788",
      "tgn:7029392"
    ],
    "placetype": [
      "aat:300008347"
    ],
    "name:en": "Ratnādesar Dūdli",
    "id": 7563460
  }
}
