{
  "geometry": {
    "type": "Point",
    "coordinates": [
      -159.35,
      59.3333
    ]
  },
  "type": "Feature",
  "properties": {
    "hierarchy": [
      "tgn:2559310",
      "tgn:7006450",
      "tgn:1000001",
      "tgn:2000071",
      "tgn:7012149",
      "tgn:7029392"
    ],
    "placetype": [
      "aat:300008707"
    ],
    "id": 2559310,
    "name:xx": "Ongoke River"
  }
}
