{
  "geometry": {
    "type": "Point",
    "coordinates": [
      -97.3833,
      46.0833
    ]
  },
  "type": "Feature",
  "properties": {
    "hierarchy": [
      "tgn:2607526",
      "tgn:1000001",
      "tgn:2001597",
      "tgn:7012149",
      "tgn:7007705",
      "tgn:7029392"
    ],
    "placetype": [
      "aat:300008347"
    ],
    "id": 2607526,
    "name:xx": "Ransom City"
  }
}
