{
  "geometry": {
    "type": "Point",
    "coordinates": [
      -77.8833,
      36.9333
    ]
  },
  "type": "Feature",
  "properties": {
    "hierarchy": [
      "tgn:2559998",
      "tgn:1000001",
      "tgn:2002147",
      "tgn:7012149",
      "tgn:7007919",
      "tgn:7029392"
    ],
    "placetype": [
      "aat:300008706"
    ],
    "id": 2559998,
    "name:xx": "Opossum Quarter Creek"
  }
}
