{
  "geometry": {
    "type": "Point",
    "coordinates": [
      -92.4833,
      39.55
    ]
  },
  "type": "Feature",
  "properties": {
    "hierarchy": [
      "tgn:2392403",
      "tgn:1000001",
      "tgn:7012149",
      "tgn:1002819",
      "tgn:7007523",
      "tgn:7029392"
    ],
    "placetype": [
      "aat:300006191"
    ],
    "id": 2392403,
    "name:xx": "Hisle Lake"
  }
}
