{
  "geometry": {
    "type": "Point",
    "coordinates": [
      -87.9167,
      38.2333
    ]
  },
  "type": "Feature",
  "properties": {
    "hierarchy": [
      "tgn:2356008",
      "tgn:1000001",
      "tgn:7012149",
      "tgn:2000543",
      "tgn:7007252",
      "tgn:7029392"
    ],
    "placetype": [
      "aat:300008680"
    ],
    "id": 2356008,
    "name:xx": "Goose Pond"
  }
}
