{
  "geometry": {
    "type": "Point",
    "coordinates": [
      -87.8333,
      36.6333
    ]
  },
  "type": "Feature",
  "properties": {
    "hierarchy": [
      "tgn:2159888",
      "tgn:1000001",
      "tgn:7012149",
      "tgn:7029392"
    ],
    "placetype": [
      "aat:300008706"
    ],
    "id": 2159888,
    "name:xx": "Beech Fork Creek"
  }
}
