{
  "geometry": {
    "type": "Point",
    "coordinates": [
      18.9333,
      44.1833
    ]
  },
  "type": "Feature",
  "properties": {
    "hierarchy": [
      "tgn:1065333",
      "tgn:7018870",
      "tgn:1000003",
      "tgn:7006664",
      "tgn:7029392"
    ],
    "placetype": [
      "aat:300008347"
    ],
    "id": 1065333,
    "name:xx": "Vlasenica"
  }
}
