{
  "geometry": {
    "type": "Point",
    "coordinates": [
      -89.1667,
      33.3667
    ]
  },
  "type": "Feature",
  "properties": {
    "hierarchy": [
      "tgn:2164804",
      "tgn:1000001",
      "tgn:2001095",
      "tgn:7012149",
      "tgn:7007522",
      "tgn:7029392"
    ],
    "placetype": [
      "aat:300008706"
    ],
    "id": 2164804,
    "name:xx": "Besa Chitto Creek"
  }
}
