{
  "geometry": {
    "type": "Point",
    "coordinates": [
      -113.9333,
      47.3667
    ]
  },
  "type": "Feature",
  "properties": {
    "hierarchy": [
      "tgn:2300859",
      "tgn:1000001",
      "tgn:7012149",
      "tgn:2001283",
      "tgn:7007524",
      "tgn:7029392"
    ],
    "placetype": [
      "aat:300008680"
    ],
    "id": 2300859,
    "name:xx": "Duncan Lake"
  }
}
