{
  "type": "FeatureCollection",
  "features": [
    {
      "geometry": {
        "type": "Point",
        "coordinates": [
          -84.9333,
          43.9
        ]
      },
      "type": "Feature",
      "properties": {
        "hierarchy": [
          "tgn:2372010",
          "tgn:1000001",
          "tgn:2000953",
          "tgn:7012149",
          "tgn:7007520",
          "tgn:7029392"
        ],
        "placetype": [
          "aat:300008680"
        ],
        "id": 2372010,
        "name:xx": "Half Moon Lake"
      }
    },
    {
      "geometry": {
        "type": "Point",
        "coordinates": [
          -84.05,
          42.0833
        ]
      },
      "type": "Feature",
      "properties": {
        "hierarchy": [
          "tgn:2372011",
          "tgn:1000001",
          "tgn:7012149",
          "tgn:1003000",
          "tgn:7007520",
          "tgn:7029392"
        ],
        "placetype": [
          "aat:300008680"
        ],
        "id": 2372011,
        "name:xx": "Half Moon Lake"
      }
    },
    {
      "geometry": {
        "type": "Point",
        "coordinates": [
          -85.05,
          43.25
        ]
      },
      "type": "Feature",
      "properties": {
        "hierarchy": [
          "tgn:2372012",
          "tgn:1000001",
          "tgn:7012149",
          "tgn:2000981",
          "tgn:7007520",
          "tgn:7029392"
        ],
        "placetype": [
          "aat:300008680"
        ],
        "id": 2372012,
        "name:xx": "Half Moon Lake"
      }
    },
    {
      "geometry": {
        "type": "Point",
        "coordinates": [
          -86.25,
          41.9
        ]
      },
      "type": "Feature",
      "properties": {
        "hierarchy": [
          "tgn:2372013",
          "tgn:1000001",
          "tgn:1002182",
          "tgn:7012149",
          "tgn:7007520",
          "tgn:7029392"
        ],
        "placetype": [
          "aat:300008905"
        ],
        "id": 2372013,
        "name:xx": "Half Moon Lake"
      }
    },
    {
      "geometry": {
        "type": "Point",
        "coordinates": [
          -94.5667,
          45.1833
        ]
      },
      "type": "Feature",
      "properties": {
        "hierarchy": [
          "tgn:2372014",
          "tgn:1000001",
          "tgn:7012149",
          "tgn:2001045",
          "tgn:7007521",
          "tgn:7029392"
        ],
        "placetype": [
          "aat:300008680"
        ],
        "id": 2372014,
        "name:xx": "Half Moon Lake"
      }
    },
    {
      "geometry": {
        "type": "Point",
        "coordinates": [
          -94.0833,
          46.5
        ]
      },
      "type": "Feature",
      "properties": {
        "hierarchy": [
          "tgn:2372015",
          "tgn:1000001",
          "tgn:2001016",
          "tgn:7012149",
          "tgn:7007521",
          "tgn:7029392"
        ],
        "placetype": [
          "aat:300008680"
        ],
        "id": 2372015,
        "name:xx": "Half Moon Lake"
      }
    },
    {
      "geometry": {
        "type": "Point",
        "coordinates": [
          -92.5,
          47.3833
        ]
      },
      "type": "Feature",
      "properties": {
        "hierarchy": [
          "tgn:2372016",
          "tgn:1000001",
          "tgn:7012149",
          "tgn:2001067",
          "tgn:7007521",
          "tgn:7029392"
        ],
        "placetype": [
          "aat:300008680"
        ],
        "id": 2372016,
        "name:xx": "Half Moon Lake"
      }
    },
    {
      "geometry": {
        "type": "Point",
        "coordinates": [
          -75.45,
          41.4333
        ]
      },
      "type": "Feature",
      "properties": {
        "hierarchy": [
          "tgn:2372017",
          "tgn:1000001",
          "tgn:7012149",
          "tgn:1002564",
          "tgn:7007710",
          "tgn:7029392"
        ],
        "placetype": [
          "aat:300006191"
        ],
        "id": 2372017,
        "name:xx": "Half Moon Lake"
      }
    },
    {
      "geometry": {
        "type": "Point",
        "coordinates": [
          -117.2,
          48.4
        ]
      },
      "type": "Feature",
      "properties": {
        "hierarchy": [
          "tgn:2372018",
          "tgn:1000001",
          "tgn:7012149",
          "tgn:2002248",
          "tgn:7007920",
          "tgn:7029392"
        ],
        "placetype": [
          "aat:300008680"
        ],
        "id": 2372018,
        "name:xx": "Half Moon Lake"
      }
    },
    {
      "geometry": {
        "type": "Point",
        "coordinates": [
          -89.7,
          44.8
        ]
      },
      "type": "Feature",
      "properties": {
        "hierarchy": [
          "tgn:2372019",
          "tgn:1000001",
          "tgn:7012149",
          "tgn:2002336",
          "tgn:7007922",
          "tgn:7029392"
        ],
        "placetype": [
          "aat:300008680"
        ],
        "id": 2372019,
        "name:xx": "Half Moon Lake"
      }
    }
  ]
}
