{
  "geometry": {
    "type": "Point",
    "coordinates": [
      -71.4833,
      42.6667
    ]
  },
  "type": "Feature",
  "properties": {
    "hierarchy": [
      "tgn:2474191",
      "tgn:1000001",
      "tgn:1002665",
      "tgn:7012149",
      "tgn:7007517",
      "tgn:7029392"
    ],
    "placetype": [
      "aat:300006191"
    ],
    "id": 2474191,
    "name:xx": "Lower Massapoag Pond"
  }
}
