{
  "geometry": {
    "type": "Point",
    "coordinates": [
      -83.7667,
      30.0167
    ]
  },
  "type": "Feature",
  "properties": {
    "hierarchy": [
      "tgn:2717799",
      "tgn:1000001",
      "tgn:7012149",
      "tgn:2000287",
      "tgn:7007240",
      "tgn:7029392"
    ],
    "placetype": [
      "aat:300008791"
    ],
    "id": 2717799,
    "name:xx": "Thomas Mill Island"
  }
}
