{
  "geometry": {
    "type": "Point",
    "coordinates": [
      60.0833,
      25.3333
    ]
  },
  "type": "Feature",
  "properties": {
    "hierarchy": [
      "tgn:7002211",
      "tgn:1000004",
      "tgn:7029392"
    ],
    "placetype": [
      "aat:300008734"
    ],
    "id": 7002211,
    "name:xx": "Makran Coast"
  }
}
