{
  "geometry": {
    "type": "Point",
    "coordinates": [
      -107.5833,
      33.8833
    ]
  },
  "type": "Feature",
  "properties": {
    "hierarchy": [
      "tgn:2557939",
      "tgn:1000001",
      "tgn:7012149",
      "tgn:2001456",
      "tgn:7007566",
      "tgn:7029392"
    ],
    "placetype": [
      "aat:300006191"
    ],
    "id": 2557939,
    "name:xx": "Old Tank"
  }
}
