{
  "geometry": {
    "type": "Point",
    "coordinates": [
      -83.9667,
      33.7333
    ]
  },
  "type": "Feature",
  "properties": {
    "hierarchy": [
      "tgn:2024809",
      "tgn:1000001",
      "tgn:7012149",
      "tgn:2000413",
      "tgn:7007248",
      "tgn:7029392"
    ],
    "placetype": [
      "aat:300008347",
      "aat:300387210"
    ],
    "id": 2024809,
    "name:xx": "Zingara"
  }
}
