{
  "geometry": {
    "type": "Point",
    "coordinates": [
      -105.6333,
      46.3333
    ]
  },
  "type": "Feature",
  "properties": {
    "hierarchy": [
      "tgn:2173672",
      "tgn:1000001",
      "tgn:2001268",
      "tgn:7012149",
      "tgn:7007524",
      "tgn:7029392"
    ],
    "placetype": [
      "aat:300008697"
    ],
    "id": 2173672,
    "name:xx": "Bircher Springs"
  }
}
