{
  "type": "FeatureCollection",
  "features": [
    {
      "geometry": {
        "type": "Point",
        "coordinates": [
          17.2333,
          62.4
        ]
      },
      "type": "Feature",
      "properties": {
        "hierarchy": [
          "tgn:4004694",
          "tgn:1000003",
          "tgn:1000466",
          "tgn:1000097",
          "tgn:7029392"
        ],
        "placetype": [
          "aat:300008347"
        ],
        "id": 4004694,
        "name:xx": "Högom"
      }
    },
    {
      "geometry": {
        "type": "Point",
        "coordinates": [
          7.666667,
          50.433333
        ]
      },
      "type": "Feature",
      "properties": {
        "hierarchy": [
          "tgn:4004695",
          "tgn:1000003",
          "tgn:7003682",
          "tgn:7000084",
          "tgn:7029392"
        ],
        "placetype": [
          "aat:300008347"
        ],
        "id": 4004695,
        "name:xx": "Höhr-Grenzhausen"
      }
    },
    {
      "geometry": {
        "type": "Point",
        "coordinates": [
          9.716667,
          53.85
        ]
      },
      "type": "Feature",
      "properties": {
        "hierarchy": [
          "tgn:4004697",
          "tgn:1000003",
          "tgn:7003688",
          "tgn:7000084",
          "tgn:7029392"
        ],
        "placetype": [
          "aat:300008347"
        ],
        "id": 4004697,
        "name:xx": "Brande-Hörnerkirchen"
      }
    }
  ]
}
