{
  "geometry": {
    "type": "Point",
    "coordinates": [
      -109.4333,
      44.3667
    ]
  },
  "type": "Feature",
  "properties": {
    "hierarchy": [
      "tgn:2759774",
      "tgn:1000001",
      "tgn:7012149",
      "tgn:2002379",
      "tgn:7007923",
      "tgn:7029392"
    ],
    "placetype": [
      "aat:300008706"
    ],
    "id": 2759774,
    "name:xx": "West Fork Jordan Creek"
  }
}
