{
  "geometry": {
    "type": "Point",
    "coordinates": [
      -82.0833,
      37.6667
    ]
  },
  "type": "Feature",
  "properties": {
    "hierarchy": [
      "tgn:2173760",
      "tgn:1000001",
      "tgn:7012149",
      "tgn:2002280",
      "tgn:7013961",
      "tgn:7029392"
    ],
    "placetype": [
      "aat:300008699"
    ],
    "id": 2173760,
    "name:xx": "Bird Branch"
  }
}
