{
  "geometry": {
    "type": "Point",
    "coordinates": [
      -97.4833,
      39.2667
    ]
  },
  "type": "Feature",
  "properties": {
    "hierarchy": [
      "tgn:2758488",
      "tgn:1000001",
      "tgn:7012149",
      "tgn:7007254",
      "tgn:7029392"
    ],
    "placetype": [
      "aat:300008706"
    ],
    "id": 2758488,
    "name:xx": "West Chapman Creek"
  }
}
