{
  "geometry": {
    "type": "Point",
    "coordinates": [
      -110.95,
      45.7333
    ]
  },
  "type": "Feature",
  "properties": {
    "hierarchy": [
      "tgn:2476891",
      "tgn:1000001",
      "tgn:7012149",
      "tgn:2001275",
      "tgn:7007524",
      "tgn:7029392"
    ],
    "placetype": [
      "aat:300008706"
    ],
    "id": 2476891,
    "name:xx": "Lyman Creek"
  }
}
