{
  "geometry": {
    "type": "Point",
    "coordinates": [
      -80.5833,
      36.9667
    ]
  },
  "type": "Feature",
  "properties": {
    "hierarchy": [
      "tgn:2162635",
      "tgn:1000001",
      "tgn:7012149",
      "tgn:2002183",
      "tgn:7007919",
      "tgn:7029392"
    ],
    "placetype": [
      "aat:300008798"
    ],
    "id": 2162635,
    "name:xx": "Bench Mountain"
  }
}
