{
  "type": "FeatureCollection",
  "features": [
    {
      "geometry": {
        "type": "Point",
        "coordinates": [
          -2.477515,
          43.254092
        ]
      },
      "type": "Feature",
      "properties": {
        "hierarchy": [
          "tgn:7325771",
          "tgn:7002849",
          "tgn:1000003",
          "tgn:7009604",
          "tgn:1000095",
          "tgn:7029392"
        ],
        "placetype": [
          "aat:300008347"
        ],
        "id": 7325771,
        "name:xx": "San Andrés de Echevarría"
      }
    },
    {
      "geometry": {
        "type": "Point",
        "coordinates": [
          -4.383333,
          42.7
        ]
      },
      "type": "Feature",
      "properties": {
        "hierarchy": [
          "tgn:7325772",
          "tgn:7002832",
          "tgn:7001158",
          "tgn:1000003",
          "tgn:1000095",
          "tgn:7029392"
        ],
        "placetype": [
          "aat:300008347"
        ],
        "id": 7325772,
        "name:xx": "San Andrés de Arroyo"
      }
    },
    {
      "geometry": {
        "type": "Point",
        "coordinates": [
          -3.016667,
          40.566667
        ]
      },
      "type": "Feature",
      "properties": {
        "hierarchy": [
          "tgn:7325773",
          "tgn:7002822",
          "tgn:1001647",
          "tgn:1000003",
          "tgn:1000095",
          "tgn:7029392"
        ],
        "placetype": [
          "aat:300008699"
        ],
        "id": 7325773,
        "name:xx": "San Andrés, Río de"
      }
    },
    {
      "geometry": {
        "type": "Point",
        "coordinates": [
          -4.7,
          36.7
        ]
      },
      "type": "Feature",
      "properties": {
        "hierarchy": [
          "tgn:7325774",
          "tgn:7002758",
          "tgn:7002830",
          "tgn:1000003",
          "tgn:1000095",
          "tgn:7029392"
        ],
        "placetype": [
          "aat:300008816"
        ],
        "id": 7325774,
        "name:xx": "San Andrés, Playa de"
      }
    },
    {
      "geometry": {
        "type": "Point",
        "coordinates": [
          -1.866667,
          36.983333
        ]
      },
      "type": "Feature",
      "properties": {
        "hierarchy": [
          "tgn:7325775",
          "tgn:7002805",
          "tgn:7002758",
          "tgn:1000003",
          "tgn:1000095",
          "tgn:7029392"
        ],
        "placetype": [
          "aat:300008791"
        ],
        "id": 7325775,
        "name:xx": "San Andrés, Isla de"
      }
    },
    {
      "geometry": {
        "type": "Point",
        "coordinates": [
          -0.916667,
          42.283333
        ]
      },
      "type": "Feature",
      "properties": {
        "hierarchy": [
          "tgn:7325776",
          "tgn:7002759",
          "tgn:7002845",
          "tgn:1000003",
          "tgn:1000095",
          "tgn:7029392"
        ],
        "placetype": [
          "aat:300266554",
          "aat:300008699"
        ],
        "id": 7325776,
        "name:xx": "San Andrés, Barranco de"
      }
    },
    {
      "geometry": {
        "type": "Point",
        "coordinates": [
          -3.9,
          41.7
        ]
      },
      "type": "Feature",
      "properties": {
        "hierarchy": [
          "tgn:7325777",
          "tgn:7002810",
          "tgn:7001158",
          "tgn:1000003",
          "tgn:1000095",
          "tgn:7029392"
        ],
        "placetype": [
          "aat:300008699"
        ],
        "id": 7325777,
        "name:xx": "San Andrés, Arroyo de"
      }
    },
    {
      "geometry": {
        "type": "Point",
        "coordinates": [
          -2.746004,
          43.409103
        ]
      },
      "type": "Feature",
      "properties": {
        "hierarchy": [
          "tgn:7325778",
          "tgn:7002849",
          "tgn:1000003",
          "tgn:7009604",
          "tgn:1000095",
          "tgn:7029392"
        ],
        "placetype": [
          "aat:300008347"
        ],
        "id": 7325778,
        "name:xx": "San Andrés"
      }
    },
    {
      "geometry": {
        "type": "Point",
        "coordinates": [
          -7.15,
          43.4
        ]
      },
      "type": "Feature",
      "properties": {
        "hierarchy": [
          "tgn:7325779",
          "tgn:7008911",
          "tgn:1000003",
          "tgn:7002763",
          "tgn:1000095",
          "tgn:7029392"
        ],
        "placetype": [
          "aat:300008347"
        ],
        "id": 7325779,
        "name:xx": "San Andrés"
      }
    }
  ]
}
