{
  "geometry": {
    "type": "Point",
    "coordinates": [
      -116.95,
      42.4333
    ]
  },
  "type": "Feature",
  "properties": {
    "hierarchy": [
      "tgn:2212727",
      "tgn:1000001",
      "tgn:7012149",
      "tgn:2000488",
      "tgn:7007250",
      "tgn:7029392"
    ],
    "placetype": [
      "aat:300008697"
    ],
    "id": 2212727,
    "name:xx": "C C C Spring"
  }
}
