{
  "geometry": {
    "type": "Point",
    "coordinates": [
      -80.3833,
      34.3333
    ]
  },
  "type": "Feature",
  "properties": {
    "hierarchy": [
      "tgn:2608009",
      "tgn:1000001",
      "tgn:7012149",
      "tgn:2001752",
      "tgn:7007712",
      "tgn:7029392"
    ],
    "placetype": [
      "aat:300006191"
    ],
    "id": 2608009,
    "name:xx": "Ratliff Millpond"
  }
}
