{
  "geometry": {
    "type": "Point",
    "coordinates": [
      -122.8833,
      47.0667
    ]
  },
  "type": "Feature",
  "properties": {
    "hierarchy": [
      "tgn:2315524",
      "tgn:1000001",
      "tgn:7012149",
      "tgn:1002942",
      "tgn:7007920",
      "tgn:7029392"
    ],
    "placetype": [
      "aat:300132316"
    ],
    "id": 2315524,
    "name:xx": "Ellis Cove"
  }
}
