{
  "geometry": {
    "type": "Point",
    "coordinates": [
      -119.35,
      36.3167
    ]
  },
  "type": "Feature",
  "properties": {
    "hierarchy": [
      "tgn:2576596",
      "tgn:1000001",
      "tgn:7012149",
      "tgn:7007157",
      "tgn:1002956",
      "tgn:7029392"
    ],
    "placetype": [
      "aat:300006075"
    ],
    "id": 2576596,
    "name:xx": "Persian Ditch"
  }
}
