{
  "geometry": {
    "type": "Point",
    "coordinates": [
      -122.2167,
      48.0167
    ]
  },
  "type": "Feature",
  "properties": {
    "hierarchy": [
      "tgn:2598760",
      "tgn:1000001",
      "tgn:7012149",
      "tgn:1002899",
      "tgn:7007920",
      "tgn:7029392"
    ],
    "placetype": [
      "aat:300008850"
    ],
    "id": 2598760,
    "name:xx": "Priest Point"
  }
}
