{
  "geometry": {
    "type": "Point",
    "coordinates": [
      113.75,
      41.1833
    ]
  },
  "type": "Feature",
  "properties": {
    "hierarchy": [
      "tgn:1067430",
      "tgn:1000004",
      "tgn:7001838",
      "tgn:1000111",
      "tgn:7029392"
    ],
    "placetype": [
      "aat:300008347"
    ],
    "id": 1067430,
    "name:xx": "Dalengtu"
  }
}
