{
  "geometry": {
    "type": "Point",
    "coordinates": [
      14.3833,
      -4.2333
    ]
  },
  "type": "Feature",
  "properties": {
    "hierarchy": [
      "tgn:1088695",
      "tgn:7001242",
      "tgn:1001023",
      "tgn:1000158",
      "tgn:7029392"
    ],
    "placetype": [
      "aat:300008347"
    ],
    "id": 1088695,
    "name:xx": "Mindouli"
  }
}
