{
  "geometry": {
    "type": "Point",
    "coordinates": [
      -106.75,
      37.1833
    ]
  },
  "type": "Feature",
  "properties": {
    "hierarchy": [
      "tgn:2559644",
      "tgn:2000195",
      "tgn:1000001",
      "tgn:7012149",
      "tgn:7007158",
      "tgn:7029392"
    ],
    "placetype": [
      "aat:300008680"
    ],
    "id": 2559644,
    "name:xx": "Opal Lake"
  }
}
