{
  "geometry": {
    "type": "Point",
    "coordinates": [
      -74.85,
      42.2833
    ]
  },
  "type": "Feature",
  "properties": {
    "hierarchy": [
      "tgn:2187332",
      "tgn:1000001",
      "tgn:1002328",
      "tgn:7012149",
      "tgn:7007568",
      "tgn:7029392"
    ],
    "placetype": [
      "aat:300008798"
    ],
    "id": 2187332,
    "name:xx": "Boomhower Hill"
  }
}
