{
  "geometry": {
    "type": "Point",
    "coordinates": [
      -93.2167,
      39.3167
    ]
  },
  "type": "Feature",
  "properties": {
    "hierarchy": [
      "tgn:2059722",
      "tgn:1000001",
      "tgn:7012149",
      "tgn:2001243",
      "tgn:7007523",
      "tgn:7029392"
    ],
    "placetype": [
      "aat:300008347"
    ],
    "id": 2059722,
    "name:xx": "Miami"
  }
}
