{
  "geometry": {
    "type": "Point",
    "coordinates": [
      -95.5833,
      45.3833
    ]
  },
  "type": "Feature",
  "properties": {
    "hierarchy": [
      "tgn:2260910",
      "tgn:1000001",
      "tgn:7012149",
      "tgn:2001074",
      "tgn:7007521",
      "tgn:7029392"
    ],
    "placetype": [
      "aat:300006075"
    ],
    "id": 2260910,
    "name:xx": "County Ditch Number Thirteen"
  }
}
