{
  "geometry": {
    "type": "Point",
    "coordinates": [
      -109.6333,
      47.6667
    ]
  },
  "type": "Feature",
  "properties": {
    "hierarchy": [
      "tgn:2613377",
      "tgn:1000001",
      "tgn:7012149",
      "tgn:2001273",
      "tgn:7007524",
      "tgn:7029392"
    ],
    "placetype": [
      "aat:300008798"
    ],
    "id": 2613377,
    "name:xx": "Reed Hill"
  }
}
