{
  "geometry": {
    "type": "Point",
    "coordinates": [
      49.45,
      56.25
    ]
  },
  "type": "Feature",
  "properties": {
    "hierarchy": [
      "tgn:1052876",
      "tgn:1000004",
      "tgn:7002435",
      "tgn:7011524",
      "tgn:7029392"
    ],
    "placetype": [
      "aat:300008347"
    ],
    "id": 1052876,
    "name:xx": "Bol'shaya Atnya"
  }
}
