{
  "geometry": {
    "type": "Point",
    "coordinates": [
      -109.9833,
      41.7333
    ]
  },
  "type": "Feature",
  "properties": {
    "hierarchy": [
      "tgn:2653391",
      "tgn:1000001",
      "tgn:7012149",
      "tgn:2002383",
      "tgn:7007923",
      "tgn:7029392"
    ],
    "placetype": [
      "aat:300008761"
    ],
    "id": 2653391,
    "name:xx": "Sevenmile Gulch"
  }
}
