{
  "geometry": {
    "type": "Point",
    "coordinates": [
      -97.4167,
      35.3333
    ]
  },
  "type": "Feature",
  "properties": {
    "hierarchy": [
      "tgn:2439747",
      "tgn:1000001",
      "tgn:2001636",
      "tgn:7012149",
      "tgn:7007707",
      "tgn:7029392"
    ],
    "placetype": [
      "aat:300006191"
    ],
    "id": 2439747,
    "name:xx": "Kitchen Lake"
  }
}
