{
  "type": "FeatureCollection",
  "features": [
    {
      "geometry": {
        "type": "Point",
        "coordinates": [
          -2.166667,
          37.583333
        ]
      },
      "type": "Feature",
      "properties": {
        "hierarchy": [
          "tgn:7343830",
          "tgn:7002805",
          "tgn:7002758",
          "tgn:1000003",
          "tgn:1000095",
          "tgn:7029392"
        ],
        "placetype": [
          "aat:300259572"
        ],
        "id": 7343830,
        "name:xx": "Campillo, Collado del"
      }
    },
    {
      "geometry": {
        "type": "Point",
        "coordinates": [
          -3,
          38.25
        ]
      },
      "type": "Feature",
      "properties": {
        "hierarchy": [
          "tgn:7343831",
          "tgn:7002758",
          "tgn:1001316",
          "tgn:1000003",
          "tgn:1000095",
          "tgn:7029392"
        ],
        "placetype": [
          "aat:300266554",
          "aat:300008699"
        ],
        "id": 7343831,
        "name:xx": "Campillo, Arroyo del"
      }
    },
    {
      "geometry": {
        "type": "Point",
        "coordinates": [
          -5.3,
          42.933333
        ]
      },
      "type": "Feature",
      "properties": {
        "hierarchy": [
          "tgn:7343832",
          "tgn:7002826",
          "tgn:7001158",
          "tgn:1000003",
          "tgn:1000095",
          "tgn:7029392"
        ],
        "placetype": [
          "aat:300008347"
        ],
        "id": 7343832,
        "name:xx": "Campillo"
      }
    },
    {
      "geometry": {
        "type": "Point",
        "coordinates": [
          -5.95,
          41.583333
        ]
      },
      "type": "Feature",
      "properties": {
        "hierarchy": [
          "tgn:7343833",
          "tgn:7001158",
          "tgn:7002850",
          "tgn:1000003",
          "tgn:1000095",
          "tgn:7029392"
        ],
        "placetype": [
          "aat:300008347"
        ],
        "id": 7343833,
        "name:xx": "Campillo"
      }
    },
    {
      "geometry": {
        "type": "Point",
        "coordinates": [
          -4.25,
          40.866667
        ]
      },
      "type": "Feature",
      "properties": {
        "hierarchy": [
          "tgn:7343834",
          "tgn:7002839",
          "tgn:7001158",
          "tgn:1000003",
          "tgn:1000095",
          "tgn:7029392"
        ],
        "placetype": [
          "aat:300008347"
        ],
        "id": 7343834,
        "name:xx": "Campillo"
      }
    },
    {
      "geometry": {
        "type": "Point",
        "coordinates": [
          -2.566667,
          38.433333
        ]
      },
      "type": "Feature",
      "properties": {
        "hierarchy": [
          "tgn:7343836",
          "tgn:7002803",
          "tgn:1001647",
          "tgn:1000003",
          "tgn:1000095",
          "tgn:7029392"
        ],
        "placetype": [
          "aat:300008347"
        ],
        "id": 7343836,
        "name:xx": "Campillo"
      }
    },
    {
      "geometry": {
        "type": "Point",
        "coordinates": [
          -5.533333,
          42.4
        ]
      },
      "type": "Feature",
      "properties": {
        "hierarchy": [
          "tgn:7343837",
          "tgn:7002826",
          "tgn:7001158",
          "tgn:1000003",
          "tgn:1000095",
          "tgn:7029392"
        ],
        "placetype": [
          "aat:300008347"
        ],
        "id": 7343837,
        "name:xx": "Cabreros del Río"
      }
    },
    {
      "geometry": {
        "type": "Point",
        "coordinates": [
          -5.266667,
          41.85
        ]
      },
      "type": "Feature",
      "properties": {
        "hierarchy": [
          "tgn:7343838",
          "tgn:7001158",
          "tgn:7002848",
          "tgn:1000003",
          "tgn:1000095",
          "tgn:7029392"
        ],
        "placetype": [
          "aat:300008347"
        ],
        "id": 7343838,
        "name:xx": "Cabreros del Monte"
      }
    },
    {
      "geometry": {
        "type": "Point",
        "coordinates": [
          -2,
          37.416667
        ]
      },
      "type": "Feature",
      "properties": {
        "hierarchy": [
          "tgn:7343839",
          "tgn:7002805",
          "tgn:7002758",
          "tgn:1000003",
          "tgn:1000095",
          "tgn:7029392"
        ],
        "placetype": [
          "aat:300266554",
          "aat:300008699"
        ],
        "id": 7343839,
        "name:xx": "Cabreros, Rambla de Los"
      }
    }
  ]
}
