{
  "geometry": {
    "type": "Point",
    "coordinates": [
      -109.9667,
      34.2667
    ]
  },
  "type": "Feature",
  "properties": {
    "hierarchy": [
      "tgn:2764538",
      "tgn:1000001",
      "tgn:7006451",
      "tgn:7012149",
      "tgn:2000099",
      "tgn:7029392"
    ],
    "placetype": [
      "aat:300008680"
    ],
    "id": 2764538,
    "name:xx": "Whipple Lake"
  }
}
