{
  "type": "FeatureCollection",
  "features": [
    {
      "geometry": {
        "type": "Point",
        "coordinates": [
          -81,
          36.2
        ]
      },
      "type": "Feature",
      "properties": {
        "hierarchy": [
          "tgn:2076370",
          "tgn:1000001",
          "tgn:7012149",
          "tgn:2001553",
          "tgn:7007709",
          "tgn:7029392"
        ],
        "placetype": [
          "aat:300008347"
        ],
        "id": 2076370,
        "name:xx": "Roaring River"
      }
    },
    {
      "geometry": {
        "type": "Point",
        "coordinates": [
          -79.5833,
          35.4333
        ]
      },
      "type": "Feature",
      "properties": {
        "hierarchy": [
          "tgn:2076371",
          "tgn:1000001",
          "tgn:7012149",
          "tgn:2001521",
          "tgn:7007709",
          "tgn:7029392"
        ],
        "placetype": [
          "aat:300008347"
        ],
        "id": 2076371,
        "name:xx": "Robbins"
      }
    },
    {
      "geometry": {
        "type": "Point",
        "coordinates": [
          -83.8,
          35.3167
        ]
      },
      "type": "Feature",
      "properties": {
        "hierarchy": [
          "tgn:2076372",
          "tgn:1000001",
          "tgn:7012149",
          "tgn:2001497",
          "tgn:7007709",
          "tgn:7029392"
        ],
        "placetype": [
          "aat:300008347"
        ],
        "id": 2076372,
        "name:xx": "Robbinsville"
      }
    },
    {
      "geometry": {
        "type": "Point",
        "coordinates": [
          -79.7333,
          34.9667
        ]
      },
      "type": "Feature",
      "properties": {
        "hierarchy": [
          "tgn:2076375",
          "tgn:1000001",
          "tgn:7012149",
          "tgn:2001533",
          "tgn:7007709",
          "tgn:7029392"
        ],
        "placetype": [
          "aat:300008347"
        ],
        "id": 2076375,
        "name:xx": "Roberdel"
      }
    },
    {
      "geometry": {
        "type": "Point",
        "coordinates": [
          -79.95,
          35.3
        ]
      },
      "type": "Feature",
      "properties": {
        "hierarchy": [
          "tgn:2076376",
          "tgn:1000001",
          "tgn:7012149",
          "tgn:2001520",
          "tgn:7007709",
          "tgn:7029392"
        ],
        "placetype": [
          "aat:300008347",
          "aat:300387210"
        ],
        "id": 2076376,
        "name:xx": "Roberdo"
      }
    },
    {
      "geometry": {
        "type": "Point",
        "coordinates": [
          -76.9667,
          35.7333
        ]
      },
      "type": "Feature",
      "properties": {
        "hierarchy": [
          "tgn:2076377",
          "tgn:1000001",
          "tgn:7012149",
          "tgn:2001517",
          "tgn:7007709",
          "tgn:7029392"
        ],
        "placetype": [
          "aat:300008347",
          "aat:300387210"
        ],
        "id": 2076377,
        "name:xx": "Roberson Store"
      }
    },
    {
      "geometry": {
        "type": "Point",
        "coordinates": [
          -77.2333,
          35.8167
        ]
      },
      "type": "Feature",
      "properties": {
        "hierarchy": [
          "tgn:2076378",
          "tgn:1000001",
          "tgn:7012149",
          "tgn:2001517",
          "tgn:7007709",
          "tgn:7029392"
        ],
        "placetype": [
          "aat:300008347"
        ],
        "id": 2076378,
        "name:xx": "Robersonville"
      }
    }
  ]
}
