{
  "geometry": {
    "type": "Point",
    "coordinates": [
      -2.5167,
      53.2167
    ]
  },
  "type": "Feature",
  "properties": {
    "hierarchy": [
      "tgn:1030100",
      "tgn:7002445",
      "tgn:7008114",
      "tgn:1000003",
      "tgn:7008591",
      "tgn:7029392"
    ],
    "placetype": [
      "aat:300008347"
    ],
    "id": 1030100,
    "name:ang": "Moletune"
  }
}
