{
  "type": "FeatureCollection",
  "features": [
    {
      "geometry": {
        "type": "Point",
        "coordinates": [
          -97.1833,
          39.3167
        ]
      },
      "type": "Feature",
      "properties": {
        "hierarchy": [
          "tgn:2736190",
          "tgn:1000001",
          "tgn:2000673",
          "tgn:7012149",
          "tgn:7007254",
          "tgn:7029392"
        ],
        "placetype": [
          "aat:300008798"
        ],
        "id": 2736190,
        "name:xx": "Twin Mounds"
      }
    },
    {
      "geometry": {
        "type": "Point",
        "coordinates": [
          -97.4833,
          38.5167
        ]
      },
      "type": "Feature",
      "properties": {
        "hierarchy": [
          "tgn:2736191",
          "tgn:1000001",
          "tgn:7012149",
          "tgn:2000716",
          "tgn:7007254",
          "tgn:7029392"
        ],
        "placetype": [
          "aat:300008798"
        ],
        "id": 2736191,
        "name:xx": "Twin Mounds"
      }
    },
    {
      "geometry": {
        "type": "Point",
        "coordinates": [
          -95.4833,
          38.85
        ]
      },
      "type": "Feature",
      "properties": {
        "hierarchy": [
          "tgn:2736192",
          "tgn:1000001",
          "tgn:2000682",
          "tgn:7012149",
          "tgn:7007254",
          "tgn:7029392"
        ],
        "placetype": [
          "aat:300008798"
        ],
        "id": 2736192,
        "name:xx": "Twin Mounds"
      }
    },
    {
      "geometry": {
        "type": "Point",
        "coordinates": [
          -89.1333,
          37.0667
        ]
      },
      "type": "Feature",
      "properties": {
        "hierarchy": [
          "tgn:2736193",
          "tgn:2000767",
          "tgn:1000001",
          "tgn:7012149",
          "tgn:7007255",
          "tgn:7029392"
        ],
        "placetype": [
          "aat:300008798"
        ],
        "id": 2736193,
        "name:xx": "Twin Mounds"
      }
    },
    {
      "geometry": {
        "type": "Point",
        "coordinates": [
          -108.3,
          36.7333
        ]
      },
      "type": "Feature",
      "properties": {
        "hierarchy": [
          "tgn:2736194",
          "tgn:1000001",
          "tgn:7012149",
          "tgn:2001452",
          "tgn:7007566",
          "tgn:7029392"
        ],
        "placetype": [
          "aat:300008798"
        ],
        "id": 2736194,
        "name:xx": "Twin Mounds"
      }
    },
    {
      "geometry": {
        "type": "Point",
        "coordinates": [
          -98.6167,
          35.4333
        ]
      },
      "type": "Feature",
      "properties": {
        "hierarchy": [
          "tgn:2736195",
          "tgn:1000001",
          "tgn:2001630",
          "tgn:7012149",
          "tgn:7007707",
          "tgn:7029392"
        ],
        "placetype": [
          "aat:300008798"
        ],
        "id": 2736195,
        "name:xx": "Twin Mounds"
      }
    },
    {
      "geometry": {
        "type": "Point",
        "coordinates": [
          -96.0167,
          35.9167
        ]
      },
      "type": "Feature",
      "properties": {
        "hierarchy": [
          "tgn:2736196",
          "tgn:1000001",
          "tgn:7012149",
          "tgn:2001694",
          "tgn:7007707",
          "tgn:7029392"
        ],
        "placetype": [
          "aat:300008798"
        ],
        "id": 2736196,
        "name:xx": "Twin Mounds"
      }
    },
    {
      "geometry": {
        "type": "Point",
        "coordinates": [
          -96.7667,
          36.1
        ]
      },
      "type": "Feature",
      "properties": {
        "hierarchy": [
          "tgn:2736197",
          "tgn:1000001",
          "tgn:7012149",
          "tgn:2001682",
          "tgn:7007707",
          "tgn:7029392"
        ],
        "placetype": [
          "aat:300008798"
        ],
        "id": 2736197,
        "name:xx": "Twin Mounds"
      }
    },
    {
      "geometry": {
        "type": "Point",
        "coordinates": [
          -95.6167,
          36.4333
        ]
      },
      "type": "Feature",
      "properties": {
        "hierarchy": [
          "tgn:2736198",
          "tgn:1000001",
          "tgn:7012149",
          "tgn:2001688",
          "tgn:7007707",
          "tgn:7029392"
        ],
        "placetype": [
          "aat:300008798"
        ],
        "id": 2736198,
        "name:xx": "Twin Mounds"
      }
    },
    {
      "geometry": {
        "type": "Point",
        "coordinates": [
          -95.9667,
          36.5667
        ]
      },
      "type": "Feature",
      "properties": {
        "hierarchy": [
          "tgn:2736199",
          "tgn:1000001",
          "tgn:7012149",
          "tgn:2001696",
          "tgn:7007707",
          "tgn:7029392"
        ],
        "placetype": [
          "aat:300008798"
        ],
        "id": 2736199,
        "name:xx": "Twin Mounds"
      }
    }
  ]
}
