{
  "geometry": {
    "type": "Point",
    "coordinates": [
      -94.6333,
      35.3333
    ]
  },
  "type": "Feature",
  "properties": {
    "hierarchy": [
      "tgn:2334152",
      "tgn:1000001",
      "tgn:7012149",
      "tgn:2001690",
      "tgn:7007707",
      "tgn:7029392"
    ],
    "placetype": [
      "aat:300008347"
    ],
    "id": 2334152,
    "name:xx": "Foreman"
  }
}
