{
  "geometry": {
    "type": "Point",
    "coordinates": [
      -104.55,
      50.95
    ]
  },
  "type": "Feature",
  "properties": {
    "hierarchy": [
      "tgn:1016118",
      "tgn:7005685",
      "tgn:1000001",
      "tgn:7005805",
      "tgn:7029392"
    ],
    "placetype": [
      "aat:300008347"
    ],
    "id": 1016118,
    "name:xx": "Southey"
  }
}
