{
  "geometry": {
    "type": "Point",
    "coordinates": [
      -72.15,
      -35.25
    ]
  },
  "type": "Feature",
  "properties": {
    "hierarchy": [
      "tgn:7314529",
      "tgn:1001705",
      "tgn:1000049",
      "tgn:1000002",
      "tgn:7029392"
    ],
    "placetype": [
      "aat:300387002"
    ],
    "id": 7314529,
    "name:xx": "Limpia, Loma"
  }
}
