{
  "geometry": {
    "type": "Point",
    "coordinates": [
      36.083,
      -0.466
    ]
  },
  "type": "Feature",
  "properties": {
    "hierarchy": [
      "tgn:7593787",
      "tgn:7001242",
      "tgn:1000169",
      "tgn:7029392"
    ],
    "placetype": [
      "aat:300387064",
      "aat:300000771"
    ],
    "id": 7593787,
    "name:xx": "Nakuru"
  }
}
