{
  "geometry": {
    "type": "Point",
    "coordinates": [
      -80.5667,
      25.15
    ]
  },
  "type": "Feature",
  "properties": {
    "hierarchy": [
      "tgn:2570099",
      "tgn:1000001",
      "tgn:7012149",
      "tgn:1002676",
      "tgn:7007240",
      "tgn:7029392"
    ],
    "placetype": [
      "aat:300008791"
    ],
    "id": 2570099,
    "name:xx": "Pass Key"
  }
}
