{
  "geometry": {
    "type": "Point",
    "coordinates": [
      -122.0667,
      42.45
    ]
  },
  "type": "Feature",
  "properties": {
    "hierarchy": [
      "tgn:2574320",
      "tgn:1000001",
      "tgn:7012149",
      "tgn:2001714",
      "tgn:7007708",
      "tgn:7029392"
    ],
    "placetype": [
      "aat:300132316"
    ],
    "id": 2574320,
    "name:xx": "Pelican Bay"
  }
}
