{
  "type": "FeatureCollection",
  "features": [
    {
      "geometry": {
        "type": "Point",
        "coordinates": [
          23,
          52.5
        ]
      },
      "type": "Feature",
      "properties": {
        "hierarchy": [
          "tgn:1112120",
          "tgn:1000003",
          "tgn:7006366",
          "tgn:7029392"
        ],
        "placetype": [
          "aat:300387346"
        ],
        "id": 1112120,
        "name:xx": "Podlasie"
      }
    },
    {
      "geometry": {
        "type": "Point",
        "coordinates": [
          17.6667,
          45.6667
        ]
      },
      "type": "Feature",
      "properties": {
        "hierarchy": [
          "tgn:1112121",
          "tgn:1000003",
          "tgn:7006663",
          "tgn:7029392"
        ],
        "placetype": [
          "aat:300387346"
        ],
        "id": 1112121,
        "name:xx": "Podravina"
      }
    },
    {
      "geometry": {
        "type": "Point",
        "coordinates": [
          -2.9833,
          48.0667
        ]
      },
      "type": "Feature",
      "properties": {
        "hierarchy": [
          "tgn:1112124",
          "tgn:1000003",
          "tgn:7012216",
          "tgn:1000070",
          "tgn:7029392"
        ],
        "placetype": [
          "aat:300387346"
        ],
        "id": 1112124,
        "name:xx": "Pontivy"
      }
    },
    {
      "geometry": {
        "type": "Point",
        "coordinates": [
          12.2667,
          41.8
        ]
      },
      "type": "Feature",
      "properties": {
        "hierarchy": [
          "tgn:1112125",
          "tgn:7003138",
          "tgn:1000003",
          "tgn:7003080",
          "tgn:1000080",
          "tgn:7029392"
        ],
        "placetype": [
          "aat:300132350",
          "aat:300236112"
        ],
        "id": 1112125,
        "name:xx": "Porto, Bonifica di"
      }
    },
    {
      "geometry": {
        "type": "Point",
        "coordinates": [
          16.1667,
          46.6667
        ]
      },
      "type": "Feature",
      "properties": {
        "hierarchy": [
          "tgn:1112126",
          "tgn:1000003",
          "tgn:7006670",
          "tgn:7029392"
        ],
        "placetype": [
          "aat:300387346"
        ],
        "id": 1112126,
        "name:xx": "Prekmurje"
      }
    },
    {
      "geometry": {
        "type": "Point",
        "coordinates": [
          12,
          53
        ]
      },
      "type": "Feature",
      "properties": {
        "hierarchy": [
          "tgn:1112127",
          "tgn:7000096",
          "tgn:1000003",
          "tgn:7000084",
          "tgn:7029392"
        ],
        "placetype": [
          "aat:300387346"
        ],
        "id": 1112127,
        "name:xx": "Prignitz"
      }
    },
    {
      "geometry": {
        "type": "Point",
        "coordinates": [
          4.9833,
          52.4833
        ]
      },
      "type": "Feature",
      "properties": {
        "hierarchy": [
          "tgn:1112128",
          "tgn:1000003",
          "tgn:7016845",
          "tgn:7029392"
        ],
        "placetype": [
          "aat:300387346"
        ],
        "id": 1112128,
        "name:xx": "Purmer"
      }
    },
    {
      "geometry": {
        "type": "Point",
        "coordinates": [
          12,
          -72.5
        ]
      },
      "type": "Feature",
      "properties": {
        "hierarchy": [
          "tgn:1112129",
          "tgn:1000007",
          "tgn:7029392"
        ],
        "placetype": [
          "aat:300387346"
        ],
        "id": 1112129,
        "name:xx": "Queen Maud Land"
      }
    }
  ]
}
