{
  "geometry": {
    "type": "Point",
    "coordinates": [
      -76.7333,
      34.8333
    ]
  },
  "type": "Feature",
  "properties": {
    "hierarchy": [
      "tgn:2377124",
      "tgn:1000001",
      "tgn:7012149",
      "tgn:7007709",
      "tgn:7029392"
    ],
    "placetype": [
      "aat:300006075"
    ],
    "id": 2377124,
    "name:xx": "Harlowe Canal"
  }
}
