{
  "geometry": {
    "type": "Point",
    "coordinates": [
      -106.2167,
      36.8667
    ]
  },
  "type": "Feature",
  "properties": {
    "hierarchy": [
      "tgn:2619355",
      "tgn:1000001",
      "tgn:7012149",
      "tgn:2001449",
      "tgn:7007566",
      "tgn:7029392"
    ],
    "placetype": [
      "aat:300006191"
    ],
    "id": 2619355,
    "name:xx": "Rim Rock Tank"
  }
}
