{
  "geometry": {
    "type": "Point",
    "coordinates": [
      -57.583,
      3.383
    ]
  },
  "type": "Feature",
  "properties": {
    "hierarchy": [
      "tgn:1127738",
      "tgn:7002574",
      "tgn:1000054",
      "tgn:1000002",
      "tgn:7029392"
    ],
    "placetype": [
      "aat:300008707"
    ],
    "id": 1127738,
    "name:xx": "New River"
  }
}
