{
  "geometry": {
    "type": "Point",
    "coordinates": [
      -94.3333,
      37.15
    ]
  },
  "type": "Feature",
  "properties": {
    "hierarchy": [
      "tgn:2060126",
      "tgn:1000001",
      "tgn:7012149",
      "tgn:2001209",
      "tgn:7007523",
      "tgn:7029392"
    ],
    "placetype": [
      "aat:300008347"
    ],
    "id": 2060126,
    "name:xx": "Pleasant Valley"
  }
}
