{
  "geometry": {
    "type": "Point",
    "coordinates": [
      -92.6667,
      47.6333
    ]
  },
  "type": "Feature",
  "properties": {
    "hierarchy": [
      "tgn:2162153",
      "tgn:1000001",
      "tgn:7012149",
      "tgn:2001067",
      "tgn:7007521",
      "tgn:7029392"
    ],
    "placetype": [
      "aat:300008680"
    ],
    "id": 2162153,
    "name:xx": "Belmont Lake"
  }
}
