{
  "geometry": {
    "type": "Point",
    "coordinates": [
      -89.0167,
      42.3333
    ]
  },
  "type": "Feature",
  "properties": {
    "hierarchy": [
      "tgn:2028203",
      "tgn:1000001",
      "tgn:7012149",
      "tgn:1003030",
      "tgn:7007251",
      "tgn:7029392"
    ],
    "placetype": [
      "aat:300008347"
    ],
    "id": 2028203,
    "name:xx": "Harlem"
  }
}
