{
  "geometry": {
    "type": "Point",
    "coordinates": [
      -83.55,
      36.6667
    ]
  },
  "type": "Feature",
  "properties": {
    "hierarchy": [
      "tgn:2242902",
      "tgn:1000001",
      "tgn:2000769",
      "tgn:7012149",
      "tgn:7007255",
      "tgn:7029392"
    ],
    "placetype": [
      "aat:300008699"
    ],
    "id": 2242902,
    "name:xx": "Clear Fork"
  }
}
