{
  "geometry": {
    "type": "Point",
    "coordinates": [
      76.64381,
      32.051075
    ]
  },
  "type": "Feature",
  "properties": {
    "hierarchy": [
      "tgn:7546113",
      "tgn:1000004",
      "tgn:7000198",
      "tgn:1001996",
      "tgn:7029392"
    ],
    "placetype": [
      "aat:300008347"
    ],
    "name:en": "Baijnāth",
    "id": 7546113
  }
}
