{
  "geometry": {
    "type": "Point",
    "coordinates": [
      124.15,
      6.2833
    ]
  },
  "type": "Feature",
  "properties": {
    "hierarchy": [
      "tgn:1084355",
      "tgn:1000004",
      "tgn:1001551",
      "tgn:1000135",
      "tgn:7029392"
    ],
    "placetype": [
      "aat:300008347"
    ],
    "id": 1084355,
    "name:xx": "Ligao"
  }
}
