{
  "geometry": {
    "type": "Point",
    "coordinates": [
      13.416,
      48.983
    ]
  },
  "type": "Feature",
  "properties": {
    "hierarchy": [
      "tgn:1105593",
      "tgn:7593919",
      "tgn:1000003",
      "tgn:1001780",
      "tgn:7029392"
    ],
    "placetype": [
      "aat:300008795"
    ],
    "id": 1105593,
    "name:xx": "Medvědí hora"
  }
}
