{
  "geometry": {
    "type": "Point",
    "coordinates": [
      -81.6833,
      30.7833
    ]
  },
  "type": "Feature",
  "properties": {
    "hierarchy": [
      "tgn:2367300",
      "tgn:1000001",
      "tgn:2000311",
      "tgn:7012149",
      "tgn:7007248",
      "tgn:7029392"
    ],
    "placetype": [
      "aat:300008347"
    ],
    "id": 2367300,
    "name:xx": "Gross Still"
  }
}
