{
  "geometry": {
    "type": "Point",
    "coordinates": [
      -88.3667,
      45.2167
    ]
  },
  "type": "Feature",
  "properties": {
    "hierarchy": [
      "tgn:2366609",
      "tgn:1000001",
      "tgn:7012149",
      "tgn:2002341",
      "tgn:7007922",
      "tgn:7029392"
    ],
    "placetype": [
      "aat:300008680"
    ],
    "id": 2366609,
    "name:xx": "Grindle Lake"
  }
}
