{
  "geometry": {
    "type": "Point",
    "coordinates": [
      -88.9833,
      30.1833
    ]
  },
  "type": "Feature",
  "properties": {
    "hierarchy": [
      "tgn:2441111",
      "tgn:1000001",
      "tgn:7012149",
      "tgn:2001109",
      "tgn:7007522",
      "tgn:7029392"
    ],
    "placetype": [
      "aat:300132348"
    ],
    "id": 2441111,
    "name:xx": "Knoll, The"
  }
}
