{
  "geometry": {
    "type": "Point",
    "coordinates": [
      -112.45,
      41.25
    ]
  },
  "type": "Feature",
  "properties": {
    "hierarchy": [
      "tgn:2486047",
      "tgn:1000001",
      "tgn:2002102",
      "tgn:7012149",
      "tgn:7007827",
      "tgn:7029392"
    ],
    "placetype": [
      "aat:300008798"
    ],
    "id": 2486047,
    "name:xx": "Lead Mountain"
  }
}
