{
  "geometry": {
    "type": "Point",
    "coordinates": [
      -112.8167,
      35.3167
    ]
  },
  "type": "Feature",
  "properties": {
    "hierarchy": [
      "tgn:2393344",
      "tgn:1000001",
      "tgn:7006451",
      "tgn:7012149",
      "tgn:2000103",
      "tgn:7029392"
    ],
    "placetype": [
      "aat:300006191"
    ],
    "id": 2393344,
    "name:xx": "Hoffman Tank"
  }
}
