{
  "geometry": {
    "type": "Point",
    "coordinates": [
      -93.35,
      45.7333
    ]
  },
  "type": "Feature",
  "properties": {
    "hierarchy": [
      "tgn:2446480",
      "tgn:1000001",
      "tgn:7012149",
      "tgn:2001031",
      "tgn:7007521",
      "tgn:7029392"
    ],
    "placetype": [
      "aat:300008680"
    ],
    "id": 2446480,
    "name:xx": "Lewis Lake"
  }
}
