{
  "type": "FeatureCollection",
  "features": [
    {
      "geometry": {
        "type": "Point",
        "coordinates": [
          -152.3333,
          57.4167
        ]
      },
      "type": "Feature",
      "properties": {
        "hierarchy": [
          "tgn:2735820",
          "tgn:7006450",
          "tgn:1000001",
          "tgn:2124012",
          "tgn:7012149",
          "tgn:7029392"
        ],
        "placetype": [
          "aat:300008680"
        ],
        "id": 2735820,
        "name:xx": "Twin Lakes"
      }
    },
    {
      "geometry": {
        "type": "Point",
        "coordinates": [
          -150.15,
          60.2667
        ]
      },
      "type": "Feature",
      "properties": {
        "hierarchy": [
          "tgn:2735821",
          "tgn:7006450",
          "tgn:1000001",
          "tgn:7019698",
          "tgn:7012149",
          "tgn:7029392"
        ],
        "placetype": [
          "aat:300008680"
        ],
        "id": 2735821,
        "name:xx": "Twin Lakes"
      }
    },
    {
      "geometry": {
        "type": "Point",
        "coordinates": [
          -146.85,
          61.9167
        ]
      },
      "type": "Feature",
      "properties": {
        "hierarchy": [
          "tgn:2735822",
          "tgn:7006450",
          "tgn:1000001",
          "tgn:7012149",
          "tgn:2000086",
          "tgn:7029392"
        ],
        "placetype": [
          "aat:300008680"
        ],
        "id": 2735822,
        "name:xx": "Twin Lakes"
      }
    },
    {
      "geometry": {
        "type": "Point",
        "coordinates": [
          -149.1333,
          66.0333
        ]
      },
      "type": "Feature",
      "properties": {
        "hierarchy": [
          "tgn:2735823",
          "tgn:7006450",
          "tgn:1000001",
          "tgn:7012149",
          "tgn:2000089",
          "tgn:7029392"
        ],
        "placetype": [
          "aat:300008680"
        ],
        "id": 2735823,
        "name:xx": "Twin Lakes"
      }
    },
    {
      "geometry": {
        "type": "Point",
        "coordinates": [
          -153.85,
          60.6333
        ]
      },
      "type": "Feature",
      "properties": {
        "hierarchy": [
          "tgn:2735824",
          "tgn:7006450",
          "tgn:1000001",
          "tgn:7030517",
          "tgn:7012149",
          "tgn:7029392"
        ],
        "placetype": [
          "aat:300008680"
        ],
        "id": 2735824,
        "name:xx": "Twin Lakes"
      }
    },
    {
      "geometry": {
        "type": "Point",
        "coordinates": [
          -110.6333,
          34.25
        ]
      },
      "type": "Feature",
      "properties": {
        "hierarchy": [
          "tgn:2735825",
          "tgn:1000001",
          "tgn:7006451",
          "tgn:7012149",
          "tgn:2000099",
          "tgn:7029392"
        ],
        "placetype": [
          "aat:300008680"
        ],
        "id": 2735825,
        "name:xx": "Twin Lakes"
      }
    },
    {
      "geometry": {
        "type": "Point",
        "coordinates": [
          -111.95,
          35.9333
        ]
      },
      "type": "Feature",
      "properties": {
        "hierarchy": [
          "tgn:2735826",
          "tgn:1000001",
          "tgn:7006451",
          "tgn:2000092",
          "tgn:7012149",
          "tgn:7029392"
        ],
        "placetype": [
          "aat:300008680"
        ],
        "id": 2735826,
        "name:xx": "Twin Lakes"
      }
    },
    {
      "geometry": {
        "type": "Point",
        "coordinates": [
          -110.9,
          32.4833
        ]
      },
      "type": "Feature",
      "properties": {
        "hierarchy": [
          "tgn:2735827",
          "tgn:1000001",
          "tgn:7006451",
          "tgn:7012149",
          "tgn:2000100",
          "tgn:7029392"
        ],
        "placetype": [
          "aat:300008680"
        ],
        "id": 2735827,
        "name:xx": "Twin Lakes"
      }
    },
    {
      "geometry": {
        "type": "Point",
        "coordinates": [
          -91.1167,
          34.1667
        ]
      },
      "type": "Feature",
      "properties": {
        "hierarchy": [
          "tgn:2735828",
          "tgn:2000105",
          "tgn:1000001",
          "tgn:7016172",
          "tgn:7012149",
          "tgn:7029392"
        ],
        "placetype": [
          "aat:300008680"
        ],
        "id": 2735828,
        "name:xx": "Twin Lakes"
      }
    },
    {
      "geometry": {
        "type": "Point",
        "coordinates": [
          -92.3667,
          34.7333
        ]
      },
      "type": "Feature",
      "properties": {
        "hierarchy": [
          "tgn:2735829",
          "tgn:1000001",
          "tgn:7016172",
          "tgn:7012149",
          "tgn:2000164",
          "tgn:7029392"
        ],
        "placetype": [
          "aat:300006191"
        ],
        "id": 2735829,
        "name:xx": "Twin Lakes"
      }
    }
  ]
}
