{
  "geometry": {
    "type": "Point",
    "coordinates": [
      -79.9333,
      35.35
    ]
  },
  "type": "Feature",
  "properties": {
    "hierarchy": [
      "tgn:2670736",
      "tgn:1000001",
      "tgn:7012149",
      "tgn:2001520",
      "tgn:7007709",
      "tgn:7029392"
    ],
    "placetype": [
      "aat:300008699"
    ],
    "id": 2670736,
    "name:xx": "Smith Branch"
  }
}
