{
  "geometry": {
    "type": "Point",
    "coordinates": [
      32.179698,
      31.208237
    ]
  },
  "type": "Feature",
  "properties": {
    "hierarchy": [
      "tgn:7539914",
      "tgn:7001242",
      "tgn:7016833",
      "tgn:1001123",
      "tgn:7029392"
    ],
    "placetype": [
      "aat:300008791"
    ],
    "id": 7539914,
    "name:xx": "Samārīyāt, Barr as"
  }
}
