{
  "geometry": {
    "type": "Point",
    "coordinates": [
      -82.4833,
      27.2167
    ]
  },
  "type": "Feature",
  "properties": {
    "hierarchy": [
      "tgn:2021636",
      "tgn:1000001",
      "tgn:7012149",
      "tgn:1002870",
      "tgn:7007240",
      "tgn:7029392"
    ],
    "placetype": [
      "aat:300008347"
    ],
    "id": 2021636,
    "name:xx": "Vamo"
  }
}
