{
  "geometry": {
    "type": "Point",
    "coordinates": [
      126.9167,
      35.1667
    ]
  },
  "type": "Feature",
  "properties": {
    "hierarchy": [
      "tgn:7001323",
      "tgn:1000004",
      "tgn:7000299",
      "tgn:7029392"
    ],
    "placetype": [
      "aat:300387064",
      "aat:300387067"
    ],
    "id": 7001323,
    "name:xx": "Kwangju-si"
  }
}
