{
  "geometry": {
    "type": "Point",
    "coordinates": [
      -89.9167,
      36.3167
    ]
  },
  "type": "Feature",
  "properties": {
    "hierarchy": [
      "tgn:2288781",
      "tgn:1000001",
      "tgn:7012149",
      "tgn:7007523",
      "tgn:7029392"
    ],
    "placetype": [
      "aat:300006075"
    ],
    "id": 2288781,
    "name:xx": "Ditch Number 251"
  }
}
