{
  "geometry": {
    "type": "Point",
    "coordinates": [
      74.758333,
      34.325
    ]
  },
  "type": "Feature",
  "properties": {
    "hierarchy": [
      "tgn:7585888",
      "tgn:1000004",
      "tgn:7000198",
      "tgn:7000799",
      "tgn:7029392"
    ],
    "placetype": [
      "aat:300387200"
    ],
    "name:en": "Lārmarg",
    "id": 7585888
  }
}
