{
  "geometry": {
    "type": "Point",
    "coordinates": [
      -92.9167,
      38.0833
    ]
  },
  "type": "Feature",
  "properties": {
    "hierarchy": [
      "tgn:2319277",
      "tgn:1000001",
      "tgn:2001178",
      "tgn:7012149",
      "tgn:7007523",
      "tgn:7029392"
    ],
    "placetype": [
      "aat:300008761"
    ],
    "id": 2319277,
    "name:xx": "Estes Hollow"
  }
}
