{
  "geometry": {
    "type": "Point",
    "coordinates": [
      -122.8833,
      40.3333
    ]
  },
  "type": "Feature",
  "properties": {
    "hierarchy": [
      "tgn:2587138",
      "tgn:1000001",
      "tgn:7012149",
      "tgn:7007157",
      "tgn:2000188",
      "tgn:7029392"
    ],
    "placetype": [
      "aat:300008761"
    ],
    "id": 2587138,
    "name:xx": "Platinum Gulch"
  }
}
