{
  "geometry": {
    "type": "Point",
    "coordinates": [
      -79.6333,
      39.9167
    ]
  },
  "type": "Feature",
  "properties": {
    "hierarchy": [
      "tgn:2261776",
      "tgn:1000001",
      "tgn:7012149",
      "tgn:7014185",
      "tgn:7007710",
      "tgn:7029392"
    ],
    "placetype": [
      "aat:300008699"
    ],
    "id": 2261776,
    "name:xx": "Cove Run"
  }
}
