{
  "type": "FeatureCollection",
  "features": [
    {
      "geometry": {
        "type": "Point",
        "coordinates": [
          13.416667,
          43.483333
        ]
      },
      "type": "Feature",
      "properties": {
        "hierarchy": [
          "tgn:7050100",
          "tgn:1003429",
          "tgn:1000003",
          "tgn:7003240",
          "tgn:1000080",
          "tgn:7029392"
        ],
        "placetype": [
          "aat:300008347"
        ],
        "id": 7050100,
        "name:xx": "La Villa"
      }
    },
    {
      "geometry": {
        "type": "Point",
        "coordinates": [
          12.4,
          42.066667
        ]
      },
      "type": "Feature",
      "properties": {
        "hierarchy": [
          "tgn:7050101",
          "tgn:7003138",
          "tgn:1000003",
          "tgn:7003080",
          "tgn:1000080",
          "tgn:7029392"
        ],
        "placetype": [
          "aat:300008347"
        ],
        "id": 7050101,
        "name:xx": "La Villa"
      }
    },
    {
      "geometry": {
        "type": "Point",
        "coordinates": [
          11.316667,
          46.9
        ]
      },
      "type": "Feature",
      "properties": {
        "hierarchy": [
          "tgn:7050103",
          "tgn:1003440",
          "tgn:1000003",
          "tgn:7003124",
          "tgn:1000080",
          "tgn:7029392"
        ],
        "placetype": [
          "aat:300008347"
        ],
        "id": 7050103,
        "name:xx": "La Via"
      }
    },
    {
      "geometry": {
        "type": "Point",
        "coordinates": [
          11.483333,
          46.35
        ]
      },
      "type": "Feature",
      "properties": {
        "hierarchy": [
          "tgn:7050105",
          "tgn:1003440",
          "tgn:1000003",
          "tgn:7003124",
          "tgn:1000080",
          "tgn:7029392"
        ],
        "placetype": [
          "aat:300259572"
        ],
        "id": 7050105,
        "name:xx": "Lavezzè, Passo di"
      }
    },
    {
      "geometry": {
        "type": "Point",
        "coordinates": [
          11.933333,
          43.7
        ]
      },
      "type": "Feature",
      "properties": {
        "hierarchy": [
          "tgn:7050106",
          "tgn:7003162",
          "tgn:1000003",
          "tgn:7009760",
          "tgn:1000080",
          "tgn:7029392"
        ],
        "placetype": [
          "aat:300008347"
        ],
        "id": 7050106,
        "name:xx": "La Verna"
      }
    },
    {
      "geometry": {
        "type": "Point",
        "coordinates": [
          12.883333,
          43.133333
        ]
      },
      "type": "Feature",
      "properties": {
        "hierarchy": [
          "tgn:7050107",
          "tgn:1003471",
          "tgn:1000003",
          "tgn:7003240",
          "tgn:1000080",
          "tgn:7029392"
        ],
        "placetype": [
          "aat:300008347"
        ],
        "id": 7050107,
        "name:xx": "Laverino"
      }
    },
    {
      "geometry": {
        "type": "Point",
        "coordinates": [
          12.866667,
          43.15
        ]
      },
      "type": "Feature",
      "properties": {
        "hierarchy": [
          "tgn:7050108",
          "tgn:7003170",
          "tgn:1000003",
          "tgn:7003125",
          "tgn:1000080",
          "tgn:7029392"
        ],
        "placetype": [
          "aat:300008761"
        ],
        "id": 7050108,
        "name:xx": "Laverinello, Val di"
      }
    },
    {
      "geometry": {
        "type": "Point",
        "coordinates": [
          10.9,
          43.933333
        ]
      },
      "type": "Feature",
      "properties": {
        "hierarchy": [
          "tgn:7050109",
          "tgn:7003167",
          "tgn:1000003",
          "tgn:7009760",
          "tgn:1000080",
          "tgn:7029392"
        ],
        "placetype": [
          "aat:300008347"
        ],
        "id": 7050109,
        "name:xx": "La Vergine"
      }
    }
  ]
}
