{
  "geometry": {
    "type": "Point",
    "coordinates": [
      -85.1667,
      41.0167
    ]
  },
  "type": "Feature",
  "properties": {
    "hierarchy": [
      "tgn:2031866",
      "tgn:1002143",
      "tgn:1000001",
      "tgn:7013933",
      "tgn:7012149",
      "tgn:7007252",
      "tgn:7029392"
    ],
    "placetype": [
      "aat:300000745"
    ],
    "id": 2031866,
    "name:xx": "Waynedale"
  }
}
