{
  "geometry": {
    "type": "Point",
    "coordinates": [
      -79.55,
      40.85
    ]
  },
  "type": "Feature",
  "properties": {
    "hierarchy": [
      "tgn:2088653",
      "tgn:1002153",
      "tgn:1000001",
      "tgn:7012149",
      "tgn:7007710",
      "tgn:7029392"
    ],
    "placetype": [
      "aat:300008347"
    ],
    "id": 2088653,
    "name:xx": "Furnace Run"
  }
}
