{
  "geometry": {
    "type": "Point",
    "coordinates": [
      31.012578,
      31.5786
    ]
  },
  "type": "Feature",
  "properties": {
    "hierarchy": [
      "tgn:7532057",
      "tgn:7001242",
      "tgn:7016833",
      "tgn:1001335",
      "tgn:7029392"
    ],
    "placetype": [
      "aat:300008347"
    ],
    "name:en": "Aulâd el-Qâḍi",
    "id": 7532057
  }
}
