{
  "geometry": {
    "type": "Point",
    "coordinates": [
      -105.5833,
      42.35
    ]
  },
  "type": "Feature",
  "properties": {
    "hierarchy": [
      "tgn:2166174",
      "tgn:1000001",
      "tgn:7012149",
      "tgn:7007923",
      "tgn:7029392"
    ],
    "placetype": [
      "aat:300008761"
    ],
    "id": 2166174,
    "name:xx": "Big Bear Canyon"
  }
}
