{
  "geometry": {
    "type": "Point",
    "coordinates": [
      -85.8667,
      39.8667
    ]
  },
  "type": "Feature",
  "properties": {
    "hierarchy": [
      "tgn:2426441",
      "tgn:1000001",
      "tgn:7012149",
      "tgn:1002447",
      "tgn:7007252",
      "tgn:7029392"
    ],
    "placetype": [
      "aat:300006075"
    ],
    "id": 2426441,
    "name:xx": "Jones Ditch"
  }
}
