{
  "type": "FeatureCollection",
  "features": [
    {
      "geometry": {
        "type": "Point",
        "coordinates": [
          10.25,
          42.8
        ]
      },
      "type": "Feature",
      "properties": {
        "hierarchy": [
          "tgn:7059020",
          "tgn:7003164",
          "tgn:1000003",
          "tgn:7009760",
          "tgn:1000080",
          "tgn:7029392"
        ],
        "placetype": [
          "aat:300132315"
        ],
        "id": 7059020,
        "name:xx": "Biodola, Golfo della"
      }
    },
    {
      "geometry": {
        "type": "Point",
        "coordinates": [
          11.133333,
          42.633333
        ]
      },
      "type": "Feature",
      "properties": {
        "hierarchy": [
          "tgn:7059021",
          "tgn:1003460",
          "tgn:1000003",
          "tgn:7009760",
          "tgn:1000080",
          "tgn:7029392"
        ],
        "placetype": [
          "aat:300007783"
        ],
        "id": 7059021,
        "name:xx": "Stazione d' Alberese"
      }
    },
    {
      "geometry": {
        "type": "Point",
        "coordinates": [
          11.583333,
          45.716667
        ]
      },
      "type": "Feature",
      "properties": {
        "hierarchy": [
          "tgn:7059023",
          "tgn:7003008",
          "tgn:1000003",
          "tgn:7002997",
          "tgn:1000080",
          "tgn:7029392"
        ],
        "placetype": [
          "aat:300008795"
        ],
        "id": 7059023,
        "name:xx": "Alberelli, Monte"
      }
    },
    {
      "geometry": {
        "type": "Point",
        "coordinates": [
          12.283333,
          44.933333
        ]
      },
      "type": "Feature",
      "properties": {
        "hierarchy": [
          "tgn:7059024",
          "tgn:7002995",
          "tgn:1000003",
          "tgn:7002997",
          "tgn:1000080",
          "tgn:7029392"
        ],
        "placetype": [
          "aat:300008347"
        ],
        "id": 7059024,
        "name:xx": "Alberazzo"
      }
    },
    {
      "geometry": {
        "type": "Point",
        "coordinates": [
          11.516667,
          45
        ]
      },
      "type": "Feature",
      "properties": {
        "hierarchy": [
          "tgn:7059025",
          "tgn:7002995",
          "tgn:1000003",
          "tgn:7002997",
          "tgn:1000080",
          "tgn:7029392"
        ],
        "placetype": [
          "aat:300008347"
        ],
        "id": 7059025,
        "name:xx": "Alberazzi"
      }
    },
    {
      "geometry": {
        "type": "Point",
        "coordinates": [
          11.183333,
          42.5
        ]
      },
      "type": "Feature",
      "properties": {
        "hierarchy": [
          "tgn:7059028",
          "tgn:1003460",
          "tgn:1000003",
          "tgn:7009760",
          "tgn:1000080",
          "tgn:7029392"
        ],
        "placetype": [
          "aat:300387057"
        ],
        "id": 7059028,
        "name:xx": "Albegna, Bocca dell'"
      }
    }
  ]
}
