{
  "geometry": {
    "type": "Point",
    "coordinates": [
      -113.4333,
      38.0667
    ]
  },
  "type": "Feature",
  "properties": {
    "hierarchy": [
      "tgn:2568056",
      "tgn:1000001",
      "tgn:7012149",
      "tgn:2002111",
      "tgn:7007827",
      "tgn:7029392"
    ],
    "placetype": [
      "aat:300008697"
    ],
    "id": 2568056,
    "name:xx": "Paramore Spring"
  }
}
