{
  "geometry": {
    "type": "Point",
    "coordinates": [
      106.3667,
      30.7833
    ]
  },
  "type": "Feature",
  "properties": {
    "hierarchy": [
      "tgn:1072262",
      "tgn:1000004",
      "tgn:7002087",
      "tgn:1000111",
      "tgn:7029392"
    ],
    "placetype": [
      "aat:300008347"
    ],
    "id": 1072262,
    "name:xx": "Tiaodengchang"
  }
}
