{
  "geometry": {
    "type": "Point",
    "coordinates": [
      -93.7667,
      47.6833
    ]
  },
  "type": "Feature",
  "properties": {
    "hierarchy": [
      "tgn:2460146",
      "tgn:1000001",
      "tgn:7012149",
      "tgn:2001029",
      "tgn:7007521",
      "tgn:7029392"
    ],
    "placetype": [
      "aat:300008680"
    ],
    "id": 2460146,
    "name:xx": "Little Round Lake"
  }
}
