{
  "geometry": {
    "type": "Point",
    "coordinates": [
      77.829406,
      30.116518
    ]
  },
  "type": "Feature",
  "properties": {
    "hierarchy": [
      "tgn:7592362",
      "tgn:1000004",
      "tgn:7000198",
      "tgn:7016722",
      "tgn:7029392"
    ],
    "placetype": [
      "aat:300008865"
    ],
    "name:en": "Thāpal Dāndi Protected Forest",
    "id": 7592362
  }
}
