{
  "geometry": {
    "type": "Point",
    "coordinates": [
      32.561236,
      25.37962
    ]
  },
  "type": "Feature",
  "properties": {
    "hierarchy": [
      "tgn:7543428",
      "tgn:7001242",
      "tgn:7016833",
      "tgn:7000123",
      "tgn:7029392"
    ],
    "placetype": [
      "aat:300008347"
    ],
    "name:en": "Wābūrāt al Maţā'inah",
    "id": 7543428
  }
}
