{
  "geometry": {
    "type": "Point",
    "coordinates": [
      -135.4333,
      57.15
    ]
  },
  "type": "Feature",
  "properties": {
    "hierarchy": [
      "tgn:2662500",
      "tgn:7006450",
      "tgn:1000001",
      "tgn:7012149",
      "tgn:2124002",
      "tgn:7029392"
    ],
    "placetype": [
      "aat:300386853"
    ],
    "id": 2662500,
    "name:xx": "Siginaka Islands"
  }
}
