{
  "geometry": {
    "type": "Point",
    "coordinates": [
      -89.4167,
      38.2333
    ]
  },
  "type": "Feature",
  "properties": {
    "hierarchy": [
      "tgn:2700958",
      "tgn:1000001",
      "tgn:7012149",
      "tgn:1002991",
      "tgn:7007251",
      "tgn:7029392"
    ],
    "placetype": [
      "aat:300008706"
    ],
    "id": 2700958,
    "name:xx": "Sugar Creek"
  }
}
