{
  "geometry": {
    "type": "Point",
    "coordinates": [
      -82.8167,
      42.7333
    ]
  },
  "type": "Feature",
  "properties": {
    "hierarchy": [
      "tgn:2757747",
      "tgn:1000001",
      "tgn:7012149",
      "tgn:1002617",
      "tgn:7007520",
      "tgn:7029392"
    ],
    "placetype": [
      "aat:300008706"
    ],
    "id": 2757747,
    "name:xx": "West Branch Fish Creek"
  }
}
