{
  "geometry": {
    "type": "Point",
    "coordinates": [
      -118.3333,
      44.3833
    ]
  },
  "type": "Feature",
  "properties": {
    "hierarchy": [
      "tgn:2313403",
      "tgn:1000001",
      "tgn:7012149",
      "tgn:7007708",
      "tgn:7029392"
    ],
    "placetype": [
      "aat:300006075"
    ],
    "id": 2313403,
    "name:xx": "Eldorado Ditch"
  }
}
