{
  "geometry": {
    "type": "Point",
    "coordinates": [
      -82.1667,
      34.2167
    ]
  },
  "type": "Feature",
  "properties": {
    "hierarchy": [
      "tgn:2161681",
      "tgn:1000001",
      "tgn:2001748",
      "tgn:7012149",
      "tgn:7007712",
      "tgn:7029392"
    ],
    "placetype": [
      "aat:300008347"
    ],
    "id": 2161681,
    "name:xx": "Belle Meade"
  }
}
