{
  "geometry": {
    "type": "Point",
    "coordinates": [
      -160.5667,
      67.8833
    ]
  },
  "type": "Feature",
  "properties": {
    "hierarchy": [
      "tgn:2358241",
      "tgn:7006450",
      "tgn:1000001",
      "tgn:7012149",
      "tgn:2124014",
      "tgn:7029392"
    ],
    "placetype": [
      "aat:300008761"
    ],
    "id": 2358241,
    "name:xx": "Grand Canyon"
  }
}
