{
  "geometry": {
    "type": "Point",
    "coordinates": [
      -109.4833,
      39.0333
    ]
  },
  "type": "Feature",
  "properties": {
    "hierarchy": [
      "tgn:2699627",
      "tgn:1000001",
      "tgn:7012149",
      "tgn:2002110",
      "tgn:7007827",
      "tgn:7029392"
    ],
    "placetype": [
      "aat:300008680"
    ],
    "id": 2699627,
    "name:xx": "Strychnine Pond"
  }
}
