{
  "type": "FeatureCollection",
  "features": [
    {
      "geometry": {
        "type": "Point",
        "coordinates": [
          8.1,
          50.9
        ]
      },
      "type": "Feature",
      "properties": {
        "hierarchy": [
          "tgn:7127670",
          "tgn:1000003",
          "tgn:7003677",
          "tgn:7000084",
          "tgn:7029392"
        ],
        "placetype": [
          "aat:300008699"
        ],
        "id": 7127670,
        "name:xx": "Obernau"
      }
    },
    {
      "geometry": {
        "type": "Point",
        "coordinates": [
          8.15,
          50.916667
        ]
      },
      "type": "Feature",
      "properties": {
        "hierarchy": [
          "tgn:7127671",
          "tgn:1000003",
          "tgn:7003677",
          "tgn:7000084",
          "tgn:7029392"
        ],
        "placetype": [
          "aat:300008347"
        ],
        "id": 7127671,
        "name:xx": "Obernau"
      }
    },
    {
      "geometry": {
        "type": "Point",
        "coordinates": [
          7.616667,
          50.783333
        ]
      },
      "type": "Feature",
      "properties": {
        "hierarchy": [
          "tgn:7127672",
          "tgn:1000003",
          "tgn:7003677",
          "tgn:7000084",
          "tgn:7029392"
        ],
        "placetype": [
          "aat:300008347"
        ],
        "id": 7127672,
        "name:xx": "Obernau"
      }
    },
    {
      "geometry": {
        "type": "Point",
        "coordinates": [
          7.566667,
          50.666667
        ]
      },
      "type": "Feature",
      "properties": {
        "hierarchy": [
          "tgn:7127673",
          "tgn:1000003",
          "tgn:7003682",
          "tgn:7000084",
          "tgn:7029392"
        ],
        "placetype": [
          "aat:300008347"
        ],
        "id": 7127673,
        "name:xx": "Obernau"
      }
    },
    {
      "geometry": {
        "type": "Point",
        "coordinates": [
          9.131389,
          49.936667
        ]
      },
      "type": "Feature",
      "properties": {
        "hierarchy": [
          "tgn:7127674",
          "tgn:7003669",
          "tgn:1000003",
          "tgn:7000084",
          "tgn:7029392"
        ],
        "placetype": [
          "aat:300008347"
        ],
        "id": 7127674,
        "name:xx": "Obernau"
      }
    },
    {
      "geometry": {
        "type": "Point",
        "coordinates": [
          8.866667,
          48.45
        ]
      },
      "type": "Feature",
      "properties": {
        "hierarchy": [
          "tgn:7127675",
          "tgn:7003692",
          "tgn:1000003",
          "tgn:7000084",
          "tgn:7029392"
        ],
        "placetype": [
          "aat:300008347"
        ],
        "id": 7127675,
        "name:xx": "Obernau"
      }
    },
    {
      "geometry": {
        "type": "Point",
        "coordinates": [
          11.05,
          47.65
        ]
      },
      "type": "Feature",
      "properties": {
        "hierarchy": [
          "tgn:7127676",
          "tgn:7003669",
          "tgn:1000003",
          "tgn:7000084",
          "tgn:7029392"
        ],
        "placetype": [
          "aat:300000206"
        ],
        "id": 7127676,
        "name:xx": "Obernau"
      }
    },
    {
      "geometry": {
        "type": "Point",
        "coordinates": [
          13.283333,
          50.583333
        ]
      },
      "type": "Feature",
      "properties": {
        "hierarchy": [
          "tgn:7127677",
          "tgn:1000003",
          "tgn:7003685",
          "tgn:7000084",
          "tgn:7029392"
        ],
        "placetype": [
          "aat:300008347"
        ],
        "id": 7127677,
        "name:xx": "Obernatzschung"
      }
    },
    {
      "geometry": {
        "type": "Point",
        "coordinates": [
          12.3,
          49.583333
        ]
      },
      "type": "Feature",
      "properties": {
        "hierarchy": [
          "tgn:7127678",
          "tgn:7003669",
          "tgn:1000003",
          "tgn:7000084",
          "tgn:7029392"
        ],
        "placetype": [
          "aat:300008347"
        ],
        "id": 7127678,
        "name:xx": "Obernankau"
      }
    },
    {
      "geometry": {
        "type": "Point",
        "coordinates": [
          13.3,
          48.7
        ]
      },
      "type": "Feature",
      "properties": {
        "hierarchy": [
          "tgn:7127679",
          "tgn:7003669",
          "tgn:1000003",
          "tgn:7000084",
          "tgn:7029392"
        ],
        "placetype": [
          "aat:300008347"
        ],
        "id": 7127679,
        "name:xx": "Obernammering"
      }
    }
  ]
}
