{
  "geometry": {
    "type": "Point",
    "coordinates": [
      -108.6333,
      34.6833
    ]
  },
  "type": "Feature",
  "properties": {
    "hierarchy": [
      "tgn:2232511",
      "tgn:1000001",
      "tgn:2001431",
      "tgn:7012149",
      "tgn:7007566",
      "tgn:7029392"
    ],
    "placetype": [
      "aat:300008680"
    ],
    "id": 2232511,
    "name:xx": "Chaparral Lake"
  }
}
