{
  "geometry": {
    "type": "Point",
    "coordinates": [
      -108.7167,
      37.4167
    ]
  },
  "type": "Feature",
  "properties": {
    "hierarchy": [
      "tgn:2354989",
      "tgn:1000001",
      "tgn:7012149",
      "tgn:2000233",
      "tgn:7007158",
      "tgn:7029392"
    ],
    "placetype": [
      "aat:300008761"
    ],
    "id": 2354989,
    "name:xx": "Goodman Canyon"
  }
}
