{
  "geometry": {
    "type": "Point",
    "coordinates": [
      -87.8333,
      42.3333
    ]
  },
  "type": "Feature",
  "properties": {
    "hierarchy": [
      "tgn:2754355",
      "tgn:1000001",
      "tgn:7012149",
      "tgn:7013855",
      "tgn:7007251",
      "tgn:7029392"
    ],
    "placetype": [
      "aat:300008707"
    ],
    "id": 2754355,
    "name:xx": "Waukegan River"
  }
}
