{
  "geometry": {
    "type": "Point",
    "coordinates": [
      -150.2167,
      67.5167
    ]
  },
  "type": "Feature",
  "properties": {
    "hierarchy": [
      "tgn:2744284",
      "tgn:7006450",
      "tgn:1000001",
      "tgn:7012149",
      "tgn:2000089",
      "tgn:7029392"
    ],
    "placetype": [
      "aat:300008706"
    ],
    "id": 2744284,
    "name:xx": "Vermont Creek"
  }
}
