{
  "geometry": {
    "type": "Point",
    "coordinates": [
      122.4667,
      42.3667
    ]
  },
  "type": "Feature",
  "properties": {
    "hierarchy": [
      "tgn:1068258",
      "tgn:1000004",
      "tgn:1001390",
      "tgn:1000111",
      "tgn:7029392"
    ],
    "placetype": [
      "aat:300008347"
    ],
    "id": 1068258,
    "name:xx": "Gaoshantai"
  }
}
