{
  "geometry": {
    "type": "Point",
    "coordinates": [
      -76.1167,
      42.3333
    ]
  },
  "type": "Feature",
  "properties": {
    "hierarchy": [
      "tgn:2775540",
      "tgn:1000001",
      "tgn:7012149",
      "tgn:1002944",
      "tgn:7007568",
      "tgn:7029392"
    ],
    "placetype": [
      "aat:300008706"
    ],
    "id": 2775540,
    "name:xx": "Wilson Creek"
  }
}
