{
  "geometry": {
    "type": "Point",
    "coordinates": [
      -75.3333,
      38.15
    ]
  },
  "type": "Feature",
  "properties": {
    "hierarchy": [
      "tgn:2571269",
      "tgn:1000001",
      "tgn:1003037",
      "tgn:7012149",
      "tgn:7007516",
      "tgn:7029392"
    ],
    "placetype": [
      "aat:300008699"
    ],
    "id": 2571269,
    "name:xx": "Pattys Branch"
  }
}
