{
  "geometry": {
    "type": "Point",
    "coordinates": [
      -78.15,
      36.3833
    ]
  },
  "type": "Feature",
  "properties": {
    "hierarchy": [
      "tgn:2077090",
      "tgn:1000001",
      "tgn:7012149",
      "tgn:2001549",
      "tgn:7007709",
      "tgn:7029392"
    ],
    "placetype": [
      "aat:300008347"
    ],
    "id": 2077090,
    "name:xx": "Warrenton"
  }
}
