{
  "geometry": {
    "type": "Point",
    "coordinates": [
      -83.5667,
      37.3167
    ]
  },
  "type": "Feature",
  "properties": {
    "hierarchy": [
      "tgn:2447174",
      "tgn:1000001",
      "tgn:7012149",
      "tgn:2000835",
      "tgn:7007255",
      "tgn:7029392"
    ],
    "placetype": [
      "aat:300008699"
    ],
    "id": 2447174,
    "name:xx": "Lick Branch"
  }
}
