{
  "geometry": {
    "type": "Point",
    "coordinates": [
      -112.4667,
      38.4833
    ]
  },
  "type": "Feature",
  "properties": {
    "hierarchy": [
      "tgn:2398644",
      "tgn:1000001",
      "tgn:7012149",
      "tgn:2002116",
      "tgn:7007827",
      "tgn:7029392"
    ],
    "placetype": [
      "aat:300008761"
    ],
    "id": 2398644,
    "name:xx": "Hop Canyon"
  }
}
