{
  "type": "FeatureCollection",
  "features": [
    {
      "geometry": {
        "type": "Point",
        "coordinates": [
          -96.933333,
          17.716667
        ]
      },
      "type": "Feature",
      "properties": {
        "hierarchy": [
          "tgn:7368060",
          "tgn:1000001",
          "tgn:7005591",
          "tgn:7005560",
          "tgn:7029392"
        ],
        "placetype": [
          "aat:300008699"
        ],
        "id": 7368060,
        "name:xx": "Grande, Río"
      }
    },
    {
      "geometry": {
        "type": "Point",
        "coordinates": [
          -95.666667,
          17.216667
        ]
      },
      "type": "Feature",
      "properties": {
        "hierarchy": [
          "tgn:7368061",
          "tgn:1000001",
          "tgn:7005591",
          "tgn:7005560",
          "tgn:7029392"
        ],
        "placetype": [
          "aat:300008699"
        ],
        "id": 7368061,
        "name:xx": "Grande, Río"
      }
    },
    {
      "geometry": {
        "type": "Point",
        "coordinates": [
          -97.483333,
          15.966667
        ]
      },
      "type": "Feature",
      "properties": {
        "hierarchy": [
          "tgn:7368063",
          "tgn:1000001",
          "tgn:7005591",
          "tgn:7005560",
          "tgn:7029392"
        ],
        "placetype": [
          "aat:300008699"
        ],
        "id": 7368063,
        "name:xx": "Grande, Río"
      }
    },
    {
      "geometry": {
        "type": "Point",
        "coordinates": [
          -108.933333,
          30.916667
        ]
      },
      "type": "Feature",
      "properties": {
        "hierarchy": [
          "tgn:7368064",
          "tgn:1000001",
          "tgn:1001960",
          "tgn:7005560",
          "tgn:7029392"
        ],
        "placetype": [
          "aat:300000241"
        ],
        "id": 7368064,
        "name:xx": "Rancho Grande"
      }
    },
    {
      "geometry": {
        "type": "Point",
        "coordinates": [
          -106.55,
          30.416667
        ]
      },
      "type": "Feature",
      "properties": {
        "hierarchy": [
          "tgn:7368065",
          "tgn:7005581",
          "tgn:1000001",
          "tgn:7005560",
          "tgn:7029392"
        ],
        "placetype": [
          "aat:300000241"
        ],
        "id": 7368065,
        "name:xx": "Rancho Grande"
      }
    },
    {
      "geometry": {
        "type": "Point",
        "coordinates": [
          -111.083333,
          29.3
        ]
      },
      "type": "Feature",
      "properties": {
        "hierarchy": [
          "tgn:7368066",
          "tgn:1000001",
          "tgn:1001960",
          "tgn:7005560",
          "tgn:7029392"
        ],
        "placetype": [
          "aat:300000241"
        ],
        "id": 7368066,
        "name:xx": "Rancho Grande"
      }
    },
    {
      "geometry": {
        "type": "Point",
        "coordinates": [
          -106.216667,
          28.85
        ]
      },
      "type": "Feature",
      "properties": {
        "hierarchy": [
          "tgn:7368067",
          "tgn:7005581",
          "tgn:1000001",
          "tgn:7005560",
          "tgn:7029392"
        ],
        "placetype": [
          "aat:300000241"
        ],
        "id": 7368067,
        "name:xx": "Rancho Grande"
      }
    },
    {
      "geometry": {
        "type": "Point",
        "coordinates": [
          -99.2,
          23.333333
        ]
      },
      "type": "Feature",
      "properties": {
        "hierarchy": [
          "tgn:7368068",
          "tgn:1000001",
          "tgn:7005597",
          "tgn:7005560",
          "tgn:7029392"
        ],
        "placetype": [
          "aat:300000241"
        ],
        "id": 7368068,
        "name:xx": "Rancho Grande"
      }
    },
    {
      "geometry": {
        "type": "Point",
        "coordinates": [
          -95.8,
          18.8
        ]
      },
      "type": "Feature",
      "properties": {
        "hierarchy": [
          "tgn:7368069",
          "tgn:1000001",
          "tgn:7005599",
          "tgn:7005560",
          "tgn:7029392"
        ],
        "placetype": [
          "aat:300386846"
        ],
        "id": 7368069,
        "name:xx": "Grande, Punta"
      }
    }
  ]
}
