{
  "type": "FeatureCollection",
  "features": [
    {
      "geometry": {
        "type": "Point",
        "coordinates": [
          -75.3333,
          39.6833
        ]
      },
      "type": "Feature",
      "properties": {
        "hierarchy": [
          "tgn:2653221",
          "tgn:1000001",
          "tgn:7014449",
          "tgn:7012149",
          "tgn:7007565",
          "tgn:7029392"
        ],
        "placetype": [
          "aat:300008347"
        ],
        "id": 2653221,
        "name:xx": "Seven Stars"
      }
    },
    {
      "geometry": {
        "type": "Point",
        "coordinates": [
          -75.3,
          40.1
        ]
      },
      "type": "Feature",
      "properties": {
        "hierarchy": [
          "tgn:2653222",
          "tgn:1000001",
          "tgn:7012149",
          "tgn:1002690",
          "tgn:7007710",
          "tgn:7029392"
        ],
        "placetype": [
          "aat:300008347"
        ],
        "id": 2653222,
        "name:xx": "Seven Stars"
      }
    },
    {
      "geometry": {
        "type": "Point",
        "coordinates": [
          -75.5833,
          40.15
        ]
      },
      "type": "Feature",
      "properties": {
        "hierarchy": [
          "tgn:2653223",
          "tgn:1000001",
          "tgn:1002266",
          "tgn:7012149",
          "tgn:7007710",
          "tgn:7029392"
        ],
        "placetype": [
          "aat:300008347"
        ],
        "id": 2653223,
        "name:xx": "Seven Stars"
      }
    },
    {
      "geometry": {
        "type": "Point",
        "coordinates": [
          -78.0667,
          40.65
        ]
      },
      "type": "Feature",
      "properties": {
        "hierarchy": [
          "tgn:2653224",
          "tgn:1000001",
          "tgn:7012149",
          "tgn:1002494",
          "tgn:7007710",
          "tgn:7029392"
        ],
        "placetype": [
          "aat:300008347"
        ],
        "id": 2653224,
        "name:xx": "Seven Stars"
      }
    },
    {
      "geometry": {
        "type": "Point",
        "coordinates": [
          -123.45,
          47.55
        ]
      },
      "type": "Feature",
      "properties": {
        "hierarchy": [
          "tgn:2653225",
          "tgn:1000001",
          "tgn:7012149",
          "tgn:1002645",
          "tgn:7007920",
          "tgn:7029392"
        ],
        "placetype": [
          "aat:300008699"
        ],
        "id": 2653225,
        "name:xx": "Seven Stream"
      }
    },
    {
      "geometry": {
        "type": "Point",
        "coordinates": [
          -116.4,
          43.6667
        ]
      },
      "type": "Feature",
      "properties": {
        "hierarchy": [
          "tgn:2653226",
          "tgn:2000452",
          "tgn:1000001",
          "tgn:7012149",
          "tgn:7007250",
          "tgn:7029392"
        ],
        "placetype": [
          "aat:300006075"
        ],
        "id": 2653226,
        "name:xx": "Seven Suckers Ditch"
      }
    },
    {
      "geometry": {
        "type": "Point",
        "coordinates": [
          -110.6333,
          31.4
        ]
      },
      "type": "Feature",
      "properties": {
        "hierarchy": [
          "tgn:2653227",
          "tgn:1000001",
          "tgn:7006451",
          "tgn:7012149",
          "tgn:2000102",
          "tgn:7029392"
        ],
        "placetype": [
          "aat:300006191"
        ],
        "id": 2653227,
        "name:xx": "Seven Tank"
      }
    },
    {
      "geometry": {
        "type": "Point",
        "coordinates": [
          -113.2,
          35.2167
        ]
      },
      "type": "Feature",
      "properties": {
        "hierarchy": [
          "tgn:2653228",
          "tgn:1000001",
          "tgn:7006451",
          "tgn:7012149",
          "tgn:2000103",
          "tgn:7029392"
        ],
        "placetype": [
          "aat:300006191"
        ],
        "id": 2653228,
        "name:xx": "Seven Tank"
      }
    },
    {
      "geometry": {
        "type": "Point",
        "coordinates": [
          -116.3167,
          40.5
        ]
      },
      "type": "Feature",
      "properties": {
        "hierarchy": [
          "tgn:2653229",
          "tgn:1000001",
          "tgn:2001413",
          "tgn:7012149",
          "tgn:7007526",
          "tgn:7029392"
        ],
        "placetype": [
          "aat:300008697"
        ],
        "id": 2653229,
        "name:xx": "Seven Tank Spring"
      }
    }
  ]
}
