{
  "geometry": {
    "type": "Point",
    "coordinates": [
      29.923184,
      25.223504
    ]
  },
  "type": "Feature",
  "properties": {
    "hierarchy": [
      "tgn:7527668",
      "tgn:7001242",
      "tgn:7016833",
      "tgn:7001334",
      "tgn:7029392"
    ],
    "placetype": [
      "aat:300008777"
    ],
    "name:en": "Zayyāt ash Sharqī, Qārat az",
    "id": 7527668
  }
}
