{
  "geometry": {
    "type": "Point",
    "coordinates": [
      -79.4167,
      34.0667
    ]
  },
  "type": "Feature",
  "properties": {
    "hierarchy": [
      "tgn:2515419",
      "tgn:1000001",
      "tgn:7012149",
      "tgn:2001758",
      "tgn:7007712",
      "tgn:7029392"
    ],
    "placetype": [
      "aat:300008699"
    ],
    "id": 2515419,
    "name:xx": "Millrace Drain"
  }
}
