{
  "geometry": {
    "type": "Point",
    "coordinates": [
      -108.3333,
      39.9333
    ]
  },
  "type": "Feature",
  "properties": {
    "hierarchy": [
      "tgn:2400293",
      "tgn:1000001",
      "tgn:7012149",
      "tgn:7007158",
      "tgn:2000243",
      "tgn:7029392"
    ],
    "placetype": [
      "aat:300008761"
    ],
    "id": 2400293,
    "name:xx": "Horse Draw"
  }
}
