{
  "geometry": {
    "type": "Point",
    "coordinates": [
      -83.3667,
      38.5167
    ]
  },
  "type": "Feature",
  "properties": {
    "hierarchy": [
      "tgn:7023536",
      "tgn:1000001",
      "tgn:7012149",
      "tgn:1002591",
      "tgn:7007255",
      "tgn:7029392"
    ],
    "placetype": [
      "aat:300008699"
    ],
    "id": 7023536,
    "name:xx": "Sugar Tree Branch"
  }
}
