{
  "geometry": {
    "type": "Point",
    "coordinates": [
      -91.35,
      36.8167
    ]
  },
  "type": "Feature",
  "properties": {
    "hierarchy": [
      "tgn:2499741",
      "tgn:1000001",
      "tgn:7012149",
      "tgn:2001225",
      "tgn:7007523",
      "tgn:7029392"
    ],
    "placetype": [
      "aat:300008697"
    ],
    "id": 2499741,
    "name:xx": "McCormack Spring"
  }
}
