{
  "geometry": {
    "type": "Point",
    "coordinates": [
      -111.6667,
      43.95
    ]
  },
  "type": "Feature",
  "properties": {
    "hierarchy": [
      "tgn:2026095",
      "tgn:1000001",
      "tgn:7012149",
      "tgn:2000473",
      "tgn:7007250",
      "tgn:7029392"
    ],
    "placetype": [
      "aat:300008347"
    ],
    "id": 2026095,
    "name:xx": "Saint Anthony"
  }
}
