{
  "geometry": {
    "type": "Point",
    "coordinates": [
      -119.8167,
      39.9667
    ]
  },
  "type": "Feature",
  "properties": {
    "hierarchy": [
      "tgn:2511876",
      "tgn:1000001",
      "tgn:7012149",
      "tgn:1002999",
      "tgn:7007526",
      "tgn:7029392"
    ],
    "placetype": [
      "aat:300006191"
    ],
    "id": 2511876,
    "name:xx": "Milk Ranch Reservoir"
  }
}
