{
  "geometry": {
    "type": "Point",
    "coordinates": [
      -74.8167,
      41.7833
    ]
  },
  "type": "Feature",
  "properties": {
    "hierarchy": [
      "tgn:2073235",
      "tgn:1000001",
      "tgn:7012149",
      "tgn:1002926",
      "tgn:7007568",
      "tgn:7029392"
    ],
    "placetype": [
      "aat:300008347"
    ],
    "id": 2073235,
    "name:xx": "White Sulphur Springs"
  }
}
