{
  "geometry": {
    "type": "Point",
    "coordinates": [
      75.504539,
      28.495274
    ]
  },
  "type": "Feature",
  "properties": {
    "hierarchy": [
      "tgn:7582026",
      "tgn:1000004",
      "tgn:7000198",
      "tgn:7016788",
      "tgn:7029392"
    ],
    "placetype": [
      "aat:300008688"
    ],
    "name:en": "Rāmdīsān Johra",
    "id": 7582026
  }
}
