{
  "geometry": {
    "type": "Point",
    "coordinates": [
      -86.5167,
      35.9167
    ]
  },
  "type": "Feature",
  "properties": {
    "hierarchy": [
      "tgn:2654192",
      "tgn:1000001",
      "tgn:7012149",
      "tgn:2001911",
      "tgn:7007825",
      "tgn:7029392"
    ],
    "placetype": [
      "aat:300008347"
    ],
    "id": 2654192,
    "name:xx": "Shadowbrook"
  }
}
