{
  "type": "FeatureCollection",
  "features": [
    {
      "geometry": {
        "type": "Point",
        "coordinates": [
          -108.85,
          38.1667
        ]
      },
      "type": "Feature",
      "properties": {
        "hierarchy": [
          "tgn:2577290",
          "tgn:1000001",
          "tgn:7012149",
          "tgn:2000234",
          "tgn:7007158",
          "tgn:7029392"
        ],
        "placetype": [
          "aat:300008798"
        ],
        "id": 2577290,
        "name:xx": "Peters Knob"
      }
    },
    {
      "geometry": {
        "type": "Point",
        "coordinates": [
          -83.4333,
          36.8833
        ]
      },
      "type": "Feature",
      "properties": {
        "hierarchy": [
          "tgn:2577291",
          "tgn:1000001",
          "tgn:7012149",
          "tgn:2000811",
          "tgn:7007255",
          "tgn:7029392"
        ],
        "placetype": [
          "aat:300008798"
        ],
        "id": 2577291,
        "name:xx": "Peters Knob"
      }
    },
    {
      "geometry": {
        "type": "Point",
        "coordinates": [
          -83.2333,
          31
        ]
      },
      "type": "Feature",
      "properties": {
        "hierarchy": [
          "tgn:2577292",
          "tgn:1000001",
          "tgn:7012149",
          "tgn:2000383",
          "tgn:7007248",
          "tgn:7029392"
        ],
        "placetype": [
          "aat:300006191"
        ],
        "id": 2577292,
        "name:xx": "Peters Lake"
      }
    },
    {
      "geometry": {
        "type": "Point",
        "coordinates": [
          -85.8667,
          39.0167
        ]
      },
      "type": "Feature",
      "properties": {
        "hierarchy": [
          "tgn:2577293",
          "tgn:1000001",
          "tgn:7012149",
          "tgn:1002508",
          "tgn:7007252",
          "tgn:7029392"
        ],
        "placetype": [
          "aat:300008680"
        ],
        "id": 2577293,
        "name:xx": "Peters Lake"
      }
    },
    {
      "geometry": {
        "type": "Point",
        "coordinates": [
          -89.8167,
          30.7833
        ]
      },
      "type": "Feature",
      "properties": {
        "hierarchy": [
          "tgn:2577294",
          "tgn:1000001",
          "tgn:7012149",
          "tgn:2000912",
          "tgn:7007256",
          "tgn:7029392"
        ],
        "placetype": [
          "aat:300008680"
        ],
        "id": 2577294,
        "name:xx": "Peters Lake"
      }
    },
    {
      "geometry": {
        "type": "Point",
        "coordinates": [
          -83.15,
          42.8833
        ]
      },
      "type": "Feature",
      "properties": {
        "hierarchy": [
          "tgn:2577295",
          "tgn:1000001",
          "tgn:7012149",
          "tgn:1002576",
          "tgn:7007520",
          "tgn:7029392"
        ],
        "placetype": [
          "aat:300008680"
        ],
        "id": 2577295,
        "name:xx": "Peters Lake"
      }
    },
    {
      "geometry": {
        "type": "Point",
        "coordinates": [
          -85.0667,
          44.8
        ]
      },
      "type": "Feature",
      "properties": {
        "hierarchy": [
          "tgn:2577296",
          "tgn:1000001",
          "tgn:7012149",
          "tgn:2000968",
          "tgn:7007520",
          "tgn:7029392"
        ],
        "placetype": [
          "aat:300008680"
        ],
        "id": 2577296,
        "name:xx": "Peters Lake"
      }
    },
    {
      "geometry": {
        "type": "Point",
        "coordinates": [
          -104.5167,
          33.2
        ]
      },
      "type": "Feature",
      "properties": {
        "hierarchy": [
          "tgn:2577297",
          "tgn:1000001",
          "tgn:2001430",
          "tgn:7012149",
          "tgn:7007566",
          "tgn:7029392"
        ],
        "placetype": [
          "aat:300008680"
        ],
        "id": 2577297,
        "name:xx": "Peters Lake"
      }
    },
    {
      "geometry": {
        "type": "Point",
        "coordinates": [
          -96.1333,
          36.7167
        ]
      },
      "type": "Feature",
      "properties": {
        "hierarchy": [
          "tgn:2577298",
          "tgn:1000001",
          "tgn:7012149",
          "tgn:2001679",
          "tgn:7007707",
          "tgn:7029392"
        ],
        "placetype": [
          "aat:300006191"
        ],
        "id": 2577298,
        "name:xx": "Peters Lake"
      }
    },
    {
      "geometry": {
        "type": "Point",
        "coordinates": [
          -79.5333,
          39.8167
        ]
      },
      "type": "Feature",
      "properties": {
        "hierarchy": [
          "tgn:2577299",
          "tgn:1000001",
          "tgn:7012149",
          "tgn:7014185",
          "tgn:7007710",
          "tgn:7029392"
        ],
        "placetype": [
          "aat:300006191"
        ],
        "id": 2577299,
        "name:xx": "Peters Lake"
      }
    }
  ]
}
