{
  "geometry": {
    "type": "Point",
    "coordinates": [
      35.109712,
      24.664842
    ]
  },
  "type": "Feature",
  "properties": {
    "hierarchy": [
      "tgn:7525266",
      "tgn:7001242",
      "tgn:7001311",
      "tgn:7016833",
      "tgn:7029392"
    ],
    "placetype": [
      "aat:300386846"
    ],
    "name:en": "Baghdādī, Ra's",
    "id": 7525266
  }
}
