{
  "type": "FeatureCollection",
  "features": [
    {
      "geometry": {
        "type": "Point",
        "coordinates": [
          -97.533333,
          20.1
        ]
      },
      "type": "Feature",
      "properties": {
        "hierarchy": [
          "tgn:7390141",
          "tgn:1000001",
          "tgn:7005592",
          "tgn:7005560",
          "tgn:7029392"
        ],
        "placetype": [
          "aat:300008347"
        ],
        "id": 7390141,
        "name:xx": "Reyes de Vallarta"
      }
    },
    {
      "geometry": {
        "type": "Point",
        "coordinates": [
          -106.133333,
          29.533333
        ]
      },
      "type": "Feature",
      "properties": {
        "hierarchy": [
          "tgn:7390142",
          "tgn:7005581",
          "tgn:1000001",
          "tgn:7005560",
          "tgn:7029392"
        ],
        "placetype": [
          "aat:300008697"
        ],
        "id": 7390142,
        "name:xx": "Reyes, Ojo de los"
      }
    },
    {
      "geometry": {
        "type": "Point",
        "coordinates": [
          -99.666667,
          26.116667
        ]
      },
      "type": "Feature",
      "properties": {
        "hierarchy": [
          "tgn:7390143",
          "tgn:1000001",
          "tgn:7005589",
          "tgn:7005560",
          "tgn:7029392"
        ],
        "placetype": [
          "aat:300266554",
          "aat:300008699"
        ],
        "id": 7390143,
        "name:xx": "Reyes, Arroyo de"
      }
    },
    {
      "geometry": {
        "type": "Point",
        "coordinates": [
          -103.066667,
          24.816667
        ]
      },
      "type": "Feature",
      "properties": {
        "hierarchy": [
          "tgn:7390144",
          "tgn:7005583",
          "tgn:1000001",
          "tgn:7005560",
          "tgn:7029392"
        ],
        "placetype": [
          "aat:300266554",
          "aat:300008699"
        ],
        "id": 7390144,
        "name:xx": "Reyes, Arroyo de"
      }
    },
    {
      "geometry": {
        "type": "Point",
        "coordinates": [
          -99.75,
          26.483333
        ]
      },
      "type": "Feature",
      "properties": {
        "hierarchy": [
          "tgn:7390145",
          "tgn:1000001",
          "tgn:7005589",
          "tgn:7005560",
          "tgn:7029392"
        ],
        "placetype": [
          "aat:300008347"
        ],
        "id": 7390145,
        "name:xx": "Reyes"
      }
    },
    {
      "geometry": {
        "type": "Point",
        "coordinates": [
          -103.116667,
          24.45
        ]
      },
      "type": "Feature",
      "properties": {
        "hierarchy": [
          "tgn:7390146",
          "tgn:7005583",
          "tgn:1000001",
          "tgn:7005560",
          "tgn:7029392"
        ],
        "placetype": [
          "aat:300008347"
        ],
        "id": 7390146,
        "name:xx": "Reyes"
      }
    },
    {
      "geometry": {
        "type": "Point",
        "coordinates": [
          -95.116667,
          17.5
        ]
      },
      "type": "Feature",
      "properties": {
        "hierarchy": [
          "tgn:7390147",
          "tgn:1000001",
          "tgn:7005599",
          "tgn:7005560",
          "tgn:7029392"
        ],
        "placetype": [
          "aat:300008347"
        ],
        "id": 7390147,
        "name:xx": "Reyes"
      }
    },
    {
      "geometry": {
        "type": "Point",
        "coordinates": [
          -106.75,
          30.783333
        ]
      },
      "type": "Feature",
      "properties": {
        "hierarchy": [
          "tgn:7390148",
          "tgn:7005581",
          "tgn:1000001",
          "tgn:7005560",
          "tgn:7029392"
        ],
        "placetype": [
          "aat:300008347"
        ],
        "id": 7390148,
        "name:xx": "Rancho Hilda"
      }
    },
    {
      "geometry": {
        "type": "Point",
        "coordinates": [
          -101.3,
          26.916667
        ]
      },
      "type": "Feature",
      "properties": {
        "hierarchy": [
          "tgn:7390149",
          "tgn:1001853",
          "tgn:1000001",
          "tgn:7005560",
          "tgn:7029392"
        ],
        "placetype": [
          "aat:300008347"
        ],
        "id": 7390149,
        "name:xx": "Rancho Higueras"
      }
    }
  ]
}
