{
  "type": "FeatureCollection",
  "features": [
    {
      "geometry": {
        "type": "Point",
        "coordinates": [
          31.645396,
          31.182983
        ]
      },
      "type": "Feature",
      "properties": {
        "hierarchy": [
          "tgn:7542320",
          "tgn:7001242",
          "tgn:1001059",
          "tgn:7016833",
          "tgn:7029392"
        ],
        "placetype": [
          "aat:300000206"
        ],
        "name:en": "'Izbat al Işlāḩ",
        "id": 7542320
      }
    },
    {
      "geometry": {
        "type": "Point",
        "coordinates": [
          31.641832,
          31.189136
        ]
      },
      "type": "Feature",
      "properties": {
        "hierarchy": [
          "tgn:7542321",
          "tgn:7001242",
          "tgn:1001059",
          "tgn:7016833",
          "tgn:7029392"
        ],
        "placetype": [
          "aat:300000206"
        ],
        "name:en": "'Izbat al Bāz",
        "id": 7542321
      }
    },
    {
      "geometry": {
        "type": "Point",
        "coordinates": [
          31.635658,
          31.185925
        ]
      },
      "type": "Feature",
      "properties": {
        "hierarchy": [
          "tgn:7542322",
          "tgn:7001242",
          "tgn:1001059",
          "tgn:7016833",
          "tgn:7029392"
        ],
        "placetype": [
          "aat:300000206"
        ],
        "name:en": "'Izbat Ibrāhīm Muşţafá",
        "id": 7542322
      }
    },
    {
      "geometry": {
        "type": "Point",
        "coordinates": [
          31.644746,
          31.198567
        ]
      },
      "type": "Feature",
      "properties": {
        "hierarchy": [
          "tgn:7542323",
          "tgn:7001242",
          "tgn:7016833",
          "tgn:1001225",
          "tgn:7029392"
        ],
        "placetype": [
          "aat:300008347"
        ],
        "name:en": "'Izbat Abū al 'Izz",
        "id": 7542323
      }
    },
    {
      "geometry": {
        "type": "Point",
        "coordinates": [
          31.568305,
          31.18593
        ]
      },
      "type": "Feature",
      "properties": {
        "hierarchy": [
          "tgn:7542324",
          "tgn:7001242",
          "tgn:1001059",
          "tgn:7016833",
          "tgn:7029392"
        ],
        "placetype": [
          "aat:300000206"
        ],
        "name:en": "'Izbat Ibrāhīm Abū Shāhīn",
        "id": 7542324
      }
    },
    {
      "geometry": {
        "type": "Point",
        "coordinates": [
          31.563981,
          31.18776
        ]
      },
      "type": "Feature",
      "properties": {
        "hierarchy": [
          "tgn:7542325",
          "tgn:7001242",
          "tgn:1001059",
          "tgn:7016833",
          "tgn:7029392"
        ],
        "placetype": [
          "aat:300000206"
        ],
        "name:en": "'Izbat Ibrāhīm ash Shabāşī",
        "id": 7542325
      }
    },
    {
      "geometry": {
        "type": "Point",
        "coordinates": [
          31.517816,
          31.185675
        ]
      },
      "type": "Feature",
      "properties": {
        "hierarchy": [
          "tgn:7542326",
          "tgn:7001242",
          "tgn:1001059",
          "tgn:7016833",
          "tgn:7029392"
        ],
        "placetype": [
          "aat:300000206"
        ],
        "name:en": "'Izbat Waqf Qandīl",
        "id": 7542326
      }
    },
    {
      "geometry": {
        "type": "Point",
        "coordinates": [
          31.740144,
          31.173144
        ]
      },
      "type": "Feature",
      "properties": {
        "hierarchy": [
          "tgn:7542327",
          "tgn:7001242",
          "tgn:1001059",
          "tgn:7016833",
          "tgn:7029392"
        ],
        "placetype": [
          "aat:300006075"
        ],
        "name:en": "Tir'at al Buḩayrah",
        "id": 7542327
      }
    },
    {
      "geometry": {
        "type": "Point",
        "coordinates": [
          31.742188,
          31.19682
        ]
      },
      "type": "Feature",
      "properties": {
        "hierarchy": [
          "tgn:7542328",
          "tgn:7001242",
          "tgn:1001059",
          "tgn:7016833",
          "tgn:7029392"
        ],
        "placetype": [
          "aat:300000206"
        ],
        "name:en": "'Izbat al Bakrī",
        "id": 7542328
      }
    },
    {
      "geometry": {
        "type": "Point",
        "coordinates": [
          31.748324,
          31.204864
        ]
      },
      "type": "Feature",
      "properties": {
        "hierarchy": [
          "tgn:7542329",
          "tgn:7001242",
          "tgn:1001059",
          "tgn:7016833",
          "tgn:7029392"
        ],
        "placetype": [
          "aat:300000206"
        ],
        "name:en": "'Izbat al Ḩājj 'Alī",
        "id": 7542329
      }
    }
  ]
}
