{
  "geometry": {
    "type": "Point",
    "coordinates": [
      -119.5833,
      38.6667
    ]
  },
  "type": "Feature",
  "properties": {
    "hierarchy": [
      "tgn:2745580",
      "tgn:1000001",
      "tgn:7012149",
      "tgn:7007157",
      "tgn:1002675",
      "tgn:7029392"
    ],
    "placetype": [
      "aat:300008697"
    ],
    "id": 2745580,
    "name:xx": "Virgil Connell Spring"
  }
}
