{
  "geometry": {
    "type": "Point",
    "coordinates": [
      -86.3833,
      30.7333
    ]
  },
  "type": "Feature",
  "properties": {
    "hierarchy": [
      "tgn:2479509",
      "tgn:1000001",
      "tgn:7012149",
      "tgn:2000290",
      "tgn:7007240",
      "tgn:7029392"
    ],
    "placetype": [
      "aat:300008706"
    ],
    "id": 2479509,
    "name:xx": "Laird Mill Creek"
  }
}
