{
  "geometry": {
    "type": "Point",
    "coordinates": [
      -114.0833,
      35.35
    ]
  },
  "type": "Feature",
  "properties": {
    "hierarchy": [
      "tgn:2220202",
      "tgn:1000001",
      "tgn:7006451",
      "tgn:7012149",
      "tgn:2000098",
      "tgn:7029392"
    ],
    "placetype": [
      "aat:300008697"
    ],
    "id": 2220202,
    "name:xx": "Canyon Station Spring"
  }
}
