{
  "geometry": {
    "type": "Point",
    "coordinates": [
      -107.45,
      38.5167
    ]
  },
  "type": "Feature",
  "properties": {
    "hierarchy": [
      "tgn:2257719",
      "tgn:1000001",
      "tgn:7012149",
      "tgn:7007158",
      "tgn:7029392"
    ],
    "placetype": [
      "aat:300008761"
    ],
    "id": 2257719,
    "name:xx": "Corral Gulch"
  }
}
