{
  "geometry": {
    "type": "Point",
    "coordinates": [
      -112.15,
      40.9333
    ]
  },
  "type": "Feature",
  "properties": {
    "hierarchy": [
      "tgn:2650001",
      "tgn:1000001",
      "tgn:2002106",
      "tgn:7012149",
      "tgn:7007827",
      "tgn:7029392"
    ],
    "placetype": [
      "aat:300008850"
    ],
    "id": 2650001,
    "name:xx": "Sea Gull Point"
  }
}
