{
  "geometry": {
    "type": "Point",
    "coordinates": [
      -75.25,
      39.85
    ]
  },
  "type": "Feature",
  "properties": {
    "hierarchy": [
      "tgn:2189503",
      "tgn:1000001",
      "tgn:7012149",
      "tgn:7007710",
      "tgn:7029392"
    ],
    "placetype": [
      "aat:300008706"
    ],
    "id": 2189503,
    "name:xx": "Bow Creek"
  }
}
