{
  "geometry": {
    "type": "Point",
    "coordinates": [
      -90.6167,
      42.4667
    ]
  },
  "type": "Feature",
  "properties": {
    "hierarchy": [
      "tgn:2708237",
      "tgn:1000001",
      "tgn:7012149",
      "tgn:2000514",
      "tgn:7007251",
      "tgn:7029392"
    ],
    "placetype": [
      "aat:300008680"
    ],
    "id": 2708237,
    "name:xx": "Switzer Lake"
  }
}
