{
  "geometry": {
    "type": "Point",
    "coordinates": [
      29.1833,
      41.0333
    ]
  },
  "type": "Feature",
  "properties": {
    "hierarchy": [
      "tgn:1086886",
      "tgn:1001052",
      "tgn:1000004",
      "tgn:7018450",
      "tgn:1000144",
      "tgn:7029392"
    ],
    "placetype": [
      "aat:300008347"
    ],
    "id": 1086886,
    "name:xx": "Sultançiftligi"
  }
}
