{
  "geometry": {
    "type": "Point",
    "coordinates": [
      -91.3167,
      39.7667
    ]
  },
  "type": "Feature",
  "properties": {
    "hierarchy": [
      "tgn:2140572",
      "tgn:1002134",
      "tgn:1000001",
      "tgn:7012149",
      "tgn:7007251",
      "tgn:7029392"
    ],
    "placetype": [
      "aat:300386845"
    ],
    "id": 2140572,
    "name:xx": "Austin Creek Settling Basin"
  }
}
