{
  "geometry": {
    "type": "Point",
    "coordinates": [
      30.921155,
      31.012418
    ]
  },
  "type": "Feature",
  "properties": {
    "hierarchy": [
      "tgn:7532984",
      "tgn:7001242",
      "tgn:7016833",
      "tgn:1001335",
      "tgn:7029392"
    ],
    "placetype": [
      "aat:300006075"
    ],
    "name:en": "Maşrif Shinū",
    "id": 7532984
  }
}
