{
  "geometry": {
    "type": "Point",
    "coordinates": [
      109.2333,
      12.5667
    ]
  },
  "type": "Feature",
  "properties": {
    "hierarchy": [
      "tgn:1087111",
      "tgn:1000004",
      "tgn:7001055",
      "tgn:1000145",
      "tgn:7029392"
    ],
    "placetype": [
      "aat:300008347"
    ],
    "id": 1087111,
    "name:xx": "Đông Hai"
  }
}
