{
  "type": "FeatureCollection",
  "features": [
    {
      "geometry": {
        "type": "Point",
        "coordinates": [
          12.186667,
          44.580833
        ]
      },
      "type": "Feature",
      "properties": {
        "hierarchy": [
          "tgn:7055360",
          "tgn:7003133",
          "tgn:1000003",
          "tgn:7008516",
          "tgn:1000080",
          "tgn:7029392"
        ],
        "placetype": [
          "aat:300008679"
        ],
        "id": 7055360,
        "name:xx": "Lido Magnavacca, Valle di"
      }
    },
    {
      "geometry": {
        "type": "Point",
        "coordinates": [
          13.333333,
          38.2
        ]
      },
      "type": "Feature",
      "properties": {
        "hierarchy": [
          "tgn:7055362",
          "tgn:1000003",
          "tgn:7003122",
          "tgn:1001732",
          "tgn:1000080",
          "tgn:7029392"
        ],
        "placetype": [
          "aat:300008347"
        ],
        "id": 7055362,
        "name:xx": "Lido di Mondello"
      }
    },
    {
      "geometry": {
        "type": "Point",
        "coordinates": [
          12.345556,
          44.312222
        ]
      },
      "type": "Feature",
      "properties": {
        "hierarchy": [
          "tgn:7055365",
          "tgn:7003133",
          "tgn:1000003",
          "tgn:7008516",
          "tgn:1000080",
          "tgn:7029392"
        ],
        "placetype": [
          "aat:300008347"
        ],
        "id": 7055365,
        "name:xx": "Lido del Savio"
      }
    },
    {
      "geometry": {
        "type": "Point",
        "coordinates": [
          12.333333,
          41.716667
        ]
      },
      "type": "Feature",
      "properties": {
        "hierarchy": [
          "tgn:7055366",
          "tgn:7003138",
          "tgn:1000003",
          "tgn:7003080",
          "tgn:1000080",
          "tgn:7029392"
        ],
        "placetype": [
          "aat:300007783"
        ],
        "id": 7055366,
        "name:xx": "Stazione Lido Castel Fusano"
      }
    },
    {
      "geometry": {
        "type": "Point",
        "coordinates": [
          12.341389,
          45.376389
        ]
      },
      "type": "Feature",
      "properties": {
        "hierarchy": [
          "tgn:7055368",
          "tgn:7003006",
          "tgn:1000003",
          "tgn:7002997",
          "tgn:1000080",
          "tgn:7029392"
        ],
        "placetype": [
          "aat:300008816"
        ],
        "id": 7055368,
        "name:xx": "Lido, Litorale di"
      }
    }
  ]
}
