{
  "geometry": {
    "type": "Point",
    "coordinates": [
      -89.1333,
      39.45
    ]
  },
  "type": "Feature",
  "properties": {
    "hierarchy": [
      "tgn:2199935",
      "tgn:1000001",
      "tgn:1002268",
      "tgn:7012149",
      "tgn:7007251",
      "tgn:7029392"
    ],
    "placetype": [
      "aat:300008699"
    ],
    "id": 2199935,
    "name:xx": "Brushy Branch"
  }
}
