{
  "geometry": {
    "type": "Point",
    "coordinates": [
      -74.5333,
      41.8333
    ]
  },
  "type": "Feature",
  "properties": {
    "hierarchy": [
      "tgn:2069438",
      "tgn:1000001",
      "tgn:7012149",
      "tgn:1002926",
      "tgn:7007568",
      "tgn:7029392"
    ],
    "placetype": [
      "aat:300008347"
    ],
    "id": 2069438,
    "name:xx": "Grahamsville"
  }
}
