{
  "type": "FeatureCollection",
  "features": [
    {
      "geometry": {
        "type": "Point",
        "coordinates": [
          -122.25,
          37.5
        ]
      },
      "type": "Feature",
      "properties": {
        "hierarchy": [
          "tgn:2013844",
          "tgn:1000001",
          "tgn:7012149",
          "tgn:7007157",
          "tgn:1002864",
          "tgn:7029392"
        ],
        "placetype": [
          "aat:300008347"
        ],
        "id": 2013844,
        "name:xx": "San Carlos"
      }
    },
    {
      "geometry": {
        "type": "Point",
        "coordinates": [
          -117.6,
          33.4167
        ]
      },
      "type": "Feature",
      "properties": {
        "hierarchy": [
          "tgn:2013845",
          "tgn:1000001",
          "tgn:7012149",
          "tgn:7007157",
          "tgn:1002748",
          "tgn:7029392"
        ],
        "placetype": [
          "aat:300008347"
        ],
        "id": 2013845,
        "name:xx": "San Clemente"
      }
    },
    {
      "geometry": {
        "type": "Point",
        "coordinates": [
          -121.8333,
          36.6167
        ]
      },
      "type": "Feature",
      "properties": {
        "hierarchy": [
          "tgn:2013849",
          "tgn:1000001",
          "tgn:7012149",
          "tgn:7007157",
          "tgn:1002684",
          "tgn:7029392"
        ],
        "placetype": [
          "aat:300008347"
        ],
        "id": 2013849,
        "name:xx": "Sand City"
      }
    }
  ]
}
