{
  "geometry": {
    "type": "Point",
    "coordinates": [
      -83.0833,
      33.9167
    ]
  },
  "type": "Feature",
  "properties": {
    "hierarchy": [
      "tgn:2410693",
      "tgn:1000001",
      "tgn:7012149",
      "tgn:2000400",
      "tgn:7007248",
      "tgn:7029392"
    ],
    "placetype": [
      "aat:300008706"
    ],
    "id": 2410693,
    "name:xx": "Indian Creek"
  }
}
