{
  "geometry": {
    "type": "Point",
    "coordinates": [
      -84.6833,
      38.1167
    ]
  },
  "type": "Feature",
  "properties": {
    "hierarchy": [
      "tgn:2551249",
      "tgn:1000001",
      "tgn:7012149",
      "tgn:1003036",
      "tgn:7007255",
      "tgn:7029392"
    ],
    "placetype": [
      "aat:300008347"
    ],
    "id": 2551249,
    "name:xx": "Nugent Crossroads"
  }
}
