{
  "geometry": {
    "type": "Point",
    "coordinates": [
      -76.65,
      41.0667
    ]
  },
  "type": "Feature",
  "properties": {
    "hierarchy": [
      "tgn:2236966",
      "tgn:1000001",
      "tgn:7012149",
      "tgn:7007710",
      "tgn:7029392"
    ],
    "placetype": [
      "aat:300008706"
    ],
    "id": 2236966,
    "name:xx": "Chillisquaque Creek"
  }
}
