{
  "geometry": {
    "type": "Point",
    "coordinates": [
      -114.7667,
      43.7833
    ]
  },
  "type": "Feature",
  "properties": {
    "hierarchy": [
      "tgn:1129462",
      "tgn:1000001",
      "tgn:7012149",
      "tgn:7007250",
      "tgn:7029392"
    ],
    "placetype": [
      "aat:300008707"
    ],
    "id": 1129462,
    "name:xx": "Salmon"
  }
}
