{
  "geometry": {
    "type": "Point",
    "coordinates": [
      -156.6667,
      56.0833
    ]
  },
  "type": "Feature",
  "properties": {
    "hierarchy": [
      "tgn:2134478",
      "tgn:7006450",
      "tgn:1000001",
      "tgn:2124012",
      "tgn:7012149",
      "tgn:7029392"
    ],
    "placetype": [
      "aat:300008791"
    ],
    "id": 2134478,
    "name:xx": "Anowik Island"
  }
}
