{
  "geometry": {
    "type": "Point",
    "coordinates": [
      -110.6167,
      42.3667
    ]
  },
  "type": "Feature",
  "properties": {
    "hierarchy": [
      "tgn:2334873",
      "tgn:1000001",
      "tgn:7012149",
      "tgn:2002376",
      "tgn:7007923",
      "tgn:7029392"
    ],
    "placetype": [
      "aat:300008706"
    ],
    "id": 2334873,
    "name:xx": "Forked Creek"
  }
}
