{
  "type": "FeatureCollection",
  "features": [
    {
      "geometry": {
        "type": "Point",
        "coordinates": [
          -92.516667,
          15.766667
        ]
      },
      "type": "Feature",
      "properties": {
        "hierarchy": [
          "tgn:7349520",
          "tgn:7005580",
          "tgn:1000001",
          "tgn:7005560",
          "tgn:7029392"
        ],
        "placetype": [
          "aat:300008795"
        ],
        "id": 7349520,
        "name:xx": "Agua Fria, Cerro"
      }
    },
    {
      "geometry": {
        "type": "Point",
        "coordinates": [
          -99.2,
          23.416667
        ]
      },
      "type": "Feature",
      "properties": {
        "hierarchy": [
          "tgn:7349521",
          "tgn:1000001",
          "tgn:7005597",
          "tgn:7005560",
          "tgn:7029392"
        ],
        "placetype": [
          "aat:300266554",
          "aat:300008699"
        ],
        "id": 7349521,
        "name:xx": "Agua Fría"
      }
    },
    {
      "geometry": {
        "type": "Point",
        "coordinates": [
          -110.866667,
          30.8
        ]
      },
      "type": "Feature",
      "properties": {
        "hierarchy": [
          "tgn:7349522",
          "tgn:1000001",
          "tgn:1001960",
          "tgn:7005560",
          "tgn:7029392"
        ],
        "placetype": [
          "aat:300008347"
        ],
        "id": 7349522,
        "name:xx": "Agua Fría"
      }
    },
    {
      "geometry": {
        "type": "Point",
        "coordinates": [
          -110.033333,
          30.766667
        ]
      },
      "type": "Feature",
      "properties": {
        "hierarchy": [
          "tgn:7349523",
          "tgn:1000001",
          "tgn:1001960",
          "tgn:7005560",
          "tgn:7029392"
        ],
        "placetype": [
          "aat:300008347"
        ],
        "id": 7349523,
        "name:xx": "Agua Fría"
      }
    },
    {
      "geometry": {
        "type": "Point",
        "coordinates": [
          -111.483333,
          30.55
        ]
      },
      "type": "Feature",
      "properties": {
        "hierarchy": [
          "tgn:7349524",
          "tgn:1000001",
          "tgn:1001960",
          "tgn:7005560",
          "tgn:7029392"
        ],
        "placetype": [
          "aat:300008347"
        ],
        "id": 7349524,
        "name:xx": "Agua Fría"
      }
    },
    {
      "geometry": {
        "type": "Point",
        "coordinates": [
          -98.133333,
          25.083333
        ]
      },
      "type": "Feature",
      "properties": {
        "hierarchy": [
          "tgn:7349525",
          "tgn:1000001",
          "tgn:7005597",
          "tgn:7005560",
          "tgn:7029392"
        ],
        "placetype": [
          "aat:300008347"
        ],
        "id": 7349525,
        "name:xx": "Abra de Emiliano"
      }
    },
    {
      "geometry": {
        "type": "Point",
        "coordinates": [
          -105.9,
          24.05
        ]
      },
      "type": "Feature",
      "properties": {
        "hierarchy": [
          "tgn:7349526",
          "tgn:7005583",
          "tgn:1000001",
          "tgn:7005560",
          "tgn:7029392"
        ],
        "placetype": [
          "aat:300008795"
        ],
        "id": 7349526,
        "name:xx": "Abra, Cerro"
      }
    },
    {
      "geometry": {
        "type": "Point",
        "coordinates": [
          -101.416667,
          26.75
        ]
      },
      "type": "Feature",
      "properties": {
        "hierarchy": [
          "tgn:7349527",
          "tgn:1001853",
          "tgn:1000001",
          "tgn:7005560",
          "tgn:7029392"
        ],
        "placetype": [
          "aat:300266554",
          "aat:300008699"
        ],
        "id": 7349527,
        "name:xx": "Abra, Arroyo del"
      }
    },
    {
      "geometry": {
        "type": "Point",
        "coordinates": [
          -99.283333,
          26.433333
        ]
      },
      "type": "Feature",
      "properties": {
        "hierarchy": [
          "tgn:7349528",
          "tgn:1000001",
          "tgn:7005597",
          "tgn:7005560",
          "tgn:7029392"
        ],
        "placetype": [
          "aat:300008347"
        ],
        "id": 7349528,
        "name:xx": "Abra"
      }
    },
    {
      "geometry": {
        "type": "Point",
        "coordinates": [
          -98.9,
          26.033333
        ]
      },
      "type": "Feature",
      "properties": {
        "hierarchy": [
          "tgn:7349529",
          "tgn:1000001",
          "tgn:7005597",
          "tgn:7005560",
          "tgn:7029392"
        ],
        "placetype": [
          "aat:300008347"
        ],
        "id": 7349529,
        "name:xx": "Abra"
      }
    }
  ]
}
