{
  "geometry": {
    "type": "Point",
    "coordinates": [
      2.24197,
      41.774305
    ]
  },
  "type": "Feature",
  "properties": {
    "hierarchy": [
      "tgn:7338961",
      "tgn:7002808",
      "tgn:7030216",
      "tgn:1000003",
      "tgn:1000095",
      "tgn:7029392"
    ],
    "placetype": [
      "aat:300008347"
    ],
    "id": 7338961,
    "name:xx": "El Cerdá de la Garga"
  }
}
