{
  "geometry": {
    "type": "Point",
    "coordinates": [
      -103.9167,
      44.15
    ]
  },
  "type": "Feature",
  "properties": {
    "hierarchy": [
      "tgn:2268499",
      "tgn:1000001",
      "tgn:2001810",
      "tgn:7012149",
      "tgn:7007713",
      "tgn:7029392"
    ],
    "placetype": [
      "aat:300008680"
    ],
    "id": 2268499,
    "name:xx": "Crooks Lake"
  }
}
