{
  "geometry": {
    "type": "Point",
    "coordinates": [
      -77.6833,
      34.3333
    ]
  },
  "type": "Feature",
  "properties": {
    "hierarchy": [
      "tgn:2725657",
      "tgn:1000001",
      "tgn:7012149",
      "tgn:2001527",
      "tgn:7007709",
      "tgn:7029392"
    ],
    "placetype": [
      "aat:300132316"
    ],
    "id": 2725657,
    "name:xx": "Topsail Sound"
  }
}
