{
  "geometry": {
    "type": "Point",
    "coordinates": [
      -118.0167,
      43.75
    ]
  },
  "type": "Feature",
  "properties": {
    "hierarchy": [
      "tgn:2186654",
      "tgn:1000001",
      "tgn:7012149",
      "tgn:2001718",
      "tgn:7007708",
      "tgn:7029392"
    ],
    "placetype": [
      "aat:300386845"
    ],
    "id": 2186654,
    "name:xx": "Boney Basin"
  }
}
