{
  "geometry": {
    "type": "Point",
    "coordinates": [
      -77.65,
      40.2833
    ]
  },
  "type": "Feature",
  "properties": {
    "hierarchy": [
      "tgn:2401076",
      "tgn:1000001",
      "tgn:7012149",
      "tgn:1002779",
      "tgn:7007710",
      "tgn:7029392"
    ],
    "placetype": [
      "aat:300008761"
    ],
    "id": 2401076,
    "name:xx": "Horse Valley"
  }
}
