{
  "geometry": {
    "type": "Point",
    "coordinates": [
      -97.4833,
      46.75
    ]
  },
  "type": "Feature",
  "properties": {
    "hierarchy": [
      "tgn:2164733",
      "tgn:2001565",
      "tgn:1000001",
      "tgn:7012149",
      "tgn:7007705",
      "tgn:7029392"
    ],
    "placetype": [
      "aat:300008680"
    ],
    "id": 2164733,
    "name:xx": "Bertha, Lake"
  }
}
