{
  "geometry": {
    "type": "Point",
    "coordinates": [
      -86.2833,
      39.9667
    ]
  },
  "type": "Feature",
  "properties": {
    "hierarchy": [
      "tgn:2413828",
      "tgn:1000001",
      "tgn:7012149",
      "tgn:7007252",
      "tgn:7029392"
    ],
    "placetype": [
      "aat:300008699"
    ],
    "id": 2413828,
    "name:xx": "Irishman Run"
  }
}
