{
  "geometry": {
    "type": "Point",
    "coordinates": [
      -122.5833,
      44.7667
    ]
  },
  "type": "Feature",
  "properties": {
    "hierarchy": [
      "tgn:2477476",
      "tgn:1000001",
      "tgn:7012149",
      "tgn:2001717",
      "tgn:7007708",
      "tgn:7029392"
    ],
    "placetype": [
      "aat:300006191"
    ],
    "id": 2477476,
    "name:xx": "Lyons Log Pond"
  }
}
