{
  "geometry": {
    "type": "Point",
    "coordinates": [
      21.1833,
      5.0167
    ]
  },
  "type": "Feature",
  "properties": {
    "hierarchy": [
      "tgn:1088313",
      "tgn:1000965",
      "tgn:7001242",
      "tgn:1000155",
      "tgn:7029392"
    ],
    "placetype": [
      "aat:300008347"
    ],
    "id": 1088313,
    "name:xx": "Alindao"
  }
}
