{
  "geometry": {
    "type": "Point",
    "coordinates": [
      -87.3167,
      34.3667
    ]
  },
  "type": "Feature",
  "properties": {
    "hierarchy": [
      "tgn:2306128",
      "tgn:7002659",
      "tgn:1000001",
      "tgn:7012149",
      "tgn:7029392"
    ],
    "placetype": [
      "aat:300008706"
    ],
    "id": 2306128,
    "name:xx": "East Fork Beech Creek"
  }
}
