{
  "geometry": {
    "type": "Point",
    "coordinates": [
      -87.2333,
      39.1833
    ]
  },
  "type": "Feature",
  "properties": {
    "hierarchy": [
      "tgn:2166568",
      "tgn:1000001",
      "tgn:7012149",
      "tgn:2000556",
      "tgn:7007252",
      "tgn:7029392"
    ],
    "placetype": [
      "aat:300008699"
    ],
    "id": 2166568,
    "name:xx": "Big Branch"
  }
}
