{
  "geometry": {
    "type": "Point",
    "coordinates": [
      33.60392,
      30.207823
    ]
  },
  "type": "Feature",
  "properties": {
    "hierarchy": [
      "tgn:7535891",
      "tgn:7001242",
      "tgn:7016833",
      "tgn:7001335",
      "tgn:7029392"
    ],
    "placetype": [
      "aat:300379998"
    ],
    "name:en": "Quday'ī, Wādī al",
    "id": 7535891
  }
}
