{
  "type": "FeatureCollection",
  "features": [
    {
      "geometry": {
        "type": "Point",
        "coordinates": [
          -73.3667,
          41.2
        ]
      },
      "type": "Feature",
      "properties": {
        "hierarchy": [
          "tgn:7016891",
          "tgn:1002366",
          "tgn:1000001",
          "tgn:7012149",
          "tgn:7007159",
          "tgn:7029392"
        ],
        "placetype": [
          "aat:300008347"
        ],
        "id": 7016891,
        "name:xx": "Weston"
      }
    },
    {
      "geometry": {
        "type": "Point",
        "coordinates": [
          20.5833,
          32.5333
        ]
      },
      "type": "Feature",
      "properties": {
        "hierarchy": [
          "tgn:7016892",
          "tgn:7001242",
          "tgn:7000604",
          "tgn:1000172",
          "tgn:7029392"
        ],
        "placetype": [
          "aat:300008347",
          "aat:300000810",
          "aat:300000835",
          "aat:300008389",
          "aat:300387231",
          "aat:300008375"
        ],
        "id": 7016892,
        "name:xx": "Tūkrah"
      }
    },
    {
      "geometry": {
        "type": "Point",
        "coordinates": [
          35.3833,
          31.0667
        ]
      },
      "type": "Feature",
      "properties": {
        "hierarchy": [
          "tgn:7016893",
          "tgn:1000861",
          "tgn:1000004",
          "tgn:1000119",
          "tgn:7029392"
        ],
        "placetype": [
          "aat:300008347",
          "aat:300167671",
          "aat:300000833"
        ],
        "id": 7016893,
        "name:xx": "Sedom"
      }
    }
  ]
}
