{
  "type": "FeatureCollection",
  "features": [
    {
      "geometry": {
        "type": "Point",
        "coordinates": [
          -80.3833,
          25.55
        ]
      },
      "type": "Feature",
      "properties": {
        "hierarchy": [
          "tgn:2624470",
          "tgn:1000001",
          "tgn:7012149",
          "tgn:1002314",
          "tgn:7007240",
          "tgn:7029392"
        ],
        "placetype": [
          "aat:300000390"
        ],
        "id": 2624470,
        "name:xx": "Rock Pit Number 57"
      }
    },
    {
      "geometry": {
        "type": "Point",
        "coordinates": [
          -119.5833,
          44.2833
        ]
      },
      "type": "Feature",
      "properties": {
        "hierarchy": [
          "tgn:2624471",
          "tgn:1000001",
          "tgn:7012149",
          "tgn:2001708",
          "tgn:7007708",
          "tgn:7029392"
        ],
        "placetype": [
          "aat:300006191"
        ],
        "id": 2624471,
        "name:xx": "Rock Pit Reservoir"
      }
    },
    {
      "geometry": {
        "type": "Point",
        "coordinates": [
          -131.4,
          55.35
        ]
      },
      "type": "Feature",
      "properties": {
        "hierarchy": [
          "tgn:2624472",
          "tgn:7006450",
          "tgn:1000001",
          "tgn:2124076",
          "tgn:7012149",
          "tgn:7029392"
        ],
        "placetype": [
          "aat:300008850"
        ],
        "id": 2624472,
        "name:xx": "Rock Point"
      }
    },
    {
      "geometry": {
        "type": "Point",
        "coordinates": [
          -132.9167,
          56.6667
        ]
      },
      "type": "Feature",
      "properties": {
        "hierarchy": [
          "tgn:2624473",
          "tgn:7006450",
          "tgn:1000001",
          "tgn:7012149",
          "tgn:2000088",
          "tgn:7029392"
        ],
        "placetype": [
          "aat:300008850"
        ],
        "id": 2624473,
        "name:xx": "Rock Point"
      }
    },
    {
      "geometry": {
        "type": "Point",
        "coordinates": [
          -135.4833,
          57.5167
        ]
      },
      "type": "Feature",
      "properties": {
        "hierarchy": [
          "tgn:2624474",
          "tgn:7006450",
          "tgn:1000001",
          "tgn:7012149",
          "tgn:2124002",
          "tgn:7029392"
        ],
        "placetype": [
          "aat:300008850"
        ],
        "id": 2624474,
        "name:xx": "Rock Point"
      }
    },
    {
      "geometry": {
        "type": "Point",
        "coordinates": [
          -133.4667,
          57.6667
        ]
      },
      "type": "Feature",
      "properties": {
        "hierarchy": [
          "tgn:2624475",
          "tgn:7006450",
          "tgn:1000001",
          "tgn:7012149",
          "tgn:7019760",
          "tgn:7029392"
        ],
        "placetype": [
          "aat:300008850"
        ],
        "id": 2624475,
        "name:xx": "Rock Point"
      }
    },
    {
      "geometry": {
        "type": "Point",
        "coordinates": [
          -153.4833,
          57.7667
        ]
      },
      "type": "Feature",
      "properties": {
        "hierarchy": [
          "tgn:2624476",
          "tgn:7006450",
          "tgn:1000001",
          "tgn:2124012",
          "tgn:7012149",
          "tgn:7029392"
        ],
        "placetype": [
          "aat:300008850"
        ],
        "id": 2624476,
        "name:xx": "Rock Point"
      }
    },
    {
      "geometry": {
        "type": "Point",
        "coordinates": [
          -142.4667,
          63.15
        ]
      },
      "type": "Feature",
      "properties": {
        "hierarchy": [
          "tgn:2624477",
          "tgn:7006450",
          "tgn:1000001",
          "tgn:7012149",
          "tgn:2000085",
          "tgn:7029392"
        ],
        "placetype": [
          "aat:300008850"
        ],
        "id": 2624477,
        "name:xx": "Rock Point"
      }
    },
    {
      "geometry": {
        "type": "Point",
        "coordinates": [
          -162.0667,
          63.5
        ]
      },
      "type": "Feature",
      "properties": {
        "hierarchy": [
          "tgn:2624478",
          "tgn:7006450",
          "tgn:1000001",
          "tgn:7012149",
          "tgn:2000079",
          "tgn:7029392"
        ],
        "placetype": [
          "aat:300008850"
        ],
        "id": 2624478,
        "name:xx": "Rock Point"
      }
    },
    {
      "geometry": {
        "type": "Point",
        "coordinates": [
          -91.0667,
          34.2833
        ]
      },
      "type": "Feature",
      "properties": {
        "hierarchy": [
          "tgn:2624479",
          "tgn:1000001",
          "tgn:7016172",
          "tgn:7012149",
          "tgn:2000158",
          "tgn:7029392"
        ],
        "placetype": [
          "aat:300008850"
        ],
        "id": 2624479,
        "name:xx": "Rock Point"
      }
    }
  ]
}
