{
  "geometry": {
    "type": "Point",
    "coordinates": [
      -77.7667,
      40.0333
    ]
  },
  "type": "Feature",
  "properties": {
    "hierarchy": [
      "tgn:2155911",
      "tgn:1000001",
      "tgn:7012149",
      "tgn:1002387",
      "tgn:7007710",
      "tgn:7029392"
    ],
    "placetype": [
      "aat:300008761"
    ],
    "id": 2155911,
    "name:xx": "Bear Valley"
  }
}
