{
  "type": "FeatureCollection",
  "features": [
    {
      "geometry": {
        "type": "Point",
        "coordinates": [
          -105.0333,
          39.2333
        ]
      },
      "type": "Feature",
      "properties": {
        "hierarchy": [
          "tgn:2297690",
          "tgn:1000001",
          "tgn:7012149",
          "tgn:2000209",
          "tgn:7007158",
          "tgn:7029392"
        ],
        "placetype": [
          "aat:300008761"
        ],
        "id": 2297690,
        "name:xx": "Dry Gulch"
      }
    },
    {
      "geometry": {
        "type": "Point",
        "coordinates": [
          -107.9167,
          37.3167
        ]
      },
      "type": "Feature",
      "properties": {
        "hierarchy": [
          "tgn:2297691",
          "tgn:1000001",
          "tgn:7012149",
          "tgn:2000225",
          "tgn:7007158",
          "tgn:7029392"
        ],
        "placetype": [
          "aat:300008761"
        ],
        "id": 2297691,
        "name:xx": "Dry Gulch"
      }
    },
    {
      "geometry": {
        "type": "Point",
        "coordinates": [
          -108.1333,
          38.8833
        ]
      },
      "type": "Feature",
      "properties": {
        "hierarchy": [
          "tgn:2297692",
          "tgn:1000001",
          "tgn:7012149",
          "tgn:2000206",
          "tgn:7007158",
          "tgn:7029392"
        ],
        "placetype": [
          "aat:300008761"
        ],
        "id": 2297692,
        "name:xx": "Dry Gulch"
      }
    },
    {
      "geometry": {
        "type": "Point",
        "coordinates": [
          -107.2,
          38.5
        ]
      },
      "type": "Feature",
      "properties": {
        "hierarchy": [
          "tgn:2297693",
          "tgn:1000001",
          "tgn:7012149",
          "tgn:2000217",
          "tgn:7007158",
          "tgn:7029392"
        ],
        "placetype": [
          "aat:300008761"
        ],
        "id": 2297693,
        "name:xx": "Dry Gulch"
      }
    },
    {
      "geometry": {
        "type": "Point",
        "coordinates": [
          -107.6667,
          37.9
        ]
      },
      "type": "Feature",
      "properties": {
        "hierarchy": [
          "tgn:2297694",
          "tgn:1000001",
          "tgn:7012149",
          "tgn:7007158",
          "tgn:2000247",
          "tgn:7029392"
        ],
        "placetype": [
          "aat:300008761"
        ],
        "id": 2297694,
        "name:xx": "Dry Gulch"
      }
    },
    {
      "geometry": {
        "type": "Point",
        "coordinates": [
          -107.6833,
          38.1667
        ]
      },
      "type": "Feature",
      "properties": {
        "hierarchy": [
          "tgn:2297695",
          "tgn:1000001",
          "tgn:7012149",
          "tgn:2000237",
          "tgn:7007158",
          "tgn:7029392"
        ],
        "placetype": [
          "aat:300008761"
        ],
        "id": 2297695,
        "name:xx": "Dry Gulch"
      }
    },
    {
      "geometry": {
        "type": "Point",
        "coordinates": [
          -106.3333,
          37.9167
        ]
      },
      "type": "Feature",
      "properties": {
        "hierarchy": [
          "tgn:2297696",
          "tgn:1000001",
          "tgn:7012149",
          "tgn:7007158",
          "tgn:2000246",
          "tgn:7029392"
        ],
        "placetype": [
          "aat:300008761"
        ],
        "id": 2297696,
        "name:xx": "Dry Gulch"
      }
    },
    {
      "geometry": {
        "type": "Point",
        "coordinates": [
          -106.8833,
          37.8667
        ]
      },
      "type": "Feature",
      "properties": {
        "hierarchy": [
          "tgn:2297697",
          "tgn:1000001",
          "tgn:7012149",
          "tgn:2000231",
          "tgn:7007158",
          "tgn:7029392"
        ],
        "placetype": [
          "aat:300008761"
        ],
        "id": 2297697,
        "name:xx": "Dry Gulch"
      }
    },
    {
      "geometry": {
        "type": "Point",
        "coordinates": [
          -106.3167,
          37.25
        ]
      },
      "type": "Feature",
      "properties": {
        "hierarchy": [
          "tgn:2297698",
          "tgn:1000001",
          "tgn:2000202",
          "tgn:7012149",
          "tgn:7007158",
          "tgn:7029392"
        ],
        "placetype": [
          "aat:300008761"
        ],
        "id": 2297698,
        "name:xx": "Dry Gulch"
      }
    },
    {
      "geometry": {
        "type": "Point",
        "coordinates": [
          -105.1,
          37.3667
        ]
      },
      "type": "Feature",
      "properties": {
        "hierarchy": [
          "tgn:2297699",
          "tgn:1000001",
          "tgn:7012149",
          "tgn:2000219",
          "tgn:7007158",
          "tgn:7029392"
        ],
        "placetype": [
          "aat:300008761"
        ],
        "id": 2297699,
        "name:xx": "Dry Gulch"
      }
    }
  ]
}
