{
  "geometry": {
    "type": "Point",
    "coordinates": [
      19.14,
      -31.424
    ]
  },
  "type": "Feature",
  "properties": {
    "hierarchy": [
      "tgn:1128121",
      "tgn:7001242",
      "tgn:7017582",
      "tgn:1000193",
      "tgn:7029392"
    ],
    "placetype": [
      "aat:300008707"
    ],
    "id": 1128121,
    "name:xx": "Oorlogskloof"
  }
}
