{
  "geometry": {
    "type": "Point",
    "coordinates": [
      -88.4333,
      42.6833
    ]
  },
  "type": "Feature",
  "properties": {
    "hierarchy": [
      "tgn:2120786",
      "tgn:1000001",
      "tgn:7012149",
      "tgn:1002982",
      "tgn:7007922",
      "tgn:7029392"
    ],
    "placetype": [
      "aat:300008347"
    ],
    "id": 2120786,
    "name:xx": "Bowers"
  }
}
