{
  "type": "FeatureCollection",
  "features": [
    {
      "geometry": {
        "type": "Point",
        "coordinates": [
          -105.188611,
          24.304444
        ]
      },
      "type": "Feature",
      "properties": {
        "hierarchy": [
          "tgn:7377060",
          "tgn:7005583",
          "tgn:1000001",
          "tgn:7005560",
          "tgn:7029392"
        ],
        "placetype": [
          "aat:300008347"
        ],
        "id": 7377060,
        "name:xx": "La Trinidad"
      }
    },
    {
      "geometry": {
        "type": "Point",
        "coordinates": [
          -109.883333,
          23.866667
        ]
      },
      "type": "Feature",
      "properties": {
        "hierarchy": [
          "tgn:7377061",
          "tgn:1001836",
          "tgn:1000001",
          "tgn:7005560",
          "tgn:7029392"
        ],
        "placetype": [
          "aat:300008347"
        ],
        "id": 7377061,
        "name:xx": "La Trinidad"
      }
    },
    {
      "geometry": {
        "type": "Point",
        "coordinates": [
          -101.216667,
          23.116667
        ]
      },
      "type": "Feature",
      "properties": {
        "hierarchy": [
          "tgn:7377062",
          "tgn:1000001",
          "tgn:7005594",
          "tgn:7005560",
          "tgn:7029392"
        ],
        "placetype": [
          "aat:300008347"
        ],
        "id": 7377062,
        "name:xx": "La Trinidad"
      }
    },
    {
      "geometry": {
        "type": "Point",
        "coordinates": [
          -100.916667,
          23.016667
        ]
      },
      "type": "Feature",
      "properties": {
        "hierarchy": [
          "tgn:7377063",
          "tgn:1000001",
          "tgn:7005594",
          "tgn:7005560",
          "tgn:7029392"
        ],
        "placetype": [
          "aat:300008347"
        ],
        "id": 7377063,
        "name:xx": "La Trinidad"
      }
    },
    {
      "geometry": {
        "type": "Point",
        "coordinates": [
          -104.016667,
          22.6
        ]
      },
      "type": "Feature",
      "properties": {
        "hierarchy": [
          "tgn:7377064",
          "tgn:1000001",
          "tgn:7005601",
          "tgn:7005560",
          "tgn:7029392"
        ],
        "placetype": [
          "aat:300008347"
        ],
        "id": 7377064,
        "name:xx": "La Trinidad"
      }
    },
    {
      "geometry": {
        "type": "Point",
        "coordinates": [
          -101.533333,
          22.466667
        ]
      },
      "type": "Feature",
      "properties": {
        "hierarchy": [
          "tgn:7377065",
          "tgn:1000001",
          "tgn:7005601",
          "tgn:7005560",
          "tgn:7029392"
        ],
        "placetype": [
          "aat:300008347"
        ],
        "id": 7377065,
        "name:xx": "La Trinidad"
      }
    },
    {
      "geometry": {
        "type": "Point",
        "coordinates": [
          -98.283333,
          21.883333
        ]
      },
      "type": "Feature",
      "properties": {
        "hierarchy": [
          "tgn:7377066",
          "tgn:1000001",
          "tgn:7005599",
          "tgn:7005560",
          "tgn:7029392"
        ],
        "placetype": [
          "aat:300008347"
        ],
        "id": 7377066,
        "name:xx": "La Trinidad"
      }
    },
    {
      "geometry": {
        "type": "Point",
        "coordinates": [
          -102.45,
          21.416667
        ]
      },
      "type": "Feature",
      "properties": {
        "hierarchy": [
          "tgn:7377067",
          "tgn:7005586",
          "tgn:1000001",
          "tgn:7005560",
          "tgn:7029392"
        ],
        "placetype": [
          "aat:300008347"
        ],
        "id": 7377067,
        "name:xx": "La Trinidad"
      }
    },
    {
      "geometry": {
        "type": "Point",
        "coordinates": [
          -100.9,
          21.333333
        ]
      },
      "type": "Feature",
      "properties": {
        "hierarchy": [
          "tgn:7377068",
          "tgn:7005584",
          "tgn:1000001",
          "tgn:7005560",
          "tgn:7029392"
        ],
        "placetype": [
          "aat:300008347"
        ],
        "id": 7377068,
        "name:xx": "La Trinidad"
      }
    },
    {
      "geometry": {
        "type": "Point",
        "coordinates": [
          -103.533333,
          20.783333
        ]
      },
      "type": "Feature",
      "properties": {
        "hierarchy": [
          "tgn:7377069",
          "tgn:7005586",
          "tgn:1000001",
          "tgn:7005560",
          "tgn:7029392"
        ],
        "placetype": [
          "aat:300008347"
        ],
        "id": 7377069,
        "name:xx": "La Trinidad"
      }
    }
  ]
}
