{
  "geometry": {
    "type": "Point",
    "coordinates": [
      -100.6667,
      34.8167
    ]
  },
  "type": "Feature",
  "properties": {
    "hierarchy": [
      "tgn:2274583",
      "tgn:1000001",
      "tgn:7012149",
      "tgn:2001976",
      "tgn:7007826",
      "tgn:7029392"
    ],
    "placetype": [
      "aat:300008706"
    ],
    "id": 2274583,
    "name:xx": "Dalton Creek"
  }
}
