{
  "geometry": {
    "type": "Point",
    "coordinates": [
      34.4833,
      0.3333
    ]
  },
  "type": "Feature",
  "properties": {
    "hierarchy": [
      "tgn:1090518",
      "tgn:7001242",
      "tgn:7593767",
      "tgn:1000169",
      "tgn:7029392"
    ],
    "placetype": [
      "aat:300008347"
    ],
    "id": 1090518,
    "name:xx": "Mumias"
  }
}
