{
  "geometry": {
    "type": "Point",
    "coordinates": [
      -102.5167,
      39.2833
    ]
  },
  "type": "Feature",
  "properties": {
    "hierarchy": [
      "tgn:2653325",
      "tgn:1000001",
      "tgn:7012149",
      "tgn:2000223",
      "tgn:7007158",
      "tgn:7029392"
    ],
    "placetype": [
      "aat:300008706"
    ],
    "id": 2653325,
    "name:xx": "Sevenmile Creek"
  }
}
