{
  "geometry": {
    "type": "Point",
    "coordinates": [
      -81.8667,
      36.0667
    ]
  },
  "type": "Feature",
  "properties": {
    "hierarchy": [
      "tgn:2194722",
      "tgn:2001468",
      "tgn:1000001",
      "tgn:7012149",
      "tgn:7007709",
      "tgn:7029392"
    ],
    "placetype": [
      "aat:300008798"
    ],
    "id": 2194722,
    "name:xx": "Brier Knob"
  }
}
