{
  "geometry": {
    "type": "Point",
    "coordinates": [
      -92.05,
      35.2667
    ]
  },
  "type": "Feature",
  "properties": {
    "hierarchy": [
      "tgn:2244359",
      "tgn:1000001",
      "tgn:7016172",
      "tgn:7012149",
      "tgn:2000177",
      "tgn:7029392"
    ],
    "placetype": [
      "aat:300008706"
    ],
    "id": 2244359,
    "name:xx": "Clifty Creek"
  }
}
