{
  "geometry": {
    "type": "Point",
    "coordinates": [
      120.612,
      23.7759
    ]
  },
  "type": "Feature",
  "properties": {
    "hierarchy": [
      "tgn:7478356",
      "tgn:1000004",
      "tgn:7467799",
      "tgn:1000141",
      "tgn:7029392"
    ],
    "placetype": [
      "aat:300008347"
    ],
    "id": 7478356,
    "name:xx": "Rongxing"
  }
}
