{
  "geometry": {
    "type": "Point",
    "coordinates": [
      2.2167,
      48.8833
    ]
  },
  "type": "Feature",
  "properties": {
    "hierarchy": [
      "tgn:1108271",
      "tgn:1000003",
      "tgn:7002883",
      "tgn:1000070",
      "tgn:7029392"
    ],
    "placetype": [
      "aat:300008777"
    ],
    "id": 1108271,
    "name:xx": "Valérien, Mont"
  }
}
