{
  "geometry": {
    "type": "Point",
    "coordinates": [
      96.8167,
      4.55
    ]
  },
  "type": "Feature",
  "properties": {
    "hierarchy": [
      "tgn:1140248",
      "tgn:7016479",
      "tgn:1000004",
      "tgn:1000116",
      "tgn:7029392"
    ],
    "placetype": [
      "aat:300008347",
      "aat:300008375"
    ],
    "id": 1140248,
    "name:xx": "Oreng"
  }
}
