{
  "type": "FeatureCollection",
  "features": [
    {
      "geometry": {
        "type": "Point",
        "coordinates": [
          -91.2667,
          37.75
        ]
      },
      "type": "Feature",
      "properties": {
        "hierarchy": [
          "tgn:2223370",
          "tgn:1000001",
          "tgn:7012149",
          "tgn:2001190",
          "tgn:7007523",
          "tgn:7029392"
        ],
        "placetype": [
          "aat:300000390"
        ],
        "id": 2223370,
        "name:xx": "Carson Iron Banks"
      }
    },
    {
      "geometry": {
        "type": "Point",
        "coordinates": [
          -108.1,
          38.9833
        ]
      },
      "type": "Feature",
      "properties": {
        "hierarchy": [
          "tgn:2223371",
          "tgn:1000001",
          "tgn:7012149",
          "tgn:2000230",
          "tgn:7007158",
          "tgn:7029392"
        ],
        "placetype": [
          "aat:300006191"
        ],
        "id": 2223371,
        "name:xx": "Carson Lake"
      }
    },
    {
      "geometry": {
        "type": "Point",
        "coordinates": [
          -103.0167,
          38.6
        ]
      },
      "type": "Feature",
      "properties": {
        "hierarchy": [
          "tgn:2223372",
          "tgn:1000001",
          "tgn:7012149",
          "tgn:7007158",
          "tgn:7029392"
        ],
        "placetype": [
          "aat:300386845"
        ],
        "id": 2223372,
        "name:xx": "Carson Lake"
      }
    },
    {
      "geometry": {
        "type": "Point",
        "coordinates": [
          -99.15,
          42.0667
        ]
      },
      "type": "Feature",
      "properties": {
        "hierarchy": [
          "tgn:2223373",
          "tgn:1000001",
          "tgn:2001351",
          "tgn:7012149",
          "tgn:7007525",
          "tgn:7029392"
        ],
        "placetype": [
          "aat:300008680"
        ],
        "id": 2223373,
        "name:xx": "Carson Lake"
      }
    },
    {
      "geometry": {
        "type": "Point",
        "coordinates": [
          -97.5333,
          45.05
        ]
      },
      "type": "Feature",
      "properties": {
        "hierarchy": [
          "tgn:2223374",
          "tgn:1000001",
          "tgn:2001782",
          "tgn:7012149",
          "tgn:7007713",
          "tgn:7029392"
        ],
        "placetype": [
          "aat:300008680"
        ],
        "id": 2223374,
        "name:xx": "Carson Lake"
      }
    },
    {
      "geometry": {
        "type": "Point",
        "coordinates": [
          -95.65,
          30.9
        ]
      },
      "type": "Feature",
      "properties": {
        "hierarchy": [
          "tgn:2223375",
          "tgn:1000001",
          "tgn:7012149",
          "tgn:1002626",
          "tgn:7007826",
          "tgn:7029392"
        ],
        "placetype": [
          "aat:300008680"
        ],
        "id": 2223375,
        "name:xx": "Carson Lake"
      }
    },
    {
      "geometry": {
        "type": "Point",
        "coordinates": [
          -123.0333,
          47.3167
        ]
      },
      "type": "Feature",
      "properties": {
        "hierarchy": [
          "tgn:2223376",
          "tgn:1000001",
          "tgn:7012149",
          "tgn:1002645",
          "tgn:7007920",
          "tgn:7029392"
        ],
        "placetype": [
          "aat:300008680"
        ],
        "id": 2223376,
        "name:xx": "Carson Lake"
      }
    },
    {
      "geometry": {
        "type": "Point",
        "coordinates": [
          -109.6333,
          43.7333
        ]
      },
      "type": "Feature",
      "properties": {
        "hierarchy": [
          "tgn:2223377",
          "tgn:1000001",
          "tgn:7012149",
          "tgn:2002371",
          "tgn:7007923",
          "tgn:7029392"
        ],
        "placetype": [
          "aat:300008680"
        ],
        "id": 2223377,
        "name:xx": "Carson Lake"
      }
    },
    {
      "geometry": {
        "type": "Point",
        "coordinates": [
          -118.7667,
          39.35
        ]
      },
      "type": "Feature",
      "properties": {
        "hierarchy": [
          "tgn:2223378",
          "tgn:1000001",
          "tgn:2001409",
          "tgn:7012149",
          "tgn:7007526",
          "tgn:7029392"
        ],
        "placetype": [
          "aat:300006075"
        ],
        "id": 2223378,
        "name:xx": "Carson Lake 1 Drain"
      }
    },
    {
      "geometry": {
        "type": "Point",
        "coordinates": [
          -118.8,
          39.3667
        ]
      },
      "type": "Feature",
      "properties": {
        "hierarchy": [
          "tgn:2223379",
          "tgn:1000001",
          "tgn:2001409",
          "tgn:7012149",
          "tgn:7007526",
          "tgn:7029392"
        ],
        "placetype": [
          "aat:300006075"
        ],
        "id": 2223379,
        "name:xx": "Carson Lake A1 Extension Drain"
      }
    }
  ]
}
