{
  "geometry": {
    "type": "Point",
    "coordinates": [
      -81.65,
      35.3167
    ]
  },
  "type": "Feature",
  "properties": {
    "hierarchy": [
      "tgn:2075404",
      "tgn:1000001",
      "tgn:2001484",
      "tgn:7012149",
      "tgn:7007709",
      "tgn:7029392"
    ],
    "placetype": [
      "aat:300008347"
    ],
    "id": 2075404,
    "name:xx": "Lattimore"
  }
}
