{
  "geometry": {
    "type": "Point",
    "coordinates": [
      -90.0167,
      40.65
    ]
  },
  "type": "Feature",
  "properties": {
    "hierarchy": [
      "tgn:2462849",
      "tgn:1000001",
      "tgn:7012149",
      "tgn:7007251",
      "tgn:7029392"
    ],
    "placetype": [
      "aat:300008706"
    ],
    "id": 2462849,
    "name:xx": "Littlers Creek"
  }
}
