{
  "type": "FeatureCollection",
  "features": [
    {
      "geometry": {
        "type": "Point",
        "coordinates": [
          34.8167,
          30.6
        ]
      },
      "type": "Feature",
      "properties": {
        "hierarchy": [
          "tgn:1103340",
          "tgn:1000861",
          "tgn:1000004",
          "tgn:1000119",
          "tgn:7029392"
        ],
        "placetype": [
          "aat:300386860"
        ],
        "id": 1103340,
        "name:xx": "Ramon, Makhtesh"
      }
    },
    {
      "geometry": {
        "type": "Point",
        "coordinates": [
          30.166667,
          29.116667
        ]
      },
      "type": "Feature",
      "properties": {
        "hierarchy": [
          "tgn:1103341",
          "tgn:7001242",
          "tgn:7016833",
          "tgn:1001418",
          "tgn:7029392"
        ],
        "placetype": [
          "aat:300386860"
        ],
        "name:en": "Ruwayān, Wādī ar",
        "id": 1103341
      }
    },
    {
      "geometry": {
        "type": "Point",
        "coordinates": [
          89,
          42.75
        ]
      },
      "type": "Feature",
      "properties": {
        "hierarchy": [
          "tgn:1103342",
          "tgn:1000004",
          "tgn:7001745",
          "tgn:1000111",
          "tgn:7029392"
        ],
        "placetype": [
          "aat:300386845",
          "aat:300386860"
        ],
        "name:en": "Turfan Depression",
        "id": 1103342
      }
    },
    {
      "geometry": {
        "type": "Point",
        "coordinates": [
          62.0833,
          29.75
        ]
      },
      "type": "Feature",
      "properties": {
        "hierarchy": [
          "tgn:1103343",
          "tgn:7016612",
          "tgn:1000004",
          "tgn:1001440",
          "tgn:7029392"
        ],
        "placetype": [
          "aat:300386860"
        ],
        "id": 1103343,
        "name:xx": "Zereh, Gowd-e"
      }
    },
    {
      "geometry": {
        "type": "Point",
        "coordinates": [
          75,
          44.3333
        ]
      },
      "type": "Feature",
      "properties": {
        "hierarchy": [
          "tgn:1103344",
          "tgn:1000004",
          "tgn:7014786",
          "tgn:7029392"
        ],
        "placetype": [
          "aat:300008916"
        ],
        "id": 1103344,
        "name:xx": "Zhusandala, Step"
      }
    },
    {
      "geometry": {
        "type": "Point",
        "coordinates": [
          12,
          30
        ]
      },
      "type": "Feature",
      "properties": {
        "hierarchy": [
          "tgn:1103345",
          "tgn:7001242",
          "tgn:1000172",
          "tgn:7029392"
        ],
        "placetype": [
          "aat:300008916"
        ],
        "id": 1103345,
        "name:xx": "Ḥamrā', Al Ḥamādah al"
      }
    },
    {
      "geometry": {
        "type": "Point",
        "coordinates": [
          48.1667,
          24.5
        ]
      },
      "type": "Feature",
      "properties": {
        "hierarchy": [
          "tgn:1103347",
          "tgn:1000004",
          "tgn:1000137",
          "tgn:7029392"
        ],
        "placetype": [
          "aat:300008916"
        ],
        "id": 1103347,
        "name:xx": "Ad-Dahnā'"
      }
    },
    {
      "geometry": {
        "type": "Point",
        "coordinates": [
          8.674,
          24.505
        ]
      },
      "type": "Feature",
      "properties": {
        "hierarchy": [
          "tgn:1103348",
          "tgn:7001242",
          "tgn:7016752",
          "tgn:7593689",
          "tgn:7029392"
        ],
        "placetype": [
          "aat:300387015",
          "aat:300008916"
        ],
        "id": 1103348,
        "name:xx": "Admer, Erg d'"
      }
    }
  ]
}
