{
  "geometry": {
    "type": "Point",
    "coordinates": [
      -115.9667,
      39.4667
    ]
  },
  "type": "Feature",
  "properties": {
    "hierarchy": [
      "tgn:2301000",
      "tgn:1000001",
      "tgn:2001413",
      "tgn:7012149",
      "tgn:7007526",
      "tgn:7029392"
    ],
    "placetype": [
      "aat:300000390"
    ],
    "id": 2301000,
    "name:xx": "Dunderberg Mine"
  }
}
