{
  "geometry": {
    "type": "Point",
    "coordinates": [
      -116.0333,
      41.8333
    ]
  },
  "type": "Feature",
  "properties": {
    "hierarchy": [
      "tgn:2780375",
      "tgn:1000001",
      "tgn:2001411",
      "tgn:7012149",
      "tgn:7007526",
      "tgn:7029392"
    ],
    "placetype": [
      "aat:300008798"
    ],
    "id": 2780375,
    "name:xx": "Wonga Douya"
  }
}
