{
  "geometry": {
    "type": "Point",
    "coordinates": [
      -116.0833,
      44.9333
    ]
  },
  "type": "Feature",
  "properties": {
    "hierarchy": [
      "tgn:2747181",
      "tgn:1000001",
      "tgn:7012149",
      "tgn:2000494",
      "tgn:7007250",
      "tgn:7029392"
    ],
    "placetype": [
      "aat:300132316"
    ],
    "id": 2747181,
    "name:xx": "Wagon Wheel Bay"
  }
}
