{
  "type": "FeatureCollection",
  "features": [
    {
      "geometry": {
        "type": "Point",
        "coordinates": [
          -80.05,
          33.1333
        ]
      },
      "type": "Feature",
      "properties": {
        "hierarchy": [
          "tgn:2716250",
          "tgn:2001732",
          "tgn:1000001",
          "tgn:7012149",
          "tgn:7007712",
          "tgn:7029392"
        ],
        "placetype": [
          "aat:300008347"
        ],
        "id": 2716250,
        "name:xx": "The Barrows"
      }
    },
    {
      "geometry": {
        "type": "Point",
        "coordinates": [
          -134.9167,
          57.2667
        ]
      },
      "type": "Feature",
      "properties": {
        "hierarchy": [
          "tgn:2716251",
          "tgn:7006450",
          "tgn:1000001",
          "tgn:7012149",
          "tgn:2124002",
          "tgn:7029392"
        ],
        "placetype": [
          "aat:300386845"
        ],
        "id": 2716251,
        "name:xx": "The Basin"
      }
    },
    {
      "geometry": {
        "type": "Point",
        "coordinates": [
          -93.15,
          36.0833
        ]
      },
      "type": "Feature",
      "properties": {
        "hierarchy": [
          "tgn:2716252",
          "tgn:1000001",
          "tgn:7016172",
          "tgn:7012149",
          "tgn:2000155",
          "tgn:7029392"
        ],
        "placetype": [
          "aat:300008347"
        ],
        "id": 2716252,
        "name:xx": "The Basin"
      }
    },
    {
      "geometry": {
        "type": "Point",
        "coordinates": [
          -122.85,
          39.5833
        ]
      },
      "type": "Feature",
      "properties": {
        "hierarchy": [
          "tgn:2716253",
          "tgn:1000001",
          "tgn:7012149",
          "tgn:1002409",
          "tgn:7007157",
          "tgn:7029392"
        ],
        "placetype": [
          "aat:300386845"
        ],
        "id": 2716253,
        "name:xx": "The Basin"
      }
    },
    {
      "geometry": {
        "type": "Point",
        "coordinates": [
          -120.1333,
          38
        ]
      },
      "type": "Feature",
      "properties": {
        "hierarchy": [
          "tgn:2716254",
          "tgn:1000001",
          "tgn:7012149",
          "tgn:7007157",
          "tgn:1002957",
          "tgn:7029392"
        ],
        "placetype": [
          "aat:300386845"
        ],
        "id": 2716254,
        "name:xx": "The Basin"
      }
    },
    {
      "geometry": {
        "type": "Point",
        "coordinates": [
          -123.95,
          40.9833
        ]
      },
      "type": "Feature",
      "properties": {
        "hierarchy": [
          "tgn:2716255",
          "tgn:1000001",
          "tgn:7012149",
          "tgn:2000181",
          "tgn:7007157",
          "tgn:7029392"
        ],
        "placetype": [
          "aat:300008905"
        ],
        "id": 2716255,
        "name:xx": "The Basin"
      }
    },
    {
      "geometry": {
        "type": "Point",
        "coordinates": [
          -121.4,
          36.3167
        ]
      },
      "type": "Feature",
      "properties": {
        "hierarchy": [
          "tgn:2716256",
          "tgn:1000001",
          "tgn:7012149",
          "tgn:7007157",
          "tgn:1002684",
          "tgn:7029392"
        ],
        "placetype": [
          "aat:300386845"
        ],
        "id": 2716256,
        "name:xx": "The Basin"
      }
    },
    {
      "geometry": {
        "type": "Point",
        "coordinates": [
          -77.9333,
          33.95
        ]
      },
      "type": "Feature",
      "properties": {
        "hierarchy": [
          "tgn:2716257",
          "tgn:1000001",
          "tgn:7012149",
          "tgn:2001523",
          "tgn:7007709",
          "tgn:7029392"
        ],
        "placetype": [
          "aat:300132316"
        ],
        "id": 2716257,
        "name:xx": "The Basin"
      }
    },
    {
      "geometry": {
        "type": "Point",
        "coordinates": [
          -163.3667,
          65.4
        ]
      },
      "type": "Feature",
      "properties": {
        "hierarchy": [
          "tgn:2716258",
          "tgn:7006450",
          "tgn:1000001",
          "tgn:7012149",
          "tgn:2000079",
          "tgn:7029392"
        ],
        "placetype": [
          "aat:300008798"
        ],
        "id": 2716258,
        "name:xx": "The Bat"
      }
    },
    {
      "geometry": {
        "type": "Point",
        "coordinates": [
          -121.55,
          36.3167
        ]
      },
      "type": "Feature",
      "properties": {
        "hierarchy": [
          "tgn:2716259",
          "tgn:1000001",
          "tgn:7012149",
          "tgn:7007157",
          "tgn:1002684",
          "tgn:7029392"
        ],
        "placetype": [
          "aat:300266640"
        ],
        "id": 2716259,
        "name:xx": "The Bear Trap"
      }
    }
  ]
}
