{
  "geometry": {
    "type": "Point",
    "coordinates": [
      -113.4167,
      48.5333
    ]
  },
  "type": "Feature",
  "properties": {
    "hierarchy": [
      "tgn:2633444",
      "tgn:1000001",
      "tgn:7012149",
      "tgn:2001277",
      "tgn:7007524",
      "tgn:7029392"
    ],
    "placetype": [
      "aat:300008680"
    ],
    "id": 2633444,
    "name:xx": "Running Crane Lake"
  }
}
