{
  "geometry": {
    "type": "Point",
    "coordinates": [
      -104.5833,
      35.4833
    ]
  },
  "type": "Feature",
  "properties": {
    "hierarchy": [
      "tgn:2405151",
      "tgn:1000001",
      "tgn:7012149",
      "tgn:2001453",
      "tgn:7007566",
      "tgn:7029392"
    ],
    "placetype": [
      "aat:300008798"
    ],
    "id": 2405151,
    "name:xx": "Huerfana, Mesa"
  }
}
