{
  "geometry": {
    "type": "Point",
    "coordinates": [
      -82.25,
      35.1833
    ]
  },
  "type": "Feature",
  "properties": {
    "hierarchy": [
      "tgn:2300158",
      "tgn:1000001",
      "tgn:7012149",
      "tgn:7029392"
    ],
    "placetype": [
      "aat:300266640"
    ],
    "id": 2300158,
    "name:xx": "Dughill Ridge"
  }
}
