{
  "geometry": {
    "type": "Point",
    "coordinates": [
      -107.6833,
      43.85
    ]
  },
  "type": "Feature",
  "properties": {
    "hierarchy": [
      "tgn:2737200",
      "tgn:1000001",
      "tgn:7012149",
      "tgn:2002386",
      "tgn:7007923",
      "tgn:7029392"
    ],
    "placetype": [
      "aat:300006191"
    ],
    "id": 2737200,
    "name:xx": "Two Wash Reservoir"
  }
}
