{
  "geometry": {
    "type": "Point",
    "coordinates": [
      -89.2167,
      45.4667
    ]
  },
  "type": "Feature",
  "properties": {
    "hierarchy": [
      "tgn:2303660",
      "tgn:1000001",
      "tgn:7012149",
      "tgn:2002342",
      "tgn:7007922",
      "tgn:7029392"
    ],
    "placetype": [
      "aat:300008680"
    ],
    "id": 2303660,
    "name:xx": "Eagle Lake"
  }
}
