{
  "geometry": {
    "type": "Point",
    "coordinates": [
      144.8333,
      13.4667
    ]
  },
  "type": "Feature",
  "properties": {
    "hierarchy": [
      "tgn:7000550",
      "tgn:1000006",
      "tgn:7029392"
    ],
    "placetype": [
      "aat:300387054",
      "aat:300387176",
      "aat:300387118"
    ],
    "name:en": "Guam",
    "id": 7000550
  }
}
