{
  "geometry": {
    "type": "Point",
    "coordinates": [
      -108.7833,
      35.15
    ]
  },
  "type": "Feature",
  "properties": {
    "hierarchy": [
      "tgn:2765537",
      "tgn:1000001",
      "tgn:7012149",
      "tgn:7019676",
      "tgn:7007566",
      "tgn:7029392"
    ],
    "placetype": [
      "aat:300008761"
    ],
    "id": 2765537,
    "name:xx": "White Canyon"
  }
}
