{
  "geometry": {
    "type": "Point",
    "coordinates": [
      -112.75,
      45.0167
    ]
  },
  "type": "Feature",
  "properties": {
    "hierarchy": [
      "tgn:2385837",
      "tgn:1000001",
      "tgn:2001260",
      "tgn:7012149",
      "tgn:7007524",
      "tgn:7029392"
    ],
    "placetype": [
      "aat:300008761"
    ],
    "id": 2385837,
    "name:xx": "Henneberry Gulch"
  }
}
