{
  "geometry": {
    "type": "Point",
    "coordinates": [
      -111.9167,
      33.6333
    ]
  },
  "type": "Feature",
  "properties": {
    "hierarchy": [
      "tgn:2260251",
      "tgn:1000001",
      "tgn:7006451",
      "tgn:7012149",
      "tgn:2000097",
      "tgn:7029392"
    ],
    "placetype": [
      "aat:300008347"
    ],
    "id": 2260251,
    "name:xx": "Country Trace"
  }
}
