{
  "geometry": {
    "type": "Point",
    "coordinates": [
      -123.55,
      39.9667
    ]
  },
  "type": "Feature",
  "properties": {
    "hierarchy": [
      "tgn:2231958",
      "tgn:1000001",
      "tgn:7012149",
      "tgn:7007157",
      "tgn:7029392"
    ],
    "placetype": [
      "aat:300008706"
    ],
    "id": 2231958,
    "name:xx": "Chamise Creek"
  }
}
