{
  "geometry": {
    "type": "Point",
    "coordinates": [
      -81.5667,
      37.1667
    ]
  },
  "type": "Feature",
  "properties": {
    "hierarchy": [
      "tgn:2424371",
      "tgn:1000001",
      "tgn:7012149",
      "tgn:2002192",
      "tgn:7007919",
      "tgn:7029392"
    ],
    "placetype": [
      "aat:300008699"
    ],
    "id": 2424371,
    "name:xx": "Johnson Branch"
  }
}
