{
  "geometry": {
    "type": "Point",
    "coordinates": [
      31.088611,
      31.570833
    ]
  },
  "type": "Feature",
  "properties": {
    "hierarchy": [
      "tgn:7520657",
      "tgn:7001242",
      "tgn:7016833",
      "tgn:1001335",
      "tgn:7029392"
    ],
    "placetype": [
      "aat:300266556"
    ],
    "name:en": "Abū adh Dhahab, Mallāḩat",
    "id": 7520657
  }
}
