{
  "geometry": {
    "type": "Point",
    "coordinates": [
      -85.4167,
      42.4833
    ]
  },
  "type": "Feature",
  "properties": {
    "hierarchy": [
      "tgn:2697474",
      "tgn:1002166",
      "tgn:1000001",
      "tgn:7012149",
      "tgn:7007520",
      "tgn:7029392"
    ],
    "placetype": [
      "aat:300008347"
    ],
    "id": 2697474,
    "name:xx": "Stony Point"
  }
}
