{
  "geometry": {
    "type": "Point",
    "coordinates": [
      -114.4333,
      43.0833
    ]
  },
  "type": "Feature",
  "properties": {
    "hierarchy": [
      "tgn:2651701",
      "tgn:1000001",
      "tgn:7012149",
      "tgn:2000483",
      "tgn:7007250",
      "tgn:7029392"
    ],
    "placetype": [
      "aat:300008680"
    ],
    "id": 2651701,
    "name:xx": "Seep Reservoir"
  }
}
