{
  "geometry": {
    "type": "Point",
    "coordinates": [
      -99.4333,
      30.05
    ]
  },
  "type": "Feature",
  "properties": {
    "hierarchy": [
      "tgn:2473279",
      "tgn:1000001",
      "tgn:7012149",
      "tgn:2002018",
      "tgn:7007826",
      "tgn:7029392"
    ],
    "placetype": [
      "aat:300008697"
    ],
    "id": 2473279,
    "name:xx": "Lower Bee Caves Spring"
  }
}
