{
  "geometry": {
    "type": "Point",
    "coordinates": [
      -99.2667,
      26.9333
    ]
  },
  "type": "Feature",
  "properties": {
    "hierarchy": [
      "tgn:2640259",
      "tgn:1000001",
      "tgn:7012149",
      "tgn:2002099",
      "tgn:7007826",
      "tgn:7029392"
    ],
    "placetype": [
      "aat:300008761"
    ],
    "id": 2640259,
    "name:xx": "San Bartolo, Arroyo"
  }
}
