{
  "type": "FeatureCollection",
  "features": [
    {
      "geometry": {
        "type": "Point",
        "coordinates": [
          124.6667,
          39.55
        ]
      },
      "type": "Feature",
      "properties": {
        "hierarchy": [
          "tgn:1007591",
          "tgn:1000004",
          "tgn:1001478",
          "tgn:1000122",
          "tgn:7029392"
        ],
        "placetype": [
          "aat:300008791"
        ],
        "id": 1007591,
        "name:xx": "Ka-do"
      }
    },
    {
      "geometry": {
        "type": "Point",
        "coordinates": [
          -176.3667,
          51.7333
        ]
      },
      "type": "Feature",
      "properties": {
        "hierarchy": [
          "tgn:1007596",
          "tgn:7019594",
          "tgn:7030516",
          "tgn:7019773",
          "tgn:7006450",
          "tgn:1000001",
          "tgn:7012149",
          "tgn:7029392"
        ],
        "placetype": [
          "aat:300008791"
        ],
        "id": 1007596,
        "name:xx": "Kagalaska Island"
      }
    },
    {
      "geometry": {
        "type": "Point",
        "coordinates": [
          -169.7,
          52.9833
        ]
      },
      "type": "Feature",
      "properties": {
        "hierarchy": [
          "tgn:1007597",
          "tgn:7030516",
          "tgn:7006450",
          "tgn:1000001",
          "tgn:7012149",
          "tgn:7019601",
          "tgn:7029392"
        ],
        "placetype": [
          "aat:300008791"
        ],
        "id": 1007597,
        "name:xx": "Kagamil Island"
      }
    },
    {
      "geometry": {
        "type": "Point",
        "coordinates": [
          -156.6,
          20.55
        ]
      },
      "type": "Feature",
      "properties": {
        "hierarchy": [
          "tgn:1007598",
          "tgn:1002648",
          "tgn:1000001",
          "tgn:7012149",
          "tgn:7007249",
          "tgn:7029392"
        ],
        "placetype": [
          "aat:300008791"
        ],
        "id": 1007598,
        "name:xx": "Kahoolawe"
      }
    },
    {
      "geometry": {
        "type": "Point",
        "coordinates": [
          -61.7833,
          16.3667
        ]
      },
      "type": "Feature",
      "properties": {
        "hierarchy": [
          "tgn:1007599",
          "tgn:7018312",
          "tgn:1000001",
          "tgn:7004545",
          "tgn:7029392"
        ],
        "placetype": [
          "aat:300386852"
        ],
        "id": 1007599,
        "name:xx": "Kahouanne, Îlet à"
      }
    }
  ]
}
