{
  "geometry": {
    "type": "Point",
    "coordinates": [
      -121.8167,
      46.2667
    ]
  },
  "type": "Feature",
  "properties": {
    "hierarchy": [
      "tgn:2379909",
      "tgn:1000001",
      "tgn:7012149",
      "tgn:1002897",
      "tgn:7007920",
      "tgn:7029392"
    ],
    "placetype": [
      "aat:300008798"
    ],
    "id": 2379909,
    "name:xx": "Hat Rock"
  }
}
