{
  "geometry": {
    "type": "Point",
    "coordinates": [
      -61.75,
      16.0667
    ]
  },
  "type": "Feature",
  "properties": {
    "hierarchy": [
      "tgn:1016622",
      "tgn:7018312",
      "tgn:1006440",
      "tgn:1000001",
      "tgn:7004545",
      "tgn:7029392"
    ],
    "placetype": [
      "aat:300008347"
    ],
    "id": 1016622,
    "name:xx": "Vieux Habitants"
  }
}
