{
  "geometry": {
    "type": "Point",
    "coordinates": [
      -110.2167,
      34.3333
    ]
  },
  "type": "Feature",
  "properties": {
    "hierarchy": [
      "tgn:2563201",
      "tgn:1000001",
      "tgn:7006451",
      "tgn:7012149",
      "tgn:2000099",
      "tgn:7029392"
    ],
    "placetype": [
      "aat:300006191"
    ],
    "id": 2563201,
    "name:xx": "Owens Tank"
  }
}
