{
  "geometry": {
    "type": "Point",
    "coordinates": [
      -114.95,
      39.2333
    ]
  },
  "type": "Feature",
  "properties": {
    "hierarchy": [
      "tgn:2161451",
      "tgn:1000001",
      "tgn:7012149",
      "tgn:2001420",
      "tgn:7007526",
      "tgn:7029392"
    ],
    "placetype": [
      "aat:300000390"
    ],
    "id": 2161451,
    "name:xx": "Bell Shaft"
  }
}
