{
  "geometry": {
    "type": "Point",
    "coordinates": [
      -79.35,
      34.15
    ]
  },
  "type": "Feature",
  "properties": {
    "hierarchy": [
      "tgn:2507989",
      "tgn:1000001",
      "tgn:7012149",
      "tgn:2001758",
      "tgn:7007712",
      "tgn:7029392"
    ],
    "placetype": [
      "aat:300008905"
    ],
    "id": 2507989,
    "name:xx": "Middle Bay"
  }
}
