{
  "geometry": {
    "type": "Point",
    "coordinates": [
      -75.55,
      40.9167
    ]
  },
  "type": "Feature",
  "properties": {
    "hierarchy": [
      "tgn:2574995",
      "tgn:1000001",
      "tgn:7012149",
      "tgn:7007710",
      "tgn:7029392"
    ],
    "placetype": [
      "aat:300006191"
    ],
    "id": 2574995,
    "name:xx": "Penn Forest Reservoir"
  }
}
