{
  "geometry": {
    "type": "Point",
    "coordinates": [
      -116.5333,
      47.9667
    ]
  },
  "type": "Feature",
  "properties": {
    "hierarchy": [
      "tgn:2178906",
      "tgn:1000001",
      "tgn:7012149",
      "tgn:2000479",
      "tgn:7007250",
      "tgn:7029392"
    ],
    "placetype": [
      "aat:300008850"
    ],
    "id": 2178906,
    "name:xx": "Blackwell Point"
  }
}
