{
  "geometry": {
    "type": "Point",
    "coordinates": [
      -104.3333,
      30.6667
    ]
  },
  "type": "Feature",
  "properties": {
    "hierarchy": [
      "tgn:2312780",
      "tgn:1000001",
      "tgn:7012149",
      "tgn:2002010",
      "tgn:7007826",
      "tgn:7029392"
    ],
    "placetype": [
      "aat:300008697"
    ],
    "id": 2312780,
    "name:xx": "El Muerto Spring"
  }
}
