{
  "geometry": {
    "type": "Point",
    "coordinates": [
      -107.1667,
      40.5667
    ]
  },
  "type": "Feature",
  "properties": {
    "hierarchy": [
      "tgn:2496248",
      "tgn:1000001",
      "tgn:7012149",
      "tgn:7007158",
      "tgn:2000245",
      "tgn:7029392"
    ],
    "placetype": [
      "aat:300008761"
    ],
    "id": 2496248,
    "name:xx": "Mat Gulch"
  }
}
