{
  "geometry": {
    "type": "Point",
    "coordinates": [
      6.7833,
      48.7167
    ]
  },
  "type": "Feature",
  "properties": {
    "hierarchy": [
      "tgn:1034209",
      "tgn:1000003",
      "tgn:7002888",
      "tgn:1000070",
      "tgn:7029392"
    ],
    "placetype": [
      "aat:300008347"
    ],
    "id": 1034209,
    "name:xx": "Maizières-lès-Vic"
  }
}
