{
  "geometry": {
    "type": "Point",
    "coordinates": [
      -115.7667,
      47.0167
    ]
  },
  "type": "Feature",
  "properties": {
    "hierarchy": [
      "tgn:7023591",
      "tgn:1000001",
      "tgn:7012149",
      "tgn:2000491",
      "tgn:7007250",
      "tgn:7029392"
    ],
    "placetype": [
      "aat:300008680"
    ],
    "id": 7023591,
    "name:xx": "Noseeum Lake"
  }
}
