{
  "geometry": {
    "type": "Point",
    "coordinates": [
      -146.2167,
      61.0167
    ]
  },
  "type": "Feature",
  "properties": {
    "hierarchy": [
      "tgn:2124773",
      "tgn:7006450",
      "tgn:1000001",
      "tgn:7012149",
      "tgn:2000086",
      "tgn:7029392"
    ],
    "placetype": [
      "aat:300008761"
    ],
    "id": 2124773,
    "name:xx": "Abercrombie Gulch"
  }
}
