{
  "geometry": {
    "type": "Point",
    "coordinates": [
      -98.0333,
      54.55
    ]
  },
  "type": "Feature",
  "properties": {
    "hierarchy": [
      "tgn:1101144",
      "tgn:7005685",
      "tgn:1000001",
      "tgn:7005734",
      "tgn:7029392"
    ],
    "placetype": [
      "aat:300006084"
    ],
    "id": 1101144,
    "name:xx": "Jenpeg Dam"
  }
}
