{
  "geometry": {
    "type": "Point",
    "coordinates": [
      -82.6333,
      41.3667
    ]
  },
  "type": "Feature",
  "properties": {
    "hierarchy": [
      "tgn:2647271",
      "tgn:1000001",
      "tgn:7012149",
      "tgn:1002357",
      "tgn:7007706",
      "tgn:7029392"
    ],
    "placetype": [
      "aat:300006075"
    ],
    "id": 2647271,
    "name:xx": "Schlessman Ditch"
  }
}
