{
  "geometry": {
    "type": "Point",
    "coordinates": [
      -79.2833,
      33.4333
    ]
  },
  "type": "Feature",
  "properties": {
    "hierarchy": [
      "tgn:2336592",
      "tgn:1000001",
      "tgn:2001746",
      "tgn:7012149",
      "tgn:7007712",
      "tgn:7029392"
    ],
    "placetype": [
      "aat:300008706"
    ],
    "id": 2336592,
    "name:xx": "Four Mile Creek"
  }
}
