{
  "geometry": {
    "type": "Point",
    "coordinates": [
      -117.1167,
      48.75
    ]
  },
  "type": "Feature",
  "properties": {
    "hierarchy": [
      "tgn:2547818",
      "tgn:1000001",
      "tgn:7012149",
      "tgn:2002248",
      "tgn:7007920",
      "tgn:7029392"
    ],
    "placetype": [
      "aat:300008706"
    ],
    "id": 2547818,
    "name:xx": "North Fork Willow Creek"
  }
}
