{
  "geometry": {
    "type": "Point",
    "coordinates": [
      -91.6167,
      40.1167
    ]
  },
  "type": "Feature",
  "properties": {
    "hierarchy": [
      "tgn:2058252",
      "tgn:1000001",
      "tgn:7012149",
      "tgn:1002592",
      "tgn:7007523",
      "tgn:7029392"
    ],
    "placetype": [
      "aat:300008347"
    ],
    "id": 2058252,
    "name:xx": "Canton"
  }
}
