{
  "geometry": {
    "type": "Point",
    "coordinates": [
      -111.3833,
      40.7167
    ]
  },
  "type": "Feature",
  "properties": {
    "hierarchy": [
      "tgn:2394568",
      "tgn:1000001",
      "tgn:7012149",
      "tgn:2002122",
      "tgn:7007827",
      "tgn:7029392"
    ],
    "placetype": [
      "aat:300266640"
    ],
    "id": 2394568,
    "name:xx": "Hogs Back"
  }
}
