{
  "geometry": {
    "type": "Point",
    "coordinates": [
      14.6167,
      -0.55
    ]
  },
  "type": "Feature",
  "properties": {
    "hierarchy": [
      "tgn:1088716",
      "tgn:7001242",
      "tgn:1000972",
      "tgn:1000158",
      "tgn:7029392"
    ],
    "placetype": [
      "aat:300008347"
    ],
    "id": 1088716,
    "name:xx": "Mbeyi-Mbola"
  }
}
