{
  "type": "FeatureCollection",
  "features": [
    {
      "geometry": {
        "type": "Point",
        "coordinates": [
          24.533333,
          35.366667
        ]
      },
      "type": "Feature",
      "properties": {
        "hierarchy": [
          "tgn:7223250",
          "tgn:7002690",
          "tgn:7012056",
          "tgn:1000003",
          "tgn:1000074",
          "tgn:7029392"
        ],
        "placetype": [
          "aat:300008699"
        ],
        "id": 7223250,
        "name:xx": "SFakoríako"
      }
    },
    {
      "geometry": {
        "type": "Point",
        "coordinates": [
          24.766667,
          35.033333
        ]
      },
      "type": "Feature",
      "properties": {
        "hierarchy": [
          "tgn:7223251",
          "tgn:7002690",
          "tgn:7012056",
          "tgn:1000003",
          "tgn:1000074",
          "tgn:7029392"
        ],
        "placetype": [
          "aat:300008699"
        ],
        "id": 7223251,
        "name:xx": "SFakoríako"
      }
    },
    {
      "geometry": {
        "type": "Point",
        "coordinates": [
          23.716667,
          35.466667
        ]
      },
      "type": "Feature",
      "properties": {
        "hierarchy": [
          "tgn:7223252",
          "tgn:7002690",
          "tgn:7012056",
          "tgn:1000003",
          "tgn:1000074",
          "tgn:7029392"
        ],
        "placetype": [
          "aat:300008347"
        ],
        "id": 7223252,
        "name:xx": "SFakopigádhion"
      }
    },
    {
      "geometry": {
        "type": "Point",
        "coordinates": [
          24.166667,
          35.2
        ]
      },
      "type": "Feature",
      "properties": {
        "hierarchy": [
          "tgn:7223253",
          "tgn:7002690",
          "tgn:7012056",
          "tgn:1000003",
          "tgn:1000074",
          "tgn:7029392"
        ],
        "placetype": [
          "aat:300008767"
        ],
        "id": 7223253,
        "name:xx": "SFakianó Farángi"
      }
    },
    {
      "geometry": {
        "type": "Point",
        "coordinates": [
          23.983333,
          35.5
        ]
      },
      "type": "Feature",
      "properties": {
        "hierarchy": [
          "tgn:7223254",
          "tgn:7002690",
          "tgn:7012056",
          "tgn:1000003",
          "tgn:1000074",
          "tgn:7029392"
        ],
        "placetype": [
          "aat:300008347"
        ],
        "id": 7223254,
        "name:xx": "SFakianalíon"
      }
    },
    {
      "geometry": {
        "type": "Point",
        "coordinates": [
          23.6,
          35.3
        ]
      },
      "type": "Feature",
      "properties": {
        "hierarchy": [
          "tgn:7223255",
          "tgn:7002690",
          "tgn:7012056",
          "tgn:1000003",
          "tgn:1000074",
          "tgn:7029392"
        ],
        "placetype": [
          "aat:300008347"
        ],
        "id": 7223255,
        "name:xx": "Sfakiá"
      }
    },
    {
      "geometry": {
        "type": "Point",
        "coordinates": [
          26.1,
          35.133333
        ]
      },
      "type": "Feature",
      "properties": {
        "hierarchy": [
          "tgn:7223256",
          "tgn:7002692",
          "tgn:7012056",
          "tgn:1000003",
          "tgn:1000074",
          "tgn:7029392"
        ],
        "placetype": [
          "aat:300008347"
        ],
        "id": 7223256,
        "name:xx": "Sfakía"
      }
    },
    {
      "geometry": {
        "type": "Point",
        "coordinates": [
          19.785833,
          39.774722
        ]
      },
      "type": "Feature",
      "properties": {
        "hierarchy": [
          "tgn:7223257",
          "tgn:7002711",
          "tgn:7001338",
          "tgn:1000003",
          "tgn:1000074",
          "tgn:7029392"
        ],
        "placetype": [
          "aat:300008347"
        ],
        "id": 7223257,
        "name:xx": "Sfakerá"
      }
    },
    {
      "geometry": {
        "type": "Point",
        "coordinates": [
          24.283333,
          35.3
        ]
      },
      "type": "Feature",
      "properties": {
        "hierarchy": [
          "tgn:7223258",
          "tgn:7002690",
          "tgn:7012056",
          "tgn:1000003",
          "tgn:1000074",
          "tgn:7029392"
        ],
        "placetype": [
          "aat:300008699"
        ],
        "id": 7223258,
        "name:xx": "Sfáka Réma"
      }
    },
    {
      "geometry": {
        "type": "Point",
        "coordinates": [
          22.85,
          38.6
        ]
      },
      "type": "Feature",
      "properties": {
        "hierarchy": [
          "tgn:7223259",
          "tgn:7002741",
          "tgn:7017076",
          "tgn:1000003",
          "tgn:1000074",
          "tgn:7029392"
        ],
        "placetype": [
          "aat:300008347"
        ],
        "id": 7223259,
        "name:xx": "Sfáka"
      }
    }
  ]
}
