{
  "geometry": {
    "type": "Point",
    "coordinates": [
      -7.966,
      53.217
    ]
  },
  "type": "Feature",
  "properties": {
    "hierarchy": [
      "tgn:1122246",
      "tgn:7001199",
      "tgn:7003492",
      "tgn:1000003",
      "tgn:1000078",
      "tgn:7029392"
    ],
    "placetype": [
      "aat:300008707"
    ],
    "id": 1122246,
    "name:xx": "Brosna, River"
  }
}
