{
  "type": "FeatureCollection",
  "features": [
    {
      "geometry": {
        "type": "Point",
        "coordinates": [
          92.9167,
          20.1667
        ]
      },
      "type": "Feature",
      "properties": {
        "hierarchy": [
          "tgn:1125340",
          "tgn:1000004",
          "tgn:7029392"
        ],
        "placetype": [
          "aat:300008707"
        ],
        "id": 1125340,
        "name:xx": "Kaladan"
      }
    },
    {
      "geometry": {
        "type": "Point",
        "coordinates": [
          23.916667,
          64.283333
        ]
      },
      "type": "Feature",
      "properties": {
        "hierarchy": [
          "tgn:1125342",
          "tgn:1001475",
          "tgn:1000003",
          "tgn:1000069",
          "tgn:7029392"
        ],
        "placetype": [
          "aat:300008707"
        ],
        "id": 1125342,
        "name:xx": "Kalajoki"
      }
    },
    {
      "geometry": {
        "type": "Point",
        "coordinates": [
          79.75,
          37
        ]
      },
      "type": "Feature",
      "properties": {
        "hierarchy": [
          "tgn:1125344",
          "tgn:1000004",
          "tgn:7029392"
        ],
        "placetype": [
          "aat:300008707"
        ],
        "id": 1125344,
        "name:xx": "Kalakashihe"
      }
    },
    {
      "geometry": {
        "type": "Point",
        "coordinates": [
          -122.25,
          46.1333
        ]
      },
      "type": "Feature",
      "properties": {
        "hierarchy": [
          "tgn:1125345",
          "tgn:1000001",
          "tgn:1002305",
          "tgn:7012149",
          "tgn:7007920",
          "tgn:7029392"
        ],
        "placetype": [
          "aat:300008707"
        ],
        "id": 1125345,
        "name:xx": "Kalama"
      }
    },
    {
      "geometry": {
        "type": "Point",
        "coordinates": [
          -84.7333,
          42.2333
        ]
      },
      "type": "Feature",
      "properties": {
        "hierarchy": [
          "tgn:1125346",
          "tgn:1000001",
          "tgn:7012149",
          "tgn:7007520",
          "tgn:7029392"
        ],
        "placetype": [
          "aat:300008707"
        ],
        "id": 1125346,
        "name:xx": "Kalamazoo"
      }
    },
    {
      "geometry": {
        "type": "Point",
        "coordinates": [
          103.8667,
          1.3
        ]
      },
      "type": "Feature",
      "properties": {
        "hierarchy": [
          "tgn:1125349",
          "tgn:1000004",
          "tgn:1000138",
          "tgn:7000381",
          "tgn:7029392"
        ],
        "placetype": [
          "aat:300008707"
        ],
        "id": 1125349,
        "name:xx": "Kalang"
      }
    }
  ]
}
