{
  "geometry": {
    "type": "Point",
    "coordinates": [
      -89.9833,
      14.65
    ]
  },
  "type": "Feature",
  "properties": {
    "hierarchy": [
      "tgn:1016666",
      "tgn:1000651",
      "tgn:1000001",
      "tgn:7005493",
      "tgn:7029392"
    ],
    "placetype": [
      "aat:300008347",
      "aat:300387225",
      "aat:300008389",
      "aat:300387512"
    ],
    "id": 1016666,
    "name:xx": "Jalapa"
  }
}
