{
  "geometry": {
    "type": "Point",
    "coordinates": [
      -111.75,
      34.7833
    ]
  },
  "type": "Feature",
  "properties": {
    "hierarchy": [
      "tgn:2161441",
      "tgn:1000001",
      "tgn:7006451",
      "tgn:7012149",
      "tgn:2000103",
      "tgn:7029392"
    ],
    "placetype": [
      "aat:300008697"
    ],
    "id": 2161441,
    "name:xx": "Bell Rock Spring"
  }
}
