{
  "type": "FeatureCollection",
  "features": [
    {
      "geometry": {
        "type": "Point",
        "coordinates": [
          8.366667,
          50.266667
        ]
      },
      "type": "Feature",
      "properties": {
        "hierarchy": [
          "tgn:7107530",
          "tgn:1000003",
          "tgn:7003678",
          "tgn:7000084",
          "tgn:7029392"
        ],
        "placetype": [
          "aat:300008347"
        ],
        "id": 7107530,
        "name:xx": "Reichenbach"
      }
    },
    {
      "geometry": {
        "type": "Point",
        "coordinates": [
          11.5,
          50.25
        ]
      },
      "type": "Feature",
      "properties": {
        "hierarchy": [
          "tgn:7107531",
          "tgn:7003669",
          "tgn:1000003",
          "tgn:7000084",
          "tgn:7029392"
        ],
        "placetype": [
          "aat:300008347"
        ],
        "id": 7107531,
        "name:xx": "Reichenbach"
      }
    },
    {
      "geometry": {
        "type": "Point",
        "coordinates": [
          12.116667,
          50.216667
        ]
      },
      "type": "Feature",
      "properties": {
        "hierarchy": [
          "tgn:7107532",
          "tgn:7003669",
          "tgn:1000003",
          "tgn:7000084",
          "tgn:7029392"
        ],
        "placetype": [
          "aat:300008347"
        ],
        "id": 7107532,
        "name:xx": "Reichenbach"
      }
    },
    {
      "geometry": {
        "type": "Point",
        "coordinates": [
          9.15,
          50.05
        ]
      },
      "type": "Feature",
      "properties": {
        "hierarchy": [
          "tgn:7107533",
          "tgn:7003669",
          "tgn:1000003",
          "tgn:7000084",
          "tgn:7029392"
        ],
        "placetype": [
          "aat:300008347"
        ],
        "id": 7107533,
        "name:xx": "Reichenbach"
      }
    },
    {
      "geometry": {
        "type": "Point",
        "coordinates": [
          11.95,
          49.983333
        ]
      },
      "type": "Feature",
      "properties": {
        "hierarchy": [
          "tgn:7107534",
          "tgn:7003669",
          "tgn:1000003",
          "tgn:7000084",
          "tgn:7029392"
        ],
        "placetype": [
          "aat:300008347"
        ],
        "id": 7107534,
        "name:xx": "Reichenbach"
      }
    },
    {
      "geometry": {
        "type": "Point",
        "coordinates": [
          11.633333,
          49.716667
        ]
      },
      "type": "Feature",
      "properties": {
        "hierarchy": [
          "tgn:7107535",
          "tgn:7003669",
          "tgn:1000003",
          "tgn:7000084",
          "tgn:7029392"
        ],
        "placetype": [
          "aat:300008347"
        ],
        "id": 7107535,
        "name:xx": "Reichenbach"
      }
    },
    {
      "geometry": {
        "type": "Point",
        "coordinates": [
          8.693333,
          49.711944
        ]
      },
      "type": "Feature",
      "properties": {
        "hierarchy": [
          "tgn:7107536",
          "tgn:1000003",
          "tgn:7003678",
          "tgn:7000084",
          "tgn:7029392"
        ],
        "placetype": [
          "aat:300008347"
        ],
        "id": 7107536,
        "name:xx": "Reichenbach"
      }
    },
    {
      "geometry": {
        "type": "Point",
        "coordinates": [
          7.283333,
          49.65
        ]
      },
      "type": "Feature",
      "properties": {
        "hierarchy": [
          "tgn:7107537",
          "tgn:1000003",
          "tgn:7003682",
          "tgn:7000084",
          "tgn:7029392"
        ],
        "placetype": [
          "aat:300008347"
        ],
        "id": 7107537,
        "name:xx": "Reichenbach"
      }
    },
    {
      "geometry": {
        "type": "Point",
        "coordinates": [
          7.533333,
          49.5
        ]
      },
      "type": "Feature",
      "properties": {
        "hierarchy": [
          "tgn:7107538",
          "tgn:1000003",
          "tgn:7003682",
          "tgn:7000084",
          "tgn:7029392"
        ],
        "placetype": [
          "aat:300000745"
        ],
        "id": 7107538,
        "name:xx": "Reichenbach"
      }
    },
    {
      "geometry": {
        "type": "Point",
        "coordinates": [
          10.15,
          49.283333
        ]
      },
      "type": "Feature",
      "properties": {
        "hierarchy": [
          "tgn:7107539",
          "tgn:7003669",
          "tgn:1000003",
          "tgn:7000084",
          "tgn:7029392"
        ],
        "placetype": [
          "aat:300008347"
        ],
        "id": 7107539,
        "name:xx": "Reichenbach"
      }
    }
  ]
}
