{
  "geometry": {
    "type": "Point",
    "coordinates": [
      -77.3167,
      40.7833
    ]
  },
  "type": "Feature",
  "properties": {
    "hierarchy": [
      "tgn:2539379",
      "tgn:1000001",
      "tgn:7012149",
      "tgn:7007710",
      "tgn:7029392"
    ],
    "placetype": [
      "aat:300008761"
    ],
    "id": 2539379,
    "name:xx": "New Lancaster Valley"
  }
}
