{
  "type": "FeatureCollection",
  "features": [
    {
      "geometry": {
        "type": "Point",
        "coordinates": [
          -93.55,
          36.3
        ]
      },
      "type": "Feature",
      "properties": {
        "hierarchy": [
          "tgn:2323250",
          "tgn:1000001",
          "tgn:7016172",
          "tgn:2000112",
          "tgn:7012149",
          "tgn:7029392"
        ],
        "placetype": [
          "aat:300008761"
        ],
        "id": 2323250,
        "name:xx": "Farmer Hollow"
      }
    },
    {
      "geometry": {
        "type": "Point",
        "coordinates": [
          -87.85,
          35.3667
        ]
      },
      "type": "Feature",
      "properties": {
        "hierarchy": [
          "tgn:2323251",
          "tgn:1000001",
          "tgn:7012149",
          "tgn:2001927",
          "tgn:7007825",
          "tgn:7029392"
        ],
        "placetype": [
          "aat:300008761"
        ],
        "id": 2323251,
        "name:xx": "Farmer Hollow"
      }
    },
    {
      "geometry": {
        "type": "Point",
        "coordinates": [
          -84.2,
          36.0667
        ]
      },
      "type": "Feature",
      "properties": {
        "hierarchy": [
          "tgn:2323252",
          "tgn:2001837",
          "tgn:1000001",
          "tgn:7012149",
          "tgn:7007825",
          "tgn:7029392"
        ],
        "placetype": [
          "aat:300008761"
        ],
        "id": 2323252,
        "name:xx": "Farmer Hollow"
      }
    },
    {
      "geometry": {
        "type": "Point",
        "coordinates": [
          -87.95,
          37.15
        ]
      },
      "type": "Feature",
      "properties": {
        "hierarchy": [
          "tgn:2323253",
          "tgn:1000001",
          "tgn:2000776",
          "tgn:7012149",
          "tgn:7007255",
          "tgn:7029392"
        ],
        "placetype": [
          "aat:300008798"
        ],
        "id": 2323253,
        "name:xx": "Farmer Knob"
      }
    },
    {
      "geometry": {
        "type": "Point",
        "coordinates": [
          -82.25,
          32.85
        ]
      },
      "type": "Feature",
      "properties": {
        "hierarchy": [
          "tgn:2323254",
          "tgn:1000001",
          "tgn:2000308",
          "tgn:7012149",
          "tgn:7007248",
          "tgn:7029392"
        ],
        "placetype": [
          "aat:300006191"
        ],
        "id": 2323254,
        "name:xx": "Farmer Lake"
      }
    },
    {
      "geometry": {
        "type": "Point",
        "coordinates": [
          -87.4167,
          39.5667
        ]
      },
      "type": "Feature",
      "properties": {
        "hierarchy": [
          "tgn:2323255",
          "tgn:1000001",
          "tgn:7012149",
          "tgn:2000559",
          "tgn:7007252",
          "tgn:7029392"
        ],
        "placetype": [
          "aat:300006191"
        ],
        "id": 2323255,
        "name:xx": "Farmer Lake"
      }
    },
    {
      "geometry": {
        "type": "Point",
        "coordinates": [
          -87.3167,
          46.2833
        ]
      },
      "type": "Feature",
      "properties": {
        "hierarchy": [
          "tgn:2323256",
          "tgn:1000001",
          "tgn:7012149",
          "tgn:2000975",
          "tgn:7007520",
          "tgn:7029392"
        ],
        "placetype": [
          "aat:300008680"
        ],
        "id": 2323256,
        "name:xx": "Farmer Lake"
      }
    },
    {
      "geometry": {
        "type": "Point",
        "coordinates": [
          -95.7333,
          32.1167
        ]
      },
      "type": "Feature",
      "properties": {
        "hierarchy": [
          "tgn:2323257",
          "tgn:1000001",
          "tgn:7012149",
          "tgn:1002464",
          "tgn:7007826",
          "tgn:7029392"
        ],
        "placetype": [
          "aat:300008680"
        ],
        "id": 2323257,
        "name:xx": "Farmer Lake"
      }
    },
    {
      "geometry": {
        "type": "Point",
        "coordinates": [
          -123.1333,
          40.5
        ]
      },
      "type": "Feature",
      "properties": {
        "hierarchy": [
          "tgn:2323258",
          "tgn:1000001",
          "tgn:7012149",
          "tgn:7007157",
          "tgn:2000191",
          "tgn:7029392"
        ],
        "placetype": [
          "aat:300000390"
        ],
        "id": 2323258,
        "name:xx": "Farmer Mine"
      }
    },
    {
      "geometry": {
        "type": "Point",
        "coordinates": [
          -117.6167,
          48.8333
        ]
      },
      "type": "Feature",
      "properties": {
        "hierarchy": [
          "tgn:2323259",
          "tgn:1000001",
          "tgn:7012149",
          "tgn:2002250",
          "tgn:7007920",
          "tgn:7029392"
        ],
        "placetype": [
          "aat:300000390"
        ],
        "id": 2323259,
        "name:xx": "Farmer Mine"
      }
    }
  ]
}
