{
  "geometry": {
    "type": "Point",
    "coordinates": [
      -90.4833,
      31.1833
    ]
  },
  "type": "Feature",
  "properties": {
    "hierarchy": [
      "tgn:2603991",
      "tgn:1000001",
      "tgn:7012149",
      "tgn:2001142",
      "tgn:7007522",
      "tgn:7029392"
    ],
    "placetype": [
      "aat:300008347"
    ],
    "id": 2603991,
    "name:xx": "Quinlivan"
  }
}
