{
  "geometry": {
    "type": "Point",
    "coordinates": [
      28.1667,
      57.6667
    ]
  },
  "type": "Feature",
  "properties": {
    "hierarchy": [
      "tgn:1053883",
      "tgn:1000004",
      "tgn:7011590",
      "tgn:7018214",
      "tgn:7002435",
      "tgn:7029392"
    ],
    "placetype": [
      "aat:300008347"
    ],
    "id": 1053883,
    "name:xx": "Filatova Gora"
  }
}
