{
  "geometry": {
    "type": "Point",
    "coordinates": [
      -77.2833,
      38.2333
    ]
  },
  "type": "Feature",
  "properties": {
    "hierarchy": [
      "tgn:2526414",
      "tgn:1000001",
      "tgn:1002235",
      "tgn:7012149",
      "tgn:7007919",
      "tgn:7029392"
    ],
    "placetype": [
      "aat:300008850"
    ],
    "id": 2526414,
    "name:xx": "Moss Neck"
  }
}
