{
  "geometry": {
    "type": "Point",
    "coordinates": [
      105.4167,
      10.5833
    ]
  },
  "type": "Feature",
  "properties": {
    "hierarchy": [
      "tgn:1127046",
      "tgn:1000004",
      "tgn:7029392"
    ],
    "placetype": [
      "aat:300008707"
    ],
    "id": 1127046,
    "name:xx": "Lancang Jiang"
  }
}
