{
  "geometry": {
    "type": "Point",
    "coordinates": [
      -74.75,
      10.7667
    ]
  },
  "type": "Feature",
  "properties": {
    "hierarchy": [
      "tgn:1024008",
      "tgn:1000511",
      "tgn:1000050",
      "tgn:1000002",
      "tgn:7029392"
    ],
    "placetype": [
      "aat:300008347"
    ],
    "id": 1024008,
    "name:xx": "Santo Tomás"
  }
}
