{
  "geometry": {
    "type": "Point",
    "coordinates": [
      121.35,
      31.7667
    ]
  },
  "type": "Feature",
  "properties": {
    "hierarchy": [
      "tgn:1066759",
      "tgn:1000004",
      "tgn:1000958",
      "tgn:1000111",
      "tgn:7029392"
    ],
    "placetype": [
      "aat:300008347"
    ],
    "id": 1066759,
    "name:xx": "Baoan"
  }
}
