{
  "geometry": {
    "type": "Point",
    "coordinates": [
      -95.05,
      49.35
    ]
  },
  "type": "Feature",
  "properties": {
    "hierarchy": [
      "tgn:2550353",
      "tgn:1000001",
      "tgn:7012149",
      "tgn:7021313",
      "tgn:7007521",
      "tgn:7029392"
    ],
    "placetype": [
      "aat:300132316"
    ],
    "id": 2550353,
    "name:xx": "Northwest Angle Inlet"
  }
}
