{
  "type": "FeatureCollection",
  "features": [
    {
      "geometry": {
        "type": "Point",
        "coordinates": [
          -97,
          29.4
        ]
      },
      "type": "Feature",
      "properties": {
        "hierarchy": [
          "tgn:2108630",
          "tgn:1000001",
          "tgn:7012149",
          "tgn:1002578",
          "tgn:7007826",
          "tgn:7029392"
        ],
        "placetype": [
          "aat:300008347",
          "aat:300387210"
        ],
        "id": 2108630,
        "name:xx": "Worthing"
      }
    },
    {
      "geometry": {
        "type": "Point",
        "coordinates": [
          -101.8167,
          34.25
        ]
      },
      "type": "Feature",
      "properties": {
        "hierarchy": [
          "tgn:2108631",
          "tgn:1000001",
          "tgn:7012149",
          "tgn:2001994",
          "tgn:7007826",
          "tgn:7029392"
        ],
        "placetype": [
          "aat:300387016"
        ],
        "id": 2108631,
        "name:xx": "Wright"
      }
    },
    {
      "geometry": {
        "type": "Point",
        "coordinates": [
          -94.9833,
          32.1833
        ]
      },
      "type": "Feature",
      "properties": {
        "hierarchy": [
          "tgn:2108632",
          "tgn:1000001",
          "tgn:7012149",
          "tgn:1002839",
          "tgn:7007826",
          "tgn:7029392"
        ],
        "placetype": [
          "aat:300008347"
        ],
        "id": 2108632,
        "name:xx": "Wright City"
      }
    },
    {
      "geometry": {
        "type": "Point",
        "coordinates": [
          -97.55,
          29.3667
        ]
      },
      "type": "Feature",
      "properties": {
        "hierarchy": [
          "tgn:2108633",
          "tgn:1000001",
          "tgn:7012149",
          "tgn:1002414",
          "tgn:7007826",
          "tgn:7029392"
        ],
        "placetype": [
          "aat:300008347"
        ],
        "id": 2108633,
        "name:xx": "Wrightsboro"
      }
    },
    {
      "geometry": {
        "type": "Point",
        "coordinates": [
          -99.7667,
          32.3667
        ]
      },
      "type": "Feature",
      "properties": {
        "hierarchy": [
          "tgn:2108634",
          "tgn:1000001",
          "tgn:7012149",
          "tgn:2002081",
          "tgn:7007826",
          "tgn:7029392"
        ],
        "placetype": [
          "aat:300008347"
        ],
        "id": 2108634,
        "name:xx": "Wylie"
      }
    },
    {
      "geometry": {
        "type": "Point",
        "coordinates": [
          -96.5333,
          33
        ]
      },
      "type": "Feature",
      "properties": {
        "hierarchy": [
          "tgn:2108636",
          "tgn:1000001",
          "tgn:7012149",
          "tgn:1002290",
          "tgn:7007826",
          "tgn:7029392"
        ],
        "placetype": [
          "aat:300008347"
        ],
        "id": 2108636,
        "name:xx": "Wylie"
      }
    }
  ]
}
