{
  "geometry": {
    "type": "Point",
    "coordinates": [
      -68.2167,
      47.3333
    ]
  },
  "type": "Feature",
  "properties": {
    "hierarchy": [
      "tgn:2045527",
      "tgn:2000919",
      "tgn:1000001",
      "tgn:7012149",
      "tgn:7007515",
      "tgn:7029392"
    ],
    "placetype": [
      "aat:300008347"
    ],
    "id": 2045527,
    "name:xx": "Saint David"
  }
}
