{
  "type": "FeatureCollection",
  "features": [
    {
      "geometry": {
        "type": "Point",
        "coordinates": [
          -82.8667,
          38.8
        ]
      },
      "type": "Feature",
      "properties": {
        "hierarchy": [
          "tgn:2510250",
          "tgn:1000001",
          "tgn:7012149",
          "tgn:1002877",
          "tgn:7007706",
          "tgn:7029392"
        ],
        "placetype": [
          "aat:300266640"
        ],
        "id": 2510250,
        "name:xx": "Middle Ridge"
      }
    },
    {
      "geometry": {
        "type": "Point",
        "coordinates": [
          -80.8167,
          40.4833
        ]
      },
      "type": "Feature",
      "properties": {
        "hierarchy": [
          "tgn:2510251",
          "tgn:1000001",
          "tgn:7012149",
          "tgn:1002519",
          "tgn:7007706",
          "tgn:7029392"
        ],
        "placetype": [
          "aat:300266640"
        ],
        "id": 2510251,
        "name:xx": "Middle Ridge"
      }
    },
    {
      "geometry": {
        "type": "Point",
        "coordinates": [
          -95.1833,
          34.7833
        ]
      },
      "type": "Feature",
      "properties": {
        "hierarchy": [
          "tgn:2510252",
          "tgn:1000001",
          "tgn:7012149",
          "tgn:2001661",
          "tgn:7007707",
          "tgn:7029392"
        ],
        "placetype": [
          "aat:300266640"
        ],
        "id": 2510252,
        "name:xx": "Middle Ridge"
      }
    },
    {
      "geometry": {
        "type": "Point",
        "coordinates": [
          -122.8167,
          42.85
        ]
      },
      "type": "Feature",
      "properties": {
        "hierarchy": [
          "tgn:2510253",
          "tgn:1000001",
          "tgn:7012149",
          "tgn:2001706",
          "tgn:7007708",
          "tgn:7029392"
        ],
        "placetype": [
          "aat:300266640"
        ],
        "id": 2510253,
        "name:xx": "Middle Ridge"
      }
    },
    {
      "geometry": {
        "type": "Point",
        "coordinates": [
          -123.7833,
          44.4167
        ]
      },
      "type": "Feature",
      "properties": {
        "hierarchy": [
          "tgn:2510254",
          "tgn:1000001",
          "tgn:7012149",
          "tgn:1002599",
          "tgn:7007708",
          "tgn:7029392"
        ],
        "placetype": [
          "aat:300266640"
        ],
        "id": 2510254,
        "name:xx": "Middle Ridge"
      }
    },
    {
      "geometry": {
        "type": "Point",
        "coordinates": [
          -123.5,
          44.7667
        ]
      },
      "type": "Feature",
      "properties": {
        "hierarchy": [
          "tgn:2510255",
          "tgn:1000001",
          "tgn:7012149",
          "tgn:1002794",
          "tgn:7007708",
          "tgn:7029392"
        ],
        "placetype": [
          "aat:300266640"
        ],
        "id": 2510255,
        "name:xx": "Middle Ridge"
      }
    },
    {
      "geometry": {
        "type": "Point",
        "coordinates": [
          -118.0167,
          45.6
        ]
      },
      "type": "Feature",
      "properties": {
        "hierarchy": [
          "tgn:2510256",
          "tgn:1000001",
          "tgn:7012149",
          "tgn:2001721",
          "tgn:7007708",
          "tgn:7029392"
        ],
        "placetype": [
          "aat:300266640"
        ],
        "id": 2510256,
        "name:xx": "Middle Ridge"
      }
    },
    {
      "geometry": {
        "type": "Point",
        "coordinates": [
          -78.4333,
          40.1833
        ]
      },
      "type": "Feature",
      "properties": {
        "hierarchy": [
          "tgn:2510257",
          "tgn:1002172",
          "tgn:1000001",
          "tgn:7012149",
          "tgn:7007710",
          "tgn:7029392"
        ],
        "placetype": [
          "aat:300266640"
        ],
        "id": 2510257,
        "name:xx": "Middle Ridge"
      }
    },
    {
      "geometry": {
        "type": "Point",
        "coordinates": [
          -77.3167,
          40.2667
        ]
      },
      "type": "Feature",
      "properties": {
        "hierarchy": [
          "tgn:2510258",
          "tgn:1000001",
          "tgn:7012149",
          "tgn:1002779",
          "tgn:7007710",
          "tgn:7029392"
        ],
        "placetype": [
          "aat:300266640"
        ],
        "id": 2510258,
        "name:xx": "Middle Ridge"
      }
    },
    {
      "geometry": {
        "type": "Point",
        "coordinates": [
          -77.7167,
          40.5167
        ]
      },
      "type": "Feature",
      "properties": {
        "hierarchy": [
          "tgn:2510259",
          "tgn:1000001",
          "tgn:7012149",
          "tgn:1002669",
          "tgn:7007710",
          "tgn:7029392"
        ],
        "placetype": [
          "aat:300266640"
        ],
        "id": 2510259,
        "name:xx": "Middle Ridge"
      }
    }
  ]
}
