{
  "type": "FeatureCollection",
  "features": [
    {
      "geometry": {
        "type": "Point",
        "coordinates": [
          -95.7,
          34.7167
        ]
      },
      "type": "Feature",
      "properties": {
        "hierarchy": [
          "tgn:2660970",
          "tgn:1000001",
          "tgn:7012149",
          "tgn:2001683",
          "tgn:7007707",
          "tgn:7029392"
        ],
        "placetype": [
          "aat:300008706"
        ],
        "id": 2660970,
        "name:xx": "Short Creek"
      }
    },
    {
      "geometry": {
        "type": "Point",
        "coordinates": [
          -99.65,
          35.3833
        ]
      },
      "type": "Feature",
      "properties": {
        "hierarchy": [
          "tgn:2660971",
          "tgn:2001627",
          "tgn:1000001",
          "tgn:7012149",
          "tgn:7007707",
          "tgn:7029392"
        ],
        "placetype": [
          "aat:300008706"
        ],
        "id": 2660971,
        "name:xx": "Short Creek"
      }
    },
    {
      "geometry": {
        "type": "Point",
        "coordinates": [
          -100.8833,
          36.8833
        ]
      },
      "type": "Feature",
      "properties": {
        "hierarchy": [
          "tgn:2660972",
          "tgn:2001626",
          "tgn:1000001",
          "tgn:7012149",
          "tgn:7007707",
          "tgn:7029392"
        ],
        "placetype": [
          "aat:300008706"
        ],
        "id": 2660972,
        "name:xx": "Short Creek"
      }
    },
    {
      "geometry": {
        "type": "Point",
        "coordinates": [
          -122.05,
          42.4167
        ]
      },
      "type": "Feature",
      "properties": {
        "hierarchy": [
          "tgn:2660973",
          "tgn:1000001",
          "tgn:7012149",
          "tgn:2001714",
          "tgn:7007708",
          "tgn:7029392"
        ],
        "placetype": [
          "aat:300008706"
        ],
        "id": 2660973,
        "name:xx": "Short Creek"
      }
    },
    {
      "geometry": {
        "type": "Point",
        "coordinates": [
          -122.1333,
          43.1333
        ]
      },
      "type": "Feature",
      "properties": {
        "hierarchy": [
          "tgn:2660974",
          "tgn:1000001",
          "tgn:7012149",
          "tgn:2001706",
          "tgn:7007708",
          "tgn:7029392"
        ],
        "placetype": [
          "aat:300008706"
        ],
        "id": 2660974,
        "name:xx": "Short Creek"
      }
    },
    {
      "geometry": {
        "type": "Point",
        "coordinates": [
          -122.9667,
          43.6667
        ]
      },
      "type": "Feature",
      "properties": {
        "hierarchy": [
          "tgn:2660975",
          "tgn:1000001",
          "tgn:7012149",
          "tgn:2001716",
          "tgn:7007708",
          "tgn:7029392"
        ],
        "placetype": [
          "aat:300008706"
        ],
        "id": 2660975,
        "name:xx": "Short Creek"
      }
    },
    {
      "geometry": {
        "type": "Point",
        "coordinates": [
          -118.4333,
          44.2667
        ]
      },
      "type": "Feature",
      "properties": {
        "hierarchy": [
          "tgn:2660976",
          "tgn:7013349",
          "tgn:1000001",
          "tgn:7012149",
          "tgn:7007708",
          "tgn:7029392"
        ],
        "placetype": [
          "aat:300008706"
        ],
        "id": 2660976,
        "name:xx": "Short Creek"
      }
    },
    {
      "geometry": {
        "type": "Point",
        "coordinates": [
          -120.3167,
          44.2667
        ]
      },
      "type": "Feature",
      "properties": {
        "hierarchy": [
          "tgn:2660977",
          "tgn:1000001",
          "tgn:2001703",
          "tgn:7012149",
          "tgn:7007708",
          "tgn:7029392"
        ],
        "placetype": [
          "aat:300008706"
        ],
        "id": 2660977,
        "name:xx": "Short Creek"
      }
    },
    {
      "geometry": {
        "type": "Point",
        "coordinates": [
          -121.9833,
          44.8167
        ]
      },
      "type": "Feature",
      "properties": {
        "hierarchy": [
          "tgn:2660978",
          "tgn:1000001",
          "tgn:7012149",
          "tgn:1002636",
          "tgn:7007708",
          "tgn:7029392"
        ],
        "placetype": [
          "aat:300008706"
        ],
        "id": 2660978,
        "name:xx": "Short Creek"
      }
    },
    {
      "geometry": {
        "type": "Point",
        "coordinates": [
          -123.7,
          44.85
        ]
      },
      "type": "Feature",
      "properties": {
        "hierarchy": [
          "tgn:2660979",
          "tgn:1000001",
          "tgn:7012149",
          "tgn:1002794",
          "tgn:7007708",
          "tgn:7029392"
        ],
        "placetype": [
          "aat:300008706"
        ],
        "id": 2660979,
        "name:xx": "Short Creek"
      }
    }
  ]
}
