{
  "geometry": {
    "type": "Point",
    "coordinates": [
      -93.9333,
      29.7333
    ]
  },
  "type": "Feature",
  "properties": {
    "hierarchy": [
      "tgn:2771196",
      "tgn:1000001",
      "tgn:7012149",
      "tgn:2002011",
      "tgn:7007826",
      "tgn:7029392"
    ],
    "placetype": [
      "aat:300266640"
    ],
    "id": 2771196,
    "name:xx": "Wildcat Ridge"
  }
}
