{
  "geometry": {
    "type": "Point",
    "coordinates": [
      -120.8667,
      45.3167
    ]
  },
  "type": "Feature",
  "properties": {
    "hierarchy": [
      "tgn:2571129",
      "tgn:1000001",
      "tgn:7012149",
      "tgn:1002891",
      "tgn:7007708",
      "tgn:7029392"
    ],
    "placetype": [
      "aat:300008761"
    ],
    "id": 2571129,
    "name:xx": "Pattlesnake Canyon"
  }
}
