{
  "type": "FeatureCollection",
  "features": [
    {
      "geometry": {
        "type": "Point",
        "coordinates": [
          31.066667,
          29.033333
        ]
      },
      "type": "Feature",
      "properties": {
        "hierarchy": [
          "tgn:7528980",
          "tgn:7001242",
          "tgn:7001105",
          "tgn:7016833",
          "tgn:7029392"
        ],
        "placetype": [
          "aat:300005926"
        ],
        "name:en": "Manāmat Sīdī 'Alī",
        "id": 7528980
      }
    },
    {
      "geometry": {
        "type": "Point",
        "coordinates": [
          32.783333,
          32.833333
        ]
      },
      "type": "Feature",
      "properties": {
        "hierarchy": [
          "tgn:7528981",
          "tgn:7001242",
          "tgn:7016833",
          "tgn:7000123",
          "tgn:7029392"
        ],
        "placetype": [
          "aat:300005926"
        ],
        "name:en": "Sīdī 'Alī",
        "id": 7528981
      }
    },
    {
      "geometry": {
        "type": "Point",
        "coordinates": [
          26.05,
          31.4
        ]
      },
      "type": "Feature",
      "properties": {
        "hierarchy": [
          "tgn:7528982",
          "tgn:7001242",
          "tgn:7016833",
          "tgn:1001418",
          "tgn:7029392"
        ],
        "placetype": [
          "aat:300005926"
        ],
        "name:en": "Sîdi 'Ali",
        "id": 7528982
      }
    },
    {
      "geometry": {
        "type": "Point",
        "coordinates": [
          26.634818,
          31.341401
        ]
      },
      "type": "Feature",
      "properties": {
        "hierarchy": [
          "tgn:7528983",
          "tgn:7001242",
          "tgn:7016833",
          "tgn:1001418",
          "tgn:7029392"
        ],
        "placetype": [
          "aat:300005926"
        ],
        "name:en": "Sīdī 'Alī",
        "id": 7528983
      }
    },
    {
      "geometry": {
        "type": "Point",
        "coordinates": [
          31.591111,
          30.564444
        ]
      },
      "type": "Feature",
      "properties": {
        "hierarchy": [
          "tgn:7528984",
          "tgn:7001242",
          "tgn:7016833",
          "tgn:1001113",
          "tgn:7029392"
        ],
        "placetype": [
          "aat:300005926"
        ],
        "id": 7528984,
        "name:xx": "Sīdī 'Alī"
      }
    },
    {
      "geometry": {
        "type": "Point",
        "coordinates": [
          31.583333,
          30.566667
        ]
      },
      "type": "Feature",
      "properties": {
        "hierarchy": [
          "tgn:7528985",
          "tgn:7001242",
          "tgn:7016833",
          "tgn:1001113",
          "tgn:7029392"
        ],
        "placetype": [
          "aat:300005926"
        ],
        "id": 7528985,
        "name:xx": "Sīdī 'Alī"
      }
    },
    {
      "geometry": {
        "type": "Point",
        "coordinates": [
          31.2,
          29.25
        ]
      },
      "type": "Feature",
      "properties": {
        "hierarchy": [
          "tgn:7528986",
          "tgn:7001242",
          "tgn:7016833",
          "tgn:1001083",
          "tgn:7029392"
        ],
        "placetype": [
          "aat:300005926"
        ],
        "name:en": "Sīdī 'Alī",
        "id": 7528986
      }
    },
    {
      "geometry": {
        "type": "Point",
        "coordinates": [
          31.116667,
          29.066667
        ]
      },
      "type": "Feature",
      "properties": {
        "hierarchy": [
          "tgn:7528987",
          "tgn:7001242",
          "tgn:7001105",
          "tgn:7016833",
          "tgn:7029392"
        ],
        "placetype": [
          "aat:300005926"
        ],
        "name:en": "Sīdī 'Alī",
        "id": 7528987
      }
    },
    {
      "geometry": {
        "type": "Point",
        "coordinates": [
          30.75,
          28.583333
        ]
      },
      "type": "Feature",
      "properties": {
        "hierarchy": [
          "tgn:7528988",
          "tgn:7001242",
          "tgn:7016833",
          "tgn:1001088",
          "tgn:7029392"
        ],
        "placetype": [
          "aat:300005926"
        ],
        "name:en": "Sīdī 'Alī",
        "id": 7528988
      }
    },
    {
      "geometry": {
        "type": "Point",
        "coordinates": [
          30.633333,
          28.466667
        ]
      },
      "type": "Feature",
      "properties": {
        "hierarchy": [
          "tgn:7528989",
          "tgn:7001242",
          "tgn:7016833",
          "tgn:1001088",
          "tgn:7029392"
        ],
        "placetype": [
          "aat:300005926"
        ],
        "name:en": "Sīdī 'Alī",
        "id": 7528989
      }
    }
  ]
}
