{
  "geometry": {
    "type": "Point",
    "coordinates": [
      -72.55,
      41.6333
    ]
  },
  "type": "Feature",
  "properties": {
    "hierarchy": [
      "tgn:2201447",
      "tgn:1000001",
      "tgn:7012149",
      "tgn:7007159",
      "tgn:7029392"
    ],
    "placetype": [
      "aat:300008699"
    ],
    "id": 2201447,
    "name:xx": "Buck Brook"
  }
}
