{
  "geometry": {
    "type": "Point",
    "coordinates": [
      74.36938,
      28.272496
    ]
  },
  "type": "Feature",
  "properties": {
    "hierarchy": [
      "tgn:7564177",
      "tgn:1000004",
      "tgn:7000198",
      "tgn:7016788",
      "tgn:7029392"
    ],
    "placetype": [
      "aat:300008750"
    ],
    "name:en": "Sādhu ka Dhora",
    "id": 7564177
  }
}
