{
  "geometry": {
    "type": "Point",
    "coordinates": [
      -86.4667,
      31.45
    ]
  },
  "type": "Feature",
  "properties": {
    "hierarchy": [
      "tgn:2609226",
      "tgn:7002659",
      "tgn:1000001",
      "tgn:2000019",
      "tgn:7012149",
      "tgn:7029392"
    ],
    "placetype": [
      "aat:300008347"
    ],
    "id": 2609226,
    "name:xx": "Rawls"
  }
}
