{
  "geometry": {
    "type": "Point",
    "coordinates": [
      -144.4167,
      68.6167
    ]
  },
  "type": "Feature",
  "properties": {
    "hierarchy": [
      "tgn:2558115",
      "tgn:7006450",
      "tgn:1000001",
      "tgn:7012149",
      "tgn:7029392"
    ],
    "placetype": [
      "aat:300008706"
    ],
    "id": 2558115,
    "name:xx": "Old Woman Creek"
  }
}
