{
  "geometry": {
    "type": "Point",
    "coordinates": [
      -68.8667,
      44.1167
    ]
  },
  "type": "Feature",
  "properties": {
    "hierarchy": [
      "tgn:2045254",
      "tgn:1000001",
      "tgn:2000924",
      "tgn:7012149",
      "tgn:7007515",
      "tgn:7029392"
    ],
    "placetype": [
      "aat:300008347"
    ],
    "id": 2045254,
    "name:xx": "North Haven"
  }
}
