{
  "geometry": {
    "type": "Point",
    "coordinates": [
      74.2261,
      25.0507
    ]
  },
  "type": "Feature",
  "properties": {
    "hierarchy": [
      "tgn:7550082",
      "tgn:1000004",
      "tgn:7000198",
      "tgn:7016788",
      "tgn:7029392"
    ],
    "placetype": [
      "aat:300008699"
    ],
    "name:en": "Chandrabhāga River",
    "id": 7550082
  }
}
