{
  "type": "FeatureCollection",
  "features": [
    {
      "geometry": {
        "type": "Point",
        "coordinates": [
          -79.8167,
          39.7167
        ]
      },
      "type": "Feature",
      "properties": {
        "hierarchy": [
          "tgn:2086103",
          "tgn:1000001",
          "tgn:7012149",
          "tgn:7014185",
          "tgn:7007710",
          "tgn:7029392"
        ],
        "placetype": [
          "aat:300387016"
        ],
        "id": 2086103,
        "name:xx": "Atchison"
      }
    },
    {
      "geometry": {
        "type": "Point",
        "coordinates": [
          -75.0833,
          41.6167
        ]
      },
      "type": "Feature",
      "properties": {
        "hierarchy": [
          "tgn:2086104",
          "tgn:1000001",
          "tgn:7012149",
          "tgn:1003008",
          "tgn:7007710",
          "tgn:7029392"
        ],
        "placetype": [
          "aat:300008347"
        ],
        "id": 2086104,
        "name:xx": "Atco"
      }
    },
    {
      "geometry": {
        "type": "Point",
        "coordinates": [
          -75.9667,
          39.9333
        ]
      },
      "type": "Feature",
      "properties": {
        "hierarchy": [
          "tgn:2086105",
          "tgn:1000001",
          "tgn:1002266",
          "tgn:7012149",
          "tgn:7007710",
          "tgn:7029392"
        ],
        "placetype": [
          "aat:300008347"
        ],
        "id": 2086105,
        "name:xx": "Atglen"
      }
    },
    {
      "geometry": {
        "type": "Point",
        "coordinates": [
          -76.5167,
          41.95
        ]
      },
      "type": "Feature",
      "properties": {
        "hierarchy": [
          "tgn:2086106",
          "tgn:1000001",
          "tgn:1002194",
          "tgn:7012149",
          "tgn:7007710",
          "tgn:7029392"
        ],
        "placetype": [
          "aat:300008347"
        ],
        "id": 2086106,
        "name:xx": "Athens"
      }
    },
    {
      "geometry": {
        "type": "Point",
        "coordinates": [
          -75.7333,
          40.3
        ]
      },
      "type": "Feature",
      "properties": {
        "hierarchy": [
          "tgn:2086107",
          "tgn:1000001",
          "tgn:7013387",
          "tgn:7012149",
          "tgn:7007710",
          "tgn:7029392"
        ],
        "placetype": [
          "aat:300008347"
        ],
        "id": 2086107,
        "name:xx": "Amityville"
      }
    },
    {
      "geometry": {
        "type": "Point",
        "coordinates": [
          -80.3333,
          41.5
        ]
      },
      "type": "Feature",
      "properties": {
        "hierarchy": [
          "tgn:2086109",
          "tgn:1000001",
          "tgn:1002308",
          "tgn:7012149",
          "tgn:7007710",
          "tgn:7029392"
        ],
        "placetype": [
          "aat:300008347"
        ],
        "id": 2086109,
        "name:xx": "Atlantic"
      }
    }
  ]
}
