{
  "type": "FeatureCollection",
  "features": [
    {
      "geometry": {
        "type": "Point",
        "coordinates": [
          -7.266667,
          42.9
        ]
      },
      "type": "Feature",
      "properties": {
        "hierarchy": [
          "tgn:7335471",
          "tgn:7002829",
          "tgn:1000003",
          "tgn:7002786",
          "tgn:1000095",
          "tgn:7029392"
        ],
        "placetype": [
          "aat:300008347"
        ],
        "id": 7335471,
        "name:xx": "Ferreiros"
      }
    },
    {
      "geometry": {
        "type": "Point",
        "coordinates": [
          -8.183333,
          42.8
        ]
      },
      "type": "Feature",
      "properties": {
        "hierarchy": [
          "tgn:7335472",
          "tgn:7002834",
          "tgn:1000003",
          "tgn:7002786",
          "tgn:1000095",
          "tgn:7029392"
        ],
        "placetype": [
          "aat:300008347"
        ],
        "id": 7335472,
        "name:xx": "Ferreirós"
      }
    },
    {
      "geometry": {
        "type": "Point",
        "coordinates": [
          -7.533333,
          42.783333
        ]
      },
      "type": "Feature",
      "properties": {
        "hierarchy": [
          "tgn:7335474",
          "tgn:7002829",
          "tgn:1000003",
          "tgn:7002786",
          "tgn:1000095",
          "tgn:7029392"
        ],
        "placetype": [
          "aat:300008347"
        ],
        "id": 7335474,
        "name:xx": "Ferreiros"
      }
    },
    {
      "geometry": {
        "type": "Point",
        "coordinates": [
          -7.816667,
          42.733333
        ]
      },
      "type": "Feature",
      "properties": {
        "hierarchy": [
          "tgn:7335475",
          "tgn:7002829",
          "tgn:1000003",
          "tgn:7002786",
          "tgn:1000095",
          "tgn:7029392"
        ],
        "placetype": [
          "aat:300008347"
        ],
        "id": 7335475,
        "name:xx": "Ferreiros"
      }
    },
    {
      "geometry": {
        "type": "Point",
        "coordinates": [
          -8.85,
          42.65
        ]
      },
      "type": "Feature",
      "properties": {
        "hierarchy": [
          "tgn:7335476",
          "tgn:7002824",
          "tgn:1000003",
          "tgn:7002786",
          "tgn:1000095",
          "tgn:7029392"
        ],
        "placetype": [
          "aat:300008347"
        ],
        "id": 7335476,
        "name:xx": "Ferreiros"
      }
    },
    {
      "geometry": {
        "type": "Point",
        "coordinates": [
          -7.366667,
          42.6
        ]
      },
      "type": "Feature",
      "properties": {
        "hierarchy": [
          "tgn:7335477",
          "tgn:7002829",
          "tgn:1000003",
          "tgn:7002786",
          "tgn:1000095",
          "tgn:7029392"
        ],
        "placetype": [
          "aat:300008347"
        ],
        "id": 7335477,
        "name:xx": "Ferreiros"
      }
    },
    {
      "geometry": {
        "type": "Point",
        "coordinates": [
          -7.15,
          43.1
        ]
      },
      "type": "Feature",
      "properties": {
        "hierarchy": [
          "tgn:7335478",
          "tgn:7002829",
          "tgn:1000003",
          "tgn:7002786",
          "tgn:1000095",
          "tgn:7029392"
        ],
        "placetype": [
          "aat:300008347"
        ],
        "id": 7335478,
        "name:xx": "Ferreirola"
      }
    },
    {
      "geometry": {
        "type": "Point",
        "coordinates": [
          -3.316667,
          36.933333
        ]
      },
      "type": "Feature",
      "properties": {
        "hierarchy": [
          "tgn:7335479",
          "tgn:7002758",
          "tgn:7002821",
          "tgn:1000003",
          "tgn:1000095",
          "tgn:7029392"
        ],
        "placetype": [
          "aat:300008347"
        ],
        "id": 7335479,
        "name:xx": "Ferreirola"
      }
    }
  ]
}
