{
  "type": "FeatureCollection",
  "features": [
    {
      "geometry": {
        "type": "Point",
        "coordinates": [
          7.616667,
          49.6
        ]
      },
      "type": "Feature",
      "properties": {
        "hierarchy": [
          "tgn:7069360",
          "tgn:1000003",
          "tgn:7003682",
          "tgn:7000084",
          "tgn:7029392"
        ],
        "placetype": [
          "aat:300000745"
        ],
        "id": 7069360,
        "name:xx": "Tiefenbach"
      }
    },
    {
      "geometry": {
        "type": "Point",
        "coordinates": [
          9.202222,
          49.298333
        ]
      },
      "type": "Feature",
      "properties": {
        "hierarchy": [
          "tgn:7069362",
          "tgn:7003692",
          "tgn:1000003",
          "tgn:7000084",
          "tgn:7029392"
        ],
        "placetype": [
          "aat:300008347"
        ],
        "id": 7069362,
        "name:xx": "Tiefenbach"
      }
    },
    {
      "geometry": {
        "type": "Point",
        "coordinates": [
          12.333333,
          49.183333
        ]
      },
      "type": "Feature",
      "properties": {
        "hierarchy": [
          "tgn:7069363",
          "tgn:7003669",
          "tgn:1000003",
          "tgn:7000084",
          "tgn:7029392"
        ],
        "placetype": [
          "aat:300008347"
        ],
        "id": 7069363,
        "name:xx": "Tiefenbach"
      }
    },
    {
      "geometry": {
        "type": "Point",
        "coordinates": [
          10.033333,
          49.166667
        ]
      },
      "type": "Feature",
      "properties": {
        "hierarchy": [
          "tgn:7069364",
          "tgn:7003692",
          "tgn:1000003",
          "tgn:7000084",
          "tgn:7029392"
        ],
        "placetype": [
          "aat:300008347"
        ],
        "id": 7069364,
        "name:xx": "Tiefenbach"
      }
    },
    {
      "geometry": {
        "type": "Point",
        "coordinates": [
          8.796944,
          49.177778
        ]
      },
      "type": "Feature",
      "properties": {
        "hierarchy": [
          "tgn:7069365",
          "tgn:7003692",
          "tgn:1000003",
          "tgn:7000084",
          "tgn:7029392"
        ],
        "placetype": [
          "aat:300008347"
        ],
        "id": 7069365,
        "name:xx": "Tiefenbach"
      }
    },
    {
      "geometry": {
        "type": "Point",
        "coordinates": [
          11.183333,
          49.133333
        ]
      },
      "type": "Feature",
      "properties": {
        "hierarchy": [
          "tgn:7069366",
          "tgn:7003669",
          "tgn:1000003",
          "tgn:7000084",
          "tgn:7029392"
        ],
        "placetype": [
          "aat:300008347"
        ],
        "id": 7069366,
        "name:xx": "Tiefenbach"
      }
    },
    {
      "geometry": {
        "type": "Point",
        "coordinates": [
          10.916667,
          49.083333
        ]
      },
      "type": "Feature",
      "properties": {
        "hierarchy": [
          "tgn:7069367",
          "tgn:7003669",
          "tgn:1000003",
          "tgn:7000084",
          "tgn:7029392"
        ],
        "placetype": [
          "aat:300008347"
        ],
        "id": 7069367,
        "name:xx": "Tiefenbach"
      }
    },
    {
      "geometry": {
        "type": "Point",
        "coordinates": [
          12.1,
          48.8
        ]
      },
      "type": "Feature",
      "properties": {
        "hierarchy": [
          "tgn:7069368",
          "tgn:7003669",
          "tgn:1000003",
          "tgn:7000084",
          "tgn:7029392"
        ],
        "placetype": [
          "aat:300008347"
        ],
        "id": 7069368,
        "name:xx": "Tiefenbach"
      }
    },
    {
      "geometry": {
        "type": "Point",
        "coordinates": [
          13.4,
          48.616667
        ]
      },
      "type": "Feature",
      "properties": {
        "hierarchy": [
          "tgn:7069369",
          "tgn:7003669",
          "tgn:1000003",
          "tgn:7000084",
          "tgn:7029392"
        ],
        "placetype": [
          "aat:300008347"
        ],
        "id": 7069369,
        "name:xx": "Tiefenbach"
      }
    }
  ]
}
