{
  "geometry": {
    "type": "Point",
    "coordinates": [
      -85.55,
      34.85
    ]
  },
  "type": "Feature",
  "properties": {
    "hierarchy": [
      "tgn:2206213",
      "tgn:1000001",
      "tgn:7012149",
      "tgn:7029392"
    ],
    "placetype": [
      "aat:300008699"
    ],
    "id": 2206213,
    "name:xx": "Bullard Branch"
  }
}
