{
  "geometry": {
    "type": "Point",
    "coordinates": [
      -76.3667,
      41.2667
    ]
  },
  "type": "Feature",
  "properties": {
    "hierarchy": [
      "tgn:2328827",
      "tgn:1000001",
      "tgn:1002294",
      "tgn:7012149",
      "tgn:7007710",
      "tgn:7029392"
    ],
    "placetype": [
      "aat:300008706"
    ],
    "id": 2328827,
    "name:xx": "Fishing Creek"
  }
}
