{
  "type": "FeatureCollection",
  "features": [
    {
      "geometry": {
        "type": "Point",
        "coordinates": [
          120.305611,
          23.903286
        ]
      },
      "type": "Feature",
      "properties": {
        "hierarchy": [
          "tgn:7471050",
          "tgn:1000004",
          "tgn:7467799",
          "tgn:1000141",
          "tgn:7029392"
        ],
        "placetype": [
          "aat:300008347"
        ],
        "id": 7471050,
        "name:xx": "Xinjie"
      }
    },
    {
      "geometry": {
        "type": "Point",
        "coordinates": [
          120.692888,
          23.880573
        ]
      },
      "type": "Feature",
      "properties": {
        "hierarchy": [
          "tgn:7471051",
          "tgn:7488858",
          "tgn:1000004",
          "tgn:1000141",
          "tgn:7029392"
        ],
        "placetype": [
          "aat:300008347"
        ],
        "id": 7471051,
        "name:xx": "Xinjie"
      }
    },
    {
      "geometry": {
        "type": "Point",
        "coordinates": [
          120.422172,
          23.627563
        ]
      },
      "type": "Feature",
      "properties": {
        "hierarchy": [
          "tgn:7471052",
          "tgn:7468018",
          "tgn:1000004",
          "tgn:1000141",
          "tgn:7029392"
        ],
        "placetype": [
          "aat:300008347"
        ],
        "id": 7471052,
        "name:xx": "Xinjie"
      }
    },
    {
      "geometry": {
        "type": "Point",
        "coordinates": [
          120.300275,
          23.58567
        ]
      },
      "type": "Feature",
      "properties": {
        "hierarchy": [
          "tgn:7471053",
          "tgn:1000004",
          "tgn:7001014",
          "tgn:1000141",
          "tgn:7029392"
        ],
        "placetype": [
          "aat:300008347"
        ],
        "id": 7471053,
        "name:xx": "Xinjie"
      }
    },
    {
      "geometry": {
        "type": "Point",
        "coordinates": [
          120.714167,
          22.058889
        ]
      },
      "type": "Feature",
      "properties": {
        "hierarchy": [
          "tgn:7471054",
          "tgn:1000004",
          "tgn:7492971",
          "tgn:1000141",
          "tgn:7029392"
        ],
        "placetype": [
          "aat:300008347"
        ],
        "id": 7471054,
        "name:xx": "Xinjie"
      }
    },
    {
      "geometry": {
        "type": "Point",
        "coordinates": [
          120.486164,
          23.722351
        ]
      },
      "type": "Feature",
      "properties": {
        "hierarchy": [
          "tgn:7471055",
          "tgn:1000004",
          "tgn:7001014",
          "tgn:1000141",
          "tgn:7029392"
        ],
        "placetype": [
          "aat:300008347"
        ],
        "id": 7471055,
        "name:xx": "Xinjizhuang"
      }
    },
    {
      "geometry": {
        "type": "Point",
        "coordinates": [
          120.384722,
          23.264167
        ]
      },
      "type": "Feature",
      "properties": {
        "hierarchy": [
          "tgn:7471056",
          "tgn:1000004",
          "tgn:7490934",
          "tgn:1000141",
          "tgn:7029392"
        ],
        "placetype": [
          "aat:300008347"
        ],
        "id": 7471056,
        "name:xx": "Xinjizhuang"
      }
    },
    {
      "geometry": {
        "type": "Point",
        "coordinates": [
          120.168611,
          23.068333
        ]
      },
      "type": "Feature",
      "properties": {
        "hierarchy": [
          "tgn:7471057",
          "tgn:1000004",
          "tgn:7490934",
          "tgn:1000141",
          "tgn:7029392"
        ],
        "placetype": [
          "aat:300008347"
        ],
        "id": 7471057,
        "name:xx": "Xinjizhuang"
      }
    },
    {
      "geometry": {
        "type": "Point",
        "coordinates": [
          120.429218,
          22.687598
        ]
      },
      "type": "Feature",
      "properties": {
        "hierarchy": [
          "tgn:7471058",
          "tgn:7001004",
          "tgn:1000004",
          "tgn:1000141",
          "tgn:7029392"
        ],
        "placetype": [
          "aat:300000745"
        ],
        "id": 7471058,
        "name:xx": "Xinji"
      }
    },
    {
      "geometry": {
        "type": "Point",
        "coordinates": [
          120.436667,
          23.4125
        ]
      },
      "type": "Feature",
      "properties": {
        "hierarchy": [
          "tgn:7471059",
          "tgn:7468018",
          "tgn:1000004",
          "tgn:1000141",
          "tgn:7029392"
        ],
        "placetype": [
          "aat:300007836"
        ],
        "id": 7471059,
        "name:xx": "Xinjiamao Qiao"
      }
    }
  ]
}
