{
  "geometry": {
    "type": "Point",
    "coordinates": [
      -107.2333,
      36.6333
    ]
  },
  "type": "Feature",
  "properties": {
    "hierarchy": [
      "tgn:2400959",
      "tgn:1000001",
      "tgn:7012149",
      "tgn:2001449",
      "tgn:7007566",
      "tgn:7029392"
    ],
    "placetype": [
      "aat:300008697"
    ],
    "id": 2400959,
    "name:xx": "Horse Spring"
  }
}
