{
  "geometry": {
    "type": "Point",
    "coordinates": [
      -81.8167,
      29.0667
    ]
  },
  "type": "Feature",
  "properties": {
    "hierarchy": [
      "tgn:2495393",
      "tgn:1000001",
      "tgn:7012149",
      "tgn:1002631",
      "tgn:7007240",
      "tgn:7029392"
    ],
    "placetype": [
      "aat:300008680"
    ],
    "id": 2495393,
    "name:xx": "Mary, Lake"
  }
}
