{
  "geometry": {
    "type": "Point",
    "coordinates": [
      -121.7167,
      48.2833
    ]
  },
  "type": "Feature",
  "properties": {
    "hierarchy": [
      "tgn:2707151",
      "tgn:1000001",
      "tgn:7012149",
      "tgn:1002899",
      "tgn:7007920",
      "tgn:7029392"
    ],
    "placetype": [
      "aat:300008347"
    ],
    "id": 2707151,
    "name:xx": "Swede Heaven"
  }
}
