{
  "type": "FeatureCollection",
  "features": [
    {
      "geometry": {
        "type": "Point",
        "coordinates": [
          -70.05,
          -24.45
        ]
      },
      "type": "Feature",
      "properties": {
        "hierarchy": [
          "tgn:7277180",
          "tgn:7016598",
          "tgn:1000049",
          "tgn:1000002",
          "tgn:7029392"
        ],
        "placetype": [
          "aat:300008795"
        ],
        "id": 7277180,
        "name:xx": "Vicuña Mackenna, Cerro"
      }
    },
    {
      "geometry": {
        "type": "Point",
        "coordinates": [
          -69.75,
          -26.55
        ]
      },
      "type": "Feature",
      "properties": {
        "hierarchy": [
          "tgn:7277181",
          "tgn:1001630",
          "tgn:1000049",
          "tgn:1000002",
          "tgn:7029392"
        ],
        "placetype": [
          "aat:300387033"
        ],
        "id": 7277181,
        "name:xx": "Vicuña III"
      }
    },
    {
      "geometry": {
        "type": "Point",
        "coordinates": [
          -69.533333,
          -26.566667
        ]
      },
      "type": "Feature",
      "properties": {
        "hierarchy": [
          "tgn:7277182",
          "tgn:1001630",
          "tgn:1000049",
          "tgn:1000002",
          "tgn:7029392"
        ],
        "placetype": [
          "aat:300008686"
        ],
        "id": 7277182,
        "name:xx": "Vicuña, Vegas del"
      }
    },
    {
      "geometry": {
        "type": "Point",
        "coordinates": [
          -69.266667,
          -26.066667
        ]
      },
      "type": "Feature",
      "properties": {
        "hierarchy": [
          "tgn:7277183",
          "tgn:1001630",
          "tgn:1000049",
          "tgn:1000002",
          "tgn:7029392"
        ],
        "placetype": [
          "aat:300008686"
        ],
        "id": 7277183,
        "name:xx": "Vicuña, Vegas de"
      }
    },
    {
      "geometry": {
        "type": "Point",
        "coordinates": [
          -69.416667,
          -26.366667
        ]
      },
      "type": "Feature",
      "properties": {
        "hierarchy": [
          "tgn:7277184",
          "tgn:1001630",
          "tgn:1000049",
          "tgn:1000002",
          "tgn:7029392"
        ],
        "placetype": [
          "aat:300008699"
        ],
        "id": 7277184,
        "name:xx": "Vicuña, Quebrada"
      }
    },
    {
      "geometry": {
        "type": "Point",
        "coordinates": [
          -69.583333,
          -26.616667
        ]
      },
      "type": "Feature",
      "properties": {
        "hierarchy": [
          "tgn:7277185",
          "tgn:1001630",
          "tgn:1000049",
          "tgn:1000002",
          "tgn:7029392"
        ],
        "placetype": [
          "aat:300259572"
        ],
        "id": 7277185,
        "name:xx": "Vicuña, Portezuelo de"
      }
    },
    {
      "geometry": {
        "type": "Point",
        "coordinates": [
          -68.8,
          -20.816667
        ]
      },
      "type": "Feature",
      "properties": {
        "hierarchy": [
          "tgn:7277186",
          "tgn:7002464",
          "tgn:1000049",
          "tgn:1000002",
          "tgn:7029392"
        ],
        "placetype": [
          "aat:300008795"
        ],
        "id": 7277186,
        "name:xx": "Vicuña, Morro"
      }
    },
    {
      "geometry": {
        "type": "Point",
        "coordinates": [
          -68.8,
          -20.8
        ]
      },
      "type": "Feature",
      "properties": {
        "hierarchy": [
          "tgn:7277187",
          "tgn:7002464",
          "tgn:1000049",
          "tgn:1000002",
          "tgn:7029392"
        ],
        "placetype": [
          "aat:300008777"
        ],
        "id": 7277187,
        "name:xx": "Vicuña, Monte"
      }
    },
    {
      "geometry": {
        "type": "Point",
        "coordinates": [
          -71.05,
          -33.883333
        ]
      },
      "type": "Feature",
      "properties": {
        "hierarchy": [
          "tgn:7277188",
          "tgn:1001708",
          "tgn:1000049",
          "tgn:1000002",
          "tgn:7029392"
        ],
        "placetype": [
          "aat:300387002"
        ],
        "id": 7277188,
        "name:xx": "Vicuña, Loma de"
      }
    },
    {
      "geometry": {
        "type": "Point",
        "coordinates": [
          -68.783333,
          -54.133333
        ]
      },
      "type": "Feature",
      "properties": {
        "hierarchy": [
          "tgn:7277189",
          "tgn:1001702",
          "tgn:1000049",
          "tgn:1000002",
          "tgn:7029392"
        ],
        "placetype": [
          "aat:300000241"
        ],
        "id": 7277189,
        "name:xx": "Estancia Vicuña"
      }
    }
  ]
}
