{
  "type": "FeatureCollection",
  "features": [
    {
      "geometry": {
        "type": "Point",
        "coordinates": [
          77.516667,
          10.6
        ]
      },
      "type": "Feature",
      "properties": {
        "hierarchy": [
          "tgn:7574640",
          "tgn:1000004",
          "tgn:7000198",
          "tgn:7001797",
          "tgn:7029392"
        ],
        "placetype": [
          "aat:300008347"
        ],
        "name:en": "Kīranūr",
        "id": 7574640
      }
    },
    {
      "geometry": {
        "type": "Point",
        "coordinates": [
          78.783333,
          10.566667
        ]
      },
      "type": "Feature",
      "properties": {
        "hierarchy": [
          "tgn:7574641",
          "tgn:1000004",
          "tgn:7000198",
          "tgn:7001797",
          "tgn:7029392"
        ],
        "placetype": [
          "aat:300008347"
        ],
        "name:en": "Kīranūr",
        "id": 7574641
      }
    },
    {
      "geometry": {
        "type": "Point",
        "coordinates": [
          81.283333,
          18.7
        ]
      },
      "type": "Feature",
      "properties": {
        "hierarchy": [
          "tgn:7574642",
          "tgn:1000004",
          "tgn:7031781",
          "tgn:7000198",
          "tgn:7029392"
        ],
        "placetype": [
          "aat:300007783"
        ],
        "name:en": "Kirandul",
        "id": 7574642
      }
    },
    {
      "geometry": {
        "type": "Point",
        "coordinates": [
          78.116667,
          11.2
        ]
      },
      "type": "Feature",
      "properties": {
        "hierarchy": [
          "tgn:7574643",
          "tgn:1000004",
          "tgn:7000198",
          "tgn:7001797",
          "tgn:7029392"
        ],
        "placetype": [
          "aat:300008347"
        ],
        "name:en": "Kīrambūr",
        "id": 7574643
      }
    },
    {
      "geometry": {
        "type": "Point",
        "coordinates": [
          82.916052,
          25.636981
        ]
      },
      "type": "Feature",
      "properties": {
        "hierarchy": [
          "tgn:7574644",
          "tgn:1000004",
          "tgn:7000198",
          "tgn:7016722",
          "tgn:7029392"
        ],
        "placetype": [
          "aat:300008347"
        ],
        "name:en": "Kirākat",
        "id": 7574644
      }
    },
    {
      "geometry": {
        "type": "Point",
        "coordinates": [
          80.233333,
          30.7
        ]
      },
      "type": "Feature",
      "properties": {
        "hierarchy": [
          "tgn:7574645",
          "tgn:1000004",
          "tgn:7000198",
          "tgn:7031786",
          "tgn:7029392"
        ],
        "placetype": [
          "aat:300259572"
        ],
        "name:en": "Kiogād Pass",
        "id": 7574645
      }
    },
    {
      "geometry": {
        "type": "Point",
        "coordinates": [
          78.2,
          19.633333
        ]
      },
      "type": "Feature",
      "properties": {
        "hierarchy": [
          "tgn:7574646",
          "tgn:1000004",
          "tgn:7000198",
          "tgn:1001895",
          "tgn:7029392"
        ],
        "placetype": [
          "aat:300008347"
        ],
        "name:en": "Kinwat",
        "id": 7574646
      }
    },
    {
      "geometry": {
        "type": "Point",
        "coordinates": [
          75.033333,
          14.866667
        ]
      },
      "type": "Feature",
      "properties": {
        "hierarchy": [
          "tgn:7574648",
          "tgn:1000004",
          "tgn:7000198",
          "tgn:1001882",
          "tgn:7029392"
        ],
        "placetype": [
          "aat:300008347"
        ],
        "name:en": "Kātūr",
        "id": 7574648
      }
    },
    {
      "geometry": {
        "type": "Point",
        "coordinates": [
          87.77636,
          25.628659
        ]
      },
      "type": "Feature",
      "properties": {
        "hierarchy": [
          "tgn:7574649",
          "tgn:1000004",
          "tgn:1001842",
          "tgn:7000198",
          "tgn:7029392"
        ],
        "placetype": [
          "aat:300008699"
        ],
        "name:en": "Katua Nadī",
        "id": 7574649
      }
    }
  ]
}
