{
  "geometry": {
    "type": "Point",
    "coordinates": [
      55.2833,
      -21.0333
    ]
  },
  "type": "Feature",
  "properties": {
    "hierarchy": [
      "tgn:7032258",
      "tgn:7001680",
      "tgn:7001242",
      "tgn:1000184",
      "tgn:7029392"
    ],
    "placetype": [
      "aat:300008699"
    ],
    "name:fr": "Saint-Gilles, Bras",
    "id": 7032258
  }
}
