{
  "geometry": {
    "type": "Point",
    "coordinates": [
      -110.1667,
      34.6167
    ]
  },
  "type": "Feature",
  "properties": {
    "hierarchy": [
      "tgn:2701665",
      "tgn:1000001",
      "tgn:7006451",
      "tgn:7012149",
      "tgn:2000099",
      "tgn:7029392"
    ],
    "placetype": [
      "aat:300008798"
    ],
    "id": 2701665,
    "name:xx": "Sugarloaf"
  }
}
