{
  "geometry": {
    "type": "Point",
    "coordinates": [
      -108.9667,
      35.5833
    ]
  },
  "type": "Feature",
  "properties": {
    "hierarchy": [
      "tgn:2725897",
      "tgn:1000001",
      "tgn:7012149",
      "tgn:7019676",
      "tgn:7007566",
      "tgn:7029392"
    ],
    "placetype": [
      "aat:300266640"
    ],
    "id": 2725897,
    "name:xx": "Torrivio Ridge"
  }
}
