{
  "geometry": {
    "type": "Point",
    "coordinates": [
      94.3167,
      38.9667
    ]
  },
  "type": "Feature",
  "properties": {
    "hierarchy": [
      "tgn:1066609",
      "tgn:1000004",
      "tgn:7002088",
      "tgn:1000111",
      "tgn:7029392"
    ],
    "placetype": [
      "aat:300008347"
    ],
    "id": 1066609,
    "name:xx": "Bag Narin"
  }
}
