{
  "geometry": {
    "type": "Point",
    "coordinates": [
      79.9172,
      27.0767
    ]
  },
  "type": "Feature",
  "properties": {
    "hierarchy": [
      "tgn:7563289",
      "tgn:1000004",
      "tgn:7000198",
      "tgn:7016722",
      "tgn:7029392"
    ],
    "placetype": [
      "aat:300008347"
    ],
    "name:en": "Chintāman Purwa",
    "id": 7563289
  }
}
