{
  "type": "FeatureCollection",
  "features": [
    {
      "geometry": {
        "type": "Point",
        "coordinates": [
          -8.9,
          43.066667
        ]
      },
      "type": "Feature",
      "properties": {
        "hierarchy": [
          "tgn:7335170",
          "tgn:7002824",
          "tgn:1000003",
          "tgn:7002786",
          "tgn:1000095",
          "tgn:7029392"
        ],
        "placetype": [
          "aat:300008347"
        ],
        "id": 7335170,
        "name:xx": "Froján"
      }
    },
    {
      "geometry": {
        "type": "Point",
        "coordinates": [
          -7.25,
          42.55
        ]
      },
      "type": "Feature",
      "properties": {
        "hierarchy": [
          "tgn:7335171",
          "tgn:7002829",
          "tgn:1000003",
          "tgn:7002786",
          "tgn:1000095",
          "tgn:7029392"
        ],
        "placetype": [
          "aat:300008347"
        ],
        "id": 7335171,
        "name:xx": "Froján"
      }
    },
    {
      "geometry": {
        "type": "Point",
        "coordinates": [
          -7.533333,
          42.816667
        ]
      },
      "type": "Feature",
      "properties": {
        "hierarchy": [
          "tgn:7335172",
          "tgn:7002829",
          "tgn:1000003",
          "tgn:7002786",
          "tgn:1000095",
          "tgn:7029392"
        ],
        "placetype": [
          "aat:300008347"
        ],
        "id": 7335172,
        "name:xx": "Friolfe"
      }
    },
    {
      "geometry": {
        "type": "Point",
        "coordinates": [
          -7.783333,
          43.033333
        ]
      },
      "type": "Feature",
      "properties": {
        "hierarchy": [
          "tgn:7335173",
          "tgn:7002829",
          "tgn:1000003",
          "tgn:7002786",
          "tgn:1000095",
          "tgn:7029392"
        ],
        "placetype": [
          "aat:300008347"
        ],
        "id": 7335173,
        "name:xx": "Friol"
      }
    },
    {
      "geometry": {
        "type": "Point",
        "coordinates": [
          -4.65,
          43.1
        ]
      },
      "type": "Feature",
      "properties": {
        "hierarchy": [
          "tgn:7335174",
          "tgn:7002760",
          "tgn:1000003",
          "tgn:1000095",
          "tgn:7029392"
        ],
        "placetype": [
          "aat:300008699"
        ],
        "id": 7335174,
        "name:xx": "Frío, Río"
      }
    },
    {
      "geometry": {
        "type": "Point",
        "coordinates": [
          -2.966667,
          42.083333
        ]
      },
      "type": "Feature",
      "properties": {
        "hierarchy": [
          "tgn:7335175",
          "tgn:7002810",
          "tgn:7001158",
          "tgn:1000003",
          "tgn:1000095",
          "tgn:7029392"
        ],
        "placetype": [
          "aat:300008699"
        ],
        "id": 7335175,
        "name:xx": "Frío, Río"
      }
    },
    {
      "geometry": {
        "type": "Point",
        "coordinates": [
          -4.183333,
          40.9
        ]
      },
      "type": "Feature",
      "properties": {
        "hierarchy": [
          "tgn:7335176",
          "tgn:7002839",
          "tgn:7001158",
          "tgn:1000003",
          "tgn:1000095",
          "tgn:7029392"
        ],
        "placetype": [
          "aat:300008699"
        ],
        "id": 7335176,
        "name:xx": "Frío, Río"
      }
    },
    {
      "geometry": {
        "type": "Point",
        "coordinates": [
          -6.666667,
          40.35
        ]
      },
      "type": "Feature",
      "properties": {
        "hierarchy": [
          "tgn:7335177",
          "tgn:7002835",
          "tgn:7001158",
          "tgn:1000003",
          "tgn:1000095",
          "tgn:7029392"
        ],
        "placetype": [
          "aat:300008699"
        ],
        "id": 7335177,
        "name:xx": "Frío, Río"
      }
    },
    {
      "geometry": {
        "type": "Point",
        "coordinates": [
          -4.683333,
          39.383333
        ]
      },
      "type": "Feature",
      "properties": {
        "hierarchy": [
          "tgn:7335178",
          "tgn:7002807",
          "tgn:1000003",
          "tgn:7003837",
          "tgn:1000095",
          "tgn:7029392"
        ],
        "placetype": [
          "aat:300008699"
        ],
        "id": 7335178,
        "name:xx": "Frío, Río"
      }
    },
    {
      "geometry": {
        "type": "Point",
        "coordinates": [
          -4.466667,
          39.033333
        ]
      },
      "type": "Feature",
      "properties": {
        "hierarchy": [
          "tgn:7335179",
          "tgn:7002816",
          "tgn:1001647",
          "tgn:1000003",
          "tgn:1000095",
          "tgn:7029392"
        ],
        "placetype": [
          "aat:300008699"
        ],
        "id": 7335179,
        "name:xx": "Frío, Río"
      }
    }
  ]
}
