{
  "geometry": {
    "type": "Point",
    "coordinates": [
      -108.2333,
      39.3333
    ]
  },
  "type": "Feature",
  "properties": {
    "hierarchy": [
      "tgn:2615245",
      "tgn:1000001",
      "tgn:7012149",
      "tgn:7007158",
      "tgn:7029392"
    ],
    "placetype": [
      "aat:300006075"
    ],
    "id": 2615245,
    "name:xx": "Reservoir Ditch"
  }
}
