{
  "geometry": {
    "type": "Point",
    "coordinates": [
      -108.55,
      39.7833
    ]
  },
  "type": "Feature",
  "properties": {
    "hierarchy": [
      "tgn:2634890",
      "tgn:1000001",
      "tgn:7012149",
      "tgn:7007158",
      "tgn:2000243",
      "tgn:7029392"
    ],
    "placetype": [
      "aat:300008761"
    ],
    "id": 2634890,
    "name:xx": "Ryan Gulch"
  }
}
