{
  "geometry": {
    "type": "Point",
    "coordinates": [
      -95.0833,
      43.7333
    ]
  },
  "type": "Feature",
  "properties": {
    "hierarchy": [
      "tgn:2428347",
      "tgn:1000001",
      "tgn:7012149",
      "tgn:2001030",
      "tgn:7007521",
      "tgn:7029392"
    ],
    "placetype": [
      "aat:300006075"
    ],
    "id": 2428347,
    "name:xx": "Judicial Ditch Number Thirtyseven"
  }
}
