{
  "geometry": {
    "type": "Point",
    "coordinates": [
      -85.7833,
      39.55
    ]
  },
  "type": "Feature",
  "properties": {
    "hierarchy": [
      "tgn:2031279",
      "tgn:1000001",
      "tgn:7012149",
      "tgn:1002886",
      "tgn:7007252",
      "tgn:7029392"
    ],
    "placetype": [
      "aat:300008347"
    ],
    "id": 2031279,
    "name:xx": "Candleglo Village"
  }
}
