{
  "geometry": {
    "type": "Point",
    "coordinates": [
      -89.5667,
      46.5667
    ]
  },
  "type": "Feature",
  "properties": {
    "hierarchy": [
      "tgn:2163973",
      "tgn:1000001",
      "tgn:7012149",
      "tgn:2000986",
      "tgn:7007520",
      "tgn:7029392"
    ],
    "placetype": [
      "aat:300132316"
    ],
    "id": 2163973,
    "name:xx": "Bergland Bay"
  }
}
