{
  "geometry": {
    "type": "Point",
    "coordinates": [
      29.3833,
      -28.3667
    ]
  },
  "type": "Feature",
  "properties": {
    "hierarchy": [
      "tgn:1093733",
      "tgn:7001242",
      "tgn:7016749",
      "tgn:1000193",
      "tgn:7029392"
    ],
    "placetype": [
      "aat:300008347"
    ],
    "id": 1093733,
    "name:xx": "Van Reenen"
  }
}
