{
  "geometry": {
    "type": "Point",
    "coordinates": [
      -65.4333,
      44.7333
    ]
  },
  "type": "Feature",
  "properties": {
    "hierarchy": [
      "tgn:1101983",
      "tgn:7005685",
      "tgn:1000001",
      "tgn:7005802",
      "tgn:7029392"
    ],
    "placetype": [
      "aat:300386977"
    ],
    "id": 1101983,
    "name:xx": "Fort Anne National Historic Park"
  }
}
