{
  "geometry": {
    "type": "Point",
    "coordinates": [
      -77.9167,
      33.9833
    ]
  },
  "type": "Feature",
  "properties": {
    "hierarchy": [
      "tgn:2577339",
      "tgn:1000001",
      "tgn:7012149",
      "tgn:2001523",
      "tgn:7007709",
      "tgn:7029392"
    ],
    "placetype": [
      "aat:300008850"
    ],
    "id": 2577339,
    "name:xx": "Peters Point"
  }
}
