{
  "geometry": {
    "type": "Point",
    "coordinates": [
      -105.8833,
      39.4667
    ]
  },
  "type": "Feature",
  "properties": {
    "hierarchy": [
      "tgn:2518285",
      "tgn:1000001",
      "tgn:7012149",
      "tgn:7007158",
      "tgn:2000250",
      "tgn:7029392"
    ],
    "placetype": [
      "aat:300008761"
    ],
    "id": 2518285,
    "name:xx": "Missouri Gulch"
  }
}
