{
  "geometry": {
    "type": "Point",
    "coordinates": [
      -76.1667,
      38.4833
    ]
  },
  "type": "Feature",
  "properties": {
    "hierarchy": [
      "tgn:2239395",
      "tgn:1002338",
      "tgn:1000001",
      "tgn:7012149",
      "tgn:7007516",
      "tgn:7029392"
    ],
    "placetype": [
      "aat:300008706"
    ],
    "id": 2239395,
    "name:xx": "Church Creek"
  }
}
