{
  "geometry": {
    "type": "Point",
    "coordinates": [
      -83.05,
      37.0333
    ]
  },
  "type": "Feature",
  "properties": {
    "hierarchy": [
      "tgn:2732628",
      "tgn:1000001",
      "tgn:7012149",
      "tgn:2000812",
      "tgn:7007255",
      "tgn:7029392"
    ],
    "placetype": [
      "aat:300008706"
    ],
    "id": 2732628,
    "name:xx": "Turkey Creek"
  }
}
