{
  "type": "FeatureCollection",
  "features": [
    {
      "geometry": {
        "type": "Point",
        "coordinates": [
          6.75,
          51.2
        ]
      },
      "type": "Feature",
      "properties": {
        "hierarchy": [
          "tgn:1004601",
          "tgn:1000003",
          "tgn:7003677",
          "tgn:7000084",
          "tgn:7004443",
          "tgn:7029392"
        ],
        "placetype": [
          "aat:300000745",
          "aat:300387332"
        ],
        "id": 1004601,
        "name:xx": "Hamm"
      }
    },
    {
      "geometry": {
        "type": "Point",
        "coordinates": [
          -0.2333,
          51.5
        ]
      },
      "type": "Feature",
      "properties": {
        "hierarchy": [
          "tgn:1004602",
          "tgn:7002445",
          "tgn:7018900",
          "tgn:7011781",
          "tgn:1000003",
          "tgn:7008136",
          "tgn:7008591",
          "tgn:7029392"
        ],
        "placetype": [
          "aat:300008347",
          "aat:300000745",
          "aat:300387220"
        ],
        "name:en": "Hammersmith",
        "id": 1004602
      }
    },
    {
      "geometry": {
        "type": "Point",
        "coordinates": [
          -0.083333,
          51.583333
        ]
      },
      "type": "Feature",
      "properties": {
        "hierarchy": [
          "tgn:1004609",
          "tgn:7002445",
          "tgn:7018917",
          "tgn:1000003",
          "tgn:7008136",
          "tgn:7008591",
          "tgn:7029392"
        ],
        "placetype": [
          "aat:300000745"
        ],
        "name:en": "Haringey",
        "id": 1004609
      }
    }
  ]
}
