{
  "geometry": {
    "type": "Point",
    "coordinates": [
      -111.95,
      43.45
    ]
  },
  "type": "Feature",
  "properties": {
    "hierarchy": [
      "tgn:1110975",
      "tgn:1000001",
      "tgn:2000461",
      "tgn:7012149",
      "tgn:7007250",
      "tgn:7029392"
    ],
    "placetype": [
      "aat:300008805"
    ],
    "id": 1110975,
    "name:xx": "Snake River Plain"
  }
}
