{
  "geometry": {
    "type": "Point",
    "coordinates": [
      -89.6333,
      46.5667
    ]
  },
  "type": "Feature",
  "properties": {
    "hierarchy": [
      "tgn:7023653",
      "tgn:1000001",
      "tgn:7012149",
      "tgn:7007520",
      "tgn:7029392"
    ],
    "placetype": [
      "aat:300008680"
    ],
    "id": 7023653,
    "name:xx": "Pendock Pond"
  }
}
