{
  "geometry": {
    "type": "Point",
    "coordinates": [
      77.980278,
      30.4875
    ]
  },
  "type": "Feature",
  "properties": {
    "hierarchy": [
      "tgn:7590995",
      "tgn:1000004",
      "tgn:7000198",
      "tgn:7031786",
      "tgn:7029392"
    ],
    "placetype": [
      "aat:300008347"
    ],
    "name:en": "Sartāll",
    "id": 7590995
  }
}
