{
  "geometry": {
    "type": "Point",
    "coordinates": [
      -107.6667,
      48.9833
    ]
  },
  "type": "Feature",
  "properties": {
    "hierarchy": [
      "tgn:2747899",
      "tgn:1000001",
      "tgn:7012149",
      "tgn:2001295",
      "tgn:7007524",
      "tgn:7029392"
    ],
    "placetype": [
      "aat:300008697"
    ],
    "id": 2747899,
    "name:xx": "Walchuk Spring"
  }
}
