{
  "geometry": {
    "type": "Point",
    "coordinates": [
      33.915278,
      29.357778
    ]
  },
  "type": "Feature",
  "properties": {
    "hierarchy": [
      "tgn:7543929",
      "tgn:7001242",
      "tgn:7016833",
      "tgn:7001336",
      "tgn:7029392"
    ],
    "placetype": [
      "aat:300379998"
    ],
    "id": 7543929,
    "name:xx": "Wad카훮t, W훮d카 al"
  }
}
