{
  "type": "FeatureCollection",
  "features": [
    {
      "geometry": {
        "type": "Point",
        "coordinates": [
          -111.6833,
          38.9667
        ]
      },
      "type": "Feature",
      "properties": {
        "hierarchy": [
          "tgn:2694380",
          "tgn:1000001",
          "tgn:7012149",
          "tgn:2002121",
          "tgn:7007827",
          "tgn:7029392"
        ],
        "placetype": [
          "aat:300008761"
        ],
        "id": 2694380,
        "name:xx": "Steves Wash"
      }
    },
    {
      "geometry": {
        "type": "Point",
        "coordinates": [
          -86.4833,
          30.8
        ]
      },
      "type": "Feature",
      "properties": {
        "hierarchy": [
          "tgn:2694381",
          "tgn:1000001",
          "tgn:7012149",
          "tgn:2000281",
          "tgn:7007240",
          "tgn:7029392"
        ],
        "placetype": [
          "aat:300008699"
        ],
        "id": 2694381,
        "name:xx": "Steves Wash Branch"
      }
    },
    {
      "geometry": {
        "type": "Point",
        "coordinates": [
          -117.5167,
          46.6833
        ]
      },
      "type": "Feature",
      "properties": {
        "hierarchy": [
          "tgn:2694382",
          "tgn:1000001",
          "tgn:7012149",
          "tgn:2002252",
          "tgn:7007920",
          "tgn:7029392"
        ],
        "placetype": [
          "aat:300008761"
        ],
        "id": 2694382,
        "name:xx": "Stevick Canyon"
      }
    },
    {
      "geometry": {
        "type": "Point",
        "coordinates": [
          -107.6667,
          45.1
        ]
      },
      "type": "Feature",
      "properties": {
        "hierarchy": [
          "tgn:2694383",
          "tgn:1000001",
          "tgn:2001261",
          "tgn:7012149",
          "tgn:7007524",
          "tgn:7029392"
        ],
        "placetype": [
          "aat:300008706"
        ],
        "id": 2694383,
        "name:xx": "Stevie Creek"
      }
    },
    {
      "geometry": {
        "type": "Point",
        "coordinates": [
          -106.6,
          41.85
        ]
      },
      "type": "Feature",
      "properties": {
        "hierarchy": [
          "tgn:2694386",
          "tgn:1000001",
          "tgn:2002368",
          "tgn:7012149",
          "tgn:7007923",
          "tgn:7029392"
        ],
        "placetype": [
          "aat:300006191"
        ],
        "id": 2694386,
        "name:xx": "Stevies Lake"
      }
    },
    {
      "geometry": {
        "type": "Point",
        "coordinates": [
          -120.8833,
          37.3667
        ]
      },
      "type": "Feature",
      "properties": {
        "hierarchy": [
          "tgn:2694387",
          "tgn:1000001",
          "tgn:7012149",
          "tgn:7007157",
          "tgn:1002656",
          "tgn:7029392"
        ],
        "placetype": [
          "aat:300006075"
        ],
        "id": 2694387,
        "name:xx": "Stevinson Lower Lateral"
      }
    },
    {
      "geometry": {
        "type": "Point",
        "coordinates": [
          -120.8833,
          37.4
        ]
      },
      "type": "Feature",
      "properties": {
        "hierarchy": [
          "tgn:2694388",
          "tgn:1000001",
          "tgn:7012149",
          "tgn:7007157",
          "tgn:1002656",
          "tgn:7029392"
        ],
        "placetype": [
          "aat:300006075"
        ],
        "id": 2694388,
        "name:xx": "Stevinson Upper Lateral"
      }
    },
    {
      "geometry": {
        "type": "Point",
        "coordinates": [
          -89.0167,
          46.65
        ]
      },
      "type": "Feature",
      "properties": {
        "hierarchy": [
          "tgn:2694389",
          "tgn:1000001",
          "tgn:7012149",
          "tgn:2000986",
          "tgn:7007520",
          "tgn:7029392"
        ],
        "placetype": [
          "aat:300008706"
        ],
        "id": 2694389,
        "name:xx": "Stew Creek"
      }
    }
  ]
}
