{
  "geometry": {
    "type": "Point",
    "coordinates": [
      -77.1333,
      38.8333
    ]
  },
  "type": "Feature",
  "properties": {
    "hierarchy": [
      "tgn:1119428",
      "tgn:1000001",
      "tgn:7012149",
      "tgn:7014160",
      "tgn:7007919",
      "tgn:7029392"
    ],
    "placetype": [
      "aat:300006191"
    ],
    "id": 1119428,
    "name:xx": "Barcroft, Lake"
  }
}
