{
  "geometry": {
    "type": "Point",
    "coordinates": [
      33.40754,
      29.12078
    ]
  },
  "type": "Feature",
  "properties": {
    "hierarchy": [
      "tgn:7538777",
      "tgn:7001242",
      "tgn:7016833",
      "tgn:7001336",
      "tgn:7029392"
    ],
    "placetype": [
      "aat:300379998"
    ],
    "id": 7538777,
    "name:xx": "Ruwaykinah, Wādī"
  }
}
