{
  "geometry": {
    "type": "Point",
    "coordinates": [
      -79.1667,
      39.7833
    ]
  },
  "type": "Feature",
  "properties": {
    "hierarchy": [
      "tgn:2151979",
      "tgn:1000001",
      "tgn:7012149",
      "tgn:1002904",
      "tgn:7007710",
      "tgn:7029392"
    ],
    "placetype": [
      "aat:300008798"
    ],
    "id": 2151979,
    "name:xx": "Baughman Rocks"
  }
}
