{
  "geometry": {
    "type": "Point",
    "coordinates": [
      74.863889,
      32.677778
    ]
  },
  "type": "Feature",
  "properties": {
    "hierarchy": [
      "tgn:7591773",
      "tgn:1000004",
      "tgn:7000198",
      "tgn:7000799",
      "tgn:7029392"
    ],
    "placetype": [
      "aat:300000517"
    ],
    "name:en": "Dangīāna Camp",
    "id": 7591773
  }
}
