{
  "geometry": {
    "type": "Point",
    "coordinates": [
      -85.5167,
      34.85
    ]
  },
  "type": "Feature",
  "properties": {
    "hierarchy": [
      "tgn:2726497",
      "tgn:1000001",
      "tgn:7012149",
      "tgn:2000332",
      "tgn:7007248",
      "tgn:7029392"
    ],
    "placetype": [
      "aat:300008706"
    ],
    "id": 2726497,
    "name:xx": "Town Creek"
  }
}
