{
  "geometry": {
    "type": "Point",
    "coordinates": [
      -121.75,
      46.8167
    ]
  },
  "type": "Feature",
  "properties": {
    "hierarchy": [
      "tgn:2750551",
      "tgn:1000001",
      "tgn:7012149",
      "tgn:1002785",
      "tgn:7007920",
      "tgn:7029392"
    ],
    "placetype": [
      "aat:300266640"
    ],
    "id": 2750551,
    "name:xx": "Wapowety Cleaver"
  }
}
