{
  "geometry": {
    "type": "Point",
    "coordinates": [
      -95.8167,
      47.3333
    ]
  },
  "type": "Feature",
  "properties": {
    "hierarchy": [
      "tgn:2001042",
      "tgn:1000001",
      "tgn:7012149",
      "tgn:7007521",
      "tgn:7029392"
    ],
    "placetype": [
      "aat:300387145",
      "aat:300000771"
    ],
    "id": 2001042,
    "name:xx": "Mahnomen"
  }
}
