{
  "geometry": {
    "type": "Point",
    "coordinates": [
      77.461221,
      25.797922
    ]
  },
  "type": "Feature",
  "properties": {
    "hierarchy": [
      "tgn:7550369",
      "tgn:1000004",
      "tgn:7000198",
      "tgn:1001894",
      "tgn:7029392"
    ],
    "placetype": [
      "aat:300008347"
    ],
    "name:en": "Dhoriā",
    "id": 7550369
  }
}
