{
  "geometry": {
    "type": "Point",
    "coordinates": [
      27.642425,
      30.31717
    ]
  },
  "type": "Feature",
  "properties": {
    "hierarchy": [
      "tgn:7520529",
      "tgn:7001242",
      "tgn:7016833",
      "tgn:1001418",
      "tgn:7029392"
    ],
    "placetype": [
      "aat:300008749"
    ],
    "name:en": "Abū Ţurţūr, Minqār",
    "id": 7520529
  }
}
