{
  "geometry": {
    "type": "Point",
    "coordinates": [
      -104.8833,
      40.4833
    ]
  },
  "type": "Feature",
  "properties": {
    "hierarchy": [
      "tgn:2776851",
      "tgn:1000001",
      "tgn:7012149",
      "tgn:7007158",
      "tgn:2000253",
      "tgn:7029392"
    ],
    "placetype": [
      "aat:300006191"
    ],
    "id": 2776851,
    "name:xx": "Windsor Lake Reservoir"
  }
}
