{
  "type": "FeatureCollection",
  "features": [
    {
      "geometry": {
        "type": "Point",
        "coordinates": [
          -91.6333,
          35.9
        ]
      },
      "type": "Feature",
      "properties": {
        "hierarchy": [
          "tgn:2009450",
          "tgn:1000001",
          "tgn:7016172",
          "tgn:7012149",
          "tgn:2000136",
          "tgn:7029392"
        ],
        "placetype": [
          "aat:300008347",
          "aat:300387210"
        ],
        "id": 2009450,
        "name:xx": "Sandtown"
      }
    },
    {
      "geometry": {
        "type": "Point",
        "coordinates": [
          -92.1,
          33.4833
        ]
      },
      "type": "Feature",
      "properties": {
        "hierarchy": [
          "tgn:2009451",
          "tgn:1000001",
          "tgn:7016172",
          "tgn:2000110",
          "tgn:7012149",
          "tgn:7029392"
        ],
        "placetype": [
          "aat:300387016"
        ],
        "id": 2009451,
        "name:xx": "Sandtuck"
      }
    },
    {
      "geometry": {
        "type": "Point",
        "coordinates": [
          -92.4,
          33.1167
        ]
      },
      "type": "Feature",
      "properties": {
        "hierarchy": [
          "tgn:2009452",
          "tgn:1000001",
          "tgn:7016172",
          "tgn:7012149",
          "tgn:2000174",
          "tgn:7029392"
        ],
        "placetype": [
          "aat:300008347",
          "aat:300387210"
        ],
        "id": 2009452,
        "name:xx": "Sandy Bend"
      }
    },
    {
      "geometry": {
        "type": "Point",
        "coordinates": [
          -93.8833,
          33.7667
        ]
      },
      "type": "Feature",
      "properties": {
        "hierarchy": [
          "tgn:2009455",
          "tgn:1000001",
          "tgn:7016172",
          "tgn:7012149",
          "tgn:2000135",
          "tgn:7029392"
        ],
        "placetype": [
          "aat:300008347"
        ],
        "id": 2009455,
        "name:xx": "Saratoga"
      }
    },
    {
      "geometry": {
        "type": "Point",
        "coordinates": [
          -92.4,
          34.5167
        ]
      },
      "type": "Feature",
      "properties": {
        "hierarchy": [
          "tgn:2009456",
          "tgn:1000001",
          "tgn:7016172",
          "tgn:7012149",
          "tgn:2000167",
          "tgn:7029392"
        ],
        "placetype": [
          "aat:300008347",
          "aat:300387210"
        ],
        "id": 2009456,
        "name:xx": "Sardis"
      }
    },
    {
      "geometry": {
        "type": "Point",
        "coordinates": [
          -94.3167,
          36.1
        ]
      },
      "type": "Feature",
      "properties": {
        "hierarchy": [
          "tgn:2009457",
          "tgn:1000001",
          "tgn:7016172",
          "tgn:7012149",
          "tgn:2000176",
          "tgn:7029392"
        ],
        "placetype": [
          "aat:300008347"
        ],
        "id": 2009457,
        "name:xx": "Savoy"
      }
    },
    {
      "geometry": {
        "type": "Point",
        "coordinates": [
          -93.95,
          33.8167
        ]
      },
      "type": "Feature",
      "properties": {
        "hierarchy": [
          "tgn:2009458",
          "tgn:1000001",
          "tgn:7016172",
          "tgn:7012149",
          "tgn:2000135",
          "tgn:7029392"
        ],
        "placetype": [
          "aat:300008347",
          "aat:300387210"
        ],
        "id": 2009458,
        "name:xx": "Schaal"
      }
    },
    {
      "geometry": {
        "type": "Point",
        "coordinates": [
          -94.1667,
          35.7167
        ]
      },
      "type": "Feature",
      "properties": {
        "hierarchy": [
          "tgn:2009459",
          "tgn:1000001",
          "tgn:7016172",
          "tgn:2000121",
          "tgn:7012149",
          "tgn:7029392"
        ],
        "placetype": [
          "aat:300008347",
          "aat:300387210"
        ],
        "id": 2009459,
        "name:xx": "Schaberg"
      }
    }
  ]
}
