{
  "geometry": {
    "type": "Point",
    "coordinates": [
      -61.6167,
      15.8667
    ]
  },
  "type": "Feature",
  "properties": {
    "hierarchy": [
      "tgn:1010257",
      "tgn:7018312",
      "tgn:1000001",
      "tgn:7004545",
      "tgn:7029392"
    ],
    "placetype": [
      "aat:300386853"
    ],
    "id": 1010257,
    "name:xx": "Saintes, Îles des"
  }
}
