{
  "type": "FeatureCollection",
  "features": [
    {
      "geometry": {
        "type": "Point",
        "coordinates": [
          -71.866667,
          -35.183333
        ]
      },
      "type": "Feature",
      "properties": {
        "hierarchy": [
          "tgn:7311930",
          "tgn:1001705",
          "tgn:1000049",
          "tgn:1000002",
          "tgn:7029392"
        ],
        "placetype": [
          "aat:300008347"
        ],
        "id": 7311930,
        "name:xx": "Las Juntas"
      }
    },
    {
      "geometry": {
        "type": "Point",
        "coordinates": [
          -70.866667,
          -30.716667
        ]
      },
      "type": "Feature",
      "properties": {
        "hierarchy": [
          "tgn:7311931",
          "tgn:1001657",
          "tgn:1000049",
          "tgn:1000002",
          "tgn:7029392"
        ],
        "placetype": [
          "aat:300008347"
        ],
        "id": 7311931,
        "name:xx": "Las Juntas"
      }
    },
    {
      "geometry": {
        "type": "Point",
        "coordinates": [
          -70.983333,
          -30.033333
        ]
      },
      "type": "Feature",
      "properties": {
        "hierarchy": [
          "tgn:7311932",
          "tgn:1001657",
          "tgn:1000049",
          "tgn:1000002",
          "tgn:7029392"
        ],
        "placetype": [
          "aat:300008347"
        ],
        "id": 7311932,
        "name:xx": "Las Juntas"
      }
    },
    {
      "geometry": {
        "type": "Point",
        "coordinates": [
          -72.166667,
          -41.316667
        ]
      },
      "type": "Feature",
      "properties": {
        "hierarchy": [
          "tgn:7311933",
          "tgn:1001699",
          "tgn:1000049",
          "tgn:1000002",
          "tgn:7029392"
        ],
        "placetype": [
          "aat:300387200"
        ],
        "id": 7311933,
        "name:xx": "Las Juntas"
      }
    },
    {
      "geometry": {
        "type": "Point",
        "coordinates": [
          -71.866667,
          -35.85
        ]
      },
      "type": "Feature",
      "properties": {
        "hierarchy": [
          "tgn:7311934",
          "tgn:1001705",
          "tgn:1000049",
          "tgn:1000002",
          "tgn:7029392"
        ],
        "placetype": [
          "aat:300387200"
        ],
        "id": 7311934,
        "name:xx": "Las Juntas"
      }
    },
    {
      "geometry": {
        "type": "Point",
        "coordinates": [
          -71.483333,
          -34.15
        ]
      },
      "type": "Feature",
      "properties": {
        "hierarchy": [
          "tgn:7311935",
          "tgn:1001708",
          "tgn:1000049",
          "tgn:1000002",
          "tgn:7029392"
        ],
        "placetype": [
          "aat:300387200"
        ],
        "id": 7311935,
        "name:xx": "Las Juntas"
      }
    },
    {
      "geometry": {
        "type": "Point",
        "coordinates": [
          -73.283333,
          -40.983333
        ]
      },
      "type": "Feature",
      "properties": {
        "hierarchy": [
          "tgn:7311936",
          "tgn:1001699",
          "tgn:1000049",
          "tgn:1000002",
          "tgn:7029392"
        ],
        "placetype": [
          "aat:300000206"
        ],
        "id": 7311936,
        "name:xx": "Las Juntas"
      }
    },
    {
      "geometry": {
        "type": "Point",
        "coordinates": [
          -70.883333,
          -30.716667
        ]
      },
      "type": "Feature",
      "properties": {
        "hierarchy": [
          "tgn:7311937",
          "tgn:1001657",
          "tgn:1000049",
          "tgn:1000002",
          "tgn:7029392"
        ],
        "placetype": [
          "aat:300000206"
        ],
        "id": 7311937,
        "name:xx": "Las Juntas"
      }
    },
    {
      "geometry": {
        "type": "Point",
        "coordinates": [
          -70.8,
          -32.683333
        ]
      },
      "type": "Feature",
      "properties": {
        "hierarchy": [
          "tgn:7311938",
          "tgn:1001768",
          "tgn:1000049",
          "tgn:1000002",
          "tgn:7029392"
        ],
        "placetype": [
          "aat:300008798"
        ],
        "id": 7311938,
        "name:xx": "Las Juncas, Cerro"
      }
    },
    {
      "geometry": {
        "type": "Point",
        "coordinates": [
          -70.85,
          -31.666667
        ]
      },
      "type": "Feature",
      "properties": {
        "hierarchy": [
          "tgn:7311939",
          "tgn:1001657",
          "tgn:1000049",
          "tgn:1000002",
          "tgn:7029392"
        ],
        "placetype": [
          "aat:300008347"
        ],
        "id": 7311939,
        "name:xx": "Las Jarillas"
      }
    }
  ]
}
