{
  "geometry": {
    "type": "Point",
    "coordinates": [
      -83.75,
      37.25
    ]
  },
  "type": "Feature",
  "properties": {
    "hierarchy": [
      "tgn:2315773",
      "tgn:1000001",
      "tgn:2000782",
      "tgn:7012149",
      "tgn:7007255",
      "tgn:7029392"
    ],
    "placetype": [
      "aat:300008699"
    ],
    "id": 2315773,
    "name:xx": "Ells Branch"
  }
}
