{
  "geometry": {
    "type": "Point",
    "coordinates": [
      31.279322,
      30.087516
    ]
  },
  "type": "Feature",
  "properties": {
    "hierarchy": [
      "tgn:7531382",
      "tgn:7001242",
      "tgn:7016833",
      "tgn:1001091",
      "tgn:7029392"
    ],
    "placetype": [
      "aat:300004792"
    ],
    "id": 7531382,
    "name:xx": "Jam'īyat Şadīqāt al Kitāb al Muqaddas"
  }
}
