{
  "geometry": {
    "type": "Point",
    "coordinates": [
      -84.05,
      35.2167
    ]
  },
  "type": "Feature",
  "properties": {
    "hierarchy": [
      "tgn:2626581",
      "tgn:1000001",
      "tgn:2001481",
      "tgn:7012149",
      "tgn:7007709",
      "tgn:7029392"
    ],
    "placetype": [
      "aat:300008798"
    ],
    "id": 2626581,
    "name:xx": "Rocky Knob"
  }
}
