{
  "geometry": {
    "type": "Point",
    "coordinates": [
      -105.2167,
      39.8667
    ]
  },
  "type": "Feature",
  "properties": {
    "hierarchy": [
      "tgn:2670475",
      "tgn:1000001",
      "tgn:7012149",
      "tgn:2000221",
      "tgn:7007158",
      "tgn:7029392"
    ],
    "placetype": [
      "aat:300006075"
    ],
    "id": 2670475,
    "name:xx": "Smart Ditch"
  }
}
