{
  "geometry": {
    "type": "Point",
    "coordinates": [
      -75.7667,
      39.15
    ]
  },
  "type": "Feature",
  "properties": {
    "hierarchy": [
      "tgn:2133483",
      "tgn:1000001",
      "tgn:7012149",
      "tgn:7007516",
      "tgn:7029392"
    ],
    "placetype": [
      "aat:300008699"
    ],
    "id": 2133483,
    "name:xx": "Andover Branch"
  }
}
