{
  "geometry": {
    "type": "Point",
    "coordinates": [
      -158.5833,
      56.1833
    ]
  },
  "type": "Feature",
  "properties": {
    "hierarchy": [
      "tgn:2593991",
      "tgn:7006450",
      "tgn:1000001",
      "tgn:7030517",
      "tgn:7012149",
      "tgn:7029392"
    ],
    "placetype": [
      "aat:300132316"
    ],
    "id": 2593991,
    "name:xx": "Portage Bay"
  }
}
