{
  "geometry": {
    "type": "Point",
    "coordinates": [
      -91.6833,
      38.0333
    ]
  },
  "type": "Feature",
  "properties": {
    "hierarchy": [
      "tgn:2255696",
      "tgn:1000001",
      "tgn:7012149",
      "tgn:7007523",
      "tgn:7029392"
    ],
    "placetype": [
      "aat:300008706"
    ],
    "id": 2255696,
    "name:xx": "Coppedge Creek"
  }
}
