{
  "geometry": {
    "type": "Point",
    "coordinates": [
      -145.1333,
      68.3833
    ]
  },
  "type": "Feature",
  "properties": {
    "hierarchy": [
      "tgn:2715826",
      "tgn:7006450",
      "tgn:1000001",
      "tgn:7012149",
      "tgn:2000089",
      "tgn:7029392"
    ],
    "placetype": [
      "aat:300008680"
    ],
    "id": 2715826,
    "name:xx": "Tetsyeh Lake"
  }
}
