{
  "geometry": {
    "type": "Point",
    "coordinates": [
      35.1667,
      33.0833
    ]
  },
  "type": "Feature",
  "properties": {
    "hierarchy": [
      "tgn:1079463",
      "tgn:7000249",
      "tgn:1000004",
      "tgn:1000119",
      "tgn:7029392"
    ],
    "placetype": [
      "aat:300008347"
    ],
    "id": 1079463,
    "name:xx": "H̲anita"
  }
}
