{
  "type": "FeatureCollection",
  "features": [
    {
      "geometry": {
        "type": "Point",
        "coordinates": [
          11.45,
          49.883333
        ]
      },
      "type": "Feature",
      "properties": {
        "hierarchy": [
          "tgn:7186090",
          "tgn:7003669",
          "tgn:1000003",
          "tgn:7000084",
          "tgn:7029392"
        ],
        "placetype": [
          "aat:300008863"
        ],
        "id": 7186090,
        "name:xx": "Glashüttner Wald"
      }
    },
    {
      "geometry": {
        "type": "Point",
        "coordinates": [
          13.483333,
          48.9
        ]
      },
      "type": "Feature",
      "properties": {
        "hierarchy": [
          "tgn:7186091",
          "tgn:7003669",
          "tgn:1000003",
          "tgn:7000084",
          "tgn:7029392"
        ],
        "placetype": [
          "aat:300008863"
        ],
        "id": 7186091,
        "name:xx": "Glashütten Wald"
      }
    },
    {
      "geometry": {
        "type": "Point",
        "coordinates": [
          10.983333,
          51.7
        ]
      },
      "type": "Feature",
      "properties": {
        "hierarchy": [
          "tgn:7186092",
          "tgn:1000003",
          "tgn:7003687",
          "tgn:7000084",
          "tgn:7029392"
        ],
        "placetype": [
          "aat:300008777"
        ],
        "id": 7186092,
        "name:xx": "Glashütten Köpfe"
      }
    },
    {
      "geometry": {
        "type": "Point",
        "coordinates": [
          8.883333,
          47.9
        ]
      },
      "type": "Feature",
      "properties": {
        "hierarchy": [
          "tgn:7186093",
          "tgn:7003692",
          "tgn:1000003",
          "tgn:7000084",
          "tgn:7029392"
        ],
        "placetype": [
          "aat:300000206"
        ],
        "id": 7186093,
        "name:xx": "Glashüttenhöfe"
      }
    },
    {
      "geometry": {
        "type": "Point",
        "coordinates": [
          8.983333,
          47.9
        ]
      },
      "type": "Feature",
      "properties": {
        "hierarchy": [
          "tgn:7186094",
          "tgn:7003692",
          "tgn:1000003",
          "tgn:7000084",
          "tgn:7029392"
        ],
        "placetype": [
          "aat:300000206"
        ],
        "id": 7186094,
        "name:xx": "Glashüttenhof"
      }
    },
    {
      "geometry": {
        "type": "Point",
        "coordinates": [
          7.7,
          47.7
        ]
      },
      "type": "Feature",
      "properties": {
        "hierarchy": [
          "tgn:7186095",
          "tgn:7003692",
          "tgn:1000003",
          "tgn:7000084",
          "tgn:7029392"
        ],
        "placetype": [
          "aat:300000206"
        ],
        "id": 7186095,
        "name:xx": "Glashüttenhof"
      }
    },
    {
      "geometry": {
        "type": "Point",
        "coordinates": [
          9.4,
          47.816667
        ]
      },
      "type": "Feature",
      "properties": {
        "hierarchy": [
          "tgn:7186096",
          "tgn:7003692",
          "tgn:1000003",
          "tgn:7000084",
          "tgn:7029392"
        ],
        "placetype": [
          "aat:300000206"
        ],
        "id": 7186096,
        "name:xx": "Höchsten"
      }
    },
    {
      "geometry": {
        "type": "Point",
        "coordinates": [
          14.283333,
          52.35
        ]
      },
      "type": "Feature",
      "properties": {
        "hierarchy": [
          "tgn:7186097",
          "tgn:7000096",
          "tgn:1000003",
          "tgn:7000084",
          "tgn:7029392"
        ],
        "placetype": [
          "aat:300000745"
        ],
        "id": 7186097,
        "name:xx": "Glashütten"
      }
    },
    {
      "geometry": {
        "type": "Point",
        "coordinates": [
          9.133333,
          50.416667
        ]
      },
      "type": "Feature",
      "properties": {
        "hierarchy": [
          "tgn:7186098",
          "tgn:1000003",
          "tgn:7003678",
          "tgn:7000084",
          "tgn:7029392"
        ],
        "placetype": [
          "aat:300008347"
        ],
        "id": 7186098,
        "name:xx": "Glashütten"
      }
    },
    {
      "geometry": {
        "type": "Point",
        "coordinates": [
          8.4,
          50.216667
        ]
      },
      "type": "Feature",
      "properties": {
        "hierarchy": [
          "tgn:7186099",
          "tgn:1000003",
          "tgn:7003678",
          "tgn:7000084",
          "tgn:7029392"
        ],
        "placetype": [
          "aat:300008347"
        ],
        "id": 7186099,
        "name:xx": "Glashütten"
      }
    }
  ]
}
