{
  "geometry": {
    "type": "Point",
    "coordinates": [
      -149.6833,
      61.25
    ]
  },
  "type": "Feature",
  "properties": {
    "hierarchy": [
      "tgn:2335498",
      "tgn:2124017",
      "tgn:7006450",
      "tgn:1000001",
      "tgn:7012149",
      "tgn:7029392"
    ],
    "placetype": [
      "aat:300008347"
    ],
    "id": 2335498,
    "name:xx": "Fort Richardson"
  }
}
