{
  "geometry": {
    "type": "Point",
    "coordinates": [
      -78.9333,
      37.05
    ]
  },
  "type": "Feature",
  "properties": {
    "hierarchy": [
      "tgn:2110823",
      "tgn:1000001",
      "tgn:2002150",
      "tgn:7012149",
      "tgn:7007919",
      "tgn:7029392"
    ],
    "placetype": [
      "aat:300008347"
    ],
    "id": 2110823,
    "name:xx": "Brookneal"
  }
}
