{
  "type": "FeatureCollection",
  "features": [
    {
      "geometry": {
        "type": "Point",
        "coordinates": [
          -79.1333,
          37.2833
        ]
      },
      "type": "Feature",
      "properties": {
        "hierarchy": [
          "tgn:2774460",
          "tgn:1000001",
          "tgn:2002150",
          "tgn:7012149",
          "tgn:7007919",
          "tgn:7029392"
        ],
        "placetype": [
          "aat:300006191"
        ],
        "id": 2774460,
        "name:xx": "Willow Lake"
      }
    },
    {
      "geometry": {
        "type": "Point",
        "coordinates": [
          -77.9333,
          39.0667
        ]
      },
      "type": "Feature",
      "properties": {
        "hierarchy": [
          "tgn:2774461",
          "tgn:1000001",
          "tgn:7012149",
          "tgn:2002153",
          "tgn:7007919",
          "tgn:7029392"
        ],
        "placetype": [
          "aat:300006191"
        ],
        "id": 2774461,
        "name:xx": "Willow Lake"
      }
    },
    {
      "geometry": {
        "type": "Point",
        "coordinates": [
          -77.75,
          38.85
        ]
      },
      "type": "Feature",
      "properties": {
        "hierarchy": [
          "tgn:2774462",
          "tgn:1000001",
          "tgn:7012149",
          "tgn:1002368",
          "tgn:7007919",
          "tgn:7029392"
        ],
        "placetype": [
          "aat:300006191"
        ],
        "id": 2774462,
        "name:xx": "Willow Lake"
      }
    },
    {
      "geometry": {
        "type": "Point",
        "coordinates": [
          -79.2333,
          37.9167
        ]
      },
      "type": "Feature",
      "properties": {
        "hierarchy": [
          "tgn:2774463",
          "tgn:1000001",
          "tgn:7012149",
          "tgn:2002186",
          "tgn:7007919",
          "tgn:7029392"
        ],
        "placetype": [
          "aat:300006191"
        ],
        "id": 2774463,
        "name:xx": "Willow Lake"
      }
    },
    {
      "geometry": {
        "type": "Point",
        "coordinates": [
          -119.3667,
          47.3333
        ]
      },
      "type": "Feature",
      "properties": {
        "hierarchy": [
          "tgn:2774464",
          "tgn:1000001",
          "tgn:7012149",
          "tgn:2002246",
          "tgn:7007920",
          "tgn:7029392"
        ],
        "placetype": [
          "aat:300008680"
        ],
        "id": 2774464,
        "name:xx": "Willow Lake"
      }
    },
    {
      "geometry": {
        "type": "Point",
        "coordinates": [
          -117.6167,
          47.55
        ]
      },
      "type": "Feature",
      "properties": {
        "hierarchy": [
          "tgn:2774465",
          "tgn:1000001",
          "tgn:7012149",
          "tgn:2002249",
          "tgn:7007920",
          "tgn:7029392"
        ],
        "placetype": [
          "aat:300008680"
        ],
        "id": 2774465,
        "name:xx": "Willow Lake"
      }
    },
    {
      "geometry": {
        "type": "Point",
        "coordinates": [
          -118.5833,
          47.5833
        ]
      },
      "type": "Feature",
      "properties": {
        "hierarchy": [
          "tgn:2774466",
          "tgn:1000001",
          "tgn:7012149",
          "tgn:2002247",
          "tgn:7007920",
          "tgn:7029392"
        ],
        "placetype": [
          "aat:300008680"
        ],
        "id": 2774466,
        "name:xx": "Willow Lake"
      }
    },
    {
      "geometry": {
        "type": "Point",
        "coordinates": [
          -121,
          48.9333
        ]
      },
      "type": "Feature",
      "properties": {
        "hierarchy": [
          "tgn:2774467",
          "tgn:1000001",
          "tgn:7012149",
          "tgn:1003020",
          "tgn:7007920",
          "tgn:7029392"
        ],
        "placetype": [
          "aat:300008680"
        ],
        "id": 2774467,
        "name:xx": "Willow Lake"
      }
    },
    {
      "geometry": {
        "type": "Point",
        "coordinates": [
          -89.9833,
          45.7
        ]
      },
      "type": "Feature",
      "properties": {
        "hierarchy": [
          "tgn:2774468",
          "tgn:1000001",
          "tgn:7012149",
          "tgn:2002342",
          "tgn:7007922",
          "tgn:7029392"
        ],
        "placetype": [
          "aat:300008680"
        ],
        "id": 2774468,
        "name:xx": "Willow Lake"
      }
    },
    {
      "geometry": {
        "type": "Point",
        "coordinates": [
          -107.05,
          44.2667
        ]
      },
      "type": "Feature",
      "properties": {
        "hierarchy": [
          "tgn:2774469",
          "tgn:1000001",
          "tgn:7012149",
          "tgn:2002374",
          "tgn:7007923",
          "tgn:7029392"
        ],
        "placetype": [
          "aat:300008680"
        ],
        "id": 2774469,
        "name:xx": "Willow Lake"
      }
    }
  ]
}
