{
  "geometry": {
    "type": "Point",
    "coordinates": [
      -76.2833,
      56.25
    ]
  },
  "type": "Feature",
  "properties": {
    "hierarchy": [
      "tgn:1116525",
      "tgn:7005685",
      "tgn:1000001",
      "tgn:7005804",
      "tgn:7029392"
    ],
    "placetype": [
      "aat:300008680"
    ],
    "id": 1116525,
    "name:xx": "Guillaume-Delisle, Lac"
  }
}
