{
  "geometry": {
    "type": "Point",
    "coordinates": [
      -88.0667,
      34.7833
    ]
  },
  "type": "Feature",
  "properties": {
    "hierarchy": [
      "tgn:2407618",
      "tgn:7002659",
      "tgn:1000001",
      "tgn:2000016",
      "tgn:7012149",
      "tgn:7029392"
    ],
    "placetype": [
      "aat:300008697"
    ],
    "id": 2407618,
    "name:xx": "Hurd Spring"
  }
}
