{
  "type": "FeatureCollection",
  "features": [
    {
      "geometry": {
        "type": "Point",
        "coordinates": [
          -73.166667,
          -39.883333
        ]
      },
      "type": "Feature",
      "properties": {
        "hierarchy": [
          "tgn:7285170",
          "tgn:1001699",
          "tgn:1000049",
          "tgn:1000002",
          "tgn:7029392"
        ],
        "placetype": [
          "aat:300008699"
        ],
        "id": 7285170,
        "name:xx": "Piedra Blanca, Río"
      }
    },
    {
      "geometry": {
        "type": "Point",
        "coordinates": [
          -73.116667,
          -38.2
        ]
      },
      "type": "Feature",
      "properties": {
        "hierarchy": [
          "tgn:7285171",
          "tgn:1001692",
          "tgn:1000049",
          "tgn:1000002",
          "tgn:7029392"
        ],
        "placetype": [
          "aat:300008699"
        ],
        "id": 7285171,
        "name:xx": "Piedra Blanca, Quebrada"
      }
    },
    {
      "geometry": {
        "type": "Point",
        "coordinates": [
          -72.733333,
          -42.916667
        ]
      },
      "type": "Feature",
      "properties": {
        "hierarchy": [
          "tgn:7285172",
          "tgn:1001699",
          "tgn:1000049",
          "tgn:1000002",
          "tgn:7029392"
        ],
        "placetype": [
          "aat:300386846"
        ],
        "id": 7285172,
        "name:xx": "Piedra Blanca, Punta"
      }
    },
    {
      "geometry": {
        "type": "Point",
        "coordinates": [
          -70.633333,
          -26.366667
        ]
      },
      "type": "Feature",
      "properties": {
        "hierarchy": [
          "tgn:7285173",
          "tgn:1001630",
          "tgn:1000049",
          "tgn:1000002",
          "tgn:7029392"
        ],
        "placetype": [
          "aat:300386846"
        ],
        "id": 7285173,
        "name:xx": "Piedra Blanca, Punta"
      }
    },
    {
      "geometry": {
        "type": "Point",
        "coordinates": [
          -71.15,
          -28.016667
        ]
      },
      "type": "Feature",
      "properties": {
        "hierarchy": [
          "tgn:7285174",
          "tgn:1001630",
          "tgn:1000049",
          "tgn:1000002",
          "tgn:7029392"
        ],
        "placetype": [
          "aat:300011692"
        ],
        "id": 7285174,
        "name:xx": "Piedra Blanca, Islote"
      }
    },
    {
      "geometry": {
        "type": "Point",
        "coordinates": [
          -72.45,
          -42.35
        ]
      },
      "type": "Feature",
      "properties": {
        "hierarchy": [
          "tgn:7285175",
          "tgn:1001699",
          "tgn:1000049",
          "tgn:1000002",
          "tgn:7029392"
        ],
        "placetype": [
          "aat:300132317"
        ],
        "id": 7285175,
        "name:xx": "Piedra Blanca, Caleta"
      }
    },
    {
      "geometry": {
        "type": "Point",
        "coordinates": [
          -73.1,
          -39.883333
        ]
      },
      "type": "Feature",
      "properties": {
        "hierarchy": [
          "tgn:7285176",
          "tgn:1001699",
          "tgn:1000049",
          "tgn:1000002",
          "tgn:7029392"
        ],
        "placetype": [
          "aat:300008347"
        ],
        "id": 7285176,
        "name:xx": "Piedra Blanca"
      }
    },
    {
      "geometry": {
        "type": "Point",
        "coordinates": [
          -71.183333,
          -33.633333
        ]
      },
      "type": "Feature",
      "properties": {
        "hierarchy": [
          "tgn:7285177",
          "tgn:1001708",
          "tgn:1000049",
          "tgn:1000002",
          "tgn:7029392"
        ],
        "placetype": [
          "aat:300008777"
        ],
        "id": 7285177,
        "name:xx": "Piedra Azul, Cerrillo"
      }
    },
    {
      "geometry": {
        "type": "Point",
        "coordinates": [
          -72.8,
          -41.5
        ]
      },
      "type": "Feature",
      "properties": {
        "hierarchy": [
          "tgn:7285178",
          "tgn:1001699",
          "tgn:1000049",
          "tgn:1000002",
          "tgn:7029392"
        ],
        "placetype": [
          "aat:300000206"
        ],
        "id": 7285178,
        "name:xx": "Piedra Azul"
      }
    },
    {
      "geometry": {
        "type": "Point",
        "coordinates": [
          -71.433333,
          -32.416667
        ]
      },
      "type": "Feature",
      "properties": {
        "hierarchy": [
          "tgn:7285179",
          "tgn:1001768",
          "tgn:1000049",
          "tgn:1000002",
          "tgn:7029392"
        ],
        "placetype": [
          "aat:300008777"
        ],
        "id": 7285179,
        "name:xx": "Piedra Alta, Cerro"
      }
    }
  ]
}
