{
  "geometry": {
    "type": "Point",
    "coordinates": [
      -114.1167,
      47.4167
    ]
  },
  "type": "Feature",
  "properties": {
    "hierarchy": [
      "tgn:2594998",
      "tgn:1000001",
      "tgn:7012149",
      "tgn:2001283",
      "tgn:7007524",
      "tgn:7029392"
    ],
    "placetype": [
      "aat:300006075"
    ],
    "id": 2594998,
    "name:xx": "Post E Canal"
  }
}
