{
  "geometry": {
    "type": "Point",
    "coordinates": [
      34.95,
      32.5667
    ]
  },
  "type": "Feature",
  "properties": {
    "hierarchy": [
      "tgn:1079654",
      "tgn:1000808",
      "tgn:1000004",
      "tgn:1000119",
      "tgn:7029392"
    ],
    "placetype": [
      "aat:300008347"
    ],
    "id": 1079654,
    "name:xx": "Zikhron Yaʻaqov"
  }
}
