{
  "geometry": {
    "type": "Point",
    "coordinates": [
      24.4667,
      53.1667
    ]
  },
  "type": "Feature",
  "properties": {
    "hierarchy": [
      "tgn:1061314",
      "tgn:7012158",
      "tgn:1000003",
      "tgn:7006657",
      "tgn:7029392"
    ],
    "placetype": [
      "aat:300008347"
    ],
    "id": 1061314,
    "name:xx": "Volkovysk"
  }
}
