{
  "geometry": {
    "type": "Point",
    "coordinates": [
      -81.8167,
      38.8833
    ]
  },
  "type": "Feature",
  "properties": {
    "hierarchy": [
      "tgn:2701464",
      "tgn:1000001",
      "tgn:7012149",
      "tgn:2002268",
      "tgn:7013961",
      "tgn:7029392"
    ],
    "placetype": [
      "aat:300008699"
    ],
    "id": 2701464,
    "name:xx": "Sugar Run"
  }
}
