{
  "geometry": {
    "type": "Point",
    "coordinates": [
      33.645634,
      27.442382
    ]
  },
  "type": "Feature",
  "properties": {
    "hierarchy": [
      "tgn:7525714",
      "tgn:7001242",
      "tgn:7001311",
      "tgn:7016833",
      "tgn:7029392"
    ],
    "placetype": [
      "aat:300379998"
    ],
    "name:en": "Balī', Wādī",
    "id": 7525714
  }
}
