{
  "geometry": {
    "type": "Point",
    "coordinates": [
      -85.1333,
      36.7833
    ]
  },
  "type": "Feature",
  "properties": {
    "hierarchy": [
      "tgn:2041242",
      "tgn:1000001",
      "tgn:2000783",
      "tgn:7012149",
      "tgn:7007255",
      "tgn:7029392"
    ],
    "placetype": [
      "aat:300008347",
      "aat:300387210"
    ],
    "id": 2041242,
    "name:xx": "Seventy Six"
  }
}
