{
  "geometry": {
    "type": "Point",
    "coordinates": [
      -95.45,
      39.05
    ]
  },
  "type": "Feature",
  "properties": {
    "hierarchy": [
      "tgn:2367850",
      "tgn:1000001",
      "tgn:2000682",
      "tgn:7012149",
      "tgn:7007254",
      "tgn:7029392"
    ],
    "placetype": [
      "aat:300008347"
    ],
    "id": 2367850,
    "name:xx": "Grover"
  }
}
