{
  "geometry": {
    "type": "Point",
    "coordinates": [
      -174.8833,
      52.0833
    ]
  },
  "type": "Feature",
  "properties": {
    "hierarchy": [
      "tgn:2748843",
      "tgn:7030516",
      "tgn:7006450",
      "tgn:1000001",
      "tgn:7012149",
      "tgn:7029392"
    ],
    "placetype": [
      "aat:300132316"
    ],
    "id": 2748843,
    "name:xx": "Wall Bay"
  }
}
