{
  "geometry": {
    "type": "Point",
    "coordinates": [
      -122.9167,
      39.55
    ]
  },
  "type": "Feature",
  "properties": {
    "hierarchy": [
      "tgn:2612108",
      "tgn:1000001",
      "tgn:7012149",
      "tgn:7007157",
      "tgn:2000185",
      "tgn:7029392"
    ],
    "placetype": [
      "aat:300266640"
    ],
    "id": 2612108,
    "name:xx": "Red Rock Ridge"
  }
}
