{
  "type": "FeatureCollection",
  "features": [
    {
      "geometry": {
        "type": "Point",
        "coordinates": [
          1.6,
          49.0833
        ]
      },
      "type": "Feature",
      "properties": {
        "hierarchy": [
          "tgn:1033290",
          "tgn:1000003",
          "tgn:7002882",
          "tgn:1000070",
          "tgn:7029392"
        ],
        "placetype": [
          "aat:300008347"
        ],
        "id": 1033290,
        "name:xx": "Gommécourt"
      }
    },
    {
      "geometry": {
        "type": "Point",
        "coordinates": [
          6,
          45.2667
        ]
      },
      "type": "Feature",
      "properties": {
        "hierarchy": [
          "tgn:1033291",
          "tgn:1000003",
          "tgn:1000070",
          "tgn:7002897",
          "tgn:7029392"
        ],
        "placetype": [
          "aat:300008347"
        ],
        "id": 1033291,
        "name:xx": "Goncelin"
      }
    },
    {
      "geometry": {
        "type": "Point",
        "coordinates": [
          5.9667,
          48.7
        ]
      },
      "type": "Feature",
      "properties": {
        "hierarchy": [
          "tgn:1033293",
          "tgn:1000003",
          "tgn:7002888",
          "tgn:1000070",
          "tgn:7029392"
        ],
        "placetype": [
          "aat:300008347"
        ],
        "id": 1033293,
        "name:xx": "Gondreville"
      }
    },
    {
      "geometry": {
        "type": "Point",
        "coordinates": [
          6.2833,
          43.3333
        ]
      },
      "type": "Feature",
      "properties": {
        "hierarchy": [
          "tgn:1033295",
          "tgn:1000003",
          "tgn:1000070",
          "tgn:7002895",
          "tgn:7029392"
        ],
        "placetype": [
          "aat:300008347"
        ],
        "id": 1033295,
        "name:xx": "Gonfaron"
      }
    },
    {
      "geometry": {
        "type": "Point",
        "coordinates": [
          -0.8167,
          48.4167
        ]
      },
      "type": "Feature",
      "properties": {
        "hierarchy": [
          "tgn:1033297",
          "tgn:1000003",
          "tgn:7002893",
          "tgn:1000070",
          "tgn:7029392"
        ],
        "placetype": [
          "aat:300008347"
        ],
        "id": 1033297,
        "name:xx": "Gorron"
      }
    },
    {
      "geometry": {
        "type": "Point",
        "coordinates": [
          -3.1833,
          48.2167
        ]
      },
      "type": "Feature",
      "properties": {
        "hierarchy": [
          "tgn:1033299",
          "tgn:1000003",
          "tgn:7012216",
          "tgn:1000070",
          "tgn:7029392"
        ],
        "placetype": [
          "aat:300008347"
        ],
        "id": 1033299,
        "name:xx": "Gouarec"
      }
    }
  ]
}
