{
  "type": "FeatureCollection",
  "features": [
    {
      "geometry": {
        "type": "Point",
        "coordinates": [
          10.033333,
          54.3
        ]
      },
      "type": "Feature",
      "properties": {
        "hierarchy": [
          "tgn:7094760",
          "tgn:1000003",
          "tgn:7003688",
          "tgn:7000084",
          "tgn:7029392"
        ],
        "placetype": [
          "aat:300000206"
        ],
        "id": 7094760,
        "name:xx": "Seeberg"
      }
    },
    {
      "geometry": {
        "type": "Point",
        "coordinates": [
          14.3,
          53.566667
        ]
      },
      "type": "Feature",
      "properties": {
        "hierarchy": [
          "tgn:7094761",
          "tgn:1000003",
          "tgn:7000094",
          "tgn:7000084",
          "tgn:7029392"
        ],
        "placetype": [
          "aat:300000206"
        ],
        "id": 7094761,
        "name:xx": "Seeberg"
      }
    },
    {
      "geometry": {
        "type": "Point",
        "coordinates": [
          12.8,
          47.916667
        ]
      },
      "type": "Feature",
      "properties": {
        "hierarchy": [
          "tgn:7094762",
          "tgn:7003669",
          "tgn:1000003",
          "tgn:7000084",
          "tgn:7029392"
        ],
        "placetype": [
          "aat:300000206"
        ],
        "id": 7094762,
        "name:xx": "Seeberg"
      }
    },
    {
      "geometry": {
        "type": "Point",
        "coordinates": [
          10.433333,
          51.033333
        ]
      },
      "type": "Feature",
      "properties": {
        "hierarchy": [
          "tgn:7094763",
          "tgn:1000003",
          "tgn:7003689",
          "tgn:7000084",
          "tgn:7029392"
        ],
        "placetype": [
          "aat:300008777"
        ],
        "id": 7094763,
        "name:xx": "Seeber-Berg"
      }
    },
    {
      "geometry": {
        "type": "Point",
        "coordinates": [
          12.233333,
          51.266667
        ]
      },
      "type": "Feature",
      "properties": {
        "hierarchy": [
          "tgn:7094764",
          "tgn:1000003",
          "tgn:7003685",
          "tgn:7000084",
          "tgn:7029392"
        ],
        "placetype": [
          "aat:300008347"
        ],
        "id": 7094764,
        "name:xx": "Seebenisch"
      }
    },
    {
      "geometry": {
        "type": "Point",
        "coordinates": [
          11.016667,
          52.9
        ]
      },
      "type": "Feature",
      "properties": {
        "hierarchy": [
          "tgn:7094765",
          "tgn:1000003",
          "tgn:7003687",
          "tgn:7000084",
          "tgn:7029392"
        ],
        "placetype": [
          "aat:300008863"
        ],
        "id": 7094765,
        "name:xx": "Seebener Holz"
      }
    },
    {
      "geometry": {
        "type": "Point",
        "coordinates": [
          11.966667,
          51.533333
        ]
      },
      "type": "Feature",
      "properties": {
        "hierarchy": [
          "tgn:7094766",
          "tgn:1000003",
          "tgn:7003687",
          "tgn:7000084",
          "tgn:7029392"
        ],
        "placetype": [
          "aat:300008777"
        ],
        "id": 7094766,
        "name:xx": "Seebener Berge"
      }
    },
    {
      "geometry": {
        "type": "Point",
        "coordinates": [
          11.033333,
          52.883333
        ]
      },
      "type": "Feature",
      "properties": {
        "hierarchy": [
          "tgn:7094767",
          "tgn:1000003",
          "tgn:7003687",
          "tgn:7000084",
          "tgn:7029392"
        ],
        "placetype": [
          "aat:300387173"
        ],
        "id": 7094767,
        "name:xx": "Seebenau"
      }
    },
    {
      "geometry": {
        "type": "Point",
        "coordinates": [
          11.016667,
          52.9
        ]
      },
      "type": "Feature",
      "properties": {
        "hierarchy": [
          "tgn:7094768",
          "tgn:1000003",
          "tgn:7003687",
          "tgn:7000084",
          "tgn:7029392"
        ],
        "placetype": [
          "aat:300004792"
        ],
        "id": 7094768,
        "name:xx": "Försterei Seeben"
      }
    },
    {
      "geometry": {
        "type": "Point",
        "coordinates": [
          11.033333,
          52.883333
        ]
      },
      "type": "Feature",
      "properties": {
        "hierarchy": [
          "tgn:7094769",
          "tgn:1000003",
          "tgn:7003687",
          "tgn:7000084",
          "tgn:7029392"
        ],
        "placetype": [
          "aat:300008347"
        ],
        "id": 7094769,
        "name:xx": "Seeben"
      }
    }
  ]
}
