{
  "geometry": {
    "type": "Point",
    "coordinates": [
      -73.8833,
      43.25
    ]
  },
  "type": "Feature",
  "properties": {
    "hierarchy": [
      "tgn:2406626",
      "tgn:1000001",
      "tgn:7012149",
      "tgn:1002871",
      "tgn:7007568",
      "tgn:7029392"
    ],
    "placetype": [
      "aat:300008699"
    ],
    "id": 2406626,
    "name:xx": "Hunt Brook"
  }
}
