{
  "geometry": {
    "type": "Point",
    "coordinates": [
      21.95,
      37.65
    ]
  },
  "type": "Feature",
  "properties": {
    "hierarchy": [
      "tgn:7235728",
      "tgn:7002743",
      "tgn:7017076",
      "tgn:1000003",
      "tgn:1000074",
      "tgn:7029392"
    ],
    "placetype": [
      "aat:300008347"
    ],
    "id": 7235728,
    "name:xx": "Arápidhes"
  }
}
