{
  "geometry": {
    "type": "Point",
    "coordinates": [
      42.2667,
      39.0667
    ]
  },
  "type": "Feature",
  "properties": {
    "hierarchy": [
      "tgn:1086122",
      "tgn:1001437",
      "tgn:1000004",
      "tgn:7018455",
      "tgn:1000144",
      "tgn:7029392"
    ],
    "placetype": [
      "aat:300008347"
    ],
    "id": 1086122,
    "name:xx": "Bulanık"
  }
}
