{
  "type": "FeatureCollection",
  "features": [
    {
      "geometry": {
        "type": "Point",
        "coordinates": [
          -57.9167,
          54.9333
        ]
      },
      "type": "Feature",
      "properties": {
        "hierarchy": [
          "tgn:1010763",
          "tgn:7005685",
          "tgn:1000001",
          "tgn:7005801",
          "tgn:7029392"
        ],
        "placetype": [
          "aat:300008850"
        ],
        "id": 1010763,
        "name:xx": "Harrison, Cape"
      }
    },
    {
      "geometry": {
        "type": "Point",
        "coordinates": [
          -113,
          74.4167
        ]
      },
      "type": "Feature",
      "properties": {
        "hierarchy": [
          "tgn:1010766",
          "tgn:7005685",
          "tgn:1000001",
          "tgn:1000296",
          "tgn:7024247",
          "tgn:7029392"
        ],
        "placetype": [
          "aat:300008850"
        ],
        "id": 1010766,
        "name:xx": "Hay, Cape"
      }
    },
    {
      "geometry": {
        "type": "Point",
        "coordinates": [
          -82.15,
          26.7667
        ]
      },
      "type": "Feature",
      "properties": {
        "hierarchy": [
          "tgn:1010767",
          "tgn:1000001",
          "tgn:1002258",
          "tgn:7012149",
          "tgn:7007240",
          "tgn:7029392"
        ],
        "placetype": [
          "aat:300008850"
        ],
        "id": 1010767,
        "name:xx": "Haze, Cape"
      }
    }
  ]
}
