{
  "geometry": {
    "type": "Point",
    "coordinates": [
      -159.7667,
      -21.2333
    ]
  },
  "type": "Feature",
  "properties": {
    "hierarchy": [
      "tgn:1008735",
      "tgn:1010314",
      "tgn:7006213",
      "tgn:1000006",
      "tgn:7029392"
    ],
    "placetype": [
      "aat:300008791"
    ],
    "id": 1008735,
    "name:xx": "Rarotonga"
  }
}
