{
  "geometry": {
    "type": "Point",
    "coordinates": [
      -92.75,
      38.8333
    ]
  },
  "type": "Feature",
  "properties": {
    "hierarchy": [
      "tgn:2408511",
      "tgn:1000001",
      "tgn:7012149",
      "tgn:2001189",
      "tgn:7007523",
      "tgn:7029392"
    ],
    "placetype": [
      "aat:300008699"
    ],
    "id": 2408511,
    "name:xx": "Hutchison Branch"
  }
}
