{
  "geometry": {
    "type": "Point",
    "coordinates": [
      -82.2833,
      39.8667
    ]
  },
  "type": "Feature",
  "properties": {
    "hierarchy": [
      "tgn:2230878",
      "tgn:1000001",
      "tgn:7012149",
      "tgn:2001620",
      "tgn:7007706",
      "tgn:7029392"
    ],
    "placetype": [
      "aat:300006191"
    ],
    "id": 2230878,
    "name:xx": "Central Silica Company Pond 9722-009"
  }
}
