{
  "geometry": {
    "type": "Point",
    "coordinates": [
      -92.8833,
      36.6833
    ]
  },
  "type": "Feature",
  "properties": {
    "hierarchy": [
      "tgn:2590696",
      "tgn:1000001",
      "tgn:7012149",
      "tgn:2001251",
      "tgn:7007523",
      "tgn:7029392"
    ],
    "placetype": [
      "aat:300008761"
    ],
    "id": 2590696,
    "name:xx": "Pole Hollow"
  }
}
