{
  "geometry": {
    "type": "Point",
    "coordinates": [
      14.316667,
      51.75
    ]
  },
  "type": "Feature",
  "properties": {
    "hierarchy": [
      "tgn:7072749",
      "tgn:7000096",
      "tgn:1000003",
      "tgn:7000084",
      "tgn:7029392"
    ],
    "placetype": [
      "aat:300000745"
    ],
    "id": 7072749,
    "name:xx": "Ströbitz"
  }
}
