{
  "type": "FeatureCollection",
  "features": [
    {
      "geometry": {
        "type": "Point",
        "coordinates": [
          -103.8,
          20.483333
        ]
      },
      "type": "Feature",
      "properties": {
        "hierarchy": [
          "tgn:7441230",
          "tgn:7005586",
          "tgn:1000001",
          "tgn:7005560",
          "tgn:7029392"
        ],
        "placetype": [
          "aat:300008347"
        ],
        "id": 7441230,
        "name:xx": "San Pablo"
      }
    },
    {
      "geometry": {
        "type": "Point",
        "coordinates": [
          -97.2,
          20.466667
        ]
      },
      "type": "Feature",
      "properties": {
        "hierarchy": [
          "tgn:7441231",
          "tgn:1000001",
          "tgn:7005599",
          "tgn:7005560",
          "tgn:7029392"
        ],
        "placetype": [
          "aat:300008347"
        ],
        "id": 7441231,
        "name:xx": "San Pablo"
      }
    },
    {
      "geometry": {
        "type": "Point",
        "coordinates": [
          -104.483333,
          20.45
        ]
      },
      "type": "Feature",
      "properties": {
        "hierarchy": [
          "tgn:7441232",
          "tgn:7005586",
          "tgn:1000001",
          "tgn:7005560",
          "tgn:7029392"
        ],
        "placetype": [
          "aat:300008347"
        ],
        "id": 7441232,
        "name:xx": "San Pablo"
      }
    },
    {
      "geometry": {
        "type": "Point",
        "coordinates": [
          -88.8,
          20.233333
        ]
      },
      "type": "Feature",
      "properties": {
        "hierarchy": [
          "tgn:7441233",
          "tgn:1000001",
          "tgn:7005600",
          "tgn:7005560",
          "tgn:7029392"
        ],
        "placetype": [
          "aat:300008347"
        ],
        "id": 7441233,
        "name:xx": "San Pablo"
      }
    },
    {
      "geometry": {
        "type": "Point",
        "coordinates": [
          -100.533333,
          20.2
        ]
      },
      "type": "Feature",
      "properties": {
        "hierarchy": [
          "tgn:7441234",
          "tgn:7005584",
          "tgn:1000001",
          "tgn:7005560",
          "tgn:7029392"
        ],
        "placetype": [
          "aat:300008347"
        ],
        "id": 7441234,
        "name:xx": "San Pablo"
      }
    },
    {
      "geometry": {
        "type": "Point",
        "coordinates": [
          -99.983333,
          20.083333
        ]
      },
      "type": "Feature",
      "properties": {
        "hierarchy": [
          "tgn:7441235",
          "tgn:1000001",
          "tgn:7005593",
          "tgn:7005560",
          "tgn:7029392"
        ],
        "placetype": [
          "aat:300008347"
        ],
        "id": 7441235,
        "name:xx": "San Pablo"
      }
    },
    {
      "geometry": {
        "type": "Point",
        "coordinates": [
          -102.916667,
          19.45
        ]
      },
      "type": "Feature",
      "properties": {
        "hierarchy": [
          "tgn:7441236",
          "tgn:7005586",
          "tgn:1000001",
          "tgn:7005560",
          "tgn:7029392"
        ],
        "placetype": [
          "aat:300008347"
        ],
        "id": 7441236,
        "name:xx": "San Pablo"
      }
    },
    {
      "geometry": {
        "type": "Point",
        "coordinates": [
          -97.95,
          19.383333
        ]
      },
      "type": "Feature",
      "properties": {
        "hierarchy": [
          "tgn:7441237",
          "tgn:1000001",
          "tgn:7005598",
          "tgn:7005560",
          "tgn:7029392"
        ],
        "placetype": [
          "aat:300008347"
        ],
        "id": 7441237,
        "name:xx": "San Pablo"
      }
    },
    {
      "geometry": {
        "type": "Point",
        "coordinates": [
          -100.15,
          19.366667
        ]
      },
      "type": "Feature",
      "properties": {
        "hierarchy": [
          "tgn:7441238",
          "tgn:1000001",
          "tgn:1001893",
          "tgn:7005560",
          "tgn:7029392"
        ],
        "placetype": [
          "aat:300008347"
        ],
        "id": 7441238,
        "name:xx": "San Pablo"
      }
    },
    {
      "geometry": {
        "type": "Point",
        "coordinates": [
          -90.833333,
          19.116667
        ]
      },
      "type": "Feature",
      "properties": {
        "hierarchy": [
          "tgn:7441239",
          "tgn:7005578",
          "tgn:1000001",
          "tgn:7005560",
          "tgn:7029392"
        ],
        "placetype": [
          "aat:300008347"
        ],
        "id": 7441239,
        "name:xx": "San Pablo"
      }
    }
  ]
}
