{
  "geometry": {
    "type": "Point",
    "coordinates": [
      151.1333,
      -33.7667
    ]
  },
  "type": "Feature",
  "properties": {
    "hierarchy": [
      "tgn:1098509",
      "tgn:7000490",
      "tgn:1000006",
      "tgn:7001828",
      "tgn:7029392"
    ],
    "placetype": [
      "aat:300008347"
    ],
    "id": 1098509,
    "name:xx": "West Pymble"
  }
}
