{
  "geometry": {
    "type": "Point",
    "coordinates": [
      -93.8167,
      47.55
    ]
  },
  "type": "Feature",
  "properties": {
    "hierarchy": [
      "tgn:2456727",
      "tgn:1000001",
      "tgn:7012149",
      "tgn:2001029",
      "tgn:7007521",
      "tgn:7029392"
    ],
    "placetype": [
      "aat:300008680"
    ],
    "id": 2456727,
    "name:xx": "Little Jessie Lake"
  }
}
