{
  "geometry": {
    "type": "Point",
    "coordinates": [
      88.0833,
      27.4167
    ]
  },
  "type": "Feature",
  "properties": {
    "hierarchy": [
      "tgn:1106466",
      "tgn:1000004",
      "tgn:7029392"
    ],
    "placetype": [
      "aat:300008795"
    ],
    "id": 1106466,
    "name:xx": "Singālila"
  }
}
