{
  "geometry": {
    "type": "Point",
    "coordinates": [
      -88.7833,
      35.4167
    ]
  },
  "type": "Feature",
  "properties": {
    "hierarchy": [
      "tgn:2649177",
      "tgn:1000001",
      "tgn:7012149",
      "tgn:2001848",
      "tgn:7007825",
      "tgn:7029392"
    ],
    "placetype": [
      "aat:300006191"
    ],
    "id": 2649177,
    "name:xx": "Scott Lake"
  }
}
