{
  "geometry": {
    "type": "Point",
    "coordinates": [
      -118.9667,
      47.95
    ]
  },
  "type": "Feature",
  "properties": {
    "hierarchy": [
      "tgn:1101123",
      "tgn:1000001",
      "tgn:7012149",
      "tgn:7007920",
      "tgn:7029392"
    ],
    "placetype": [
      "aat:300006084"
    ],
    "id": 1101123,
    "name:xx": "Grand Coulee Dam"
  }
}
