{
  "type": "FeatureCollection",
  "features": [
    {
      "geometry": {
        "type": "Point",
        "coordinates": [
          22.8,
          36.75
        ]
      },
      "type": "Feature",
      "properties": {
        "hierarchy": [
          "tgn:1042000",
          "tgn:7002745",
          "tgn:7017076",
          "tgn:1000003",
          "tgn:1000074",
          "tgn:7029392"
        ],
        "placetype": [
          "aat:300008347"
        ],
        "id": 1042000,
        "name:xx": "Elaía"
      }
    },
    {
      "geometry": {
        "type": "Point",
        "coordinates": [
          24.251389,
          40.913889
        ]
      },
      "type": "Feature",
      "properties": {
        "hierarchy": [
          "tgn:1042003",
          "tgn:7011170",
          "tgn:7002715",
          "tgn:1000003",
          "tgn:1000074",
          "tgn:7029392"
        ],
        "placetype": [
          "aat:300008347"
        ],
        "id": 1042003,
        "name:xx": "Elevtheroúpolis"
      }
    },
    {
      "geometry": {
        "type": "Point",
        "coordinates": [
          23.733333,
          37.883333
        ]
      },
      "type": "Feature",
      "properties": {
        "hierarchy": [
          "tgn:1042004",
          "tgn:7002681",
          "tgn:7001395",
          "tgn:1000003",
          "tgn:1000074",
          "tgn:7029392"
        ],
        "placetype": [
          "aat:300008347"
        ],
        "id": 1042004,
        "name:xx": "Ellinikón"
      }
    },
    {
      "geometry": {
        "type": "Point",
        "coordinates": [
          22.928624,
          40.426381
        ]
      },
      "type": "Feature",
      "properties": {
        "hierarchy": [
          "tgn:1042005",
          "tgn:7002715",
          "tgn:7002731",
          "tgn:1000003",
          "tgn:1000074",
          "tgn:7029392"
        ],
        "placetype": [
          "aat:300008347"
        ],
        "id": 1042005,
        "name:xx": "Epanomí"
      }
    },
    {
      "geometry": {
        "type": "Point",
        "coordinates": [
          25.933333,
          39.166667
        ]
      },
      "type": "Feature",
      "properties": {
        "hierarchy": [
          "tgn:1042007",
          "tgn:7011163",
          "tgn:7002674",
          "tgn:1000003",
          "tgn:7002672",
          "tgn:1000074",
          "tgn:7029392"
        ],
        "placetype": [
          "aat:300008347"
        ],
        "id": 1042007,
        "name:xx": "Eressós"
      }
    }
  ]
}
