{
  "geometry": {
    "type": "Point",
    "coordinates": [
      -90.5667,
      42.4333
    ]
  },
  "type": "Feature",
  "properties": {
    "hierarchy": [
      "tgn:2541801",
      "tgn:1000001",
      "tgn:2000591",
      "tgn:7012149",
      "tgn:7007253",
      "tgn:7029392"
    ],
    "placetype": [
      "aat:300008791"
    ],
    "id": 2541801,
    "name:xx": "Ninemile Island"
  }
}
