{
  "geometry": {
    "type": "Point",
    "coordinates": [
      -90.15,
      37.8167
    ]
  },
  "type": "Feature",
  "properties": {
    "hierarchy": [
      "tgn:2460312",
      "tgn:1000001",
      "tgn:7012149",
      "tgn:2001240",
      "tgn:7007523",
      "tgn:7029392"
    ],
    "placetype": [
      "aat:300008706"
    ],
    "id": 2460312,
    "name:xx": "Little Saline Creek"
  }
}
