{
  "geometry": {
    "type": "Point",
    "coordinates": [
      -83.05,
      38.35
    ]
  },
  "type": "Feature",
  "properties": {
    "hierarchy": [
      "tgn:2365735",
      "tgn:1000001",
      "tgn:1002240",
      "tgn:7012149",
      "tgn:7007255",
      "tgn:7029392"
    ],
    "placetype": [
      "aat:300008761"
    ],
    "id": 2365735,
    "name:xx": "Gregory Hollow"
  }
}
