{
  "type": "FeatureCollection",
  "features": [
    {
      "geometry": {
        "type": "Point",
        "coordinates": [
          -109.0667,
          33.65
        ]
      },
      "type": "Feature",
      "properties": {
        "hierarchy": [
          "tgn:2542890",
          "tgn:1000001",
          "tgn:7006451",
          "tgn:2000095",
          "tgn:7012149",
          "tgn:7029392"
        ],
        "placetype": [
          "aat:300008697"
        ],
        "id": 2542890,
        "name:xx": "Nolan Spring"
      }
    },
    {
      "geometry": {
        "type": "Point",
        "coordinates": [
          -87.75,
          35.9833
        ]
      },
      "type": "Feature",
      "properties": {
        "hierarchy": [
          "tgn:2542891",
          "tgn:1000001",
          "tgn:7012149",
          "tgn:2001879",
          "tgn:7007825",
          "tgn:7029392"
        ],
        "placetype": [
          "aat:300008697"
        ],
        "id": 2542891,
        "name:xx": "Nolan Spring"
      }
    },
    {
      "geometry": {
        "type": "Point",
        "coordinates": [
          -111.9,
          34.8833
        ]
      },
      "type": "Feature",
      "properties": {
        "hierarchy": [
          "tgn:2542892",
          "tgn:1000001",
          "tgn:7006451",
          "tgn:7012149",
          "tgn:2000103",
          "tgn:7029392"
        ],
        "placetype": [
          "aat:300006191"
        ],
        "id": 2542892,
        "name:xx": "Nolan Tank"
      }
    },
    {
      "geometry": {
        "type": "Point",
        "coordinates": [
          -109.0333,
          33.6833
        ]
      },
      "type": "Feature",
      "properties": {
        "hierarchy": [
          "tgn:2542893",
          "tgn:1000001",
          "tgn:7006451",
          "tgn:2000095",
          "tgn:7012149",
          "tgn:7029392"
        ],
        "placetype": [
          "aat:300006191"
        ],
        "id": 2542893,
        "name:xx": "Nolan Tank"
      }
    },
    {
      "geometry": {
        "type": "Point",
        "coordinates": [
          -87.9333,
          33.2667
        ]
      },
      "type": "Feature",
      "properties": {
        "hierarchy": [
          "tgn:2542894",
          "tgn:7002659",
          "tgn:1000001",
          "tgn:7012149",
          "tgn:2000053",
          "tgn:7029392"
        ],
        "placetype": [
          "aat:300008347"
        ],
        "id": 2542894,
        "name:xx": "Noland"
      }
    },
    {
      "geometry": {
        "type": "Point",
        "coordinates": [
          -105.25,
          40.25
        ]
      },
      "type": "Feature",
      "properties": {
        "hierarchy": [
          "tgn:2542895",
          "tgn:1000001",
          "tgn:2000198",
          "tgn:7012149",
          "tgn:7007158",
          "tgn:7029392"
        ],
        "placetype": [
          "aat:300008347"
        ],
        "id": 2542895,
        "name:xx": "Noland"
      }
    },
    {
      "geometry": {
        "type": "Point",
        "coordinates": [
          -86.5333,
          32.4667
        ]
      },
      "type": "Feature",
      "properties": {
        "hierarchy": [
          "tgn:2542896",
          "tgn:2000000",
          "tgn:7002659",
          "tgn:1000001",
          "tgn:7012149",
          "tgn:7029392"
        ],
        "placetype": [
          "aat:300008706"
        ],
        "id": 2542896,
        "name:xx": "Noland Creek"
      }
    },
    {
      "geometry": {
        "type": "Point",
        "coordinates": [
          -108.9833,
          33.6833
        ]
      },
      "type": "Feature",
      "properties": {
        "hierarchy": [
          "tgn:2542897",
          "tgn:1000001",
          "tgn:7012149",
          "tgn:7029392"
        ],
        "placetype": [
          "aat:300008706"
        ],
        "id": 2542897,
        "name:xx": "Noland Creek"
      }
    },
    {
      "geometry": {
        "type": "Point",
        "coordinates": [
          -84.0333,
          37.8
        ]
      },
      "type": "Feature",
      "properties": {
        "hierarchy": [
          "tgn:2542898",
          "tgn:1000001",
          "tgn:7012149",
          "tgn:7007255",
          "tgn:7029392"
        ],
        "placetype": [
          "aat:300008706"
        ],
        "id": 2542898,
        "name:xx": "Noland Creek"
      }
    },
    {
      "geometry": {
        "type": "Point",
        "coordinates": [
          -80.5333,
          35.9167
        ]
      },
      "type": "Feature",
      "properties": {
        "hierarchy": [
          "tgn:2542899",
          "tgn:1000001",
          "tgn:7012149",
          "tgn:2001490",
          "tgn:7007709",
          "tgn:7029392"
        ],
        "placetype": [
          "aat:300008706"
        ],
        "id": 2542899,
        "name:xx": "Noland Creek"
      }
    }
  ]
}
