{
  "geometry": {
    "type": "Point",
    "coordinates": [
      -60.15,
      45.8333
    ]
  },
  "type": "Feature",
  "properties": {
    "hierarchy": [
      "tgn:1014431",
      "tgn:7013022",
      "tgn:7005685",
      "tgn:1000001",
      "tgn:7005802",
      "tgn:7029392"
    ],
    "placetype": [
      "aat:300008347"
    ],
    "id": 1014431,
    "name:xx": "Gabarus"
  }
}
