{
  "geometry": {
    "type": "Point",
    "coordinates": [
      -82.35,
      39.45
    ]
  },
  "type": "Feature",
  "properties": {
    "hierarchy": [
      "tgn:2082300",
      "tgn:1000001",
      "tgn:7012149",
      "tgn:2001613",
      "tgn:7007706",
      "tgn:7029392"
    ],
    "placetype": [
      "aat:300008347"
    ],
    "id": 2082300,
    "name:xx": "Union Furnace"
  }
}
