{
  "type": "FeatureCollection",
  "features": [
    {
      "geometry": {
        "type": "Point",
        "coordinates": [
          -94.95,
          32.6833
        ]
      },
      "type": "Feature",
      "properties": {
        "hierarchy": [
          "tgn:2701070",
          "tgn:1000001",
          "tgn:7012149",
          "tgn:1002966",
          "tgn:7007826",
          "tgn:7029392"
        ],
        "placetype": [
          "aat:300008706"
        ],
        "id": 2701070,
        "name:xx": "Sugar Creek"
      }
    },
    {
      "geometry": {
        "type": "Point",
        "coordinates": [
          -99.5167,
          28.7333
        ]
      },
      "type": "Feature",
      "properties": {
        "hierarchy": [
          "tgn:2701071",
          "tgn:1000001",
          "tgn:7012149",
          "tgn:2002100",
          "tgn:7007826",
          "tgn:7029392"
        ],
        "placetype": [
          "aat:300008706"
        ],
        "id": 2701071,
        "name:xx": "Sugar Creek"
      }
    },
    {
      "geometry": {
        "type": "Point",
        "coordinates": [
          -94.35,
          30.95
        ]
      },
      "type": "Feature",
      "properties": {
        "hierarchy": [
          "tgn:2701072",
          "tgn:1000001",
          "tgn:7012149",
          "tgn:1002959",
          "tgn:7007826",
          "tgn:7029392"
        ],
        "placetype": [
          "aat:300008706"
        ],
        "id": 2701072,
        "name:xx": "Sugar Creek"
      }
    },
    {
      "geometry": {
        "type": "Point",
        "coordinates": [
          -97.65,
          29.4333
        ]
      },
      "type": "Feature",
      "properties": {
        "hierarchy": [
          "tgn:2701073",
          "tgn:1000001",
          "tgn:7012149",
          "tgn:1002414",
          "tgn:7007826",
          "tgn:7029392"
        ],
        "placetype": [
          "aat:300008706"
        ],
        "id": 2701073,
        "name:xx": "Sugar Creek"
      }
    },
    {
      "geometry": {
        "type": "Point",
        "coordinates": [
          -79.55,
          37.8167
        ]
      },
      "type": "Feature",
      "properties": {
        "hierarchy": [
          "tgn:2701074",
          "tgn:1000001",
          "tgn:7012149",
          "tgn:2002186",
          "tgn:7007919",
          "tgn:7029392"
        ],
        "placetype": [
          "aat:300008706"
        ],
        "id": 2701074,
        "name:xx": "Sugar Creek"
      }
    },
    {
      "geometry": {
        "type": "Point",
        "coordinates": [
          -81.1833,
          37.8833
        ]
      },
      "type": "Feature",
      "properties": {
        "hierarchy": [
          "tgn:2701075",
          "tgn:1000001",
          "tgn:2002261",
          "tgn:7012149",
          "tgn:7013961",
          "tgn:7029392"
        ],
        "placetype": [
          "aat:300008706"
        ],
        "id": 2701075,
        "name:xx": "Sugar Creek"
      }
    },
    {
      "geometry": {
        "type": "Point",
        "coordinates": [
          -80.2333,
          38.2833
        ]
      },
      "type": "Feature",
      "properties": {
        "hierarchy": [
          "tgn:2701076",
          "tgn:1000001",
          "tgn:7012149",
          "tgn:2002287",
          "tgn:7013961",
          "tgn:7029392"
        ],
        "placetype": [
          "aat:300008706"
        ],
        "id": 2701076,
        "name:xx": "Sugar Creek"
      }
    },
    {
      "geometry": {
        "type": "Point",
        "coordinates": [
          -80.8167,
          38.7
        ]
      },
      "type": "Feature",
      "properties": {
        "hierarchy": [
          "tgn:2701078",
          "tgn:1000001",
          "tgn:2002256",
          "tgn:7012149",
          "tgn:7013961",
          "tgn:7029392"
        ],
        "placetype": [
          "aat:300008706"
        ],
        "id": 2701078,
        "name:xx": "Sugar Creek"
      }
    },
    {
      "geometry": {
        "type": "Point",
        "coordinates": [
          -80.1667,
          38.6
        ]
      },
      "type": "Feature",
      "properties": {
        "hierarchy": [
          "tgn:2701079",
          "tgn:1000001",
          "tgn:7012149",
          "tgn:7013961",
          "tgn:7029392"
        ],
        "placetype": [
          "aat:300008706"
        ],
        "id": 2701079,
        "name:xx": "Sugar Creek"
      }
    }
  ]
}
