{
  "type": "FeatureCollection",
  "features": [
    {
      "geometry": {
        "type": "Point",
        "coordinates": [
          -2.083333,
          39.55
        ]
      },
      "type": "Feature",
      "properties": {
        "hierarchy": [
          "tgn:7017510",
          "tgn:7002818",
          "tgn:1001647",
          "tgn:1000003",
          "tgn:1000095",
          "tgn:7029392"
        ],
        "placetype": [
          "aat:300008347",
          "aat:300000835",
          "aat:300008372"
        ],
        "id": 7017510,
        "name:xx": "Alarcón"
      }
    },
    {
      "geometry": {
        "type": "Point",
        "coordinates": [
          -2.4333,
          41.8
        ]
      },
      "type": "Feature",
      "properties": {
        "hierarchy": [
          "tgn:7017511",
          "tgn:7002842",
          "tgn:7001158",
          "tgn:1000003",
          "tgn:1000095",
          "tgn:7029392"
        ],
        "placetype": [
          "aat:300008347",
          "aat:300000810",
          "aat:300167671"
        ],
        "id": 7017511,
        "name:xx": "Numancia"
      }
    },
    {
      "geometry": {
        "type": "Point",
        "coordinates": [
          -116.2667,
          45.7833
        ]
      },
      "type": "Feature",
      "properties": {
        "hierarchy": [
          "tgn:7017514",
          "tgn:1000001",
          "tgn:7012149",
          "tgn:2000476",
          "tgn:7007250",
          "tgn:7029392"
        ],
        "placetype": [
          "aat:300386977",
          "aat:300132339"
        ],
        "id": 7017514,
        "name:xx": "Nez Perce National Historical Park"
      }
    },
    {
      "geometry": {
        "type": "Point",
        "coordinates": [
          2.1167,
          42.3833
        ]
      },
      "type": "Feature",
      "properties": {
        "hierarchy": [
          "tgn:7017516",
          "tgn:1000003",
          "tgn:7029392"
        ],
        "placetype": [
          "aat:300008795"
        ],
        "name:fr": "Puigmal",
        "id": 7017516,
        "name:es": "Puigmale"
      }
    }
  ]
}
