{
  "geometry": {
    "type": "Point",
    "coordinates": [
      30.8833,
      48.7833
    ]
  },
  "type": "Feature",
  "properties": {
    "hierarchy": [
      "tgn:1124222",
      "tgn:1000003",
      "tgn:7006660",
      "tgn:7029392"
    ],
    "placetype": [
      "aat:300008707"
    ],
    "id": 1124222,
    "name:xx": "Hnylyy Tikych"
  }
}
