{
  "geometry": {
    "type": "Point",
    "coordinates": [
      -81.1667,
      26.1833
    ]
  },
  "type": "Feature",
  "properties": {
    "hierarchy": [
      "tgn:2457630",
      "tgn:1000001",
      "tgn:1002289",
      "tgn:7012149",
      "tgn:7007240",
      "tgn:7029392"
    ],
    "placetype": [
      "aat:300008905"
    ],
    "id": 2457630,
    "name:xx": "Little Marsh"
  }
}
