{
  "geometry": {
    "type": "Point",
    "coordinates": [
      31.016667,
      29.316667
    ]
  },
  "type": "Feature",
  "properties": {
    "hierarchy": [
      "tgn:7533613",
      "tgn:7001242",
      "tgn:7001105",
      "tgn:7016833",
      "tgn:7029392"
    ],
    "placetype": [
      "aat:300387086"
    ],
    "name:en": "Lusātū, Baḩr",
    "id": 7533613
  }
}
