{
  "geometry": {
    "type": "Point",
    "coordinates": [
      44.4667,
      46.4167
    ]
  },
  "type": "Feature",
  "properties": {
    "hierarchy": [
      "tgn:1056381",
      "tgn:1000004",
      "tgn:7011497",
      "tgn:7002435",
      "tgn:7029392"
    ],
    "placetype": [
      "aat:300008347"
    ],
    "id": 1056381,
    "name:xx": "Leninskiy"
  }
}
