{
  "geometry": {
    "type": "Point",
    "coordinates": [
      -99.15,
      31.2167
    ]
  },
  "type": "Feature",
  "properties": {
    "hierarchy": [
      "tgn:2617392",
      "tgn:1000001",
      "tgn:7012149",
      "tgn:7007826",
      "tgn:7029392"
    ],
    "placetype": [
      "aat:300008706"
    ],
    "id": 2617392,
    "name:xx": "Richland Springs Creek"
  }
}
