{
  "type": "FeatureCollection",
  "features": [
    {
      "geometry": {
        "type": "Point",
        "coordinates": [
          -115.3833,
          38.3167
        ]
      },
      "type": "Feature",
      "properties": {
        "hierarchy": [
          "tgn:2400950",
          "tgn:1000001",
          "tgn:2001418",
          "tgn:7012149",
          "tgn:7007526",
          "tgn:7029392"
        ],
        "placetype": [
          "aat:300008697"
        ],
        "id": 2400950,
        "name:xx": "Horse Spring"
      }
    },
    {
      "geometry": {
        "type": "Point",
        "coordinates": [
          -119.3,
          39.5167
        ]
      },
      "type": "Feature",
      "properties": {
        "hierarchy": [
          "tgn:2400951",
          "tgn:1000001",
          "tgn:1002614",
          "tgn:7012149",
          "tgn:7007526",
          "tgn:7029392"
        ],
        "placetype": [
          "aat:300008697"
        ],
        "id": 2400951,
        "name:xx": "Horse Spring"
      }
    },
    {
      "geometry": {
        "type": "Point",
        "coordinates": [
          -119.95,
          39.7667
        ]
      },
      "type": "Feature",
      "properties": {
        "hierarchy": [
          "tgn:2400952",
          "tgn:1000001",
          "tgn:7012149",
          "tgn:1002999",
          "tgn:7007526",
          "tgn:7029392"
        ],
        "placetype": [
          "aat:300008697"
        ],
        "id": 2400952,
        "name:xx": "Horse Spring"
      }
    },
    {
      "geometry": {
        "type": "Point",
        "coordinates": [
          -115.6167,
          41.15
        ]
      },
      "type": "Feature",
      "properties": {
        "hierarchy": [
          "tgn:2400953",
          "tgn:1000001",
          "tgn:2001411",
          "tgn:7012149",
          "tgn:7007526",
          "tgn:7029392"
        ],
        "placetype": [
          "aat:300008697"
        ],
        "id": 2400953,
        "name:xx": "Horse Spring"
      }
    },
    {
      "geometry": {
        "type": "Point",
        "coordinates": [
          -119.05,
          41.2833
        ]
      },
      "type": "Feature",
      "properties": {
        "hierarchy": [
          "tgn:2400954",
          "tgn:1000001",
          "tgn:2001414",
          "tgn:7012149",
          "tgn:7007526",
          "tgn:7029392"
        ],
        "placetype": [
          "aat:300008697"
        ],
        "id": 2400954,
        "name:xx": "Horse Spring"
      }
    },
    {
      "geometry": {
        "type": "Point",
        "coordinates": [
          -114.5833,
          39.95
        ]
      },
      "type": "Feature",
      "properties": {
        "hierarchy": [
          "tgn:2400955",
          "tgn:1000001",
          "tgn:7012149",
          "tgn:2001420",
          "tgn:7007526",
          "tgn:7029392"
        ],
        "placetype": [
          "aat:300008697"
        ],
        "id": 2400955,
        "name:xx": "Horse Spring"
      }
    },
    {
      "geometry": {
        "type": "Point",
        "coordinates": [
          -104.65,
          32.1333
        ]
      },
      "type": "Feature",
      "properties": {
        "hierarchy": [
          "tgn:2400956",
          "tgn:1000001",
          "tgn:2001436",
          "tgn:7012149",
          "tgn:7007566",
          "tgn:7029392"
        ],
        "placetype": [
          "aat:300008697"
        ],
        "id": 2400956,
        "name:xx": "Horse Spring"
      }
    },
    {
      "geometry": {
        "type": "Point",
        "coordinates": [
          -105.7167,
          33.0333
        ]
      },
      "type": "Feature",
      "properties": {
        "hierarchy": [
          "tgn:2400957",
          "tgn:1000001",
          "tgn:7012149",
          "tgn:2001447",
          "tgn:7007566",
          "tgn:7029392"
        ],
        "placetype": [
          "aat:300008697"
        ],
        "id": 2400957,
        "name:xx": "Horse Spring"
      }
    },
    {
      "geometry": {
        "type": "Point",
        "coordinates": [
          -108.45,
          33.25
        ]
      },
      "type": "Feature",
      "properties": {
        "hierarchy": [
          "tgn:2400958",
          "tgn:1000001",
          "tgn:2001429",
          "tgn:7012149",
          "tgn:7007566",
          "tgn:7029392"
        ],
        "placetype": [
          "aat:300008697"
        ],
        "id": 2400958,
        "name:xx": "Horse Spring"
      }
    },
    {
      "geometry": {
        "type": "Point",
        "coordinates": [
          -107.2333,
          36.6333
        ]
      },
      "type": "Feature",
      "properties": {
        "hierarchy": [
          "tgn:2400959",
          "tgn:1000001",
          "tgn:7012149",
          "tgn:2001449",
          "tgn:7007566",
          "tgn:7029392"
        ],
        "placetype": [
          "aat:300008697"
        ],
        "id": 2400959,
        "name:xx": "Horse Spring"
      }
    }
  ]
}
