{
  "geometry": {
    "type": "Point",
    "coordinates": [
      -82.35,
      28.95
    ]
  },
  "type": "Feature",
  "properties": {
    "hierarchy": [
      "tgn:2588929",
      "tgn:1000001",
      "tgn:1002269",
      "tgn:7012149",
      "tgn:7007240",
      "tgn:7029392"
    ],
    "placetype": [
      "aat:300008791"
    ],
    "id": 2588929,
    "name:xx": "Pocket, The"
  }
}
