{
  "type": "FeatureCollection",
  "features": [
    {
      "geometry": {
        "type": "Point",
        "coordinates": [
          11.3,
          48.366667
        ]
      },
      "type": "Feature",
      "properties": {
        "hierarchy": [
          "tgn:7114160",
          "tgn:7003669",
          "tgn:1000003",
          "tgn:7000084",
          "tgn:7029392"
        ],
        "placetype": [
          "aat:300008347"
        ],
        "id": 7114160,
        "name:xx": "Riedhof"
      }
    },
    {
      "geometry": {
        "type": "Point",
        "coordinates": [
          11.116667,
          48.283333
        ]
      },
      "type": "Feature",
      "properties": {
        "hierarchy": [
          "tgn:7114161",
          "tgn:7003669",
          "tgn:1000003",
          "tgn:7000084",
          "tgn:7029392"
        ],
        "placetype": [
          "aat:300008347"
        ],
        "id": 7114161,
        "name:xx": "Riedhof"
      }
    },
    {
      "geometry": {
        "type": "Point",
        "coordinates": [
          11.466667,
          47.916667
        ]
      },
      "type": "Feature",
      "properties": {
        "hierarchy": [
          "tgn:7114162",
          "tgn:7003669",
          "tgn:1000003",
          "tgn:7000084",
          "tgn:7029392"
        ],
        "placetype": [
          "aat:300008347"
        ],
        "id": 7114162,
        "name:xx": "Riedhof"
      }
    },
    {
      "geometry": {
        "type": "Point",
        "coordinates": [
          10.683333,
          47.766667
        ]
      },
      "type": "Feature",
      "properties": {
        "hierarchy": [
          "tgn:7114163",
          "tgn:7003669",
          "tgn:1000003",
          "tgn:7000084",
          "tgn:7029392"
        ],
        "placetype": [
          "aat:300008347"
        ],
        "id": 7114163,
        "name:xx": "Riedhof"
      }
    },
    {
      "geometry": {
        "type": "Point",
        "coordinates": [
          10.766667,
          47.75
        ]
      },
      "type": "Feature",
      "properties": {
        "hierarchy": [
          "tgn:7114164",
          "tgn:7003669",
          "tgn:1000003",
          "tgn:7000084",
          "tgn:7029392"
        ],
        "placetype": [
          "aat:300008347"
        ],
        "id": 7114164,
        "name:xx": "Riedhof"
      }
    },
    {
      "geometry": {
        "type": "Point",
        "coordinates": [
          8.483333,
          49.416667
        ]
      },
      "type": "Feature",
      "properties": {
        "hierarchy": [
          "tgn:7114165",
          "tgn:1000003",
          "tgn:7003682",
          "tgn:7000084",
          "tgn:7029392"
        ],
        "placetype": [
          "aat:300000206"
        ],
        "id": 7114165,
        "name:xx": "Riedhof"
      }
    },
    {
      "geometry": {
        "type": "Point",
        "coordinates": [
          12.733333,
          49.133333
        ]
      },
      "type": "Feature",
      "properties": {
        "hierarchy": [
          "tgn:7114166",
          "tgn:7003669",
          "tgn:1000003",
          "tgn:7000084",
          "tgn:7029392"
        ],
        "placetype": [
          "aat:300000206"
        ],
        "id": 7114166,
        "name:xx": "Riedhof"
      }
    },
    {
      "geometry": {
        "type": "Point",
        "coordinates": [
          11.816667,
          48.95
        ]
      },
      "type": "Feature",
      "properties": {
        "hierarchy": [
          "tgn:7114168",
          "tgn:7003669",
          "tgn:1000003",
          "tgn:7000084",
          "tgn:7029392"
        ],
        "placetype": [
          "aat:300000206"
        ],
        "id": 7114168,
        "name:xx": "Riedhof"
      }
    },
    {
      "geometry": {
        "type": "Point",
        "coordinates": [
          12.816667,
          48.9
        ]
      },
      "type": "Feature",
      "properties": {
        "hierarchy": [
          "tgn:7114169",
          "tgn:7003669",
          "tgn:1000003",
          "tgn:7000084",
          "tgn:7029392"
        ],
        "placetype": [
          "aat:300000206"
        ],
        "id": 7114169,
        "name:xx": "Riedhof"
      }
    }
  ]
}
