{
  "geometry": {
    "type": "Point",
    "coordinates": [
      -80.4667,
      37.8167
    ]
  },
  "type": "Feature",
  "properties": {
    "hierarchy": [
      "tgn:2713337",
      "tgn:1000001",
      "tgn:7012149",
      "tgn:2002264",
      "tgn:7013961",
      "tgn:7029392"
    ],
    "placetype": [
      "aat:300008746"
    ],
    "id": 2713337,
    "name:xx": "Taylors Falls Cave"
  }
}
