{
  "type": "FeatureCollection",
  "features": [
    {
      "geometry": {
        "type": "Point",
        "coordinates": [
          -72.433333,
          -36.733333
        ]
      },
      "type": "Feature",
      "properties": {
        "hierarchy": [
          "tgn:7311830",
          "tgn:1001637",
          "tgn:1000049",
          "tgn:1000002",
          "tgn:7029392"
        ],
        "placetype": [
          "aat:300000206"
        ],
        "id": 7311830,
        "name:xx": "Las Mercedes"
      }
    },
    {
      "geometry": {
        "type": "Point",
        "coordinates": [
          -72.25,
          -35.733333
        ]
      },
      "type": "Feature",
      "properties": {
        "hierarchy": [
          "tgn:7311831",
          "tgn:1001705",
          "tgn:1000049",
          "tgn:1000002",
          "tgn:7029392"
        ],
        "placetype": [
          "aat:300000206"
        ],
        "id": 7311831,
        "name:xx": "Las Mercedes"
      }
    },
    {
      "geometry": {
        "type": "Point",
        "coordinates": [
          -70.833333,
          -34.266667
        ]
      },
      "type": "Feature",
      "properties": {
        "hierarchy": [
          "tgn:7311832",
          "tgn:1001695",
          "tgn:1000049",
          "tgn:1000002",
          "tgn:7029392"
        ],
        "placetype": [
          "aat:300000206"
        ],
        "id": 7311832,
        "name:xx": "Las Mercedes"
      }
    },
    {
      "geometry": {
        "type": "Point",
        "coordinates": [
          -70.883333,
          -33.783333
        ]
      },
      "type": "Feature",
      "properties": {
        "hierarchy": [
          "tgn:7311833",
          "tgn:1001708",
          "tgn:1000049",
          "tgn:1000002",
          "tgn:7029392"
        ],
        "placetype": [
          "aat:300000206"
        ],
        "id": 7311833,
        "name:xx": "Las Mercedes"
      }
    },
    {
      "geometry": {
        "type": "Point",
        "coordinates": [
          -71.183333,
          -33.5
        ]
      },
      "type": "Feature",
      "properties": {
        "hierarchy": [
          "tgn:7311834",
          "tgn:1001708",
          "tgn:1000049",
          "tgn:1000002",
          "tgn:7029392"
        ],
        "placetype": [
          "aat:300000206"
        ],
        "id": 7311834,
        "name:xx": "Las Mercedes"
      }
    },
    {
      "geometry": {
        "type": "Point",
        "coordinates": [
          -70.533333,
          -29.916667
        ]
      },
      "type": "Feature",
      "properties": {
        "hierarchy": [
          "tgn:7311835",
          "tgn:1001657",
          "tgn:1000049",
          "tgn:1000002",
          "tgn:7029392"
        ],
        "placetype": [
          "aat:300000206"
        ],
        "id": 7311835,
        "name:xx": "Las Mercedes"
      }
    },
    {
      "geometry": {
        "type": "Point",
        "coordinates": [
          -71.05,
          -34.733333
        ]
      },
      "type": "Feature",
      "properties": {
        "hierarchy": [
          "tgn:7311836",
          "tgn:1001695",
          "tgn:1000049",
          "tgn:1000002",
          "tgn:7029392"
        ],
        "placetype": [
          "aat:300004792"
        ],
        "id": 7311836,
        "name:xx": "Las Mercedes"
      }
    },
    {
      "geometry": {
        "type": "Point",
        "coordinates": [
          -71.516667,
          -33.516667
        ]
      },
      "type": "Feature",
      "properties": {
        "hierarchy": [
          "tgn:7311837",
          "tgn:1001708",
          "tgn:1000049",
          "tgn:1000002",
          "tgn:7029392"
        ],
        "placetype": [
          "aat:300387200"
        ],
        "id": 7311837,
        "name:xx": "Las Mellizas"
      }
    },
    {
      "geometry": {
        "type": "Point",
        "coordinates": [
          -70.833333,
          -32.95
        ]
      },
      "type": "Feature",
      "properties": {
        "hierarchy": [
          "tgn:7311838",
          "tgn:1001708",
          "tgn:1000049",
          "tgn:1000002",
          "tgn:7029392"
        ],
        "placetype": [
          "aat:300266554",
          "aat:300008699"
        ],
        "id": 7311838,
        "name:xx": "Las Mazas, Estero de"
      }
    },
    {
      "geometry": {
        "type": "Point",
        "coordinates": [
          -70.9,
          -32.933333
        ]
      },
      "type": "Feature",
      "properties": {
        "hierarchy": [
          "tgn:7311839",
          "tgn:1001768",
          "tgn:1000049",
          "tgn:1000002",
          "tgn:7029392"
        ],
        "placetype": [
          "aat:300000206"
        ],
        "id": 7311839,
        "name:xx": "Las Mazas"
      }
    }
  ]
}
