{
  "geometry": {
    "type": "Point",
    "coordinates": [
      27.3725,
      36.390833
    ]
  },
  "type": "Feature",
  "properties": {
    "hierarchy": [
      "tgn:7220458",
      "tgn:7011330",
      "tgn:7002674",
      "tgn:1000003",
      "tgn:1000074",
      "tgn:7029392"
    ],
    "placetype": [
      "aat:300132316"
    ],
    "id": 7220458,
    "name:xx": "Stavrós, Órmos"
  }
}
