{
  "geometry": {
    "type": "Point",
    "coordinates": [
      -79.9167,
      38.2333
    ]
  },
  "type": "Feature",
  "properties": {
    "hierarchy": [
      "tgn:2522744",
      "tgn:1000001",
      "tgn:7012149",
      "tgn:2002287",
      "tgn:7013961",
      "tgn:7029392"
    ],
    "placetype": [
      "aat:300008746"
    ],
    "id": 2522744,
    "name:xx": "Moore Cave Number 2"
  }
}
