{
  "geometry": {
    "type": "Point",
    "coordinates": [
      -108.7667,
      32.2833
    ]
  },
  "type": "Feature",
  "properties": {
    "hierarchy": [
      "tgn:7019485",
      "tgn:1000001",
      "tgn:7012149",
      "tgn:2001440",
      "tgn:7007566",
      "tgn:7029392"
    ],
    "placetype": [
      "aat:300000390"
    ],
    "id": 7019485,
    "name:xx": "Nellie Gray Mine"
  }
}
