{
  "type": "FeatureCollection",
  "features": [
    {
      "geometry": {
        "type": "Point",
        "coordinates": [
          -114.8667,
          42.85
        ]
      },
      "type": "Feature",
      "properties": {
        "hierarchy": [
          "tgn:2173320",
          "tgn:1000001",
          "tgn:7012149",
          "tgn:2000475",
          "tgn:7007250",
          "tgn:7029392"
        ],
        "placetype": [
          "aat:300008706"
        ],
        "id": 2173320,
        "name:xx": "Birch Creek"
      }
    },
    {
      "geometry": {
        "type": "Point",
        "coordinates": [
          -111.5833,
          43.4833
        ]
      },
      "type": "Feature",
      "properties": {
        "hierarchy": [
          "tgn:2173321",
          "tgn:1000001",
          "tgn:2000461",
          "tgn:7012149",
          "tgn:7007250",
          "tgn:7029392"
        ],
        "placetype": [
          "aat:300008706"
        ],
        "id": 2173321,
        "name:xx": "Birch Creek"
      }
    },
    {
      "geometry": {
        "type": "Point",
        "coordinates": [
          -115.15,
          46.8667
        ]
      },
      "type": "Feature",
      "properties": {
        "hierarchy": [
          "tgn:2173322",
          "tgn:1000001",
          "tgn:2000469",
          "tgn:7012149",
          "tgn:7007250",
          "tgn:7029392"
        ],
        "placetype": [
          "aat:300008706"
        ],
        "id": 2173322,
        "name:xx": "Birch Creek"
      }
    },
    {
      "geometry": {
        "type": "Point",
        "coordinates": [
          -113.2167,
          42
        ]
      },
      "type": "Feature",
      "properties": {
        "hierarchy": [
          "tgn:2173323",
          "tgn:1000001",
          "tgn:7012149",
          "tgn:7029392"
        ],
        "placetype": [
          "aat:300008706"
        ],
        "id": 2173323,
        "name:xx": "Birch Creek"
      }
    },
    {
      "geometry": {
        "type": "Point",
        "coordinates": [
          -87.7167,
          38.85
        ]
      },
      "type": "Feature",
      "properties": {
        "hierarchy": [
          "tgn:2173324",
          "tgn:1000001",
          "tgn:7012149",
          "tgn:7007251",
          "tgn:7029392"
        ],
        "placetype": [
          "aat:300008706"
        ],
        "id": 2173324,
        "name:xx": "Birch Creek"
      }
    },
    {
      "geometry": {
        "type": "Point",
        "coordinates": [
          -87,
          38.4333
        ]
      },
      "type": "Feature",
      "properties": {
        "hierarchy": [
          "tgn:2173325",
          "tgn:1000001",
          "tgn:7012149",
          "tgn:7007252",
          "tgn:7029392"
        ],
        "placetype": [
          "aat:300008706"
        ],
        "id": 2173325,
        "name:xx": "Birch Creek"
      }
    },
    {
      "geometry": {
        "type": "Point",
        "coordinates": [
          -91.8667,
          41.5167
        ]
      },
      "type": "Feature",
      "properties": {
        "hierarchy": [
          "tgn:2173326",
          "tgn:1000001",
          "tgn:7012149",
          "tgn:7007253",
          "tgn:7029392"
        ],
        "placetype": [
          "aat:300008706"
        ],
        "id": 2173326,
        "name:xx": "Birch Creek"
      }
    },
    {
      "geometry": {
        "type": "Point",
        "coordinates": [
          -91.5333,
          40.5833
        ]
      },
      "type": "Feature",
      "properties": {
        "hierarchy": [
          "tgn:2173327",
          "tgn:1000001",
          "tgn:7012149",
          "tgn:2000616",
          "tgn:7007253",
          "tgn:7029392"
        ],
        "placetype": [
          "aat:300008706"
        ],
        "id": 2173327,
        "name:xx": "Birch Creek"
      }
    },
    {
      "geometry": {
        "type": "Point",
        "coordinates": [
          -96.0333,
          37.0333
        ]
      },
      "type": "Feature",
      "properties": {
        "hierarchy": [
          "tgn:2173328",
          "tgn:1000001",
          "tgn:2000669",
          "tgn:7012149",
          "tgn:7007254",
          "tgn:7029392"
        ],
        "placetype": [
          "aat:300008706"
        ],
        "id": 2173328,
        "name:xx": "Birch Creek"
      }
    },
    {
      "geometry": {
        "type": "Point",
        "coordinates": [
          -90.7667,
          30.85
        ]
      },
      "type": "Feature",
      "properties": {
        "hierarchy": [
          "tgn:2173329",
          "tgn:1000001",
          "tgn:7012149",
          "tgn:2000899",
          "tgn:7007256",
          "tgn:7029392"
        ],
        "placetype": [
          "aat:300008706"
        ],
        "id": 2173329,
        "name:xx": "Birch Creek"
      }
    }
  ]
}
