{
  "geometry": {
    "type": "Point",
    "coordinates": [
      -78.0667,
      40.7667
    ]
  },
  "type": "Feature",
  "properties": {
    "hierarchy": [
      "tgn:2182803",
      "tgn:1000001",
      "tgn:1002249",
      "tgn:7012149",
      "tgn:7007710",
      "tgn:7029392"
    ],
    "placetype": [
      "aat:300008761"
    ],
    "id": 2182803,
    "name:xx": "Blue Springs Hollow"
  }
}
