{
  "type": "FeatureCollection",
  "features": [
    {
      "geometry": {
        "type": "Point",
        "coordinates": [
          -93.5167,
          46.7333
        ]
      },
      "type": "Feature",
      "properties": {
        "hierarchy": [
          "tgn:2611330",
          "tgn:2000999",
          "tgn:1000001",
          "tgn:7012149",
          "tgn:7007521",
          "tgn:7029392"
        ],
        "placetype": [
          "aat:300008680"
        ],
        "id": 2611330,
        "name:xx": "Red Lake"
      }
    },
    {
      "geometry": {
        "type": "Point",
        "coordinates": [
          -93.2667,
          47.8167
        ]
      },
      "type": "Feature",
      "properties": {
        "hierarchy": [
          "tgn:2611331",
          "tgn:1000001",
          "tgn:7012149",
          "tgn:2001029",
          "tgn:7007521",
          "tgn:7029392"
        ],
        "placetype": [
          "aat:300008680"
        ],
        "id": 2611331,
        "name:xx": "Red Lake"
      }
    },
    {
      "geometry": {
        "type": "Point",
        "coordinates": [
          -90.2167,
          34.3167
        ]
      },
      "type": "Feature",
      "properties": {
        "hierarchy": [
          "tgn:2611332",
          "tgn:1000001",
          "tgn:7012149",
          "tgn:2001145",
          "tgn:7007522",
          "tgn:7029392"
        ],
        "placetype": [
          "aat:300008680"
        ],
        "id": 2611332,
        "name:xx": "Red Lake"
      }
    },
    {
      "geometry": {
        "type": "Point",
        "coordinates": [
          -111.8667,
          44.9667
        ]
      },
      "type": "Feature",
      "properties": {
        "hierarchy": [
          "tgn:2611333",
          "tgn:1000001",
          "tgn:7012149",
          "tgn:2001288",
          "tgn:7007524",
          "tgn:7029392"
        ],
        "placetype": [
          "aat:300008680"
        ],
        "id": 2611333,
        "name:xx": "Red Lake"
      }
    },
    {
      "geometry": {
        "type": "Point",
        "coordinates": [
          -112.7,
          47.5833
        ]
      },
      "type": "Feature",
      "properties": {
        "hierarchy": [
          "tgn:2611334",
          "tgn:1000001",
          "tgn:7012149",
          "tgn:2001284",
          "tgn:7007524",
          "tgn:7029392"
        ],
        "placetype": [
          "aat:300008680"
        ],
        "id": 2611334,
        "name:xx": "Red Lake"
      }
    },
    {
      "geometry": {
        "type": "Point",
        "coordinates": [
          -114.3167,
          47.8667
        ]
      },
      "type": "Feature",
      "properties": {
        "hierarchy": [
          "tgn:2611335",
          "tgn:1000001",
          "tgn:7012149",
          "tgn:2001283",
          "tgn:7007524",
          "tgn:7029392"
        ],
        "placetype": [
          "aat:300008680"
        ],
        "id": 2611335,
        "name:xx": "Red Lake"
      }
    },
    {
      "geometry": {
        "type": "Point",
        "coordinates": [
          -107.5,
          32.0667
        ]
      },
      "type": "Feature",
      "properties": {
        "hierarchy": [
          "tgn:2611336",
          "tgn:1000001",
          "tgn:7012149",
          "tgn:2001444",
          "tgn:7007566",
          "tgn:7029392"
        ],
        "placetype": [
          "aat:300008680"
        ],
        "id": 2611336,
        "name:xx": "Red Lake"
      }
    },
    {
      "geometry": {
        "type": "Point",
        "coordinates": [
          -104.6833,
          32.1833
        ]
      },
      "type": "Feature",
      "properties": {
        "hierarchy": [
          "tgn:2611337",
          "tgn:1000001",
          "tgn:2001436",
          "tgn:7012149",
          "tgn:7007566",
          "tgn:7029392"
        ],
        "placetype": [
          "aat:300008680"
        ],
        "id": 2611337,
        "name:xx": "Red Lake"
      }
    },
    {
      "geometry": {
        "type": "Point",
        "coordinates": [
          -106.8167,
          32.7
        ]
      },
      "type": "Feature",
      "properties": {
        "hierarchy": [
          "tgn:2611338",
          "tgn:1000001",
          "tgn:2001435",
          "tgn:7012149",
          "tgn:7007566",
          "tgn:7029392"
        ],
        "placetype": [
          "aat:300008680"
        ],
        "id": 2611338,
        "name:xx": "Red Lake"
      }
    },
    {
      "geometry": {
        "type": "Point",
        "coordinates": [
          -105.35,
          33.2
        ]
      },
      "type": "Feature",
      "properties": {
        "hierarchy": [
          "tgn:2611339",
          "tgn:1000001",
          "tgn:7012149",
          "tgn:2001447",
          "tgn:7007566",
          "tgn:7029392"
        ],
        "placetype": [
          "aat:300008680"
        ],
        "id": 2611339,
        "name:xx": "Red Lake"
      }
    }
  ]
}
