{
  "geometry": {
    "type": "Point",
    "coordinates": [
      -83.4833,
      32.4833
    ]
  },
  "type": "Feature",
  "properties": {
    "hierarchy": [
      "tgn:2024698",
      "tgn:1000001",
      "tgn:7012149",
      "tgn:2000434",
      "tgn:7007248",
      "tgn:7029392"
    ],
    "placetype": [
      "aat:300387016"
    ],
    "id": 2024698,
    "name:xx": "Westlake"
  }
}
