{
  "geometry": {
    "type": "Point",
    "coordinates": [
      -93.8167,
      38.8167
    ]
  },
  "type": "Feature",
  "properties": {
    "hierarchy": [
      "tgn:2364768",
      "tgn:1000001",
      "tgn:7012149",
      "tgn:2001210",
      "tgn:7007523",
      "tgn:7029392"
    ],
    "placetype": [
      "aat:300008347"
    ],
    "id": 2364768,
    "name:xx": "Greendoor"
  }
}
