{
  "geometry": {
    "type": "Point",
    "coordinates": [
      -86.5833,
      37.15
    ]
  },
  "type": "Feature",
  "properties": {
    "hierarchy": [
      "tgn:2586097",
      "tgn:1000001",
      "tgn:7012149",
      "tgn:2000848",
      "tgn:7007255",
      "tgn:7029392"
    ],
    "placetype": [
      "aat:300266640"
    ],
    "id": 2586097,
    "name:xx": "Pisgah Ridge"
  }
}
