{
  "geometry": {
    "type": "Point",
    "coordinates": [
      -120.0833,
      38.8833
    ]
  },
  "type": "Feature",
  "properties": {
    "hierarchy": [
      "tgn:2226370",
      "tgn:1000001",
      "tgn:7012149",
      "tgn:1002350",
      "tgn:7007157",
      "tgn:7029392"
    ],
    "placetype": [
      "aat:300008706"
    ],
    "id": 2226370,
    "name:xx": "Cathedral Creek"
  }
}
