{
  "geometry": {
    "type": "Point",
    "coordinates": [
      -82.75,
      43.7333
    ]
  },
  "type": "Feature",
  "properties": {
    "hierarchy": [
      "tgn:2253529",
      "tgn:1000001",
      "tgn:7012149",
      "tgn:2000964",
      "tgn:7007520",
      "tgn:7029392"
    ],
    "placetype": [
      "aat:300006075"
    ],
    "id": 2253529,
    "name:xx": "Cook Drain"
  }
}
