{
  "geometry": {
    "type": "Point",
    "coordinates": [
      -123.5833,
      46.3167
    ]
  },
  "type": "Feature",
  "properties": {
    "hierarchy": [
      "tgn:2716093",
      "tgn:1000001",
      "tgn:7012149",
      "tgn:1002979",
      "tgn:7007920",
      "tgn:7029392"
    ],
    "placetype": [
      "aat:300008706"
    ],
    "id": 2716093,
    "name:xx": "Thadbar Creek"
  }
}
