{
  "geometry": {
    "type": "Point",
    "coordinates": [
      -113.6833,
      43.4833
    ]
  },
  "type": "Feature",
  "properties": {
    "hierarchy": [
      "tgn:2306669",
      "tgn:1000001",
      "tgn:7012149",
      "tgn:7007250",
      "tgn:7029392"
    ],
    "placetype": [
      "aat:300008706"
    ],
    "id": 2306669,
    "name:xx": "East Fork Fish Creek"
  }
}
