{
  "geometry": {
    "type": "Point",
    "coordinates": [
      -111.5833,
      46.8833
    ]
  },
  "type": "Feature",
  "properties": {
    "hierarchy": [
      "tgn:2314608",
      "tgn:1000001",
      "tgn:7012149",
      "tgn:2001289",
      "tgn:7007524",
      "tgn:7029392"
    ],
    "placetype": [
      "aat:300266640"
    ],
    "id": 2314608,
    "name:xx": "Elk Ridge"
  }
}
