{
  "geometry": {
    "type": "Point",
    "coordinates": [
      -106.1333,
      41.5667
    ]
  },
  "type": "Feature",
  "properties": {
    "hierarchy": [
      "tgn:2219646",
      "tgn:1000001",
      "tgn:7012149",
      "tgn:7007923",
      "tgn:7029392"
    ],
    "placetype": [
      "aat:300006075"
    ],
    "id": 2219646,
    "name:xx": "Canon Ditch"
  }
}
