{
  "geometry": {
    "type": "Point",
    "coordinates": [
      114.1667,
      35.6833
    ]
  },
  "type": "Feature",
  "properties": {
    "hierarchy": [
      "tgn:1070464",
      "tgn:1000004",
      "tgn:7016672",
      "tgn:1000111",
      "tgn:7029392"
    ],
    "placetype": [
      "aat:300008347"
    ],
    "id": 1070464,
    "name:xx": "Miaokou"
  }
}
