{
  "type": "FeatureCollection",
  "features": [
    {
      "geometry": {
        "type": "Point",
        "coordinates": [
          -104.8667,
          32.85
        ]
      },
      "type": "Feature",
      "properties": {
        "hierarchy": [
          "tgn:2370620",
          "tgn:1000001",
          "tgn:7012149",
          "tgn:7007566",
          "tgn:7029392"
        ],
        "placetype": [
          "aat:300008761"
        ],
        "id": 2370620,
        "name:xx": "Hackberry Draw"
      }
    },
    {
      "geometry": {
        "type": "Point",
        "coordinates": [
          -99.6333,
          29.4333
        ]
      },
      "type": "Feature",
      "properties": {
        "hierarchy": [
          "tgn:2370621",
          "tgn:1000001",
          "tgn:7012149",
          "tgn:2002087",
          "tgn:7007826",
          "tgn:7029392"
        ],
        "placetype": [
          "aat:300008761"
        ],
        "id": 2370621,
        "name:xx": "Hackberry Draw"
      }
    },
    {
      "geometry": {
        "type": "Point",
        "coordinates": [
          -103.8333,
          29.9833
        ]
      },
      "type": "Feature",
      "properties": {
        "hierarchy": [
          "tgn:2370622",
          "tgn:1000001",
          "tgn:7012149",
          "tgn:7007826",
          "tgn:7029392"
        ],
        "placetype": [
          "aat:300008761"
        ],
        "id": 2370622,
        "name:xx": "Hackberry Draw"
      }
    },
    {
      "geometry": {
        "type": "Point",
        "coordinates": [
          -101.35,
          32.5667
        ]
      },
      "type": "Feature",
      "properties": {
        "hierarchy": [
          "tgn:2370623",
          "tgn:1000001",
          "tgn:2001943",
          "tgn:7012149",
          "tgn:7007826",
          "tgn:7029392"
        ],
        "placetype": [
          "aat:300008761"
        ],
        "id": 2370623,
        "name:xx": "Hackberry Draw"
      }
    },
    {
      "geometry": {
        "type": "Point",
        "coordinates": [
          -102.4667,
          30.5833
        ]
      },
      "type": "Feature",
      "properties": {
        "hierarchy": [
          "tgn:2370624",
          "tgn:1000001",
          "tgn:7012149",
          "tgn:2002055",
          "tgn:7007826",
          "tgn:7029392"
        ],
        "placetype": [
          "aat:300008761"
        ],
        "id": 2370624,
        "name:xx": "Hackberry Draw"
      }
    },
    {
      "geometry": {
        "type": "Point",
        "coordinates": [
          -103.9167,
          31
        ]
      },
      "type": "Feature",
      "properties": {
        "hierarchy": [
          "tgn:2370625",
          "tgn:1000001",
          "tgn:7012149",
          "tgn:2002062",
          "tgn:7007826",
          "tgn:7029392"
        ],
        "placetype": [
          "aat:300008761"
        ],
        "id": 2370625,
        "name:xx": "Hackberry Draw"
      }
    },
    {
      "geometry": {
        "type": "Point",
        "coordinates": [
          -101,
          33.5833
        ]
      },
      "type": "Feature",
      "properties": {
        "hierarchy": [
          "tgn:2370626",
          "tgn:1000001",
          "tgn:7012149",
          "tgn:2001974",
          "tgn:7007826",
          "tgn:7029392"
        ],
        "placetype": [
          "aat:300008761"
        ],
        "id": 2370626,
        "name:xx": "Hackberry Draw"
      }
    },
    {
      "geometry": {
        "type": "Point",
        "coordinates": [
          -100.85,
          33.9833
        ]
      },
      "type": "Feature",
      "properties": {
        "hierarchy": [
          "tgn:2370627",
          "tgn:1000001",
          "tgn:7012149",
          "tgn:2002046",
          "tgn:7007826",
          "tgn:7029392"
        ],
        "placetype": [
          "aat:300008761"
        ],
        "id": 2370627,
        "name:xx": "Hackberry Draw"
      }
    },
    {
      "geometry": {
        "type": "Point",
        "coordinates": [
          -110.9167,
          33.1333
        ]
      },
      "type": "Feature",
      "properties": {
        "hierarchy": [
          "tgn:2370628",
          "tgn:1000001",
          "tgn:7006451",
          "tgn:7012149",
          "tgn:2000101",
          "tgn:7029392"
        ],
        "placetype": [
          "aat:300008761"
        ],
        "id": 2370628,
        "name:xx": "Hackberry Gulch"
      }
    },
    {
      "geometry": {
        "type": "Point",
        "coordinates": [
          -117.0667,
          46.0667
        ]
      },
      "type": "Feature",
      "properties": {
        "hierarchy": [
          "tgn:2370629",
          "tgn:2002239",
          "tgn:1000001",
          "tgn:7012149",
          "tgn:7007920",
          "tgn:7029392"
        ],
        "placetype": [
          "aat:300008761"
        ],
        "id": 2370629,
        "name:xx": "Hackberry Gulch"
      }
    }
  ]
}
