{
  "geometry": {
    "type": "Point",
    "coordinates": [
      3.4333,
      44.1833
    ]
  },
  "type": "Feature",
  "properties": {
    "hierarchy": [
      "tgn:1034377",
      "tgn:1000003",
      "tgn:7002885",
      "tgn:1000070",
      "tgn:7029392"
    ],
    "placetype": [
      "aat:300008347"
    ],
    "id": 1034377,
    "name:xx": "Meyrueis"
  }
}
