{
  "type": "FeatureCollection",
  "features": [
    {
      "geometry": {
        "type": "Point",
        "coordinates": [
          31.525953,
          30.822891
        ]
      },
      "type": "Feature",
      "properties": {
        "hierarchy": [
          "tgn:7543440",
          "tgn:7001242",
          "tgn:1001059",
          "tgn:7016833",
          "tgn:7029392"
        ],
        "placetype": [
          "aat:300008347"
        ],
        "id": 7543440,
        "name:xx": "Manshīyat 'Izzat"
      }
    },
    {
      "geometry": {
        "type": "Point",
        "coordinates": [
          31.655123,
          30.765685
        ]
      },
      "type": "Feature",
      "properties": {
        "hierarchy": [
          "tgn:7543441",
          "tgn:7001242",
          "tgn:7016833",
          "tgn:1001113",
          "tgn:7029392"
        ],
        "placetype": [
          "aat:300008347"
        ],
        "id": 7543441,
        "name:xx": "Kafr an Nazlah"
      }
    },
    {
      "geometry": {
        "type": "Point",
        "coordinates": [
          31.737895,
          30.93244
        ]
      },
      "type": "Feature",
      "properties": {
        "hierarchy": [
          "tgn:7543442",
          "tgn:7001242",
          "tgn:7016833",
          "tgn:1001113",
          "tgn:7029392"
        ],
        "placetype": [
          "aat:300008347"
        ],
        "id": 7543442,
        "name:xx": "As Sa'ādāt"
      }
    },
    {
      "geometry": {
        "type": "Point",
        "coordinates": [
          31.66159,
          30.789582
        ]
      },
      "type": "Feature",
      "properties": {
        "hierarchy": [
          "tgn:7543443",
          "tgn:7001242",
          "tgn:7016833",
          "tgn:1001113",
          "tgn:7029392"
        ],
        "placetype": [
          "aat:300008347"
        ],
        "id": 7543443,
        "name:xx": "'Izbat 'Abd al Majīd al Mīhilmī"
      }
    },
    {
      "geometry": {
        "type": "Point",
        "coordinates": [
          31.652632,
          30.793552
        ]
      },
      "type": "Feature",
      "properties": {
        "hierarchy": [
          "tgn:7543444",
          "tgn:7001242",
          "tgn:7016833",
          "tgn:1001113",
          "tgn:7029392"
        ],
        "placetype": [
          "aat:300008347"
        ],
        "id": 7543444,
        "name:xx": "'Izbat Minashshah"
      }
    },
    {
      "geometry": {
        "type": "Point",
        "coordinates": [
          31.660102,
          30.807214
        ]
      },
      "type": "Feature",
      "properties": {
        "hierarchy": [
          "tgn:7543445",
          "tgn:7001242",
          "tgn:7016833",
          "tgn:1001113",
          "tgn:7029392"
        ],
        "placetype": [
          "aat:300008347"
        ],
        "id": 7543445,
        "name:xx": "'Izbat Idrīs"
      }
    },
    {
      "geometry": {
        "type": "Point",
        "coordinates": [
          31.669111,
          30.799261
        ]
      },
      "type": "Feature",
      "properties": {
        "hierarchy": [
          "tgn:7543446",
          "tgn:7001242",
          "tgn:7016833",
          "tgn:1001113",
          "tgn:7029392"
        ],
        "placetype": [
          "aat:300008347"
        ],
        "id": 7543446,
        "name:xx": "'Izbat at Tall"
      }
    },
    {
      "geometry": {
        "type": "Point",
        "coordinates": [
          31.714834,
          30.92214
        ]
      },
      "type": "Feature",
      "properties": {
        "hierarchy": [
          "tgn:7543447",
          "tgn:7001242",
          "tgn:7016833",
          "tgn:1001113",
          "tgn:7029392"
        ],
        "placetype": [
          "aat:300008347"
        ],
        "id": 7543447,
        "name:xx": "Banī Manşūr"
      }
    },
    {
      "geometry": {
        "type": "Point",
        "coordinates": [
          31.618926,
          30.824646
        ]
      },
      "type": "Feature",
      "properties": {
        "hierarchy": [
          "tgn:7543448",
          "tgn:7001242",
          "tgn:7016833",
          "tgn:1001113",
          "tgn:7029392"
        ],
        "placetype": [
          "aat:300008347"
        ],
        "id": 7543448,
        "name:xx": "Kafr as Suwayrkī"
      }
    },
    {
      "geometry": {
        "type": "Point",
        "coordinates": [
          31.591936,
          30.833962
        ]
      },
      "type": "Feature",
      "properties": {
        "hierarchy": [
          "tgn:7543449",
          "tgn:7001242",
          "tgn:7016833",
          "tgn:1001113",
          "tgn:7029392"
        ],
        "placetype": [
          "aat:300008347"
        ],
        "id": 7543449,
        "name:xx": "'Izbat Rāghib"
      }
    }
  ]
}
