{
  "geometry": {
    "type": "Point",
    "coordinates": [
      -115.3833,
      45.3667
    ]
  },
  "type": "Feature",
  "properties": {
    "hierarchy": [
      "tgn:2460743",
      "tgn:1000001",
      "tgn:7012149",
      "tgn:2000476",
      "tgn:7007250",
      "tgn:7029392"
    ],
    "placetype": [
      "aat:300008680"
    ],
    "id": 2460743,
    "name:xx": "Little Sheepeater Lake"
  }
}
