{
  "geometry": {
    "type": "Point",
    "coordinates": [
      -93.7667,
      36.5333
    ]
  },
  "type": "Feature",
  "properties": {
    "hierarchy": [
      "tgn:2574393",
      "tgn:2001170",
      "tgn:1000001",
      "tgn:7012149",
      "tgn:7007523",
      "tgn:7029392"
    ],
    "placetype": [
      "aat:300008798"
    ],
    "id": 2574393,
    "name:xx": "Pelican Mountain"
  }
}
