{
  "geometry": {
    "type": "Point",
    "coordinates": [
      -80.2667,
      41.7167
    ]
  },
  "type": "Feature",
  "properties": {
    "hierarchy": [
      "tgn:2633402",
      "tgn:1000001",
      "tgn:1002308",
      "tgn:7012149",
      "tgn:7007710",
      "tgn:7029392"
    ],
    "placetype": [
      "aat:300008706"
    ],
    "id": 2633402,
    "name:xx": "Rundelltown Creek"
  }
}
