{
  "geometry": {
    "type": "Point",
    "coordinates": [
      -115.0333,
      35.0167
    ]
  },
  "type": "Feature",
  "properties": {
    "hierarchy": [
      "tgn:2444952",
      "tgn:1000001",
      "tgn:7012149",
      "tgn:7007157",
      "tgn:1002857",
      "tgn:7029392"
    ],
    "placetype": [
      "aat:300000390"
    ],
    "id": 2444952,
    "name:xx": "Leiser Ray Mine"
  }
}
