{
  "geometry": {
    "type": "Point",
    "coordinates": [
      -79.3333,
      37.1667
    ]
  },
  "type": "Feature",
  "properties": {
    "hierarchy": [
      "tgn:2588884",
      "tgn:1000001",
      "tgn:2002150",
      "tgn:7012149",
      "tgn:7007919",
      "tgn:7029392"
    ],
    "placetype": [
      "aat:300008706"
    ],
    "id": 2588884,
    "name:xx": "Pocket Creek"
  }
}
