{
  "geometry": {
    "type": "Point",
    "coordinates": [
      -78.0667,
      39.8667
    ]
  },
  "type": "Feature",
  "properties": {
    "hierarchy": [
      "tgn:2235560",
      "tgn:1000001",
      "tgn:7012149",
      "tgn:1002399",
      "tgn:7007710",
      "tgn:7029392"
    ],
    "placetype": [
      "aat:300266640"
    ],
    "id": 2235560,
    "name:xx": "Chestnut Flat"
  }
}
