{
  "type": "FeatureCollection",
  "features": [
    {
      "geometry": {
        "type": "Point",
        "coordinates": [
          -71.466667,
          -29.083333
        ]
      },
      "type": "Feature",
      "properties": {
        "hierarchy": [
          "tgn:7315420",
          "tgn:1001630",
          "tgn:1000049",
          "tgn:1000002",
          "tgn:7029392"
        ],
        "placetype": [
          "aat:300008699"
        ],
        "id": 7315420,
        "name:xx": "Chañaral, Quebrada de"
      }
    },
    {
      "geometry": {
        "type": "Point",
        "coordinates": [
          -71.416667,
          -29.066667
        ]
      },
      "type": "Feature",
      "properties": {
        "hierarchy": [
          "tgn:7315422",
          "tgn:1001630",
          "tgn:1000049",
          "tgn:1000002",
          "tgn:7029392"
        ],
        "placetype": [
          "aat:300008805"
        ],
        "id": 7315422,
        "name:xx": "Chañaral, Llanos de"
      }
    },
    {
      "geometry": {
        "type": "Point",
        "coordinates": [
          -70.65,
          -26.283333
        ]
      },
      "type": "Feature",
      "properties": {
        "hierarchy": [
          "tgn:7315424",
          "tgn:1001630",
          "tgn:1000049",
          "tgn:1000002",
          "tgn:7029392"
        ],
        "placetype": [
          "aat:300008795"
        ],
        "id": 7315424,
        "name:xx": "Chañaral, Cerro"
      }
    },
    {
      "geometry": {
        "type": "Point",
        "coordinates": [
          -71.5,
          -29.05
        ]
      },
      "type": "Feature",
      "properties": {
        "hierarchy": [
          "tgn:7315425",
          "tgn:1001630",
          "tgn:1000049",
          "tgn:1000002",
          "tgn:7029392"
        ],
        "placetype": [
          "aat:300132316"
        ],
        "id": 7315425,
        "name:xx": "Chañaral, Caleta"
      }
    },
    {
      "geometry": {
        "type": "Point",
        "coordinates": [
          -71.433333,
          -29.033333
        ]
      },
      "type": "Feature",
      "properties": {
        "hierarchy": [
          "tgn:7315426",
          "tgn:1001630",
          "tgn:1000049",
          "tgn:1000002",
          "tgn:7029392"
        ],
        "placetype": [
          "aat:300008347"
        ],
        "id": 7315426,
        "name:xx": "Chañaral"
      }
    },
    {
      "geometry": {
        "type": "Point",
        "coordinates": [
          -70.1,
          -27.85
        ]
      },
      "type": "Feature",
      "properties": {
        "hierarchy": [
          "tgn:7315428",
          "tgn:1001630",
          "tgn:1000049",
          "tgn:1000002",
          "tgn:7029392"
        ],
        "placetype": [
          "aat:300266554",
          "aat:300008699"
        ],
        "id": 7315428,
        "name:xx": "Chañar, Quebrada"
      }
    },
    {
      "geometry": {
        "type": "Point",
        "coordinates": [
          -70.05,
          -27.6
        ]
      },
      "type": "Feature",
      "properties": {
        "hierarchy": [
          "tgn:7315429",
          "tgn:1001630",
          "tgn:1000049",
          "tgn:1000002",
          "tgn:7029392"
        ],
        "placetype": [
          "aat:300266554",
          "aat:300008699"
        ],
        "id": 7315429,
        "name:xx": "Chañar, Quebrada"
      }
    }
  ]
}
