{
  "geometry": {
    "type": "Point",
    "coordinates": [
      -121.2333,
      43.0167
    ]
  },
  "type": "Feature",
  "properties": {
    "hierarchy": [
      "tgn:2224746",
      "tgn:1000001",
      "tgn:7012149",
      "tgn:2001715",
      "tgn:7007708",
      "tgn:7029392"
    ],
    "placetype": [
      "aat:300008697"
    ],
    "id": 2224746,
    "name:xx": "Cashow Springs"
  }
}
