{
  "type": "FeatureCollection",
  "features": [
    {
      "geometry": {
        "type": "Point",
        "coordinates": [
          -1.3,
          53.983333
        ]
      },
      "type": "Feature",
      "properties": {
        "hierarchy": [
          "tgn:4005732",
          "tgn:7002445",
          "tgn:1000003",
          "tgn:7008166",
          "tgn:7008591",
          "tgn:7029392"
        ],
        "placetype": [
          "aat:300008347"
        ],
        "id": 4005732,
        "name:xx": "Kirk Hammerton"
      }
    },
    {
      "geometry": {
        "type": "Point",
        "coordinates": [
          -1.566667,
          54.35
        ]
      },
      "type": "Feature",
      "properties": {
        "hierarchy": [
          "tgn:4005733",
          "tgn:7002445",
          "tgn:1000003",
          "tgn:7008166",
          "tgn:7008591",
          "tgn:7029392"
        ],
        "placetype": [
          "aat:300008347"
        ],
        "name:en": "Kirkby Fleetham",
        "id": 4005733
      }
    },
    {
      "geometry": {
        "type": "Point",
        "coordinates": [
          -1.983333,
          55.116667
        ]
      },
      "type": "Feature",
      "properties": {
        "hierarchy": [
          "tgn:4005738",
          "tgn:7002445",
          "tgn:1000003",
          "tgn:7008165",
          "tgn:7008591",
          "tgn:7029392"
        ],
        "placetype": [
          "aat:300008347"
        ],
        "name:en": "Kirkharle",
        "id": 4005738
      }
    }
  ]
}
