{
  "geometry": {
    "type": "Point",
    "coordinates": [
      -96.2833,
      44.4167
    ]
  },
  "type": "Feature",
  "properties": {
    "hierarchy": [
      "tgn:2138674",
      "tgn:1000001",
      "tgn:7012149",
      "tgn:2001039",
      "tgn:7007521",
      "tgn:7029392"
    ],
    "placetype": [
      "aat:300008680"
    ],
    "id": 2138674,
    "name:xx": "Ash Lake"
  }
}
