{
  "geometry": {
    "type": "Point",
    "coordinates": [
      -122.1833,
      38.0167
    ]
  },
  "type": "Feature",
  "properties": {
    "hierarchy": [
      "tgn:2338923",
      "tgn:1000001",
      "tgn:7012149",
      "tgn:1002298",
      "tgn:7007157",
      "tgn:7029392"
    ],
    "placetype": [
      "aat:300008761"
    ],
    "id": 2338923,
    "name:xx": "Franklin Canyon"
  }
}
