{
  "geometry": {
    "type": "Point",
    "coordinates": [
      -80.0333,
      40.1833
    ]
  },
  "type": "Feature",
  "properties": {
    "hierarchy": [
      "tgn:2089681",
      "tgn:1000001",
      "tgn:7012149",
      "tgn:1002995",
      "tgn:7007710",
      "tgn:7029392"
    ],
    "placetype": [
      "aat:300008347",
      "aat:300387210"
    ],
    "id": 2089681,
    "name:xx": "Kammerer"
  }
}
