{
  "geometry": {
    "type": "Point",
    "coordinates": [
      -82.2667,
      37.9833
    ]
  },
  "type": "Feature",
  "properties": {
    "hierarchy": [
      "tgn:2183258",
      "tgn:1000001",
      "tgn:7012149",
      "tgn:2002299",
      "tgn:7013961",
      "tgn:7029392"
    ],
    "placetype": [
      "aat:300008699"
    ],
    "id": 2183258,
    "name:xx": "Bluewater Branch"
  }
}
