{
  "geometry": {
    "type": "Point",
    "coordinates": [
      -78.3167,
      37.8667
    ]
  },
  "type": "Feature",
  "properties": {
    "hierarchy": [
      "tgn:2111398",
      "tgn:1000001",
      "tgn:7012149",
      "tgn:2002159",
      "tgn:7007919",
      "tgn:7029392"
    ],
    "placetype": [
      "aat:300008347"
    ],
    "id": 2111398,
    "name:xx": "Cunningham"
  }
}
