{
  "geometry": {
    "type": "Point",
    "coordinates": [
      29.833333,
      30.95
    ]
  },
  "type": "Feature",
  "properties": {
    "hierarchy": [
      "tgn:7535260",
      "tgn:7001242",
      "tgn:7016833",
      "tgn:1001079",
      "tgn:7029392"
    ],
    "placetype": [
      "aat:300006207"
    ],
    "name:en": "Sāniyat Ḩunaysh",
    "id": 7535260
  }
}
