{
  "geometry": {
    "type": "Point",
    "coordinates": [
      -123.7167,
      44.6667
    ]
  },
  "type": "Feature",
  "properties": {
    "hierarchy": [
      "tgn:2712188",
      "tgn:1000001",
      "tgn:7012149",
      "tgn:1002599",
      "tgn:7007708",
      "tgn:7029392"
    ],
    "placetype": [
      "aat:300008798"
    ],
    "id": 2712188,
    "name:xx": "Tater Hill"
  }
}
