{
  "geometry": {
    "type": "Point",
    "coordinates": [
      38.7833,
      -15.4333
    ]
  },
  "type": "Feature",
  "properties": {
    "hierarchy": [
      "tgn:1091640",
      "tgn:7001242",
      "tgn:1000902",
      "tgn:1000180",
      "tgn:7029392"
    ],
    "placetype": [
      "aat:300008347"
    ],
    "id": 1091640,
    "name:xx": "Murrupula"
  }
}
