{
  "geometry": {
    "type": "Point",
    "coordinates": [
      10.5833,
      46.1667
    ]
  },
  "type": "Feature",
  "properties": {
    "hierarchy": [
      "tgn:1108665",
      "tgn:1000003",
      "tgn:1000080",
      "tgn:7029392"
    ],
    "placetype": [
      "aat:300008795"
    ],
    "id": 1108665,
    "name:it": "Adamello"
  }
}
