{
  "geometry": {
    "type": "Point",
    "coordinates": [
      -76.8667,
      39.65
    ]
  },
  "type": "Feature",
  "properties": {
    "hierarchy": [
      "tgn:2361149",
      "tgn:1000001",
      "tgn:7012149",
      "tgn:7007516",
      "tgn:7029392"
    ],
    "placetype": [
      "aat:300008699"
    ],
    "id": 2361149,
    "name:xx": "Grave Run"
  }
}
