{
  "geometry": {
    "type": "Point",
    "coordinates": [
      -82.2833,
      37.0333
    ]
  },
  "type": "Feature",
  "properties": {
    "hierarchy": [
      "tgn:2348670",
      "tgn:1000001",
      "tgn:7012149",
      "tgn:2002157",
      "tgn:7007919",
      "tgn:7029392"
    ],
    "placetype": [
      "aat:300008699"
    ],
    "id": 2348670,
    "name:xx": "Gibson Branch"
  }
}
