{
  "geometry": {
    "type": "Point",
    "coordinates": [
      -152.7333,
      60.35
    ]
  },
  "type": "Feature",
  "properties": {
    "hierarchy": [
      "tgn:2266869",
      "tgn:7006450",
      "tgn:1000001",
      "tgn:7019698",
      "tgn:7012149",
      "tgn:7029392"
    ],
    "placetype": [
      "aat:300008707"
    ],
    "id": 2266869,
    "name:xx": "Crescent River"
  }
}
