{
  "geometry": {
    "type": "Point",
    "coordinates": [
      40.2167,
      55.6833
    ]
  },
  "type": "Feature",
  "properties": {
    "hierarchy": [
      "tgn:1060684",
      "tgn:1000004",
      "tgn:1003421",
      "tgn:7018214",
      "tgn:7002435",
      "tgn:7029392"
    ],
    "placetype": [
      "aat:300008347"
    ],
    "id": 1060684,
    "name:xx": "Urshel'skiy"
  }
}
