{
  "geometry": {
    "type": "Point",
    "coordinates": [
      -85.9667,
      44.8667
    ]
  },
  "type": "Feature",
  "properties": {
    "hierarchy": [
      "tgn:2351441",
      "tgn:1000001",
      "tgn:7012149",
      "tgn:2000971",
      "tgn:7007520",
      "tgn:7029392"
    ],
    "placetype": [
      "aat:300008680"
    ],
    "id": 2351441,
    "name:xx": "Glen Lake"
  }
}
