{
  "geometry": {
    "type": "Point",
    "coordinates": [
      27.016,
      57.833
    ]
  },
  "type": "Feature",
  "properties": {
    "hierarchy": [
      "tgn:1060887",
      "tgn:7006645",
      "tgn:1000003",
      "tgn:7006540",
      "tgn:7029392"
    ],
    "placetype": [
      "aat:300008347",
      "aat:300387222"
    ],
    "name:en": "Võru",
    "id": 1060887
  }
}
