{
  "geometry": {
    "type": "Point",
    "coordinates": [
      -93.4167,
      47.9167
    ]
  },
  "type": "Feature",
  "properties": {
    "hierarchy": [
      "tgn:2614485",
      "tgn:1000001",
      "tgn:7012149",
      "tgn:2001034",
      "tgn:7007521",
      "tgn:7029392"
    ],
    "placetype": [
      "aat:300008699"
    ],
    "id": 2614485,
    "name:xx": "Reilly Brook"
  }
}
