{
  "geometry": {
    "type": "Point",
    "coordinates": [
      -91.8167,
      37.85
    ]
  },
  "type": "Feature",
  "properties": {
    "hierarchy": [
      "tgn:2728343",
      "tgn:1000001",
      "tgn:7012149",
      "tgn:2001230",
      "tgn:7007523",
      "tgn:7029392"
    ],
    "placetype": [
      "aat:300008706"
    ],
    "id": 2728343,
    "name:xx": "Treable Creek"
  }
}
