{
  "geometry": {
    "type": "Point",
    "coordinates": [
      -124.4333,
      47.85
    ]
  },
  "type": "Feature",
  "properties": {
    "hierarchy": [
      "tgn:2322583",
      "tgn:1000001",
      "tgn:7012149",
      "tgn:1002521",
      "tgn:7007920",
      "tgn:7029392"
    ],
    "placetype": [
      "aat:300008706"
    ],
    "id": 2322583,
    "name:xx": "Falls Creek"
  }
}
