{
  "geometry": {
    "type": "Point",
    "coordinates": [
      -122.9333,
      45.8833
    ]
  },
  "type": "Feature",
  "properties": {
    "hierarchy": [
      "tgn:2638614",
      "tgn:1000001",
      "tgn:1002293",
      "tgn:7012149",
      "tgn:7007708",
      "tgn:7029392"
    ],
    "placetype": [
      "aat:300008706"
    ],
    "id": 2638614,
    "name:xx": "Salmonberry Creek"
  }
}
