{
  "geometry": {
    "type": "Point",
    "coordinates": [
      -120.65,
      48.3833
    ]
  },
  "type": "Feature",
  "properties": {
    "hierarchy": [
      "tgn:2498488",
      "tgn:1000001",
      "tgn:1002260",
      "tgn:7012149",
      "tgn:7007920",
      "tgn:7029392"
    ],
    "placetype": [
      "aat:300008798"
    ],
    "id": 2498488,
    "name:xx": "McAlester Mountain"
  }
}
