{
  "geometry": {
    "type": "Point",
    "coordinates": [
      -104.25,
      36.0667
    ]
  },
  "type": "Feature",
  "properties": {
    "hierarchy": [
      "tgn:2507035",
      "tgn:1000001",
      "tgn:7012149",
      "tgn:7007566",
      "tgn:7029392"
    ],
    "placetype": [
      "aat:300008761"
    ],
    "id": 2507035,
    "name:xx": "Mesteno, Cañon"
  }
}
