{
  "geometry": {
    "type": "Point",
    "coordinates": [
      -100.95,
      42.2333
    ]
  },
  "type": "Feature",
  "properties": {
    "hierarchy": [
      "tgn:2298678",
      "tgn:1000001",
      "tgn:2001331",
      "tgn:7012149",
      "tgn:7007525",
      "tgn:7029392"
    ],
    "placetype": [
      "aat:300386845"
    ],
    "id": 2298678,
    "name:xx": "Dry Valley"
  }
}
