{
  "geometry": {
    "type": "Point",
    "coordinates": [
      126.6833,
      38.3167
    ]
  },
  "type": "Feature",
  "properties": {
    "hierarchy": [
      "tgn:1082112",
      "tgn:1001302",
      "tgn:1000004",
      "tgn:1000122",
      "tgn:7029392"
    ],
    "placetype": [
      "aat:300008347"
    ],
    "id": 1082112,
    "name:xx": "Sibyŏn"
  }
}
