{
  "geometry": {
    "type": "Point",
    "coordinates": [
      -90.1333,
      33.7667
    ]
  },
  "type": "Feature",
  "properties": {
    "hierarchy": [
      "tgn:2128987",
      "tgn:1000001",
      "tgn:7012149",
      "tgn:2001153",
      "tgn:7007522",
      "tgn:7029392"
    ],
    "placetype": [
      "aat:300008680"
    ],
    "id": 2128987,
    "name:xx": "Alexander Lake"
  }
}
