{
  "type": "FeatureCollection",
  "features": [
    {
      "geometry": {
        "type": "Point",
        "coordinates": [
          -77.25,
          38.8333
        ]
      },
      "type": "Feature",
      "properties": {
        "hierarchy": [
          "tgn:2112640",
          "tgn:1000001",
          "tgn:7012149",
          "tgn:7014160",
          "tgn:7007919",
          "tgn:7029392"
        ],
        "placetype": [
          "aat:300008347"
        ],
        "id": 2112640,
        "name:xx": "Lee Forest"
      }
    },
    {
      "geometry": {
        "type": "Point",
        "coordinates": [
          -77.35,
          38.8333
        ]
      },
      "type": "Feature",
      "properties": {
        "hierarchy": [
          "tgn:2112644",
          "tgn:1000001",
          "tgn:7012149",
          "tgn:7014160",
          "tgn:7007919",
          "tgn:7029392"
        ],
        "placetype": [
          "aat:300008347"
        ],
        "id": 2112644,
        "name:xx": "Lee-Hi Village"
      }
    },
    {
      "geometry": {
        "type": "Point",
        "coordinates": [
          -82.1167,
          37.1833
        ]
      },
      "type": "Feature",
      "properties": {
        "hierarchy": [
          "tgn:2112645",
          "tgn:1000001",
          "tgn:2002148",
          "tgn:7012149",
          "tgn:7007919",
          "tgn:7029392"
        ],
        "placetype": [
          "aat:300008347"
        ],
        "id": 2112645,
        "name:xx": "Leemaster"
      }
    },
    {
      "geometry": {
        "type": "Point",
        "coordinates": [
          -75.6667,
          37.7667
        ]
      },
      "type": "Feature",
      "properties": {
        "hierarchy": [
          "tgn:2112646",
          "tgn:1002132",
          "tgn:1000001",
          "tgn:7012149",
          "tgn:7007919",
          "tgn:7029392"
        ],
        "placetype": [
          "aat:300008347"
        ],
        "id": 2112646,
        "name:xx": "Lee Mont"
      }
    },
    {
      "geometry": {
        "type": "Point",
        "coordinates": [
          -77.55,
          39.1
        ]
      },
      "type": "Feature",
      "properties": {
        "hierarchy": [
          "tgn:2112647",
          "tgn:1000001",
          "tgn:7012149",
          "tgn:7015770",
          "tgn:7007919",
          "tgn:7029392"
        ],
        "placetype": [
          "aat:300008347"
        ],
        "id": 2112647,
        "name:xx": "Leesburg"
      }
    }
  ]
}
