{
  "geometry": {
    "type": "Point",
    "coordinates": [
      -94.45,
      40.7833
    ]
  },
  "type": "Feature",
  "properties": {
    "hierarchy": [
      "tgn:2732608",
      "tgn:1000001",
      "tgn:7012149",
      "tgn:2000640",
      "tgn:7007253",
      "tgn:7029392"
    ],
    "placetype": [
      "aat:300008706"
    ],
    "id": 2732608,
    "name:xx": "Turkey Creek"
  }
}
