{
  "geometry": {
    "type": "Point",
    "coordinates": [
      -108.7833,
      38.1833
    ]
  },
  "type": "Feature",
  "properties": {
    "hierarchy": [
      "tgn:2713650",
      "tgn:1000001",
      "tgn:7012149",
      "tgn:2000234",
      "tgn:7007158",
      "tgn:7029392"
    ],
    "placetype": [
      "aat:300000390"
    ],
    "id": 2713650,
    "name:xx": "Teapot Dome Number 2 Mine"
  }
}
