{
  "geometry": {
    "type": "Point",
    "coordinates": [
      -111.6833,
      40.4833
    ]
  },
  "type": "Feature",
  "properties": {
    "hierarchy": [
      "tgn:2190498",
      "tgn:1000001",
      "tgn:7012149",
      "tgn:2002125",
      "tgn:7007827",
      "tgn:7029392"
    ],
    "placetype": [
      "aat:300008798"
    ],
    "id": 2190498,
    "name:xx": "Box Elder Peak"
  }
}
