{
  "geometry": {
    "type": "Point",
    "coordinates": [
      -79.2167,
      41.65
    ]
  },
  "type": "Feature",
  "properties": {
    "hierarchy": [
      "tgn:2184281",
      "tgn:1000001",
      "tgn:7012149",
      "tgn:7007710",
      "tgn:7029392"
    ],
    "placetype": [
      "aat:300008706"
    ],
    "id": 2184281,
    "name:xx": "Bobbs Creek"
  }
}
