{
  "geometry": {
    "type": "Point",
    "coordinates": [
      78.531678,
      29.877337
    ]
  },
  "type": "Feature",
  "properties": {
    "hierarchy": [
      "tgn:7570416",
      "tgn:1000004",
      "tgn:7000198",
      "tgn:7031786",
      "tgn:7029392"
    ],
    "placetype": [
      "aat:300008347"
    ],
    "name:en": "Kathūr",
    "id": 7570416
  }
}
