{
  "geometry": {
    "type": "Point",
    "coordinates": [
      123.7167,
      8.0167
    ]
  },
  "type": "Feature",
  "properties": {
    "hierarchy": [
      "tgn:1113576",
      "tgn:1000004",
      "tgn:7016744",
      "tgn:1000135",
      "tgn:7029392"
    ],
    "placetype": [
      "aat:300132316"
    ],
    "id": 1113576,
    "name:xx": "Panguil Bay"
  }
}
