{
  "geometry": {
    "type": "Point",
    "coordinates": [
      -38.7167,
      -6.7833
    ]
  },
  "type": "Feature",
  "properties": {
    "hierarchy": [
      "tgn:1021654",
      "tgn:7006064",
      "tgn:1000047",
      "tgn:7002455",
      "tgn:1000002",
      "tgn:7029392"
    ],
    "placetype": [
      "aat:300008347"
    ],
    "id": 1021654,
    "name:xx": "Ipaumirim"
  }
}
