{
  "geometry": {
    "type": "Point",
    "coordinates": [
      -83.4667,
      44.7667
    ]
  },
  "type": "Feature",
  "properties": {
    "hierarchy": [
      "tgn:2282126",
      "tgn:2000942",
      "tgn:1000001",
      "tgn:7012149",
      "tgn:7007520",
      "tgn:7029392"
    ],
    "placetype": [
      "aat:300008680"
    ],
    "id": 2282126,
    "name:xx": "Deer Lake"
  }
}
