{
  "geometry": {
    "type": "Point",
    "coordinates": [
      -78.2333,
      38.7333
    ]
  },
  "type": "Feature",
  "properties": {
    "hierarchy": [
      "tgn:2436119",
      "tgn:1000001",
      "tgn:7012149",
      "tgn:2002184",
      "tgn:7007919",
      "tgn:7029392"
    ],
    "placetype": [
      "aat:300008798"
    ],
    "id": 2436119,
    "name:xx": "Keyser Mountain"
  }
}
