{
  "geometry": {
    "type": "Point",
    "coordinates": [
      22.6667,
      61.75
    ]
  },
  "type": "Feature",
  "properties": {
    "hierarchy": [
      "tgn:1103517",
      "tgn:7024077",
      "tgn:1000003",
      "tgn:1000069",
      "tgn:7029392"
    ],
    "placetype": [
      "aat:300386886"
    ],
    "id": 1103517,
    "name:xx": "Hämeenkangas"
  }
}
