{
  "geometry": {
    "type": "Point",
    "coordinates": [
      29.739782,
      25.582794
    ]
  },
  "type": "Feature",
  "properties": {
    "hierarchy": [
      "tgn:7520530",
      "tgn:7001242",
      "tgn:7016833",
      "tgn:7001334",
      "tgn:7029392"
    ],
    "placetype": [
      "aat:300008795"
    ],
    "name:en": "Abū Ţurţūr, Jabal",
    "id": 7520530
  }
}
