{
  "type": "FeatureCollection",
  "features": [
    {
      "geometry": {
        "type": "Point",
        "coordinates": [
          13.8,
          45.65
        ]
      },
      "type": "Feature",
      "properties": {
        "hierarchy": [
          "tgn:7041580",
          "tgn:1003505",
          "tgn:1000003",
          "tgn:7002993",
          "tgn:1000080",
          "tgn:7029392"
        ],
        "placetype": [
          "aat:300004792"
        ],
        "id": 7041580,
        "name:xx": "Castello di San Giusto"
      }
    },
    {
      "geometry": {
        "type": "Point",
        "coordinates": [
          13.8,
          45.65
        ]
      },
      "type": "Feature",
      "properties": {
        "hierarchy": [
          "tgn:7041581",
          "tgn:1003505",
          "tgn:1000003",
          "tgn:7002993",
          "tgn:1000080",
          "tgn:7029392"
        ],
        "placetype": [
          "aat:300000745"
        ],
        "id": 7041581,
        "name:xx": "San Giusto"
      }
    },
    {
      "geometry": {
        "type": "Point",
        "coordinates": [
          10.983333,
          43.783333
        ]
      },
      "type": "Feature",
      "properties": {
        "hierarchy": [
          "tgn:7041582",
          "tgn:7003163",
          "tgn:1000003",
          "tgn:7009760",
          "tgn:1000080",
          "tgn:7029392"
        ],
        "placetype": [
          "aat:300008347"
        ],
        "id": 7041582,
        "name:xx": "San Giusto"
      }
    },
    {
      "geometry": {
        "type": "Point",
        "coordinates": [
          11.7,
          43.55
        ]
      },
      "type": "Feature",
      "properties": {
        "hierarchy": [
          "tgn:7041583",
          "tgn:7003162",
          "tgn:1000003",
          "tgn:7009760",
          "tgn:1000080",
          "tgn:7029392"
        ],
        "placetype": [
          "aat:300008347"
        ],
        "id": 7041583,
        "name:xx": "San Giustino Valdarno"
      }
    },
    {
      "geometry": {
        "type": "Point",
        "coordinates": [
          8.241944,
          40.807778
        ]
      },
      "type": "Feature",
      "properties": {
        "hierarchy": [
          "tgn:7041585",
          "tgn:7015163",
          "tgn:1000003",
          "tgn:7003121",
          "tgn:1000080",
          "tgn:7029392"
        ],
        "placetype": [
          "aat:300008795"
        ],
        "id": 7041585,
        "name:xx": "San Giusta, Monte"
      }
    },
    {
      "geometry": {
        "type": "Point",
        "coordinates": [
          12.130833,
          46.877222
        ]
      },
      "type": "Feature",
      "properties": {
        "hierarchy": [
          "tgn:7041587",
          "tgn:1003440",
          "tgn:1000003",
          "tgn:7003124",
          "tgn:1000080",
          "tgn:7029392"
        ],
        "placetype": [
          "aat:300008347"
        ],
        "id": 7041587,
        "name:xx": "San Giuseppe in Anterselva"
      }
    },
    {
      "geometry": {
        "type": "Point",
        "coordinates": [
          13.833333,
          45.633333
        ]
      },
      "type": "Feature",
      "properties": {
        "hierarchy": [
          "tgn:7041589",
          "tgn:1003505",
          "tgn:1000003",
          "tgn:7002993",
          "tgn:1000080",
          "tgn:7029392"
        ],
        "placetype": [
          "aat:300008347"
        ],
        "id": 7041589,
        "name:xx": "San Giuseppe della Chiusa"
      }
    }
  ]
}
