{
  "geometry": {
    "type": "Point",
    "coordinates": [
      42.55,
      16.9333
    ]
  },
  "type": "Feature",
  "properties": {
    "hierarchy": [
      "tgn:7000682",
      "tgn:7003875",
      "tgn:1000004",
      "tgn:1000137",
      "tgn:7029392"
    ],
    "placetype": [
      "aat:300387145",
      "aat:300387172"
    ],
    "id": 7000682,
    "name:xx": "Jīzān"
  }
}
