{
  "geometry": {
    "type": "Point",
    "coordinates": [
      44.5333,
      43.0833
    ]
  },
  "type": "Feature",
  "properties": {
    "hierarchy": [
      "tgn:1052270",
      "tgn:1000004",
      "tgn:7014987",
      "tgn:7002435",
      "tgn:7029392"
    ],
    "placetype": [
      "aat:300008347"
    ],
    "id": 1052270,
    "name:xx": "Arkhonskaya"
  }
}
