{
  "type": "FeatureCollection",
  "features": [
    {
      "geometry": {
        "type": "Point",
        "coordinates": [
          133.1667,
          34.3333
        ]
      },
      "type": "Feature",
      "properties": {
        "hierarchy": [
          "tgn:1007501",
          "tgn:1000984",
          "tgn:7000897",
          "tgn:1000004",
          "tgn:1000120",
          "tgn:7029392"
        ],
        "placetype": [
          "aat:300008791"
        ],
        "id": 1007501,
        "name:xx": "Inno-shima"
      }
    },
    {
      "geometry": {
        "type": "Point",
        "coordinates": [
          -74.763056,
          -44.606111
        ]
      },
      "type": "Feature",
      "properties": {
        "hierarchy": [
          "tgn:1007504",
          "tgn:1001623",
          "tgn:1000049",
          "tgn:1000002",
          "tgn:1009936",
          "tgn:7029392"
        ],
        "placetype": [
          "aat:300008791"
        ],
        "id": 1007504,
        "name:xx": "Ipun, Isla"
      }
    },
    {
      "geometry": {
        "type": "Point",
        "coordinates": [
          -105.916667,
          21.85
        ]
      },
      "type": "Feature",
      "properties": {
        "hierarchy": [
          "tgn:1007509",
          "tgn:1000001",
          "tgn:1001906",
          "tgn:7005560",
          "tgn:7029392"
        ],
        "placetype": [
          "aat:300008791"
        ],
        "id": 1007509,
        "name:xx": "Isabela, Isla"
      }
    }
  ]
}
