{
  "geometry": {
    "type": "Point",
    "coordinates": [
      6.6833,
      49.0667
    ]
  },
  "type": "Feature",
  "properties": {
    "hierarchy": [
      "tgn:1033129",
      "tgn:1000003",
      "tgn:7002888",
      "tgn:1000070",
      "tgn:7029392"
    ],
    "placetype": [
      "aat:300008347"
    ],
    "id": 1033129,
    "name:xx": "Folschviller"
  }
}
