{
  "geometry": {
    "type": "Point",
    "coordinates": [
      87.27124,
      24.179004
    ]
  },
  "type": "Feature",
  "properties": {
    "hierarchy": [
      "tgn:1075968",
      "tgn:1000004",
      "tgn:7000198",
      "tgn:7031783",
      "tgn:7029392"
    ],
    "placetype": [
      "aat:300008347"
    ],
    "name:en": "Kumrābād",
    "id": 1075968
  }
}
