{
  "geometry": {
    "type": "Point",
    "coordinates": [
      -95.5167,
      32.4667
    ]
  },
  "type": "Feature",
  "properties": {
    "hierarchy": [
      "tgn:2103135",
      "tgn:1000001",
      "tgn:7012149",
      "tgn:1002898",
      "tgn:7007826",
      "tgn:7029392"
    ],
    "placetype": [
      "aat:300008347"
    ],
    "id": 2103135,
    "name:xx": "Carroll"
  }
}
