{
  "type": "FeatureCollection",
  "features": [
    {
      "geometry": {
        "type": "Point",
        "coordinates": [
          -109.433333,
          28.583333
        ]
      },
      "type": "Feature",
      "properties": {
        "hierarchy": [
          "tgn:7381220",
          "tgn:1000001",
          "tgn:1001960",
          "tgn:7005560",
          "tgn:7029392"
        ],
        "placetype": [
          "aat:300008347"
        ],
        "id": 7381220,
        "name:xx": "Majada"
      }
    },
    {
      "geometry": {
        "type": "Point",
        "coordinates": [
          -98.766667,
          26.183333
        ]
      },
      "type": "Feature",
      "properties": {
        "hierarchy": [
          "tgn:7381221",
          "tgn:1000001",
          "tgn:7005597",
          "tgn:7005560",
          "tgn:7029392"
        ],
        "placetype": [
          "aat:300008347"
        ],
        "id": 7381221,
        "name:xx": "Majada"
      }
    },
    {
      "geometry": {
        "type": "Point",
        "coordinates": [
          -98.266667,
          26.033333
        ]
      },
      "type": "Feature",
      "properties": {
        "hierarchy": [
          "tgn:7381223",
          "tgn:1000001",
          "tgn:7005597",
          "tgn:7005560",
          "tgn:7029392"
        ],
        "placetype": [
          "aat:300008347"
        ],
        "id": 7381223,
        "name:xx": "Majada"
      }
    },
    {
      "geometry": {
        "type": "Point",
        "coordinates": [
          -93.866667,
          15.966667
        ]
      },
      "type": "Feature",
      "properties": {
        "hierarchy": [
          "tgn:7381224",
          "tgn:7005580",
          "tgn:1000001",
          "tgn:7005560",
          "tgn:7029392"
        ],
        "placetype": [
          "aat:300008347"
        ],
        "id": 7381224,
        "name:xx": "Majada"
      }
    },
    {
      "geometry": {
        "type": "Point",
        "coordinates": [
          -92.233333,
          15.766667
        ]
      },
      "type": "Feature",
      "properties": {
        "hierarchy": [
          "tgn:7381225",
          "tgn:7005580",
          "tgn:1000001",
          "tgn:7005560",
          "tgn:7029392"
        ],
        "placetype": [
          "aat:300008699"
        ],
        "id": 7381225,
        "name:xx": "Maiz Blanco"
      }
    },
    {
      "geometry": {
        "type": "Point",
        "coordinates": [
          -107.883333,
          30.9
        ]
      },
      "type": "Feature",
      "properties": {
        "hierarchy": [
          "tgn:7381226",
          "tgn:7005581",
          "tgn:1000001",
          "tgn:7005560",
          "tgn:7029392"
        ],
        "placetype": [
          "aat:300000241"
        ],
        "id": 7381226,
        "name:xx": "Rancho del Maíz"
      }
    },
    {
      "geometry": {
        "type": "Point",
        "coordinates": [
          -106.316667,
          26.5
        ]
      },
      "type": "Feature",
      "properties": {
        "hierarchy": [
          "tgn:7381227",
          "tgn:7005581",
          "tgn:1000001",
          "tgn:7005560",
          "tgn:7029392"
        ],
        "placetype": [
          "aat:300000241"
        ],
        "id": 7381227,
        "name:xx": "Rancho del Maíz"
      }
    },
    {
      "geometry": {
        "type": "Point",
        "coordinates": [
          -91.483333,
          17.583333
        ]
      },
      "type": "Feature",
      "properties": {
        "hierarchy": [
          "tgn:7381228",
          "tgn:1000001",
          "tgn:7005596",
          "tgn:7005560",
          "tgn:7029392"
        ],
        "placetype": [
          "aat:300008680"
        ],
        "id": 7381228,
        "name:xx": "Maiz, Laguna el"
      }
    },
    {
      "geometry": {
        "type": "Point",
        "coordinates": [
          -106.283333,
          26.45
        ]
      },
      "type": "Feature",
      "properties": {
        "hierarchy": [
          "tgn:7381229",
          "tgn:7005581",
          "tgn:1000001",
          "tgn:7005560",
          "tgn:7029392"
        ],
        "placetype": [
          "aat:300008699"
        ],
        "id": 7381229,
        "name:xx": "Maiz, Arroyo del"
      }
    }
  ]
}
