{
  "geometry": {
    "type": "Point",
    "coordinates": [
      -49.9167,
      1.7167
    ]
  },
  "type": "Feature",
  "properties": {
    "hierarchy": [
      "tgn:1010989",
      "tgn:1001986",
      "tgn:1000047",
      "tgn:7002456",
      "tgn:1000002",
      "tgn:7029392"
    ],
    "placetype": [
      "aat:300008850"
    ],
    "id": 1010989,
    "name:xx": "Norte, Cabo"
  }
}
