{
  "geometry": {
    "type": "Point",
    "coordinates": [
      -100.95,
      31.9333
    ]
  },
  "type": "Feature",
  "properties": {
    "hierarchy": [
      "tgn:2774092",
      "tgn:1000001",
      "tgn:7012149",
      "tgn:2002077",
      "tgn:7007826",
      "tgn:7029392"
    ],
    "placetype": [
      "aat:300008706"
    ],
    "id": 2774092,
    "name:xx": "Willow Creek"
  }
}
