{
  "geometry": {
    "type": "Point",
    "coordinates": [
      -95.2333,
      30.0333
    ]
  },
  "type": "Feature",
  "properties": {
    "hierarchy": [
      "tgn:2175574",
      "tgn:1000001",
      "tgn:7012149",
      "tgn:1002456",
      "tgn:7007826",
      "tgn:7029392"
    ],
    "placetype": [
      "aat:300266640"
    ],
    "id": 2175574,
    "name:xx": "Black Cat Ridge"
  }
}
