{
  "geometry": {
    "type": "Point",
    "coordinates": [
      -123.6167,
      40.45
    ]
  },
  "type": "Feature",
  "properties": {
    "hierarchy": [
      "tgn:2703007",
      "tgn:1000001",
      "tgn:7012149",
      "tgn:2000181",
      "tgn:7007157",
      "tgn:7029392"
    ],
    "placetype": [
      "aat:300386845"
    ],
    "id": 2703007,
    "name:xx": "Sulphur Valley"
  }
}
