{
  "geometry": {
    "type": "Point",
    "coordinates": [
      107.6333,
      24.8833
    ]
  },
  "type": "Feature",
  "properties": {
    "hierarchy": [
      "tgn:1067151",
      "tgn:1000004",
      "tgn:1001678",
      "tgn:1000111",
      "tgn:7029392"
    ],
    "placetype": [
      "aat:300008347"
    ],
    "id": 1067151,
    "name:xx": "Chehe"
  }
}
