{
  "geometry": {
    "type": "Point",
    "coordinates": [
      2.35,
      48.7833
    ]
  },
  "type": "Feature",
  "properties": {
    "hierarchy": [
      "tgn:1033663",
      "tgn:1000003",
      "tgn:7002883",
      "tgn:1000070",
      "tgn:7029392"
    ],
    "placetype": [
      "aat:300008347"
    ],
    "id": 1033663,
    "name:xx": "La Häy-les-Rosas"
  }
}
