{
  "geometry": {
    "type": "Point",
    "coordinates": [
      -96.4667,
      34.0667
    ]
  },
  "type": "Feature",
  "properties": {
    "hierarchy": [
      "tgn:2452244",
      "tgn:1000001",
      "tgn:2001629",
      "tgn:7012149",
      "tgn:7007707",
      "tgn:7029392"
    ],
    "placetype": [
      "aat:300008707"
    ],
    "id": 2452244,
    "name:xx": "Little Blue River"
  }
}
