{
  "geometry": {
    "type": "Point",
    "coordinates": [
      -79.1333,
      42.3167
    ]
  },
  "type": "Feature",
  "properties": {
    "hierarchy": [
      "tgn:2234791",
      "tgn:1000001",
      "tgn:7012149",
      "tgn:7007568",
      "tgn:7029392"
    ],
    "placetype": [
      "aat:300008706"
    ],
    "id": 2234791,
    "name:xx": "Cherry Creek"
  }
}
