{
  "geometry": {
    "type": "Point",
    "coordinates": [
      65.5167,
      53.65
    ]
  },
  "type": "Feature",
  "properties": {
    "hierarchy": [
      "tgn:1054361",
      "tgn:1000004",
      "tgn:7012922",
      "tgn:7014786",
      "tgn:7029392"
    ],
    "placetype": [
      "aat:300008347"
    ],
    "id": 1054361,
    "name:xx": "Imeni Timir'azeva"
  }
}
