{
  "geometry": {
    "type": "Point",
    "coordinates": [
      -81.85,
      33.7333
    ]
  },
  "type": "Feature",
  "properties": {
    "hierarchy": [
      "tgn:2564323",
      "tgn:1000001",
      "tgn:7012149",
      "tgn:7007712",
      "tgn:7029392"
    ],
    "placetype": [
      "aat:300008699"
    ],
    "id": 2564323,
    "name:xx": "Paces Branch"
  }
}
