{
  "geometry": {
    "type": "Point",
    "coordinates": [
      36.5833,
      28.5833
    ]
  },
  "type": "Feature",
  "properties": {
    "hierarchy": [
      "tgn:1111080",
      "tgn:1000004",
      "tgn:1000137",
      "tgn:7029392"
    ],
    "placetype": [
      "aat:300387091"
    ],
    "id": 1111080,
    "name:xx": "Akhḍar, Wādī al-"
  }
}
