{
  "geometry": {
    "type": "Point",
    "coordinates": [
      -101.8333,
      36.7333
    ]
  },
  "type": "Feature",
  "properties": {
    "hierarchy": [
      "tgn:2685590",
      "tgn:1000001",
      "tgn:7012149",
      "tgn:2001692",
      "tgn:7007707",
      "tgn:7029392"
    ],
    "placetype": [
      "aat:300008706"
    ],
    "id": 2685590,
    "name:xx": "Spring Aroa Creek"
  }
}
