{
  "type": "FeatureCollection",
  "features": [
    {
      "geometry": {
        "type": "Point",
        "coordinates": [
          38.8833,
          53.4333
        ]
      },
      "type": "Feature",
      "properties": {
        "hierarchy": [
          "tgn:1137270",
          "tgn:1000004",
          "tgn:7011575",
          "tgn:7018214",
          "tgn:7002435",
          "tgn:7029392"
        ],
        "placetype": [
          "aat:300008347"
        ],
        "id": 1137270,
        "name:xx": "Ber'ozovka"
      }
    },
    {
      "geometry": {
        "type": "Point",
        "coordinates": [
          25.5,
          53.7167
        ]
      },
      "type": "Feature",
      "properties": {
        "hierarchy": [
          "tgn:1137271",
          "tgn:7012158",
          "tgn:1000003",
          "tgn:7006657",
          "tgn:7029392"
        ],
        "placetype": [
          "aat:300008347"
        ],
        "id": 1137271,
        "name:xx": "Ber'ozovka"
      }
    },
    {
      "geometry": {
        "type": "Point",
        "coordinates": [
          76.5833,
          54.0333
        ]
      },
      "type": "Feature",
      "properties": {
        "hierarchy": [
          "tgn:1137272",
          "tgn:1000004",
          "tgn:7011589",
          "tgn:7018214",
          "tgn:7002435",
          "tgn:7029392"
        ],
        "placetype": [
          "aat:300008347"
        ],
        "id": 1137272,
        "name:xx": "Ber'ozovka"
      }
    },
    {
      "geometry": {
        "type": "Point",
        "coordinates": [
          93.1167,
          56.05
        ]
      },
      "type": "Feature",
      "properties": {
        "hierarchy": [
          "tgn:1137273",
          "tgn:1000004",
          "tgn:1003314",
          "tgn:7018214",
          "tgn:7002435",
          "tgn:7029392"
        ],
        "placetype": [
          "aat:300008347"
        ],
        "id": 1137273,
        "name:xx": "Ber'ozovka"
      }
    },
    {
      "geometry": {
        "type": "Point",
        "coordinates": [
          57.3,
          57.6167
        ]
      },
      "type": "Feature",
      "properties": {
        "hierarchy": [
          "tgn:1137274",
          "tgn:1000004",
          "tgn:7013412",
          "tgn:7018214",
          "tgn:7002435",
          "tgn:7029392"
        ],
        "placetype": [
          "aat:300008347"
        ],
        "id": 1137274,
        "name:xx": "Berozovka"
      }
    },
    {
      "geometry": {
        "type": "Point",
        "coordinates": [
          116.15,
          57.7667
        ]
      },
      "type": "Feature",
      "properties": {
        "hierarchy": [
          "tgn:1137275",
          "tgn:1003373",
          "tgn:1000004",
          "tgn:7018214",
          "tgn:7002435",
          "tgn:7029392"
        ],
        "placetype": [
          "aat:300008347"
        ],
        "id": 1137275,
        "name:xx": "Ber'ozovka"
      }
    },
    {
      "geometry": {
        "type": "Point",
        "coordinates": [
          82.6333,
          59.4
        ]
      },
      "type": "Feature",
      "properties": {
        "hierarchy": [
          "tgn:1137276",
          "tgn:1000004",
          "tgn:7011604",
          "tgn:7018214",
          "tgn:7002435",
          "tgn:7029392"
        ],
        "placetype": [
          "aat:300008347"
        ],
        "id": 1137276,
        "name:xx": "Ber'ozovka"
      }
    },
    {
      "geometry": {
        "type": "Point",
        "coordinates": [
          56.0333,
          59.5833
        ]
      },
      "type": "Feature",
      "properties": {
        "hierarchy": [
          "tgn:1137277",
          "tgn:1000004",
          "tgn:7013412",
          "tgn:7018214",
          "tgn:7002435",
          "tgn:7029392"
        ],
        "placetype": [
          "aat:300008347"
        ],
        "id": 1137277,
        "name:xx": "Ber'ozovka"
      }
    },
    {
      "geometry": {
        "type": "Point",
        "coordinates": [
          30.8167,
          59.9333
        ]
      },
      "type": "Feature",
      "properties": {
        "hierarchy": [
          "tgn:1137278",
          "tgn:1000004",
          "tgn:7011572",
          "tgn:7018214",
          "tgn:7002435",
          "tgn:7029392"
        ],
        "placetype": [
          "aat:300008347"
        ],
        "id": 1137278,
        "name:xx": "Ber'ozovka"
      }
    },
    {
      "geometry": {
        "type": "Point",
        "coordinates": [
          56.4333,
          65
        ]
      },
      "type": "Feature",
      "properties": {
        "hierarchy": [
          "tgn:1137279",
          "tgn:1000004",
          "tgn:6003149",
          "tgn:7002435",
          "tgn:7029392"
        ],
        "placetype": [
          "aat:300008347"
        ],
        "id": 1137279,
        "name:xx": "Ber'ozovka"
      }
    }
  ]
}
