{
  "geometry": {
    "type": "Point",
    "coordinates": [
      -102.3167,
      48.75
    ]
  },
  "type": "Feature",
  "properties": {
    "hierarchy": [
      "tgn:2077511",
      "tgn:2001563",
      "tgn:1000001",
      "tgn:7012149",
      "tgn:7007705",
      "tgn:7029392"
    ],
    "placetype": [
      "aat:300008347"
    ],
    "id": 2077511,
    "name:xx": "Coteau"
  }
}
