{
  "geometry": {
    "type": "Point",
    "coordinates": [
      -91.55,
      34.0667
    ]
  },
  "type": "Feature",
  "properties": {
    "hierarchy": [
      "tgn:2669936",
      "tgn:1000001",
      "tgn:7016172",
      "tgn:7012149",
      "tgn:2000144",
      "tgn:7029392"
    ],
    "placetype": [
      "aat:300008791"
    ],
    "id": 2669936,
    "name:xx": "Sloan Island"
  }
}
