{
  "type": "FeatureCollection",
  "features": [
    {
      "geometry": {
        "type": "Point",
        "coordinates": [
          -89.9,
          36.35
        ]
      },
      "type": "Feature",
      "properties": {
        "hierarchy": [
          "tgn:2288900",
          "tgn:1000001",
          "tgn:7012149",
          "tgn:2001227",
          "tgn:7007523",
          "tgn:7029392"
        ],
        "placetype": [
          "aat:300006075"
        ],
        "id": 2288900,
        "name:xx": "Ditch Number 82"
      }
    },
    {
      "geometry": {
        "type": "Point",
        "coordinates": [
          -89.9167,
          36.35
        ]
      },
      "type": "Feature",
      "properties": {
        "hierarchy": [
          "tgn:2288901",
          "tgn:1000001",
          "tgn:7012149",
          "tgn:2001227",
          "tgn:7007523",
          "tgn:7029392"
        ],
        "placetype": [
          "aat:300006075"
        ],
        "id": 2288901,
        "name:xx": "Ditch Number 83"
      }
    },
    {
      "geometry": {
        "type": "Point",
        "coordinates": [
          -89.9333,
          36.3333
        ]
      },
      "type": "Feature",
      "properties": {
        "hierarchy": [
          "tgn:2288902",
          "tgn:1000001",
          "tgn:7012149",
          "tgn:2001227",
          "tgn:7007523",
          "tgn:7029392"
        ],
        "placetype": [
          "aat:300006075"
        ],
        "id": 2288902,
        "name:xx": "Ditch Number 84"
      }
    },
    {
      "geometry": {
        "type": "Point",
        "coordinates": [
          -89.95,
          36.35
        ]
      },
      "type": "Feature",
      "properties": {
        "hierarchy": [
          "tgn:2288903",
          "tgn:1000001",
          "tgn:7012149",
          "tgn:7007523",
          "tgn:7029392"
        ],
        "placetype": [
          "aat:300006075"
        ],
        "id": 2288903,
        "name:xx": "Ditch Number 85"
      }
    },
    {
      "geometry": {
        "type": "Point",
        "coordinates": [
          -93.9167,
          42.55
        ]
      },
      "type": "Feature",
      "properties": {
        "hierarchy": [
          "tgn:2288904",
          "tgn:1000001",
          "tgn:7012149",
          "tgn:7007253",
          "tgn:7029392"
        ],
        "placetype": [
          "aat:300006075"
        ],
        "id": 2288904,
        "name:xx": "Ditch Number 86"
      }
    },
    {
      "geometry": {
        "type": "Point",
        "coordinates": [
          -93.85,
          42.6833
        ]
      },
      "type": "Feature",
      "properties": {
        "hierarchy": [
          "tgn:2288905",
          "tgn:1000001",
          "tgn:7012149",
          "tgn:2000659",
          "tgn:7007253",
          "tgn:7029392"
        ],
        "placetype": [
          "aat:300006075"
        ],
        "id": 2288905,
        "name:xx": "Ditch Number 9"
      }
    },
    {
      "geometry": {
        "type": "Point",
        "coordinates": [
          -89.85,
          36.4333
        ]
      },
      "type": "Feature",
      "properties": {
        "hierarchy": [
          "tgn:2288906",
          "tgn:1000001",
          "tgn:7012149",
          "tgn:7007523",
          "tgn:7029392"
        ],
        "placetype": [
          "aat:300006075"
        ],
        "id": 2288906,
        "name:xx": "Ditch Number 9"
      }
    },
    {
      "geometry": {
        "type": "Point",
        "coordinates": [
          -90.2333,
          36.9333
        ]
      },
      "type": "Feature",
      "properties": {
        "hierarchy": [
          "tgn:2288907",
          "tgn:1000001",
          "tgn:7012149",
          "tgn:2001255",
          "tgn:7007523",
          "tgn:7029392"
        ],
        "placetype": [
          "aat:300006075"
        ],
        "id": 2288907,
        "name:xx": "Ditch Number 9"
      }
    },
    {
      "geometry": {
        "type": "Point",
        "coordinates": [
          -107.1167,
          44.7333
        ]
      },
      "type": "Feature",
      "properties": {
        "hierarchy": [
          "tgn:2288908",
          "tgn:1000001",
          "tgn:7012149",
          "tgn:2002381",
          "tgn:7007923",
          "tgn:7029392"
        ],
        "placetype": [
          "aat:300006075"
        ],
        "id": 2288908,
        "name:xx": "Ditch Number 9"
      }
    },
    {
      "geometry": {
        "type": "Point",
        "coordinates": [
          -93.4167,
          42.9833
        ]
      },
      "type": "Feature",
      "properties": {
        "hierarchy": [
          "tgn:2288909",
          "tgn:1000001",
          "tgn:2000577",
          "tgn:7012149",
          "tgn:7007253",
          "tgn:7029392"
        ],
        "placetype": [
          "aat:300006075"
        ],
        "id": 2288909,
        "name:xx": "Ditch Number 92"
      }
    }
  ]
}
