{
  "geometry": {
    "type": "Point",
    "coordinates": [
      28.9167,
      39.75
    ]
  },
  "type": "Feature",
  "properties": {
    "hierarchy": [
      "tgn:1140841",
      "tgn:1001167",
      "tgn:1000004",
      "tgn:7018450",
      "tgn:1000144",
      "tgn:7029392"
    ],
    "placetype": [
      "aat:300008347"
    ],
    "id": 1140841,
    "name:xx": "Yenıce"
  }
}
