{
  "geometry": {
    "type": "Point",
    "coordinates": [
      -98.0167,
      32.35
    ]
  },
  "type": "Feature",
  "properties": {
    "hierarchy": [
      "tgn:1128349",
      "tgn:1000001",
      "tgn:7012149",
      "tgn:7007826",
      "tgn:7029392"
    ],
    "placetype": [
      "aat:300008707"
    ],
    "id": 1128349,
    "name:xx": "Paluxy"
  }
}
