{
  "geometry": {
    "type": "Point",
    "coordinates": [
      -85.2167,
      35.3333
    ]
  },
  "type": "Feature",
  "properties": {
    "hierarchy": [
      "tgn:2748203",
      "tgn:1000001",
      "tgn:7012149",
      "tgn:2001869",
      "tgn:7007825",
      "tgn:7029392"
    ],
    "placetype": [
      "aat:300008699"
    ],
    "id": 2748203,
    "name:xx": "Walker Branch"
  }
}
