{
  "geometry": {
    "type": "Point",
    "coordinates": [
      -113.15,
      34.8833
    ]
  },
  "type": "Feature",
  "properties": {
    "hierarchy": [
      "tgn:2248544",
      "tgn:1000001",
      "tgn:7006451",
      "tgn:7012149",
      "tgn:2000103",
      "tgn:7029392"
    ],
    "placetype": [
      "aat:300008761"
    ],
    "id": 2248544,
    "name:xx": "Cold Spring Canyon"
  }
}
