{
  "geometry": {
    "type": "Point",
    "coordinates": [
      -72.3333,
      42.75
    ]
  },
  "type": "Feature",
  "properties": {
    "hierarchy": [
      "tgn:2572718",
      "tgn:7019618",
      "tgn:1000001",
      "tgn:7012149",
      "tgn:7007564",
      "tgn:7029392"
    ],
    "placetype": [
      "aat:300008798"
    ],
    "id": 2572718,
    "name:xx": "Peaked Mountain"
  }
}
