{
  "geometry": {
    "type": "Point",
    "coordinates": [
      -75.15,
      41.05
    ]
  },
  "type": "Feature",
  "properties": {
    "hierarchy": [
      "tgn:2309303",
      "tgn:1000001",
      "tgn:7012149",
      "tgn:1002682",
      "tgn:7007710",
      "tgn:7029392"
    ],
    "placetype": [
      "aat:300006191"
    ],
    "id": 2309303,
    "name:xx": "East Stroudsburg Reservoir"
  }
}
