{
  "geometry": {
    "type": "Point",
    "coordinates": [
      -85.2167,
      43.4167
    ]
  },
  "type": "Feature",
  "properties": {
    "hierarchy": [
      "tgn:2166824",
      "tgn:1000001",
      "tgn:7012149",
      "tgn:2000981",
      "tgn:7007520",
      "tgn:7029392"
    ],
    "placetype": [
      "aat:300008680"
    ],
    "id": 2166824,
    "name:xx": "Big Brimmer Lake"
  }
}
