{
  "geometry": {
    "type": "Point",
    "coordinates": [
      -86.9833,
      34.3667
    ]
  },
  "type": "Feature",
  "properties": {
    "hierarchy": [
      "tgn:2642783",
      "tgn:7002659",
      "tgn:1000001",
      "tgn:7012149",
      "tgn:2000051",
      "tgn:7029392"
    ],
    "placetype": [
      "aat:300008699"
    ],
    "id": 2642783,
    "name:xx": "Sandlin Branch"
  }
}
