{
  "type": "FeatureCollection",
  "features": [
    {
      "geometry": {
        "type": "Point",
        "coordinates": [
          -114.5,
          53.5833
        ]
      },
      "type": "Feature",
      "properties": {
        "hierarchy": [
          "tgn:1118610",
          "tgn:7005694",
          "tgn:7005685",
          "tgn:1000001",
          "tgn:7029392"
        ],
        "placetype": [
          "aat:300008680"
        ],
        "id": 1118610,
        "name:xx": "Wabamun Lake"
      }
    },
    {
      "geometry": {
        "type": "Point",
        "coordinates": [
          -71.3,
          42.2833
        ]
      },
      "type": "Feature",
      "properties": {
        "hierarchy": [
          "tgn:1118611",
          "tgn:1000001",
          "tgn:1002724",
          "tgn:7012149",
          "tgn:7007517",
          "tgn:7029392"
        ],
        "placetype": [
          "aat:300008680"
        ],
        "id": 1118611,
        "name:xx": "Waban, Lake"
      }
    },
    {
      "geometry": {
        "type": "Point",
        "coordinates": [
          -92.6667,
          49.75
        ]
      },
      "type": "Feature",
      "properties": {
        "hierarchy": [
          "tgn:1118613",
          "tgn:7005685",
          "tgn:1000001",
          "tgn:7013154",
          "tgn:7029392"
        ],
        "placetype": [
          "aat:300008680"
        ],
        "id": 1118613,
        "name:xx": "Wabigoon Lake"
      }
    },
    {
      "geometry": {
        "type": "Point",
        "coordinates": [
          116.9,
          32.3833
        ]
      },
      "type": "Feature",
      "properties": {
        "hierarchy": [
          "tgn:1118614",
          "tgn:7002075",
          "tgn:1000004",
          "tgn:1000111",
          "tgn:7029392"
        ],
        "placetype": [
          "aat:300008680"
        ],
        "id": 1118614,
        "name:xx": "Wabu Hu"
      }
    },
    {
      "geometry": {
        "type": "Point",
        "coordinates": [
          -78.5,
          34.2833
        ]
      },
      "type": "Feature",
      "properties": {
        "hierarchy": [
          "tgn:1118615",
          "tgn:1000001",
          "tgn:2001485",
          "tgn:7012149",
          "tgn:7007709",
          "tgn:7029392"
        ],
        "placetype": [
          "aat:300008680"
        ],
        "id": 1118615,
        "name:xx": "Waccamaw, Lake"
      }
    },
    {
      "geometry": {
        "type": "Point",
        "coordinates": [
          12.783333,
          47.933333
        ]
      },
      "type": "Feature",
      "properties": {
        "hierarchy": [
          "tgn:1118616",
          "tgn:7003669",
          "tgn:1000003",
          "tgn:7000084",
          "tgn:7029392"
        ],
        "placetype": [
          "aat:300008680"
        ],
        "id": 1118616,
        "name:xx": "Waginger See"
      }
    },
    {
      "geometry": {
        "type": "Point",
        "coordinates": [
          174.8,
          -39.666667
        ]
      },
      "type": "Feature",
      "properties": {
        "hierarchy": [
          "tgn:1118617",
          "tgn:1008380",
          "tgn:1000226",
          "tgn:7018426",
          "tgn:1000006",
          "tgn:7029392"
        ],
        "placetype": [
          "aat:300008680"
        ],
        "id": 1118617,
        "name:xx": "Waikare, Lake"
      }
    },
    {
      "geometry": {
        "type": "Point",
        "coordinates": [
          177.083333,
          -38.766667
        ]
      },
      "type": "Feature",
      "properties": {
        "hierarchy": [
          "tgn:1118618",
          "tgn:7016670",
          "tgn:1008380",
          "tgn:1000226",
          "tgn:1000006",
          "tgn:7029392"
        ],
        "placetype": [
          "aat:300008680"
        ],
        "name:en": "Waikaremoana, Lake",
        "id": 1118618
      }
    },
    {
      "geometry": {
        "type": "Point",
        "coordinates": [
          175.25,
          -41.216667
        ]
      },
      "type": "Feature",
      "properties": {
        "hierarchy": [
          "tgn:1118619",
          "tgn:1008380",
          "tgn:1000226",
          "tgn:7000512",
          "tgn:1000006",
          "tgn:7029392"
        ],
        "placetype": [
          "aat:300008680"
        ],
        "name:en": "Wairarapa, Lake",
        "id": 1118619
      }
    }
  ]
}
