{
  "geometry": {
    "type": "Point",
    "coordinates": [
      -104.6333,
      30.6667
    ]
  },
  "type": "Feature",
  "properties": {
    "hierarchy": [
      "tgn:2463587",
      "tgn:1000001",
      "tgn:7012149",
      "tgn:7007826",
      "tgn:7029392"
    ],
    "placetype": [
      "aat:300008761"
    ],
    "id": 2463587,
    "name:xx": "Lobo Valley"
  }
}
