{
  "geometry": {
    "type": "Point",
    "coordinates": [
      43.3333,
      12.6667
    ]
  },
  "type": "Feature",
  "properties": {
    "hierarchy": [
      "tgn:7014774",
      "tgn:7029392"
    ],
    "placetype": [
      "aat:300266559"
    ],
    "id": 7014774,
    "name:xx": "Mandeb, Bab el"
  }
}
