{
  "geometry": {
    "type": "Point",
    "coordinates": [
      -76.4667,
      34.9333
    ]
  },
  "type": "Feature",
  "properties": {
    "hierarchy": [
      "tgn:2342733",
      "tgn:1000001",
      "tgn:2001477",
      "tgn:7012149",
      "tgn:7007709",
      "tgn:7029392"
    ],
    "placetype": [
      "aat:300008706"
    ],
    "id": 2342733,
    "name:xx": "Fur Creek"
  }
}
