{
  "geometry": {
    "type": "Point",
    "coordinates": [
      -84.2333,
      44.3667
    ]
  },
  "type": "Feature",
  "properties": {
    "hierarchy": [
      "tgn:2749323",
      "tgn:1000001",
      "tgn:7012149",
      "tgn:2000985",
      "tgn:7007520",
      "tgn:7029392"
    ],
    "placetype": [
      "aat:300008680"
    ],
    "id": 2749323,
    "name:xx": "Wallin Lake"
  }
}
