{
  "geometry": {
    "type": "Point",
    "coordinates": [
      115.8333,
      39.15
    ]
  },
  "type": "Feature",
  "properties": {
    "hierarchy": [
      "tgn:1139941",
      "tgn:1000004",
      "tgn:7002077",
      "tgn:1000111",
      "tgn:7029392"
    ],
    "placetype": [
      "aat:300008347"
    ],
    "id": 1139941,
    "name:xx": "Yangcun"
  }
}
