{
  "geometry": {
    "type": "Point",
    "coordinates": [
      78.5425,
      17.505278
    ]
  },
  "type": "Feature",
  "properties": {
    "hierarchy": [
      "tgn:7568184",
      "tgn:1001828",
      "tgn:1000004",
      "tgn:7000198",
      "tgn:7029392"
    ],
    "placetype": [
      "aat:300008347"
    ],
    "name:en": "Yaprāl",
    "id": 7568184
  }
}
