{
  "geometry": {
    "type": "Point",
    "coordinates": [
      -97.3667,
      28.85
    ]
  },
  "type": "Feature",
  "properties": {
    "hierarchy": [
      "tgn:2108414",
      "tgn:1000001",
      "tgn:7012149",
      "tgn:1002413",
      "tgn:7007826",
      "tgn:7029392"
    ],
    "placetype": [
      "aat:300008347",
      "aat:300387210"
    ],
    "id": 2108414,
    "name:xx": "Weser"
  }
}
