{
  "geometry": {
    "type": "Point",
    "coordinates": [
      -90.8667,
      39.7667
    ]
  },
  "type": "Feature",
  "properties": {
    "hierarchy": [
      "tgn:2509176",
      "tgn:1000001",
      "tgn:7012149",
      "tgn:1002786",
      "tgn:7007251",
      "tgn:7029392"
    ],
    "placetype": [
      "aat:300008706"
    ],
    "id": 2509176,
    "name:xx": "Middle Fork McKee Creek"
  }
}
