{
  "geometry": {
    "type": "Point",
    "coordinates": [
      -85.7167,
      34.4167
    ]
  },
  "type": "Feature",
  "properties": {
    "hierarchy": [
      "tgn:2490503",
      "tgn:7002659",
      "tgn:1000001",
      "tgn:7012149",
      "tgn:7021514",
      "tgn:7029392"
    ],
    "placetype": [
      "aat:300008697"
    ],
    "id": 2490503,
    "name:xx": "Manitou Spring"
  }
}
