{
  "geometry": {
    "type": "Point",
    "coordinates": [
      28.0333,
      -27.7333
    ]
  },
  "type": "Feature",
  "properties": {
    "hierarchy": [
      "tgn:1093383",
      "tgn:7001242",
      "tgn:7016562",
      "tgn:1000193",
      "tgn:7029392"
    ],
    "placetype": [
      "aat:300008347"
    ],
    "id": 1093383,
    "name:xx": "Middenin"
  }
}
