{
  "type": "FeatureCollection",
  "features": [
    {
      "geometry": {
        "type": "Point",
        "coordinates": [
          -77.1667,
          39.0333
        ]
      },
      "type": "Feature",
      "properties": {
        "hierarchy": [
          "tgn:1132601",
          "tgn:1000001",
          "tgn:7016104",
          "tgn:7012149",
          "tgn:7007516",
          "tgn:7029392"
        ],
        "placetype": [
          "aat:300008706"
        ],
        "id": 1132601,
        "name:xx": "Buck Branch"
      }
    },
    {
      "geometry": {
        "type": "Point",
        "coordinates": [
          -86.0833,
          39.0167
        ]
      },
      "type": "Feature",
      "properties": {
        "hierarchy": [
          "tgn:1132602",
          "tgn:1000001",
          "tgn:7012149",
          "tgn:7007252",
          "tgn:7029392"
        ],
        "placetype": [
          "aat:300008706"
        ],
        "id": 1132602,
        "name:xx": "Buck Creek"
      }
    },
    {
      "geometry": {
        "type": "Point",
        "coordinates": [
          -86.1,
          36.9667
        ]
      },
      "type": "Feature",
      "properties": {
        "hierarchy": [
          "tgn:1132603",
          "tgn:1000001",
          "tgn:7012149",
          "tgn:7007255",
          "tgn:7029392"
        ],
        "placetype": [
          "aat:300008706"
        ],
        "id": 1132603,
        "name:xx": "Buck Creek"
      }
    },
    {
      "geometry": {
        "type": "Point",
        "coordinates": [
          -83.6167,
          40.1333
        ]
      },
      "type": "Feature",
      "properties": {
        "hierarchy": [
          "tgn:1132604",
          "tgn:1000001",
          "tgn:7012149",
          "tgn:7007706",
          "tgn:7029392"
        ],
        "placetype": [
          "aat:300008706"
        ],
        "id": 1132604,
        "name:xx": "Buck Creek"
      }
    },
    {
      "geometry": {
        "type": "Point",
        "coordinates": [
          -74.8667,
          40.2167
        ]
      },
      "type": "Feature",
      "properties": {
        "hierarchy": [
          "tgn:1132605",
          "tgn:1000001",
          "tgn:1002213",
          "tgn:7012149",
          "tgn:7007710",
          "tgn:7029392"
        ],
        "placetype": [
          "aat:300008706"
        ],
        "id": 1132605,
        "name:xx": "Buck Creek"
      }
    },
    {
      "geometry": {
        "type": "Point",
        "coordinates": [
          -99.95,
          34.5667
        ]
      },
      "type": "Feature",
      "properties": {
        "hierarchy": [
          "tgn:1132606",
          "tgn:1000001",
          "tgn:7012149",
          "tgn:7029392"
        ],
        "placetype": [
          "aat:300008706"
        ],
        "id": 1132606,
        "name:xx": "Buck Creek"
      }
    },
    {
      "geometry": {
        "type": "Point",
        "coordinates": [
          -88.55,
          32.3667
        ]
      },
      "type": "Feature",
      "properties": {
        "hierarchy": [
          "tgn:1132608",
          "tgn:1000001",
          "tgn:7012149",
          "tgn:7007522",
          "tgn:7029392"
        ],
        "placetype": [
          "aat:300008706"
        ],
        "id": 1132608,
        "name:xx": "Buckatunna Creek"
      }
    }
  ]
}
