{
  "type": "FeatureCollection",
  "features": [
    {
      "geometry": {
        "type": "Point",
        "coordinates": [
          -111.6,
          42.15
        ]
      },
      "type": "Feature",
      "properties": {
        "hierarchy": [
          "tgn:1109883",
          "tgn:1000001",
          "tgn:7012149",
          "tgn:7029392"
        ],
        "placetype": [
          "aat:300386831"
        ],
        "id": 1109883,
        "name:xx": "Bear River Range"
      }
    },
    {
      "geometry": {
        "type": "Point",
        "coordinates": [
          -116.1333,
          37.35
        ]
      },
      "type": "Feature",
      "properties": {
        "hierarchy": [
          "tgn:1109884",
          "tgn:1000001",
          "tgn:2001418",
          "tgn:7012149",
          "tgn:7007526",
          "tgn:7029392"
        ],
        "placetype": [
          "aat:300386831"
        ],
        "id": 1109884,
        "name:xx": "Belted Range"
      }
    },
    {
      "geometry": {
        "type": "Point",
        "coordinates": [
          170,
          -44
        ]
      },
      "type": "Feature",
      "properties": {
        "hierarchy": [
          "tgn:1109885",
          "tgn:1009227",
          "tgn:7001866",
          "tgn:1000226",
          "tgn:1000006",
          "tgn:7029392"
        ],
        "placetype": [
          "aat:300386831",
          "aat:300008795"
        ],
        "name:en": "Ben Ohau Range",
        "id": 1109885
      }
    },
    {
      "geometry": {
        "type": "Point",
        "coordinates": [
          -133.75,
          61.1667
        ]
      },
      "type": "Feature",
      "properties": {
        "hierarchy": [
          "tgn:1109886",
          "tgn:7005685",
          "tgn:1000001",
          "tgn:7005806",
          "tgn:7029392"
        ],
        "placetype": [
          "aat:300386831"
        ],
        "id": 1109886,
        "name:xx": "Big Salmon Range"
      }
    },
    {
      "geometry": {
        "type": "Point",
        "coordinates": [
          99,
          13
        ]
      },
      "type": "Feature",
      "properties": {
        "hierarchy": [
          "tgn:1109887",
          "tgn:1000004",
          "tgn:7029392"
        ],
        "placetype": [
          "aat:300386831"
        ],
        "id": 1109887,
        "name:xx": "Bilauktaung Range"
      }
    }
  ]
}
