{
  "geometry": {
    "type": "Point",
    "coordinates": [
      -82.9333,
      39.0333
    ]
  },
  "type": "Feature",
  "properties": {
    "hierarchy": [
      "tgn:2583075",
      "tgn:1000001",
      "tgn:7012149",
      "tgn:1002788",
      "tgn:7007706",
      "tgn:7029392"
    ],
    "placetype": [
      "aat:300006191"
    ],
    "id": 2583075,
    "name:xx": "Pine Lake"
  }
}
