{
  "geometry": {
    "type": "Point",
    "coordinates": [
      -88.25,
      20.65
    ]
  },
  "type": "Feature",
  "properties": {
    "hierarchy": [
      "tgn:7360552",
      "tgn:1000001",
      "tgn:7005600",
      "tgn:7005560",
      "tgn:7029392"
    ],
    "placetype": [
      "aat:300008347"
    ],
    "id": 7360552,
    "name:xx": "Ebtún"
  }
}
