{
  "geometry": {
    "type": "Point",
    "coordinates": [
      -113.1333,
      38.3667
    ]
  },
  "type": "Feature",
  "properties": {
    "hierarchy": [
      "tgn:2229874",
      "tgn:2002101",
      "tgn:1000001",
      "tgn:7012149",
      "tgn:7007827",
      "tgn:7029392"
    ],
    "placetype": [
      "aat:300000390"
    ],
    "id": 2229874,
    "name:xx": "Cedar Talisman Mine"
  }
}
