{
  "geometry": {
    "type": "Point",
    "coordinates": [
      -116.4833,
      33.4833
    ]
  },
  "type": "Feature",
  "properties": {
    "hierarchy": [
      "tgn:2767551",
      "tgn:1000001",
      "tgn:7012149",
      "tgn:7007157",
      "tgn:1002828",
      "tgn:7029392"
    ],
    "placetype": [
      "aat:300008699"
    ],
    "id": 2767551,
    "name:xx": "White Wash"
  }
}
