{
  "geometry": {
    "type": "Point",
    "coordinates": [
      -80.2333,
      27.3333
    ]
  },
  "type": "Feature",
  "properties": {
    "hierarchy": [
      "tgn:2386654",
      "tgn:1000001",
      "tgn:7012149",
      "tgn:7016124",
      "tgn:7007240",
      "tgn:7029392"
    ],
    "placetype": [
      "aat:300132316"
    ],
    "id": 2386654,
    "name:xx": "Herman Bay"
  }
}
