{
  "geometry": {
    "type": "Point",
    "coordinates": [
      -121.5333,
      36.4833
    ]
  },
  "type": "Feature",
  "properties": {
    "hierarchy": [
      "tgn:2606927",
      "tgn:1000001",
      "tgn:7012149",
      "tgn:7007157",
      "tgn:1002684",
      "tgn:7029392"
    ],
    "placetype": [
      "aat:300008706"
    ],
    "id": 2606927,
    "name:xx": "Rana Creek"
  }
}
