{
  "geometry": {
    "type": "Point",
    "coordinates": [
      74.633333,
      20.166667
    ]
  },
  "type": "Feature",
  "properties": {
    "hierarchy": [
      "tgn:7555941",
      "tgn:1000004",
      "tgn:7000198",
      "tgn:1001895",
      "tgn:7029392"
    ],
    "placetype": [
      "aat:300008347"
    ],
    "name:en": "Rājāpur",
    "id": 7555941
  }
}
