{
  "type": "FeatureCollection",
  "features": [
    {
      "geometry": {
        "type": "Point",
        "coordinates": [
          -6.816667,
          42.433333
        ]
      },
      "type": "Feature",
      "properties": {
        "hierarchy": [
          "tgn:7298250",
          "tgn:7002831",
          "tgn:1000003",
          "tgn:7002786",
          "tgn:1000095",
          "tgn:7029392"
        ],
        "placetype": [
          "aat:300008347"
        ],
        "id": 7298250,
        "name:xx": "Sobrado"
      }
    },
    {
      "geometry": {
        "type": "Point",
        "coordinates": [
          -7.233333,
          42.316667
        ]
      },
      "type": "Feature",
      "properties": {
        "hierarchy": [
          "tgn:7298251",
          "tgn:7002831",
          "tgn:1000003",
          "tgn:7002786",
          "tgn:1000095",
          "tgn:7029392"
        ],
        "placetype": [
          "aat:300008347"
        ],
        "id": 7298251,
        "name:xx": "Sobrado"
      }
    },
    {
      "geometry": {
        "type": "Point",
        "coordinates": [
          -5.9,
          41.383333
        ]
      },
      "type": "Feature",
      "properties": {
        "hierarchy": [
          "tgn:7298252",
          "tgn:7001158",
          "tgn:7002850",
          "tgn:1000003",
          "tgn:1000095",
          "tgn:7029392"
        ],
        "placetype": [
          "aat:300008347"
        ],
        "id": 7298252,
        "name:xx": "Sobradillo de Palomares"
      }
    },
    {
      "geometry": {
        "type": "Point",
        "coordinates": [
          -5.916667,
          41.433333
        ]
      },
      "type": "Feature",
      "properties": {
        "hierarchy": [
          "tgn:7298253",
          "tgn:7001158",
          "tgn:7002850",
          "tgn:1000003",
          "tgn:1000095",
          "tgn:7029392"
        ],
        "placetype": [
          "aat:300008699"
        ],
        "id": 7298253,
        "name:xx": "Sobradillo, Rivera de"
      }
    },
    {
      "geometry": {
        "type": "Point",
        "coordinates": [
          -6.8,
          40.916667
        ]
      },
      "type": "Feature",
      "properties": {
        "hierarchy": [
          "tgn:7298254",
          "tgn:7002835",
          "tgn:7001158",
          "tgn:1000003",
          "tgn:1000095",
          "tgn:7029392"
        ],
        "placetype": [
          "aat:300008347"
        ],
        "id": 7298254,
        "name:xx": "Sobradillo"
      }
    },
    {
      "geometry": {
        "type": "Point",
        "coordinates": [
          -16.3,
          28.433333
        ]
      },
      "type": "Feature",
      "properties": {
        "hierarchy": [
          "tgn:7298255",
          "tgn:7002836",
          "tgn:7016622",
          "tgn:1000003",
          "tgn:1000095",
          "tgn:7029392"
        ],
        "placetype": [
          "aat:300008347"
        ],
        "id": 7298255,
        "name:xx": "Sobradillo"
      }
    },
    {
      "geometry": {
        "type": "Point",
        "coordinates": [
          -6.266667,
          39.433333
        ]
      },
      "type": "Feature",
      "properties": {
        "hierarchy": [
          "tgn:7298257",
          "tgn:7002811",
          "tgn:1000003",
          "tgn:7003837",
          "tgn:1000095",
          "tgn:7029392"
        ],
        "placetype": [
          "aat:300008347"
        ],
        "id": 7298257,
        "name:xx": "Sierra de Fuentes"
      }
    },
    {
      "geometry": {
        "type": "Point",
        "coordinates": [
          -0.8,
          42.266667
        ]
      },
      "type": "Feature",
      "properties": {
        "hierarchy": [
          "tgn:7298258",
          "tgn:7002759",
          "tgn:7002845",
          "tgn:1000003",
          "tgn:1000095",
          "tgn:7029392"
        ],
        "placetype": [
          "aat:300008347"
        ],
        "id": 7298258,
        "name:xx": "Sierra de Estronad"
      }
    },
    {
      "geometry": {
        "type": "Point",
        "coordinates": [
          -2.4,
          36.966667
        ]
      },
      "type": "Feature",
      "properties": {
        "hierarchy": [
          "tgn:7298259",
          "tgn:7002805",
          "tgn:7002758",
          "tgn:1000003",
          "tgn:1000095",
          "tgn:7029392"
        ],
        "placetype": [
          "aat:300008347"
        ],
        "id": 7298259,
        "name:xx": "Sierra Alhamilla"
      }
    }
  ]
}
