{
  "geometry": {
    "type": "Point",
    "coordinates": [
      40.5833,
      5.1333
    ]
  },
  "type": "Feature",
  "properties": {
    "hierarchy": [
      "tgn:1089806",
      "tgn:7001242",
      "tgn:1001537",
      "tgn:7000489",
      "tgn:7029392"
    ],
    "placetype": [
      "aat:300008347"
    ],
    "id": 1089806,
    "name:xx": "Fīltu"
  }
}
