{
  "geometry": {
    "type": "Point",
    "coordinates": [
      -108.7167,
      42.5167
    ]
  },
  "type": "Feature",
  "properties": {
    "hierarchy": [
      "tgn:2136256",
      "tgn:1000001",
      "tgn:7012149",
      "tgn:2002371",
      "tgn:7007923",
      "tgn:7029392"
    ],
    "placetype": [
      "aat:300008761"
    ],
    "id": 2136256,
    "name:xx": "Arasta Gulch"
  }
}
