{
  "geometry": {
    "type": "Point",
    "coordinates": [
      43.35,
      -21.7833
    ]
  },
  "type": "Feature",
  "properties": {
    "hierarchy": [
      "tgn:1090985",
      "tgn:7001242",
      "tgn:1001575",
      "tgn:1000173",
      "tgn:7029392"
    ],
    "placetype": [
      "aat:300008347"
    ],
    "id": 1090985,
    "name:xx": "Morombe"
  }
}
