{
  "geometry": {
    "type": "Point",
    "coordinates": [
      -85.6833,
      42.2667
    ]
  },
  "type": "Feature",
  "properties": {
    "hierarchy": [
      "tgn:2680873",
      "tgn:1000001",
      "tgn:7012149",
      "tgn:1002529",
      "tgn:7007520",
      "tgn:7029392"
    ],
    "placetype": [
      "aat:300008905"
    ],
    "id": 2680873,
    "name:xx": "South Lake"
  }
}
