{
  "type": "FeatureCollection",
  "features": [
    {
      "geometry": {
        "type": "Point",
        "coordinates": [
          -106.1,
          33.9833
        ]
      },
      "type": "Feature",
      "properties": {
        "hierarchy": [
          "tgn:2682100",
          "tgn:1000001",
          "tgn:7012149",
          "tgn:2001456",
          "tgn:7007566",
          "tgn:7029392"
        ],
        "placetype": [
          "aat:300006191"
        ],
        "id": 2682100,
        "name:xx": "South Tank"
      }
    },
    {
      "geometry": {
        "type": "Point",
        "coordinates": [
          -105.35,
          34.9667
        ]
      },
      "type": "Feature",
      "properties": {
        "hierarchy": [
          "tgn:2682101",
          "tgn:1000001",
          "tgn:7012149",
          "tgn:2001458",
          "tgn:7007566",
          "tgn:7029392"
        ],
        "placetype": [
          "aat:300006191"
        ],
        "id": 2682101,
        "name:xx": "South Tank"
      }
    },
    {
      "geometry": {
        "type": "Point",
        "coordinates": [
          -105.6667,
          35.0833
        ]
      },
      "type": "Feature",
      "properties": {
        "hierarchy": [
          "tgn:2682102",
          "tgn:1000001",
          "tgn:7012149",
          "tgn:2001453",
          "tgn:7007566",
          "tgn:7029392"
        ],
        "placetype": [
          "aat:300006191"
        ],
        "id": 2682102,
        "name:xx": "South Tank"
      }
    },
    {
      "geometry": {
        "type": "Point",
        "coordinates": [
          -108.6,
          32.0667
        ]
      },
      "type": "Feature",
      "properties": {
        "hierarchy": [
          "tgn:2682103",
          "tgn:1000001",
          "tgn:7012149",
          "tgn:2001440",
          "tgn:7007566",
          "tgn:7029392"
        ],
        "placetype": [
          "aat:300006191"
        ],
        "id": 2682103,
        "name:xx": "South Tank"
      }
    },
    {
      "geometry": {
        "type": "Point",
        "coordinates": [
          -108.0833,
          33.3833
        ]
      },
      "type": "Feature",
      "properties": {
        "hierarchy": [
          "tgn:2682104",
          "tgn:1000001",
          "tgn:2001429",
          "tgn:7012149",
          "tgn:7007566",
          "tgn:7029392"
        ],
        "placetype": [
          "aat:300006191"
        ],
        "id": 2682104,
        "name:xx": "South Tank"
      }
    },
    {
      "geometry": {
        "type": "Point",
        "coordinates": [
          -106.8167,
          36.3833
        ]
      },
      "type": "Feature",
      "properties": {
        "hierarchy": [
          "tgn:2682105",
          "tgn:1000001",
          "tgn:7012149",
          "tgn:2001449",
          "tgn:7007566",
          "tgn:7029392"
        ],
        "placetype": [
          "aat:300006191"
        ],
        "id": 2682105,
        "name:xx": "South Tank"
      }
    },
    {
      "geometry": {
        "type": "Point",
        "coordinates": [
          -103.5667,
          32.5
        ]
      },
      "type": "Feature",
      "properties": {
        "hierarchy": [
          "tgn:2682106",
          "tgn:1000001",
          "tgn:7012149",
          "tgn:2001441",
          "tgn:7007566",
          "tgn:7029392"
        ],
        "placetype": [
          "aat:300006191"
        ],
        "id": 2682106,
        "name:xx": "South Tank"
      }
    },
    {
      "geometry": {
        "type": "Point",
        "coordinates": [
          -108.3,
          31.9167
        ]
      },
      "type": "Feature",
      "properties": {
        "hierarchy": [
          "tgn:2682107",
          "tgn:1000001",
          "tgn:7012149",
          "tgn:2001437",
          "tgn:7007566",
          "tgn:7029392"
        ],
        "placetype": [
          "aat:300006191"
        ],
        "id": 2682107,
        "name:xx": "South Tank"
      }
    },
    {
      "geometry": {
        "type": "Point",
        "coordinates": [
          -106.9333,
          32.6
        ]
      },
      "type": "Feature",
      "properties": {
        "hierarchy": [
          "tgn:2682108",
          "tgn:1000001",
          "tgn:2001435",
          "tgn:7012149",
          "tgn:7007566",
          "tgn:7029392"
        ],
        "placetype": [
          "aat:300006191"
        ],
        "id": 2682108,
        "name:xx": "South Tank"
      }
    },
    {
      "geometry": {
        "type": "Point",
        "coordinates": [
          -101.4667,
          32.5333
        ]
      },
      "type": "Feature",
      "properties": {
        "hierarchy": [
          "tgn:2682109",
          "tgn:1000001",
          "tgn:2001943",
          "tgn:7012149",
          "tgn:7007826",
          "tgn:7029392"
        ],
        "placetype": [
          "aat:300006191"
        ],
        "id": 2682109,
        "name:xx": "South Tank"
      }
    }
  ]
}
