{
  "geometry": {
    "type": "Point",
    "coordinates": [
      -76.4833,
      -13.0833
    ]
  },
  "type": "Feature",
  "properties": {
    "hierarchy": [
      "tgn:1024426",
      "tgn:1000670",
      "tgn:1000002",
      "tgn:1000056",
      "tgn:7029392"
    ],
    "placetype": [
      "aat:300008347"
    ],
    "id": 1024426,
    "name:xx": "Cerro Azul"
  }
}
