{
  "geometry": {
    "type": "Point",
    "coordinates": [
      31.131919,
      27.223751
    ]
  },
  "type": "Feature",
  "properties": {
    "hierarchy": [
      "tgn:7524247",
      "tgn:7001242",
      "tgn:7016833",
      "tgn:1001114",
      "tgn:7029392"
    ],
    "placetype": [
      "aat:300008347"
    ],
    "name:en": "Aţ Ţawābīyah",
    "id": 7524247
  }
}
