{
  "geometry": {
    "type": "Point",
    "coordinates": [
      -100.3333,
      29.0167
    ]
  },
  "type": "Feature",
  "properties": {
    "hierarchy": [
      "tgn:2327446",
      "tgn:1000001",
      "tgn:7012149",
      "tgn:2002038",
      "tgn:7007826",
      "tgn:7029392"
    ],
    "placetype": [
      "aat:300006191"
    ],
    "id": 2327446,
    "name:xx": "First Tank"
  }
}
