{
  "type": "FeatureCollection",
  "features": [
    {
      "geometry": {
        "type": "Point",
        "coordinates": [
          -73.816667,
          -49.4
        ]
      },
      "type": "Feature",
      "properties": {
        "hierarchy": [
          "tgn:7275500",
          "tgn:1001702",
          "tgn:1000049",
          "tgn:1000002",
          "tgn:7029392"
        ],
        "placetype": [
          "aat:300008699"
        ],
        "id": 7275500,
        "name:xx": "Trinidad, Río"
      }
    },
    {
      "geometry": {
        "type": "Point",
        "coordinates": [
          -73.45,
          -40.333333
        ]
      },
      "type": "Feature",
      "properties": {
        "hierarchy": [
          "tgn:7275501",
          "tgn:1001699",
          "tgn:1000049",
          "tgn:1000002",
          "tgn:7029392"
        ],
        "placetype": [
          "aat:300008680"
        ],
        "id": 7275501,
        "name:xx": "Trinidad, Laguna de la"
      }
    },
    {
      "geometry": {
        "type": "Point",
        "coordinates": [
          -73.533333,
          -45.183333
        ]
      },
      "type": "Feature",
      "properties": {
        "hierarchy": [
          "tgn:7275502",
          "tgn:1001623",
          "tgn:1000049",
          "tgn:1000002",
          "tgn:7029392"
        ],
        "placetype": [
          "aat:300008791"
        ],
        "id": 7275502,
        "name:xx": "Trinidad, Isla"
      }
    },
    {
      "geometry": {
        "type": "Point",
        "coordinates": [
          -71.5,
          -34.4
        ]
      },
      "type": "Feature",
      "properties": {
        "hierarchy": [
          "tgn:7275504",
          "tgn:1001695",
          "tgn:1000049",
          "tgn:1000002",
          "tgn:7029392"
        ],
        "placetype": [
          "aat:300266554",
          "aat:300008699"
        ],
        "id": 7275504,
        "name:xx": "Trinidad, Estero de"
      }
    },
    {
      "geometry": {
        "type": "Point",
        "coordinates": [
          -72.1,
          -41.433333
        ]
      },
      "type": "Feature",
      "properties": {
        "hierarchy": [
          "tgn:7275505",
          "tgn:1001699",
          "tgn:1000049",
          "tgn:1000002",
          "tgn:7029392"
        ],
        "placetype": [
          "aat:300008795"
        ],
        "id": 7275505,
        "name:xx": "Trinidad, Cerro"
      }
    },
    {
      "geometry": {
        "type": "Point",
        "coordinates": [
          -75,
          -50
        ]
      },
      "type": "Feature",
      "properties": {
        "hierarchy": [
          "tgn:7275506",
          "tgn:1001702",
          "tgn:1000049",
          "tgn:1000002",
          "tgn:7029392"
        ],
        "placetype": [
          "aat:300387026"
        ],
        "id": 7275506,
        "name:xx": "Trinidad, Canal"
      }
    },
    {
      "geometry": {
        "type": "Point",
        "coordinates": [
          -71.566667,
          -34.383333
        ]
      },
      "type": "Feature",
      "properties": {
        "hierarchy": [
          "tgn:7275507",
          "tgn:1001695",
          "tgn:1000049",
          "tgn:1000002",
          "tgn:7029392"
        ],
        "placetype": [
          "aat:300008347"
        ],
        "id": 7275507,
        "name:xx": "Trinidad"
      }
    },
    {
      "geometry": {
        "type": "Point",
        "coordinates": [
          -72.383333,
          -40.333333
        ]
      },
      "type": "Feature",
      "properties": {
        "hierarchy": [
          "tgn:7275508",
          "tgn:1001699",
          "tgn:1000049",
          "tgn:1000002",
          "tgn:7029392"
        ],
        "placetype": [
          "aat:300000206"
        ],
        "id": 7275508,
        "name:xx": "Tringlo"
      }
    },
    {
      "geometry": {
        "type": "Point",
        "coordinates": [
          -72.083333,
          -38.6
        ]
      },
      "type": "Feature",
      "properties": {
        "hierarchy": [
          "tgn:7275509",
          "tgn:1001692",
          "tgn:1000049",
          "tgn:1000002",
          "tgn:7029392"
        ],
        "placetype": [
          "aat:300000206"
        ],
        "id": 7275509,
        "name:xx": "Trinchera"
      }
    }
  ]
}
