{
  "type": "FeatureCollection",
  "features": [
    {
      "geometry": {
        "type": "Point",
        "coordinates": [
          -89.8833,
          35.6833
        ]
      },
      "type": "Feature",
      "properties": {
        "hierarchy": [
          "tgn:2331900",
          "tgn:1000001",
          "tgn:7012149",
          "tgn:2001885",
          "tgn:7007825",
          "tgn:7029392"
        ],
        "placetype": [
          "aat:300008680"
        ],
        "id": 2331900,
        "name:xx": "Fletcher Lake"
      }
    },
    {
      "geometry": {
        "type": "Point",
        "coordinates": [
          -78.2,
          38.6333
        ]
      },
      "type": "Feature",
      "properties": {
        "hierarchy": [
          "tgn:2331902",
          "tgn:1000001",
          "tgn:7012149",
          "tgn:2002184",
          "tgn:7007919",
          "tgn:7029392"
        ],
        "placetype": [
          "aat:300008347"
        ],
        "id": 2331902,
        "name:xx": "Fletcher Mill"
      }
    },
    {
      "geometry": {
        "type": "Point",
        "coordinates": [
          -92.4667,
          34.55
        ]
      },
      "type": "Feature",
      "properties": {
        "hierarchy": [
          "tgn:2331903",
          "tgn:1000001",
          "tgn:7016172",
          "tgn:7012149",
          "tgn:2000167",
          "tgn:7029392"
        ],
        "placetype": [
          "aat:300000390"
        ],
        "id": 2331903,
        "name:xx": "Fletcher Mine"
      }
    },
    {
      "geometry": {
        "type": "Point",
        "coordinates": [
          -91.1,
          37.45
        ]
      },
      "type": "Feature",
      "properties": {
        "hierarchy": [
          "tgn:2331904",
          "tgn:1000001",
          "tgn:7012149",
          "tgn:2001236",
          "tgn:7007523",
          "tgn:7029392"
        ],
        "placetype": [
          "aat:300000390"
        ],
        "id": 2331904,
        "name:xx": "Fletcher Mine"
      }
    },
    {
      "geometry": {
        "type": "Point",
        "coordinates": [
          -91.1,
          37.45
        ]
      },
      "type": "Feature",
      "properties": {
        "hierarchy": [
          "tgn:2331905",
          "tgn:1000001",
          "tgn:7012149",
          "tgn:2001236",
          "tgn:7007523",
          "tgn:7029392"
        ],
        "placetype": [
          "aat:300006191"
        ],
        "id": 2331905,
        "name:xx": "Fletcher Mine Clarification Basin"
      }
    },
    {
      "geometry": {
        "type": "Point",
        "coordinates": [
          -92.45,
          36.2
        ]
      },
      "type": "Feature",
      "properties": {
        "hierarchy": [
          "tgn:2331906",
          "tgn:2000107",
          "tgn:1000001",
          "tgn:7016172",
          "tgn:7012149",
          "tgn:7029392"
        ],
        "placetype": [
          "aat:300008798"
        ],
        "id": 2331906,
        "name:xx": "Fletcher Mountain"
      }
    },
    {
      "geometry": {
        "type": "Point",
        "coordinates": [
          -106.1167,
          39.4
        ]
      },
      "type": "Feature",
      "properties": {
        "hierarchy": [
          "tgn:2331907",
          "tgn:1000001",
          "tgn:7012149",
          "tgn:7007158",
          "tgn:2000250",
          "tgn:7029392"
        ],
        "placetype": [
          "aat:300008798"
        ],
        "id": 2331907,
        "name:xx": "Fletcher Mountain"
      }
    },
    {
      "geometry": {
        "type": "Point",
        "coordinates": [
          -69.9333,
          45.0333
        ]
      },
      "type": "Feature",
      "properties": {
        "hierarchy": [
          "tgn:2331908",
          "tgn:1000001",
          "tgn:7012149",
          "tgn:2000930",
          "tgn:7007515",
          "tgn:7029392"
        ],
        "placetype": [
          "aat:300008798"
        ],
        "id": 2331908,
        "name:xx": "Fletcher Mountain"
      }
    },
    {
      "geometry": {
        "type": "Point",
        "coordinates": [
          -112.1,
          46.0833
        ]
      },
      "type": "Feature",
      "properties": {
        "hierarchy": [
          "tgn:2331909",
          "tgn:1000001",
          "tgn:7012149",
          "tgn:2001281",
          "tgn:7007524",
          "tgn:7029392"
        ],
        "placetype": [
          "aat:300008798"
        ],
        "id": 2331909,
        "name:xx": "Fletcher Mountain"
      }
    }
  ]
}
