{
  "geometry": {
    "type": "Point",
    "coordinates": [
      -112.25,
      35.75
    ]
  },
  "type": "Feature",
  "properties": {
    "hierarchy": [
      "tgn:2772127",
      "tgn:1000001",
      "tgn:7006451",
      "tgn:2000092",
      "tgn:7012149",
      "tgn:7029392"
    ],
    "placetype": [
      "aat:300008347"
    ],
    "id": 2772127,
    "name:xx": "Willaha"
  }
}
