{
  "geometry": {
    "type": "Point",
    "coordinates": [
      73.316667,
      21.45
    ]
  },
  "type": "Feature",
  "properties": {
    "hierarchy": [
      "tgn:7584609",
      "tgn:1000004",
      "tgn:1001869",
      "tgn:7000198",
      "tgn:7029392"
    ],
    "placetype": [
      "aat:300007783"
    ],
    "name:en": "Zankhvāv",
    "id": 7584609
  }
}
