{
  "geometry": {
    "type": "Point",
    "coordinates": [
      -150.35,
      63.7833
    ]
  },
  "type": "Feature",
  "properties": {
    "hierarchy": [
      "tgn:2533905",
      "tgn:7006450",
      "tgn:1000001",
      "tgn:7030547",
      "tgn:7012149",
      "tgn:7029392"
    ],
    "placetype": [
      "aat:300008706"
    ],
    "id": 2533905,
    "name:xx": "Myers Creek"
  }
}
