{
  "geometry": {
    "type": "Point",
    "coordinates": [
      -82.05,
      39.8667
    ]
  },
  "type": "Feature",
  "properties": {
    "hierarchy": [
      "tgn:2313983",
      "tgn:1000001",
      "tgn:7012149",
      "tgn:1002701",
      "tgn:7007706",
      "tgn:7029392"
    ],
    "placetype": [
      "aat:300008347"
    ],
    "id": 2313983,
    "name:xx": "Elizabeth"
  }
}
