{
  "type": "FeatureCollection",
  "features": [
    {
      "geometry": {
        "type": "Point",
        "coordinates": [
          -86.05,
          36.5667
        ]
      },
      "type": "Feature",
      "properties": {
        "hierarchy": [
          "tgn:2686640",
          "tgn:1000001",
          "tgn:7012149",
          "tgn:2001892",
          "tgn:7007825",
          "tgn:7029392"
        ],
        "placetype": [
          "aat:300008706"
        ],
        "id": 2686640,
        "name:xx": "Spring Creek"
      }
    },
    {
      "geometry": {
        "type": "Point",
        "coordinates": [
          -86.1333,
          35.35
        ]
      },
      "type": "Feature",
      "properties": {
        "hierarchy": [
          "tgn:2686641",
          "tgn:1000001",
          "tgn:7012149",
          "tgn:2001862",
          "tgn:7007825",
          "tgn:7029392"
        ],
        "placetype": [
          "aat:300008706"
        ],
        "id": 2686641,
        "name:xx": "Spring Creek"
      }
    },
    {
      "geometry": {
        "type": "Point",
        "coordinates": [
          -88.4667,
          35.4167
        ]
      },
      "type": "Feature",
      "properties": {
        "hierarchy": [
          "tgn:2686642",
          "tgn:1000001",
          "tgn:7012149",
          "tgn:2001848",
          "tgn:7007825",
          "tgn:7029392"
        ],
        "placetype": [
          "aat:300008706"
        ],
        "id": 2686642,
        "name:xx": "Spring Creek"
      }
    },
    {
      "geometry": {
        "type": "Point",
        "coordinates": [
          -86.6833,
          35.6833
        ]
      },
      "type": "Feature",
      "properties": {
        "hierarchy": [
          "tgn:2686643",
          "tgn:1000001",
          "tgn:7012149",
          "tgn:2001895",
          "tgn:7007825",
          "tgn:7029392"
        ],
        "placetype": [
          "aat:300008706"
        ],
        "id": 2686643,
        "name:xx": "Spring Creek"
      }
    },
    {
      "geometry": {
        "type": "Point",
        "coordinates": [
          -87.9,
          35.65
        ]
      },
      "type": "Feature",
      "properties": {
        "hierarchy": [
          "tgn:2686644",
          "tgn:1000001",
          "tgn:7012149",
          "tgn:2001904",
          "tgn:7007825",
          "tgn:7029392"
        ],
        "placetype": [
          "aat:300008706"
        ],
        "id": 2686644,
        "name:xx": "Spring Creek"
      }
    },
    {
      "geometry": {
        "type": "Point",
        "coordinates": [
          -88.4667,
          35.7667
        ]
      },
      "type": "Feature",
      "properties": {
        "hierarchy": [
          "tgn:2686645",
          "tgn:1000001",
          "tgn:7012149",
          "tgn:2001875",
          "tgn:7007825",
          "tgn:7029392"
        ],
        "placetype": [
          "aat:300008706"
        ],
        "id": 2686645,
        "name:xx": "Spring Creek"
      }
    },
    {
      "geometry": {
        "type": "Point",
        "coordinates": [
          -88.2167,
          36.1833
        ]
      },
      "type": "Feature",
      "properties": {
        "hierarchy": [
          "tgn:2686646",
          "tgn:1000001",
          "tgn:7012149",
          "tgn:2001876",
          "tgn:7007825",
          "tgn:7029392"
        ],
        "placetype": [
          "aat:300008706"
        ],
        "id": 2686646,
        "name:xx": "Spring Creek"
      }
    },
    {
      "geometry": {
        "type": "Point",
        "coordinates": [
          -83.2333,
          36.2
        ]
      },
      "type": "Feature",
      "properties": {
        "hierarchy": [
          "tgn:2686647",
          "tgn:1000001",
          "tgn:7012149",
          "tgn:2001868",
          "tgn:7007825",
          "tgn:7029392"
        ],
        "placetype": [
          "aat:300008706"
        ],
        "id": 2686647,
        "name:xx": "Spring Creek"
      }
    },
    {
      "geometry": {
        "type": "Point",
        "coordinates": [
          -88.6333,
          35.7333
        ]
      },
      "type": "Feature",
      "properties": {
        "hierarchy": [
          "tgn:2686648",
          "tgn:1000001",
          "tgn:7012149",
          "tgn:2001893",
          "tgn:7007825",
          "tgn:7029392"
        ],
        "placetype": [
          "aat:300008706"
        ],
        "id": 2686648,
        "name:xx": "Spring Creek"
      }
    },
    {
      "geometry": {
        "type": "Point",
        "coordinates": [
          -86.2333,
          36.1333
        ]
      },
      "type": "Feature",
      "properties": {
        "hierarchy": [
          "tgn:2686649",
          "tgn:1000001",
          "tgn:7012149",
          "tgn:2001931",
          "tgn:7007825",
          "tgn:7029392"
        ],
        "placetype": [
          "aat:300008347"
        ],
        "id": 2686649,
        "name:xx": "Spring Creek"
      }
    }
  ]
}
