{
  "geometry": {
    "type": "Point",
    "coordinates": [
      -84.55,
      30.05
    ]
  },
  "type": "Feature",
  "properties": {
    "hierarchy": [
      "tgn:2130547",
      "tgn:1000001",
      "tgn:7012149",
      "tgn:2000289",
      "tgn:7007240",
      "tgn:7029392"
    ],
    "placetype": [
      "aat:300008706"
    ],
    "id": 2130547,
    "name:xx": "Alligator Creek"
  }
}
