{
  "geometry": {
    "type": "Point",
    "coordinates": [
      -93.9833,
      32.2167
    ]
  },
  "type": "Feature",
  "properties": {
    "hierarchy": [
      "tgn:2042812",
      "tgn:1000001",
      "tgn:2000862",
      "tgn:7012149",
      "tgn:7007256",
      "tgn:7029392"
    ],
    "placetype": [
      "aat:300008347",
      "aat:300387210"
    ],
    "id": 2042812,
    "name:xx": "Four Forks"
  }
}
