{
  "type": "FeatureCollection",
  "features": [
    {
      "geometry": {
        "type": "Point",
        "coordinates": [
          9.983333,
          48.483333
        ]
      },
      "type": "Feature",
      "properties": {
        "hierarchy": [
          "tgn:7211080",
          "tgn:7003692",
          "tgn:1000003",
          "tgn:7000084",
          "tgn:7029392"
        ],
        "placetype": [
          "aat:300008347"
        ],
        "id": 7211080,
        "name:xx": "Beimerstetten"
      }
    },
    {
      "geometry": {
        "type": "Point",
        "coordinates": [
          8.2,
          53.166667
        ]
      },
      "type": "Feature",
      "properties": {
        "hierarchy": [
          "tgn:7211081",
          "tgn:1000003",
          "tgn:7003676",
          "tgn:7000084",
          "tgn:7029392"
        ],
        "placetype": [
          "aat:300000745"
        ],
        "id": 7211081,
        "name:xx": "Beim Bürgerbusch"
      }
    },
    {
      "geometry": {
        "type": "Point",
        "coordinates": [
          9.970833,
          49.243611
        ]
      },
      "type": "Feature",
      "properties": {
        "hierarchy": [
          "tgn:7211082",
          "tgn:7003692",
          "tgn:1000003",
          "tgn:7000084",
          "tgn:7029392"
        ],
        "placetype": [
          "aat:300008347"
        ],
        "id": 7211082,
        "name:xx": "Beimbach"
      }
    },
    {
      "geometry": {
        "type": "Point",
        "coordinates": [
          8.35,
          50.75
        ]
      },
      "type": "Feature",
      "properties": {
        "hierarchy": [
          "tgn:7211083",
          "tgn:1000003",
          "tgn:7003678",
          "tgn:7000084",
          "tgn:7029392"
        ],
        "placetype": [
          "aat:300008347"
        ],
        "id": 7211083,
        "name:xx": "Beilstein"
      }
    },
    {
      "geometry": {
        "type": "Point",
        "coordinates": [
          8.516667,
          50.866667
        ]
      },
      "type": "Feature",
      "properties": {
        "hierarchy": [
          "tgn:7211087",
          "tgn:1000003",
          "tgn:7003678",
          "tgn:7000084",
          "tgn:7029392"
        ],
        "placetype": [
          "aat:300008777"
        ],
        "id": 7211087,
        "name:xx": "Beilstein"
      }
    },
    {
      "geometry": {
        "type": "Point",
        "coordinates": [
          6.966667,
          50.283333
        ]
      },
      "type": "Feature",
      "properties": {
        "hierarchy": [
          "tgn:7211088",
          "tgn:1000003",
          "tgn:7003682",
          "tgn:7000084",
          "tgn:7029392"
        ],
        "placetype": [
          "aat:300008777"
        ],
        "id": 7211088,
        "name:xx": "Beilstein"
      }
    },
    {
      "geometry": {
        "type": "Point",
        "coordinates": [
          9.4,
          50.166667
        ]
      },
      "type": "Feature",
      "properties": {
        "hierarchy": [
          "tgn:7211089",
          "tgn:1000003",
          "tgn:7003678",
          "tgn:7000084",
          "tgn:7029392"
        ],
        "placetype": [
          "aat:300008777"
        ],
        "id": 7211089,
        "name:xx": "Beilstein"
      }
    }
  ]
}
