{
  "geometry": {
    "type": "Point",
    "coordinates": [
      14.4167,
      50.083
    ]
  },
  "type": "Feature",
  "properties": {
    "hierarchy": [
      "tgn:1003530",
      "tgn:1000003",
      "tgn:1001780",
      "tgn:7029392"
    ],
    "placetype": [
      "aat:300387064",
      "aat:300236112"
    ],
    "name:en": "Středočeský",
    "name:cs": "Středočeský",
    "id": 1003530
  }
}
