{
  "geometry": {
    "type": "Point",
    "coordinates": [
      -86.6333,
      34.4833
    ]
  },
  "type": "Feature",
  "properties": {
    "hierarchy": [
      "tgn:2781377",
      "tgn:7002659",
      "tgn:1000001",
      "tgn:7012149",
      "tgn:2000051",
      "tgn:7029392"
    ],
    "placetype": [
      "aat:300008706"
    ],
    "id": 2781377,
    "name:xx": "Woodland Mills Creek"
  }
}
