{
  "geometry": {
    "type": "Point",
    "coordinates": [
      -78.9167,
      40.3333
    ]
  },
  "type": "Feature",
  "properties": {
    "hierarchy": [
      "tgn:2215663",
      "tgn:1000001",
      "tgn:1002225",
      "tgn:7012149",
      "tgn:7007710",
      "tgn:7029392"
    ],
    "placetype": [
      "aat:300008347"
    ],
    "id": 2215663,
    "name:xx": "Cambria City"
  }
}
