{
  "geometry": {
    "type": "Point",
    "coordinates": [
      74.766667,
      34.25
    ]
  },
  "type": "Feature",
  "properties": {
    "hierarchy": [
      "tgn:7589294",
      "tgn:1000004",
      "tgn:7000198",
      "tgn:7000799",
      "tgn:7029392"
    ],
    "placetype": [
      "aat:300008347"
    ],
    "name:en": "Chak-i-Wātalbāgh",
    "id": 7589294
  }
}
