{
  "geometry": {
    "type": "Point",
    "coordinates": [
      -104.4667,
      46.3333
    ]
  },
  "type": "Feature",
  "properties": {
    "hierarchy": [
      "tgn:2681815",
      "tgn:1000001",
      "tgn:7012149",
      "tgn:2001272",
      "tgn:7007524",
      "tgn:7029392"
    ],
    "placetype": [
      "aat:300006191"
    ],
    "id": 2681815,
    "name:xx": "South Sandstone Reservoir"
  }
}
