{
  "geometry": {
    "type": "Point",
    "coordinates": [
      -83.5333,
      32.6333
    ]
  },
  "type": "Feature",
  "properties": {
    "hierarchy": [
      "tgn:2416613",
      "tgn:1000001",
      "tgn:7012149",
      "tgn:2000434",
      "tgn:7007248",
      "tgn:7029392"
    ],
    "placetype": [
      "aat:300008680"
    ],
    "id": 2416613,
    "name:xx": "Jack Hole"
  }
}
