{
  "type": "FeatureCollection",
  "features": [
    {
      "geometry": {
        "type": "Point",
        "coordinates": [
          9.548889,
          49.385
        ]
      },
      "type": "Feature",
      "properties": {
        "hierarchy": [
          "tgn:7187840",
          "tgn:7003692",
          "tgn:1000003",
          "tgn:7000084",
          "tgn:7029392"
        ],
        "placetype": [
          "aat:300008347"
        ],
        "id": 7187840,
        "name:xx": "Erlenbach"
      }
    },
    {
      "geometry": {
        "type": "Point",
        "coordinates": [
          7.85,
          49.333333
        ]
      },
      "type": "Feature",
      "properties": {
        "hierarchy": [
          "tgn:7187841",
          "tgn:1000003",
          "tgn:7003682",
          "tgn:7000084",
          "tgn:7029392"
        ],
        "placetype": [
          "aat:300008347"
        ],
        "id": 7187841,
        "name:xx": "Erlenbach"
      }
    },
    {
      "geometry": {
        "type": "Point",
        "coordinates": [
          9.268333,
          49.1725
        ]
      },
      "type": "Feature",
      "properties": {
        "hierarchy": [
          "tgn:7187842",
          "tgn:7003692",
          "tgn:1000003",
          "tgn:7000084",
          "tgn:7029392"
        ],
        "placetype": [
          "aat:300008347"
        ],
        "id": 7187842,
        "name:xx": "Erlenbach"
      }
    },
    {
      "geometry": {
        "type": "Point",
        "coordinates": [
          8.186111,
          49.110833
        ]
      },
      "type": "Feature",
      "properties": {
        "hierarchy": [
          "tgn:7187843",
          "tgn:1000003",
          "tgn:7003682",
          "tgn:7000084",
          "tgn:7029392"
        ],
        "placetype": [
          "aat:300008347"
        ],
        "id": 7187843,
        "name:xx": "Erlenbach"
      }
    },
    {
      "geometry": {
        "type": "Point",
        "coordinates": [
          7.866667,
          49.116667
        ]
      },
      "type": "Feature",
      "properties": {
        "hierarchy": [
          "tgn:7187844",
          "tgn:1000003",
          "tgn:7003682",
          "tgn:7000084",
          "tgn:7029392"
        ],
        "placetype": [
          "aat:300008347"
        ],
        "id": 7187844,
        "name:xx": "Erlenbach"
      }
    },
    {
      "geometry": {
        "type": "Point",
        "coordinates": [
          8.833333,
          48.95
        ]
      },
      "type": "Feature",
      "properties": {
        "hierarchy": [
          "tgn:7187845",
          "tgn:7003692",
          "tgn:1000003",
          "tgn:7000084",
          "tgn:7029392"
        ],
        "placetype": [
          "aat:300008347"
        ],
        "id": 7187845,
        "name:xx": "Erlenbach"
      }
    },
    {
      "geometry": {
        "type": "Point",
        "coordinates": [
          9.716667,
          49.016667
        ]
      },
      "type": "Feature",
      "properties": {
        "hierarchy": [
          "tgn:7187846",
          "tgn:7003692",
          "tgn:1000003",
          "tgn:7000084",
          "tgn:7029392"
        ],
        "placetype": [
          "aat:300000206"
        ],
        "id": 7187846,
        "name:xx": "Erlenbach"
      }
    },
    {
      "geometry": {
        "type": "Point",
        "coordinates": [
          13.466667,
          48.55
        ]
      },
      "type": "Feature",
      "properties": {
        "hierarchy": [
          "tgn:7187847",
          "tgn:7003669",
          "tgn:1000003",
          "tgn:7000084",
          "tgn:7029392"
        ],
        "placetype": [
          "aat:300000206"
        ],
        "id": 7187847,
        "name:xx": "Erlenbach"
      }
    },
    {
      "geometry": {
        "type": "Point",
        "coordinates": [
          7.95,
          47.9
        ]
      },
      "type": "Feature",
      "properties": {
        "hierarchy": [
          "tgn:7187848",
          "tgn:7003692",
          "tgn:1000003",
          "tgn:7000084",
          "tgn:7029392"
        ],
        "placetype": [
          "aat:300000206"
        ],
        "id": 7187848,
        "name:xx": "Erlenbach"
      }
    },
    {
      "geometry": {
        "type": "Point",
        "coordinates": [
          14.033333,
          51.75
        ]
      },
      "type": "Feature",
      "properties": {
        "hierarchy": [
          "tgn:7187849",
          "tgn:7000096",
          "tgn:1000003",
          "tgn:7000084",
          "tgn:7029392"
        ],
        "placetype": [
          "aat:300008347"
        ],
        "id": 7187849,
        "name:xx": "Erlenau"
      }
    }
  ]
}
