{
  "geometry": {
    "type": "Point",
    "coordinates": [
      1.8167,
      42.85
    ]
  },
  "type": "Feature",
  "properties": {
    "hierarchy": [
      "tgn:7009373",
      "tgn:1000003",
      "tgn:7002889",
      "tgn:1000070",
      "tgn:7029392"
    ],
    "placetype": [
      "aat:300000833"
    ],
    "id": 7009373,
    "name:xx": "Montségur"
  }
}
