{
  "geometry": {
    "type": "Point",
    "coordinates": [
      -119.3167,
      47.5333
    ]
  },
  "type": "Feature",
  "properties": {
    "hierarchy": [
      "tgn:2405000",
      "tgn:1000001",
      "tgn:7012149",
      "tgn:2002246",
      "tgn:7007920",
      "tgn:7029392"
    ],
    "placetype": [
      "aat:300008761"
    ],
    "id": 2405000,
    "name:xx": "Hudson Coulee"
  }
}
