{
  "geometry": {
    "type": "Point",
    "coordinates": [
      -80.7667,
      25.4833
    ]
  },
  "type": "Feature",
  "properties": {
    "hierarchy": [
      "tgn:2567462",
      "tgn:1000001",
      "tgn:7012149",
      "tgn:1002314",
      "tgn:7007240",
      "tgn:7029392"
    ],
    "placetype": [
      "aat:300008791"
    ],
    "id": 2567462,
    "name:xx": "Papaya Hammock"
  }
}
