{
  "geometry": {
    "type": "Point",
    "coordinates": [
      23.8833,
      46.4167
    ]
  },
  "type": "Feature",
  "properties": {
    "hierarchy": [
      "tgn:1050206",
      "tgn:1000336",
      "tgn:1000003",
      "tgn:1000091",
      "tgn:7029392"
    ],
    "placetype": [
      "aat:300008347"
    ],
    "id": 1050206,
    "name:xx": "Ocna Mureș"
  }
}
