{
  "type": "FeatureCollection",
  "features": [
    {
      "geometry": {
        "type": "Point",
        "coordinates": [
          7.216667,
          49.5
        ]
      },
      "type": "Feature",
      "properties": {
        "hierarchy": [
          "tgn:7103370",
          "tgn:1000003",
          "tgn:7003684",
          "tgn:7000084",
          "tgn:7029392"
        ],
        "placetype": [
          "aat:300008777"
        ],
        "id": 7103370,
        "name:xx": "Roter Berg"
      }
    },
    {
      "geometry": {
        "type": "Point",
        "coordinates": [
          8.866667,
          49.233333
        ]
      },
      "type": "Feature",
      "properties": {
        "hierarchy": [
          "tgn:7103371",
          "tgn:7003692",
          "tgn:1000003",
          "tgn:7000084",
          "tgn:7029392"
        ],
        "placetype": [
          "aat:300008777"
        ],
        "id": 7103371,
        "name:xx": "Roterberg"
      }
    },
    {
      "geometry": {
        "type": "Point",
        "coordinates": [
          8.081389,
          49.119444
        ]
      },
      "type": "Feature",
      "properties": {
        "hierarchy": [
          "tgn:7103372",
          "tgn:1000003",
          "tgn:7003682",
          "tgn:7000084",
          "tgn:7029392"
        ],
        "placetype": [
          "aat:300008777"
        ],
        "id": 7103372,
        "name:xx": "Roter Berg"
      }
    },
    {
      "geometry": {
        "type": "Point",
        "coordinates": [
          10.716667,
          48.983333
        ]
      },
      "type": "Feature",
      "properties": {
        "hierarchy": [
          "tgn:7103373",
          "tgn:7003669",
          "tgn:1000003",
          "tgn:7000084",
          "tgn:7029392"
        ],
        "placetype": [
          "aat:300008777"
        ],
        "id": 7103373,
        "name:xx": "Roter Berg"
      }
    },
    {
      "geometry": {
        "type": "Point",
        "coordinates": [
          9.266667,
          48.783333
        ]
      },
      "type": "Feature",
      "properties": {
        "hierarchy": [
          "tgn:7103374",
          "tgn:7003692",
          "tgn:1000003",
          "tgn:7000084",
          "tgn:7029392"
        ],
        "placetype": [
          "aat:300008777"
        ],
        "id": 7103374,
        "name:xx": "Roter Berg"
      }
    },
    {
      "geometry": {
        "type": "Point",
        "coordinates": [
          9.1,
          48.65
        ]
      },
      "type": "Feature",
      "properties": {
        "hierarchy": [
          "tgn:7103375",
          "tgn:7003692",
          "tgn:1000003",
          "tgn:7000084",
          "tgn:7029392"
        ],
        "placetype": [
          "aat:300008777"
        ],
        "id": 7103375,
        "name:xx": "Roter Berg"
      }
    },
    {
      "geometry": {
        "type": "Point",
        "coordinates": [
          10.516667,
          48.366667
        ]
      },
      "type": "Feature",
      "properties": {
        "hierarchy": [
          "tgn:7103376",
          "tgn:7003669",
          "tgn:1000003",
          "tgn:7000084",
          "tgn:7029392"
        ],
        "placetype": [
          "aat:300008777"
        ],
        "id": 7103376,
        "name:xx": "Roter Berg"
      }
    },
    {
      "geometry": {
        "type": "Point",
        "coordinates": [
          9.7,
          48.333333
        ]
      },
      "type": "Feature",
      "properties": {
        "hierarchy": [
          "tgn:7103377",
          "tgn:7003692",
          "tgn:1000003",
          "tgn:7000084",
          "tgn:7029392"
        ],
        "placetype": [
          "aat:300008777"
        ],
        "id": 7103377,
        "name:xx": "Roter Berg"
      }
    },
    {
      "geometry": {
        "type": "Point",
        "coordinates": [
          8.616667,
          51.75
        ]
      },
      "type": "Feature",
      "properties": {
        "hierarchy": [
          "tgn:7103378",
          "tgn:1000003",
          "tgn:7003677",
          "tgn:7000084",
          "tgn:7029392"
        ],
        "placetype": [
          "aat:300008699"
        ],
        "id": 7103378,
        "name:xx": "Roter Bach"
      }
    },
    {
      "geometry": {
        "type": "Point",
        "coordinates": [
          6.833333,
          51.583333
        ]
      },
      "type": "Feature",
      "properties": {
        "hierarchy": [
          "tgn:7103379",
          "tgn:1000003",
          "tgn:7003677",
          "tgn:7000084",
          "tgn:7029392"
        ],
        "placetype": [
          "aat:300008699"
        ],
        "id": 7103379,
        "name:xx": "Roter Bach"
      }
    }
  ]
}
