{
  "geometry": {
    "type": "Point",
    "coordinates": [
      -106.6333,
      35.15
    ]
  },
  "type": "Feature",
  "properties": {
    "hierarchy": [
      "tgn:2067160",
      "tgn:1000001",
      "tgn:2001428",
      "tgn:7012149",
      "tgn:7007566",
      "tgn:7029392"
    ],
    "placetype": [
      "aat:300008347"
    ],
    "id": 2067160,
    "name:xx": "Los Ranchos de Albuquerque"
  }
}
