{
  "geometry": {
    "type": "Point",
    "coordinates": [
      -119.5333,
      37.2833
    ]
  },
  "type": "Feature",
  "properties": {
    "hierarchy": [
      "tgn:2778278",
      "tgn:1000001",
      "tgn:7012149",
      "tgn:7007157",
      "tgn:1002621",
      "tgn:7029392"
    ],
    "placetype": [
      "aat:300132316"
    ],
    "id": 2778278,
    "name:xx": "Wishon Cove"
  }
}
