{
  "geometry": {
    "type": "Point",
    "coordinates": [
      -120.1833,
      48.8333
    ]
  },
  "type": "Feature",
  "properties": {
    "hierarchy": [
      "tgn:2176620",
      "tgn:1000001",
      "tgn:7012149",
      "tgn:1002742",
      "tgn:7007920",
      "tgn:7029392"
    ],
    "placetype": [
      "aat:300266640"
    ],
    "id": 2176620,
    "name:xx": "Black Lake Ridge"
  }
}
