{
  "type": "FeatureCollection",
  "features": [
    {
      "geometry": {
        "type": "Point",
        "coordinates": [
          -73.75,
          42.3167
        ]
      },
      "type": "Feature",
      "properties": {
        "hierarchy": [
          "tgn:2068611",
          "tgn:1000001",
          "tgn:7013638",
          "tgn:7012149",
          "tgn:7007568",
          "tgn:7029392"
        ],
        "placetype": [
          "aat:300008347"
        ],
        "id": 2068611,
        "name:xx": "Columbiaville"
      }
    },
    {
      "geometry": {
        "type": "Point",
        "coordinates": [
          -75.3667,
          42.6833
        ]
      },
      "type": "Feature",
      "properties": {
        "hierarchy": [
          "tgn:2068612",
          "tgn:1000001",
          "tgn:1002262",
          "tgn:7012149",
          "tgn:7007568",
          "tgn:7029392"
        ],
        "placetype": [
          "aat:300008347"
        ],
        "id": 2068612,
        "name:xx": "Columbus"
      }
    },
    {
      "geometry": {
        "type": "Point",
        "coordinates": [
          -73.2833,
          40.8333
        ]
      },
      "type": "Feature",
      "properties": {
        "hierarchy": [
          "tgn:2068613",
          "tgn:1000001",
          "tgn:7012149",
          "tgn:1002924",
          "tgn:7007568",
          "tgn:7029392"
        ],
        "placetype": [
          "aat:300008347"
        ],
        "id": 2068613,
        "name:xx": "Commack"
      }
    },
    {
      "geometry": {
        "type": "Point",
        "coordinates": [
          -73.4333,
          43.45
        ]
      },
      "type": "Feature",
      "properties": {
        "hierarchy": [
          "tgn:2068618",
          "tgn:1000001",
          "tgn:7012149",
          "tgn:1002993",
          "tgn:7007568",
          "tgn:7029392"
        ],
        "placetype": [
          "aat:300008347"
        ],
        "id": 2068618,
        "name:xx": "Comstock"
      }
    }
  ]
}
