{
  "geometry": {
    "type": "Point",
    "coordinates": [
      -81.0833,
      44.7833
    ]
  },
  "type": "Feature",
  "properties": {
    "hierarchy": [
      "tgn:1112830",
      "tgn:7005685",
      "tgn:1000001",
      "tgn:7013154",
      "tgn:7029392"
    ],
    "placetype": [
      "aat:300132316"
    ],
    "id": 1112830,
    "name:xx": "Colpoys Bay"
  }
}
