{
  "geometry": {
    "type": "Point",
    "coordinates": [
      -94.3167,
      39.6333
    ]
  },
  "type": "Feature",
  "properties": {
    "hierarchy": [
      "tgn:2060738",
      "tgn:1000001",
      "tgn:7012149",
      "tgn:2001188",
      "tgn:7007523",
      "tgn:7029392"
    ],
    "placetype": [
      "aat:300008347"
    ],
    "id": 2060738,
    "name:xx": "Turney"
  }
}
