{
  "geometry": {
    "type": "Point",
    "coordinates": [
      -73.4333,
      41.4833
    ]
  },
  "type": "Feature",
  "properties": {
    "hierarchy": [
      "tgn:2490582",
      "tgn:1000001",
      "tgn:7012149",
      "tgn:7007159",
      "tgn:7029392"
    ],
    "placetype": [
      "aat:300008699"
    ],
    "id": 2490582,
    "name:xx": "Mann Brook"
  }
}
