{
  "geometry": {
    "type": "Point",
    "coordinates": [
      -110.4333,
      42.1667
    ]
  },
  "type": "Feature",
  "properties": {
    "hierarchy": [
      "tgn:2458367",
      "tgn:1000001",
      "tgn:7012149",
      "tgn:2002376",
      "tgn:7007923",
      "tgn:7029392"
    ],
    "placetype": [
      "aat:300008706"
    ],
    "id": 2458367,
    "name:xx": "Little Muddy Creek"
  }
}
