{
  "geometry": {
    "type": "Point",
    "coordinates": [
      -114.3833,
      45.9333
    ]
  },
  "type": "Feature",
  "properties": {
    "hierarchy": [
      "tgn:2722370",
      "tgn:1000001",
      "tgn:7012149",
      "tgn:2001300",
      "tgn:7007524",
      "tgn:7029392"
    ],
    "placetype": [
      "aat:300008706"
    ],
    "id": 2722370,
    "name:xx": "Tin Cup Creek"
  }
}
