{
  "geometry": {
    "type": "Point",
    "coordinates": [
      -84.5667,
      39.3333
    ]
  },
  "type": "Feature",
  "properties": {
    "hierarchy": [
      "tgn:2708849",
      "tgn:1000001",
      "tgn:1002216",
      "tgn:7012149",
      "tgn:7007706",
      "tgn:7029392"
    ],
    "placetype": [
      "aat:300008347"
    ],
    "id": 2708849,
    "name:xx": "Symmes Corner"
  }
}
