{
  "geometry": {
    "type": "Point",
    "coordinates": [
      2.0333,
      48.95
    ]
  },
  "type": "Feature",
  "properties": {
    "hierarchy": [
      "tgn:1032428",
      "tgn:1000003",
      "tgn:7002883",
      "tgn:1000070",
      "tgn:7029392"
    ],
    "placetype": [
      "aat:300008347"
    ],
    "id": 1032428,
    "name:xx": "Carrières-sous-Poissy"
  }
}
