{
  "geometry": {
    "type": "Point",
    "coordinates": [
      32.55,
      30.916667
    ]
  },
  "type": "Feature",
  "properties": {
    "hierarchy": [
      "tgn:7534844",
      "tgn:7001242",
      "tgn:7016833",
      "tgn:7001335",
      "tgn:7029392"
    ],
    "placetype": [
      "aat:300006207"
    ],
    "name:en": "Bîr el-Kasîba",
    "id": 7534844
  }
}
