{
  "type": "FeatureCollection",
  "features": [
    {
      "geometry": {
        "type": "Point",
        "coordinates": [
          -87.5667,
          33.9333
        ]
      },
      "type": "Feature",
      "properties": {
        "hierarchy": [
          "tgn:2343940",
          "tgn:7002659",
          "tgn:1000001",
          "tgn:7012149",
          "tgn:2000063",
          "tgn:7029392"
        ],
        "placetype": [
          "aat:300000390"
        ],
        "id": 2343940,
        "name:xx": "Galloway Mines"
      }
    },
    {
      "geometry": {
        "type": "Point",
        "coordinates": [
          -83.6833,
          35
        ]
      },
      "type": "Feature",
      "properties": {
        "hierarchy": [
          "tgn:2343941",
          "tgn:1000001",
          "tgn:2001483",
          "tgn:7012149",
          "tgn:7007709",
          "tgn:7029392"
        ],
        "placetype": [
          "aat:300008798"
        ],
        "id": 2343941,
        "name:xx": "Galloway Mountain"
      }
    },
    {
      "geometry": {
        "type": "Point",
        "coordinates": [
          -89.9167,
          32.5167
        ]
      },
      "type": "Feature",
      "properties": {
        "hierarchy": [
          "tgn:2343942",
          "tgn:1000001",
          "tgn:7012149",
          "tgn:2001130",
          "tgn:7007522",
          "tgn:7029392"
        ],
        "placetype": [
          "aat:300008680"
        ],
        "id": 2343942,
        "name:xx": "Galloway Pocket"
      }
    },
    {
      "geometry": {
        "type": "Point",
        "coordinates": [
          -76.4,
          39.3
        ]
      },
      "type": "Feature",
      "properties": {
        "hierarchy": [
          "tgn:2343943",
          "tgn:7016099",
          "tgn:1000001",
          "tgn:7012149",
          "tgn:7007516",
          "tgn:7029392"
        ],
        "placetype": [
          "aat:300008850"
        ],
        "id": 2343943,
        "name:xx": "Galloway Point"
      }
    },
    {
      "geometry": {
        "type": "Point",
        "coordinates": [
          -76.0333,
          38.8
        ]
      },
      "type": "Feature",
      "properties": {
        "hierarchy": [
          "tgn:2343944",
          "tgn:1000001",
          "tgn:2000939",
          "tgn:7012149",
          "tgn:7007516",
          "tgn:7029392"
        ],
        "placetype": [
          "aat:300008699"
        ],
        "id": 2343944,
        "name:xx": "Galloway Run"
      }
    },
    {
      "geometry": {
        "type": "Point",
        "coordinates": [
          -92.0833,
          36.8833
        ]
      },
      "type": "Feature",
      "properties": {
        "hierarchy": [
          "tgn:2343947",
          "tgn:1000001",
          "tgn:7012149",
          "tgn:2001206",
          "tgn:7007523",
          "tgn:7029392"
        ],
        "placetype": [
          "aat:300008697"
        ],
        "id": 2343947,
        "name:xx": "Galloway Spring"
      }
    },
    {
      "geometry": {
        "type": "Point",
        "coordinates": [
          -117.9333,
          45.6
        ]
      },
      "type": "Feature",
      "properties": {
        "hierarchy": [
          "tgn:2343949",
          "tgn:1000001",
          "tgn:7012149",
          "tgn:2001721",
          "tgn:7007708",
          "tgn:7029392"
        ],
        "placetype": [
          "aat:300008697"
        ],
        "id": 2343949,
        "name:xx": "Galloway Spring"
      }
    }
  ]
}
