{
  "geometry": {
    "type": "Point",
    "coordinates": [
      -112.6833,
      37.75
    ]
  },
  "type": "Feature",
  "properties": {
    "hierarchy": [
      "tgn:2667563",
      "tgn:1000001",
      "tgn:7012149",
      "tgn:7007827",
      "tgn:7029392"
    ],
    "placetype": [
      "aat:300008706"
    ],
    "id": 2667563,
    "name:xx": "Skoots Creek"
  }
}
