{
  "type": "FeatureCollection",
  "features": [
    {
      "geometry": {
        "type": "Point",
        "coordinates": [
          -81.1167,
          40.8333
        ]
      },
      "type": "Feature",
      "properties": {
        "hierarchy": [
          "tgn:2177550",
          "tgn:1000001",
          "tgn:7012149",
          "tgn:1002917",
          "tgn:7007706",
          "tgn:7029392"
        ],
        "placetype": [
          "aat:300008699"
        ],
        "id": 2177550,
        "name:xx": "Black Run"
      }
    },
    {
      "geometry": {
        "type": "Point",
        "coordinates": [
          -76.9333,
          41.15
        ]
      },
      "type": "Feature",
      "properties": {
        "hierarchy": [
          "tgn:2177551",
          "tgn:1000001",
          "tgn:7012149",
          "tgn:7007710",
          "tgn:7029392"
        ],
        "placetype": [
          "aat:300008699"
        ],
        "id": 2177551,
        "name:xx": "Black Run"
      }
    },
    {
      "geometry": {
        "type": "Point",
        "coordinates": [
          -80.0833,
          41.2333
        ]
      },
      "type": "Feature",
      "properties": {
        "hierarchy": [
          "tgn:2177552",
          "tgn:1000001",
          "tgn:7012149",
          "tgn:1002659",
          "tgn:7007710",
          "tgn:7029392"
        ],
        "placetype": [
          "aat:300008699"
        ],
        "id": 2177552,
        "name:xx": "Black Run"
      }
    },
    {
      "geometry": {
        "type": "Point",
        "coordinates": [
          -77.35,
          41.6167
        ]
      },
      "type": "Feature",
      "properties": {
        "hierarchy": [
          "tgn:2177553",
          "tgn:1000001",
          "tgn:7012149",
          "tgn:1002945",
          "tgn:7007710",
          "tgn:7029392"
        ],
        "placetype": [
          "aat:300008699"
        ],
        "id": 2177553,
        "name:xx": "Black Run"
      }
    },
    {
      "geometry": {
        "type": "Point",
        "coordinates": [
          -80.0667,
          41
        ]
      },
      "type": "Feature",
      "properties": {
        "hierarchy": [
          "tgn:2177554",
          "tgn:1000001",
          "tgn:1002217",
          "tgn:7012149",
          "tgn:7007710",
          "tgn:7029392"
        ],
        "placetype": [
          "aat:300008699"
        ],
        "id": 2177554,
        "name:xx": "Black Run"
      }
    },
    {
      "geometry": {
        "type": "Point",
        "coordinates": [
          -79.0833,
          41.2667
        ]
      },
      "type": "Feature",
      "properties": {
        "hierarchy": [
          "tgn:2177555",
          "tgn:1000001",
          "tgn:7012149",
          "tgn:1002520",
          "tgn:7007710",
          "tgn:7029392"
        ],
        "placetype": [
          "aat:300008699"
        ],
        "id": 2177555,
        "name:xx": "Black Run"
      }
    },
    {
      "geometry": {
        "type": "Point",
        "coordinates": [
          -77.05,
          41
        ]
      },
      "type": "Feature",
      "properties": {
        "hierarchy": [
          "tgn:2177556",
          "tgn:1000001",
          "tgn:7012149",
          "tgn:1002965",
          "tgn:7007710",
          "tgn:7029392"
        ],
        "placetype": [
          "aat:300008699"
        ],
        "id": 2177556,
        "name:xx": "Black Run"
      }
    },
    {
      "geometry": {
        "type": "Point",
        "coordinates": [
          -76.0333,
          39.7167
        ]
      },
      "type": "Feature",
      "properties": {
        "hierarchy": [
          "tgn:2177557",
          "tgn:1000001",
          "tgn:1002266",
          "tgn:7012149",
          "tgn:7007710",
          "tgn:7029392"
        ],
        "placetype": [
          "aat:300008699"
        ],
        "id": 2177557,
        "name:xx": "Black Run"
      }
    },
    {
      "geometry": {
        "type": "Point",
        "coordinates": [
          -79.6,
          37.9
        ]
      },
      "type": "Feature",
      "properties": {
        "hierarchy": [
          "tgn:2177558",
          "tgn:1000001",
          "tgn:7012149",
          "tgn:2002186",
          "tgn:7007919",
          "tgn:7029392"
        ],
        "placetype": [
          "aat:300008699"
        ],
        "id": 2177558,
        "name:xx": "Black Run"
      }
    },
    {
      "geometry": {
        "type": "Point",
        "coordinates": [
          -78.0667,
          38.2667
        ]
      },
      "type": "Feature",
      "properties": {
        "hierarchy": [
          "tgn:2177559",
          "tgn:1000001",
          "tgn:7012149",
          "tgn:7007919",
          "tgn:7029392"
        ],
        "placetype": [
          "aat:300008699"
        ],
        "id": 2177559,
        "name:xx": "Black Run"
      }
    }
  ]
}
