{
  "geometry": {
    "type": "Point",
    "coordinates": [
      -71.85,
      42.5333
    ]
  },
  "type": "Feature",
  "properties": {
    "hierarchy": [
      "tgn:2269349",
      "tgn:1000001",
      "tgn:7012149",
      "tgn:1003038",
      "tgn:7007517",
      "tgn:7029392"
    ],
    "placetype": [
      "aat:300008798"
    ],
    "id": 2269349,
    "name:xx": "Crow Hills"
  }
}
