{
  "geometry": {
    "type": "Point",
    "coordinates": [
      6.55,
      50.466667
    ]
  },
  "type": "Feature",
  "properties": {
    "hierarchy": [
      "tgn:7072762",
      "tgn:1000003",
      "tgn:7003677",
      "tgn:7000084",
      "tgn:7029392"
    ],
    "placetype": [
      "aat:300004792"
    ],
    "id": 7072762,
    "name:xx": "Försterei Stritterhof"
  }
}
