{
  "type": "FeatureCollection",
  "features": [
    {
      "geometry": {
        "type": "Point",
        "coordinates": [
          8.916667,
          51.633333
        ]
      },
      "type": "Feature",
      "properties": {
        "hierarchy": [
          "tgn:7076000",
          "tgn:1000003",
          "tgn:7003677",
          "tgn:7000084",
          "tgn:7029392"
        ],
        "placetype": [
          "aat:300055621"
        ],
        "id": 7076000,
        "name:xx": "Soratfeld"
      }
    },
    {
      "geometry": {
        "type": "Point",
        "coordinates": [
          8.6,
          51.983333
        ]
      },
      "type": "Feature",
      "properties": {
        "hierarchy": [
          "tgn:7076001",
          "tgn:1000003",
          "tgn:7003677",
          "tgn:7000084",
          "tgn:7029392"
        ],
        "placetype": [
          "aat:300266640"
        ],
        "id": 7076001,
        "name:xx": "Osning"
      }
    },
    {
      "geometry": {
        "type": "Point",
        "coordinates": [
          8.65,
          52.116667
        ]
      },
      "type": "Feature",
      "properties": {
        "hierarchy": [
          "tgn:7076002",
          "tgn:1000003",
          "tgn:7003677",
          "tgn:7000084",
          "tgn:7029392"
        ],
        "placetype": [
          "aat:300055621"
        ],
        "id": 7076002,
        "name:xx": "Ravensberger Land"
      }
    },
    {
      "geometry": {
        "type": "Point",
        "coordinates": [
          7.8,
          52.2
        ]
      },
      "type": "Feature",
      "properties": {
        "hierarchy": [
          "tgn:7076004",
          "tgn:1000003",
          "tgn:7003677",
          "tgn:7000084",
          "tgn:7029392"
        ],
        "placetype": [
          "aat:300055621"
        ],
        "id": 7076004,
        "name:xx": "Tecklenburger Land"
      }
    },
    {
      "geometry": {
        "type": "Point",
        "coordinates": [
          7.2,
          52.25
        ]
      },
      "type": "Feature",
      "properties": {
        "hierarchy": [
          "tgn:7076005",
          "tgn:1000003",
          "tgn:7594165",
          "tgn:7000084",
          "tgn:7029392"
        ],
        "placetype": [
          "aat:300055621"
        ],
        "id": 7076005,
        "name:xx": "Brechte"
      }
    },
    {
      "geometry": {
        "type": "Point",
        "coordinates": [
          12.2,
          51.766667
        ]
      },
      "type": "Feature",
      "properties": {
        "hierarchy": [
          "tgn:7076006",
          "tgn:1000003",
          "tgn:7003687",
          "tgn:7000084",
          "tgn:7029392"
        ],
        "placetype": [
          "aat:300008863"
        ],
        "id": 7076006,
        "name:xx": "Mosigkauer Heide"
      }
    },
    {
      "geometry": {
        "type": "Point",
        "coordinates": [
          11.3,
          51.866667
        ]
      },
      "type": "Feature",
      "properties": {
        "hierarchy": [
          "tgn:7076007",
          "tgn:1000003",
          "tgn:7003687",
          "tgn:7000084",
          "tgn:7029392"
        ],
        "placetype": [
          "aat:300266640"
        ],
        "id": 7076007,
        "name:xx": "Hakel"
      }
    },
    {
      "geometry": {
        "type": "Point",
        "coordinates": [
          11.75,
          51.583333
        ]
      },
      "type": "Feature",
      "properties": {
        "hierarchy": [
          "tgn:7076008",
          "tgn:1000003",
          "tgn:7003687",
          "tgn:7000084",
          "tgn:7029392"
        ],
        "placetype": [
          "aat:300055621"
        ],
        "id": 7076008,
        "name:xx": "Östliches Harzvorland"
      }
    },
    {
      "geometry": {
        "type": "Point",
        "coordinates": [
          11.033333,
          51.916667
        ]
      },
      "type": "Feature",
      "properties": {
        "hierarchy": [
          "tgn:7076009",
          "tgn:1000003",
          "tgn:7003687",
          "tgn:7000084",
          "tgn:7029392"
        ],
        "placetype": [
          "aat:300055621"
        ],
        "id": 7076009,
        "name:xx": "Nördliches Harzvorland"
      }
    }
  ]
}
