{
  "geometry": {
    "type": "Point",
    "coordinates": [
      -85.85,
      41.4167
    ]
  },
  "type": "Feature",
  "properties": {
    "hierarchy": [
      "tgn:2598209",
      "tgn:1000001",
      "tgn:7012149",
      "tgn:7007252",
      "tgn:7029392"
    ],
    "placetype": [
      "aat:300006075"
    ],
    "id": 2598209,
    "name:xx": "Preston Miles Ditch"
  }
}
