{
  "geometry": {
    "type": "Point",
    "coordinates": [
      -75.2333,
      38.3667
    ]
  },
  "type": "Feature",
  "properties": {
    "hierarchy": [
      "tgn:2637546",
      "tgn:1000001",
      "tgn:1003037",
      "tgn:7012149",
      "tgn:7007516",
      "tgn:7029392"
    ],
    "placetype": [
      "aat:300008347"
    ],
    "id": 2637546,
    "name:xx": "Saint Martin"
  }
}
