{
  "geometry": {
    "type": "Point",
    "coordinates": [
      -87.5333,
      39.0167
    ]
  },
  "type": "Feature",
  "properties": {
    "hierarchy": [
      "tgn:2506159",
      "tgn:1000001",
      "tgn:7012149",
      "tgn:2000556",
      "tgn:7007252",
      "tgn:7029392"
    ],
    "placetype": [
      "aat:300008347"
    ],
    "id": 2506159,
    "name:xx": "Merom Station"
  }
}
