{
  "geometry": {
    "type": "Point",
    "coordinates": [
      79.165728,
      25.71497
    ]
  },
  "type": "Feature",
  "properties": {
    "hierarchy": [
      "tgn:7566219",
      "tgn:1000004",
      "tgn:7000198",
      "tgn:7016722",
      "tgn:7029392"
    ],
    "placetype": [
      "aat:300008347"
    ],
    "name:en": "Bāmaur",
    "id": 7566219
  }
}
