{
  "geometry": {
    "type": "Point",
    "coordinates": [
      -107.65,
      37.6167
    ]
  },
  "type": "Feature",
  "properties": {
    "hierarchy": [
      "tgn:2721016",
      "tgn:1000001",
      "tgn:7012149",
      "tgn:7007158",
      "tgn:7029392"
    ],
    "placetype": [
      "aat:300008706"
    ],
    "id": 2721016,
    "name:xx": "Tie Creek"
  }
}
