{
  "geometry": {
    "type": "Point",
    "coordinates": [
      -95.1667,
      44.6833
    ]
  },
  "type": "Feature",
  "properties": {
    "hierarchy": [
      "tgn:2722210",
      "tgn:1000001",
      "tgn:7012149",
      "tgn:2001063",
      "tgn:7007521",
      "tgn:7029392"
    ],
    "placetype": [
      "aat:300008706"
    ],
    "id": 2722210,
    "name:xx": "Timms Creek"
  }
}
