{
  "geometry": {
    "type": "Point",
    "coordinates": [
      -97.2833,
      39.1167
    ]
  },
  "type": "Feature",
  "properties": {
    "hierarchy": [
      "tgn:2150622",
      "tgn:1000001",
      "tgn:7012149",
      "tgn:7007254",
      "tgn:7029392"
    ],
    "placetype": [
      "aat:300008706"
    ],
    "id": 2150622,
    "name:xx": "Basket Creek"
  }
}
