{
  "geometry": {
    "type": "Point",
    "coordinates": [
      -106.55,
      40.6167
    ]
  },
  "type": "Feature",
  "properties": {
    "hierarchy": [
      "tgn:2210988",
      "tgn:1000001",
      "tgn:7012149",
      "tgn:2000220",
      "tgn:7007158",
      "tgn:7029392"
    ],
    "placetype": [
      "aat:300006075"
    ],
    "id": 2210988,
    "name:xx": "Butler Ditch Number 4"
  }
}
