{
  "geometry": {
    "type": "Point",
    "coordinates": [
      -75.6667,
      39.2667
    ]
  },
  "type": "Feature",
  "properties": {
    "hierarchy": [
      "tgn:2365128",
      "tgn:1000001",
      "tgn:7012149",
      "tgn:7007239",
      "tgn:7029392"
    ],
    "placetype": [
      "aat:300008699"
    ],
    "id": 2365128,
    "name:xx": "Greens Branch"
  }
}
