{
  "geometry": {
    "type": "Point",
    "coordinates": [
      -114.9333,
      47.3167
    ]
  },
  "type": "Feature",
  "properties": {
    "hierarchy": [
      "tgn:2635300",
      "tgn:1000001",
      "tgn:7012149",
      "tgn:2001304",
      "tgn:7007524",
      "tgn:7029392"
    ],
    "placetype": [
      "aat:300000390"
    ],
    "id": 2635300,
    "name:xx": "S and H Mine"
  }
}
