{
  "geometry": {
    "type": "Point",
    "coordinates": [
      71.55,
      50.25
    ]
  },
  "type": "Feature",
  "properties": {
    "hierarchy": [
      "tgn:1137644",
      "tgn:1000004",
      "tgn:7011459",
      "tgn:7014786",
      "tgn:7029392"
    ],
    "placetype": [
      "aat:300008347"
    ],
    "id": 1137644,
    "name:xx": "Kiyevka"
  }
}
