{
  "geometry": {
    "type": "Point",
    "coordinates": [
      78.973516,
      25.08893
    ]
  },
  "type": "Feature",
  "properties": {
    "hierarchy": [
      "tgn:7583856",
      "tgn:1000004",
      "tgn:7000198",
      "tgn:1001894",
      "tgn:7029392"
    ],
    "placetype": [
      "aat:300387086"
    ],
    "name:en": "Jakhnīra Tāl",
    "id": 7583856
  }
}
