{
  "geometry": {
    "type": "Point",
    "coordinates": [
      -75.95,
      -10.6667
    ]
  },
  "type": "Feature",
  "properties": {
    "hierarchy": [
      "tgn:1024511",
      "tgn:1000726",
      "tgn:1000002",
      "tgn:1000056",
      "tgn:7029392"
    ],
    "placetype": [
      "aat:300008347"
    ],
    "id": 1024511,
    "name:xx": "Huachón"
  }
}
