{
  "geometry": {
    "type": "Point",
    "coordinates": [
      22.7833,
      47.5333
    ]
  },
  "type": "Feature",
  "properties": {
    "hierarchy": [
      "tgn:7004055",
      "tgn:1000003",
      "tgn:1000442",
      "tgn:1000091",
      "tgn:7029392"
    ],
    "placetype": [
      "aat:300008347"
    ],
    "id": 7004055,
    "name:xx": "Acîș"
  }
}
