{
  "geometry": {
    "type": "Point",
    "coordinates": [
      -114.4167,
      48.5833
    ]
  },
  "type": "Feature",
  "properties": {
    "hierarchy": [
      "tgn:2757096",
      "tgn:1000001",
      "tgn:7012149",
      "tgn:2001274",
      "tgn:7007524",
      "tgn:7029392"
    ],
    "placetype": [
      "aat:300008706"
    ],
    "id": 2757096,
    "name:xx": "Werner Creek"
  }
}
