{
  "geometry": {
    "type": "Point",
    "coordinates": [
      -78.8667,
      38.4167
    ]
  },
  "type": "Feature",
  "properties": {
    "hierarchy": [
      "tgn:2540309",
      "tgn:1000001",
      "tgn:7012149",
      "tgn:2002214",
      "tgn:7007919",
      "tgn:7029392"
    ],
    "placetype": [
      "aat:300006191"
    ],
    "id": 2540309,
    "name:xx": "Newman Lake"
  }
}
