{
  "geometry": {
    "type": "Point",
    "coordinates": [
      2.8833,
      50.85
    ]
  },
  "type": "Feature",
  "properties": {
    "hierarchy": [
      "tgn:1135942",
      "tgn:1000003",
      "tgn:1000063",
      "tgn:7029392"
    ],
    "placetype": [
      "aat:300006075"
    ],
    "id": 1135942,
    "name:xx": "IJzerkanaal"
  }
}
