{
  "geometry": {
    "type": "Point",
    "coordinates": [
      9.3667,
      51.35
    ]
  },
  "type": "Feature",
  "properties": {
    "hierarchy": [
      "tgn:1100370",
      "tgn:1000003",
      "tgn:7003678",
      "tgn:7000084",
      "tgn:7029392"
    ],
    "placetype": [
      "aat:300006891"
    ],
    "id": 1100370,
    "name:xx": "Wilhelmshöhe, Schloss"
  }
}
