{
  "geometry": {
    "type": "Point",
    "coordinates": [
      -122.3833,
      48.6667
    ]
  },
  "type": "Feature",
  "properties": {
    "hierarchy": [
      "tgn:2639851",
      "tgn:1000001",
      "tgn:7012149",
      "tgn:1003020",
      "tgn:7007920",
      "tgn:7029392"
    ],
    "placetype": [
      "aat:300008680"
    ],
    "id": 2639851,
    "name:xx": "Samish, Lake"
  }
}
