{
  "geometry": {
    "type": "Point",
    "coordinates": [
      -88.8167,
      31.7333
    ]
  },
  "type": "Feature",
  "properties": {
    "hierarchy": [
      "tgn:2784883",
      "tgn:1000001",
      "tgn:7012149",
      "tgn:2001162",
      "tgn:7007522",
      "tgn:7029392"
    ],
    "placetype": [
      "aat:300008706"
    ],
    "id": 2784883,
    "name:xx": "Yellow Creek"
  }
}
