{
  "type": "FeatureCollection",
  "features": [
    {
      "geometry": {
        "type": "Point",
        "coordinates": [
          171.25,
          -43.4
        ]
      },
      "type": "Feature",
      "properties": {
        "hierarchy": [
          "tgn:7513400",
          "tgn:1009227",
          "tgn:7001866",
          "tgn:1000226",
          "tgn:1000006",
          "tgn:7029392"
        ],
        "placetype": [
          "aat:300008699"
        ],
        "name:en": "Godley Stream",
        "id": 7513400
      }
    },
    {
      "geometry": {
        "type": "Point",
        "coordinates": [
          170.533333,
          -43.8
        ]
      },
      "type": "Feature",
      "properties": {
        "hierarchy": [
          "tgn:7513401",
          "tgn:1009227",
          "tgn:7001866",
          "tgn:1000226",
          "tgn:1000006",
          "tgn:7029392"
        ],
        "placetype": [
          "aat:300008699"
        ],
        "name:en": "Godley River",
        "id": 7513401
      }
    },
    {
      "geometry": {
        "type": "Point",
        "coordinates": [
          171.283333,
          -43.35
        ]
      },
      "type": "Feature",
      "properties": {
        "hierarchy": [
          "tgn:7513402",
          "tgn:1009227",
          "tgn:7001866",
          "tgn:1000226",
          "tgn:1000006",
          "tgn:7029392"
        ],
        "placetype": [
          "aat:300008798"
        ],
        "name:en": "Godley Peak",
        "id": 7513402
      }
    },
    {
      "geometry": {
        "type": "Point",
        "coordinates": [
          170.416667,
          -43.566667
        ]
      },
      "type": "Feature",
      "properties": {
        "hierarchy": [
          "tgn:7513403",
          "tgn:1009227",
          "tgn:7001866",
          "tgn:1000226",
          "tgn:1000006",
          "tgn:7029392"
        ],
        "placetype": [
          "aat:300259572"
        ],
        "name:en": "Godley Pass",
        "id": 7513403
      }
    },
    {
      "geometry": {
        "type": "Point",
        "coordinates": [
          172.8,
          -43.6
        ]
      },
      "type": "Feature",
      "properties": {
        "hierarchy": [
          "tgn:7513404",
          "tgn:1009227",
          "tgn:7001866",
          "tgn:1000226",
          "tgn:1000006",
          "tgn:7029392"
        ],
        "placetype": [
          "aat:300008850"
        ],
        "name:en": "Godley Head",
        "id": 7513404
      }
    },
    {
      "geometry": {
        "type": "Point",
        "coordinates": [
          170.55,
          -43.45
        ]
      },
      "type": "Feature",
      "properties": {
        "hierarchy": [
          "tgn:7513405",
          "tgn:1009227",
          "tgn:7001866",
          "tgn:1000226",
          "tgn:1000006",
          "tgn:7029392"
        ],
        "placetype": [
          "aat:300008835"
        ],
        "name:en": "Godley Glacier",
        "id": 7513405
      }
    },
    {
      "geometry": {
        "type": "Point",
        "coordinates": [
          172.8,
          -41.183333
        ]
      },
      "type": "Feature",
      "properties": {
        "hierarchy": [
          "tgn:7513406",
          "tgn:1009227",
          "tgn:1000226",
          "tgn:7520095",
          "tgn:1000006",
          "tgn:7029392"
        ],
        "placetype": [
          "aat:300008699"
        ],
        "name:en": "Goat Stream",
        "id": 7513406
      }
    },
    {
      "geometry": {
        "type": "Point",
        "coordinates": [
          173.1,
          -43.833333
        ]
      },
      "type": "Feature",
      "properties": {
        "hierarchy": [
          "tgn:7513407",
          "tgn:1009227",
          "tgn:7001866",
          "tgn:1000226",
          "tgn:1000006",
          "tgn:7029392"
        ],
        "placetype": [
          "aat:300386846"
        ],
        "name:en": "Goat Point",
        "id": 7513407
      }
    },
    {
      "geometry": {
        "type": "Point",
        "coordinates": [
          171.633333,
          -42.9
        ]
      },
      "type": "Feature",
      "properties": {
        "hierarchy": [
          "tgn:7513408",
          "tgn:1009227",
          "tgn:1000226",
          "tgn:1000006",
          "tgn:7016850",
          "tgn:7029392"
        ],
        "placetype": [
          "aat:300259572"
        ],
        "name:en": "Goat Pass",
        "id": 7513408
      }
    },
    {
      "geometry": {
        "type": "Point",
        "coordinates": [
          168.15,
          -46.95
        ]
      },
      "type": "Feature",
      "properties": {
        "hierarchy": [
          "tgn:7513409",
          "tgn:1009227",
          "tgn:1000226",
          "tgn:7016822",
          "tgn:1000006",
          "tgn:7029392"
        ],
        "placetype": [
          "aat:300008791"
        ],
        "name:en": "Goat Island",
        "id": 7513409
      }
    }
  ]
}
