{
  "geometry": {
    "type": "Point",
    "coordinates": [
      -111.1167,
      37.25
    ]
  },
  "type": "Feature",
  "properties": {
    "hierarchy": [
      "tgn:2378680",
      "tgn:1000001",
      "tgn:7012149",
      "tgn:2002113",
      "tgn:7007827",
      "tgn:7029392"
    ],
    "placetype": [
      "aat:300008761"
    ],
    "id": 2378680,
    "name:xx": "Harry Colwes Draw"
  }
}
