{
  "geometry": {
    "type": "Point",
    "coordinates": [
      -84.6833,
      38.8667
    ]
  },
  "type": "Feature",
  "properties": {
    "hierarchy": [
      "tgn:2037651",
      "tgn:1000001",
      "tgn:1002189",
      "tgn:7012149",
      "tgn:7007255",
      "tgn:7029392"
    ],
    "placetype": [
      "aat:300008347"
    ],
    "id": 2037651,
    "name:xx": "Beaverlick"
  }
}
