{
  "geometry": {
    "type": "Point",
    "coordinates": [
      -111.7333,
      46.0833
    ]
  },
  "type": "Feature",
  "properties": {
    "hierarchy": [
      "tgn:2664252",
      "tgn:1000001",
      "tgn:2001263",
      "tgn:7012149",
      "tgn:7007524",
      "tgn:7029392"
    ],
    "placetype": [
      "aat:300000390"
    ],
    "id": 2664252,
    "name:xx": "Silver Star Mine"
  }
}
