{
  "type": "FeatureCollection",
  "features": [
    {
      "geometry": {
        "type": "Point",
        "coordinates": [
          -7.35,
          43
        ]
      },
      "type": "Feature",
      "properties": {
        "hierarchy": [
          "tgn:7301150",
          "tgn:7002829",
          "tgn:1000003",
          "tgn:7002786",
          "tgn:1000095",
          "tgn:7029392"
        ],
        "placetype": [
          "aat:300008347"
        ],
        "id": 7301150,
        "name:xx": "Monte"
      }
    },
    {
      "geometry": {
        "type": "Point",
        "coordinates": [
          -7.95,
          42.966667
        ]
      },
      "type": "Feature",
      "properties": {
        "hierarchy": [
          "tgn:7301151",
          "tgn:7002824",
          "tgn:1000003",
          "tgn:7002786",
          "tgn:1000095",
          "tgn:7029392"
        ],
        "placetype": [
          "aat:300008347"
        ],
        "id": 7301151,
        "name:xx": "Monte"
      }
    },
    {
      "geometry": {
        "type": "Point",
        "coordinates": [
          -8.65,
          42.933333
        ]
      },
      "type": "Feature",
      "properties": {
        "hierarchy": [
          "tgn:7301153",
          "tgn:7002824",
          "tgn:1000003",
          "tgn:7002786",
          "tgn:1000095",
          "tgn:7029392"
        ],
        "placetype": [
          "aat:300008347"
        ],
        "id": 7301153,
        "name:xx": "Monte"
      }
    },
    {
      "geometry": {
        "type": "Point",
        "coordinates": [
          -7.233333,
          42.783333
        ]
      },
      "type": "Feature",
      "properties": {
        "hierarchy": [
          "tgn:7301154",
          "tgn:7002829",
          "tgn:1000003",
          "tgn:7002786",
          "tgn:1000095",
          "tgn:7029392"
        ],
        "placetype": [
          "aat:300008347"
        ],
        "id": 7301154,
        "name:xx": "Monte"
      }
    },
    {
      "geometry": {
        "type": "Point",
        "coordinates": [
          -7.95,
          42.633333
        ]
      },
      "type": "Feature",
      "properties": {
        "hierarchy": [
          "tgn:7301155",
          "tgn:7002834",
          "tgn:1000003",
          "tgn:7002786",
          "tgn:1000095",
          "tgn:7029392"
        ],
        "placetype": [
          "aat:300008347"
        ],
        "id": 7301155,
        "name:xx": "Monte"
      }
    },
    {
      "geometry": {
        "type": "Point",
        "coordinates": [
          -8.816667,
          42.533333
        ]
      },
      "type": "Feature",
      "properties": {
        "hierarchy": [
          "tgn:7301156",
          "tgn:7002834",
          "tgn:1000003",
          "tgn:7002786",
          "tgn:1000095",
          "tgn:7029392"
        ],
        "placetype": [
          "aat:300008347"
        ],
        "id": 7301156,
        "name:xx": "Monte"
      }
    },
    {
      "geometry": {
        "type": "Point",
        "coordinates": [
          -7.466667,
          42.5
        ]
      },
      "type": "Feature",
      "properties": {
        "hierarchy": [
          "tgn:7301157",
          "tgn:7002829",
          "tgn:1000003",
          "tgn:7002786",
          "tgn:1000095",
          "tgn:7029392"
        ],
        "placetype": [
          "aat:300008347"
        ],
        "id": 7301157,
        "name:xx": "Monte"
      }
    },
    {
      "geometry": {
        "type": "Point",
        "coordinates": [
          1.041892,
          41.846688
        ]
      },
      "type": "Feature",
      "properties": {
        "hierarchy": [
          "tgn:7301158",
          "tgn:7008912",
          "tgn:7030216",
          "tgn:1000003",
          "tgn:1000095",
          "tgn:7029392"
        ],
        "placetype": [
          "aat:300008347"
        ],
        "id": 7301158,
        "name:xx": "Montclar"
      }
    },
    {
      "geometry": {
        "type": "Point",
        "coordinates": [
          1,
          41.116667
        ]
      },
      "type": "Feature",
      "properties": {
        "hierarchy": [
          "tgn:7301159",
          "tgn:7002844",
          "tgn:7030216",
          "tgn:1000003",
          "tgn:1000095",
          "tgn:7029392"
        ],
        "placetype": [
          "aat:300008347"
        ],
        "id": 7301159,
        "name:xx": "Montbrió de Tarragona"
      }
    }
  ]
}
