{
  "type": "FeatureCollection",
  "features": [
    {
      "geometry": {
        "type": "Point",
        "coordinates": [
          16.25,
          41.25
        ]
      },
      "type": "Feature",
      "properties": {
        "hierarchy": [
          "tgn:7010380",
          "tgn:1000003",
          "tgn:1000080",
          "tgn:7029392"
        ],
        "placetype": [
          "aat:300387064",
          "aat:300236112"
        ],
        "name:en": "Apulia",
        "id": 7010380,
        "name:it": "Puglia"
      }
    },
    {
      "geometry": {
        "type": "Point",
        "coordinates": [
          11.3,
          42.4
        ]
      },
      "type": "Feature",
      "properties": {
        "hierarchy": [
          "tgn:7010381",
          "tgn:1003460",
          "tgn:1000003",
          "tgn:7009760",
          "tgn:1000080",
          "tgn:7029392"
        ],
        "placetype": [
          "aat:300008347",
          "aat:300008372",
          "aat:300387339"
        ],
        "id": 7010381,
        "name:xx": "Ansedónia"
      }
    },
    {
      "geometry": {
        "type": "Point",
        "coordinates": [
          14.030128,
          40.921094
        ]
      },
      "type": "Feature",
      "properties": {
        "hierarchy": [
          "tgn:7010382",
          "tgn:7003013",
          "tgn:7003005",
          "tgn:1000003",
          "tgn:1000080",
          "tgn:7029392"
        ],
        "placetype": [
          "aat:300235115",
          "aat:300008347",
          "aat:300000810",
          "aat:300167671",
          "aat:300020533"
        ],
        "id": 7010382,
        "name:xx": "Liternum"
      }
    },
    {
      "geometry": {
        "type": "Point",
        "coordinates": [
          15.181,
          37.203
        ]
      },
      "type": "Feature",
      "properties": {
        "hierarchy": [
          "tgn:7010383",
          "tgn:1000003",
          "tgn:7003122",
          "tgn:1001753",
          "tgn:1000080",
          "tgn:7029392"
        ],
        "placetype": [
          "aat:300235115",
          "aat:300008347",
          "aat:300000810",
          "aat:300167671",
          "aat:300019267",
          "aat:300020072"
        ],
        "id": 7010383,
        "name:xx": "Megara Hyblaea"
      }
    },
    {
      "geometry": {
        "type": "Point",
        "coordinates": [
          -2.616667,
          53.533333
        ]
      },
      "type": "Feature",
      "properties": {
        "hierarchy": [
          "tgn:7010384",
          "tgn:7002445",
          "tgn:1003664",
          "tgn:1000003",
          "tgn:7026570",
          "tgn:7008591",
          "tgn:7029392"
        ],
        "placetype": [
          "aat:300008347",
          "aat:300387308",
          "aat:300387305",
          "aat:300387220",
          "aat:300008375"
        ],
        "name:en": "Wigan",
        "id": 7010384
      }
    },
    {
      "geometry": {
        "type": "Point",
        "coordinates": [
          -2.4,
          53.866667
        ]
      },
      "type": "Feature",
      "properties": {
        "hierarchy": [
          "tgn:7010389",
          "tgn:7002445",
          "tgn:1000003",
          "tgn:7008154",
          "tgn:7008591",
          "tgn:7029392"
        ],
        "placetype": [
          "aat:300008347"
        ],
        "name:en": "Clitheroe",
        "id": 7010389
      }
    }
  ]
}
