{
  "geometry": {
    "type": "Point",
    "coordinates": [
      -97.5833,
      26.4833
    ]
  },
  "type": "Feature",
  "properties": {
    "hierarchy": [
      "tgn:2603656",
      "tgn:1000001",
      "tgn:7012149",
      "tgn:2002094",
      "tgn:7007826",
      "tgn:7029392"
    ],
    "placetype": [
      "aat:300006191"
    ],
    "id": 2603656,
    "name:xx": "Quemada Tank"
  }
}
