{
  "geometry": {
    "type": "Point",
    "coordinates": [
      -77.1333,
      38.7667
    ]
  },
  "type": "Feature",
  "properties": {
    "hierarchy": [
      "tgn:2216040",
      "tgn:1000001",
      "tgn:7012149",
      "tgn:7014160",
      "tgn:7007919",
      "tgn:7029392"
    ],
    "placetype": [
      "aat:300008347"
    ],
    "id": 2216040,
    "name:xx": "Cameron Villa Farms"
  }
}
