{
  "geometry": {
    "type": "Point",
    "coordinates": [
      -71.1333,
      48.4167
    ]
  },
  "type": "Feature",
  "properties": {
    "hierarchy": [
      "tgn:7013192",
      "tgn:7005685",
      "tgn:1000001",
      "tgn:7005804",
      "tgn:7029392"
    ],
    "placetype": [
      "aat:300008347",
      "aat:300008375"
    ],
    "id": 7013192,
    "name:xx": "Arvida"
  }
}
