{
  "geometry": {
    "type": "Point",
    "coordinates": [
      84.132939,
      24.0744
    ]
  },
  "type": "Feature",
  "properties": {
    "hierarchy": [
      "tgn:7554719",
      "tgn:1000004",
      "tgn:7000198",
      "tgn:7031783",
      "tgn:7029392"
    ],
    "placetype": [
      "aat:300008699"
    ],
    "name:en": "Mailā Nadī",
    "id": 7554719
  }
}
