{
  "geometry": {
    "type": "Point",
    "coordinates": [
      -118.6167,
      35.3167
    ]
  },
  "type": "Feature",
  "properties": {
    "hierarchy": [
      "tgn:2714136",
      "tgn:1000001",
      "tgn:7012149",
      "tgn:1002545",
      "tgn:7007157",
      "tgn:7029392"
    ],
    "placetype": [
      "aat:300008761"
    ],
    "id": 2714136,
    "name:xx": "Telephone Canyon"
  }
}
