{
  "geometry": {
    "type": "Point",
    "coordinates": [
      -159.85,
      67.9833
    ]
  },
  "type": "Feature",
  "properties": {
    "hierarchy": [
      "tgn:2453682",
      "tgn:7006450",
      "tgn:1000001",
      "tgn:7012149",
      "tgn:7029392"
    ],
    "placetype": [
      "aat:300008706"
    ],
    "id": 2453682,
    "name:xx": "Little Cottonwood Creek"
  }
}
