{
  "geometry": {
    "type": "Point",
    "coordinates": [
      -89.8167,
      39.3667
    ]
  },
  "type": "Feature",
  "properties": {
    "hierarchy": [
      "tgn:2132821",
      "tgn:1000001",
      "tgn:7012149",
      "tgn:1002620",
      "tgn:7007251",
      "tgn:7029392"
    ],
    "placetype": [
      "aat:300008699"
    ],
    "id": 2132821,
    "name:xx": "Anderson Branch"
  }
}
