{
  "geometry": {
    "type": "Point",
    "coordinates": [
      118.5667,
      24.5333
    ]
  },
  "type": "Feature",
  "properties": {
    "hierarchy": [
      "tgn:1072543",
      "tgn:1000004",
      "tgn:7001796",
      "tgn:1000111",
      "tgn:7029392"
    ],
    "placetype": [
      "aat:300008347"
    ],
    "id": 1072543,
    "name:xx": "Weitou"
  }
}
