{
  "geometry": {
    "type": "Point",
    "coordinates": [
      -61.9333,
      3.3333
    ]
  },
  "type": "Feature",
  "properties": {
    "hierarchy": [
      "tgn:1131274",
      "tgn:1002001",
      "tgn:1000047",
      "tgn:7002456",
      "tgn:1000002",
      "tgn:7029392"
    ],
    "placetype": [
      "aat:300008707"
    ],
    "id": 1131274,
    "name:xx": "Uraricaá"
  }
}
