{
  "geometry": {
    "type": "Point",
    "coordinates": [
      -100.35,
      45.65
    ]
  },
  "type": "Feature",
  "properties": {
    "hierarchy": [
      "tgn:2343764",
      "tgn:1000001",
      "tgn:2001780",
      "tgn:7012149",
      "tgn:7007713",
      "tgn:7029392"
    ],
    "placetype": [
      "aat:300132316"
    ],
    "id": 2343764,
    "name:xx": "Gallaway Bay"
  }
}
