{
  "geometry": {
    "type": "Point",
    "coordinates": [
      -67.5167,
      44.55
    ]
  },
  "type": "Feature",
  "properties": {
    "hierarchy": [
      "tgn:2461196",
      "tgn:1000001",
      "tgn:7012149",
      "tgn:7014589",
      "tgn:7007515",
      "tgn:7029392"
    ],
    "placetype": [
      "aat:300008791"
    ],
    "id": 2461196,
    "name:xx": "Little Spruce Island"
  }
}
