{
  "geometry": {
    "type": "Point",
    "coordinates": [
      76.527412,
      29.849694
    ]
  },
  "type": "Feature",
  "properties": {
    "hierarchy": [
      "tgn:7580638",
      "tgn:1000004",
      "tgn:1001871",
      "tgn:7000198",
      "tgn:7029392"
    ],
    "placetype": [
      "aat:300007783"
    ],
    "name:en": "Tīk Railroad Station",
    "id": 7580638
  }
}
