{
  "geometry": {
    "type": "Point",
    "coordinates": [
      9.35,
      52.95
    ]
  },
  "type": "Feature",
  "properties": {
    "hierarchy": [
      "tgn:7141445",
      "tgn:1000003",
      "tgn:7003676",
      "tgn:7000084",
      "tgn:7029392"
    ],
    "placetype": [
      "aat:300008863"
    ],
    "id": 7141445,
    "name:xx": "Lintelner Stüh"
  }
}
