{
  "geometry": {
    "type": "Point",
    "coordinates": [
      -3.15,
      58.65
    ]
  },
  "type": "Feature",
  "properties": {
    "hierarchy": [
      "tgn:7450318",
      "tgn:7002444",
      "tgn:1000003",
      "tgn:7008082",
      "tgn:7008591",
      "tgn:7029392"
    ],
    "placetype": [
      "aat:300132316"
    ],
    "name:en": "Gills Bay",
    "id": 7450318
  }
}
