{
  "geometry": {
    "type": "Point",
    "coordinates": [
      -91.2667,
      39.4833
    ]
  },
  "type": "Feature",
  "properties": {
    "hierarchy": [
      "tgn:2380723",
      "tgn:1000001",
      "tgn:7012149",
      "tgn:1002787",
      "tgn:7007523",
      "tgn:7029392"
    ],
    "placetype": [
      "aat:300008706"
    ],
    "id": 2380723,
    "name:xx": "Haw Creek"
  }
}
