{
  "geometry": {
    "type": "Point",
    "coordinates": [
      104.5333,
      28.8333
    ]
  },
  "type": "Feature",
  "properties": {
    "hierarchy": [
      "tgn:1071901",
      "tgn:1000004",
      "tgn:7002087",
      "tgn:1000111",
      "tgn:7029392"
    ],
    "placetype": [
      "aat:300008347"
    ],
    "id": 1071901,
    "name:xx": "Sibochi"
  }
}
