{
  "geometry": {
    "type": "Point",
    "coordinates": [
      79.560767,
      26.92322
    ]
  },
  "type": "Feature",
  "properties": {
    "hierarchy": [
      "tgn:7563956",
      "tgn:1000004",
      "tgn:7000198",
      "tgn:7016722",
      "tgn:7029392"
    ],
    "placetype": [
      "aat:300167671"
    ],
    "name:en": "Kabīrpur",
    "id": 7563956
  }
}
