{
  "geometry": {
    "type": "Point",
    "coordinates": [
      -83.1833,
      41.5833
    ]
  },
  "type": "Feature",
  "properties": {
    "hierarchy": [
      "tgn:2491383",
      "tgn:1000001",
      "tgn:7012149",
      "tgn:1002761",
      "tgn:7007706",
      "tgn:7029392"
    ],
    "placetype": [
      "aat:300008347"
    ],
    "id": 2491383,
    "name:xx": "Maple Grove"
  }
}
