{
  "geometry": {
    "type": "Point",
    "coordinates": [
      18.4667,
      -33.7833
    ]
  },
  "type": "Feature",
  "properties": {
    "hierarchy": [
      "tgn:1092887",
      "tgn:7001242",
      "tgn:7017584",
      "tgn:1000193",
      "tgn:7029392"
    ],
    "placetype": [
      "aat:300008347"
    ],
    "id": 1092887,
    "name:xx": "Bloubergstrand"
  }
}
