{
  "geometry": {
    "type": "Point",
    "coordinates": [
      -95.1167,
      35.0333
    ]
  },
  "type": "Feature",
  "properties": {
    "hierarchy": [
      "tgn:2460166",
      "tgn:1000001",
      "tgn:7012149",
      "tgn:2001661",
      "tgn:7007707",
      "tgn:7029392"
    ],
    "placetype": [
      "aat:300008798"
    ],
    "id": 2460166,
    "name:xx": "Little Round Mountain"
  }
}
