{
  "type": "FeatureCollection",
  "features": [
    {
      "geometry": {
        "type": "Point",
        "coordinates": [
          -71.183333,
          -52.266667
        ]
      },
      "type": "Feature",
      "properties": {
        "hierarchy": [
          "tgn:7288740",
          "tgn:1001702",
          "tgn:1000049",
          "tgn:1000002",
          "tgn:7029392"
        ],
        "placetype": [
          "aat:300000241"
        ],
        "id": 7288740,
        "name:xx": "Estancia Laguna Blanca"
      }
    },
    {
      "geometry": {
        "type": "Point",
        "coordinates": [
          -71.133333,
          -34.016667
        ]
      },
      "type": "Feature",
      "properties": {
        "hierarchy": [
          "tgn:7288741",
          "tgn:1001708",
          "tgn:1000049",
          "tgn:1000002",
          "tgn:7029392"
        ],
        "placetype": [
          "aat:300387002"
        ],
        "id": 7288741,
        "name:xx": "La Campana, Morro"
      }
    },
    {
      "geometry": {
        "type": "Point",
        "coordinates": [
          -71.133333,
          -32.95
        ]
      },
      "type": "Feature",
      "properties": {
        "hierarchy": [
          "tgn:7288742",
          "tgn:1001768",
          "tgn:1000049",
          "tgn:1000002",
          "tgn:7029392"
        ],
        "placetype": [
          "aat:300008795"
        ],
        "id": 7288742,
        "name:xx": "La Campana, Cerro de"
      }
    },
    {
      "geometry": {
        "type": "Point",
        "coordinates": [
          -70.75,
          -34
        ]
      },
      "type": "Feature",
      "properties": {
        "hierarchy": [
          "tgn:7288743",
          "tgn:1001695",
          "tgn:1000049",
          "tgn:1000002",
          "tgn:7029392"
        ],
        "placetype": [
          "aat:300008795"
        ],
        "id": 7288743,
        "name:xx": "La Campana, Cerro"
      }
    },
    {
      "geometry": {
        "type": "Point",
        "coordinates": [
          -70.75,
          -29.35
        ]
      },
      "type": "Feature",
      "properties": {
        "hierarchy": [
          "tgn:7288744",
          "tgn:1001657",
          "tgn:1000049",
          "tgn:1000002",
          "tgn:7029392"
        ],
        "placetype": [
          "aat:300008795"
        ],
        "id": 7288744,
        "name:xx": "La Campana, Cerro"
      }
    },
    {
      "geometry": {
        "type": "Point",
        "coordinates": [
          -69.883333,
          -26.766667
        ]
      },
      "type": "Feature",
      "properties": {
        "hierarchy": [
          "tgn:7288745",
          "tgn:1001630",
          "tgn:1000049",
          "tgn:1000002",
          "tgn:7029392"
        ],
        "placetype": [
          "aat:300008795"
        ],
        "id": 7288745,
        "name:xx": "La Campana, Cerro"
      }
    },
    {
      "geometry": {
        "type": "Point",
        "coordinates": [
          -68.416667,
          -21.283333
        ]
      },
      "type": "Feature",
      "properties": {
        "hierarchy": [
          "tgn:7288746",
          "tgn:7016598",
          "tgn:1000049",
          "tgn:1000002",
          "tgn:7029392"
        ],
        "placetype": [
          "aat:300008795"
        ],
        "id": 7288746,
        "name:xx": "La Campana, Cerro"
      }
    },
    {
      "geometry": {
        "type": "Point",
        "coordinates": [
          -71.466667,
          -34.016667
        ]
      },
      "type": "Feature",
      "properties": {
        "hierarchy": [
          "tgn:7288747",
          "tgn:1001708",
          "tgn:1000049",
          "tgn:1000002",
          "tgn:7029392"
        ],
        "placetype": [
          "aat:300008777"
        ],
        "id": 7288747,
        "name:xx": "La Campana, Cerro"
      }
    },
    {
      "geometry": {
        "type": "Point",
        "coordinates": [
          -70.683333,
          -33.316667
        ]
      },
      "type": "Feature",
      "properties": {
        "hierarchy": [
          "tgn:7288748",
          "tgn:1001708",
          "tgn:1000049",
          "tgn:1000002",
          "tgn:7029392"
        ],
        "placetype": [
          "aat:300008777"
        ],
        "id": 7288748,
        "name:xx": "La Campana, Cerro"
      }
    },
    {
      "geometry": {
        "type": "Point",
        "coordinates": [
          -70,
          -24.383333
        ]
      },
      "type": "Feature",
      "properties": {
        "hierarchy": [
          "tgn:7288749",
          "tgn:7016598",
          "tgn:1000049",
          "tgn:1000002",
          "tgn:7029392"
        ],
        "placetype": [
          "aat:300387033"
        ],
        "id": 7288749,
        "name:xx": "La Campana"
      }
    }
  ]
}
