{
  "geometry": {
    "type": "Point",
    "coordinates": [
      -92.7667,
      37.4333
    ]
  },
  "type": "Feature",
  "properties": {
    "hierarchy": [
      "tgn:2060779",
      "tgn:1000001",
      "tgn:7012149",
      "tgn:2001256",
      "tgn:7007523",
      "tgn:7029392"
    ],
    "placetype": [
      "aat:300008347",
      "aat:300387210"
    ],
    "id": 2060779,
    "name:xx": "Vance"
  }
}
