{
  "geometry": {
    "type": "Point",
    "coordinates": [
      -87.3833,
      41.3833
    ]
  },
  "type": "Feature",
  "properties": {
    "hierarchy": [
      "tgn:2386754",
      "tgn:1000001",
      "tgn:7012149",
      "tgn:1002569",
      "tgn:7007252",
      "tgn:7029392"
    ],
    "placetype": [
      "aat:300008680"
    ],
    "id": 2386754,
    "name:xx": "Hermit Lake"
  }
}
