{
  "geometry": {
    "type": "Point",
    "coordinates": [
      -113.2167,
      36.35
    ]
  },
  "type": "Feature",
  "properties": {
    "hierarchy": [
      "tgn:2384862",
      "tgn:1000001",
      "tgn:7006451",
      "tgn:7012149",
      "tgn:2000098",
      "tgn:7029392"
    ],
    "placetype": [
      "aat:300008761"
    ],
    "id": 2384862,
    "name:xx": "Hells Hollow"
  }
}
