{
  "geometry": {
    "type": "Point",
    "coordinates": [
      -93.15,
      35.1667
    ]
  },
  "type": "Feature",
  "properties": {
    "hierarchy": [
      "tgn:2313008",
      "tgn:1000001",
      "tgn:7016172",
      "tgn:7012149",
      "tgn:2000179",
      "tgn:7029392"
    ],
    "placetype": [
      "aat:300008347"
    ],
    "id": 2313008,
    "name:xx": "Elberta"
  }
}
