{
  "geometry": {
    "type": "Point",
    "coordinates": [
      -93.3833,
      45.1833
    ]
  },
  "type": "Feature",
  "properties": {
    "hierarchy": [
      "tgn:2054119",
      "tgn:1000001",
      "tgn:2001025",
      "tgn:7012149",
      "tgn:7007521",
      "tgn:7029392"
    ],
    "placetype": [
      "aat:300008347"
    ],
    "id": 2054119,
    "name:xx": "Champlin"
  }
}
