{
  "geometry": {
    "type": "Point",
    "coordinates": [
      -68.983333,
      -22.75
    ]
  },
  "type": "Feature",
  "properties": {
    "hierarchy": [
      "tgn:7314706",
      "tgn:7016598",
      "tgn:1000049",
      "tgn:1000002",
      "tgn:7029392"
    ],
    "placetype": [
      "aat:300008795"
    ],
    "id": 7314706,
    "name:xx": "Limón Verde, Cerro"
  }
}
