{
  "geometry": {
    "type": "Point",
    "coordinates": [
      76.108056,
      28.0125
    ]
  },
  "type": "Feature",
  "properties": {
    "hierarchy": [
      "tgn:7567333",
      "tgn:1000004",
      "tgn:1001871",
      "tgn:7000198",
      "tgn:7029392"
    ],
    "placetype": [
      "aat:300008777"
    ],
    "name:en": "Kapūri Pahāri",
    "id": 7567333
  }
}
