{
  "type": "FeatureCollection",
  "features": [
    {
      "geometry": {
        "type": "Point",
        "coordinates": [
          -83.9,
          35.0333
        ]
      },
      "type": "Feature",
      "properties": {
        "hierarchy": [
          "tgn:2729900",
          "tgn:1000001",
          "tgn:2001483",
          "tgn:7012149",
          "tgn:7007709",
          "tgn:7029392"
        ],
        "placetype": [
          "aat:300008699"
        ],
        "id": 2729900,
        "name:xx": "Trout Cove Branch"
      }
    },
    {
      "geometry": {
        "type": "Point",
        "coordinates": [
          -86.2333,
          33.7667
        ]
      },
      "type": "Feature",
      "properties": {
        "hierarchy": [
          "tgn:2729901",
          "tgn:7002659",
          "tgn:1000001",
          "tgn:7012149",
          "tgn:2000057",
          "tgn:7029392"
        ],
        "placetype": [
          "aat:300008706"
        ],
        "id": 2729901,
        "name:xx": "Trout Creek"
      }
    },
    {
      "geometry": {
        "type": "Point",
        "coordinates": [
          -144.0333,
          60.4167
        ]
      },
      "type": "Feature",
      "properties": {
        "hierarchy": [
          "tgn:2729902",
          "tgn:7006450",
          "tgn:1000001",
          "tgn:7012149",
          "tgn:2000086",
          "tgn:7029392"
        ],
        "placetype": [
          "aat:300008706"
        ],
        "id": 2729902,
        "name:xx": "Trout Creek"
      }
    },
    {
      "geometry": {
        "type": "Point",
        "coordinates": [
          -150.9,
          62.4667
        ]
      },
      "type": "Feature",
      "properties": {
        "hierarchy": [
          "tgn:2729903",
          "tgn:7006450",
          "tgn:1000001",
          "tgn:2124053",
          "tgn:7012149",
          "tgn:7029392"
        ],
        "placetype": [
          "aat:300008706"
        ],
        "id": 2729903,
        "name:xx": "Trout Creek"
      }
    },
    {
      "geometry": {
        "type": "Point",
        "coordinates": [
          -165.3333,
          64.7167
        ]
      },
      "type": "Feature",
      "properties": {
        "hierarchy": [
          "tgn:2729904",
          "tgn:7006450",
          "tgn:1000001",
          "tgn:7012149",
          "tgn:2000079",
          "tgn:7029392"
        ],
        "placetype": [
          "aat:300008706"
        ],
        "id": 2729904,
        "name:xx": "Trout Creek"
      }
    },
    {
      "geometry": {
        "type": "Point",
        "coordinates": [
          -150.2333,
          65.3
        ]
      },
      "type": "Feature",
      "properties": {
        "hierarchy": [
          "tgn:2729905",
          "tgn:7006450",
          "tgn:1000001",
          "tgn:7012149",
          "tgn:2000089",
          "tgn:7029392"
        ],
        "placetype": [
          "aat:300008706"
        ],
        "id": 2729905,
        "name:xx": "Trout Creek"
      }
    },
    {
      "geometry": {
        "type": "Point",
        "coordinates": [
          -132.2833,
          56.0167
        ]
      },
      "type": "Feature",
      "properties": {
        "hierarchy": [
          "tgn:2729906",
          "tgn:7006450",
          "tgn:1000001",
          "tgn:7012149",
          "tgn:2000088",
          "tgn:7029392"
        ],
        "placetype": [
          "aat:300008706"
        ],
        "id": 2729906,
        "name:xx": "Trout Creek"
      }
    },
    {
      "geometry": {
        "type": "Point",
        "coordinates": [
          -133.5333,
          56.0167
        ]
      },
      "type": "Feature",
      "properties": {
        "hierarchy": [
          "tgn:2729907",
          "tgn:7006450",
          "tgn:1000001",
          "tgn:7012149",
          "tgn:2000082",
          "tgn:7029392"
        ],
        "placetype": [
          "aat:300008706"
        ],
        "id": 2729907,
        "name:xx": "Trout Creek"
      }
    },
    {
      "geometry": {
        "type": "Point",
        "coordinates": [
          -141.5833,
          64.9833
        ]
      },
      "type": "Feature",
      "properties": {
        "hierarchy": [
          "tgn:2729908",
          "tgn:7006450",
          "tgn:1000001",
          "tgn:7012149",
          "tgn:2000085",
          "tgn:7029392"
        ],
        "placetype": [
          "aat:300008706"
        ],
        "id": 2729908,
        "name:xx": "Trout Creek"
      }
    },
    {
      "geometry": {
        "type": "Point",
        "coordinates": [
          -109.7167,
          33.9833
        ]
      },
      "type": "Feature",
      "properties": {
        "hierarchy": [
          "tgn:2729909",
          "tgn:2000090",
          "tgn:1000001",
          "tgn:7006451",
          "tgn:7012149",
          "tgn:7029392"
        ],
        "placetype": [
          "aat:300008706"
        ],
        "id": 2729909,
        "name:xx": "Trout Creek"
      }
    }
  ]
}
