{
  "geometry": {
    "type": "Point",
    "coordinates": [
      -116.55,
      43.35
    ]
  },
  "type": "Feature",
  "properties": {
    "hierarchy": [
      "tgn:2750052",
      "tgn:1000001",
      "tgn:2000465",
      "tgn:7012149",
      "tgn:7007250",
      "tgn:7029392"
    ],
    "placetype": [
      "aat:300006075"
    ],
    "id": 2750052,
    "name:xx": "Walters Butte Lateral"
  }
}
