{
  "type": "FeatureCollection",
  "features": [
    {
      "geometry": {
        "type": "Point",
        "coordinates": [
          -85.05,
          39.1
        ]
      },
      "type": "Feature",
      "properties": {
        "hierarchy": [
          "tgn:2337590",
          "tgn:1000001",
          "tgn:1002324",
          "tgn:7012149",
          "tgn:7007252",
          "tgn:7029392"
        ],
        "placetype": [
          "aat:300008699"
        ],
        "id": 2337590,
        "name:xx": "Fox Branch"
      }
    },
    {
      "geometry": {
        "type": "Point",
        "coordinates": [
          -85.2167,
          36.65
        ]
      },
      "type": "Feature",
      "properties": {
        "hierarchy": [
          "tgn:2337591",
          "tgn:1000001",
          "tgn:2000783",
          "tgn:7012149",
          "tgn:7007255",
          "tgn:7029392"
        ],
        "placetype": [
          "aat:300008699"
        ],
        "id": 2337591,
        "name:xx": "Fox Branch"
      }
    },
    {
      "geometry": {
        "type": "Point",
        "coordinates": [
          -83.7833,
          37.3
        ]
      },
      "type": "Feature",
      "properties": {
        "hierarchy": [
          "tgn:2337592",
          "tgn:1000001",
          "tgn:2000782",
          "tgn:7012149",
          "tgn:7007255",
          "tgn:7029392"
        ],
        "placetype": [
          "aat:300008699"
        ],
        "id": 2337592,
        "name:xx": "Fox Branch"
      }
    },
    {
      "geometry": {
        "type": "Point",
        "coordinates": [
          -84.4333,
          36.6
        ]
      },
      "type": "Feature",
      "properties": {
        "hierarchy": [
          "tgn:2337593",
          "tgn:1000001",
          "tgn:7012149",
          "tgn:2000818",
          "tgn:7007255",
          "tgn:7029392"
        ],
        "placetype": [
          "aat:300008699"
        ],
        "id": 2337593,
        "name:xx": "Fox Branch"
      }
    },
    {
      "geometry": {
        "type": "Point",
        "coordinates": [
          -90.1667,
          30.45
        ]
      },
      "type": "Feature",
      "properties": {
        "hierarchy": [
          "tgn:2337594",
          "tgn:1000001",
          "tgn:7012149",
          "tgn:2000905",
          "tgn:7007256",
          "tgn:7029392"
        ],
        "placetype": [
          "aat:300008699"
        ],
        "id": 2337594,
        "name:xx": "Fox Branch"
      }
    },
    {
      "geometry": {
        "type": "Point",
        "coordinates": [
          -90.3167,
          30.5333
        ]
      },
      "type": "Feature",
      "properties": {
        "hierarchy": [
          "tgn:2337595",
          "tgn:1000001",
          "tgn:7012149",
          "tgn:2000906",
          "tgn:7007256",
          "tgn:7029392"
        ],
        "placetype": [
          "aat:300008699"
        ],
        "id": 2337595,
        "name:xx": "Fox Branch"
      }
    },
    {
      "geometry": {
        "type": "Point",
        "coordinates": [
          -93.3167,
          31.5333
        ]
      },
      "type": "Feature",
      "properties": {
        "hierarchy": [
          "tgn:2337596",
          "tgn:1000001",
          "tgn:7012149",
          "tgn:7007256",
          "tgn:7029392"
        ],
        "placetype": [
          "aat:300008699"
        ],
        "id": 2337596,
        "name:xx": "Fox Branch"
      }
    },
    {
      "geometry": {
        "type": "Point",
        "coordinates": [
          -88.9833,
          31.3667
        ]
      },
      "type": "Feature",
      "properties": {
        "hierarchy": [
          "tgn:2337597",
          "tgn:1000001",
          "tgn:7012149",
          "tgn:2001141",
          "tgn:7007522",
          "tgn:7029392"
        ],
        "placetype": [
          "aat:300008699"
        ],
        "id": 2337597,
        "name:xx": "Fox Branch"
      }
    },
    {
      "geometry": {
        "type": "Point",
        "coordinates": [
          -89.0333,
          32.9667
        ]
      },
      "type": "Feature",
      "properties": {
        "hierarchy": [
          "tgn:2337598",
          "tgn:1000001",
          "tgn:7012149",
          "tgn:7007522",
          "tgn:7029392"
        ],
        "placetype": [
          "aat:300008699"
        ],
        "id": 2337598,
        "name:xx": "Fox Branch"
      }
    },
    {
      "geometry": {
        "type": "Point",
        "coordinates": [
          -90.6,
          36.6333
        ]
      },
      "type": "Feature",
      "properties": {
        "hierarchy": [
          "tgn:2337599",
          "tgn:1000001",
          "tgn:7012149",
          "tgn:7007523",
          "tgn:7029392"
        ],
        "placetype": [
          "aat:300008699"
        ],
        "id": 2337599,
        "name:xx": "Fox Branch"
      }
    }
  ]
}
