{
  "type": "FeatureCollection",
  "features": [
    {
      "geometry": {
        "type": "Point",
        "coordinates": [
          -88.5333,
          48.1667
        ]
      },
      "type": "Feature",
      "properties": {
        "hierarchy": [
          "tgn:2286560",
          "tgn:1000001",
          "tgn:7012149",
          "tgn:2000969",
          "tgn:7007520",
          "tgn:7029392"
        ],
        "placetype": [
          "aat:300008791"
        ],
        "id": 2286560,
        "name:xx": "Diamond Island"
      }
    },
    {
      "geometry": {
        "type": "Point",
        "coordinates": [
          -93.05,
          48.5833
        ]
      },
      "type": "Feature",
      "properties": {
        "hierarchy": [
          "tgn:2286561",
          "tgn:1000001",
          "tgn:7012149",
          "tgn:2001067",
          "tgn:7007521",
          "tgn:7029392"
        ],
        "placetype": [
          "aat:300008791"
        ],
        "id": 2286561,
        "name:xx": "Diamond Island"
      }
    },
    {
      "geometry": {
        "type": "Point",
        "coordinates": [
          -91.0333,
          32.2333
        ]
      },
      "type": "Feature",
      "properties": {
        "hierarchy": [
          "tgn:2286562",
          "tgn:1000001",
          "tgn:7012149",
          "tgn:2001160",
          "tgn:7007522",
          "tgn:7029392"
        ],
        "placetype": [
          "aat:300055621"
        ],
        "id": 2286562,
        "name:xx": "Diamond Island"
      }
    },
    {
      "geometry": {
        "type": "Point",
        "coordinates": [
          -71.3167,
          43.5667
        ]
      },
      "type": "Feature",
      "properties": {
        "hierarchy": [
          "tgn:2286564",
          "tgn:2001422",
          "tgn:1000001",
          "tgn:7012149",
          "tgn:7007564",
          "tgn:7029392"
        ],
        "placetype": [
          "aat:300008791"
        ],
        "id": 2286564,
        "name:xx": "Diamond Island"
      }
    },
    {
      "geometry": {
        "type": "Point",
        "coordinates": [
          -73.6667,
          43.45
        ]
      },
      "type": "Feature",
      "properties": {
        "hierarchy": [
          "tgn:2286565",
          "tgn:1000001",
          "tgn:7012149",
          "tgn:1002986",
          "tgn:7007568",
          "tgn:7029392"
        ],
        "placetype": [
          "aat:300008791"
        ],
        "id": 2286565,
        "name:xx": "Diamond Island"
      }
    },
    {
      "geometry": {
        "type": "Point",
        "coordinates": [
          -75.8833,
          43.9667
        ]
      },
      "type": "Feature",
      "properties": {
        "hierarchy": [
          "tgn:2286566",
          "tgn:1000001",
          "tgn:7012149",
          "tgn:1002518",
          "tgn:7007568",
          "tgn:7029392"
        ],
        "placetype": [
          "aat:300008791"
        ],
        "id": 2286566,
        "name:xx": "Diamond Island"
      }
    },
    {
      "geometry": {
        "type": "Point",
        "coordinates": [
          -73.3333,
          44.2333
        ]
      },
      "type": "Feature",
      "properties": {
        "hierarchy": [
          "tgn:2286567",
          "tgn:1000001",
          "tgn:7012149",
          "tgn:2001461",
          "tgn:7007568",
          "tgn:7029392"
        ],
        "placetype": [
          "aat:300008791"
        ],
        "id": 2286567,
        "name:xx": "Diamond Island"
      }
    },
    {
      "geometry": {
        "type": "Point",
        "coordinates": [
          -88.3,
          35.1667
        ]
      },
      "type": "Feature",
      "properties": {
        "hierarchy": [
          "tgn:2286568",
          "tgn:1000001",
          "tgn:7012149",
          "tgn:2001872",
          "tgn:7007825",
          "tgn:7029392"
        ],
        "placetype": [
          "aat:300008791"
        ],
        "id": 2286568,
        "name:xx": "Diamond Island"
      }
    },
    {
      "geometry": {
        "type": "Point",
        "coordinates": [
          -95.0667,
          29.8
        ]
      },
      "type": "Feature",
      "properties": {
        "hierarchy": [
          "tgn:2286569",
          "tgn:1000001",
          "tgn:7012149",
          "tgn:1002456",
          "tgn:7007826",
          "tgn:7029392"
        ],
        "placetype": [
          "aat:300008791"
        ],
        "id": 2286569,
        "name:xx": "Diamond Island"
      }
    }
  ]
}
