{
  "geometry": {
    "type": "Point",
    "coordinates": [
      -112.3667,
      46.1833
    ]
  },
  "type": "Feature",
  "properties": {
    "hierarchy": [
      "tgn:2443454",
      "tgn:1000001",
      "tgn:7012149",
      "tgn:2001281",
      "tgn:7007524",
      "tgn:7029392"
    ],
    "placetype": [
      "aat:300008761"
    ],
    "id": 2443454,
    "name:xx": "La Belle Gulch"
  }
}
