{
  "geometry": {
    "type": "Point",
    "coordinates": [
      14.002,
      -11.44
    ]
  },
  "type": "Feature",
  "properties": {
    "hierarchy": [
      "tgn:1123174",
      "tgn:7001242",
      "tgn:1000149",
      "tgn:1000835",
      "tgn:7029392"
    ],
    "placetype": [
      "aat:300008707"
    ],
    "id": 1123174,
    "name:xx": "Cubal"
  }
}
