{
  "geometry": {
    "type": "Point",
    "coordinates": [
      -77.3167,
      38.2333
    ]
  },
  "type": "Feature",
  "properties": {
    "hierarchy": [
      "tgn:2382071",
      "tgn:1000001",
      "tgn:7012149",
      "tgn:7007919",
      "tgn:7029392"
    ],
    "placetype": [
      "aat:300132348"
    ],
    "id": 2382071,
    "name:xx": "Hayfield Bar"
  }
}
