{
  "type": "FeatureCollection",
  "features": [
    {
      "geometry": {
        "type": "Point",
        "coordinates": [
          -102.766667,
          21.2
        ]
      },
      "type": "Feature",
      "properties": {
        "hierarchy": [
          "tgn:7388050",
          "tgn:7005586",
          "tgn:1000001",
          "tgn:7005560",
          "tgn:7029392"
        ],
        "placetype": [
          "aat:300008347"
        ],
        "id": 7388050,
        "name:xx": "Potrero"
      }
    },
    {
      "geometry": {
        "type": "Point",
        "coordinates": [
          -97.383333,
          20.433333
        ]
      },
      "type": "Feature",
      "properties": {
        "hierarchy": [
          "tgn:7388051",
          "tgn:1000001",
          "tgn:7005599",
          "tgn:7005560",
          "tgn:7029392"
        ],
        "placetype": [
          "aat:300008347"
        ],
        "id": 7388051,
        "name:xx": "Potrero"
      }
    },
    {
      "geometry": {
        "type": "Point",
        "coordinates": [
          -98.066667,
          19.916667
        ]
      },
      "type": "Feature",
      "properties": {
        "hierarchy": [
          "tgn:7388052",
          "tgn:1000001",
          "tgn:7005592",
          "tgn:7005560",
          "tgn:7029392"
        ],
        "placetype": [
          "aat:300008347"
        ],
        "id": 7388052,
        "name:xx": "Potrero"
      }
    },
    {
      "geometry": {
        "type": "Point",
        "coordinates": [
          -100.533333,
          18.183333
        ]
      },
      "type": "Feature",
      "properties": {
        "hierarchy": [
          "tgn:7388053",
          "tgn:7005585",
          "tgn:1000001",
          "tgn:7005560",
          "tgn:7029392"
        ],
        "placetype": [
          "aat:300008347"
        ],
        "id": 7388053,
        "name:xx": "Potrero"
      }
    },
    {
      "geometry": {
        "type": "Point",
        "coordinates": [
          -90.116667,
          21.15
        ]
      },
      "type": "Feature",
      "properties": {
        "hierarchy": [
          "tgn:7388054",
          "tgn:1000001",
          "tgn:7005600",
          "tgn:7005560",
          "tgn:7029392"
        ],
        "placetype": [
          "aat:300386846"
        ],
        "id": 7388054,
        "name:xx": "Piedra, Punta de"
      }
    },
    {
      "geometry": {
        "type": "Point",
        "coordinates": [
          -106.316667,
          21.416667
        ]
      },
      "type": "Feature",
      "properties": {
        "hierarchy": [
          "tgn:7388055",
          "tgn:1000001",
          "tgn:1001906",
          "tgn:7005560",
          "tgn:7029392"
        ],
        "placetype": [
          "aat:300386846"
        ],
        "id": 7388055,
        "name:xx": "Piedra, Punta"
      }
    },
    {
      "geometry": {
        "type": "Point",
        "coordinates": [
          -87.4,
          19.583333
        ]
      },
      "type": "Feature",
      "properties": {
        "hierarchy": [
          "tgn:7388056",
          "tgn:1000001",
          "tgn:1001937",
          "tgn:7005560",
          "tgn:7029392"
        ],
        "placetype": [
          "aat:300386846"
        ],
        "id": 7388056,
        "name:xx": "Piedra, Punta"
      }
    },
    {
      "geometry": {
        "type": "Point",
        "coordinates": [
          -106.333333,
          23.166667
        ]
      },
      "type": "Feature",
      "properties": {
        "hierarchy": [
          "tgn:7388057",
          "tgn:1000001",
          "tgn:1001960",
          "tgn:7005560",
          "tgn:7029392"
        ],
        "placetype": [
          "aat:300008791"
        ],
        "id": 7388057,
        "name:xx": "Piedra, Isla de"
      }
    },
    {
      "geometry": {
        "type": "Point",
        "coordinates": [
          -90.483333,
          20.366667
        ]
      },
      "type": "Feature",
      "properties": {
        "hierarchy": [
          "tgn:7388058",
          "tgn:7005578",
          "tgn:1000001",
          "tgn:7005560",
          "tgn:7029392"
        ],
        "placetype": [
          "aat:300008791"
        ],
        "id": 7388058,
        "name:xx": "Piedras, Isla de"
      }
    },
    {
      "geometry": {
        "type": "Point",
        "coordinates": [
          -97.183333,
          20.7
        ]
      },
      "type": "Feature",
      "properties": {
        "hierarchy": [
          "tgn:7388059",
          "tgn:1000001",
          "tgn:7005599",
          "tgn:7005560",
          "tgn:7029392"
        ],
        "placetype": [
          "aat:300387057"
        ],
        "id": 7388059,
        "name:xx": "Piedra, Boquilla de"
      }
    }
  ]
}
