{
  "geometry": {
    "type": "Point",
    "coordinates": [
      -73.8833,
      43.9333
    ]
  },
  "type": "Feature",
  "properties": {
    "hierarchy": [
      "tgn:2642140",
      "tgn:1000001",
      "tgn:7012149",
      "tgn:2001461",
      "tgn:7007568",
      "tgn:7029392"
    ],
    "placetype": [
      "aat:300008798"
    ],
    "id": 2642140,
    "name:xx": "Sand Pond Mountain"
  }
}
