{
  "geometry": {
    "type": "Point",
    "coordinates": [
      -145.3167,
      65.4167
    ]
  },
  "type": "Feature",
  "properties": {
    "hierarchy": [
      "tgn:2546347",
      "tgn:7006450",
      "tgn:1000001",
      "tgn:7012149",
      "tgn:2000089",
      "tgn:7029392"
    ],
    "placetype": [
      "aat:300008706"
    ],
    "id": 2546347,
    "name:xx": "North Fork Harrison Creek"
  }
}
