{
  "geometry": {
    "type": "Point",
    "coordinates": [
      -121.0167,
      48.9333
    ]
  },
  "type": "Feature",
  "properties": {
    "hierarchy": [
      "tgn:2404301",
      "tgn:1000001",
      "tgn:7012149",
      "tgn:1003020",
      "tgn:7007920",
      "tgn:7029392"
    ],
    "placetype": [
      "aat:300008706"
    ],
    "id": 2404301,
    "name:xx": "Hozomeen Creek"
  }
}
