{
  "geometry": {
    "type": "Point",
    "coordinates": [
      -112.0167,
      35.65
    ]
  },
  "type": "Feature",
  "properties": {
    "hierarchy": [
      "tgn:2520077",
      "tgn:1000001",
      "tgn:7006451",
      "tgn:2000092",
      "tgn:7012149",
      "tgn:7029392"
    ],
    "placetype": [
      "aat:300008761"
    ],
    "id": 2520077,
    "name:xx": "Molly Ann Draw"
  }
}
