{
  "geometry": {
    "type": "Point",
    "coordinates": [
      -84.1667,
      34.6333
    ]
  },
  "type": "Feature",
  "properties": {
    "hierarchy": [
      "tgn:2738508",
      "tgn:1000001",
      "tgn:7012149",
      "tgn:2000346",
      "tgn:7007248",
      "tgn:7029392"
    ],
    "placetype": [
      "aat:300008706"
    ],
    "id": 2738508,
    "name:xx": "Underwood Creek"
  }
}
