{
  "geometry": {
    "type": "Point",
    "coordinates": [
      -113.3667,
      34.05
    ]
  },
  "type": "Feature",
  "properties": {
    "hierarchy": [
      "tgn:1109106",
      "tgn:1000001",
      "tgn:7006451",
      "tgn:7012149",
      "tgn:7029392"
    ],
    "placetype": [
      "aat:300008795"
    ],
    "id": 1109106,
    "name:xx": "Harcuvar Mountains"
  }
}
