{
  "geometry": {
    "type": "Point",
    "coordinates": [
      -75.65,
      38.0333
    ]
  },
  "type": "Feature",
  "properties": {
    "hierarchy": [
      "tgn:2048434",
      "tgn:1000001",
      "tgn:1002902",
      "tgn:7012149",
      "tgn:7007516",
      "tgn:7029392"
    ],
    "placetype": [
      "aat:300008347"
    ],
    "id": 2048434,
    "name:xx": "Rehobeth"
  }
}
