{
  "geometry": {
    "type": "Point",
    "coordinates": [
      31.9333,
      40.1667
    ]
  },
  "type": "Feature",
  "properties": {
    "hierarchy": [
      "tgn:1086097",
      "tgn:1001101",
      "tgn:1000004",
      "tgn:7018453",
      "tgn:1000144",
      "tgn:7029392"
    ],
    "placetype": [
      "aat:300008347"
    ],
    "id": 1086097,
    "name:xx": "Beypazarı"
  }
}
