{
  "geometry": {
    "type": "Point",
    "coordinates": [
      -79.5333,
      33.45
    ]
  },
  "type": "Feature",
  "properties": {
    "hierarchy": [
      "tgn:2445904",
      "tgn:1000001",
      "tgn:2001746",
      "tgn:7012149",
      "tgn:7007712",
      "tgn:7029392"
    ],
    "placetype": [
      "aat:300008706"
    ],
    "id": 2445904,
    "name:xx": "Lester Creek"
  }
}
