{
  "type": "FeatureCollection",
  "features": [
    {
      "geometry": {
        "type": "Point",
        "coordinates": [
          -6.266667,
          40.6
        ]
      },
      "type": "Feature",
      "properties": {
        "hierarchy": [
          "tgn:1062270",
          "tgn:7002835",
          "tgn:7001158",
          "tgn:1000003",
          "tgn:1000095",
          "tgn:7029392"
        ],
        "placetype": [
          "aat:300008347"
        ],
        "id": 1062270,
        "name:xx": "Morasverdes"
      }
    },
    {
      "geometry": {
        "type": "Point",
        "coordinates": [
          -1.883333,
          38.2
        ]
      },
      "type": "Feature",
      "properties": {
        "hierarchy": [
          "tgn:1062271",
          "tgn:1001439",
          "tgn:1000003",
          "tgn:7002797",
          "tgn:1000095",
          "tgn:7029392"
        ],
        "placetype": [
          "aat:300008347"
        ],
        "id": 1062271,
        "name:xx": "Moratalla"
      }
    },
    {
      "geometry": {
        "type": "Point",
        "coordinates": [
          -0.1,
          40.616667
        ]
      },
      "type": "Feature",
      "properties": {
        "hierarchy": [
          "tgn:1062272",
          "tgn:7002815",
          "tgn:1000003",
          "tgn:7002793",
          "tgn:1000095",
          "tgn:7029392"
        ],
        "placetype": [
          "aat:300008347"
        ],
        "id": 1062272,
        "name:xx": "Morella"
      }
    },
    {
      "geometry": {
        "type": "Point",
        "coordinates": [
          -2.866667,
          39.5
        ]
      },
      "type": "Feature",
      "properties": {
        "hierarchy": [
          "tgn:1062273",
          "tgn:7002818",
          "tgn:1001647",
          "tgn:1000003",
          "tgn:1000095",
          "tgn:7029392"
        ],
        "placetype": [
          "aat:300008347"
        ],
        "id": 1062273,
        "name:xx": "Mota del Cuervo"
      }
    },
    {
      "geometry": {
        "type": "Point",
        "coordinates": [
          -3.516667,
          36.75
        ]
      },
      "type": "Feature",
      "properties": {
        "hierarchy": [
          "tgn:1062276",
          "tgn:7002758",
          "tgn:7002821",
          "tgn:1000003",
          "tgn:1000095",
          "tgn:7029392"
        ],
        "placetype": [
          "aat:300008347"
        ],
        "id": 1062276,
        "name:xx": "Motril"
      }
    },
    {
      "geometry": {
        "type": "Point",
        "coordinates": [
          -1.5,
          38.05
        ]
      },
      "type": "Feature",
      "properties": {
        "hierarchy": [
          "tgn:1062277",
          "tgn:1001439",
          "tgn:1000003",
          "tgn:7002797",
          "tgn:1000095",
          "tgn:7029392"
        ],
        "placetype": [
          "aat:300008347"
        ],
        "id": 1062277,
        "name:xx": "Mula"
      }
    },
    {
      "geometry": {
        "type": "Point",
        "coordinates": [
          -2.466667,
          39.033333
        ]
      },
      "type": "Feature",
      "properties": {
        "hierarchy": [
          "tgn:1062278",
          "tgn:7002803",
          "tgn:1001647",
          "tgn:1000003",
          "tgn:1000095",
          "tgn:7029392"
        ],
        "placetype": [
          "aat:300008347"
        ],
        "id": 1062278,
        "name:xx": "Munera"
      }
    },
    {
      "geometry": {
        "type": "Point",
        "coordinates": [
          -0.8,
          41.033333
        ]
      },
      "type": "Feature",
      "properties": {
        "hierarchy": [
          "tgn:1062279",
          "tgn:7002759",
          "tgn:7002843",
          "tgn:1000003",
          "tgn:1000095",
          "tgn:7029392"
        ],
        "placetype": [
          "aat:300008347"
        ],
        "id": 1062279,
        "name:xx": "Muniesa"
      }
    }
  ]
}
