{
  "geometry": {
    "type": "Point",
    "coordinates": [
      -88.2833,
      36.8833
    ]
  },
  "type": "Feature",
  "properties": {
    "hierarchy": [
      "tgn:2313994",
      "tgn:1000001",
      "tgn:7012149",
      "tgn:2000823",
      "tgn:7007255",
      "tgn:7029392"
    ],
    "placetype": [
      "aat:300008706"
    ],
    "id": 2313994,
    "name:xx": "Elizabeth Creek"
  }
}
