{
  "geometry": {
    "type": "Point",
    "coordinates": [
      -107.7833,
      37.9333
    ]
  },
  "type": "Feature",
  "properties": {
    "hierarchy": [
      "tgn:2446922",
      "tgn:1000001",
      "tgn:7012149",
      "tgn:7007158",
      "tgn:2000248",
      "tgn:7029392"
    ],
    "placetype": [
      "aat:300008347"
    ],
    "id": 2446922,
    "name:xx": "Liberty Bell"
  }
}
