{
  "type": "FeatureCollection",
  "features": [
    {
      "geometry": {
        "type": "Point",
        "coordinates": [
          -56.8333,
          -33.5833
        ]
      },
      "type": "Feature",
      "properties": {
        "hierarchy": [
          "tgn:1000610",
          "tgn:1000002",
          "tgn:1000058",
          "tgn:7029392"
        ],
        "placetype": [
          "aat:300387064",
          "aat:300000772"
        ],
        "id": 1000610,
        "name:xx": "Flores"
      }
    },
    {
      "geometry": {
        "type": "Point",
        "coordinates": [
          -55.9167,
          -33.8333
        ]
      },
      "type": "Feature",
      "properties": {
        "hierarchy": [
          "tgn:1000611",
          "tgn:1000002",
          "tgn:1000058",
          "tgn:7029392"
        ],
        "placetype": [
          "aat:300387064",
          "aat:300000772"
        ],
        "id": 1000611,
        "name:xx": "Florida"
      }
    },
    {
      "geometry": {
        "type": "Point",
        "coordinates": [
          -87.1667,
          14.25
        ]
      },
      "type": "Feature",
      "properties": {
        "hierarchy": [
          "tgn:1000612",
          "tgn:1000001",
          "tgn:7005554",
          "tgn:7029392"
        ],
        "placetype": [
          "aat:300387064",
          "aat:300000772"
        ],
        "id": 1000612,
        "name:xx": "Francisco Morazán"
      }
    },
    {
      "geometry": {
        "type": "Point",
        "coordinates": [
          -6,
          6.1667
        ]
      },
      "type": "Feature",
      "properties": {
        "hierarchy": [
          "tgn:1000613",
          "tgn:7001242",
          "tgn:1000168",
          "tgn:7029392"
        ],
        "placetype": [
          "aat:300387064",
          "aat:300000772"
        ],
        "id": 1000613,
        "name:xx": "Gagnoa, Département de"
      }
    },
    {
      "geometry": {
        "type": "Point",
        "coordinates": [
          -84.3333,
          15.25
        ]
      },
      "type": "Feature",
      "properties": {
        "hierarchy": [
          "tgn:1000617",
          "tgn:1000001",
          "tgn:7005554",
          "tgn:7029392"
        ],
        "placetype": [
          "aat:300387064",
          "aat:300000772"
        ],
        "id": 1000617,
        "name:xx": "Gracias a Dios"
      }
    },
    {
      "geometry": {
        "type": "Point",
        "coordinates": [
          -86,
          11.8333
        ]
      },
      "type": "Feature",
      "properties": {
        "hierarchy": [
          "tgn:1000618",
          "tgn:1000001",
          "tgn:7005562",
          "tgn:7029392"
        ],
        "placetype": [
          "aat:300387064",
          "aat:300000772"
        ],
        "id": 1000618,
        "name:xx": "Granada"
      }
    },
    {
      "geometry": {
        "type": "Point",
        "coordinates": [
          -69,
          2.5
        ]
      },
      "type": "Feature",
      "properties": {
        "hierarchy": [
          "tgn:1000619",
          "tgn:1000050",
          "tgn:1000002",
          "tgn:7029392"
        ],
        "placetype": [
          "aat:300387064",
          "aat:300000772"
        ],
        "id": 1000619,
        "name:xx": "Guainía"
      }
    }
  ]
}
