{
  "geometry": {
    "type": "Point",
    "coordinates": [
      31.351885,
      30.047304
    ]
  },
  "type": "Feature",
  "properties": {
    "hierarchy": [
      "tgn:7531904",
      "tgn:7001242",
      "tgn:7016833",
      "tgn:1001091",
      "tgn:7029392"
    ],
    "placetype": [
      "aat:300386970"
    ],
    "id": 7531904,
    "name:xx": "Mişr al 'Arabī al Afrīqī, Bank"
  }
}
