{
  "geometry": {
    "type": "Point",
    "coordinates": [
      -88.6667,
      32.9167
    ]
  },
  "type": "Feature",
  "properties": {
    "hierarchy": [
      "tgn:2493583",
      "tgn:1000001",
      "tgn:7012149",
      "tgn:7007522",
      "tgn:7029392"
    ],
    "placetype": [
      "aat:300008761"
    ],
    "id": 2493583,
    "name:xx": "Marsh Hollow"
  }
}
