{
  "geometry": {
    "type": "Point",
    "coordinates": [
      -70.8333,
      42.55
    ]
  },
  "type": "Feature",
  "properties": {
    "hierarchy": [
      "tgn:2671780",
      "tgn:1000001",
      "tgn:1002359",
      "tgn:7012149",
      "tgn:7007517",
      "tgn:7029392"
    ],
    "placetype": [
      "aat:300008850"
    ],
    "id": 2671780,
    "name:xx": "Smith Point"
  }
}
