{
  "geometry": {
    "type": "Point",
    "coordinates": [
      -75.7167,
      38.6333
    ]
  },
  "type": "Feature",
  "properties": {
    "hierarchy": [
      "tgn:2343620",
      "tgn:1000001",
      "tgn:7012149",
      "tgn:7007516",
      "tgn:7029392"
    ],
    "placetype": [
      "aat:300008706"
    ],
    "id": 2343620,
    "name:xx": "Gales Creek"
  }
}
