{
  "geometry": {
    "type": "Point",
    "coordinates": [
      -81.5333,
      39.6167
    ]
  },
  "type": "Feature",
  "properties": {
    "hierarchy": [
      "tgn:2609859",
      "tgn:1000001",
      "tgn:7012149",
      "tgn:7007706",
      "tgn:7029392"
    ],
    "placetype": [
      "aat:300008699"
    ],
    "id": 2609859,
    "name:xx": "Reasoners Run"
  }
}
