{
  "geometry": {
    "type": "Point",
    "coordinates": [
      -77.9667,
      41.3333
    ]
  },
  "type": "Feature",
  "properties": {
    "hierarchy": [
      "tgn:2447708",
      "tgn:1000001",
      "tgn:1002286",
      "tgn:7012149",
      "tgn:7007710",
      "tgn:7029392"
    ],
    "placetype": [
      "aat:300008699"
    ],
    "id": 2447708,
    "name:xx": "Lick Run"
  }
}
