{
  "type": "FeatureCollection",
  "features": [
    {
      "geometry": {
        "type": "Point",
        "coordinates": [
          168.916667,
          -44
        ]
      },
      "type": "Feature",
      "properties": {
        "hierarchy": [
          "tgn:7505240",
          "tgn:1009227",
          "tgn:1000226",
          "tgn:7018437",
          "tgn:1000006",
          "tgn:7029392"
        ],
        "placetype": [
          "aat:300008777"
        ],
        "name:en": "Woolsack, The",
        "id": 7505240
      }
    },
    {
      "geometry": {
        "type": "Point",
        "coordinates": [
          172.216667,
          -42.2
        ]
      },
      "type": "Feature",
      "properties": {
        "hierarchy": [
          "tgn:7505241",
          "tgn:1009227",
          "tgn:1000226",
          "tgn:1000006",
          "tgn:7016850",
          "tgn:7029392"
        ],
        "placetype": [
          "aat:300008699"
        ],
        "name:en": "Woolley River",
        "id": 7505241
      }
    },
    {
      "geometry": {
        "type": "Point",
        "coordinates": [
          168.35,
          -46.066667
        ]
      },
      "type": "Feature",
      "properties": {
        "hierarchy": [
          "tgn:7505242",
          "tgn:1009227",
          "tgn:1000226",
          "tgn:7016822",
          "tgn:1000006",
          "tgn:7029392"
        ],
        "placetype": [
          "aat:300008777"
        ],
        "name:en": "Woody Knoll",
        "id": 7505242
      }
    },
    {
      "geometry": {
        "type": "Point",
        "coordinates": [
          175.8,
          -37.033333
        ]
      },
      "type": "Feature",
      "properties": {
        "hierarchy": [
          "tgn:7505243",
          "tgn:1008380",
          "tgn:1000226",
          "tgn:7018426",
          "tgn:1000006",
          "tgn:7029392"
        ],
        "placetype": [
          "aat:300008795"
        ],
        "name:en": "Woody Hill",
        "id": 7505243
      }
    },
    {
      "geometry": {
        "type": "Point",
        "coordinates": [
          174.766667,
          -37.85
        ]
      },
      "type": "Feature",
      "properties": {
        "hierarchy": [
          "tgn:7505244",
          "tgn:1008380",
          "tgn:1000226",
          "tgn:7018426",
          "tgn:1000006",
          "tgn:7029392"
        ],
        "placetype": [
          "aat:300386846"
        ],
        "name:en": "Woody Head",
        "id": 7505244
      }
    },
    {
      "geometry": {
        "type": "Point",
        "coordinates": [
          168.716667,
          -44.7
        ]
      },
      "type": "Feature",
      "properties": {
        "hierarchy": [
          "tgn:7505245",
          "tgn:1009227",
          "tgn:1000226",
          "tgn:7018437",
          "tgn:1000006",
          "tgn:7029392"
        ],
        "placetype": [
          "aat:300008767"
        ],
        "name:en": "Woody Gully",
        "id": 7505245
      }
    },
    {
      "geometry": {
        "type": "Point",
        "coordinates": [
          171,
          -42.766667
        ]
      },
      "type": "Feature",
      "properties": {
        "hierarchy": [
          "tgn:7505249",
          "tgn:1009227",
          "tgn:1000226",
          "tgn:1000006",
          "tgn:7016850",
          "tgn:7029392"
        ],
        "placetype": [
          "aat:300008347"
        ],
        "name:en": "Woodstock",
        "id": 7505249
      }
    }
  ]
}
