{
  "geometry": {
    "type": "Point",
    "coordinates": [
      -100.5333,
      32.5167
    ]
  },
  "type": "Feature",
  "properties": {
    "hierarchy": [
      "tgn:1133688",
      "tgn:1000001",
      "tgn:7012149",
      "tgn:7007826",
      "tgn:7029392"
    ],
    "placetype": [
      "aat:300008706"
    ],
    "id": 1133688,
    "name:xx": "Live Oak Creek"
  }
}
