{
  "geometry": {
    "type": "Point",
    "coordinates": [
      -80.9833,
      36.3667
    ]
  },
  "type": "Feature",
  "properties": {
    "hierarchy": [
      "tgn:2697391",
      "tgn:2001465",
      "tgn:1000001",
      "tgn:7012149",
      "tgn:7007709",
      "tgn:7029392"
    ],
    "placetype": [
      "aat:300008798"
    ],
    "id": 2697391,
    "name:xx": "Stony Knob"
  }
}
