{
  "geometry": {
    "type": "Point",
    "coordinates": [
      12.15,
      51.65
    ]
  },
  "type": "Feature",
  "properties": {
    "hierarchy": [
      "tgn:7112973",
      "tgn:1000003",
      "tgn:7003687",
      "tgn:7000084",
      "tgn:7029392"
    ],
    "placetype": [
      "aat:300008347"
    ],
    "id": 7112973,
    "name:xx": "Rodigkau"
  }
}
