{
  "geometry": {
    "type": "Point",
    "coordinates": [
      -80.4333,
      37.8667
    ]
  },
  "type": "Feature",
  "properties": {
    "hierarchy": [
      "tgn:2664747",
      "tgn:1000001",
      "tgn:7012149",
      "tgn:2002264",
      "tgn:7013961",
      "tgn:7029392"
    ],
    "placetype": [
      "aat:300008746"
    ],
    "id": 2664747,
    "name:xx": "Simms Cave"
  }
}
