{
  "type": "FeatureCollection",
  "features": [
    {
      "geometry": {
        "type": "Point",
        "coordinates": [
          -3.916667,
          55.233333
        ]
      },
      "type": "Feature",
      "properties": {
        "hierarchy": [
          "tgn:7462600",
          "tgn:7002444",
          "tgn:7008074",
          "tgn:1000003",
          "tgn:7008591",
          "tgn:7029392"
        ],
        "placetype": [
          "aat:300008699"
        ],
        "name:en": "Kirkconnell Burn",
        "id": 7462600
      }
    },
    {
      "geometry": {
        "type": "Point",
        "coordinates": [
          -3.6,
          54.983333
        ]
      },
      "type": "Feature",
      "properties": {
        "hierarchy": [
          "tgn:7462601",
          "tgn:7002444",
          "tgn:7008074",
          "tgn:1000003",
          "tgn:7008591",
          "tgn:7029392"
        ],
        "placetype": [
          "aat:300008347"
        ],
        "name:en": "Kirkconnell",
        "id": 7462601
      }
    },
    {
      "geometry": {
        "type": "Point",
        "coordinates": [
          -3.1,
          55.266667
        ]
      },
      "type": "Feature",
      "properties": {
        "hierarchy": [
          "tgn:7462604",
          "tgn:7002444",
          "tgn:7008074",
          "tgn:1000003",
          "tgn:7008591",
          "tgn:7029392"
        ],
        "placetype": [
          "aat:300008699"
        ],
        "name:en": "Kirk Cleuch",
        "id": 7462604
      }
    },
    {
      "geometry": {
        "type": "Point",
        "coordinates": [
          -4.55,
          54.9
        ]
      },
      "type": "Feature",
      "properties": {
        "hierarchy": [
          "tgn:7462605",
          "tgn:7002444",
          "tgn:7008074",
          "tgn:1000003",
          "tgn:7008591",
          "tgn:7029392"
        ],
        "placetype": [
          "aat:300008347"
        ],
        "name:en": "Kirkchrist",
        "id": 7462605
      }
    },
    {
      "geometry": {
        "type": "Point",
        "coordinates": [
          -2.733333,
          55
        ]
      },
      "type": "Feature",
      "properties": {
        "hierarchy": [
          "tgn:7462606",
          "tgn:7002445",
          "tgn:1000003",
          "tgn:7008117",
          "tgn:7008591",
          "tgn:7029392"
        ],
        "placetype": [
          "aat:300008347"
        ],
        "name:en": "Kirkcambeck",
        "id": 7462606
      }
    },
    {
      "geometry": {
        "type": "Point",
        "coordinates": [
          -3.15,
          56.116667
        ]
      },
      "type": "Feature",
      "properties": {
        "hierarchy": [
          "tgn:7462607",
          "tgn:7002444",
          "tgn:1000003",
          "tgn:7008076",
          "tgn:7008591",
          "tgn:7029392"
        ],
        "placetype": [
          "aat:300008678"
        ],
        "name:en": "Kirkcaldy Harbour",
        "id": 7462607
      }
    },
    {
      "geometry": {
        "type": "Point",
        "coordinates": [
          -3.1,
          56.1
        ]
      },
      "type": "Feature",
      "properties": {
        "hierarchy": [
          "tgn:7462608",
          "tgn:7002444",
          "tgn:1000003",
          "tgn:7008076",
          "tgn:7008591",
          "tgn:7029392"
        ],
        "placetype": [
          "aat:300132316"
        ],
        "name:en": "Kirkcaldy Bay",
        "id": 7462608
      }
    }
  ]
}
