{
  "geometry": {
    "type": "Point",
    "coordinates": [
      -120.7167,
      37.9167
    ]
  },
  "type": "Feature",
  "properties": {
    "hierarchy": [
      "tgn:2393665",
      "tgn:1000001",
      "tgn:1002219",
      "tgn:7012149",
      "tgn:7007157",
      "tgn:7029392"
    ],
    "placetype": [
      "aat:300008798"
    ],
    "id": 2393665,
    "name:xx": "Hog Hill"
  }
}
