{
  "geometry": {
    "type": "Point",
    "coordinates": [
      -123.9333,
      45.3167
    ]
  },
  "type": "Feature",
  "properties": {
    "hierarchy": [
      "tgn:2631958",
      "tgn:1000001",
      "tgn:7012149",
      "tgn:1002943",
      "tgn:7007708",
      "tgn:7029392"
    ],
    "placetype": [
      "aat:300008706"
    ],
    "id": 2631958,
    "name:xx": "Rover Creek"
  }
}
