{
  "geometry": {
    "type": "Point",
    "coordinates": [
      -92.25,
      40.8167
    ]
  },
  "type": "Feature",
  "properties": {
    "hierarchy": [
      "tgn:2463725",
      "tgn:1000001",
      "tgn:2000586",
      "tgn:7012149",
      "tgn:7007253",
      "tgn:7029392"
    ],
    "placetype": [
      "aat:300008699"
    ],
    "id": 2463725,
    "name:xx": "Locke Branch"
  }
}
