{
  "geometry": {
    "type": "Point",
    "coordinates": [
      -108.95,
      44.3833
    ]
  },
  "type": "Feature",
  "properties": {
    "hierarchy": [
      "tgn:2771707",
      "tgn:1000001",
      "tgn:7012149",
      "tgn:2002379",
      "tgn:7007923",
      "tgn:7029392"
    ],
    "placetype": [
      "aat:300008347"
    ],
    "id": 2771707,
    "name:xx": "Wiley"
  }
}
