{
  "geometry": {
    "type": "Point",
    "coordinates": [
      -3.45,
      37.65
    ]
  },
  "type": "Feature",
  "properties": {
    "hierarchy": [
      "tgn:1062079",
      "tgn:7002758",
      "tgn:1001316",
      "tgn:1000003",
      "tgn:1000095",
      "tgn:7029392"
    ],
    "placetype": [
      "aat:300008347"
    ],
    "id": 1062079,
    "name:xx": "Huelma"
  }
}
