{
  "geometry": {
    "type": "Point",
    "coordinates": [
      -156.0333,
      20.65
    ]
  },
  "type": "Feature",
  "properties": {
    "hierarchy": [
      "tgn:2489161",
      "tgn:1002648",
      "tgn:1000001",
      "tgn:7019158",
      "tgn:7012149",
      "tgn:7007249",
      "tgn:7029392"
    ],
    "placetype": [
      "aat:300008850"
    ],
    "id": 2489161,
    "name:xx": "Makaaikuloa Point"
  }
}
