{
  "geometry": {
    "type": "Point",
    "coordinates": [
      77.37512,
      29.628527
    ]
  },
  "type": "Feature",
  "properties": {
    "hierarchy": [
      "tgn:7590491",
      "tgn:1000004",
      "tgn:7000198",
      "tgn:7016722",
      "tgn:7029392"
    ],
    "placetype": [
      "aat:300008347"
    ],
    "name:en": "Māzra Bhanera",
    "id": 7590491
  }
}
