{
  "geometry": {
    "type": "Point",
    "coordinates": [
      -115.7667,
      43.95
    ]
  },
  "type": "Feature",
  "properties": {
    "hierarchy": [
      "tgn:2680017",
      "tgn:1000001",
      "tgn:2000459",
      "tgn:7012149",
      "tgn:7007250",
      "tgn:7029392"
    ],
    "placetype": [
      "aat:300008706"
    ],
    "id": 2680017,
    "name:xx": "South Fork Smith Creek"
  }
}
