{
  "geometry": {
    "type": "Point",
    "coordinates": [
      69.233333,
      22.833333
    ]
  },
  "type": "Feature",
  "properties": {
    "hierarchy": [
      "tgn:7547532",
      "tgn:1000004",
      "tgn:1001869",
      "tgn:7000198",
      "tgn:7029392"
    ],
    "placetype": [
      "aat:300007595"
    ],
    "name:en": "Āsār Māta",
    "id": 7547532
  }
}
