{
  "geometry": {
    "type": "Point",
    "coordinates": [
      32.392762,
      30.07345
    ]
  },
  "type": "Feature",
  "properties": {
    "hierarchy": [
      "tgn:7528953",
      "tgn:7001242",
      "tgn:7016833",
      "tgn:1001110",
      "tgn:7029392"
    ],
    "placetype": [
      "aat:300008347"
    ],
    "id": 7528953,
    "name:xx": "Ţābiyat al 'Ajrūd"
  }
}
