{
  "geometry": {
    "type": "Point",
    "coordinates": [
      79.316611,
      26.26865
    ]
  },
  "type": "Feature",
  "properties": {
    "hierarchy": [
      "tgn:7564773",
      "tgn:1000004",
      "tgn:7000198",
      "tgn:7016722",
      "tgn:7029392"
    ],
    "placetype": [
      "aat:300008347"
    ],
    "name:en": "Gorābhūpka",
    "id": 7564773
  }
}
