{
  "geometry": {
    "type": "Point",
    "coordinates": [
      -80.5167,
      27.7333
    ]
  },
  "type": "Feature",
  "properties": {
    "hierarchy": [
      "tgn:2021656",
      "tgn:1000001",
      "tgn:1002500",
      "tgn:7012149",
      "tgn:7007240",
      "tgn:7029392"
    ],
    "placetype": [
      "aat:300008347"
    ],
    "id": 2021656,
    "name:xx": "Vero Lake Estates"
  }
}
