{
  "geometry": {
    "type": "Point",
    "coordinates": [
      -108.5333,
      37.45
    ]
  },
  "type": "Feature",
  "properties": {
    "hierarchy": [
      "tgn:2379099",
      "tgn:1000001",
      "tgn:7012149",
      "tgn:2000233",
      "tgn:7007158",
      "tgn:7029392"
    ],
    "placetype": [
      "aat:300008761"
    ],
    "id": 2379099,
    "name:xx": "Hartman Draw"
  }
}
