{
  "type": "FeatureCollection",
  "features": [
    {
      "geometry": {
        "type": "Point",
        "coordinates": [
          9.633333,
          50.466667
        ]
      },
      "type": "Feature",
      "properties": {
        "hierarchy": [
          "tgn:7151920",
          "tgn:1000003",
          "tgn:7003678",
          "tgn:7000084",
          "tgn:7029392"
        ],
        "placetype": [
          "aat:300008347"
        ],
        "id": 7151920,
        "name:xx": "Kahlberg"
      }
    },
    {
      "geometry": {
        "type": "Point",
        "coordinates": [
          10.083333,
          51.8
        ]
      },
      "type": "Feature",
      "properties": {
        "hierarchy": [
          "tgn:7151921",
          "tgn:1000003",
          "tgn:7003676",
          "tgn:7000084",
          "tgn:7029392"
        ],
        "placetype": [
          "aat:300008777"
        ],
        "id": 7151921,
        "name:xx": "Kahlberg"
      }
    },
    {
      "geometry": {
        "type": "Point",
        "coordinates": [
          10.05,
          51.5
        ]
      },
      "type": "Feature",
      "properties": {
        "hierarchy": [
          "tgn:7151922",
          "tgn:1000003",
          "tgn:7003676",
          "tgn:7000084",
          "tgn:7029392"
        ],
        "placetype": [
          "aat:300008777"
        ],
        "id": 7151922,
        "name:xx": "Kahl-Berg"
      }
    },
    {
      "geometry": {
        "type": "Point",
        "coordinates": [
          7.95,
          50.283333
        ]
      },
      "type": "Feature",
      "properties": {
        "hierarchy": [
          "tgn:7151923",
          "tgn:1000003",
          "tgn:7003682",
          "tgn:7000084",
          "tgn:7029392"
        ],
        "placetype": [
          "aat:300008777"
        ],
        "id": 7151923,
        "name:xx": "Kahl-Berg"
      }
    },
    {
      "geometry": {
        "type": "Point",
        "coordinates": [
          9.783333,
          49.866667
        ]
      },
      "type": "Feature",
      "properties": {
        "hierarchy": [
          "tgn:7151924",
          "tgn:7003669",
          "tgn:1000003",
          "tgn:7000084",
          "tgn:7029392"
        ],
        "placetype": [
          "aat:300008777"
        ],
        "id": 7151924,
        "name:xx": "Kahl-Berg"
      }
    },
    {
      "geometry": {
        "type": "Point",
        "coordinates": [
          8.866667,
          49.65
        ]
      },
      "type": "Feature",
      "properties": {
        "hierarchy": [
          "tgn:7151925",
          "tgn:1000003",
          "tgn:7003678",
          "tgn:7000084",
          "tgn:7029392"
        ],
        "placetype": [
          "aat:300008777"
        ],
        "id": 7151925,
        "name:xx": "Kahlberg"
      }
    },
    {
      "geometry": {
        "type": "Point",
        "coordinates": [
          11.116667,
          49.55
        ]
      },
      "type": "Feature",
      "properties": {
        "hierarchy": [
          "tgn:7151926",
          "tgn:7003669",
          "tgn:1000003",
          "tgn:7000084",
          "tgn:7029392"
        ],
        "placetype": [
          "aat:300008777"
        ],
        "id": 7151926,
        "name:xx": "Kahl-Berg"
      }
    },
    {
      "geometry": {
        "type": "Point",
        "coordinates": [
          11.533333,
          52.516667
        ]
      },
      "type": "Feature",
      "properties": {
        "hierarchy": [
          "tgn:7151927",
          "tgn:1000003",
          "tgn:7003687",
          "tgn:7000084",
          "tgn:7029392"
        ],
        "placetype": [
          "aat:300008863"
        ],
        "id": 7151927,
        "name:xx": "Jävenitzer Bauernheide"
      }
    },
    {
      "geometry": {
        "type": "Point",
        "coordinates": [
          11.55,
          52.533333
        ]
      },
      "type": "Feature",
      "properties": {
        "hierarchy": [
          "tgn:7151928",
          "tgn:1000003",
          "tgn:7003687",
          "tgn:7000084",
          "tgn:7029392"
        ],
        "placetype": [
          "aat:300008863"
        ],
        "id": 7151928,
        "name:xx": "Jävenitz, Forst"
      }
    }
  ]
}
