{
  "geometry": {
    "type": "Point",
    "coordinates": [
      -99.2833,
      35.3833
    ]
  },
  "type": "Feature",
  "properties": {
    "hierarchy": [
      "tgn:2727513",
      "tgn:1000001",
      "tgn:7012149",
      "tgn:2001697",
      "tgn:7007707",
      "tgn:7029392"
    ],
    "placetype": [
      "aat:300008706"
    ],
    "id": 2727513,
    "name:xx": "Trail Creek"
  }
}
