{
  "geometry": {
    "type": "Point",
    "coordinates": [
      -92.9833,
      33.9167
    ]
  },
  "type": "Feature",
  "properties": {
    "hierarchy": [
      "tgn:2451930",
      "tgn:1000001",
      "tgn:7016172",
      "tgn:2000114",
      "tgn:7012149",
      "tgn:7029392"
    ],
    "placetype": [
      "aat:300008699"
    ],
    "id": 2451930,
    "name:xx": "Little Beech Branch"
  }
}
