{
  "geometry": {
    "type": "Point",
    "coordinates": [
      -95.0167,
      29.8667
    ]
  },
  "type": "Feature",
  "properties": {
    "hierarchy": [
      "tgn:2201854",
      "tgn:1000001",
      "tgn:7012149",
      "tgn:1002456",
      "tgn:7007826",
      "tgn:7029392"
    ],
    "placetype": [
      "aat:300008761"
    ],
    "id": 2201854,
    "name:xx": "Buck Gully"
  }
}
