{
  "type": "FeatureCollection",
  "features": [
    {
      "geometry": {
        "type": "Point",
        "coordinates": [
          -85.4,
          43.3167
        ]
      },
      "type": "Feature",
      "properties": {
        "hierarchy": [
          "tgn:2579760",
          "tgn:1000001",
          "tgn:7012149",
          "tgn:2000981",
          "tgn:7007520",
          "tgn:7029392"
        ],
        "placetype": [
          "aat:300008680"
        ],
        "id": 2579760,
        "name:xx": "Picnic Lake"
      }
    },
    {
      "geometry": {
        "type": "Point",
        "coordinates": [
          -86.1,
          44.0333
        ]
      },
      "type": "Feature",
      "properties": {
        "hierarchy": [
          "tgn:2579761",
          "tgn:1000001",
          "tgn:7012149",
          "tgn:2000976",
          "tgn:7007520",
          "tgn:7029392"
        ],
        "placetype": [
          "aat:300008680"
        ],
        "id": 2579761,
        "name:xx": "Picnic Lake"
      }
    },
    {
      "geometry": {
        "type": "Point",
        "coordinates": [
          -91.2667,
          45.2
        ]
      },
      "type": "Feature",
      "properties": {
        "hierarchy": [
          "tgn:2579762",
          "tgn:1000001",
          "tgn:2002313",
          "tgn:7012149",
          "tgn:7007922",
          "tgn:7029392"
        ],
        "placetype": [
          "aat:300008680"
        ],
        "id": 2579762,
        "name:xx": "Picnic Lake"
      }
    },
    {
      "geometry": {
        "type": "Point",
        "coordinates": [
          -113.9167,
          48.15
        ]
      },
      "type": "Feature",
      "properties": {
        "hierarchy": [
          "tgn:2579763",
          "tgn:1000001",
          "tgn:7012149",
          "tgn:2001274",
          "tgn:7007524",
          "tgn:7029392"
        ],
        "placetype": [
          "aat:300008680"
        ],
        "id": 2579763,
        "name:xx": "Picnic Lakes"
      }
    },
    {
      "geometry": {
        "type": "Point",
        "coordinates": [
          -112.1167,
          39.9
        ]
      },
      "type": "Feature",
      "properties": {
        "hierarchy": [
          "tgn:2579764",
          "tgn:1000001",
          "tgn:7012149",
          "tgn:2002112",
          "tgn:7007827",
          "tgn:7029392"
        ],
        "placetype": [
          "aat:300000390"
        ],
        "id": 2579764,
        "name:xx": "Picnic Mine"
      }
    },
    {
      "geometry": {
        "type": "Point",
        "coordinates": [
          -158.35,
          59.0333
        ]
      },
      "type": "Feature",
      "properties": {
        "hierarchy": [
          "tgn:2579765",
          "tgn:7006450",
          "tgn:1000001",
          "tgn:2000071",
          "tgn:7012149",
          "tgn:7029392"
        ],
        "placetype": [
          "aat:300008850"
        ],
        "id": 2579765,
        "name:xx": "Picnic Point"
      }
    },
    {
      "geometry": {
        "type": "Point",
        "coordinates": [
          -92.4333,
          35.1333
        ]
      },
      "type": "Feature",
      "properties": {
        "hierarchy": [
          "tgn:2579766",
          "tgn:1000001",
          "tgn:7016172",
          "tgn:7012149",
          "tgn:2000127",
          "tgn:7029392"
        ],
        "placetype": [
          "aat:300008850"
        ],
        "id": 2579766,
        "name:xx": "Picnic Point"
      }
    },
    {
      "geometry": {
        "type": "Point",
        "coordinates": [
          -115.6667,
          44.65
        ]
      },
      "type": "Feature",
      "properties": {
        "hierarchy": [
          "tgn:2579767",
          "tgn:1000001",
          "tgn:7012149",
          "tgn:2000494",
          "tgn:7007250",
          "tgn:7029392"
        ],
        "placetype": [
          "aat:300008850"
        ],
        "id": 2579767,
        "name:xx": "Picnic Point"
      }
    },
    {
      "geometry": {
        "type": "Point",
        "coordinates": [
          -67.75,
          45.5167
        ]
      },
      "type": "Feature",
      "properties": {
        "hierarchy": [
          "tgn:2579768",
          "tgn:1000001",
          "tgn:7012149",
          "tgn:7014589",
          "tgn:7007515",
          "tgn:7029392"
        ],
        "placetype": [
          "aat:300008850"
        ],
        "id": 2579768,
        "name:xx": "Picnic Point"
      }
    },
    {
      "geometry": {
        "type": "Point",
        "coordinates": [
          -73.9333,
          41.9833
        ]
      },
      "type": "Feature",
      "properties": {
        "hierarchy": [
          "tgn:2579769",
          "tgn:1000001",
          "tgn:1002347",
          "tgn:7012149",
          "tgn:7007568",
          "tgn:7029392"
        ],
        "placetype": [
          "aat:300008850"
        ],
        "id": 2579769,
        "name:xx": "Picnic Point"
      }
    }
  ]
}
