{
  "geometry": {
    "type": "Point",
    "coordinates": [
      -110.05,
      28.35
    ]
  },
  "type": "Feature",
  "properties": {
    "hierarchy": [
      "tgn:7435734",
      "tgn:1000001",
      "tgn:1001960",
      "tgn:7005560",
      "tgn:7029392"
    ],
    "placetype": [
      "aat:300000241"
    ],
    "id": 7435734,
    "name:xx": "Rancho Torimacuca"
  }
}
