{
  "geometry": {
    "type": "Point",
    "coordinates": [
      -75.3833,
      42.2667
    ]
  },
  "type": "Feature",
  "properties": {
    "hierarchy": [
      "tgn:2662294",
      "tgn:1000001",
      "tgn:1002328",
      "tgn:7012149",
      "tgn:7007568",
      "tgn:7029392"
    ],
    "placetype": [
      "aat:300008798"
    ],
    "id": 2662294,
    "name:xx": "Sidney Mountain"
  }
}
