{
  "geometry": {
    "type": "Point",
    "coordinates": [
      -145.9167,
      62.4333
    ]
  },
  "type": "Feature",
  "properties": {
    "hierarchy": [
      "tgn:2290712",
      "tgn:7006450",
      "tgn:1000001",
      "tgn:7012149",
      "tgn:2000086",
      "tgn:7029392"
    ],
    "placetype": [
      "aat:300008706"
    ],
    "id": 2290712,
    "name:xx": "Dog Creek"
  }
}
