{
  "type": "FeatureCollection",
  "features": [
    {
      "geometry": {
        "type": "Point",
        "coordinates": [
          -95.1,
          18.65
        ]
      },
      "type": "Feature",
      "properties": {
        "hierarchy": [
          "tgn:7439930",
          "tgn:1000001",
          "tgn:7005599",
          "tgn:7005560",
          "tgn:7029392"
        ],
        "placetype": [
          "aat:300386846"
        ],
        "id": 7439930,
        "name:xx": "San Martín, Punta"
      }
    },
    {
      "geometry": {
        "type": "Point",
        "coordinates": [
          -91.333333,
          17.4
        ]
      },
      "type": "Feature",
      "properties": {
        "hierarchy": [
          "tgn:7439931",
          "tgn:1000001",
          "tgn:7005596",
          "tgn:7005560",
          "tgn:7029392"
        ],
        "placetype": [
          "aat:300008680"
        ],
        "id": 7439931,
        "name:xx": "San Martin, Laguna"
      }
    },
    {
      "geometry": {
        "type": "Point",
        "coordinates": [
          -116.116667,
          30.5
        ]
      },
      "type": "Feature",
      "properties": {
        "hierarchy": [
          "tgn:7439932",
          "tgn:1001835",
          "tgn:1000001",
          "tgn:7005560",
          "tgn:7029392"
        ],
        "placetype": [
          "aat:300008791"
        ],
        "id": 7439932,
        "name:xx": "San Martín, Isla"
      }
    },
    {
      "geometry": {
        "type": "Point",
        "coordinates": [
          -108.451389,
          26.835278
        ]
      },
      "type": "Feature",
      "properties": {
        "hierarchy": [
          "tgn:7439933",
          "tgn:1000001",
          "tgn:7005595",
          "tgn:7005560",
          "tgn:7029392"
        ],
        "placetype": [
          "aat:300008795"
        ],
        "id": 7439933,
        "name:xx": "San Martin, Cerro"
      }
    },
    {
      "geometry": {
        "type": "Point",
        "coordinates": [
          -103.216667,
          20.516667
        ]
      },
      "type": "Feature",
      "properties": {
        "hierarchy": [
          "tgn:7439934",
          "tgn:7005586",
          "tgn:1000001",
          "tgn:7005560",
          "tgn:7029392"
        ],
        "placetype": [
          "aat:300008795"
        ],
        "id": 7439934,
        "name:xx": "San Martin, Cerro"
      }
    },
    {
      "geometry": {
        "type": "Point",
        "coordinates": [
          -94.8,
          18.316667
        ]
      },
      "type": "Feature",
      "properties": {
        "hierarchy": [
          "tgn:7439935",
          "tgn:1000001",
          "tgn:7005599",
          "tgn:7005560",
          "tgn:7029392"
        ],
        "placetype": [
          "aat:300008795"
        ],
        "id": 7439935,
        "name:xx": "San Martín, Cerro"
      }
    },
    {
      "geometry": {
        "type": "Point",
        "coordinates": [
          -106.066667,
          26.733333
        ]
      },
      "type": "Feature",
      "properties": {
        "hierarchy": [
          "tgn:7439936",
          "tgn:7005583",
          "tgn:1000001",
          "tgn:7005560",
          "tgn:7029392"
        ],
        "placetype": [
          "aat:300007783"
        ],
        "id": 7439936,
        "name:xx": "San Martín"
      }
    },
    {
      "geometry": {
        "type": "Point",
        "coordinates": [
          -107.633333,
          26.8
        ]
      },
      "type": "Feature",
      "properties": {
        "hierarchy": [
          "tgn:7439937",
          "tgn:7005581",
          "tgn:1000001",
          "tgn:7005560",
          "tgn:7029392"
        ],
        "placetype": [
          "aat:300008347"
        ],
        "id": 7439937,
        "name:xx": "San Martín"
      }
    },
    {
      "geometry": {
        "type": "Point",
        "coordinates": [
          -99.716667,
          26.783333
        ]
      },
      "type": "Feature",
      "properties": {
        "hierarchy": [
          "tgn:7439938",
          "tgn:1000001",
          "tgn:7005589",
          "tgn:7005560",
          "tgn:7029392"
        ],
        "placetype": [
          "aat:300008347"
        ],
        "id": 7439938,
        "name:xx": "San Martín"
      }
    },
    {
      "geometry": {
        "type": "Point",
        "coordinates": [
          -106.066667,
          26.733333
        ]
      },
      "type": "Feature",
      "properties": {
        "hierarchy": [
          "tgn:7439939",
          "tgn:7005583",
          "tgn:1000001",
          "tgn:7005560",
          "tgn:7029392"
        ],
        "placetype": [
          "aat:300008347"
        ],
        "id": 7439939,
        "name:xx": "San Martín"
      }
    }
  ]
}
