{
  "geometry": {
    "type": "Point",
    "coordinates": [
      -121.0667,
      46.8833
    ]
  },
  "type": "Feature",
  "properties": {
    "hierarchy": [
      "tgn:2546904",
      "tgn:1000001",
      "tgn:7012149",
      "tgn:1003042",
      "tgn:7007920",
      "tgn:7029392"
    ],
    "placetype": [
      "aat:300008706"
    ],
    "id": 2546904,
    "name:xx": "North Fork Nile Creek"
  }
}
