{
  "geometry": {
    "type": "Point",
    "coordinates": [
      -106.7333,
      37.1667
    ]
  },
  "type": "Feature",
  "properties": {
    "hierarchy": [
      "tgn:2225128",
      "tgn:2000195",
      "tgn:1000001",
      "tgn:7012149",
      "tgn:7007158",
      "tgn:7029392"
    ],
    "placetype": [
      "aat:300008706"
    ],
    "id": 2225128,
    "name:xx": "Castle Creek"
  }
}
