{
  "geometry": {
    "type": "Point",
    "coordinates": [
      -95.7167,
      34.8167
    ]
  },
  "type": "Feature",
  "properties": {
    "hierarchy": [
      "tgn:2194692",
      "tgn:1000001",
      "tgn:7012149",
      "tgn:2001683",
      "tgn:7007707",
      "tgn:7029392"
    ],
    "placetype": [
      "aat:300008706"
    ],
    "id": 2194692,
    "name:xx": "Brier Creek"
  }
}
