{
  "type": "FeatureCollection",
  "features": [
    {
      "geometry": {
        "type": "Point",
        "coordinates": [
          -111.15,
          48.7833
        ]
      },
      "type": "Feature",
      "properties": {
        "hierarchy": [
          "tgn:2390960",
          "tgn:1000001",
          "tgn:7012149",
          "tgn:2001285",
          "tgn:7007524",
          "tgn:7029392"
        ],
        "placetype": [
          "aat:300008347"
        ],
        "id": 2390960,
        "name:xx": "Hill"
      }
    },
    {
      "geometry": {
        "type": "Point",
        "coordinates": [
          -118.65,
          39.4
        ]
      },
      "type": "Feature",
      "properties": {
        "hierarchy": [
          "tgn:2390961",
          "tgn:1000001",
          "tgn:2001409",
          "tgn:7012149",
          "tgn:7007526",
          "tgn:7029392"
        ],
        "placetype": [
          "aat:300008347"
        ],
        "id": 2390961,
        "name:xx": "Hill"
      }
    },
    {
      "geometry": {
        "type": "Point",
        "coordinates": [
          -77.5,
          35.75
        ]
      },
      "type": "Feature",
      "properties": {
        "hierarchy": [
          "tgn:2390962",
          "tgn:1000001",
          "tgn:7012149",
          "tgn:2001530",
          "tgn:7007709",
          "tgn:7029392"
        ],
        "placetype": [
          "aat:300008347"
        ],
        "id": 2390962,
        "name:xx": "Hill"
      }
    },
    {
      "geometry": {
        "type": "Point",
        "coordinates": [
          -86.9333,
          35.5333
        ]
      },
      "type": "Feature",
      "properties": {
        "hierarchy": [
          "tgn:2390963",
          "tgn:1000001",
          "tgn:7012149",
          "tgn:2001896",
          "tgn:7007825",
          "tgn:7029392"
        ],
        "placetype": [
          "aat:300008347"
        ],
        "id": 2390963,
        "name:xx": "Hill"
      }
    },
    {
      "geometry": {
        "type": "Point",
        "coordinates": [
          -93.2667,
          47.3333
        ]
      },
      "type": "Feature",
      "properties": {
        "hierarchy": [
          "tgn:2390964",
          "tgn:1000001",
          "tgn:7012149",
          "tgn:2001029",
          "tgn:7007521",
          "tgn:7029392"
        ],
        "placetype": [
          "aat:300000390"
        ],
        "id": 2390964,
        "name:xx": "Hill-Annex Mine"
      }
    },
    {
      "geometry": {
        "type": "Point",
        "coordinates": [
          -74.9167,
          41.8167
        ]
      },
      "type": "Feature",
      "properties": {
        "hierarchy": [
          "tgn:2390965",
          "tgn:1000001",
          "tgn:7012149",
          "tgn:1002926",
          "tgn:7007568",
          "tgn:7029392"
        ],
        "placetype": [
          "aat:300008798"
        ],
        "id": 2390965,
        "name:xx": "Hill 16"
      }
    },
    {
      "geometry": {
        "type": "Point",
        "coordinates": [
          -121.7333,
          41.6333
        ]
      },
      "type": "Feature",
      "properties": {
        "hierarchy": [
          "tgn:2390966",
          "tgn:1000001",
          "tgn:7012149",
          "tgn:7007157",
          "tgn:2000189",
          "tgn:7029392"
        ],
        "placetype": [
          "aat:300008798"
        ],
        "id": 2390966,
        "name:xx": "Hill 22"
      }
    },
    {
      "geometry": {
        "type": "Point",
        "coordinates": [
          -121.7,
          41.6333
        ]
      },
      "type": "Feature",
      "properties": {
        "hierarchy": [
          "tgn:2390967",
          "tgn:1000001",
          "tgn:7012149",
          "tgn:7007157",
          "tgn:2000189",
          "tgn:7029392"
        ],
        "placetype": [
          "aat:300008798"
        ],
        "id": 2390967,
        "name:xx": "Hill 23"
      }
    },
    {
      "geometry": {
        "type": "Point",
        "coordinates": [
          -116,
          47.2833
        ]
      },
      "type": "Feature",
      "properties": {
        "hierarchy": [
          "tgn:2390968",
          "tgn:1000001",
          "tgn:7012149",
          "tgn:2000491",
          "tgn:7007250",
          "tgn:7029392"
        ],
        "placetype": [
          "aat:300008798"
        ],
        "id": 2390968,
        "name:xx": "Hill 36"
      }
    }
  ]
}
