{
  "geometry": {
    "type": "Point",
    "coordinates": [
      -77.6833,
      36.8167
    ]
  },
  "type": "Feature",
  "properties": {
    "hierarchy": [
      "tgn:2110238",
      "tgn:1000001",
      "tgn:2002147",
      "tgn:7012149",
      "tgn:7007919",
      "tgn:7029392"
    ],
    "placetype": [
      "aat:300008347",
      "aat:300387210"
    ],
    "id": 2110238,
    "name:xx": "Adsit"
  }
}
