{
  "geometry": {
    "type": "Point",
    "coordinates": [
      72.575455,
      23.53035
    ]
  },
  "type": "Feature",
  "properties": {
    "hierarchy": [
      "tgn:7579120",
      "tgn:1000004",
      "tgn:1001869",
      "tgn:7000198",
      "tgn:7029392"
    ],
    "placetype": [
      "aat:300007783"
    ],
    "name:en": "Wasāi Dābhla",
    "id": 7579120
  }
}
