{
  "geometry": {
    "type": "Point",
    "coordinates": [
      -121.6333,
      46.0833
    ]
  },
  "type": "Feature",
  "properties": {
    "hierarchy": [
      "tgn:2669115",
      "tgn:1000001",
      "tgn:7012149",
      "tgn:1002897",
      "tgn:7007920",
      "tgn:7029392"
    ],
    "placetype": [
      "aat:300008798"
    ],
    "id": 2669115,
    "name:xx": "Sleeping Beauty"
  }
}
