{
  "geometry": {
    "type": "Point",
    "coordinates": [
      -115.683333,
      31.25
    ]
  },
  "type": "Feature",
  "properties": {
    "hierarchy": [
      "tgn:7386810",
      "tgn:1001835",
      "tgn:1000001",
      "tgn:7005560",
      "tgn:7029392"
    ],
    "placetype": [
      "aat:300008763"
    ],
    "id": 7386810,
    "name:xx": "Pleito, Cañón del"
  }
}
