{
  "geometry": {
    "type": "Point",
    "coordinates": [
      -110.8333,
      44.6667
    ]
  },
  "type": "Feature",
  "properties": {
    "hierarchy": [
      "tgn:2651187",
      "tgn:1000001",
      "tgn:7012149",
      "tgn:7007923",
      "tgn:7029392"
    ],
    "placetype": [
      "aat:300008706"
    ],
    "id": 2651187,
    "name:xx": "Secret Valley Creek"
  }
}
