{
  "geometry": {
    "type": "Point",
    "coordinates": [
      -93.3833,
      37.9167
    ]
  },
  "type": "Feature",
  "properties": {
    "hierarchy": [
      "tgn:2228959",
      "tgn:1000001",
      "tgn:7012149",
      "tgn:2001203",
      "tgn:7007523",
      "tgn:7029392"
    ],
    "placetype": [
      "aat:300008761"
    ],
    "id": 2228959,
    "name:xx": "Cedar Hollow"
  }
}
