{
  "type": "FeatureCollection",
  "features": [
    {
      "geometry": {
        "type": "Point",
        "coordinates": [
          -70.533333,
          -32.316667
        ]
      },
      "type": "Feature",
      "properties": {
        "hierarchy": [
          "tgn:7288920",
          "tgn:1001768",
          "tgn:1000049",
          "tgn:1000002",
          "tgn:7029392"
        ],
        "placetype": [
          "aat:300008699"
        ],
        "id": 7288920,
        "name:xx": "Laguna, Quebrada de"
      }
    },
    {
      "geometry": {
        "type": "Point",
        "coordinates": [
          -70.45,
          -32.15
        ]
      },
      "type": "Feature",
      "properties": {
        "hierarchy": [
          "tgn:7288921",
          "tgn:1001657",
          "tgn:1000049",
          "tgn:1000002",
          "tgn:7029392"
        ],
        "placetype": [
          "aat:300259572"
        ],
        "id": 7288921,
        "name:xx": "Laguna, Portillo de la"
      }
    },
    {
      "geometry": {
        "type": "Point",
        "coordinates": [
          -70.433333,
          -31.116667
        ]
      },
      "type": "Feature",
      "properties": {
        "hierarchy": [
          "tgn:7288922",
          "tgn:1001657",
          "tgn:1000049",
          "tgn:1000002",
          "tgn:7029392"
        ],
        "placetype": [
          "aat:300259572"
        ],
        "id": 7288922,
        "name:xx": "Laguna de la Overa Primero, Paso de la"
      }
    },
    {
      "geometry": {
        "type": "Point",
        "coordinates": [
          -73.666667,
          -41.066667
        ]
      },
      "type": "Feature",
      "properties": {
        "hierarchy": [
          "tgn:7288923",
          "tgn:1001699",
          "tgn:1000049",
          "tgn:1000002",
          "tgn:7029392"
        ],
        "placetype": [
          "aat:300008699"
        ],
        "id": 7288923,
        "name:xx": "Laguna, Estero de la"
      }
    },
    {
      "geometry": {
        "type": "Point",
        "coordinates": [
          -72.066667,
          -35.083333
        ]
      },
      "type": "Feature",
      "properties": {
        "hierarchy": [
          "tgn:7288924",
          "tgn:1001705",
          "tgn:1000049",
          "tgn:1000002",
          "tgn:7029392"
        ],
        "placetype": [
          "aat:300008699"
        ],
        "id": 7288924,
        "name:xx": "Laguna, Estero"
      }
    },
    {
      "geometry": {
        "type": "Point",
        "coordinates": [
          -70.1,
          -30.25
        ]
      },
      "type": "Feature",
      "properties": {
        "hierarchy": [
          "tgn:7288925",
          "tgn:1001657",
          "tgn:1000049",
          "tgn:1000002",
          "tgn:7029392"
        ],
        "placetype": [
          "aat:300008795"
        ],
        "id": 7288925,
        "name:xx": "Laguna, Cerro de la"
      }
    },
    {
      "geometry": {
        "type": "Point",
        "coordinates": [
          -69.266667,
          -27.516667
        ]
      },
      "type": "Feature",
      "properties": {
        "hierarchy": [
          "tgn:7288926",
          "tgn:1001630",
          "tgn:1000049",
          "tgn:1000002",
          "tgn:7029392"
        ],
        "placetype": [
          "aat:300008795"
        ],
        "id": 7288926,
        "name:xx": "Laguna, Cerro de la"
      }
    },
    {
      "geometry": {
        "type": "Point",
        "coordinates": [
          -70.016667,
          -30.2
        ]
      },
      "type": "Feature",
      "properties": {
        "hierarchy": [
          "tgn:7288927",
          "tgn:1001657",
          "tgn:1000049",
          "tgn:1000002",
          "tgn:7029392"
        ],
        "placetype": [
          "aat:300008795"
        ],
        "id": 7288927,
        "name:xx": "Laguna, Cerro"
      }
    },
    {
      "geometry": {
        "type": "Point",
        "coordinates": [
          -68.566667,
          -20.766667
        ]
      },
      "type": "Feature",
      "properties": {
        "hierarchy": [
          "tgn:7288928",
          "tgn:7002464",
          "tgn:1000049",
          "tgn:1000002",
          "tgn:7029392"
        ],
        "placetype": [
          "aat:300008795"
        ],
        "id": 7288928,
        "name:xx": "La Laguna, Cerro"
      }
    },
    {
      "geometry": {
        "type": "Point",
        "coordinates": [
          -68.683333,
          -20.666667
        ]
      },
      "type": "Feature",
      "properties": {
        "hierarchy": [
          "tgn:7288929",
          "tgn:7002464",
          "tgn:1000049",
          "tgn:1000002",
          "tgn:7029392"
        ],
        "placetype": [
          "aat:300008777"
        ],
        "id": 7288929,
        "name:xx": "Laguna, Cerro"
      }
    }
  ]
}
