{
  "geometry": {
    "type": "Point",
    "coordinates": [
      -113.8667,
      42.7667
    ]
  },
  "type": "Feature",
  "properties": {
    "hierarchy": [
      "tgn:2437159",
      "tgn:1000001",
      "tgn:7012149",
      "tgn:2000483",
      "tgn:7007250",
      "tgn:7029392"
    ],
    "placetype": [
      "aat:300008746"
    ],
    "id": 2437159,
    "name:xx": "Kimama Butte Cave"
  }
}
