{
  "geometry": {
    "type": "Point",
    "coordinates": [
      -83.4167,
      33.6833
    ]
  },
  "type": "Feature",
  "properties": {
    "hierarchy": [
      "tgn:2021944",
      "tgn:1000001",
      "tgn:7012149",
      "tgn:2000395",
      "tgn:7007248",
      "tgn:7029392"
    ],
    "placetype": [
      "aat:300008347"
    ],
    "id": 2021944,
    "name:xx": "Apalachee"
  }
}
