{
  "geometry": {
    "type": "Point",
    "coordinates": [
      -108.1167,
      39.6167
    ]
  },
  "type": "Feature",
  "properties": {
    "hierarchy": [
      "tgn:2277472",
      "tgn:1000001",
      "tgn:7012149",
      "tgn:2000214",
      "tgn:7007158",
      "tgn:7029392"
    ],
    "placetype": [
      "aat:300266640"
    ],
    "id": 2277472,
    "name:xx": "Davis Point"
  }
}
