{
  "geometry": {
    "type": "Point",
    "coordinates": [
      -103.7667,
      39.65
    ]
  },
  "type": "Feature",
  "properties": {
    "hierarchy": [
      "tgn:2425859",
      "tgn:2000194",
      "tgn:1000001",
      "tgn:7012149",
      "tgn:7007158",
      "tgn:7029392"
    ],
    "placetype": [
      "aat:300006191"
    ],
    "id": 2425859,
    "name:xx": "Jolly John Reservoir"
  }
}
