{
  "geometry": {
    "type": "Point",
    "coordinates": [
      77.93165,
      30.32547
    ]
  },
  "type": "Feature",
  "properties": {
    "hierarchy": [
      "tgn:7591952",
      "tgn:1000004",
      "tgn:7000198",
      "tgn:7031786",
      "tgn:7029392"
    ],
    "placetype": [
      "aat:300008347"
    ],
    "name:en": "Motīpur",
    "id": 7591952
  }
}
