{
  "geometry": {
    "type": "Point",
    "coordinates": [
      -72.7667,
      44.3667
    ]
  },
  "type": "Feature",
  "properties": {
    "hierarchy": [
      "tgn:2753214",
      "tgn:1000001",
      "tgn:2002135",
      "tgn:7012149",
      "tgn:7007828",
      "tgn:7029392"
    ],
    "placetype": [
      "aat:300006191"
    ],
    "id": 2753214,
    "name:xx": "Waterbury Reservoir"
  }
}
