{
  "geometry": {
    "type": "Point",
    "coordinates": [
      -113.4333,
      46.7667
    ]
  },
  "type": "Feature",
  "properties": {
    "hierarchy": [
      "tgn:2714821",
      "tgn:1000001",
      "tgn:7012149",
      "tgn:7007524",
      "tgn:7029392"
    ],
    "placetype": [
      "aat:300008706"
    ],
    "id": 2714821,
    "name:xx": "Tenmile Creek"
  }
}
