{
  "geometry": {
    "type": "Point",
    "coordinates": [
      34.6833,
      -21.3833
    ]
  },
  "type": "Feature",
  "properties": {
    "hierarchy": [
      "tgn:1091550",
      "tgn:7001242",
      "tgn:1000869",
      "tgn:1000180",
      "tgn:7029392"
    ],
    "placetype": [
      "aat:300008347"
    ],
    "id": 1091550,
    "name:xx": "Luido"
  }
}
