{
  "geometry": {
    "type": "Point",
    "coordinates": [
      31.62487,
      30.104998
    ]
  },
  "type": "Feature",
  "properties": {
    "hierarchy": [
      "tgn:7531614",
      "tgn:7001242",
      "tgn:7016833",
      "tgn:7029392"
    ],
    "placetype": [
      "aat:300008777"
    ],
    "id": 7531614,
    "name:xx": "Qiţţah, Tall al"
  }
}
