{
  "type": "FeatureCollection",
  "features": [
    {
      "geometry": {
        "type": "Point",
        "coordinates": [
          -82.2,
          33.65
        ]
      },
      "type": "Feature",
      "properties": {
        "hierarchy": [
          "tgn:2416301",
          "tgn:1000001",
          "tgn:7012149",
          "tgn:7029392"
        ],
        "placetype": [
          "aat:300006191"
        ],
        "id": 2416301,
        "name:xx": "J. Strom Thurmond Reservoir"
      }
    },
    {
      "geometry": {
        "type": "Point",
        "coordinates": [
          -106.8,
          39.1833
        ]
      },
      "type": "Feature",
      "properties": {
        "hierarchy": [
          "tgn:2416302",
          "tgn:1000001",
          "tgn:7012149",
          "tgn:7007158",
          "tgn:2000240",
          "tgn:7029392"
        ],
        "placetype": [
          "aat:300000390"
        ],
        "id": 2416302,
        "name:xx": "J. c. Johnson Tunnel"
      }
    },
    {
      "geometry": {
        "type": "Point",
        "coordinates": [
          -110.7167,
          34.3333
        ]
      },
      "type": "Feature",
      "properties": {
        "hierarchy": [
          "tgn:2416303",
          "tgn:1000001",
          "tgn:7006451",
          "tgn:7012149",
          "tgn:2000099",
          "tgn:7029392"
        ],
        "placetype": [
          "aat:300006191"
        ],
        "id": 2416303,
        "name:xx": "J. J. Tank"
      }
    },
    {
      "geometry": {
        "type": "Point",
        "coordinates": [
          -91.4167,
          38
        ]
      },
      "type": "Feature",
      "properties": {
        "hierarchy": [
          "tgn:2416304",
          "tgn:1000001",
          "tgn:7012149",
          "tgn:2001190",
          "tgn:7007523",
          "tgn:7029392"
        ],
        "placetype": [
          "aat:300000390"
        ],
        "id": 2416304,
        "name:xx": "J. P. Card and Companys Iron Bank"
      }
    },
    {
      "geometry": {
        "type": "Point",
        "coordinates": [
          -90.5667,
          37.35
        ]
      },
      "type": "Feature",
      "properties": {
        "hierarchy": [
          "tgn:2416305",
          "tgn:1000001",
          "tgn:7012149",
          "tgn:2001207",
          "tgn:7007523",
          "tgn:7029392"
        ],
        "placetype": [
          "aat:300000390"
        ],
        "id": 2416305,
        "name:xx": "J. S. Benson Porphyry Quarry"
      }
    },
    {
      "geometry": {
        "type": "Point",
        "coordinates": [
          -118.3167,
          44.1167
        ]
      },
      "type": "Feature",
      "properties": {
        "hierarchy": [
          "tgn:2416306",
          "tgn:1000001",
          "tgn:7012149",
          "tgn:2001708",
          "tgn:7007708",
          "tgn:7029392"
        ],
        "placetype": [
          "aat:300006191"
        ],
        "id": 2416306,
        "name:xx": "JB Reservoir"
      }
    },
    {
      "geometry": {
        "type": "Point",
        "coordinates": [
          -113.9833,
          40.35
        ]
      },
      "type": "Feature",
      "properties": {
        "hierarchy": [
          "tgn:2416307",
          "tgn:1000001",
          "tgn:7012149",
          "tgn:2002123",
          "tgn:7007827",
          "tgn:7029392"
        ],
        "placetype": [
          "aat:300006191"
        ],
        "id": 2416307,
        "name:xx": "JB Reservoir"
      }
    },
    {
      "geometry": {
        "type": "Point",
        "coordinates": [
          -105.5833,
          31.2
        ]
      },
      "type": "Feature",
      "properties": {
        "hierarchy": [
          "tgn:2416308",
          "tgn:1000001",
          "tgn:7012149",
          "tgn:2002005",
          "tgn:7007826",
          "tgn:7029392"
        ],
        "placetype": [
          "aat:300006191"
        ],
        "id": 2416308,
        "name:xx": "JB Tank"
      }
    },
    {
      "geometry": {
        "type": "Point",
        "coordinates": [
          -109.1333,
          33.8
        ]
      },
      "type": "Feature",
      "properties": {
        "hierarchy": [
          "tgn:2416309",
          "tgn:2000090",
          "tgn:1000001",
          "tgn:7006451",
          "tgn:7012149",
          "tgn:7029392"
        ],
        "placetype": [
          "aat:300006191"
        ],
        "id": 2416309,
        "name:xx": "JC Tank"
      }
    }
  ]
}
