{
  "geometry": {
    "type": "Point",
    "coordinates": [
      21.55,
      9.7667
    ]
  },
  "type": "Feature",
  "properties": {
    "hierarchy": [
      "tgn:1088395",
      "tgn:7001242",
      "tgn:1001038",
      "tgn:1000155",
      "tgn:7029392"
    ],
    "placetype": [
      "aat:300008347"
    ],
    "id": 1088395,
    "name:xx": "Mélé"
  }
}
