{
  "geometry": {
    "type": "Point",
    "coordinates": [
      -109.1833,
      33.0667
    ]
  },
  "type": "Feature",
  "properties": {
    "hierarchy": [
      "tgn:2200016",
      "tgn:1000001",
      "tgn:7006451",
      "tgn:2000095",
      "tgn:7012149",
      "tgn:7029392"
    ],
    "placetype": [
      "aat:300006191"
    ],
    "id": 2200016,
    "name:xx": "Brushy Canyon Tank"
  }
}
