{
  "geometry": {
    "type": "Point",
    "coordinates": [
      14.9667,
      -5.2667
    ]
  },
  "type": "Feature",
  "properties": {
    "hierarchy": [
      "tgn:1089315",
      "tgn:1001144",
      "tgn:7001242",
      "tgn:1000159",
      "tgn:7029392"
    ],
    "placetype": [
      "aat:300008347"
    ],
    "id": 1089315,
    "name:xx": "Marchal"
  }
}
