{
  "geometry": {
    "type": "Point",
    "coordinates": [
      -85.8833,
      37.8167
    ]
  },
  "type": "Feature",
  "properties": {
    "hierarchy": [
      "tgn:2473648",
      "tgn:1000001",
      "tgn:7012149",
      "tgn:2000796",
      "tgn:7007255",
      "tgn:7029392"
    ],
    "placetype": [
      "aat:300006191"
    ],
    "id": 2473648,
    "name:xx": "Lower Douglas Lake"
  }
}
