{
  "geometry": {
    "type": "Point",
    "coordinates": [
      32.3833,
      34.8833
    ]
  },
  "type": "Feature",
  "properties": {
    "hierarchy": [
      "tgn:1074262",
      "tgn:7000840",
      "tgn:1000004",
      "tgn:1000112",
      "tgn:7029392"
    ],
    "placetype": [
      "aat:300008347"
    ],
    "id": 1074262,
    "name:xx": "Peyia"
  }
}
