{
  "geometry": {
    "type": "Point",
    "coordinates": [
      -87.6833,
      35.4667
    ]
  },
  "type": "Feature",
  "properties": {
    "hierarchy": [
      "tgn:2706285",
      "tgn:1000001",
      "tgn:7012149",
      "tgn:2001927",
      "tgn:7007825",
      "tgn:7029392"
    ],
    "placetype": [
      "aat:300008761"
    ],
    "id": 2706285,
    "name:xx": "Swamp Hollow"
  }
}
