{
  "geometry": {
    "type": "Point",
    "coordinates": [
      11.45,
      4.3667
    ]
  },
  "type": "Feature",
  "properties": {
    "hierarchy": [
      "tgn:1088275",
      "tgn:1001189",
      "tgn:7001242",
      "tgn:1000153",
      "tgn:7029392"
    ],
    "placetype": [
      "aat:300008347"
    ],
    "id": 1088275,
    "name:xx": "Saa"
  }
}
