{
  "geometry": {
    "type": "Point",
    "coordinates": [
      -77.8167,
      37.25
    ]
  },
  "type": "Feature",
  "properties": {
    "hierarchy": [
      "tgn:2401323",
      "tgn:2002139",
      "tgn:1000001",
      "tgn:7012149",
      "tgn:7007919",
      "tgn:7029392"
    ],
    "placetype": [
      "aat:300008699"
    ],
    "id": 2401323,
    "name:xx": "Horsepen Branch"
  }
}
