{
  "type": "FeatureCollection",
  "features": [
    {
      "geometry": {
        "type": "Point",
        "coordinates": [
          -99.133333,
          26.233333
        ]
      },
      "type": "Feature",
      "properties": {
        "hierarchy": [
          "tgn:7353190",
          "tgn:1000001",
          "tgn:7005597",
          "tgn:7005560",
          "tgn:7029392"
        ],
        "placetype": [
          "aat:300008347"
        ],
        "id": 7353190,
        "name:xx": "Buenavista"
      }
    },
    {
      "geometry": {
        "type": "Point",
        "coordinates": [
          -99.5,
          26.216667
        ]
      },
      "type": "Feature",
      "properties": {
        "hierarchy": [
          "tgn:7353191",
          "tgn:1000001",
          "tgn:7005589",
          "tgn:7005560",
          "tgn:7029392"
        ],
        "placetype": [
          "aat:300008347"
        ],
        "id": 7353191,
        "name:xx": "Buenavista"
      }
    },
    {
      "geometry": {
        "type": "Point",
        "coordinates": [
          -108.783333,
          26.1
        ]
      },
      "type": "Feature",
      "properties": {
        "hierarchy": [
          "tgn:7353192",
          "tgn:1000001",
          "tgn:7005595",
          "tgn:7005560",
          "tgn:7029392"
        ],
        "placetype": [
          "aat:300008347"
        ],
        "id": 7353192,
        "name:xx": "Buena Vista"
      }
    },
    {
      "geometry": {
        "type": "Point",
        "coordinates": [
          -98.916667,
          25.983333
        ]
      },
      "type": "Feature",
      "properties": {
        "hierarchy": [
          "tgn:7353193",
          "tgn:1000001",
          "tgn:7005589",
          "tgn:7005560",
          "tgn:7029392"
        ],
        "placetype": [
          "aat:300008347"
        ],
        "id": 7353193,
        "name:xx": "Buenavista"
      }
    },
    {
      "geometry": {
        "type": "Point",
        "coordinates": [
          -97.983333,
          25.983333
        ]
      },
      "type": "Feature",
      "properties": {
        "hierarchy": [
          "tgn:7353194",
          "tgn:1000001",
          "tgn:7005597",
          "tgn:7005560",
          "tgn:7029392"
        ],
        "placetype": [
          "aat:300008347"
        ],
        "id": 7353194,
        "name:xx": "Buenavista"
      }
    },
    {
      "geometry": {
        "type": "Point",
        "coordinates": [
          -108.116667,
          25.85
        ]
      },
      "type": "Feature",
      "properties": {
        "hierarchy": [
          "tgn:7353195",
          "tgn:1000001",
          "tgn:7005595",
          "tgn:7005560",
          "tgn:7029392"
        ],
        "placetype": [
          "aat:300008347"
        ],
        "id": 7353195,
        "name:xx": "Buenavista"
      }
    },
    {
      "geometry": {
        "type": "Point",
        "coordinates": [
          -103.3,
          25.8
        ]
      },
      "type": "Feature",
      "properties": {
        "hierarchy": [
          "tgn:7353196",
          "tgn:1001853",
          "tgn:1000001",
          "tgn:7005560",
          "tgn:7029392"
        ],
        "placetype": [
          "aat:300008347"
        ],
        "id": 7353196,
        "name:xx": "Buenavista"
      }
    },
    {
      "geometry": {
        "type": "Point",
        "coordinates": [
          -106.816667,
          25.75
        ]
      },
      "type": "Feature",
      "properties": {
        "hierarchy": [
          "tgn:7353197",
          "tgn:7005581",
          "tgn:1000001",
          "tgn:7005560",
          "tgn:7029392"
        ],
        "placetype": [
          "aat:300008347"
        ],
        "id": 7353197,
        "name:xx": "Buenavista"
      }
    },
    {
      "geometry": {
        "type": "Point",
        "coordinates": [
          -112.083333,
          24.583333
        ]
      },
      "type": "Feature",
      "properties": {
        "hierarchy": [
          "tgn:7353198",
          "tgn:1001836",
          "tgn:1000001",
          "tgn:7005560",
          "tgn:7029392"
        ],
        "placetype": [
          "aat:300386846"
        ],
        "id": 7353198,
        "name:xx": "Belcher, Punta"
      }
    },
    {
      "geometry": {
        "type": "Point",
        "coordinates": [
          -99.783333,
          26.616667
        ]
      },
      "type": "Feature",
      "properties": {
        "hierarchy": [
          "tgn:7353199",
          "tgn:1000001",
          "tgn:7005589",
          "tgn:7005560",
          "tgn:7029392"
        ],
        "placetype": [
          "aat:300000241"
        ],
        "id": 7353199,
        "name:xx": "Rancho Belcebú"
      }
    }
  ]
}
