{
  "geometry": {
    "type": "Point",
    "coordinates": [
      -109.3167,
      43.5833
    ]
  },
  "type": "Feature",
  "properties": {
    "hierarchy": [
      "tgn:2219759",
      "tgn:1000001",
      "tgn:7012149",
      "tgn:2002371",
      "tgn:7007923",
      "tgn:7029392"
    ],
    "placetype": [
      "aat:300008697"
    ],
    "id": 2219759,
    "name:xx": "Cantell Spring"
  }
}
