{
  "geometry": {
    "type": "Point",
    "coordinates": [
      -80.2667,
      36.65
    ]
  },
  "type": "Feature",
  "properties": {
    "hierarchy": [
      "tgn:2217418",
      "tgn:1000001",
      "tgn:7012149",
      "tgn:2002179",
      "tgn:7007919",
      "tgn:7029392"
    ],
    "placetype": [
      "aat:300008699"
    ],
    "id": 2217418,
    "name:xx": "Campbell Branch"
  }
}
