{
  "geometry": {
    "type": "Point",
    "coordinates": [
      23.6667,
      63.2167
    ]
  },
  "type": "Feature",
  "properties": {
    "hierarchy": [
      "tgn:1031426",
      "tgn:7024077",
      "tgn:1000003",
      "tgn:1000069",
      "tgn:7029392"
    ],
    "placetype": [
      "aat:300008347"
    ],
    "id": 1031426,
    "name:xx": "Lappajärvi"
  }
}
