{
  "geometry": {
    "type": "Point",
    "coordinates": [
      -75.1833,
      41.8333
    ]
  },
  "type": "Feature",
  "properties": {
    "hierarchy": [
      "tgn:2763003",
      "tgn:1000001",
      "tgn:7012149",
      "tgn:1003008",
      "tgn:7007710",
      "tgn:7029392"
    ],
    "placetype": [
      "aat:300008699"
    ],
    "id": 2763003,
    "name:xx": "Weston Brook"
  }
}
