{
  "geometry": {
    "type": "Point",
    "coordinates": [
      -85.2833,
      37.5333
    ]
  },
  "type": "Feature",
  "properties": {
    "hierarchy": [
      "tgn:2203206",
      "tgn:1000001",
      "tgn:7012149",
      "tgn:2000822",
      "tgn:7007255",
      "tgn:7029392"
    ],
    "placetype": [
      "aat:300008706"
    ],
    "id": 2203206,
    "name:xx": "Buckhorn Creek"
  }
}
