{
  "geometry": {
    "type": "Point",
    "coordinates": [
      -111.0833,
      46.3167
    ]
  },
  "type": "Feature",
  "properties": {
    "hierarchy": [
      "tgn:2511209",
      "tgn:1000001",
      "tgn:7012149",
      "tgn:2001289",
      "tgn:7007524",
      "tgn:7029392"
    ],
    "placetype": [
      "aat:300008706"
    ],
    "id": 2511209,
    "name:xx": "Mike Day Creek"
  }
}
