{
  "geometry": {
    "type": "Point",
    "coordinates": [
      -95.15,
      42.8167
    ]
  },
  "type": "Feature",
  "properties": {
    "hierarchy": [
      "tgn:2035525",
      "tgn:1000001",
      "tgn:2000571",
      "tgn:7012149",
      "tgn:7007253",
      "tgn:7029392"
    ],
    "placetype": [
      "aat:300008347"
    ],
    "id": 2035525,
    "name:xx": "Rembrandt"
  }
}
