{
  "type": "FeatureCollection",
  "features": [
    {
      "geometry": {
        "type": "Point",
        "coordinates": [
          -0.8,
          50.833333
        ]
      },
      "type": "Feature",
      "properties": {
        "hierarchy": [
          "tgn:7449710",
          "tgn:7002445",
          "tgn:1000003",
          "tgn:7008134",
          "tgn:7008591",
          "tgn:7029392"
        ],
        "placetype": [
          "aat:300008347"
        ],
        "name:en": "Fishbourne",
        "id": 7449710
      }
    },
    {
      "geometry": {
        "type": "Point",
        "coordinates": [
          -4.116667,
          56.883333
        ]
      },
      "type": "Feature",
      "properties": {
        "hierarchy": [
          "tgn:7449712",
          "tgn:7002444",
          "tgn:1000003",
          "tgn:7019152",
          "tgn:7008591",
          "tgn:7029392"
        ],
        "placetype": [
          "aat:300008699"
        ],
        "name:en": "Edendon Water",
        "id": 7449712
      }
    },
    {
      "geometry": {
        "type": "Point",
        "coordinates": [
          -2.666667,
          54.7
        ]
      },
      "type": "Feature",
      "properties": {
        "hierarchy": [
          "tgn:7449714",
          "tgn:7002445",
          "tgn:1000003",
          "tgn:7008117",
          "tgn:7008591",
          "tgn:7029392"
        ],
        "placetype": [
          "aat:300008761"
        ],
        "name:en": "Eden, Vale of",
        "id": 7449714
      }
    },
    {
      "geometry": {
        "type": "Point",
        "coordinates": [
          0.433333,
          51.216667
        ]
      },
      "type": "Feature",
      "properties": {
        "hierarchy": [
          "tgn:7449717",
          "tgn:7002445",
          "tgn:1000003",
          "tgn:7008153",
          "tgn:7008591",
          "tgn:7029392"
        ],
        "placetype": [
          "aat:300008699"
        ],
        "name:en": "Eden, River",
        "id": 7449717
      }
    }
  ]
}
