{
  "type": "FeatureCollection",
  "features": [
    {
      "geometry": {
        "type": "Point",
        "coordinates": [
          76.493284,
          26.6643
        ]
      },
      "type": "Feature",
      "properties": {
        "hierarchy": [
          "tgn:7545320",
          "tgn:1000004",
          "tgn:7000198",
          "tgn:7016788",
          "tgn:7029392"
        ],
        "placetype": [
          "aat:300008347"
        ],
        "name:en": "Amārwā",
        "id": 7545320
      }
    },
    {
      "geometry": {
        "type": "Point",
        "coordinates": [
          75.832002,
          27.371611
        ]
      },
      "type": "Feature",
      "properties": {
        "hierarchy": [
          "tgn:7545321",
          "tgn:1000004",
          "tgn:7000198",
          "tgn:7016788",
          "tgn:7029392"
        ],
        "placetype": [
          "aat:300008347"
        ],
        "name:en": "Amarsar",
        "id": 7545321
      }
    },
    {
      "geometry": {
        "type": "Point",
        "coordinates": [
          72.851615,
          28.257732
        ]
      },
      "type": "Feature",
      "properties": {
        "hierarchy": [
          "tgn:7545322",
          "tgn:1000004",
          "tgn:7000198",
          "tgn:7016788",
          "tgn:7029392"
        ],
        "placetype": [
          "aat:300008347"
        ],
        "name:en": "Amarpura",
        "id": 7545322
      }
    },
    {
      "geometry": {
        "type": "Point",
        "coordinates": [
          74.11727,
          26.362439
        ]
      },
      "type": "Feature",
      "properties": {
        "hierarchy": [
          "tgn:7545323",
          "tgn:1000004",
          "tgn:7000198",
          "tgn:7016788",
          "tgn:7029392"
        ],
        "placetype": [
          "aat:300008347"
        ],
        "name:en": "Amarpura",
        "id": 7545323
      }
    },
    {
      "geometry": {
        "type": "Point",
        "coordinates": [
          84.100998,
          26.097093
        ]
      },
      "type": "Feature",
      "properties": {
        "hierarchy": [
          "tgn:7545324",
          "tgn:1000004",
          "tgn:7000198",
          "tgn:7016722",
          "tgn:7029392"
        ],
        "placetype": [
          "aat:300008347"
        ],
        "name:en": "Amarpur",
        "id": 7545324
      }
    },
    {
      "geometry": {
        "type": "Point",
        "coordinates": [
          86.902473,
          25.039667
        ]
      },
      "type": "Feature",
      "properties": {
        "hierarchy": [
          "tgn:7545325",
          "tgn:1000004",
          "tgn:1001842",
          "tgn:7000198",
          "tgn:7029392"
        ],
        "placetype": [
          "aat:300008347"
        ],
        "name:en": "Amarpur",
        "id": 7545325
      }
    },
    {
      "geometry": {
        "type": "Point",
        "coordinates": [
          80.899242,
          23.957469
        ]
      },
      "type": "Feature",
      "properties": {
        "hierarchy": [
          "tgn:7545326",
          "tgn:1000004",
          "tgn:7000198",
          "tgn:1001894",
          "tgn:7029392"
        ],
        "placetype": [
          "aat:300008347"
        ],
        "name:en": "Amarpur",
        "id": 7545326
      }
    },
    {
      "geometry": {
        "type": "Point",
        "coordinates": [
          91.658791,
          23.525696
        ]
      },
      "type": "Feature",
      "properties": {
        "hierarchy": [
          "tgn:7545327",
          "tgn:1000004",
          "tgn:7000198",
          "tgn:1001578",
          "tgn:7029392"
        ],
        "placetype": [
          "aat:300008347"
        ],
        "name:en": "Amarpur",
        "id": 7545327
      }
    },
    {
      "geometry": {
        "type": "Point",
        "coordinates": [
          80.96153,
          22.788586
        ]
      },
      "type": "Feature",
      "properties": {
        "hierarchy": [
          "tgn:7545329",
          "tgn:1000004",
          "tgn:7000198",
          "tgn:1001894",
          "tgn:7029392"
        ],
        "placetype": [
          "aat:300008347"
        ],
        "name:en": "Amarpur",
        "id": 7545329
      }
    }
  ]
}
