{
  "geometry": {
    "type": "Point",
    "coordinates": [
      150.7833,
      -34.1667
    ]
  },
  "type": "Feature",
  "properties": {
    "hierarchy": [
      "tgn:1100919",
      "tgn:7000490",
      "tgn:1000006",
      "tgn:7001828",
      "tgn:7029392"
    ],
    "placetype": [
      "aat:300006958"
    ],
    "id": 1100919,
    "name:xx": "Hume and Hovell Memorial"
  }
}
