{
  "geometry": {
    "type": "Point",
    "coordinates": [
      -114.8333,
      32.8167
    ]
  },
  "type": "Feature",
  "properties": {
    "hierarchy": [
      "tgn:2013077",
      "tgn:1000001",
      "tgn:7012149",
      "tgn:2000182",
      "tgn:7007157",
      "tgn:7029392"
    ],
    "placetype": [
      "aat:300387016"
    ],
    "id": 2013077,
    "name:xx": "Ogilby"
  }
}
