{
  "geometry": {
    "type": "Point",
    "coordinates": [
      -115.4333,
      34.9833
    ]
  },
  "type": "Feature",
  "properties": {
    "hierarchy": [
      "tgn:2764898",
      "tgn:1000001",
      "tgn:7012149",
      "tgn:7007157",
      "tgn:1002857",
      "tgn:7029392"
    ],
    "placetype": [
      "aat:300008697"
    ],
    "id": 2764898,
    "name:xx": "Whiskey Spring"
  }
}
