{
  "type": "FeatureCollection",
  "features": [
    {
      "geometry": {
        "type": "Point",
        "coordinates": [
          -105.25,
          42.1
        ]
      },
      "type": "Feature",
      "properties": {
        "hierarchy": [
          "tgn:2300200",
          "tgn:1000001",
          "tgn:7012149",
          "tgn:2002380",
          "tgn:7007923",
          "tgn:7029392"
        ],
        "placetype": [
          "aat:300008706"
        ],
        "id": 2300200,
        "name:xx": "Dugout Creek"
      }
    },
    {
      "geometry": {
        "type": "Point",
        "coordinates": [
          -105.35,
          43.3833
        ]
      },
      "type": "Feature",
      "properties": {
        "hierarchy": [
          "tgn:2300201",
          "tgn:1000001",
          "tgn:2002369",
          "tgn:7012149",
          "tgn:7007923",
          "tgn:7029392"
        ],
        "placetype": [
          "aat:300008706"
        ],
        "id": 2300201,
        "name:xx": "Dugout Creek"
      }
    },
    {
      "geometry": {
        "type": "Point",
        "coordinates": [
          -106.4333,
          43.3333
        ]
      },
      "type": "Feature",
      "properties": {
        "hierarchy": [
          "tgn:2300202",
          "tgn:1000001",
          "tgn:7012149",
          "tgn:7007923",
          "tgn:7029392"
        ],
        "placetype": [
          "aat:300008706"
        ],
        "id": 2300202,
        "name:xx": "Dugout Creek"
      }
    },
    {
      "geometry": {
        "type": "Point",
        "coordinates": [
          -109.3667,
          43.7167
        ]
      },
      "type": "Feature",
      "properties": {
        "hierarchy": [
          "tgn:2300203",
          "tgn:1000001",
          "tgn:7012149",
          "tgn:2002371",
          "tgn:7007923",
          "tgn:7029392"
        ],
        "placetype": [
          "aat:300008706"
        ],
        "id": 2300203,
        "name:xx": "Dugout Creek"
      }
    },
    {
      "geometry": {
        "type": "Point",
        "coordinates": [
          -108.2833,
          40.8333
        ]
      },
      "type": "Feature",
      "properties": {
        "hierarchy": [
          "tgn:2300204",
          "tgn:1000001",
          "tgn:7012149",
          "tgn:2000232",
          "tgn:7007158",
          "tgn:7029392"
        ],
        "placetype": [
          "aat:300008761"
        ],
        "id": 2300204,
        "name:xx": "Dugout Draw"
      }
    },
    {
      "geometry": {
        "type": "Point",
        "coordinates": [
          -101.7167,
          43.8833
        ]
      },
      "type": "Feature",
      "properties": {
        "hierarchy": [
          "tgn:2300205",
          "tgn:1000001",
          "tgn:2001805",
          "tgn:7012149",
          "tgn:7007713",
          "tgn:7029392"
        ],
        "placetype": [
          "aat:300008761"
        ],
        "id": 2300205,
        "name:xx": "Dugout Draw"
      }
    },
    {
      "geometry": {
        "type": "Point",
        "coordinates": [
          -103.1667,
          29.2667
        ]
      },
      "type": "Feature",
      "properties": {
        "hierarchy": [
          "tgn:2300206",
          "tgn:1000001",
          "tgn:2001945",
          "tgn:7012149",
          "tgn:7007826",
          "tgn:7029392"
        ],
        "placetype": [
          "aat:300008761"
        ],
        "id": 2300206,
        "name:xx": "Dugout Draw"
      }
    },
    {
      "geometry": {
        "type": "Point",
        "coordinates": [
          -101.7167,
          35.0167
        ]
      },
      "type": "Feature",
      "properties": {
        "hierarchy": [
          "tgn:2300207",
          "tgn:1000001",
          "tgn:7012149",
          "tgn:2002058",
          "tgn:7007826",
          "tgn:7029392"
        ],
        "placetype": [
          "aat:300008761"
        ],
        "id": 2300207,
        "name:xx": "Dugout Draw"
      }
    },
    {
      "geometry": {
        "type": "Point",
        "coordinates": [
          -108.7833,
          43.8
        ]
      },
      "type": "Feature",
      "properties": {
        "hierarchy": [
          "tgn:2300208",
          "tgn:1000001",
          "tgn:7012149",
          "tgn:2002373",
          "tgn:7007923",
          "tgn:7029392"
        ],
        "placetype": [
          "aat:300008761"
        ],
        "id": 2300208,
        "name:xx": "Dugout Draw"
      }
    },
    {
      "geometry": {
        "type": "Point",
        "coordinates": [
          -105.3,
          44.0667
        ]
      },
      "type": "Feature",
      "properties": {
        "hierarchy": [
          "tgn:2300209",
          "tgn:1000001",
          "tgn:2002367",
          "tgn:7012149",
          "tgn:7007923",
          "tgn:7029392"
        ],
        "placetype": [
          "aat:300008761"
        ],
        "id": 2300209,
        "name:xx": "Dugout Draw"
      }
    }
  ]
}
