{
  "geometry": {
    "type": "Point",
    "coordinates": [
      -116.1667,
      38.0167
    ]
  },
  "type": "Feature",
  "properties": {
    "hierarchy": [
      "tgn:2615572",
      "tgn:1000001",
      "tgn:2001418",
      "tgn:7012149",
      "tgn:7007526",
      "tgn:7029392"
    ],
    "placetype": [
      "aat:300008347"
    ],
    "id": 2615572,
    "name:xx": "Reveille"
  }
}
