{
  "geometry": {
    "type": "Point",
    "coordinates": [
      4.95,
      52.116667
    ]
  },
  "type": "Feature",
  "properties": {
    "hierarchy": [
      "tgn:7262331",
      "tgn:1000003",
      "tgn:7003627",
      "tgn:7016845",
      "tgn:7029392"
    ],
    "placetype": [
      "aat:300008347"
    ],
    "name:nl": "Gerverskop",
    "id": 7262331
  }
}
