{
  "geometry": {
    "type": "Point",
    "coordinates": [
      -105.6333,
      40.4667
    ]
  },
  "type": "Feature",
  "properties": {
    "hierarchy": [
      "tgn:2621514",
      "tgn:1000001",
      "tgn:7012149",
      "tgn:2000226",
      "tgn:7007158",
      "tgn:7029392"
    ],
    "placetype": [
      "aat:300008707"
    ],
    "id": 2621514,
    "name:xx": "Roaring River"
  }
}
