{
  "type": "FeatureCollection",
  "features": [
    {
      "geometry": {
        "type": "Point",
        "coordinates": [
          -83.1667,
          42.4667
        ]
      },
      "type": "Feature",
      "properties": {
        "hierarchy": [
          "tgn:2052240",
          "tgn:1000001",
          "tgn:7012149",
          "tgn:1002737",
          "tgn:7007520",
          "tgn:7029392"
        ],
        "placetype": [
          "aat:300008347"
        ],
        "id": 2052240,
        "name:xx": "Huntington Woods"
      }
    },
    {
      "geometry": {
        "type": "Point",
        "coordinates": [
          -82.5167,
          43.2
        ]
      },
      "type": "Feature",
      "properties": {
        "hierarchy": [
          "tgn:2052242",
          "tgn:1000001",
          "tgn:7012149",
          "tgn:2000995",
          "tgn:7007520",
          "tgn:7029392"
        ],
        "placetype": [
          "aat:300008347"
        ],
        "id": 2052242,
        "name:xx": "Huronia Heights"
      }
    },
    {
      "geometry": {
        "type": "Point",
        "coordinates": [
          -87.85,
          46.8833
        ]
      },
      "type": "Feature",
      "properties": {
        "hierarchy": [
          "tgn:2052243",
          "tgn:1000001",
          "tgn:7012149",
          "tgn:2000975",
          "tgn:7007520",
          "tgn:7029392"
        ],
        "placetype": [
          "aat:300008347"
        ],
        "id": 2052243,
        "name:xx": "Huron Mountain"
      }
    },
    {
      "geometry": {
        "type": "Point",
        "coordinates": [
          -88.5667,
          47.1
        ]
      },
      "type": "Feature",
      "properties": {
        "hierarchy": [
          "tgn:2052244",
          "tgn:1000001",
          "tgn:7012149",
          "tgn:2000963",
          "tgn:7007520",
          "tgn:7029392"
        ],
        "placetype": [
          "aat:300008347"
        ],
        "id": 2052244,
        "name:xx": "Hurontown"
      }
    },
    {
      "geometry": {
        "type": "Point",
        "coordinates": [
          -87.6667,
          45.95
        ]
      },
      "type": "Feature",
      "properties": {
        "hierarchy": [
          "tgn:2052247",
          "tgn:1000001",
          "tgn:2000956",
          "tgn:7012149",
          "tgn:7007520",
          "tgn:7029392"
        ],
        "placetype": [
          "aat:300008347",
          "aat:300387210"
        ],
        "id": 2052247,
        "name:xx": "Hylas"
      }
    },
    {
      "geometry": {
        "type": "Point",
        "coordinates": [
          -83.5667,
          41.9
        ]
      },
      "type": "Feature",
      "properties": {
        "hierarchy": [
          "tgn:2052248",
          "tgn:1000001",
          "tgn:7012149",
          "tgn:1002679",
          "tgn:7007520",
          "tgn:7029392"
        ],
        "placetype": [
          "aat:300008347"
        ],
        "id": 2052248,
        "name:xx": "Ida"
      }
    },
    {
      "geometry": {
        "type": "Point",
        "coordinates": [
          -85.8,
          43.8833
        ]
      },
      "type": "Feature",
      "properties": {
        "hierarchy": [
          "tgn:2052249",
          "tgn:1000001",
          "tgn:7012149",
          "tgn:2000970",
          "tgn:7007520",
          "tgn:7029392"
        ],
        "placetype": [
          "aat:300008347"
        ],
        "id": 2052249,
        "name:xx": "Idlewild"
      }
    }
  ]
}
