{
  "geometry": {
    "type": "Point",
    "coordinates": [
      -71.8167,
      42.1833
    ]
  },
  "type": "Feature",
  "properties": {
    "hierarchy": [
      "tgn:2592059",
      "tgn:1000001",
      "tgn:7012149",
      "tgn:1003038",
      "tgn:7007517",
      "tgn:7029392"
    ],
    "placetype": [
      "aat:300006191"
    ],
    "id": 2592059,
    "name:xx": "Pondville Pond"
  }
}
