{
  "geometry": {
    "type": "Point",
    "coordinates": [
      -122.8833,
      45.3167
    ]
  },
  "type": "Feature",
  "properties": {
    "hierarchy": [
      "tgn:2746218",
      "tgn:1000001",
      "tgn:7012149",
      "tgn:1002994",
      "tgn:7007708",
      "tgn:7029392"
    ],
    "placetype": [
      "aat:300008347"
    ],
    "id": 2746218,
    "name:xx": "Votaw"
  }
}
