{
  "geometry": {
    "type": "Point",
    "coordinates": [
      -91.0833,
      29.85
    ]
  },
  "type": "Feature",
  "properties": {
    "hierarchy": [
      "tgn:2543312",
      "tgn:2000857",
      "tgn:1000001",
      "tgn:7012149",
      "tgn:7007256",
      "tgn:7029392"
    ],
    "placetype": [
      "aat:300006075"
    ],
    "id": 2543312,
    "name:xx": "Norman Canal"
  }
}
