{
  "geometry": {
    "type": "Point",
    "coordinates": [
      -90.8667,
      40.1167
    ]
  },
  "type": "Feature",
  "properties": {
    "hierarchy": [
      "tgn:2358448",
      "tgn:1000001",
      "tgn:7012149",
      "tgn:1002874",
      "tgn:7007251",
      "tgn:7029392"
    ],
    "placetype": [
      "aat:300008699"
    ],
    "id": 2358448,
    "name:xx": "Grand Tower Branch"
  }
}
