{
  "geometry": {
    "type": "Point",
    "coordinates": [
      27.6833,
      20.9167
    ]
  },
  "type": "Feature",
  "properties": {
    "hierarchy": [
      "tgn:1107823",
      "tgn:7001242",
      "tgn:1001112",
      "tgn:1000201",
      "tgn:7029392"
    ],
    "placetype": [
      "aat:300008777"
    ],
    "id": 1107823,
    "name:xx": "Ṭuyūr, Burj aṭ-"
  }
}
