{
  "type": "FeatureCollection",
  "features": [
    {
      "geometry": {
        "type": "Point",
        "coordinates": [
          -120,
          44.8167
        ]
      },
      "type": "Feature",
      "properties": {
        "hierarchy": [
          "tgn:2420470",
          "tgn:1000001",
          "tgn:7012149",
          "tgn:2001723",
          "tgn:7007708",
          "tgn:7029392"
        ],
        "placetype": [
          "aat:300008706"
        ],
        "id": 2420470,
        "name:xx": "Jenkins Creek"
      }
    },
    {
      "geometry": {
        "type": "Point",
        "coordinates": [
          -119.1667,
          44.2333
        ]
      },
      "type": "Feature",
      "properties": {
        "hierarchy": [
          "tgn:2420471",
          "tgn:1000001",
          "tgn:7012149",
          "tgn:2001708",
          "tgn:7007708",
          "tgn:7029392"
        ],
        "placetype": [
          "aat:300008706"
        ],
        "id": 2420471,
        "name:xx": "Jenkins Creek"
      }
    },
    {
      "geometry": {
        "type": "Point",
        "coordinates": [
          -85.6333,
          35.35
        ]
      },
      "type": "Feature",
      "properties": {
        "hierarchy": [
          "tgn:2420472",
          "tgn:1000001",
          "tgn:7012149",
          "tgn:2001867",
          "tgn:7007825",
          "tgn:7029392"
        ],
        "placetype": [
          "aat:300008706"
        ],
        "id": 2420472,
        "name:xx": "Jenkins Creek"
      }
    },
    {
      "geometry": {
        "type": "Point",
        "coordinates": [
          -87.45,
          36.1333
        ]
      },
      "type": "Feature",
      "properties": {
        "hierarchy": [
          "tgn:2420473",
          "tgn:1000001",
          "tgn:7012149",
          "tgn:2001858",
          "tgn:7007825",
          "tgn:7029392"
        ],
        "placetype": [
          "aat:300008706"
        ],
        "id": 2420473,
        "name:xx": "Jenkins Creek"
      }
    },
    {
      "geometry": {
        "type": "Point",
        "coordinates": [
          -81.7167,
          36.35
        ]
      },
      "type": "Feature",
      "properties": {
        "hierarchy": [
          "tgn:2420474",
          "tgn:1000001",
          "tgn:7012149",
          "tgn:2001882",
          "tgn:7007825",
          "tgn:7029392"
        ],
        "placetype": [
          "aat:300008706"
        ],
        "id": 2420474,
        "name:xx": "Jenkins Creek"
      }
    },
    {
      "geometry": {
        "type": "Point",
        "coordinates": [
          -99.4833,
          32.4333
        ]
      },
      "type": "Feature",
      "properties": {
        "hierarchy": [
          "tgn:2420475",
          "tgn:1000001",
          "tgn:7012149",
          "tgn:7007826",
          "tgn:7029392"
        ],
        "placetype": [
          "aat:300008706"
        ],
        "id": 2420475,
        "name:xx": "Jenkins Creek"
      }
    },
    {
      "geometry": {
        "type": "Point",
        "coordinates": [
          -78.6833,
          37.1833
        ]
      },
      "type": "Feature",
      "properties": {
        "hierarchy": [
          "tgn:2420476",
          "tgn:1000001",
          "tgn:2002152",
          "tgn:7012149",
          "tgn:7007919",
          "tgn:7029392"
        ],
        "placetype": [
          "aat:300008706"
        ],
        "id": 2420476,
        "name:xx": "Jenkins Creek"
      }
    },
    {
      "geometry": {
        "type": "Point",
        "coordinates": [
          -78.6167,
          37.4
        ]
      },
      "type": "Feature",
      "properties": {
        "hierarchy": [
          "tgn:2420477",
          "tgn:1000001",
          "tgn:2002149",
          "tgn:7012149",
          "tgn:7007919",
          "tgn:7029392"
        ],
        "placetype": [
          "aat:300008706"
        ],
        "id": 2420477,
        "name:xx": "Jenkins Creek"
      }
    },
    {
      "geometry": {
        "type": "Point",
        "coordinates": [
          -120.7333,
          45.9333
        ]
      },
      "type": "Feature",
      "properties": {
        "hierarchy": [
          "tgn:2420478",
          "tgn:1000001",
          "tgn:7012149",
          "tgn:1002554",
          "tgn:7007920",
          "tgn:7029392"
        ],
        "placetype": [
          "aat:300008706"
        ],
        "id": 2420478,
        "name:xx": "Jenkins Creek"
      }
    },
    {
      "geometry": {
        "type": "Point",
        "coordinates": [
          -122.0333,
          47.3667
        ]
      },
      "type": "Feature",
      "properties": {
        "hierarchy": [
          "tgn:2420479",
          "tgn:1000001",
          "tgn:7012149",
          "tgn:7018871",
          "tgn:7007920",
          "tgn:7029392"
        ],
        "placetype": [
          "aat:300008706"
        ],
        "id": 2420479,
        "name:xx": "Jenkins Creek"
      }
    }
  ]
}
