{
  "geometry": {
    "type": "Point",
    "coordinates": [
      -121.5167,
      37.15
    ]
  },
  "type": "Feature",
  "properties": {
    "hierarchy": [
      "tgn:2256696",
      "tgn:1000001",
      "tgn:7012149",
      "tgn:7007157",
      "tgn:7014475",
      "tgn:7029392"
    ],
    "placetype": [
      "aat:300266640"
    ],
    "id": 2256696,
    "name:xx": "Cordoza Ridge"
  }
}
