{
  "geometry": {
    "type": "Point",
    "coordinates": [
      -120.3833,
      37.85
    ]
  },
  "type": "Feature",
  "properties": {
    "hierarchy": [
      "tgn:2490007",
      "tgn:1000001",
      "tgn:7012149",
      "tgn:7007157",
      "tgn:1002957",
      "tgn:7029392"
    ],
    "placetype": [
      "aat:300000390"
    ],
    "id": 2490007,
    "name:xx": "Mammoth Mine"
  }
}
