{
  "geometry": {
    "type": "Point",
    "coordinates": [
      8.45,
      50.45
    ]
  },
  "type": "Feature",
  "properties": {
    "hierarchy": [
      "tgn:7106293",
      "tgn:1000003",
      "tgn:7003678",
      "tgn:7000084",
      "tgn:7029392"
    ],
    "placetype": [
      "aat:300004792"
    ],
    "id": 7106293,
    "name:xx": "Oberförsterei Schmiedenhof"
  }
}
