{
  "type": "FeatureCollection",
  "features": [
    {
      "geometry": {
        "type": "Point",
        "coordinates": [
          -95.5667,
          30.7333
        ]
      },
      "type": "Feature",
      "properties": {
        "hierarchy": [
          "tgn:1002980",
          "tgn:1000001",
          "tgn:7012149",
          "tgn:7007826",
          "tgn:7029392"
        ],
        "placetype": [
          "aat:300387145",
          "aat:300000771"
        ],
        "id": 1002980,
        "name:xx": "Walker"
      }
    },
    {
      "geometry": {
        "type": "Point",
        "coordinates": [
          -96,
          30
        ]
      },
      "type": "Feature",
      "properties": {
        "hierarchy": [
          "tgn:1002981",
          "tgn:1000001",
          "tgn:7012149",
          "tgn:7007826",
          "tgn:7029392"
        ],
        "placetype": [
          "aat:300387145",
          "aat:300000771"
        ],
        "id": 1002981,
        "name:xx": "Waller"
      }
    },
    {
      "geometry": {
        "type": "Point",
        "coordinates": [
          -88.5333,
          42.6667
        ]
      },
      "type": "Feature",
      "properties": {
        "hierarchy": [
          "tgn:1002982",
          "tgn:1000001",
          "tgn:7012149",
          "tgn:7007922",
          "tgn:7029392"
        ],
        "placetype": [
          "aat:300387145",
          "aat:300000771"
        ],
        "id": 1002982,
        "name:xx": "Walworth"
      }
    },
    {
      "geometry": {
        "type": "Point",
        "coordinates": [
          -87.2833,
          40.2833
        ]
      },
      "type": "Feature",
      "properties": {
        "hierarchy": [
          "tgn:1002983",
          "tgn:1000001",
          "tgn:7012149",
          "tgn:7007252",
          "tgn:7029392"
        ],
        "placetype": [
          "aat:300387145",
          "aat:300000771"
        ],
        "id": 1002983,
        "name:xx": "Warren"
      }
    },
    {
      "geometry": {
        "type": "Point",
        "coordinates": [
          -91.1667,
          38.7667
        ]
      },
      "type": "Feature",
      "properties": {
        "hierarchy": [
          "tgn:1002984",
          "tgn:1000001",
          "tgn:7012149",
          "tgn:7007523",
          "tgn:7029392"
        ],
        "placetype": [
          "aat:300387145",
          "aat:300000771"
        ],
        "id": 1002984,
        "name:xx": "Warren"
      }
    },
    {
      "geometry": {
        "type": "Point",
        "coordinates": [
          -74.95,
          40.8333
        ]
      },
      "type": "Feature",
      "properties": {
        "hierarchy": [
          "tgn:1002985",
          "tgn:1000001",
          "tgn:7012149",
          "tgn:7007565",
          "tgn:7029392"
        ],
        "placetype": [
          "aat:300387145",
          "aat:300000771"
        ],
        "id": 1002985,
        "name:xx": "Warren"
      }
    },
    {
      "geometry": {
        "type": "Point",
        "coordinates": [
          -73.8,
          43.55
        ]
      },
      "type": "Feature",
      "properties": {
        "hierarchy": [
          "tgn:1002986",
          "tgn:1000001",
          "tgn:7012149",
          "tgn:7007568",
          "tgn:7029392"
        ],
        "placetype": [
          "aat:300387145",
          "aat:300000771"
        ],
        "id": 1002986,
        "name:xx": "Warren"
      }
    },
    {
      "geometry": {
        "type": "Point",
        "coordinates": [
          -84.1667,
          39.4333
        ]
      },
      "type": "Feature",
      "properties": {
        "hierarchy": [
          "tgn:1002987",
          "tgn:1000001",
          "tgn:7012149",
          "tgn:7007706",
          "tgn:7029392"
        ],
        "placetype": [
          "aat:300387145",
          "aat:300000771"
        ],
        "id": 1002987,
        "name:xx": "Warren"
      }
    },
    {
      "geometry": {
        "type": "Point",
        "coordinates": [
          -79.5,
          41.8667
        ]
      },
      "type": "Feature",
      "properties": {
        "hierarchy": [
          "tgn:1002988",
          "tgn:1000001",
          "tgn:7012149",
          "tgn:7007710",
          "tgn:7029392"
        ],
        "placetype": [
          "aat:300387145",
          "aat:300000771"
        ],
        "id": 1002988,
        "name:xx": "Warren"
      }
    }
  ]
}
