{
  "geometry": {
    "type": "Point",
    "coordinates": [
      -116.3833,
      34.05
    ]
  },
  "type": "Feature",
  "properties": {
    "hierarchy": [
      "tgn:2177507",
      "tgn:1000001",
      "tgn:7012149",
      "tgn:7007157",
      "tgn:1002857",
      "tgn:7029392"
    ],
    "placetype": [
      "aat:300008697"
    ],
    "id": 2177507,
    "name:xx": "Black Rock Spring"
  }
}
