{
  "geometry": {
    "type": "Point",
    "coordinates": [
      -107.3167,
      39.7667
    ]
  },
  "type": "Feature",
  "properties": {
    "hierarchy": [
      "tgn:2383324",
      "tgn:1000001",
      "tgn:7012149",
      "tgn:2000214",
      "tgn:7007158",
      "tgn:7029392"
    ],
    "placetype": [
      "aat:300006191"
    ],
    "id": 2383324,
    "name:xx": "Heart Lake"
  }
}
