{
  "geometry": {
    "type": "Point",
    "coordinates": [
      -118.0667,
      43.7333
    ]
  },
  "type": "Feature",
  "properties": {
    "hierarchy": [
      "tgn:2084949",
      "tgn:1000001",
      "tgn:7012149",
      "tgn:2001718",
      "tgn:7007708",
      "tgn:7029392"
    ],
    "placetype": [
      "aat:300008347"
    ],
    "id": 2084949,
    "name:xx": "Juntura"
  }
}
