{
  "geometry": {
    "type": "Point",
    "coordinates": [
      -123.5333,
      40.15
    ]
  },
  "type": "Feature",
  "properties": {
    "hierarchy": [
      "tgn:2720892",
      "tgn:1000001",
      "tgn:7012149",
      "tgn:2000181",
      "tgn:7007157",
      "tgn:7029392"
    ],
    "placetype": [
      "aat:300008706"
    ],
    "id": 2720892,
    "name:xx": "Ticknor Creek"
  }
}
