{
  "geometry": {
    "type": "Point",
    "coordinates": [
      99.75,
      1.2833
    ]
  },
  "type": "Feature",
  "properties": {
    "hierarchy": [
      "tgn:1077335",
      "tgn:1000004",
      "tgn:1001555",
      "tgn:1000116",
      "tgn:7029392"
    ],
    "placetype": [
      "aat:300008347"
    ],
    "id": 1077335,
    "name:xx": "Aeknabara"
  }
}
