{
  "geometry": {
    "type": "Point",
    "coordinates": [
      -88.5667,
      39.6167
    ]
  },
  "type": "Feature",
  "properties": {
    "hierarchy": [
      "tgn:2027168",
      "tgn:1000001",
      "tgn:7012149",
      "tgn:1002698",
      "tgn:7007251",
      "tgn:7029392"
    ],
    "placetype": [
      "aat:300387016"
    ],
    "id": 2027168,
    "name:xx": "Chipps"
  }
}
