{
  "geometry": {
    "type": "Point",
    "coordinates": [
      -111.65,
      34.15
    ]
  },
  "type": "Feature",
  "properties": {
    "hierarchy": [
      "tgn:2298712",
      "tgn:1000001",
      "tgn:7006451",
      "tgn:7012149",
      "tgn:7029392"
    ],
    "placetype": [
      "aat:300008699"
    ],
    "id": 2298712,
    "name:xx": "Dry Wash"
  }
}
