{
  "geometry": {
    "type": "Point",
    "coordinates": [
      -6.516667,
      38.016667
    ]
  },
  "type": "Feature",
  "properties": {
    "hierarchy": [
      "tgn:7342674",
      "tgn:7002758",
      "tgn:7002823",
      "tgn:1000003",
      "tgn:1000095",
      "tgn:7029392"
    ],
    "placetype": [
      "aat:300008347"
    ],
    "id": 7342674,
    "name:xx": "Cañaveral de León"
  }
}
