{
  "type": "FeatureCollection",
  "features": [
    {
      "geometry": {
        "type": "Point",
        "coordinates": [
          -97.85,
          18.416667
        ]
      },
      "type": "Feature",
      "properties": {
        "hierarchy": [
          "tgn:7384460",
          "tgn:1000001",
          "tgn:7005592",
          "tgn:7005560",
          "tgn:7029392"
        ],
        "placetype": [
          "aat:300008347"
        ],
        "id": 7384460,
        "name:xx": "Natívitas Cuautempan"
      }
    },
    {
      "geometry": {
        "type": "Point",
        "coordinates": [
          -98.3,
          20.05
        ]
      },
      "type": "Feature",
      "properties": {
        "hierarchy": [
          "tgn:7384461",
          "tgn:7005587",
          "tgn:1000001",
          "tgn:7005560",
          "tgn:7029392"
        ],
        "placetype": [
          "aat:300008347"
        ],
        "id": 7384461,
        "name:xx": "Natívitas"
      }
    },
    {
      "geometry": {
        "type": "Point",
        "coordinates": [
          -98.833333,
          19.5
        ]
      },
      "type": "Feature",
      "properties": {
        "hierarchy": [
          "tgn:7384462",
          "tgn:1000001",
          "tgn:1001893",
          "tgn:7005560",
          "tgn:7029392"
        ],
        "placetype": [
          "aat:300008347"
        ],
        "id": 7384462,
        "name:xx": "Natívitas"
      }
    },
    {
      "geometry": {
        "type": "Point",
        "coordinates": [
          -98.316667,
          19.233333
        ]
      },
      "type": "Feature",
      "properties": {
        "hierarchy": [
          "tgn:7384463",
          "tgn:1000001",
          "tgn:7005598",
          "tgn:7005560",
          "tgn:7029392"
        ],
        "placetype": [
          "aat:300008347"
        ],
        "id": 7384463,
        "name:xx": "Nativitas"
      }
    },
    {
      "geometry": {
        "type": "Point",
        "coordinates": [
          -99.6,
          19.216667
        ]
      },
      "type": "Feature",
      "properties": {
        "hierarchy": [
          "tgn:7384464",
          "tgn:1000001",
          "tgn:1001893",
          "tgn:7005560",
          "tgn:7029392"
        ],
        "placetype": [
          "aat:300008347"
        ],
        "id": 7384464,
        "name:xx": "Natívitas"
      }
    },
    {
      "geometry": {
        "type": "Point",
        "coordinates": [
          -97.3,
          18.416667
        ]
      },
      "type": "Feature",
      "properties": {
        "hierarchy": [
          "tgn:7384465",
          "tgn:1000001",
          "tgn:7005592",
          "tgn:7005560",
          "tgn:7029392"
        ],
        "placetype": [
          "aat:300008347"
        ],
        "id": 7384465,
        "name:xx": "Natívitas"
      }
    },
    {
      "geometry": {
        "type": "Point",
        "coordinates": [
          -115.183333,
          27.866667
        ]
      },
      "type": "Feature",
      "properties": {
        "hierarchy": [
          "tgn:7384466",
          "tgn:1001836",
          "tgn:1000001",
          "tgn:7005560",
          "tgn:7029392"
        ],
        "placetype": [
          "aat:300008791"
        ],
        "id": 7384466,
        "name:xx": "Natividad, Isla"
      }
    },
    {
      "geometry": {
        "type": "Point",
        "coordinates": [
          -110.866667,
          24.816667
        ]
      },
      "type": "Feature",
      "properties": {
        "hierarchy": [
          "tgn:7384467",
          "tgn:1001836",
          "tgn:1000001",
          "tgn:7005560",
          "tgn:7029392"
        ],
        "placetype": [
          "aat:300008795"
        ],
        "id": 7384467,
        "name:xx": "Natividad, Cerro"
      }
    },
    {
      "geometry": {
        "type": "Point",
        "coordinates": [
          -106.183333,
          27.45
        ]
      },
      "type": "Feature",
      "properties": {
        "hierarchy": [
          "tgn:7384468",
          "tgn:7005581",
          "tgn:1000001",
          "tgn:7005560",
          "tgn:7029392"
        ],
        "placetype": [
          "aat:300008347"
        ],
        "id": 7384468,
        "name:xx": "Natividad"
      }
    },
    {
      "geometry": {
        "type": "Point",
        "coordinates": [
          -110.933333,
          24.766667
        ]
      },
      "type": "Feature",
      "properties": {
        "hierarchy": [
          "tgn:7384469",
          "tgn:1001836",
          "tgn:1000001",
          "tgn:7005560",
          "tgn:7029392"
        ],
        "placetype": [
          "aat:300008347"
        ],
        "id": 7384469,
        "name:xx": "Natividad"
      }
    }
  ]
}
