{
  "geometry": {
    "type": "Point",
    "coordinates": [
      10.8167,
      56.3167
    ]
  },
  "type": "Feature",
  "properties": {
    "hierarchy": [
      "tgn:1027909",
      "tgn:7594006",
      "tgn:1000003",
      "tgn:1000066",
      "tgn:7029392"
    ],
    "placetype": [
      "aat:300008347"
    ],
    "id": 1027909,
    "name:xx": "Hoed"
  }
}
