{
  "geometry": {
    "type": "Point",
    "coordinates": [
      79.8022,
      27.1463
    ]
  },
  "type": "Feature",
  "properties": {
    "hierarchy": [
      "tgn:7562464",
      "tgn:1000004",
      "tgn:7000198",
      "tgn:7016722",
      "tgn:7029392"
    ],
    "placetype": [
      "aat:300008347"
    ],
    "name:en": "Nawal Purwa",
    "id": 7562464
  }
}
