{
  "geometry": {
    "type": "Point",
    "coordinates": [
      -79.15,
      41.0833
    ]
  },
  "type": "Feature",
  "properties": {
    "hierarchy": [
      "tgn:2091518",
      "tgn:1000001",
      "tgn:7012149",
      "tgn:1002520",
      "tgn:7007710",
      "tgn:7029392"
    ],
    "placetype": [
      "aat:300008347"
    ],
    "id": 2091518,
    "name:xx": "Ohl"
  }
}
