{
  "geometry": {
    "type": "Point",
    "coordinates": [
      -91.8833,
      39.9833
    ]
  },
  "type": "Feature",
  "properties": {
    "hierarchy": [
      "tgn:2129857",
      "tgn:1000001",
      "tgn:7012149",
      "tgn:1002592",
      "tgn:7007523",
      "tgn:7029392"
    ],
    "placetype": [
      "aat:300008699"
    ],
    "id": 2129857,
    "name:xx": "Allen Branch"
  }
}
