{
  "geometry": {
    "type": "Point",
    "coordinates": [
      -83.9833,
      38.0167
    ]
  },
  "type": "Feature",
  "properties": {
    "hierarchy": [
      "tgn:1133410",
      "tgn:1000001",
      "tgn:7012149",
      "tgn:7007255",
      "tgn:7029392"
    ],
    "placetype": [
      "aat:300008706"
    ],
    "id": 1133410,
    "name:xx": "Hinkston Creek"
  }
}
