{
  "geometry": {
    "type": "Point",
    "coordinates": [
      -74.5333,
      43.2667
    ]
  },
  "type": "Feature",
  "properties": {
    "hierarchy": [
      "tgn:2730140",
      "tgn:1000001",
      "tgn:7012149",
      "tgn:1002440",
      "tgn:7007568",
      "tgn:7029392"
    ],
    "placetype": [
      "aat:300008798"
    ],
    "id": 2730140,
    "name:xx": "Trout Lake Mountain"
  }
}
