{
  "geometry": {
    "type": "Point",
    "coordinates": [
      31.9667,
      52.5167
    ]
  },
  "type": "Feature",
  "properties": {
    "hierarchy": [
      "tgn:1057807",
      "tgn:7011551",
      "tgn:1000004",
      "tgn:7018214",
      "tgn:7002435",
      "tgn:7029392"
    ],
    "placetype": [
      "aat:300008347"
    ],
    "id": 1057807,
    "name:xx": "Novozybkov"
  }
}
