{
  "geometry": {
    "type": "Point",
    "coordinates": [
      31.268288,
      30.850171
    ]
  },
  "type": "Feature",
  "properties": {
    "hierarchy": [
      "tgn:7542429",
      "tgn:7001242",
      "tgn:1001059",
      "tgn:7016833",
      "tgn:7029392"
    ],
    "placetype": [
      "aat:300006075"
    ],
    "name:en": "Tir'at Mīt Mi'ānid",
    "id": 7542429
  }
}
