{
  "geometry": {
    "type": "Point",
    "coordinates": [
      -95.15,
      49.15
    ]
  },
  "type": "Feature",
  "properties": {
    "hierarchy": [
      "tgn:2204278",
      "tgn:1000001",
      "tgn:7012149",
      "tgn:7021313",
      "tgn:7007521",
      "tgn:7029392"
    ],
    "placetype": [
      "aat:300132316"
    ],
    "id": 2204278,
    "name:xx": "Buffalo Bay"
  }
}
