{
  "geometry": {
    "type": "Point",
    "coordinates": [
      -6.9333,
      41.0333
    ]
  },
  "type": "Feature",
  "properties": {
    "hierarchy": [
      "tgn:1120767",
      "tgn:1000003",
      "tgn:7029392"
    ],
    "placetype": [
      "aat:300008707"
    ],
    "id": 1120767,
    "name:es": "Águeda"
  }
}
