{
  "geometry": {
    "type": "Point",
    "coordinates": [
      17.5333,
      49.1667
    ]
  },
  "type": "Feature",
  "properties": {
    "hierarchy": [
      "tgn:1027408",
      "tgn:7593922",
      "tgn:1000003",
      "tgn:1001780",
      "tgn:7029392"
    ],
    "placetype": [
      "aat:300008347"
    ],
    "id": 1027408,
    "name:xx": "Napajedla"
  }
}
