{
  "geometry": {
    "type": "Point",
    "coordinates": [
      -147.4667,
      64.8167
    ]
  },
  "type": "Feature",
  "properties": {
    "hierarchy": [
      "tgn:2198433",
      "tgn:7006450",
      "tgn:1000001",
      "tgn:7019674",
      "tgn:7012149",
      "tgn:7029392"
    ],
    "placetype": [
      "aat:300008798"
    ],
    "id": 2198433,
    "name:xx": "Browns Hill"
  }
}
