{
  "type": "FeatureCollection",
  "features": [
    {
      "geometry": {
        "type": "Point",
        "coordinates": [
          6.2,
          50.583333
        ]
      },
      "type": "Feature",
      "properties": {
        "hierarchy": [
          "tgn:7254931",
          "tgn:7003460",
          "tgn:1000003",
          "tgn:1000063",
          "tgn:4012014",
          "tgn:7029392"
        ],
        "placetype": [
          "aat:300008347"
        ],
        "id": 7254931,
        "name:xx": "Stelingberg"
      }
    },
    {
      "geometry": {
        "type": "Point",
        "coordinates": [
          5.6,
          50.966667
        ]
      },
      "type": "Feature",
      "properties": {
        "hierarchy": [
          "tgn:7254932",
          "tgn:7003461",
          "tgn:1000003",
          "tgn:1000063",
          "tgn:7018236",
          "tgn:7029392"
        ],
        "placetype": [
          "aat:300008688"
        ],
        "id": 7254932,
        "name:xx": "Stele Ven"
      }
    },
    {
      "geometry": {
        "type": "Point",
        "coordinates": [
          4.966667,
          51.133333
        ]
      },
      "type": "Feature",
      "properties": {
        "hierarchy": [
          "tgn:7254933",
          "tgn:7003456",
          "tgn:1000003",
          "tgn:1000063",
          "tgn:7018236",
          "tgn:7029392"
        ],
        "placetype": [
          "aat:300008347"
        ],
        "id": 7254933,
        "name:xx": "Stelen"
      }
    },
    {
      "geometry": {
        "type": "Point",
        "coordinates": [
          5.566667,
          50.916667
        ]
      },
      "type": "Feature",
      "properties": {
        "hierarchy": [
          "tgn:7254934",
          "tgn:7003461",
          "tgn:1000003",
          "tgn:1000063",
          "tgn:7018236",
          "tgn:7029392"
        ],
        "placetype": [
          "aat:300008863"
        ],
        "id": 7254934,
        "name:xx": "Stelebos"
      }
    },
    {
      "geometry": {
        "type": "Point",
        "coordinates": [
          4.883333,
          51.1
        ]
      },
      "type": "Feature",
      "properties": {
        "hierarchy": [
          "tgn:7254937",
          "tgn:7003456",
          "tgn:1000003",
          "tgn:1000063",
          "tgn:7018236",
          "tgn:7029392"
        ],
        "placetype": [
          "aat:300000206"
        ],
        "id": 7254937,
        "name:xx": "Steinnenhoeve"
      }
    },
    {
      "geometry": {
        "type": "Point",
        "coordinates": [
          6.171667,
          50.196111
        ]
      },
      "type": "Feature",
      "properties": {
        "hierarchy": [
          "tgn:7254938",
          "tgn:7003460",
          "tgn:1000003",
          "tgn:1000063",
          "tgn:4012014",
          "tgn:7029392"
        ],
        "placetype": [
          "aat:300008777"
        ],
        "id": 7254938,
        "name:xx": "Steinkopf"
      }
    },
    {
      "geometry": {
        "type": "Point",
        "coordinates": [
          4.7,
          51.15
        ]
      },
      "type": "Feature",
      "properties": {
        "hierarchy": [
          "tgn:7254939",
          "tgn:7003456",
          "tgn:1000003",
          "tgn:1000063",
          "tgn:7018236",
          "tgn:7029392"
        ],
        "placetype": [
          "aat:300000206"
        ],
        "id": 7254939,
        "name:xx": "Steinhoeve"
      }
    }
  ]
}
