{
  "geometry": {
    "type": "Point",
    "coordinates": [
      -80.85,
      41.0167
    ]
  },
  "type": "Feature",
  "properties": {
    "hierarchy": [
      "tgn:2079436",
      "tgn:1000001",
      "tgn:7012149",
      "tgn:1002627",
      "tgn:7007706",
      "tgn:7029392"
    ],
    "placetype": [
      "aat:300008347"
    ],
    "id": 2079436,
    "name:xx": "Ellsworth"
  }
}
