{
  "geometry": {
    "type": "Point",
    "coordinates": [
      -77.7333,
      42.1833
    ]
  },
  "type": "Feature",
  "properties": {
    "hierarchy": [
      "tgn:2661512",
      "tgn:1000001",
      "tgn:7012149",
      "tgn:7007568",
      "tgn:7029392"
    ],
    "placetype": [
      "aat:300008761"
    ],
    "id": 2661512,
    "name:xx": "Shovel Hollow"
  }
}
