{
  "geometry": {
    "type": "Point",
    "coordinates": [
      -120.95,
      42.6167
    ]
  },
  "type": "Feature",
  "properties": {
    "hierarchy": [
      "tgn:2187212",
      "tgn:1000001",
      "tgn:7012149",
      "tgn:2001714",
      "tgn:7007708",
      "tgn:7029392"
    ],
    "placetype": [
      "aat:300008697"
    ],
    "id": 2187212,
    "name:xx": "Book Spring"
  }
}
