{
  "type": "FeatureCollection",
  "features": [
    {
      "geometry": {
        "type": "Point",
        "coordinates": [
          -77.4167,
          37.8333
        ]
      },
      "type": "Feature",
      "properties": {
        "hierarchy": [
          "tgn:2378800",
          "tgn:1000001",
          "tgn:1002235",
          "tgn:7012149",
          "tgn:7007919",
          "tgn:7029392"
        ],
        "placetype": [
          "aat:300008347"
        ],
        "id": 2378800,
        "name:xx": "Hart Corner"
      }
    },
    {
      "geometry": {
        "type": "Point",
        "coordinates": [
          -84.1167,
          34.8167
        ]
      },
      "type": "Feature",
      "properties": {
        "hierarchy": [
          "tgn:2378801",
          "tgn:1000001",
          "tgn:7012149",
          "tgn:2000435",
          "tgn:7007248",
          "tgn:7029392"
        ],
        "placetype": [
          "aat:300132316"
        ],
        "id": 2378801,
        "name:xx": "Hart Cove"
      }
    },
    {
      "geometry": {
        "type": "Point",
        "coordinates": [
          -72.7333,
          40.7833
        ]
      },
      "type": "Feature",
      "properties": {
        "hierarchy": [
          "tgn:2378802",
          "tgn:1000001",
          "tgn:7012149",
          "tgn:1002924",
          "tgn:7007568",
          "tgn:7029392"
        ],
        "placetype": [
          "aat:300132316"
        ],
        "id": 2378802,
        "name:xx": "Hart Cove"
      }
    },
    {
      "geometry": {
        "type": "Point",
        "coordinates": [
          -86.6833,
          31.25
        ]
      },
      "type": "Feature",
      "properties": {
        "hierarchy": [
          "tgn:2378803",
          "tgn:7002659",
          "tgn:1000001",
          "tgn:7012149",
          "tgn:7029392"
        ],
        "placetype": [
          "aat:300008706"
        ],
        "id": 2378803,
        "name:xx": "Hart Creek"
      }
    },
    {
      "geometry": {
        "type": "Point",
        "coordinates": [
          -165.3333,
          64.6
        ]
      },
      "type": "Feature",
      "properties": {
        "hierarchy": [
          "tgn:2378804",
          "tgn:7006450",
          "tgn:1000001",
          "tgn:7012149",
          "tgn:2000079",
          "tgn:7029392"
        ],
        "placetype": [
          "aat:300008706"
        ],
        "id": 2378804,
        "name:xx": "Hart Creek"
      }
    },
    {
      "geometry": {
        "type": "Point",
        "coordinates": [
          -94.25,
          35.7
        ]
      },
      "type": "Feature",
      "properties": {
        "hierarchy": [
          "tgn:2378805",
          "tgn:1000001",
          "tgn:7016172",
          "tgn:2000121",
          "tgn:7012149",
          "tgn:7029392"
        ],
        "placetype": [
          "aat:300008706"
        ],
        "id": 2378805,
        "name:xx": "Hart Creek"
      }
    },
    {
      "geometry": {
        "type": "Point",
        "coordinates": [
          -82.7167,
          33.4667
        ]
      },
      "type": "Feature",
      "properties": {
        "hierarchy": [
          "tgn:2378806",
          "tgn:1000001",
          "tgn:7012149",
          "tgn:7007248",
          "tgn:7029392"
        ],
        "placetype": [
          "aat:300008706"
        ],
        "id": 2378806,
        "name:xx": "Hart Creek"
      }
    },
    {
      "geometry": {
        "type": "Point",
        "coordinates": [
          -116.0167,
          47.6833
        ]
      },
      "type": "Feature",
      "properties": {
        "hierarchy": [
          "tgn:2378807",
          "tgn:1000001",
          "tgn:7012149",
          "tgn:2000491",
          "tgn:7007250",
          "tgn:7029392"
        ],
        "placetype": [
          "aat:300008706"
        ],
        "id": 2378807,
        "name:xx": "Hart Creek"
      }
    },
    {
      "geometry": {
        "type": "Point",
        "coordinates": [
          -116.6167,
          42.95
        ]
      },
      "type": "Feature",
      "properties": {
        "hierarchy": [
          "tgn:2378808",
          "tgn:1000001",
          "tgn:7012149",
          "tgn:2000488",
          "tgn:7007250",
          "tgn:7029392"
        ],
        "placetype": [
          "aat:300008706"
        ],
        "id": 2378808,
        "name:xx": "Hart Creek"
      }
    },
    {
      "geometry": {
        "type": "Point",
        "coordinates": [
          -88.45,
          37.5333
        ]
      },
      "type": "Feature",
      "properties": {
        "hierarchy": [
          "tgn:2378809",
          "tgn:1000001",
          "tgn:7012149",
          "tgn:2000523",
          "tgn:7007251",
          "tgn:7029392"
        ],
        "placetype": [
          "aat:300008706"
        ],
        "id": 2378809,
        "name:xx": "Hart Creek"
      }
    }
  ]
}
