{
  "geometry": {
    "type": "Point",
    "coordinates": [
      -105.6167,
      38.0833
    ]
  },
  "type": "Feature",
  "properties": {
    "hierarchy": [
      "tgn:2386753",
      "tgn:1000001",
      "tgn:7012149",
      "tgn:2000205",
      "tgn:7007158",
      "tgn:7029392"
    ],
    "placetype": [
      "aat:300008680"
    ],
    "id": 2386753,
    "name:xx": "Hermit Lake"
  }
}
