{
  "geometry": {
    "type": "Point",
    "coordinates": [
      -87.8833,
      30.6667
    ]
  },
  "type": "Feature",
  "properties": {
    "hierarchy": [
      "tgn:2683136",
      "tgn:2000001",
      "tgn:7002659",
      "tgn:1000001",
      "tgn:7012149",
      "tgn:7029392"
    ],
    "placetype": [
      "aat:300008699"
    ],
    "id": 2683136,
    "name:xx": "Spanish Fort Branch"
  }
}
