{
  "geometry": {
    "type": "Point",
    "coordinates": [
      99.65,
      31.6833
    ]
  },
  "type": "Feature",
  "properties": {
    "hierarchy": [
      "tgn:1071235",
      "tgn:1000004",
      "tgn:7002087",
      "tgn:1000111",
      "tgn:7029392"
    ],
    "placetype": [
      "aat:300008347"
    ],
    "id": 1071235,
    "name:xx": "Rongbaca"
  }
}
