{
  "geometry": {
    "type": "Point",
    "coordinates": [
      88.326646,
      25.634415
    ]
  },
  "type": "Feature",
  "properties": {
    "hierarchy": [
      "tgn:1075662",
      "tgn:1000004",
      "tgn:7000198",
      "tgn:1001977",
      "tgn:7029392"
    ],
    "placetype": [
      "aat:300008347"
    ],
    "name:en": "Kāliyāganj",
    "id": 1075662
  }
}
