{
  "type": "FeatureCollection",
  "features": [
    {
      "geometry": {
        "type": "Point",
        "coordinates": [
          43.25,
          13.3167
        ]
      },
      "type": "Feature",
      "properties": {
        "hierarchy": [
          "tgn:7004341",
          "tgn:1000146",
          "tgn:7004344",
          "tgn:1000004",
          "tgn:7000261",
          "tgn:7029392"
        ],
        "placetype": [
          "aat:300008347",
          "aat:300008375",
          "aat:300120599",
          "aat:300387286"
        ],
        "id": 7004341,
        "name:xx": "Al-Mukhā"
      }
    },
    {
      "geometry": {
        "type": "Point",
        "coordinates": [
          49.6,
          14.75
        ]
      },
      "type": "Feature",
      "properties": {
        "hierarchy": [
          "tgn:7004342",
          "tgn:1000139",
          "tgn:7004345",
          "tgn:1000004",
          "tgn:7000261",
          "tgn:7029392"
        ],
        "placetype": [
          "aat:300008347",
          "aat:300387286"
        ],
        "id": 7004342,
        "name:xx": "Ash-Shiḥr"
      }
    },
    {
      "geometry": {
        "type": "Point",
        "coordinates": [
          43.3,
          14.1667
        ]
      },
      "type": "Feature",
      "properties": {
        "hierarchy": [
          "tgn:7004343",
          "tgn:1000146",
          "tgn:7004346",
          "tgn:1000004",
          "tgn:7000261",
          "tgn:7029392"
        ],
        "placetype": [
          "aat:300008347",
          "aat:300387218",
          "aat:300387286"
        ],
        "id": 7004343,
        "name:xx": "Zabīd"
      }
    },
    {
      "geometry": {
        "type": "Point",
        "coordinates": [
          42.2,
          14.8
        ]
      },
      "type": "Feature",
      "properties": {
        "hierarchy": [
          "tgn:7004346",
          "tgn:1000146",
          "tgn:1000004",
          "tgn:7000261",
          "tgn:7029392"
        ],
        "placetype": [
          "aat:300387145",
          "aat:300235093"
        ],
        "id": 7004346,
        "name:xx": "al-Ḥudaydah"
      }
    },
    {
      "geometry": {
        "type": "Point",
        "coordinates": [
          44.5,
          14.55
        ]
      },
      "type": "Feature",
      "properties": {
        "hierarchy": [
          "tgn:7004347",
          "tgn:1000146",
          "tgn:1000004",
          "tgn:7000261",
          "tgn:7029392"
        ],
        "placetype": [
          "aat:300387145",
          "aat:300235093"
        ],
        "id": 7004347,
        "name:xx": "Dhamār"
      }
    },
    {
      "geometry": {
        "type": "Point",
        "coordinates": [
          44.1667,
          14.05
        ]
      },
      "type": "Feature",
      "properties": {
        "hierarchy": [
          "tgn:7004348",
          "tgn:1000146",
          "tgn:1000004",
          "tgn:7000261",
          "tgn:7029392"
        ],
        "placetype": [
          "aat:300387145",
          "aat:300235093"
        ],
        "id": 7004348,
        "name:xx": "Ibb"
      }
    },
    {
      "geometry": {
        "type": "Point",
        "coordinates": [
          45.5,
          15.5
        ]
      },
      "type": "Feature",
      "properties": {
        "hierarchy": [
          "tgn:7004349",
          "tgn:1000146",
          "tgn:1000004",
          "tgn:7000261",
          "tgn:7029392"
        ],
        "placetype": [
          "aat:300387145",
          "aat:300235093"
        ],
        "id": 7004349,
        "name:xx": "Ma'rib"
      }
    }
  ]
}
