{
  "geometry": {
    "type": "Point",
    "coordinates": [
      7.1167,
      45.3333
    ]
  },
  "type": "Feature",
  "properties": {
    "hierarchy": [
      "tgn:1103686",
      "tgn:1000003",
      "tgn:1000070",
      "tgn:7002897",
      "tgn:7029392"
    ],
    "placetype": [
      "aat:300008795"
    ],
    "id": 1103686,
    "name:xx": "Albaron"
  }
}
