{
  "geometry": {
    "type": "Point",
    "coordinates": [
      -113.25,
      47.6667
    ]
  },
  "type": "Feature",
  "properties": {
    "hierarchy": [
      "tgn:2446331",
      "tgn:1000001",
      "tgn:7012149",
      "tgn:2001274",
      "tgn:7007524",
      "tgn:7029392"
    ],
    "placetype": [
      "aat:300008706"
    ],
    "id": 2446331,
    "name:xx": "Lewis Creek"
  }
}
