{
  "geometry": {
    "type": "Point",
    "coordinates": [
      40.2333,
      45.0167
    ]
  },
  "type": "Feature",
  "properties": {
    "hierarchy": [
      "tgn:1051717",
      "tgn:7011488",
      "tgn:1000004",
      "tgn:7002435",
      "tgn:7029392"
    ],
    "placetype": [
      "aat:300008347"
    ],
    "id": 1051717,
    "name:xx": "Shovgenovskiy"
  }
}
