{
  "geometry": {
    "type": "Point",
    "coordinates": [
      -79.25,
      40.9833
    ]
  },
  "type": "Feature",
  "properties": {
    "hierarchy": [
      "tgn:2458376",
      "tgn:1002153",
      "tgn:1000001",
      "tgn:7012149",
      "tgn:7007710",
      "tgn:7029392"
    ],
    "placetype": [
      "aat:300008706"
    ],
    "id": 2458376,
    "name:xx": "Little Mudlick Creek"
  }
}
