{
  "geometry": {
    "type": "Point",
    "coordinates": [
      -84.9167,
      35.25
    ]
  },
  "type": "Feature",
  "properties": {
    "hierarchy": [
      "tgn:2766796",
      "tgn:1000001",
      "tgn:2001842",
      "tgn:7012149",
      "tgn:7007825",
      "tgn:7029392"
    ],
    "placetype": [
      "aat:300008761"
    ],
    "id": 2766796,
    "name:xx": "White Oak Valley"
  }
}
