{
  "geometry": {
    "type": "Point",
    "coordinates": [
      -11.5167,
      6.9333
    ]
  },
  "type": "Feature",
  "properties": {
    "hierarchy": [
      "tgn:1126809",
      "tgn:7001242",
      "tgn:7029392"
    ],
    "placetype": [
      "aat:300008707"
    ],
    "id": 1126809,
    "name:xx": "Mano"
  }
}
