{
  "type": "FeatureCollection",
  "features": [
    {
      "geometry": {
        "type": "Point",
        "coordinates": [
          -124.1667,
          40.8
        ]
      },
      "type": "Feature",
      "properties": {
        "hierarchy": [
          "tgn:2411540",
          "tgn:1000001",
          "tgn:7012149",
          "tgn:2000181",
          "tgn:7007157",
          "tgn:7029392"
        ],
        "placetype": [
          "aat:300008791"
        ],
        "id": 2411540,
        "name:xx": "Indian Island"
      }
    },
    {
      "geometry": {
        "type": "Point",
        "coordinates": [
          -122.2667,
          38.6167
        ]
      },
      "type": "Feature",
      "properties": {
        "hierarchy": [
          "tgn:2411541",
          "tgn:1000001",
          "tgn:7012149",
          "tgn:7007157",
          "tgn:1002706",
          "tgn:7029392"
        ],
        "placetype": [
          "aat:300008791"
        ],
        "id": 2411541,
        "name:xx": "Indian Island"
      }
    },
    {
      "geometry": {
        "type": "Point",
        "coordinates": [
          -86.1,
          30.4
        ]
      },
      "type": "Feature",
      "properties": {
        "hierarchy": [
          "tgn:2411542",
          "tgn:1000001",
          "tgn:7012149",
          "tgn:2000290",
          "tgn:7007240",
          "tgn:7029392"
        ],
        "placetype": [
          "aat:300008905"
        ],
        "id": 2411542,
        "name:xx": "Indian Island"
      }
    },
    {
      "geometry": {
        "type": "Point",
        "coordinates": [
          -82.1333,
          30.8
        ]
      },
      "type": "Feature",
      "properties": {
        "hierarchy": [
          "tgn:2411543",
          "tgn:1000001",
          "tgn:2000315",
          "tgn:7012149",
          "tgn:7007248",
          "tgn:7029392"
        ],
        "placetype": [
          "aat:300008791"
        ],
        "id": 2411543,
        "name:xx": "Indian Island"
      }
    },
    {
      "geometry": {
        "type": "Point",
        "coordinates": [
          -88.7333,
          41.45
        ]
      },
      "type": "Feature",
      "properties": {
        "hierarchy": [
          "tgn:2411544",
          "tgn:1000001",
          "tgn:7012149",
          "tgn:1002562",
          "tgn:7007251",
          "tgn:7029392"
        ],
        "placetype": [
          "aat:300008791"
        ],
        "id": 2411544,
        "name:xx": "Indian Island"
      }
    },
    {
      "geometry": {
        "type": "Point",
        "coordinates": [
          -90.5833,
          41.4667
        ]
      },
      "type": "Feature",
      "properties": {
        "hierarchy": [
          "tgn:2411545",
          "tgn:1000001",
          "tgn:7012149",
          "tgn:2000528",
          "tgn:7007251",
          "tgn:7029392"
        ],
        "placetype": [
          "aat:300008791"
        ],
        "id": 2411545,
        "name:xx": "Indian Island"
      }
    },
    {
      "geometry": {
        "type": "Point",
        "coordinates": [
          -89.9667,
          41.6667
        ]
      },
      "type": "Feature",
      "properties": {
        "hierarchy": [
          "tgn:2411546",
          "tgn:1000001",
          "tgn:7012149",
          "tgn:2000538",
          "tgn:7007251",
          "tgn:7029392"
        ],
        "placetype": [
          "aat:300008791"
        ],
        "id": 2411546,
        "name:xx": "Indian Island"
      }
    },
    {
      "geometry": {
        "type": "Point",
        "coordinates": [
          -70.5,
          43.7833
        ]
      },
      "type": "Feature",
      "properties": {
        "hierarchy": [
          "tgn:2411547",
          "tgn:1000001",
          "tgn:2000920",
          "tgn:7012149",
          "tgn:7007515",
          "tgn:7029392"
        ],
        "placetype": [
          "aat:300008791"
        ],
        "id": 2411547,
        "name:xx": "Indian Island"
      }
    },
    {
      "geometry": {
        "type": "Point",
        "coordinates": [
          -69.4167,
          43.9333
        ]
      },
      "type": "Feature",
      "properties": {
        "hierarchy": [
          "tgn:2411548",
          "tgn:1000001",
          "tgn:2000925",
          "tgn:7012149",
          "tgn:7007515",
          "tgn:7029392"
        ],
        "placetype": [
          "aat:300008791"
        ],
        "id": 2411548,
        "name:xx": "Indian Island"
      }
    },
    {
      "geometry": {
        "type": "Point",
        "coordinates": [
          -69.05,
          44.15
        ]
      },
      "type": "Feature",
      "properties": {
        "hierarchy": [
          "tgn:2411549",
          "tgn:1000001",
          "tgn:2000924",
          "tgn:7012149",
          "tgn:7007515",
          "tgn:7029392"
        ],
        "placetype": [
          "aat:300008791"
        ],
        "id": 2411549,
        "name:xx": "Indian Island"
      }
    }
  ]
}
