{
  "geometry": {
    "type": "Point",
    "coordinates": [
      2.25,
      48.3667
    ]
  },
  "type": "Feature",
  "properties": {
    "hierarchy": [
      "tgn:6003283",
      "tgn:1000003",
      "tgn:7002883",
      "tgn:1000070",
      "tgn:7029392"
    ],
    "placetype": [
      "aat:300008347",
      "aat:300008372"
    ],
    "id": 6003283,
    "name:xx": "Forêt-Sainte-Croix, la"
  }
}
