{
  "type": "FeatureCollection",
  "features": [
    {
      "geometry": {
        "type": "Point",
        "coordinates": [
          -84.65,
          30.6167
        ]
      },
      "type": "Feature",
      "properties": {
        "hierarchy": [
          "tgn:2019501",
          "tgn:1000001",
          "tgn:2000268",
          "tgn:7012149",
          "tgn:7007240",
          "tgn:7029392"
        ],
        "placetype": [
          "aat:300008347"
        ],
        "id": 2019501,
        "name:xx": "Gretna"
      }
    },
    {
      "geometry": {
        "type": "Point",
        "coordinates": [
          -81.9833,
          28.0833
        ]
      },
      "type": "Feature",
      "properties": {
        "hierarchy": [
          "tgn:2019502",
          "tgn:1000001",
          "tgn:7012149",
          "tgn:1002793",
          "tgn:7007240",
          "tgn:7029392"
        ],
        "placetype": [
          "aat:300008347"
        ],
        "id": 2019502,
        "name:xx": "Griffin"
      }
    },
    {
      "geometry": {
        "type": "Point",
        "coordinates": [
          -81.6667,
          30.7
        ]
      },
      "type": "Feature",
      "properties": {
        "hierarchy": [
          "tgn:2019503",
          "tgn:1000001",
          "tgn:7012149",
          "tgn:2000280",
          "tgn:7007240",
          "tgn:7029392"
        ],
        "placetype": [
          "aat:300008347",
          "aat:300387210"
        ],
        "id": 2019503,
        "name:xx": "Gross"
      }
    },
    {
      "geometry": {
        "type": "Point",
        "coordinates": [
          -82.3167,
          26.9
        ]
      },
      "type": "Feature",
      "properties": {
        "hierarchy": [
          "tgn:2019504",
          "tgn:1000001",
          "tgn:1002258",
          "tgn:7012149",
          "tgn:7007240",
          "tgn:7029392"
        ],
        "placetype": [
          "aat:300008347"
        ],
        "id": 2019504,
        "name:xx": "Grove City"
      }
    },
    {
      "geometry": {
        "type": "Point",
        "coordinates": [
          -81.85,
          28.55
        ]
      },
      "type": "Feature",
      "properties": {
        "hierarchy": [
          "tgn:2019505",
          "tgn:1000001",
          "tgn:7012149",
          "tgn:1002567",
          "tgn:7007240",
          "tgn:7029392"
        ],
        "placetype": [
          "aat:300008347"
        ],
        "id": 2019505,
        "name:xx": "Groveland"
      }
    },
    {
      "geometry": {
        "type": "Point",
        "coordinates": [
          -82.15,
          29.6
        ]
      },
      "type": "Feature",
      "properties": {
        "hierarchy": [
          "tgn:2019509",
          "tgn:2000256",
          "tgn:1000001",
          "tgn:7012149",
          "tgn:7007240",
          "tgn:7029392"
        ],
        "placetype": [
          "aat:300008347",
          "aat:300387210"
        ],
        "id": 2019509,
        "name:xx": "Grove Park"
      }
    }
  ]
}
