{
  "geometry": {
    "type": "Point",
    "coordinates": [
      100.0833,
      54.1667
    ]
  },
  "type": "Feature",
  "properties": {
    "hierarchy": [
      "tgn:1054297",
      "tgn:1003373",
      "tgn:1000004",
      "tgn:7018214",
      "tgn:7002435",
      "tgn:7029392"
    ],
    "placetype": [
      "aat:300008347"
    ],
    "id": 1054297,
    "name:xx": "Ikey"
  }
}
