{
  "geometry": {
    "type": "Point",
    "coordinates": [
      -109.55,
      34.1333
    ]
  },
  "type": "Feature",
  "properties": {
    "hierarchy": [
      "tgn:2637709",
      "tgn:2000090",
      "tgn:1000001",
      "tgn:7006451",
      "tgn:7012149",
      "tgn:7029392"
    ],
    "placetype": [
      "aat:300008798"
    ],
    "id": 2637709,
    "name:xx": "Saint Peters Dome"
  }
}
