{
  "geometry": {
    "type": "Point",
    "coordinates": [
      -83.0167,
      33.2167
    ]
  },
  "type": "Feature",
  "properties": {
    "hierarchy": [
      "tgn:2626126",
      "tgn:1000001",
      "tgn:7012149",
      "tgn:2000361",
      "tgn:7007248",
      "tgn:7029392"
    ],
    "placetype": [
      "aat:300008706"
    ],
    "id": 2626126,
    "name:xx": "Rocky Creek"
  }
}
