{
  "geometry": {
    "type": "Point",
    "coordinates": [
      -143.9167,
      60.2333
    ]
  },
  "type": "Feature",
  "properties": {
    "hierarchy": [
      "tgn:2217753",
      "tgn:7006450",
      "tgn:1000001",
      "tgn:7012149",
      "tgn:2000086",
      "tgn:7029392"
    ],
    "placetype": [
      "aat:300008707"
    ],
    "id": 2217753,
    "name:xx": "Campbell River"
  }
}
