{
  "type": "FeatureCollection",
  "features": [
    {
      "geometry": {
        "type": "Point",
        "coordinates": [
          -89.7333,
          32.8167
        ]
      },
      "type": "Feature",
      "properties": {
        "hierarchy": [
          "tgn:2541730",
          "tgn:1000001",
          "tgn:7012149",
          "tgn:7007522",
          "tgn:7029392"
        ],
        "placetype": [
          "aat:300008706"
        ],
        "id": 2541730,
        "name:xx": "Ninemile Creek"
      }
    },
    {
      "geometry": {
        "type": "Point",
        "coordinates": [
          -104.2333,
          45.1
        ]
      },
      "type": "Feature",
      "properties": {
        "hierarchy": [
          "tgn:2541731",
          "tgn:1000001",
          "tgn:2001265",
          "tgn:7012149",
          "tgn:7007524",
          "tgn:7029392"
        ],
        "placetype": [
          "aat:300008706"
        ],
        "id": 2541731,
        "name:xx": "Ninemile Creek"
      }
    },
    {
      "geometry": {
        "type": "Point",
        "coordinates": [
          -107.4167,
          45.8167
        ]
      },
      "type": "Feature",
      "properties": {
        "hierarchy": [
          "tgn:2541732",
          "tgn:1000001",
          "tgn:2001261",
          "tgn:7012149",
          "tgn:7007524",
          "tgn:7029392"
        ],
        "placetype": [
          "aat:300008706"
        ],
        "id": 2541732,
        "name:xx": "Ninemile Creek"
      }
    },
    {
      "geometry": {
        "type": "Point",
        "coordinates": [
          -109.1,
          46.3667
        ]
      },
      "type": "Feature",
      "properties": {
        "hierarchy": [
          "tgn:2541733",
          "tgn:1000001",
          "tgn:7012149",
          "tgn:2001278",
          "tgn:7007524",
          "tgn:7029392"
        ],
        "placetype": [
          "aat:300008706"
        ],
        "id": 2541733,
        "name:xx": "Ninemile Creek"
      }
    },
    {
      "geometry": {
        "type": "Point",
        "coordinates": [
          -114.7167,
          47.2333
        ]
      },
      "type": "Feature",
      "properties": {
        "hierarchy": [
          "tgn:2541734",
          "tgn:1000001",
          "tgn:7012149",
          "tgn:2001291",
          "tgn:7007524",
          "tgn:7029392"
        ],
        "placetype": [
          "aat:300008706"
        ],
        "id": 2541734,
        "name:xx": "Ninemile Creek"
      }
    },
    {
      "geometry": {
        "type": "Point",
        "coordinates": [
          -103.35,
          41.95
        ]
      },
      "type": "Feature",
      "properties": {
        "hierarchy": [
          "tgn:2541735",
          "tgn:1000001",
          "tgn:7012149",
          "tgn:7007525",
          "tgn:7029392"
        ],
        "placetype": [
          "aat:300008706"
        ],
        "id": 2541735,
        "name:xx": "Ninemile Creek"
      }
    },
    {
      "geometry": {
        "type": "Point",
        "coordinates": [
          -105.3333,
          36.45
        ]
      },
      "type": "Feature",
      "properties": {
        "hierarchy": [
          "tgn:2541736",
          "tgn:1000001",
          "tgn:2001432",
          "tgn:7012149",
          "tgn:7007566",
          "tgn:7029392"
        ],
        "placetype": [
          "aat:300008706"
        ],
        "id": 2541736,
        "name:xx": "Ninemile Creek"
      }
    },
    {
      "geometry": {
        "type": "Point",
        "coordinates": [
          -74.3667,
          43.2833
        ]
      },
      "type": "Feature",
      "properties": {
        "hierarchy": [
          "tgn:2541737",
          "tgn:1000001",
          "tgn:7012149",
          "tgn:1002440",
          "tgn:7007568",
          "tgn:7029392"
        ],
        "placetype": [
          "aat:300008706"
        ],
        "id": 2541737,
        "name:xx": "Ninemile Creek"
      }
    },
    {
      "geometry": {
        "type": "Point",
        "coordinates": [
          -78.5333,
          42.1667
        ]
      },
      "type": "Feature",
      "properties": {
        "hierarchy": [
          "tgn:2541738",
          "tgn:1000001",
          "tgn:1002245",
          "tgn:7012149",
          "tgn:7007568",
          "tgn:7029392"
        ],
        "placetype": [
          "aat:300008706"
        ],
        "id": 2541738,
        "name:xx": "Ninemile Creek"
      }
    },
    {
      "geometry": {
        "type": "Point",
        "coordinates": [
          -76.3,
          42.9
        ]
      },
      "type": "Feature",
      "properties": {
        "hierarchy": [
          "tgn:2541739",
          "tgn:1000001",
          "tgn:7012149",
          "tgn:1002746",
          "tgn:7007568",
          "tgn:7029392"
        ],
        "placetype": [
          "aat:300008706"
        ],
        "id": 2541739,
        "name:xx": "Ninemile Creek"
      }
    }
  ]
}
