{
  "geometry": {
    "type": "Point",
    "coordinates": [
      -105.25,
      75.25
    ]
  },
  "type": "Feature",
  "properties": {
    "hierarchy": [
      "tgn:1114099",
      "tgn:7005685",
      "tgn:1000001",
      "tgn:1000296",
      "tgn:7029392"
    ],
    "placetype": [
      "aat:300008713"
    ],
    "id": 1114099,
    "name:xx": "Byam Channel"
  }
}
