{
  "geometry": {
    "type": "Point",
    "coordinates": [
      42.8833,
      50.4167
    ]
  },
  "type": "Feature",
  "properties": {
    "hierarchy": [
      "tgn:1058189",
      "tgn:1000004",
      "tgn:7013207",
      "tgn:7018214",
      "tgn:7002435",
      "tgn:7029392"
    ],
    "placetype": [
      "aat:300008347"
    ],
    "id": 1058189,
    "name:xx": "Panfilovo"
  }
}
