{
  "geometry": {
    "type": "Point",
    "coordinates": [
      -104.6333,
      41.5333
    ]
  },
  "type": "Feature",
  "properties": {
    "hierarchy": [
      "tgn:2411442",
      "tgn:1000001",
      "tgn:7012149",
      "tgn:2002375",
      "tgn:7007923",
      "tgn:7029392"
    ],
    "placetype": [
      "aat:300008798"
    ],
    "id": 2411442,
    "name:xx": "Indian Hill"
  }
}
