{
  "geometry": {
    "type": "Point",
    "coordinates": [
      -121.45,
      46.9333
    ]
  },
  "type": "Feature",
  "properties": {
    "hierarchy": [
      "tgn:2206544",
      "tgn:1000001",
      "tgn:7012149",
      "tgn:1002785",
      "tgn:7007920",
      "tgn:7029392"
    ],
    "placetype": [
      "aat:300386845"
    ],
    "id": 2206544,
    "name:xx": "Bullion Basin"
  }
}
