{
  "geometry": {
    "type": "Point",
    "coordinates": [
      -76.7833,
      40.4667
    ]
  },
  "type": "Feature",
  "properties": {
    "hierarchy": [
      "tgn:2596733",
      "tgn:1000001",
      "tgn:1002318",
      "tgn:7012149",
      "tgn:7007710",
      "tgn:7029392"
    ],
    "placetype": [
      "aat:300008706"
    ],
    "id": 2596733,
    "name:xx": "Powell Creek"
  }
}
