{
  "geometry": {
    "type": "Point",
    "coordinates": [
      -76.5333,
      39.4833
    ]
  },
  "type": "Feature",
  "properties": {
    "hierarchy": [
      "tgn:2300389",
      "tgn:7016099",
      "tgn:1000001",
      "tgn:7012149",
      "tgn:7007516",
      "tgn:7029392"
    ],
    "placetype": [
      "aat:300008699"
    ],
    "id": 2300389,
    "name:xx": "Dulaney Branch"
  }
}
