{
  "type": "FeatureCollection",
  "features": [
    {
      "geometry": {
        "type": "Point",
        "coordinates": [
          -102.366667,
          23.25
        ]
      },
      "type": "Feature",
      "properties": {
        "hierarchy": [
          "tgn:7363270",
          "tgn:1000001",
          "tgn:7005601",
          "tgn:7005560",
          "tgn:7029392"
        ],
        "placetype": [
          "aat:300008347"
        ],
        "id": 7363270,
        "name:xx": "El Fraile"
      }
    },
    {
      "geometry": {
        "type": "Point",
        "coordinates": [
          -103.25,
          22.266667
        ]
      },
      "type": "Feature",
      "properties": {
        "hierarchy": [
          "tgn:7363271",
          "tgn:7005586",
          "tgn:1000001",
          "tgn:7005560",
          "tgn:7029392"
        ],
        "placetype": [
          "aat:300008347"
        ],
        "id": 7363271,
        "name:xx": "El Fraile"
      }
    },
    {
      "geometry": {
        "type": "Point",
        "coordinates": [
          -102.4,
          20.916667
        ]
      },
      "type": "Feature",
      "properties": {
        "hierarchy": [
          "tgn:7363272",
          "tgn:7005586",
          "tgn:1000001",
          "tgn:7005560",
          "tgn:7029392"
        ],
        "placetype": [
          "aat:300008347"
        ],
        "id": 7363272,
        "name:xx": "El Fraile"
      }
    },
    {
      "geometry": {
        "type": "Point",
        "coordinates": [
          -102.383333,
          20.466667
        ]
      },
      "type": "Feature",
      "properties": {
        "hierarchy": [
          "tgn:7363273",
          "tgn:7005586",
          "tgn:1000001",
          "tgn:7005560",
          "tgn:7029392"
        ],
        "placetype": [
          "aat:300008347"
        ],
        "id": 7363273,
        "name:xx": "El Fraile"
      }
    },
    {
      "geometry": {
        "type": "Point",
        "coordinates": [
          -106.566667,
          30.466667
        ]
      },
      "type": "Feature",
      "properties": {
        "hierarchy": [
          "tgn:7363275",
          "tgn:7005581",
          "tgn:1000001",
          "tgn:7005560",
          "tgn:7029392"
        ],
        "placetype": [
          "aat:300008347"
        ],
        "id": 7363275,
        "name:xx": "El Fortín"
      }
    },
    {
      "geometry": {
        "type": "Point",
        "coordinates": [
          -104.916667,
          29.55
        ]
      },
      "type": "Feature",
      "properties": {
        "hierarchy": [
          "tgn:7363276",
          "tgn:7005581",
          "tgn:1000001",
          "tgn:7005560",
          "tgn:7029392"
        ],
        "placetype": [
          "aat:300008347"
        ],
        "id": 7363276,
        "name:xx": "El Fortín"
      }
    },
    {
      "geometry": {
        "type": "Point",
        "coordinates": [
          -106.2,
          28.45
        ]
      },
      "type": "Feature",
      "properties": {
        "hierarchy": [
          "tgn:7363278",
          "tgn:7005581",
          "tgn:1000001",
          "tgn:7005560",
          "tgn:7029392"
        ],
        "placetype": [
          "aat:300008347"
        ],
        "id": 7363278,
        "name:xx": "El Fortín"
      }
    },
    {
      "geometry": {
        "type": "Point",
        "coordinates": [
          -102.066667,
          27.95
        ]
      },
      "type": "Feature",
      "properties": {
        "hierarchy": [
          "tgn:7363279",
          "tgn:1001853",
          "tgn:1000001",
          "tgn:7005560",
          "tgn:7029392"
        ],
        "placetype": [
          "aat:300008347"
        ],
        "id": 7363279,
        "name:xx": "El Fortín"
      }
    }
  ]
}
