{
  "type": "FeatureCollection",
  "features": [
    {
      "geometry": {
        "type": "Point",
        "coordinates": [
          -1.266667,
          51
        ]
      },
      "type": "Feature",
      "properties": {
        "hierarchy": [
          "tgn:7458931",
          "tgn:7002445",
          "tgn:1000003",
          "tgn:7008139",
          "tgn:7008591",
          "tgn:7029392"
        ],
        "placetype": [
          "aat:300008347"
        ],
        "name:en": "Owslebury",
        "id": 7458931
      }
    },
    {
      "geometry": {
        "type": "Point",
        "coordinates": [
          2,
          53.183333
        ]
      },
      "type": "Feature",
      "properties": {
        "hierarchy": [
          "tgn:7458934",
          "tgn:7002445",
          "tgn:1000003",
          "tgn:7008160",
          "tgn:7008591",
          "tgn:7029392"
        ],
        "placetype": [
          "aat:300386970"
        ],
        "name:en": "Ower Bank",
        "id": 7458934
      }
    },
    {
      "geometry": {
        "type": "Point",
        "coordinates": [
          -6.933333,
          54.933333
        ]
      },
      "type": "Feature",
      "properties": {
        "hierarchy": [
          "tgn:7458936",
          "tgn:7002448",
          "tgn:7019215",
          "tgn:1000003",
          "tgn:7008591",
          "tgn:7029392"
        ],
        "placetype": [
          "aat:300008699"
        ],
        "name:en": "Owenrigh River",
        "id": 7458936
      }
    },
    {
      "geometry": {
        "type": "Point",
        "coordinates": [
          -7.183333,
          54.716667
        ]
      },
      "type": "Feature",
      "properties": {
        "hierarchy": [
          "tgn:7458937",
          "tgn:7002448",
          "tgn:1000003",
          "tgn:7019206",
          "tgn:7008591",
          "tgn:7029392"
        ],
        "placetype": [
          "aat:300008699"
        ],
        "name:en": "Owenreagh River",
        "id": 7458937
      }
    },
    {
      "geometry": {
        "type": "Point",
        "coordinates": [
          -7.316667,
          54.55
        ]
      },
      "type": "Feature",
      "properties": {
        "hierarchy": [
          "tgn:7458938",
          "tgn:7002448",
          "tgn:1000003",
          "tgn:7019206",
          "tgn:7008591",
          "tgn:7029392"
        ],
        "placetype": [
          "aat:300008761"
        ],
        "name:en": "Owenreagh River Valley",
        "id": 7458938
      }
    }
  ]
}
