{
  "geometry": {
    "type": "Point",
    "coordinates": [
      -72.5333,
      41.25
    ]
  },
  "type": "Feature",
  "properties": {
    "hierarchy": [
      "tgn:2299790",
      "tgn:1000001",
      "tgn:1002712",
      "tgn:7012149",
      "tgn:7007159",
      "tgn:7029392"
    ],
    "placetype": [
      "aat:300008706"
    ],
    "id": 2299790,
    "name:xx": "Dudley Creek"
  }
}
