{
  "type": "FeatureCollection",
  "features": [
    {
      "geometry": {
        "type": "Point",
        "coordinates": [
          -94.9667,
          38.1
        ]
      },
      "type": "Feature",
      "properties": {
        "hierarchy": [
          "tgn:2425060",
          "tgn:1000001",
          "tgn:7012149",
          "tgn:2000713",
          "tgn:7007254",
          "tgn:7029392"
        ],
        "placetype": [
          "aat:300006191"
        ],
        "id": 2425060,
        "name:xx": "Johnson Lake"
      }
    },
    {
      "geometry": {
        "type": "Point",
        "coordinates": [
          -85.6667,
          37.7333
        ]
      },
      "type": "Feature",
      "properties": {
        "hierarchy": [
          "tgn:2425061",
          "tgn:1000001",
          "tgn:7012149",
          "tgn:2000833",
          "tgn:7007255",
          "tgn:7029392"
        ],
        "placetype": [
          "aat:300006191"
        ],
        "id": 2425061,
        "name:xx": "Johnson Lake"
      }
    },
    {
      "geometry": {
        "type": "Point",
        "coordinates": [
          -89.6667,
          30.3
        ]
      },
      "type": "Feature",
      "properties": {
        "hierarchy": [
          "tgn:2425062",
          "tgn:1000001",
          "tgn:7012149",
          "tgn:2000905",
          "tgn:7007256",
          "tgn:7029392"
        ],
        "placetype": [
          "aat:300008680"
        ],
        "id": 2425062,
        "name:xx": "Johnson Lake"
      }
    },
    {
      "geometry": {
        "type": "Point",
        "coordinates": [
          -91.5167,
          32.0667
        ]
      },
      "type": "Feature",
      "properties": {
        "hierarchy": [
          "tgn:2425063",
          "tgn:1000001",
          "tgn:7012149",
          "tgn:2000874",
          "tgn:7007256",
          "tgn:7029392"
        ],
        "placetype": [
          "aat:300008680"
        ],
        "id": 2425063,
        "name:xx": "Johnson Lake"
      }
    },
    {
      "geometry": {
        "type": "Point",
        "coordinates": [
          -91.1833,
          32.0833
        ]
      },
      "type": "Feature",
      "properties": {
        "hierarchy": [
          "tgn:2425064",
          "tgn:1000001",
          "tgn:7012149",
          "tgn:2000907",
          "tgn:7007256",
          "tgn:7029392"
        ],
        "placetype": [
          "aat:300008680"
        ],
        "id": 2425064,
        "name:xx": "Johnson Lake"
      }
    },
    {
      "geometry": {
        "type": "Point",
        "coordinates": [
          -91.3167,
          32.8
        ]
      },
      "type": "Feature",
      "properties": {
        "hierarchy": [
          "tgn:2425065",
          "tgn:1000001",
          "tgn:2000871",
          "tgn:7012149",
          "tgn:7007256",
          "tgn:7029392"
        ],
        "placetype": [
          "aat:300008680"
        ],
        "id": 2425065,
        "name:xx": "Johnson Lake"
      }
    },
    {
      "geometry": {
        "type": "Point",
        "coordinates": [
          -86.0833,
          42.1167
        ]
      },
      "type": "Feature",
      "properties": {
        "hierarchy": [
          "tgn:2425066",
          "tgn:1000001",
          "tgn:7012149",
          "tgn:1002967",
          "tgn:7007520",
          "tgn:7029392"
        ],
        "placetype": [
          "aat:300008680"
        ],
        "id": 2425066,
        "name:xx": "Johnson Lake"
      }
    },
    {
      "geometry": {
        "type": "Point",
        "coordinates": [
          -83.95,
          44.2
        ]
      },
      "type": "Feature",
      "properties": {
        "hierarchy": [
          "tgn:2425067",
          "tgn:1000001",
          "tgn:7012149",
          "tgn:2000985",
          "tgn:7007520",
          "tgn:7029392"
        ],
        "placetype": [
          "aat:300008680"
        ],
        "id": 2425067,
        "name:xx": "Johnson Lake"
      }
    },
    {
      "geometry": {
        "type": "Point",
        "coordinates": [
          -84.5833,
          44.8167
        ]
      },
      "type": "Feature",
      "properties": {
        "hierarchy": [
          "tgn:2425068",
          "tgn:1000001",
          "tgn:2000954",
          "tgn:7012149",
          "tgn:7007520",
          "tgn:7029392"
        ],
        "placetype": [
          "aat:300008680"
        ],
        "id": 2425068,
        "name:xx": "Johnson Lake"
      }
    },
    {
      "geometry": {
        "type": "Point",
        "coordinates": [
          -87.7667,
          45.4167
        ]
      },
      "type": "Feature",
      "properties": {
        "hierarchy": [
          "tgn:2425069",
          "tgn:1000001",
          "tgn:7012149",
          "tgn:2000978",
          "tgn:7007520",
          "tgn:7029392"
        ],
        "placetype": [
          "aat:300008680"
        ],
        "id": 2425069,
        "name:xx": "Johnson Lake"
      }
    }
  ]
}
