{
  "geometry": {
    "type": "Point",
    "coordinates": [
      -99.7833,
      45.6667
    ]
  },
  "type": "Feature",
  "properties": {
    "hierarchy": [
      "tgn:2330769",
      "tgn:1000001",
      "tgn:2001780",
      "tgn:7012149",
      "tgn:7007713",
      "tgn:7029392"
    ],
    "placetype": [
      "aat:300008680"
    ],
    "id": 2330769,
    "name:xx": "Flat Lake"
  }
}
