{
  "geometry": {
    "type": "Point",
    "coordinates": [
      7.866667,
      50.95
    ]
  },
  "type": "Feature",
  "properties": {
    "hierarchy": [
      "tgn:7164102",
      "tgn:1000003",
      "tgn:7003677",
      "tgn:7000084",
      "tgn:7029392"
    ],
    "placetype": [
      "aat:300008777"
    ],
    "id": 7164102,
    "name:xx": "Hüns-Berg"
  }
}
