{
  "geometry": {
    "type": "Point",
    "coordinates": [
      -82.5833,
      30.6167
    ]
  },
  "type": "Feature",
  "properties": {
    "hierarchy": [
      "tgn:2507213",
      "tgn:1000001",
      "tgn:7012149",
      "tgn:2000341",
      "tgn:7007248",
      "tgn:7029392"
    ],
    "placetype": [
      "aat:300008905"
    ],
    "id": 2507213,
    "name:xx": "Mett Bay"
  }
}
