{
  "geometry": {
    "type": "Point",
    "coordinates": [
      31.05,
      28.05
    ]
  },
  "type": "Feature",
  "properties": {
    "hierarchy": [
      "tgn:7538627",
      "tgn:7001242",
      "tgn:7001311",
      "tgn:7016833",
      "tgn:7029392"
    ],
    "placetype": [
      "aat:300259572"
    ],
    "name:en": "Mulaysah, Naqb",
    "id": 7538627
  }
}
