{
  "geometry": {
    "type": "Point",
    "coordinates": [
      -153.8667,
      59.65
    ]
  },
  "type": "Feature",
  "properties": {
    "hierarchy": [
      "tgn:2663139",
      "tgn:7006450",
      "tgn:1000001",
      "tgn:7012149",
      "tgn:7029392"
    ],
    "placetype": [
      "aat:300008706"
    ],
    "id": 2663139,
    "name:xx": "Silver Creek"
  }
}
