{
  "geometry": {
    "type": "Point",
    "coordinates": [
      32.2833,
      1.4667
    ]
  },
  "type": "Feature",
  "properties": {
    "hierarchy": [
      "tgn:1095087",
      "tgn:7001242",
      "tgn:1000909",
      "tgn:1000206",
      "tgn:7029392"
    ],
    "placetype": [
      "aat:300008347"
    ],
    "id": 1095087,
    "name:xx": "Nabiswera"
  }
}
