{
  "geometry": {
    "type": "Point",
    "coordinates": [
      -78.5333,
      38.55
    ]
  },
  "type": "Feature",
  "properties": {
    "hierarchy": [
      "tgn:2585133",
      "tgn:1000001",
      "tgn:7012149",
      "tgn:2002178",
      "tgn:7007919",
      "tgn:7029392"
    ],
    "placetype": [
      "aat:300008798"
    ],
    "id": 2585133,
    "name:xx": "Pinnacle, The"
  }
}
