{
  "geometry": {
    "type": "Point",
    "coordinates": [
      75.019444,
      34.561111
    ]
  },
  "type": "Feature",
  "properties": {
    "hierarchy": [
      "tgn:7591552",
      "tgn:1000004",
      "tgn:7000198",
      "tgn:7000799",
      "tgn:7029392"
    ],
    "placetype": [
      "aat:300008347"
    ],
    "name:en": "Sultāna",
    "id": 7591552
  }
}
