{
  "geometry": {
    "type": "Point",
    "coordinates": [
      -81.0333,
      35.0333
    ]
  },
  "type": "Feature",
  "properties": {
    "hierarchy": [
      "tgn:2783661",
      "tgn:1000001",
      "tgn:7012149",
      "tgn:7029392"
    ],
    "placetype": [
      "aat:300006191"
    ],
    "id": 2783661,
    "name:xx": "Wylie, Lake"
  }
}
