{
  "geometry": {
    "type": "Point",
    "coordinates": [
      -77.05,
      35.6833
    ]
  },
  "type": "Feature",
  "properties": {
    "hierarchy": [
      "tgn:2369308",
      "tgn:1000001",
      "tgn:7012149",
      "tgn:7007709",
      "tgn:7029392"
    ],
    "placetype": [
      "aat:300008699"
    ],
    "id": 2369308,
    "name:xx": "Gum Swamp"
  }
}
