{
  "geometry": {
    "type": "Point",
    "coordinates": [
      -94.85,
      39.7167
    ]
  },
  "type": "Feature",
  "properties": {
    "hierarchy": [
      "tgn:2437837",
      "tgn:1000001",
      "tgn:2001175",
      "tgn:7012149",
      "tgn:7007523",
      "tgn:7029392"
    ],
    "placetype": [
      "aat:300008798"
    ],
    "id": 2437837,
    "name:xx": "King Hill"
  }
}
