{
  "geometry": {
    "type": "Point",
    "coordinates": [
      -82.4333,
      36.8167
    ]
  },
  "type": "Feature",
  "properties": {
    "hierarchy": [
      "tgn:2603894",
      "tgn:1000001",
      "tgn:7012149",
      "tgn:7022249",
      "tgn:2002189",
      "tgn:7007919",
      "tgn:7029392"
    ],
    "placetype": [
      "aat:300008746"
    ],
    "id": 2603894,
    "name:xx": "Quillen Cave Number 2"
  }
}
