{
  "geometry": {
    "type": "Point",
    "coordinates": [
      -86.7333,
      37.9667
    ]
  },
  "type": "Feature",
  "properties": {
    "hierarchy": [
      "tgn:2433022",
      "tgn:1000001",
      "tgn:7012149",
      "tgn:2000550",
      "tgn:7007252",
      "tgn:7029392"
    ],
    "placetype": [
      "aat:300008798"
    ],
    "id": 2433022,
    "name:xx": "Keiser Hill"
  }
}
