{
  "geometry": {
    "type": "Point",
    "coordinates": [
      3.3833,
      6.45
    ]
  },
  "type": "Feature",
  "properties": {
    "hierarchy": [
      "tgn:1007786",
      "tgn:7001242",
      "tgn:1001889",
      "tgn:7000497",
      "tgn:1000182",
      "tgn:7029392"
    ],
    "placetype": [
      "aat:300008791"
    ],
    "id": 1007786,
    "name:xx": "Lagos Island"
  }
}
