{
  "geometry": {
    "type": "Point",
    "coordinates": [
      -73.3333,
      44.5333
    ]
  },
  "type": "Feature",
  "properties": {
    "hierarchy": [
      "tgn:7024078",
      "tgn:1000001",
      "tgn:7029392"
    ],
    "placetype": [
      "aat:300008680"
    ],
    "id": 7024078,
    "name:xx": "Champlain, Lake"
  }
}
