{
  "geometry": {
    "type": "Point",
    "coordinates": [
      -81.0833,
      28.95
    ]
  },
  "type": "Feature",
  "properties": {
    "hierarchy": [
      "tgn:2479561",
      "tgn:1000001",
      "tgn:7012149",
      "tgn:1002977",
      "tgn:7007240",
      "tgn:7029392"
    ],
    "placetype": [
      "aat:300008706"
    ],
    "id": 2479561,
    "name:xx": "Lake Ashby Creek"
  }
}
