{
  "geometry": {
    "type": "Point",
    "coordinates": [
      -84.7667,
      37.3667
    ]
  },
  "type": "Feature",
  "properties": {
    "hierarchy": [
      "tgn:2460141",
      "tgn:1000001",
      "tgn:7012149",
      "tgn:2000813",
      "tgn:7007255",
      "tgn:7029392"
    ],
    "placetype": [
      "aat:300008798"
    ],
    "id": 2460141,
    "name:xx": "Little Round Hill"
  }
}
