{
  "geometry": {
    "type": "Point",
    "coordinates": [
      20.6333,
      8.4167
    ]
  },
  "type": "Feature",
  "properties": {
    "hierarchy": [
      "tgn:1088413",
      "tgn:1000964",
      "tgn:7001242",
      "tgn:1000155",
      "tgn:7029392"
    ],
    "placetype": [
      "aat:300008347",
      "aat:300387220"
    ],
    "id": 1088413,
    "name:xx": "Ndélé"
  }
}
