{
  "geometry": {
    "type": "Point",
    "coordinates": [
      -79.8167,
      38.9333
    ]
  },
  "type": "Feature",
  "properties": {
    "hierarchy": [
      "tgn:2204764",
      "tgn:1000001",
      "tgn:7012149",
      "tgn:2002291",
      "tgn:7013961",
      "tgn:7029392"
    ],
    "placetype": [
      "aat:300008699"
    ],
    "id": 2204764,
    "name:xx": "Buffalo Run"
  }
}
