{
  "geometry": {
    "type": "Point",
    "coordinates": [
      -83.2833,
      41.65
    ]
  },
  "type": "Feature",
  "properties": {
    "hierarchy": [
      "tgn:2614922",
      "tgn:1000001",
      "tgn:7012149",
      "tgn:1002611",
      "tgn:7007706",
      "tgn:7029392"
    ],
    "placetype": [
      "aat:300006075"
    ],
    "id": 2614922,
    "name:xx": "Reno Side Cut"
  }
}
