{
  "type": "FeatureCollection",
  "features": [
    {
      "geometry": {
        "type": "Point",
        "coordinates": [
          120.3591,
          22.5124
        ]
      },
      "type": "Feature",
      "properties": {
        "hierarchy": [
          "tgn:6001985",
          "tgn:7001004",
          "tgn:1000004",
          "tgn:1000141",
          "tgn:7029392"
        ],
        "placetype": [
          "aat:300008347",
          "aat:300008375"
        ],
        "id": 6001985,
        "name:xx": "Feng-pi-t'ou"
      }
    },
    {
      "geometry": {
        "type": "Point",
        "coordinates": [
          24.0667,
          45.1333
        ]
      },
      "type": "Feature",
      "properties": {
        "hierarchy": [
          "tgn:6001989",
          "tgn:1000003",
          "tgn:1000463",
          "tgn:1000091",
          "tgn:7029392"
        ],
        "placetype": [
          "aat:300008347",
          "aat:300000810",
          "aat:300008375"
        ],
        "id": 6001989,
        "name:xx": "Ferigile"
      }
    }
  ]
}
