{
  "geometry": {
    "type": "Point",
    "coordinates": [
      -121.7333,
      46.4833
    ]
  },
  "type": "Feature",
  "properties": {
    "hierarchy": [
      "tgn:2736518",
      "tgn:1000001",
      "tgn:7012149",
      "tgn:1002594",
      "tgn:7007920",
      "tgn:7029392"
    ],
    "placetype": [
      "aat:300008798"
    ],
    "id": 2736518,
    "name:xx": "Twin Sisters"
  }
}
