{
  "geometry": {
    "type": "Point",
    "coordinates": [
      -97.4667,
      33.2167
    ]
  },
  "type": "Feature",
  "properties": {
    "hierarchy": [
      "tgn:2524958",
      "tgn:1000001",
      "tgn:7012149",
      "tgn:7007826",
      "tgn:7029392"
    ],
    "placetype": [
      "aat:300008699"
    ],
    "id": 2524958,
    "name:xx": "Morris Branch"
  }
}
