{
  "geometry": {
    "type": "Point",
    "coordinates": [
      -84.5833,
      36.5833
    ]
  },
  "type": "Feature",
  "properties": {
    "hierarchy": [
      "tgn:2191621",
      "tgn:1000001",
      "tgn:7012149",
      "tgn:7029392"
    ],
    "placetype": [
      "aat:300008699"
    ],
    "id": 2191621,
    "name:xx": "Bradley Branch"
  }
}
