{
  "geometry": {
    "type": "Point",
    "coordinates": [
      1.5667,
      44.4667
    ]
  },
  "type": "Feature",
  "properties": {
    "hierarchy": [
      "tgn:1035326",
      "tgn:1000003",
      "tgn:7002889",
      "tgn:1000070",
      "tgn:7029392"
    ],
    "placetype": [
      "aat:300008347"
    ],
    "id": 1035326,
    "name:xx": "Saint-Géry"
  }
}
