{
  "geometry": {
    "type": "Point",
    "coordinates": [
      -98.7667,
      38.45
    ]
  },
  "type": "Feature",
  "properties": {
    "hierarchy": [
      "tgn:2150090",
      "tgn:2000664",
      "tgn:1000001",
      "tgn:7012149",
      "tgn:7007254",
      "tgn:7029392"
    ],
    "placetype": [
      "aat:300006191"
    ],
    "id": 2150090,
    "name:xx": "Barton Lake"
  }
}
