{
  "geometry": {
    "type": "Point",
    "coordinates": [
      -113.5167,
      36.6333
    ]
  },
  "type": "Feature",
  "properties": {
    "hierarchy": [
      "tgn:2717425",
      "tgn:1000001",
      "tgn:7006451",
      "tgn:7012149",
      "tgn:2000098",
      "tgn:7029392"
    ],
    "placetype": [
      "aat:300006191"
    ],
    "id": 2717425,
    "name:xx": "Thistle Flat Pond"
  }
}
