{
  "geometry": {
    "type": "Point",
    "coordinates": [
      -124.2167,
      43.25
    ]
  },
  "type": "Feature",
  "properties": {
    "hierarchy": [
      "tgn:2438405",
      "tgn:1000001",
      "tgn:2001702",
      "tgn:7012149",
      "tgn:7007708",
      "tgn:7029392"
    ],
    "placetype": [
      "aat:300008347"
    ],
    "id": 2438405,
    "name:xx": "Kings Landing"
  }
}
