{
  "geometry": {
    "type": "Point",
    "coordinates": [
      -171.9833,
      -13.9167
    ]
  },
  "type": "Feature",
  "properties": {
    "hierarchy": [
      "tgn:1099659",
      "tgn:1009572",
      "tgn:1000239",
      "tgn:1000006",
      "tgn:7029392"
    ],
    "placetype": [
      "aat:300008347"
    ],
    "id": 1099659,
    "name:xx": "Falelatai"
  }
}
