{
  "geometry": {
    "type": "Point",
    "coordinates": [
      -98.1167,
      31.35
    ]
  },
  "type": "Feature",
  "properties": {
    "hierarchy": [
      "tgn:2512194",
      "tgn:1000001",
      "tgn:7012149",
      "tgn:2002026",
      "tgn:7007826",
      "tgn:7029392"
    ],
    "placetype": [
      "aat:300008699"
    ],
    "id": 2512194,
    "name:xx": "Mill Branch"
  }
}
