{
  "geometry": {
    "type": "Point",
    "coordinates": [
      -65.3833,
      9.4167
    ]
  },
  "type": "Feature",
  "properties": {
    "hierarchy": [
      "tgn:1130562",
      "tgn:1001866",
      "tgn:1000002",
      "tgn:1000059",
      "tgn:7029392"
    ],
    "placetype": [
      "aat:300008707"
    ],
    "id": 1130562,
    "name:xx": "Tamanaco, Río"
  }
}
