{
  "geometry": {
    "type": "Point",
    "coordinates": [
      8.6833,
      49.7333
    ]
  },
  "type": "Feature",
  "properties": {
    "hierarchy": [
      "tgn:1105603",
      "tgn:1000003",
      "tgn:7003678",
      "tgn:7000084",
      "tgn:7029392"
    ],
    "placetype": [
      "aat:300008795"
    ],
    "id": 1105603,
    "name:xx": "Malibocus"
  }
}
