{
  "type": "FeatureCollection",
  "features": [
    {
      "geometry": {
        "type": "Point",
        "coordinates": [
          -111.416667,
          28.75
        ]
      },
      "type": "Feature",
      "properties": {
        "hierarchy": [
          "tgn:7363430",
          "tgn:1000001",
          "tgn:1001960",
          "tgn:7005560",
          "tgn:7029392"
        ],
        "placetype": [
          "aat:300008347"
        ],
        "id": 7363430,
        "name:xx": "El Alamo"
      }
    },
    {
      "geometry": {
        "type": "Point",
        "coordinates": [
          -110.366667,
          28.666667
        ]
      },
      "type": "Feature",
      "properties": {
        "hierarchy": [
          "tgn:7363431",
          "tgn:1000001",
          "tgn:1001960",
          "tgn:7005560",
          "tgn:7029392"
        ],
        "placetype": [
          "aat:300008347"
        ],
        "id": 7363431,
        "name:xx": "El Álamo"
      }
    },
    {
      "geometry": {
        "type": "Point",
        "coordinates": [
          -106.433333,
          28.35
        ]
      },
      "type": "Feature",
      "properties": {
        "hierarchy": [
          "tgn:7363432",
          "tgn:7005581",
          "tgn:1000001",
          "tgn:7005560",
          "tgn:7029392"
        ],
        "placetype": [
          "aat:300008347"
        ],
        "id": 7363432,
        "name:xx": "El Alamo"
      }
    },
    {
      "geometry": {
        "type": "Point",
        "coordinates": [
          -100.583333,
          21.566667
        ]
      },
      "type": "Feature",
      "properties": {
        "hierarchy": [
          "tgn:7363433",
          "tgn:1000001",
          "tgn:7005594",
          "tgn:7005560",
          "tgn:7029392"
        ],
        "placetype": [
          "aat:300008347"
        ],
        "id": 7363433,
        "name:xx": "El Minero"
      }
    },
    {
      "geometry": {
        "type": "Point",
        "coordinates": [
          -106.15,
          30
        ]
      },
      "type": "Feature",
      "properties": {
        "hierarchy": [
          "tgn:7363434",
          "tgn:7005581",
          "tgn:1000001",
          "tgn:7005560",
          "tgn:7029392"
        ],
        "placetype": [
          "aat:300000241"
        ],
        "id": 7363434,
        "name:xx": "Rancho El Mimbre"
      }
    },
    {
      "geometry": {
        "type": "Point",
        "coordinates": [
          -104.283333,
          28.766667
        ]
      },
      "type": "Feature",
      "properties": {
        "hierarchy": [
          "tgn:7363435",
          "tgn:7005581",
          "tgn:1000001",
          "tgn:7005560",
          "tgn:7029392"
        ],
        "placetype": [
          "aat:300000241"
        ],
        "id": 7363435,
        "name:xx": "Rancho El Mimbre"
      }
    },
    {
      "geometry": {
        "type": "Point",
        "coordinates": [
          -104.816667,
          28.65
        ]
      },
      "type": "Feature",
      "properties": {
        "hierarchy": [
          "tgn:7363436",
          "tgn:7005581",
          "tgn:1000001",
          "tgn:7005560",
          "tgn:7029392"
        ],
        "placetype": [
          "aat:300000241"
        ],
        "id": 7363436,
        "name:xx": "Rancho El Mimbre"
      }
    },
    {
      "geometry": {
        "type": "Point",
        "coordinates": [
          -101.066667,
          28.416667
        ]
      },
      "type": "Feature",
      "properties": {
        "hierarchy": [
          "tgn:7363437",
          "tgn:1001853",
          "tgn:1000001",
          "tgn:7005560",
          "tgn:7029392"
        ],
        "placetype": [
          "aat:300000241"
        ],
        "id": 7363437,
        "name:xx": "Rancho El Mimbre"
      }
    },
    {
      "geometry": {
        "type": "Point",
        "coordinates": [
          -105,
          27.8
        ]
      },
      "type": "Feature",
      "properties": {
        "hierarchy": [
          "tgn:7363438",
          "tgn:7005581",
          "tgn:1000001",
          "tgn:7005560",
          "tgn:7029392"
        ],
        "placetype": [
          "aat:300000241"
        ],
        "id": 7363438,
        "name:xx": "Rancho El Mimbre"
      }
    },
    {
      "geometry": {
        "type": "Point",
        "coordinates": [
          -104.633333,
          27.716667
        ]
      },
      "type": "Feature",
      "properties": {
        "hierarchy": [
          "tgn:7363439",
          "tgn:7005581",
          "tgn:1000001",
          "tgn:7005560",
          "tgn:7029392"
        ],
        "placetype": [
          "aat:300000241"
        ],
        "id": 7363439,
        "name:xx": "Rancho El Mimbre"
      }
    }
  ]
}
