{
  "geometry": {
    "type": "Point",
    "coordinates": [
      -109.0333,
      32.25
    ]
  },
  "type": "Feature",
  "properties": {
    "hierarchy": [
      "tgn:2535959",
      "tgn:1000001",
      "tgn:7012149",
      "tgn:2001440",
      "tgn:7007566",
      "tgn:7029392"
    ],
    "placetype": [
      "aat:300000390"
    ],
    "id": 2535959,
    "name:xx": "National Mine"
  }
}
