{
  "geometry": {
    "type": "Point",
    "coordinates": [
      16.1333,
      46.5333
    ]
  },
  "type": "Feature",
  "properties": {
    "hierarchy": [
      "tgn:7015115",
      "tgn:1000003",
      "tgn:7006670",
      "tgn:7029392"
    ],
    "placetype": [
      "aat:300387064",
      "aat:300387081"
    ],
    "id": 7015115,
    "name:xx": "Ljutomer, Občina"
  }
}
