{
  "geometry": {
    "type": "Point",
    "coordinates": [
      -121.5667,
      46.4167
    ]
  },
  "type": "Feature",
  "properties": {
    "hierarchy": [
      "tgn:2314559",
      "tgn:1000001",
      "tgn:7012149",
      "tgn:1002594",
      "tgn:7007920",
      "tgn:7029392"
    ],
    "placetype": [
      "aat:300008798"
    ],
    "id": 2314559,
    "name:xx": "Elk Peak"
  }
}
