{
  "geometry": {
    "type": "Point",
    "coordinates": [
      -111.1667,
      39.3667
    ]
  },
  "type": "Feature",
  "properties": {
    "hierarchy": [
      "tgn:2764384",
      "tgn:1000001",
      "tgn:2002108",
      "tgn:7012149",
      "tgn:7007827",
      "tgn:7029392"
    ],
    "placetype": [
      "aat:300008706"
    ],
    "id": 2764384,
    "name:xx": "Whetstone Creek"
  }
}
