{
  "geometry": {
    "type": "Point",
    "coordinates": [
      -75.2333,
      40.3167
    ]
  },
  "type": "Feature",
  "properties": {
    "hierarchy": [
      "tgn:2609722",
      "tgn:1000001",
      "tgn:1002213",
      "tgn:7012149",
      "tgn:7007710",
      "tgn:7029392"
    ],
    "placetype": [
      "aat:300008706"
    ],
    "id": 2609722,
    "name:xx": "Reading Creek"
  }
}
