{
  "geometry": {
    "type": "Point",
    "coordinates": [
      -85.5667,
      34.5667
    ]
  },
  "type": "Feature",
  "properties": {
    "hierarchy": [
      "tgn:2522219",
      "tgn:7002659",
      "tgn:1000001",
      "tgn:7012149",
      "tgn:7021514",
      "tgn:7029392"
    ],
    "placetype": [
      "aat:300008680"
    ],
    "id": 2522219,
    "name:xx": "Moon Lake"
  }
}
