{
  "geometry": {
    "type": "Point",
    "coordinates": [
      -104.8333,
      56.1333
    ]
  },
  "type": "Feature",
  "properties": {
    "hierarchy": [
      "tgn:1117684",
      "tgn:7005685",
      "tgn:1000001",
      "tgn:7005805",
      "tgn:7029392"
    ],
    "placetype": [
      "aat:300008680"
    ],
    "id": 1117684,
    "name:xx": "Paull Lake"
  }
}
