{
  "geometry": {
    "type": "Point",
    "coordinates": [
      3.55,
      50.633333
    ]
  },
  "type": "Feature",
  "properties": {
    "hierarchy": [
      "tgn:7254653",
      "tgn:7007877",
      "tgn:1000003",
      "tgn:1000063",
      "tgn:4012014",
      "tgn:7029392"
    ],
    "placetype": [
      "aat:300008347"
    ],
    "id": 7254653,
    "name:xx": "Vériom Planque"
  }
}
