{
  "geometry": {
    "type": "Point",
    "coordinates": [
      -115.45,
      44.8167
    ]
  },
  "type": "Feature",
  "properties": {
    "hierarchy": [
      "tgn:2678021",
      "tgn:1000001",
      "tgn:7012149",
      "tgn:2000494",
      "tgn:7007250",
      "tgn:7029392"
    ],
    "placetype": [
      "aat:300008706"
    ],
    "id": 2678021,
    "name:xx": "South Fork Bear Creek"
  }
}
