{
  "geometry": {
    "type": "Point",
    "coordinates": [
      -104.65,
      38.0333
    ]
  },
  "type": "Feature",
  "properties": {
    "hierarchy": [
      "tgn:2487976",
      "tgn:1000001",
      "tgn:7012149",
      "tgn:7007158",
      "tgn:2000242",
      "tgn:7029392"
    ],
    "placetype": [
      "aat:300008798"
    ],
    "id": 2487976,
    "name:xx": "Maggies Knob"
  }
}
