{
  "geometry": {
    "type": "Point",
    "coordinates": [
      1.265025,
      42.56085
    ]
  },
  "type": "Feature",
  "properties": {
    "hierarchy": [
      "tgn:7342801",
      "tgn:7008912",
      "tgn:7030216",
      "tgn:1000003",
      "tgn:1000095",
      "tgn:7029392"
    ],
    "placetype": [
      "aat:300008798"
    ],
    "id": 7342801,
    "name:xx": "Casibrós, Puig"
  }
}
