{
  "geometry": {
    "type": "Point",
    "coordinates": [
      -74.0333,
      41.1667
    ]
  },
  "type": "Feature",
  "properties": {
    "hierarchy": [
      "tgn:2375926",
      "tgn:1000001",
      "tgn:7012149",
      "tgn:1002833",
      "tgn:7007568",
      "tgn:7029392"
    ],
    "placetype": [
      "aat:300008347"
    ],
    "id": 2375926,
    "name:xx": "Happy Valley"
  }
}
