{
  "geometry": {
    "type": "Point",
    "coordinates": [
      43.4833,
      17.6667
    ]
  },
  "type": "Feature",
  "properties": {
    "hierarchy": [
      "tgn:1084781",
      "tgn:7003883",
      "tgn:7003875",
      "tgn:1000004",
      "tgn:1000137",
      "tgn:7029392"
    ],
    "placetype": [
      "aat:300008347"
    ],
    "id": 1084781,
    "name:xx": "Ẓahrān"
  }
}
