{
  "geometry": {
    "type": "Point",
    "coordinates": [
      -113.6667,
      42.3667
    ]
  },
  "type": "Feature",
  "properties": {
    "hierarchy": [
      "tgn:2361829",
      "tgn:1000001",
      "tgn:2000467",
      "tgn:7012149",
      "tgn:7007250",
      "tgn:7029392"
    ],
    "placetype": [
      "aat:300008761"
    ],
    "id": 2361829,
    "name:xx": "Gray Canyon"
  }
}
