{
  "geometry": {
    "type": "Point",
    "coordinates": [
      20.3333,
      -13.1167
    ]
  },
  "type": "Feature",
  "properties": {
    "hierarchy": [
      "tgn:1087712",
      "tgn:7001242",
      "tgn:1000149",
      "tgn:1000899",
      "tgn:7029392"
    ],
    "placetype": [
      "aat:300008347"
    ],
    "id": 1087712,
    "name:xx": "Cassamba"
  }
}
