{
  "geometry": {
    "type": "Point",
    "coordinates": [
      127.2167,
      36.35
    ]
  },
  "type": "Feature",
  "properties": {
    "hierarchy": [
      "tgn:1101651",
      "tgn:1001190",
      "tgn:1000004",
      "tgn:7000299",
      "tgn:7029392"
    ],
    "placetype": [
      "aat:300008189"
    ],
    "id": 1101651,
    "name:xx": "Kyeryong-san Kukrip Kongwŏn"
  }
}
