{
  "geometry": {
    "type": "Point",
    "coordinates": [
      -109.9167,
      33.7833
    ]
  },
  "type": "Feature",
  "properties": {
    "hierarchy": [
      "tgn:2006756",
      "tgn:1000001",
      "tgn:7006451",
      "tgn:7012149",
      "tgn:2000099",
      "tgn:7029392"
    ],
    "placetype": [
      "aat:300008347"
    ],
    "id": 2006756,
    "name:xx": "East Fork"
  }
}
