{
  "geometry": {
    "type": "Point",
    "coordinates": [
      -122.4167,
      39.4167
    ]
  },
  "type": "Feature",
  "properties": {
    "hierarchy": [
      "tgn:2389869",
      "tgn:1000001",
      "tgn:7012149",
      "tgn:1002409",
      "tgn:7007157",
      "tgn:7029392"
    ],
    "placetype": [
      "aat:300008798"
    ],
    "id": 2389869,
    "name:xx": "High Peak"
  }
}
