{
  "geometry": {
    "type": "Point",
    "coordinates": [
      -8.7167,
      52.5167
    ]
  },
  "type": "Feature",
  "properties": {
    "hierarchy": [
      "tgn:1042744",
      "tgn:7003496",
      "tgn:7001201",
      "tgn:1000003",
      "tgn:1000078",
      "tgn:7029392"
    ],
    "placetype": [
      "aat:300008347"
    ],
    "id": 1042744,
    "name:xx": "Croom"
  }
}
