{
  "geometry": {
    "type": "Point",
    "coordinates": [
      -110.0333,
      40.5667
    ]
  },
  "type": "Feature",
  "properties": {
    "hierarchy": [
      "tgn:2179626",
      "tgn:1000001",
      "tgn:2002107",
      "tgn:7012149",
      "tgn:7007827",
      "tgn:7029392"
    ],
    "placetype": [
      "aat:300008697"
    ],
    "id": 2179626,
    "name:xx": "Blank Spring"
  }
}
