{
  "geometry": {
    "type": "Point",
    "coordinates": [
      34.5325,
      30.462222
    ]
  },
  "type": "Feature",
  "properties": {
    "hierarchy": [
      "tgn:7529948",
      "tgn:7001242",
      "tgn:7016833",
      "tgn:7001335",
      "tgn:7029392"
    ],
    "placetype": [
      "aat:300379998"
    ],
    "name:en": "Luşşān, Wādī",
    "id": 7529948
  }
}
