{
  "geometry": {
    "type": "Point",
    "coordinates": [
      31.257107,
      30.033451
    ]
  },
  "type": "Feature",
  "properties": {
    "hierarchy": [
      "tgn:7527149",
      "tgn:7001242",
      "tgn:7016833",
      "tgn:1001091",
      "tgn:7029392"
    ],
    "placetype": [
      "aat:300005768"
    ],
    "id": 7527149,
    "name:xx": "Mutḩaf Jawharat al Lālā"
  }
}
