{
  "geometry": {
    "type": "Point",
    "coordinates": [
      -162.8167,
      64.5667
    ]
  },
  "type": "Feature",
  "properties": {
    "hierarchy": [
      "tgn:2200742",
      "tgn:7006450",
      "tgn:1000001",
      "tgn:7012149",
      "tgn:2000079",
      "tgn:7029392"
    ],
    "placetype": [
      "aat:300008706"
    ],
    "id": 2200742,
    "name:xx": "Bryan Creek"
  }
}
