{
  "geometry": {
    "type": "Point",
    "coordinates": [
      -54.9333,
      -2.0667
    ]
  },
  "type": "Feature",
  "properties": {
    "hierarchy": [
      "tgn:1006315",
      "tgn:7006247",
      "tgn:1000047",
      "tgn:7002456",
      "tgn:1000002",
      "tgn:7029392"
    ],
    "placetype": [
      "aat:300008791"
    ],
    "id": 1006315,
    "name:xx": "Arapiri, Ilha"
  }
}
