{
  "type": "FeatureCollection",
  "features": [
    {
      "geometry": {
        "type": "Point",
        "coordinates": [
          -92.2667,
          34.4
        ]
      },
      "type": "Feature",
      "properties": {
        "hierarchy": [
          "tgn:2775310",
          "tgn:1000001",
          "tgn:7016172",
          "tgn:7012149",
          "tgn:2000131",
          "tgn:7029392"
        ],
        "placetype": [
          "aat:300008699"
        ],
        "id": 2775310,
        "name:xx": "Wilson Branch"
      }
    },
    {
      "geometry": {
        "type": "Point",
        "coordinates": [
          -91.7167,
          35.8833
        ]
      },
      "type": "Feature",
      "properties": {
        "hierarchy": [
          "tgn:2775311",
          "tgn:1000001",
          "tgn:7016172",
          "tgn:7012149",
          "tgn:2000136",
          "tgn:7029392"
        ],
        "placetype": [
          "aat:300008699"
        ],
        "id": 2775311,
        "name:xx": "Wilson Branch"
      }
    },
    {
      "geometry": {
        "type": "Point",
        "coordinates": [
          -92.8,
          33.0333
        ]
      },
      "type": "Feature",
      "properties": {
        "hierarchy": [
          "tgn:2775312",
          "tgn:1000001",
          "tgn:7012149",
          "tgn:7029392"
        ],
        "placetype": [
          "aat:300008699"
        ],
        "id": 2775312,
        "name:xx": "Wilson Branch"
      }
    },
    {
      "geometry": {
        "type": "Point",
        "coordinates": [
          -84.8,
          30.5667
        ]
      },
      "type": "Feature",
      "properties": {
        "hierarchy": [
          "tgn:2775313",
          "tgn:1000001",
          "tgn:2000268",
          "tgn:7012149",
          "tgn:7007240",
          "tgn:7029392"
        ],
        "placetype": [
          "aat:300008699"
        ],
        "id": 2775313,
        "name:xx": "Wilson Branch"
      }
    },
    {
      "geometry": {
        "type": "Point",
        "coordinates": [
          -87.1833,
          30.9333
        ]
      },
      "type": "Feature",
      "properties": {
        "hierarchy": [
          "tgn:2775314",
          "tgn:1000001",
          "tgn:7012149",
          "tgn:7007240",
          "tgn:7029392"
        ],
        "placetype": [
          "aat:300008699"
        ],
        "id": 2775314,
        "name:xx": "Wilson Branch"
      }
    },
    {
      "geometry": {
        "type": "Point",
        "coordinates": [
          -83.35,
          32.5333
        ]
      },
      "type": "Feature",
      "properties": {
        "hierarchy": [
          "tgn:2775315",
          "tgn:1000001",
          "tgn:7012149",
          "tgn:7007248",
          "tgn:7029392"
        ],
        "placetype": [
          "aat:300008699"
        ],
        "id": 2775315,
        "name:xx": "Wilson Branch"
      }
    },
    {
      "geometry": {
        "type": "Point",
        "coordinates": [
          -84.0167,
          30.9333
        ]
      },
      "type": "Feature",
      "properties": {
        "hierarchy": [
          "tgn:2775316",
          "tgn:1000001",
          "tgn:7012149",
          "tgn:7014371",
          "tgn:7007248",
          "tgn:7029392"
        ],
        "placetype": [
          "aat:300008699"
        ],
        "id": 2775316,
        "name:xx": "Wilson Branch"
      }
    },
    {
      "geometry": {
        "type": "Point",
        "coordinates": [
          -81.7667,
          32.5333
        ]
      },
      "type": "Feature",
      "properties": {
        "hierarchy": [
          "tgn:2775317",
          "tgn:1000001",
          "tgn:2000307",
          "tgn:7012149",
          "tgn:7007248",
          "tgn:7029392"
        ],
        "placetype": [
          "aat:300008699"
        ],
        "id": 2775317,
        "name:xx": "Wilson Branch"
      }
    },
    {
      "geometry": {
        "type": "Point",
        "coordinates": [
          -83.9167,
          34.8
        ]
      },
      "type": "Feature",
      "properties": {
        "hierarchy": [
          "tgn:2775318",
          "tgn:1000001",
          "tgn:7012149",
          "tgn:2000435",
          "tgn:7007248",
          "tgn:7029392"
        ],
        "placetype": [
          "aat:300008699"
        ],
        "id": 2775318,
        "name:xx": "Wilson Branch"
      }
    },
    {
      "geometry": {
        "type": "Point",
        "coordinates": [
          -84.6,
          34.9833
        ]
      },
      "type": "Feature",
      "properties": {
        "hierarchy": [
          "tgn:2775319",
          "tgn:1000001",
          "tgn:7012149",
          "tgn:2000346",
          "tgn:7007248",
          "tgn:7029392"
        ],
        "placetype": [
          "aat:300008699"
        ],
        "id": 2775319,
        "name:xx": "Wilson Branch"
      }
    }
  ]
}
