{
  "type": "FeatureCollection",
  "features": [
    {
      "geometry": {
        "type": "Point",
        "coordinates": [
          -119.1,
          46.5667
        ]
      },
      "type": "Feature",
      "properties": {
        "hierarchy": [
          "tgn:2273780",
          "tgn:1000001",
          "tgn:2002244",
          "tgn:7012149",
          "tgn:7007920",
          "tgn:7029392"
        ],
        "placetype": [
          "aat:300006075"
        ],
        "id": 2273780,
        "name:xx": "DPE Thirtynine"
      }
    },
    {
      "geometry": {
        "type": "Point",
        "coordinates": [
          -108.7833,
          37.8667
        ]
      },
      "type": "Feature",
      "properties": {
        "hierarchy": [
          "tgn:2273781",
          "tgn:1000001",
          "tgn:7012149",
          "tgn:2000208",
          "tgn:7007158",
          "tgn:7029392"
        ],
        "placetype": [
          "aat:300006191"
        ],
        "id": 2273781,
        "name:xx": "DR Reservoir"
      }
    },
    {
      "geometry": {
        "type": "Point",
        "coordinates": [
          -109.2333,
          33.8667
        ]
      },
      "type": "Feature",
      "properties": {
        "hierarchy": [
          "tgn:2273782",
          "tgn:2000090",
          "tgn:1000001",
          "tgn:7006451",
          "tgn:7012149",
          "tgn:7029392"
        ],
        "placetype": [
          "aat:300386845"
        ],
        "id": 2273782,
        "name:xx": "DT Sink"
      }
    },
    {
      "geometry": {
        "type": "Point",
        "coordinates": [
          -108.6167,
          47.7833
        ]
      },
      "type": "Feature",
      "properties": {
        "hierarchy": [
          "tgn:2273785",
          "tgn:1000001",
          "tgn:7012149",
          "tgn:2001295",
          "tgn:7007524",
          "tgn:7029392"
        ],
        "placetype": [
          "aat:300008347"
        ],
        "id": 2273785,
        "name:xx": "DY Junction"
      }
    },
    {
      "geometry": {
        "type": "Point",
        "coordinates": [
          -110.5667,
          35.85
        ]
      },
      "type": "Feature",
      "properties": {
        "hierarchy": [
          "tgn:2273786",
          "tgn:1000001",
          "tgn:7006451",
          "tgn:7012149",
          "tgn:2000099",
          "tgn:7029392"
        ],
        "placetype": [
          "aat:300008798"
        ],
        "id": 2273786,
        "name:xx": "Da Wa Ke"
      }
    },
    {
      "geometry": {
        "type": "Point",
        "coordinates": [
          -123.3,
          43.1667
        ]
      },
      "type": "Feature",
      "properties": {
        "hierarchy": [
          "tgn:2273787",
          "tgn:1000001",
          "tgn:7012149",
          "tgn:2001706",
          "tgn:7007708",
          "tgn:7029392"
        ],
        "placetype": [
          "aat:300008699"
        ],
        "id": 2273787,
        "name:xx": "DaMotta Branch"
      }
    },
    {
      "geometry": {
        "type": "Point",
        "coordinates": [
          -82.3,
          32.6
        ]
      },
      "type": "Feature",
      "properties": {
        "hierarchy": [
          "tgn:2273788",
          "tgn:1000001",
          "tgn:7012149",
          "tgn:2000344",
          "tgn:7007248",
          "tgn:7029392"
        ],
        "placetype": [
          "aat:300006191"
        ],
        "id": 2273788,
        "name:xx": "Daniels Pond"
      }
    },
    {
      "geometry": {
        "type": "Point",
        "coordinates": [
          -70,
          46.5833
        ]
      },
      "type": "Feature",
      "properties": {
        "hierarchy": [
          "tgn:2273789",
          "tgn:2000919",
          "tgn:1000001",
          "tgn:7012149",
          "tgn:7007515",
          "tgn:7029392"
        ],
        "placetype": [
          "aat:300008347"
        ],
        "id": 2273789,
        "name:xx": "Daaquam"
      }
    }
  ]
}
