{
  "geometry": {
    "type": "Point",
    "coordinates": [
      -94.8167,
      30.15
    ]
  },
  "type": "Feature",
  "properties": {
    "hierarchy": [
      "tgn:2539507",
      "tgn:1000001",
      "tgn:7012149",
      "tgn:1002595",
      "tgn:7007826",
      "tgn:7029392"
    ],
    "placetype": [
      "aat:300008680"
    ],
    "id": 2539507,
    "name:xx": "New Old River Lake"
  }
}
