{
  "geometry": {
    "type": "Point",
    "coordinates": [
      -83.9333,
      37.7667
    ]
  },
  "type": "Feature",
  "properties": {
    "hierarchy": [
      "tgn:2455984",
      "tgn:1000001",
      "tgn:7012149",
      "tgn:7007255",
      "tgn:7029392"
    ],
    "placetype": [
      "aat:300008706"
    ],
    "id": 2455984,
    "name:xx": "Little Hardwick Creek"
  }
}
