{
  "geometry": {
    "type": "Point",
    "coordinates": [
      -92.3167,
      29.65
    ]
  },
  "type": "Feature",
  "properties": {
    "hierarchy": [
      "tgn:2600934",
      "tgn:1000001",
      "tgn:7012149",
      "tgn:2000910",
      "tgn:7007256",
      "tgn:7029392"
    ],
    "placetype": [
      "aat:300386853"
    ],
    "id": 2600934,
    "name:xx": "Pumpkin Islands"
  }
}
