{
  "geometry": {
    "type": "Point",
    "coordinates": [
      -105.2333,
      31.5167
    ]
  },
  "type": "Feature",
  "properties": {
    "hierarchy": [
      "tgn:2244338",
      "tgn:1000001",
      "tgn:7012149",
      "tgn:2002005",
      "tgn:7007826",
      "tgn:7029392"
    ],
    "placetype": [
      "aat:300006191"
    ],
    "id": 2244338,
    "name:xx": "Clifton Tank"
  }
}
