{
  "geometry": {
    "type": "Point",
    "coordinates": [
      -119.3333,
      34.8333
    ]
  },
  "type": "Feature",
  "properties": {
    "hierarchy": [
      "tgn:2182515",
      "tgn:1000001",
      "tgn:7012149",
      "tgn:7007157",
      "tgn:1002972",
      "tgn:7029392"
    ],
    "placetype": [
      "aat:300008697"
    ],
    "id": 2182515,
    "name:xx": "Blue Rock Spring"
  }
}
