{
  "geometry": {
    "type": "Point",
    "coordinates": [
      -123.75,
      45.8667
    ]
  },
  "type": "Feature",
  "properties": {
    "hierarchy": [
      "tgn:2164003",
      "tgn:1000001",
      "tgn:1002276",
      "tgn:7012149",
      "tgn:7007708",
      "tgn:7029392"
    ],
    "placetype": [
      "aat:300008706"
    ],
    "id": 2164003,
    "name:xx": "Bergsvik Creek"
  }
}
