{
  "type": "FeatureCollection",
  "features": [
    {
      "geometry": {
        "type": "Point",
        "coordinates": [
          69.5,
          33.5
        ]
      },
      "type": "Feature",
      "properties": {
        "hierarchy": [
          "tgn:1001480",
          "tgn:7016612",
          "tgn:1000004",
          "tgn:7029392"
        ],
        "placetype": [
          "aat:300387064",
          "aat:300000774"
        ],
        "id": 1001480,
        "name:xx": "Paktīā"
      }
    },
    {
      "geometry": {
        "type": "Point",
        "coordinates": [
          118.8333,
          10
        ]
      },
      "type": "Feature",
      "properties": {
        "hierarchy": [
          "tgn:1001481",
          "tgn:1000004",
          "tgn:1000135",
          "tgn:7029392"
        ],
        "placetype": [
          "aat:300387064",
          "aat:300000774"
        ],
        "id": 1001481,
        "name:xx": "Palawan"
      }
    },
    {
      "geometry": {
        "type": "Point",
        "coordinates": [
          120.6667,
          15.0667
        ]
      },
      "type": "Feature",
      "properties": {
        "hierarchy": [
          "tgn:1001482",
          "tgn:1000004",
          "tgn:1000135",
          "tgn:7029392"
        ],
        "placetype": [
          "aat:300387064",
          "aat:300000774"
        ],
        "id": 1001482,
        "name:xx": "Pampanga"
      }
    },
    {
      "geometry": {
        "type": "Point",
        "coordinates": [
          -79.25,
          9.183
        ]
      },
      "type": "Feature",
      "properties": {
        "hierarchy": [
          "tgn:1001483",
          "tgn:1000001",
          "tgn:7005565",
          "tgn:7029392"
        ],
        "placetype": [
          "aat:300008631",
          "aat:300387064",
          "aat:300000774"
        ],
        "id": 1001483,
        "name:xx": "Panamá"
      }
    },
    {
      "geometry": {
        "type": "Point",
        "coordinates": [
          120.3333,
          15.9167
        ]
      },
      "type": "Feature",
      "properties": {
        "hierarchy": [
          "tgn:1001484",
          "tgn:1000004",
          "tgn:1000135",
          "tgn:7029392"
        ],
        "placetype": [
          "aat:300387064",
          "aat:300000774"
        ],
        "id": 1001484,
        "name:xx": "Pangasinan"
      }
    },
    {
      "geometry": {
        "type": "Point",
        "coordinates": [
          69.5,
          35.25
        ]
      },
      "type": "Feature",
      "properties": {
        "hierarchy": [
          "tgn:1001485",
          "tgn:7016612",
          "tgn:1000004",
          "tgn:7029392"
        ],
        "placetype": [
          "aat:300387064",
          "aat:300000774"
        ],
        "id": 1001485,
        "name:xx": "Parvān"
      }
    },
    {
      "geometry": {
        "type": "Point",
        "coordinates": [
          -77,
          -1.916
        ]
      },
      "type": "Feature",
      "properties": {
        "hierarchy": [
          "tgn:1001486",
          "tgn:7002559",
          "tgn:1000051",
          "tgn:1000002",
          "tgn:7029392"
        ],
        "placetype": [
          "aat:300387064",
          "aat:300000774"
        ],
        "id": 1001486,
        "name:xx": "Pastaza"
      }
    },
    {
      "geometry": {
        "type": "Point",
        "coordinates": [
          -78.5,
          -0.083
        ]
      },
      "type": "Feature",
      "properties": {
        "hierarchy": [
          "tgn:1001487",
          "tgn:7002561",
          "tgn:1000051",
          "tgn:1000002",
          "tgn:7029392"
        ],
        "placetype": [
          "aat:300387064",
          "aat:300000774"
        ],
        "id": 1001487,
        "name:xx": "Pichincha"
      }
    },
    {
      "geometry": {
        "type": "Point",
        "coordinates": [
          -83.833,
          22.416
        ]
      },
      "type": "Feature",
      "properties": {
        "hierarchy": [
          "tgn:1001488",
          "tgn:1000001",
          "tgn:7004624",
          "tgn:7029392"
        ],
        "placetype": [
          "aat:300008631",
          "aat:300387064",
          "aat:300000774"
        ],
        "id": 1001488,
        "name:xx": "Pinar del Río"
      }
    }
  ]
}
