{
  "geometry": {
    "type": "Point",
    "coordinates": [
      26.23696,
      22.805891
    ]
  },
  "type": "Feature",
  "properties": {
    "hierarchy": [
      "tgn:7526457",
      "tgn:7001242",
      "tgn:7016833",
      "tgn:7001334",
      "tgn:7029392"
    ],
    "placetype": [
      "aat:300008777"
    ],
    "name:en": "Thamāniyat Ajrās",
    "id": 7526457
  }
}
