{
  "geometry": {
    "type": "Point",
    "coordinates": [
      -92.15,
      42.1667
    ]
  },
  "type": "Feature",
  "properties": {
    "hierarchy": [
      "tgn:2392154",
      "tgn:2000566",
      "tgn:1000001",
      "tgn:7012149",
      "tgn:7007253",
      "tgn:7029392"
    ],
    "placetype": [
      "aat:300008706"
    ],
    "id": 2392154,
    "name:xx": "Hinkle Creek"
  }
}
