{
  "geometry": {
    "type": "Point",
    "coordinates": [
      117.4333,
      39.15
    ]
  },
  "type": "Feature",
  "properties": {
    "hierarchy": [
      "tgn:1070645",
      "tgn:1000004",
      "tgn:1000960",
      "tgn:1000111",
      "tgn:7029392"
    ],
    "placetype": [
      "aat:300008347"
    ],
    "id": 1070645,
    "name:xx": "Nanshanlingcun"
  }
}
