{
  "geometry": {
    "type": "Point",
    "coordinates": [
      -71.55,
      -39.5833
    ]
  },
  "type": "Feature",
  "properties": {
    "hierarchy": [
      "tgn:1107705",
      "tgn:1000002",
      "tgn:7029392"
    ],
    "placetype": [
      "aat:300132325"
    ],
    "id": 1107705,
    "name:xx": "Lanín, Volcán"
  }
}
