{
  "geometry": {
    "type": "Point",
    "coordinates": [
      -76.6333,
      -9.5333
    ]
  },
  "type": "Feature",
  "properties": {
    "hierarchy": [
      "tgn:1024722",
      "tgn:1000637",
      "tgn:1000002",
      "tgn:1000056",
      "tgn:7029392"
    ],
    "placetype": [
      "aat:300008347"
    ],
    "id": 1024722,
    "name:xx": "Quivilla"
  }
}
