{
  "geometry": {
    "type": "Point",
    "coordinates": [
      -52.85,
      -12.9333
    ]
  },
  "type": "Feature",
  "properties": {
    "hierarchy": [
      "tgn:1129889",
      "tgn:7006260",
      "tgn:7002454",
      "tgn:1000047",
      "tgn:1000002",
      "tgn:7029392"
    ],
    "placetype": [
      "aat:300008707"
    ],
    "id": 1129889,
    "name:xx": "Sete de Setembro"
  }
}
