{
  "geometry": {
    "type": "Point",
    "coordinates": [
      8.55,
      52.316667
    ]
  },
  "type": "Feature",
  "properties": {
    "hierarchy": [
      "tgn:7145101",
      "tgn:1000003",
      "tgn:7003677",
      "tgn:7000084",
      "tgn:7029392"
    ],
    "placetype": [
      "aat:300000206"
    ],
    "id": 7145101,
    "name:xx": "Knöttinghausen"
  }
}
