{
  "geometry": {
    "type": "Point",
    "coordinates": [
      -77.5667,
      37.35
    ]
  },
  "type": "Feature",
  "properties": {
    "hierarchy": [
      "tgn:2588824",
      "tgn:1000001",
      "tgn:1002267",
      "tgn:7012149",
      "tgn:7007919",
      "tgn:7029392"
    ],
    "placetype": [
      "aat:300008863"
    ],
    "id": 2588824,
    "name:xx": "Pocahontas State Forest"
  }
}
