{
  "geometry": {
    "type": "Point",
    "coordinates": [
      -154.2667,
      58.2833
    ]
  },
  "type": "Feature",
  "properties": {
    "hierarchy": [
      "tgn:2126960",
      "tgn:7006450",
      "tgn:1000001",
      "tgn:2124012",
      "tgn:7012149",
      "tgn:7029392"
    ],
    "placetype": [
      "aat:300008791"
    ],
    "id": 2126960,
    "name:xx": "Aguchik Island"
  }
}
