{
  "geometry": {
    "type": "Point",
    "coordinates": [
      139.55,
      35.3167
    ]
  },
  "type": "Feature",
  "properties": {
    "hierarchy": [
      "tgn:1080374",
      "tgn:7016696",
      "tgn:1000004",
      "tgn:7000894",
      "tgn:1000120",
      "tgn:7029392"
    ],
    "placetype": [
      "aat:300008347",
      "aat:300000547",
      "aat:300008375",
      "aat:300387270"
    ],
    "id": 1080374,
    "name:xx": "Kamakura"
  }
}
