{
  "geometry": {
    "type": "Point",
    "coordinates": [
      -88.2667,
      38.8333
    ]
  },
  "type": "Feature",
  "properties": {
    "hierarchy": [
      "tgn:2763362",
      "tgn:1000001",
      "tgn:1002277",
      "tgn:7012149",
      "tgn:7007251",
      "tgn:7029392"
    ],
    "placetype": [
      "aat:300008706"
    ],
    "id": 2763362,
    "name:xx": "Wet Weather Creek"
  }
}
