{
  "geometry": {
    "type": "Point",
    "coordinates": [
      -79.7167,
      35.8833
    ]
  },
  "type": "Feature",
  "properties": {
    "hierarchy": [
      "tgn:2766203",
      "tgn:1000001",
      "tgn:7012149",
      "tgn:2001532",
      "tgn:7007709",
      "tgn:7029392"
    ],
    "placetype": [
      "aat:300006191"
    ],
    "id": 2766203,
    "name:xx": "White Lake"
  }
}
