{
  "geometry": {
    "type": "Point",
    "coordinates": [
      -91.55,
      36.0833
    ]
  },
  "type": "Feature",
  "properties": {
    "hierarchy": [
      "tgn:2299448",
      "tgn:1000001",
      "tgn:7016172",
      "tgn:7012149",
      "tgn:2000172",
      "tgn:7029392"
    ],
    "placetype": [
      "aat:300008680"
    ],
    "id": 2299448,
    "name:xx": "Duck Pond"
  }
}
