{
  "geometry": {
    "type": "Point",
    "coordinates": [
      -85.9167,
      35.9833
    ]
  },
  "type": "Feature",
  "properties": {
    "hierarchy": [
      "tgn:2421952",
      "tgn:1000001",
      "tgn:7012149",
      "tgn:7022246",
      "tgn:7007825",
      "tgn:7029392"
    ],
    "placetype": [
      "aat:300008746"
    ],
    "id": 2421952,
    "name:xx": "Jim Cave"
  }
}
