{
  "geometry": {
    "type": "Point",
    "coordinates": [
      -111.7333,
      42.5167
    ]
  },
  "type": "Feature",
  "properties": {
    "hierarchy": [
      "tgn:2197496",
      "tgn:1000001",
      "tgn:2000466",
      "tgn:7012149",
      "tgn:7007250",
      "tgn:7029392"
    ],
    "placetype": [
      "aat:300006075"
    ],
    "id": 2197496,
    "name:xx": "Brown Ditch"
  }
}
