{
  "geometry": {
    "type": "Point",
    "coordinates": [
      -114.7833,
      48.8167
    ]
  },
  "type": "Feature",
  "properties": {
    "hierarchy": [
      "tgn:2442414",
      "tgn:1000001",
      "tgn:7012149",
      "tgn:2001286",
      "tgn:7007524",
      "tgn:7029392"
    ],
    "placetype": [
      "aat:300008798"
    ],
    "id": 2442414,
    "name:xx": "Krinklehorn Peak"
  }
}
