{
  "geometry": {
    "type": "Point",
    "coordinates": [
      -85.7833,
      37.0833
    ]
  },
  "type": "Feature",
  "properties": {
    "hierarchy": [
      "tgn:2777462",
      "tgn:2000768",
      "tgn:1000001",
      "tgn:7012149",
      "tgn:7007255",
      "tgn:7029392"
    ],
    "placetype": [
      "aat:300008798"
    ],
    "id": 2777462,
    "name:xx": "Winlock Knob"
  }
}
