{
  "geometry": {
    "type": "Point",
    "coordinates": [
      -91.75,
      44.5167
    ]
  },
  "type": "Feature",
  "properties": {
    "hierarchy": [
      "tgn:2692912",
      "tgn:1000001",
      "tgn:2002310",
      "tgn:7012149",
      "tgn:7007922",
      "tgn:7029392"
    ],
    "placetype": [
      "aat:300008761"
    ],
    "id": 2692912,
    "name:xx": "Steele Valley"
  }
}
