{
  "geometry": {
    "type": "Point",
    "coordinates": [
      -121.0833,
      37.4667
    ]
  },
  "type": "Feature",
  "properties": {
    "hierarchy": [
      "tgn:2488825",
      "tgn:1000001",
      "tgn:7012149",
      "tgn:7007157",
      "tgn:1002915",
      "tgn:7029392"
    ],
    "placetype": [
      "aat:300006075"
    ],
    "id": 2488825,
    "name:xx": "Main Canal"
  }
}
