{
  "geometry": {
    "type": "Point",
    "coordinates": [
      -83.5167,
      36.3667
    ]
  },
  "type": "Feature",
  "properties": {
    "hierarchy": [
      "tgn:2393081",
      "tgn:1000001",
      "tgn:7012149",
      "tgn:2001849",
      "tgn:7007825",
      "tgn:7029392"
    ],
    "placetype": [
      "aat:300008699"
    ],
    "id": 2393081,
    "name:xx": "Hodges Branch"
  }
}
