{
  "geometry": {
    "type": "Point",
    "coordinates": [
      -111.2167,
      47.1833
    ]
  },
  "type": "Feature",
  "properties": {
    "hierarchy": [
      "tgn:2188324",
      "tgn:1000001",
      "tgn:2001266",
      "tgn:7012149",
      "tgn:7007524",
      "tgn:7029392"
    ],
    "placetype": [
      "aat:300008761"
    ],
    "id": 2188324,
    "name:xx": "Boston Coulee"
  }
}
