{
  "geometry": {
    "type": "Point",
    "coordinates": [
      86.36607,
      23.117654
    ]
  },
  "type": "Feature",
  "properties": {
    "hierarchy": [
      "tgn:7547347",
      "tgn:1000004",
      "tgn:7000198",
      "tgn:1001977",
      "tgn:7029392"
    ],
    "placetype": [
      "aat:300008347"
    ],
    "name:en": "Bāmundīha",
    "id": 7547347
  }
}
