{
  "geometry": {
    "type": "Point",
    "coordinates": [
      -94.2667,
      30.0833
    ]
  },
  "type": "Feature",
  "properties": {
    "hierarchy": [
      "tgn:2364214",
      "tgn:1000001",
      "tgn:7012149",
      "tgn:2002011",
      "tgn:7007826",
      "tgn:7029392"
    ],
    "placetype": [
      "aat:300008761"
    ],
    "id": 2364214,
    "name:xx": "Green Pond Gully"
  }
}
