{
  "geometry": {
    "type": "Point",
    "coordinates": [
      -87.9333,
      46.25
    ]
  },
  "type": "Feature",
  "properties": {
    "hierarchy": [
      "tgn:2594409",
      "tgn:1000001",
      "tgn:7012149",
      "tgn:2000975",
      "tgn:7007520",
      "tgn:7029392"
    ],
    "placetype": [
      "aat:300008680"
    ],
    "id": 2594409,
    "name:xx": "Porterfield Lake"
  }
}
