{
  "geometry": {
    "type": "Point",
    "coordinates": [
      -109.4667,
      33.2167
    ]
  },
  "type": "Feature",
  "properties": {
    "hierarchy": [
      "tgn:2325955",
      "tgn:1000001",
      "tgn:7006451",
      "tgn:7012149",
      "tgn:7029392"
    ],
    "placetype": [
      "aat:300008761"
    ],
    "id": 2325955,
    "name:xx": "Fifteenmile Canyon"
  }
}
