{
  "geometry": {
    "type": "Point",
    "coordinates": [
      -112.0333,
      42.4833
    ]
  },
  "type": "Feature",
  "properties": {
    "hierarchy": [
      "tgn:2199379",
      "tgn:2000454",
      "tgn:1000001",
      "tgn:7012149",
      "tgn:7007250",
      "tgn:7029392"
    ],
    "placetype": [
      "aat:300008706"
    ],
    "id": 2199379,
    "name:xx": "Brush Creek"
  }
}
