{
  "geometry": {
    "type": "Point",
    "coordinates": [
      -72.9833,
      42.25
    ]
  },
  "type": "Feature",
  "properties": {
    "hierarchy": [
      "tgn:2366208",
      "tgn:1000001",
      "tgn:7019982",
      "tgn:7012149",
      "tgn:7007517",
      "tgn:7029392"
    ],
    "placetype": [
      "aat:300008699"
    ],
    "id": 2366208,
    "name:xx": "Griffin Brook"
  }
}
