{
  "geometry": {
    "type": "Point",
    "coordinates": [
      -113.2333,
      37.7167
    ]
  },
  "type": "Feature",
  "properties": {
    "hierarchy": [
      "tgn:2359090",
      "tgn:1000001",
      "tgn:7012149",
      "tgn:2002111",
      "tgn:7007827",
      "tgn:7029392"
    ],
    "placetype": [
      "aat:300008798"
    ],
    "id": 2359090,
    "name:xx": "Granite Mountain"
  }
}
