{
  "geometry": {
    "type": "Point",
    "coordinates": [
      -82.9833,
      33.7167
    ]
  },
  "type": "Feature",
  "properties": {
    "hierarchy": [
      "tgn:2023904",
      "tgn:1000001",
      "tgn:7012149",
      "tgn:2000400",
      "tgn:7007248",
      "tgn:7029392"
    ],
    "placetype": [
      "aat:300008347"
    ],
    "id": 2023904,
    "name:xx": "Philomath"
  }
}
