{
  "type": "FeatureCollection",
  "features": [
    {
      "geometry": {
        "type": "Point",
        "coordinates": [
          -5.133333,
          55.616667
        ]
      },
      "type": "Feature",
      "properties": {
        "hierarchy": [
          "tgn:7467010",
          "tgn:7002444",
          "tgn:1000003",
          "tgn:7019091",
          "tgn:7008591",
          "tgn:7029392"
        ],
        "placetype": [
          "aat:300386846"
        ],
        "name:en": "Birch Point",
        "id": 7467010
      }
    },
    {
      "geometry": {
        "type": "Point",
        "coordinates": [
          -3.208611,
          51.511944
        ]
      },
      "type": "Feature",
      "properties": {
        "hierarchy": [
          "tgn:7467012",
          "tgn:7002443",
          "tgn:7018962",
          "tgn:1000003",
          "tgn:7008591",
          "tgn:7029392"
        ],
        "placetype": [
          "aat:300000745"
        ],
        "name:en": "Birchgrove",
        "id": 7467012
      }
    },
    {
      "geometry": {
        "type": "Point",
        "coordinates": [
          -6.55,
          54.483333
        ]
      },
      "type": "Feature",
      "properties": {
        "hierarchy": [
          "tgn:7467013",
          "tgn:7002448",
          "tgn:7019200",
          "tgn:1000003",
          "tgn:7008591",
          "tgn:7029392"
        ],
        "placetype": [
          "aat:300008347"
        ],
        "name:en": "The Birches",
        "id": 7467013
      }
    }
  ]
}
