{
  "geometry": {
    "type": "Point",
    "coordinates": [
      -82.6667,
      35.05
    ]
  },
  "type": "Feature",
  "properties": {
    "hierarchy": [
      "tgn:2709390",
      "tgn:1000001",
      "tgn:2001747",
      "tgn:7012149",
      "tgn:7007712",
      "tgn:7029392"
    ],
    "placetype": [
      "aat:300006191"
    ],
    "id": 2709390,
    "name:xx": "Table Rock Cove"
  }
}
