{
  "type": "FeatureCollection",
  "features": [
    {
      "geometry": {
        "type": "Point",
        "coordinates": [
          -105.466667,
          28.583333
        ]
      },
      "type": "Feature",
      "properties": {
        "hierarchy": [
          "tgn:7350470",
          "tgn:7005581",
          "tgn:1000001",
          "tgn:7005560",
          "tgn:7029392"
        ],
        "placetype": [
          "aat:300008795"
        ],
        "id": 7350470,
        "name:xx": "Blanca, Loma"
      }
    },
    {
      "geometry": {
        "type": "Point",
        "coordinates": [
          -99.55,
          25.133333
        ]
      },
      "type": "Feature",
      "properties": {
        "hierarchy": [
          "tgn:7350471",
          "tgn:1000001",
          "tgn:7005589",
          "tgn:7005560",
          "tgn:7029392"
        ],
        "placetype": [
          "aat:300008777"
        ],
        "id": 7350471,
        "name:xx": "Blanca, Loma"
      }
    },
    {
      "geometry": {
        "type": "Point",
        "coordinates": [
          -97.783333,
          24.616667
        ]
      },
      "type": "Feature",
      "properties": {
        "hierarchy": [
          "tgn:7350472",
          "tgn:1000001",
          "tgn:7005597",
          "tgn:7005560",
          "tgn:7029392"
        ],
        "placetype": [
          "aat:300387086"
        ],
        "id": 7350472,
        "name:xx": "Blanca, Laguna"
      }
    },
    {
      "geometry": {
        "type": "Point",
        "coordinates": [
          -102.4,
          23.216667
        ]
      },
      "type": "Feature",
      "properties": {
        "hierarchy": [
          "tgn:7350473",
          "tgn:1000001",
          "tgn:7005601",
          "tgn:7005560",
          "tgn:7029392"
        ],
        "placetype": [
          "aat:300008680"
        ],
        "id": 7350473,
        "name:xx": "Blanca, Laguna"
      }
    },
    {
      "geometry": {
        "type": "Point",
        "coordinates": [
          -95.483333,
          15.983333
        ]
      },
      "type": "Feature",
      "properties": {
        "hierarchy": [
          "tgn:7350474",
          "tgn:1000001",
          "tgn:7005591",
          "tgn:7005560",
          "tgn:7029392"
        ],
        "placetype": [
          "aat:300008679"
        ],
        "id": 7350474,
        "name:xx": "Blanca, Laguna"
      }
    },
    {
      "geometry": {
        "type": "Point",
        "coordinates": [
          -110.983333,
          27.916667
        ]
      },
      "type": "Feature",
      "properties": {
        "hierarchy": [
          "tgn:7350475",
          "tgn:1000001",
          "tgn:1001960",
          "tgn:7005560",
          "tgn:7029392"
        ],
        "placetype": [
          "aat:300008791"
        ],
        "id": 7350475,
        "name:xx": "Blanca, Isla"
      }
    },
    {
      "geometry": {
        "type": "Point",
        "coordinates": [
          -86.85,
          21.4
        ]
      },
      "type": "Feature",
      "properties": {
        "hierarchy": [
          "tgn:7350476",
          "tgn:1000001",
          "tgn:1001937",
          "tgn:7005560",
          "tgn:7029392"
        ],
        "placetype": [
          "aat:300008791"
        ],
        "id": 7350476,
        "name:xx": "Blanca, Isla"
      }
    },
    {
      "geometry": {
        "type": "Point",
        "coordinates": [
          -102.15,
          22.683333
        ]
      },
      "type": "Feature",
      "properties": {
        "hierarchy": [
          "tgn:7350477",
          "tgn:1000001",
          "tgn:7005601",
          "tgn:7005560",
          "tgn:7029392"
        ],
        "placetype": [
          "aat:300008777"
        ],
        "id": 7350477,
        "name:xx": "Blanca, Cerro la"
      }
    },
    {
      "geometry": {
        "type": "Point",
        "coordinates": [
          -96,
          19.083333
        ]
      },
      "type": "Feature",
      "properties": {
        "hierarchy": [
          "tgn:7350478",
          "tgn:1000001",
          "tgn:7005599",
          "tgn:7005560",
          "tgn:7029392"
        ],
        "placetype": [
          "aat:300008808"
        ],
        "id": 7350478,
        "name:xx": "Blanca, Arrecife"
      }
    },
    {
      "geometry": {
        "type": "Point",
        "coordinates": [
          -96.783333,
          17.116667
        ]
      },
      "type": "Feature",
      "properties": {
        "hierarchy": [
          "tgn:7350479",
          "tgn:1000001",
          "tgn:7005591",
          "tgn:7005560",
          "tgn:7029392"
        ],
        "placetype": [
          "aat:300007783"
        ],
        "id": 7350479,
        "name:xx": "Blanca"
      }
    }
  ]
}
