{
  "type": "FeatureCollection",
  "features": [
    {
      "geometry": {
        "type": "Point",
        "coordinates": [
          -75.6167,
          38.3167
        ]
      },
      "type": "Feature",
      "properties": {
        "hierarchy": [
          "tgn:2655620",
          "tgn:1000001",
          "tgn:1003023",
          "tgn:7012149",
          "tgn:7007516",
          "tgn:7029392"
        ],
        "placetype": [
          "aat:300008706"
        ],
        "id": 2655620,
        "name:xx": "Sharps Creek"
      }
    },
    {
      "geometry": {
        "type": "Point",
        "coordinates": [
          -85.6167,
          42.8
        ]
      },
      "type": "Feature",
      "properties": {
        "hierarchy": [
          "tgn:2655621",
          "tgn:1000001",
          "tgn:7012149",
          "tgn:1002540",
          "tgn:7007520",
          "tgn:7029392"
        ],
        "placetype": [
          "aat:300008706"
        ],
        "id": 2655621,
        "name:xx": "Sharps Creek"
      }
    },
    {
      "geometry": {
        "type": "Point",
        "coordinates": [
          -91.1,
          31.05
        ]
      },
      "type": "Feature",
      "properties": {
        "hierarchy": [
          "tgn:2655622",
          "tgn:1000001",
          "tgn:7012149",
          "tgn:7029392"
        ],
        "placetype": [
          "aat:300008706"
        ],
        "id": 2655622,
        "name:xx": "Sharps Creek"
      }
    },
    {
      "geometry": {
        "type": "Point",
        "coordinates": [
          -115.2333,
          40.75
        ]
      },
      "type": "Feature",
      "properties": {
        "hierarchy": [
          "tgn:2655623",
          "tgn:1000001",
          "tgn:2001411",
          "tgn:7012149",
          "tgn:7007526",
          "tgn:7029392"
        ],
        "placetype": [
          "aat:300008706"
        ],
        "id": 2655623,
        "name:xx": "Sharps Creek"
      }
    },
    {
      "geometry": {
        "type": "Point",
        "coordinates": [
          -82.55,
          38.5833
        ]
      },
      "type": "Feature",
      "properties": {
        "hierarchy": [
          "tgn:2655624",
          "tgn:1000001",
          "tgn:7012149",
          "tgn:2001615",
          "tgn:7007706",
          "tgn:7029392"
        ],
        "placetype": [
          "aat:300008706"
        ],
        "id": 2655624,
        "name:xx": "Sharps Creek"
      }
    },
    {
      "geometry": {
        "type": "Point",
        "coordinates": [
          -122.65,
          43.5667
        ]
      },
      "type": "Feature",
      "properties": {
        "hierarchy": [
          "tgn:2655625",
          "tgn:1000001",
          "tgn:7012149",
          "tgn:2001716",
          "tgn:7007708",
          "tgn:7029392"
        ],
        "placetype": [
          "aat:300008706"
        ],
        "id": 2655625,
        "name:xx": "Sharps Creek"
      }
    },
    {
      "geometry": {
        "type": "Point",
        "coordinates": [
          -81.5333,
          34.7833
        ]
      },
      "type": "Feature",
      "properties": {
        "hierarchy": [
          "tgn:2655626",
          "tgn:1000001",
          "tgn:7012149",
          "tgn:2001768",
          "tgn:7007712",
          "tgn:7029392"
        ],
        "placetype": [
          "aat:300008706"
        ],
        "id": 2655626,
        "name:xx": "Sharps Creek"
      }
    },
    {
      "geometry": {
        "type": "Point",
        "coordinates": [
          -81.9667,
          36.5167
        ]
      },
      "type": "Feature",
      "properties": {
        "hierarchy": [
          "tgn:2655627",
          "tgn:1000001",
          "tgn:7012149",
          "tgn:2001918",
          "tgn:7007825",
          "tgn:7029392"
        ],
        "placetype": [
          "aat:300008706"
        ],
        "id": 2655627,
        "name:xx": "Sharps Creek"
      }
    },
    {
      "geometry": {
        "type": "Point",
        "coordinates": [
          -76.25,
          37.8667
        ]
      },
      "type": "Feature",
      "properties": {
        "hierarchy": [
          "tgn:2655628",
          "tgn:1000001",
          "tgn:7012149",
          "tgn:1002733",
          "tgn:7007919",
          "tgn:7029392"
        ],
        "placetype": [
          "aat:300008706"
        ],
        "id": 2655628,
        "name:xx": "Sharps Creek"
      }
    },
    {
      "geometry": {
        "type": "Point",
        "coordinates": [
          -78.5,
          37.6667
        ]
      },
      "type": "Feature",
      "properties": {
        "hierarchy": [
          "tgn:2655629",
          "tgn:1000001",
          "tgn:2002149",
          "tgn:7012149",
          "tgn:7007919",
          "tgn:7029392"
        ],
        "placetype": [
          "aat:300008706"
        ],
        "id": 2655629,
        "name:xx": "Sharps Creek"
      }
    }
  ]
}
