{
  "geometry": {
    "type": "Point",
    "coordinates": [
      -71.8333,
      -44.8833
    ]
  },
  "type": "Feature",
  "properties": {
    "hierarchy": [
      "tgn:1116952",
      "tgn:7006477",
      "tgn:1001203",
      "tgn:1000002",
      "tgn:7029392"
    ],
    "placetype": [
      "aat:300008680"
    ],
    "id": 1116952,
    "name:xx": "La Plata, Lago"
  }
}
