{
  "type": "FeatureCollection",
  "features": [
    {
      "geometry": {
        "type": "Point",
        "coordinates": [
          -110.45,
          34.3
        ]
      },
      "type": "Feature",
      "properties": {
        "hierarchy": [
          "tgn:2704300",
          "tgn:1000001",
          "tgn:7006451",
          "tgn:7012149",
          "tgn:2000099",
          "tgn:7029392"
        ],
        "placetype": [
          "aat:300008761"
        ],
        "id": 2704300,
        "name:xx": "Sunny Park Draw"
      }
    },
    {
      "geometry": {
        "type": "Point",
        "coordinates": [
          -145.7,
          61.7667
        ]
      },
      "type": "Feature",
      "properties": {
        "hierarchy": [
          "tgn:2704301",
          "tgn:7006450",
          "tgn:1000001",
          "tgn:7012149",
          "tgn:2000086",
          "tgn:7029392"
        ],
        "placetype": [
          "aat:300008798"
        ],
        "id": 2704301,
        "name:xx": "Sunny Peak"
      }
    },
    {
      "geometry": {
        "type": "Point",
        "coordinates": [
          -119.7833,
          48.5667
        ]
      },
      "type": "Feature",
      "properties": {
        "hierarchy": [
          "tgn:2704302",
          "tgn:1000001",
          "tgn:7012149",
          "tgn:1002742",
          "tgn:7007920",
          "tgn:7029392"
        ],
        "placetype": [
          "aat:300000390"
        ],
        "id": 2704302,
        "name:xx": "Sunny Peak Mine"
      }
    },
    {
      "geometry": {
        "type": "Point",
        "coordinates": [
          -132.2167,
          55.2333
        ]
      },
      "type": "Feature",
      "properties": {
        "hierarchy": [
          "tgn:2704303",
          "tgn:7006450",
          "tgn:1000001",
          "tgn:7012149",
          "tgn:2000082",
          "tgn:7029392"
        ],
        "placetype": [
          "aat:300008850"
        ],
        "id": 2704303,
        "name:xx": "Sunny Point"
      }
    },
    {
      "geometry": {
        "type": "Point",
        "coordinates": [
          -134.5167,
          58.35
        ]
      },
      "type": "Feature",
      "properties": {
        "hierarchy": [
          "tgn:2704304",
          "tgn:7006450",
          "tgn:1000001",
          "tgn:2124089",
          "tgn:7012149",
          "tgn:7029392"
        ],
        "placetype": [
          "aat:300008850"
        ],
        "id": 2704304,
        "name:xx": "Sunny Point"
      }
    },
    {
      "geometry": {
        "type": "Point",
        "coordinates": [
          -135.15,
          57.7667
        ]
      },
      "type": "Feature",
      "properties": {
        "hierarchy": [
          "tgn:2704305",
          "tgn:7006450",
          "tgn:1000001",
          "tgn:7012149",
          "tgn:7019760",
          "tgn:7029392"
        ],
        "placetype": [
          "aat:300008850"
        ],
        "id": 2704305,
        "name:xx": "Sunny Point"
      }
    },
    {
      "geometry": {
        "type": "Point",
        "coordinates": [
          -93.65,
          32.3833
        ]
      },
      "type": "Feature",
      "properties": {
        "hierarchy": [
          "tgn:2704306",
          "tgn:1000001",
          "tgn:7012149",
          "tgn:7007256",
          "tgn:7029392"
        ],
        "placetype": [
          "aat:300008850"
        ],
        "id": 2704306,
        "name:xx": "Sunny Point"
      }
    },
    {
      "geometry": {
        "type": "Point",
        "coordinates": [
          -77.95,
          33.9833
        ]
      },
      "type": "Feature",
      "properties": {
        "hierarchy": [
          "tgn:2704307",
          "tgn:1000001",
          "tgn:2001472",
          "tgn:7012149",
          "tgn:7007709",
          "tgn:7029392"
        ],
        "placetype": [
          "aat:300008850"
        ],
        "id": 2704307,
        "name:xx": "Sunny Point"
      }
    },
    {
      "geometry": {
        "type": "Point",
        "coordinates": [
          -84.2,
          35.0333
        ]
      },
      "type": "Feature",
      "properties": {
        "hierarchy": [
          "tgn:2704308",
          "tgn:1000001",
          "tgn:2001481",
          "tgn:7012149",
          "tgn:7007709",
          "tgn:7029392"
        ],
        "placetype": [
          "aat:300008347"
        ],
        "id": 2704308,
        "name:xx": "Sunny Point"
      }
    },
    {
      "geometry": {
        "type": "Point",
        "coordinates": [
          -82.3667,
          36.8167
        ]
      },
      "type": "Feature",
      "properties": {
        "hierarchy": [
          "tgn:2704309",
          "tgn:1000001",
          "tgn:7012149",
          "tgn:2002188",
          "tgn:7007919",
          "tgn:7029392"
        ],
        "placetype": [
          "aat:300008347"
        ],
        "id": 2704309,
        "name:xx": "Sunny Point"
      }
    }
  ]
}
