{
  "geometry": {
    "type": "Point",
    "coordinates": [
      -71.1833,
      41.5167
    ]
  },
  "type": "Feature",
  "properties": {
    "hierarchy": [
      "tgn:2301004",
      "tgn:1002716",
      "tgn:1000001",
      "tgn:7012149",
      "tgn:7007711",
      "tgn:7029392"
    ],
    "placetype": [
      "aat:300008699"
    ],
    "id": 2301004,
    "name:xx": "Dundery Brook"
  }
}
