{
  "geometry": {
    "type": "Point",
    "coordinates": [
      76.51762,
      30.022605
    ]
  },
  "type": "Feature",
  "properties": {
    "hierarchy": [
      "tgn:7546294",
      "tgn:1000004",
      "tgn:1001871",
      "tgn:7000198",
      "tgn:7029392"
    ],
    "placetype": [
      "aat:300008347"
    ],
    "name:en": "Bākhli",
    "id": 7546294
  }
}
