{
  "geometry": {
    "type": "Point",
    "coordinates": [
      -94.4333,
      36.5167
    ]
  },
  "type": "Feature",
  "properties": {
    "hierarchy": [
      "tgn:2282290",
      "tgn:1000001",
      "tgn:7012149",
      "tgn:2001216",
      "tgn:7007523",
      "tgn:7029392"
    ],
    "placetype": [
      "aat:300008697"
    ],
    "id": 2282290,
    "name:xx": "Deer Lick Spring"
  }
}
