{
  "geometry": {
    "type": "Point",
    "coordinates": [
      -103.5833,
      48.5667
    ]
  },
  "type": "Feature",
  "properties": {
    "hierarchy": [
      "tgn:2129583",
      "tgn:1000001",
      "tgn:7012149",
      "tgn:2001609",
      "tgn:7007705",
      "tgn:7029392"
    ],
    "placetype": [
      "aat:300008680"
    ],
    "id": 2129583,
    "name:xx": "Alkali Lake"
  }
}
