{
  "geometry": {
    "type": "Point",
    "coordinates": [
      110.1333,
      -2.0167
    ]
  },
  "type": "Feature",
  "properties": {
    "hierarchy": [
      "tgn:1077915",
      "tgn:1000004",
      "tgn:1001336",
      "tgn:1000116",
      "tgn:7029392"
    ],
    "placetype": [
      "aat:300008347"
    ],
    "id": 1077915,
    "name:xx": "Kualapesaguan"
  }
}
