{
  "geometry": {
    "type": "Point",
    "coordinates": [
      31.436752,
      30.769432
    ]
  },
  "type": "Feature",
  "properties": {
    "hierarchy": [
      "tgn:7542154",
      "tgn:7001242",
      "tgn:1001059",
      "tgn:7016833",
      "tgn:7029392"
    ],
    "placetype": [
      "aat:300000206"
    ],
    "name:en": "Muḩammad ash Shaḩḩāt",
    "id": 7542154
  }
}
