{
  "geometry": {
    "type": "Point",
    "coordinates": [
      31.85,
      30.333333
    ]
  },
  "type": "Feature",
  "properties": {
    "hierarchy": [
      "tgn:7522141",
      "tgn:7001242",
      "tgn:7016833",
      "tgn:1001080",
      "tgn:7029392"
    ],
    "placetype": [
      "aat:300008805"
    ],
    "name:en": "Abū Rimth, Ḩāmad",
    "id": 7522141
  }
}
