{
  "geometry": {
    "type": "Point",
    "coordinates": [
      36.5333,
      55.5333
    ]
  },
  "type": "Feature",
  "properties": {
    "hierarchy": [
      "tgn:1053704",
      "tgn:1000004",
      "tgn:7011573",
      "tgn:7018214",
      "tgn:7002435",
      "tgn:7029392"
    ],
    "placetype": [
      "aat:300008347"
    ],
    "id": 1053704,
    "name:xx": "Dorokhovo"
  }
}
