{
  "geometry": {
    "type": "Point",
    "coordinates": [
      -119.15,
      48.2667
    ]
  },
  "type": "Feature",
  "properties": {
    "hierarchy": [
      "tgn:2431471",
      "tgn:1000001",
      "tgn:7012149",
      "tgn:1002742",
      "tgn:7007920",
      "tgn:7029392"
    ],
    "placetype": [
      "aat:300008706"
    ],
    "id": 2431471,
    "name:xx": "Kartar Creek"
  }
}
