{
  "geometry": {
    "type": "Point",
    "coordinates": [
      -78.9167,
      39.4667
    ]
  },
  "type": "Feature",
  "properties": {
    "hierarchy": [
      "tgn:2138876",
      "tgn:1000001",
      "tgn:7012149",
      "tgn:2002279",
      "tgn:7013961",
      "tgn:7029392"
    ],
    "placetype": [
      "aat:300008699"
    ],
    "id": 2138876,
    "name:xx": "Ashcabin Run"
  }
}
