{
  "geometry": {
    "type": "Point",
    "coordinates": [
      31.989369,
      30.780112
    ]
  },
  "type": "Feature",
  "properties": {
    "hierarchy": [
      "tgn:7523599",
      "tgn:7001242",
      "tgn:7016833",
      "tgn:1001113",
      "tgn:7029392"
    ],
    "placetype": [
      "aat:300008347"
    ],
    "name:en": "Aş Şālḩīyah",
    "id": 7523599
  }
}
