{
  "type": "FeatureCollection",
  "features": [
    {
      "geometry": {
        "type": "Point",
        "coordinates": [
          -90.2,
          30.5667
        ]
      },
      "type": "Feature",
      "properties": {
        "hierarchy": [
          "tgn:2564160",
          "tgn:1000001",
          "tgn:7012149",
          "tgn:2000905",
          "tgn:7007256",
          "tgn:7029392"
        ],
        "placetype": [
          "aat:300006191"
        ],
        "id": 2564160,
        "name:xx": "P+l Ranch Pond"
      }
    },
    {
      "geometry": {
        "type": "Point",
        "coordinates": [
          -104.35,
          42.2
        ]
      },
      "type": "Feature",
      "properties": {
        "hierarchy": [
          "tgn:2564164",
          "tgn:1000001",
          "tgn:7012149",
          "tgn:2002372",
          "tgn:7007923",
          "tgn:7029392"
        ],
        "placetype": [
          "aat:300008798"
        ],
        "id": 2564164,
        "name:xx": "P-F Hill"
      }
    },
    {
      "geometry": {
        "type": "Point",
        "coordinates": [
          -90.2667,
          30.5333
        ]
      },
      "type": "Feature",
      "properties": {
        "hierarchy": [
          "tgn:2564165",
          "tgn:1000001",
          "tgn:7012149",
          "tgn:2000906",
          "tgn:7007256",
          "tgn:7029392"
        ],
        "placetype": [
          "aat:300008706"
        ],
        "id": 2564165,
        "name:xx": "P-Kaw-Shun Creek"
      }
    },
    {
      "geometry": {
        "type": "Point",
        "coordinates": [
          -111.4667,
          31.8
        ]
      },
      "type": "Feature",
      "properties": {
        "hierarchy": [
          "tgn:2564166",
          "tgn:1000001",
          "tgn:7006451",
          "tgn:7012149",
          "tgn:2000100",
          "tgn:7029392"
        ],
        "placetype": [
          "aat:300006191"
        ],
        "id": 2564166,
        "name:xx": "P-Y Tank"
      }
    },
    {
      "geometry": {
        "type": "Point",
        "coordinates": [
          -108.2167,
          39.8667
        ]
      },
      "type": "Feature",
      "properties": {
        "hierarchy": [
          "tgn:2564167",
          "tgn:1000001",
          "tgn:7012149",
          "tgn:7007158",
          "tgn:2000243",
          "tgn:7029392"
        ],
        "placetype": [
          "aat:300008761"
        ],
        "id": 2564167,
        "name:xx": "P. L. Gulch"
      }
    },
    {
      "geometry": {
        "type": "Point",
        "coordinates": [
          -121.6333,
          41.9833
        ]
      },
      "type": "Feature",
      "properties": {
        "hierarchy": [
          "tgn:2564168",
          "tgn:1000001",
          "tgn:7012149",
          "tgn:7029392"
        ],
        "placetype": [
          "aat:300006075"
        ],
        "id": 2564168,
        "name:xx": "P1 Canal"
      }
    },
    {
      "geometry": {
        "type": "Point",
        "coordinates": [
          -110.8333,
          34.2833
        ]
      },
      "type": "Feature",
      "properties": {
        "hierarchy": [
          "tgn:2564169",
          "tgn:1000001",
          "tgn:7006451",
          "tgn:2000092",
          "tgn:7012149",
          "tgn:7029392"
        ],
        "placetype": [
          "aat:300006191"
        ],
        "id": 2564169,
        "name:xx": "P51 Tank"
      }
    }
  ]
}
