{
  "geometry": {
    "type": "Point",
    "coordinates": [
      -84.3167,
      35.2167
    ]
  },
  "type": "Feature",
  "properties": {
    "hierarchy": [
      "tgn:2682807",
      "tgn:1000001",
      "tgn:7012149",
      "tgn:2001898",
      "tgn:7007825",
      "tgn:7029392"
    ],
    "placetype": [
      "aat:300000390"
    ],
    "id": 2682807,
    "name:xx": "Southwest Lonsdale Mine"
  }
}
