{
  "geometry": {
    "type": "Point",
    "coordinates": [
      114.1667,
      30.9333
    ]
  },
  "type": "Feature",
  "properties": {
    "hierarchy": [
      "tgn:1074148",
      "tgn:1000004",
      "tgn:7002078",
      "tgn:1000111",
      "tgn:7029392"
    ],
    "placetype": [
      "aat:300008347"
    ],
    "id": 1074148,
    "name:xx": "Zhujiawan"
  }
}
