{
  "geometry": {
    "type": "Point",
    "coordinates": [
      3.68235,
      50.31774
    ]
  },
  "type": "Feature",
  "properties": {
    "hierarchy": [
      "tgn:7242256",
      "tgn:7007877",
      "tgn:1000003",
      "tgn:1000063",
      "tgn:4012014",
      "tgn:7029392"
    ],
    "placetype": [
      "aat:300008347"
    ],
    "id": 7242256,
    "name:xx": "La Houlette"
  }
}
