{
  "geometry": {
    "type": "Point",
    "coordinates": [
      -115.7833,
      39.5167
    ]
  },
  "type": "Feature",
  "properties": {
    "hierarchy": [
      "tgn:2350134",
      "tgn:1000001",
      "tgn:7012149",
      "tgn:2001420",
      "tgn:7007526",
      "tgn:7029392"
    ],
    "placetype": [
      "aat:300000390"
    ],
    "id": 2350134,
    "name:xx": "Gimmie Mine"
  }
}
