{
  "geometry": {
    "type": "Point",
    "coordinates": [
      -88.6167,
      30.4833
    ]
  },
  "type": "Feature",
  "properties": {
    "hierarchy": [
      "tgn:2582829",
      "tgn:1000001",
      "tgn:7012149",
      "tgn:2001115",
      "tgn:7007522",
      "tgn:7029392"
    ],
    "placetype": [
      "aat:300008791"
    ],
    "id": 2582829,
    "name:xx": "Pine Island"
  }
}
