{
  "geometry": {
    "type": "Point",
    "coordinates": [
      -105.1333,
      38.7333
    ]
  },
  "type": "Feature",
  "properties": {
    "hierarchy": [
      "tgn:2334512",
      "tgn:1000001",
      "tgn:7012149",
      "tgn:7007158",
      "tgn:2000251",
      "tgn:7029392"
    ],
    "placetype": [
      "aat:300000390"
    ],
    "id": 2334512,
    "name:xx": "Forest Queen Mine"
  }
}
