{
  "type": "FeatureCollection",
  "features": [
    {
      "geometry": {
        "type": "Point",
        "coordinates": [
          -95.8167,
          32.7833
        ]
      },
      "type": "Feature",
      "properties": {
        "hierarchy": [
          "tgn:2328020",
          "tgn:1000001",
          "tgn:7012149",
          "tgn:1002816",
          "tgn:7007826",
          "tgn:7029392"
        ],
        "placetype": [
          "aat:300008680"
        ],
        "id": 2328020,
        "name:xx": "Fish Lake"
      }
    },
    {
      "geometry": {
        "type": "Point",
        "coordinates": [
          -111.7,
          38.5333
        ]
      },
      "type": "Feature",
      "properties": {
        "hierarchy": [
          "tgn:2328021",
          "tgn:1000001",
          "tgn:7012149",
          "tgn:2002121",
          "tgn:7007827",
          "tgn:7029392"
        ],
        "placetype": [
          "aat:300008680"
        ],
        "id": 2328021,
        "name:xx": "Fish Lake"
      }
    },
    {
      "geometry": {
        "type": "Point",
        "coordinates": [
          -109.85,
          40.7167
        ]
      },
      "type": "Feature",
      "properties": {
        "hierarchy": [
          "tgn:2328022",
          "tgn:1000001",
          "tgn:7012149",
          "tgn:2002124",
          "tgn:7007827",
          "tgn:7029392"
        ],
        "placetype": [
          "aat:300008680"
        ],
        "id": 2328022,
        "name:xx": "Fish Lake"
      }
    },
    {
      "geometry": {
        "type": "Point",
        "coordinates": [
          -110.0667,
          40.8333
        ]
      },
      "type": "Feature",
      "properties": {
        "hierarchy": [
          "tgn:2328023",
          "tgn:1000001",
          "tgn:7012149",
          "tgn:2002122",
          "tgn:7007827",
          "tgn:7029392"
        ],
        "placetype": [
          "aat:300008680"
        ],
        "id": 2328023,
        "name:xx": "Fish Lake"
      }
    },
    {
      "geometry": {
        "type": "Point",
        "coordinates": [
          -110.9333,
          40.75
        ]
      },
      "type": "Feature",
      "properties": {
        "hierarchy": [
          "tgn:2328024",
          "tgn:1000001",
          "tgn:7012149",
          "tgn:2002122",
          "tgn:7007827",
          "tgn:7029392"
        ],
        "placetype": [
          "aat:300006191"
        ],
        "id": 2328024,
        "name:xx": "Fish Lake"
      }
    },
    {
      "geometry": {
        "type": "Point",
        "coordinates": [
          -121.35,
          46.35
        ]
      },
      "type": "Feature",
      "properties": {
        "hierarchy": [
          "tgn:2328025",
          "tgn:1000001",
          "tgn:7012149",
          "tgn:1003042",
          "tgn:7007920",
          "tgn:7029392"
        ],
        "placetype": [
          "aat:300008680"
        ],
        "id": 2328025,
        "name:xx": "Fish Lake"
      }
    },
    {
      "geometry": {
        "type": "Point",
        "coordinates": [
          -118.2833,
          48.2
        ]
      },
      "type": "Feature",
      "properties": {
        "hierarchy": [
          "tgn:2328026",
          "tgn:1000001",
          "tgn:2002243",
          "tgn:7012149",
          "tgn:7007920",
          "tgn:7029392"
        ],
        "placetype": [
          "aat:300008680"
        ],
        "id": 2328026,
        "name:xx": "Fish Lake"
      }
    },
    {
      "geometry": {
        "type": "Point",
        "coordinates": [
          -121.95,
          47.2667
        ]
      },
      "type": "Feature",
      "properties": {
        "hierarchy": [
          "tgn:2328027",
          "tgn:1000001",
          "tgn:7012149",
          "tgn:7018871",
          "tgn:7007920",
          "tgn:7029392"
        ],
        "placetype": [
          "aat:300008680"
        ],
        "id": 2328027,
        "name:xx": "Fish Lake"
      }
    },
    {
      "geometry": {
        "type": "Point",
        "coordinates": [
          -117.5167,
          47.5167
        ]
      },
      "type": "Feature",
      "properties": {
        "hierarchy": [
          "tgn:2328028",
          "tgn:1000001",
          "tgn:7012149",
          "tgn:2002249",
          "tgn:7007920",
          "tgn:7029392"
        ],
        "placetype": [
          "aat:300008680"
        ],
        "id": 2328028,
        "name:xx": "Fish Lake"
      }
    },
    {
      "geometry": {
        "type": "Point",
        "coordinates": [
          -119.0333,
          47.8667
        ]
      },
      "type": "Feature",
      "properties": {
        "hierarchy": [
          "tgn:2328029",
          "tgn:1000001",
          "tgn:7012149",
          "tgn:2002246",
          "tgn:7007920",
          "tgn:7029392"
        ],
        "placetype": [
          "aat:300008680"
        ],
        "id": 2328029,
        "name:xx": "Fish Lake"
      }
    }
  ]
}
