{
  "geometry": {
    "type": "Point",
    "coordinates": [
      -96.4167,
      32.9333
    ]
  },
  "type": "Feature",
  "properties": {
    "hierarchy": [
      "tgn:2185848",
      "tgn:1000001",
      "tgn:7012149",
      "tgn:1002834",
      "tgn:7007826",
      "tgn:7029392"
    ],
    "placetype": [
      "aat:300006191"
    ],
    "id": 2185848,
    "name:xx": "Boles Lake"
  }
}
