{
  "geometry": {
    "type": "Point",
    "coordinates": [
      -88.05,
      33.4833
    ]
  },
  "type": "Feature",
  "properties": {
    "hierarchy": [
      "tgn:2277303",
      "tgn:7002659",
      "tgn:1000001",
      "tgn:7012149",
      "tgn:2000053",
      "tgn:7029392"
    ],
    "placetype": [
      "aat:300006191"
    ],
    "id": 2277303,
    "name:xx": "Davis Lake"
  }
}
