{
  "geometry": {
    "type": "Point",
    "coordinates": [
      -94.0333,
      29.75
    ]
  },
  "type": "Feature",
  "properties": {
    "hierarchy": [
      "tgn:2774451",
      "tgn:1000001",
      "tgn:7012149",
      "tgn:2002011",
      "tgn:7007826",
      "tgn:7029392"
    ],
    "placetype": [
      "aat:300008680"
    ],
    "id": 2774451,
    "name:xx": "Willow Lake"
  }
}
