{
  "geometry": {
    "type": "Point",
    "coordinates": [
      -83.0667,
      39.2167
    ]
  },
  "type": "Feature",
  "properties": {
    "hierarchy": [
      "tgn:2146001",
      "tgn:1000001",
      "tgn:7012149",
      "tgn:1002835",
      "tgn:7007706",
      "tgn:7029392"
    ],
    "placetype": [
      "aat:300008798"
    ],
    "id": 2146001,
    "name:xx": "Ball Knob"
  }
}
