{
  "geometry": {
    "type": "Point",
    "coordinates": [
      -94.2833,
      32.6667
    ]
  },
  "type": "Feature",
  "properties": {
    "hierarchy": [
      "tgn:2158965",
      "tgn:1000001",
      "tgn:7012149",
      "tgn:1002460",
      "tgn:7007826",
      "tgn:7029392"
    ],
    "placetype": [
      "aat:300008706"
    ],
    "id": 2158965,
    "name:xx": "Beckum Creek"
  }
}
