{
  "geometry": {
    "type": "Point",
    "coordinates": [
      120.25,
      36.8667
    ]
  },
  "type": "Feature",
  "properties": {
    "hierarchy": [
      "tgn:1074132",
      "tgn:1000004",
      "tgn:7002085",
      "tgn:1000111",
      "tgn:7029392"
    ],
    "placetype": [
      "aat:300008347"
    ],
    "id": 1074132,
    "name:xx": "Zhugou"
  }
}
