{
  "geometry": {
    "type": "Point",
    "coordinates": [
      -94.9333,
      37.2833
    ]
  },
  "type": "Feature",
  "properties": {
    "hierarchy": [
      "tgn:2161345",
      "tgn:1000001",
      "tgn:2000670",
      "tgn:7012149",
      "tgn:7007254",
      "tgn:7029392"
    ],
    "placetype": [
      "aat:300008798"
    ],
    "id": 2161345,
    "name:xx": "Bell Mound"
  }
}
