{
  "geometry": {
    "type": "Point",
    "coordinates": [
      -73.9333,
      44.7833
    ]
  },
  "type": "Feature",
  "properties": {
    "hierarchy": [
      "tgn:2567134",
      "tgn:1000001",
      "tgn:1002284",
      "tgn:7012149",
      "tgn:7007568",
      "tgn:7029392"
    ],
    "placetype": [
      "aat:300008798"
    ],
    "id": 2567134,
    "name:xx": "Panther Hill"
  }
}
