{
  "type": "FeatureCollection",
  "features": [
    {
      "geometry": {
        "type": "Point",
        "coordinates": [
          -106.733333,
          31.4
        ]
      },
      "type": "Feature",
      "properties": {
        "hierarchy": [
          "tgn:7379130",
          "tgn:7005581",
          "tgn:1000001",
          "tgn:7005560",
          "tgn:7029392"
        ],
        "placetype": [
          "aat:300007783"
        ],
        "id": 7379130,
        "name:xx": "Mezquite"
      }
    },
    {
      "geometry": {
        "type": "Point",
        "coordinates": [
          -101.133333,
          27.833333
        ]
      },
      "type": "Feature",
      "properties": {
        "hierarchy": [
          "tgn:7379131",
          "tgn:1001853",
          "tgn:1000001",
          "tgn:7005560",
          "tgn:7029392"
        ],
        "placetype": [
          "aat:300007783"
        ],
        "id": 7379131,
        "name:xx": "Mezquite"
      }
    },
    {
      "geometry": {
        "type": "Point",
        "coordinates": [
          -109.9,
          28.35
        ]
      },
      "type": "Feature",
      "properties": {
        "hierarchy": [
          "tgn:7379132",
          "tgn:1000001",
          "tgn:1001960",
          "tgn:7005560",
          "tgn:7029392"
        ],
        "placetype": [
          "aat:300008347"
        ],
        "id": 7379132,
        "name:xx": "Mezquite"
      }
    },
    {
      "geometry": {
        "type": "Point",
        "coordinates": [
          -106.15,
          28.266667
        ]
      },
      "type": "Feature",
      "properties": {
        "hierarchy": [
          "tgn:7379133",
          "tgn:7005581",
          "tgn:1000001",
          "tgn:7005560",
          "tgn:7029392"
        ],
        "placetype": [
          "aat:300008347"
        ],
        "id": 7379133,
        "name:xx": "Mezquite"
      }
    },
    {
      "geometry": {
        "type": "Point",
        "coordinates": [
          -105.516667,
          26.866667
        ]
      },
      "type": "Feature",
      "properties": {
        "hierarchy": [
          "tgn:7379134",
          "tgn:7005581",
          "tgn:1000001",
          "tgn:7005560",
          "tgn:7029392"
        ],
        "placetype": [
          "aat:300008347"
        ],
        "id": 7379134,
        "name:xx": "Mezquite"
      }
    },
    {
      "geometry": {
        "type": "Point",
        "coordinates": [
          -108.741667,
          26.5525
        ]
      },
      "type": "Feature",
      "properties": {
        "hierarchy": [
          "tgn:7379135",
          "tgn:1000001",
          "tgn:7005595",
          "tgn:7005560",
          "tgn:7029392"
        ],
        "placetype": [
          "aat:300008347"
        ],
        "id": 7379135,
        "name:xx": "Mezquite"
      }
    },
    {
      "geometry": {
        "type": "Point",
        "coordinates": [
          -108.566667,
          26.433333
        ]
      },
      "type": "Feature",
      "properties": {
        "hierarchy": [
          "tgn:7379136",
          "tgn:1000001",
          "tgn:7005595",
          "tgn:7005560",
          "tgn:7029392"
        ],
        "placetype": [
          "aat:300008347"
        ],
        "id": 7379136,
        "name:xx": "Mezquite"
      }
    },
    {
      "geometry": {
        "type": "Point",
        "coordinates": [
          -102.033333,
          25.5
        ]
      },
      "type": "Feature",
      "properties": {
        "hierarchy": [
          "tgn:7379137",
          "tgn:1001853",
          "tgn:1000001",
          "tgn:7005560",
          "tgn:7029392"
        ],
        "placetype": [
          "aat:300008347"
        ],
        "id": 7379137,
        "name:xx": "Mezquite"
      }
    },
    {
      "geometry": {
        "type": "Point",
        "coordinates": [
          -107.633333,
          24.816667
        ]
      },
      "type": "Feature",
      "properties": {
        "hierarchy": [
          "tgn:7379138",
          "tgn:1000001",
          "tgn:7005595",
          "tgn:7005560",
          "tgn:7029392"
        ],
        "placetype": [
          "aat:300008347"
        ],
        "id": 7379138,
        "name:xx": "Mezquite"
      }
    },
    {
      "geometry": {
        "type": "Point",
        "coordinates": [
          -104.516667,
          24.716667
        ]
      },
      "type": "Feature",
      "properties": {
        "hierarchy": [
          "tgn:7379139",
          "tgn:7005583",
          "tgn:1000001",
          "tgn:7005560",
          "tgn:7029392"
        ],
        "placetype": [
          "aat:300008347"
        ],
        "id": 7379139,
        "name:xx": "Mezquite"
      }
    }
  ]
}
