{
  "type": "FeatureCollection",
  "features": [
    {
      "geometry": {
        "type": "Point",
        "coordinates": [
          -88.9,
          42.8833
        ]
      },
      "type": "Feature",
      "properties": {
        "hierarchy": [
          "tgn:2349090",
          "tgn:1000001",
          "tgn:7012149",
          "tgn:1002522",
          "tgn:7007922",
          "tgn:7029392"
        ],
        "placetype": [
          "aat:300132316"
        ],
        "id": 2349090,
        "name:xx": "Gilbert Bay"
      }
    },
    {
      "geometry": {
        "type": "Point",
        "coordinates": [
          -73.4,
          41.2667
        ]
      },
      "type": "Feature",
      "properties": {
        "hierarchy": [
          "tgn:2349091",
          "tgn:1002366",
          "tgn:1000001",
          "tgn:7012149",
          "tgn:7007159",
          "tgn:7029392"
        ],
        "placetype": [
          "aat:300008699"
        ],
        "id": 2349091,
        "name:xx": "Gilbert Bennett Brook"
      }
    },
    {
      "geometry": {
        "type": "Point",
        "coordinates": [
          -85.55,
          34.5167
        ]
      },
      "type": "Feature",
      "properties": {
        "hierarchy": [
          "tgn:2349092",
          "tgn:7002659",
          "tgn:1000001",
          "tgn:7012149",
          "tgn:7021514",
          "tgn:7029392"
        ],
        "placetype": [
          "aat:300008699"
        ],
        "id": 2349092,
        "name:xx": "Gilbert Branch"
      }
    },
    {
      "geometry": {
        "type": "Point",
        "coordinates": [
          -85.85,
          34.7167
        ]
      },
      "type": "Feature",
      "properties": {
        "hierarchy": [
          "tgn:2349093",
          "tgn:7002659",
          "tgn:1000001",
          "tgn:7012149",
          "tgn:2000035",
          "tgn:7029392"
        ],
        "placetype": [
          "aat:300008699"
        ],
        "id": 2349093,
        "name:xx": "Gilbert Branch"
      }
    },
    {
      "geometry": {
        "type": "Point",
        "coordinates": [
          -92.3833,
          33.4667
        ]
      },
      "type": "Feature",
      "properties": {
        "hierarchy": [
          "tgn:2349094",
          "tgn:1000001",
          "tgn:7016172",
          "tgn:2000111",
          "tgn:7012149",
          "tgn:7029392"
        ],
        "placetype": [
          "aat:300008699"
        ],
        "id": 2349094,
        "name:xx": "Gilbert Branch"
      }
    },
    {
      "geometry": {
        "type": "Point",
        "coordinates": [
          -85.9,
          40.7333
        ]
      },
      "type": "Feature",
      "properties": {
        "hierarchy": [
          "tgn:2349095",
          "tgn:1000001",
          "tgn:7012149",
          "tgn:7007252",
          "tgn:7029392"
        ],
        "placetype": [
          "aat:300008699"
        ],
        "id": 2349095,
        "name:xx": "Gilbert Branch"
      }
    },
    {
      "geometry": {
        "type": "Point",
        "coordinates": [
          -93.5833,
          31.3167
        ]
      },
      "type": "Feature",
      "properties": {
        "hierarchy": [
          "tgn:2349096",
          "tgn:1000001",
          "tgn:7012149",
          "tgn:2000896",
          "tgn:7007256",
          "tgn:7029392"
        ],
        "placetype": [
          "aat:300008699"
        ],
        "id": 2349096,
        "name:xx": "Gilbert Branch"
      }
    },
    {
      "geometry": {
        "type": "Point",
        "coordinates": [
          -83.4833,
          43.5333
        ]
      },
      "type": "Feature",
      "properties": {
        "hierarchy": [
          "tgn:2349097",
          "tgn:1000001",
          "tgn:7012149",
          "tgn:2000997",
          "tgn:7007520",
          "tgn:7029392"
        ],
        "placetype": [
          "aat:300008699"
        ],
        "id": 2349097,
        "name:xx": "Gilbert Branch"
      }
    },
    {
      "geometry": {
        "type": "Point",
        "coordinates": [
          -82.8167,
          35.6833
        ]
      },
      "type": "Feature",
      "properties": {
        "hierarchy": [
          "tgn:2349098",
          "tgn:1000001",
          "tgn:7012149",
          "tgn:2001516",
          "tgn:7007709",
          "tgn:7029392"
        ],
        "placetype": [
          "aat:300008699"
        ],
        "id": 2349098,
        "name:xx": "Gilbert Branch"
      }
    },
    {
      "geometry": {
        "type": "Point",
        "coordinates": [
          -81.6667,
          36.0833
        ]
      },
      "type": "Feature",
      "properties": {
        "hierarchy": [
          "tgn:2349099",
          "tgn:1000001",
          "tgn:2001476",
          "tgn:7012149",
          "tgn:7007709",
          "tgn:7029392"
        ],
        "placetype": [
          "aat:300008699"
        ],
        "id": 2349099,
        "name:xx": "Gilbert Branch"
      }
    }
  ]
}
