{
  "geometry": {
    "type": "Point",
    "coordinates": [
      89.36612,
      26.734554
    ]
  },
  "type": "Feature",
  "properties": {
    "hierarchy": [
      "tgn:7571472",
      "tgn:1000004",
      "tgn:7000198",
      "tgn:1001977",
      "tgn:7029392"
    ],
    "placetype": [
      "aat:300007783"
    ],
    "name:en": "Hāsimāra",
    "id": 7571472
  }
}
