{
  "geometry": {
    "type": "Point",
    "coordinates": [
      -72.75,
      41.7333
    ]
  },
  "type": "Feature",
  "properties": {
    "hierarchy": [
      "tgn:2781615",
      "tgn:1000001",
      "tgn:1002461",
      "tgn:7012149",
      "tgn:7007159",
      "tgn:7029392"
    ],
    "placetype": [
      "aat:300008680"
    ],
    "id": 2781615,
    "name:xx": "Woodridge Lake"
  }
}
