{
  "geometry": {
    "type": "Point",
    "coordinates": [
      -81.85,
      29.0833
    ]
  },
  "type": "Feature",
  "properties": {
    "hierarchy": [
      "tgn:2467862",
      "tgn:1000001",
      "tgn:7012149",
      "tgn:1002631",
      "tgn:7007240",
      "tgn:7029392"
    ],
    "placetype": [
      "aat:300008680"
    ],
    "id": 2467862,
    "name:xx": "Long Lake"
  }
}
