{
  "geometry": {
    "type": "Point",
    "coordinates": [
      -81.9667,
      31.3333
    ]
  },
  "type": "Feature",
  "properties": {
    "hierarchy": [
      "tgn:2490924",
      "tgn:1000001",
      "tgn:2000304",
      "tgn:7012149",
      "tgn:7007248",
      "tgn:7029392"
    ],
    "placetype": [
      "aat:300008347"
    ],
    "id": 2490924,
    "name:xx": "Manson"
  }
}
