{
  "geometry": {
    "type": "Point",
    "coordinates": [
      -83.0333,
      38.5333
    ]
  },
  "type": "Feature",
  "properties": {
    "hierarchy": [
      "tgn:2458623",
      "tgn:1000001",
      "tgn:7012149",
      "tgn:1002426",
      "tgn:7007255",
      "tgn:7029392"
    ],
    "placetype": [
      "aat:300008706"
    ],
    "id": 2458623,
    "name:xx": "Little Oak Creek"
  }
}
