{
  "geometry": {
    "type": "Point",
    "coordinates": [
      66.8333,
      36.0833
    ]
  },
  "type": "Feature",
  "properties": {
    "hierarchy": [
      "tgn:1065364",
      "tgn:7016612",
      "tgn:1001138",
      "tgn:1000004",
      "tgn:7029392"
    ],
    "placetype": [
      "aat:300008347"
    ],
    "id": 1065364,
    "name:xx": "Keshendeh"
  }
}
