{
  "type": "FeatureCollection",
  "features": [
    {
      "geometry": {
        "type": "Point",
        "coordinates": [
          4.433333,
          50.8
        ]
      },
      "type": "Feature",
      "properties": {
        "hierarchy": [
          "tgn:7253660",
          "tgn:7018237",
          "tgn:1000003",
          "tgn:1000063",
          "tgn:7029392"
        ],
        "placetype": [
          "aat:300008347"
        ],
        "id": 7253660,
        "name:xx": "Tenreuken"
      }
    },
    {
      "geometry": {
        "type": "Point",
        "coordinates": [
          3.787826,
          50.64977
        ]
      },
      "type": "Feature",
      "properties": {
        "hierarchy": [
          "tgn:7253661",
          "tgn:7007877",
          "tgn:1000003",
          "tgn:1000063",
          "tgn:4012014",
          "tgn:7029392"
        ],
        "placetype": [
          "aat:300000206"
        ],
        "id": 7253661,
        "name:xx": "Tenre"
      }
    },
    {
      "geometry": {
        "type": "Point",
        "coordinates": [
          4.133185,
          50.820999
        ]
      },
      "type": "Feature",
      "properties": {
        "hierarchy": [
          "tgn:7253664",
          "tgn:7003457",
          "tgn:1000003",
          "tgn:1000063",
          "tgn:7018236",
          "tgn:7029392"
        ],
        "placetype": [
          "aat:300008347"
        ],
        "id": 7253664,
        "name:xx": "Ten Nelleken"
      }
    },
    {
      "geometry": {
        "type": "Point",
        "coordinates": [
          3.483333,
          50.783333
        ]
      },
      "type": "Feature",
      "properties": {
        "hierarchy": [
          "tgn:7253665",
          "tgn:7003458",
          "tgn:1000003",
          "tgn:1000063",
          "tgn:7018236",
          "tgn:7029392"
        ],
        "placetype": [
          "aat:300008347"
        ],
        "id": 7253665,
        "name:xx": "Tenhove"
      }
    },
    {
      "geometry": {
        "type": "Point",
        "coordinates": [
          4.45,
          51.1
        ]
      },
      "type": "Feature",
      "properties": {
        "hierarchy": [
          "tgn:7253666",
          "tgn:7003456",
          "tgn:1000003",
          "tgn:1000063",
          "tgn:7018236",
          "tgn:7029392"
        ],
        "placetype": [
          "aat:300000206"
        ],
        "id": 7253666,
        "name:xx": "Ten Houtenhof"
      }
    },
    {
      "geometry": {
        "type": "Point",
        "coordinates": [
          4.208449,
          50.979339
        ]
      },
      "type": "Feature",
      "properties": {
        "hierarchy": [
          "tgn:7253667",
          "tgn:7003457",
          "tgn:1000003",
          "tgn:1000063",
          "tgn:7018236",
          "tgn:7029392"
        ],
        "placetype": [
          "aat:300008347"
        ],
        "id": 7253667,
        "name:xx": "Ten Houte"
      }
    },
    {
      "geometry": {
        "type": "Point",
        "coordinates": [
          4.2,
          50.983333
        ]
      },
      "type": "Feature",
      "properties": {
        "hierarchy": [
          "tgn:7253668",
          "tgn:7003457",
          "tgn:1000003",
          "tgn:1000063",
          "tgn:7018236",
          "tgn:7029392"
        ],
        "placetype": [
          "aat:300000206"
        ],
        "id": 7253668,
        "name:xx": "Ten Houte"
      }
    },
    {
      "geometry": {
        "type": "Point",
        "coordinates": [
          5.4,
          51.033333
        ]
      },
      "type": "Feature",
      "properties": {
        "hierarchy": [
          "tgn:7253669",
          "tgn:7003461",
          "tgn:1000003",
          "tgn:1000063",
          "tgn:7018236",
          "tgn:7029392"
        ],
        "placetype": [
          "aat:300008347"
        ],
        "id": 7253669,
        "name:xx": "Tenhout"
      }
    }
  ]
}
