{
  "geometry": {
    "type": "Point",
    "coordinates": [
      -113.8333,
      47.35
    ]
  },
  "type": "Feature",
  "properties": {
    "hierarchy": [
      "tgn:2479298",
      "tgn:1000001",
      "tgn:7012149",
      "tgn:2001291",
      "tgn:7007524",
      "tgn:7029392"
    ],
    "placetype": [
      "aat:300008680"
    ],
    "id": 2479298,
    "name:xx": "Lagoon Lake"
  }
}
