{
  "geometry": {
    "type": "Point",
    "coordinates": [
      -109.3833,
      33.4167
    ]
  },
  "type": "Feature",
  "properties": {
    "hierarchy": [
      "tgn:2154551",
      "tgn:1000001",
      "tgn:7006451",
      "tgn:2000095",
      "tgn:7012149",
      "tgn:7029392"
    ],
    "placetype": [
      "aat:300008697"
    ],
    "id": 2154551,
    "name:xx": "Bear Cub Spring"
  }
}
