{
  "type": "FeatureCollection",
  "features": [
    {
      "geometry": {
        "type": "Point",
        "coordinates": [
          -1.016,
          52.168
        ]
      },
      "type": "Feature",
      "properties": {
        "hierarchy": [
          "tgn:7030800",
          "tgn:7002445",
          "tgn:1000003",
          "tgn:7012031",
          "tgn:7008591",
          "tgn:7029392"
        ],
        "placetype": [
          "aat:300008347",
          "aat:300008372"
        ],
        "id": 7030800,
        "name:xx": "Cold Higham"
      }
    },
    {
      "geometry": {
        "type": "Point",
        "coordinates": [
          -0.9,
          52.183333
        ]
      },
      "type": "Feature",
      "properties": {
        "hierarchy": [
          "tgn:7030801",
          "tgn:7002445",
          "tgn:1000003",
          "tgn:7012031",
          "tgn:7008591",
          "tgn:7029392"
        ],
        "placetype": [
          "aat:300008347",
          "aat:300008372"
        ],
        "name:en": "Collingtree",
        "id": 7030801
      }
    },
    {
      "geometry": {
        "type": "Point",
        "coordinates": [
          -1,
          52.333
        ]
      },
      "type": "Feature",
      "properties": {
        "hierarchy": [
          "tgn:7030803",
          "tgn:7002445",
          "tgn:1000003",
          "tgn:7012031",
          "tgn:7008591",
          "tgn:7029392"
        ],
        "placetype": [
          "aat:300008347",
          "aat:300008372"
        ],
        "id": 7030803,
        "name:xx": "Coton"
      }
    },
    {
      "geometry": {
        "type": "Point",
        "coordinates": [
          -0.45,
          52.5
        ]
      },
      "type": "Feature",
      "properties": {
        "hierarchy": [
          "tgn:7030804",
          "tgn:7002445",
          "tgn:1000003",
          "tgn:7012031",
          "tgn:7008591",
          "tgn:7029392"
        ],
        "placetype": [
          "aat:300008347",
          "aat:300008372"
        ],
        "name:en": "Cotterstock",
        "id": 7030804
      }
    },
    {
      "geometry": {
        "type": "Point",
        "coordinates": [
          -0.75,
          52.483333
        ]
      },
      "type": "Feature",
      "properties": {
        "hierarchy": [
          "tgn:7030806",
          "tgn:7002445",
          "tgn:1000003",
          "tgn:7012031",
          "tgn:7008591",
          "tgn:7029392"
        ],
        "placetype": [
          "aat:300008347",
          "aat:300008372"
        ],
        "name:en": "Cottingham",
        "id": 7030806
      }
    },
    {
      "geometry": {
        "type": "Point",
        "coordinates": [
          -0.643,
          52.368
        ]
      },
      "type": "Feature",
      "properties": {
        "hierarchy": [
          "tgn:7030807",
          "tgn:7002445",
          "tgn:1000003",
          "tgn:7012031",
          "tgn:7008591",
          "tgn:7029392"
        ],
        "placetype": [
          "aat:300008347",
          "aat:300008372"
        ],
        "id": 7030807,
        "name:xx": "Cranford Saint John"
      }
    },
    {
      "geometry": {
        "type": "Point",
        "coordinates": [
          -0.779,
          52.368
        ]
      },
      "type": "Feature",
      "properties": {
        "hierarchy": [
          "tgn:7030808",
          "tgn:7002445",
          "tgn:1000003",
          "tgn:7012031",
          "tgn:7008591",
          "tgn:7029392"
        ],
        "placetype": [
          "aat:300008347",
          "aat:300008372"
        ],
        "id": 7030808,
        "name:xx": "Great Cransley"
      }
    },
    {
      "geometry": {
        "type": "Point",
        "coordinates": [
          -0.779,
          52.368
        ]
      },
      "type": "Feature",
      "properties": {
        "hierarchy": [
          "tgn:7030809",
          "tgn:7002445",
          "tgn:1000003",
          "tgn:7012031",
          "tgn:7008591",
          "tgn:7029392"
        ],
        "placetype": [
          "aat:300008347"
        ],
        "id": 7030809,
        "name:xx": "Little Cransley"
      }
    }
  ]
}
