{
  "geometry": {
    "type": "Point",
    "coordinates": [
      -74.2667,
      42.6167
    ]
  },
  "type": "Feature",
  "properties": {
    "hierarchy": [
      "tgn:2697231",
      "tgn:1000001",
      "tgn:7012149",
      "tgn:1002873",
      "tgn:7007568",
      "tgn:7029392"
    ],
    "placetype": [
      "aat:300008706"
    ],
    "id": 2697231,
    "name:xx": "Stony Creek"
  }
}
