{
  "geometry": {
    "type": "Point",
    "coordinates": [
      145.3333,
      -37.8833
    ]
  },
  "type": "Feature",
  "properties": {
    "hierarchy": [
      "tgn:1096894",
      "tgn:7000490",
      "tgn:1000006",
      "tgn:7006238",
      "tgn:7029392"
    ],
    "placetype": [
      "aat:300008347"
    ],
    "id": 1096894,
    "name:xx": "Ferny Creek"
  }
}
