{
  "geometry": {
    "type": "Point",
    "coordinates": [
      121.0923,
      22.8203
    ]
  },
  "type": "Feature",
  "properties": {
    "hierarchy": [
      "tgn:7498591",
      "tgn:1000004",
      "tgn:7491221",
      "tgn:1000141",
      "tgn:7029392"
    ],
    "placetype": [
      "aat:300007836"
    ],
    "id": 7498591,
    "name:xx": "Gaotai Qiao"
  }
}
