{
  "geometry": {
    "type": "Point",
    "coordinates": [
      -152.7167,
      63.6833
    ]
  },
  "type": "Feature",
  "properties": {
    "hierarchy": [
      "tgn:2327769",
      "tgn:7006450",
      "tgn:1000001",
      "tgn:7012149",
      "tgn:2000089",
      "tgn:7029392"
    ],
    "placetype": [
      "aat:300008680"
    ],
    "id": 2327769,
    "name:xx": "Fish Creek Lake"
  }
}
