{
  "geometry": {
    "type": "Point",
    "coordinates": [
      88.7175,
      22.491111
    ]
  },
  "type": "Feature",
  "properties": {
    "hierarchy": [
      "tgn:7588321",
      "tgn:1000004",
      "tgn:7000198",
      "tgn:1001977",
      "tgn:7029392"
    ],
    "placetype": [
      "aat:300008347"
    ],
    "name:en": "Thāola",
    "id": 7588321
  }
}
