{
  "geometry": {
    "type": "Point",
    "coordinates": [
      72.9167,
      57.6667
    ]
  },
  "type": "Feature",
  "properties": {
    "hierarchy": [
      "tgn:1054726",
      "tgn:1000004",
      "tgn:6004412",
      "tgn:7018214",
      "tgn:7002435",
      "tgn:7029392"
    ],
    "placetype": [
      "aat:300008347"
    ],
    "id": 1054726,
    "name:xx": "Yermilovka"
  }
}
