{
  "geometry": {
    "type": "Point",
    "coordinates": [
      -85.2333,
      32.4333
    ]
  },
  "type": "Feature",
  "properties": {
    "hierarchy": [
      "tgn:2476749",
      "tgn:7002659",
      "tgn:1000001",
      "tgn:7012149",
      "tgn:2000056",
      "tgn:7029392"
    ],
    "placetype": [
      "aat:300006191"
    ],
    "id": 2476749,
    "name:xx": "Lydells Pond"
  }
}
