{
  "geometry": {
    "type": "Point",
    "coordinates": [
      -87.8167,
      42.5833
    ]
  },
  "type": "Feature",
  "properties": {
    "hierarchy": [
      "tgn:2236085",
      "tgn:1000001",
      "tgn:7012149",
      "tgn:1002537",
      "tgn:7007922",
      "tgn:7029392"
    ],
    "placetype": [
      "aat:300008347"
    ],
    "id": 2236085,
    "name:xx": "Chicago"
  }
}
