{
  "geometry": {
    "type": "Point",
    "coordinates": [
      -78.1333,
      34.4167
    ]
  },
  "type": "Feature",
  "properties": {
    "hierarchy": [
      "tgn:2128663",
      "tgn:1000001",
      "tgn:7012149",
      "tgn:2001527",
      "tgn:7007709",
      "tgn:7029392"
    ],
    "placetype": [
      "aat:300132316"
    ],
    "id": 2128663,
    "name:xx": "Aldermans Cove"
  }
}
