{
  "geometry": {
    "type": "Point",
    "coordinates": [
      -156.75,
      63.4167
    ]
  },
  "type": "Feature",
  "properties": {
    "hierarchy": [
      "tgn:2319005",
      "tgn:7006450",
      "tgn:1000001",
      "tgn:7012149",
      "tgn:2000089",
      "tgn:7029392"
    ],
    "placetype": [
      "aat:300000390"
    ],
    "id": 2319005,
    "name:xx": "Esperanto Placer Mine"
  }
}
