{
  "geometry": {
    "type": "Point",
    "coordinates": [
      -72.0667,
      43.45
    ]
  },
  "type": "Feature",
  "properties": {
    "hierarchy": [
      "tgn:2147127",
      "tgn:1000001",
      "tgn:2001427",
      "tgn:7012149",
      "tgn:7007564",
      "tgn:7029392"
    ],
    "placetype": [
      "aat:300008680"
    ],
    "id": 2147127,
    "name:xx": "Baptist Pond"
  }
}
