{
  "geometry": {
    "type": "Point",
    "coordinates": [
      -94.7667,
      30.7333
    ]
  },
  "type": "Feature",
  "properties": {
    "hierarchy": [
      "tgn:2425587",
      "tgn:1000001",
      "tgn:7012149",
      "tgn:1002795",
      "tgn:7007826",
      "tgn:7029392"
    ],
    "placetype": [
      "aat:300008706"
    ],
    "id": 2425587,
    "name:xx": "Johnsons Mill Creek"
  }
}
