{
  "geometry": {
    "type": "Point",
    "coordinates": [
      -116.9167,
      44.5833
    ]
  },
  "type": "Feature",
  "properties": {
    "hierarchy": [
      "tgn:2392497",
      "tgn:1000001",
      "tgn:7012149",
      "tgn:2000495",
      "tgn:7007250",
      "tgn:7029392"
    ],
    "placetype": [
      "aat:300008798"
    ],
    "id": 2392497,
    "name:xx": "Hitt Peak"
  }
}
