{
  "type": "FeatureCollection",
  "features": [
    {
      "geometry": {
        "type": "Point",
        "coordinates": [
          -93.6833,
          35.7667
        ]
      },
      "type": "Feature",
      "properties": {
        "hierarchy": [
          "tgn:2124930",
          "tgn:1000001",
          "tgn:7016172",
          "tgn:7012149",
          "tgn:2000148",
          "tgn:7029392"
        ],
        "placetype": [
          "aat:300008699"
        ],
        "id": 2124930,
        "name:xx": "Abner Branch"
      }
    },
    {
      "geometry": {
        "type": "Point",
        "coordinates": [
          -83.3167,
          36.7333
        ]
      },
      "type": "Feature",
      "properties": {
        "hierarchy": [
          "tgn:2124931",
          "tgn:1000001",
          "tgn:7012149",
          "tgn:2000797",
          "tgn:7007255",
          "tgn:7029392"
        ],
        "placetype": [
          "aat:300008699"
        ],
        "id": 2124931,
        "name:xx": "Abner Branch"
      }
    },
    {
      "geometry": {
        "type": "Point",
        "coordinates": [
          -83.2333,
          36.95
        ]
      },
      "type": "Feature",
      "properties": {
        "hierarchy": [
          "tgn:2124932",
          "tgn:1000001",
          "tgn:7012149",
          "tgn:2000811",
          "tgn:7007255",
          "tgn:7029392"
        ],
        "placetype": [
          "aat:300008699"
        ],
        "id": 2124932,
        "name:xx": "Abner Branch"
      }
    },
    {
      "geometry": {
        "type": "Point",
        "coordinates": [
          -82.9,
          37.0333
        ]
      },
      "type": "Feature",
      "properties": {
        "hierarchy": [
          "tgn:2124933",
          "tgn:1000001",
          "tgn:7012149",
          "tgn:2000812",
          "tgn:7007255",
          "tgn:7029392"
        ],
        "placetype": [
          "aat:300008699"
        ],
        "id": 2124933,
        "name:xx": "Abner Branch"
      }
    },
    {
      "geometry": {
        "type": "Point",
        "coordinates": [
          -83.2333,
          36.9333
        ]
      },
      "type": "Feature",
      "properties": {
        "hierarchy": [
          "tgn:2124934",
          "tgn:1000001",
          "tgn:7012149",
          "tgn:7007255",
          "tgn:7029392"
        ],
        "placetype": [
          "aat:300008699"
        ],
        "id": 2124934,
        "name:xx": "Abner Branch"
      }
    },
    {
      "geometry": {
        "type": "Point",
        "coordinates": [
          -82.2,
          37.1
        ]
      },
      "type": "Feature",
      "properties": {
        "hierarchy": [
          "tgn:2124935",
          "tgn:1000001",
          "tgn:7012149",
          "tgn:7007919",
          "tgn:7029392"
        ],
        "placetype": [
          "aat:300008699"
        ],
        "id": 2124935,
        "name:xx": "Abner Branch"
      }
    },
    {
      "geometry": {
        "type": "Point",
        "coordinates": [
          -74.3,
          43.2833
        ]
      },
      "type": "Feature",
      "properties": {
        "hierarchy": [
          "tgn:2124936",
          "tgn:1000001",
          "tgn:7012149",
          "tgn:1002440",
          "tgn:7007568",
          "tgn:7029392"
        ],
        "placetype": [
          "aat:300008699"
        ],
        "id": 2124936,
        "name:xx": "Abner Brook"
      }
    },
    {
      "geometry": {
        "type": "Point",
        "coordinates": [
          -86.45,
          39.8
        ]
      },
      "type": "Feature",
      "properties": {
        "hierarchy": [
          "tgn:2124937",
          "tgn:1000001",
          "tgn:7012149",
          "tgn:1002465",
          "tgn:7007252",
          "tgn:7029392"
        ],
        "placetype": [
          "aat:300008706"
        ],
        "id": 2124937,
        "name:xx": "Abner Creek"
      }
    },
    {
      "geometry": {
        "type": "Point",
        "coordinates": [
          -82.7833,
          35.0833
        ]
      },
      "type": "Feature",
      "properties": {
        "hierarchy": [
          "tgn:2124938",
          "tgn:1000001",
          "tgn:7012149",
          "tgn:2001763",
          "tgn:7007712",
          "tgn:7029392"
        ],
        "placetype": [
          "aat:300008706"
        ],
        "id": 2124938,
        "name:xx": "Abner Creek"
      }
    },
    {
      "geometry": {
        "type": "Point",
        "coordinates": [
          -82.1833,
          34.8833
        ]
      },
      "type": "Feature",
      "properties": {
        "hierarchy": [
          "tgn:2124939",
          "tgn:1000001",
          "tgn:7012149",
          "tgn:2001766",
          "tgn:7007712",
          "tgn:7029392"
        ],
        "placetype": [
          "aat:300008706"
        ],
        "id": 2124939,
        "name:xx": "Abner Creek"
      }
    }
  ]
}
