{
  "geometry": {
    "type": "Point",
    "coordinates": [
      -78.45,
      41.5167
    ]
  },
  "type": "Feature",
  "properties": {
    "hierarchy": [
      "tgn:2370332",
      "tgn:1000001",
      "tgn:7012149",
      "tgn:1002352",
      "tgn:7007710",
      "tgn:7029392"
    ],
    "placetype": [
      "aat:300008761"
    ],
    "id": 2370332,
    "name:xx": "H C Hollow"
  }
}
