{
  "geometry": {
    "type": "Point",
    "coordinates": [
      -113.25,
      28.833333
    ]
  },
  "type": "Feature",
  "properties": {
    "hierarchy": [
      "tgn:1012082",
      "tgn:1000001",
      "tgn:1001960",
      "tgn:7005560",
      "tgn:1009445",
      "tgn:7029392"
    ],
    "placetype": [
      "aat:300386846"
    ],
    "id": 1012082,
    "name:xx": "Las Ánimas, Punta"
  }
}
