{
  "type": "FeatureCollection",
  "features": [
    {
      "geometry": {
        "type": "Point",
        "coordinates": [
          -108.1667,
          32.8833
        ]
      },
      "type": "Feature",
      "properties": {
        "hierarchy": [
          "tgn:2736510",
          "tgn:1000001",
          "tgn:7012149",
          "tgn:2001437",
          "tgn:7007566",
          "tgn:7029392"
        ],
        "placetype": [
          "aat:300008798"
        ],
        "id": 2736510,
        "name:xx": "Twin Sisters"
      }
    },
    {
      "geometry": {
        "type": "Point",
        "coordinates": [
          -124.0333,
          43.6167
        ]
      },
      "type": "Feature",
      "properties": {
        "hierarchy": [
          "tgn:2736511",
          "tgn:1000001",
          "tgn:7012149",
          "tgn:2001706",
          "tgn:7007708",
          "tgn:7029392"
        ],
        "placetype": [
          "aat:300008798"
        ],
        "id": 2736511,
        "name:xx": "Twin Sisters"
      }
    },
    {
      "geometry": {
        "type": "Point",
        "coordinates": [
          -103.7,
          43.7
        ]
      },
      "type": "Feature",
      "properties": {
        "hierarchy": [
          "tgn:2736512",
          "tgn:1000001",
          "tgn:2001786",
          "tgn:7012149",
          "tgn:7007713",
          "tgn:7029392"
        ],
        "placetype": [
          "aat:300008798"
        ],
        "id": 2736512,
        "name:xx": "Twin Sisters"
      }
    },
    {
      "geometry": {
        "type": "Point",
        "coordinates": [
          -103.45,
          44.0167
        ]
      },
      "type": "Feature",
      "properties": {
        "hierarchy": [
          "tgn:2736513",
          "tgn:1000001",
          "tgn:7012149",
          "tgn:2001821",
          "tgn:7007713",
          "tgn:7029392"
        ],
        "placetype": [
          "aat:300008798"
        ],
        "id": 2736513,
        "name:xx": "Twin Sisters"
      }
    },
    {
      "geometry": {
        "type": "Point",
        "coordinates": [
          -98.4,
          30
        ]
      },
      "type": "Feature",
      "properties": {
        "hierarchy": [
          "tgn:2736514",
          "tgn:1000001",
          "tgn:2001942",
          "tgn:7012149",
          "tgn:7007826",
          "tgn:7029392"
        ],
        "placetype": [
          "aat:300008347"
        ],
        "id": 2736514,
        "name:xx": "Twin Sisters"
      }
    },
    {
      "geometry": {
        "type": "Point",
        "coordinates": [
          -99.0333,
          29.9667
        ]
      },
      "type": "Feature",
      "properties": {
        "hierarchy": [
          "tgn:2736515",
          "tgn:1000001",
          "tgn:7012149",
          "tgn:2002018",
          "tgn:7007826",
          "tgn:7029392"
        ],
        "placetype": [
          "aat:300008798"
        ],
        "id": 2736515,
        "name:xx": "Twin Sisters"
      }
    },
    {
      "geometry": {
        "type": "Point",
        "coordinates": [
          -103.7167,
          30.3167
        ]
      },
      "type": "Feature",
      "properties": {
        "hierarchy": [
          "tgn:2736516",
          "tgn:1000001",
          "tgn:2001945",
          "tgn:7012149",
          "tgn:7007826",
          "tgn:7029392"
        ],
        "placetype": [
          "aat:300008798"
        ],
        "id": 2736516,
        "name:xx": "Twin Sisters"
      }
    },
    {
      "geometry": {
        "type": "Point",
        "coordinates": [
          -98.4333,
          29.9667
        ]
      },
      "type": "Feature",
      "properties": {
        "hierarchy": [
          "tgn:2736517",
          "tgn:1000001",
          "tgn:2001942",
          "tgn:7012149",
          "tgn:7007826",
          "tgn:7029392"
        ],
        "placetype": [
          "aat:300008798"
        ],
        "id": 2736517,
        "name:xx": "Twin Sisters"
      }
    },
    {
      "geometry": {
        "type": "Point",
        "coordinates": [
          -121.7333,
          46.4833
        ]
      },
      "type": "Feature",
      "properties": {
        "hierarchy": [
          "tgn:2736518",
          "tgn:1000001",
          "tgn:7012149",
          "tgn:1002594",
          "tgn:7007920",
          "tgn:7029392"
        ],
        "placetype": [
          "aat:300008798"
        ],
        "id": 2736518,
        "name:xx": "Twin Sisters"
      }
    },
    {
      "geometry": {
        "type": "Point",
        "coordinates": [
          -118.3667,
          48.7
        ]
      },
      "type": "Feature",
      "properties": {
        "hierarchy": [
          "tgn:2736519",
          "tgn:1000001",
          "tgn:2002243",
          "tgn:7012149",
          "tgn:7007920",
          "tgn:7029392"
        ],
        "placetype": [
          "aat:300008798"
        ],
        "id": 2736519,
        "name:xx": "Twin Sisters"
      }
    }
  ]
}
