{
  "geometry": {
    "type": "Point",
    "coordinates": [
      31.143611,
      31.564444
    ]
  },
  "type": "Feature",
  "properties": {
    "hierarchy": [
      "tgn:7532248",
      "tgn:7001242",
      "tgn:7016833",
      "tgn:1001335",
      "tgn:7029392"
    ],
    "placetype": [
      "aat:300005433"
    ],
    "name:en": "Sakn 'Abd el-Galîl Ḥimeida",
    "id": 7532248
  }
}
