{
  "geometry": {
    "type": "Point",
    "coordinates": [
      -97.6667,
      38.7833
    ]
  },
  "type": "Feature",
  "properties": {
    "hierarchy": [
      "tgn:2000744",
      "tgn:1000001",
      "tgn:7012149",
      "tgn:7007254",
      "tgn:7029392"
    ],
    "placetype": [
      "aat:300387145",
      "aat:300000771"
    ],
    "id": 2000744,
    "name:xx": "Saline"
  }
}
