{
  "geometry": {
    "type": "Point",
    "coordinates": [
      -83.7167,
      48.3667
    ]
  },
  "type": "Feature",
  "properties": {
    "hierarchy": [
      "tgn:1112637",
      "tgn:7005685",
      "tgn:1000001",
      "tgn:7013154",
      "tgn:7029392"
    ],
    "placetype": [
      "aat:300132316"
    ],
    "id": 1112637,
    "name:xx": "Baltic Bay"
  }
}
