{
  "type": "FeatureCollection",
  "features": [
    {
      "geometry": {
        "type": "Point",
        "coordinates": [
          30.571895,
          24.794328
        ]
      },
      "type": "Feature",
      "properties": {
        "hierarchy": [
          "tgn:7527820",
          "tgn:7001242",
          "tgn:7016833",
          "tgn:7001334",
          "tgn:7029392"
        ],
        "placetype": [
          "aat:300005926"
        ],
        "name:en": "Sīdī Zakarīyah",
        "id": 7527820
      }
    },
    {
      "geometry": {
        "type": "Point",
        "coordinates": [
          30.518611,
          31.422778
        ]
      },
      "type": "Feature",
      "properties": {
        "hierarchy": [
          "tgn:7527821",
          "tgn:7001242",
          "tgn:7016833",
          "tgn:1001335",
          "tgn:7029392"
        ],
        "placetype": [
          "aat:300005926"
        ],
        "name:en": "Sīdī Yūsuf Abū Rājiḩ",
        "id": 7527821
      }
    },
    {
      "geometry": {
        "type": "Point",
        "coordinates": [
          30.512778,
          31.43
        ]
      },
      "type": "Feature",
      "properties": {
        "hierarchy": [
          "tgn:7527822",
          "tgn:7001242",
          "tgn:7016833",
          "tgn:1001335",
          "tgn:7029392"
        ],
        "placetype": [
          "aat:300008903"
        ],
        "name:en": "Sīdī Yūsuf, Gharrāqat",
        "id": 7527822
      }
    },
    {
      "geometry": {
        "type": "Point",
        "coordinates": [
          30.766667,
          28.2
        ]
      },
      "type": "Feature",
      "properties": {
        "hierarchy": [
          "tgn:7527823",
          "tgn:7001242",
          "tgn:7016833",
          "tgn:1001088",
          "tgn:7029392"
        ],
        "placetype": [
          "aat:300005926"
        ],
        "name:en": "Sīdī Yūsuf",
        "id": 7527823
      }
    },
    {
      "geometry": {
        "type": "Point",
        "coordinates": [
          31.383333,
          27.083333
        ]
      },
      "type": "Feature",
      "properties": {
        "hierarchy": [
          "tgn:7527824",
          "tgn:7001242",
          "tgn:7016833",
          "tgn:1001114",
          "tgn:7029392"
        ],
        "placetype": [
          "aat:300005926"
        ],
        "name:en": "Sīdī Yūsuf",
        "id": 7527824
      }
    },
    {
      "geometry": {
        "type": "Point",
        "coordinates": [
          31.5,
          26.666667
        ]
      },
      "type": "Feature",
      "properties": {
        "hierarchy": [
          "tgn:7527825",
          "tgn:7001242",
          "tgn:7016833",
          "tgn:7000124",
          "tgn:7029392"
        ],
        "placetype": [
          "aat:300005926"
        ],
        "name:en": "Sīdī Yūsuf",
        "id": 7527825
      }
    },
    {
      "geometry": {
        "type": "Point",
        "coordinates": [
          31.633333,
          26.633333
        ]
      },
      "type": "Feature",
      "properties": {
        "hierarchy": [
          "tgn:7527826",
          "tgn:7001242",
          "tgn:7016833",
          "tgn:7000124",
          "tgn:7029392"
        ],
        "placetype": [
          "aat:300005926"
        ],
        "name:en": "Sīdī Yūsuf",
        "id": 7527826
      }
    },
    {
      "geometry": {
        "type": "Point",
        "coordinates": [
          32.866667,
          24.466667
        ]
      },
      "type": "Feature",
      "properties": {
        "hierarchy": [
          "tgn:7527827",
          "tgn:7001242",
          "tgn:7016833",
          "tgn:7000122",
          "tgn:7029392"
        ],
        "placetype": [
          "aat:300005926"
        ],
        "name:en": "Sīdī Yūsuf",
        "id": 7527827
      }
    },
    {
      "geometry": {
        "type": "Point",
        "coordinates": [
          27.406525,
          30.978239
        ]
      },
      "type": "Feature",
      "properties": {
        "hierarchy": [
          "tgn:7527828",
          "tgn:7001242",
          "tgn:7016833",
          "tgn:1001418",
          "tgn:7029392"
        ],
        "placetype": [
          "aat:300005926"
        ],
        "name:en": "Sīdī Yūnus",
        "id": 7527828
      }
    },
    {
      "geometry": {
        "type": "Point",
        "coordinates": [
          30.9,
          27.283333
        ]
      },
      "type": "Feature",
      "properties": {
        "hierarchy": [
          "tgn:7527829",
          "tgn:7001242",
          "tgn:7016833",
          "tgn:1001114",
          "tgn:7029392"
        ],
        "placetype": [
          "aat:300005926"
        ],
        "name:en": "Sīdī Yūnus",
        "id": 7527829
      }
    }
  ]
}
