{
  "geometry": {
    "type": "Point",
    "coordinates": [
      39.1167,
      53.0167
    ]
  },
  "type": "Feature",
  "properties": {
    "hierarchy": [
      "tgn:1056348",
      "tgn:1000004",
      "tgn:7011575",
      "tgn:7018214",
      "tgn:7002435",
      "tgn:7029392"
    ],
    "placetype": [
      "aat:300008347"
    ],
    "id": 1056348,
    "name:xx": "Lebedyan"
  }
}
