{
  "geometry": {
    "type": "Point",
    "coordinates": [
      -64.7667,
      -7.3333
    ]
  },
  "type": "Feature",
  "properties": {
    "hierarchy": [
      "tgn:1021915",
      "tgn:1001826",
      "tgn:1000047",
      "tgn:7002456",
      "tgn:1000002",
      "tgn:7029392"
    ],
    "placetype": [
      "aat:300008347"
    ],
    "id": 1021915,
    "name:xx": "Lábrea"
  }
}
