{
  "geometry": {
    "type": "Point",
    "coordinates": [
      -57.85,
      -31.0833
    ]
  },
  "type": "Feature",
  "properties": {
    "hierarchy": [
      "tgn:1024882",
      "tgn:7002640",
      "tgn:1000002",
      "tgn:1000058",
      "tgn:7029392"
    ],
    "placetype": [
      "aat:300008347"
    ],
    "id": 1024882,
    "name:xx": "Constitución"
  }
}
