{
  "geometry": {
    "type": "Point",
    "coordinates": [
      -94.2667,
      46.8833
    ]
  },
  "type": "Feature",
  "properties": {
    "hierarchy": [
      "tgn:2458392",
      "tgn:1000001",
      "tgn:2001009",
      "tgn:7012149",
      "tgn:7007521",
      "tgn:7029392"
    ],
    "placetype": [
      "aat:300008680"
    ],
    "id": 2458392,
    "name:xx": "Little Mule Lake"
  }
}
