{
  "geometry": {
    "type": "Point",
    "coordinates": [
      -72.6333,
      78.3167
    ]
  },
  "type": "Feature",
  "properties": {
    "hierarchy": [
      "tgn:1016567",
      "tgn:7593552",
      "tgn:1000001",
      "tgn:7024573",
      "tgn:7029392"
    ],
    "placetype": [
      "aat:300008347",
      "aat:300167671"
    ],
    "id": 1016567,
    "name:xx": "Etah"
  }
}
