{
  "geometry": {
    "type": "Point",
    "coordinates": [
      -80.3167,
      40.8833
    ]
  },
  "type": "Feature",
  "properties": {
    "hierarchy": [
      "tgn:2087215",
      "tgn:1000001",
      "tgn:7012149",
      "tgn:1002580",
      "tgn:7007710",
      "tgn:7029392"
    ],
    "placetype": [
      "aat:300008347"
    ],
    "id": 2087215,
    "name:xx": "Chewton"
  }
}
