{
  "geometry": {
    "type": "Point",
    "coordinates": [
      35.75,
      30.1833
    ]
  },
  "type": "Feature",
  "properties": {
    "hierarchy": [
      "tgn:1081901",
      "tgn:1000004",
      "tgn:1000121",
      "tgn:1002092",
      "tgn:7029392"
    ],
    "placetype": [
      "aat:300008347",
      "aat:300387220"
    ],
    "id": 1081901,
    "name:xx": "Maʻān"
  }
}
