{
  "geometry": {
    "type": "Point",
    "coordinates": [
      -93.9667,
      32.0333
    ]
  },
  "type": "Feature",
  "properties": {
    "hierarchy": [
      "tgn:2042830",
      "tgn:1000001",
      "tgn:7020680",
      "tgn:7012149",
      "tgn:7007256",
      "tgn:7029392"
    ],
    "placetype": [
      "aat:300008347",
      "aat:300387210"
    ],
    "id": 2042830,
    "name:xx": "Funston"
  }
}
