{
  "geometry": {
    "type": "Point",
    "coordinates": [
      -110.3333,
      53.9167
    ]
  },
  "type": "Feature",
  "properties": {
    "hierarchy": [
      "tgn:1116341",
      "tgn:7005694",
      "tgn:7005685",
      "tgn:1000001",
      "tgn:7029392"
    ],
    "placetype": [
      "aat:300008680"
    ],
    "id": 1116341,
    "name:xx": "Frog Lake"
  }
}
