{
  "geometry": {
    "type": "Point",
    "coordinates": [
      -115.516667,
      30.25
    ]
  },
  "type": "Feature",
  "properties": {
    "hierarchy": [
      "tgn:7385020",
      "tgn:1001835",
      "tgn:1000001",
      "tgn:7005560",
      "tgn:7029392"
    ],
    "placetype": [
      "aat:300008763"
    ],
    "id": 7385020,
    "name:xx": "Palmas, Cañón de las"
  }
}
