{
  "geometry": {
    "type": "Point",
    "coordinates": [
      -78.6333,
      35.65
    ]
  },
  "type": "Feature",
  "properties": {
    "hierarchy": [
      "tgn:2628041",
      "tgn:1000001",
      "tgn:7012149",
      "tgn:2001548",
      "tgn:7007709",
      "tgn:7029392"
    ],
    "placetype": [
      "aat:300008347"
    ],
    "id": 2628041,
    "name:xx": "Rolling Hills"
  }
}
