{
  "geometry": {
    "type": "Point",
    "coordinates": [
      13.75,
      46.3333
    ]
  },
  "type": "Feature",
  "properties": {
    "hierarchy": [
      "tgn:1109169",
      "tgn:1000003",
      "tgn:7006670",
      "tgn:7029392"
    ],
    "placetype": [
      "aat:300386831"
    ],
    "name:en": "Julian Alps",
    "id": 1109169
  }
}
