{
  "geometry": {
    "type": "Point",
    "coordinates": [
      78.3758,
      24.9174
    ]
  },
  "type": "Feature",
  "properties": {
    "hierarchy": [
      "tgn:7582086",
      "tgn:1000004",
      "tgn:7000198",
      "tgn:7016722",
      "tgn:7029392"
    ],
    "placetype": [
      "aat:300008865"
    ],
    "name:en": "Pipra West Reserved Forest",
    "id": 7582086
  }
}
