{
  "geometry": {
    "type": "Point",
    "coordinates": [
      -82.35,
      27.9333
    ]
  },
  "type": "Feature",
  "properties": {
    "hierarchy": [
      "tgn:2682083",
      "tgn:1000001",
      "tgn:1002479",
      "tgn:7012149",
      "tgn:7007240",
      "tgn:7029392"
    ],
    "placetype": [
      "aat:300008347"
    ],
    "id": 2682083,
    "name:xx": "South Tampa"
  }
}
