{
  "geometry": {
    "type": "Point",
    "coordinates": [
      -82.8833,
      32.7667
    ]
  },
  "type": "Feature",
  "properties": {
    "hierarchy": [
      "tgn:2386535",
      "tgn:1000001",
      "tgn:7012149",
      "tgn:7007248",
      "tgn:7029392"
    ],
    "placetype": [
      "aat:300006191"
    ],
    "id": 2386535,
    "name:xx": "Herds Pond"
  }
}
