{
  "geometry": {
    "type": "Point",
    "coordinates": [
      -90.5167,
      43.6833
    ]
  },
  "type": "Feature",
  "properties": {
    "hierarchy": [
      "tgn:2522329",
      "tgn:1000001",
      "tgn:7012149",
      "tgn:2002358",
      "tgn:7007922",
      "tgn:7029392"
    ],
    "placetype": [
      "aat:300266640"
    ],
    "id": 2522329,
    "name:xx": "Moon Ridge"
  }
}
