{
  "geometry": {
    "type": "Point",
    "coordinates": [
      108.8333,
      15.15
    ]
  },
  "type": "Feature",
  "properties": {
    "hierarchy": [
      "tgn:1087217",
      "tgn:1000004",
      "tgn:7001054",
      "tgn:1000145",
      "tgn:7029392"
    ],
    "placetype": [
      "aat:300008347",
      "aat:300008375",
      "aat:300120599"
    ],
    "id": 1087217,
    "name:xx": "Quảng Ngãi"
  }
}
