{
  "geometry": {
    "type": "Point",
    "coordinates": [
      -96.2667,
      30.9333
    ]
  },
  "type": "Feature",
  "properties": {
    "hierarchy": [
      "tgn:2203142",
      "tgn:1000001",
      "tgn:1002199",
      "tgn:7012149",
      "tgn:7007826",
      "tgn:7029392"
    ],
    "placetype": [
      "aat:300008699"
    ],
    "id": 2203142,
    "name:xx": "Buckhorn Branch"
  }
}
