{
  "geometry": {
    "type": "Point",
    "coordinates": [
      -75.8667,
      41.3333
    ]
  },
  "type": "Feature",
  "properties": {
    "hierarchy": [
      "tgn:2208093",
      "tgn:1000001",
      "tgn:7012149",
      "tgn:1002612",
      "tgn:7007710",
      "tgn:7029392"
    ],
    "placetype": [
      "aat:300006191"
    ],
    "id": 2208093,
    "name:xx": "Burkett Pond"
  }
}
