{
  "geometry": {
    "type": "Point",
    "coordinates": [
      75.8159,
      15.9484
    ]
  },
  "type": "Feature",
  "properties": {
    "hierarchy": [
      "tgn:7593817",
      "tgn:1000004",
      "tgn:7000198",
      "tgn:1001882",
      "tgn:7029392"
    ],
    "placetype": [
      "aat:300008347",
      "aat:300000810",
      "aat:300073727",
      "aat:300008372",
      "aat:300000833",
      "aat:300143540",
      "aat:300263063"
    ],
    "id": 7593817,
    "name:xx": "Paṭṭadakal"
  }
}
