{
  "geometry": {
    "type": "Point",
    "coordinates": [
      -69.2667,
      46.4667
    ]
  },
  "type": "Feature",
  "properties": {
    "hierarchy": [
      "tgn:2239616",
      "tgn:1000001",
      "tgn:7012149",
      "tgn:2000928",
      "tgn:7007515",
      "tgn:7029392"
    ],
    "placetype": [
      "aat:300266640"
    ],
    "id": 2239616,
    "name:xx": "Churchill Ridge"
  }
}
