{
  "geometry": {
    "type": "Point",
    "coordinates": [
      -83.4667,
      33.0333
    ]
  },
  "type": "Feature",
  "properties": {
    "hierarchy": [
      "tgn:2251524",
      "tgn:1000001",
      "tgn:7012149",
      "tgn:7007248",
      "tgn:7029392"
    ],
    "placetype": [
      "aat:300008706"
    ],
    "id": 2251524,
    "name:xx": "Commissioner Creek"
  }
}
