{
  "type": "FeatureCollection",
  "features": [
    {
      "geometry": {
        "type": "Point",
        "coordinates": [
          -84.3167,
          36.4167
        ]
      },
      "type": "Feature",
      "properties": {
        "hierarchy": [
          "tgn:2404980",
          "tgn:1000001",
          "tgn:7012149",
          "tgn:2001843",
          "tgn:7007825",
          "tgn:7029392"
        ],
        "placetype": [
          "aat:300008699"
        ],
        "id": 2404980,
        "name:xx": "Hudson Branch"
      }
    },
    {
      "geometry": {
        "type": "Point",
        "coordinates": [
          -88.65,
          35.5
        ]
      },
      "type": "Feature",
      "properties": {
        "hierarchy": [
          "tgn:2404981",
          "tgn:1000001",
          "tgn:7012149",
          "tgn:2001893",
          "tgn:7007825",
          "tgn:7029392"
        ],
        "placetype": [
          "aat:300008699"
        ],
        "id": 2404981,
        "name:xx": "Hudson Branch"
      }
    },
    {
      "geometry": {
        "type": "Point",
        "coordinates": [
          -99.2667,
          31.05
        ]
      },
      "type": "Feature",
      "properties": {
        "hierarchy": [
          "tgn:2404982",
          "tgn:1000001",
          "tgn:7012149",
          "tgn:2002034",
          "tgn:7007826",
          "tgn:7029392"
        ],
        "placetype": [
          "aat:300008699"
        ],
        "id": 2404982,
        "name:xx": "Hudson Branch"
      }
    },
    {
      "geometry": {
        "type": "Point",
        "coordinates": [
          -96.3,
          31
        ]
      },
      "type": "Feature",
      "properties": {
        "hierarchy": [
          "tgn:2404983",
          "tgn:1000001",
          "tgn:7012149",
          "tgn:1002830",
          "tgn:7007826",
          "tgn:7029392"
        ],
        "placetype": [
          "aat:300008699"
        ],
        "id": 2404983,
        "name:xx": "Hudson Branch"
      }
    },
    {
      "geometry": {
        "type": "Point",
        "coordinates": [
          -105.4667,
          37.8667
        ]
      },
      "type": "Feature",
      "properties": {
        "hierarchy": [
          "tgn:2404984",
          "tgn:1000001",
          "tgn:7012149",
          "tgn:7007158",
          "tgn:2000246",
          "tgn:7029392"
        ],
        "placetype": [
          "aat:300008706"
        ],
        "id": 2404984,
        "name:xx": "Hudson Branch Medano Creek"
      }
    },
    {
      "geometry": {
        "type": "Point",
        "coordinates": [
          -69,
          46.1667
        ]
      },
      "type": "Feature",
      "properties": {
        "hierarchy": [
          "tgn:2404985",
          "tgn:1000001",
          "tgn:7012149",
          "tgn:2000928",
          "tgn:7007515",
          "tgn:7029392"
        ],
        "placetype": [
          "aat:300008699"
        ],
        "id": 2404985,
        "name:xx": "Hudson Brook"
      }
    },
    {
      "geometry": {
        "type": "Point",
        "coordinates": [
          -69,
          45.0833
        ]
      },
      "type": "Feature",
      "properties": {
        "hierarchy": [
          "tgn:2404986",
          "tgn:1000001",
          "tgn:7012149",
          "tgn:2000927",
          "tgn:7007515",
          "tgn:7029392"
        ],
        "placetype": [
          "aat:300008699"
        ],
        "id": 2404986,
        "name:xx": "Hudson Brook"
      }
    },
    {
      "geometry": {
        "type": "Point",
        "coordinates": [
          -73.1167,
          42.7333
        ]
      },
      "type": "Feature",
      "properties": {
        "hierarchy": [
          "tgn:2404987",
          "tgn:7013388",
          "tgn:1000001",
          "tgn:7012149",
          "tgn:7007517",
          "tgn:7029392"
        ],
        "placetype": [
          "aat:300008699"
        ],
        "id": 2404987,
        "name:xx": "Hudson Brook"
      }
    },
    {
      "geometry": {
        "type": "Point",
        "coordinates": [
          -71.5667,
          44.9333
        ]
      },
      "type": "Feature",
      "properties": {
        "hierarchy": [
          "tgn:2404988",
          "tgn:1000001",
          "tgn:1002361",
          "tgn:7012149",
          "tgn:7007828",
          "tgn:7029392"
        ],
        "placetype": [
          "aat:300008699"
        ],
        "id": 2404988,
        "name:xx": "Hudson Brook"
      }
    },
    {
      "geometry": {
        "type": "Point",
        "coordinates": [
          -103.4833,
          35.2333
        ]
      },
      "type": "Feature",
      "properties": {
        "hierarchy": [
          "tgn:2404989",
          "tgn:1000001",
          "tgn:7012149",
          "tgn:2001448",
          "tgn:7007566",
          "tgn:7029392"
        ],
        "placetype": [
          "aat:300006075"
        ],
        "id": 2404989,
        "name:xx": "Hudson Canal"
      }
    }
  ]
}
