{
  "geometry": {
    "type": "Point",
    "coordinates": [
      -76.7333,
      37.4833
    ]
  },
  "type": "Feature",
  "properties": {
    "hierarchy": [
      "tgn:2161783",
      "tgn:1000001",
      "tgn:7012149",
      "tgn:1002549",
      "tgn:7007919",
      "tgn:7029392"
    ],
    "placetype": [
      "aat:300008347"
    ],
    "id": 2161783,
    "name:xx": "Belleview"
  }
}
