{
  "geometry": {
    "type": "Point",
    "coordinates": [
      6.0667,
      48.8833
    ]
  },
  "type": "Feature",
  "properties": {
    "hierarchy": [
      "tgn:1032159",
      "tgn:1000003",
      "tgn:7002888",
      "tgn:1000070",
      "tgn:7029392"
    ],
    "placetype": [
      "aat:300008347"
    ],
    "id": 1032159,
    "name:xx": "Blénod-lès-Pont-à-Mousson"
  }
}
