{
  "geometry": {
    "type": "Point",
    "coordinates": [
      90.35,
      23.25
    ]
  },
  "type": "Feature",
  "properties": {
    "hierarchy": [
      "tgn:1135794",
      "tgn:1000004",
      "tgn:1000105",
      "tgn:7029392"
    ],
    "placetype": [
      "aat:300387055"
    ],
    "id": 1135794,
    "name:xx": "Pālang"
  }
}
