{
  "geometry": {
    "type": "Point",
    "coordinates": [
      -72.7333,
      42.2833
    ]
  },
  "type": "Feature",
  "properties": {
    "hierarchy": [
      "tgn:2242889",
      "tgn:1000001",
      "tgn:7013686",
      "tgn:7012149",
      "tgn:7007517",
      "tgn:7029392"
    ],
    "placetype": [
      "aat:300006191"
    ],
    "id": 2242889,
    "name:xx": "Clear Falls Pond"
  }
}
