{
  "geometry": {
    "type": "Point",
    "coordinates": [
      26.3333,
      55.4833
    ]
  },
  "type": "Feature",
  "properties": {
    "hierarchy": [
      "tgn:1116170",
      "tgn:7006557",
      "tgn:1000003",
      "tgn:7006542",
      "tgn:7029392"
    ],
    "placetype": [
      "aat:300008680"
    ],
    "id": 1116170,
    "name:xx": "Dysnų Ežeras"
  }
}
