{
  "geometry": {
    "type": "Point",
    "coordinates": [
      -97.35,
      40.4667
    ]
  },
  "type": "Feature",
  "properties": {
    "hierarchy": [
      "tgn:2749610",
      "tgn:1000001",
      "tgn:7012149",
      "tgn:7007525",
      "tgn:7029392"
    ],
    "placetype": [
      "aat:300008706"
    ],
    "id": 2749610,
    "name:xx": "Walnut Creek"
  }
}
