{
  "geometry": {
    "type": "Point",
    "coordinates": [
      120.5659,
      23.8811
    ]
  },
  "type": "Feature",
  "properties": {
    "hierarchy": [
      "tgn:7490988",
      "tgn:1000004",
      "tgn:7467799",
      "tgn:1000141",
      "tgn:7029392"
    ],
    "placetype": [
      "aat:300008347"
    ],
    "id": 7490988,
    "name:xx": "Paizilutou"
  }
}
