{
  "geometry": {
    "type": "Point",
    "coordinates": [
      -85.75,
      42.0167
    ]
  },
  "type": "Feature",
  "properties": {
    "hierarchy": [
      "tgn:2446474",
      "tgn:1000001",
      "tgn:7012149",
      "tgn:7007520",
      "tgn:7029392"
    ],
    "placetype": [
      "aat:300008680"
    ],
    "id": 2446474,
    "name:xx": "Lewis Lake"
  }
}
