{
  "geometry": {
    "type": "Point",
    "coordinates": [
      22.366667,
      37.45
    ]
  },
  "type": "Feature",
  "properties": {
    "hierarchy": [
      "tgn:7236136",
      "tgn:7002739",
      "tgn:7017076",
      "tgn:1000003",
      "tgn:1000074",
      "tgn:7029392"
    ],
    "placetype": [
      "aat:300008347"
    ],
    "id": 7236136,
    "name:xx": "Évandron"
  }
}
