{
  "geometry": {
    "type": "Point",
    "coordinates": [
      -112.2167,
      37.55
    ]
  },
  "type": "Feature",
  "properties": {
    "hierarchy": [
      "tgn:2543086",
      "tgn:1000001",
      "tgn:2002109",
      "tgn:7012149",
      "tgn:7007827",
      "tgn:7029392"
    ],
    "placetype": [
      "aat:300008761"
    ],
    "id": 2543086,
    "name:xx": "Noon Canyon"
  }
}
