{
  "geometry": {
    "type": "Point",
    "coordinates": [
      -122.8333,
      41.2833
    ]
  },
  "type": "Feature",
  "properties": {
    "hierarchy": [
      "tgn:2718322",
      "tgn:1000001",
      "tgn:7012149",
      "tgn:7007157",
      "tgn:2000189",
      "tgn:7029392"
    ],
    "placetype": [
      "aat:300008761"
    ],
    "id": 2718322,
    "name:xx": "Thompson Gulch"
  }
}
