{
  "type": "FeatureCollection",
  "features": [
    {
      "geometry": {
        "type": "Point",
        "coordinates": [
          32.9,
          24.116667
        ]
      },
      "type": "Feature",
      "properties": {
        "hierarchy": [
          "tgn:7540320",
          "tgn:7001242",
          "tgn:7016833",
          "tgn:7000122",
          "tgn:7029392"
        ],
        "placetype": [
          "aat:300008347"
        ],
        "name:en": "Naj' al 'Amrāb",
        "id": 7540320
      }
    },
    {
      "geometry": {
        "type": "Point",
        "coordinates": [
          31.169933,
          29.125521
        ]
      },
      "type": "Feature",
      "properties": {
        "hierarchy": [
          "tgn:7540321",
          "tgn:7001242",
          "tgn:7001311",
          "tgn:7016833",
          "tgn:7029392"
        ],
        "placetype": [
          "aat:300008347"
        ],
        "name:en": "Naj' al 'Alālimah",
        "id": 7540321
      }
    },
    {
      "geometry": {
        "type": "Point",
        "coordinates": [
          33.122188,
          23.297302
        ]
      },
      "type": "Feature",
      "properties": {
        "hierarchy": [
          "tgn:7540322",
          "tgn:7001242",
          "tgn:7001311",
          "tgn:7016833",
          "tgn:7029392"
        ],
        "placetype": [
          "aat:300008795"
        ],
        "name:en": "Najājīr, Jabal",
        "id": 7540322
      }
    },
    {
      "geometry": {
        "type": "Point",
        "coordinates": [
          32.016667,
          26.1
        ]
      },
      "type": "Feature",
      "properties": {
        "hierarchy": [
          "tgn:7540323",
          "tgn:7001242",
          "tgn:7016833",
          "tgn:7000123",
          "tgn:7029392"
        ],
        "placetype": [
          "aat:300008347"
        ],
        "name:en": "Naj' ad Dayr al Gharbī",
        "id": 7540323
      }
    },
    {
      "geometry": {
        "type": "Point",
        "coordinates": [
          32.791389,
          26.108056
        ]
      },
      "type": "Feature",
      "properties": {
        "hierarchy": [
          "tgn:7540324",
          "tgn:7001242",
          "tgn:7016833",
          "tgn:7000123",
          "tgn:7029392"
        ],
        "placetype": [
          "aat:300008347"
        ],
        "name:en": "Naj' ad Dawmah",
        "id": 7540324
      }
    },
    {
      "geometry": {
        "type": "Point",
        "coordinates": [
          32.733333,
          23.15
        ]
      },
      "type": "Feature",
      "properties": {
        "hierarchy": [
          "tgn:7540325",
          "tgn:7001242",
          "tgn:7016833",
          "tgn:7000122",
          "tgn:7029392"
        ],
        "placetype": [
          "aat:300185707"
        ],
        "name:en": "Naj' ad Dakkah al Qiblīyah, Khawr",
        "id": 7540325
      }
    },
    {
      "geometry": {
        "type": "Point",
        "coordinates": [
          32.733333,
          23.166667
        ]
      },
      "type": "Feature",
      "properties": {
        "hierarchy": [
          "tgn:7540326",
          "tgn:7001242",
          "tgn:7016833",
          "tgn:7000122",
          "tgn:7029392"
        ],
        "placetype": [
          "aat:300008347"
        ],
        "name:en": "Naj' ad Dakkah al Qiblī",
        "id": 7540326
      }
    },
    {
      "geometry": {
        "type": "Point",
        "coordinates": [
          32.733333,
          23.166667
        ]
      },
      "type": "Feature",
      "properties": {
        "hierarchy": [
          "tgn:7540327",
          "tgn:7001242",
          "tgn:7016833",
          "tgn:7000122",
          "tgn:7029392"
        ],
        "placetype": [
          "aat:300008347"
        ],
        "name:en": "Naj' ad Dakkah al Baḩrī",
        "id": 7540327
      }
    },
    {
      "geometry": {
        "type": "Point",
        "coordinates": [
          33.633333,
          25.066667
        ]
      },
      "type": "Feature",
      "properties": {
        "hierarchy": [
          "tgn:7540328",
          "tgn:7001242",
          "tgn:7001311",
          "tgn:7016833",
          "tgn:7029392"
        ],
        "placetype": [
          "aat:300132339"
        ],
        "name:en": "Naj' Abū al 'Ashā'ir",
        "id": 7540328
      }
    },
    {
      "geometry": {
        "type": "Point",
        "coordinates": [
          30.733333,
          27.733333
        ]
      },
      "type": "Feature",
      "properties": {
        "hierarchy": [
          "tgn:7540329",
          "tgn:7001242",
          "tgn:7016833",
          "tgn:1001088",
          "tgn:7029392"
        ],
        "placetype": [
          "aat:300008347"
        ],
        "name:en": "Naj' Abd Allāh Abū 'Ammār",
        "id": 7540329
      }
    }
  ]
}
