{
  "geometry": {
    "type": "Point",
    "coordinates": [
      3.2333,
      50.1667
    ]
  },
  "type": "Feature",
  "properties": {
    "name:en": "Cambrai",
    "name:nl": "Kamerijk",
    "hierarchy": [
      "tgn:7008456",
      "tgn:1000003",
      "tgn:7001097",
      "tgn:1000070",
      "tgn:7029392"
    ],
    "name:de": "Cambrai",
    "placetype": [
      "aat:300387277",
      "aat:300008347",
      "aat:300132180",
      "aat:300387218",
      "aat:300008389",
      "aat:300387330",
      "aat:300387302"
    ],
    "name:fr": "Cambrai",
    "id": 7008456
  }
}
