{
  "geometry": {
    "type": "Point",
    "coordinates": [
      41.85,
      47.45
    ]
  },
  "type": "Feature",
  "properties": {
    "hierarchy": [
      "tgn:1061380",
      "tgn:1000004",
      "tgn:1003405",
      "tgn:7018214",
      "tgn:7002435",
      "tgn:7029392"
    ],
    "placetype": [
      "aat:300008347"
    ],
    "id": 1061380,
    "name:xx": "Voskhod"
  }
}
