{
  "type": "FeatureCollection",
  "features": [
    {
      "geometry": {
        "type": "Point",
        "coordinates": [
          27.1,
          62.6667
        ]
      },
      "type": "Feature",
      "properties": {
        "hierarchy": [
          "tgn:1031571",
          "tgn:7594394",
          "tgn:1000003",
          "tgn:1000069",
          "tgn:7029392"
        ],
        "placetype": [
          "aat:300008347"
        ],
        "id": 1031571,
        "name:xx": "Suonenjoki"
      }
    },
    {
      "geometry": {
        "type": "Point",
        "coordinates": [
          25.6833,
          61.5
        ]
      },
      "type": "Feature",
      "properties": {
        "hierarchy": [
          "tgn:1031572",
          "tgn:7594388",
          "tgn:1000003",
          "tgn:1000069",
          "tgn:7029392"
        ],
        "placetype": [
          "aat:300008347"
        ],
        "id": 1031572,
        "name:xx": "Sysmä"
      }
    },
    {
      "geometry": {
        "type": "Point",
        "coordinates": [
          27.5667,
          60.9167
        ]
      },
      "type": "Feature",
      "properties": {
        "hierarchy": [
          "tgn:1031573",
          "tgn:7594379",
          "tgn:1000003",
          "tgn:1000069",
          "tgn:7029392"
        ],
        "placetype": [
          "aat:300008347"
        ],
        "id": 1031573,
        "name:xx": "Taavetti"
      }
    },
    {
      "geometry": {
        "type": "Point",
        "coordinates": [
          28.3333,
          65.5833
        ]
      },
      "type": "Feature",
      "properties": {
        "hierarchy": [
          "tgn:1031574",
          "tgn:1001475",
          "tgn:1000003",
          "tgn:1000069",
          "tgn:7029392"
        ],
        "placetype": [
          "aat:300008347"
        ],
        "id": 1031574,
        "name:xx": "Taivalkoski"
      }
    },
    {
      "geometry": {
        "type": "Point",
        "coordinates": [
          26,
          65.5
        ]
      },
      "type": "Feature",
      "properties": {
        "hierarchy": [
          "tgn:1031576",
          "tgn:1001475",
          "tgn:1000003",
          "tgn:1000069",
          "tgn:7029392"
        ],
        "placetype": [
          "aat:300008347"
        ],
        "id": 1031576,
        "name:xx": "Tannila"
      }
    },
    {
      "geometry": {
        "type": "Point",
        "coordinates": [
          23.5,
          63.5333
        ]
      },
      "type": "Feature",
      "properties": {
        "hierarchy": [
          "tgn:1031577",
          "tgn:7024077",
          "tgn:1000003",
          "tgn:1000069",
          "tgn:7029392"
        ],
        "placetype": [
          "aat:300008347"
        ],
        "id": 1031577,
        "name:xx": "Teerijärvi"
      }
    },
    {
      "geometry": {
        "type": "Point",
        "coordinates": [
          24.6167,
          60.8
        ]
      },
      "type": "Feature",
      "properties": {
        "hierarchy": [
          "tgn:1031578",
          "tgn:7024077",
          "tgn:1000003",
          "tgn:1000069",
          "tgn:7029392"
        ],
        "placetype": [
          "aat:300008347"
        ],
        "id": 1031578,
        "name:xx": "Tervakoski"
      }
    },
    {
      "geometry": {
        "type": "Point",
        "coordinates": [
          24.8333,
          66.0833
        ]
      },
      "type": "Feature",
      "properties": {
        "hierarchy": [
          "tgn:1031579",
          "tgn:1001385",
          "tgn:1000003",
          "tgn:1000069",
          "tgn:7029392"
        ],
        "placetype": [
          "aat:300008347"
        ],
        "id": 1031579,
        "name:xx": "Tervola"
      }
    }
  ]
}
