{
  "type": "FeatureCollection",
  "features": [
    {
      "geometry": {
        "type": "Point",
        "coordinates": [
          -84.15,
          37.9
        ]
      },
      "type": "Feature",
      "properties": {
        "hierarchy": [
          "tgn:2039480",
          "tgn:1000001",
          "tgn:2000781",
          "tgn:7012149",
          "tgn:7007255",
          "tgn:7029392"
        ],
        "placetype": [
          "aat:300008347",
          "aat:300387210"
        ],
        "id": 2039480,
        "name:xx": "Hunt"
      }
    },
    {
      "geometry": {
        "type": "Point",
        "coordinates": [
          -82.75,
          37.5
        ]
      },
      "type": "Feature",
      "properties": {
        "hierarchy": [
          "tgn:2039481",
          "tgn:1000001",
          "tgn:7012149",
          "tgn:2000789",
          "tgn:7007255",
          "tgn:7029392"
        ],
        "placetype": [
          "aat:300008347"
        ],
        "id": 2039481,
        "name:xx": "Hunter"
      }
    },
    {
      "geometry": {
        "type": "Point",
        "coordinates": [
          -85.5,
          37.85
        ]
      },
      "type": "Feature",
      "properties": {
        "hierarchy": [
          "tgn:2039482",
          "tgn:1000001",
          "tgn:7012149",
          "tgn:2000833",
          "tgn:7007255",
          "tgn:7029392"
        ],
        "placetype": [
          "aat:300008347",
          "aat:300387210"
        ],
        "id": 2039482,
        "name:xx": "Hunters"
      }
    },
    {
      "geometry": {
        "type": "Point",
        "coordinates": [
          -85.8167,
          38.1667
        ]
      },
      "type": "Feature",
      "properties": {
        "hierarchy": [
          "tgn:2039485",
          "tgn:1000001",
          "tgn:7012149",
          "tgn:1002516",
          "tgn:7007255",
          "tgn:7029392"
        ],
        "placetype": [
          "aat:300008347"
        ],
        "id": 2039485,
        "name:xx": "Hunters Trace"
      }
    },
    {
      "geometry": {
        "type": "Point",
        "coordinates": [
          -86.8667,
          37.15
        ]
      },
      "type": "Feature",
      "properties": {
        "hierarchy": [
          "tgn:2039488",
          "tgn:1000001",
          "tgn:2000775",
          "tgn:7012149",
          "tgn:7007255",
          "tgn:7029392"
        ],
        "placetype": [
          "aat:300008347"
        ],
        "id": 2039488,
        "name:xx": "Huntsville"
      }
    },
    {
      "geometry": {
        "type": "Point",
        "coordinates": [
          -84.0333,
          37.4
        ]
      },
      "type": "Feature",
      "properties": {
        "hierarchy": [
          "tgn:2039489",
          "tgn:1000001",
          "tgn:7012149",
          "tgn:2000802",
          "tgn:7007255",
          "tgn:7029392"
        ],
        "placetype": [
          "aat:300008347",
          "aat:300387210"
        ],
        "id": 2039489,
        "name:xx": "Hurley"
      }
    }
  ]
}
