{
  "geometry": {
    "type": "Point",
    "coordinates": [
      -92.2667,
      38.15
    ]
  },
  "type": "Feature",
  "properties": {
    "hierarchy": [
      "tgn:2060331",
      "tgn:1000001",
      "tgn:7012149",
      "tgn:1002671",
      "tgn:7007523",
      "tgn:7029392"
    ],
    "placetype": [
      "aat:300008347"
    ],
    "id": 2060331,
    "name:xx": "Saint Anthony"
  }
}
