{
  "geometry": {
    "type": "Point",
    "coordinates": [
      -80.0667,
      39.3333
    ]
  },
  "type": "Feature",
  "properties": {
    "hierarchy": [
      "tgn:2119666",
      "tgn:1000001",
      "tgn:7012149",
      "tgn:2002295",
      "tgn:7013961",
      "tgn:7029392"
    ],
    "placetype": [
      "aat:300008347"
    ],
    "id": 2119666,
    "name:xx": "Pruntytown"
  }
}
