{
  "geometry": {
    "type": "Point",
    "coordinates": [
      -106.6333,
      35.85
    ]
  },
  "type": "Feature",
  "properties": {
    "hierarchy": [
      "tgn:2640326",
      "tgn:1000001",
      "tgn:7012149",
      "tgn:2001451",
      "tgn:7007566",
      "tgn:7029392"
    ],
    "placetype": [
      "aat:300008761"
    ],
    "id": 2640326,
    "name:xx": "San Diego, Cañon de"
  }
}
