{
  "geometry": {
    "type": "Point",
    "coordinates": [
      -127.8667,
      51.8667
    ]
  },
  "type": "Feature",
  "properties": {
    "hierarchy": [
      "tgn:7016588",
      "tgn:7005735",
      "tgn:7005685",
      "tgn:1000001",
      "tgn:7029392"
    ],
    "placetype": [
      "aat:300008347"
    ],
    "id": 7016588,
    "name:xx": "Namu"
  }
}
