{
  "geometry": {
    "type": "Point",
    "coordinates": [
      -91.3333,
      32.65
    ]
  },
  "type": "Feature",
  "properties": {
    "hierarchy": [
      "tgn:2221028",
      "tgn:1000001",
      "tgn:2000871",
      "tgn:7012149",
      "tgn:7007256",
      "tgn:7029392"
    ],
    "placetype": [
      "aat:300008680"
    ],
    "id": 2221028,
    "name:xx": "Caraway Lake"
  }
}
