{
  "geometry": {
    "type": "Point",
    "coordinates": [
      88.256994,
      24.418933
    ]
  },
  "type": "Feature",
  "properties": {
    "hierarchy": [
      "tgn:7576209",
      "tgn:1000004",
      "tgn:7000198",
      "tgn:1001977",
      "tgn:7029392"
    ],
    "placetype": [
      "aat:300007783"
    ],
    "name:en": "Lālgola Ghāt",
    "id": 7576209
  }
}
