{
  "geometry": {
    "type": "Point",
    "coordinates": [
      -89.4167,
      36.2333
    ]
  },
  "type": "Feature",
  "properties": {
    "hierarchy": [
      "tgn:2271738",
      "tgn:1000001",
      "tgn:7012149",
      "tgn:2001902",
      "tgn:7007825",
      "tgn:7029392"
    ],
    "placetype": [
      "aat:300008347"
    ],
    "id": 2271738,
    "name:xx": "Cunningham"
  }
}
