{
  "geometry": {
    "type": "Point",
    "coordinates": [
      -120.5667,
      41.1833
    ]
  },
  "type": "Feature",
  "properties": {
    "hierarchy": [
      "tgn:2259471",
      "tgn:1000001",
      "tgn:7012149",
      "tgn:7007157",
      "tgn:2000186",
      "tgn:7029392"
    ],
    "placetype": [
      "aat:300008697"
    ],
    "id": 2259471,
    "name:xx": "Cottonwood Springs"
  }
}
