{
  "geometry": {
    "type": "Point",
    "coordinates": [
      -81.0667,
      38.2333
    ]
  },
  "type": "Feature",
  "properties": {
    "hierarchy": [
      "tgn:2487649",
      "tgn:1000001",
      "tgn:7012149",
      "tgn:2002284",
      "tgn:7013961",
      "tgn:7029392"
    ],
    "placetype": [
      "aat:300008706"
    ],
    "id": 2487649,
    "name:xx": "Left Fork Laurel Creek"
  }
}
