{
  "geometry": {
    "type": "Point",
    "coordinates": [
      -93.7667,
      39.9667
    ]
  },
  "type": "Feature",
  "properties": {
    "hierarchy": [
      "tgn:2530534",
      "tgn:1000001",
      "tgn:7012149",
      "tgn:2001193",
      "tgn:7007523",
      "tgn:7029392"
    ],
    "placetype": [
      "aat:300008706"
    ],
    "id": 2530534,
    "name:xx": "Muddy Creek"
  }
}
