{
  "geometry": {
    "type": "Point",
    "coordinates": [
      -77.5833,
      40.0333
    ]
  },
  "type": "Feature",
  "properties": {
    "hierarchy": [
      "tgn:2091959",
      "tgn:1000001",
      "tgn:7012149",
      "tgn:1002387",
      "tgn:7007710",
      "tgn:7029392"
    ],
    "placetype": [
      "aat:300008347"
    ],
    "id": 2091959,
    "name:xx": "Pinola"
  }
}
