{
  "geometry": {
    "type": "Point",
    "coordinates": [
      -124.1833,
      40.8167
    ]
  },
  "type": "Feature",
  "properties": {
    "hierarchy": [
      "tgn:2639876",
      "tgn:1000001",
      "tgn:7012149",
      "tgn:2000181",
      "tgn:7007157",
      "tgn:7029392"
    ],
    "placetype": [
      "aat:300008850"
    ],
    "id": 2639876,
    "name:xx": "Samoa Peninsula"
  }
}
