{
  "type": "FeatureCollection",
  "features": [
    {
      "geometry": {
        "type": "Point",
        "coordinates": [
          -114.7,
          30.733333
        ]
      },
      "type": "Feature",
      "properties": {
        "hierarchy": [
          "tgn:7348910",
          "tgn:1001835",
          "tgn:1000001",
          "tgn:7005560",
          "tgn:7029392"
        ],
        "placetype": [
          "aat:300008699"
        ],
        "id": 7348910,
        "name:xx": "Agua Caliente, Arroyo"
      }
    },
    {
      "geometry": {
        "type": "Point",
        "coordinates": [
          -106.933333,
          26.55
        ]
      },
      "type": "Feature",
      "properties": {
        "hierarchy": [
          "tgn:7348911",
          "tgn:7005581",
          "tgn:1000001",
          "tgn:7005560",
          "tgn:7029392"
        ],
        "placetype": [
          "aat:300008699"
        ],
        "id": 7348911,
        "name:xx": "Agua Caliente, Arroyo"
      }
    },
    {
      "geometry": {
        "type": "Point",
        "coordinates": [
          -107.4,
          26.216667
        ]
      },
      "type": "Feature",
      "properties": {
        "hierarchy": [
          "tgn:7348912",
          "tgn:7005581",
          "tgn:1000001",
          "tgn:7005560",
          "tgn:7029392"
        ],
        "placetype": [
          "aat:300008699"
        ],
        "id": 7348912,
        "name:xx": "Agua Caliente, Arroyo"
      }
    },
    {
      "geometry": {
        "type": "Point",
        "coordinates": [
          -92.983333,
          15.433333
        ]
      },
      "type": "Feature",
      "properties": {
        "hierarchy": [
          "tgn:7348913",
          "tgn:7005580",
          "tgn:1000001",
          "tgn:7005560",
          "tgn:7029392"
        ],
        "placetype": [
          "aat:300008699"
        ],
        "id": 7348913,
        "name:xx": "Agua Caliente, Arroyo"
      }
    },
    {
      "geometry": {
        "type": "Point",
        "coordinates": [
          -103.583333,
          20.533333
        ]
      },
      "type": "Feature",
      "properties": {
        "hierarchy": [
          "tgn:7348914",
          "tgn:7005586",
          "tgn:1000001",
          "tgn:7005560",
          "tgn:7029392"
        ],
        "placetype": [
          "aat:300266554",
          "aat:300008699"
        ],
        "id": 7348914,
        "name:xx": "Agua Caliente"
      }
    },
    {
      "geometry": {
        "type": "Point",
        "coordinates": [
          -103.833333,
          20.15
        ]
      },
      "type": "Feature",
      "properties": {
        "hierarchy": [
          "tgn:7348915",
          "tgn:7005586",
          "tgn:1000001",
          "tgn:7005560",
          "tgn:7029392"
        ],
        "placetype": [
          "aat:300008699"
        ],
        "id": 7348915,
        "name:xx": "Agua Caliente"
      }
    },
    {
      "geometry": {
        "type": "Point",
        "coordinates": [
          -92.566667,
          15.416667
        ]
      },
      "type": "Feature",
      "properties": {
        "hierarchy": [
          "tgn:7348916",
          "tgn:7005580",
          "tgn:1000001",
          "tgn:7005560",
          "tgn:7029392"
        ],
        "placetype": [
          "aat:300008699"
        ],
        "id": 7348916,
        "name:xx": "Agua Caliente"
      }
    },
    {
      "geometry": {
        "type": "Point",
        "coordinates": [
          -92.166667,
          15.383333
        ]
      },
      "type": "Feature",
      "properties": {
        "hierarchy": [
          "tgn:7348917",
          "tgn:7005580",
          "tgn:1000001",
          "tgn:7005560",
          "tgn:7029392"
        ],
        "placetype": [
          "aat:300008699"
        ],
        "id": 7348917,
        "name:xx": "Agua Caliente"
      }
    },
    {
      "geometry": {
        "type": "Point",
        "coordinates": [
          -105.966667,
          26.883333
        ]
      },
      "type": "Feature",
      "properties": {
        "hierarchy": [
          "tgn:7348918",
          "tgn:7005581",
          "tgn:1000001",
          "tgn:7005560",
          "tgn:7029392"
        ],
        "placetype": [
          "aat:300007783"
        ],
        "id": 7348918,
        "name:xx": "Agua Caliente"
      }
    },
    {
      "geometry": {
        "type": "Point",
        "coordinates": [
          -103.816667,
          20.9
        ]
      },
      "type": "Feature",
      "properties": {
        "hierarchy": [
          "tgn:7348919",
          "tgn:7005586",
          "tgn:1000001",
          "tgn:7005560",
          "tgn:7029392"
        ],
        "placetype": [
          "aat:300000241"
        ],
        "id": 7348919,
        "name:xx": "Agua Caliente"
      }
    }
  ]
}
