{
  "type": "FeatureCollection",
  "features": [
    {
      "geometry": {
        "type": "Point",
        "coordinates": [
          -105.783333,
          27.533333
        ]
      },
      "type": "Feature",
      "properties": {
        "hierarchy": [
          "tgn:7390290",
          "tgn:7005581",
          "tgn:1000001",
          "tgn:7005560",
          "tgn:7029392"
        ],
        "placetype": [
          "aat:300008347"
        ],
        "id": 7390290,
        "name:xx": "Rinconada"
      }
    },
    {
      "geometry": {
        "type": "Point",
        "coordinates": [
          -107.266667,
          25.916667
        ]
      },
      "type": "Feature",
      "properties": {
        "hierarchy": [
          "tgn:7390291",
          "tgn:7005581",
          "tgn:1000001",
          "tgn:7005560",
          "tgn:7029392"
        ],
        "placetype": [
          "aat:300008347"
        ],
        "id": 7390291,
        "name:xx": "Rinconada"
      }
    },
    {
      "geometry": {
        "type": "Point",
        "coordinates": [
          -103.333333,
          25.733333
        ]
      },
      "type": "Feature",
      "properties": {
        "hierarchy": [
          "tgn:7390292",
          "tgn:7005583",
          "tgn:1000001",
          "tgn:7005560",
          "tgn:7029392"
        ],
        "placetype": [
          "aat:300008347"
        ],
        "id": 7390292,
        "name:xx": "Rinconada"
      }
    },
    {
      "geometry": {
        "type": "Point",
        "coordinates": [
          -100.716667,
          25.7
        ]
      },
      "type": "Feature",
      "properties": {
        "hierarchy": [
          "tgn:7390293",
          "tgn:1000001",
          "tgn:7005589",
          "tgn:7005560",
          "tgn:7029392"
        ],
        "placetype": [
          "aat:300008347"
        ],
        "id": 7390293,
        "name:xx": "Rinconada"
      }
    },
    {
      "geometry": {
        "type": "Point",
        "coordinates": [
          -100.65,
          23.75
        ]
      },
      "type": "Feature",
      "properties": {
        "hierarchy": [
          "tgn:7390294",
          "tgn:1000001",
          "tgn:7005594",
          "tgn:7005560",
          "tgn:7029392"
        ],
        "placetype": [
          "aat:300008347"
        ],
        "id": 7390294,
        "name:xx": "Rinconada"
      }
    },
    {
      "geometry": {
        "type": "Point",
        "coordinates": [
          -100.25,
          22.45
        ]
      },
      "type": "Feature",
      "properties": {
        "hierarchy": [
          "tgn:7390295",
          "tgn:1000001",
          "tgn:7005594",
          "tgn:7005560",
          "tgn:7029392"
        ],
        "placetype": [
          "aat:300008347"
        ],
        "id": 7390295,
        "name:xx": "Rinconada"
      }
    },
    {
      "geometry": {
        "type": "Point",
        "coordinates": [
          -100.95,
          22.266667
        ]
      },
      "type": "Feature",
      "properties": {
        "hierarchy": [
          "tgn:7390296",
          "tgn:1000001",
          "tgn:7005594",
          "tgn:7005560",
          "tgn:7029392"
        ],
        "placetype": [
          "aat:300008347"
        ],
        "id": 7390296,
        "name:xx": "Rinconada"
      }
    },
    {
      "geometry": {
        "type": "Point",
        "coordinates": [
          -99.283333,
          20.516667
        ]
      },
      "type": "Feature",
      "properties": {
        "hierarchy": [
          "tgn:7390297",
          "tgn:7005587",
          "tgn:1000001",
          "tgn:7005560",
          "tgn:7029392"
        ],
        "placetype": [
          "aat:300008347"
        ],
        "id": 7390297,
        "name:xx": "Rinconada"
      }
    },
    {
      "geometry": {
        "type": "Point",
        "coordinates": [
          -96.516667,
          19.35
        ]
      },
      "type": "Feature",
      "properties": {
        "hierarchy": [
          "tgn:7390298",
          "tgn:1000001",
          "tgn:7005599",
          "tgn:7005560",
          "tgn:7029392"
        ],
        "placetype": [
          "aat:300008347"
        ],
        "id": 7390298,
        "name:xx": "Rinconada"
      }
    },
    {
      "geometry": {
        "type": "Point",
        "coordinates": [
          -101.883333,
          27.1
        ]
      },
      "type": "Feature",
      "properties": {
        "hierarchy": [
          "tgn:7390299",
          "tgn:1001853",
          "tgn:1000001",
          "tgn:7005560",
          "tgn:7029392"
        ],
        "placetype": [
          "aat:300008795"
        ],
        "id": 7390299,
        "name:xx": "Rincon, Picacho del"
      }
    }
  ]
}
