{
  "geometry": {
    "type": "Point",
    "coordinates": [
      -76.3667,
      41.2833
    ]
  },
  "type": "Feature",
  "properties": {
    "hierarchy": [
      "tgn:2087078",
      "tgn:1000001",
      "tgn:1002294",
      "tgn:7012149",
      "tgn:7007710",
      "tgn:7029392"
    ],
    "placetype": [
      "aat:300008347"
    ],
    "id": 2087078,
    "name:xx": "Central"
  }
}
