{
  "type": "FeatureCollection",
  "features": [
    {
      "geometry": {
        "type": "Point",
        "coordinates": [
          9.493889,
          49.218056
        ]
      },
      "type": "Feature",
      "properties": {
        "hierarchy": [
          "tgn:7207510",
          "tgn:7003692",
          "tgn:1000003",
          "tgn:7000084",
          "tgn:7029392"
        ],
        "placetype": [
          "aat:300008347"
        ],
        "id": 7207510,
        "name:xx": "Büttelbronn"
      }
    },
    {
      "geometry": {
        "type": "Point",
        "coordinates": [
          10.9,
          48.9
        ]
      },
      "type": "Feature",
      "properties": {
        "hierarchy": [
          "tgn:7207511",
          "tgn:7003669",
          "tgn:1000003",
          "tgn:7000084",
          "tgn:7029392"
        ],
        "placetype": [
          "aat:300008347"
        ],
        "id": 7207511,
        "name:xx": "Büttelbronn"
      }
    },
    {
      "geometry": {
        "type": "Point",
        "coordinates": [
          8.523333,
          49.903333
        ]
      },
      "type": "Feature",
      "properties": {
        "hierarchy": [
          "tgn:7207512",
          "tgn:1000003",
          "tgn:7003678",
          "tgn:7000084",
          "tgn:7029392"
        ],
        "placetype": [
          "aat:300008347"
        ],
        "id": 7207512,
        "name:xx": "Büttelborn"
      }
    },
    {
      "geometry": {
        "type": "Point",
        "coordinates": [
          9.016667,
          54.4
        ]
      },
      "type": "Feature",
      "properties": {
        "hierarchy": [
          "tgn:7207513",
          "tgn:1000003",
          "tgn:7003688",
          "tgn:7000084",
          "tgn:7029392"
        ],
        "placetype": [
          "aat:300008347"
        ],
        "id": 7207513,
        "name:xx": "Büttel"
      }
    },
    {
      "geometry": {
        "type": "Point",
        "coordinates": [
          8.7,
          54.333333
        ]
      },
      "type": "Feature",
      "properties": {
        "hierarchy": [
          "tgn:7207514",
          "tgn:1000003",
          "tgn:7003688",
          "tgn:7000084",
          "tgn:7029392"
        ],
        "placetype": [
          "aat:300008347"
        ],
        "id": 7207514,
        "name:xx": "Büttel"
      }
    },
    {
      "geometry": {
        "type": "Point",
        "coordinates": [
          9.233333,
          53.9
        ]
      },
      "type": "Feature",
      "properties": {
        "hierarchy": [
          "tgn:7207515",
          "tgn:1000003",
          "tgn:7003688",
          "tgn:7000084",
          "tgn:7029392"
        ],
        "placetype": [
          "aat:300008347"
        ],
        "id": 7207515,
        "name:xx": "Büttel"
      }
    },
    {
      "geometry": {
        "type": "Point",
        "coordinates": [
          8.55,
          53.433333
        ]
      },
      "type": "Feature",
      "properties": {
        "hierarchy": [
          "tgn:7207516",
          "tgn:1000003",
          "tgn:7003676",
          "tgn:7000084",
          "tgn:7029392"
        ],
        "placetype": [
          "aat:300008347"
        ],
        "id": 7207516,
        "name:xx": "Büttel"
      }
    },
    {
      "geometry": {
        "type": "Point",
        "coordinates": [
          8.25,
          53.216667
        ]
      },
      "type": "Feature",
      "properties": {
        "hierarchy": [
          "tgn:7207517",
          "tgn:1000003",
          "tgn:7003676",
          "tgn:7000084",
          "tgn:7029392"
        ],
        "placetype": [
          "aat:300008347"
        ],
        "id": 7207517,
        "name:xx": "Buttel"
      }
    },
    {
      "geometry": {
        "type": "Point",
        "coordinates": [
          8.416667,
          53.166667
        ]
      },
      "type": "Feature",
      "properties": {
        "hierarchy": [
          "tgn:7207518",
          "tgn:1000003",
          "tgn:7003676",
          "tgn:7000084",
          "tgn:7029392"
        ],
        "placetype": [
          "aat:300008347"
        ],
        "id": 7207518,
        "name:xx": "Buttel"
      }
    },
    {
      "geometry": {
        "type": "Point",
        "coordinates": [
          8.75,
          53.283333
        ]
      },
      "type": "Feature",
      "properties": {
        "hierarchy": [
          "tgn:7207519",
          "tgn:1000003",
          "tgn:7003676",
          "tgn:7000084",
          "tgn:7029392"
        ],
        "placetype": [
          "aat:300000206"
        ],
        "id": 7207519,
        "name:xx": "Büttel"
      }
    }
  ]
}
