{
  "geometry": {
    "type": "Point",
    "coordinates": [
      -114.7667,
      32.8333
    ]
  },
  "type": "Feature",
  "properties": {
    "hierarchy": [
      "tgn:2221444",
      "tgn:1000001",
      "tgn:7012149",
      "tgn:2000182",
      "tgn:7007157",
      "tgn:7029392"
    ],
    "placetype": [
      "aat:300000390"
    ],
    "id": 2221444,
    "name:xx": "Cargo Mine"
  }
}
