{
  "type": "FeatureCollection",
  "features": [
    {
      "geometry": {
        "type": "Point",
        "coordinates": [
          -111.1,
          30.416667
        ]
      },
      "type": "Feature",
      "properties": {
        "hierarchy": [
          "tgn:7440750",
          "tgn:1000001",
          "tgn:1001960",
          "tgn:7005560",
          "tgn:7029392"
        ],
        "placetype": [
          "aat:300000241"
        ],
        "id": 7440750,
        "name:xx": "Rancho Santa Anita"
      }
    },
    {
      "geometry": {
        "type": "Point",
        "coordinates": [
          -106.55,
          30.216667
        ]
      },
      "type": "Feature",
      "properties": {
        "hierarchy": [
          "tgn:7440751",
          "tgn:7005581",
          "tgn:1000001",
          "tgn:7005560",
          "tgn:7029392"
        ],
        "placetype": [
          "aat:300000241"
        ],
        "id": 7440751,
        "name:xx": "Rancho Santa Anita"
      }
    },
    {
      "geometry": {
        "type": "Point",
        "coordinates": [
          -111.283333,
          30
        ]
      },
      "type": "Feature",
      "properties": {
        "hierarchy": [
          "tgn:7440752",
          "tgn:1000001",
          "tgn:1001960",
          "tgn:7005560",
          "tgn:7029392"
        ],
        "placetype": [
          "aat:300000241"
        ],
        "id": 7440752,
        "name:xx": "Rancho Santa Anita"
      }
    },
    {
      "geometry": {
        "type": "Point",
        "coordinates": [
          -111.816667,
          29.166667
        ]
      },
      "type": "Feature",
      "properties": {
        "hierarchy": [
          "tgn:7440753",
          "tgn:1000001",
          "tgn:1001960",
          "tgn:7005560",
          "tgn:7029392"
        ],
        "placetype": [
          "aat:300000241"
        ],
        "id": 7440753,
        "name:xx": "Rancho Santa Anita"
      }
    },
    {
      "geometry": {
        "type": "Point",
        "coordinates": [
          -111.533333,
          28.766667
        ]
      },
      "type": "Feature",
      "properties": {
        "hierarchy": [
          "tgn:7440754",
          "tgn:1000001",
          "tgn:1001960",
          "tgn:7005560",
          "tgn:7029392"
        ],
        "placetype": [
          "aat:300000241"
        ],
        "id": 7440754,
        "name:xx": "Rancho Santa Anita"
      }
    },
    {
      "geometry": {
        "type": "Point",
        "coordinates": [
          -103.5,
          28.316667
        ]
      },
      "type": "Feature",
      "properties": {
        "hierarchy": [
          "tgn:7440755",
          "tgn:1001853",
          "tgn:1000001",
          "tgn:7005560",
          "tgn:7029392"
        ],
        "placetype": [
          "aat:300000241"
        ],
        "id": 7440755,
        "name:xx": "Rancho Santa Anita"
      }
    },
    {
      "geometry": {
        "type": "Point",
        "coordinates": [
          -107.666667,
          26.75
        ]
      },
      "type": "Feature",
      "properties": {
        "hierarchy": [
          "tgn:7440756",
          "tgn:7005581",
          "tgn:1000001",
          "tgn:7005560",
          "tgn:7029392"
        ],
        "placetype": [
          "aat:300000241"
        ],
        "id": 7440756,
        "name:xx": "Rancho Santa Anita"
      }
    },
    {
      "geometry": {
        "type": "Point",
        "coordinates": [
          -101.016667,
          25
        ]
      },
      "type": "Feature",
      "properties": {
        "hierarchy": [
          "tgn:7440757",
          "tgn:1001853",
          "tgn:1000001",
          "tgn:7005560",
          "tgn:7029392"
        ],
        "placetype": [
          "aat:300000241"
        ],
        "id": 7440757,
        "name:xx": "Rancho Santa Anita"
      }
    },
    {
      "geometry": {
        "type": "Point",
        "coordinates": [
          -100.75,
          24.116667
        ]
      },
      "type": "Feature",
      "properties": {
        "hierarchy": [
          "tgn:7440758",
          "tgn:1000001",
          "tgn:7005594",
          "tgn:7005560",
          "tgn:7029392"
        ],
        "placetype": [
          "aat:300000241"
        ],
        "id": 7440758,
        "name:xx": "Rancho Santa Anita"
      }
    },
    {
      "geometry": {
        "type": "Point",
        "coordinates": [
          -92.466667,
          18.65
        ]
      },
      "type": "Feature",
      "properties": {
        "hierarchy": [
          "tgn:7440759",
          "tgn:7005578",
          "tgn:1000001",
          "tgn:7005560",
          "tgn:7029392"
        ],
        "placetype": [
          "aat:300008347"
        ],
        "id": 7440759,
        "name:xx": "San Pedro"
      }
    }
  ]
}
