{
  "type": "FeatureCollection",
  "features": [
    {
      "geometry": {
        "type": "Point",
        "coordinates": [
          -86.8,
          20.533333
        ]
      },
      "type": "Feature",
      "properties": {
        "hierarchy": [
          "tgn:7372760",
          "tgn:1000001",
          "tgn:1001937",
          "tgn:7005560",
          "tgn:7029392"
        ],
        "placetype": [
          "aat:300008679"
        ],
        "id": 7372760,
        "name:xx": "La Laguna"
      }
    },
    {
      "geometry": {
        "type": "Point",
        "coordinates": [
          -110.866667,
          27.933333
        ]
      },
      "type": "Feature",
      "properties": {
        "hierarchy": [
          "tgn:7372761",
          "tgn:1000001",
          "tgn:1001960",
          "tgn:7005560",
          "tgn:7029392"
        ],
        "placetype": [
          "aat:300132316"
        ],
        "id": 7372761,
        "name:xx": "Empalme, La Luguna de"
      }
    },
    {
      "geometry": {
        "type": "Point",
        "coordinates": [
          -105.433333,
          30.333333
        ]
      },
      "type": "Feature",
      "properties": {
        "hierarchy": [
          "tgn:7372762",
          "tgn:7005581",
          "tgn:1000001",
          "tgn:7005560",
          "tgn:7029392"
        ],
        "placetype": [
          "aat:300266640"
        ],
        "id": 7372762,
        "name:xx": "La Lagrima, Sierra"
      }
    },
    {
      "geometry": {
        "type": "Point",
        "coordinates": [
          -105.283333,
          29.983333
        ]
      },
      "type": "Feature",
      "properties": {
        "hierarchy": [
          "tgn:7372763",
          "tgn:7005581",
          "tgn:1000001",
          "tgn:7005560",
          "tgn:7029392"
        ],
        "placetype": [
          "aat:300000241"
        ],
        "id": 7372763,
        "name:xx": "Rancho La Lágrima"
      }
    },
    {
      "geometry": {
        "type": "Point",
        "coordinates": [
          -104.716667,
          27.95
        ]
      },
      "type": "Feature",
      "properties": {
        "hierarchy": [
          "tgn:7372764",
          "tgn:7005581",
          "tgn:1000001",
          "tgn:7005560",
          "tgn:7029392"
        ],
        "placetype": [
          "aat:300000241"
        ],
        "id": 7372764,
        "name:xx": "Rancho La Lágrima"
      }
    },
    {
      "geometry": {
        "type": "Point",
        "coordinates": [
          -115.566667,
          30.116667
        ]
      },
      "type": "Feature",
      "properties": {
        "hierarchy": [
          "tgn:7372765",
          "tgn:1001835",
          "tgn:1000001",
          "tgn:7005560",
          "tgn:7029392"
        ],
        "placetype": [
          "aat:300008795"
        ],
        "id": 7372765,
        "name:xx": "La Fe, Cerro"
      }
    },
    {
      "geometry": {
        "type": "Point",
        "coordinates": [
          -102.5,
          27.816667
        ]
      },
      "type": "Feature",
      "properties": {
        "hierarchy": [
          "tgn:7372766",
          "tgn:1001853",
          "tgn:1000001",
          "tgn:7005560",
          "tgn:7029392"
        ],
        "placetype": [
          "aat:300008347"
        ],
        "id": 7372766,
        "name:xx": "La Fe"
      }
    },
    {
      "geometry": {
        "type": "Point",
        "coordinates": [
          -103.95,
          26.8
        ]
      },
      "type": "Feature",
      "properties": {
        "hierarchy": [
          "tgn:7372767",
          "tgn:7005581",
          "tgn:1000001",
          "tgn:7005560",
          "tgn:7029392"
        ],
        "placetype": [
          "aat:300008347"
        ],
        "id": 7372767,
        "name:xx": "La Fe"
      }
    },
    {
      "geometry": {
        "type": "Point",
        "coordinates": [
          -103.133333,
          25.366667
        ]
      },
      "type": "Feature",
      "properties": {
        "hierarchy": [
          "tgn:7372768",
          "tgn:1001853",
          "tgn:1000001",
          "tgn:7005560",
          "tgn:7029392"
        ],
        "placetype": [
          "aat:300008347"
        ],
        "id": 7372768,
        "name:xx": "La Fe"
      }
    },
    {
      "geometry": {
        "type": "Point",
        "coordinates": [
          -103.880278,
          24.953611
        ]
      },
      "type": "Feature",
      "properties": {
        "hierarchy": [
          "tgn:7372769",
          "tgn:7005583",
          "tgn:1000001",
          "tgn:7005560",
          "tgn:7029392"
        ],
        "placetype": [
          "aat:300008347"
        ],
        "id": 7372769,
        "name:xx": "La Fé"
      }
    }
  ]
}
