{
  "type": "FeatureCollection",
  "features": [
    {
      "geometry": {
        "type": "Point",
        "coordinates": [
          -98.3667,
          26.6833
        ]
      },
      "type": "Feature",
      "properties": {
        "hierarchy": [
          "tgn:2105544",
          "tgn:1000001",
          "tgn:7012149",
          "tgn:2002075",
          "tgn:7007826",
          "tgn:7029392"
        ],
        "placetype": [
          "aat:300008347"
        ],
        "id": 2105544,
        "name:xx": "La Reforma"
      }
    },
    {
      "geometry": {
        "type": "Point",
        "coordinates": [
          -102.9,
          34.3167
        ]
      },
      "type": "Feature",
      "properties": {
        "hierarchy": [
          "tgn:2105545",
          "tgn:1000001",
          "tgn:7012149",
          "tgn:2002054",
          "tgn:7007826",
          "tgn:7029392"
        ],
        "placetype": [
          "aat:300008347"
        ],
        "id": 2105545,
        "name:xx": "Lariat"
      }
    },
    {
      "geometry": {
        "type": "Point",
        "coordinates": [
          -96.6667,
          28.7833
        ]
      },
      "type": "Feature",
      "properties": {
        "hierarchy": [
          "tgn:2105548",
          "tgn:1000001",
          "tgn:7012149",
          "tgn:1002510",
          "tgn:7007826",
          "tgn:7029392"
        ],
        "placetype": [
          "aat:300008347"
        ],
        "id": 2105548,
        "name:xx": "La Salle"
      }
    },
    {
      "geometry": {
        "type": "Point",
        "coordinates": [
          -97.9,
          26.45
        ]
      },
      "type": "Feature",
      "properties": {
        "hierarchy": [
          "tgn:2105549",
          "tgn:1000001",
          "tgn:7012149",
          "tgn:2002094",
          "tgn:7007826",
          "tgn:7029392"
        ],
        "placetype": [
          "aat:300008347"
        ],
        "id": 2105549,
        "name:xx": "Lasara"
      }
    }
  ]
}
