{
  "type": "FeatureCollection",
  "features": [
    {
      "geometry": {
        "type": "Point",
        "coordinates": [
          40.25,
          1
        ]
      },
      "type": "Feature",
      "properties": {
        "hierarchy": [
          "tgn:1001721",
          "tgn:7001242",
          "tgn:1000169",
          "tgn:7029392"
        ],
        "placetype": [
          "aat:300387179",
          "aat:300387064",
          "aat:300000774"
        ],
        "id": 1001721,
        "name:xx": "North Eastern"
      }
    },
    {
      "geometry": {
        "type": "Point",
        "coordinates": [
          -1.0167,
          9.5167
        ]
      },
      "type": "Feature",
      "properties": {
        "hierarchy": [
          "tgn:1001722",
          "tgn:7001242",
          "tgn:1000166",
          "tgn:7029392"
        ],
        "placetype": [
          "aat:300387064",
          "aat:300236112"
        ],
        "id": 1001722,
        "name:xx": "Northern"
      }
    },
    {
      "geometry": {
        "type": "Point",
        "coordinates": [
          49,
          8.5
        ]
      },
      "type": "Feature",
      "properties": {
        "hierarchy": [
          "tgn:1001723",
          "tgn:7001242",
          "tgn:1000192",
          "tgn:7029392"
        ],
        "placetype": [
          "aat:300387064",
          "aat:300236112"
        ],
        "id": 1001723,
        "name:xx": "Nugaal"
      }
    },
    {
      "geometry": {
        "type": "Point",
        "coordinates": [
          9.333333,
          40.166667
        ]
      },
      "type": "Feature",
      "properties": {
        "hierarchy": [
          "tgn:1001724",
          "tgn:1000003",
          "tgn:7003121",
          "tgn:1000080",
          "tgn:7029392"
        ],
        "placetype": [
          "aat:300387145",
          "aat:300000774"
        ],
        "id": 1001724,
        "name:xx": "Nuoro"
      }
    },
    {
      "geometry": {
        "type": "Point",
        "coordinates": [
          11,
          -3
        ]
      },
      "type": "Feature",
      "properties": {
        "hierarchy": [
          "tgn:1001725",
          "tgn:7001242",
          "tgn:1000164",
          "tgn:7029392"
        ],
        "placetype": [
          "aat:300387064",
          "aat:300000774"
        ],
        "id": 1001725,
        "name:xx": "Nyanga"
      }
    },
    {
      "geometry": {
        "type": "Point",
        "coordinates": [
          34.5,
          -0.5
        ]
      },
      "type": "Feature",
      "properties": {
        "hierarchy": [
          "tgn:1001726",
          "tgn:7001242",
          "tgn:1000169",
          "tgn:7029392"
        ],
        "placetype": [
          "aat:300387179",
          "aat:300387064",
          "aat:300000774"
        ],
        "id": 1001726,
        "name:xx": "Nyanza"
      }
    },
    {
      "geometry": {
        "type": "Point",
        "coordinates": [
          13,
          0.5
        ]
      },
      "type": "Feature",
      "properties": {
        "hierarchy": [
          "tgn:1001727",
          "tgn:7001242",
          "tgn:1000164",
          "tgn:7029392"
        ],
        "placetype": [
          "aat:300387064",
          "aat:300000774"
        ],
        "id": 1001727,
        "name:xx": "Ogooué-Ivindo"
      }
    },
    {
      "geometry": {
        "type": "Point",
        "coordinates": [
          12.5,
          -1
        ]
      },
      "type": "Feature",
      "properties": {
        "hierarchy": [
          "tgn:1001728",
          "tgn:7001242",
          "tgn:1000164",
          "tgn:7029392"
        ],
        "placetype": [
          "aat:300387064",
          "aat:300000774"
        ],
        "id": 1001728,
        "name:xx": "Ogooué-Lolo, Province de l'"
      }
    },
    {
      "geometry": {
        "type": "Point",
        "coordinates": [
          9.5,
          -2
        ]
      },
      "type": "Feature",
      "properties": {
        "hierarchy": [
          "tgn:1001729",
          "tgn:7001242",
          "tgn:1000164",
          "tgn:7029392"
        ],
        "placetype": [
          "aat:300387064",
          "aat:300000774"
        ],
        "id": 1001729,
        "name:xx": "Ogooué-Maritime"
      }
    }
  ]
}
