{
  "geometry": {
    "type": "Point",
    "coordinates": [
      -119.35,
      44.35
    ]
  },
  "type": "Feature",
  "properties": {
    "hierarchy": [
      "tgn:2462356",
      "tgn:1000001",
      "tgn:7012149",
      "tgn:2001708",
      "tgn:7007708",
      "tgn:7029392"
    ],
    "placetype": [
      "aat:300008697"
    ],
    "id": 2462356,
    "name:xx": "Little Weasel Spring"
  }
}
