{
  "geometry": {
    "type": "Point",
    "coordinates": [
      -86.4167,
      39.3667
    ]
  },
  "type": "Feature",
  "properties": {
    "hierarchy": [
      "tgn:2218105",
      "tgn:1000001",
      "tgn:7012149",
      "tgn:1002694",
      "tgn:7007252",
      "tgn:7029392"
    ],
    "placetype": [
      "aat:300008761"
    ],
    "id": 2218105,
    "name:xx": "Canada Hollow"
  }
}
