{
  "geometry": {
    "type": "Point",
    "coordinates": [
      -78.0667,
      34.3667
    ]
  },
  "type": "Feature",
  "properties": {
    "hierarchy": [
      "tgn:2268943",
      "tgn:1000001",
      "tgn:7012149",
      "tgn:2001527",
      "tgn:7007709",
      "tgn:7029392"
    ],
    "placetype": [
      "aat:300008791"
    ],
    "id": 2268943,
    "name:xx": "Cross Way Island"
  }
}
