{
  "geometry": {
    "type": "Point",
    "coordinates": [
      -176.4167,
      51.7833
    ]
  },
  "type": "Feature",
  "properties": {
    "hierarchy": [
      "tgn:2217871",
      "tgn:7030516",
      "tgn:7006450",
      "tgn:1000001",
      "tgn:7012149",
      "tgn:7029392"
    ],
    "placetype": [
      "aat:300008850"
    ],
    "id": 2217871,
    "name:xx": "Campers Point"
  }
}
