{
  "geometry": {
    "type": "Point",
    "coordinates": [
      -74.75,
      44.2667
    ]
  },
  "type": "Feature",
  "properties": {
    "hierarchy": [
      "tgn:2640006",
      "tgn:1000001",
      "tgn:7012149",
      "tgn:7016021",
      "tgn:7007568",
      "tgn:7029392"
    ],
    "placetype": [
      "aat:300008699"
    ],
    "id": 2640006,
    "name:xx": "Sampson Pond Outlet"
  }
}
