{
  "geometry": {
    "type": "Point",
    "coordinates": [
      -116.0167,
      47.8333
    ]
  },
  "type": "Feature",
  "properties": {
    "hierarchy": [
      "tgn:2384800",
      "tgn:1000001",
      "tgn:7012149",
      "tgn:2000491",
      "tgn:7007250",
      "tgn:7029392"
    ],
    "placetype": [
      "aat:300008761"
    ],
    "id": 2384800,
    "name:xx": "Hells Gulch"
  }
}
