{
  "geometry": {
    "type": "Point",
    "coordinates": [
      113.3333,
      25.55
    ]
  },
  "type": "Feature",
  "properties": {
    "hierarchy": [
      "tgn:1072581",
      "tgn:1000004",
      "tgn:7002079",
      "tgn:1000111",
      "tgn:7029392"
    ],
    "placetype": [
      "aat:300008347"
    ],
    "id": 1072581,
    "name:xx": "Wenmingsi"
  }
}
