{
  "geometry": {
    "type": "Point",
    "coordinates": [
      -82.2167,
      26.6167
    ]
  },
  "type": "Feature",
  "properties": {
    "hierarchy": [
      "tgn:2574232",
      "tgn:1000001",
      "tgn:7012149",
      "tgn:1002582",
      "tgn:7007240",
      "tgn:7029392"
    ],
    "placetype": [
      "aat:300008850"
    ],
    "id": 2574232,
    "name:xx": "Pejuan Point"
  }
}
