{
  "geometry": {
    "type": "Point",
    "coordinates": [
      86.03744,
      23.986851
    ]
  },
  "type": "Feature",
  "properties": {
    "hierarchy": [
      "tgn:1076551",
      "tgn:1000004",
      "tgn:7000198",
      "tgn:7031783",
      "tgn:7029392"
    ],
    "placetype": [
      "aat:300007783"
    ],
    "name:en": "Parasnāth",
    "id": 1076551
  }
}
