{
  "geometry": {
    "type": "Point",
    "coordinates": [
      -66.9667,
      47.9833
    ]
  },
  "type": "Feature",
  "properties": {
    "hierarchy": [
      "tgn:1015504",
      "tgn:7005685",
      "tgn:1000001",
      "tgn:7005804",
      "tgn:7029392"
    ],
    "placetype": [
      "aat:300008347"
    ],
    "id": 1015504,
    "name:xx": "Matapédia"
  }
}
