{
  "geometry": {
    "type": "Point",
    "coordinates": [
      -79.65,
      38.6833
    ]
  },
  "type": "Feature",
  "properties": {
    "hierarchy": [
      "tgn:2314675",
      "tgn:1000001",
      "tgn:7012149",
      "tgn:2002291",
      "tgn:7013961",
      "tgn:7029392"
    ],
    "placetype": [
      "aat:300008699"
    ],
    "id": 2314675,
    "name:xx": "Elk Run"
  }
}
