{
  "geometry": {
    "type": "Point",
    "coordinates": [
      32.051927,
      29.030969
    ]
  },
  "type": "Feature",
  "properties": {
    "hierarchy": [
      "tgn:7532933",
      "tgn:7001242",
      "tgn:7016833",
      "tgn:1001110",
      "tgn:7029392"
    ],
    "placetype": [
      "aat:300379998"
    ],
    "name:en": "Ab큰 Qas큰'ah, W훮d카",
    "id": 7532933
  }
}
