{
  "geometry": {
    "type": "Point",
    "coordinates": [
      -75.7333,
      39.75
    ]
  },
  "type": "Feature",
  "properties": {
    "hierarchy": [
      "tgn:2481052",
      "tgn:7014201",
      "tgn:1000001",
      "tgn:7012149",
      "tgn:7007239",
      "tgn:7029392"
    ],
    "placetype": [
      "aat:300008347"
    ],
    "id": 2481052,
    "name:xx": "Lamatan II"
  }
}
