{
  "geometry": {
    "type": "Point",
    "coordinates": [
      -84.7667,
      39.5167
    ]
  },
  "type": "Feature",
  "properties": {
    "hierarchy": [
      "tgn:2500410",
      "tgn:1000001",
      "tgn:1002216",
      "tgn:7012149",
      "tgn:7007706",
      "tgn:7029392"
    ],
    "placetype": [
      "aat:300008347"
    ],
    "id": 2500410,
    "name:xx": "McDonald"
  }
}
