{
  "geometry": {
    "type": "Point",
    "coordinates": [
      -84.9833,
      31.6333
    ]
  },
  "type": "Feature",
  "properties": {
    "hierarchy": [
      "tgn:2573423",
      "tgn:1000001",
      "tgn:2000321",
      "tgn:7012149",
      "tgn:7007248",
      "tgn:7029392"
    ],
    "placetype": [
      "aat:300008347"
    ],
    "id": 2573423,
    "name:xx": "Pecan"
  }
}
