{
  "geometry": {
    "type": "Point",
    "coordinates": [
      -151.7333,
      61.6333
    ]
  },
  "type": "Feature",
  "properties": {
    "hierarchy": [
      "tgn:2709978",
      "tgn:7006450",
      "tgn:1000001",
      "tgn:2124053",
      "tgn:7012149",
      "tgn:7029392"
    ],
    "placetype": [
      "aat:300008706"
    ],
    "id": 2709978,
    "name:xx": "Talachulitna Creek"
  }
}
