{
  "type": "FeatureCollection",
  "features": [
    {
      "geometry": {
        "type": "Point",
        "coordinates": [
          7.35,
          51.4
        ]
      },
      "type": "Feature",
      "properties": {
        "hierarchy": [
          "tgn:7062340",
          "tgn:1000003",
          "tgn:7003677",
          "tgn:7000084",
          "tgn:7029392"
        ],
        "placetype": [
          "aat:300000206"
        ],
        "id": 7062340,
        "name:xx": "Am Lütgen Hölzken"
      }
    },
    {
      "geometry": {
        "type": "Point",
        "coordinates": [
          8.433333,
          51.333333
        ]
      },
      "type": "Feature",
      "properties": {
        "hierarchy": [
          "tgn:7062341",
          "tgn:1000003",
          "tgn:7003677",
          "tgn:7000084",
          "tgn:7029392"
        ],
        "placetype": [
          "aat:300008777"
        ],
        "id": 7062341,
        "name:xx": "Am Löh"
      }
    },
    {
      "geometry": {
        "type": "Point",
        "coordinates": [
          7.9,
          51.133333
        ]
      },
      "type": "Feature",
      "properties": {
        "hierarchy": [
          "tgn:7062342",
          "tgn:1000003",
          "tgn:7003677",
          "tgn:7000084",
          "tgn:7029392"
        ],
        "placetype": [
          "aat:300000206"
        ],
        "id": 7062342,
        "name:xx": "Am Loh"
      }
    },
    {
      "geometry": {
        "type": "Point",
        "coordinates": [
          9.962222,
          49.264167
        ]
      },
      "type": "Feature",
      "properties": {
        "hierarchy": [
          "tgn:7062343",
          "tgn:7003692",
          "tgn:1000003",
          "tgn:7000084",
          "tgn:7029392"
        ],
        "placetype": [
          "aat:300008347"
        ],
        "id": 7062343,
        "name:xx": "Amlishagen"
      }
    },
    {
      "geometry": {
        "type": "Point",
        "coordinates": [
          11,
          49.85
        ]
      },
      "type": "Feature",
      "properties": {
        "hierarchy": [
          "tgn:7062344",
          "tgn:7003669",
          "tgn:1000003",
          "tgn:7000084",
          "tgn:7029392"
        ],
        "placetype": [
          "aat:300008347"
        ],
        "id": 7062344,
        "name:xx": "Amlingstadt"
      }
    },
    {
      "geometry": {
        "type": "Point",
        "coordinates": [
          6.5,
          51.416667
        ]
      },
      "type": "Feature",
      "properties": {
        "hierarchy": [
          "tgn:7062345",
          "tgn:1000003",
          "tgn:7003677",
          "tgn:7000084",
          "tgn:7029392"
        ],
        "placetype": [
          "aat:300000206"
        ],
        "id": 7062345,
        "name:xx": "Am Leursdik"
      }
    },
    {
      "geometry": {
        "type": "Point",
        "coordinates": [
          10.983333,
          52.183333
        ]
      },
      "type": "Feature",
      "properties": {
        "hierarchy": [
          "tgn:7062346",
          "tgn:1000003",
          "tgn:7003676",
          "tgn:7000084",
          "tgn:7029392"
        ],
        "placetype": [
          "aat:300008863"
        ],
        "id": 7062346,
        "name:xx": "Am Kurzen Holze"
      }
    },
    {
      "geometry": {
        "type": "Point",
        "coordinates": [
          7.633333,
          51.383333
        ]
      },
      "type": "Feature",
      "properties": {
        "hierarchy": [
          "tgn:7062347",
          "tgn:1000003",
          "tgn:7003677",
          "tgn:7000084",
          "tgn:7029392"
        ],
        "placetype": [
          "aat:300000206"
        ],
        "id": 7062347,
        "name:xx": "Am Kuhwege"
      }
    },
    {
      "geometry": {
        "type": "Point",
        "coordinates": [
          7.9,
          51.2
        ]
      },
      "type": "Feature",
      "properties": {
        "hierarchy": [
          "tgn:7062348",
          "tgn:1000003",
          "tgn:7003677",
          "tgn:7000084",
          "tgn:7029392"
        ],
        "placetype": [
          "aat:300008777"
        ],
        "id": 7062348,
        "name:xx": "Am Kroppe"
      }
    },
    {
      "geometry": {
        "type": "Point",
        "coordinates": [
          7.633333,
          51.4
        ]
      },
      "type": "Feature",
      "properties": {
        "hierarchy": [
          "tgn:7062349",
          "tgn:1000003",
          "tgn:7003677",
          "tgn:7000084",
          "tgn:7029392"
        ],
        "placetype": [
          "aat:300000206"
        ],
        "id": 7062349,
        "name:xx": "Am Kronenberge"
      }
    }
  ]
}
