{
  "geometry": {
    "type": "Point",
    "coordinates": [
      -80.583,
      7.666
    ]
  },
  "type": "Feature",
  "properties": {
    "hierarchy": [
      "tgn:1012707",
      "tgn:1000001",
      "tgn:7005565",
      "tgn:7029392"
    ],
    "placetype": [
      "aat:300008804"
    ],
    "id": 1012707,
    "name:xx": "Azuero, Península de"
  }
}
