{
  "geometry": {
    "type": "Point",
    "coordinates": [
      -166.2167,
      65.2667
    ]
  },
  "type": "Feature",
  "properties": {
    "hierarchy": [
      "tgn:2359587",
      "tgn:7006450",
      "tgn:1000001",
      "tgn:7012149",
      "tgn:2000079",
      "tgn:7029392"
    ],
    "placetype": [
      "aat:300008678"
    ],
    "id": 2359587,
    "name:xx": "Grantley Harbor"
  }
}
