{
  "geometry": {
    "type": "Point",
    "coordinates": [
      -81.3167,
      26.9167
    ]
  },
  "type": "Feature",
  "properties": {
    "hierarchy": [
      "tgn:2019555",
      "tgn:1000001",
      "tgn:1002408",
      "tgn:7012149",
      "tgn:7007240",
      "tgn:7029392"
    ],
    "placetype": [
      "aat:300387016"
    ],
    "id": 2019555,
    "name:xx": "Harrisburg"
  }
}
