{
  "geometry": {
    "type": "Point",
    "coordinates": [
      63.8333,
      28.7333
    ]
  },
  "type": "Feature",
  "properties": {
    "hierarchy": [
      "tgn:1083862",
      "tgn:7000360",
      "tgn:1000004",
      "tgn:1000133",
      "tgn:7029392"
    ],
    "placetype": [
      "aat:300008347"
    ],
    "id": 1083862,
    "name:xx": "Yakmach"
  }
}
