{
  "geometry": {
    "type": "Point",
    "coordinates": [
      -83.65,
      35.65
    ]
  },
  "type": "Feature",
  "properties": {
    "hierarchy": [
      "tgn:2505204",
      "tgn:1000001",
      "tgn:7012149",
      "tgn:7007825",
      "tgn:7029392"
    ],
    "placetype": [
      "aat:300008706"
    ],
    "id": 2505204,
    "name:xx": "Meigs Creek"
  }
}
