{
  "geometry": {
    "type": "Point",
    "coordinates": [
      -106.5667,
      36.0167
    ]
  },
  "type": "Feature",
  "properties": {
    "hierarchy": [
      "tgn:2574515",
      "tgn:1000001",
      "tgn:7012149",
      "tgn:2001449",
      "tgn:7007566",
      "tgn:7029392"
    ],
    "placetype": [
      "aat:300008699"
    ],
    "id": 2574515,
    "name:xx": "Pelon, Rito"
  }
}
