{
  "geometry": {
    "type": "Point",
    "coordinates": [
      -95.0833,
      41.6833
    ]
  },
  "type": "Feature",
  "properties": {
    "hierarchy": [
      "tgn:2592873",
      "tgn:1000001",
      "tgn:7012149",
      "tgn:2000643",
      "tgn:7007253",
      "tgn:7029392"
    ],
    "placetype": [
      "aat:300008347"
    ],
    "id": 2592873,
    "name:xx": "Poplar"
  }
}
