{
  "geometry": {
    "type": "Point",
    "coordinates": [
      -86.65,
      41.2333
    ]
  },
  "type": "Feature",
  "properties": {
    "hierarchy": [
      "tgn:2630787",
      "tgn:1000001",
      "tgn:7012149",
      "tgn:1002918",
      "tgn:7007252",
      "tgn:7029392"
    ],
    "placetype": [
      "aat:300008680"
    ],
    "id": 2630787,
    "name:xx": "Round Lake"
  }
}
