{
  "geometry": {
    "type": "Point",
    "coordinates": [
      81.586667,
      20.084722
    ]
  },
  "type": "Feature",
  "properties": {
    "hierarchy": [
      "tgn:7575522",
      "tgn:1000004",
      "tgn:7031781",
      "tgn:7000198",
      "tgn:7029392"
    ],
    "placetype": [
      "aat:300008347"
    ],
    "name:en": "Keskāl",
    "id": 7575522
  }
}
