{
  "geometry": {
    "type": "Point",
    "coordinates": [
      -119.1333,
      38.3333
    ]
  },
  "type": "Feature",
  "properties": {
    "hierarchy": [
      "tgn:2502846",
      "tgn:1000001",
      "tgn:7012149",
      "tgn:7007157",
      "tgn:1002675",
      "tgn:7029392"
    ],
    "placetype": [
      "aat:300008697"
    ],
    "id": 2502846,
    "name:xx": "McMillan Spring"
  }
}
