{
  "type": "FeatureCollection",
  "features": [
    {
      "geometry": {
        "type": "Point",
        "coordinates": [
          -167.1833,
          53.4667
        ]
      },
      "type": "Feature",
      "properties": {
        "hierarchy": [
          "tgn:2202000",
          "tgn:7030516",
          "tgn:7006450",
          "tgn:1000001",
          "tgn:7012149",
          "tgn:7029392"
        ],
        "placetype": [
          "aat:300008791"
        ],
        "id": 2202000,
        "name:xx": "Buck Island"
      }
    },
    {
      "geometry": {
        "type": "Point",
        "coordinates": [
          -134.1,
          57.7167
        ]
      },
      "type": "Feature",
      "properties": {
        "hierarchy": [
          "tgn:2202001",
          "tgn:7006450",
          "tgn:1000001",
          "tgn:7012149",
          "tgn:7019760",
          "tgn:7029392"
        ],
        "placetype": [
          "aat:300008791"
        ],
        "id": 2202001,
        "name:xx": "Buck Island"
      }
    },
    {
      "geometry": {
        "type": "Point",
        "coordinates": [
          -92.05,
          35.9167
        ]
      },
      "type": "Feature",
      "properties": {
        "hierarchy": [
          "tgn:2202002",
          "tgn:1000001",
          "tgn:7016172",
          "tgn:7012149",
          "tgn:2000173",
          "tgn:7029392"
        ],
        "placetype": [
          "aat:300008791"
        ],
        "id": 2202002,
        "name:xx": "Buck Island"
      }
    },
    {
      "geometry": {
        "type": "Point",
        "coordinates": [
          -122.3667,
          38.9167
        ]
      },
      "type": "Feature",
      "properties": {
        "hierarchy": [
          "tgn:2202003",
          "tgn:1000001",
          "tgn:7012149",
          "tgn:7007157",
          "tgn:7029392"
        ],
        "placetype": [
          "aat:300008791"
        ],
        "id": 2202003,
        "name:xx": "Buck Island"
      }
    },
    {
      "geometry": {
        "type": "Point",
        "coordinates": [
          -83.0667,
          29.2
        ]
      },
      "type": "Feature",
      "properties": {
        "hierarchy": [
          "tgn:2202004",
          "tgn:1000001",
          "tgn:7012149",
          "tgn:2000277",
          "tgn:7007240",
          "tgn:7029392"
        ],
        "placetype": [
          "aat:300008791"
        ],
        "id": 2202004,
        "name:xx": "Buck Island"
      }
    },
    {
      "geometry": {
        "type": "Point",
        "coordinates": [
          -83.1833,
          29.8667
        ]
      },
      "type": "Feature",
      "properties": {
        "hierarchy": [
          "tgn:2202005",
          "tgn:1000001",
          "tgn:2000275",
          "tgn:7012149",
          "tgn:7007240",
          "tgn:7029392"
        ],
        "placetype": [
          "aat:300008791"
        ],
        "id": 2202005,
        "name:xx": "Buck Island"
      }
    },
    {
      "geometry": {
        "type": "Point",
        "coordinates": [
          -82.0667,
          30.1667
        ]
      },
      "type": "Feature",
      "properties": {
        "hierarchy": [
          "tgn:2202006",
          "tgn:2000257",
          "tgn:1000001",
          "tgn:7012149",
          "tgn:7007240",
          "tgn:7029392"
        ],
        "placetype": [
          "aat:300008791"
        ],
        "id": 2202006,
        "name:xx": "Buck Island"
      }
    },
    {
      "geometry": {
        "type": "Point",
        "coordinates": [
          -81.4167,
          30.3667
        ]
      },
      "type": "Feature",
      "properties": {
        "hierarchy": [
          "tgn:2202007",
          "tgn:1000001",
          "tgn:2000264",
          "tgn:7012149",
          "tgn:7007240",
          "tgn:7029392"
        ],
        "placetype": [
          "aat:300008791"
        ],
        "id": 2202007,
        "name:xx": "Buck Island"
      }
    },
    {
      "geometry": {
        "type": "Point",
        "coordinates": [
          -82.4833,
          30.4
        ]
      },
      "type": "Feature",
      "properties": {
        "hierarchy": [
          "tgn:2202008",
          "tgn:1000001",
          "tgn:2000262",
          "tgn:7012149",
          "tgn:7007240",
          "tgn:7029392"
        ],
        "placetype": [
          "aat:300008791"
        ],
        "id": 2202008,
        "name:xx": "Buck Island"
      }
    },
    {
      "geometry": {
        "type": "Point",
        "coordinates": [
          -82.4667,
          30.6333
        ]
      },
      "type": "Feature",
      "properties": {
        "hierarchy": [
          "tgn:2202009",
          "tgn:1000001",
          "tgn:2000323",
          "tgn:7012149",
          "tgn:7007248",
          "tgn:7029392"
        ],
        "placetype": [
          "aat:300008791"
        ],
        "id": 2202009,
        "name:xx": "Buck Island"
      }
    }
  ]
}
