{
  "geometry": {
    "type": "Point",
    "coordinates": [
      -93.7667,
      40.85
    ]
  },
  "type": "Feature",
  "properties": {
    "hierarchy": [
      "tgn:2459808",
      "tgn:1000001",
      "tgn:7019179",
      "tgn:7012149",
      "tgn:7007253",
      "tgn:7029392"
    ],
    "placetype": [
      "aat:300008707"
    ],
    "id": 2459808,
    "name:xx": "Little River"
  }
}
