{
  "type": "FeatureCollection",
  "features": [
    {
      "geometry": {
        "type": "Point",
        "coordinates": [
          -118.0667,
          44.5167
        ]
      },
      "type": "Feature",
      "properties": {
        "hierarchy": [
          "tgn:2530220",
          "tgn:7013349",
          "tgn:1000001",
          "tgn:7012149",
          "tgn:7007708",
          "tgn:7029392"
        ],
        "placetype": [
          "aat:300008697"
        ],
        "id": 2530220,
        "name:xx": "Mud Springs"
      }
    },
    {
      "geometry": {
        "type": "Point",
        "coordinates": [
          -118.7833,
          44.7833
        ]
      },
      "type": "Feature",
      "properties": {
        "hierarchy": [
          "tgn:2530221",
          "tgn:1000001",
          "tgn:7012149",
          "tgn:2001708",
          "tgn:7007708",
          "tgn:7029392"
        ],
        "placetype": [
          "aat:300008697"
        ],
        "id": 2530221,
        "name:xx": "Mud Springs"
      }
    },
    {
      "geometry": {
        "type": "Point",
        "coordinates": [
          -100.6167,
          29.45
        ]
      },
      "type": "Feature",
      "properties": {
        "hierarchy": [
          "tgn:2530222",
          "tgn:1000001",
          "tgn:7012149",
          "tgn:2002021",
          "tgn:7007826",
          "tgn:7029392"
        ],
        "placetype": [
          "aat:300008697"
        ],
        "id": 2530222,
        "name:xx": "Mud Springs"
      }
    },
    {
      "geometry": {
        "type": "Point",
        "coordinates": [
          -97,
          32.8833
        ]
      },
      "type": "Feature",
      "properties": {
        "hierarchy": [
          "tgn:2530223",
          "tgn:1000001",
          "tgn:7012149",
          "tgn:1002315",
          "tgn:7007826",
          "tgn:7029392"
        ],
        "placetype": [
          "aat:300008699"
        ],
        "id": 2530223,
        "name:xx": "Mud Springs"
      }
    },
    {
      "geometry": {
        "type": "Point",
        "coordinates": [
          -98.3167,
          30.8667
        ]
      },
      "type": "Feature",
      "properties": {
        "hierarchy": [
          "tgn:2530224",
          "tgn:1000001",
          "tgn:7012149",
          "tgn:2001949",
          "tgn:7007826",
          "tgn:7029392"
        ],
        "placetype": [
          "aat:300008697"
        ],
        "id": 2530224,
        "name:xx": "Mud Springs"
      }
    },
    {
      "geometry": {
        "type": "Point",
        "coordinates": [
          -113.1833,
          37.6
        ]
      },
      "type": "Feature",
      "properties": {
        "hierarchy": [
          "tgn:2530225",
          "tgn:1000001",
          "tgn:7012149",
          "tgn:2002111",
          "tgn:7007827",
          "tgn:7029392"
        ],
        "placetype": [
          "aat:300008697"
        ],
        "id": 2530225,
        "name:xx": "Mud Springs"
      }
    },
    {
      "geometry": {
        "type": "Point",
        "coordinates": [
          -112.6,
          39.1167
        ]
      },
      "type": "Feature",
      "properties": {
        "hierarchy": [
          "tgn:2530226",
          "tgn:1000001",
          "tgn:7012149",
          "tgn:2002114",
          "tgn:7007827",
          "tgn:7029392"
        ],
        "placetype": [
          "aat:300008697"
        ],
        "id": 2530226,
        "name:xx": "Mud Springs"
      }
    },
    {
      "geometry": {
        "type": "Point",
        "coordinates": [
          -112.0667,
          39.7667
        ]
      },
      "type": "Feature",
      "properties": {
        "hierarchy": [
          "tgn:2530227",
          "tgn:1000001",
          "tgn:7012149",
          "tgn:2002112",
          "tgn:7007827",
          "tgn:7029392"
        ],
        "placetype": [
          "aat:300008697"
        ],
        "id": 2530227,
        "name:xx": "Mud Springs"
      }
    },
    {
      "geometry": {
        "type": "Point",
        "coordinates": [
          -111.3667,
          40.6833
        ]
      },
      "type": "Feature",
      "properties": {
        "hierarchy": [
          "tgn:2530228",
          "tgn:1000001",
          "tgn:7012149",
          "tgn:2002122",
          "tgn:7007827",
          "tgn:7029392"
        ],
        "placetype": [
          "aat:300008697"
        ],
        "id": 2530228,
        "name:xx": "Mud Springs"
      }
    },
    {
      "geometry": {
        "type": "Point",
        "coordinates": [
          -112.5833,
          41.5167
        ]
      },
      "type": "Feature",
      "properties": {
        "hierarchy": [
          "tgn:2530229",
          "tgn:1000001",
          "tgn:2002102",
          "tgn:7012149",
          "tgn:7007827",
          "tgn:7029392"
        ],
        "placetype": [
          "aat:300008697"
        ],
        "id": 2530229,
        "name:xx": "Mud Springs"
      }
    }
  ]
}
