{
  "geometry": {
    "type": "Point",
    "coordinates": [
      -87.3167,
      33.3167
    ]
  },
  "type": "Feature",
  "properties": {
    "hierarchy": [
      "tgn:2005241",
      "tgn:7002659",
      "tgn:1000001",
      "tgn:7012149",
      "tgn:2000062",
      "tgn:7029392"
    ],
    "placetype": [
      "aat:300008347"
    ],
    "id": 2005241,
    "name:xx": "Searles"
  }
}
