{
  "geometry": {
    "type": "Point",
    "coordinates": [
      -90.0167,
      46.4667
    ]
  },
  "type": "Feature",
  "properties": {
    "hierarchy": [
      "tgn:2135488",
      "tgn:1000001",
      "tgn:7012149",
      "tgn:2000960",
      "tgn:7007520",
      "tgn:7029392"
    ],
    "placetype": [
      "aat:300008347"
    ],
    "id": 2135488,
    "name:xx": "Anvil"
  }
}
