{
  "geometry": {
    "type": "Point",
    "coordinates": [
      -116.3167,
      44.5833
    ]
  },
  "type": "Feature",
  "properties": {
    "hierarchy": [
      "tgn:2714178",
      "tgn:2000453",
      "tgn:1000001",
      "tgn:7012149",
      "tgn:7007250",
      "tgn:7029392"
    ],
    "placetype": [
      "aat:300008761"
    ],
    "id": 2714178,
    "name:xx": "Telephone Draw"
  }
}
