{
  "geometry": {
    "type": "Point",
    "coordinates": [
      28.5333,
      40.55
    ]
  },
  "type": "Feature",
  "properties": {
    "hierarchy": [
      "tgn:7002663",
      "tgn:1001167",
      "tgn:1000004",
      "tgn:7018450",
      "tgn:1000144",
      "tgn:7029392"
    ],
    "placetype": [
      "aat:300008791"
    ],
    "id": 7002663,
    "name:xx": "İmralı"
  }
}
