{
  "geometry": {
    "type": "Point",
    "coordinates": [
      -9.8167,
      54.0333
    ]
  },
  "type": "Feature",
  "properties": {
    "hierarchy": [
      "tgn:1042616",
      "tgn:7001198",
      "tgn:7003481",
      "tgn:1000003",
      "tgn:1000078",
      "tgn:7029392"
    ],
    "placetype": [
      "aat:300008347"
    ],
    "id": 1042616,
    "name:xx": "Ballycroy"
  }
}
