{
  "type": "FeatureCollection",
  "features": [
    {
      "geometry": {
        "type": "Point",
        "coordinates": [
          5.583333,
          50.55
        ]
      },
      "type": "Feature",
      "properties": {
        "hierarchy": [
          "tgn:7249200",
          "tgn:7003460",
          "tgn:1000003",
          "tgn:1000063",
          "tgn:4012014",
          "tgn:7029392"
        ],
        "placetype": [
          "aat:300008863"
        ],
        "id": 7249200,
        "name:xx": "Monceau, Bois de"
      }
    },
    {
      "geometry": {
        "type": "Point",
        "coordinates": [
          4.25,
          50.016667
        ]
      },
      "type": "Feature",
      "properties": {
        "hierarchy": [
          "tgn:7249201",
          "tgn:7007877",
          "tgn:1000003",
          "tgn:1000063",
          "tgn:4012014",
          "tgn:7029392"
        ],
        "placetype": [
          "aat:300008863"
        ],
        "id": 7249201,
        "name:xx": "Monceau, Bois de"
      }
    },
    {
      "geometry": {
        "type": "Point",
        "coordinates": [
          3.594951,
          50.646961
        ]
      },
      "type": "Feature",
      "properties": {
        "hierarchy": [
          "tgn:7249202",
          "tgn:7007877",
          "tgn:1000003",
          "tgn:1000063",
          "tgn:4012014",
          "tgn:7029392"
        ],
        "placetype": [
          "aat:300008347"
        ],
        "id": 7249202,
        "name:xx": "Monceau"
      }
    },
    {
      "geometry": {
        "type": "Point",
        "coordinates": [
          3.733333,
          50.4
        ]
      },
      "type": "Feature",
      "properties": {
        "hierarchy": [
          "tgn:7249203",
          "tgn:7007877",
          "tgn:1000003",
          "tgn:1000063",
          "tgn:4012014",
          "tgn:7029392"
        ],
        "placetype": [
          "aat:300008347"
        ],
        "id": 7249203,
        "name:xx": "Monceau"
      }
    },
    {
      "geometry": {
        "type": "Point",
        "coordinates": [
          5.816667,
          50.383333
        ]
      },
      "type": "Feature",
      "properties": {
        "hierarchy": [
          "tgn:7249204",
          "tgn:7003460",
          "tgn:1000003",
          "tgn:1000063",
          "tgn:4012014",
          "tgn:7029392"
        ],
        "placetype": [
          "aat:300008347"
        ],
        "id": 7249204,
        "name:xx": "Monceau"
      }
    },
    {
      "geometry": {
        "type": "Point",
        "coordinates": [
          4.983333,
          49.9
        ]
      },
      "type": "Feature",
      "properties": {
        "hierarchy": [
          "tgn:7249205",
          "tgn:7003466",
          "tgn:1000003",
          "tgn:1000063",
          "tgn:4012014",
          "tgn:7029392"
        ],
        "placetype": [
          "aat:300008347"
        ],
        "id": 7249205,
        "name:xx": "Monceau"
      }
    },
    {
      "geometry": {
        "type": "Point",
        "coordinates": [
          5.7,
          50.05
        ]
      },
      "type": "Feature",
      "properties": {
        "hierarchy": [
          "tgn:7249207",
          "tgn:7003465",
          "tgn:1000003",
          "tgn:1000063",
          "tgn:4012014",
          "tgn:7029392"
        ],
        "placetype": [
          "aat:300008347"
        ],
        "id": 7249207,
        "name:xx": "Monaville"
      }
    },
    {
      "geometry": {
        "type": "Point",
        "coordinates": [
          4.566667,
          50.766667
        ]
      },
      "type": "Feature",
      "properties": {
        "hierarchy": [
          "tgn:7249208",
          "tgn:7018239",
          "tgn:1000003",
          "tgn:1000063",
          "tgn:7018236",
          "tgn:7029392"
        ],
        "placetype": [
          "aat:300000206"
        ],
        "id": 7249208,
        "name:xx": "Mommaartshof"
      }
    }
  ]
}
