{
  "type": "FeatureCollection",
  "features": [
    {
      "geometry": {
        "type": "Point",
        "coordinates": [
          -72.116667,
          -53.3
        ]
      },
      "type": "Feature",
      "properties": {
        "hierarchy": [
          "tgn:7281300",
          "tgn:1001702",
          "tgn:1000049",
          "tgn:1000002",
          "tgn:7029392"
        ],
        "placetype": [
          "aat:300386846"
        ],
        "id": 7281300,
        "name:xx": "Santa Cruz, Punta"
      }
    },
    {
      "geometry": {
        "type": "Point",
        "coordinates": [
          -70.283333,
          -54.166667
        ]
      },
      "type": "Feature",
      "properties": {
        "hierarchy": [
          "tgn:7281301",
          "tgn:1001702",
          "tgn:1000049",
          "tgn:1000002",
          "tgn:7029392"
        ],
        "placetype": [
          "aat:300008791"
        ],
        "id": 7281301,
        "name:xx": "Santa Cruz, Isla"
      }
    },
    {
      "geometry": {
        "type": "Point",
        "coordinates": [
          -72.483333,
          -53.2
        ]
      },
      "type": "Feature",
      "properties": {
        "hierarchy": [
          "tgn:7281302",
          "tgn:1001702",
          "tgn:1000049",
          "tgn:1000002",
          "tgn:7029392"
        ],
        "placetype": [
          "aat:300008791"
        ],
        "id": 7281302,
        "name:xx": "Santa Cruz, Isla"
      }
    },
    {
      "geometry": {
        "type": "Point",
        "coordinates": [
          -71.35,
          -34.633333
        ]
      },
      "type": "Feature",
      "properties": {
        "hierarchy": [
          "tgn:7281303",
          "tgn:1001695",
          "tgn:1000049",
          "tgn:1000002",
          "tgn:7029392"
        ],
        "placetype": [
          "aat:300007783"
        ],
        "id": 7281303,
        "name:xx": "Estación Santa Cruz"
      }
    },
    {
      "geometry": {
        "type": "Point",
        "coordinates": [
          -71.383333,
          -52.75
        ]
      },
      "type": "Feature",
      "properties": {
        "hierarchy": [
          "tgn:7281304",
          "tgn:1001702",
          "tgn:1000049",
          "tgn:1000002",
          "tgn:7029392"
        ],
        "placetype": [
          "aat:300266563"
        ],
        "id": 7281304,
        "name:xx": "Santa Cruz, Angostura"
      }
    },
    {
      "geometry": {
        "type": "Point",
        "coordinates": [
          -72.55,
          -36.266667
        ]
      },
      "type": "Feature",
      "properties": {
        "hierarchy": [
          "tgn:7281305",
          "tgn:1001637",
          "tgn:1000049",
          "tgn:1000002",
          "tgn:7029392"
        ],
        "placetype": [
          "aat:300008347"
        ],
        "id": 7281305,
        "name:xx": "Santa Cruz"
      }
    },
    {
      "geometry": {
        "type": "Point",
        "coordinates": [
          -72.3,
          -36.216667
        ]
      },
      "type": "Feature",
      "properties": {
        "hierarchy": [
          "tgn:7281307",
          "tgn:1001705",
          "tgn:1000049",
          "tgn:1000002",
          "tgn:7029392"
        ],
        "placetype": [
          "aat:300000206"
        ],
        "id": 7281307,
        "name:xx": "Santa Cruz"
      }
    },
    {
      "geometry": {
        "type": "Point",
        "coordinates": [
          -71.95,
          -34.366667
        ]
      },
      "type": "Feature",
      "properties": {
        "hierarchy": [
          "tgn:7281308",
          "tgn:1001695",
          "tgn:1000049",
          "tgn:1000002",
          "tgn:7029392"
        ],
        "placetype": [
          "aat:300008777"
        ],
        "id": 7281308,
        "name:xx": "Santa Cornelia"
      }
    },
    {
      "geometry": {
        "type": "Point",
        "coordinates": [
          -70.783333,
          -33.466667
        ]
      },
      "type": "Feature",
      "properties": {
        "hierarchy": [
          "tgn:7281309",
          "tgn:1001708",
          "tgn:1000049",
          "tgn:1000002",
          "tgn:7029392"
        ],
        "placetype": [
          "aat:300000206"
        ],
        "id": 7281309,
        "name:xx": "Santa Corina"
      }
    }
  ]
}
