{
  "geometry": {
    "type": "Point",
    "coordinates": [
      75.74519,
      28.519958
    ]
  },
  "type": "Feature",
  "properties": {
    "hierarchy": [
      "tgn:7564819",
      "tgn:1000004",
      "tgn:1001871",
      "tgn:7000198",
      "tgn:7029392"
    ],
    "placetype": [
      "aat:300008347"
    ],
    "name:en": "Ahamad ki Dhāni",
    "id": 7564819
  }
}
