{
  "geometry": {
    "type": "Point",
    "coordinates": [
      -78.4667,
      37.0333
    ]
  },
  "type": "Feature",
  "properties": {
    "hierarchy": [
      "tgn:2349830",
      "tgn:1000001",
      "tgn:7012149",
      "tgn:7007919",
      "tgn:7029392"
    ],
    "placetype": [
      "aat:300008706"
    ],
    "id": 2349830,
    "name:xx": "Gills Creek"
  }
}
