{
  "geometry": {
    "type": "Point",
    "coordinates": [
      -105.7833,
      42.5833
    ]
  },
  "type": "Feature",
  "properties": {
    "hierarchy": [
      "tgn:2576359",
      "tgn:1000001",
      "tgn:2002369",
      "tgn:7012149",
      "tgn:7007923",
      "tgn:7029392"
    ],
    "placetype": [
      "aat:300008706"
    ],
    "id": 2576359,
    "name:xx": "Perry Creek"
  }
}
