{
  "geometry": {
    "type": "Point",
    "coordinates": [
      -98.7833,
      33.4333
    ]
  },
  "type": "Feature",
  "properties": {
    "hierarchy": [
      "tgn:2255291",
      "tgn:2001934",
      "tgn:1000001",
      "tgn:7012149",
      "tgn:7007826",
      "tgn:7029392"
    ],
    "placetype": [
      "aat:300006191"
    ],
    "id": 2255291,
    "name:xx": "Cooper, Lake"
  }
}
