{
  "geometry": {
    "type": "Point",
    "coordinates": [
      -82.8167,
      30.7667
    ]
  },
  "type": "Feature",
  "properties": {
    "hierarchy": [
      "tgn:2164799",
      "tgn:1000001",
      "tgn:7012149",
      "tgn:2000341",
      "tgn:7007248",
      "tgn:7029392"
    ],
    "placetype": [
      "aat:300008680"
    ],
    "id": 2164799,
    "name:xx": "Beryl Lake"
  }
}
