{
  "type": "FeatureCollection",
  "features": [
    {
      "geometry": {
        "type": "Point",
        "coordinates": [
          4.283333,
          50.266667
        ]
      },
      "type": "Feature",
      "properties": {
        "hierarchy": [
          "tgn:7252761",
          "tgn:7007877",
          "tgn:1000003",
          "tgn:1000063",
          "tgn:4012014",
          "tgn:7029392"
        ],
        "placetype": [
          "aat:300008347"
        ],
        "id": 7252761,
        "name:xx": "Tourivet"
      }
    },
    {
      "geometry": {
        "type": "Point",
        "coordinates": [
          4.716667,
          50.633333
        ]
      },
      "type": "Feature",
      "properties": {
        "hierarchy": [
          "tgn:7252762",
          "tgn:7018238",
          "tgn:1000003",
          "tgn:1000063",
          "tgn:4012014",
          "tgn:7029392"
        ],
        "placetype": [
          "aat:300008347"
        ],
        "id": 7252762,
        "name:xx": "Tourinnes-Saint-Lambert"
      }
    },
    {
      "geometry": {
        "type": "Point",
        "coordinates": [
          4.75,
          50.783333
        ]
      },
      "type": "Feature",
      "properties": {
        "hierarchy": [
          "tgn:7252764",
          "tgn:7018238",
          "tgn:1000003",
          "tgn:1000063",
          "tgn:4012014",
          "tgn:7029392"
        ],
        "placetype": [
          "aat:300008347"
        ],
        "id": 7252764,
        "name:xx": "Tourinnes-la-Grosse"
      }
    },
    {
      "geometry": {
        "type": "Point",
        "coordinates": [
          5.175212,
          50.638866
        ]
      },
      "type": "Feature",
      "properties": {
        "hierarchy": [
          "tgn:7252766",
          "tgn:7003460",
          "tgn:1000003",
          "tgn:1000063",
          "tgn:4012014",
          "tgn:7029392"
        ],
        "placetype": [
          "aat:300008347"
        ],
        "id": 7252766,
        "name:xx": "Tourinne"
      }
    },
    {
      "geometry": {
        "type": "Point",
        "coordinates": [
          4.283333,
          50.266667
        ]
      },
      "type": "Feature",
      "properties": {
        "hierarchy": [
          "tgn:7252767",
          "tgn:7007877",
          "tgn:1000003",
          "tgn:1000063",
          "tgn:4012014",
          "tgn:7029392"
        ],
        "placetype": [
          "aat:300008347"
        ],
        "id": 7252767,
        "name:xx": "Strée"
      }
    }
  ]
}
