{
  "type": "FeatureCollection",
  "features": [
    {
      "geometry": {
        "type": "Point",
        "coordinates": [
          -111.6833,
          42.05
        ]
      },
      "type": "Feature",
      "properties": {
        "hierarchy": [
          "tgn:2144370",
          "tgn:1000001",
          "tgn:7012149",
          "tgn:2000472",
          "tgn:7007250",
          "tgn:7029392"
        ],
        "placetype": [
          "aat:300008697"
        ],
        "id": 2144370,
        "name:xx": "Baker Spring"
      }
    },
    {
      "geometry": {
        "type": "Point",
        "coordinates": [
          -112.05,
          45.2833
        ]
      },
      "type": "Feature",
      "properties": {
        "hierarchy": [
          "tgn:2144371",
          "tgn:1000001",
          "tgn:7012149",
          "tgn:2001288",
          "tgn:7007524",
          "tgn:7029392"
        ],
        "placetype": [
          "aat:300008697"
        ],
        "id": 2144371,
        "name:xx": "Baker Spring"
      }
    },
    {
      "geometry": {
        "type": "Point",
        "coordinates": [
          -112.5333,
          46.05
        ]
      },
      "type": "Feature",
      "properties": {
        "hierarchy": [
          "tgn:2144372",
          "tgn:1000001",
          "tgn:7012149",
          "tgn:2001306",
          "tgn:7007524",
          "tgn:7029392"
        ],
        "placetype": [
          "aat:300008697"
        ],
        "id": 2144372,
        "name:xx": "Baker Spring"
      }
    },
    {
      "geometry": {
        "type": "Point",
        "coordinates": [
          -114.5333,
          41.1333
        ]
      },
      "type": "Feature",
      "properties": {
        "hierarchy": [
          "tgn:2144373",
          "tgn:1000001",
          "tgn:2001411",
          "tgn:7012149",
          "tgn:7007526",
          "tgn:7029392"
        ],
        "placetype": [
          "aat:300008697"
        ],
        "id": 2144373,
        "name:xx": "Baker Spring"
      }
    },
    {
      "geometry": {
        "type": "Point",
        "coordinates": [
          -103.0667,
          32.4333
        ]
      },
      "type": "Feature",
      "properties": {
        "hierarchy": [
          "tgn:2144374",
          "tgn:1000001",
          "tgn:7012149",
          "tgn:2001441",
          "tgn:7007566",
          "tgn:7029392"
        ],
        "placetype": [
          "aat:300008697"
        ],
        "id": 2144374,
        "name:xx": "Baker Spring"
      }
    },
    {
      "geometry": {
        "type": "Point",
        "coordinates": [
          -118.9833,
          43.7667
        ]
      },
      "type": "Feature",
      "properties": {
        "hierarchy": [
          "tgn:2144375",
          "tgn:1000001",
          "tgn:7012149",
          "tgn:2001709",
          "tgn:7007708",
          "tgn:7029392"
        ],
        "placetype": [
          "aat:300008697"
        ],
        "id": 2144375,
        "name:xx": "Baker Spring"
      }
    },
    {
      "geometry": {
        "type": "Point",
        "coordinates": [
          -117.1833,
          45.7667
        ]
      },
      "type": "Feature",
      "properties": {
        "hierarchy": [
          "tgn:2144376",
          "tgn:1000001",
          "tgn:7012149",
          "tgn:2001722",
          "tgn:7007708",
          "tgn:7029392"
        ],
        "placetype": [
          "aat:300008697"
        ],
        "id": 2144376,
        "name:xx": "Baker Spring"
      }
    },
    {
      "geometry": {
        "type": "Point",
        "coordinates": [
          -118.0167,
          43.9
        ]
      },
      "type": "Feature",
      "properties": {
        "hierarchy": [
          "tgn:2144377",
          "tgn:1000001",
          "tgn:7012149",
          "tgn:2001718",
          "tgn:7007708",
          "tgn:7029392"
        ],
        "placetype": [
          "aat:300008697"
        ],
        "id": 2144377,
        "name:xx": "Baker Spring"
      }
    },
    {
      "geometry": {
        "type": "Point",
        "coordinates": [
          -83.25,
          36.1167
        ]
      },
      "type": "Feature",
      "properties": {
        "hierarchy": [
          "tgn:2144378",
          "tgn:1000001",
          "tgn:7012149",
          "tgn:2001868",
          "tgn:7007825",
          "tgn:7029392"
        ],
        "placetype": [
          "aat:300008697"
        ],
        "id": 2144378,
        "name:xx": "Baker Spring"
      }
    },
    {
      "geometry": {
        "type": "Point",
        "coordinates": [
          -83.6667,
          36.05
        ]
      },
      "type": "Feature",
      "properties": {
        "hierarchy": [
          "tgn:2144379",
          "tgn:1000001",
          "tgn:7012149",
          "tgn:2001881",
          "tgn:7007825",
          "tgn:7029392"
        ],
        "placetype": [
          "aat:300008697"
        ],
        "id": 2144379,
        "name:xx": "Baker Spring"
      }
    }
  ]
}
