{
  "geometry": {
    "type": "Point",
    "coordinates": [
      -84.0167,
      42.7167
    ]
  },
  "type": "Feature",
  "properties": {
    "hierarchy": [
      "tgn:2685433",
      "tgn:1000001",
      "tgn:7012149",
      "tgn:1002603",
      "tgn:7007520",
      "tgn:7029392"
    ],
    "placetype": [
      "aat:300008706"
    ],
    "id": 2685433,
    "name:xx": "Sprague Creek"
  }
}
