{
  "type": "FeatureCollection",
  "features": [
    {
      "geometry": {
        "type": "Point",
        "coordinates": [
          6.9,
          51
        ]
      },
      "type": "Feature",
      "properties": {
        "hierarchy": [
          "tgn:7141390",
          "tgn:1000003",
          "tgn:7003677",
          "tgn:7000084",
          "tgn:7029392"
        ],
        "placetype": [
          "aat:300000745"
        ],
        "id": 7141390,
        "name:xx": "Longerich"
      }
    },
    {
      "geometry": {
        "type": "Point",
        "coordinates": [
          6.783333,
          49.8
        ]
      },
      "type": "Feature",
      "properties": {
        "hierarchy": [
          "tgn:7141391",
          "tgn:1000003",
          "tgn:7003682",
          "tgn:7000084",
          "tgn:7029392"
        ],
        "placetype": [
          "aat:300008347"
        ],
        "id": 7141391,
        "name:xx": "Longen"
      }
    },
    {
      "geometry": {
        "type": "Point",
        "coordinates": [
          9.9,
          48.55
        ]
      },
      "type": "Feature",
      "properties": {
        "hierarchy": [
          "tgn:7141392",
          "tgn:7003692",
          "tgn:1000003",
          "tgn:7000084",
          "tgn:7029392"
        ],
        "placetype": [
          "aat:300008697"
        ],
        "id": 7141392,
        "name:xx": "Lone, Ursprung der"
      }
    },
    {
      "geometry": {
        "type": "Point",
        "coordinates": [
          10.2,
          48.566667
        ]
      },
      "type": "Feature",
      "properties": {
        "hierarchy": [
          "tgn:7141393",
          "tgn:7003692",
          "tgn:1000003",
          "tgn:7000084",
          "tgn:7029392"
        ],
        "placetype": [
          "aat:300008699"
        ],
        "id": 7141393,
        "name:xx": "Lonetal River"
      }
    },
    {
      "geometry": {
        "type": "Point",
        "coordinates": [
          8.866667,
          50.666667
        ]
      },
      "type": "Feature",
      "properties": {
        "hierarchy": [
          "tgn:7141394",
          "tgn:1000003",
          "tgn:7003678",
          "tgn:7000084",
          "tgn:7029392"
        ],
        "placetype": [
          "aat:300008347"
        ],
        "id": 7141394,
        "name:xx": "Londorf"
      }
    },
    {
      "geometry": {
        "type": "Point",
        "coordinates": [
          10.35,
          51.666667
        ]
      },
      "type": "Feature",
      "properties": {
        "hierarchy": [
          "tgn:7141395",
          "tgn:1000003",
          "tgn:7003676",
          "tgn:7000084",
          "tgn:7029392"
        ],
        "placetype": [
          "aat:300008347"
        ],
        "id": 7141395,
        "name:xx": "Lonauer Hammerhütte"
      }
    },
    {
      "geometry": {
        "type": "Point",
        "coordinates": [
          10.333333,
          51.7
        ]
      },
      "type": "Feature",
      "properties": {
        "hierarchy": [
          "tgn:7141397",
          "tgn:1000003",
          "tgn:7003676",
          "tgn:7000084",
          "tgn:7029392"
        ],
        "placetype": [
          "aat:300008863"
        ],
        "id": 7141397,
        "name:xx": "Lonau, Staatsforst"
      }
    },
    {
      "geometry": {
        "type": "Point",
        "coordinates": [
          10.366667,
          51.683333
        ]
      },
      "type": "Feature",
      "properties": {
        "hierarchy": [
          "tgn:7141398",
          "tgn:1000003",
          "tgn:7003676",
          "tgn:7000084",
          "tgn:7029392"
        ],
        "placetype": [
          "aat:300008347"
        ],
        "id": 7141398,
        "name:xx": "Lonau"
      }
    },
    {
      "geometry": {
        "type": "Point",
        "coordinates": [
          14.416667,
          51.266667
        ]
      },
      "type": "Feature",
      "properties": {
        "hierarchy": [
          "tgn:7141399",
          "tgn:1000003",
          "tgn:7003685",
          "tgn:7000084",
          "tgn:7029392"
        ],
        "placetype": [
          "aat:300008347"
        ],
        "id": 7141399,
        "name:xx": "Lomske"
      }
    }
  ]
}
