{
  "geometry": {
    "type": "Point",
    "coordinates": [
      -96.8167,
      28.6833
    ]
  },
  "type": "Feature",
  "properties": {
    "hierarchy": [
      "tgn:2106794",
      "tgn:1000001",
      "tgn:7012149",
      "tgn:1002975",
      "tgn:7007826",
      "tgn:7029392"
    ],
    "placetype": [
      "aat:300008347"
    ],
    "id": 2106794,
    "name:xx": "Placedo"
  }
}
