{
  "type": "FeatureCollection",
  "features": [
    {
      "geometry": {
        "type": "Point",
        "coordinates": [
          -6,
          42.333333
        ]
      },
      "type": "Feature",
      "properties": {
        "hierarchy": [
          "tgn:7337751",
          "tgn:7002826",
          "tgn:7001158",
          "tgn:1000003",
          "tgn:1000095",
          "tgn:7029392"
        ],
        "placetype": [
          "aat:300008347"
        ],
        "id": 7337751,
        "name:xx": "Castrotierra de la Valduerna"
      }
    },
    {
      "geometry": {
        "type": "Point",
        "coordinates": [
          -5.25,
          42.35
        ]
      },
      "type": "Feature",
      "properties": {
        "hierarchy": [
          "tgn:7337752",
          "tgn:7002826",
          "tgn:7001158",
          "tgn:1000003",
          "tgn:1000095",
          "tgn:7029392"
        ],
        "placetype": [
          "aat:300008347"
        ],
        "id": 7337752,
        "name:xx": "Castrotierra"
      }
    },
    {
      "geometry": {
        "type": "Point",
        "coordinates": [
          -6.516667,
          43.216667
        ]
      },
      "type": "Feature",
      "properties": {
        "hierarchy": [
          "tgn:7337753",
          "tgn:7008911",
          "tgn:1000003",
          "tgn:7002763",
          "tgn:1000095",
          "tgn:7029392"
        ],
        "placetype": [
          "aat:300008347"
        ],
        "id": 7337753,
        "name:xx": "Castrosín"
      }
    },
    {
      "geometry": {
        "type": "Point",
        "coordinates": [
          -3.8,
          41.4
        ]
      },
      "type": "Feature",
      "properties": {
        "hierarchy": [
          "tgn:7337754",
          "tgn:7002839",
          "tgn:7001158",
          "tgn:1000003",
          "tgn:1000095",
          "tgn:7029392"
        ],
        "placetype": [
          "aat:300008347"
        ],
        "id": 7337754,
        "name:xx": "Castroserracín"
      }
    },
    {
      "geometry": {
        "type": "Point",
        "coordinates": [
          -3.733333,
          41.2
        ]
      },
      "type": "Feature",
      "properties": {
        "hierarchy": [
          "tgn:7337756",
          "tgn:7002839",
          "tgn:7001158",
          "tgn:1000003",
          "tgn:1000095",
          "tgn:7029392"
        ],
        "placetype": [
          "aat:300008347"
        ],
        "id": 7337756,
        "name:xx": "Castroserna de Abajo"
      }
    },
    {
      "geometry": {
        "type": "Point",
        "coordinates": [
          -7.4,
          42.583333
        ]
      },
      "type": "Feature",
      "properties": {
        "hierarchy": [
          "tgn:7337757",
          "tgn:7002829",
          "tgn:1000003",
          "tgn:7002786",
          "tgn:1000095",
          "tgn:7029392"
        ],
        "placetype": [
          "aat:300008347"
        ],
        "id": 7337757,
        "name:xx": "Castrosante"
      }
    },
    {
      "geometry": {
        "type": "Point",
        "coordinates": [
          -6.733333,
          42.416667
        ]
      },
      "type": "Feature",
      "properties": {
        "hierarchy": [
          "tgn:7337758",
          "tgn:7002826",
          "tgn:7001158",
          "tgn:1000003",
          "tgn:1000095",
          "tgn:7029392"
        ],
        "placetype": [
          "aat:300008347"
        ],
        "id": 7337758,
        "name:xx": "Castroquilame"
      }
    },
    {
      "geometry": {
        "type": "Point",
        "coordinates": [
          -7.266667,
          42.533333
        ]
      },
      "type": "Feature",
      "properties": {
        "hierarchy": [
          "tgn:7337759",
          "tgn:7002829",
          "tgn:1000003",
          "tgn:7002786",
          "tgn:1000095",
          "tgn:7029392"
        ],
        "placetype": [
          "aat:300008347"
        ],
        "id": 7337759,
        "name:xx": "Castro Portela"
      }
    }
  ]
}
