{
  "geometry": {
    "type": "Point",
    "coordinates": [
      -92.2333,
      39.2333
    ]
  },
  "type": "Feature",
  "properties": {
    "hierarchy": [
      "tgn:2059488",
      "tgn:1002158",
      "tgn:1000001",
      "tgn:7012149",
      "tgn:7007523",
      "tgn:7029392"
    ],
    "placetype": [
      "aat:300387016"
    ],
    "id": 2059488,
    "name:xx": "Larrabee"
  }
}
