{
  "geometry": {
    "type": "Point",
    "coordinates": [
      70.8833,
      28.95
    ]
  },
  "type": "Feature",
  "properties": {
    "hierarchy": [
      "tgn:1083341",
      "tgn:1000004",
      "tgn:1001490",
      "tgn:1000133",
      "tgn:7029392"
    ],
    "placetype": [
      "aat:300008347"
    ],
    "id": 1083341,
    "name:xx": "Allahabad"
  }
}
