{
  "geometry": {
    "type": "Point",
    "coordinates": [
      -176.9167,
      51.6833
    ]
  },
  "type": "Feature",
  "properties": {
    "hierarchy": [
      "tgn:2755640",
      "tgn:7030516",
      "tgn:7006450",
      "tgn:1000001",
      "tgn:7012149",
      "tgn:7029392"
    ],
    "placetype": [
      "aat:300008850"
    ],
    "id": 2755640,
    "name:xx": "Wedge Point"
  }
}
