{
  "geometry": {
    "type": "Point",
    "coordinates": [
      -81.65,
      31.3833
    ]
  },
  "type": "Feature",
  "properties": {
    "hierarchy": [
      "tgn:2193887",
      "tgn:1000001",
      "tgn:7012149",
      "tgn:2000354",
      "tgn:7007248",
      "tgn:7029392"
    ],
    "placetype": [
      "aat:300008791"
    ],
    "id": 2193887,
    "name:xx": "Briar Island"
  }
}
