{
  "geometry": {
    "type": "Point",
    "coordinates": [
      -77.6333,
      43.2167
    ]
  },
  "type": "Feature",
  "properties": {
    "hierarchy": [
      "tgn:2331715",
      "tgn:1000001",
      "tgn:7012149",
      "tgn:1002681",
      "tgn:7007568",
      "tgn:7029392"
    ],
    "placetype": [
      "aat:300008706"
    ],
    "id": 2331715,
    "name:xx": "Fleming Creek"
  }
}
