{
  "type": "FeatureCollection",
  "features": [
    {
      "geometry": {
        "type": "Point",
        "coordinates": [
          10.183333,
          53.633333
        ]
      },
      "type": "Feature",
      "properties": {
        "hierarchy": [
          "tgn:7129411",
          "tgn:1000003",
          "tgn:7003673",
          "tgn:7000084",
          "tgn:7029392"
        ],
        "placetype": [
          "aat:300008777"
        ],
        "id": 7129411,
        "name:xx": "Mellen-Berg"
      }
    },
    {
      "geometry": {
        "type": "Point",
        "coordinates": [
          12.3,
          48.516667
        ]
      },
      "type": "Feature",
      "properties": {
        "hierarchy": [
          "tgn:7129412",
          "tgn:7003669",
          "tgn:1000003",
          "tgn:7000084",
          "tgn:7029392"
        ],
        "placetype": [
          "aat:300000206"
        ],
        "id": 7129412,
        "name:xx": "Mellenberg"
      }
    },
    {
      "geometry": {
        "type": "Point",
        "coordinates": [
          11.1,
          50.616667
        ]
      },
      "type": "Feature",
      "properties": {
        "hierarchy": [
          "tgn:7129413",
          "tgn:1000003",
          "tgn:7003689",
          "tgn:7000084",
          "tgn:7029392"
        ],
        "placetype": [
          "aat:300008347"
        ],
        "id": 7129413,
        "name:xx": "Mellenbach-Glasbach"
      }
    },
    {
      "geometry": {
        "type": "Point",
        "coordinates": [
          11.1,
          50.6
        ]
      },
      "type": "Feature",
      "properties": {
        "hierarchy": [
          "tgn:7129414",
          "tgn:1000003",
          "tgn:7003689",
          "tgn:7000084",
          "tgn:7029392"
        ],
        "placetype": [
          "aat:300000745"
        ],
        "id": 7129414,
        "name:xx": "Mellenbach"
      }
    },
    {
      "geometry": {
        "type": "Point",
        "coordinates": [
          12.5,
          53.866667
        ]
      },
      "type": "Feature",
      "properties": {
        "hierarchy": [
          "tgn:7129415",
          "tgn:1000003",
          "tgn:7000094",
          "tgn:7000084",
          "tgn:7029392"
        ],
        "placetype": [
          "aat:300008347"
        ],
        "id": 7129415,
        "name:xx": "Matgendorf"
      }
    },
    {
      "geometry": {
        "type": "Point",
        "coordinates": [
          12,
          53.983333
        ]
      },
      "type": "Feature",
      "properties": {
        "hierarchy": [
          "tgn:7129416",
          "tgn:1000003",
          "tgn:7000094",
          "tgn:7000084",
          "tgn:7029392"
        ],
        "placetype": [
          "aat:300008347"
        ],
        "id": 7129416,
        "name:xx": "Matersen"
      }
    },
    {
      "geometry": {
        "type": "Point",
        "coordinates": [
          7.966667,
          51.633333
        ]
      },
      "type": "Feature",
      "properties": {
        "hierarchy": [
          "tgn:7129418",
          "tgn:1000003",
          "tgn:7003677",
          "tgn:7000084",
          "tgn:7029392"
        ],
        "placetype": [
          "aat:300000206"
        ],
        "id": 7129418,
        "name:xx": "Matena"
      }
    },
    {
      "geometry": {
        "type": "Point",
        "coordinates": [
          7.133333,
          51.633333
        ]
      },
      "type": "Feature",
      "properties": {
        "hierarchy": [
          "tgn:7129419",
          "tgn:1000003",
          "tgn:7003677",
          "tgn:7000084",
          "tgn:7029392"
        ],
        "placetype": [
          "aat:300055621"
        ],
        "id": 7129419,
        "name:xx": "Matena"
      }
    }
  ]
}
