{
  "geometry": {
    "type": "Point",
    "coordinates": [
      114.3333,
      25.4333
    ]
  },
  "type": "Feature",
  "properties": {
    "hierarchy": [
      "tgn:1072989",
      "tgn:1000004",
      "tgn:7002082",
      "tgn:1000111",
      "tgn:7029392"
    ],
    "placetype": [
      "aat:300008347"
    ],
    "id": 1072989,
    "name:xx": "Xihuashan"
  }
}
