{
  "type": "FeatureCollection",
  "features": [
    {
      "geometry": {
        "type": "Point",
        "coordinates": [
          -0.7667,
          45.8167
        ]
      },
      "type": "Feature",
      "properties": {
        "hierarchy": [
          "tgn:4009781",
          "tgn:1000003",
          "tgn:7002892",
          "tgn:1000070",
          "tgn:7029392"
        ],
        "placetype": [
          "aat:300008347"
        ],
        "id": 4009781,
        "name:xx": "Saint-Porchaire"
      }
    },
    {
      "geometry": {
        "type": "Point",
        "coordinates": [
          2,
          48.7833
        ]
      },
      "type": "Feature",
      "properties": {
        "hierarchy": [
          "tgn:4009785",
          "tgn:1000003",
          "tgn:7002883",
          "tgn:1000070",
          "tgn:7029392"
        ],
        "placetype": [
          "aat:300008347"
        ],
        "id": 4009785,
        "name:xx": "Saint-Quentin-en-Yvelines"
      }
    },
    {
      "geometry": {
        "type": "Point",
        "coordinates": [
          4.45,
          44.05
        ]
      },
      "type": "Feature",
      "properties": {
        "hierarchy": [
          "tgn:4009786",
          "tgn:1000003",
          "tgn:7002885",
          "tgn:1000070",
          "tgn:7029392"
        ],
        "placetype": [
          "aat:300008347"
        ],
        "id": 4009786,
        "name:xx": "Saint-Quentin-la-Poterie"
      }
    }
  ]
}
