{
  "geometry": {
    "type": "Point",
    "coordinates": [
      -97.05,
      27.8333
    ]
  },
  "type": "Feature",
  "properties": {
    "hierarchy": [
      "tgn:2244488",
      "tgn:1000001",
      "tgn:7012149",
      "tgn:2002049",
      "tgn:7007826",
      "tgn:7029392"
    ],
    "placetype": [
      "aat:300008850"
    ],
    "id": 2244488,
    "name:xx": "Cline Point"
  }
}
