{
  "geometry": {
    "type": "Point",
    "coordinates": [
      -111.0333,
      45.9167
    ]
  },
  "type": "Feature",
  "properties": {
    "hierarchy": [
      "tgn:2602555",
      "tgn:1000001",
      "tgn:7012149",
      "tgn:2001275",
      "tgn:7007524",
      "tgn:7029392"
    ],
    "placetype": [
      "aat:300008706"
    ],
    "id": 2602555,
    "name:xx": "Quagle Creek"
  }
}
