{
  "geometry": {
    "type": "Point",
    "coordinates": [
      -122.0333,
      47.3333
    ]
  },
  "type": "Feature",
  "properties": {
    "hierarchy": [
      "tgn:2646425",
      "tgn:1000001",
      "tgn:7012149",
      "tgn:7018871",
      "tgn:7007920",
      "tgn:7029392"
    ],
    "placetype": [
      "aat:300006191"
    ],
    "id": 2646425,
    "name:xx": "Sawyer, Lake"
  }
}
