{
  "geometry": {
    "type": "Point",
    "coordinates": [
      -123.1833,
      45.9667
    ]
  },
  "type": "Feature",
  "properties": {
    "hierarchy": [
      "tgn:2085174",
      "tgn:1000001",
      "tgn:1002293",
      "tgn:7012149",
      "tgn:7007708",
      "tgn:7029392"
    ],
    "placetype": [
      "aat:300008347",
      "aat:300387210"
    ],
    "id": 2085174,
    "name:xx": "Natal"
  }
}
