{
  "geometry": {
    "type": "Point",
    "coordinates": [
      -80.5833,
      38.0167
    ]
  },
  "type": "Feature",
  "properties": {
    "hierarchy": [
      "tgn:2194777",
      "tgn:1000001",
      "tgn:7012149",
      "tgn:2002264",
      "tgn:7013961",
      "tgn:7029392"
    ],
    "placetype": [
      "aat:300008798"
    ],
    "id": 2194777,
    "name:xx": "Briery Knob"
  }
}
