{
  "geometry": {
    "type": "Point",
    "coordinates": [
      32.203,
      30.126
    ]
  },
  "type": "Feature",
  "properties": {
    "hierarchy": [
      "tgn:1095514",
      "tgn:7001242",
      "tgn:7016833",
      "tgn:1001110",
      "tgn:7029392"
    ],
    "placetype": [
      "aat:300007783"
    ],
    "id": 1095514,
    "name:xx": "Maḩaţţat 'Uwaybid"
  }
}
