{
  "geometry": {
    "type": "Point",
    "coordinates": [
      -85.6833,
      30.8667
    ]
  },
  "type": "Feature",
  "properties": {
    "hierarchy": [
      "tgn:2398579",
      "tgn:1000001",
      "tgn:2000272",
      "tgn:7012149",
      "tgn:7007240",
      "tgn:7029392"
    ],
    "placetype": [
      "aat:300008347"
    ],
    "id": 2398579,
    "name:xx": "Hoover Mill"
  }
}
