{
  "geometry": {
    "type": "Point",
    "coordinates": [
      -83.6333,
      37.7667
    ]
  },
  "type": "Feature",
  "properties": {
    "hierarchy": [
      "tgn:2290401",
      "tgn:1000001",
      "tgn:7012149",
      "tgn:2000853",
      "tgn:7007255",
      "tgn:7029392"
    ],
    "placetype": [
      "aat:300008699"
    ],
    "id": 2290401,
    "name:xx": "Doe Branch"
  }
}
