{
  "geometry": {
    "type": "Point",
    "coordinates": [
      -106.0833,
      45.1833
    ]
  },
  "type": "Feature",
  "properties": {
    "hierarchy": [
      "tgn:2609822",
      "tgn:1000001",
      "tgn:7012149",
      "tgn:2001297",
      "tgn:7007524",
      "tgn:7029392"
    ],
    "placetype": [
      "aat:300006191"
    ],
    "id": 2609822,
    "name:xx": "Reanus Reservoir"
  }
}
