{
  "type": "FeatureCollection",
  "features": [
    {
      "geometry": {
        "type": "Point",
        "coordinates": [
          174.5,
          -35.816667
        ]
      },
      "type": "Feature",
      "properties": {
        "hierarchy": [
          "tgn:7505580",
          "tgn:1008380",
          "tgn:7000507",
          "tgn:1000226",
          "tgn:1000006",
          "tgn:7029392"
        ],
        "placetype": [
          "aat:300008347"
        ],
        "name:en": "Whangarei Heads",
        "id": 7505580
      }
    },
    {
      "geometry": {
        "type": "Point",
        "coordinates": [
          174.416667,
          -35.8
        ]
      },
      "type": "Feature",
      "properties": {
        "hierarchy": [
          "tgn:7505581",
          "tgn:1008380",
          "tgn:7000507",
          "tgn:1000226",
          "tgn:1000006",
          "tgn:7029392"
        ],
        "placetype": [
          "aat:300008678"
        ],
        "name:en": "Whangarei Harbour",
        "id": 7505581
      }
    },
    {
      "geometry": {
        "type": "Point",
        "coordinates": [
          174.966667,
          -37.25
        ]
      },
      "type": "Feature",
      "properties": {
        "hierarchy": [
          "tgn:7505585",
          "tgn:1008380",
          "tgn:1000226",
          "tgn:7018426",
          "tgn:1000006",
          "tgn:7029392"
        ],
        "placetype": [
          "aat:300008347"
        ],
        "name:en": "Whangarata",
        "id": 7505585
      }
    },
    {
      "geometry": {
        "type": "Point",
        "coordinates": [
          175.366667,
          -36.25
        ]
      },
      "type": "Feature",
      "properties": {
        "hierarchy": [
          "tgn:7505586",
          "tgn:7000508",
          "tgn:1008380",
          "tgn:1000226",
          "tgn:1000006",
          "tgn:7029392"
        ],
        "placetype": [
          "aat:300008791"
        ],
        "name:en": "Whangarara",
        "id": 7505586
      }
    },
    {
      "geometry": {
        "type": "Point",
        "coordinates": [
          178.233333,
          -38.566667
        ]
      },
      "type": "Feature",
      "properties": {
        "hierarchy": [
          "tgn:7505587",
          "tgn:7520092",
          "tgn:1008380",
          "tgn:1000226",
          "tgn:1000006",
          "tgn:7029392"
        ],
        "placetype": [
          "aat:300008791"
        ],
        "name:en": "Whangara Island",
        "id": 7505587
      }
    },
    {
      "geometry": {
        "type": "Point",
        "coordinates": [
          173.633333,
          -41.083333
        ]
      },
      "type": "Feature",
      "properties": {
        "hierarchy": [
          "tgn:7505588",
          "tgn:1009227",
          "tgn:1000226",
          "tgn:7016729",
          "tgn:1000006",
          "tgn:7029392"
        ],
        "placetype": [
          "aat:300132316"
        ],
        "name:en": "Whangarae",
        "id": 7505588
      }
    }
  ]
}
