{
  "geometry": {
    "type": "Point",
    "coordinates": [
      -86.1833,
      32.6333
    ]
  },
  "type": "Feature",
  "properties": {
    "hierarchy": [
      "tgn:2511361",
      "tgn:7002659",
      "tgn:1000001",
      "tgn:7012149",
      "tgn:2000025",
      "tgn:7029392"
    ],
    "placetype": [
      "aat:300006191"
    ],
    "id": 2511361,
    "name:xx": "Milam Lake"
  }
}
