{
  "type": "FeatureCollection",
  "features": [
    {
      "geometry": {
        "type": "Point",
        "coordinates": [
          -72.75,
          -41.283333
        ]
      },
      "type": "Feature",
      "properties": {
        "hierarchy": [
          "tgn:7282530",
          "tgn:1001699",
          "tgn:1000049",
          "tgn:1000002",
          "tgn:7029392"
        ],
        "placetype": [
          "aat:300008699"
        ],
        "id": 7282530,
        "name:xx": "Pescado del Sur, Río"
      }
    },
    {
      "geometry": {
        "type": "Point",
        "coordinates": [
          -70.9,
          -52.916667
        ]
      },
      "type": "Feature",
      "properties": {
        "hierarchy": [
          "tgn:7282531",
          "tgn:1001702",
          "tgn:1000049",
          "tgn:1000002",
          "tgn:7029392"
        ],
        "placetype": [
          "aat:300008699"
        ],
        "id": 7282531,
        "name:xx": "Pescado, Río"
      }
    },
    {
      "geometry": {
        "type": "Point",
        "coordinates": [
          -72.8,
          -41.25
        ]
      },
      "type": "Feature",
      "properties": {
        "hierarchy": [
          "tgn:7282532",
          "tgn:1001699",
          "tgn:1000049",
          "tgn:1000002",
          "tgn:7029392"
        ],
        "placetype": [
          "aat:300008699"
        ],
        "id": 7282532,
        "name:xx": "Pescado, Río"
      }
    },
    {
      "geometry": {
        "type": "Point",
        "coordinates": [
          -73.15,
          -41.016667
        ]
      },
      "type": "Feature",
      "properties": {
        "hierarchy": [
          "tgn:7282533",
          "tgn:1001699",
          "tgn:1000049",
          "tgn:1000002",
          "tgn:7029392"
        ],
        "placetype": [
          "aat:300008699"
        ],
        "id": 7282533,
        "name:xx": "Pescado, Estero"
      }
    },
    {
      "geometry": {
        "type": "Point",
        "coordinates": [
          -72.2,
          -40.883333
        ]
      },
      "type": "Feature",
      "properties": {
        "hierarchy": [
          "tgn:7282534",
          "tgn:1001699",
          "tgn:1000049",
          "tgn:1000002",
          "tgn:7029392"
        ],
        "placetype": [
          "aat:300008699"
        ],
        "id": 7282534,
        "name:xx": "Pescado, Estero"
      }
    },
    {
      "geometry": {
        "type": "Point",
        "coordinates": [
          -73.033333,
          -40.05
        ]
      },
      "type": "Feature",
      "properties": {
        "hierarchy": [
          "tgn:7282535",
          "tgn:1001699",
          "tgn:1000049",
          "tgn:1000002",
          "tgn:7029392"
        ],
        "placetype": [
          "aat:300008699"
        ],
        "id": 7282535,
        "name:xx": "Pescado, Estero"
      }
    },
    {
      "geometry": {
        "type": "Point",
        "coordinates": [
          -66.533333,
          -55.166667
        ]
      },
      "type": "Feature",
      "properties": {
        "hierarchy": [
          "tgn:7282536",
          "tgn:1001702",
          "tgn:1000049",
          "tgn:1000002",
          "tgn:7029392"
        ],
        "placetype": [
          "aat:300132317"
        ],
        "id": 7282536,
        "name:xx": "Pescado, Caleta"
      }
    },
    {
      "geometry": {
        "type": "Point",
        "coordinates": [
          -72.7,
          -48.833333
        ]
      },
      "type": "Feature",
      "properties": {
        "hierarchy": [
          "tgn:7282537",
          "tgn:1001623",
          "tgn:1000049",
          "tgn:1000002",
          "tgn:7029392"
        ],
        "placetype": [
          "aat:300132316"
        ],
        "id": 7282537,
        "name:xx": "Pescado, Bahía"
      }
    },
    {
      "geometry": {
        "type": "Point",
        "coordinates": [
          -72.483333,
          -40.766667
        ]
      },
      "type": "Feature",
      "properties": {
        "hierarchy": [
          "tgn:7282538",
          "tgn:1001699",
          "tgn:1000049",
          "tgn:1000002",
          "tgn:7029392"
        ],
        "placetype": [
          "aat:300132316"
        ],
        "id": 7282538,
        "name:xx": "Pescadero Grande, Bahía"
      }
    },
    {
      "geometry": {
        "type": "Point",
        "coordinates": [
          -72.516667,
          -40.766667
        ]
      },
      "type": "Feature",
      "properties": {
        "hierarchy": [
          "tgn:7282539",
          "tgn:1001699",
          "tgn:1000049",
          "tgn:1000002",
          "tgn:7029392"
        ],
        "placetype": [
          "aat:300008699"
        ],
        "id": 7282539,
        "name:xx": "Pescadero, Río"
      }
    }
  ]
}
