{
  "geometry": {
    "type": "Point",
    "coordinates": [
      -97.05,
      43.3333
    ]
  },
  "type": "Feature",
  "properties": {
    "hierarchy": [
      "tgn:2128120",
      "tgn:1000001",
      "tgn:7012149",
      "tgn:2001832",
      "tgn:7007713",
      "tgn:7029392"
    ],
    "placetype": [
      "aat:300006075"
    ],
    "id": 2128120,
    "name:xx": "Alberty Ditch"
  }
}
