{
  "geometry": {
    "type": "Point",
    "coordinates": [
      -96.7667,
      33.9167
    ]
  },
  "type": "Feature",
  "properties": {
    "hierarchy": [
      "tgn:2643282",
      "tgn:1000001",
      "tgn:7012149",
      "tgn:2001670",
      "tgn:7007707",
      "tgn:7029392"
    ],
    "placetype": [
      "aat:300008706"
    ],
    "id": 2643282,
    "name:xx": "Sandy Creek"
  }
}
