{
  "geometry": {
    "type": "Point",
    "coordinates": [
      -96.1333,
      41.4833
    ]
  },
  "type": "Feature",
  "properties": {
    "hierarchy": [
      "tgn:2392294",
      "tgn:1000001",
      "tgn:7012149",
      "tgn:2001404",
      "tgn:7007525",
      "tgn:7029392"
    ],
    "placetype": [
      "aat:300008699"
    ],
    "id": 2392294,
    "name:xx": "Hinz Fork"
  }
}
