{
  "geometry": {
    "type": "Point",
    "coordinates": [
      33.65,
      56.4167
    ]
  },
  "type": "Feature",
  "properties": {
    "hierarchy": [
      "tgn:1057104",
      "tgn:1000004",
      "tgn:7012941",
      "tgn:7018214",
      "tgn:7002435",
      "tgn:7029392"
    ],
    "placetype": [
      "aat:300008347"
    ],
    "id": 1057104,
    "name:xx": "Molodoy-Tud"
  }
}
