{
  "geometry": {
    "type": "Point",
    "coordinates": [
      -96.5667,
      45.5667
    ]
  },
  "type": "Feature",
  "properties": {
    "hierarchy": [
      "tgn:2149720",
      "tgn:2001004",
      "tgn:1000001",
      "tgn:7012149",
      "tgn:7007521",
      "tgn:7029392"
    ],
    "placetype": [
      "aat:300008680"
    ],
    "id": 2149720,
    "name:xx": "Barry Lake"
  }
}
