{
  "geometry": {
    "type": "Point",
    "coordinates": [
      10.65,
      51.65
    ]
  },
  "type": "Feature",
  "properties": {
    "hierarchy": [
      "tgn:7209883",
      "tgn:1000003",
      "tgn:7003676",
      "tgn:7000084",
      "tgn:7029392"
    ],
    "placetype": [
      "aat:300008699"
    ],
    "id": 7209883,
    "name:xx": "Bären-Bach"
  }
}
