{
  "geometry": {
    "type": "Point",
    "coordinates": [
      -135.3333,
      57.05
    ]
  },
  "type": "Feature",
  "properties": {
    "hierarchy": [
      "tgn:2718742",
      "tgn:7006450",
      "tgn:1000001",
      "tgn:7012149",
      "tgn:2124002",
      "tgn:7029392"
    ],
    "placetype": [
      "aat:300132316"
    ],
    "id": 2718742,
    "name:xx": "Thomsen Harbor"
  }
}
