{
  "geometry": {
    "type": "Point",
    "coordinates": [
      103.9167,
      29.1667
    ]
  },
  "type": "Feature",
  "properties": {
    "hierarchy": [
      "tgn:1071096",
      "tgn:1000004",
      "tgn:7002087",
      "tgn:1000111",
      "tgn:7029392"
    ],
    "placetype": [
      "aat:300008347"
    ],
    "id": 1071096,
    "name:xx": "Qingshuixi"
  }
}
