{
  "geometry": {
    "type": "Point",
    "coordinates": [
      32.066667,
      30.833333
    ]
  },
  "type": "Feature",
  "properties": {
    "hierarchy": [
      "tgn:7527624",
      "tgn:7001242",
      "tgn:7016833",
      "tgn:1001113",
      "tgn:7029392"
    ],
    "placetype": [
      "aat:300008777"
    ],
    "name:en": "Umm 'Akīm, Jazīrat",
    "id": 7527624
  }
}
