{
  "geometry": {
    "type": "Point",
    "coordinates": [
      -115.1333,
      45.0667
    ]
  },
  "type": "Feature",
  "properties": {
    "hierarchy": [
      "tgn:2710060",
      "tgn:1000001",
      "tgn:7012149",
      "tgn:2000494",
      "tgn:7007250",
      "tgn:7029392"
    ],
    "placetype": [
      "aat:300008706"
    ],
    "id": 2710060,
    "name:xx": "Talc Creek"
  }
}
