{
  "geometry": {
    "type": "Point",
    "coordinates": [
      -122.8167,
      41.7333
    ]
  },
  "type": "Feature",
  "properties": {
    "hierarchy": [
      "tgn:2633613",
      "tgn:1000001",
      "tgn:7012149",
      "tgn:7007157",
      "tgn:2000189",
      "tgn:7029392"
    ],
    "placetype": [
      "aat:300008761"
    ],
    "id": 2633613,
    "name:xx": "Rusby Gulch"
  }
}
