{
  "geometry": {
    "type": "Point",
    "coordinates": [
      4.95,
      51.55
    ]
  },
  "type": "Feature",
  "properties": {
    "hierarchy": [
      "tgn:1047790",
      "tgn:1000003",
      "tgn:7003624",
      "tgn:7016845",
      "tgn:7029392"
    ],
    "placetype": [
      "aat:300008347"
    ],
    "name:nl": "Gilze",
    "id": 1047790
  }
}
