{
  "geometry": {
    "type": "Point",
    "coordinates": [
      -90.35,
      41.2833
    ]
  },
  "type": "Feature",
  "properties": {
    "hierarchy": [
      "tgn:2028879",
      "tgn:1000001",
      "tgn:7012149",
      "tgn:2000511",
      "tgn:7007251",
      "tgn:7029392"
    ],
    "placetype": [
      "aat:300008347"
    ],
    "id": 2028879,
    "name:xx": "Lynn Center"
  }
}
