{
  "type": "FeatureCollection",
  "features": [
    {
      "geometry": {
        "type": "Point",
        "coordinates": [
          8.466667,
          49.5
        ]
      },
      "type": "Feature",
      "properties": {
        "hierarchy": [
          "tgn:7170960",
          "tgn:7003692",
          "tgn:1000003",
          "tgn:7000084",
          "tgn:7029392"
        ],
        "placetype": [
          "aat:300008187"
        ],
        "id": 7170960,
        "name:xx": "Herzogenriedpark"
      }
    },
    {
      "geometry": {
        "type": "Point",
        "coordinates": [
          11.083333,
          49.9
        ]
      },
      "type": "Feature",
      "properties": {
        "hierarchy": [
          "tgn:7170961",
          "tgn:7003669",
          "tgn:1000003",
          "tgn:7000084",
          "tgn:7029392"
        ],
        "placetype": [
          "aat:300008347"
        ],
        "id": 7170961,
        "name:xx": "Herzogenreuth"
      }
    },
    {
      "geometry": {
        "type": "Point",
        "coordinates": [
          8.016667,
          47.833333
        ]
      },
      "type": "Feature",
      "properties": {
        "hierarchy": [
          "tgn:7170963",
          "tgn:7003692",
          "tgn:1000003",
          "tgn:7000084",
          "tgn:7029392"
        ],
        "placetype": [
          "aat:300008795"
        ],
        "id": 7170963,
        "name:xx": "Herzogenhorn"
      }
    },
    {
      "geometry": {
        "type": "Point",
        "coordinates": [
          9.583333,
          48.616667
        ]
      },
      "type": "Feature",
      "properties": {
        "hierarchy": [
          "tgn:7170965",
          "tgn:7003692",
          "tgn:1000003",
          "tgn:7000084",
          "tgn:7029392"
        ],
        "placetype": [
          "aat:300008347"
        ],
        "id": 7170965,
        "name:xx": "Herzogenau"
      }
    },
    {
      "geometry": {
        "type": "Point",
        "coordinates": [
          8.45,
          51
        ]
      },
      "type": "Feature",
      "properties": {
        "hierarchy": [
          "tgn:7170966",
          "tgn:1000003",
          "tgn:7003677",
          "tgn:7000084",
          "tgn:7029392"
        ],
        "placetype": [
          "aat:300008777"
        ],
        "id": 7170966,
        "name:xx": "Herzogeiche"
      }
    },
    {
      "geometry": {
        "type": "Point",
        "coordinates": [
          13.1,
          48.683333
        ]
      },
      "type": "Feature",
      "properties": {
        "hierarchy": [
          "tgn:7170967",
          "tgn:7003669",
          "tgn:1000003",
          "tgn:7000084",
          "tgn:7029392"
        ],
        "placetype": [
          "aat:300387200"
        ],
        "id": 7170967,
        "name:xx": "Herzogau"
      }
    },
    {
      "geometry": {
        "type": "Point",
        "coordinates": [
          12.716667,
          49.35
        ]
      },
      "type": "Feature",
      "properties": {
        "hierarchy": [
          "tgn:7170968",
          "tgn:7003669",
          "tgn:1000003",
          "tgn:7000084",
          "tgn:7029392"
        ],
        "placetype": [
          "aat:300008347"
        ],
        "id": 7170968,
        "name:xx": "Herzogau"
      }
    },
    {
      "geometry": {
        "type": "Point",
        "coordinates": [
          12.666667,
          48.683333
        ]
      },
      "type": "Feature",
      "properties": {
        "hierarchy": [
          "tgn:7170969",
          "tgn:7003669",
          "tgn:1000003",
          "tgn:7000084",
          "tgn:7029392"
        ],
        "placetype": [
          "aat:300000206"
        ],
        "id": 7170969,
        "name:xx": "Herzogau"
      }
    }
  ]
}
