{
  "geometry": {
    "type": "Point",
    "coordinates": [
      -106.1167,
      41.65
    ]
  },
  "type": "Feature",
  "properties": {
    "hierarchy": [
      "tgn:2123044",
      "tgn:1000001",
      "tgn:2002368",
      "tgn:7012149",
      "tgn:7007923",
      "tgn:7029392"
    ],
    "placetype": [
      "aat:300008347"
    ],
    "id": 2123044,
    "name:xx": "McFadden"
  }
}
