{
  "geometry": {
    "type": "Point",
    "coordinates": [
      32.35,
      26.066667
    ]
  },
  "type": "Feature",
  "properties": {
    "hierarchy": [
      "tgn:7540580",
      "tgn:7001242",
      "tgn:7016833",
      "tgn:7000123",
      "tgn:7029392"
    ],
    "placetype": [
      "aat:300008347"
    ],
    "name:en": "Naj' Hawwārah",
    "id": 7540580
  }
}
