{
  "geometry": {
    "type": "Point",
    "coordinates": [
      -109.0667,
      34.0167
    ]
  },
  "type": "Feature",
  "properties": {
    "hierarchy": [
      "tgn:2597728",
      "tgn:2000090",
      "tgn:1000001",
      "tgn:7006451",
      "tgn:7012149",
      "tgn:7029392"
    ],
    "placetype": [
      "aat:300008680"
    ],
    "id": 2597728,
    "name:xx": "Pratt Lake"
  }
}
