{
  "type": "FeatureCollection",
  "features": [
    {
      "geometry": {
        "type": "Point",
        "coordinates": [
          -105.6,
          26.183333
        ]
      },
      "type": "Feature",
      "properties": {
        "hierarchy": [
          "tgn:7375570",
          "tgn:7005583",
          "tgn:1000001",
          "tgn:7005560",
          "tgn:7029392"
        ],
        "placetype": [
          "aat:300008347"
        ],
        "id": 7375570,
        "name:xx": "La Quesera"
      }
    },
    {
      "geometry": {
        "type": "Point",
        "coordinates": [
          -103.05,
          20.85
        ]
      },
      "type": "Feature",
      "properties": {
        "hierarchy": [
          "tgn:7375571",
          "tgn:7005586",
          "tgn:1000001",
          "tgn:7005560",
          "tgn:7029392"
        ],
        "placetype": [
          "aat:300000241"
        ],
        "id": 7375571,
        "name:xx": "La Quemada de Tateposco"
      }
    },
    {
      "geometry": {
        "type": "Point",
        "coordinates": [
          -107,
          28.766667
        ]
      },
      "type": "Feature",
      "properties": {
        "hierarchy": [
          "tgn:7375572",
          "tgn:7005581",
          "tgn:1000001",
          "tgn:7005560",
          "tgn:7029392"
        ],
        "placetype": [
          "aat:300008699"
        ],
        "id": 7375572,
        "name:xx": "La Quemada, Arroyo de"
      }
    },
    {
      "geometry": {
        "type": "Point",
        "coordinates": [
          -104.016667,
          20.966667
        ]
      },
      "type": "Feature",
      "properties": {
        "hierarchy": [
          "tgn:7375573",
          "tgn:7005586",
          "tgn:1000001",
          "tgn:7005560",
          "tgn:7029392"
        ],
        "placetype": [
          "aat:300007783"
        ],
        "id": 7375573,
        "name:xx": "La Quemada"
      }
    },
    {
      "geometry": {
        "type": "Point",
        "coordinates": [
          -106.966667,
          28.8
        ]
      },
      "type": "Feature",
      "properties": {
        "hierarchy": [
          "tgn:7375574",
          "tgn:7005581",
          "tgn:1000001",
          "tgn:7005560",
          "tgn:7029392"
        ],
        "placetype": [
          "aat:300008347"
        ],
        "id": 7375574,
        "name:xx": "La Quemada"
      }
    },
    {
      "geometry": {
        "type": "Point",
        "coordinates": [
          -102,
          25.1
        ]
      },
      "type": "Feature",
      "properties": {
        "hierarchy": [
          "tgn:7375577",
          "tgn:1001853",
          "tgn:1000001",
          "tgn:7005560",
          "tgn:7029392"
        ],
        "placetype": [
          "aat:300008347"
        ],
        "id": 7375577,
        "name:xx": "La Quemada"
      }
    },
    {
      "geometry": {
        "type": "Point",
        "coordinates": [
          -102.816667,
          23.5
        ]
      },
      "type": "Feature",
      "properties": {
        "hierarchy": [
          "tgn:7375578",
          "tgn:1000001",
          "tgn:7005601",
          "tgn:7005560",
          "tgn:7029392"
        ],
        "placetype": [
          "aat:300008347"
        ],
        "id": 7375578,
        "name:xx": "La Quemada"
      }
    },
    {
      "geometry": {
        "type": "Point",
        "coordinates": [
          -103.3,
          23.3
        ]
      },
      "type": "Feature",
      "properties": {
        "hierarchy": [
          "tgn:7375579",
          "tgn:1000001",
          "tgn:7005601",
          "tgn:7005560",
          "tgn:7029392"
        ],
        "placetype": [
          "aat:300008347"
        ],
        "id": 7375579,
        "name:xx": "La Quemada"
      }
    }
  ]
}
