{
  "geometry": {
    "type": "Point",
    "coordinates": [
      -100.45,
      33.2667
    ]
  },
  "type": "Feature",
  "properties": {
    "hierarchy": [
      "tgn:2785876",
      "tgn:1000001",
      "tgn:7012149",
      "tgn:2002078",
      "tgn:7007826",
      "tgn:7029392"
    ],
    "placetype": [
      "aat:300006191"
    ],
    "id": 2785876,
    "name:xx": "York Tanks"
  }
}
