{
  "geometry": {
    "type": "Point",
    "coordinates": [
      -75.7833,
      35.5667
    ]
  },
  "type": "Feature",
  "properties": {
    "hierarchy": [
      "tgn:2468963",
      "tgn:1000001",
      "tgn:7012149",
      "tgn:2001488",
      "tgn:7007709",
      "tgn:7029392"
    ],
    "placetype": [
      "aat:300132348"
    ],
    "id": 2468963,
    "name:xx": "Long Shoal"
  }
}
