{
  "type": "FeatureCollection",
  "features": [
    {
      "geometry": {
        "type": "Point",
        "coordinates": [
          15.2167,
          49
        ]
      },
      "type": "Feature",
      "properties": {
        "hierarchy": [
          "tgn:1027320",
          "tgn:7011506",
          "tgn:1000003",
          "tgn:1001780",
          "tgn:7029392"
        ],
        "placetype": [
          "aat:300008347"
        ],
        "id": 1027320,
        "name:xx": "Landštejn"
      }
    },
    {
      "geometry": {
        "type": "Point",
        "coordinates": [
          14.6333,
          48.95
        ]
      },
      "type": "Feature",
      "properties": {
        "hierarchy": [
          "tgn:1027321",
          "tgn:7011506",
          "tgn:1000003",
          "tgn:1001780",
          "tgn:7029392"
        ],
        "placetype": [
          "aat:300008347"
        ],
        "id": 1027321,
        "name:xx": "Ledenice"
      }
    },
    {
      "geometry": {
        "type": "Point",
        "coordinates": [
          13.8,
          48.9167
        ]
      },
      "type": "Feature",
      "properties": {
        "hierarchy": [
          "tgn:1027323",
          "tgn:7011506",
          "tgn:1000003",
          "tgn:1001780",
          "tgn:7029392"
        ],
        "placetype": [
          "aat:300008347"
        ],
        "id": 1027323,
        "name:xx": "Lenora"
      }
    },
    {
      "geometry": {
        "type": "Point",
        "coordinates": [
          12.8667,
          49.8833
        ]
      },
      "type": "Feature",
      "properties": {
        "hierarchy": [
          "tgn:1027324",
          "tgn:7593919",
          "tgn:1000003",
          "tgn:1001780",
          "tgn:7029392"
        ],
        "placetype": [
          "aat:300008347"
        ],
        "id": 1027324,
        "name:xx": "Lestkov"
      }
    },
    {
      "geometry": {
        "type": "Point",
        "coordinates": [
          18.5833,
          48.2333
        ]
      },
      "type": "Feature",
      "properties": {
        "hierarchy": [
          "tgn:1027325",
          "tgn:7027129",
          "tgn:1000003",
          "tgn:7011765",
          "tgn:7029392"
        ],
        "placetype": [
          "aat:300008347"
        ],
        "id": 1027325,
        "name:xx": "Levice"
      }
    },
    {
      "geometry": {
        "type": "Point",
        "coordinates": [
          14.6,
          49.0167
        ]
      },
      "type": "Feature",
      "properties": {
        "hierarchy": [
          "tgn:1027327",
          "tgn:7011506",
          "tgn:1000003",
          "tgn:1001780",
          "tgn:7029392"
        ],
        "placetype": [
          "aat:300008347"
        ],
        "id": 1027327,
        "name:xx": "Lišov"
      }
    },
    {
      "geometry": {
        "type": "Point",
        "coordinates": [
          14.3333,
          50.1667
        ]
      },
      "type": "Feature",
      "properties": {
        "hierarchy": [
          "tgn:1027329",
          "tgn:1003530",
          "tgn:1000003",
          "tgn:1001780",
          "tgn:7029392"
        ],
        "placetype": [
          "aat:300008347"
        ],
        "id": 1027329,
        "name:xx": "Libčice nad Vltavou"
      }
    }
  ]
}
