{
  "type": "FeatureCollection",
  "features": [
    {
      "geometry": {
        "type": "Point",
        "coordinates": [
          38.6,
          -17.0667
        ]
      },
      "type": "Feature",
      "properties": {
        "hierarchy": [
          "tgn:1127052",
          "tgn:7001242",
          "tgn:1000955",
          "tgn:1000180",
          "tgn:7029392"
        ],
        "placetype": [
          "aat:300008707"
        ],
        "id": 1127052,
        "name:xx": "Melela, Rio"
      }
    },
    {
      "geometry": {
        "type": "Point",
        "coordinates": [
          13.583333,
          41.5
        ]
      },
      "type": "Feature",
      "properties": {
        "hierarchy": [
          "tgn:1127053",
          "tgn:7003135",
          "tgn:1000003",
          "tgn:7003080",
          "tgn:1000080",
          "tgn:7029392"
        ],
        "placetype": [
          "aat:300008707",
          "aat:300008699"
        ],
        "id": 1127053,
        "name:xx": "Melfa"
      }
    },
    {
      "geometry": {
        "type": "Point",
        "coordinates": [
          -10.7,
          8.2667
        ]
      },
      "type": "Feature",
      "properties": {
        "hierarchy": [
          "tgn:1127054",
          "tgn:7001242",
          "tgn:7029392"
        ],
        "placetype": [
          "aat:300008707"
        ],
        "id": 1127054,
        "name:xx": "Meli"
      }
    },
    {
      "geometry": {
        "type": "Point",
        "coordinates": [
          10.3,
          36.7667
        ]
      },
      "type": "Feature",
      "properties": {
        "hierarchy": [
          "tgn:1127055",
          "tgn:7001242",
          "tgn:1000205",
          "tgn:7029392"
        ],
        "placetype": [
          "aat:300008707"
        ],
        "id": 1127055,
        "name:xx": "Meliane, Oued"
      }
    },
    {
      "geometry": {
        "type": "Point",
        "coordinates": [
          15.3167,
          48.2333
        ]
      },
      "type": "Feature",
      "properties": {
        "hierarchy": [
          "tgn:1127056",
          "tgn:7003025",
          "tgn:1000003",
          "tgn:1000062",
          "tgn:7029392"
        ],
        "placetype": [
          "aat:300008707"
        ],
        "id": 1127056,
        "name:xx": "Melk"
      }
    },
    {
      "geometry": {
        "type": "Point",
        "coordinates": [
          8.85,
          36.5333
        ]
      },
      "type": "Feature",
      "properties": {
        "hierarchy": [
          "tgn:1127057",
          "tgn:7001242",
          "tgn:7029392"
        ],
        "placetype": [
          "aat:300008707"
        ],
        "id": 1127057,
        "name:xx": "Mellègue, Oued"
      }
    },
    {
      "geometry": {
        "type": "Point",
        "coordinates": [
          10.216667,
          45.216667
        ]
      },
      "type": "Feature",
      "properties": {
        "hierarchy": [
          "tgn:1127058",
          "tgn:7005765",
          "tgn:1000003",
          "tgn:7003237",
          "tgn:1000080",
          "tgn:7029392"
        ],
        "placetype": [
          "aat:300008707",
          "aat:300008699"
        ],
        "id": 1127058,
        "name:xx": "Mella"
      }
    },
    {
      "geometry": {
        "type": "Point",
        "coordinates": [
          5.533333,
          49.716667
        ]
      },
      "type": "Feature",
      "properties": {
        "hierarchy": [
          "tgn:1127059",
          "tgn:7003465",
          "tgn:1000003",
          "tgn:1000063",
          "tgn:4012014",
          "tgn:7029392"
        ],
        "placetype": [
          "aat:300008707",
          "aat:300008699"
        ],
        "id": 1127059,
        "name:xx": "Mellier"
      }
    }
  ]
}
