{
  "type": "FeatureCollection",
  "features": [
    {
      "geometry": {
        "type": "Point",
        "coordinates": [
          -93.3,
          46.7167
        ]
      },
      "type": "Feature",
      "properties": {
        "hierarchy": [
          "tgn:2643640",
          "tgn:2000999",
          "tgn:1000001",
          "tgn:7012149",
          "tgn:7007521",
          "tgn:7029392"
        ],
        "placetype": [
          "aat:300008680"
        ],
        "id": 2643640,
        "name:xx": "Sandy River Lake"
      }
    },
    {
      "geometry": {
        "type": "Point",
        "coordinates": [
          -70.55,
          44.8833
        ]
      },
      "type": "Feature",
      "properties": {
        "hierarchy": [
          "tgn:2643641",
          "tgn:1000001",
          "tgn:2000921",
          "tgn:7012149",
          "tgn:7007515",
          "tgn:7029392"
        ],
        "placetype": [
          "aat:300008680"
        ],
        "id": 2643641,
        "name:xx": "Sandy River Ponds"
      }
    },
    {
      "geometry": {
        "type": "Point",
        "coordinates": [
          -81.4333,
          30.25
        ]
      },
      "type": "Feature",
      "properties": {
        "hierarchy": [
          "tgn:2643642",
          "tgn:1000001",
          "tgn:2000264",
          "tgn:7012149",
          "tgn:7007240",
          "tgn:7029392"
        ],
        "placetype": [
          "aat:300008699"
        ],
        "id": 2643642,
        "name:xx": "Sandy Run"
      }
    },
    {
      "geometry": {
        "type": "Point",
        "coordinates": [
          -83.1167,
          33.2167
        ]
      },
      "type": "Feature",
      "properties": {
        "hierarchy": [
          "tgn:2643643",
          "tgn:1000001",
          "tgn:7012149",
          "tgn:2000361",
          "tgn:7007248",
          "tgn:7029392"
        ],
        "placetype": [
          "aat:300008347"
        ],
        "id": 2643643,
        "name:xx": "Sandy Run"
      }
    },
    {
      "geometry": {
        "type": "Point",
        "coordinates": [
          -83.1167,
          33.2333
        ]
      },
      "type": "Feature",
      "properties": {
        "hierarchy": [
          "tgn:2643644",
          "tgn:1000001",
          "tgn:7012149",
          "tgn:2000361",
          "tgn:7007248",
          "tgn:7029392"
        ],
        "placetype": [
          "aat:300008699"
        ],
        "id": 2643644,
        "name:xx": "Sandy Run"
      }
    },
    {
      "geometry": {
        "type": "Point",
        "coordinates": [
          -88.9167,
          38.9667
        ]
      },
      "type": "Feature",
      "properties": {
        "hierarchy": [
          "tgn:2643645",
          "tgn:1000001",
          "tgn:1002369",
          "tgn:7012149",
          "tgn:7007251",
          "tgn:7029392"
        ],
        "placetype": [
          "aat:300008699"
        ],
        "id": 2643645,
        "name:xx": "Sandy Run"
      }
    },
    {
      "geometry": {
        "type": "Point",
        "coordinates": [
          -92.1,
          31.6
        ]
      },
      "type": "Feature",
      "properties": {
        "hierarchy": [
          "tgn:2643646",
          "tgn:1000001",
          "tgn:7012149",
          "tgn:2000883",
          "tgn:7007256",
          "tgn:7029392"
        ],
        "placetype": [
          "aat:300008699"
        ],
        "id": 2643646,
        "name:xx": "Sandy Run"
      }
    },
    {
      "geometry": {
        "type": "Point",
        "coordinates": [
          -90.7167,
          30.9
        ]
      },
      "type": "Feature",
      "properties": {
        "hierarchy": [
          "tgn:2643647",
          "tgn:1000001",
          "tgn:7012149",
          "tgn:2000899",
          "tgn:7007256",
          "tgn:7029392"
        ],
        "placetype": [
          "aat:300008699"
        ],
        "id": 2643647,
        "name:xx": "Sandy Run"
      }
    },
    {
      "geometry": {
        "type": "Point",
        "coordinates": [
          -77.45,
          39.55
        ]
      },
      "type": "Feature",
      "properties": {
        "hierarchy": [
          "tgn:2643648",
          "tgn:1000001",
          "tgn:7016101",
          "tgn:7012149",
          "tgn:7007516",
          "tgn:7029392"
        ],
        "placetype": [
          "aat:300008699"
        ],
        "id": 2643648,
        "name:xx": "Sandy Run"
      }
    },
    {
      "geometry": {
        "type": "Point",
        "coordinates": [
          -85.1833,
          43.8667
        ]
      },
      "type": "Feature",
      "properties": {
        "hierarchy": [
          "tgn:2643649",
          "tgn:1000001",
          "tgn:7012149",
          "tgn:2000987",
          "tgn:7007520",
          "tgn:7029392"
        ],
        "placetype": [
          "aat:300008699"
        ],
        "id": 2643649,
        "name:xx": "Sandy Run"
      }
    }
  ]
}
