{
  "geometry": {
    "type": "Point",
    "coordinates": [
      -87.9833,
      35.35
    ]
  },
  "type": "Feature",
  "properties": {
    "hierarchy": [
      "tgn:2648231",
      "tgn:1000001",
      "tgn:7012149",
      "tgn:2001927",
      "tgn:7007825",
      "tgn:7029392"
    ],
    "placetype": [
      "aat:300008761"
    ],
    "id": 2648231,
    "name:xx": "Schote Hollow"
  }
}
