{
  "geometry": {
    "type": "Point",
    "coordinates": [
      23.9333,
      30.3333
    ]
  },
  "type": "Feature",
  "properties": {
    "hierarchy": [
      "tgn:1099886",
      "tgn:7001242",
      "tgn:7000605",
      "tgn:1000172",
      "tgn:7029392"
    ],
    "placetype": [
      "aat:300008347",
      "aat:300167671"
    ],
    "id": 1099886,
    "name:xx": "Quṣayr ad Daffah"
  }
}
