{
  "geometry": {
    "type": "Point",
    "coordinates": [
      62.45,
      53.1833
    ]
  },
  "type": "Feature",
  "properties": {
    "hierarchy": [
      "tgn:1056760",
      "tgn:1000004",
      "tgn:7012922",
      "tgn:7014786",
      "tgn:7029392"
    ],
    "placetype": [
      "aat:300008347"
    ],
    "id": 1056760,
    "name:xx": "Malorossiyskiy"
  }
}
