{
  "geometry": {
    "type": "Point",
    "coordinates": [
      9.1333,
      46.2667
    ]
  },
  "type": "Feature",
  "properties": {
    "hierarchy": [
      "tgn:1064376",
      "tgn:7003748",
      "tgn:1000003",
      "tgn:7011731",
      "tgn:7029392"
    ],
    "placetype": [
      "aat:300008347",
      "aat:300008375"
    ],
    "id": 1064376,
    "name:xx": "Santa Maria"
  }
}
