{
  "geometry": {
    "type": "Point",
    "coordinates": [
      -110.4833,
      40.55
    ]
  },
  "type": "Feature",
  "properties": {
    "hierarchy": [
      "tgn:2522300",
      "tgn:1000001",
      "tgn:2002107",
      "tgn:7012149",
      "tgn:7007827",
      "tgn:7029392"
    ],
    "placetype": [
      "aat:300008347"
    ],
    "id": 2522300,
    "name:xx": "Moon Lake Resort"
  }
}
