{
  "geometry": {
    "type": "Point",
    "coordinates": [
      -90.1833,
      33.9833
    ]
  },
  "type": "Feature",
  "properties": {
    "hierarchy": [
      "tgn:2464024",
      "tgn:1000001",
      "tgn:7012149",
      "tgn:2001153",
      "tgn:7007522",
      "tgn:7029392"
    ],
    "placetype": [
      "aat:300008347"
    ],
    "id": 2464024,
    "name:xx": "Locopolis"
  }
}
