{
  "geometry": {
    "type": "Point",
    "coordinates": [
      -82.7333,
      35.2667
    ]
  },
  "type": "Feature",
  "properties": {
    "hierarchy": [
      "tgn:2423123",
      "tgn:1000001",
      "tgn:7012149",
      "tgn:2001544",
      "tgn:7007709",
      "tgn:7029392"
    ],
    "placetype": [
      "aat:300008699"
    ],
    "id": 2423123,
    "name:xx": "Joel Branch"
  }
}
