{
  "geometry": {
    "type": "Point",
    "coordinates": [
      -104.5167,
      33.9333
    ]
  },
  "type": "Feature",
  "properties": {
    "hierarchy": [
      "tgn:2370235",
      "tgn:1000001",
      "tgn:2001430",
      "tgn:7012149",
      "tgn:7007566",
      "tgn:7029392"
    ],
    "placetype": [
      "aat:300008697"
    ],
    "id": 2370235,
    "name:xx": "Gyp Spring"
  }
}
