{
  "geometry": {
    "type": "Point",
    "coordinates": [
      -88.7667,
      33.4667
    ]
  },
  "type": "Feature",
  "properties": {
    "hierarchy": [
      "tgn:2173143",
      "tgn:1000001",
      "tgn:7012149",
      "tgn:2001138",
      "tgn:7007522",
      "tgn:7029392"
    ],
    "placetype": [
      "aat:300008347"
    ],
    "id": 2173143,
    "name:xx": "Bingham Estates"
  }
}
