{
  "geometry": {
    "type": "Point",
    "coordinates": [
      88.323,
      22.531
    ]
  },
  "type": "Feature",
  "properties": {
    "hierarchy": [
      "tgn:1003948",
      "tgn:1000004",
      "tgn:7000198",
      "tgn:1001977",
      "tgn:7029392"
    ],
    "placetype": [
      "aat:300008347",
      "aat:300000745"
    ],
    "name:en": "Ālīpur",
    "id": 1003948
  }
}
