{
  "geometry": {
    "type": "Point",
    "coordinates": [
      -103.0333,
      40.5667
    ]
  },
  "type": "Feature",
  "properties": {
    "hierarchy": [
      "tgn:2227554",
      "tgn:1000001",
      "tgn:7012149",
      "tgn:2000229",
      "tgn:7007158",
      "tgn:7029392"
    ],
    "placetype": [
      "aat:300008746"
    ],
    "id": 2227554,
    "name:xx": "Cave, The"
  }
}
