{
  "geometry": {
    "type": "Point",
    "coordinates": [
      -110.65,
      27.783333
    ]
  },
  "type": "Feature",
  "properties": {
    "hierarchy": [
      "tgn:7391012",
      "tgn:1000001",
      "tgn:1001960",
      "tgn:7005560",
      "tgn:7029392"
    ],
    "placetype": [
      "aat:300185707"
    ],
    "id": 7391012,
    "name:xx": "Río Muerto, Estero del"
  }
}
