{
  "geometry": {
    "type": "Point",
    "coordinates": [
      -107.05,
      42.15
    ]
  },
  "type": "Feature",
  "properties": {
    "hierarchy": [
      "tgn:2571124",
      "tgn:1000001",
      "tgn:2002368",
      "tgn:7012149",
      "tgn:7007923",
      "tgn:7029392"
    ],
    "placetype": [
      "aat:300386845"
    ],
    "id": 2571124,
    "name:xx": "Pattison Basin"
  }
}
