{
  "geometry": {
    "type": "Point",
    "coordinates": [
      -83.7167,
      41.55
    ]
  },
  "type": "Feature",
  "properties": {
    "hierarchy": [
      "tgn:2080818",
      "tgn:1000001",
      "tgn:7012149",
      "tgn:1002611",
      "tgn:7007706",
      "tgn:7029392"
    ],
    "placetype": [
      "aat:300008347"
    ],
    "id": 2080818,
    "name:xx": "Monclova"
  }
}
