{
  "geometry": {
    "type": "Point",
    "coordinates": [
      -99.35,
      41.3333
    ]
  },
  "type": "Feature",
  "properties": {
    "hierarchy": [
      "tgn:2522078",
      "tgn:1000001",
      "tgn:2001336",
      "tgn:7012149",
      "tgn:7007525",
      "tgn:7029392"
    ],
    "placetype": [
      "aat:300008761"
    ],
    "id": 2522078,
    "name:xx": "Moody Valley"
  }
}
