{
  "geometry": {
    "type": "Point",
    "coordinates": [
      -89.7333,
      30.2667
    ]
  },
  "type": "Feature",
  "properties": {
    "hierarchy": [
      "tgn:2621927",
      "tgn:1000001",
      "tgn:7012149",
      "tgn:2000905",
      "tgn:7007256",
      "tgn:7029392"
    ],
    "placetype": [
      "aat:300008347"
    ],
    "id": 2621927,
    "name:xx": "Robert Park"
  }
}
