{
  "geometry": {
    "type": "Point",
    "coordinates": [
      -109.95,
      34.0833
    ]
  },
  "type": "Feature",
  "properties": {
    "hierarchy": [
      "tgn:2333385",
      "tgn:1000001",
      "tgn:7006451",
      "tgn:7012149",
      "tgn:2000099",
      "tgn:7029392"
    ],
    "placetype": [
      "aat:300008697"
    ],
    "id": 2333385,
    "name:xx": "Folette Spring"
  }
}
