{
  "geometry": {
    "type": "Point",
    "coordinates": [
      82.757279,
      21.131996
    ]
  },
  "type": "Feature",
  "properties": {
    "hierarchy": [
      "tgn:7551350",
      "tgn:1000004",
      "tgn:7031781",
      "tgn:7000198",
      "tgn:7029392"
    ],
    "placetype": [
      "aat:300008347"
    ],
    "name:en": "Dīwānpāli",
    "id": 7551350
  }
}
