{
  "type": "FeatureCollection",
  "features": [
    {
      "geometry": {
        "type": "Point",
        "coordinates": [
          -93.55,
          39.6167
        ]
      },
      "type": "Feature",
      "properties": {
        "hierarchy": [
          "tgn:2058090",
          "tgn:1000001",
          "tgn:7012149",
          "tgn:2001215",
          "tgn:7007523",
          "tgn:7029392"
        ],
        "placetype": [
          "aat:300008347",
          "aat:300387210"
        ],
        "id": 2058090,
        "name:xx": "Blue Mound"
      }
    },
    {
      "geometry": {
        "type": "Point",
        "coordinates": [
          -93.9333,
          40.1833
        ]
      },
      "type": "Feature",
      "properties": {
        "hierarchy": [
          "tgn:2058091",
          "tgn:1000001",
          "tgn:7012149",
          "tgn:2001201",
          "tgn:7007523",
          "tgn:7029392"
        ],
        "placetype": [
          "aat:300008347"
        ],
        "id": 2058091,
        "name:xx": "Blue Ridge"
      }
    },
    {
      "geometry": {
        "type": "Point",
        "coordinates": [
          -94.2667,
          39.0167
        ]
      },
      "type": "Feature",
      "properties": {
        "hierarchy": [
          "tgn:2058092",
          "tgn:1000001",
          "tgn:7012149",
          "tgn:2001208",
          "tgn:7007523",
          "tgn:7029392"
        ],
        "placetype": [
          "aat:300008347"
        ],
        "id": 2058092,
        "name:xx": "Blue Springs"
      }
    },
    {
      "geometry": {
        "type": "Point",
        "coordinates": [
          -94.5,
          39.0667
        ]
      },
      "type": "Feature",
      "properties": {
        "hierarchy": [
          "tgn:2058094",
          "tgn:1000001",
          "tgn:7012149",
          "tgn:2001208",
          "tgn:7007523",
          "tgn:7029392"
        ],
        "placetype": [
          "aat:300387016"
        ],
        "id": 2058094,
        "name:xx": "Blue Valley"
      }
    },
    {
      "geometry": {
        "type": "Point",
        "coordinates": [
          -91.6167,
          38.7
        ]
      },
      "type": "Feature",
      "properties": {
        "hierarchy": [
          "tgn:2058095",
          "tgn:1000001",
          "tgn:7012149",
          "tgn:1002687",
          "tgn:7007523",
          "tgn:7029392"
        ],
        "placetype": [
          "aat:300008347",
          "aat:300387210"
        ],
        "id": 2058095,
        "name:xx": "Bluffton"
      }
    },
    {
      "geometry": {
        "type": "Point",
        "coordinates": [
          -93.9167,
          40.4667
        ]
      },
      "type": "Feature",
      "properties": {
        "hierarchy": [
          "tgn:2058096",
          "tgn:1000001",
          "tgn:7012149",
          "tgn:2001201",
          "tgn:7007523",
          "tgn:7029392"
        ],
        "placetype": [
          "aat:300008347"
        ],
        "id": 2058096,
        "name:xx": "Blythedale"
      }
    },
    {
      "geometry": {
        "type": "Point",
        "coordinates": [
          -93.4,
          37.0167
        ]
      },
      "type": "Feature",
      "properties": {
        "hierarchy": [
          "tgn:2058097",
          "tgn:1000001",
          "tgn:2001185",
          "tgn:7012149",
          "tgn:7007523",
          "tgn:7029392"
        ],
        "placetype": [
          "aat:300008347",
          "aat:300387210"
        ],
        "id": 2058097,
        "name:xx": "Boaz"
      }
    },
    {
      "geometry": {
        "type": "Point",
        "coordinates": [
          -89.75,
          36.4
        ]
      },
      "type": "Feature",
      "properties": {
        "hierarchy": [
          "tgn:2058098",
          "tgn:1000001",
          "tgn:7012149",
          "tgn:2001222",
          "tgn:7007523",
          "tgn:7029392"
        ],
        "placetype": [
          "aat:300008347"
        ],
        "id": 2058098,
        "name:xx": "Boekerton"
      }
    }
  ]
}
