{
  "geometry": {
    "type": "Point",
    "coordinates": [
      54.55,
      46.7667
    ]
  },
  "type": "Feature",
  "properties": {
    "hierarchy": [
      "tgn:1057210",
      "tgn:7012908",
      "tgn:1000004",
      "tgn:7014786",
      "tgn:7029392"
    ],
    "placetype": [
      "aat:300008347"
    ],
    "id": 1057210,
    "name:xx": "Munayly"
  }
}
