{
  "type": "FeatureCollection",
  "features": [
    {
      "geometry": {
        "type": "Point",
        "coordinates": [
          -68.85,
          44.1333
        ]
      },
      "type": "Feature",
      "properties": {
        "hierarchy": [
          "tgn:2328090",
          "tgn:1000001",
          "tgn:2000924",
          "tgn:7012149",
          "tgn:7007515",
          "tgn:7029392"
        ],
        "placetype": [
          "aat:300132348"
        ],
        "id": 2328090,
        "name:xx": "Fish Point Ledge"
      }
    },
    {
      "geometry": {
        "type": "Point",
        "coordinates": [
          -87.1333,
          34.6333
        ]
      },
      "type": "Feature",
      "properties": {
        "hierarchy": [
          "tgn:2328091",
          "tgn:7002659",
          "tgn:1000001",
          "tgn:7012149",
          "tgn:2000039",
          "tgn:7029392"
        ],
        "placetype": [
          "aat:300008680"
        ],
        "id": 2328091,
        "name:xx": "Fish Pond"
      }
    },
    {
      "geometry": {
        "type": "Point",
        "coordinates": [
          -91.1833,
          36
        ]
      },
      "type": "Feature",
      "properties": {
        "hierarchy": [
          "tgn:2328092",
          "tgn:1000001",
          "tgn:7016172",
          "tgn:7012149",
          "tgn:2000142",
          "tgn:7029392"
        ],
        "placetype": [
          "aat:300008680"
        ],
        "id": 2328092,
        "name:xx": "Fish Pond"
      }
    },
    {
      "geometry": {
        "type": "Point",
        "coordinates": [
          -82.1667,
          28.6333
        ]
      },
      "type": "Feature",
      "properties": {
        "hierarchy": [
          "tgn:2328093",
          "tgn:1000001",
          "tgn:7012149",
          "tgn:1002929",
          "tgn:7007240",
          "tgn:7029392"
        ],
        "placetype": [
          "aat:300008680"
        ],
        "id": 2328093,
        "name:xx": "Fish Pond"
      }
    },
    {
      "geometry": {
        "type": "Point",
        "coordinates": [
          -85.0167,
          30.3
        ]
      },
      "type": "Feature",
      "properties": {
        "hierarchy": [
          "tgn:2328094",
          "tgn:1000001",
          "tgn:7012149",
          "tgn:2000278",
          "tgn:7007240",
          "tgn:7029392"
        ],
        "placetype": [
          "aat:300008680"
        ],
        "id": 2328094,
        "name:xx": "Fish Pond"
      }
    },
    {
      "geometry": {
        "type": "Point",
        "coordinates": [
          -82.7333,
          29.75
        ]
      },
      "type": "Feature",
      "properties": {
        "hierarchy": [
          "tgn:2328095",
          "tgn:1000001",
          "tgn:2000269",
          "tgn:7012149",
          "tgn:7007240",
          "tgn:7029392"
        ],
        "placetype": [
          "aat:300008680"
        ],
        "id": 2328095,
        "name:xx": "Fish Pond"
      }
    },
    {
      "geometry": {
        "type": "Point",
        "coordinates": [
          -82.25,
          29.5
        ]
      },
      "type": "Feature",
      "properties": {
        "hierarchy": [
          "tgn:2328096",
          "tgn:2000256",
          "tgn:1000001",
          "tgn:7012149",
          "tgn:7007240",
          "tgn:7029392"
        ],
        "placetype": [
          "aat:300008680"
        ],
        "id": 2328096,
        "name:xx": "Fish Pond"
      }
    },
    {
      "geometry": {
        "type": "Point",
        "coordinates": [
          -83,
          29.75
        ]
      },
      "type": "Feature",
      "properties": {
        "hierarchy": [
          "tgn:2328097",
          "tgn:1000001",
          "tgn:2000263",
          "tgn:7012149",
          "tgn:7007240",
          "tgn:7029392"
        ],
        "placetype": [
          "aat:300008680"
        ],
        "id": 2328097,
        "name:xx": "Fish Pond"
      }
    },
    {
      "geometry": {
        "type": "Point",
        "coordinates": [
          -82.9833,
          30.95
        ]
      },
      "type": "Feature",
      "properties": {
        "hierarchy": [
          "tgn:2328098",
          "tgn:1000001",
          "tgn:7012149",
          "tgn:2000377",
          "tgn:7007248",
          "tgn:7029392"
        ],
        "placetype": [
          "aat:300008680"
        ],
        "id": 2328098,
        "name:xx": "Fish Pond"
      }
    },
    {
      "geometry": {
        "type": "Point",
        "coordinates": [
          -84.0333,
          31.6833
        ]
      },
      "type": "Feature",
      "properties": {
        "hierarchy": [
          "tgn:2328099",
          "tgn:1000001",
          "tgn:7012149",
          "tgn:2000379",
          "tgn:7007248",
          "tgn:7029392"
        ],
        "placetype": [
          "aat:300008680"
        ],
        "id": 2328099,
        "name:xx": "Fish Pond"
      }
    }
  ]
}
