{
  "geometry": {
    "type": "Point",
    "coordinates": [
      -71.9667,
      44.2667
    ]
  },
  "type": "Feature",
  "properties": {
    "hierarchy": [
      "tgn:2715771",
      "tgn:1000001",
      "tgn:2001424",
      "tgn:7012149",
      "tgn:7007564",
      "tgn:7029392"
    ],
    "placetype": [
      "aat:300008699"
    ],
    "id": 2715771,
    "name:xx": "Teter Meadow Brook"
  }
}
