{
  "geometry": {
    "type": "Point",
    "coordinates": [
      -103.7833,
      39.7167
    ]
  },
  "type": "Feature",
  "properties": {
    "hierarchy": [
      "tgn:2763438",
      "tgn:1000001",
      "tgn:7012149",
      "tgn:7007158",
      "tgn:7029392"
    ],
    "placetype": [
      "aat:300008706"
    ],
    "id": 2763438,
    "name:xx": "Wetzel Creek"
  }
}
