{
  "geometry": {
    "type": "Point",
    "coordinates": [
      -71.9167,
      43.1667
    ]
  },
  "type": "Feature",
  "properties": {
    "hierarchy": [
      "tgn:2537935",
      "tgn:1000001",
      "tgn:1002480",
      "tgn:7012149",
      "tgn:7007564",
      "tgn:7029392"
    ],
    "placetype": [
      "aat:300008699"
    ],
    "id": 2537935,
    "name:xx": "Nelson Brook"
  }
}
