{
  "geometry": {
    "type": "Point",
    "coordinates": [
      -86.1333,
      33.95
    ]
  },
  "type": "Feature",
  "properties": {
    "hierarchy": [
      "tgn:2757246",
      "tgn:7002659",
      "tgn:1000001",
      "tgn:7012149",
      "tgn:2000027",
      "tgn:7029392"
    ],
    "placetype": [
      "aat:300006191"
    ],
    "id": 2757246,
    "name:xx": "Wessons Lake"
  }
}
