{
  "geometry": {
    "type": "Point",
    "coordinates": [
      33.560429,
      28.390418
    ]
  },
  "type": "Feature",
  "properties": {
    "hierarchy": [
      "tgn:7534544",
      "tgn:7001242",
      "tgn:7016833",
      "tgn:7001336",
      "tgn:7029392"
    ],
    "placetype": [
      "aat:300379998"
    ],
    "name:en": "Ḩibrān, Wādī",
    "id": 7534544
  }
}
