{
  "geometry": {
    "type": "Point",
    "coordinates": [
      32.84691,
      30.72682
    ]
  },
  "type": "Feature",
  "properties": {
    "hierarchy": [
      "tgn:7524390",
      "tgn:7001242",
      "tgn:7016833",
      "tgn:7001335",
      "tgn:7029392"
    ],
    "placetype": [
      "aat:300008750"
    ],
    "id": 7524390,
    "name:xx": "Awghādat al Māshiyah"
  }
}
