{
  "geometry": {
    "type": "Point",
    "coordinates": [
      -75.8167,
      39.2667
    ]
  },
  "type": "Feature",
  "properties": {
    "hierarchy": [
      "tgn:2513575",
      "tgn:1000001",
      "tgn:1002539",
      "tgn:7012149",
      "tgn:7007516",
      "tgn:7029392"
    ],
    "placetype": [
      "aat:300008680"
    ],
    "id": 2513575,
    "name:xx": "Mill Pond"
  }
}
