{
  "geometry": {
    "type": "Point",
    "coordinates": [
      -122.55,
      37.85
    ]
  },
  "type": "Feature",
  "properties": {
    "hierarchy": [
      "tgn:2586008",
      "tgn:1000001",
      "tgn:7012149",
      "tgn:7007157",
      "tgn:7014005",
      "tgn:7029392"
    ],
    "placetype": [
      "aat:300132316"
    ],
    "id": 2586008,
    "name:xx": "Pirates Cove"
  }
}
