{
  "geometry": {
    "type": "Point",
    "coordinates": [
      -78.05,
      33.9833
    ]
  },
  "type": "Feature",
  "properties": {
    "hierarchy": [
      "tgn:2561179",
      "tgn:1000001",
      "tgn:2001472",
      "tgn:7012149",
      "tgn:7007709",
      "tgn:7029392"
    ],
    "placetype": [
      "aat:300008706"
    ],
    "id": 2561179,
    "name:xx": "Orton Creek"
  }
}
