{
  "geometry": {
    "type": "Point",
    "coordinates": [
      -15.9167,
      66.4667
    ]
  },
  "type": "Feature",
  "properties": {
    "hierarchy": [
      "tgn:1042545",
      "tgn:7594017",
      "tgn:1000003",
      "tgn:1000077",
      "tgn:7029392"
    ],
    "placetype": [
      "aat:300008347"
    ],
    "id": 1042545,
    "name:xx": "Raufarhöfn"
  }
}
