{
  "geometry": {
    "type": "Point",
    "coordinates": [
      -70.9333,
      42.2667
    ]
  },
  "type": "Feature",
  "properties": {
    "hierarchy": [
      "tgn:2684491",
      "tgn:1000001",
      "tgn:1002724",
      "tgn:7012149",
      "tgn:7007517",
      "tgn:7029392"
    ],
    "placetype": [
      "aat:300011692"
    ],
    "id": 2684491,
    "name:xx": "Spiers Stand"
  }
}
