{
  "geometry": {
    "type": "Point",
    "coordinates": [
      -83.55,
      34.75
    ]
  },
  "type": "Feature",
  "properties": {
    "hierarchy": [
      "tgn:2269237",
      "tgn:1000001",
      "tgn:7012149",
      "tgn:2000410",
      "tgn:7007248",
      "tgn:7029392"
    ],
    "placetype": [
      "aat:300008706"
    ],
    "id": 2269237,
    "name:xx": "Crow Creek"
  }
}
