{
  "geometry": {
    "type": "Point",
    "coordinates": [
      -117.35,
      46.1167
    ]
  },
  "type": "Feature",
  "properties": {
    "hierarchy": [
      "tgn:2137684",
      "tgn:2002239",
      "tgn:1000001",
      "tgn:7012149",
      "tgn:7007920",
      "tgn:7029392"
    ],
    "placetype": [
      "aat:300008697"
    ],
    "id": 2137684,
    "name:xx": "Arnold Spring"
  }
}
