{
  "geometry": {
    "type": "Point",
    "coordinates": [
      -74.5833,
      45.9833
    ]
  },
  "type": "Feature",
  "properties": {
    "hierarchy": [
      "tgn:1115595",
      "tgn:7005685",
      "tgn:1000001",
      "tgn:7005804",
      "tgn:7029392"
    ],
    "placetype": [
      "aat:300008680"
    ],
    "id": 1115595,
    "name:xx": "Bevin, Lac"
  }
}
