{
  "geometry": {
    "type": "Point",
    "coordinates": [
      79.9945,
      27.2324
    ]
  },
  "type": "Feature",
  "properties": {
    "hierarchy": [
      "tgn:7561868",
      "tgn:1000004",
      "tgn:7000198",
      "tgn:7016722",
      "tgn:7029392"
    ],
    "placetype": [
      "aat:300008347"
    ],
    "name:en": "Durgāganj",
    "id": 7561868
  }
}
