{
  "type": "FeatureCollection",
  "features": [
    {
      "geometry": {
        "type": "Point",
        "coordinates": [
          -86.15,
          -77.5833
        ]
      },
      "type": "Feature",
      "properties": {
        "hierarchy": [
          "tgn:1106854",
          "tgn:1000007",
          "tgn:7029392"
        ],
        "placetype": [
          "aat:300008795"
        ],
        "id": 1106854,
        "name:xx": "Ulmer, Mount"
      }
    },
    {
      "geometry": {
        "type": "Point",
        "coordinates": [
          179.9833,
          -16.9
        ]
      },
      "type": "Feature",
      "properties": {
        "hierarchy": [
          "tgn:1106858",
          "tgn:1009396",
          "tgn:1000914",
          "tgn:7000493",
          "tgn:1000006",
          "tgn:7029392"
        ],
        "placetype": [
          "aat:300008795"
        ],
        "id": 1106858,
        "name:xx": "Uluinggalau"
      }
    }
  ]
}
