{
  "geometry": {
    "type": "Point",
    "coordinates": [
      -43.55,
      -21.9167
    ]
  },
  "type": "Feature",
  "properties": {
    "hierarchy": [
      "tgn:1127322",
      "tgn:7006237",
      "tgn:1000047",
      "tgn:7002457",
      "tgn:1000002",
      "tgn:7029392"
    ],
    "placetype": [
      "aat:300008707"
    ],
    "id": 1127322,
    "name:xx": "Monte Verde"
  }
}
