{
  "geometry": {
    "type": "Point",
    "coordinates": [
      79.75708,
      26.750114
    ]
  },
  "type": "Feature",
  "properties": {
    "hierarchy": [
      "tgn:7566186",
      "tgn:1000004",
      "tgn:7000198",
      "tgn:7016722",
      "tgn:7029392"
    ],
    "placetype": [
      "aat:300008347"
    ],
    "name:en": "Bāmhangaon",
    "id": 7566186
  }
}
