{
  "geometry": {
    "type": "Point",
    "coordinates": [
      106.05,
      34.299
    ]
  },
  "type": "Feature",
  "properties": {
    "hierarchy": [
      "tgn:7030404",
      "tgn:1000004",
      "tgn:1001261",
      "tgn:1000111",
      "tgn:7029392"
    ],
    "placetype": [
      "aat:300387007",
      "aat:300008795"
    ],
    "id": 7030404,
    "name:xx": "Maiji Shan"
  }
}
