{
  "type": "FeatureCollection",
  "features": [
    {
      "geometry": {
        "type": "Point",
        "coordinates": [
          -171.75,
          63.65
        ]
      },
      "type": "Feature",
      "properties": {
        "hierarchy": [
          "tgn:2432000",
          "tgn:7006450",
          "tgn:1000001",
          "tgn:7012149",
          "tgn:2000079",
          "tgn:7029392"
        ],
        "placetype": [
          "aat:300132316"
        ],
        "id": 2432000,
        "name:xx": "Kavalghak Bay"
      }
    },
    {
      "geometry": {
        "type": "Point",
        "coordinates": [
          -115,
          48.25
        ]
      },
      "type": "Feature",
      "properties": {
        "hierarchy": [
          "tgn:2432001",
          "tgn:1000001",
          "tgn:7012149",
          "tgn:2001286",
          "tgn:7007524",
          "tgn:7029392"
        ],
        "placetype": [
          "aat:300008706"
        ],
        "id": 2432001,
        "name:xx": "Kavalla Creek"
      }
    },
    {
      "geometry": {
        "type": "Point",
        "coordinates": [
          -91.2,
          45.95
        ]
      },
      "type": "Feature",
      "properties": {
        "hierarchy": [
          "tgn:2432002",
          "tgn:1000001",
          "tgn:7012149",
          "tgn:2002353",
          "tgn:7007922",
          "tgn:7029392"
        ],
        "placetype": [
          "aat:300132316"
        ],
        "id": 2432002,
        "name:xx": "Kavanagh Bay"
      }
    },
    {
      "geometry": {
        "type": "Point",
        "coordinates": [
          -78.75,
          41.85
        ]
      },
      "type": "Feature",
      "properties": {
        "hierarchy": [
          "tgn:2432003",
          "tgn:1000001",
          "tgn:7012149",
          "tgn:7016020",
          "tgn:7007710",
          "tgn:7029392"
        ],
        "placetype": [
          "aat:300008699"
        ],
        "id": 2432003,
        "name:xx": "Kavanaugh Branch"
      }
    },
    {
      "geometry": {
        "type": "Point",
        "coordinates": [
          -121.05,
          35.8
        ]
      },
      "type": "Feature",
      "properties": {
        "hierarchy": [
          "tgn:2432004",
          "tgn:1000001",
          "tgn:7012149",
          "tgn:7007157",
          "tgn:7029392"
        ],
        "placetype": [
          "aat:300008706"
        ],
        "id": 2432004,
        "name:xx": "Kavanaugh Creek"
      }
    },
    {
      "geometry": {
        "type": "Point",
        "coordinates": [
          -116.9333,
          48.3
        ]
      },
      "type": "Feature",
      "properties": {
        "hierarchy": [
          "tgn:2432005",
          "tgn:1000001",
          "tgn:2000460",
          "tgn:7012149",
          "tgn:7007250",
          "tgn:7029392"
        ],
        "placetype": [
          "aat:300008706"
        ],
        "id": 2432005,
        "name:xx": "Kavanaugh Creek"
      }
    },
    {
      "geometry": {
        "type": "Point",
        "coordinates": [
          -110.5667,
          46.2
        ]
      },
      "type": "Feature",
      "properties": {
        "hierarchy": [
          "tgn:2432006",
          "tgn:1000001",
          "tgn:7012149",
          "tgn:7007524",
          "tgn:7029392"
        ],
        "placetype": [
          "aat:300008706"
        ],
        "id": 2432006,
        "name:xx": "Kavanaugh Creek"
      }
    },
    {
      "geometry": {
        "type": "Point",
        "coordinates": [
          -73.2333,
          41.5833
        ]
      },
      "type": "Feature",
      "properties": {
        "hierarchy": [
          "tgn:2432007",
          "tgn:1000001",
          "tgn:1002601",
          "tgn:7012149",
          "tgn:7007159",
          "tgn:7029392"
        ],
        "placetype": [
          "aat:300008798"
        ],
        "id": 2432007,
        "name:xx": "Kavanaugh Hill"
      }
    },
    {
      "geometry": {
        "type": "Point",
        "coordinates": [
          -110.65,
          46.1
        ]
      },
      "type": "Feature",
      "properties": {
        "hierarchy": [
          "tgn:2432008",
          "tgn:1000001",
          "tgn:7012149",
          "tgn:2001293",
          "tgn:7007524",
          "tgn:7029392"
        ],
        "placetype": [
          "aat:300008697"
        ],
        "id": 2432008,
        "name:xx": "Kavanaugh Hills"
      }
    },
    {
      "geometry": {
        "type": "Point",
        "coordinates": [
          -78.0833,
          41.7833
        ]
      },
      "type": "Feature",
      "properties": {
        "hierarchy": [
          "tgn:2432009",
          "tgn:1000001",
          "tgn:7012149",
          "tgn:1002800",
          "tgn:7007710",
          "tgn:7029392"
        ],
        "placetype": [
          "aat:300008761"
        ],
        "id": 2432009,
        "name:xx": "Kavanaugh Hollow"
      }
    }
  ]
}
