{
  "geometry": {
    "type": "Point",
    "coordinates": [
      -91.5333,
      40.2167
    ]
  },
  "type": "Feature",
  "properties": {
    "hierarchy": [
      "tgn:2202686",
      "tgn:1000001",
      "tgn:7012149",
      "tgn:1002592",
      "tgn:7007523",
      "tgn:7029392"
    ],
    "placetype": [
      "aat:300006191"
    ],
    "id": 2202686,
    "name:xx": "Buck-Doe Run Watershed Lake Number 25"
  }
}
