{
  "geometry": {
    "type": "Point",
    "coordinates": [
      100.5833,
      26.0167
    ]
  },
  "type": "Feature",
  "properties": {
    "hierarchy": [
      "tgn:1070841",
      "tgn:1000004",
      "tgn:7018118",
      "tgn:1000111",
      "tgn:7029392"
    ],
    "placetype": [
      "aat:300008347"
    ],
    "id": 1070841,
    "name:xx": "Pianjiao"
  }
}
