{
  "geometry": {
    "type": "Point",
    "coordinates": [
      63.5667,
      39.0167
    ]
  },
  "type": "Feature",
  "properties": {
    "hierarchy": [
      "tgn:1055558",
      "tgn:7012220",
      "tgn:1000004",
      "tgn:7006659",
      "tgn:7029392"
    ],
    "placetype": [
      "aat:300008347"
    ],
    "id": 1055558,
    "name:xx": "Komsomolsk"
  }
}
