{
  "geometry": {
    "type": "Point",
    "coordinates": [
      -80.8667,
      37.9167
    ]
  },
  "type": "Feature",
  "properties": {
    "hierarchy": [
      "tgn:2672426",
      "tgn:1000001",
      "tgn:2002261",
      "tgn:7012149",
      "tgn:7013961",
      "tgn:7029392"
    ],
    "placetype": [
      "aat:300008699"
    ],
    "id": 2672426,
    "name:xx": "Smoky Branch"
  }
}
