{
  "geometry": {
    "type": "Point",
    "coordinates": [
      120.9223,
      23.9261
    ]
  },
  "type": "Feature",
  "properties": {
    "hierarchy": [
      "tgn:7477616",
      "tgn:7488858",
      "tgn:1000004",
      "tgn:1000141",
      "tgn:7029392"
    ],
    "placetype": [
      "aat:300007899"
    ],
    "id": 7477616,
    "name:xx": "Dayan Suidao"
  }
}
