{
  "geometry": {
    "type": "Point",
    "coordinates": [
      3.199,
      10.161
    ]
  },
  "type": "Feature",
  "properties": {
    "hierarchy": [
      "tgn:7593733",
      "tgn:7001242",
      "tgn:1000533",
      "tgn:1000160",
      "tgn:7029392"
    ],
    "placetype": [
      "aat:300008347"
    ],
    "id": 7593733,
    "name:xx": "Guénébé"
  }
}
