{
  "geometry": {
    "type": "Point",
    "coordinates": [
      -83.6333,
      31.6667
    ]
  },
  "type": "Feature",
  "properties": {
    "hierarchy": [
      "tgn:2024459",
      "tgn:1000001",
      "tgn:7012149",
      "tgn:2000433",
      "tgn:7007248",
      "tgn:7029392"
    ],
    "placetype": [
      "aat:300008347"
    ],
    "id": 2024459,
    "name:xx": "Sycamore"
  }
}
