{
  "type": "FeatureCollection",
  "features": [
    {
      "geometry": {
        "type": "Point",
        "coordinates": [
          -115.6333,
          33.1
        ]
      },
      "type": "Feature",
      "properties": {
        "hierarchy": [
          "tgn:2718290",
          "tgn:1000001",
          "tgn:7012149",
          "tgn:2000182",
          "tgn:7007157",
          "tgn:7029392"
        ],
        "placetype": [
          "aat:300006075"
        ],
        "id": 2718290,
        "name:xx": "Thompson Drain"
      }
    },
    {
      "geometry": {
        "type": "Point",
        "coordinates": [
          -83.9333,
          43.0167
        ]
      },
      "type": "Feature",
      "properties": {
        "hierarchy": [
          "tgn:2718291",
          "tgn:1000001",
          "tgn:7012149",
          "tgn:1002892",
          "tgn:7007520",
          "tgn:7029392"
        ],
        "placetype": [
          "aat:300006075"
        ],
        "id": 2718291,
        "name:xx": "Thompson Drain"
      }
    },
    {
      "geometry": {
        "type": "Point",
        "coordinates": [
          -82.4667,
          43.05
        ]
      },
      "type": "Feature",
      "properties": {
        "hierarchy": [
          "tgn:2718292",
          "tgn:1000001",
          "tgn:7012149",
          "tgn:7016056",
          "tgn:7007520",
          "tgn:7029392"
        ],
        "placetype": [
          "aat:300006075"
        ],
        "id": 2718292,
        "name:xx": "Thompson Drain"
      }
    },
    {
      "geometry": {
        "type": "Point",
        "coordinates": [
          -82.7833,
          43.5333
        ]
      },
      "type": "Feature",
      "properties": {
        "hierarchy": [
          "tgn:2718293",
          "tgn:1000001",
          "tgn:7012149",
          "tgn:2000995",
          "tgn:7007520",
          "tgn:7029392"
        ],
        "placetype": [
          "aat:300006075"
        ],
        "id": 2718293,
        "name:xx": "Thompson Drain"
      }
    },
    {
      "geometry": {
        "type": "Point",
        "coordinates": [
          -83.1667,
          43.9167
        ]
      },
      "type": "Feature",
      "properties": {
        "hierarchy": [
          "tgn:2718294",
          "tgn:1000001",
          "tgn:7012149",
          "tgn:2000964",
          "tgn:7007520",
          "tgn:7029392"
        ],
        "placetype": [
          "aat:300006075"
        ],
        "id": 2718294,
        "name:xx": "Thompson Drain"
      }
    },
    {
      "geometry": {
        "type": "Point",
        "coordinates": [
          -84.3333,
          43.9167
        ]
      },
      "type": "Feature",
      "properties": {
        "hierarchy": [
          "tgn:2718295",
          "tgn:1000001",
          "tgn:7012149",
          "tgn:2000959",
          "tgn:7007520",
          "tgn:7029392"
        ],
        "placetype": [
          "aat:300006075"
        ],
        "id": 2718295,
        "name:xx": "Thompson Drain"
      }
    },
    {
      "geometry": {
        "type": "Point",
        "coordinates": [
          -82.8333,
          43.1
        ]
      },
      "type": "Feature",
      "properties": {
        "hierarchy": [
          "tgn:2718296",
          "tgn:1000001",
          "tgn:7012149",
          "tgn:7016056",
          "tgn:7007520",
          "tgn:7029392"
        ],
        "placetype": [
          "aat:300008699"
        ],
        "id": 2718296,
        "name:xx": "Thompson Drain"
      }
    },
    {
      "geometry": {
        "type": "Point",
        "coordinates": [
          -111.35,
          34.1667
        ]
      },
      "type": "Feature",
      "properties": {
        "hierarchy": [
          "tgn:2718297",
          "tgn:1000001",
          "tgn:7006451",
          "tgn:2000093",
          "tgn:7012149",
          "tgn:7029392"
        ],
        "placetype": [
          "aat:300008761"
        ],
        "id": 2718297,
        "name:xx": "Thompson Draw"
      }
    },
    {
      "geometry": {
        "type": "Point",
        "coordinates": [
          -108.9333,
          32.6
        ]
      },
      "type": "Feature",
      "properties": {
        "hierarchy": [
          "tgn:2718298",
          "tgn:1000001",
          "tgn:7012149",
          "tgn:7029392"
        ],
        "placetype": [
          "aat:300008761"
        ],
        "id": 2718298,
        "name:xx": "Thompson Draw"
      }
    },
    {
      "geometry": {
        "type": "Point",
        "coordinates": [
          -108.6,
          40.5333
        ]
      },
      "type": "Feature",
      "properties": {
        "hierarchy": [
          "tgn:2718299",
          "tgn:1000001",
          "tgn:7012149",
          "tgn:2000232",
          "tgn:7007158",
          "tgn:7029392"
        ],
        "placetype": [
          "aat:300008761"
        ],
        "id": 2718299,
        "name:xx": "Thompson Draw"
      }
    }
  ]
}
