{
  "geometry": {
    "type": "Point",
    "coordinates": [
      2.3667,
      49.0333
    ]
  },
  "type": "Feature",
  "properties": {
    "hierarchy": [
      "tgn:1031676",
      "tgn:1000003",
      "tgn:7002883",
      "tgn:1000070",
      "tgn:7029392"
    ],
    "placetype": [
      "aat:300008347"
    ],
    "id": 1031676,
    "name:xx": "Ézanville"
  }
}
