{
  "geometry": {
    "type": "Point",
    "coordinates": [
      -94.5667,
      29.8833
    ]
  },
  "type": "Feature",
  "properties": {
    "hierarchy": [
      "tgn:2268331",
      "tgn:1000001",
      "tgn:7012149",
      "tgn:7007826",
      "tgn:7029392"
    ],
    "placetype": [
      "aat:300008905"
    ],
    "id": 2268331,
    "name:xx": "Crooked Marsh"
  }
}
