{
  "geometry": {
    "type": "Point",
    "coordinates": [
      -81.8833,
      38.0667
    ]
  },
  "type": "Feature",
  "properties": {
    "hierarchy": [
      "tgn:2168842",
      "tgn:1000001",
      "tgn:7012149",
      "tgn:7013961",
      "tgn:7029392"
    ],
    "placetype": [
      "aat:300008706"
    ],
    "id": 2168842,
    "name:xx": "Big Horse Creek"
  }
}
