{
  "geometry": {
    "type": "Point",
    "coordinates": [
      -67.7667,
      44.55
    ]
  },
  "type": "Feature",
  "properties": {
    "hierarchy": [
      "tgn:2606719",
      "tgn:1000001",
      "tgn:7012149",
      "tgn:7014589",
      "tgn:7007515",
      "tgn:7029392"
    ],
    "placetype": [
      "aat:300132316"
    ],
    "id": 2606719,
    "name:xx": "Ramsdell Cove"
  }
}
