{
  "geometry": {
    "type": "Point",
    "coordinates": [
      79.083333,
      11.616667
    ]
  },
  "type": "Feature",
  "properties": {
    "hierarchy": [
      "tgn:7547351",
      "tgn:1000004",
      "tgn:7000198",
      "tgn:7001797",
      "tgn:7029392"
    ],
    "placetype": [
      "aat:300007783"
    ],
    "name:en": "Asakalattūr",
    "id": 7547351
  }
}
