{
  "geometry": {
    "type": "Point",
    "coordinates": [
      -100.4167,
      33.9667
    ]
  },
  "type": "Feature",
  "properties": {
    "hierarchy": [
      "tgn:2216872",
      "tgn:1000001",
      "tgn:7012149",
      "tgn:2001965",
      "tgn:7007826",
      "tgn:7029392"
    ],
    "placetype": [
      "aat:300008706"
    ],
    "id": 2216872,
    "name:xx": "Camp Hollow Creek"
  }
}
