{
  "type": "FeatureCollection",
  "features": [
    {
      "geometry": {
        "type": "Point",
        "coordinates": [
          -111.4667,
          40.5
        ]
      },
      "type": "Feature",
      "properties": {
        "hierarchy": [
          "tgn:2109070",
          "tgn:1000001",
          "tgn:7012149",
          "tgn:2002126",
          "tgn:7007827",
          "tgn:7029392"
        ],
        "placetype": [
          "aat:300008347"
        ],
        "id": 2109070,
        "name:xx": "Midway"
      }
    },
    {
      "geometry": {
        "type": "Point",
        "coordinates": [
          -111.4167,
          39.7
        ]
      },
      "type": "Feature",
      "properties": {
        "hierarchy": [
          "tgn:2109071",
          "tgn:1000001",
          "tgn:7012149",
          "tgn:2002120",
          "tgn:7007827",
          "tgn:7029392"
        ],
        "placetype": [
          "aat:300008347",
          "aat:300387210"
        ],
        "id": 2109071,
        "name:xx": "Milburn"
      }
    },
    {
      "geometry": {
        "type": "Point",
        "coordinates": [
          -113,
          38.3833
        ]
      },
      "type": "Feature",
      "properties": {
        "hierarchy": [
          "tgn:2109072",
          "tgn:2002101",
          "tgn:1000001",
          "tgn:7012149",
          "tgn:7007827",
          "tgn:7029392"
        ],
        "placetype": [
          "aat:300008347"
        ],
        "id": 2109072,
        "name:xx": "Milford"
      }
    },
    {
      "geometry": {
        "type": "Point",
        "coordinates": [
          -111.8,
          40.7
        ]
      },
      "type": "Feature",
      "properties": {
        "hierarchy": [
          "tgn:2109073",
          "tgn:1000001",
          "tgn:7012149",
          "tgn:2002118",
          "tgn:7007827",
          "tgn:7029392"
        ],
        "placetype": [
          "aat:300008347"
        ],
        "id": 2109073,
        "name:xx": "East Millcreek"
      }
    },
    {
      "geometry": {
        "type": "Point",
        "coordinates": [
          -112.0167,
          39.4667
        ]
      },
      "type": "Feature",
      "properties": {
        "hierarchy": [
          "tgn:2109075",
          "tgn:1000001",
          "tgn:7012149",
          "tgn:2002112",
          "tgn:7007827",
          "tgn:7029392"
        ],
        "placetype": [
          "aat:300008347",
          "aat:300387210"
        ],
        "id": 2109075,
        "name:xx": "Mills"
      }
    },
    {
      "geometry": {
        "type": "Point",
        "coordinates": [
          -111.8167,
          41.6667
        ]
      },
      "type": "Feature",
      "properties": {
        "hierarchy": [
          "tgn:2109076",
          "tgn:1000001",
          "tgn:2002103",
          "tgn:7012149",
          "tgn:7007827",
          "tgn:7029392"
        ],
        "placetype": [
          "aat:300008347"
        ],
        "id": 2109076,
        "name:xx": "Millville"
      }
    },
    {
      "geometry": {
        "type": "Point",
        "coordinates": [
          -111.7167,
          41.05
        ]
      },
      "type": "Feature",
      "properties": {
        "hierarchy": [
          "tgn:2109077",
          "tgn:1000001",
          "tgn:7012149",
          "tgn:2002115",
          "tgn:7007827",
          "tgn:7029392"
        ],
        "placetype": [
          "aat:300008347"
        ],
        "id": 2109077,
        "name:xx": "Milton"
      }
    },
    {
      "geometry": {
        "type": "Point",
        "coordinates": [
          -112.9167,
          38.2
        ]
      },
      "type": "Feature",
      "properties": {
        "hierarchy": [
          "tgn:2109078",
          "tgn:2002101",
          "tgn:1000001",
          "tgn:7012149",
          "tgn:7007827",
          "tgn:7029392"
        ],
        "placetype": [
          "aat:300008347"
        ],
        "id": 2109078,
        "name:xx": "Minersville"
      }
    },
    {
      "geometry": {
        "type": "Point",
        "coordinates": [
          -109.5333,
          38.5667
        ]
      },
      "type": "Feature",
      "properties": {
        "hierarchy": [
          "tgn:2109079",
          "tgn:1000001",
          "tgn:7012149",
          "tgn:2002110",
          "tgn:7007827",
          "tgn:7029392"
        ],
        "placetype": [
          "aat:300008347"
        ],
        "id": 2109079,
        "name:xx": "Moab"
      }
    }
  ]
}
