{
  "geometry": {
    "type": "Point",
    "coordinates": [
      -106.3167,
      39.8667
    ]
  },
  "type": "Feature",
  "properties": {
    "hierarchy": [
      "tgn:2364094",
      "tgn:1000001",
      "tgn:7012149",
      "tgn:7007158",
      "tgn:2000250",
      "tgn:7029392"
    ],
    "placetype": [
      "aat:300006191"
    ],
    "id": 2364094,
    "name:xx": "Green Mountain Reservoir"
  }
}
