{
  "geometry": {
    "type": "Point",
    "coordinates": [
      -122.8667,
      46.0667
    ]
  },
  "type": "Feature",
  "properties": {
    "hierarchy": [
      "tgn:2259190",
      "tgn:1000001",
      "tgn:1002305",
      "tgn:7012149",
      "tgn:7007920",
      "tgn:7029392"
    ],
    "placetype": [
      "aat:300008791"
    ],
    "id": 2259190,
    "name:xx": "Cottonwood Island"
  }
}
