{
  "geometry": {
    "type": "Point",
    "coordinates": [
      -110.9333,
      41.35
    ]
  },
  "type": "Feature",
  "properties": {
    "hierarchy": [
      "tgn:2296514",
      "tgn:1000001",
      "tgn:7012149",
      "tgn:2002385",
      "tgn:7007923",
      "tgn:7029392"
    ],
    "placetype": [
      "aat:300008761"
    ],
    "id": 2296514,
    "name:xx": "Dry Canyon"
  }
}
