{
  "geometry": {
    "type": "Point",
    "coordinates": [
      31.241,
      30.105
    ]
  },
  "type": "Feature",
  "properties": {
    "hierarchy": [
      "tgn:1135950",
      "tgn:7001242",
      "tgn:7016833",
      "tgn:7029392"
    ],
    "placetype": [
      "aat:300006075"
    ],
    "id": 1135950,
    "name:xx": "Tur'at al Ismā'īlīyah"
  }
}
