{
  "geometry": {
    "type": "Point",
    "coordinates": [
      -97.0667,
      45.4667
    ]
  },
  "type": "Feature",
  "properties": {
    "hierarchy": [
      "tgn:2167334",
      "tgn:1000001",
      "tgn:7012149",
      "tgn:2001824",
      "tgn:7007713",
      "tgn:7029392"
    ],
    "placetype": [
      "aat:300008761"
    ],
    "id": 2167334,
    "name:xx": "Big Coulee"
  }
}
