{
  "geometry": {
    "type": "Point",
    "coordinates": [
      -106.3167,
      44.1667
    ]
  },
  "type": "Feature",
  "properties": {
    "hierarchy": [
      "tgn:2588104",
      "tgn:1000001",
      "tgn:7012149",
      "tgn:2002374",
      "tgn:7007923",
      "tgn:7029392"
    ],
    "placetype": [
      "aat:300008680"
    ],
    "id": 2588104,
    "name:xx": "Ploessers Dry Lake"
  }
}
