{
  "geometry": {
    "type": "Point",
    "coordinates": [
      -98.3833,
      26.3167
    ]
  },
  "type": "Feature",
  "properties": {
    "hierarchy": [
      "tgn:2388694",
      "tgn:1000001",
      "tgn:7012149",
      "tgn:2002002",
      "tgn:7007826",
      "tgn:7029392"
    ],
    "placetype": [
      "aat:300008178"
    ],
    "id": 2388694,
    "name:xx": "Hidalgo County Water District Number 16"
  }
}
