{
  "geometry": {
    "type": "Point",
    "coordinates": [
      30.85,
      27.366667
    ]
  },
  "type": "Feature",
  "properties": {
    "hierarchy": [
      "tgn:7538464",
      "tgn:7001242",
      "tgn:7016833",
      "tgn:1001114",
      "tgn:7029392"
    ],
    "placetype": [
      "aat:300343519"
    ],
    "name:en": "Muḩarraq, Ḩawḑ al",
    "id": 7538464
  }
}
