{
  "type": "FeatureCollection",
  "features": [
    {
      "geometry": {
        "type": "Point",
        "coordinates": [
          30.95,
          61.9833
        ]
      },
      "type": "Feature",
      "properties": {
        "hierarchy": [
          "tgn:1116730",
          "tgn:1000004",
          "tgn:7011509",
          "tgn:7002435",
          "tgn:7029392"
        ],
        "placetype": [
          "aat:300008680"
        ],
        "id": 1116730,
        "name:xx": "Yanisyarvi, Ozero"
      }
    },
    {
      "geometry": {
        "type": "Point",
        "coordinates": [
          -62.35,
          -5
        ]
      },
      "type": "Feature",
      "properties": {
        "hierarchy": [
          "tgn:1116731",
          "tgn:1000002",
          "tgn:7029392"
        ],
        "placetype": [
          "aat:300008680"
        ],
        "id": 1116731,
        "name:xx": "Jari, Lago"
      }
    },
    {
      "geometry": {
        "type": "Point",
        "coordinates": [
          105.6667,
          39.75
        ]
      },
      "type": "Feature",
      "properties": {
        "hierarchy": [
          "tgn:1116732",
          "tgn:1000004",
          "tgn:7001838",
          "tgn:1000111",
          "tgn:7029392"
        ],
        "placetype": [
          "aat:300008680"
        ],
        "id": 1116732,
        "name:xx": "Jartai Yanchi"
      }
    },
    {
      "geometry": {
        "type": "Point",
        "coordinates": [
          -118,
          53.1167
        ]
      },
      "type": "Feature",
      "properties": {
        "hierarchy": [
          "tgn:1116733",
          "tgn:7005694",
          "tgn:7005685",
          "tgn:1000001",
          "tgn:7029392"
        ],
        "placetype": [
          "aat:300008680"
        ],
        "id": 1116733,
        "name:xx": "Jasper Lake"
      }
    },
    {
      "geometry": {
        "type": "Point",
        "coordinates": [
          -81.2,
          28.7167
        ]
      },
      "type": "Feature",
      "properties": {
        "hierarchy": [
          "tgn:1116735",
          "tgn:1000001",
          "tgn:7012149",
          "tgn:1002881",
          "tgn:7007240",
          "tgn:7029392"
        ],
        "placetype": [
          "aat:300008680"
        ],
        "id": 1116735,
        "name:xx": "Jesup, Lake"
      }
    },
    {
      "geometry": {
        "type": "Point",
        "coordinates": [
          -104.65,
          56.15
        ]
      },
      "type": "Feature",
      "properties": {
        "hierarchy": [
          "tgn:1116736",
          "tgn:7005685",
          "tgn:1000001",
          "tgn:7005805",
          "tgn:7029392"
        ],
        "placetype": [
          "aat:300008680"
        ],
        "id": 1116736,
        "name:xx": "Jewett Lake"
      }
    },
    {
      "geometry": {
        "type": "Point",
        "coordinates": [
          87.3333,
          47
        ]
      },
      "type": "Feature",
      "properties": {
        "hierarchy": [
          "tgn:1116739",
          "tgn:1000004",
          "tgn:7001745",
          "tgn:1000111",
          "tgn:7029392"
        ],
        "placetype": [
          "aat:300008680"
        ],
        "id": 1116739,
        "name:xx": "Jili Hu"
      }
    }
  ]
}
