{
  "geometry": {
    "type": "Point",
    "coordinates": [
      -81.7833,
      36.5667
    ]
  },
  "type": "Feature",
  "properties": {
    "hierarchy": [
      "tgn:2710953",
      "tgn:1000001",
      "tgn:7012149",
      "tgn:2001882",
      "tgn:7007825",
      "tgn:7029392"
    ],
    "placetype": [
      "aat:300008761"
    ],
    "id": 2710953,
    "name:xx": "Tank Hollow"
  }
}
