{
  "geometry": {
    "type": "Point",
    "coordinates": [
      -115.7167,
      42.2833
    ]
  },
  "type": "Feature",
  "properties": {
    "hierarchy": [
      "tgn:2467875",
      "tgn:1000001",
      "tgn:7012149",
      "tgn:2000488",
      "tgn:7007250",
      "tgn:7029392"
    ],
    "placetype": [
      "aat:300008680"
    ],
    "id": 2467875,
    "name:xx": "Long Lake"
  }
}
