{
  "geometry": {
    "type": "Point",
    "coordinates": [
      120.6466,
      23.9701
    ]
  },
  "type": "Feature",
  "properties": {
    "hierarchy": [
      "tgn:7495049",
      "tgn:7488858",
      "tgn:1000004",
      "tgn:1000141",
      "tgn:7029392"
    ],
    "placetype": [
      "aat:300007836"
    ],
    "id": 7495049,
    "name:xx": "Xitou Qiao"
  }
}
