{
  "geometry": {
    "type": "Point",
    "coordinates": [
      -108.35,
      38.7333
    ]
  },
  "type": "Feature",
  "properties": {
    "hierarchy": [
      "tgn:2448029",
      "tgn:1000001",
      "tgn:7012149",
      "tgn:7007158",
      "tgn:7029392"
    ],
    "placetype": [
      "aat:300008761"
    ],
    "id": 2448029,
    "name:xx": "Lightening Basin"
  }
}
