{
  "geometry": {
    "type": "Point",
    "coordinates": [
      5.8333,
      44.2667
    ]
  },
  "type": "Feature",
  "properties": {
    "hierarchy": [
      "tgn:1126568",
      "tgn:1000003",
      "tgn:1000070",
      "tgn:7029392"
    ],
    "placetype": [
      "aat:300008707"
    ],
    "id": 1126568,
    "name:xx": "Méouge, Torrent la"
  }
}
