{
  "geometry": {
    "type": "Point",
    "coordinates": [
      120.73,
      24.42
    ]
  },
  "type": "Feature",
  "properties": {
    "hierarchy": [
      "tgn:7483417",
      "tgn:7487020",
      "tgn:1000004",
      "tgn:1000141",
      "tgn:7029392"
    ],
    "placetype": [
      "aat:300007836"
    ],
    "id": 7483417,
    "name:xx": "Fuxing Qiao"
  }
}
