{
  "geometry": {
    "type": "Point",
    "coordinates": [
      -97.65,
      31.7833
    ]
  },
  "type": "Feature",
  "properties": {
    "hierarchy": [
      "tgn:2166260",
      "tgn:1000001",
      "tgn:1002191",
      "tgn:7012149",
      "tgn:7007826",
      "tgn:7029392"
    ],
    "placetype": [
      "aat:300008798"
    ],
    "id": 2166260,
    "name:xx": "Big Bee Mountain"
  }
}
