{
  "geometry": {
    "type": "Point",
    "coordinates": [
      87.1667,
      24.1667
    ]
  },
  "type": "Feature",
  "properties": {
    "hierarchy": [
      "tgn:1101088",
      "tgn:1000004",
      "tgn:7000198",
      "tgn:7031783",
      "tgn:7029392"
    ],
    "placetype": [
      "aat:300006084"
    ],
    "id": 1101088,
    "name:xx": "Canada Dam"
  }
}
