{
  "type": "FeatureCollection",
  "features": [
    {
      "geometry": {
        "type": "Point",
        "coordinates": [
          -91.1333,
          36.2333
        ]
      },
      "type": "Feature",
      "properties": {
        "hierarchy": [
          "tgn:2228240",
          "tgn:1000001",
          "tgn:7016172",
          "tgn:7012149",
          "tgn:2000165",
          "tgn:7029392"
        ],
        "placetype": [
          "aat:300008706"
        ],
        "id": 2228240,
        "name:xx": "Cedar Creek"
      }
    },
    {
      "geometry": {
        "type": "Point",
        "coordinates": [
          -93.9167,
          36.3833
        ]
      },
      "type": "Feature",
      "properties": {
        "hierarchy": [
          "tgn:2228241",
          "tgn:1000001",
          "tgn:2000108",
          "tgn:7016172",
          "tgn:7012149",
          "tgn:7029392"
        ],
        "placetype": [
          "aat:300008706"
        ],
        "id": 2228241,
        "name:xx": "Cedar Creek"
      }
    },
    {
      "geometry": {
        "type": "Point",
        "coordinates": [
          -93.1167,
          36.45
        ]
      },
      "type": "Feature",
      "properties": {
        "hierarchy": [
          "tgn:2228242",
          "tgn:1000001",
          "tgn:7016172",
          "tgn:2000109",
          "tgn:7012149",
          "tgn:7029392"
        ],
        "placetype": [
          "aat:300008706"
        ],
        "id": 2228242,
        "name:xx": "Cedar Creek"
      }
    },
    {
      "geometry": {
        "type": "Point",
        "coordinates": [
          -93.1167,
          35.3667
        ]
      },
      "type": "Feature",
      "properties": {
        "hierarchy": [
          "tgn:2228243",
          "tgn:1000001",
          "tgn:7016172",
          "tgn:7012149",
          "tgn:2000162",
          "tgn:7029392"
        ],
        "placetype": [
          "aat:300008706"
        ],
        "id": 2228243,
        "name:xx": "Cedar Creek"
      }
    },
    {
      "geometry": {
        "type": "Point",
        "coordinates": [
          -118.8,
          36.55
        ]
      },
      "type": "Feature",
      "properties": {
        "hierarchy": [
          "tgn:2228244",
          "tgn:1000001",
          "tgn:7012149",
          "tgn:7007157",
          "tgn:1002956",
          "tgn:7029392"
        ],
        "placetype": [
          "aat:300008706"
        ],
        "id": 2228244,
        "name:xx": "Cedar Creek"
      }
    },
    {
      "geometry": {
        "type": "Point",
        "coordinates": [
          -121.35,
          37.1
        ]
      },
      "type": "Feature",
      "properties": {
        "hierarchy": [
          "tgn:2228245",
          "tgn:1000001",
          "tgn:7012149",
          "tgn:7007157",
          "tgn:7014475",
          "tgn:7029392"
        ],
        "placetype": [
          "aat:300008706"
        ],
        "id": 2228245,
        "name:xx": "Cedar Creek"
      }
    },
    {
      "geometry": {
        "type": "Point",
        "coordinates": [
          -123.1167,
          38.6333
        ]
      },
      "type": "Feature",
      "properties": {
        "hierarchy": [
          "tgn:2228246",
          "tgn:1000001",
          "tgn:7012149",
          "tgn:7007157",
          "tgn:7014516",
          "tgn:7029392"
        ],
        "placetype": [
          "aat:300008706"
        ],
        "id": 2228246,
        "name:xx": "Cedar Creek"
      }
    },
    {
      "geometry": {
        "type": "Point",
        "coordinates": [
          -120.3167,
          39.2833
        ]
      },
      "type": "Feature",
      "properties": {
        "hierarchy": [
          "tgn:2228247",
          "tgn:1000001",
          "tgn:7012149",
          "tgn:7007157",
          "tgn:1002791",
          "tgn:7029392"
        ],
        "placetype": [
          "aat:300008706"
        ],
        "id": 2228247,
        "name:xx": "Cedar Creek"
      }
    },
    {
      "geometry": {
        "type": "Point",
        "coordinates": [
          -123.0667,
          39.4167
        ]
      },
      "type": "Feature",
      "properties": {
        "hierarchy": [
          "tgn:2228248",
          "tgn:1000001",
          "tgn:7012149",
          "tgn:7007157",
          "tgn:1002566",
          "tgn:7029392"
        ],
        "placetype": [
          "aat:300008706"
        ],
        "id": 2228248,
        "name:xx": "Cedar Creek"
      }
    },
    {
      "geometry": {
        "type": "Point",
        "coordinates": [
          -120.6167,
          39.8333
        ]
      },
      "type": "Feature",
      "properties": {
        "hierarchy": [
          "tgn:2228249",
          "tgn:1000001",
          "tgn:7012149",
          "tgn:7007157",
          "tgn:2000187",
          "tgn:7029392"
        ],
        "placetype": [
          "aat:300008706"
        ],
        "id": 2228249,
        "name:xx": "Cedar Creek"
      }
    }
  ]
}
