{
  "geometry": {
    "type": "Point",
    "coordinates": [
      29.602366,
      30.399088
    ]
  },
  "type": "Feature",
  "properties": {
    "hierarchy": [
      "tgn:7539043",
      "tgn:7001242",
      "tgn:7016833",
      "tgn:1001418",
      "tgn:7029392"
    ],
    "placetype": [
      "aat:300008777"
    ],
    "name:en": "Sadd, Qārat as",
    "id": 7539043
  }
}
