{
  "geometry": {
    "type": "Point",
    "coordinates": [
      7.45,
      53.15
    ]
  },
  "type": "Feature",
  "properties": {
    "hierarchy": [
      "tgn:7140653",
      "tgn:1000003",
      "tgn:7003676",
      "tgn:7000084",
      "tgn:7029392"
    ],
    "placetype": [
      "aat:300008347"
    ],
    "id": 7140653,
    "name:xx": "Lütjewolde"
  }
}
