{
  "geometry": {
    "type": "Point",
    "coordinates": [
      -114.1167,
      34.15
    ]
  },
  "type": "Feature",
  "properties": {
    "hierarchy": [
      "tgn:2489949",
      "tgn:1000001",
      "tgn:7006451",
      "tgn:7012149",
      "tgn:2000104",
      "tgn:7029392"
    ],
    "placetype": [
      "aat:300000390"
    ],
    "id": 2489949,
    "name:xx": "Mammon Mine"
  }
}
