{
  "geometry": {
    "type": "Point",
    "coordinates": [
      -80.8167,
      35.3667
    ]
  },
  "type": "Feature",
  "properties": {
    "hierarchy": [
      "tgn:2218623",
      "tgn:1000001",
      "tgn:7012149",
      "tgn:7014021",
      "tgn:7007709",
      "tgn:7029392"
    ],
    "placetype": [
      "aat:300008706"
    ],
    "id": 2218623,
    "name:xx": "Cane Creek"
  }
}
