{
  "geometry": {
    "type": "Point",
    "coordinates": [
      -85.9667,
      35.0167
    ]
  },
  "type": "Feature",
  "properties": {
    "hierarchy": [
      "tgn:2454321",
      "tgn:1000001",
      "tgn:7012149",
      "tgn:2001862",
      "tgn:7007825",
      "tgn:7029392"
    ],
    "placetype": [
      "aat:300008746"
    ],
    "id": 2454321,
    "name:xx": "Little Crow Creek Cave"
  }
}
