{
  "geometry": {
    "type": "Point",
    "coordinates": [
      -82.0833,
      37.3333
    ]
  },
  "type": "Feature",
  "properties": {
    "hierarchy": [
      "tgn:2477134",
      "tgn:1000001",
      "tgn:2002148",
      "tgn:7012149",
      "tgn:7007919",
      "tgn:7029392"
    ],
    "placetype": [
      "aat:300008706"
    ],
    "id": 2477134,
    "name:xx": "Lynn Camp Creek"
  }
}
