{
  "geometry": {
    "type": "Point",
    "coordinates": [
      -112.7167,
      45.9333
    ]
  },
  "type": "Feature",
  "properties": {
    "hierarchy": [
      "tgn:2703969",
      "tgn:1000001",
      "tgn:7012149",
      "tgn:2001306",
      "tgn:7007524",
      "tgn:7029392"
    ],
    "placetype": [
      "aat:300266640"
    ],
    "id": 2703969,
    "name:xx": "Sunday Ridge"
  }
}
