{
  "geometry": {
    "type": "Point",
    "coordinates": [
      -83.45,
      39.8167
    ]
  },
  "type": "Feature",
  "properties": {
    "hierarchy": [
      "tgn:2317207",
      "tgn:1000001",
      "tgn:7012149",
      "tgn:1002625",
      "tgn:7007706",
      "tgn:7029392"
    ],
    "placetype": [
      "aat:300006075"
    ],
    "id": 2317207,
    "name:xx": "Emma Welch Ditch"
  }
}
