{
  "geometry": {
    "type": "Point",
    "coordinates": [
      -122.1167,
      37.6833
    ]
  },
  "type": "Feature",
  "properties": {
    "hierarchy": [
      "tgn:2470350",
      "tgn:1002138",
      "tgn:1000001",
      "tgn:7012149",
      "tgn:7007157",
      "tgn:7029392"
    ],
    "placetype": [
      "aat:300008347"
    ],
    "id": 2470350,
    "name:xx": "Lorenzo Station"
  }
}
