{
  "geometry": {
    "type": "Point",
    "coordinates": [
      -58.8667,
      -33.7333
    ]
  },
  "type": "Feature",
  "properties": {
    "hierarchy": [
      "tgn:1133043",
      "tgn:7006477",
      "tgn:1001237",
      "tgn:1000002",
      "tgn:7029392"
    ],
    "placetype": [
      "aat:300008706"
    ],
    "id": 1133043,
    "name:xx": "Deslinde, Arroyo"
  }
}
