{
  "type": "FeatureCollection",
  "features": [
    {
      "geometry": {
        "type": "Point",
        "coordinates": [
          -85.2,
          33.8167
        ]
      },
      "type": "Feature",
      "properties": {
        "hierarchy": [
          "tgn:2378030",
          "tgn:1000001",
          "tgn:7012149",
          "tgn:2000362",
          "tgn:7007248",
          "tgn:7029392"
        ],
        "placetype": [
          "aat:300008706"
        ],
        "id": 2378030,
        "name:xx": "Harris Creek"
      }
    },
    {
      "geometry": {
        "type": "Point",
        "coordinates": [
          -84.55,
          34.5833
        ]
      },
      "type": "Feature",
      "properties": {
        "hierarchy": [
          "tgn:2378031",
          "tgn:1000001",
          "tgn:7012149",
          "tgn:2000352",
          "tgn:7007248",
          "tgn:7029392"
        ],
        "placetype": [
          "aat:300008706"
        ],
        "id": 2378031,
        "name:xx": "Harris Creek"
      }
    },
    {
      "geometry": {
        "type": "Point",
        "coordinates": [
          -83.2167,
          33.7333
        ]
      },
      "type": "Feature",
      "properties": {
        "hierarchy": [
          "tgn:2378032",
          "tgn:1000001",
          "tgn:7012149",
          "tgn:2000357",
          "tgn:7007248",
          "tgn:7029392"
        ],
        "placetype": [
          "aat:300008706"
        ],
        "id": 2378032,
        "name:xx": "Harris Creek"
      }
    },
    {
      "geometry": {
        "type": "Point",
        "coordinates": [
          -116.25,
          42.3333
        ]
      },
      "type": "Feature",
      "properties": {
        "hierarchy": [
          "tgn:2378033",
          "tgn:1000001",
          "tgn:7012149",
          "tgn:2000488",
          "tgn:7007250",
          "tgn:7029392"
        ],
        "placetype": [
          "aat:300008706"
        ],
        "id": 2378033,
        "name:xx": "Harris Creek"
      }
    },
    {
      "geometry": {
        "type": "Point",
        "coordinates": [
          -116.0167,
          43.9
        ]
      },
      "type": "Feature",
      "properties": {
        "hierarchy": [
          "tgn:2378034",
          "tgn:1000001",
          "tgn:2000459",
          "tgn:7012149",
          "tgn:7007250",
          "tgn:7029392"
        ],
        "placetype": [
          "aat:300008706"
        ],
        "id": 2378034,
        "name:xx": "Harris Creek"
      }
    },
    {
      "geometry": {
        "type": "Point",
        "coordinates": [
          -88.2667,
          37.5167
        ]
      },
      "type": "Feature",
      "properties": {
        "hierarchy": [
          "tgn:2378035",
          "tgn:1000001",
          "tgn:7012149",
          "tgn:2000509",
          "tgn:7007251",
          "tgn:7029392"
        ],
        "placetype": [
          "aat:300008706"
        ],
        "id": 2378035,
        "name:xx": "Harris Creek"
      }
    },
    {
      "geometry": {
        "type": "Point",
        "coordinates": [
          -85.1833,
          40.4167
        ]
      },
      "type": "Feature",
      "properties": {
        "hierarchy": [
          "tgn:2378036",
          "tgn:1000001",
          "tgn:7012149",
          "tgn:1002513",
          "tgn:7007252",
          "tgn:7029392"
        ],
        "placetype": [
          "aat:300008706"
        ],
        "id": 2378036,
        "name:xx": "Harris Creek"
      }
    },
    {
      "geometry": {
        "type": "Point",
        "coordinates": [
          -96.8833,
          39.85
        ]
      },
      "type": "Feature",
      "properties": {
        "hierarchy": [
          "tgn:2378037",
          "tgn:1000001",
          "tgn:7012149",
          "tgn:2000725",
          "tgn:7007254",
          "tgn:7029392"
        ],
        "placetype": [
          "aat:300008706"
        ],
        "id": 2378037,
        "name:xx": "Harris Creek"
      }
    },
    {
      "geometry": {
        "type": "Point",
        "coordinates": [
          -84.85,
          37.5167
        ]
      },
      "type": "Feature",
      "properties": {
        "hierarchy": [
          "tgn:2378038",
          "tgn:1000001",
          "tgn:7012149",
          "tgn:7007255",
          "tgn:7029392"
        ],
        "placetype": [
          "aat:300008706"
        ],
        "id": 2378038,
        "name:xx": "Harris Creek"
      }
    },
    {
      "geometry": {
        "type": "Point",
        "coordinates": [
          -84.35,
          38.7333
        ]
      },
      "type": "Feature",
      "properties": {
        "hierarchy": [
          "tgn:2378039",
          "tgn:1000001",
          "tgn:7012149",
          "tgn:1002778",
          "tgn:7007255",
          "tgn:7029392"
        ],
        "placetype": [
          "aat:300008706"
        ],
        "id": 2378039,
        "name:xx": "Harris Creek"
      }
    }
  ]
}
