{
  "geometry": {
    "type": "Point",
    "coordinates": [
      -84.3667,
      45.65
    ]
  },
  "type": "Feature",
  "properties": {
    "hierarchy": [
      "tgn:2359955",
      "tgn:1000001",
      "tgn:2000951",
      "tgn:7012149",
      "tgn:7007520",
      "tgn:7029392"
    ],
    "placetype": [
      "aat:300132316"
    ],
    "id": 2359955,
    "name:xx": "Grass Bay"
  }
}
