{
  "geometry": {
    "type": "Point",
    "coordinates": [
      -122.5333,
      38.2667
    ]
  },
  "type": "Feature",
  "properties": {
    "hierarchy": [
      "tgn:2324407",
      "tgn:1000001",
      "tgn:7012149",
      "tgn:7007157",
      "tgn:7014516",
      "tgn:7029392"
    ],
    "placetype": [
      "aat:300008706"
    ],
    "id": 2324407,
    "name:xx": "Felder Creek"
  }
}
