{
  "geometry": {
    "type": "Point",
    "coordinates": [
      -118.2167,
      37.6167
    ]
  },
  "type": "Feature",
  "properties": {
    "hierarchy": [
      "tgn:2679627",
      "tgn:1000001",
      "tgn:7012149",
      "tgn:7007157",
      "tgn:1002675",
      "tgn:7029392"
    ],
    "placetype": [
      "aat:300008706"
    ],
    "id": 2679627,
    "name:xx": "South Fork Perry Aiken Creek"
  }
}
