{
  "geometry": {
    "type": "Point",
    "coordinates": [
      -99.9667,
      38.8333
    ]
  },
  "type": "Feature",
  "properties": {
    "hierarchy": [
      "tgn:2335241",
      "tgn:1000001",
      "tgn:7012149",
      "tgn:2000757",
      "tgn:7007254",
      "tgn:7029392"
    ],
    "placetype": [
      "aat:300008347"
    ],
    "id": 2335241,
    "name:xx": "Fort Downer"
  }
}
