{
  "geometry": {
    "type": "Point",
    "coordinates": [
      105.15,
      20.3667
    ]
  },
  "type": "Feature",
  "properties": {
    "hierarchy": [
      "tgn:1087138",
      "tgn:1000004",
      "tgn:7001062",
      "tgn:1000145",
      "tgn:7029392"
    ],
    "placetype": [
      "aat:300008347"
    ],
    "id": 1087138,
    "name:xx": "Hồi Xuân"
  }
}
