{
  "geometry": {
    "type": "Point",
    "coordinates": [
      88.4667,
      26.0333
    ]
  },
  "type": "Feature",
  "properties": {
    "hierarchy": [
      "tgn:1065963",
      "tgn:1000004",
      "tgn:7000191",
      "tgn:1000105",
      "tgn:7029392"
    ],
    "placetype": [
      "aat:300008347"
    ],
    "id": 1065963,
    "name:xx": "Thākurgaon"
  }
}
