{
  "geometry": {
    "type": "Point",
    "coordinates": [
      -70.7833,
      42.6667
    ]
  },
  "type": "Feature",
  "properties": {
    "hierarchy": [
      "tgn:2607560",
      "tgn:1000001",
      "tgn:1002359",
      "tgn:7012149",
      "tgn:7007517",
      "tgn:7029392"
    ],
    "placetype": [
      "aat:300006191"
    ],
    "id": 2607560,
    "name:xx": "Rantoul Pond"
  }
}
