{
  "geometry": {
    "type": "Point",
    "coordinates": [
      -110.1833,
      44.7833
    ]
  },
  "type": "Feature",
  "properties": {
    "hierarchy": [
      "tgn:2559641",
      "tgn:1000001",
      "tgn:7012149",
      "tgn:2002379",
      "tgn:7007923",
      "tgn:7029392"
    ],
    "placetype": [
      "aat:300008706"
    ],
    "id": 2559641,
    "name:xx": "Opal Creek"
  }
}
