{
  "geometry": {
    "type": "Point",
    "coordinates": [
      -85.2333,
      44.1333
    ]
  },
  "type": "Feature",
  "properties": {
    "hierarchy": [
      "tgn:2634854",
      "tgn:1000001",
      "tgn:7012149",
      "tgn:7007520",
      "tgn:7029392"
    ],
    "placetype": [
      "aat:300008706"
    ],
    "id": 2634854,
    "name:xx": "Ryan Creek"
  }
}
