{
  "geometry": {
    "type": "Point",
    "coordinates": [
      -63.6667,
      64.9333
    ]
  },
  "type": "Feature",
  "properties": {
    "hierarchy": [
      "tgn:1010941",
      "tgn:7013003",
      "tgn:7005685",
      "tgn:1000001",
      "tgn:7024197",
      "tgn:7029392"
    ],
    "placetype": [
      "aat:300008850"
    ],
    "id": 1010941,
    "name:xx": "Mercy, Cape"
  }
}
