{
  "geometry": {
    "type": "Point",
    "coordinates": [
      -68.3833,
      -41.05
    ]
  },
  "type": "Feature",
  "properties": {
    "hierarchy": [
      "tgn:1019122",
      "tgn:7006477",
      "tgn:7006348",
      "tgn:1000002",
      "tgn:7029392"
    ],
    "placetype": [
      "aat:300008347"
    ],
    "id": 1019122,
    "name:xx": "Aguada de Guerra"
  }
}
