{
  "geometry": {
    "type": "Point",
    "coordinates": [
      -106.0667,
      42.7333
    ]
  },
  "type": "Feature",
  "properties": {
    "hierarchy": [
      "tgn:2481157",
      "tgn:1000001",
      "tgn:2002369",
      "tgn:7012149",
      "tgn:7007923",
      "tgn:7029392"
    ],
    "placetype": [
      "aat:300006191"
    ],
    "id": 2481157,
    "name:xx": "Lamb Upper Reservoir"
  }
}
