{
  "geometry": {
    "type": "Point",
    "coordinates": [
      -108.3333,
      42.2667
    ]
  },
  "type": "Feature",
  "properties": {
    "hierarchy": [
      "tgn:2360841",
      "tgn:1000001",
      "tgn:7012149",
      "tgn:2002371",
      "tgn:7007923",
      "tgn:7029392"
    ],
    "placetype": [
      "aat:300008680"
    ],
    "id": 2360841,
    "name:xx": "Grassy Lake"
  }
}
