{
  "geometry": {
    "type": "Point",
    "coordinates": [
      -120.7333,
      37.9667
    ]
  },
  "type": "Feature",
  "properties": {
    "hierarchy": [
      "tgn:2673725",
      "tgn:1000001",
      "tgn:7012149",
      "tgn:7007157",
      "tgn:7029392"
    ],
    "placetype": [
      "aat:300008706"
    ],
    "id": 2673725,
    "name:xx": "Snow Creek"
  }
}
