{
  "type": "FeatureCollection",
  "features": [
    {
      "geometry": {
        "type": "Point",
        "coordinates": [
          -111.7667,
          34.4833
        ]
      },
      "type": "Feature",
      "properties": {
        "hierarchy": [
          "tgn:2506910",
          "tgn:1000001",
          "tgn:7006451",
          "tgn:7012149",
          "tgn:2000103",
          "tgn:7029392"
        ],
        "placetype": [
          "aat:300008697"
        ],
        "id": 2506910,
        "name:xx": "Mesquite Spring"
      }
    },
    {
      "geometry": {
        "type": "Point",
        "coordinates": [
          -113.4167,
          35.6667
        ]
      },
      "type": "Feature",
      "properties": {
        "hierarchy": [
          "tgn:2506911",
          "tgn:1000001",
          "tgn:7006451",
          "tgn:7012149",
          "tgn:2000098",
          "tgn:7029392"
        ],
        "placetype": [
          "aat:300008697"
        ],
        "id": 2506911,
        "name:xx": "Mesquite Spring"
      }
    },
    {
      "geometry": {
        "type": "Point",
        "coordinates": [
          -111.5333,
          33.7167
        ]
      },
      "type": "Feature",
      "properties": {
        "hierarchy": [
          "tgn:2506912",
          "tgn:1000001",
          "tgn:7006451",
          "tgn:7012149",
          "tgn:2000097",
          "tgn:7029392"
        ],
        "placetype": [
          "aat:300008697"
        ],
        "id": 2506912,
        "name:xx": "Mesquite Spring"
      }
    },
    {
      "geometry": {
        "type": "Point",
        "coordinates": [
          -111.1833,
          33.3833
        ]
      },
      "type": "Feature",
      "properties": {
        "hierarchy": [
          "tgn:2506913",
          "tgn:1000001",
          "tgn:7006451",
          "tgn:7012149",
          "tgn:2000101",
          "tgn:7029392"
        ],
        "placetype": [
          "aat:300008697"
        ],
        "id": 2506913,
        "name:xx": "Mesquite Spring"
      }
    },
    {
      "geometry": {
        "type": "Point",
        "coordinates": [
          -116.0667,
          35.2
        ]
      },
      "type": "Feature",
      "properties": {
        "hierarchy": [
          "tgn:2506914",
          "tgn:1000001",
          "tgn:7012149",
          "tgn:7007157",
          "tgn:1002857",
          "tgn:7029392"
        ],
        "placetype": [
          "aat:300008697"
        ],
        "id": 2506914,
        "name:xx": "Mesquite Spring"
      }
    },
    {
      "geometry": {
        "type": "Point",
        "coordinates": [
          -106.0667,
          33.0167
        ]
      },
      "type": "Feature",
      "properties": {
        "hierarchy": [
          "tgn:2506916",
          "tgn:1000001",
          "tgn:7012149",
          "tgn:2001447",
          "tgn:7007566",
          "tgn:7029392"
        ],
        "placetype": [
          "aat:300008697"
        ],
        "id": 2506916,
        "name:xx": "Mesquite Spring"
      }
    },
    {
      "geometry": {
        "type": "Point",
        "coordinates": [
          -104.9333,
          30.6667
        ]
      },
      "type": "Feature",
      "properties": {
        "hierarchy": [
          "tgn:2506917",
          "tgn:1000001",
          "tgn:7012149",
          "tgn:2002005",
          "tgn:7007826",
          "tgn:7029392"
        ],
        "placetype": [
          "aat:300008697"
        ],
        "id": 2506917,
        "name:xx": "Mesquite Spring"
      }
    },
    {
      "geometry": {
        "type": "Point",
        "coordinates": [
          -111.5667,
          33.7333
        ]
      },
      "type": "Feature",
      "properties": {
        "hierarchy": [
          "tgn:2506918",
          "tgn:1000001",
          "tgn:7006451",
          "tgn:7012149",
          "tgn:2000097",
          "tgn:7029392"
        ],
        "placetype": [
          "aat:300006191"
        ],
        "id": 2506918,
        "name:xx": "Mesquite Spring Tank"
      }
    },
    {
      "geometry": {
        "type": "Point",
        "coordinates": [
          -117.8,
          35.3833
        ]
      },
      "type": "Feature",
      "properties": {
        "hierarchy": [
          "tgn:2506919",
          "tgn:1000001",
          "tgn:7012149",
          "tgn:1002545",
          "tgn:7007157",
          "tgn:7029392"
        ],
        "placetype": [
          "aat:300008697"
        ],
        "id": 2506919,
        "name:xx": "Mesquite Springs"
      }
    }
  ]
}
