{
  "geometry": {
    "type": "Point",
    "coordinates": [
      31.119736,
      30.719075
    ]
  },
  "type": "Feature",
  "properties": {
    "hierarchy": [
      "tgn:7520879",
      "tgn:7001242",
      "tgn:7016833",
      "tgn:7001312",
      "tgn:7029392"
    ],
    "placetype": [
      "aat:300008347"
    ],
    "name:en": "Abū al Juhūr",
    "id": 7520879
  }
}
