{
  "geometry": {
    "type": "Point",
    "coordinates": [
      -79.2167,
      38.9333
    ]
  },
  "type": "Feature",
  "properties": {
    "hierarchy": [
      "tgn:2572552",
      "tgn:1000001",
      "tgn:2002263",
      "tgn:7012149",
      "tgn:7013961",
      "tgn:7029392"
    ],
    "placetype": [
      "aat:300008746"
    ],
    "id": 2572552,
    "name:xx": "Peacock Cave"
  }
}
