{
  "geometry": {
    "type": "Point",
    "coordinates": [
      -82.6333,
      35.2833
    ]
  },
  "type": "Feature",
  "properties": {
    "hierarchy": [
      "tgn:2333265",
      "tgn:1000001",
      "tgn:7012149",
      "tgn:2001544",
      "tgn:7007709",
      "tgn:7029392"
    ],
    "placetype": [
      "aat:300008798"
    ],
    "id": 2333265,
    "name:xx": "Fodderstack Mountain"
  }
}
