{
  "geometry": {
    "type": "Point",
    "coordinates": [
      -87.3167,
      35.6833
    ]
  },
  "type": "Feature",
  "properties": {
    "hierarchy": [
      "tgn:2290985",
      "tgn:1000001",
      "tgn:7012149",
      "tgn:7015666",
      "tgn:7007825",
      "tgn:7029392"
    ],
    "placetype": [
      "aat:300266640"
    ],
    "id": 2290985,
    "name:xx": "Dog Ridge"
  }
}
