{
  "geometry": {
    "type": "Point",
    "coordinates": [
      -124.0833,
      41.7833
    ]
  },
  "type": "Feature",
  "properties": {
    "hierarchy": [
      "tgn:2442285",
      "tgn:1000001",
      "tgn:7012149",
      "tgn:2000180",
      "tgn:7007157",
      "tgn:7029392"
    ],
    "placetype": [
      "aat:300132451"
    ],
    "id": 2442285,
    "name:xx": "Krause Grove North"
  }
}
