{
  "geometry": {
    "type": "Point",
    "coordinates": [
      -86.5833,
      40.8833
    ]
  },
  "type": "Feature",
  "properties": {
    "hierarchy": [
      "tgn:2752248",
      "tgn:1000001",
      "tgn:7012149",
      "tgn:1003021",
      "tgn:7007252",
      "tgn:7029392"
    ],
    "placetype": [
      "aat:300006075"
    ],
    "id": 2752248,
    "name:xx": "Washburn Ditch"
  }
}
