{
  "geometry": {
    "type": "Point",
    "coordinates": [
      -85.7333,
      40.8167
    ]
  },
  "type": "Feature",
  "properties": {
    "hierarchy": [
      "tgn:2552030",
      "tgn:1000001",
      "tgn:7012149",
      "tgn:1002978",
      "tgn:7007252",
      "tgn:7029392"
    ],
    "placetype": [
      "aat:300008178"
    ],
    "id": 2552030,
    "name:xx": "Number Fourteen, Reserve"
  }
}
