{
  "geometry": {
    "type": "Point",
    "coordinates": [
      -72.5667,
      43.0667
    ]
  },
  "type": "Feature",
  "properties": {
    "hierarchy": [
      "tgn:2360476",
      "tgn:1000001",
      "tgn:1003029",
      "tgn:7012149",
      "tgn:7007828",
      "tgn:7029392"
    ],
    "placetype": [
      "aat:300008699"
    ],
    "id": 2360476,
    "name:xx": "Grassy Brook"
  }
}
