{
  "geometry": {
    "type": "Point",
    "coordinates": [
      -81.2667,
      41.7333
    ]
  },
  "type": "Feature",
  "properties": {
    "hierarchy": [
      "tgn:2606423",
      "tgn:1000001",
      "tgn:7012149",
      "tgn:1002570",
      "tgn:7007706",
      "tgn:7029392"
    ],
    "placetype": [
      "aat:300008791"
    ],
    "id": 2606423,
    "name:xx": "Ram Island"
  }
}
