{
  "geometry": {
    "type": "Point",
    "coordinates": [
      -96.9333,
      45.7833
    ]
  },
  "type": "Feature",
  "properties": {
    "hierarchy": [
      "tgn:2668765",
      "tgn:1000001",
      "tgn:7012149",
      "tgn:2001824",
      "tgn:7007713",
      "tgn:7029392"
    ],
    "placetype": [
      "aat:300008905"
    ],
    "id": 2668765,
    "name:xx": "Slather Slough"
  }
}
