{
  "geometry": {
    "type": "Point",
    "coordinates": [
      -152.7833,
      57.9167
    ]
  },
  "type": "Feature",
  "properties": {
    "hierarchy": [
      "tgn:2173987",
      "tgn:7006450",
      "tgn:1000001",
      "tgn:2124012",
      "tgn:7012149",
      "tgn:7029392"
    ],
    "placetype": [
      "aat:300008850"
    ],
    "id": 2173987,
    "name:xx": "Bird Point"
  }
}
