{
  "geometry": {
    "type": "Point",
    "coordinates": [
      -117.1167,
      34.5667
    ]
  },
  "type": "Feature",
  "properties": {
    "hierarchy": [
      "tgn:2321686",
      "tgn:1000001",
      "tgn:7012149",
      "tgn:7007157",
      "tgn:1002857",
      "tgn:7029392"
    ],
    "placetype": [
      "aat:300008798"
    ],
    "id": 2321686,
    "name:xx": "Fairview Mountain"
  }
}
