{
  "geometry": {
    "type": "Point",
    "coordinates": [
      74.16882,
      22.179787
    ]
  },
  "type": "Feature",
  "properties": {
    "hierarchy": [
      "tgn:7556408",
      "tgn:1000004",
      "tgn:7000198",
      "tgn:1001894",
      "tgn:7029392"
    ],
    "placetype": [
      "aat:300008347"
    ],
    "name:en": "Phulmāi",
    "id": 7556408
  }
}
