{
  "geometry": {
    "type": "Point",
    "coordinates": [
      35.0161,
      23.010933
    ]
  },
  "type": "Feature",
  "properties": {
    "hierarchy": [
      "tgn:7538705",
      "tgn:7001242",
      "tgn:7001311",
      "tgn:7016833",
      "tgn:7029392"
    ],
    "placetype": [
      "aat:300008795"
    ],
    "name:en": "Niqrūb at Taḩtānī, Jabal",
    "id": 7538705
  }
}
