{
  "geometry": {
    "type": "Point",
    "coordinates": [
      -78.6667,
      39.9167
    ]
  },
  "type": "Feature",
  "properties": {
    "hierarchy": [
      "tgn:2625559",
      "tgn:1002172",
      "tgn:1000001",
      "tgn:7012149",
      "tgn:7007710",
      "tgn:7029392"
    ],
    "placetype": [
      "aat:300008347"
    ],
    "id": 2625559,
    "name:xx": "Rockville"
  }
}
