{
  "type": "FeatureCollection",
  "features": [
    {
      "geometry": {
        "type": "Point",
        "coordinates": [
          -70.916667,
          -34.4
        ]
      },
      "type": "Feature",
      "properties": {
        "hierarchy": [
          "tgn:7280870",
          "tgn:1001695",
          "tgn:1000049",
          "tgn:1000002",
          "tgn:7029392"
        ],
        "placetype": [
          "aat:300004792"
        ],
        "id": 7280870,
        "name:xx": "Santa Julia"
      }
    },
    {
      "geometry": {
        "type": "Point",
        "coordinates": [
          -72.416667,
          -37.366667
        ]
      },
      "type": "Feature",
      "properties": {
        "hierarchy": [
          "tgn:7280871",
          "tgn:1001637",
          "tgn:1000049",
          "tgn:1000002",
          "tgn:7029392"
        ],
        "placetype": [
          "aat:300000206"
        ],
        "id": 7280871,
        "name:xx": "Santa Juana de Guaqui"
      }
    },
    {
      "geometry": {
        "type": "Point",
        "coordinates": [
          -69.933333,
          -26.883333
        ]
      },
      "type": "Feature",
      "properties": {
        "hierarchy": [
          "tgn:7280872",
          "tgn:1001630",
          "tgn:1000049",
          "tgn:1000002",
          "tgn:7029392"
        ],
        "placetype": [
          "aat:300008795"
        ],
        "id": 7280872,
        "name:xx": "Santa Juana, Cerro"
      }
    },
    {
      "geometry": {
        "type": "Point",
        "coordinates": [
          -72.933333,
          -37.166667
        ]
      },
      "type": "Feature",
      "properties": {
        "hierarchy": [
          "tgn:7280873",
          "tgn:1001637",
          "tgn:1000049",
          "tgn:1000002",
          "tgn:7029392"
        ],
        "placetype": [
          "aat:300008347"
        ],
        "id": 7280873,
        "name:xx": "Santa Juana"
      }
    },
    {
      "geometry": {
        "type": "Point",
        "coordinates": [
          -70.666667,
          -33.583333
        ]
      },
      "type": "Feature",
      "properties": {
        "hierarchy": [
          "tgn:7280874",
          "tgn:1001708",
          "tgn:1000049",
          "tgn:1000002",
          "tgn:7029392"
        ],
        "placetype": [
          "aat:300000206"
        ],
        "id": 7280874,
        "name:xx": "Santa Juana"
      }
    },
    {
      "geometry": {
        "type": "Point",
        "coordinates": [
          -70.866667,
          -32.766667
        ]
      },
      "type": "Feature",
      "properties": {
        "hierarchy": [
          "tgn:7280875",
          "tgn:1001768",
          "tgn:1000049",
          "tgn:1000002",
          "tgn:7029392"
        ],
        "placetype": [
          "aat:300008777"
        ],
        "id": 7280875,
        "name:xx": "Santa Isabel, Cerro"
      }
    },
    {
      "geometry": {
        "type": "Point",
        "coordinates": [
          -69.616667,
          -22.083333
        ]
      },
      "type": "Feature",
      "properties": {
        "hierarchy": [
          "tgn:7280876",
          "tgn:7016598",
          "tgn:1000049",
          "tgn:1000002",
          "tgn:7029392"
        ],
        "placetype": [
          "aat:300387033"
        ],
        "id": 7280876,
        "name:xx": "Santa Isabel"
      }
    },
    {
      "geometry": {
        "type": "Point",
        "coordinates": [
          -70.816667,
          -34.783333
        ]
      },
      "type": "Feature",
      "properties": {
        "hierarchy": [
          "tgn:7280877",
          "tgn:1001695",
          "tgn:1000049",
          "tgn:1000002",
          "tgn:7029392"
        ],
        "placetype": [
          "aat:300387200"
        ],
        "id": 7280877,
        "name:xx": "Santa Isabel"
      }
    },
    {
      "geometry": {
        "type": "Point",
        "coordinates": [
          -72.133333,
          -37.883333
        ]
      },
      "type": "Feature",
      "properties": {
        "hierarchy": [
          "tgn:7280878",
          "tgn:1001637",
          "tgn:1000049",
          "tgn:1000002",
          "tgn:7029392"
        ],
        "placetype": [
          "aat:300000206"
        ],
        "id": 7280878,
        "name:xx": "Santa Isabel"
      }
    },
    {
      "geometry": {
        "type": "Point",
        "coordinates": [
          -72.816667,
          -37.45
        ]
      },
      "type": "Feature",
      "properties": {
        "hierarchy": [
          "tgn:7280879",
          "tgn:1001637",
          "tgn:1000049",
          "tgn:1000002",
          "tgn:7029392"
        ],
        "placetype": [
          "aat:300000206"
        ],
        "id": 7280879,
        "name:xx": "Santa Isabel"
      }
    }
  ]
}
