{
  "geometry": {
    "type": "Point",
    "coordinates": [
      -108.5667,
      43.8833
    ]
  },
  "type": "Feature",
  "properties": {
    "hierarchy": [
      "tgn:2409862",
      "tgn:1000001",
      "tgn:7012149",
      "tgn:2002373",
      "tgn:7007923",
      "tgn:7029392"
    ],
    "placetype": [
      "aat:300266640"
    ],
    "id": 2409862,
    "name:xx": "Ilo Ridge"
  }
}
