{
  "geometry": {
    "type": "Point",
    "coordinates": [
      -71.4167,
      41.9833
    ]
  },
  "type": "Feature",
  "properties": {
    "hierarchy": [
      "tgn:2138789",
      "tgn:1002808",
      "tgn:1000001",
      "tgn:7012149",
      "tgn:7007711",
      "tgn:7029392"
    ],
    "placetype": [
      "aat:300008905"
    ],
    "id": 2138789,
    "name:xx": "Ash Swamp"
  }
}
