{
  "geometry": {
    "type": "Point",
    "coordinates": [
      -105.1333,
      38.7833
    ]
  },
  "type": "Feature",
  "properties": {
    "hierarchy": [
      "tgn:2148435",
      "tgn:1000001",
      "tgn:7012149",
      "tgn:7007158",
      "tgn:2000251",
      "tgn:7029392"
    ],
    "placetype": [
      "aat:300008706"
    ],
    "id": 2148435,
    "name:xx": "Barnard Creek"
  }
}
