{
  "type": "FeatureCollection",
  "features": [
    {
      "geometry": {
        "type": "Point",
        "coordinates": [
          -102.95,
          25.35
        ]
      },
      "type": "Feature",
      "properties": {
        "hierarchy": [
          "tgn:7433861",
          "tgn:1001853",
          "tgn:1000001",
          "tgn:7005560",
          "tgn:7029392"
        ],
        "placetype": [
          "aat:300008347"
        ],
        "id": 7433861,
        "name:xx": "Venustiano Carranza"
      }
    },
    {
      "geometry": {
        "type": "Point",
        "coordinates": [
          -104.6,
          24.45
        ]
      },
      "type": "Feature",
      "properties": {
        "hierarchy": [
          "tgn:7433862",
          "tgn:7005583",
          "tgn:1000001",
          "tgn:7005560",
          "tgn:7029392"
        ],
        "placetype": [
          "aat:300008347"
        ],
        "id": 7433862,
        "name:xx": "Venustiano Carranza"
      }
    },
    {
      "geometry": {
        "type": "Point",
        "coordinates": [
          -104.983333,
          21.516667
        ]
      },
      "type": "Feature",
      "properties": {
        "hierarchy": [
          "tgn:7433863",
          "tgn:1000001",
          "tgn:1001906",
          "tgn:7005560",
          "tgn:7029392"
        ],
        "placetype": [
          "aat:300008347"
        ],
        "id": 7433863,
        "name:xx": "El Gringo"
      }
    },
    {
      "geometry": {
        "type": "Point",
        "coordinates": [
          -102.65,
          20.116667
        ]
      },
      "type": "Feature",
      "properties": {
        "hierarchy": [
          "tgn:7433864",
          "tgn:1000001",
          "tgn:7005590",
          "tgn:7005560",
          "tgn:7029392"
        ],
        "placetype": [
          "aat:300008347"
        ],
        "id": 7433864,
        "name:xx": "Venustiano Carranza"
      }
    },
    {
      "geometry": {
        "type": "Point",
        "coordinates": [
          -104.1,
          19
        ]
      },
      "type": "Feature",
      "properties": {
        "hierarchy": [
          "tgn:7433866",
          "tgn:7016644",
          "tgn:1000001",
          "tgn:7005560",
          "tgn:7029392"
        ],
        "placetype": [
          "aat:300008347"
        ],
        "id": 7433866,
        "name:xx": "Venustiano Carranza"
      }
    },
    {
      "geometry": {
        "type": "Point",
        "coordinates": [
          -101.883333,
          25.683333
        ]
      },
      "type": "Feature",
      "properties": {
        "hierarchy": [
          "tgn:7433868",
          "tgn:1001853",
          "tgn:1000001",
          "tgn:7005560",
          "tgn:7029392"
        ],
        "placetype": [
          "aat:300007783"
        ],
        "id": 7433868,
        "name:xx": "Venus"
      }
    },
    {
      "geometry": {
        "type": "Point",
        "coordinates": [
          -107.916667,
          25.716667
        ]
      },
      "type": "Feature",
      "properties": {
        "hierarchy": [
          "tgn:7433869",
          "tgn:1000001",
          "tgn:7005595",
          "tgn:7005560",
          "tgn:7029392"
        ],
        "placetype": [
          "aat:300008347"
        ],
        "id": 7433869,
        "name:xx": "Ventura de los Gerardos"
      }
    }
  ]
}
