{
  "geometry": {
    "type": "Point",
    "coordinates": [
      -112.8667,
      33.2167
    ]
  },
  "type": "Feature",
  "properties": {
    "hierarchy": [
      "tgn:2376873",
      "tgn:1000001",
      "tgn:7006451",
      "tgn:7012149",
      "tgn:2000097",
      "tgn:7029392"
    ],
    "placetype": [
      "aat:300000390"
    ],
    "id": 2376873,
    "name:xx": "Hargan Mine"
  }
}
