{
  "geometry": {
    "type": "Point",
    "coordinates": [
      74.296597,
      34.406778
    ]
  },
  "type": "Feature",
  "properties": {
    "hierarchy": [
      "tgn:7586021",
      "tgn:1000004",
      "tgn:7000198",
      "tgn:7000799",
      "tgn:7029392"
    ],
    "placetype": [
      "aat:300008347"
    ],
    "name:en": "Brāripur",
    "id": 7586021
  }
}
