{
  "geometry": {
    "type": "Point",
    "coordinates": [
      138.65,
      -35.0167
    ]
  },
  "type": "Feature",
  "properties": {
    "hierarchy": [
      "tgn:1102692",
      "tgn:7000490",
      "tgn:1000006",
      "tgn:7001831",
      "tgn:7029392"
    ],
    "placetype": [
      "aat:300008187"
    ],
    "id": 1102692,
    "name:xx": "Belair Recreation Park"
  }
}
