{
  "type": "FeatureCollection",
  "features": [
    {
      "geometry": {
        "type": "Point",
        "coordinates": [
          -120.1,
          44.15
        ]
      },
      "type": "Feature",
      "properties": {
        "hierarchy": [
          "tgn:2754080",
          "tgn:1000001",
          "tgn:2001703",
          "tgn:7012149",
          "tgn:7007708",
          "tgn:7029392"
        ],
        "placetype": [
          "aat:300006191"
        ],
        "id": 2754080,
        "name:xx": "Watson Reservoir"
      }
    },
    {
      "geometry": {
        "type": "Point",
        "coordinates": [
          -71.1833,
          41.5333
        ]
      },
      "type": "Feature",
      "properties": {
        "hierarchy": [
          "tgn:2754081",
          "tgn:1002716",
          "tgn:1000001",
          "tgn:7012149",
          "tgn:7007711",
          "tgn:7029392"
        ],
        "placetype": [
          "aat:300006191"
        ],
        "id": 2754081,
        "name:xx": "Watson Reservoir"
      }
    },
    {
      "geometry": {
        "type": "Point",
        "coordinates": [
          -93.6833,
          35.8667
        ]
      },
      "type": "Feature",
      "properties": {
        "hierarchy": [
          "tgn:2754082",
          "tgn:1000001",
          "tgn:7016172",
          "tgn:7012149",
          "tgn:2000148",
          "tgn:7029392"
        ],
        "placetype": [
          "aat:300266640"
        ],
        "id": 2754082,
        "name:xx": "Watson Ridge"
      }
    },
    {
      "geometry": {
        "type": "Point",
        "coordinates": [
          -121.2167,
          39.6833
        ]
      },
      "type": "Feature",
      "properties": {
        "hierarchy": [
          "tgn:2754083",
          "tgn:1000001",
          "tgn:1002218",
          "tgn:7012149",
          "tgn:7007157",
          "tgn:7029392"
        ],
        "placetype": [
          "aat:300266640"
        ],
        "id": 2754083,
        "name:xx": "Watson Ridge"
      }
    },
    {
      "geometry": {
        "type": "Point",
        "coordinates": [
          -80.9,
          40.55
        ]
      },
      "type": "Feature",
      "properties": {
        "hierarchy": [
          "tgn:2754084",
          "tgn:1000001",
          "tgn:7012149",
          "tgn:7007706",
          "tgn:7029392"
        ],
        "placetype": [
          "aat:300266640"
        ],
        "id": 2754084,
        "name:xx": "Watson Ridge"
      }
    },
    {
      "geometry": {
        "type": "Point",
        "coordinates": [
          -122.3167,
          43.2667
        ]
      },
      "type": "Feature",
      "properties": {
        "hierarchy": [
          "tgn:2754085",
          "tgn:1000001",
          "tgn:7012149",
          "tgn:2001706",
          "tgn:7007708",
          "tgn:7029392"
        ],
        "placetype": [
          "aat:300266640"
        ],
        "id": 2754085,
        "name:xx": "Watson Ridge"
      }
    },
    {
      "geometry": {
        "type": "Point",
        "coordinates": [
          -83.7,
          36.45
        ]
      },
      "type": "Feature",
      "properties": {
        "hierarchy": [
          "tgn:2754086",
          "tgn:1000001",
          "tgn:7012149",
          "tgn:2001849",
          "tgn:7007825",
          "tgn:7029392"
        ],
        "placetype": [
          "aat:300266640"
        ],
        "id": 2754086,
        "name:xx": "Watson Ridge"
      }
    },
    {
      "geometry": {
        "type": "Point",
        "coordinates": [
          -84.9667,
          36.6
        ]
      },
      "type": "Feature",
      "properties": {
        "hierarchy": [
          "tgn:2754087",
          "tgn:1000001",
          "tgn:7012149",
          "tgn:2001905",
          "tgn:7007825",
          "tgn:7029392"
        ],
        "placetype": [
          "aat:300266640"
        ],
        "id": 2754087,
        "name:xx": "Watson Ridge"
      }
    },
    {
      "geometry": {
        "type": "Point",
        "coordinates": [
          -84.4667,
          35.6333
        ]
      },
      "type": "Feature",
      "properties": {
        "hierarchy": [
          "tgn:2754088",
          "tgn:1000001",
          "tgn:7012149",
          "tgn:7007825",
          "tgn:7029392"
        ],
        "placetype": [
          "aat:300266640"
        ],
        "id": 2754088,
        "name:xx": "Watson Ridge"
      }
    },
    {
      "geometry": {
        "type": "Point",
        "coordinates": [
          -118.6,
          48.0667
        ]
      },
      "type": "Feature",
      "properties": {
        "hierarchy": [
          "tgn:2754089",
          "tgn:1000001",
          "tgn:2002243",
          "tgn:7012149",
          "tgn:7007920",
          "tgn:7029392"
        ],
        "placetype": [
          "aat:300266640"
        ],
        "id": 2754089,
        "name:xx": "Watson Ridge"
      }
    }
  ]
}
