{
  "geometry": {
    "type": "Point",
    "coordinates": [
      74.666667,
      18.95
    ]
  },
  "type": "Feature",
  "properties": {
    "hierarchy": [
      "tgn:7559351",
      "tgn:1000004",
      "tgn:7000198",
      "tgn:1001895",
      "tgn:7029392"
    ],
    "placetype": [
      "aat:300008347"
    ],
    "name:en": "Sārola",
    "id": 7559351
  }
}
