{
  "geometry": {
    "type": "Point",
    "coordinates": [
      -158.75,
      69.3333
    ]
  },
  "type": "Feature",
  "properties": {
    "hierarchy": [
      "tgn:1121532",
      "tgn:7006450",
      "tgn:1000001",
      "tgn:7012149",
      "tgn:2124005",
      "tgn:7029392"
    ],
    "placetype": [
      "aat:300008707"
    ],
    "id": 1121532,
    "name:xx": "Awuna"
  }
}
