{
  "geometry": {
    "type": "Point",
    "coordinates": [
      33.607148,
      25.733488
    ]
  },
  "type": "Feature",
  "properties": {
    "hierarchy": [
      "tgn:7534194",
      "tgn:7001242",
      "tgn:7001311",
      "tgn:7016833",
      "tgn:7029392"
    ],
    "placetype": [
      "aat:300379998"
    ],
    "name:en": "Maḩdaf, Wādī al",
    "id": 7534194
  }
}
