{
  "geometry": {
    "type": "Point",
    "coordinates": [
      -109.5667,
      33.7667
    ]
  },
  "type": "Feature",
  "properties": {
    "hierarchy": [
      "tgn:2211518",
      "tgn:2000090",
      "tgn:1000001",
      "tgn:7006451",
      "tgn:7012149",
      "tgn:7029392"
    ],
    "placetype": [
      "aat:300008905"
    ],
    "id": 2211518,
    "name:xx": "Butterfly Cienega"
  }
}
