{
  "geometry": {
    "type": "Point",
    "coordinates": [
      -80.1667,
      34.5667
    ]
  },
  "type": "Feature",
  "properties": {
    "hierarchy": [
      "tgn:2498120",
      "tgn:1000001",
      "tgn:2001737",
      "tgn:7012149",
      "tgn:7007712",
      "tgn:7029392"
    ],
    "placetype": [
      "aat:300006191"
    ],
    "id": 2498120,
    "name:xx": "Mays Lake"
  }
}
