{
  "geometry": {
    "type": "Point",
    "coordinates": [
      -91.9833,
      44.35
    ]
  },
  "type": "Feature",
  "properties": {
    "hierarchy": [
      "tgn:2622813",
      "tgn:1000001",
      "tgn:7012149",
      "tgn:2001077",
      "tgn:7007521",
      "tgn:7029392"
    ],
    "placetype": [
      "aat:300008680"
    ],
    "id": 2622813,
    "name:xx": "Robinson Lake"
  }
}
