{
  "geometry": {
    "type": "Point",
    "coordinates": [
      -89.0333,
      31.6333
    ]
  },
  "type": "Feature",
  "properties": {
    "hierarchy": [
      "tgn:2557585",
      "tgn:1000001",
      "tgn:7012149",
      "tgn:2001119",
      "tgn:7007522",
      "tgn:7029392"
    ],
    "placetype": [
      "aat:300008699"
    ],
    "id": 2557585,
    "name:xx": "Old Place Branch"
  }
}
