{
  "geometry": {
    "type": "Point",
    "coordinates": [
      79.062217,
      26.95881
    ]
  },
  "type": "Feature",
  "properties": {
    "hierarchy": [
      "tgn:7560333",
      "tgn:1000004",
      "tgn:7000198",
      "tgn:7016722",
      "tgn:7029392"
    ],
    "placetype": [
      "aat:300008347"
    ],
    "name:en": "Hīrāpur",
    "id": 7560333
  }
}
