{
  "geometry": {
    "type": "Point",
    "coordinates": [
      21.0167,
      4.2833
    ]
  },
  "type": "Feature",
  "properties": {
    "hierarchy": [
      "tgn:7018936",
      "tgn:7001242",
      "tgn:7016654",
      "tgn:1000159",
      "tgn:7029392"
    ],
    "placetype": [
      "aat:300008347"
    ],
    "id": 7018936,
    "name:xx": "Gbadolite"
  }
}
