{
  "geometry": {
    "type": "Point",
    "coordinates": [
      31.206085,
      30.061994
    ]
  },
  "type": "Feature",
  "properties": {
    "hierarchy": [
      "tgn:7531055",
      "tgn:7001242",
      "tgn:7016833",
      "tgn:1001083",
      "tgn:7029392"
    ],
    "placetype": [
      "aat:300386996"
    ],
    "id": 7531055,
    "name:xx": "Wizārat al Ma'lūmāt wa al Ittişālāt"
  }
}
