{
  "geometry": {
    "type": "Point",
    "coordinates": [
      16.3333,
      59.4333
    ]
  },
  "type": "Feature",
  "properties": {
    "hierarchy": [
      "tgn:1063502",
      "tgn:1000003",
      "tgn:7003781",
      "tgn:1000097",
      "tgn:7029392"
    ],
    "placetype": [
      "aat:300008347"
    ],
    "id": 1063502,
    "name:xx": "Rekarne"
  }
}
