{
  "geometry": {
    "type": "Point",
    "coordinates": [
      -108.3167,
      43.45
    ]
  },
  "type": "Feature",
  "properties": {
    "hierarchy": [
      "tgn:2690396",
      "tgn:1000001",
      "tgn:7012149",
      "tgn:7007923",
      "tgn:7029392"
    ],
    "placetype": [
      "aat:300008706"
    ],
    "id": 2690396,
    "name:xx": "Stagner Creek"
  }
}
