{
  "geometry": {
    "type": "Point",
    "coordinates": [
      -91.7667,
      38.9833
    ]
  },
  "type": "Feature",
  "properties": {
    "hierarchy": [
      "tgn:2141928",
      "tgn:1000001",
      "tgn:1002223",
      "tgn:7012149",
      "tgn:7007523",
      "tgn:7029392"
    ],
    "placetype": [
      "aat:300008347"
    ],
    "id": 2141928,
    "name:xx": "Bachelor"
  }
}
