{
  "geometry": {
    "type": "Point",
    "coordinates": [
      -72.4167,
      44.7333
    ]
  },
  "type": "Feature",
  "properties": {
    "hierarchy": [
      "tgn:2654893",
      "tgn:1000001",
      "tgn:1002753",
      "tgn:7012149",
      "tgn:7007828",
      "tgn:7029392"
    ],
    "placetype": [
      "aat:300008699"
    ],
    "id": 2654893,
    "name:xx": "Shalney Branch"
  }
}
