{
  "geometry": {
    "type": "Point",
    "coordinates": [
      -94.5667,
      33.8167
    ]
  },
  "type": "Feature",
  "properties": {
    "hierarchy": [
      "tgn:2568776",
      "tgn:1000001",
      "tgn:7012149",
      "tgn:2001667",
      "tgn:7007707",
      "tgn:7029392"
    ],
    "placetype": [
      "aat:300008706"
    ],
    "id": 2568776,
    "name:xx": "Parker Creek"
  }
}
