{
  "geometry": {
    "type": "Point",
    "coordinates": [
      -96.7167,
      43.5667
    ]
  },
  "type": "Feature",
  "properties": {
    "hierarchy": [
      "tgn:2289020",
      "tgn:1000001",
      "tgn:2001819",
      "tgn:7012149",
      "tgn:7007713",
      "tgn:7029392"
    ],
    "placetype": [
      "aat:300006075"
    ],
    "id": 2289020,
    "name:xx": "Diversion Canal"
  }
}
