{
  "geometry": {
    "type": "Point",
    "coordinates": [
      -119.05,
      44.3333
    ]
  },
  "type": "Feature",
  "properties": {
    "hierarchy": [
      "tgn:2535266",
      "tgn:1000001",
      "tgn:7012149",
      "tgn:2001708",
      "tgn:7007708",
      "tgn:7029392"
    ],
    "placetype": [
      "aat:300008798"
    ],
    "id": 2535266,
    "name:xx": "Nans Rock"
  }
}
