{
  "geometry": {
    "type": "Point",
    "coordinates": [
      113.567,
      22.119
    ]
  },
  "type": "Feature",
  "properties": {
    "hierarchy": [
      "tgn:7031818",
      "tgn:1000004",
      "tgn:7005019",
      "tgn:7029392"
    ],
    "placetype": [
      "aat:300008347"
    ],
    "id": 7031818,
    "name:xx": "Hac Sá"
  }
}
