{
  "geometry": {
    "type": "Point",
    "coordinates": [
      -76.7167,
      36.5333
    ]
  },
  "type": "Feature",
  "properties": {
    "hierarchy": [
      "tgn:2074380",
      "tgn:1000001",
      "tgn:7012149",
      "tgn:1002403",
      "tgn:7007709",
      "tgn:7029392"
    ],
    "placetype": [
      "aat:300008347",
      "aat:300387210"
    ],
    "id": 2074380,
    "name:xx": "Drum Hill"
  }
}
