{
  "geometry": {
    "type": "Point",
    "coordinates": [
      24.95,
      35.083333
    ]
  },
  "type": "Feature",
  "properties": {
    "hierarchy": [
      "tgn:7223477",
      "tgn:7002690",
      "tgn:7012056",
      "tgn:1000003",
      "tgn:1000074",
      "tgn:7029392"
    ],
    "placetype": [
      "aat:300008777"
    ],
    "id": 7223477,
    "name:xx": "Orthí Pétra"
  }
}
