{
  "geometry": {
    "type": "Point",
    "coordinates": [
      -85.9333,
      46.55
    ]
  },
  "type": "Feature",
  "properties": {
    "hierarchy": [
      "tgn:2540611",
      "tgn:2000943",
      "tgn:1000001",
      "tgn:7012149",
      "tgn:7007520",
      "tgn:7029392"
    ],
    "placetype": [
      "aat:300008680"
    ],
    "id": 2540611,
    "name:xx": "Newton Lake"
  }
}
