{
  "geometry": {
    "type": "Point",
    "coordinates": [
      78.952834,
      24.660228
    ]
  },
  "type": "Feature",
  "properties": {
    "hierarchy": [
      "tgn:7585082",
      "tgn:1000004",
      "tgn:7000198",
      "tgn:1001894",
      "tgn:7029392"
    ],
    "placetype": [
      "aat:300008347"
    ],
    "name:en": "Rādhāpur",
    "id": 7585082
  }
}
