{
  "geometry": {
    "type": "Point",
    "coordinates": [
      -122.6333,
      37.9333
    ]
  },
  "type": "Feature",
  "properties": {
    "hierarchy": [
      "tgn:2131126",
      "tgn:1000001",
      "tgn:7012149",
      "tgn:7007157",
      "tgn:7014005",
      "tgn:7029392"
    ],
    "placetype": [
      "aat:300006191"
    ],
    "id": 2131126,
    "name:xx": "Alpine Lake"
  }
}
