{
  "geometry": {
    "type": "Point",
    "coordinates": [
      -82.4167,
      30.5667
    ]
  },
  "type": "Feature",
  "properties": {
    "hierarchy": [
      "tgn:2644644",
      "tgn:2000257",
      "tgn:1000001",
      "tgn:7012149",
      "tgn:7007240",
      "tgn:7029392"
    ],
    "placetype": [
      "aat:300008347"
    ],
    "id": 2644644,
    "name:xx": "Sargent"
  }
}
