{
  "geometry": {
    "type": "Point",
    "coordinates": [
      121.35,
      41.9333
    ]
  },
  "type": "Feature",
  "properties": {
    "hierarchy": [
      "tgn:1070771",
      "tgn:1000004",
      "tgn:1001390",
      "tgn:1000111",
      "tgn:7029392"
    ],
    "placetype": [
      "aat:300008347"
    ],
    "id": 1070771,
    "name:xx": "Niuxintun"
  }
}
