{
  "geometry": {
    "type": "Point",
    "coordinates": [
      -92.0667,
      45.55
    ]
  },
  "type": "Feature",
  "properties": {
    "hierarchy": [
      "tgn:2740998",
      "tgn:2002307",
      "tgn:1000001",
      "tgn:7012149",
      "tgn:7007922",
      "tgn:7029392"
    ],
    "placetype": [
      "aat:300008680"
    ],
    "id": 2740998,
    "name:xx": "Upper Spirit Lake"
  }
}
