{
  "geometry": {
    "type": "Point",
    "coordinates": [
      -104.9333,
      33.9167
    ]
  },
  "type": "Feature",
  "properties": {
    "hierarchy": [
      "tgn:2564879",
      "tgn:1000001",
      "tgn:7012149",
      "tgn:2001442",
      "tgn:7007566",
      "tgn:7029392"
    ],
    "placetype": [
      "aat:300008761"
    ],
    "id": 2564879,
    "name:xx": "Padilla Canyon"
  }
}
