{
  "geometry": {
    "type": "Point",
    "coordinates": [
      -80.05,
      36.75
    ]
  },
  "type": "Feature",
  "properties": {
    "hierarchy": [
      "tgn:2200946",
      "tgn:1000001",
      "tgn:7012149",
      "tgn:2002167",
      "tgn:7007919",
      "tgn:7029392"
    ],
    "placetype": [
      "aat:300006191"
    ],
    "id": 2200946,
    "name:xx": "Bryant Lakes"
  }
}
