{
  "geometry": {
    "type": "Point",
    "coordinates": [
      -88.8333,
      37.2167
    ]
  },
  "type": "Feature",
  "properties": {
    "hierarchy": [
      "tgn:2152687",
      "tgn:1000001",
      "tgn:7012149",
      "tgn:2000519",
      "tgn:7007251",
      "tgn:7029392"
    ],
    "placetype": [
      "aat:300008706"
    ],
    "id": 2152687,
    "name:xx": "Bayou Creek"
  }
}
