{
  "geometry": {
    "type": "Point",
    "coordinates": [
      -69.55,
      46.7333
    ]
  },
  "type": "Feature",
  "properties": {
    "hierarchy": [
      "tgn:2737993",
      "tgn:2000919",
      "tgn:1000001",
      "tgn:7012149",
      "tgn:7007515",
      "tgn:7029392"
    ],
    "placetype": [
      "aat:300008680"
    ],
    "id": 2737993,
    "name:xx": "Ugh Lake"
  }
}
