{
  "geometry": {
    "type": "Point",
    "coordinates": [
      -106.5667,
      37.1667
    ]
  },
  "type": "Feature",
  "properties": {
    "hierarchy": [
      "tgn:2318861",
      "tgn:1000001",
      "tgn:2000202",
      "tgn:7012149",
      "tgn:7007158",
      "tgn:7029392"
    ],
    "placetype": [
      "aat:300008761"
    ],
    "id": 2318861,
    "name:xx": "Escondido, Cañon"
  }
}
