{
  "geometry": {
    "type": "Point",
    "coordinates": [
      -120.6333,
      44.1333
    ]
  },
  "type": "Feature",
  "properties": {
    "hierarchy": [
      "tgn:2641421",
      "tgn:1000001",
      "tgn:2001703",
      "tgn:7012149",
      "tgn:7007708",
      "tgn:7029392"
    ],
    "placetype": [
      "aat:300008706"
    ],
    "id": 2641421,
    "name:xx": "Sand Creek"
  }
}
