{
  "type": "FeatureCollection",
  "features": [
    {
      "geometry": {
        "type": "Point",
        "coordinates": [
          -84.8333,
          40.35
        ]
      },
      "type": "Feature",
      "properties": {
        "hierarchy": [
          "tgn:2657520",
          "tgn:1000001",
          "tgn:7012149",
          "tgn:1002513",
          "tgn:7007252",
          "tgn:7029392"
        ],
        "placetype": [
          "aat:300006075"
        ],
        "id": 2657520,
        "name:xx": "Sheffer Ditch"
      }
    },
    {
      "geometry": {
        "type": "Point",
        "coordinates": [
          -84.4667,
          33.9833
        ]
      },
      "type": "Feature",
      "properties": {
        "hierarchy": [
          "tgn:2657521",
          "tgn:1000001",
          "tgn:2000324",
          "tgn:7012149",
          "tgn:7007248",
          "tgn:7029392"
        ],
        "placetype": [
          "aat:300006191"
        ],
        "id": 2657521,
        "name:xx": "Sheffer Lake"
      }
    },
    {
      "geometry": {
        "type": "Point",
        "coordinates": [
          -85.8667,
          42.4667
        ]
      },
      "type": "Feature",
      "properties": {
        "hierarchy": [
          "tgn:2657522",
          "tgn:1002140",
          "tgn:1000001",
          "tgn:7012149",
          "tgn:7007520",
          "tgn:7029392"
        ],
        "placetype": [
          "aat:300008680"
        ],
        "id": 2657522,
        "name:xx": "Sheffer Lake"
      }
    },
    {
      "geometry": {
        "type": "Point",
        "coordinates": [
          -85.4833,
          43.1833
        ]
      },
      "type": "Feature",
      "properties": {
        "hierarchy": [
          "tgn:2657523",
          "tgn:1000001",
          "tgn:7012149",
          "tgn:1002540",
          "tgn:7007520",
          "tgn:7029392"
        ],
        "placetype": [
          "aat:300008347"
        ],
        "id": 2657523,
        "name:xx": "Sheffield"
      }
    },
    {
      "geometry": {
        "type": "Point",
        "coordinates": [
          -106.1333,
          46.3167
        ]
      },
      "type": "Feature",
      "properties": {
        "hierarchy": [
          "tgn:2657525",
          "tgn:1000001",
          "tgn:2001268",
          "tgn:7012149",
          "tgn:7007524",
          "tgn:7029392"
        ],
        "placetype": [
          "aat:300008347"
        ],
        "id": 2657525,
        "name:xx": "Sheffield"
      }
    },
    {
      "geometry": {
        "type": "Point",
        "coordinates": [
          -82.1833,
          34.1833
        ]
      },
      "type": "Feature",
      "properties": {
        "hierarchy": [
          "tgn:2657526",
          "tgn:1000001",
          "tgn:2001748",
          "tgn:7012149",
          "tgn:7007712",
          "tgn:7029392"
        ],
        "placetype": [
          "aat:300008347"
        ],
        "id": 2657526,
        "name:xx": "Sheffield"
      }
    },
    {
      "geometry": {
        "type": "Point",
        "coordinates": [
          -81.9667,
          34.9167
        ]
      },
      "type": "Feature",
      "properties": {
        "hierarchy": [
          "tgn:2657527",
          "tgn:1000001",
          "tgn:7012149",
          "tgn:2001766",
          "tgn:7007712",
          "tgn:7029392"
        ],
        "placetype": [
          "aat:300008347"
        ],
        "id": 2657527,
        "name:xx": "Sheffield"
      }
    },
    {
      "geometry": {
        "type": "Point",
        "coordinates": [
          -98.0667,
          44.4
        ]
      },
      "type": "Feature",
      "properties": {
        "hierarchy": [
          "tgn:2657528",
          "tgn:2001772",
          "tgn:1000001",
          "tgn:7012149",
          "tgn:7007713",
          "tgn:7029392"
        ],
        "placetype": [
          "aat:300008347"
        ],
        "id": 2657528,
        "name:xx": "Sheffield"
      }
    },
    {
      "geometry": {
        "type": "Point",
        "coordinates": [
          -94.25,
          32.9333
        ]
      },
      "type": "Feature",
      "properties": {
        "hierarchy": [
          "tgn:2657529",
          "tgn:1000001",
          "tgn:7012149",
          "tgn:1002244",
          "tgn:7007826",
          "tgn:7029392"
        ],
        "placetype": [
          "aat:300008347"
        ],
        "id": 2657529,
        "name:xx": "Sheffield"
      }
    }
  ]
}
