{
  "geometry": {
    "type": "Point",
    "coordinates": [
      145.9167,
      -41.05
    ]
  },
  "type": "Feature",
  "properties": {
    "hierarchy": [
      "tgn:1096432",
      "tgn:7000490",
      "tgn:1000006",
      "tgn:7001992",
      "tgn:7029392"
    ],
    "placetype": [
      "aat:300008347"
    ],
    "id": 1096432,
    "name:xx": "Burnie"
  }
}
