{
  "geometry": {
    "type": "Point",
    "coordinates": [
      -81.85,
      31.4667
    ]
  },
  "type": "Feature",
  "properties": {
    "hierarchy": [
      "tgn:2152437",
      "tgn:1000001",
      "tgn:7012149",
      "tgn:2000442",
      "tgn:7007248",
      "tgn:7029392"
    ],
    "placetype": [
      "aat:300008905"
    ],
    "id": 2152437,
    "name:xx": "Bay Pond"
  }
}
