{
  "geometry": {
    "type": "Point",
    "coordinates": [
      -113.7167,
      46.4833
    ]
  },
  "type": "Feature",
  "properties": {
    "hierarchy": [
      "tgn:2403976",
      "tgn:1000001",
      "tgn:7012149",
      "tgn:2001279",
      "tgn:7007524",
      "tgn:7029392"
    ],
    "placetype": [
      "aat:300008706"
    ],
    "id": 2403976,
    "name:xx": "Howell Creek"
  }
}
