{
  "geometry": {
    "type": "Point",
    "coordinates": [
      -78.25,
      42.0167
    ]
  },
  "type": "Feature",
  "properties": {
    "hierarchy": [
      "tgn:2161940",
      "tgn:1000001",
      "tgn:7012149",
      "tgn:7029392"
    ],
    "placetype": [
      "aat:300008699"
    ],
    "id": 2161940,
    "name:xx": "Bells Brook"
  }
}
