{
  "type": "FeatureCollection",
  "features": [
    {
      "geometry": {
        "type": "Point",
        "coordinates": [
          11.95,
          42.8
        ]
      },
      "type": "Feature",
      "properties": {
        "hierarchy": [
          "tgn:7049621",
          "tgn:7003171",
          "tgn:1000003",
          "tgn:7003125",
          "tgn:1000080",
          "tgn:7029392"
        ],
        "placetype": [
          "aat:300008795"
        ],
        "id": 7049621,
        "name:xx": "Cupa, Poggio la"
      }
    },
    {
      "geometry": {
        "type": "Point",
        "coordinates": [
          13.9,
          41.233333
        ]
      },
      "type": "Feature",
      "properties": {
        "hierarchy": [
          "tgn:7049622",
          "tgn:7003011",
          "tgn:7003005",
          "tgn:1000003",
          "tgn:1000080",
          "tgn:7029392"
        ],
        "placetype": [
          "aat:300008347"
        ],
        "id": 7049622,
        "name:xx": "Cupa"
      }
    },
    {
      "geometry": {
        "type": "Point",
        "coordinates": [
          9.15,
          41.116667
        ]
      },
      "type": "Feature",
      "properties": {
        "hierarchy": [
          "tgn:7049624",
          "tgn:7015163",
          "tgn:1000003",
          "tgn:7003121",
          "tgn:1000080",
          "tgn:7029392"
        ],
        "placetype": [
          "aat:300008699"
        ],
        "id": 7049624,
        "name:xx": "Cuoni, Riu di"
      }
    },
    {
      "geometry": {
        "type": "Point",
        "coordinates": [
          8.671944,
          40.873056
        ]
      },
      "type": "Feature",
      "properties": {
        "hierarchy": [
          "tgn:7049625",
          "tgn:7015163",
          "tgn:1000003",
          "tgn:7003121",
          "tgn:1000080",
          "tgn:7029392"
        ],
        "placetype": [
          "aat:300008795"
        ],
        "id": 7049625,
        "name:xx": "Cuntrasta, Punta"
      }
    },
    {
      "geometry": {
        "type": "Point",
        "coordinates": [
          8.1,
          45.033333
        ]
      },
      "type": "Feature",
      "properties": {
        "hierarchy": [
          "tgn:7049626",
          "tgn:7005611",
          "tgn:1000003",
          "tgn:7003120",
          "tgn:1000080",
          "tgn:7029392"
        ],
        "placetype": [
          "aat:300008347"
        ],
        "id": 7049626,
        "name:xx": "Cunico"
      }
    },
    {
      "geometry": {
        "type": "Point",
        "coordinates": [
          7.566667,
          44.516667
        ]
      },
      "type": "Feature",
      "properties": {
        "hierarchy": [
          "tgn:7049627",
          "tgn:7005126",
          "tgn:1000003",
          "tgn:7003120",
          "tgn:1000080",
          "tgn:7029392"
        ],
        "placetype": [
          "aat:300387198"
        ],
        "id": 7049627,
        "name:xx": "Provincia di Cuneo"
      }
    },
    {
      "geometry": {
        "type": "Point",
        "coordinates": [
          8.566667,
          40.366667
        ]
      },
      "type": "Feature",
      "properties": {
        "hierarchy": [
          "tgn:7049629",
          "tgn:7015163",
          "tgn:1000003",
          "tgn:7003121",
          "tgn:1000080",
          "tgn:7029392"
        ],
        "placetype": [
          "aat:300008699"
        ],
        "id": 7049629,
        "name:xx": "Cumone, Riu"
      }
    }
  ]
}
