{
  "type": "FeatureCollection",
  "features": [
    {
      "geometry": {
        "type": "Point",
        "coordinates": [
          -119.3,
          36.6167
        ]
      },
      "type": "Feature",
      "properties": {
        "hierarchy": [
          "tgn:2013123",
          "tgn:1000001",
          "tgn:7012149",
          "tgn:1002392",
          "tgn:7007157",
          "tgn:7029392"
        ],
        "placetype": [
          "aat:300008347"
        ],
        "id": 2013123,
        "name:xx": "Orange Cove"
      }
    },
    {
      "geometry": {
        "type": "Point",
        "coordinates": [
          -117.7667,
          33.8
        ]
      },
      "type": "Feature",
      "properties": {
        "hierarchy": [
          "tgn:2013124",
          "tgn:1000001",
          "tgn:7012149",
          "tgn:7007157",
          "tgn:1002748",
          "tgn:7029392"
        ],
        "placetype": [
          "aat:300008347"
        ],
        "id": 2013124,
        "name:xx": "Orange Park Acres"
      }
    },
    {
      "geometry": {
        "type": "Point",
        "coordinates": [
          -121.2167,
          38.6667
        ]
      },
      "type": "Feature",
      "properties": {
        "hierarchy": [
          "tgn:2013125",
          "tgn:1000001",
          "tgn:7012149",
          "tgn:7007157",
          "tgn:1002841",
          "tgn:7029392"
        ],
        "placetype": [
          "aat:300008347"
        ],
        "id": 2013125,
        "name:xx": "Orangevale"
      }
    },
    {
      "geometry": {
        "type": "Point",
        "coordinates": [
          -120.4333,
          34.85
        ]
      },
      "type": "Feature",
      "properties": {
        "hierarchy": [
          "tgn:2013126",
          "tgn:1000001",
          "tgn:7012149",
          "tgn:7007157",
          "tgn:1002867",
          "tgn:7029392"
        ],
        "placetype": [
          "aat:300008347"
        ],
        "id": 2013126,
        "name:xx": "Orcutt"
      }
    },
    {
      "geometry": {
        "type": "Point",
        "coordinates": [
          -122,
          39.6167
        ]
      },
      "type": "Feature",
      "properties": {
        "hierarchy": [
          "tgn:2013127",
          "tgn:1000001",
          "tgn:7012149",
          "tgn:1002409",
          "tgn:7007157",
          "tgn:7029392"
        ],
        "placetype": [
          "aat:300008347"
        ],
        "id": 2013127,
        "name:xx": "Ordbend"
      }
    },
    {
      "geometry": {
        "type": "Point",
        "coordinates": [
          -117.1667,
          34
        ]
      },
      "type": "Feature",
      "properties": {
        "hierarchy": [
          "tgn:2013128",
          "tgn:1000001",
          "tgn:7012149",
          "tgn:7007157",
          "tgn:7029392"
        ],
        "placetype": [
          "aat:300387016"
        ],
        "id": 2013128,
        "name:xx": "Ordway"
      }
    },
    {
      "geometry": {
        "type": "Point",
        "coordinates": [
          -121.5167,
          39.5833
        ]
      },
      "type": "Feature",
      "properties": {
        "hierarchy": [
          "tgn:2013129",
          "tgn:1000001",
          "tgn:1002218",
          "tgn:7012149",
          "tgn:7007157",
          "tgn:7029392"
        ],
        "placetype": [
          "aat:300008347",
          "aat:300387210"
        ],
        "id": 2013129,
        "name:xx": "Oregon City"
      }
    }
  ]
}
