{
  "geometry": {
    "type": "Point",
    "coordinates": [
      -79.2833,
      37.9333
    ]
  },
  "type": "Feature",
  "properties": {
    "hierarchy": [
      "tgn:2382331",
      "tgn:1000001",
      "tgn:7012149",
      "tgn:2002186",
      "tgn:7007919",
      "tgn:7029392"
    ],
    "placetype": [
      "aat:300008706"
    ],
    "id": 2382331,
    "name:xx": "Hays Creek"
  }
}
