{
  "geometry": {
    "type": "Point",
    "coordinates": [
      -119.9167,
      38.0833
    ]
  },
  "type": "Feature",
  "properties": {
    "hierarchy": [
      "tgn:2615828",
      "tgn:1000001",
      "tgn:7012149",
      "tgn:7007157",
      "tgn:1002957",
      "tgn:7029392"
    ],
    "placetype": [
      "aat:300008706"
    ],
    "id": 2615828,
    "name:xx": "Reynolds Creek"
  }
}
