{
  "geometry": {
    "type": "Point",
    "coordinates": [
      -133.0667,
      55.3667
    ]
  },
  "type": "Feature",
  "properties": {
    "hierarchy": [
      "tgn:2576134",
      "tgn:7006450",
      "tgn:1000001",
      "tgn:7012149",
      "tgn:2000082",
      "tgn:7029392"
    ],
    "placetype": [
      "aat:300008850"
    ],
    "id": 2576134,
    "name:xx": "Perlas Point"
  }
}
