{
  "geometry": {
    "type": "Point",
    "coordinates": [
      -83.7833,
      36.3667
    ]
  },
  "type": "Feature",
  "properties": {
    "hierarchy": [
      "tgn:2486100",
      "tgn:1000001",
      "tgn:7012149",
      "tgn:2001923",
      "tgn:7007825",
      "tgn:7029392"
    ],
    "placetype": [
      "aat:300008706"
    ],
    "id": 2486100,
    "name:xx": "Leadmine Bend Creek"
  }
}
