{
  "geometry": {
    "type": "Point",
    "coordinates": [
      -123.95,
      48.15
    ]
  },
  "type": "Feature",
  "properties": {
    "hierarchy": [
      "tgn:2735257",
      "tgn:1000001",
      "tgn:1002271",
      "tgn:7012149",
      "tgn:7007920",
      "tgn:7029392"
    ],
    "placetype": [
      "aat:300008347"
    ],
    "id": 2735257,
    "name:xx": "Twin"
  }
}
