{
  "geometry": {
    "type": "Point",
    "coordinates": [
      -118.4833,
      44.75
    ]
  },
  "type": "Feature",
  "properties": {
    "hierarchy": [
      "tgn:2603398",
      "tgn:1000001",
      "tgn:7012149",
      "tgn:2001708",
      "tgn:7007708",
      "tgn:7029392"
    ],
    "placetype": [
      "aat:300000390"
    ],
    "id": 2603398,
    "name:xx": "Quebac Mine"
  }
}
