{
  "geometry": {
    "type": "Point",
    "coordinates": [
      -98.6833,
      30.0833
    ]
  },
  "type": "Feature",
  "properties": {
    "hierarchy": [
      "tgn:1122002",
      "tgn:1000001",
      "tgn:7012149",
      "tgn:7007826",
      "tgn:7029392"
    ],
    "placetype": [
      "aat:300008707"
    ],
    "id": 1122002,
    "name:xx": "Blanco"
  }
}
