{
  "geometry": {
    "type": "Point",
    "coordinates": [
      -108.05,
      42.7667
    ]
  },
  "type": "Feature",
  "properties": {
    "hierarchy": [
      "tgn:2522369",
      "tgn:1000001",
      "tgn:7012149",
      "tgn:2002371",
      "tgn:7007923",
      "tgn:7029392"
    ],
    "placetype": [
      "aat:300008697"
    ],
    "id": 2522369,
    "name:xx": "Moone Spring"
  }
}
