{
  "geometry": {
    "type": "Point",
    "coordinates": [
      -80.6667,
      39.85
    ]
  },
  "type": "Feature",
  "properties": {
    "hierarchy": [
      "tgn:2149980",
      "tgn:1000001",
      "tgn:7012149",
      "tgn:2002276",
      "tgn:7013961",
      "tgn:7029392"
    ],
    "placetype": [
      "aat:300008699"
    ],
    "id": 2149980,
    "name:xx": "Bartletts Run"
  }
}
