{
  "geometry": {
    "type": "Point",
    "coordinates": [
      20.05,
      48.7333
    ]
  },
  "type": "Feature",
  "properties": {
    "hierarchy": [
      "tgn:1027399",
      "tgn:7027131",
      "tgn:1000003",
      "tgn:7011765",
      "tgn:7029392"
    ],
    "placetype": [
      "aat:300008347"
    ],
    "id": 1027399,
    "name:xx": "Muráň"
  }
}
