{
  "geometry": {
    "type": "Point",
    "coordinates": [
      -79.2333,
      41.8333
    ]
  },
  "type": "Feature",
  "properties": {
    "hierarchy": [
      "tgn:2360005",
      "tgn:1000001",
      "tgn:7012149",
      "tgn:1002988",
      "tgn:7007710",
      "tgn:7029392"
    ],
    "placetype": [
      "aat:300008791"
    ],
    "id": 2360005,
    "name:xx": "Grass Flat Island"
  }
}
