{
  "geometry": {
    "type": "Point",
    "coordinates": [
      121.083333,
      24.85
    ]
  },
  "type": "Feature",
  "properties": {
    "hierarchy": [
      "tgn:7468590",
      "tgn:1000004",
      "tgn:7471332",
      "tgn:1000141",
      "tgn:7029392"
    ],
    "placetype": [
      "aat:300387173"
    ],
    "id": 7468590,
    "name:xx": "Xinbu Zhen"
  }
}
