{
  "geometry": {
    "type": "Point",
    "coordinates": [
      28.1833,
      -4.7667
    ]
  },
  "type": "Feature",
  "properties": {
    "hierarchy": [
      "tgn:1088967",
      "tgn:7001242",
      "tgn:7016707",
      "tgn:1000159",
      "tgn:7029392"
    ],
    "placetype": [
      "aat:300008347"
    ],
    "id": 1088967,
    "name:xx": "Fataki"
  }
}
