{
  "geometry": {
    "type": "Point",
    "coordinates": [
      72.0833,
      34.2333
    ]
  },
  "type": "Feature",
  "properties": {
    "hierarchy": [
      "tgn:1083643",
      "tgn:7002460",
      "tgn:1000004",
      "tgn:1000133",
      "tgn:7029392"
    ],
    "placetype": [
      "aat:300008347",
      "aat:300008375"
    ],
    "id": 1083643,
    "name:xx": "Mardān"
  }
}
