{
  "geometry": {
    "type": "Point",
    "coordinates": [
      -87.7833,
      34.35
    ]
  },
  "type": "Feature",
  "properties": {
    "hierarchy": [
      "tgn:2542172",
      "tgn:7002659",
      "tgn:1000001",
      "tgn:7012149",
      "tgn:2000029",
      "tgn:7029392"
    ],
    "placetype": [
      "aat:300008347"
    ],
    "id": 2542172,
    "name:xx": "Nix"
  }
}
