{
  "geometry": {
    "type": "Point",
    "coordinates": [
      -78.0167,
      38.4667
    ]
  },
  "type": "Feature",
  "properties": {
    "hierarchy": [
      "tgn:2574308",
      "tgn:1000001",
      "tgn:7012149",
      "tgn:2002155",
      "tgn:7007919",
      "tgn:7029392"
    ],
    "placetype": [
      "aat:300006191"
    ],
    "id": 2574308,
    "name:xx": "Pelham, Lake"
  }
}
