{
  "geometry": {
    "type": "Point",
    "coordinates": [
      -96.85,
      34.5833
    ]
  },
  "type": "Feature",
  "properties": {
    "hierarchy": [
      "tgn:2462384",
      "tgn:1000001",
      "tgn:7012149",
      "tgn:7007707",
      "tgn:7029392"
    ],
    "placetype": [
      "aat:300008706"
    ],
    "id": 2462384,
    "name:xx": "Little West Blue Creek"
  }
}
