{
  "geometry": {
    "type": "Point",
    "coordinates": [
      -76.5333,
      36.7667
    ]
  },
  "type": "Feature",
  "properties": {
    "hierarchy": [
      "tgn:2229225",
      "tgn:1000001",
      "tgn:7012149",
      "tgn:7022217",
      "tgn:7007919",
      "tgn:7029392"
    ],
    "placetype": [
      "aat:300006191"
    ],
    "id": 2229225,
    "name:xx": "Cedar Lake"
  }
}
