{
  "geometry": {
    "type": "Point",
    "coordinates": [
      50.8833,
      52.55
    ]
  },
  "type": "Feature",
  "properties": {
    "hierarchy": [
      "tgn:1059163",
      "tgn:1000004",
      "tgn:1003407",
      "tgn:7018214",
      "tgn:7002435",
      "tgn:7029392"
    ],
    "placetype": [
      "aat:300008347"
    ],
    "id": 1059163,
    "name:xx": "Samovol'no-Ivanovka"
  }
}
