{
  "geometry": {
    "type": "Point",
    "coordinates": [
      79.525642,
      27.744636
    ]
  },
  "type": "Feature",
  "properties": {
    "hierarchy": [
      "tgn:7562926",
      "tgn:1000004",
      "tgn:7000198",
      "tgn:7016722",
      "tgn:7029392"
    ],
    "placetype": [
      "aat:300008347"
    ],
    "name:en": "Habibullāhpur Amritpur",
    "id": 7562926
  }
}
