{
  "geometry": {
    "type": "Point",
    "coordinates": [
      -94.9667,
      47.1833
    ]
  },
  "type": "Feature",
  "properties": {
    "hierarchy": [
      "tgn:2347567",
      "tgn:1000001",
      "tgn:7012149",
      "tgn:2001027",
      "tgn:7007521",
      "tgn:7029392"
    ],
    "placetype": [
      "aat:300008680"
    ],
    "id": 2347567,
    "name:xx": "George, Lake"
  }
}
