{
  "type": "FeatureCollection",
  "features": [
    {
      "geometry": {
        "type": "Point",
        "coordinates": [
          10.633333,
          51.45
        ]
      },
      "type": "Feature",
      "properties": {
        "hierarchy": [
          "tgn:7125920",
          "tgn:1000003",
          "tgn:7003689",
          "tgn:7000084",
          "tgn:7029392"
        ],
        "placetype": [
          "aat:300008347"
        ],
        "id": 7125920,
        "name:xx": "Oberdorf"
      }
    },
    {
      "geometry": {
        "type": "Point",
        "coordinates": [
          7.366667,
          50.866667
        ]
      },
      "type": "Feature",
      "properties": {
        "hierarchy": [
          "tgn:7125921",
          "tgn:1000003",
          "tgn:7003677",
          "tgn:7000084",
          "tgn:7029392"
        ],
        "placetype": [
          "aat:300008347"
        ],
        "id": 7125921,
        "name:xx": "Oberdorf"
      }
    },
    {
      "geometry": {
        "type": "Point",
        "coordinates": [
          12.516667,
          50.883333
        ]
      },
      "type": "Feature",
      "properties": {
        "hierarchy": [
          "tgn:7125922",
          "tgn:1000003",
          "tgn:7003685",
          "tgn:7000084",
          "tgn:7029392"
        ],
        "placetype": [
          "aat:300008347"
        ],
        "id": 7125922,
        "name:xx": "Oberdorf"
      }
    },
    {
      "geometry": {
        "type": "Point",
        "coordinates": [
          14.683333,
          50.85
        ]
      },
      "type": "Feature",
      "properties": {
        "hierarchy": [
          "tgn:7125924",
          "tgn:1000003",
          "tgn:7003685",
          "tgn:7000084",
          "tgn:7029392"
        ],
        "placetype": [
          "aat:300008347"
        ],
        "id": 7125924,
        "name:xx": "Oberdorf"
      }
    },
    {
      "geometry": {
        "type": "Point",
        "coordinates": [
          12.75,
          50.683333
        ]
      },
      "type": "Feature",
      "properties": {
        "hierarchy": [
          "tgn:7125925",
          "tgn:1000003",
          "tgn:7003685",
          "tgn:7000084",
          "tgn:7029392"
        ],
        "placetype": [
          "aat:300008347"
        ],
        "id": 7125925,
        "name:xx": "Oberdorf"
      }
    },
    {
      "geometry": {
        "type": "Point",
        "coordinates": [
          11.366667,
          50.683333
        ]
      },
      "type": "Feature",
      "properties": {
        "hierarchy": [
          "tgn:7125926",
          "tgn:1000003",
          "tgn:7003689",
          "tgn:7000084",
          "tgn:7029392"
        ],
        "placetype": [
          "aat:300008347"
        ],
        "id": 7125926,
        "name:xx": "Oberdorf"
      }
    },
    {
      "geometry": {
        "type": "Point",
        "coordinates": [
          12.516667,
          49.2
        ]
      },
      "type": "Feature",
      "properties": {
        "hierarchy": [
          "tgn:7125927",
          "tgn:7003669",
          "tgn:1000003",
          "tgn:7000084",
          "tgn:7029392"
        ],
        "placetype": [
          "aat:300008347"
        ],
        "id": 7125927,
        "name:xx": "Oberdorf"
      }
    },
    {
      "geometry": {
        "type": "Point",
        "coordinates": [
          10.35,
          48.866667
        ]
      },
      "type": "Feature",
      "properties": {
        "hierarchy": [
          "tgn:7125928",
          "tgn:7003692",
          "tgn:1000003",
          "tgn:7000084",
          "tgn:7029392"
        ],
        "placetype": [
          "aat:300008347"
        ],
        "id": 7125928,
        "name:xx": "Oberdorf"
      }
    },
    {
      "geometry": {
        "type": "Point",
        "coordinates": [
          11.316667,
          48.433333
        ]
      },
      "type": "Feature",
      "properties": {
        "hierarchy": [
          "tgn:7125929",
          "tgn:7003669",
          "tgn:1000003",
          "tgn:7000084",
          "tgn:7029392"
        ],
        "placetype": [
          "aat:300008347"
        ],
        "id": 7125929,
        "name:xx": "Oberdorf"
      }
    }
  ]
}
