{
  "type": "FeatureCollection",
  "features": [
    {
      "geometry": {
        "type": "Point",
        "coordinates": [
          -72.183333,
          -35.15
        ]
      },
      "type": "Feature",
      "properties": {
        "hierarchy": [
          "tgn:7312330",
          "tgn:1001705",
          "tgn:1000049",
          "tgn:1000002",
          "tgn:7029392"
        ],
        "placetype": [
          "aat:300387200"
        ],
        "id": 7312330,
        "name:xx": "La Rinconada"
      }
    },
    {
      "geometry": {
        "type": "Point",
        "coordinates": [
          -71.233333,
          -33.566667
        ]
      },
      "type": "Feature",
      "properties": {
        "hierarchy": [
          "tgn:7312332",
          "tgn:1001708",
          "tgn:1000049",
          "tgn:1000002",
          "tgn:7029392"
        ],
        "placetype": [
          "aat:300387200"
        ],
        "id": 7312332,
        "name:xx": "La Rinconada"
      }
    },
    {
      "geometry": {
        "type": "Point",
        "coordinates": [
          -69.2,
          -18.083333
        ]
      },
      "type": "Feature",
      "properties": {
        "hierarchy": [
          "tgn:7312333",
          "tgn:7002464",
          "tgn:1000049",
          "tgn:1000002",
          "tgn:7029392"
        ],
        "placetype": [
          "aat:300387200"
        ],
        "id": 7312333,
        "name:xx": "La Rinconada"
      }
    },
    {
      "geometry": {
        "type": "Point",
        "coordinates": [
          -71.533333,
          -33.75
        ]
      },
      "type": "Feature",
      "properties": {
        "hierarchy": [
          "tgn:7312334",
          "tgn:1001708",
          "tgn:1000049",
          "tgn:1000002",
          "tgn:7029392"
        ],
        "placetype": [
          "aat:300000206"
        ],
        "id": 7312334,
        "name:xx": "La Rinconada"
      }
    },
    {
      "geometry": {
        "type": "Point",
        "coordinates": [
          -70.516667,
          -23.466667
        ]
      },
      "type": "Feature",
      "properties": {
        "hierarchy": [
          "tgn:7312335",
          "tgn:7016598",
          "tgn:1000049",
          "tgn:1000002",
          "tgn:7029392"
        ],
        "placetype": [
          "aat:300000517"
        ],
        "id": 7312335,
        "name:xx": "La Rinconada"
      }
    },
    {
      "geometry": {
        "type": "Point",
        "coordinates": [
          -71.7,
          -34.766667
        ]
      },
      "type": "Feature",
      "properties": {
        "hierarchy": [
          "tgn:7312336",
          "tgn:1001695",
          "tgn:1000049",
          "tgn:1000002",
          "tgn:7029392"
        ],
        "placetype": [
          "aat:300008777"
        ],
        "id": 7312336,
        "name:xx": "La Riconada, Alto"
      }
    },
    {
      "geometry": {
        "type": "Point",
        "coordinates": [
          -74.833333,
          -52.266667
        ]
      },
      "type": "Feature",
      "properties": {
        "hierarchy": [
          "tgn:7312337",
          "tgn:1001702",
          "tgn:1000049",
          "tgn:1000002",
          "tgn:7029392"
        ],
        "placetype": [
          "aat:300132317"
        ],
        "id": 7312337,
        "name:xx": "La Ría, Estero"
      }
    },
    {
      "geometry": {
        "type": "Point",
        "coordinates": [
          -67.25,
          -23.716667
        ]
      },
      "type": "Feature",
      "properties": {
        "hierarchy": [
          "tgn:7312338",
          "tgn:7016598",
          "tgn:1000049",
          "tgn:1000002",
          "tgn:7029392"
        ],
        "placetype": [
          "aat:300008805"
        ],
        "id": 7312338,
        "name:xx": "Lari, Pampa de"
      }
    },
    {
      "geometry": {
        "type": "Point",
        "coordinates": [
          -67.4,
          -23.666667
        ]
      },
      "type": "Feature",
      "properties": {
        "hierarchy": [
          "tgn:7312339",
          "tgn:7016598",
          "tgn:1000049",
          "tgn:1000002",
          "tgn:7029392"
        ],
        "placetype": [
          "aat:300008795"
        ],
        "id": 7312339,
        "name:xx": "Lari, Alto del"
      }
    }
  ]
}
