{
  "geometry": {
    "type": "Point",
    "coordinates": [
      77.783971,
      30.47485
    ]
  },
  "type": "Feature",
  "properties": {
    "hierarchy": [
      "tgn:7590978",
      "tgn:1000004",
      "tgn:7000198",
      "tgn:7031786",
      "tgn:7029392"
    ],
    "placetype": [
      "aat:300008347"
    ],
    "name:en": "Rasūlpur",
    "id": 7590978
  }
}
