{
  "geometry": {
    "type": "Point",
    "coordinates": [
      -83.7333,
      34.5167
    ]
  },
  "type": "Feature",
  "properties": {
    "hierarchy": [
      "tgn:2230666",
      "tgn:1000001",
      "tgn:7012149",
      "tgn:2000445",
      "tgn:7007248",
      "tgn:7029392"
    ],
    "placetype": [
      "aat:300008347"
    ],
    "id": 2230666,
    "name:xx": "Centerside"
  }
}
