{
  "geometry": {
    "type": "Point",
    "coordinates": [
      -81.9167,
      38.5333
    ]
  },
  "type": "Feature",
  "properties": {
    "hierarchy": [
      "tgn:2118108",
      "tgn:1000001",
      "tgn:7012149",
      "tgn:2002289",
      "tgn:7013961",
      "tgn:7029392"
    ],
    "placetype": [
      "aat:300008347"
    ],
    "id": 2118108,
    "name:xx": "Eleanor"
  }
}
