{
  "geometry": {
    "type": "Point",
    "coordinates": [
      -123.15,
      39.0833
    ]
  },
  "type": "Feature",
  "properties": {
    "hierarchy": [
      "tgn:2738078",
      "tgn:1000001",
      "tgn:7012149",
      "tgn:7007157",
      "tgn:2000185",
      "tgn:7029392"
    ],
    "placetype": [
      "aat:300008347"
    ],
    "id": 2738078,
    "name:xx": "Ukiah Rancheria"
  }
}
