{
  "geometry": {
    "type": "Point",
    "coordinates": [
      -90.9833,
      36.8333
    ]
  },
  "type": "Feature",
  "properties": {
    "hierarchy": [
      "tgn:2356278",
      "tgn:1000001",
      "tgn:2001181",
      "tgn:7012149",
      "tgn:7007523",
      "tgn:7029392"
    ],
    "placetype": [
      "aat:300008761"
    ],
    "id": 2356278,
    "name:xx": "Gooseneck Hollow"
  }
}
