{
  "geometry": {
    "type": "Point",
    "coordinates": [
      -72.6167,
      43.3667
    ]
  },
  "type": "Feature",
  "properties": {
    "hierarchy": [
      "tgn:2362621",
      "tgn:1000001",
      "tgn:2002136",
      "tgn:7012149",
      "tgn:7007828",
      "tgn:7029392"
    ],
    "placetype": [
      "aat:300008699"
    ],
    "id": 2362621,
    "name:xx": "Great Brook"
  }
}
