{
  "geometry": {
    "type": "Point",
    "coordinates": [
      -88.0667,
      38.5167
    ]
  },
  "type": "Feature",
  "properties": {
    "hierarchy": [
      "tgn:2657606",
      "tgn:1000001",
      "tgn:2000505",
      "tgn:7012149",
      "tgn:7007251",
      "tgn:7029392"
    ],
    "placetype": [
      "aat:300008706"
    ],
    "id": 2657606,
    "name:xx": "Shelby Creek"
  }
}
