{
  "geometry": {
    "type": "Point",
    "coordinates": [
      -100.95,
      48.9833
    ]
  },
  "type": "Feature",
  "properties": {
    "hierarchy": [
      "tgn:2739004",
      "tgn:7020393",
      "tgn:1000001",
      "tgn:7012149",
      "tgn:7007705",
      "tgn:7029392"
    ],
    "placetype": [
      "aat:300006191"
    ],
    "id": 2739004,
    "name:xx": "Unit 357 Reservoir"
  }
}
