{
  "geometry": {
    "type": "Point",
    "coordinates": [
      -94.55,
      18.116667
    ]
  },
  "type": "Feature",
  "properties": {
    "hierarchy": [
      "tgn:7377795",
      "tgn:1000001",
      "tgn:7005599",
      "tgn:7005560",
      "tgn:7029392"
    ],
    "placetype": [
      "aat:300008347"
    ],
    "id": 7377795,
    "name:xx": "Las Cánticas"
  }
}
