{
  "geometry": {
    "type": "Point",
    "coordinates": [
      -79.7167,
      41.4667
    ]
  },
  "type": "Feature",
  "properties": {
    "hierarchy": [
      "tgn:2214333",
      "tgn:1000001",
      "tgn:7012149",
      "tgn:1002971",
      "tgn:7007710",
      "tgn:7029392"
    ],
    "placetype": [
      "aat:300008699"
    ],
    "id": 2214333,
    "name:xx": "Calaboose Run"
  }
}
