{
  "type": "FeatureCollection",
  "features": [
    {
      "geometry": {
        "type": "Point",
        "coordinates": [
          -5.75,
          54.783333
        ]
      },
      "type": "Feature",
      "properties": {
        "hierarchy": [
          "tgn:7446720",
          "tgn:7002448",
          "tgn:7019159",
          "tgn:1000003",
          "tgn:7008591",
          "tgn:7029392"
        ],
        "placetype": [
          "aat:300387502"
        ],
        "name:en": "Red Hall",
        "id": 7446720
      }
    },
    {
      "geometry": {
        "type": "Point",
        "coordinates": [
          1.016667,
          52.35
        ]
      },
      "type": "Feature",
      "properties": {
        "hierarchy": [
          "tgn:7446721",
          "tgn:7002445",
          "tgn:1000003",
          "tgn:7008185",
          "tgn:7008591",
          "tgn:7029392"
        ],
        "placetype": [
          "aat:300008187"
        ],
        "name:en": "Redgrave Park",
        "id": 7446721
      }
    },
    {
      "geometry": {
        "type": "Point",
        "coordinates": [
          1,
          52.366667
        ]
      },
      "type": "Feature",
      "properties": {
        "hierarchy": [
          "tgn:7446722",
          "tgn:7002445",
          "tgn:1000003",
          "tgn:7008185",
          "tgn:7008591",
          "tgn:7029392"
        ],
        "placetype": [
          "aat:300008347"
        ],
        "name:en": "Redgrave",
        "id": 7446722
      }
    },
    {
      "geometry": {
        "type": "Point",
        "coordinates": [
          -2.533333,
          56.016667
        ]
      },
      "type": "Feature",
      "properties": {
        "hierarchy": [
          "tgn:7446723",
          "tgn:7002444",
          "tgn:7019115",
          "tgn:1000003",
          "tgn:7008591",
          "tgn:7029392"
        ],
        "placetype": [
          "aat:300008808"
        ],
        "name:en": "Red Gable",
        "id": 7446723
      }
    },
    {
      "geometry": {
        "type": "Point",
        "coordinates": [
          -3,
          55.433333
        ]
      },
      "type": "Feature",
      "properties": {
        "hierarchy": [
          "tgn:7446724",
          "tgn:7002444",
          "tgn:1000003",
          "tgn:7008072",
          "tgn:7008591",
          "tgn:7029392"
        ],
        "placetype": [
          "aat:300004792"
        ],
        "name:en": "Redfordgreen",
        "id": 7446724
      }
    },
    {
      "geometry": {
        "type": "Point",
        "coordinates": [
          -2.2,
          55.116667
        ]
      },
      "type": "Feature",
      "properties": {
        "hierarchy": [
          "tgn:7446725",
          "tgn:7002445",
          "tgn:1000003",
          "tgn:7008165",
          "tgn:7008591",
          "tgn:7029392"
        ],
        "placetype": [
          "aat:300007783"
        ],
        "name:en": "Redesmouth",
        "id": 7446725
      }
    },
    {
      "geometry": {
        "type": "Point",
        "coordinates": [
          0.633333,
          52.166667
        ]
      },
      "type": "Feature",
      "properties": {
        "hierarchy": [
          "tgn:7446727",
          "tgn:7002445",
          "tgn:1000003",
          "tgn:7008185",
          "tgn:7008591",
          "tgn:7029392"
        ],
        "placetype": [
          "aat:300008347"
        ],
        "name:en": "Rede",
        "id": 7446727
      }
    }
  ]
}
