{
  "geometry": {
    "type": "Point",
    "coordinates": [
      77.4167,
      43.1667
    ]
  },
  "type": "Feature",
  "properties": {
    "hierarchy": [
      "tgn:1101373",
      "tgn:1003353",
      "tgn:1000004",
      "tgn:7014786",
      "tgn:7029392"
    ],
    "placetype": [
      "aat:300008189"
    ],
    "id": 1101373,
    "name:xx": "Alma-Atinskij zapovednik"
  }
}
