{
  "geometry": {
    "type": "Point",
    "coordinates": [
      -99.1833,
      36.9667
    ]
  },
  "type": "Feature",
  "properties": {
    "hierarchy": [
      "tgn:2533579",
      "tgn:1000001",
      "tgn:7012149",
      "tgn:7029392"
    ],
    "placetype": [
      "aat:300008706"
    ],
    "id": 2533579,
    "name:xx": "Mustang Creek"
  }
}
