{
  "geometry": {
    "type": "Point",
    "coordinates": [
      -111.7667,
      32.7667
    ]
  },
  "type": "Feature",
  "properties": {
    "hierarchy": [
      "tgn:2644020",
      "tgn:1000001",
      "tgn:7006451",
      "tgn:7012149",
      "tgn:2000101",
      "tgn:7029392"
    ],
    "placetype": [
      "aat:300008701"
    ],
    "id": 2644020,
    "name:xx": "Santa Cruz Wash"
  }
}
