{
  "type": "FeatureCollection",
  "features": [
    {
      "geometry": {
        "type": "Point",
        "coordinates": [
          124.75,
          9.1667
        ]
      },
      "type": "Feature",
      "properties": {
        "hierarchy": [
          "tgn:7005901",
          "tgn:1000004",
          "tgn:1000135",
          "tgn:7029392"
        ],
        "placetype": [
          "aat:300387064",
          "aat:300000774"
        ],
        "id": 7005901,
        "name:xx": "Camiguin"
      }
    },
    {
      "geometry": {
        "type": "Point",
        "coordinates": [
          9.2,
          45.466667
        ]
      },
      "type": "Feature",
      "properties": {
        "hierarchy": [
          "tgn:7005903",
          "tgn:7003150",
          "tgn:1000003",
          "tgn:7003237",
          "tgn:1000080",
          "tgn:7029392"
        ],
        "placetype": [
          "aat:300008347",
          "aat:300387218",
          "aat:300008389",
          "aat:300387308",
          "aat:300005135",
          "aat:300387512",
          "aat:300387223",
          "aat:300387235",
          "aat:300387220",
          "aat:300387284",
          "aat:300387270",
          "aat:300387302",
          "aat:300387293"
        ],
        "name:en": "Milan",
        "id": 7005903
      }
    },
    {
      "geometry": {
        "type": "Point",
        "coordinates": [
          9.1667,
          45.5167
        ]
      },
      "type": "Feature",
      "properties": {
        "hierarchy": [
          "tgn:7005904",
          "tgn:7003150",
          "tgn:1000003",
          "tgn:7003237",
          "tgn:7005903",
          "tgn:1000080",
          "tgn:7029392"
        ],
        "placetype": [
          "aat:300387336"
        ],
        "id": 7005904,
        "name:xx": "Affori"
      }
    },
    {
      "geometry": {
        "type": "Point",
        "coordinates": [
          9.25,
          45.5167
        ]
      },
      "type": "Feature",
      "properties": {
        "hierarchy": [
          "tgn:7005905",
          "tgn:7003150",
          "tgn:1000003",
          "tgn:7003237",
          "tgn:7005903",
          "tgn:1000080",
          "tgn:7029392"
        ],
        "placetype": [
          "aat:300008347",
          "aat:300387336"
        ],
        "id": 7005905,
        "name:xx": "Crescenzago"
      }
    },
    {
      "geometry": {
        "type": "Point",
        "coordinates": [
          134.4667,
          7.3667
        ]
      },
      "type": "Feature",
      "properties": {
        "hierarchy": [
          "tgn:7005906",
          "tgn:7005668",
          "tgn:1010206",
          "tgn:1000006",
          "tgn:7029392"
        ],
        "placetype": [
          "aat:300008791"
        ],
        "id": 7005906,
        "name:xx": "Arakabesan"
      }
    }
  ]
}
