{
  "geometry": {
    "type": "Point",
    "coordinates": [
      13.1667,
      32.8333
    ]
  },
  "type": "Feature",
  "properties": {
    "hierarchy": [
      "tgn:7000623",
      "tgn:7001242",
      "tgn:1000172",
      "tgn:7029392"
    ],
    "placetype": [
      "aat:300387064",
      "aat:300000774"
    ],
    "name:en": "Tripoli",
    "id": 7000623
  }
}
