{
  "geometry": {
    "type": "Point",
    "coordinates": [
      21.76278,
      41.77583
    ]
  },
  "type": "Feature",
  "properties": {
    "hierarchy": [
      "tgn:7017390",
      "tgn:1000003",
      "tgn:7006667",
      "tgn:7029392"
    ],
    "placetype": [
      "aat:300387064",
      "aat:300265612",
      "aat:300387081"
    ],
    "id": 7017390,
    "name:xx": "Veles"
  }
}
