{
  "geometry": {
    "type": "Point",
    "coordinates": [
      -85.5167,
      30.1667
    ]
  },
  "type": "Feature",
  "properties": {
    "hierarchy": [
      "tgn:2185154",
      "tgn:2000258",
      "tgn:1000001",
      "tgn:7012149",
      "tgn:7007240",
      "tgn:7029392"
    ],
    "placetype": [
      "aat:300008706"
    ],
    "id": 2185154,
    "name:xx": "Boggy Creek"
  }
}
