{
  "geometry": {
    "type": "Point",
    "coordinates": [
      -61.6667,
      10.6667
    ]
  },
  "type": "Feature",
  "properties": {
    "hierarchy": [
      "tgn:1012319",
      "tgn:1008058",
      "tgn:1001914",
      "tgn:1000002",
      "tgn:1000059",
      "tgn:7029392"
    ],
    "placetype": [
      "aat:300386846"
    ],
    "id": 1012319,
    "name:xx": "Piedras, Punta"
  }
}
