{
  "geometry": {
    "type": "Point",
    "coordinates": [
      -98.4167,
      44.0667
    ]
  },
  "type": "Feature",
  "properties": {
    "hierarchy": [
      "tgn:2097310",
      "tgn:1000001",
      "tgn:2001806",
      "tgn:7012149",
      "tgn:7007713",
      "tgn:7029392"
    ],
    "placetype": [
      "aat:300008347"
    ],
    "id": 2097310,
    "name:xx": "Lane"
  }
}
