{
  "geometry": {
    "type": "Point",
    "coordinates": [
      -122.6333,
      44.8833
    ]
  },
  "type": "Feature",
  "properties": {
    "hierarchy": [
      "tgn:2405886",
      "tgn:1000001",
      "tgn:7012149",
      "tgn:1002636",
      "tgn:7007708",
      "tgn:7029392"
    ],
    "placetype": [
      "aat:300008347"
    ],
    "id": 2405886,
    "name:xx": "Hullt"
  }
}
