{
  "geometry": {
    "type": "Point",
    "coordinates": [
      -146.35,
      64.7167
    ]
  },
  "type": "Feature",
  "properties": {
    "hierarchy": [
      "tgn:2317320",
      "tgn:7006450",
      "tgn:1000001",
      "tgn:7019674",
      "tgn:7012149",
      "tgn:7029392"
    ],
    "placetype": [
      "aat:300008706"
    ],
    "id": 2317320,
    "name:xx": "Emory Creek"
  }
}
