{
  "geometry": {
    "type": "Point",
    "coordinates": [
      -133.6833,
      57.7833
    ]
  },
  "type": "Feature",
  "properties": {
    "hierarchy": [
      "tgn:2589381",
      "tgn:7006450",
      "tgn:1000001",
      "tgn:7012149",
      "tgn:7029392"
    ],
    "placetype": [
      "aat:300008850"
    ],
    "id": 2589381,
    "name:xx": "Coke Pit, Point"
  }
}
