{
  "geometry": {
    "type": "Point",
    "coordinates": [
      -94.05,
      31.9167
    ]
  },
  "type": "Feature",
  "properties": {
    "hierarchy": [
      "tgn:2779150",
      "tgn:1000001",
      "tgn:7012149",
      "tgn:2002073",
      "tgn:7007826",
      "tgn:7029392"
    ],
    "placetype": [
      "aat:300008706"
    ],
    "id": 2779150,
    "name:xx": "Wolf Creek"
  }
}
