{
  "type": "FeatureCollection",
  "features": [
    {
      "geometry": {
        "type": "Point",
        "coordinates": [
          4.966667,
          50.933333
        ]
      },
      "type": "Feature",
      "properties": {
        "hierarchy": [
          "tgn:7254813",
          "tgn:7003461",
          "tgn:1000003",
          "tgn:1000063",
          "tgn:7018236",
          "tgn:7029392"
        ],
        "placetype": [
          "aat:300008347"
        ],
        "id": 7254813,
        "name:xx": "Veurenberg"
      }
    },
    {
      "geometry": {
        "type": "Point",
        "coordinates": [
          5.305651,
          50.763815
        ]
      },
      "type": "Feature",
      "properties": {
        "hierarchy": [
          "tgn:7254814",
          "tgn:7003461",
          "tgn:1000003",
          "tgn:1000063",
          "tgn:7018236",
          "tgn:7029392"
        ],
        "placetype": [
          "aat:300008347"
        ],
        "id": 7254814,
        "name:xx": "Veulen"
      }
    },
    {
      "geometry": {
        "type": "Point",
        "coordinates": [
          4.933333,
          50.966667
        ]
      },
      "type": "Feature",
      "properties": {
        "hierarchy": [
          "tgn:7254816",
          "tgn:7003456",
          "tgn:1000003",
          "tgn:1000063",
          "tgn:7018236",
          "tgn:7029392"
        ],
        "placetype": [
          "aat:300008347"
        ],
        "id": 7254816,
        "name:xx": "Veugelberg"
      }
    },
    {
      "geometry": {
        "type": "Point",
        "coordinates": [
          4.633333,
          50.766667
        ]
      },
      "type": "Feature",
      "properties": {
        "hierarchy": [
          "tgn:7254817",
          "tgn:7018239",
          "tgn:1000003",
          "tgn:1000063",
          "tgn:7018236",
          "tgn:7029392"
        ],
        "placetype": [
          "aat:300008347"
        ],
        "id": 7254817,
        "name:xx": "Vetzaat"
      }
    },
    {
      "geometry": {
        "type": "Point",
        "coordinates": [
          5.2,
          50.2
        ]
      },
      "type": "Feature",
      "properties": {
        "hierarchy": [
          "tgn:7254818",
          "tgn:7003466",
          "tgn:1000003",
          "tgn:1000063",
          "tgn:4012014",
          "tgn:7029392"
        ],
        "placetype": [
          "aat:300008347"
        ],
        "id": 7254818,
        "name:xx": "Vesty"
      }
    },
    {
      "geometry": {
        "type": "Point",
        "coordinates": [
          5.416667,
          50
        ]
      },
      "type": "Feature",
      "properties": {
        "hierarchy": [
          "tgn:7254819",
          "tgn:7003465",
          "tgn:1000003",
          "tgn:1000063",
          "tgn:4012014",
          "tgn:7029392"
        ],
        "placetype": [
          "aat:300008863"
        ],
        "id": 7254819,
        "name:xx": "Vesqueville, Bois de"
      }
    }
  ]
}
