{
  "geometry": {
    "type": "Point",
    "coordinates": [
      13.883333,
      53.25
    ]
  },
  "type": "Feature",
  "properties": {
    "hierarchy": [
      "tgn:7200097",
      "tgn:7000096",
      "tgn:1000003",
      "tgn:7000084",
      "tgn:7029392"
    ],
    "placetype": [
      "aat:300000206"
    ],
    "id": 7200097,
    "name:xx": "Dree Brök"
  }
}
