{
  "geometry": {
    "type": "Point",
    "coordinates": [
      -98.45,
      31.3333
    ]
  },
  "type": "Feature",
  "properties": {
    "hierarchy": [
      "tgn:2159380",
      "tgn:1000001",
      "tgn:7012149",
      "tgn:2002042",
      "tgn:7007826",
      "tgn:7029392"
    ],
    "placetype": [
      "aat:300008706"
    ],
    "id": 2159380,
    "name:xx": "Bee Cove Creek"
  }
}
