{
  "geometry": {
    "type": "Point",
    "coordinates": [
      -106.0167,
      33.65
    ]
  },
  "type": "Feature",
  "properties": {
    "hierarchy": [
      "tgn:2666625",
      "tgn:1000001",
      "tgn:7012149",
      "tgn:2001442",
      "tgn:7007566",
      "tgn:7029392"
    ],
    "placetype": [
      "aat:300006191"
    ],
    "id": 2666625,
    "name:xx": "Sixshooter Tank"
  }
}
