{
  "geometry": {
    "type": "Point",
    "coordinates": [
      -81.8167,
      26.3167
    ]
  },
  "type": "Feature",
  "properties": {
    "hierarchy": [
      "tgn:2186816",
      "tgn:1000001",
      "tgn:7012149",
      "tgn:1002582",
      "tgn:7007240",
      "tgn:7029392"
    ],
    "placetype": [
      "aat:300008347"
    ],
    "id": 2186816,
    "name:xx": "Bonita Shores"
  }
}
