{
  "geometry": {
    "type": "Point",
    "coordinates": [
      44.55,
      1.6333
    ]
  },
  "type": "Feature",
  "properties": {
    "hierarchy": [
      "tgn:1092710",
      "tgn:7001242",
      "tgn:1001747",
      "tgn:1000192",
      "tgn:7029392"
    ],
    "placetype": [
      "aat:300008347"
    ],
    "id": 1092710,
    "name:xx": "Golweyn"
  }
}
