{
  "geometry": {
    "type": "Point",
    "coordinates": [
      -113.3167,
      46.55
    ]
  },
  "type": "Feature",
  "properties": {
    "hierarchy": [
      "tgn:2474997",
      "tgn:1000001",
      "tgn:7012149",
      "tgn:2001279",
      "tgn:7007524",
      "tgn:7029392"
    ],
    "placetype": [
      "aat:300008706"
    ],
    "id": 2474997,
    "name:xx": "Lower Willow Creek"
  }
}
