{
  "geometry": {
    "type": "Point",
    "coordinates": [
      31.22357,
      30.027685
    ]
  },
  "type": "Feature",
  "properties": {
    "hierarchy": [
      "tgn:7529789",
      "tgn:7001242",
      "tgn:7016833",
      "tgn:1001083",
      "tgn:7029392"
    ],
    "placetype": [
      "aat:300004792"
    ],
    "id": 7529789,
    "name:xx": "Nādī an Nīl"
  }
}
