{
  "type": "FeatureCollection",
  "features": [
    {
      "geometry": {
        "type": "Point",
        "coordinates": [
          -117.4,
          38.85
        ]
      },
      "type": "Feature",
      "properties": {
        "hierarchy": [
          "tgn:2143770",
          "tgn:1000001",
          "tgn:2001418",
          "tgn:7012149",
          "tgn:7007526",
          "tgn:7029392"
        ],
        "placetype": [
          "aat:300008706"
        ],
        "id": 2143770,
        "name:xx": "Bakeoven Creek"
      }
    },
    {
      "geometry": {
        "type": "Point",
        "coordinates": [
          -75.4833,
          39.35
        ]
      },
      "type": "Feature",
      "properties": {
        "hierarchy": [
          "tgn:2143771",
          "tgn:1002538",
          "tgn:1000001",
          "tgn:7012149",
          "tgn:7007239",
          "tgn:7029392"
        ],
        "placetype": [
          "aat:300008850"
        ],
        "id": 2143771,
        "name:xx": "Bakeoven Point"
      }
    },
    {
      "geometry": {
        "type": "Point",
        "coordinates": [
          -93.5333,
          33.45
        ]
      },
      "type": "Feature",
      "properties": {
        "hierarchy": [
          "tgn:2143772",
          "tgn:1000001",
          "tgn:7016172",
          "tgn:7012149",
          "tgn:2000141",
          "tgn:7029392"
        ],
        "placetype": [
          "aat:300008347"
        ],
        "id": 2143772,
        "name:xx": "Baker"
      }
    },
    {
      "geometry": {
        "type": "Point",
        "coordinates": [
          -92.5833,
          35.9
        ]
      },
      "type": "Feature",
      "properties": {
        "hierarchy": [
          "tgn:2143773",
          "tgn:1000001",
          "tgn:7016172",
          "tgn:7012149",
          "tgn:2000169",
          "tgn:7029392"
        ],
        "placetype": [
          "aat:300008347"
        ],
        "id": 2143773,
        "name:xx": "Baker"
      }
    },
    {
      "geometry": {
        "type": "Point",
        "coordinates": [
          -87.3,
          39.1167
        ]
      },
      "type": "Feature",
      "properties": {
        "hierarchy": [
          "tgn:2143774",
          "tgn:1000001",
          "tgn:7012149",
          "tgn:2000556",
          "tgn:7007252",
          "tgn:7029392"
        ],
        "placetype": [
          "aat:300008347"
        ],
        "id": 2143774,
        "name:xx": "Baker"
      }
    },
    {
      "geometry": {
        "type": "Point",
        "coordinates": [
          -95.55,
          39.75
        ]
      },
      "type": "Feature",
      "properties": {
        "hierarchy": [
          "tgn:2143775",
          "tgn:1000001",
          "tgn:2000666",
          "tgn:7012149",
          "tgn:7007254",
          "tgn:7029392"
        ],
        "placetype": [
          "aat:300008347"
        ],
        "id": 2143775,
        "name:xx": "Baker"
      }
    },
    {
      "geometry": {
        "type": "Point",
        "coordinates": [
          -94.5167,
          47.1167
        ]
      },
      "type": "Feature",
      "properties": {
        "hierarchy": [
          "tgn:2143776",
          "tgn:1000001",
          "tgn:2001009",
          "tgn:7012149",
          "tgn:7007521",
          "tgn:7029392"
        ],
        "placetype": [
          "aat:300008347"
        ],
        "id": 2143776,
        "name:xx": "Baker"
      }
    },
    {
      "geometry": {
        "type": "Point",
        "coordinates": [
          -93.5833,
          38.1833
        ]
      },
      "type": "Feature",
      "properties": {
        "hierarchy": [
          "tgn:2143777",
          "tgn:1000001",
          "tgn:7012149",
          "tgn:2001239",
          "tgn:7007523",
          "tgn:7029392"
        ],
        "placetype": [
          "aat:300008347",
          "aat:300167671"
        ],
        "id": 2143777,
        "name:xx": "Baker"
      }
    },
    {
      "geometry": {
        "type": "Point",
        "coordinates": [
          -77.7833,
          42.9667
        ]
      },
      "type": "Feature",
      "properties": {
        "hierarchy": [
          "tgn:2143778",
          "tgn:1000001",
          "tgn:7012149",
          "tgn:1002604",
          "tgn:7007568",
          "tgn:7029392"
        ],
        "placetype": [
          "aat:300008347"
        ],
        "id": 2143778,
        "name:xx": "Baker"
      }
    },
    {
      "geometry": {
        "type": "Point",
        "coordinates": [
          -84.7,
          40.05
        ]
      },
      "type": "Feature",
      "properties": {
        "hierarchy": [
          "tgn:2143779",
          "tgn:1000001",
          "tgn:1002317",
          "tgn:7012149",
          "tgn:7007706",
          "tgn:7029392"
        ],
        "placetype": [
          "aat:300008347"
        ],
        "id": 2143779,
        "name:xx": "Baker"
      }
    }
  ]
}
