{
  "geometry": {
    "type": "Point",
    "coordinates": [
      -82.65,
      40.7667
    ]
  },
  "type": "Feature",
  "properties": {
    "hierarchy": [
      "tgn:2329265",
      "tgn:1000001",
      "tgn:7012149",
      "tgn:1002823",
      "tgn:7007706",
      "tgn:7029392"
    ],
    "placetype": [
      "aat:300008347"
    ],
    "id": 2329265,
    "name:xx": "Five Corners"
  }
}
