{
  "geometry": {
    "type": "Point",
    "coordinates": [
      25.0667,
      54.8667
    ]
  },
  "type": "Feature",
  "properties": {
    "hierarchy": [
      "tgn:1056661",
      "tgn:1000003",
      "tgn:7006618",
      "tgn:7006542",
      "tgn:7029392"
    ],
    "placetype": [
      "aat:300008347"
    ],
    "id": 1056661,
    "name:xx": "Maišiagala"
  }
}
