{
  "geometry": {
    "type": "Point",
    "coordinates": [
      -123.1167,
      42.95
    ]
  },
  "type": "Feature",
  "properties": {
    "hierarchy": [
      "tgn:2179546",
      "tgn:1000001",
      "tgn:7012149",
      "tgn:2001706",
      "tgn:7007708",
      "tgn:7029392"
    ],
    "placetype": [
      "aat:300008699"
    ],
    "id": 2179546,
    "name:xx": "Bland Branch"
  }
}
