{
  "geometry": {
    "type": "Point",
    "coordinates": [
      -107.0333,
      44.7333
    ]
  },
  "type": "Feature",
  "properties": {
    "hierarchy": [
      "tgn:2779276",
      "tgn:1000001",
      "tgn:7012149",
      "tgn:2002381",
      "tgn:7007923",
      "tgn:7029392"
    ],
    "placetype": [
      "aat:300008761"
    ],
    "id": 2779276,
    "name:xx": "Wolf Draw"
  }
}
