{
  "geometry": {
    "type": "Point",
    "coordinates": [
      4.7667,
      44.35
    ]
  },
  "type": "Feature",
  "properties": {
    "hierarchy": [
      "tgn:1035483",
      "tgn:1000003",
      "tgn:1000070",
      "tgn:7002897",
      "tgn:7029392"
    ],
    "placetype": [
      "aat:300008347"
    ],
    "id": 1035483,
    "name:xx": "Saint Paul-Trois-Châteaux"
  }
}
