{
  "geometry": {
    "type": "Point",
    "coordinates": [
      -81.0833,
      27.4833
    ]
  },
  "type": "Feature",
  "properties": {
    "hierarchy": [
      "tgn:2779814",
      "tgn:1000001",
      "tgn:7012149",
      "tgn:1002743",
      "tgn:7007240",
      "tgn:7029392"
    ],
    "placetype": [
      "aat:300008905"
    ],
    "id": 2779814,
    "name:xx": "Wolf Sawgrass Pond"
  }
}
