{
  "geometry": {
    "type": "Point",
    "coordinates": [
      -102.05,
      40.05
    ]
  },
  "type": "Feature",
  "properties": {
    "hierarchy": [
      "tgn:7023064",
      "tgn:1000001",
      "tgn:7012149",
      "tgn:7029392"
    ],
    "placetype": [
      "aat:300006075"
    ],
    "id": 7023064,
    "name:xx": "Haigler Canal"
  }
}
