{
  "geometry": {
    "type": "Point",
    "coordinates": [
      -103.8167,
      44.35
    ]
  },
  "type": "Feature",
  "properties": {
    "hierarchy": [
      "tgn:2322716",
      "tgn:1000001",
      "tgn:7012149",
      "tgn:7007713",
      "tgn:7029392"
    ],
    "placetype": [
      "aat:300008706"
    ],
    "id": 2322716,
    "name:xx": "False Bottom Creek"
  }
}
