{
  "geometry": {
    "type": "Point",
    "coordinates": [
      -81.5833,
      29.9833
    ]
  },
  "type": "Feature",
  "properties": {
    "hierarchy": [
      "tgn:2332499",
      "tgn:1000001",
      "tgn:7012149",
      "tgn:2000283",
      "tgn:7007240",
      "tgn:7029392"
    ],
    "placetype": [
      "aat:300008850"
    ],
    "id": 2332499,
    "name:xx": "Florence Point"
  }
}
