{
  "geometry": {
    "type": "Point",
    "coordinates": [
      -80.5833,
      38.4167
    ]
  },
  "type": "Feature",
  "properties": {
    "hierarchy": [
      "tgn:1121936",
      "tgn:1000001",
      "tgn:7012149",
      "tgn:7013961",
      "tgn:7029392"
    ],
    "placetype": [
      "aat:300008707"
    ],
    "id": 1121936,
    "name:xx": "Birch"
  }
}
