{
  "geometry": {
    "type": "Point",
    "coordinates": [
      -100.4667,
      38.3667
    ]
  },
  "type": "Feature",
  "properties": {
    "hierarchy": [
      "tgn:2204388",
      "tgn:1000001",
      "tgn:7012149",
      "tgn:2000710",
      "tgn:7007254",
      "tgn:7029392"
    ],
    "placetype": [
      "aat:300008706"
    ],
    "id": 2204388,
    "name:xx": "Buffalo Creek"
  }
}
