{
  "geometry": {
    "type": "Point",
    "coordinates": [
      -92.9167,
      35.65
    ]
  },
  "type": "Feature",
  "properties": {
    "hierarchy": [
      "tgn:2672677",
      "tgn:1000001",
      "tgn:7016172",
      "tgn:7012149",
      "tgn:2000162",
      "tgn:7029392"
    ],
    "placetype": [
      "aat:300008347"
    ],
    "id": 2672677,
    "name:xx": "Smyrna"
  }
}
