{
  "type": "FeatureCollection",
  "features": [
    {
      "geometry": {
        "type": "Point",
        "coordinates": [
          7.75,
          48.383333
        ]
      },
      "type": "Feature",
      "properties": {
        "hierarchy": [
          "tgn:7116830",
          "tgn:7003692",
          "tgn:1000003",
          "tgn:7000084",
          "tgn:7029392"
        ],
        "placetype": [
          "aat:300008347"
        ],
        "id": 7116830,
        "name:xx": "Ottenheim"
      }
    },
    {
      "geometry": {
        "type": "Point",
        "coordinates": [
          9.033333,
          51.866667
        ]
      },
      "type": "Feature",
      "properties": {
        "hierarchy": [
          "tgn:7116831",
          "tgn:1000003",
          "tgn:7003677",
          "tgn:7000084",
          "tgn:7029392"
        ],
        "placetype": [
          "aat:300008347"
        ],
        "id": 7116831,
        "name:xx": "Ottenhausen"
      }
    },
    {
      "geometry": {
        "type": "Point",
        "coordinates": [
          11,
          51.216667
        ]
      },
      "type": "Feature",
      "properties": {
        "hierarchy": [
          "tgn:7116832",
          "tgn:1000003",
          "tgn:7003689",
          "tgn:7000084",
          "tgn:7029392"
        ],
        "placetype": [
          "aat:300008347"
        ],
        "id": 7116832,
        "name:xx": "Ottenhausen"
      }
    },
    {
      "geometry": {
        "type": "Point",
        "coordinates": [
          10.333333,
          50.1
        ]
      },
      "type": "Feature",
      "properties": {
        "hierarchy": [
          "tgn:7116833",
          "tgn:7003669",
          "tgn:1000003",
          "tgn:7000084",
          "tgn:7029392"
        ],
        "placetype": [
          "aat:300008347"
        ],
        "id": 7116833,
        "name:xx": "Ottenhausen"
      }
    },
    {
      "geometry": {
        "type": "Point",
        "coordinates": [
          6.9,
          49.233333
        ]
      },
      "type": "Feature",
      "properties": {
        "hierarchy": [
          "tgn:7116834",
          "tgn:1000003",
          "tgn:7003684",
          "tgn:7000084",
          "tgn:7029392"
        ],
        "placetype": [
          "aat:300008347"
        ],
        "id": 7116834,
        "name:xx": "Ottenhausen"
      }
    },
    {
      "geometry": {
        "type": "Point",
        "coordinates": [
          8.55,
          48.866667
        ]
      },
      "type": "Feature",
      "properties": {
        "hierarchy": [
          "tgn:7116835",
          "tgn:7003692",
          "tgn:1000003",
          "tgn:7000084",
          "tgn:7029392"
        ],
        "placetype": [
          "aat:300008347"
        ],
        "id": 7116835,
        "name:xx": "Ottenhausen"
      }
    },
    {
      "geometry": {
        "type": "Point",
        "coordinates": [
          8.8,
          51.966667
        ]
      },
      "type": "Feature",
      "properties": {
        "hierarchy": [
          "tgn:7116836",
          "tgn:1000003",
          "tgn:7003677",
          "tgn:7000084",
          "tgn:7029392"
        ],
        "placetype": [
          "aat:300000206"
        ],
        "id": 7116836,
        "name:xx": "Ottenhausen"
      }
    },
    {
      "geometry": {
        "type": "Point",
        "coordinates": [
          10.75,
          48.75
        ]
      },
      "type": "Feature",
      "properties": {
        "hierarchy": [
          "tgn:7116837",
          "tgn:7003669",
          "tgn:1000003",
          "tgn:7000084",
          "tgn:7029392"
        ],
        "placetype": [
          "aat:300008863"
        ],
        "id": 7116837,
        "name:xx": "Ottenhart"
      }
    },
    {
      "geometry": {
        "type": "Point",
        "coordinates": [
          12.7,
          51.083333
        ]
      },
      "type": "Feature",
      "properties": {
        "hierarchy": [
          "tgn:7116838",
          "tgn:1000003",
          "tgn:7003685",
          "tgn:7000084",
          "tgn:7029392"
        ],
        "placetype": [
          "aat:300008347"
        ],
        "id": 7116838,
        "name:xx": "Ottenhain"
      }
    },
    {
      "geometry": {
        "type": "Point",
        "coordinates": [
          14.7,
          51.066667
        ]
      },
      "type": "Feature",
      "properties": {
        "hierarchy": [
          "tgn:7116839",
          "tgn:1000003",
          "tgn:7003685",
          "tgn:7000084",
          "tgn:7029392"
        ],
        "placetype": [
          "aat:300008347"
        ],
        "id": 7116839,
        "name:xx": "Ottenhain"
      }
    }
  ]
}
