{
  "geometry": {
    "type": "Point",
    "coordinates": [
      -85.2833,
      41.9833
    ]
  },
  "type": "Feature",
  "properties": {
    "hierarchy": [
      "tgn:2620370",
      "tgn:1000001",
      "tgn:1002195",
      "tgn:7012149",
      "tgn:7007520",
      "tgn:7029392"
    ],
    "placetype": [
      "aat:300008680"
    ],
    "id": 2620370,
    "name:xx": "River Lake"
  }
}
