{
  "geometry": {
    "type": "Point",
    "coordinates": [
      79.189084,
      24.622311
    ]
  },
  "type": "Feature",
  "properties": {
    "hierarchy": [
      "tgn:7566082",
      "tgn:1000004",
      "tgn:7000198",
      "tgn:1001894",
      "tgn:7029392"
    ],
    "placetype": [
      "aat:300008347"
    ],
    "name:en": "Mirāwali",
    "id": 7566082
  }
}
