{
  "geometry": {
    "type": "Point",
    "coordinates": [
      17.491,
      -27.916
    ]
  },
  "type": "Feature",
  "properties": {
    "hierarchy": [
      "tgn:7031950",
      "tgn:7001242",
      "tgn:7030585",
      "tgn:1000198",
      "tgn:7029392"
    ],
    "placetype": [
      "aat:300008347"
    ],
    "name:en": "Ai-Ais",
    "id": 7031950
  }
}
