{
  "geometry": {
    "type": "Point",
    "coordinates": [
      -88.9667,
      41.6833
    ]
  },
  "type": "Feature",
  "properties": {
    "hierarchy": [
      "tgn:2571652",
      "tgn:1000001",
      "tgn:7012149",
      "tgn:7007251",
      "tgn:7029392"
    ],
    "placetype": [
      "aat:300008699"
    ],
    "id": 2571652,
    "name:xx": "Paw Paw Run"
  }
}
