{
  "type": "FeatureCollection",
  "features": [
    {
      "geometry": {
        "type": "Point",
        "coordinates": [
          -72.2167,
          42.0667
        ]
      },
      "type": "Feature",
      "properties": {
        "hierarchy": [
          "tgn:2050790",
          "tgn:1000001",
          "tgn:7019982",
          "tgn:7012149",
          "tgn:7007517",
          "tgn:7029392"
        ],
        "placetype": [
          "aat:300008347"
        ],
        "id": 2050790,
        "name:xx": "Wales"
      }
    },
    {
      "geometry": {
        "type": "Point",
        "coordinates": [
          -71.25,
          42.1333
        ]
      },
      "type": "Feature",
      "properties": {
        "hierarchy": [
          "tgn:2050791",
          "tgn:1000001",
          "tgn:1002724",
          "tgn:7012149",
          "tgn:7007517",
          "tgn:7029392"
        ],
        "placetype": [
          "aat:300008347"
        ],
        "id": 2050791,
        "name:xx": "Walpole"
      }
    },
    {
      "geometry": {
        "type": "Point",
        "coordinates": [
          -71.2333,
          42.15
        ]
      },
      "type": "Feature",
      "properties": {
        "hierarchy": [
          "tgn:2050793",
          "tgn:1000001",
          "tgn:1002724",
          "tgn:7012149",
          "tgn:2050791",
          "tgn:7007517",
          "tgn:7029392"
        ],
        "placetype": [
          "aat:300000745"
        ],
        "id": 2050793,
        "name:xx": "Plimptonville"
      }
    }
  ]
}
