{
  "geometry": {
    "type": "Point",
    "coordinates": [
      37.45,
      8.8333
    ]
  },
  "type": "Feature",
  "properties": {
    "hierarchy": [
      "tgn:1105095",
      "tgn:7001242",
      "tgn:1001535",
      "tgn:7000489",
      "tgn:7029392"
    ],
    "placetype": [
      "aat:300008795"
    ],
    "id": 1105095,
    "name:xx": "Jībat"
  }
}
