{
  "geometry": {
    "type": "Point",
    "coordinates": [
      -81.8167,
      26.6833
    ]
  },
  "type": "Feature",
  "properties": {
    "hierarchy": [
      "tgn:2511053",
      "tgn:1000001",
      "tgn:7012149",
      "tgn:1002582",
      "tgn:7007240",
      "tgn:7029392"
    ],
    "placetype": [
      "aat:300008791"
    ],
    "id": 2511053,
    "name:xx": "Midway Island"
  }
}
