{
  "geometry": {
    "type": "Point",
    "coordinates": [
      -86.1833,
      36.6333
    ]
  },
  "type": "Feature",
  "properties": {
    "hierarchy": [
      "tgn:2147773",
      "tgn:1000001",
      "tgn:7012149",
      "tgn:2001892",
      "tgn:7007825",
      "tgn:7029392"
    ],
    "placetype": [
      "aat:300008347"
    ],
    "id": 2147773,
    "name:xx": "Barefoot"
  }
}
