{
  "geometry": {
    "type": "Point",
    "coordinates": [
      -85.2833,
      30.15
    ]
  },
  "type": "Feature",
  "properties": {
    "hierarchy": [
      "tgn:2263591",
      "tgn:1000001",
      "tgn:2000270",
      "tgn:7012149",
      "tgn:7007240",
      "tgn:7029392"
    ],
    "placetype": [
      "aat:300008905"
    ],
    "id": 2263591,
    "name:xx": "Coxwell Swamp"
  }
}
