{
  "geometry": {
    "type": "Point",
    "coordinates": [
      73.4167,
      40.75
    ]
  },
  "type": "Feature",
  "properties": {
    "hierarchy": [
      "tgn:1057035",
      "tgn:7011476",
      "tgn:1000004",
      "tgn:7006655",
      "tgn:7029392"
    ],
    "placetype": [
      "aat:300008347"
    ],
    "id": 1057035,
    "name:xx": "Mirza-Aki"
  }
}
