{
  "geometry": {
    "type": "Point",
    "coordinates": [
      23.55,
      49.2667
    ]
  },
  "type": "Feature",
  "properties": {
    "hierarchy": [
      "tgn:1060463",
      "tgn:1000003",
      "tgn:7011664",
      "tgn:7006660",
      "tgn:7029392"
    ],
    "placetype": [
      "aat:300008347"
    ],
    "id": 1060463,
    "name:xx": "Truskavets'"
  }
}
