{
  "type": "FeatureCollection",
  "features": [
    {
      "geometry": {
        "type": "Point",
        "coordinates": [
          -83.5,
          34.05
        ]
      },
      "type": "Feature",
      "properties": {
        "hierarchy": [
          "tgn:2754960",
          "tgn:1000001",
          "tgn:7012149",
          "tgn:2000369",
          "tgn:7007248",
          "tgn:7029392"
        ],
        "placetype": [
          "aat:300006191"
        ],
        "id": 2754960,
        "name:xx": "Weaver Lake"
      }
    },
    {
      "geometry": {
        "type": "Point",
        "coordinates": [
          -83.9667,
          33.6667
        ]
      },
      "type": "Feature",
      "properties": {
        "hierarchy": [
          "tgn:2754961",
          "tgn:1000001",
          "tgn:7012149",
          "tgn:2000413",
          "tgn:7007248",
          "tgn:7029392"
        ],
        "placetype": [
          "aat:300006191"
        ],
        "id": 2754961,
        "name:xx": "Weaver Lake"
      }
    },
    {
      "geometry": {
        "type": "Point",
        "coordinates": [
          -84.5667,
          33.1167
        ]
      },
      "type": "Feature",
      "properties": {
        "hierarchy": [
          "tgn:2754962",
          "tgn:1000001",
          "tgn:7012149",
          "tgn:2000390",
          "tgn:7007248",
          "tgn:7029392"
        ],
        "placetype": [
          "aat:300006191"
        ],
        "id": 2754962,
        "name:xx": "Weaver Lake"
      }
    },
    {
      "geometry": {
        "type": "Point",
        "coordinates": [
          -84.5333,
          32.2333
        ]
      },
      "type": "Feature",
      "properties": {
        "hierarchy": [
          "tgn:2754963",
          "tgn:1000001",
          "tgn:7012149",
          "tgn:2000389",
          "tgn:7007248",
          "tgn:7029392"
        ],
        "placetype": [
          "aat:300006191"
        ],
        "id": 2754963,
        "name:xx": "Weaver Lake"
      }
    },
    {
      "geometry": {
        "type": "Point",
        "coordinates": [
          -86.3833,
          41.8333
        ]
      },
      "type": "Feature",
      "properties": {
        "hierarchy": [
          "tgn:2754964",
          "tgn:1000001",
          "tgn:1002182",
          "tgn:7012149",
          "tgn:7007520",
          "tgn:7029392"
        ],
        "placetype": [
          "aat:300008680"
        ],
        "id": 2754964,
        "name:xx": "Weaver Lake"
      }
    },
    {
      "geometry": {
        "type": "Point",
        "coordinates": [
          -93.4833,
          45.1
        ]
      },
      "type": "Feature",
      "properties": {
        "hierarchy": [
          "tgn:2754965",
          "tgn:1000001",
          "tgn:2001025",
          "tgn:7012149",
          "tgn:7007521",
          "tgn:7029392"
        ],
        "placetype": [
          "aat:300008680"
        ],
        "id": 2754965,
        "name:xx": "Weaver Lake"
      }
    },
    {
      "geometry": {
        "type": "Point",
        "coordinates": [
          -74.9167,
          42.85
        ]
      },
      "type": "Feature",
      "properties": {
        "hierarchy": [
          "tgn:2754966",
          "tgn:1000001",
          "tgn:7012149",
          "tgn:1002472",
          "tgn:7007568",
          "tgn:7029392"
        ],
        "placetype": [
          "aat:300008680"
        ],
        "id": 2754966,
        "name:xx": "Weaver Lake"
      }
    },
    {
      "geometry": {
        "type": "Point",
        "coordinates": [
          -119.1333,
          43.4
        ]
      },
      "type": "Feature",
      "properties": {
        "hierarchy": [
          "tgn:2754967",
          "tgn:1000001",
          "tgn:7012149",
          "tgn:2001709",
          "tgn:7007708",
          "tgn:7029392"
        ],
        "placetype": [
          "aat:300008680"
        ],
        "id": 2754967,
        "name:xx": "Weaver Lake"
      }
    },
    {
      "geometry": {
        "type": "Point",
        "coordinates": [
          -68.3333,
          44.2167
        ]
      },
      "type": "Feature",
      "properties": {
        "hierarchy": [
          "tgn:2754968",
          "tgn:1000001",
          "tgn:2000922",
          "tgn:7012149",
          "tgn:7007515",
          "tgn:7029392"
        ],
        "placetype": [
          "aat:300132348"
        ],
        "id": 2754968,
        "name:xx": "Weaver Ledge"
      }
    },
    {
      "geometry": {
        "type": "Point",
        "coordinates": [
          -86.2,
          32.05
        ]
      },
      "type": "Feature",
      "properties": {
        "hierarchy": [
          "tgn:2754969",
          "tgn:7002659",
          "tgn:1000001",
          "tgn:7012149",
          "tgn:7029392"
        ],
        "placetype": [
          "aat:300008706"
        ],
        "id": 2754969,
        "name:xx": "Weaver Mill Creek"
      }
    }
  ]
}
