{
  "geometry": {
    "type": "Point",
    "coordinates": [
      -70.1333,
      41.2833
    ]
  },
  "type": "Feature",
  "properties": {
    "hierarchy": [
      "tgn:2497296",
      "tgn:1008293",
      "tgn:1000001",
      "tgn:1002705",
      "tgn:7012149",
      "tgn:7007517",
      "tgn:7029392"
    ],
    "placetype": [
      "aat:300008680"
    ],
    "id": 2497296,
    "name:xx": "Maxcy Pond"
  }
}
