{
  "geometry": {
    "type": "Point",
    "coordinates": [
      -58.5833,
      -18.85
    ]
  },
  "type": "Feature",
  "properties": {
    "hierarchy": [
      "tgn:1020302",
      "tgn:1000752",
      "tgn:1000046",
      "tgn:1000002",
      "tgn:7029392"
    ],
    "placetype": [
      "aat:300008347"
    ],
    "id": 1020302,
    "name:xx": "El Carmen"
  }
}
