{
  "geometry": {
    "type": "Point",
    "coordinates": [
      -88.7667,
      34.7667
    ]
  },
  "type": "Feature",
  "properties": {
    "hierarchy": [
      "tgn:2664233",
      "tgn:1000001",
      "tgn:7012149",
      "tgn:2001155",
      "tgn:7007522",
      "tgn:7029392"
    ],
    "placetype": [
      "aat:300008798"
    ],
    "id": 2664233,
    "name:xx": "Silver Springs Hill"
  }
}
