{
  "geometry": {
    "type": "Point",
    "coordinates": [
      24.85,
      57.15
    ]
  },
  "type": "Feature",
  "properties": {
    "hierarchy": [
      "tgn:1059406",
      "tgn:7012152",
      "tgn:1000003",
      "tgn:7006541",
      "tgn:7029392"
    ],
    "placetype": [
      "aat:300008347"
    ],
    "id": 1059406,
    "name:xx": "Sigulda"
  }
}
