{
  "geometry": {
    "type": "Point",
    "coordinates": [
      -84.5667,
      32.0167
    ]
  },
  "type": "Feature",
  "properties": {
    "hierarchy": [
      "tgn:2377711",
      "tgn:1000001",
      "tgn:7012149",
      "tgn:2000443",
      "tgn:7007248",
      "tgn:7029392"
    ],
    "placetype": [
      "aat:300008706"
    ],
    "id": 2377711,
    "name:xx": "Harrel Mill Creek"
  }
}
