{
  "geometry": {
    "type": "Point",
    "coordinates": [
      -83.8833,
      37.5167
    ]
  },
  "type": "Feature",
  "properties": {
    "hierarchy": [
      "tgn:2591343",
      "tgn:1000001",
      "tgn:7012149",
      "tgn:2000802",
      "tgn:7007255",
      "tgn:7029392"
    ],
    "placetype": [
      "aat:300008699"
    ],
    "id": 2591343,
    "name:xx": "Polly Spark Branch"
  }
}
