{
  "geometry": {
    "type": "Point",
    "coordinates": [
      -77.3833,
      41.4167
    ]
  },
  "type": "Feature",
  "properties": {
    "hierarchy": [
      "tgn:2147909",
      "tgn:1000001",
      "tgn:7012149",
      "tgn:1002613",
      "tgn:7007710",
      "tgn:7029392"
    ],
    "placetype": [
      "aat:300055621"
    ],
    "id": 2147909,
    "name:xx": "Bark Cabin Natural Area"
  }
}
