{
  "type": "FeatureCollection",
  "features": [
    {
      "geometry": {
        "type": "Point",
        "coordinates": [
          -90.5833,
          35.2833
        ]
      },
      "type": "Feature",
      "properties": {
        "hierarchy": [
          "tgn:2148630",
          "tgn:1000001",
          "tgn:7016172",
          "tgn:2000123",
          "tgn:7012149",
          "tgn:7029392"
        ],
        "placetype": [
          "aat:300008680"
        ],
        "id": 2148630,
        "name:xx": "Barnes Lake"
      }
    },
    {
      "geometry": {
        "type": "Point",
        "coordinates": [
          -93.9333,
          34
        ]
      },
      "type": "Feature",
      "properties": {
        "hierarchy": [
          "tgn:2148631",
          "tgn:1000001",
          "tgn:7016172",
          "tgn:7012149",
          "tgn:2000135",
          "tgn:7029392"
        ],
        "placetype": [
          "aat:300006191"
        ],
        "id": 2148631,
        "name:xx": "Barnes Lake"
      }
    },
    {
      "geometry": {
        "type": "Point",
        "coordinates": [
          -81.45,
          32.85
        ]
      },
      "type": "Feature",
      "properties": {
        "hierarchy": [
          "tgn:2148632",
          "tgn:1000001",
          "tgn:7012149",
          "tgn:2000415",
          "tgn:7007248",
          "tgn:7029392"
        ],
        "placetype": [
          "aat:300008680"
        ],
        "id": 2148632,
        "name:xx": "Barnes Lake"
      }
    },
    {
      "geometry": {
        "type": "Point",
        "coordinates": [
          -84.7667,
          33.5167
        ]
      },
      "type": "Feature",
      "properties": {
        "hierarchy": [
          "tgn:2148633",
          "tgn:1000001",
          "tgn:7012149",
          "tgn:2000351",
          "tgn:7007248",
          "tgn:7029392"
        ],
        "placetype": [
          "aat:300006191"
        ],
        "id": 2148633,
        "name:xx": "Barnes Lake"
      }
    },
    {
      "geometry": {
        "type": "Point",
        "coordinates": [
          -83.35,
          34.6
        ]
      },
      "type": "Feature",
      "properties": {
        "hierarchy": [
          "tgn:2148634",
          "tgn:1000001",
          "tgn:7012149",
          "tgn:2000418",
          "tgn:7007248",
          "tgn:7029392"
        ],
        "placetype": [
          "aat:300006191"
        ],
        "id": 2148634,
        "name:xx": "Barnes Lake"
      }
    },
    {
      "geometry": {
        "type": "Point",
        "coordinates": [
          -85.0333,
          33.5833
        ]
      },
      "type": "Feature",
      "properties": {
        "hierarchy": [
          "tgn:2148635",
          "tgn:1000001",
          "tgn:2000313",
          "tgn:7012149",
          "tgn:7007248",
          "tgn:7029392"
        ],
        "placetype": [
          "aat:300006191"
        ],
        "id": 2148635,
        "name:xx": "Barnes Lake"
      }
    },
    {
      "geometry": {
        "type": "Point",
        "coordinates": [
          -86.8833,
          39.4167
        ]
      },
      "type": "Feature",
      "properties": {
        "hierarchy": [
          "tgn:2148636",
          "tgn:1000001",
          "tgn:7012149",
          "tgn:2000548",
          "tgn:7007252",
          "tgn:7029392"
        ],
        "placetype": [
          "aat:300006191"
        ],
        "id": 2148636,
        "name:xx": "Barnes Lake"
      }
    },
    {
      "geometry": {
        "type": "Point",
        "coordinates": [
          -93.45,
          32.1
        ]
      },
      "type": "Feature",
      "properties": {
        "hierarchy": [
          "tgn:2148637",
          "tgn:1000001",
          "tgn:7012149",
          "tgn:2000894",
          "tgn:7007256",
          "tgn:7029392"
        ],
        "placetype": [
          "aat:300008680"
        ],
        "id": 2148637,
        "name:xx": "Barnes Lake"
      }
    },
    {
      "geometry": {
        "type": "Point",
        "coordinates": [
          -83.3,
          43.1833
        ]
      },
      "type": "Feature",
      "properties": {
        "hierarchy": [
          "tgn:2148638",
          "tgn:1000001",
          "tgn:7012149",
          "tgn:1002576",
          "tgn:7007520",
          "tgn:7029392"
        ],
        "placetype": [
          "aat:300008680"
        ],
        "id": 2148638,
        "name:xx": "Barnes Lake"
      }
    },
    {
      "geometry": {
        "type": "Point",
        "coordinates": [
          -84.6,
          44.8167
        ]
      },
      "type": "Feature",
      "properties": {
        "hierarchy": [
          "tgn:2148639",
          "tgn:1000001",
          "tgn:2000954",
          "tgn:7012149",
          "tgn:7007520",
          "tgn:7029392"
        ],
        "placetype": [
          "aat:300008680"
        ],
        "id": 2148639,
        "name:xx": "Barnes Lake"
      }
    }
  ]
}
