{
  "geometry": {
    "type": "Point",
    "coordinates": [
      5.9667,
      46.15
    ]
  },
  "type": "Feature",
  "properties": {
    "hierarchy": [
      "tgn:1063986",
      "tgn:7003746",
      "tgn:1000003",
      "tgn:7011731",
      "tgn:7029392"
    ],
    "placetype": [
      "aat:300008347"
    ],
    "id": 1063986,
    "name:xx": "Chancy"
  }
}
