{
  "geometry": {
    "type": "Point",
    "coordinates": [
      -110.6167,
      34.05
    ]
  },
  "type": "Feature",
  "properties": {
    "hierarchy": [
      "tgn:2687748",
      "tgn:1000001",
      "tgn:7006451",
      "tgn:7012149",
      "tgn:2000099",
      "tgn:7029392"
    ],
    "placetype": [
      "aat:300006191"
    ],
    "id": 2687748,
    "name:xx": "Spring Tank"
  }
}
