{
  "geometry": {
    "type": "Point",
    "coordinates": [
      -74.0167,
      44.3333
    ]
  },
  "type": "Feature",
  "properties": {
    "hierarchy": [
      "tgn:2149956",
      "tgn:1000001",
      "tgn:7012149",
      "tgn:2001461",
      "tgn:7007568",
      "tgn:7029392"
    ],
    "placetype": [
      "aat:300008680"
    ],
    "id": 2149956,
    "name:xx": "Bartlett Pond"
  }
}
