{
  "geometry": {
    "type": "Point",
    "coordinates": [
      17.5833,
      60.6167
    ]
  },
  "type": "Feature",
  "properties": {
    "hierarchy": [
      "tgn:1063004",
      "tgn:1000003",
      "tgn:1000462",
      "tgn:1000097",
      "tgn:7029392"
    ],
    "placetype": [
      "aat:300008347"
    ],
    "id": 1063004,
    "name:xx": "Gårdskär"
  }
}
