{
  "geometry": {
    "type": "Point",
    "coordinates": [
      18.75,
      44.55
    ]
  },
  "type": "Feature",
  "properties": {
    "hierarchy": [
      "tgn:6002304",
      "tgn:7018774",
      "tgn:1000003",
      "tgn:7006664",
      "tgn:7029392"
    ],
    "placetype": [
      "aat:300008347"
    ],
    "id": 6002304,
    "name:xx": "Gornja Tuzla"
  }
}
