{
  "geometry": {
    "type": "Point",
    "coordinates": [
      13.95,
      45.75
    ]
  },
  "type": "Feature",
  "properties": {
    "hierarchy": [
      "tgn:7016872",
      "tgn:1000003",
      "tgn:7015085",
      "tgn:7006670",
      "tgn:7029392"
    ],
    "placetype": [
      "aat:300000835",
      "aat:300132339"
    ],
    "id": 7016872,
    "name:xx": "Kras"
  }
}
