{
  "geometry": {
    "type": "Point",
    "coordinates": [
      -92.1167,
      30.3667
    ]
  },
  "type": "Feature",
  "properties": {
    "hierarchy": [
      "tgn:2259866",
      "tgn:1000001",
      "tgn:7012149",
      "tgn:2000902",
      "tgn:7007256",
      "tgn:7029392"
    ],
    "placetype": [
      "aat:300008699"
    ],
    "id": 2259866,
    "name:xx": "Coulee Croche"
  }
}
