{
  "geometry": {
    "type": "Point",
    "coordinates": [
      -80.5167,
      39.0833
    ]
  },
  "type": "Feature",
  "properties": {
    "hierarchy": [
      "tgn:2339947",
      "tgn:1000001",
      "tgn:7012149",
      "tgn:2002271",
      "tgn:7013961",
      "tgn:7029392"
    ],
    "placetype": [
      "aat:300008706"
    ],
    "id": 2339947,
    "name:xx": "Freemans Creek"
  }
}
