{
  "geometry": {
    "type": "Point",
    "coordinates": [
      -111.9667,
      43.65
    ]
  },
  "type": "Feature",
  "properties": {
    "hierarchy": [
      "tgn:2514194",
      "tgn:1000001",
      "tgn:7012149",
      "tgn:2000477",
      "tgn:7007250",
      "tgn:7029392"
    ],
    "placetype": [
      "aat:300006075"
    ],
    "id": 2514194,
    "name:xx": "Miller Canal"
  }
}
