{
  "geometry": {
    "type": "Point",
    "coordinates": [
      124.9833,
      8.1167
    ]
  },
  "type": "Feature",
  "properties": {
    "hierarchy": [
      "tgn:1105131",
      "tgn:1000004",
      "tgn:1001161",
      "tgn:1000135",
      "tgn:7029392"
    ],
    "placetype": [
      "aat:300008795"
    ],
    "id": 1105131,
    "name:xx": "Kaatoan"
  }
}
