{
  "type": "FeatureCollection",
  "features": [
    {
      "geometry": {
        "type": "Point",
        "coordinates": [
          2.1167,
          50.7167
        ]
      },
      "type": "Feature",
      "properties": {
        "hierarchy": [
          "tgn:1034140",
          "tgn:1000003",
          "tgn:7001097",
          "tgn:1000070",
          "tgn:7029392"
        ],
        "placetype": [
          "aat:300008347"
        ],
        "id": 1034140,
        "name:xx": "Lumbres"
      }
    },
    {
      "geometry": {
        "type": "Point",
        "coordinates": [
          0.9167,
          49.8333
        ]
      },
      "type": "Feature",
      "properties": {
        "hierarchy": [
          "tgn:1034143",
          "tgn:1000003",
          "tgn:7002882",
          "tgn:1000070",
          "tgn:7029392"
        ],
        "placetype": [
          "aat:300008347"
        ],
        "id": 1034143,
        "name:xx": "Luneray"
      }
    },
    {
      "geometry": {
        "type": "Point",
        "coordinates": [
          5.7,
          44.6667
        ]
      },
      "type": "Feature",
      "properties": {
        "hierarchy": [
          "tgn:1034145",
          "tgn:1000003",
          "tgn:1000070",
          "tgn:7002897",
          "tgn:7029392"
        ],
        "placetype": [
          "aat:300008347"
        ],
        "id": 1034145,
        "name:xx": "Lus-la-Croix-Haute"
      }
    },
    {
      "geometry": {
        "type": "Point",
        "coordinates": [
          0.1333,
          46.4333
        ]
      },
      "type": "Feature",
      "properties": {
        "hierarchy": [
          "tgn:1034146",
          "tgn:1000003",
          "tgn:7002892",
          "tgn:1000070",
          "tgn:7029392"
        ],
        "placetype": [
          "aat:300008347"
        ],
        "id": 1034146,
        "name:xx": "Lusignan"
      }
    },
    {
      "geometry": {
        "type": "Point",
        "coordinates": [
          0.7333,
          46.4
        ]
      },
      "type": "Feature",
      "properties": {
        "hierarchy": [
          "tgn:1034148",
          "tgn:1000003",
          "tgn:7002892",
          "tgn:1000070",
          "tgn:7029392"
        ],
        "placetype": [
          "aat:300008347"
        ],
        "id": 1034148,
        "name:xx": "Lussac-les Châteaux"
      }
    },
    {
      "geometry": {
        "type": "Point",
        "coordinates": [
          4.3667,
          44.1333
        ]
      },
      "type": "Feature",
      "properties": {
        "hierarchy": [
          "tgn:1034149",
          "tgn:1000003",
          "tgn:7002885",
          "tgn:1000070",
          "tgn:7029392"
        ],
        "placetype": [
          "aat:300008347"
        ],
        "id": 1034149,
        "name:xx": "Lussan"
      }
    }
  ]
}
