{
  "geometry": {
    "type": "Point",
    "coordinates": [
      -86.1167,
      43.2667
    ]
  },
  "type": "Feature",
  "properties": {
    "hierarchy": [
      "tgn:2411909",
      "tgn:1000001",
      "tgn:7012149",
      "tgn:1002700",
      "tgn:7007520",
      "tgn:7029392"
    ],
    "placetype": [
      "aat:300008850"
    ],
    "id": 2411909,
    "name:xx": "Indian Point"
  }
}
