{
  "geometry": {
    "type": "Point",
    "coordinates": [
      17.35,
      60.65
    ]
  },
  "type": "Feature",
  "properties": {
    "hierarchy": [
      "tgn:1063866",
      "tgn:1000003",
      "tgn:1000462",
      "tgn:1000097",
      "tgn:7029392"
    ],
    "placetype": [
      "aat:300008347"
    ],
    "id": 1063866,
    "name:xx": "Ytterharnäs"
  }
}
