{
  "geometry": {
    "type": "Point",
    "coordinates": [
      -82.1167,
      28.9667
    ]
  },
  "type": "Feature",
  "properties": {
    "hierarchy": [
      "tgn:2020819",
      "tgn:1000001",
      "tgn:7012149",
      "tgn:1002631",
      "tgn:7007240",
      "tgn:7029392"
    ],
    "placetype": [
      "aat:300008347",
      "aat:300387210"
    ],
    "id": 2020819,
    "name:xx": "Pedro"
  }
}
