{
  "type": "FeatureCollection",
  "features": [
    {
      "geometry": {
        "type": "Point",
        "coordinates": [
          -90.8333,
          36.55
        ]
      },
      "type": "Feature",
      "properties": {
        "hierarchy": [
          "tgn:2168990",
          "tgn:1000001",
          "tgn:7012149",
          "tgn:2001237",
          "tgn:7007523",
          "tgn:7029392"
        ],
        "placetype": [
          "aat:300008791"
        ],
        "id": 2168990,
        "name:xx": "Big Island"
      }
    },
    {
      "geometry": {
        "type": "Point",
        "coordinates": [
          -90.3167,
          36.6333
        ]
      },
      "type": "Feature",
      "properties": {
        "hierarchy": [
          "tgn:2168991",
          "tgn:1000001",
          "tgn:2001176",
          "tgn:7012149",
          "tgn:7007523",
          "tgn:7029392"
        ],
        "placetype": [
          "aat:300008791"
        ],
        "id": 2168991,
        "name:xx": "Big Island"
      }
    },
    {
      "geometry": {
        "type": "Point",
        "coordinates": [
          -104.3667,
          48.4333
        ]
      },
      "type": "Feature",
      "properties": {
        "hierarchy": [
          "tgn:2168993",
          "tgn:1000001",
          "tgn:7012149",
          "tgn:2001305",
          "tgn:7007524",
          "tgn:7029392"
        ],
        "placetype": [
          "aat:300008791"
        ],
        "id": 2168993,
        "name:xx": "Big Island"
      }
    },
    {
      "geometry": {
        "type": "Point",
        "coordinates": [
          -71.1333,
          43.0833
        ]
      },
      "type": "Feature",
      "properties": {
        "hierarchy": [
          "tgn:2168994",
          "tgn:1000001",
          "tgn:7014352",
          "tgn:7012149",
          "tgn:7007564",
          "tgn:7029392"
        ],
        "placetype": [
          "aat:300008791"
        ],
        "id": 2168994,
        "name:xx": "Big Island"
      }
    },
    {
      "geometry": {
        "type": "Point",
        "coordinates": [
          -71,
          43.5333
        ]
      },
      "type": "Feature",
      "properties": {
        "hierarchy": [
          "tgn:2168995",
          "tgn:2001423",
          "tgn:1000001",
          "tgn:7012149",
          "tgn:7007564",
          "tgn:7029392"
        ],
        "placetype": [
          "aat:300008791"
        ],
        "id": 2168995,
        "name:xx": "Big Island"
      }
    },
    {
      "geometry": {
        "type": "Point",
        "coordinates": [
          -71.45,
          43.5667
        ]
      },
      "type": "Feature",
      "properties": {
        "hierarchy": [
          "tgn:2168996",
          "tgn:2001422",
          "tgn:1000001",
          "tgn:7012149",
          "tgn:7007564",
          "tgn:7029392"
        ],
        "placetype": [
          "aat:300008791"
        ],
        "id": 2168996,
        "name:xx": "Big Island"
      }
    },
    {
      "geometry": {
        "type": "Point",
        "coordinates": [
          -71.0667,
          44.7167
        ]
      },
      "type": "Feature",
      "properties": {
        "hierarchy": [
          "tgn:2168997",
          "tgn:1002300",
          "tgn:1000001",
          "tgn:7012149",
          "tgn:7007564",
          "tgn:7029392"
        ],
        "placetype": [
          "aat:300008791"
        ],
        "id": 2168997,
        "name:xx": "Big Island"
      }
    },
    {
      "geometry": {
        "type": "Point",
        "coordinates": [
          -104.2,
          35.4667
        ]
      },
      "type": "Feature",
      "properties": {
        "hierarchy": [
          "tgn:2168998",
          "tgn:1000001",
          "tgn:7012149",
          "tgn:2001453",
          "tgn:7007566",
          "tgn:7029392"
        ],
        "placetype": [
          "aat:300008791"
        ],
        "id": 2168998,
        "name:xx": "Big Island"
      }
    },
    {
      "geometry": {
        "type": "Point",
        "coordinates": [
          -74.4,
          41.3167
        ]
      },
      "type": "Feature",
      "properties": {
        "hierarchy": [
          "tgn:2168999",
          "tgn:1000001",
          "tgn:7012149",
          "tgn:1002751",
          "tgn:7007568",
          "tgn:7029392"
        ],
        "placetype": [
          "aat:300008791"
        ],
        "id": 2168999,
        "name:xx": "Big Island"
      }
    }
  ]
}
