{
  "type": "FeatureCollection",
  "features": [
    {
      "geometry": {
        "type": "Point",
        "coordinates": [
          -95.8667,
          28.9667
        ]
      },
      "type": "Feature",
      "properties": {
        "hierarchy": [
          "tgn:2462940",
          "tgn:1000001",
          "tgn:7012149",
          "tgn:1002646",
          "tgn:7007826",
          "tgn:7029392"
        ],
        "placetype": [
          "aat:300008699"
        ],
        "id": 2462940,
        "name:xx": "Live Oak Bayou"
      }
    },
    {
      "geometry": {
        "type": "Point",
        "coordinates": [
          -97.05,
          30.1
        ]
      },
      "type": "Feature",
      "properties": {
        "hierarchy": [
          "tgn:2462941",
          "tgn:1000001",
          "tgn:1002168",
          "tgn:7012149",
          "tgn:7007826",
          "tgn:7029392"
        ],
        "placetype": [
          "aat:300008699"
        ],
        "id": 2462941,
        "name:xx": "Live Oak Branch"
      }
    },
    {
      "geometry": {
        "type": "Point",
        "coordinates": [
          -99.3833,
          32.0333
        ]
      },
      "type": "Feature",
      "properties": {
        "hierarchy": [
          "tgn:2462942",
          "tgn:1000001",
          "tgn:7012149",
          "tgn:2001959",
          "tgn:7007826",
          "tgn:7029392"
        ],
        "placetype": [
          "aat:300008699"
        ],
        "id": 2462942,
        "name:xx": "Live Oak Branch"
      }
    },
    {
      "geometry": {
        "type": "Point",
        "coordinates": [
          -99.25,
          32.1167
        ]
      },
      "type": "Feature",
      "properties": {
        "hierarchy": [
          "tgn:2462943",
          "tgn:1000001",
          "tgn:7012149",
          "tgn:7007826",
          "tgn:7029392"
        ],
        "placetype": [
          "aat:300008699"
        ],
        "id": 2462943,
        "name:xx": "Live Oak Branch"
      }
    },
    {
      "geometry": {
        "type": "Point",
        "coordinates": [
          -121.65,
          39.2667
        ]
      },
      "type": "Feature",
      "properties": {
        "hierarchy": [
          "tgn:2462944",
          "tgn:1000001",
          "tgn:7012149",
          "tgn:7007157",
          "tgn:1002937",
          "tgn:7029392"
        ],
        "placetype": [
          "aat:300006075"
        ],
        "id": 2462944,
        "name:xx": "Live Oak Canal"
      }
    },
    {
      "geometry": {
        "type": "Point",
        "coordinates": [
          -121.9,
          41.15
        ]
      },
      "type": "Feature",
      "properties": {
        "hierarchy": [
          "tgn:2462945",
          "tgn:1000001",
          "tgn:7012149",
          "tgn:7007157",
          "tgn:2000188",
          "tgn:7029392"
        ],
        "placetype": [
          "aat:300008761"
        ],
        "id": 2462945,
        "name:xx": "Live Oak Canyon"
      }
    },
    {
      "geometry": {
        "type": "Point",
        "coordinates": [
          -117.6,
          33.6833
        ]
      },
      "type": "Feature",
      "properties": {
        "hierarchy": [
          "tgn:2462946",
          "tgn:1000001",
          "tgn:7012149",
          "tgn:7007157",
          "tgn:1002748",
          "tgn:7029392"
        ],
        "placetype": [
          "aat:300008761"
        ],
        "id": 2462946,
        "name:xx": "Live Oak Canyon"
      }
    },
    {
      "geometry": {
        "type": "Point",
        "coordinates": [
          -118.5833,
          35.0667
        ]
      },
      "type": "Feature",
      "properties": {
        "hierarchy": [
          "tgn:2462947",
          "tgn:1000001",
          "tgn:7012149",
          "tgn:1002545",
          "tgn:7007157",
          "tgn:7029392"
        ],
        "placetype": [
          "aat:300008761"
        ],
        "id": 2462947,
        "name:xx": "Live Oak Canyon"
      }
    },
    {
      "geometry": {
        "type": "Point",
        "coordinates": [
          -115.3,
          35.2667
        ]
      },
      "type": "Feature",
      "properties": {
        "hierarchy": [
          "tgn:2462948",
          "tgn:1000001",
          "tgn:7012149",
          "tgn:7007157",
          "tgn:1002857",
          "tgn:7029392"
        ],
        "placetype": [
          "aat:300008761"
        ],
        "id": 2462948,
        "name:xx": "Live Oak Canyon"
      }
    },
    {
      "geometry": {
        "type": "Point",
        "coordinates": [
          -116.55,
          33.6167
        ]
      },
      "type": "Feature",
      "properties": {
        "hierarchy": [
          "tgn:2462949",
          "tgn:1000001",
          "tgn:7012149",
          "tgn:7007157",
          "tgn:1002828",
          "tgn:7029392"
        ],
        "placetype": [
          "aat:300008761"
        ],
        "id": 2462949,
        "name:xx": "Live Oak Canyon"
      }
    }
  ]
}
