{
  "geometry": {
    "type": "Point",
    "coordinates": [
      -96.7333,
      32.8333
    ]
  },
  "type": "Feature",
  "properties": {
    "hierarchy": [
      "tgn:2609212",
      "tgn:1000001",
      "tgn:7012149",
      "tgn:1002315",
      "tgn:7007826",
      "tgn:7029392"
    ],
    "placetype": [
      "aat:300008347"
    ],
    "id": 2609212,
    "name:xx": "Rawlins"
  }
}
