{
  "geometry": {
    "type": "Point",
    "coordinates": [
      -78.55,
      33.9333
    ]
  },
  "type": "Feature",
  "properties": {
    "hierarchy": [
      "tgn:2717945",
      "tgn:1000001",
      "tgn:2001472",
      "tgn:7012149",
      "tgn:7007709",
      "tgn:7029392"
    ],
    "placetype": [
      "aat:300008347"
    ],
    "id": 2717945,
    "name:xx": "Thomasboro"
  }
}
