{
  "geometry": {
    "type": "Point",
    "coordinates": [
      -70.7167,
      42.1167
    ]
  },
  "type": "Feature",
  "properties": {
    "hierarchy": [
      "tgn:2222262",
      "tgn:1000001",
      "tgn:7014423",
      "tgn:7012149",
      "tgn:7007517",
      "tgn:7029392"
    ],
    "placetype": [
      "aat:300008798"
    ],
    "id": 2222262,
    "name:xx": "Carolina Hill"
  }
}
