{
  "geometry": {
    "type": "Point",
    "coordinates": [
      -158.75,
      59.5667
    ]
  },
  "type": "Feature",
  "properties": {
    "hierarchy": [
      "tgn:2509685",
      "tgn:7006450",
      "tgn:1000001",
      "tgn:2000071",
      "tgn:7012149",
      "tgn:7029392"
    ],
    "placetype": [
      "aat:300008791"
    ],
    "id": 2509685,
    "name:xx": "Middle Island"
  }
}
