{
  "type": "FeatureCollection",
  "features": [
    {
      "geometry": {
        "type": "Point",
        "coordinates": [
          -90.8,
          32.3667
        ]
      },
      "type": "Feature",
      "properties": {
        "hierarchy": [
          "tgn:2781440",
          "tgn:1000001",
          "tgn:7012149",
          "tgn:2001160",
          "tgn:7007522",
          "tgn:7029392"
        ],
        "placetype": [
          "aat:300008347"
        ],
        "id": 2781440,
        "name:xx": "Woodlawn"
      }
    },
    {
      "geometry": {
        "type": "Point",
        "coordinates": [
          -90.2667,
          32.85
        ]
      },
      "type": "Feature",
      "properties": {
        "hierarchy": [
          "tgn:2781441",
          "tgn:1000001",
          "tgn:7012149",
          "tgn:2001167",
          "tgn:7007522",
          "tgn:7029392"
        ],
        "placetype": [
          "aat:300008347"
        ],
        "id": 2781441,
        "name:xx": "Woodlawn"
      }
    },
    {
      "geometry": {
        "type": "Point",
        "coordinates": [
          -89.5667,
          34.35
        ]
      },
      "type": "Feature",
      "properties": {
        "hierarchy": [
          "tgn:2781442",
          "tgn:1000001",
          "tgn:7012149",
          "tgn:2001121",
          "tgn:7007522",
          "tgn:7029392"
        ],
        "placetype": [
          "aat:300008347"
        ],
        "id": 2781442,
        "name:xx": "Woodlawn"
      }
    },
    {
      "geometry": {
        "type": "Point",
        "coordinates": [
          -88.3,
          33.6167
        ]
      },
      "type": "Feature",
      "properties": {
        "hierarchy": [
          "tgn:2781443",
          "tgn:1000001",
          "tgn:7012149",
          "tgn:2001129",
          "tgn:7007522",
          "tgn:7029392"
        ],
        "placetype": [
          "aat:300008347"
        ],
        "id": 2781443,
        "name:xx": "Woodlawn"
      }
    },
    {
      "geometry": {
        "type": "Point",
        "coordinates": [
          -92.2,
          39.5667
        ]
      },
      "type": "Feature",
      "properties": {
        "hierarchy": [
          "tgn:2781444",
          "tgn:1000001",
          "tgn:7012149",
          "tgn:1002680",
          "tgn:7007523",
          "tgn:7029392"
        ],
        "placetype": [
          "aat:300008347"
        ],
        "id": 2781444,
        "name:xx": "Woodlawn"
      }
    },
    {
      "geometry": {
        "type": "Point",
        "coordinates": [
          -82.0333,
          35.7833
        ]
      },
      "type": "Feature",
      "properties": {
        "hierarchy": [
          "tgn:2781446",
          "tgn:1000001",
          "tgn:7012149",
          "tgn:2001514",
          "tgn:7007709",
          "tgn:7029392"
        ],
        "placetype": [
          "aat:300008347"
        ],
        "id": 2781446,
        "name:xx": "Woodlawn"
      }
    },
    {
      "geometry": {
        "type": "Point",
        "coordinates": [
          -80.2333,
          40.6167
        ]
      },
      "type": "Feature",
      "properties": {
        "hierarchy": [
          "tgn:2781447",
          "tgn:1002171",
          "tgn:1000001",
          "tgn:7012149",
          "tgn:7007710",
          "tgn:7029392"
        ],
        "placetype": [
          "aat:300008347"
        ],
        "id": 2781447,
        "name:xx": "Woodlawn"
      }
    },
    {
      "geometry": {
        "type": "Point",
        "coordinates": [
          -82.2167,
          34.1833
        ]
      },
      "type": "Feature",
      "properties": {
        "hierarchy": [
          "tgn:2781448",
          "tgn:1000001",
          "tgn:2001748",
          "tgn:7012149",
          "tgn:7007712",
          "tgn:7029392"
        ],
        "placetype": [
          "aat:300008347"
        ],
        "id": 2781448,
        "name:xx": "Woodlawn"
      }
    },
    {
      "geometry": {
        "type": "Point",
        "coordinates": [
          -81.9833,
          33.5
        ]
      },
      "type": "Feature",
      "properties": {
        "hierarchy": [
          "tgn:2781449",
          "tgn:2001726",
          "tgn:1000001",
          "tgn:7012149",
          "tgn:7007712",
          "tgn:7029392"
        ],
        "placetype": [
          "aat:300008347"
        ],
        "id": 2781449,
        "name:xx": "Woodlawn"
      }
    }
  ]
}
