{
  "geometry": {
    "type": "Point",
    "coordinates": [
      -85.35,
      35.1833
    ]
  },
  "type": "Feature",
  "properties": {
    "hierarchy": [
      "tgn:2362340",
      "tgn:1000001",
      "tgn:7012149",
      "tgn:2001913",
      "tgn:7007825",
      "tgn:7029392"
    ],
    "placetype": [
      "aat:300266640"
    ],
    "id": 2362340,
    "name:xx": "Grayson Ridge"
  }
}
