{
  "type": "FeatureCollection",
  "features": [
    {
      "geometry": {
        "type": "Point",
        "coordinates": [
          -106.333333,
          27.033333
        ]
      },
      "type": "Feature",
      "properties": {
        "hierarchy": [
          "tgn:7365650",
          "tgn:7005581",
          "tgn:1000001",
          "tgn:7005560",
          "tgn:7029392"
        ],
        "placetype": [
          "aat:300008347"
        ],
        "id": 7365650,
        "name:xx": "Frontera"
      }
    },
    {
      "geometry": {
        "type": "Point",
        "coordinates": [
          -105.066667,
          27.033333
        ]
      },
      "type": "Feature",
      "properties": {
        "hierarchy": [
          "tgn:7365651",
          "tgn:7005581",
          "tgn:1000001",
          "tgn:7005560",
          "tgn:7029392"
        ],
        "placetype": [
          "aat:300008347"
        ],
        "id": 7365651,
        "name:xx": "Frontera"
      }
    },
    {
      "geometry": {
        "type": "Point",
        "coordinates": [
          -94.066667,
          16.316667
        ]
      },
      "type": "Feature",
      "properties": {
        "hierarchy": [
          "tgn:7365653",
          "tgn:1000001",
          "tgn:7005591",
          "tgn:7005560",
          "tgn:7029392"
        ],
        "placetype": [
          "aat:300008347"
        ],
        "id": 7365653,
        "name:xx": "Frontera"
      }
    },
    {
      "geometry": {
        "type": "Point",
        "coordinates": [
          -110.366667,
          29.566667
        ]
      },
      "type": "Feature",
      "properties": {
        "hierarchy": [
          "tgn:7365654",
          "tgn:1000001",
          "tgn:1001960",
          "tgn:7005560",
          "tgn:7029392"
        ],
        "placetype": [
          "aat:300008347"
        ],
        "id": 7365654,
        "name:xx": "Enmedio"
      }
    },
    {
      "geometry": {
        "type": "Point",
        "coordinates": [
          -105.983333,
          28.716667
        ]
      },
      "type": "Feature",
      "properties": {
        "hierarchy": [
          "tgn:7365656",
          "tgn:7005581",
          "tgn:1000001",
          "tgn:7005560",
          "tgn:7029392"
        ],
        "placetype": [
          "aat:300008347"
        ],
        "id": 7365656,
        "name:xx": "Enmedio"
      }
    },
    {
      "geometry": {
        "type": "Point",
        "coordinates": [
          -105.55,
          26.766667
        ]
      },
      "type": "Feature",
      "properties": {
        "hierarchy": [
          "tgn:7365657",
          "tgn:7005581",
          "tgn:1000001",
          "tgn:7005560",
          "tgn:7029392"
        ],
        "placetype": [
          "aat:300008347"
        ],
        "id": 7365657,
        "name:xx": "Enmedio"
      }
    },
    {
      "geometry": {
        "type": "Point",
        "coordinates": [
          -106.766667,
          26.05
        ]
      },
      "type": "Feature",
      "properties": {
        "hierarchy": [
          "tgn:7365658",
          "tgn:7005581",
          "tgn:1000001",
          "tgn:7005560",
          "tgn:7029392"
        ],
        "placetype": [
          "aat:300008347"
        ],
        "id": 7365658,
        "name:xx": "Enmedio"
      }
    },
    {
      "geometry": {
        "type": "Point",
        "coordinates": [
          -106.933333,
          25.916667
        ]
      },
      "type": "Feature",
      "properties": {
        "hierarchy": [
          "tgn:7365659",
          "tgn:7005581",
          "tgn:1000001",
          "tgn:7005560",
          "tgn:7029392"
        ],
        "placetype": [
          "aat:300008347"
        ],
        "id": 7365659,
        "name:xx": "Enmedio"
      }
    }
  ]
}
