{
  "geometry": {
    "type": "Point",
    "coordinates": [
      -99.8833,
      30.4833
    ]
  },
  "type": "Feature",
  "properties": {
    "hierarchy": [
      "tgn:2214741",
      "tgn:1000001",
      "tgn:7012149",
      "tgn:2002019",
      "tgn:7007826",
      "tgn:7029392"
    ],
    "placetype": [
      "aat:300008706"
    ],
    "id": 2214741,
    "name:xx": "Calf Creek"
  }
}
