{
  "type": "FeatureCollection",
  "features": [
    {
      "geometry": {
        "type": "Point",
        "coordinates": [
          -104.166667,
          20.733333
        ]
      },
      "type": "Feature",
      "properties": {
        "hierarchy": [
          "tgn:7396390",
          "tgn:7005586",
          "tgn:1000001",
          "tgn:7005560",
          "tgn:7029392"
        ],
        "placetype": [
          "aat:300008347"
        ],
        "id": 7396390,
        "name:xx": "San Rafael"
      }
    },
    {
      "geometry": {
        "type": "Point",
        "coordinates": [
          -90.15,
          20.7
        ]
      },
      "type": "Feature",
      "properties": {
        "hierarchy": [
          "tgn:7396391",
          "tgn:1000001",
          "tgn:7005600",
          "tgn:7005560",
          "tgn:7029392"
        ],
        "placetype": [
          "aat:300008347"
        ],
        "id": 7396391,
        "name:xx": "San Rafael"
      }
    },
    {
      "geometry": {
        "type": "Point",
        "coordinates": [
          -88.483333,
          20.633333
        ]
      },
      "type": "Feature",
      "properties": {
        "hierarchy": [
          "tgn:7396392",
          "tgn:1000001",
          "tgn:7005600",
          "tgn:7005560",
          "tgn:7029392"
        ],
        "placetype": [
          "aat:300008347"
        ],
        "id": 7396392,
        "name:xx": "San Rafael"
      }
    },
    {
      "geometry": {
        "type": "Point",
        "coordinates": [
          -101.033333,
          23.7
        ]
      },
      "type": "Feature",
      "properties": {
        "hierarchy": [
          "tgn:7396393",
          "tgn:1000001",
          "tgn:7005594",
          "tgn:7005560",
          "tgn:7029392"
        ],
        "placetype": [
          "aat:300008347"
        ],
        "id": 7396393,
        "name:xx": "San Miguel"
      }
    },
    {
      "geometry": {
        "type": "Point",
        "coordinates": [
          -97.95,
          23.7
        ]
      },
      "type": "Feature",
      "properties": {
        "hierarchy": [
          "tgn:7396394",
          "tgn:1000001",
          "tgn:7005597",
          "tgn:7005560",
          "tgn:7029392"
        ],
        "placetype": [
          "aat:300008347"
        ],
        "id": 7396394,
        "name:xx": "San Miguel"
      }
    },
    {
      "geometry": {
        "type": "Point",
        "coordinates": [
          -103.283333,
          23.533333
        ]
      },
      "type": "Feature",
      "properties": {
        "hierarchy": [
          "tgn:7396395",
          "tgn:1000001",
          "tgn:7005601",
          "tgn:7005560",
          "tgn:7029392"
        ],
        "placetype": [
          "aat:300008347"
        ],
        "id": 7396395,
        "name:xx": "San Miguel"
      }
    },
    {
      "geometry": {
        "type": "Point",
        "coordinates": [
          -100.2,
          23.416667
        ]
      },
      "type": "Feature",
      "properties": {
        "hierarchy": [
          "tgn:7396396",
          "tgn:1000001",
          "tgn:7005589",
          "tgn:7005560",
          "tgn:7029392"
        ],
        "placetype": [
          "aat:300008347"
        ],
        "id": 7396396,
        "name:xx": "San Miguel"
      }
    },
    {
      "geometry": {
        "type": "Point",
        "coordinates": [
          -102.716667,
          23.35
        ]
      },
      "type": "Feature",
      "properties": {
        "hierarchy": [
          "tgn:7396398",
          "tgn:1000001",
          "tgn:7005601",
          "tgn:7005560",
          "tgn:7029392"
        ],
        "placetype": [
          "aat:300008347"
        ],
        "id": 7396398,
        "name:xx": "San Miguel"
      }
    },
    {
      "geometry": {
        "type": "Point",
        "coordinates": [
          -100.55,
          23.316667
        ]
      },
      "type": "Feature",
      "properties": {
        "hierarchy": [
          "tgn:7396399",
          "tgn:1000001",
          "tgn:7005594",
          "tgn:7005560",
          "tgn:7029392"
        ],
        "placetype": [
          "aat:300008347"
        ],
        "id": 7396399,
        "name:xx": "San Miguel"
      }
    }
  ]
}
