{
  "geometry": {
    "type": "Point",
    "coordinates": [
      -60.6333,
      45.8333
    ]
  },
  "type": "Feature",
  "properties": {
    "hierarchy": [
      "tgn:1117066",
      "tgn:7013022",
      "tgn:7005685",
      "tgn:1000001",
      "tgn:7005802",
      "tgn:7029392"
    ],
    "placetype": [
      "aat:300008680"
    ],
    "id": 1117066,
    "name:xx": "Lomond, Loch"
  }
}
