{
  "geometry": {
    "type": "Point",
    "coordinates": [
      -0.3833,
      51.4333
    ]
  },
  "type": "Feature",
  "properties": {
    "hierarchy": [
      "tgn:7011834",
      "tgn:7002445",
      "tgn:7018921",
      "tgn:1000003",
      "tgn:7008136",
      "tgn:7008591",
      "tgn:7029392"
    ],
    "placetype": [
      "aat:300008347",
      "aat:300000745",
      "aat:300000874"
    ],
    "name:en": "Hanworth",
    "id": 7011834
  }
}
