{
  "geometry": {
    "type": "Point",
    "coordinates": [
      -87.85,
      38.25
    ]
  },
  "type": "Feature",
  "properties": {
    "hierarchy": [
      "tgn:2333754",
      "tgn:1000001",
      "tgn:7012149",
      "tgn:2000543",
      "tgn:7007252",
      "tgn:7029392"
    ],
    "placetype": [
      "aat:300008680"
    ],
    "id": 2333754,
    "name:xx": "Foote Pond"
  }
}
