{
  "geometry": {
    "type": "Point",
    "coordinates": [
      -92.1667,
      34.7167
    ]
  },
  "type": "Feature",
  "properties": {
    "hierarchy": [
      "tgn:2460018",
      "tgn:1000001",
      "tgn:7016172",
      "tgn:7012149",
      "tgn:2000164",
      "tgn:7029392"
    ],
    "placetype": [
      "aat:300008678"
    ],
    "id": 2460018,
    "name:xx": "Little Rock Port"
  }
}
