{
  "geometry": {
    "type": "Point",
    "coordinates": [
      -73.9667,
      44.3167
    ]
  },
  "type": "Feature",
  "properties": {
    "hierarchy": [
      "tgn:2523473",
      "tgn:1000001",
      "tgn:7012149",
      "tgn:2001461",
      "tgn:7007568",
      "tgn:7029392"
    ],
    "placetype": [
      "aat:300008791"
    ],
    "id": 2523473,
    "name:xx": "Moose Island"
  }
}
