{
  "geometry": {
    "type": "Point",
    "coordinates": [
      -107.25,
      34.1333
    ]
  },
  "type": "Feature",
  "properties": {
    "hierarchy": [
      "tgn:2416584",
      "tgn:1000001",
      "tgn:7012149",
      "tgn:2001456",
      "tgn:7007566",
      "tgn:7029392"
    ],
    "placetype": [
      "aat:300000390"
    ],
    "id": 2416584,
    "name:xx": "Jack Frost"
  }
}
