{
  "geometry": {
    "type": "Point",
    "coordinates": [
      -105.8833,
      32.4667
    ]
  },
  "type": "Feature",
  "properties": {
    "hierarchy": [
      "tgn:2558141",
      "tgn:1000001",
      "tgn:7012149",
      "tgn:2001447",
      "tgn:7007566",
      "tgn:7029392"
    ],
    "placetype": [
      "aat:300008347"
    ],
    "id": 2558141,
    "name:xx": "Old Wright Place"
  }
}
