{
  "geometry": {
    "type": "Point",
    "coordinates": [
      -120.85,
      39.0167
    ]
  },
  "type": "Feature",
  "properties": {
    "hierarchy": [
      "tgn:2015049",
      "tgn:1000001",
      "tgn:7012149",
      "tgn:7007157",
      "tgn:1002791",
      "tgn:7029392"
    ],
    "placetype": [
      "aat:300008347"
    ],
    "id": 2015049,
    "name:xx": "Yankee Jims"
  }
}
