{
  "geometry": {
    "type": "Point",
    "coordinates": [
      87.99181,
      23.066635
    ]
  },
  "type": "Feature",
  "properties": {
    "hierarchy": [
      "tgn:7570829",
      "tgn:1000004",
      "tgn:7000198",
      "tgn:1001977",
      "tgn:7029392"
    ],
    "placetype": [
      "aat:300008347"
    ],
    "name:en": "Jamālpur",
    "id": 7570829
  }
}
