{
  "geometry": {
    "type": "Point",
    "coordinates": [
      -2.8833,
      27.3667
    ]
  },
  "type": "Feature",
  "properties": {
    "hierarchy": [
      "tgn:1087394",
      "tgn:1000486",
      "tgn:7001242",
      "tgn:7016752",
      "tgn:7029392"
    ],
    "placetype": [
      "aat:300008347"
    ],
    "id": 1087394,
    "name:xx": "Bous Bernous"
  }
}
