{
  "geometry": {
    "type": "Point",
    "coordinates": [
      -77.9833,
      8.25
    ]
  },
  "type": "Feature",
  "properties": {
    "hierarchy": [
      "tgn:1121637",
      "tgn:7005572",
      "tgn:1000001",
      "tgn:7005565",
      "tgn:7029392"
    ],
    "placetype": [
      "aat:300008707"
    ],
    "id": 1121637,
    "name:xx": "Balsas, Río"
  }
}
