{
  "geometry": {
    "type": "Point",
    "coordinates": [
      -106.2167,
      48.2833
    ]
  },
  "type": "Feature",
  "properties": {
    "hierarchy": [
      "tgn:2644671",
      "tgn:1000001",
      "tgn:7012149",
      "tgn:2001312",
      "tgn:7007524",
      "tgn:7029392"
    ],
    "placetype": [
      "aat:300008706"
    ],
    "id": 2644671,
    "name:xx": "Sargent Creek"
  }
}
