{
  "type": "FeatureCollection",
  "features": [
    {
      "geometry": {
        "type": "Point",
        "coordinates": [
          -70.983333,
          -33.2
        ]
      },
      "type": "Feature",
      "properties": {
        "hierarchy": [
          "tgn:7279340",
          "tgn:1001708",
          "tgn:1000049",
          "tgn:1000002",
          "tgn:7029392"
        ],
        "placetype": [
          "aat:300387002"
        ],
        "id": 7279340,
        "name:xx": "Roble Alto, Loma del"
      }
    },
    {
      "geometry": {
        "type": "Point",
        "coordinates": [
          -71,
          -33.2
        ]
      },
      "type": "Feature",
      "properties": {
        "hierarchy": [
          "tgn:7279341",
          "tgn:1001708",
          "tgn:1000049",
          "tgn:1000002",
          "tgn:7029392"
        ],
        "placetype": [
          "aat:300008795"
        ],
        "id": 7279341,
        "name:xx": "Roble Alto, Cerro"
      }
    },
    {
      "geometry": {
        "type": "Point",
        "coordinates": [
          -71.983333,
          -34.333333
        ]
      },
      "type": "Feature",
      "properties": {
        "hierarchy": [
          "tgn:7279342",
          "tgn:1001695",
          "tgn:1000049",
          "tgn:1000002",
          "tgn:7029392"
        ],
        "placetype": [
          "aat:300008699"
        ],
        "id": 7279342,
        "name:xx": "Roble, Quebrada del"
      }
    },
    {
      "geometry": {
        "type": "Point",
        "coordinates": [
          -70.966667,
          -34.033333
        ]
      },
      "type": "Feature",
      "properties": {
        "hierarchy": [
          "tgn:7279343",
          "tgn:1001708",
          "tgn:1000049",
          "tgn:1000002",
          "tgn:7029392"
        ],
        "placetype": [
          "aat:300008699"
        ],
        "id": 7279343,
        "name:xx": "Roble, Quebrada del"
      }
    },
    {
      "geometry": {
        "type": "Point",
        "coordinates": [
          -74.355,
          -43.285833
        ]
      },
      "type": "Feature",
      "properties": {
        "hierarchy": [
          "tgn:7279344",
          "tgn:1001699",
          "tgn:1000049",
          "tgn:1000002",
          "tgn:7029392"
        ],
        "placetype": [
          "aat:300386846"
        ],
        "id": 7279344,
        "name:xx": "Roble, Punta"
      }
    },
    {
      "geometry": {
        "type": "Point",
        "coordinates": [
          -73.916667,
          -52.25
        ]
      },
      "type": "Feature",
      "properties": {
        "hierarchy": [
          "tgn:7279345",
          "tgn:1001702",
          "tgn:1000049",
          "tgn:1000002",
          "tgn:7029392"
        ],
        "placetype": [
          "aat:300008795"
        ],
        "id": 7279345,
        "name:xx": "Roble, Pico del"
      }
    },
    {
      "geometry": {
        "type": "Point",
        "coordinates": [
          -73.15,
          -40.4
        ]
      },
      "type": "Feature",
      "properties": {
        "hierarchy": [
          "tgn:7279346",
          "tgn:1001699",
          "tgn:1000049",
          "tgn:1000002",
          "tgn:7029392"
        ],
        "placetype": [
          "aat:300008699"
        ],
        "id": 7279346,
        "name:xx": "Roble, Estero"
      }
    },
    {
      "geometry": {
        "type": "Point",
        "coordinates": [
          -72,
          -35.383333
        ]
      },
      "type": "Feature",
      "properties": {
        "hierarchy": [
          "tgn:7279348",
          "tgn:1001705",
          "tgn:1000049",
          "tgn:1000002",
          "tgn:7029392"
        ],
        "placetype": [
          "aat:300008795"
        ],
        "id": 7279348,
        "name:xx": "Roble, Alto del"
      }
    }
  ]
}
