{
  "geometry": {
    "type": "Point",
    "coordinates": [
      -110.6167,
      41.0333
    ]
  },
  "type": "Feature",
  "properties": {
    "hierarchy": [
      "tgn:7020028",
      "tgn:1000001",
      "tgn:7012149",
      "tgn:2002385",
      "tgn:7007923",
      "tgn:7029392"
    ],
    "placetype": [
      "aat:300006191"
    ],
    "id": 7020028,
    "name:xx": "Van Tassel Lake"
  }
}
