{
  "geometry": {
    "type": "Point",
    "coordinates": [
      38.3833,
      48.5333
    ]
  },
  "type": "Feature",
  "properties": {
    "hierarchy": [
      "tgn:1138522",
      "tgn:1000003",
      "tgn:7012067",
      "tgn:7006660",
      "tgn:7029392"
    ],
    "placetype": [
      "aat:300008347",
      "aat:300008375"
    ],
    "id": 1138522,
    "name:xx": "Troyits'ke"
  }
}
