{
  "geometry": {
    "type": "Point",
    "coordinates": [
      79.9833,
      6.5833
    ]
  },
  "type": "Feature",
  "properties": {
    "hierarchy": [
      "tgn:1066458",
      "tgn:1000004",
      "tgn:7000408",
      "tgn:1000110",
      "tgn:7029392"
    ],
    "placetype": [
      "aat:300008347"
    ],
    "id": 1066458,
    "name:xx": "Kalutara"
  }
}
