{
  "geometry": {
    "type": "Point",
    "coordinates": [
      -119.25,
      40.4167
    ]
  },
  "type": "Feature",
  "properties": {
    "hierarchy": [
      "tgn:2165352",
      "tgn:1000001",
      "tgn:2001419",
      "tgn:7012149",
      "tgn:7007526",
      "tgn:7029392"
    ],
    "placetype": [
      "aat:300008706"
    ],
    "id": 2165352,
    "name:xx": "Betty Creek"
  }
}
