{
  "geometry": {
    "type": "Point",
    "coordinates": [
      -161.2667,
      67.6333
    ]
  },
  "type": "Feature",
  "properties": {
    "hierarchy": [
      "tgn:2127437",
      "tgn:7006450",
      "tgn:1000001",
      "tgn:7012149",
      "tgn:2124014",
      "tgn:7029392"
    ],
    "placetype": [
      "aat:300008706"
    ],
    "id": 2127437,
    "name:xx": "Akikukchiak Creek"
  }
}
