{
  "geometry": {
    "type": "Point",
    "coordinates": [
      77.413626,
      29.74927
    ]
  },
  "type": "Feature",
  "properties": {
    "hierarchy": [
      "tgn:7590235",
      "tgn:1000004",
      "tgn:7000198",
      "tgn:7016722",
      "tgn:7029392"
    ],
    "placetype": [
      "aat:300008347"
    ],
    "name:en": "Jogīpura",
    "id": 7590235
  }
}
