{
  "geometry": {
    "type": "Point",
    "coordinates": [
      8.2667,
      47.05
    ]
  },
  "type": "Feature",
  "properties": {
    "hierarchy": [
      "tgn:1064200",
      "tgn:1000003",
      "tgn:7003750",
      "tgn:7011731",
      "tgn:7029392"
    ],
    "placetype": [
      "aat:300008347"
    ],
    "id": 1064200,
    "name:xx": "Littau"
  }
}
