{
  "geometry": {
    "type": "Point",
    "coordinates": [
      -77.2833,
      40.4167
    ]
  },
  "type": "Feature",
  "properties": {
    "hierarchy": [
      "tgn:2452730",
      "tgn:1000001",
      "tgn:7012149",
      "tgn:1002779",
      "tgn:7007710",
      "tgn:7029392"
    ],
    "placetype": [
      "aat:300008706"
    ],
    "id": 2452730,
    "name:xx": "Little Buffalo Creek"
  }
}
