{
  "geometry": {
    "type": "Point",
    "coordinates": [
      23.7167,
      50.1333
    ]
  },
  "type": "Feature",
  "properties": {
    "hierarchy": [
      "tgn:1056656",
      "tgn:1000003",
      "tgn:7011664",
      "tgn:7006660",
      "tgn:7029392"
    ],
    "placetype": [
      "aat:300008347"
    ],
    "id": 1056656,
    "name:xx": "Maheriv"
  }
}
