{
  "geometry": {
    "type": "Point",
    "coordinates": [
      -102.747222,
      21.8875
    ]
  },
  "type": "Feature",
  "properties": {
    "hierarchy": [
      "tgn:7421537",
      "tgn:7005579",
      "tgn:1000001",
      "tgn:7005560",
      "tgn:7029392"
    ],
    "placetype": [
      "aat:300008347"
    ],
    "id": 7421537,
    "name:xx": "Peña Blanca"
  }
}
