{
  "geometry": {
    "type": "Point",
    "coordinates": [
      -124.2167,
      42.5333
    ]
  },
  "type": "Feature",
  "properties": {
    "hierarchy": [
      "tgn:2279233",
      "tgn:1000001",
      "tgn:2001704",
      "tgn:7012149",
      "tgn:7007708",
      "tgn:7029392"
    ],
    "placetype": [
      "aat:300008706"
    ],
    "id": 2279233,
    "name:xx": "Deadline Creek"
  }
}
