{
  "type": "FeatureCollection",
  "features": [
    {
      "geometry": {
        "type": "Point",
        "coordinates": [
          -89.85,
          34.9833
        ]
      },
      "type": "Feature",
      "properties": {
        "hierarchy": [
          "tgn:2056991",
          "tgn:1000001",
          "tgn:2001102",
          "tgn:7012149",
          "tgn:7007522",
          "tgn:7029392"
        ],
        "placetype": [
          "aat:300008347"
        ],
        "id": 2056991,
        "name:xx": "Mineral Wells"
      }
    },
    {
      "geometry": {
        "type": "Point",
        "coordinates": [
          -88.15,
          34.6167
        ]
      },
      "type": "Feature",
      "properties": {
        "hierarchy": [
          "tgn:2056992",
          "tgn:1000001",
          "tgn:7012149",
          "tgn:2001156",
          "tgn:7007522",
          "tgn:7029392"
        ],
        "placetype": [
          "aat:300008347",
          "aat:300387210"
        ],
        "id": 2056992,
        "name:xx": "Mingo"
      }
    },
    {
      "geometry": {
        "type": "Point",
        "coordinates": [
          -90.2833,
          33.75
        ]
      },
      "type": "Feature",
      "properties": {
        "hierarchy": [
          "tgn:2056993",
          "tgn:1000001",
          "tgn:7012149",
          "tgn:2001127",
          "tgn:7007522",
          "tgn:7029392"
        ],
        "placetype": [
          "aat:300008347"
        ],
        "id": 2056993,
        "name:xx": "Minter City"
      }
    },
    {
      "geometry": {
        "type": "Point",
        "coordinates": [
          -89.05,
          32.1
        ]
      },
      "type": "Feature",
      "properties": {
        "hierarchy": [
          "tgn:2056994",
          "tgn:1000001",
          "tgn:7012149",
          "tgn:2001116",
          "tgn:7007522",
          "tgn:7029392"
        ],
        "placetype": [
          "aat:300008347",
          "aat:300387210"
        ],
        "id": 2056994,
        "name:xx": "Missionary"
      }
    },
    {
      "geometry": {
        "type": "Point",
        "coordinates": [
          -88.7833,
          33.45
        ]
      },
      "type": "Feature",
      "properties": {
        "hierarchy": [
          "tgn:2056995",
          "tgn:1000001",
          "tgn:7012149",
          "tgn:2001138",
          "tgn:7007522",
          "tgn:7029392"
        ],
        "placetype": [
          "aat:300008347"
        ],
        "id": 2056995,
        "name:xx": "State College"
      }
    },
    {
      "geometry": {
        "type": "Point",
        "coordinates": [
          -90.3333,
          33.5
        ]
      },
      "type": "Feature",
      "properties": {
        "hierarchy": [
          "tgn:2056997",
          "tgn:1000001",
          "tgn:7012149",
          "tgn:2001127",
          "tgn:7007522",
          "tgn:7029392"
        ],
        "placetype": [
          "aat:300006617"
        ],
        "id": 2056997,
        "name:xx": "Mississippi Valley State University"
      }
    },
    {
      "geometry": {
        "type": "Point",
        "coordinates": [
          -88.8333,
          34.7
        ]
      },
      "type": "Feature",
      "properties": {
        "hierarchy": [
          "tgn:2056998",
          "tgn:1000001",
          "tgn:7012149",
          "tgn:2001155",
          "tgn:7007522",
          "tgn:7029392"
        ],
        "placetype": [
          "aat:300008347",
          "aat:300387210"
        ],
        "id": 2056998,
        "name:xx": "Mitchell"
      }
    }
  ]
}
