{
  "type": "FeatureCollection",
  "features": [
    {
      "geometry": {
        "type": "Point",
        "coordinates": [
          -72.25,
          -41.433333
        ]
      },
      "type": "Feature",
      "properties": {
        "hierarchy": [
          "tgn:7319180",
          "tgn:1001699",
          "tgn:1000049",
          "tgn:1000002",
          "tgn:7029392"
        ],
        "placetype": [
          "aat:300008795"
        ],
        "id": 7319180,
        "name:xx": "Angostura, Cerro de la"
      }
    },
    {
      "geometry": {
        "type": "Point",
        "coordinates": [
          -71.016667,
          -35.1
        ]
      },
      "type": "Feature",
      "properties": {
        "hierarchy": [
          "tgn:7319181",
          "tgn:1001705",
          "tgn:1000049",
          "tgn:1000002",
          "tgn:7029392"
        ],
        "placetype": [
          "aat:300008777"
        ],
        "id": 7319181,
        "name:xx": "Angostura, Cerro"
      }
    },
    {
      "geometry": {
        "type": "Point",
        "coordinates": [
          -71.2,
          -33.883333
        ]
      },
      "type": "Feature",
      "properties": {
        "hierarchy": [
          "tgn:7319182",
          "tgn:1001708",
          "tgn:1000049",
          "tgn:1000002",
          "tgn:7029392"
        ],
        "placetype": [
          "aat:300008777"
        ],
        "id": 7319182,
        "name:xx": "Angostura, Cerro"
      }
    },
    {
      "geometry": {
        "type": "Point",
        "coordinates": [
          -70,
          -26.616667
        ]
      },
      "type": "Feature",
      "properties": {
        "hierarchy": [
          "tgn:7319183",
          "tgn:1001630",
          "tgn:1000049",
          "tgn:1000002",
          "tgn:7029392"
        ],
        "placetype": [
          "aat:300008777"
        ],
        "id": 7319183,
        "name:xx": "Angostura, Cerro"
      }
    },
    {
      "geometry": {
        "type": "Point",
        "coordinates": [
          -69.983333,
          -19.116667
        ]
      },
      "type": "Feature",
      "properties": {
        "hierarchy": [
          "tgn:7319184",
          "tgn:7002464",
          "tgn:1000049",
          "tgn:1000002",
          "tgn:7029392"
        ],
        "placetype": [
          "aat:300387033"
        ],
        "id": 7319184,
        "name:xx": "Angostura"
      }
    },
    {
      "geometry": {
        "type": "Point",
        "coordinates": [
          -69.816667,
          -18.233333
        ]
      },
      "type": "Feature",
      "properties": {
        "hierarchy": [
          "tgn:7319185",
          "tgn:7002464",
          "tgn:1000049",
          "tgn:1000002",
          "tgn:7029392"
        ],
        "placetype": [
          "aat:300007783"
        ],
        "id": 7319185,
        "name:xx": "Angostura"
      }
    },
    {
      "geometry": {
        "type": "Point",
        "coordinates": [
          -70.733333,
          -33.9
        ]
      },
      "type": "Feature",
      "properties": {
        "hierarchy": [
          "tgn:7319186",
          "tgn:1001708",
          "tgn:1000049",
          "tgn:1000002",
          "tgn:7029392"
        ],
        "placetype": [
          "aat:300008347"
        ],
        "id": 7319186,
        "name:xx": "Angostura"
      }
    },
    {
      "geometry": {
        "type": "Point",
        "coordinates": [
          -71.55,
          -31.5
        ]
      },
      "type": "Feature",
      "properties": {
        "hierarchy": [
          "tgn:7319187",
          "tgn:1001657",
          "tgn:1000049",
          "tgn:1000002",
          "tgn:7029392"
        ],
        "placetype": [
          "aat:300008347"
        ],
        "id": 7319187,
        "name:xx": "Angostura"
      }
    },
    {
      "geometry": {
        "type": "Point",
        "coordinates": [
          -71.633333,
          -30.716667
        ]
      },
      "type": "Feature",
      "properties": {
        "hierarchy": [
          "tgn:7319188",
          "tgn:1001657",
          "tgn:1000049",
          "tgn:1000002",
          "tgn:7029392"
        ],
        "placetype": [
          "aat:300008347"
        ],
        "id": 7319188,
        "name:xx": "Angostura"
      }
    },
    {
      "geometry": {
        "type": "Point",
        "coordinates": [
          -69.466667,
          -27.55
        ]
      },
      "type": "Feature",
      "properties": {
        "hierarchy": [
          "tgn:7319189",
          "tgn:1001630",
          "tgn:1000049",
          "tgn:1000002",
          "tgn:7029392"
        ],
        "placetype": [
          "aat:300008347"
        ],
        "id": 7319189,
        "name:xx": "Angostura"
      }
    }
  ]
}
