{
  "geometry": {
    "type": "Point",
    "coordinates": [
      -112.05,
      45.4167
    ]
  },
  "type": "Feature",
  "properties": {
    "hierarchy": [
      "tgn:2635386",
      "tgn:1000001",
      "tgn:7012149",
      "tgn:2001288",
      "tgn:7007524",
      "tgn:7029392"
    ],
    "placetype": [
      "aat:300000390"
    ],
    "id": 2635386,
    "name:xx": "SE SE Section 11 Mine"
  }
}
