{
  "type": "FeatureCollection",
  "features": [
    {
      "geometry": {
        "type": "Point",
        "coordinates": [
          -110.6833,
          34.55
        ]
      },
      "type": "Feature",
      "properties": {
        "hierarchy": [
          "tgn:2601340",
          "tgn:1000001",
          "tgn:7006451",
          "tgn:7012149",
          "tgn:2000099",
          "tgn:7029392"
        ],
        "placetype": [
          "aat:300006191"
        ],
        "id": 2601340,
        "name:xx": "Purcell Tank"
      }
    },
    {
      "geometry": {
        "type": "Point",
        "coordinates": [
          -116.5,
          49
        ]
      },
      "type": "Feature",
      "properties": {
        "hierarchy": [
          "tgn:2601341",
          "tgn:1000001",
          "tgn:7012149",
          "tgn:7007250",
          "tgn:7029392"
        ],
        "placetype": [
          "aat:300008761"
        ],
        "id": 2601341,
        "name:xx": "Purcell Trench"
      }
    },
    {
      "geometry": {
        "type": "Point",
        "coordinates": [
          -77.7667,
          39.1833
        ]
      },
      "type": "Feature",
      "properties": {
        "hierarchy": [
          "tgn:2601342",
          "tgn:1000001",
          "tgn:7012149",
          "tgn:7015770",
          "tgn:7007919",
          "tgn:7029392"
        ],
        "placetype": [
          "aat:300006191"
        ],
        "id": 2601342,
        "name:xx": "Purcellville Reservoir"
      }
    },
    {
      "geometry": {
        "type": "Point",
        "coordinates": [
          -93.7,
          37.8
        ]
      },
      "type": "Feature",
      "properties": {
        "hierarchy": [
          "tgn:2601343",
          "tgn:1000001",
          "tgn:7012149",
          "tgn:7007523",
          "tgn:7029392"
        ],
        "placetype": [
          "aat:300008699"
        ],
        "id": 2601343,
        "name:xx": "Purcett Branch"
      }
    },
    {
      "geometry": {
        "type": "Point",
        "coordinates": [
          -70.9167,
          41.9
        ]
      },
      "type": "Feature",
      "properties": {
        "hierarchy": [
          "tgn:2601344",
          "tgn:1000001",
          "tgn:7014423",
          "tgn:7012149",
          "tgn:7007517",
          "tgn:7029392"
        ],
        "placetype": [
          "aat:300008699"
        ],
        "id": 2601344,
        "name:xx": "Purchade Brook"
      }
    },
    {
      "geometry": {
        "type": "Point",
        "coordinates": [
          -73.2833,
          41.4833
        ]
      },
      "type": "Feature",
      "properties": {
        "hierarchy": [
          "tgn:2601345",
          "tgn:1000001",
          "tgn:1002601",
          "tgn:7012149",
          "tgn:7007159",
          "tgn:7029392"
        ],
        "placetype": [
          "aat:300008699"
        ],
        "id": 2601345,
        "name:xx": "Purchase Brook"
      }
    },
    {
      "geometry": {
        "type": "Point",
        "coordinates": [
          -73.0833,
          43.4
        ]
      },
      "type": "Feature",
      "properties": {
        "hierarchy": [
          "tgn:2601346",
          "tgn:1000001",
          "tgn:1002840",
          "tgn:7012149",
          "tgn:7007828",
          "tgn:7029392"
        ],
        "placetype": [
          "aat:300008699"
        ],
        "id": 2601346,
        "name:xx": "Purchase Brook"
      }
    },
    {
      "geometry": {
        "type": "Point",
        "coordinates": [
          -76.7167,
          35.9
        ]
      },
      "type": "Feature",
      "properties": {
        "hierarchy": [
          "tgn:2601347",
          "tgn:1000001",
          "tgn:7012149",
          "tgn:7007709",
          "tgn:7029392"
        ],
        "placetype": [
          "aat:300386853"
        ],
        "id": 2601347,
        "name:xx": "Purchase Islands"
      }
    },
    {
      "geometry": {
        "type": "Point",
        "coordinates": [
          -83.05,
          35.5833
        ]
      },
      "type": "Feature",
      "properties": {
        "hierarchy": [
          "tgn:2601348",
          "tgn:1000001",
          "tgn:7012149",
          "tgn:2001503",
          "tgn:7007709",
          "tgn:7029392"
        ],
        "placetype": [
          "aat:300008798"
        ],
        "id": 2601348,
        "name:xx": "Purchase Knob"
      }
    },
    {
      "geometry": {
        "type": "Point",
        "coordinates": [
          -82.8,
          36.6667
        ]
      },
      "type": "Feature",
      "properties": {
        "hierarchy": [
          "tgn:2601349",
          "tgn:1000001",
          "tgn:7012149",
          "tgn:2002189",
          "tgn:7007919",
          "tgn:7029392"
        ],
        "placetype": [
          "aat:300008798"
        ],
        "id": 2601349,
        "name:xx": "Purchase Knob"
      }
    }
  ]
}
