{
  "geometry": {
    "type": "Point",
    "coordinates": [
      -88.9833,
      31.3667
    ]
  },
  "type": "Feature",
  "properties": {
    "hierarchy": [
      "tgn:2377476",
      "tgn:1000001",
      "tgn:7012149",
      "tgn:2001141",
      "tgn:7007522",
      "tgn:7029392"
    ],
    "placetype": [
      "aat:300008699"
    ],
    "id": 2377476,
    "name:xx": "Harper Branch"
  }
}
