{
  "geometry": {
    "type": "Point",
    "coordinates": [
      -79.05,
      43.25
    ]
  },
  "type": "Feature",
  "properties": {
    "hierarchy": [
      "tgn:1102272",
      "tgn:1000001",
      "tgn:7012149",
      "tgn:1002718",
      "tgn:7007568",
      "tgn:7029392"
    ],
    "placetype": [
      "aat:300008192"
    ],
    "id": 1102272,
    "name:xx": "Fort Niagara State Park"
  }
}
