{
  "geometry": {
    "type": "Point",
    "coordinates": [
      -117.4667,
      33.65
    ]
  },
  "type": "Feature",
  "properties": {
    "hierarchy": [
      "tgn:2470611",
      "tgn:1000001",
      "tgn:7012149",
      "tgn:7007157",
      "tgn:1002748",
      "tgn:7029392"
    ],
    "placetype": [
      "aat:300008798"
    ],
    "id": 2470611,
    "name:xx": "Los Pinos Peak"
  }
}
