{
  "geometry": {
    "type": "Point",
    "coordinates": [
      -114.1333,
      36.2667
    ]
  },
  "type": "Feature",
  "properties": {
    "hierarchy": [
      "tgn:2344897",
      "tgn:1000001",
      "tgn:7012149",
      "tgn:7029392"
    ],
    "placetype": [
      "aat:300008761"
    ],
    "id": 2344897,
    "name:xx": "Garden Wash"
  }
}
