{
  "geometry": {
    "type": "Point",
    "coordinates": [
      -104.4667,
      43.65
    ]
  },
  "type": "Feature",
  "properties": {
    "hierarchy": [
      "tgn:2721819",
      "tgn:1000001",
      "tgn:7012149",
      "tgn:2002387",
      "tgn:7007923",
      "tgn:7029392"
    ],
    "placetype": [
      "aat:300008706"
    ],
    "id": 2721819,
    "name:xx": "Timber Creek"
  }
}
