{
  "geometry": {
    "type": "Point",
    "coordinates": [
      -111.7667,
      40.5833
    ]
  },
  "type": "Feature",
  "properties": {
    "hierarchy": [
      "tgn:2420193",
      "tgn:1000001",
      "tgn:7012149",
      "tgn:2002118",
      "tgn:7007827",
      "tgn:7029392"
    ],
    "placetype": [
      "aat:300008761"
    ],
    "id": 2420193,
    "name:xx": "Jefferson Hollow"
  }
}
