{
  "geometry": {
    "type": "Point",
    "coordinates": [
      -109.4167,
      44.5167
    ]
  },
  "type": "Feature",
  "properties": {
    "hierarchy": [
      "tgn:2369623",
      "tgn:1000001",
      "tgn:7012149",
      "tgn:2002379",
      "tgn:7007923",
      "tgn:7029392"
    ],
    "placetype": [
      "aat:300008706"
    ],
    "id": 2369623,
    "name:xx": "Gunnysack Creek"
  }
}
