{
  "geometry": {
    "type": "Point",
    "coordinates": [
      -121.3667,
      40.4667
    ]
  },
  "type": "Feature",
  "properties": {
    "hierarchy": [
      "tgn:1101667",
      "tgn:1000001",
      "tgn:7012149",
      "tgn:7007157",
      "tgn:7029392"
    ],
    "placetype": [
      "aat:300008189"
    ],
    "id": 1101667,
    "name:xx": "Lassen Volcanic National Park"
  }
}
