{
  "geometry": {
    "type": "Point",
    "coordinates": [
      -84.8833,
      38.7667
    ]
  },
  "type": "Feature",
  "properties": {
    "hierarchy": [
      "tgn:2424872",
      "tgn:1000001",
      "tgn:7012149",
      "tgn:1002400",
      "tgn:7007255",
      "tgn:7029392"
    ],
    "placetype": [
      "aat:300008798"
    ],
    "id": 2424872,
    "name:xx": "Johnson Hill"
  }
}
