{
  "geometry": {
    "type": "Point",
    "coordinates": [
      -73.1667,
      44.9833
    ]
  },
  "type": "Feature",
  "properties": {
    "hierarchy": [
      "tgn:2292164",
      "tgn:1000001",
      "tgn:1002389",
      "tgn:7012149",
      "tgn:7007828",
      "tgn:7029392"
    ],
    "placetype": [
      "aat:300008850"
    ],
    "id": 2292164,
    "name:xx": "Donaldson Point"
  }
}
