{
  "geometry": {
    "type": "Point",
    "coordinates": [
      -88.3333,
      37.05
    ]
  },
  "type": "Feature",
  "properties": {
    "hierarchy": [
      "tgn:2255183",
      "tgn:1000001",
      "tgn:7012149",
      "tgn:2000814",
      "tgn:7007255",
      "tgn:7029392"
    ],
    "placetype": [
      "aat:300008347"
    ],
    "id": 2255183,
    "name:xx": "Cooper Landing"
  }
}
