{
  "type": "FeatureCollection",
  "features": [
    {
      "geometry": {
        "type": "Point",
        "coordinates": [
          31.832688,
          31.422549
        ]
      },
      "type": "Feature",
      "properties": {
        "hierarchy": [
          "tgn:7544260",
          "tgn:7001242",
          "tgn:1001059",
          "tgn:7016833",
          "tgn:7029392"
        ],
        "placetype": [
          "aat:300000206"
        ],
        "name:en": "'Izbat al Qubūr",
        "id": 7544260
      }
    },
    {
      "geometry": {
        "type": "Point",
        "coordinates": [
          31.598151,
          31.185535
        ]
      },
      "type": "Feature",
      "properties": {
        "hierarchy": [
          "tgn:7544261",
          "tgn:7001242",
          "tgn:7016833",
          "tgn:1001225",
          "tgn:7029392"
        ],
        "placetype": [
          "aat:300006075"
        ],
        "name:en": "Tir'at ash Sharqāwīyah",
        "id": 7544261
      }
    },
    {
      "geometry": {
        "type": "Point",
        "coordinates": [
          31.778856,
          31.419552
        ]
      },
      "type": "Feature",
      "properties": {
        "hierarchy": [
          "tgn:7544262",
          "tgn:7001242",
          "tgn:7016833",
          "tgn:1001225",
          "tgn:7029392"
        ],
        "placetype": [
          "aat:300006075"
        ],
        "name:en": "Tir'at as Samānīyah",
        "id": 7544262
      }
    },
    {
      "geometry": {
        "type": "Point",
        "coordinates": [
          31.766667,
          31.423611
        ]
      },
      "type": "Feature",
      "properties": {
        "hierarchy": [
          "tgn:7544263",
          "tgn:7001242",
          "tgn:7016833",
          "tgn:1001225",
          "tgn:7029392"
        ],
        "placetype": [
          "aat:300000206"
        ],
        "name:en": "'Izbat an Najjārīn",
        "id": 7544263
      }
    },
    {
      "geometry": {
        "type": "Point",
        "coordinates": [
          31.8125,
          31.441667
        ]
      },
      "type": "Feature",
      "properties": {
        "hierarchy": [
          "tgn:7544264",
          "tgn:7001242",
          "tgn:7016833",
          "tgn:1001225",
          "tgn:7029392"
        ],
        "placetype": [
          "aat:300008347"
        ],
        "name:en": "Al Buşaylah",
        "id": 7544264
      }
    },
    {
      "geometry": {
        "type": "Point",
        "coordinates": [
          31.791667,
          31.441667
        ]
      },
      "type": "Feature",
      "properties": {
        "hierarchy": [
          "tgn:7544265",
          "tgn:7001242",
          "tgn:7016833",
          "tgn:1001225",
          "tgn:7029392"
        ],
        "placetype": [
          "aat:300008347"
        ],
        "name:en": "Sakan Muḩammad Ḑayf",
        "id": 7544265
      }
    },
    {
      "geometry": {
        "type": "Point",
        "coordinates": [
          31.829543,
          31.47607
        ]
      },
      "type": "Feature",
      "properties": {
        "hierarchy": [
          "tgn:7544266",
          "tgn:7001242",
          "tgn:1001059",
          "tgn:7016833",
          "tgn:7029392"
        ],
        "placetype": [
          "aat:300008713"
        ],
        "name:en": "Raţmah, Qanāl ar",
        "id": 7544266
      }
    },
    {
      "geometry": {
        "type": "Point",
        "coordinates": [
          31.81542,
          31.451599
        ]
      },
      "type": "Feature",
      "properties": {
        "hierarchy": [
          "tgn:7544267",
          "tgn:7001242",
          "tgn:1001059",
          "tgn:7016833",
          "tgn:7029392"
        ],
        "placetype": [
          "aat:300008347"
        ],
        "name:en": "'Izbat al Khayyāţah",
        "id": 7544267
      }
    },
    {
      "geometry": {
        "type": "Point",
        "coordinates": [
          31.813052,
          31.453729
        ]
      },
      "type": "Feature",
      "properties": {
        "hierarchy": [
          "tgn:7544268",
          "tgn:7001242",
          "tgn:1001059",
          "tgn:7016833",
          "tgn:7029392"
        ],
        "placetype": [
          "aat:300008347"
        ],
        "name:en": "'Izbat ash Sharāyid",
        "id": 7544268
      }
    },
    {
      "geometry": {
        "type": "Point",
        "coordinates": [
          31.808333,
          31.448611
        ]
      },
      "type": "Feature",
      "properties": {
        "hierarchy": [
          "tgn:7544269",
          "tgn:7001242",
          "tgn:7016833",
          "tgn:1001225",
          "tgn:7029392"
        ],
        "placetype": [
          "aat:300008347"
        ],
        "name:en": "'Izbat al 'Awwām",
        "id": 7544269
      }
    }
  ]
}
