{
  "geometry": {
    "type": "Point",
    "coordinates": [
      -74.2167,
      43.4833
    ]
  },
  "type": "Feature",
  "properties": {
    "hierarchy": [
      "tgn:2726305",
      "tgn:1000001",
      "tgn:7012149",
      "tgn:1002440",
      "tgn:7007568",
      "tgn:7029392"
    ],
    "placetype": [
      "aat:300008699"
    ],
    "id": 2726305,
    "name:xx": "Towers Brook"
  }
}
