{
  "geometry": {
    "type": "Point",
    "coordinates": [
      -81.75,
      28.5667
    ]
  },
  "type": "Feature",
  "properties": {
    "hierarchy": [
      "tgn:2311282",
      "tgn:1000001",
      "tgn:7012149",
      "tgn:1002567",
      "tgn:7007240",
      "tgn:7029392"
    ],
    "placetype": [
      "aat:300008680"
    ],
    "id": 2311282,
    "name:xx": "Edgewood Lake"
  }
}
