{
  "geometry": {
    "type": "Point",
    "coordinates": [
      -145.85,
      63.2667
    ]
  },
  "type": "Feature",
  "properties": {
    "hierarchy": [
      "tgn:2606215",
      "tgn:7006450",
      "tgn:1000001",
      "tgn:7012149",
      "tgn:2000085",
      "tgn:7029392"
    ],
    "placetype": [
      "aat:300008798"
    ],
    "id": 2606215,
    "name:xx": "Rainy Mountain"
  }
}
