{
  "geometry": {
    "type": "Point",
    "coordinates": [
      -91.2333,
      45.65
    ]
  },
  "type": "Feature",
  "properties": {
    "hierarchy": [
      "tgn:2146433",
      "tgn:1000001",
      "tgn:7012149",
      "tgn:2002353",
      "tgn:7007922",
      "tgn:7029392"
    ],
    "placetype": [
      "aat:300008680"
    ],
    "id": 2146433,
    "name:xx": "Balsam Lake"
  }
}
