{
  "geometry": {
    "type": "Point",
    "coordinates": [
      -86.1667,
      32.3667
    ]
  },
  "type": "Feature",
  "properties": {
    "hierarchy": [
      "tgn:2004472",
      "tgn:7002659",
      "tgn:1000001",
      "tgn:7012149",
      "tgn:2000050",
      "tgn:7029392"
    ],
    "placetype": [
      "aat:300387016"
    ],
    "id": 2004472,
    "name:xx": "Mitylene"
  }
}
