{
  "geometry": {
    "type": "Point",
    "coordinates": [
      -106.5333,
      38.0167
    ]
  },
  "type": "Feature",
  "properties": {
    "hierarchy": [
      "tgn:2379916",
      "tgn:1000001",
      "tgn:7012149",
      "tgn:7007158",
      "tgn:2000246",
      "tgn:7029392"
    ],
    "placetype": [
      "aat:300008706"
    ],
    "id": 2379916,
    "name:xx": "Hat Springs Creek"
  }
}
