{
  "geometry": {
    "type": "Point",
    "coordinates": [
      -121.0333,
      39.15
    ]
  },
  "type": "Feature",
  "properties": {
    "hierarchy": [
      "tgn:2334536",
      "tgn:1000001",
      "tgn:7012149",
      "tgn:7007157",
      "tgn:1002710",
      "tgn:7029392"
    ],
    "placetype": [
      "aat:300006075"
    ],
    "id": 2334536,
    "name:xx": "Forest Springs Lateral"
  }
}
