{
  "type": "FeatureCollection",
  "features": [
    {
      "geometry": {
        "type": "Point",
        "coordinates": [
          -77.35,
          41.2
        ]
      },
      "type": "Feature",
      "properties": {
        "hierarchy": [
          "tgn:2702740",
          "tgn:1000001",
          "tgn:1002286",
          "tgn:7012149",
          "tgn:7007710",
          "tgn:7029392"
        ],
        "placetype": [
          "aat:300008699"
        ],
        "id": 2702740,
        "name:xx": "Sulphur Run"
      }
    },
    {
      "geometry": {
        "type": "Point",
        "coordinates": [
          -80.5333,
          38.7167
        ]
      },
      "type": "Feature",
      "properties": {
        "hierarchy": [
          "tgn:2702741",
          "tgn:1000001",
          "tgn:2002256",
          "tgn:7012149",
          "tgn:7013961",
          "tgn:7029392"
        ],
        "placetype": [
          "aat:300008699"
        ],
        "id": 2702741,
        "name:xx": "Sulphur Run"
      }
    },
    {
      "geometry": {
        "type": "Point",
        "coordinates": [
          -86.4333,
          33.1
        ]
      },
      "type": "Feature",
      "properties": {
        "hierarchy": [
          "tgn:2702742",
          "tgn:7002659",
          "tgn:1000001",
          "tgn:7012149",
          "tgn:2000060",
          "tgn:7029392"
        ],
        "placetype": [
          "aat:300008347"
        ],
        "id": 2702742,
        "name:xx": "Sulphur Spring"
      }
    },
    {
      "geometry": {
        "type": "Point",
        "coordinates": [
          -86.7833,
          33.9167
        ]
      },
      "type": "Feature",
      "properties": {
        "hierarchy": [
          "tgn:2702743",
          "tgn:7002659",
          "tgn:1000001",
          "tgn:2000004",
          "tgn:7012149",
          "tgn:7029392"
        ],
        "placetype": [
          "aat:300008697"
        ],
        "id": 2702743,
        "name:xx": "Sulphur Spring"
      }
    },
    {
      "geometry": {
        "type": "Point",
        "coordinates": [
          -87.1833,
          34.5667
        ]
      },
      "type": "Feature",
      "properties": {
        "hierarchy": [
          "tgn:2702744",
          "tgn:7002659",
          "tgn:1000001",
          "tgn:7012149",
          "tgn:2000039",
          "tgn:7029392"
        ],
        "placetype": [
          "aat:300008697"
        ],
        "id": 2702744,
        "name:xx": "Sulphur Spring"
      }
    },
    {
      "geometry": {
        "type": "Point",
        "coordinates": [
          -109.1333,
          31.8333
        ]
      },
      "type": "Feature",
      "properties": {
        "hierarchy": [
          "tgn:2702745",
          "tgn:1000001",
          "tgn:7006451",
          "tgn:2000091",
          "tgn:7012149",
          "tgn:7029392"
        ],
        "placetype": [
          "aat:300008697"
        ],
        "id": 2702745,
        "name:xx": "Sulphur Spring"
      }
    },
    {
      "geometry": {
        "type": "Point",
        "coordinates": [
          -91.9,
          35.5
        ]
      },
      "type": "Feature",
      "properties": {
        "hierarchy": [
          "tgn:2702746",
          "tgn:1000001",
          "tgn:7016172",
          "tgn:2000116",
          "tgn:7012149",
          "tgn:7029392"
        ],
        "placetype": [
          "aat:300008697"
        ],
        "id": 2702746,
        "name:xx": "Sulphur Spring"
      }
    },
    {
      "geometry": {
        "type": "Point",
        "coordinates": [
          -93.0667,
          36.1
        ]
      },
      "type": "Feature",
      "properties": {
        "hierarchy": [
          "tgn:2702747",
          "tgn:1000001",
          "tgn:7016172",
          "tgn:7012149",
          "tgn:2000155",
          "tgn:7029392"
        ],
        "placetype": [
          "aat:300008697"
        ],
        "id": 2702747,
        "name:xx": "Sulphur Spring"
      }
    },
    {
      "geometry": {
        "type": "Point",
        "coordinates": [
          -92.0167,
          33.0667
        ]
      },
      "type": "Feature",
      "properties": {
        "hierarchy": [
          "tgn:2702748",
          "tgn:2000106",
          "tgn:1000001",
          "tgn:7016172",
          "tgn:7012149",
          "tgn:7029392"
        ],
        "placetype": [
          "aat:300008697"
        ],
        "id": 2702748,
        "name:xx": "Sulphur Spring"
      }
    },
    {
      "geometry": {
        "type": "Point",
        "coordinates": [
          -93.0667,
          36.1
        ]
      },
      "type": "Feature",
      "properties": {
        "hierarchy": [
          "tgn:2702749",
          "tgn:1000001",
          "tgn:7016172",
          "tgn:7012149",
          "tgn:2000155",
          "tgn:7029392"
        ],
        "placetype": [
          "aat:300008347"
        ],
        "id": 2702749,
        "name:xx": "Sulphur Spring"
      }
    }
  ]
}
