{
  "geometry": {
    "type": "Point",
    "coordinates": [
      79.45,
      15.983333
    ]
  },
  "type": "Feature",
  "properties": {
    "hierarchy": [
      "tgn:7578129",
      "tgn:1001828",
      "tgn:1000004",
      "tgn:7000198",
      "tgn:7029392"
    ],
    "placetype": [
      "aat:300008347"
    ],
    "name:en": "Tripurāntakam",
    "id": 7578129
  }
}
