{
  "geometry": {
    "type": "Point",
    "coordinates": [
      -85.7667,
      37.5333
    ]
  },
  "type": "Feature",
  "properties": {
    "hierarchy": [
      "tgn:2496355",
      "tgn:1000001",
      "tgn:7012149",
      "tgn:2000807",
      "tgn:7007255",
      "tgn:7029392"
    ],
    "placetype": [
      "aat:300008347"
    ],
    "id": 2496355,
    "name:xx": "Mathers Mill"
  }
}
