{
  "geometry": {
    "type": "Point",
    "coordinates": [
      -103.0667,
      47.8667
    ]
  },
  "type": "Feature",
  "properties": {
    "hierarchy": [
      "tgn:2721998",
      "tgn:1000001",
      "tgn:2001583",
      "tgn:7012149",
      "tgn:7007705",
      "tgn:7029392"
    ],
    "placetype": [
      "aat:300008706"
    ],
    "id": 2721998,
    "name:xx": "Timber Prong Creek"
  }
}
