{
  "type": "FeatureCollection",
  "features": [
    {
      "geometry": {
        "type": "Point",
        "coordinates": [
          -121.5333,
          47.4167
        ]
      },
      "type": "Feature",
      "properties": {
        "hierarchy": [
          "tgn:2605920",
          "tgn:1000001",
          "tgn:7012149",
          "tgn:7018871",
          "tgn:7007920",
          "tgn:7029392"
        ],
        "placetype": [
          "aat:300008680"
        ],
        "id": 2605920,
        "name:xx": "Rainbow Lake"
      }
    },
    {
      "geometry": {
        "type": "Point",
        "coordinates": [
          -120.7333,
          48.4
        ]
      },
      "type": "Feature",
      "properties": {
        "hierarchy": [
          "tgn:2605921",
          "tgn:1000001",
          "tgn:1002260",
          "tgn:7012149",
          "tgn:7007920",
          "tgn:7029392"
        ],
        "placetype": [
          "aat:300008680"
        ],
        "id": 2605921,
        "name:xx": "Rainbow Lake"
      }
    },
    {
      "geometry": {
        "type": "Point",
        "coordinates": [
          -119.3667,
          47.5833
        ]
      },
      "type": "Feature",
      "properties": {
        "hierarchy": [
          "tgn:2605922",
          "tgn:1000001",
          "tgn:7012149",
          "tgn:2002246",
          "tgn:7007920",
          "tgn:7029392"
        ],
        "placetype": [
          "aat:300008680"
        ],
        "id": 2605922,
        "name:xx": "Rainbow Lake"
      }
    },
    {
      "geometry": {
        "type": "Point",
        "coordinates": [
          -123.05,
          47.25
        ]
      },
      "type": "Feature",
      "properties": {
        "hierarchy": [
          "tgn:2605924",
          "tgn:1000001",
          "tgn:7012149",
          "tgn:1002645",
          "tgn:7007920",
          "tgn:7029392"
        ],
        "placetype": [
          "aat:300008680"
        ],
        "id": 2605924,
        "name:xx": "Rainbow Lake"
      }
    },
    {
      "geometry": {
        "type": "Point",
        "coordinates": [
          -89.15,
          44.3333
        ]
      },
      "type": "Feature",
      "properties": {
        "hierarchy": [
          "tgn:2605925",
          "tgn:1000001",
          "tgn:7012149",
          "tgn:2002361",
          "tgn:7007922",
          "tgn:7029392"
        ],
        "placetype": [
          "aat:300008680"
        ],
        "id": 2605925,
        "name:xx": "Rainbow Lake"
      }
    },
    {
      "geometry": {
        "type": "Point",
        "coordinates": [
          -91.8333,
          46.2167
        ]
      },
      "type": "Feature",
      "properties": {
        "hierarchy": [
          "tgn:2605926",
          "tgn:1000001",
          "tgn:2002318",
          "tgn:7012149",
          "tgn:7007922",
          "tgn:7029392"
        ],
        "placetype": [
          "aat:300008680"
        ],
        "id": 2605926,
        "name:xx": "Rainbow Lake"
      }
    },
    {
      "geometry": {
        "type": "Point",
        "coordinates": [
          -91.3,
          46.4167
        ]
      },
      "type": "Feature",
      "properties": {
        "hierarchy": [
          "tgn:2605927",
          "tgn:2002308",
          "tgn:1000001",
          "tgn:7012149",
          "tgn:7007922",
          "tgn:7029392"
        ],
        "placetype": [
          "aat:300008680"
        ],
        "id": 2605927,
        "name:xx": "Rainbow Lake"
      }
    },
    {
      "geometry": {
        "type": "Point",
        "coordinates": [
          -89.8333,
          46.2333
        ]
      },
      "type": "Feature",
      "properties": {
        "hierarchy": [
          "tgn:2605928",
          "tgn:1000001",
          "tgn:7012149",
          "tgn:2002359",
          "tgn:7007922",
          "tgn:7029392"
        ],
        "placetype": [
          "aat:300008680"
        ],
        "id": 2605928,
        "name:xx": "Rainbow Lake"
      }
    },
    {
      "geometry": {
        "type": "Point",
        "coordinates": [
          -109.3833,
          42.8833
        ]
      },
      "type": "Feature",
      "properties": {
        "hierarchy": [
          "tgn:2605929",
          "tgn:1000001",
          "tgn:7012149",
          "tgn:2002382",
          "tgn:7007923",
          "tgn:7029392"
        ],
        "placetype": [
          "aat:300008680"
        ],
        "id": 2605929,
        "name:xx": "Rainbow Lake"
      }
    }
  ]
}
