{
  "geometry": {
    "type": "Point",
    "coordinates": [
      -151.3833,
      60.2167
    ]
  },
  "type": "Feature",
  "properties": {
    "hierarchy": [
      "tgn:2005974",
      "tgn:7006450",
      "tgn:1000001",
      "tgn:7019698",
      "tgn:7012149",
      "tgn:7029392"
    ],
    "placetype": [
      "aat:300008347"
    ],
    "id": 2005974,
    "name:xx": "Clam Gulch"
  }
}
