{
  "geometry": {
    "type": "Point",
    "coordinates": [
      -98.9333,
      34.6833
    ]
  },
  "type": "Feature",
  "properties": {
    "hierarchy": [
      "tgn:2083636",
      "tgn:1000001",
      "tgn:7012149",
      "tgn:2001660",
      "tgn:7007707",
      "tgn:7029392"
    ],
    "placetype": [
      "aat:300008347"
    ],
    "id": 2083636,
    "name:xx": "Mountain Park"
  }
}
