{
  "geometry": {
    "type": "Point",
    "coordinates": [
      -83.7167,
      35.5167
    ]
  },
  "type": "Feature",
  "properties": {
    "hierarchy": [
      "tgn:2235000",
      "tgn:1000001",
      "tgn:7012149",
      "tgn:2001543",
      "tgn:7007709",
      "tgn:7029392"
    ],
    "placetype": [
      "aat:300008798"
    ],
    "id": 2235000,
    "name:xx": "Cherry Knob"
  }
}
