{
  "geometry": {
    "type": "Point",
    "coordinates": [
      -121.0333,
      48.4833
    ]
  },
  "type": "Feature",
  "properties": {
    "hierarchy": [
      "tgn:2188389",
      "tgn:1000001",
      "tgn:7012149",
      "tgn:7014510",
      "tgn:7007920",
      "tgn:7029392"
    ],
    "placetype": [
      "aat:300008798"
    ],
    "id": 2188389,
    "name:xx": "Boston Peak"
  }
}
