{
  "geometry": {
    "type": "Point",
    "coordinates": [
      13.5333,
      -10.4667
    ]
  },
  "type": "Feature",
  "properties": {
    "hierarchy": [
      "tgn:1011331",
      "tgn:7001242",
      "tgn:1000149",
      "tgn:1000835",
      "tgn:7029392"
    ],
    "placetype": [
      "aat:300008850"
    ],
    "id": 1011331,
    "name:xx": "Três Pontas, Cabo das"
  }
}
