{
  "geometry": {
    "type": "Point",
    "coordinates": [
      -106.65,
      47.75
    ]
  },
  "type": "Feature",
  "properties": {
    "hierarchy": [
      "tgn:2636439",
      "tgn:1000001",
      "tgn:7012149",
      "tgn:2001276",
      "tgn:7007524",
      "tgn:7029392"
    ],
    "placetype": [
      "aat:300386845"
    ],
    "id": 2636439,
    "name:xx": "Sag, The"
  }
}
