{
  "geometry": {
    "type": "Point",
    "coordinates": [
      -105.8833,
      40.4667
    ]
  },
  "type": "Feature",
  "properties": {
    "hierarchy": [
      "tgn:2673890",
      "tgn:1000001",
      "tgn:7012149",
      "tgn:2000220",
      "tgn:7007158",
      "tgn:7029392"
    ],
    "placetype": [
      "aat:300008680"
    ],
    "id": 2673890,
    "name:xx": "Snow Lake"
  }
}
