{
  "geometry": {
    "type": "Point",
    "coordinates": [
      18.75,
      -32.9167
    ]
  },
  "type": "Feature",
  "properties": {
    "hierarchy": [
      "tgn:1093508",
      "tgn:7001242",
      "tgn:7017584",
      "tgn:1000193",
      "tgn:7029392"
    ],
    "placetype": [
      "aat:300008347"
    ],
    "id": 1093508,
    "name:xx": "Piketberg"
  }
}
