{
  "geometry": {
    "type": "Point",
    "coordinates": [
      -81.4667,
      39.0667
    ]
  },
  "type": "Feature",
  "properties": {
    "hierarchy": [
      "tgn:2523901",
      "tgn:1000001",
      "tgn:7012149",
      "tgn:2002302",
      "tgn:7013961",
      "tgn:7029392"
    ],
    "placetype": [
      "aat:300266640"
    ],
    "id": 2523901,
    "name:xx": "Morehead Ridge"
  }
}
