{
  "geometry": {
    "type": "Point",
    "coordinates": [
      -76.0667,
      40.7333
    ]
  },
  "type": "Feature",
  "properties": {
    "hierarchy": [
      "tgn:2086736",
      "tgn:1000001",
      "tgn:7012149",
      "tgn:1002876",
      "tgn:7007710",
      "tgn:7029392"
    ],
    "placetype": [
      "aat:300008347"
    ],
    "id": 2086736,
    "name:xx": "Brockton"
  }
}
