{
  "geometry": {
    "type": "Point",
    "coordinates": [
      -94.6167,
      36.7333
    ]
  },
  "type": "Feature",
  "properties": {
    "hierarchy": [
      "tgn:2688035",
      "tgn:1000001",
      "tgn:7012149",
      "tgn:7007523",
      "tgn:7029392"
    ],
    "placetype": [
      "aat:300055621"
    ],
    "id": 2688035,
    "name:xx": "Springfield Plain"
  }
}
