{
  "geometry": {
    "type": "Point",
    "coordinates": [
      -80.5833,
      36.05
    ]
  },
  "type": "Feature",
  "properties": {
    "hierarchy": [
      "tgn:2237779",
      "tgn:1000001",
      "tgn:7012149",
      "tgn:7007709",
      "tgn:7029392"
    ],
    "placetype": [
      "aat:300008706"
    ],
    "id": 2237779,
    "name:xx": "Chinquapin Creek"
  }
}
