{
  "geometry": {
    "type": "Point",
    "coordinates": [
      -80.5333,
      38.6667
    ]
  },
  "type": "Feature",
  "properties": {
    "hierarchy": [
      "tgn:2118622",
      "tgn:1000001",
      "tgn:2002256",
      "tgn:7012149",
      "tgn:7013961",
      "tgn:7029392"
    ],
    "placetype": [
      "aat:300387016"
    ],
    "id": 2118622,
    "name:xx": "Holly"
  }
}
