{
  "geometry": {
    "type": "Point",
    "coordinates": [
      -93.1833,
      45.35
    ]
  },
  "type": "Feature",
  "properties": {
    "hierarchy": [
      "tgn:2525538",
      "tgn:2001000",
      "tgn:1000001",
      "tgn:7012149",
      "tgn:7007521",
      "tgn:7029392"
    ],
    "placetype": [
      "aat:300008347"
    ],
    "id": 2525538,
    "name:xx": "Mort"
  }
}
