{
  "geometry": {
    "type": "Point",
    "coordinates": [
      31.08888,
      30.786042
    ]
  },
  "type": "Feature",
  "properties": {
    "hierarchy": [
      "tgn:7521498",
      "tgn:7001242",
      "tgn:7016833",
      "tgn:7001312",
      "tgn:7029392"
    ],
    "placetype": [
      "aat:300008347"
    ],
    "name:en": "Al Anbūţayn",
    "id": 7521498
  }
}
