{
  "geometry": {
    "type": "Point",
    "coordinates": [
      -112.9167,
      34.2167
    ]
  },
  "type": "Feature",
  "properties": {
    "hierarchy": [
      "tgn:2276232",
      "tgn:1000001",
      "tgn:7006451",
      "tgn:7012149",
      "tgn:2000103",
      "tgn:7029392"
    ],
    "placetype": [
      "aat:300386831"
    ],
    "id": 2276232,
    "name:xx": "Date Creek Mountains"
  }
}
