{
  "geometry": {
    "type": "Point",
    "coordinates": [
      44.1167,
      51.8667
    ]
  },
  "type": "Feature",
  "properties": {
    "hierarchy": [
      "tgn:1055507",
      "tgn:1000004",
      "tgn:1003408",
      "tgn:7018214",
      "tgn:7002435",
      "tgn:7029392"
    ],
    "placetype": [
      "aat:300008347"
    ],
    "id": 1055507,
    "name:xx": "Koleno"
  }
}
