{
  "type": "FeatureCollection",
  "features": [
    {
      "geometry": {
        "type": "Point",
        "coordinates": [
          -79.8167,
          39.9333
        ]
      },
      "type": "Feature",
      "properties": {
        "hierarchy": [
          "tgn:2089240",
          "tgn:1000001",
          "tgn:7012149",
          "tgn:7014185",
          "tgn:7007710",
          "tgn:7029392"
        ],
        "placetype": [
          "aat:300008347"
        ],
        "id": 2089240,
        "name:xx": "Herbert"
      }
    },
    {
      "geometry": {
        "type": "Point",
        "coordinates": [
          -75.55,
          40.4333
        ]
      },
      "type": "Feature",
      "properties": {
        "hierarchy": [
          "tgn:2089241",
          "tgn:1000001",
          "tgn:7013387",
          "tgn:7012149",
          "tgn:7007710",
          "tgn:7029392"
        ],
        "placetype": [
          "aat:300008347"
        ],
        "id": 2089241,
        "name:xx": "Hereford"
      }
    },
    {
      "geometry": {
        "type": "Point",
        "coordinates": [
          -79.8,
          40.8167
        ]
      },
      "type": "Feature",
      "properties": {
        "hierarchy": [
          "tgn:2089243",
          "tgn:1000001",
          "tgn:1002217",
          "tgn:7012149",
          "tgn:7007710",
          "tgn:7029392"
        ],
        "placetype": [
          "aat:300008347"
        ],
        "id": 2089243,
        "name:xx": "Herman"
      }
    },
    {
      "geometry": {
        "type": "Point",
        "coordinates": [
          -79.7167,
          40.25
        ]
      },
      "type": "Feature",
      "properties": {
        "hierarchy": [
          "tgn:2089245",
          "tgn:1000001",
          "tgn:7012149",
          "tgn:1003017",
          "tgn:7007710",
          "tgn:7029392"
        ],
        "placetype": [
          "aat:300008347"
        ],
        "id": 2089245,
        "name:xx": "Herminie"
      }
    },
    {
      "geometry": {
        "type": "Point",
        "coordinates": [
          -80.4333,
          41.2333
        ]
      },
      "type": "Feature",
      "properties": {
        "hierarchy": [
          "tgn:2089246",
          "tgn:1000001",
          "tgn:7012149",
          "tgn:1002659",
          "tgn:7007710",
          "tgn:7029392"
        ],
        "placetype": [
          "aat:300008347"
        ],
        "id": 2089246,
        "name:xx": "Hermitage"
      }
    }
  ]
}
