{
  "geometry": {
    "type": "Point",
    "coordinates": [
      -96.15,
      39.65
    ]
  },
  "type": "Feature",
  "properties": {
    "hierarchy": [
      "tgn:2340261",
      "tgn:1000001",
      "tgn:7012149",
      "tgn:7007254",
      "tgn:7029392"
    ],
    "placetype": [
      "aat:300008706"
    ],
    "id": 2340261,
    "name:xx": "French Creek"
  }
}
