{
  "geometry": {
    "type": "Point",
    "coordinates": [
      -83.0167,
      35.8333
    ]
  },
  "type": "Feature",
  "properties": {
    "hierarchy": [
      "tgn:2408154",
      "tgn:1000001",
      "tgn:7012149",
      "tgn:2001851",
      "tgn:7007825",
      "tgn:7029392"
    ],
    "placetype": [
      "aat:300266640"
    ],
    "id": 2408154,
    "name:xx": "Hurricane Ridge"
  }
}
