{
  "type": "FeatureCollection",
  "features": [
    {
      "geometry": {
        "type": "Point",
        "coordinates": [
          -80.4833,
          39.7667
        ]
      },
      "type": "Feature",
      "properties": {
        "hierarchy": [
          "tgn:2254740",
          "tgn:1000001",
          "tgn:7012149",
          "tgn:2001724",
          "tgn:7007710",
          "tgn:7029392"
        ],
        "placetype": [
          "aat:300008699"
        ],
        "id": 2254740,
        "name:xx": "Coon Run"
      }
    },
    {
      "geometry": {
        "type": "Point",
        "coordinates": [
          -78.85,
          41.5833
        ]
      },
      "type": "Feature",
      "properties": {
        "hierarchy": [
          "tgn:2254741",
          "tgn:1000001",
          "tgn:7012149",
          "tgn:1002352",
          "tgn:7007710",
          "tgn:7029392"
        ],
        "placetype": [
          "aat:300008699"
        ],
        "id": 2254741,
        "name:xx": "Coon Run"
      }
    },
    {
      "geometry": {
        "type": "Point",
        "coordinates": [
          -78.8667,
          41.8333
        ]
      },
      "type": "Feature",
      "properties": {
        "hierarchy": [
          "tgn:2254742",
          "tgn:1000001",
          "tgn:7012149",
          "tgn:7016020",
          "tgn:7007710",
          "tgn:7029392"
        ],
        "placetype": [
          "aat:300008699"
        ],
        "id": 2254742,
        "name:xx": "Coon Run"
      }
    },
    {
      "geometry": {
        "type": "Point",
        "coordinates": [
          -80.4333,
          38.1833
        ]
      },
      "type": "Feature",
      "properties": {
        "hierarchy": [
          "tgn:2254743",
          "tgn:1000001",
          "tgn:7012149",
          "tgn:2002264",
          "tgn:7013961",
          "tgn:7029392"
        ],
        "placetype": [
          "aat:300008699"
        ],
        "id": 2254743,
        "name:xx": "Coon Run"
      }
    },
    {
      "geometry": {
        "type": "Point",
        "coordinates": [
          -81.5,
          38.6833
        ]
      },
      "type": "Feature",
      "properties": {
        "hierarchy": [
          "tgn:2254744",
          "tgn:1000001",
          "tgn:7012149",
          "tgn:2002293",
          "tgn:7013961",
          "tgn:7029392"
        ],
        "placetype": [
          "aat:300008699"
        ],
        "id": 2254744,
        "name:xx": "Coon Run"
      }
    },
    {
      "geometry": {
        "type": "Point",
        "coordinates": [
          -80.9833,
          38.6833
        ]
      },
      "type": "Feature",
      "properties": {
        "hierarchy": [
          "tgn:2254745",
          "tgn:1000001",
          "tgn:2002256",
          "tgn:7012149",
          "tgn:7013961",
          "tgn:7029392"
        ],
        "placetype": [
          "aat:300008699"
        ],
        "id": 2254745,
        "name:xx": "Coon Run"
      }
    },
    {
      "geometry": {
        "type": "Point",
        "coordinates": [
          -81.55,
          38.8833
        ]
      },
      "type": "Feature",
      "properties": {
        "hierarchy": [
          "tgn:2254746",
          "tgn:1000001",
          "tgn:7012149",
          "tgn:2002268",
          "tgn:7013961",
          "tgn:7029392"
        ],
        "placetype": [
          "aat:300008699"
        ],
        "id": 2254746,
        "name:xx": "Coon Run"
      }
    },
    {
      "geometry": {
        "type": "Point",
        "coordinates": [
          -80.7833,
          39.7333
        ]
      },
      "type": "Feature",
      "properties": {
        "hierarchy": [
          "tgn:2254747",
          "tgn:1000001",
          "tgn:7012149",
          "tgn:2002276",
          "tgn:7013961",
          "tgn:7029392"
        ],
        "placetype": [
          "aat:300008699"
        ],
        "id": 2254747,
        "name:xx": "Coon Run"
      }
    },
    {
      "geometry": {
        "type": "Point",
        "coordinates": [
          -111.0167,
          33.4167
        ]
      },
      "type": "Feature",
      "properties": {
        "hierarchy": [
          "tgn:2254748",
          "tgn:1000001",
          "tgn:7006451",
          "tgn:2000093",
          "tgn:7012149",
          "tgn:7029392"
        ],
        "placetype": [
          "aat:300008697"
        ],
        "id": 2254748,
        "name:xx": "Coon Spring"
      }
    },
    {
      "geometry": {
        "type": "Point",
        "coordinates": [
          -109.3667,
          34.05
        ]
      },
      "type": "Feature",
      "properties": {
        "hierarchy": [
          "tgn:2254749",
          "tgn:2000090",
          "tgn:1000001",
          "tgn:7006451",
          "tgn:7012149",
          "tgn:7029392"
        ],
        "placetype": [
          "aat:300008697"
        ],
        "id": 2254749,
        "name:xx": "Coon Spring"
      }
    }
  ]
}
