{
  "geometry": {
    "type": "Point",
    "coordinates": [
      -75.25,
      40.2333
    ]
  },
  "type": "Feature",
  "properties": {
    "hierarchy": [
      "tgn:1135100",
      "tgn:1000001",
      "tgn:7012149",
      "tgn:7007710",
      "tgn:7029392"
    ],
    "placetype": [
      "aat:300008706"
    ],
    "id": 1135100,
    "name:xx": "Wissahickon Creek"
  }
}
