{
  "type": "FeatureCollection",
  "features": [
    {
      "geometry": {
        "type": "Point",
        "coordinates": [
          -121.3833,
          42.4333
        ]
      },
      "type": "Feature",
      "properties": {
        "hierarchy": [
          "tgn:2528612",
          "tgn:1000001",
          "tgn:7012149",
          "tgn:2001714",
          "tgn:7007708",
          "tgn:7029392"
        ],
        "placetype": [
          "aat:300008680"
        ],
        "id": 2528612,
        "name:xx": "Muckney Lake"
      }
    },
    {
      "geometry": {
        "type": "Point",
        "coordinates": [
          -74.7667,
          41.0167
        ]
      },
      "type": "Feature",
      "properties": {
        "hierarchy": [
          "tgn:2528613",
          "tgn:1000001",
          "tgn:1002934",
          "tgn:7012149",
          "tgn:7007565",
          "tgn:7029392"
        ],
        "placetype": [
          "aat:300008680"
        ],
        "id": 2528613,
        "name:xx": "Muckshaw Ponds"
      }
    },
    {
      "geometry": {
        "type": "Point",
        "coordinates": [
          -82.45,
          40.3
        ]
      },
      "type": "Feature",
      "properties": {
        "hierarchy": [
          "tgn:2528614",
          "tgn:1000001",
          "tgn:7012149",
          "tgn:1002556",
          "tgn:7007706",
          "tgn:7029392"
        ],
        "placetype": [
          "aat:300008699"
        ],
        "id": 2528614,
        "name:xx": "Muckshaw Run"
      }
    },
    {
      "geometry": {
        "type": "Point",
        "coordinates": [
          -86,
          44.0833
        ]
      },
      "type": "Feature",
      "properties": {
        "hierarchy": [
          "tgn:2528615",
          "tgn:1000001",
          "tgn:7012149",
          "tgn:7007520",
          "tgn:7029392"
        ],
        "placetype": [
          "aat:300008706"
        ],
        "id": 2528615,
        "name:xx": "Muckwa Creek"
      }
    },
    {
      "geometry": {
        "type": "Point",
        "coordinates": [
          -91.9833,
          47.7833
        ]
      },
      "type": "Feature",
      "properties": {
        "hierarchy": [
          "tgn:2528616",
          "tgn:1000001",
          "tgn:7012149",
          "tgn:2001067",
          "tgn:7007521",
          "tgn:7029392"
        ],
        "placetype": [
          "aat:300008680"
        ],
        "id": 2528616,
        "name:xx": "Muckwa Lake"
      }
    },
    {
      "geometry": {
        "type": "Point",
        "coordinates": [
          -90.3167,
          47.9167
        ]
      },
      "type": "Feature",
      "properties": {
        "hierarchy": [
          "tgn:2528617",
          "tgn:1000001",
          "tgn:2001014",
          "tgn:7012149",
          "tgn:7007521",
          "tgn:7029392"
        ],
        "placetype": [
          "aat:300008680"
        ],
        "id": 2528617,
        "name:xx": "Muckwa Lake"
      }
    },
    {
      "geometry": {
        "type": "Point",
        "coordinates": [
          -94.8,
          46.8667
        ]
      },
      "type": "Feature",
      "properties": {
        "hierarchy": [
          "tgn:2528618",
          "tgn:1000001",
          "tgn:7012149",
          "tgn:2001027",
          "tgn:7007521",
          "tgn:7029392"
        ],
        "placetype": [
          "aat:300008706"
        ],
        "id": 2528618,
        "name:xx": "Mucky Creek"
      }
    },
    {
      "geometry": {
        "type": "Point",
        "coordinates": [
          -97.6167,
          28.6
        ]
      },
      "type": "Feature",
      "properties": {
        "hierarchy": [
          "tgn:2528619",
          "tgn:1000001",
          "tgn:7012149",
          "tgn:1002413",
          "tgn:7007826",
          "tgn:7029392"
        ],
        "placetype": [
          "aat:300008706"
        ],
        "id": 2528619,
        "name:xx": "Mucorrera Creek"
      }
    }
  ]
}
