{
  "type": "FeatureCollection",
  "features": [
    {
      "geometry": {
        "type": "Point",
        "coordinates": [
          8.6,
          47.616667
        ]
      },
      "type": "Feature",
      "properties": {
        "hierarchy": [
          "tgn:7176860",
          "tgn:7003692",
          "tgn:1000003",
          "tgn:7000084",
          "tgn:7029392"
        ],
        "placetype": [
          "aat:300008863"
        ],
        "id": 7176860,
        "name:xx": "Hardt"
      }
    },
    {
      "geometry": {
        "type": "Point",
        "coordinates": [
          7.65,
          51.383333
        ]
      },
      "type": "Feature",
      "properties": {
        "hierarchy": [
          "tgn:7176861",
          "tgn:1000003",
          "tgn:7003677",
          "tgn:7000084",
          "tgn:7029392"
        ],
        "placetype": [
          "aat:300000206"
        ],
        "id": 7176861,
        "name:xx": "Hardt"
      }
    },
    {
      "geometry": {
        "type": "Point",
        "coordinates": [
          6.6,
          51.25
        ]
      },
      "type": "Feature",
      "properties": {
        "hierarchy": [
          "tgn:7176862",
          "tgn:1000003",
          "tgn:7003677",
          "tgn:7000084",
          "tgn:7029392"
        ],
        "placetype": [
          "aat:300008347"
        ],
        "id": 7176862,
        "name:xx": "Hardt"
      }
    },
    {
      "geometry": {
        "type": "Point",
        "coordinates": [
          7.35,
          50.85
        ]
      },
      "type": "Feature",
      "properties": {
        "hierarchy": [
          "tgn:7176863",
          "tgn:1000003",
          "tgn:7003677",
          "tgn:7000084",
          "tgn:7029392"
        ],
        "placetype": [
          "aat:300000206"
        ],
        "id": 7176863,
        "name:xx": "Hardt"
      }
    },
    {
      "geometry": {
        "type": "Point",
        "coordinates": [
          7.5,
          50.65
        ]
      },
      "type": "Feature",
      "properties": {
        "hierarchy": [
          "tgn:7176864",
          "tgn:1000003",
          "tgn:7003682",
          "tgn:7000084",
          "tgn:7029392"
        ],
        "placetype": [
          "aat:300000206"
        ],
        "id": 7176864,
        "name:xx": "Hardt"
      }
    },
    {
      "geometry": {
        "type": "Point",
        "coordinates": [
          6.6,
          50.166667
        ]
      },
      "type": "Feature",
      "properties": {
        "hierarchy": [
          "tgn:7176865",
          "tgn:1000003",
          "tgn:7003682",
          "tgn:7000084",
          "tgn:7029392"
        ],
        "placetype": [
          "aat:300000206"
        ],
        "id": 7176865,
        "name:xx": "Hardt"
      }
    },
    {
      "geometry": {
        "type": "Point",
        "coordinates": [
          12.416667,
          49.166667
        ]
      },
      "type": "Feature",
      "properties": {
        "hierarchy": [
          "tgn:7176866",
          "tgn:7003669",
          "tgn:1000003",
          "tgn:7000084",
          "tgn:7029392"
        ],
        "placetype": [
          "aat:300000206"
        ],
        "id": 7176866,
        "name:xx": "Hardt"
      }
    },
    {
      "geometry": {
        "type": "Point",
        "coordinates": [
          12.366667,
          48.866667
        ]
      },
      "type": "Feature",
      "properties": {
        "hierarchy": [
          "tgn:7176867",
          "tgn:7003669",
          "tgn:1000003",
          "tgn:7000084",
          "tgn:7029392"
        ],
        "placetype": [
          "aat:300000206"
        ],
        "id": 7176867,
        "name:xx": "Keller"
      }
    },
    {
      "geometry": {
        "type": "Point",
        "coordinates": [
          12.516667,
          48.8
        ]
      },
      "type": "Feature",
      "properties": {
        "hierarchy": [
          "tgn:7176868",
          "tgn:7003669",
          "tgn:1000003",
          "tgn:7000084",
          "tgn:7029392"
        ],
        "placetype": [
          "aat:300000206"
        ],
        "id": 7176868,
        "name:xx": "Hardt"
      }
    },
    {
      "geometry": {
        "type": "Point",
        "coordinates": [
          13.116667,
          48.716667
        ]
      },
      "type": "Feature",
      "properties": {
        "hierarchy": [
          "tgn:7176869",
          "tgn:7003669",
          "tgn:1000003",
          "tgn:7000084",
          "tgn:7029392"
        ],
        "placetype": [
          "aat:300000206"
        ],
        "id": 7176869,
        "name:xx": "Hardt"
      }
    }
  ]
}
