{
  "geometry": {
    "type": "Point",
    "coordinates": [
      -86.15,
      42.7667
    ]
  },
  "type": "Feature",
  "properties": {
    "hierarchy": [
      "tgn:2477872",
      "tgn:1000001",
      "tgn:7012149",
      "tgn:1002760",
      "tgn:7007520",
      "tgn:7029392"
    ],
    "placetype": [
      "aat:300008680"
    ],
    "id": 2477872,
    "name:xx": "Macatawa, Lake"
  }
}
