{
  "geometry": {
    "type": "Point",
    "coordinates": [
      -113.8667,
      37.5333
    ]
  },
  "type": "Feature",
  "properties": {
    "hierarchy": [
      "tgn:2394221",
      "tgn:1000001",
      "tgn:7012149",
      "tgn:2002127",
      "tgn:7007827",
      "tgn:7029392"
    ],
    "placetype": [
      "aat:300266640"
    ],
    "id": 2394221,
    "name:xx": "Hogback"
  }
}
