{
  "geometry": {
    "type": "Point",
    "coordinates": [
      8.25,
      53.15
    ]
  },
  "type": "Feature",
  "properties": {
    "hierarchy": [
      "tgn:7088747",
      "tgn:1000003",
      "tgn:7003676",
      "tgn:7000084",
      "tgn:7029392"
    ],
    "placetype": [
      "aat:300008347"
    ],
    "id": 7088747,
    "name:xx": "Waterende"
  }
}
