{
  "geometry": {
    "type": "Point",
    "coordinates": [
      -81.3833,
      33.8833
    ]
  },
  "type": "Feature",
  "properties": {
    "hierarchy": [
      "tgn:2561735",
      "tgn:1000001",
      "tgn:7012149",
      "tgn:2001756",
      "tgn:7007712",
      "tgn:7029392"
    ],
    "placetype": [
      "aat:300006191"
    ],
    "id": 2561735,
    "name:xx": "Oswalds Pond"
  }
}
