{
  "geometry": {
    "type": "Point",
    "coordinates": [
      70.8333,
      40.75
    ]
  },
  "type": "Feature",
  "properties": {
    "hierarchy": [
      "tgn:1058755",
      "tgn:7011683",
      "tgn:1000004",
      "tgn:7006661",
      "tgn:7029392"
    ],
    "placetype": [
      "aat:300008347"
    ],
    "id": 1058755,
    "name:xx": "Pungan"
  }
}
