{
  "geometry": {
    "type": "Point",
    "coordinates": [
      -67.2167,
      44.7667
    ]
  },
  "type": "Feature",
  "properties": {
    "hierarchy": [
      "tgn:2319297",
      "tgn:1000001",
      "tgn:7012149",
      "tgn:7014589",
      "tgn:7007515",
      "tgn:7029392"
    ],
    "placetype": [
      "aat:300008798"
    ],
    "id": 2319297,
    "name:xx": "Estey Mountain"
  }
}
