{
  "geometry": {
    "type": "Point",
    "coordinates": [
      -164.4833,
      66.2833
    ]
  },
  "type": "Feature",
  "properties": {
    "hierarchy": [
      "tgn:2442142",
      "tgn:7006450",
      "tgn:1000001",
      "tgn:7012149",
      "tgn:7029392"
    ],
    "placetype": [
      "aat:300008706"
    ],
    "id": 2442142,
    "name:xx": "Kougachuk Creek"
  }
}
