{
  "geometry": {
    "type": "Point",
    "coordinates": [
      -88.1833,
      46.5333
    ]
  },
  "type": "Feature",
  "properties": {
    "hierarchy": [
      "tgn:2156901",
      "tgn:2000947",
      "tgn:1000001",
      "tgn:7012149",
      "tgn:7007520",
      "tgn:7029392"
    ],
    "placetype": [
      "aat:300008680"
    ],
    "id": 2156901,
    "name:xx": "Beaufort Lake"
  }
}
