{
  "geometry": {
    "type": "Point",
    "coordinates": [
      -90.05,
      35.6667
    ]
  },
  "type": "Feature",
  "properties": {
    "hierarchy": [
      "tgn:2740888",
      "tgn:1000001",
      "tgn:7016172",
      "tgn:7012149",
      "tgn:2000151",
      "tgn:7029392"
    ],
    "placetype": [
      "aat:300008699"
    ],
    "id": 2740888,
    "name:xx": "Upper Sandy Bayou"
  }
}
