{
  "geometry": {
    "type": "Point",
    "coordinates": [
      -132.6167,
      56.5667
    ]
  },
  "type": "Feature",
  "properties": {
    "hierarchy": [
      "tgn:2639773",
      "tgn:7006450",
      "tgn:1000001",
      "tgn:7012149",
      "tgn:2000088",
      "tgn:7029392"
    ],
    "placetype": [
      "aat:300008798"
    ],
    "id": 2639773,
    "name:xx": "Sam Peak"
  }
}
