{
  "geometry": {
    "type": "Point",
    "coordinates": [
      22.8833,
      -29.0333
    ]
  },
  "type": "Feature",
  "properties": {
    "hierarchy": [
      "tgn:1093651",
      "tgn:7001242",
      "tgn:7017582",
      "tgn:1000193",
      "tgn:7029392"
    ],
    "placetype": [
      "aat:300008347"
    ],
    "id": 1093651,
    "name:xx": "Springfield"
  }
}
