{
  "geometry": {
    "type": "Point",
    "coordinates": [
      -93.5167,
      44.25
    ]
  },
  "type": "Feature",
  "properties": {
    "hierarchy": [
      "tgn:2401746",
      "tgn:1000001",
      "tgn:7012149",
      "tgn:2001038",
      "tgn:7007521",
      "tgn:7029392"
    ],
    "placetype": [
      "aat:300008680"
    ],
    "id": 2401746,
    "name:xx": "Horseshoe Lake"
  }
}
