{
  "geometry": {
    "type": "Point",
    "coordinates": [
      -76.7667,
      38.1667
    ]
  },
  "type": "Feature",
  "properties": {
    "hierarchy": [
      "tgn:2380443",
      "tgn:1000001",
      "tgn:7012149",
      "tgn:7029392"
    ],
    "placetype": [
      "aat:300132316"
    ],
    "id": 2380443,
    "name:xx": "Haulover Inlet"
  }
}
