{
  "geometry": {
    "type": "Point",
    "coordinates": [
      -80.9833,
      32.05
    ]
  },
  "type": "Feature",
  "properties": {
    "hierarchy": [
      "tgn:2528807",
      "tgn:1000001",
      "tgn:2000316",
      "tgn:7012149",
      "tgn:7007248",
      "tgn:7029392"
    ],
    "placetype": [
      "aat:300008706"
    ],
    "id": 2528807,
    "name:xx": "Mud Creek"
  }
}
