{
  "geometry": {
    "type": "Point",
    "coordinates": [
      -95.35,
      32.7167
    ]
  },
  "type": "Feature",
  "properties": {
    "hierarchy": [
      "tgn:2104647",
      "tgn:1000001",
      "tgn:7012149",
      "tgn:1003034",
      "tgn:7007826",
      "tgn:7029392"
    ],
    "placetype": [
      "aat:300008347"
    ],
    "id": 2104647,
    "name:xx": "Hainesville"
  }
}
