{
  "geometry": {
    "type": "Point",
    "coordinates": [
      -118.05,
      48.3667
    ]
  },
  "type": "Feature",
  "properties": {
    "hierarchy": [
      "tgn:2478931",
      "tgn:1000001",
      "tgn:7012149",
      "tgn:2002250",
      "tgn:7007920",
      "tgn:7029392"
    ],
    "placetype": [
      "aat:300008706"
    ],
    "id": 2478931,
    "name:xx": "Magee Creek"
  }
}
