{
  "geometry": {
    "type": "Point",
    "coordinates": [
      -109.4333,
      44.7833
    ]
  },
  "type": "Feature",
  "properties": {
    "hierarchy": [
      "tgn:2134893",
      "tgn:1000001",
      "tgn:7012149",
      "tgn:2002379",
      "tgn:7007923",
      "tgn:7029392"
    ],
    "placetype": [
      "aat:300008798"
    ],
    "id": 2134893,
    "name:xx": "Antelope Mountain"
  }
}
