{
  "geometry": {
    "type": "Point",
    "coordinates": [
      -86.8167,
      32.8833
    ]
  },
  "type": "Feature",
  "properties": {
    "hierarchy": [
      "tgn:2524136",
      "tgn:7002659",
      "tgn:1000001",
      "tgn:2000010",
      "tgn:7012149",
      "tgn:7029392"
    ],
    "placetype": [
      "aat:300008706"
    ],
    "id": 2524136,
    "name:xx": "Morgan Creek"
  }
}
