{
  "geometry": {
    "type": "Point",
    "coordinates": [
      -105.8667,
      40.55
    ]
  },
  "type": "Feature",
  "properties": {
    "hierarchy": [
      "tgn:2423112",
      "tgn:1000001",
      "tgn:7012149",
      "tgn:2000226",
      "tgn:7007158",
      "tgn:7029392"
    ],
    "placetype": [
      "aat:300006191"
    ],
    "id": 2423112,
    "name:xx": "Joe Wright Reservoir"
  }
}
