{
  "geometry": {
    "type": "Point",
    "coordinates": [
      -90.6833,
      32.3333
    ]
  },
  "type": "Feature",
  "properties": {
    "hierarchy": [
      "tgn:2181037",
      "tgn:1000001",
      "tgn:7012149",
      "tgn:2001110",
      "tgn:7007522",
      "tgn:7029392"
    ],
    "placetype": [
      "aat:300008699"
    ],
    "id": 2181037,
    "name:xx": "Blue Bayou"
  }
}
