{
  "geometry": {
    "type": "Point",
    "coordinates": [
      -99.35,
      25.95
    ]
  },
  "type": "Feature",
  "properties": {
    "hierarchy": [
      "tgn:7389475",
      "tgn:1000001",
      "tgn:7005589",
      "tgn:7005560",
      "tgn:7029392"
    ],
    "placetype": [
      "aat:300266554",
      "aat:300008699"
    ],
    "id": 7389475,
    "name:xx": "Salado, Arroyo"
  }
}
