{
  "type": "FeatureCollection",
  "features": [
    {
      "geometry": {
        "type": "Point",
        "coordinates": [
          -94.2833,
          45.0833
        ]
      },
      "type": "Feature",
      "properties": {
        "hierarchy": [
          "tgn:2687330",
          "tgn:1000001",
          "tgn:7012149",
          "tgn:2001045",
          "tgn:7007521",
          "tgn:7029392"
        ],
        "placetype": [
          "aat:300008680"
        ],
        "id": 2687330,
        "name:xx": "Spring Lake"
      }
    },
    {
      "geometry": {
        "type": "Point",
        "coordinates": [
          -93.2167,
          45.1
        ]
      },
      "type": "Feature",
      "properties": {
        "hierarchy": [
          "tgn:2687331",
          "tgn:1000001",
          "tgn:7012149",
          "tgn:7007521",
          "tgn:7029392"
        ],
        "placetype": [
          "aat:300008680"
        ],
        "id": 2687331,
        "name:xx": "Spring Lake"
      }
    },
    {
      "geometry": {
        "type": "Point",
        "coordinates": [
          -96.05,
          45.2333
        ]
      },
      "type": "Feature",
      "properties": {
        "hierarchy": [
          "tgn:2687332",
          "tgn:1000001",
          "tgn:7012149",
          "tgn:2001074",
          "tgn:7007521",
          "tgn:7029392"
        ],
        "placetype": [
          "aat:300008680"
        ],
        "id": 2687332,
        "name:xx": "Spring Lake"
      }
    },
    {
      "geometry": {
        "type": "Point",
        "coordinates": [
          -93.05,
          45.5333
        ]
      },
      "type": "Feature",
      "properties": {
        "hierarchy": [
          "tgn:2687333",
          "tgn:1000001",
          "tgn:7012149",
          "tgn:2001028",
          "tgn:7007521",
          "tgn:7029392"
        ],
        "placetype": [
          "aat:300008680"
        ],
        "id": 2687333,
        "name:xx": "Spring Lake"
      }
    },
    {
      "geometry": {
        "type": "Point",
        "coordinates": [
          -93.2667,
          45.8833
        ]
      },
      "type": "Feature",
      "properties": {
        "hierarchy": [
          "tgn:2687334",
          "tgn:1000001",
          "tgn:7012149",
          "tgn:2001031",
          "tgn:7007521",
          "tgn:7029392"
        ],
        "placetype": [
          "aat:300008680"
        ],
        "id": 2687334,
        "name:xx": "Spring Lake"
      }
    },
    {
      "geometry": {
        "type": "Point",
        "coordinates": [
          -95.4333,
          46.05
        ]
      },
      "type": "Feature",
      "properties": {
        "hierarchy": [
          "tgn:2687335",
          "tgn:1000001",
          "tgn:2001019",
          "tgn:7012149",
          "tgn:7007521",
          "tgn:7029392"
        ],
        "placetype": [
          "aat:300008680"
        ],
        "id": 2687335,
        "name:xx": "Spring Lake"
      }
    },
    {
      "geometry": {
        "type": "Point",
        "coordinates": [
          -93.8333,
          46.1667
        ]
      },
      "type": "Feature",
      "properties": {
        "hierarchy": [
          "tgn:2687336",
          "tgn:1000001",
          "tgn:2001016",
          "tgn:7012149",
          "tgn:7007521",
          "tgn:7029392"
        ],
        "placetype": [
          "aat:300008680"
        ],
        "id": 2687336,
        "name:xx": "Spring Lake"
      }
    },
    {
      "geometry": {
        "type": "Point",
        "coordinates": [
          -95.9667,
          46.2833
        ]
      },
      "type": "Feature",
      "properties": {
        "hierarchy": [
          "tgn:2687337",
          "tgn:1000001",
          "tgn:7012149",
          "tgn:2001054",
          "tgn:7007521",
          "tgn:7029392"
        ],
        "placetype": [
          "aat:300008680"
        ],
        "id": 2687337,
        "name:xx": "Spring Lake"
      }
    },
    {
      "geometry": {
        "type": "Point",
        "coordinates": [
          -92.7333,
          46.45
        ]
      },
      "type": "Feature",
      "properties": {
        "hierarchy": [
          "tgn:2687338",
          "tgn:1000001",
          "tgn:2001007",
          "tgn:7012149",
          "tgn:7007521",
          "tgn:7029392"
        ],
        "placetype": [
          "aat:300008680"
        ],
        "id": 2687338,
        "name:xx": "Spring Lake"
      }
    },
    {
      "geometry": {
        "type": "Point",
        "coordinates": [
          -93.5167,
          46.4667
        ]
      },
      "type": "Feature",
      "properties": {
        "hierarchy": [
          "tgn:2687339",
          "tgn:2000999",
          "tgn:1000001",
          "tgn:7012149",
          "tgn:7007521",
          "tgn:7029392"
        ],
        "placetype": [
          "aat:300008680"
        ],
        "id": 2687339,
        "name:xx": "Spring Lake"
      }
    }
  ]
}
