{
  "geometry": {
    "type": "Point",
    "coordinates": [
      -83.1167,
      37.3667
    ]
  },
  "type": "Feature",
  "properties": {
    "hierarchy": [
      "tgn:2246322",
      "tgn:1000001",
      "tgn:7012149",
      "tgn:2000836",
      "tgn:7007255",
      "tgn:7029392"
    ],
    "placetype": [
      "aat:300008699"
    ],
    "id": 2246322,
    "name:xx": "Coates Branch"
  }
}
