{
  "geometry": {
    "type": "Point",
    "coordinates": [
      -81.6833,
      36.45
    ]
  },
  "type": "Feature",
  "properties": {
    "hierarchy": [
      "tgn:2568635",
      "tgn:2001467",
      "tgn:1000001",
      "tgn:7012149",
      "tgn:7007709",
      "tgn:7029392"
    ],
    "placetype": [
      "aat:300008347"
    ],
    "id": 2568635,
    "name:xx": "Parker"
  }
}
