{
  "geometry": {
    "type": "Point",
    "coordinates": [
      -95.1167,
      36.1333
    ]
  },
  "type": "Feature",
  "properties": {
    "hierarchy": [
      "tgn:2146270",
      "tgn:1000001",
      "tgn:7012149",
      "tgn:2001671",
      "tgn:7007707",
      "tgn:7029392"
    ],
    "placetype": [
      "aat:300008699"
    ],
    "id": 2146270,
    "name:xx": "Ballou Branch"
  }
}
