{
  "type": "FeatureCollection",
  "features": [
    {
      "geometry": {
        "type": "Point",
        "coordinates": [
          30.783333,
          30.633333
        ]
      },
      "type": "Feature",
      "properties": {
        "hierarchy": [
          "tgn:7524301",
          "tgn:7001242",
          "tgn:1001075",
          "tgn:7016833",
          "tgn:7029392"
        ],
        "placetype": [
          "aat:300007783"
        ],
        "name:en": "Maḩaţţat aţ Ţayrīyah",
        "id": 7524301
      }
    },
    {
      "geometry": {
        "type": "Point",
        "coordinates": [
          31.424126,
          31.119956
        ]
      },
      "type": "Feature",
      "properties": {
        "hierarchy": [
          "tgn:7524303",
          "tgn:7001242",
          "tgn:1001059",
          "tgn:7016833",
          "tgn:7029392"
        ],
        "placetype": [
          "aat:300008347"
        ],
        "name:en": "Aţ Ţawīlah",
        "id": 7524303
      }
    },
    {
      "geometry": {
        "type": "Point",
        "coordinates": [
          31.735596,
          30.654196
        ]
      },
      "type": "Feature",
      "properties": {
        "hierarchy": [
          "tgn:7524304",
          "tgn:7001242",
          "tgn:7016833",
          "tgn:1001113",
          "tgn:7029392"
        ],
        "placetype": [
          "aat:300008347"
        ],
        "id": 7524304,
        "name:xx": "Aţ Ţawīlah"
      }
    },
    {
      "geometry": {
        "type": "Point",
        "coordinates": [
          30.75,
          30.816667
        ]
      },
      "type": "Feature",
      "properties": {
        "hierarchy": [
          "tgn:7524305",
          "tgn:7001242",
          "tgn:1001075",
          "tgn:7016833",
          "tgn:7029392"
        ],
        "placetype": [
          "aat:300007783"
        ],
        "name:en": "Maḩaţţat at Tawfīqīyah",
        "id": 7524305
      }
    },
    {
      "geometry": {
        "type": "Point",
        "coordinates": [
          30.050756,
          31.217733
        ]
      },
      "type": "Feature",
      "properties": {
        "hierarchy": [
          "tgn:7524306",
          "tgn:7001242",
          "tgn:7016833",
          "tgn:1001079",
          "tgn:7029392"
        ],
        "placetype": [
          "aat:300008347"
        ],
        "name:en": "At Tawfīqīyah",
        "id": 7524306
      }
    },
    {
      "geometry": {
        "type": "Point",
        "coordinates": [
          30.746891,
          30.815567
        ]
      },
      "type": "Feature",
      "properties": {
        "hierarchy": [
          "tgn:7524307",
          "tgn:7001242",
          "tgn:1001075",
          "tgn:7016833",
          "tgn:7029392"
        ],
        "placetype": [
          "aat:300008347"
        ],
        "name:en": "At Tawfīqīyah",
        "id": 7524307
      }
    },
    {
      "geometry": {
        "type": "Point",
        "coordinates": [
          30.810553,
          29.376815
        ]
      },
      "type": "Feature",
      "properties": {
        "hierarchy": [
          "tgn:7524308",
          "tgn:7001242",
          "tgn:7001105",
          "tgn:7016833",
          "tgn:7029392"
        ],
        "placetype": [
          "aat:300008347"
        ],
        "name:en": "At Tawfīqīyah",
        "id": 7524308
      }
    },
    {
      "geometry": {
        "type": "Point",
        "coordinates": [
          30.76048,
          28.364797
        ]
      },
      "type": "Feature",
      "properties": {
        "hierarchy": [
          "tgn:7524309",
          "tgn:7001242",
          "tgn:7016833",
          "tgn:1001088",
          "tgn:7029392"
        ],
        "placetype": [
          "aat:300008347"
        ],
        "name:en": "At Tawfīqīyah",
        "id": 7524309
      }
    }
  ]
}
