{
  "geometry": {
    "type": "Point",
    "coordinates": [
      16.0667,
      51.8667
    ]
  },
  "type": "Feature",
  "properties": {
    "hierarchy": [
      "tgn:1049437",
      "tgn:1000003",
      "tgn:7024120",
      "tgn:7006366",
      "tgn:7029392"
    ],
    "placetype": [
      "aat:300008347"
    ],
    "id": 1049437,
    "name:xx": "Sława"
  }
}
