{
  "geometry": {
    "type": "Point",
    "coordinates": [
      28.3333,
      -29.0833
    ]
  },
  "type": "Feature",
  "properties": {
    "hierarchy": [
      "tgn:1109973",
      "tgn:7001242",
      "tgn:7001660",
      "tgn:7029392"
    ],
    "placetype": [
      "aat:300386831"
    ],
    "id": 1109973,
    "name:xx": "Front Range"
  }
}
