{
  "geometry": {
    "type": "Point",
    "coordinates": [
      75.4905,
      28.7739
    ]
  },
  "type": "Feature",
  "properties": {
    "hierarchy": [
      "tgn:7584270",
      "tgn:1000004",
      "tgn:7000198",
      "tgn:7016788",
      "tgn:7029392"
    ],
    "placetype": [
      "aat:300008688"
    ],
    "name:en": "Dolariya ki Johri",
    "id": 7584270
  }
}
