{
  "type": "FeatureCollection",
  "features": [
    {
      "geometry": {
        "type": "Point",
        "coordinates": [
          -101.366667,
          21.533333
        ]
      },
      "type": "Feature",
      "properties": {
        "hierarchy": [
          "tgn:7440720",
          "tgn:7005584",
          "tgn:1000001",
          "tgn:7005560",
          "tgn:7029392"
        ],
        "placetype": [
          "aat:300008347"
        ],
        "id": 7440720,
        "name:xx": "Santa Bárbara"
      }
    },
    {
      "geometry": {
        "type": "Point",
        "coordinates": [
          -104.616667,
          21.333333
        ]
      },
      "type": "Feature",
      "properties": {
        "hierarchy": [
          "tgn:7440721",
          "tgn:1000001",
          "tgn:1001906",
          "tgn:7005560",
          "tgn:7029392"
        ],
        "placetype": [
          "aat:300008347"
        ],
        "id": 7440721,
        "name:xx": "Santa Barbara"
      }
    },
    {
      "geometry": {
        "type": "Point",
        "coordinates": [
          -89.1,
          21.133333
        ]
      },
      "type": "Feature",
      "properties": {
        "hierarchy": [
          "tgn:7440722",
          "tgn:1000001",
          "tgn:7005600",
          "tgn:7005560",
          "tgn:7029392"
        ],
        "placetype": [
          "aat:300008347"
        ],
        "id": 7440722,
        "name:xx": "Santa Bárbara"
      }
    },
    {
      "geometry": {
        "type": "Point",
        "coordinates": [
          -102.7,
          20.95
        ]
      },
      "type": "Feature",
      "properties": {
        "hierarchy": [
          "tgn:7440723",
          "tgn:7005586",
          "tgn:1000001",
          "tgn:7005560",
          "tgn:7029392"
        ],
        "placetype": [
          "aat:300008347"
        ],
        "id": 7440723,
        "name:xx": "Santa Bárbara"
      }
    },
    {
      "geometry": {
        "type": "Point",
        "coordinates": [
          -99.816667,
          20.75
        ]
      },
      "type": "Feature",
      "properties": {
        "hierarchy": [
          "tgn:7440724",
          "tgn:1000001",
          "tgn:7005593",
          "tgn:7005560",
          "tgn:7029392"
        ],
        "placetype": [
          "aat:300008347"
        ],
        "id": 7440724,
        "name:xx": "Santa Bárbara"
      }
    },
    {
      "geometry": {
        "type": "Point",
        "coordinates": [
          -88.216667,
          20.7
        ]
      },
      "type": "Feature",
      "properties": {
        "hierarchy": [
          "tgn:7440725",
          "tgn:1000001",
          "tgn:7005600",
          "tgn:7005560",
          "tgn:7029392"
        ],
        "placetype": [
          "aat:300008347"
        ],
        "id": 7440725,
        "name:xx": "Santa Bárbara"
      }
    },
    {
      "geometry": {
        "type": "Point",
        "coordinates": [
          -90.05,
          20.383333
        ]
      },
      "type": "Feature",
      "properties": {
        "hierarchy": [
          "tgn:7440726",
          "tgn:7005578",
          "tgn:1000001",
          "tgn:7005560",
          "tgn:7029392"
        ],
        "placetype": [
          "aat:300008347"
        ],
        "id": 7440726,
        "name:xx": "Santa Bárbara"
      }
    },
    {
      "geometry": {
        "type": "Point",
        "coordinates": [
          -104.483333,
          20.316667
        ]
      },
      "type": "Feature",
      "properties": {
        "hierarchy": [
          "tgn:7440727",
          "tgn:7005586",
          "tgn:1000001",
          "tgn:7005560",
          "tgn:7029392"
        ],
        "placetype": [
          "aat:300008347"
        ],
        "id": 7440727,
        "name:xx": "Santa Bárbara"
      }
    },
    {
      "geometry": {
        "type": "Point",
        "coordinates": [
          -100.833333,
          20.3
        ]
      },
      "type": "Feature",
      "properties": {
        "hierarchy": [
          "tgn:7440728",
          "tgn:7005584",
          "tgn:1000001",
          "tgn:7005560",
          "tgn:7029392"
        ],
        "placetype": [
          "aat:300008347"
        ],
        "id": 7440728,
        "name:xx": "Santa Bárbara"
      }
    }
  ]
}
