{
  "geometry": {
    "type": "Point",
    "coordinates": [
      -115.6833,
      48.2167
    ]
  },
  "type": "Feature",
  "properties": {
    "hierarchy": [
      "tgn:2545550",
      "tgn:1000001",
      "tgn:7012149",
      "tgn:2001304",
      "tgn:7007524",
      "tgn:7029392"
    ],
    "placetype": [
      "aat:300008707"
    ],
    "id": 2545550,
    "name:xx": "North Fork Bull River"
  }
}
