{
  "geometry": {
    "type": "Point",
    "coordinates": [
      -73.6667,
      44.4667
    ]
  },
  "type": "Feature",
  "properties": {
    "hierarchy": [
      "tgn:2580548",
      "tgn:1000001",
      "tgn:1002284",
      "tgn:7012149",
      "tgn:7007568",
      "tgn:7029392"
    ],
    "placetype": [
      "aat:300008798"
    ],
    "id": 2580548,
    "name:xx": "Pigeon Hill"
  }
}
