{
  "geometry": {
    "type": "Point",
    "coordinates": [
      -81.05,
      32.65
    ]
  },
  "type": "Feature",
  "properties": {
    "hierarchy": [
      "tgn:2717852",
      "tgn:1000001",
      "tgn:2001749",
      "tgn:7012149",
      "tgn:7007712",
      "tgn:7029392"
    ],
    "placetype": [
      "aat:300006191"
    ],
    "id": 2717852,
    "name:xx": "Thomas Pond"
  }
}
