{
  "geometry": {
    "type": "Point",
    "coordinates": [
      -82.4167,
      38.5833
    ]
  },
  "type": "Feature",
  "properties": {
    "hierarchy": [
      "tgn:2702145",
      "tgn:1000001",
      "tgn:7012149",
      "tgn:2001615",
      "tgn:7007706",
      "tgn:7029392"
    ],
    "placetype": [
      "aat:300008347"
    ],
    "id": 2702145,
    "name:xx": "Suiter"
  }
}
