{
  "type": "FeatureCollection",
  "features": [
    {
      "geometry": {
        "type": "Point",
        "coordinates": [
          -8.5,
          42.383333
        ]
      },
      "type": "Feature",
      "properties": {
        "hierarchy": [
          "tgn:1062380",
          "tgn:7002834",
          "tgn:1000003",
          "tgn:7002786",
          "tgn:1000095",
          "tgn:7029392"
        ],
        "placetype": [
          "aat:300008347"
        ],
        "id": 1062380,
        "name:xx": "Puente-Caldelas"
      }
    },
    {
      "geometry": {
        "type": "Point",
        "coordinates": [
          -4.783333,
          37.383333
        ]
      },
      "type": "Feature",
      "properties": {
        "hierarchy": [
          "tgn:1062381",
          "tgn:7002758",
          "tgn:7002817",
          "tgn:1000003",
          "tgn:1000095",
          "tgn:7029392"
        ],
        "placetype": [
          "aat:300008347"
        ],
        "id": 1062381,
        "name:xx": "Puente-Genil"
      }
    },
    {
      "geometry": {
        "type": "Point",
        "coordinates": [
          -8.5,
          42.183333
        ]
      },
      "type": "Feature",
      "properties": {
        "hierarchy": [
          "tgn:1062382",
          "tgn:7002834",
          "tgn:1000003",
          "tgn:7002786",
          "tgn:1000095",
          "tgn:7029392"
        ],
        "placetype": [
          "aat:300008347"
        ],
        "id": 1062382,
        "name:xx": "Puenteareas"
      }
    },
    {
      "geometry": {
        "type": "Point",
        "coordinates": [
          -8.166667,
          43.4
        ]
      },
      "type": "Feature",
      "properties": {
        "hierarchy": [
          "tgn:1062383",
          "tgn:7002824",
          "tgn:1000003",
          "tgn:7002786",
          "tgn:1000095",
          "tgn:7029392"
        ],
        "placetype": [
          "aat:300008347"
        ],
        "id": 1062383,
        "name:xx": "Puentedeume"
      }
    },
    {
      "geometry": {
        "type": "Point",
        "coordinates": [
          6.1833,
          36.5333
        ]
      },
      "type": "Feature",
      "properties": {
        "hierarchy": [
          "tgn:1062384",
          "tgn:7002813",
          "tgn:7002758",
          "tgn:1000003",
          "tgn:1000095",
          "tgn:7029392"
        ],
        "placetype": [
          "aat:300008347"
        ],
        "id": 1062384,
        "name:xx": "Puerto Real"
      }
    },
    {
      "geometry": {
        "type": "Point",
        "coordinates": [
          3.066667,
          39.9
        ]
      },
      "type": "Feature",
      "properties": {
        "hierarchy": [
          "tgn:1062385",
          "tgn:7001122",
          "tgn:1000003",
          "tgn:7002765",
          "tgn:1000095",
          "tgn:7007959",
          "tgn:7029392"
        ],
        "placetype": [
          "aat:300008347"
        ],
        "id": 1062385,
        "name:xx": "Puerto de Pollensa"
      }
    },
    {
      "geometry": {
        "type": "Point",
        "coordinates": [
          -13.866667,
          28.5
        ]
      },
      "type": "Feature",
      "properties": {
        "hierarchy": [
          "tgn:1062386",
          "tgn:7002825",
          "tgn:7016622",
          "tgn:1000003",
          "tgn:1000095",
          "tgn:1007139",
          "tgn:7029392"
        ],
        "placetype": [
          "aat:300008347"
        ],
        "id": 1062386,
        "name:xx": "Puerto del Rosario"
      }
    },
    {
      "geometry": {
        "type": "Point",
        "coordinates": [
          1.928407,
          42.430977
        ]
      },
      "type": "Feature",
      "properties": {
        "hierarchy": [
          "tgn:1062388",
          "tgn:7002820",
          "tgn:7030216",
          "tgn:1000003",
          "tgn:1000095",
          "tgn:7029392"
        ],
        "placetype": [
          "aat:300008347",
          "aat:300387218",
          "aat:300008375"
        ],
        "id": 1062388,
        "name:xx": "Puigcerdá"
      }
    },
    {
      "geometry": {
        "type": "Point",
        "coordinates": [
          -2.366667,
          37.35
        ]
      },
      "type": "Feature",
      "properties": {
        "hierarchy": [
          "tgn:1062389",
          "tgn:7002805",
          "tgn:7002758",
          "tgn:1000003",
          "tgn:1000095",
          "tgn:7029392"
        ],
        "placetype": [
          "aat:300008347"
        ],
        "id": 1062389,
        "name:xx": "Purchena"
      }
    }
  ]
}
