{
  "geometry": {
    "type": "Point",
    "coordinates": [
      -105.2167,
      38.8833
    ]
  },
  "type": "Feature",
  "properties": {
    "hierarchy": [
      "tgn:2358988",
      "tgn:1000001",
      "tgn:7012149",
      "tgn:7007158",
      "tgn:2000251",
      "tgn:7029392"
    ],
    "placetype": [
      "aat:300008798"
    ],
    "id": 2358988,
    "name:xx": "Granite Hills"
  }
}
