{
  "type": "FeatureCollection",
  "features": [
    {
      "geometry": {
        "type": "Point",
        "coordinates": [
          -81.7,
          36.2833
        ]
      },
      "type": "Feature",
      "properties": {
        "hierarchy": [
          "tgn:2377210",
          "tgn:1000001",
          "tgn:7012149",
          "tgn:2001551",
          "tgn:7007709",
          "tgn:7029392"
        ],
        "placetype": [
          "aat:300008798"
        ],
        "id": 2377210,
        "name:xx": "Harmon Knob"
      }
    },
    {
      "geometry": {
        "type": "Point",
        "coordinates": [
          -86.2833,
          33.5
        ]
      },
      "type": "Feature",
      "properties": {
        "hierarchy": [
          "tgn:2377211",
          "tgn:7002659",
          "tgn:1000001",
          "tgn:7012149",
          "tgn:2000057",
          "tgn:7029392"
        ],
        "placetype": [
          "aat:300008680"
        ],
        "id": 2377211,
        "name:xx": "Harmon Lake"
      }
    },
    {
      "geometry": {
        "type": "Point",
        "coordinates": [
          -93.6833,
          43.4667
        ]
      },
      "type": "Feature",
      "properties": {
        "hierarchy": [
          "tgn:2377212",
          "tgn:1000001",
          "tgn:7012149",
          "tgn:2000655",
          "tgn:7007253",
          "tgn:7029392"
        ],
        "placetype": [
          "aat:300008680"
        ],
        "id": 2377212,
        "name:xx": "Harmon Lake"
      }
    },
    {
      "geometry": {
        "type": "Point",
        "coordinates": [
          -91.8,
          31.6
        ]
      },
      "type": "Feature",
      "properties": {
        "hierarchy": [
          "tgn:2377213",
          "tgn:1000001",
          "tgn:2000868",
          "tgn:7012149",
          "tgn:7007256",
          "tgn:7029392"
        ],
        "placetype": [
          "aat:300008680"
        ],
        "id": 2377213,
        "name:xx": "Harmon Lake"
      }
    },
    {
      "geometry": {
        "type": "Point",
        "coordinates": [
          -93.55,
          32.5
        ]
      },
      "type": "Feature",
      "properties": {
        "hierarchy": [
          "tgn:2377214",
          "tgn:1000001",
          "tgn:2000861",
          "tgn:7012149",
          "tgn:7007256",
          "tgn:7029392"
        ],
        "placetype": [
          "aat:300006191"
        ],
        "id": 2377214,
        "name:xx": "Harmon Lake"
      }
    },
    {
      "geometry": {
        "type": "Point",
        "coordinates": [
          -67.5333,
          44.7667
        ]
      },
      "type": "Feature",
      "properties": {
        "hierarchy": [
          "tgn:2377215",
          "tgn:1000001",
          "tgn:7012149",
          "tgn:7014589",
          "tgn:7007515",
          "tgn:7029392"
        ],
        "placetype": [
          "aat:300008680"
        ],
        "id": 2377215,
        "name:xx": "Harmon Lake"
      }
    },
    {
      "geometry": {
        "type": "Point",
        "coordinates": [
          -83.3167,
          43.3833
        ]
      },
      "type": "Feature",
      "properties": {
        "hierarchy": [
          "tgn:2377216",
          "tgn:1000001",
          "tgn:7012149",
          "tgn:2000997",
          "tgn:7007520",
          "tgn:7029392"
        ],
        "placetype": [
          "aat:300008680"
        ],
        "id": 2377216,
        "name:xx": "Harmon Lake"
      }
    },
    {
      "geometry": {
        "type": "Point",
        "coordinates": [
          -88.7167,
          33.5667
        ]
      },
      "type": "Feature",
      "properties": {
        "hierarchy": [
          "tgn:2377217",
          "tgn:1000001",
          "tgn:2001098",
          "tgn:7012149",
          "tgn:7007522",
          "tgn:7029392"
        ],
        "placetype": [
          "aat:300008680"
        ],
        "id": 2377217,
        "name:xx": "Harmon Lake"
      }
    },
    {
      "geometry": {
        "type": "Point",
        "coordinates": [
          -94.8833,
          31.9333
        ]
      },
      "type": "Feature",
      "properties": {
        "hierarchy": [
          "tgn:2377218",
          "tgn:1000001",
          "tgn:7012149",
          "tgn:1002839",
          "tgn:7007826",
          "tgn:7029392"
        ],
        "placetype": [
          "aat:300008680"
        ],
        "id": 2377218,
        "name:xx": "Harmon Lake"
      }
    },
    {
      "geometry": {
        "type": "Point",
        "coordinates": [
          -91.65,
          45.7667
        ]
      },
      "type": "Feature",
      "properties": {
        "hierarchy": [
          "tgn:2377219",
          "tgn:1000001",
          "tgn:7012149",
          "tgn:2002360",
          "tgn:7007922",
          "tgn:7029392"
        ],
        "placetype": [
          "aat:300008680"
        ],
        "id": 2377219,
        "name:xx": "Harmon Lake"
      }
    }
  ]
}
