{
  "geometry": {
    "type": "Point",
    "coordinates": [
      5.9333,
      45.7167
    ]
  },
  "type": "Feature",
  "properties": {
    "hierarchy": [
      "tgn:1033312",
      "tgn:1000003",
      "tgn:1000070",
      "tgn:7002897",
      "tgn:7029392"
    ],
    "placetype": [
      "aat:300008347"
    ],
    "id": 1033312,
    "name:xx": "Grésy-sur-Aix"
  }
}
