{
  "geometry": {
    "type": "Point",
    "coordinates": [
      -89.8667,
      31.5833
    ]
  },
  "type": "Feature",
  "properties": {
    "hierarchy": [
      "tgn:2057289",
      "tgn:1000001",
      "tgn:7012149",
      "tgn:2001118",
      "tgn:7007522",
      "tgn:7029392"
    ],
    "placetype": [
      "aat:300008347",
      "aat:300008416"
    ],
    "id": 2057289,
    "name:xx": "Prentiss"
  }
}
