{
  "type": "FeatureCollection",
  "features": [
    {
      "geometry": {
        "type": "Point",
        "coordinates": [
          25.55,
          36.95
        ]
      },
      "type": "Feature",
      "properties": {
        "hierarchy": [
          "tgn:7221620",
          "tgn:7011270",
          "tgn:7002674",
          "tgn:1000003",
          "tgn:1000074",
          "tgn:7029392"
        ],
        "placetype": [
          "aat:300008850"
        ],
        "id": 7221620,
        "name:xx": "Pánormos, Ákra"
      }
    },
    {
      "geometry": {
        "type": "Point",
        "coordinates": [
          22.25,
          38.366667
        ]
      },
      "type": "Feature",
      "properties": {
        "hierarchy": [
          "tgn:7221621",
          "tgn:7002680",
          "tgn:7001395",
          "tgn:1000003",
          "tgn:1000074",
          "tgn:7029392"
        ],
        "placetype": [
          "aat:300008347"
        ],
        "id": 7221621,
        "name:xx": "Pánormos"
      }
    },
    {
      "geometry": {
        "type": "Point",
        "coordinates": [
          24.7,
          35.416667
        ]
      },
      "type": "Feature",
      "properties": {
        "hierarchy": [
          "tgn:7221623",
          "tgn:7002691",
          "tgn:7012056",
          "tgn:1000003",
          "tgn:1000074",
          "tgn:7029392"
        ],
        "placetype": [
          "aat:300008347"
        ],
        "id": 7221623,
        "name:xx": "Pánormos"
      }
    },
    {
      "geometry": {
        "type": "Point",
        "coordinates": [
          27.833333,
          36.533333
        ]
      },
      "type": "Feature",
      "properties": {
        "hierarchy": [
          "tgn:7221624",
          "tgn:7011330",
          "tgn:7002674",
          "tgn:1000003",
          "tgn:1000074",
          "tgn:7029392"
        ],
        "placetype": [
          "aat:300008678"
        ],
        "id": 7221624,
        "name:xx": "Panormítis, Limín"
      }
    },
    {
      "geometry": {
        "type": "Point",
        "coordinates": [
          27.85,
          36.533333
        ]
      },
      "type": "Feature",
      "properties": {
        "hierarchy": [
          "tgn:7221625",
          "tgn:7011330",
          "tgn:7002674",
          "tgn:1000003",
          "tgn:1000074",
          "tgn:7029392"
        ],
        "placetype": [
          "aat:300008347"
        ],
        "id": 7221625,
        "name:xx": "Panormítis"
      }
    },
    {
      "geometry": {
        "type": "Point",
        "coordinates": [
          23.816667,
          41.25
        ]
      },
      "type": "Feature",
      "properties": {
        "hierarchy": [
          "tgn:7221627",
          "tgn:7011170",
          "tgn:7002715",
          "tgn:1000003",
          "tgn:1000074",
          "tgn:7029392"
        ],
        "placetype": [
          "aat:300008347"
        ],
        "id": 7221627,
        "name:xx": "Panórama"
      }
    },
    {
      "geometry": {
        "type": "Point",
        "coordinates": [
          23.031501,
          40.587793
        ]
      },
      "type": "Feature",
      "properties": {
        "hierarchy": [
          "tgn:7221628",
          "tgn:7002715",
          "tgn:7002731",
          "tgn:1000003",
          "tgn:1000074",
          "tgn:7029392"
        ],
        "placetype": [
          "aat:300008347"
        ],
        "id": 7221628,
        "name:xx": "Panórama"
      }
    },
    {
      "geometry": {
        "type": "Point",
        "coordinates": [
          21.183333,
          40.033333
        ]
      },
      "type": "Feature",
      "properties": {
        "hierarchy": [
          "tgn:7221629",
          "tgn:7002707",
          "tgn:7002705",
          "tgn:1000003",
          "tgn:1000074",
          "tgn:7029392"
        ],
        "placetype": [
          "aat:300008347"
        ],
        "id": 7221629,
        "name:xx": "Panórama"
      }
    }
  ]
}
