{
  "geometry": {
    "type": "Point",
    "coordinates": [
      -92.8833,
      36.2833
    ]
  },
  "type": "Feature",
  "properties": {
    "hierarchy": [
      "tgn:2247891",
      "tgn:1000001",
      "tgn:7016172",
      "tgn:7012149",
      "tgn:7029392"
    ],
    "placetype": [
      "aat:300008761"
    ],
    "id": 2247891,
    "name:xx": "Coker Hollow"
  }
}
