{
  "geometry": {
    "type": "Point",
    "coordinates": [
      101.6667,
      23.45
    ]
  },
  "type": "Feature",
  "properties": {
    "hierarchy": [
      "tgn:1070513",
      "tgn:1000004",
      "tgn:7018118",
      "tgn:1000111",
      "tgn:7029392"
    ],
    "placetype": [
      "aat:300008347"
    ],
    "id": 1070513,
    "name:xx": "Mojiang"
  }
}
