{
  "geometry": {
    "type": "Point",
    "coordinates": [
      -111.3833,
      48.8667
    ]
  },
  "type": "Feature",
  "properties": {
    "hierarchy": [
      "tgn:2353301",
      "tgn:1000001",
      "tgn:7012149",
      "tgn:2001310",
      "tgn:7007524",
      "tgn:7029392"
    ],
    "placetype": [
      "aat:300008347"
    ],
    "id": 2353301,
    "name:xx": "Gold Butte"
  }
}
