{
  "geometry": {
    "type": "Point",
    "coordinates": [
      -73.5667,
      40.65
    ]
  },
  "type": "Feature",
  "properties": {
    "hierarchy": [
      "tgn:2339977",
      "tgn:1000001",
      "tgn:7012149",
      "tgn:1002708",
      "tgn:7007568",
      "tgn:7029392"
    ],
    "placetype": [
      "aat:300008706"
    ],
    "id": 2339977,
    "name:xx": "Freeport Creek"
  }
}
