{
  "geometry": {
    "type": "Point",
    "coordinates": [
      -117.45,
      46.0833
    ]
  },
  "type": "Feature",
  "properties": {
    "hierarchy": [
      "tgn:2759948",
      "tgn:2002239",
      "tgn:1000001",
      "tgn:7012149",
      "tgn:7007920",
      "tgn:7029392"
    ],
    "placetype": [
      "aat:300008706"
    ],
    "id": 2759948,
    "name:xx": "West Fork Menatchee Creek"
  }
}
