{
  "geometry": {
    "type": "Point",
    "coordinates": [
      46.7833,
      23.45
    ]
  },
  "type": "Feature",
  "properties": {
    "hierarchy": [
      "tgn:1084809",
      "tgn:7000680",
      "tgn:1000004",
      "tgn:7003879",
      "tgn:1000137",
      "tgn:7029392"
    ],
    "placetype": [
      "aat:300008347"
    ],
    "id": 1084809,
    "name:xx": "Al-Ḥulwah"
  }
}
