{
  "geometry": {
    "type": "Point",
    "coordinates": [
      -45.5167,
      -22.3667
    ]
  },
  "type": "Feature",
  "properties": {
    "hierarchy": [
      "tgn:1126392",
      "tgn:7006237",
      "tgn:1000047",
      "tgn:7002457",
      "tgn:1000002",
      "tgn:7029392"
    ],
    "placetype": [
      "aat:300008707"
    ],
    "id": 1126392,
    "name:xx": "Lourenço Velho"
  }
}
