{
  "geometry": {
    "type": "Point",
    "coordinates": [
      -136.7833,
      58.8667
    ]
  },
  "type": "Feature",
  "properties": {
    "hierarchy": [
      "tgn:2409008",
      "tgn:7006450",
      "tgn:1000001",
      "tgn:7012149",
      "tgn:7019760",
      "tgn:7029392"
    ],
    "placetype": [
      "aat:300008850"
    ],
    "id": 2409008,
    "name:xx": "Ibach Point"
  }
}
