{
  "geometry": {
    "type": "Point",
    "coordinates": [
      -91.7667,
      41.7833
    ]
  },
  "type": "Feature",
  "properties": {
    "hierarchy": [
      "tgn:2496622",
      "tgn:1000001",
      "tgn:7012149",
      "tgn:2000612",
      "tgn:7007253",
      "tgn:7029392"
    ],
    "placetype": [
      "aat:300008680"
    ],
    "id": 2496622,
    "name:xx": "Matson Pond"
  }
}
