{
  "geometry": {
    "type": "Point",
    "coordinates": [
      76.705093,
      28.90405
    ]
  },
  "type": "Feature",
  "properties": {
    "hierarchy": [
      "tgn:7547821",
      "tgn:1000004",
      "tgn:1001871",
      "tgn:7000198",
      "tgn:7029392"
    ],
    "placetype": [
      "aat:300008347"
    ],
    "name:en": "Bhālaut",
    "id": 7547821
  }
}
