{
  "geometry": {
    "type": "Point",
    "coordinates": [
      -83.5667,
      33.3667
    ]
  },
  "type": "Feature",
  "properties": {
    "hierarchy": [
      "tgn:2416475",
      "tgn:1000001",
      "tgn:7012149",
      "tgn:2000370",
      "tgn:7007248",
      "tgn:7029392"
    ],
    "placetype": [
      "aat:300008706"
    ],
    "id": 2416475,
    "name:xx": "Jack Creek"
  }
}
