{
  "geometry": {
    "type": "Point",
    "coordinates": [
      0.65,
      48.1833
    ]
  },
  "type": "Feature",
  "properties": {
    "hierarchy": [
      "tgn:1126569",
      "tgn:1000003",
      "tgn:1000070",
      "tgn:7029392"
    ],
    "placetype": [
      "aat:300008707"
    ],
    "id": 1126569,
    "name:xx": "Même"
  }
}
