{
  "type": "FeatureCollection",
  "features": [
    {
      "geometry": {
        "type": "Point",
        "coordinates": [
          4.566667,
          51.3
        ]
      },
      "type": "Feature",
      "properties": {
        "hierarchy": [
          "tgn:7242221",
          "tgn:7003456",
          "tgn:1000003",
          "tgn:1000063",
          "tgn:7018236",
          "tgn:7029392"
        ],
        "placetype": [
          "aat:300008347"
        ],
        "id": 7242221,
        "name:xx": "Lochtenberg"
      }
    },
    {
      "geometry": {
        "type": "Point",
        "coordinates": [
          4.62597,
          51.328825
        ]
      },
      "type": "Feature",
      "properties": {
        "hierarchy": [
          "tgn:7242222",
          "tgn:7003456",
          "tgn:1000003",
          "tgn:1000063",
          "tgn:7018236",
          "tgn:7029392"
        ],
        "placetype": [
          "aat:300008347"
        ],
        "id": 7242222,
        "name:xx": "Locht"
      }
    },
    {
      "geometry": {
        "type": "Point",
        "coordinates": [
          5.366667,
          51.15
        ]
      },
      "type": "Feature",
      "properties": {
        "hierarchy": [
          "tgn:7242223",
          "tgn:7003461",
          "tgn:1000003",
          "tgn:1000063",
          "tgn:7018236",
          "tgn:7029392"
        ],
        "placetype": [
          "aat:300008347"
        ],
        "id": 7242223,
        "name:xx": "Locht"
      }
    },
    {
      "geometry": {
        "type": "Point",
        "coordinates": [
          4.835826,
          51.08362
        ]
      },
      "type": "Feature",
      "properties": {
        "hierarchy": [
          "tgn:7242224",
          "tgn:7003456",
          "tgn:1000003",
          "tgn:1000063",
          "tgn:7018236",
          "tgn:7029392"
        ],
        "placetype": [
          "aat:300008347"
        ],
        "id": 7242224,
        "name:xx": "Locht"
      }
    },
    {
      "geometry": {
        "type": "Point",
        "coordinates": [
          5.55,
          50.883333
        ]
      },
      "type": "Feature",
      "properties": {
        "hierarchy": [
          "tgn:7242225",
          "tgn:7003461",
          "tgn:1000003",
          "tgn:1000063",
          "tgn:7018236",
          "tgn:7029392"
        ],
        "placetype": [
          "aat:300008347"
        ],
        "id": 7242225,
        "name:xx": "Locht"
      }
    },
    {
      "geometry": {
        "type": "Point",
        "coordinates": [
          2.733333,
          50.983333
        ]
      },
      "type": "Feature",
      "properties": {
        "hierarchy": [
          "tgn:7242228",
          "tgn:7003458",
          "tgn:1000003",
          "tgn:1000063",
          "tgn:7018236",
          "tgn:7029392"
        ],
        "placetype": [
          "aat:300008347"
        ],
        "id": 7242228,
        "name:xx": "Lobrug"
      }
    },
    {
      "geometry": {
        "type": "Point",
        "coordinates": [
          5.516667,
          51.166667
        ]
      },
      "type": "Feature",
      "properties": {
        "hierarchy": [
          "tgn:7242229",
          "tgn:7003461",
          "tgn:1000003",
          "tgn:1000063",
          "tgn:7018236",
          "tgn:7029392"
        ],
        "placetype": [
          "aat:300008347"
        ],
        "id": 7242229,
        "name:xx": "Lobroek"
      }
    }
  ]
}
