{
  "geometry": {
    "type": "Point",
    "coordinates": [
      -77.2667,
      38.0167
    ]
  },
  "type": "Feature",
  "properties": {
    "hierarchy": [
      "tgn:2592624",
      "tgn:1000001",
      "tgn:1002235",
      "tgn:7012149",
      "tgn:7007919",
      "tgn:7029392"
    ],
    "placetype": [
      "aat:300008347"
    ],
    "id": 2592624,
    "name:xx": "Poorhouse Corner"
  }
}
