{
  "geometry": {
    "type": "Point",
    "coordinates": [
      -86.0333,
      16.0167
    ]
  },
  "type": "Feature",
  "properties": {
    "hierarchy": [
      "tgn:1011724",
      "tgn:1000573",
      "tgn:1000001",
      "tgn:7005554",
      "tgn:7029392"
    ],
    "placetype": [
      "aat:300386846"
    ],
    "id": 1011724,
    "name:xx": "Caxinas, Punta"
  }
}
