{
  "geometry": {
    "type": "Point",
    "coordinates": [
      -96.1333,
      31.35
    ]
  },
  "type": "Feature",
  "properties": {
    "hierarchy": [
      "tgn:1133734",
      "tgn:1000001",
      "tgn:7012149",
      "tgn:1002590",
      "tgn:7007826",
      "tgn:7029392"
    ],
    "placetype": [
      "aat:300008706"
    ],
    "id": 1133734,
    "name:xx": "Lower Keechi Creek"
  }
}
