{
  "geometry": {
    "type": "Point",
    "coordinates": [
      -62.8667,
      -8.05
    ]
  },
  "type": "Feature",
  "properties": {
    "hierarchy": [
      "tgn:1125198",
      "tgn:1001944",
      "tgn:1000047",
      "tgn:7002456",
      "tgn:1000002",
      "tgn:7029392"
    ],
    "placetype": [
      "aat:300008707"
    ],
    "id": 1125198,
    "name:xx": "Jiparaná"
  }
}
