{
  "geometry": {
    "type": "Point",
    "coordinates": [
      -86.8333,
      33.3333
    ]
  },
  "type": "Feature",
  "properties": {
    "hierarchy": [
      "tgn:7022322",
      "tgn:7002659",
      "tgn:1000001",
      "tgn:7012149",
      "tgn:7029392"
    ],
    "placetype": [
      "aat:300008699"
    ],
    "id": 7022322,
    "name:xx": "Bailey Brook"
  }
}
