{
  "geometry": {
    "type": "Point",
    "coordinates": [
      -68.45,
      44.8333
    ]
  },
  "type": "Feature",
  "properties": {
    "hierarchy": [
      "tgn:2355229",
      "tgn:1000001",
      "tgn:7012149",
      "tgn:7007515",
      "tgn:7029392"
    ],
    "placetype": [
      "aat:300008699"
    ],
    "id": 2355229,
    "name:xx": "Goodwin Brook"
  }
}
