{
  "geometry": {
    "type": "Point",
    "coordinates": [
      -89.5333,
      36.25
    ]
  },
  "type": "Feature",
  "properties": {
    "hierarchy": [
      "tgn:2487084",
      "tgn:1000001",
      "tgn:7012149",
      "tgn:2001227",
      "tgn:7007523",
      "tgn:7029392"
    ],
    "placetype": [
      "aat:300008791"
    ],
    "id": 2487084,
    "name:xx": "Lee Towhead"
  }
}
