{
  "geometry": {
    "type": "Point",
    "coordinates": [
      -110.5167,
      31.4667
    ]
  },
  "type": "Feature",
  "properties": {
    "hierarchy": [
      "tgn:2571454",
      "tgn:1000001",
      "tgn:7006451",
      "tgn:7012149",
      "tgn:2000102",
      "tgn:7029392"
    ],
    "placetype": [
      "aat:300008761"
    ],
    "id": 2571454,
    "name:xx": "Pauline Canyon"
  }
}
