{
  "geometry": {
    "type": "Point",
    "coordinates": [
      -72.3333,
      42.0167
    ]
  },
  "type": "Feature",
  "properties": {
    "hierarchy": [
      "tgn:7021212",
      "tgn:1000001",
      "tgn:7012149",
      "tgn:7029392"
    ],
    "placetype": [
      "aat:300008707"
    ],
    "id": 7021212,
    "name:xx": "Scantic River"
  }
}
