{
  "geometry": {
    "type": "Point",
    "coordinates": [
      -71.0833,
      41.8333
    ]
  },
  "type": "Feature",
  "properties": {
    "hierarchy": [
      "tgn:2049406",
      "tgn:1002201",
      "tgn:1000001",
      "tgn:7012149",
      "tgn:7007517",
      "tgn:7029392"
    ],
    "placetype": [
      "aat:300008347"
    ],
    "id": 2049406,
    "name:xx": "Berkley"
  }
}
