{
  "geometry": {
    "type": "Point",
    "coordinates": [
      4.3333,
      44.4333
    ]
  },
  "type": "Feature",
  "properties": {
    "hierarchy": [
      "tgn:1121728",
      "tgn:1000003",
      "tgn:1000070",
      "tgn:7002897",
      "tgn:7029392"
    ],
    "placetype": [
      "aat:300008707"
    ],
    "id": 1121728,
    "name:xx": "Baume"
  }
}
