{
  "geometry": {
    "type": "Point",
    "coordinates": [
      137.1333,
      35.4167
    ]
  },
  "type": "Feature",
  "properties": {
    "hierarchy": [
      "tgn:1080815",
      "tgn:7000895",
      "tgn:1000004",
      "tgn:1000977",
      "tgn:1000120",
      "tgn:7029392"
    ],
    "placetype": [
      "aat:300008347"
    ],
    "id": 1080815,
    "name:xx": "Mitake"
  }
}
