{
  "geometry": {
    "type": "Point",
    "coordinates": [
      34.06784,
      22.477341
    ]
  },
  "type": "Feature",
  "properties": {
    "hierarchy": [
      "tgn:7528161",
      "tgn:7001242",
      "tgn:7001311",
      "tgn:7016833",
      "tgn:7029392"
    ],
    "placetype": [
      "aat:300379998"
    ],
    "name:en": "Umm Durayrah, Wādī",
    "id": 7528161
  }
}
