{
  "type": "FeatureCollection",
  "features": [
    {
      "geometry": {
        "type": "Point",
        "coordinates": [
          -117.8,
          44.7833
        ]
      },
      "type": "Feature",
      "properties": {
        "hierarchy": [
          "tgn:2539240",
          "tgn:7013349",
          "tgn:1000001",
          "tgn:7012149",
          "tgn:7007708",
          "tgn:7029392"
        ],
        "placetype": [
          "aat:300006075"
        ],
        "id": 2539240,
        "name:xx": "New Home Ditch"
      }
    },
    {
      "geometry": {
        "type": "Point",
        "coordinates": [
          -112.1,
          33.5
        ]
      },
      "type": "Feature",
      "properties": {
        "hierarchy": [
          "tgn:2539241",
          "tgn:1000001",
          "tgn:7006451",
          "tgn:7012149",
          "tgn:2000097",
          "tgn:7029392"
        ],
        "placetype": [
          "aat:300008347"
        ],
        "id": 2539241,
        "name:xx": "New Home Mobile Park"
      }
    },
    {
      "geometry": {
        "type": "Point",
        "coordinates": [
          -86.3333,
          31.5333
        ]
      },
      "type": "Feature",
      "properties": {
        "hierarchy": [
          "tgn:2539242",
          "tgn:7002659",
          "tgn:1000001",
          "tgn:2000020",
          "tgn:7012149",
          "tgn:7029392"
        ],
        "placetype": [
          "aat:300008347"
        ],
        "id": 2539242,
        "name:xx": "New Hope"
      }
    },
    {
      "geometry": {
        "type": "Point",
        "coordinates": [
          -86.8167,
          34.5833
        ]
      },
      "type": "Feature",
      "properties": {
        "hierarchy": [
          "tgn:2539243",
          "tgn:7002659",
          "tgn:1000001",
          "tgn:7012149",
          "tgn:2000041",
          "tgn:7029392"
        ],
        "placetype": [
          "aat:300008347"
        ],
        "id": 2539243,
        "name:xx": "New Hope"
      }
    },
    {
      "geometry": {
        "type": "Point",
        "coordinates": [
          -87.6833,
          33.5333
        ]
      },
      "type": "Feature",
      "properties": {
        "hierarchy": [
          "tgn:2539244",
          "tgn:7002659",
          "tgn:1000001",
          "tgn:7012149",
          "tgn:2000028",
          "tgn:7029392"
        ],
        "placetype": [
          "aat:300008347"
        ],
        "id": 2539244,
        "name:xx": "New Hope"
      }
    },
    {
      "geometry": {
        "type": "Point",
        "coordinates": [
          -87.7833,
          34.8667
        ]
      },
      "type": "Feature",
      "properties": {
        "hierarchy": [
          "tgn:2539245",
          "tgn:7002659",
          "tgn:1000001",
          "tgn:7012149",
          "tgn:2000038",
          "tgn:7029392"
        ],
        "placetype": [
          "aat:300008347"
        ],
        "id": 2539245,
        "name:xx": "New Hope"
      }
    },
    {
      "geometry": {
        "type": "Point",
        "coordinates": [
          -113.7667,
          33.6167
        ]
      },
      "type": "Feature",
      "properties": {
        "hierarchy": [
          "tgn:2539246",
          "tgn:1000001",
          "tgn:7006451",
          "tgn:7012149",
          "tgn:2000096",
          "tgn:7029392"
        ],
        "placetype": [
          "aat:300008347"
        ],
        "id": 2539246,
        "name:xx": "New Hope"
      }
    },
    {
      "geometry": {
        "type": "Point",
        "coordinates": [
          -92.9167,
          33.05
        ]
      },
      "type": "Feature",
      "properties": {
        "hierarchy": [
          "tgn:2539247",
          "tgn:1000001",
          "tgn:7016172",
          "tgn:7012149",
          "tgn:2000174",
          "tgn:7029392"
        ],
        "placetype": [
          "aat:300008347"
        ],
        "id": 2539247,
        "name:xx": "New Hope"
      }
    },
    {
      "geometry": {
        "type": "Point",
        "coordinates": [
          -92.7833,
          33.8833
        ]
      },
      "type": "Feature",
      "properties": {
        "hierarchy": [
          "tgn:2539248",
          "tgn:1000001",
          "tgn:7016172",
          "tgn:7012149",
          "tgn:2000124",
          "tgn:7029392"
        ],
        "placetype": [
          "aat:300008347"
        ],
        "id": 2539248,
        "name:xx": "New Hope"
      }
    },
    {
      "geometry": {
        "type": "Point",
        "coordinates": [
          -93.1167,
          36.45
        ]
      },
      "type": "Feature",
      "properties": {
        "hierarchy": [
          "tgn:2539249",
          "tgn:1000001",
          "tgn:7016172",
          "tgn:2000109",
          "tgn:7012149",
          "tgn:7029392"
        ],
        "placetype": [
          "aat:300008347"
        ],
        "id": 2539249,
        "name:xx": "New Hope"
      }
    }
  ]
}
