{
  "type": "FeatureCollection",
  "features": [
    {
      "geometry": {
        "type": "Point",
        "coordinates": [
          -113.8333,
          47.3667
        ]
      },
      "type": "Feature",
      "properties": {
        "hierarchy": [
          "tgn:2383350",
          "tgn:1000001",
          "tgn:7012149",
          "tgn:2001291",
          "tgn:7007524",
          "tgn:7029392"
        ],
        "placetype": [
          "aat:300008680"
        ],
        "id": 2383350,
        "name:xx": "Heart Lake"
      }
    },
    {
      "geometry": {
        "type": "Point",
        "coordinates": [
          -111.8667,
          45.2333
        ]
      },
      "type": "Feature",
      "properties": {
        "hierarchy": [
          "tgn:2383351",
          "tgn:1000001",
          "tgn:7012149",
          "tgn:2001288",
          "tgn:7007524",
          "tgn:7029392"
        ],
        "placetype": [
          "aat:300008680"
        ],
        "id": 2383351,
        "name:xx": "Heart Lake"
      }
    },
    {
      "geometry": {
        "type": "Point",
        "coordinates": [
          -109.6333,
          45.0167
        ]
      },
      "type": "Feature",
      "properties": {
        "hierarchy": [
          "tgn:2383352",
          "tgn:1000001",
          "tgn:2001264",
          "tgn:7012149",
          "tgn:7007524",
          "tgn:7029392"
        ],
        "placetype": [
          "aat:300008680"
        ],
        "id": 2383352,
        "name:xx": "Heart Lake"
      }
    },
    {
      "geometry": {
        "type": "Point",
        "coordinates": [
          -105.45,
          36.7833
        ]
      },
      "type": "Feature",
      "properties": {
        "hierarchy": [
          "tgn:2383353",
          "tgn:1000001",
          "tgn:7012149",
          "tgn:2001457",
          "tgn:7007566",
          "tgn:7029392"
        ],
        "placetype": [
          "aat:300008680"
        ],
        "id": 2383353,
        "name:xx": "Heart Lake"
      }
    },
    {
      "geometry": {
        "type": "Point",
        "coordinates": [
          -73.9667,
          44.1667
        ]
      },
      "type": "Feature",
      "properties": {
        "hierarchy": [
          "tgn:2383354",
          "tgn:1000001",
          "tgn:7012149",
          "tgn:2001461",
          "tgn:7007568",
          "tgn:7029392"
        ],
        "placetype": [
          "aat:300008680"
        ],
        "id": 2383354,
        "name:xx": "Heart Lake"
      }
    },
    {
      "geometry": {
        "type": "Point",
        "coordinates": [
          -81.6833,
          36.1333
        ]
      },
      "type": "Feature",
      "properties": {
        "hierarchy": [
          "tgn:2383355",
          "tgn:1000001",
          "tgn:7012149",
          "tgn:2001551",
          "tgn:7007709",
          "tgn:7029392"
        ],
        "placetype": [
          "aat:300006191"
        ],
        "id": 2383355,
        "name:xx": "Heart Lake"
      }
    },
    {
      "geometry": {
        "type": "Point",
        "coordinates": [
          -120.8333,
          42.25
        ]
      },
      "type": "Feature",
      "properties": {
        "hierarchy": [
          "tgn:2383356",
          "tgn:1000001",
          "tgn:7012149",
          "tgn:2001715",
          "tgn:7007708",
          "tgn:7029392"
        ],
        "placetype": [
          "aat:300008680"
        ],
        "id": 2383356,
        "name:xx": "Heart Lake"
      }
    },
    {
      "geometry": {
        "type": "Point",
        "coordinates": [
          -122.0833,
          44.3833
        ]
      },
      "type": "Feature",
      "properties": {
        "hierarchy": [
          "tgn:2383357",
          "tgn:1000001",
          "tgn:7012149",
          "tgn:2001717",
          "tgn:7007708",
          "tgn:7029392"
        ],
        "placetype": [
          "aat:300008680"
        ],
        "id": 2383357,
        "name:xx": "Heart Lake"
      }
    },
    {
      "geometry": {
        "type": "Point",
        "coordinates": [
          -117.3833,
          45.1
        ]
      },
      "type": "Feature",
      "properties": {
        "hierarchy": [
          "tgn:2383358",
          "tgn:1000001",
          "tgn:7012149",
          "tgn:2001721",
          "tgn:7007708",
          "tgn:7029392"
        ],
        "placetype": [
          "aat:300008680"
        ],
        "id": 2383358,
        "name:xx": "Heart Lake"
      }
    },
    {
      "geometry": {
        "type": "Point",
        "coordinates": [
          -122.9167,
          42.95
        ]
      },
      "type": "Feature",
      "properties": {
        "hierarchy": [
          "tgn:2383359",
          "tgn:1000001",
          "tgn:7012149",
          "tgn:2001706",
          "tgn:7007708",
          "tgn:7029392"
        ],
        "placetype": [
          "aat:300008680"
        ],
        "id": 2383359,
        "name:xx": "Heart Lake"
      }
    }
  ]
}
