{
  "geometry": {
    "type": "Point",
    "coordinates": [
      -76.65,
      41.2167
    ]
  },
  "type": "Feature",
  "properties": {
    "hierarchy": [
      "tgn:2195780",
      "tgn:1000001",
      "tgn:7012149",
      "tgn:1002613",
      "tgn:7007710",
      "tgn:7029392"
    ],
    "placetype": [
      "aat:300008699"
    ],
    "id": 2195780,
    "name:xx": "Broad Run"
  }
}
