{
  "geometry": {
    "type": "Point",
    "coordinates": [
      4.45,
      50.333333
    ]
  },
  "type": "Feature",
  "properties": {
    "hierarchy": [
      "tgn:7240751",
      "tgn:7007877",
      "tgn:1000003",
      "tgn:1000063",
      "tgn:4012014",
      "tgn:7029392"
    ],
    "placetype": [
      "aat:300008863"
    ],
    "id": 7240751,
    "name:xx": "Ferrée, Bois de la"
  }
}
