{
  "geometry": {
    "type": "Point",
    "coordinates": [
      -80.5667,
      27.1167
    ]
  },
  "type": "Feature",
  "properties": {
    "hierarchy": [
      "tgn:2533855",
      "tgn:1000001",
      "tgn:7012149",
      "tgn:1002641",
      "tgn:7007240",
      "tgn:7029392"
    ],
    "placetype": [
      "aat:300008791"
    ],
    "id": 2533855,
    "name:xx": "Myer Hammock"
  }
}
