{
  "geometry": {
    "type": "Point",
    "coordinates": [
      -104.9833,
      37.3667
    ]
  },
  "type": "Feature",
  "properties": {
    "hierarchy": [
      "tgn:1107629",
      "tgn:1000001",
      "tgn:7012149",
      "tgn:7007158",
      "tgn:7029392"
    ],
    "placetype": [
      "aat:300008798"
    ],
    "id": 1107629,
    "name:xx": "West Spanish Peak"
  }
}
