{
  "type": "FeatureCollection",
  "features": [
    {
      "geometry": {
        "type": "Point",
        "coordinates": [
          -70.233333,
          -28.966667
        ]
      },
      "type": "Feature",
      "properties": {
        "hierarchy": [
          "tgn:7312820",
          "tgn:1001630",
          "tgn:1000049",
          "tgn:1000002",
          "tgn:7029392"
        ],
        "placetype": [
          "aat:300008347"
        ],
        "id": 7312820,
        "name:xx": "La Pampa"
      }
    },
    {
      "geometry": {
        "type": "Point",
        "coordinates": [
          -71.25,
          -29.933333
        ]
      },
      "type": "Feature",
      "properties": {
        "hierarchy": [
          "tgn:7312821",
          "tgn:1001657",
          "tgn:1000049",
          "tgn:1000002",
          "tgn:7029392"
        ],
        "placetype": [
          "aat:300387200"
        ],
        "id": 7312821,
        "name:xx": "La Pampa"
      }
    },
    {
      "geometry": {
        "type": "Point",
        "coordinates": [
          -70.316667,
          -26.383333
        ]
      },
      "type": "Feature",
      "properties": {
        "hierarchy": [
          "tgn:7312822",
          "tgn:1001630",
          "tgn:1000049",
          "tgn:1000002",
          "tgn:7029392"
        ],
        "placetype": [
          "aat:300008795"
        ],
        "id": 7312822,
        "name:xx": "La Paloma, Sierra"
      }
    },
    {
      "geometry": {
        "type": "Point",
        "coordinates": [
          -72.45,
          -45.783333
        ]
      },
      "type": "Feature",
      "properties": {
        "hierarchy": [
          "tgn:7312823",
          "tgn:1001623",
          "tgn:1000049",
          "tgn:1000002",
          "tgn:7029392"
        ],
        "placetype": [
          "aat:300008699"
        ],
        "id": 7312823,
        "name:xx": "La Paloma, Río"
      }
    },
    {
      "geometry": {
        "type": "Point",
        "coordinates": [
          -70.116667,
          -33.55
        ]
      },
      "type": "Feature",
      "properties": {
        "hierarchy": [
          "tgn:7312824",
          "tgn:1001708",
          "tgn:1000049",
          "tgn:1000002",
          "tgn:7029392"
        ],
        "placetype": [
          "aat:300259572"
        ],
        "id": 7312824,
        "name:xx": "La Paloma, Portezuelo de"
      }
    },
    {
      "geometry": {
        "type": "Point",
        "coordinates": [
          -69.25,
          -22.95
        ]
      },
      "type": "Feature",
      "properties": {
        "hierarchy": [
          "tgn:7312825",
          "tgn:7016598",
          "tgn:1000049",
          "tgn:1000002",
          "tgn:7029392"
        ],
        "placetype": [
          "aat:300008805"
        ],
        "id": 7312825,
        "name:xx": "La Paloma, Pampa"
      }
    },
    {
      "geometry": {
        "type": "Point",
        "coordinates": [
          -72.116667,
          -45.916667
        ]
      },
      "type": "Feature",
      "properties": {
        "hierarchy": [
          "tgn:7312826",
          "tgn:1001623",
          "tgn:1000049",
          "tgn:1000002",
          "tgn:7029392"
        ],
        "placetype": [
          "aat:300008680"
        ],
        "id": 7312826,
        "name:xx": "La Paloma, Lago"
      }
    },
    {
      "geometry": {
        "type": "Point",
        "coordinates": [
          -70.133333,
          -33.616667
        ]
      },
      "type": "Feature",
      "properties": {
        "hierarchy": [
          "tgn:7312827",
          "tgn:1001708",
          "tgn:1000049",
          "tgn:1000002",
          "tgn:7029392"
        ],
        "placetype": [
          "aat:300008699"
        ],
        "id": 7312827,
        "name:xx": "La Paloma, Estero"
      }
    },
    {
      "geometry": {
        "type": "Point",
        "coordinates": [
          -69.45,
          -23.416667
        ]
      },
      "type": "Feature",
      "properties": {
        "hierarchy": [
          "tgn:7312829",
          "tgn:7016598",
          "tgn:1000049",
          "tgn:1000002",
          "tgn:7029392"
        ],
        "placetype": [
          "aat:300008777"
        ],
        "id": 7312829,
        "name:xx": "La Paloma, Cerros de"
      }
    }
  ]
}
