{
  "geometry": {
    "type": "Point",
    "coordinates": [
      6.7167,
      44.55
    ]
  },
  "type": "Feature",
  "properties": {
    "hierarchy": [
      "tgn:1108607",
      "tgn:1000003",
      "tgn:1000070",
      "tgn:7002895",
      "tgn:7029392"
    ],
    "placetype": [
      "aat:300259572"
    ],
    "id": 1108607,
    "name:xx": "Vars, Col du"
  }
}
