{
  "geometry": {
    "type": "Point",
    "coordinates": [
      13.05,
      51.233333
    ]
  },
  "type": "Feature",
  "properties": {
    "hierarchy": [
      "tgn:1037246",
      "tgn:1000003",
      "tgn:7003685",
      "tgn:7000084",
      "tgn:7029392"
    ],
    "placetype": [
      "aat:300008347"
    ],
    "id": 1037246,
    "name:xx": "Mügeln"
  }
}
