{
  "geometry": {
    "type": "Point",
    "coordinates": [
      -82.5667,
      27.3333
    ]
  },
  "type": "Feature",
  "properties": {
    "hierarchy": [
      "tgn:2603747",
      "tgn:1000001",
      "tgn:7012149",
      "tgn:1002870",
      "tgn:7007240",
      "tgn:7029392"
    ],
    "placetype": [
      "aat:300008850"
    ],
    "id": 2603747,
    "name:xx": "Quick Point"
  }
}
