{
  "geometry": {
    "type": "Point",
    "coordinates": [
      -111.2167,
      37.35
    ]
  },
  "type": "Feature",
  "properties": {
    "hierarchy": [
      "tgn:2346201",
      "tgn:1000001",
      "tgn:7012149",
      "tgn:2002113",
      "tgn:7007827",
      "tgn:7029392"
    ],
    "placetype": [
      "aat:300008761"
    ],
    "id": 2346201,
    "name:xx": "Gates Canyon"
  }
}
