{
  "geometry": {
    "type": "Point",
    "coordinates": [
      -89.1667,
      46.7333
    ]
  },
  "type": "Feature",
  "properties": {
    "hierarchy": [
      "tgn:2053161",
      "tgn:1000001",
      "tgn:7012149",
      "tgn:2000986",
      "tgn:7007520",
      "tgn:7029392"
    ],
    "placetype": [
      "aat:300008347"
    ],
    "id": 2053161,
    "name:xx": "Rockland"
  }
}
