{
  "geometry": {
    "type": "Point",
    "coordinates": [
      -107.1833,
      34.05
    ]
  },
  "type": "Feature",
  "properties": {
    "hierarchy": [
      "tgn:2696921",
      "tgn:1000001",
      "tgn:7012149",
      "tgn:2001456",
      "tgn:7007566",
      "tgn:7029392"
    ],
    "placetype": [
      "aat:300000390"
    ],
    "id": 2696921,
    "name:xx": "Stonewall Tunnel"
  }
}
