{
  "geometry": {
    "type": "Point",
    "coordinates": [
      -109.7333,
      42.85
    ]
  },
  "type": "Feature",
  "properties": {
    "hierarchy": [
      "tgn:2590640",
      "tgn:1000001",
      "tgn:7012149",
      "tgn:2002382",
      "tgn:7007923",
      "tgn:7029392"
    ],
    "placetype": [
      "aat:300006075"
    ],
    "id": 2590640,
    "name:xx": "Pole Creek Ditch Number 2"
  }
}
