{
  "geometry": {
    "type": "Point",
    "coordinates": [
      123.7333,
      13.35
    ]
  },
  "type": "Feature",
  "properties": {
    "hierarchy": [
      "tgn:1084671",
      "tgn:1001094",
      "tgn:1000004",
      "tgn:1000135",
      "tgn:7029392"
    ],
    "placetype": [
      "aat:300008347"
    ],
    "id": 1084671,
    "name:xx": "Tabaco"
  }
}
