{
  "geometry": {
    "type": "Point",
    "coordinates": [
      -90.3833,
      42.6667
    ]
  },
  "type": "Feature",
  "properties": {
    "hierarchy": [
      "tgn:2314348",
      "tgn:1000001",
      "tgn:7012149",
      "tgn:2002332",
      "tgn:7007922",
      "tgn:7029392"
    ],
    "placetype": [
      "aat:300008347"
    ],
    "id": 2314348,
    "name:xx": "Elk Grove"
  }
}
