{
  "geometry": {
    "type": "Point",
    "coordinates": [
      -81.75,
      37.6667
    ]
  },
  "type": "Feature",
  "properties": {
    "hierarchy": [
      "tgn:2526530",
      "tgn:1000001",
      "tgn:7012149",
      "tgn:2002304",
      "tgn:7013961",
      "tgn:7029392"
    ],
    "placetype": [
      "aat:300008699"
    ],
    "id": 2526530,
    "name:xx": "Mossy Branch"
  }
}
