{
  "geometry": {
    "type": "Point",
    "coordinates": [
      -78.3833,
      38.1667
    ]
  },
  "type": "Feature",
  "properties": {
    "hierarchy": [
      "tgn:2643146",
      "tgn:2002137",
      "tgn:1000001",
      "tgn:7012149",
      "tgn:7007919",
      "tgn:7029392"
    ],
    "placetype": [
      "aat:300008699"
    ],
    "id": 2643146,
    "name:xx": "Sandy Branch"
  }
}
