{
  "type": "FeatureCollection",
  "features": [
    {
      "geometry": {
        "type": "Point",
        "coordinates": [
          122.3333,
          30.6667
        ]
      },
      "type": "Feature",
      "properties": {
        "hierarchy": [
          "tgn:1010291",
          "tgn:1000004",
          "tgn:7002076",
          "tgn:1000111",
          "tgn:7029392"
        ],
        "placetype": [
          "aat:300008791"
        ],
        "id": 1010291,
        "name:xx": "Shengsi Liedao"
      }
    },
    {
      "geometry": {
        "type": "Point",
        "coordinates": [
          168.6,
          -16.9167
        ]
      },
      "type": "Feature",
      "properties": {
        "hierarchy": [
          "tgn:1010292",
          "tgn:7024015",
          "tgn:1000225",
          "tgn:1000006",
          "tgn:7029392"
        ],
        "placetype": [
          "aat:300386853"
        ],
        "id": 1010292,
        "name:xx": "Shepherd Islands"
      }
    },
    {
      "geometry": {
        "type": "Point",
        "coordinates": [
          -6.35,
          57.883333
        ]
      },
      "type": "Feature",
      "properties": {
        "hierarchy": [
          "tgn:1010294",
          "tgn:7002444",
          "tgn:1000003",
          "tgn:7008094",
          "tgn:7008591",
          "tgn:7029392"
        ],
        "placetype": [
          "aat:300008791",
          "aat:300386853"
        ],
        "name:en": "Shiant Islands",
        "id": 1010294
      }
    },
    {
      "geometry": {
        "type": "Point",
        "coordinates": [
          155.8833,
          -6.9167
        ]
      },
      "type": "Feature",
      "properties": {
        "hierarchy": [
          "tgn:1010296",
          "tgn:1001601",
          "tgn:1000233",
          "tgn:1000006",
          "tgn:7029392"
        ],
        "placetype": [
          "aat:300386853"
        ],
        "id": 1010296,
        "name:xx": "Shortland Islands"
      }
    }
  ]
}
