{
  "geometry": {
    "type": "Point",
    "coordinates": [
      8.0333,
      46.8333
    ]
  },
  "type": "Feature",
  "properties": {
    "hierarchy": [
      "tgn:1064347",
      "tgn:1000003",
      "tgn:7003750",
      "tgn:7011731",
      "tgn:7029392"
    ],
    "placetype": [
      "aat:300008347"
    ],
    "id": 1064347,
    "name:xx": "Sörenberg"
  }
}
