{
  "geometry": {
    "type": "Point",
    "coordinates": [
      -158.2167,
      61.4167
    ]
  },
  "type": "Feature",
  "properties": {
    "hierarchy": [
      "tgn:2160422",
      "tgn:7006450",
      "tgn:2000069",
      "tgn:1000001",
      "tgn:7012149",
      "tgn:7029392"
    ],
    "placetype": [
      "aat:300008706"
    ],
    "id": 2160422,
    "name:xx": "Beemguiga Creek"
  }
}
