{
  "type": "FeatureCollection",
  "features": [
    {
      "geometry": {
        "type": "Point",
        "coordinates": [
          -80.3333,
          34.2833
        ]
      },
      "type": "Feature",
      "properties": {
        "hierarchy": [
          "tgn:2096170",
          "tgn:1000001",
          "tgn:7012149",
          "tgn:2001755",
          "tgn:7007712",
          "tgn:7029392"
        ],
        "placetype": [
          "aat:300008347",
          "aat:300387210"
        ],
        "id": 2096170,
        "name:xx": "Lucknow"
      }
    },
    {
      "geometry": {
        "type": "Point",
        "coordinates": [
          -80.6833,
          34.2167
        ]
      },
      "type": "Feature",
      "properties": {
        "hierarchy": [
          "tgn:2096171",
          "tgn:1000001",
          "tgn:7012149",
          "tgn:2001752",
          "tgn:7007712",
          "tgn:7029392"
        ],
        "placetype": [
          "aat:300008347"
        ],
        "id": 2096171,
        "name:xx": "Lugoff"
      }
    },
    {
      "geometry": {
        "type": "Point",
        "coordinates": [
          -81.2333,
          32.8
        ]
      },
      "type": "Feature",
      "properties": {
        "hierarchy": [
          "tgn:2096172",
          "tgn:1000001",
          "tgn:2001749",
          "tgn:7012149",
          "tgn:7007712",
          "tgn:7029392"
        ],
        "placetype": [
          "aat:300008347"
        ],
        "id": 2096172,
        "name:xx": "Luray"
      }
    },
    {
      "geometry": {
        "type": "Point",
        "coordinates": [
          -80.1,
          34.2833
        ]
      },
      "type": "Feature",
      "properties": {
        "hierarchy": [
          "tgn:2096173",
          "tgn:1000001",
          "tgn:2001740",
          "tgn:7012149",
          "tgn:7007712",
          "tgn:7029392"
        ],
        "placetype": [
          "aat:300008347"
        ],
        "id": 2096173,
        "name:xx": "Lydia"
      }
    },
    {
      "geometry": {
        "type": "Point",
        "coordinates": [
          -81.9,
          34.45
        ]
      },
      "type": "Feature",
      "properties": {
        "hierarchy": [
          "tgn:2096174",
          "tgn:1000001",
          "tgn:7012149",
          "tgn:2001754",
          "tgn:7007712",
          "tgn:7029392"
        ],
        "placetype": [
          "aat:300008347"
        ],
        "id": 2096174,
        "name:xx": "Lydia Mills"
      }
    },
    {
      "geometry": {
        "type": "Point",
        "coordinates": [
          -80.9,
          33.9333
        ]
      },
      "type": "Feature",
      "properties": {
        "hierarchy": [
          "tgn:2096175",
          "tgn:1000001",
          "tgn:7012149",
          "tgn:2001764",
          "tgn:7007712",
          "tgn:7029392"
        ],
        "placetype": [
          "aat:300008347",
          "aat:300387210"
        ],
        "id": 2096175,
        "name:xx": "Lykes"
      }
    },
    {
      "geometry": {
        "type": "Point",
        "coordinates": [
          -82.1167,
          34.9333
        ]
      },
      "type": "Feature",
      "properties": {
        "hierarchy": [
          "tgn:2096176",
          "tgn:1000001",
          "tgn:7012149",
          "tgn:2001766",
          "tgn:7007712",
          "tgn:7029392"
        ],
        "placetype": [
          "aat:300008347"
        ],
        "id": 2096176,
        "name:xx": "Lyman"
      }
    },
    {
      "geometry": {
        "type": "Point",
        "coordinates": [
          -80.0667,
          34.05
        ]
      },
      "type": "Feature",
      "properties": {
        "hierarchy": [
          "tgn:2096177",
          "tgn:1000001",
          "tgn:7012149",
          "tgn:2001755",
          "tgn:7007712",
          "tgn:7029392"
        ],
        "placetype": [
          "aat:300008347"
        ],
        "id": 2096177,
        "name:xx": "Lynchburg"
      }
    },
    {
      "geometry": {
        "type": "Point",
        "coordinates": [
          -81.85,
          33.5
        ]
      },
      "type": "Feature",
      "properties": {
        "hierarchy": [
          "tgn:2096179",
          "tgn:2001726",
          "tgn:1000001",
          "tgn:7012149",
          "tgn:7007712",
          "tgn:7029392"
        ],
        "placetype": [
          "aat:300008347"
        ],
        "id": 2096179,
        "name:xx": "Lynwood"
      }
    }
  ]
}
