{
  "geometry": {
    "type": "Point",
    "coordinates": [
      -70.788,
      19.54
    ]
  },
  "type": "Feature",
  "properties": {
    "hierarchy": [
      "tgn:7593534",
      "tgn:7005421",
      "tgn:1000001",
      "tgn:7005388",
      "tgn:7029392"
    ],
    "placetype": [
      "aat:300008347"
    ],
    "id": 7593534,
    "name:xx": "Villa González"
  }
}
