{
  "geometry": {
    "type": "Point",
    "coordinates": [
      10.533333,
      54.05
    ]
  },
  "type": "Feature",
  "properties": {
    "hierarchy": [
      "tgn:7125402",
      "tgn:1000003",
      "tgn:7003688",
      "tgn:7000084",
      "tgn:7029392"
    ],
    "placetype": [
      "aat:300000206"
    ],
    "id": 7125402,
    "name:xx": "Nettelteich"
  }
}
