{
  "type": "FeatureCollection",
  "features": [
    {
      "geometry": {
        "type": "Point",
        "coordinates": [
          -78.1333,
          42.7833
        ]
      },
      "type": "Feature",
      "properties": {
        "hierarchy": [
          "tgn:2420570",
          "tgn:1000001",
          "tgn:7012149",
          "tgn:1003040",
          "tgn:7007568",
          "tgn:7029392"
        ],
        "placetype": [
          "aat:300008680"
        ],
        "id": 2420570,
        "name:xx": "Jenkins Pond"
      }
    },
    {
      "geometry": {
        "type": "Point",
        "coordinates": [
          -74.85,
          44
        ]
      },
      "type": "Feature",
      "properties": {
        "hierarchy": [
          "tgn:2420571",
          "tgn:1000001",
          "tgn:7012149",
          "tgn:1002472",
          "tgn:7007568",
          "tgn:7029392"
        ],
        "placetype": [
          "aat:300008680"
        ],
        "id": 2420571,
        "name:xx": "Jenkins Pond"
      }
    },
    {
      "geometry": {
        "type": "Point",
        "coordinates": [
          -77.7667,
          35.0167
        ]
      },
      "type": "Feature",
      "properties": {
        "hierarchy": [
          "tgn:2420572",
          "tgn:1000001",
          "tgn:7012149",
          "tgn:2001491",
          "tgn:7007709",
          "tgn:7029392"
        ],
        "placetype": [
          "aat:300008680"
        ],
        "id": 2420572,
        "name:xx": "Jenkins Pond"
      }
    },
    {
      "geometry": {
        "type": "Point",
        "coordinates": [
          -79.6833,
          34.9333
        ]
      },
      "type": "Feature",
      "properties": {
        "hierarchy": [
          "tgn:2420573",
          "tgn:1000001",
          "tgn:7012149",
          "tgn:2001533",
          "tgn:7007709",
          "tgn:7029392"
        ],
        "placetype": [
          "aat:300006191"
        ],
        "id": 2420573,
        "name:xx": "Jenkins Pond"
      }
    },
    {
      "geometry": {
        "type": "Point",
        "coordinates": [
          -71.45,
          41.55
        ]
      },
      "type": "Feature",
      "properties": {
        "hierarchy": [
          "tgn:2420574",
          "tgn:1002996",
          "tgn:1000001",
          "tgn:7012149",
          "tgn:7007711",
          "tgn:7029392"
        ],
        "placetype": [
          "aat:300008680"
        ],
        "id": 2420574,
        "name:xx": "Jenkins Pond"
      }
    },
    {
      "geometry": {
        "type": "Point",
        "coordinates": [
          -77.0333,
          36.95
        ]
      },
      "type": "Feature",
      "properties": {
        "hierarchy": [
          "tgn:2420576",
          "tgn:1000001",
          "tgn:7012149",
          "tgn:1002935",
          "tgn:7007919",
          "tgn:7029392"
        ],
        "placetype": [
          "aat:300006191"
        ],
        "id": 2420576,
        "name:xx": "Jenkins Pond"
      }
    },
    {
      "geometry": {
        "type": "Point",
        "coordinates": [
          -123.9667,
          42.9833
        ]
      },
      "type": "Feature",
      "properties": {
        "hierarchy": [
          "tgn:2420578",
          "tgn:1000001",
          "tgn:2001702",
          "tgn:7012149",
          "tgn:7007708",
          "tgn:7029392"
        ],
        "placetype": [
          "aat:300055621"
        ],
        "id": 2420578,
        "name:xx": "Jenkins Prairie"
      }
    },
    {
      "geometry": {
        "type": "Point",
        "coordinates": [
          -85.75,
          33.2667
        ]
      },
      "type": "Feature",
      "properties": {
        "hierarchy": [
          "tgn:2420579",
          "tgn:7002659",
          "tgn:1000001",
          "tgn:2000013",
          "tgn:7012149",
          "tgn:7029392"
        ],
        "placetype": [
          "aat:300000390"
        ],
        "id": 2420579,
        "name:xx": "Jenkins Prospect"
      }
    }
  ]
}
