{
  "type": "FeatureCollection",
  "features": [
    {
      "geometry": {
        "type": "Point",
        "coordinates": [
          -13.65,
          57.633333
        ]
      },
      "type": "Feature",
      "properties": {
        "hierarchy": [
          "tgn:7452501",
          "tgn:7002444",
          "tgn:1000003",
          "tgn:7008094",
          "tgn:7008591",
          "tgn:7029392"
        ],
        "placetype": [
          "aat:300011692"
        ],
        "name:en": "Haslewood Rock",
        "id": 7452501
      }
    },
    {
      "geometry": {
        "type": "Point",
        "coordinates": [
          -7.683333,
          57.7
        ]
      },
      "type": "Feature",
      "properties": {
        "hierarchy": [
          "tgn:7452503",
          "tgn:7002444",
          "tgn:1000003",
          "tgn:7008094",
          "tgn:7008591",
          "tgn:7029392"
        ],
        "placetype": [
          "aat:300008791"
        ],
        "name:en": "Haskeir Island",
        "id": 7452503
      }
    },
    {
      "geometry": {
        "type": "Point",
        "coordinates": [
          -1.7,
          52.683333
        ]
      },
      "type": "Feature",
      "properties": {
        "hierarchy": [
          "tgn:7452505",
          "tgn:7002445",
          "tgn:1000003",
          "tgn:7008174",
          "tgn:7008591",
          "tgn:7029392"
        ],
        "placetype": [
          "aat:300008347"
        ],
        "name:en": "Haselour",
        "id": 7452505
      }
    },
    {
      "geometry": {
        "type": "Point",
        "coordinates": [
          -2.75,
          50.9
        ]
      },
      "type": "Feature",
      "properties": {
        "hierarchy": [
          "tgn:7452506",
          "tgn:7002445",
          "tgn:1000003",
          "tgn:7012032",
          "tgn:7008591",
          "tgn:7029392"
        ],
        "placetype": [
          "aat:300008347"
        ],
        "name:en": "Haselbury Plucknett",
        "id": 7452506
      }
    },
    {
      "geometry": {
        "type": "Point",
        "coordinates": [
          -2.366667,
          50.866667
        ]
      },
      "type": "Feature",
      "properties": {
        "hierarchy": [
          "tgn:7452507",
          "tgn:7002445",
          "tgn:1000003",
          "tgn:7011961",
          "tgn:7008591",
          "tgn:7029392"
        ],
        "placetype": [
          "aat:300008347"
        ],
        "name:en": "Haselbury Bryan",
        "id": 7452507
      }
    },
    {
      "geometry": {
        "type": "Point",
        "coordinates": [
          -1.016667,
          60.616667
        ]
      },
      "type": "Feature",
      "properties": {
        "hierarchy": [
          "tgn:7452509",
          "tgn:7002444",
          "tgn:1000003",
          "tgn:7029508",
          "tgn:7008591",
          "tgn:7029392"
        ],
        "placetype": [
          "aat:300266558"
        ],
        "name:en": "Hascosay Sound",
        "id": 7452509
      }
    }
  ]
}
