{
  "geometry": {
    "type": "Point",
    "coordinates": [
      -94.0333,
      47.0667
    ]
  },
  "type": "Feature",
  "properties": {
    "hierarchy": [
      "tgn:2461524",
      "tgn:1000001",
      "tgn:2001009",
      "tgn:7012149",
      "tgn:7007521",
      "tgn:7029392"
    ],
    "placetype": [
      "aat:300008680"
    ],
    "id": 2461524,
    "name:xx": "Little Swift Lake"
  }
}
