{
  "geometry": {
    "type": "Point",
    "coordinates": [
      -93.2667,
      36.1333
    ]
  },
  "type": "Feature",
  "properties": {
    "hierarchy": [
      "tgn:2569844",
      "tgn:1000001",
      "tgn:7016172",
      "tgn:2000109",
      "tgn:7012149",
      "tgn:7029392"
    ],
    "placetype": [
      "aat:300008761"
    ],
    "id": 2569844,
    "name:xx": "Parton Hollow"
  }
}
