{
  "geometry": {
    "type": "Point",
    "coordinates": [
      -84.9667,
      36.0167
    ]
  },
  "type": "Feature",
  "properties": {
    "hierarchy": [
      "tgn:2749009",
      "tgn:1000001",
      "tgn:7012149",
      "tgn:2001854",
      "tgn:7007825",
      "tgn:7029392"
    ],
    "placetype": [
      "aat:300008699"
    ],
    "id": 2749009,
    "name:xx": "Wallace Branch"
  }
}
