{
  "type": "FeatureCollection",
  "features": [
    {
      "geometry": {
        "type": "Point",
        "coordinates": [
          -87.1167,
          34.3667
        ]
      },
      "type": "Feature",
      "properties": {
        "hierarchy": [
          "tgn:2593141",
          "tgn:7002659",
          "tgn:1000001",
          "tgn:7012149",
          "tgn:2000039",
          "tgn:7029392"
        ],
        "placetype": [
          "aat:300008761"
        ],
        "id": 2593141,
        "name:xx": "Poplar Log Cove"
      }
    },
    {
      "geometry": {
        "type": "Point",
        "coordinates": [
          -83.7333,
          37.0167
        ]
      },
      "type": "Feature",
      "properties": {
        "hierarchy": [
          "tgn:2593142",
          "tgn:1000001",
          "tgn:2000782",
          "tgn:7012149",
          "tgn:7007255",
          "tgn:7029392"
        ],
        "placetype": [
          "aat:300008699"
        ],
        "id": 2593142,
        "name:xx": "Poplar Log Fork"
      }
    },
    {
      "geometry": {
        "type": "Point",
        "coordinates": [
          -82.8667,
          37.0833
        ]
      },
      "type": "Feature",
      "properties": {
        "hierarchy": [
          "tgn:2593143",
          "tgn:1000001",
          "tgn:7012149",
          "tgn:2000812",
          "tgn:7007255",
          "tgn:7029392"
        ],
        "placetype": [
          "aat:300008761"
        ],
        "id": 2593143,
        "name:xx": "Poplar Log Hollow"
      }
    },
    {
      "geometry": {
        "type": "Point",
        "coordinates": [
          -81.7667,
          37.6667
        ]
      },
      "type": "Feature",
      "properties": {
        "hierarchy": [
          "tgn:2593144",
          "tgn:1000001",
          "tgn:7012149",
          "tgn:2002273",
          "tgn:7013961",
          "tgn:7029392"
        ],
        "placetype": [
          "aat:300008761"
        ],
        "id": 2593144,
        "name:xx": "Poplar Log Hollow"
      }
    },
    {
      "geometry": {
        "type": "Point",
        "coordinates": [
          -70.15,
          45.05
        ]
      },
      "type": "Feature",
      "properties": {
        "hierarchy": [
          "tgn:2593145",
          "tgn:1000001",
          "tgn:2000921",
          "tgn:7012149",
          "tgn:7007515",
          "tgn:7029392"
        ],
        "placetype": [
          "aat:300008798"
        ],
        "id": 2593145,
        "name:xx": "Poplar Mountain"
      }
    },
    {
      "geometry": {
        "type": "Point",
        "coordinates": [
          -72.45,
          42.5833
        ]
      },
      "type": "Feature",
      "properties": {
        "hierarchy": [
          "tgn:2593146",
          "tgn:1000001",
          "tgn:7013942",
          "tgn:7012149",
          "tgn:7007517",
          "tgn:7029392"
        ],
        "placetype": [
          "aat:300008798"
        ],
        "id": 2593146,
        "name:xx": "Poplar Mountain"
      }
    },
    {
      "geometry": {
        "type": "Point",
        "coordinates": [
          -74.45,
          43.4167
        ]
      },
      "type": "Feature",
      "properties": {
        "hierarchy": [
          "tgn:2593147",
          "tgn:1000001",
          "tgn:7012149",
          "tgn:1002440",
          "tgn:7007568",
          "tgn:7029392"
        ],
        "placetype": [
          "aat:300008798"
        ],
        "id": 2593147,
        "name:xx": "Poplar Mountain"
      }
    },
    {
      "geometry": {
        "type": "Point",
        "coordinates": [
          -83.0167,
          35.1833
        ]
      },
      "type": "Feature",
      "properties": {
        "hierarchy": [
          "tgn:2593148",
          "tgn:1000001",
          "tgn:7012149",
          "tgn:2001508",
          "tgn:7007709",
          "tgn:7029392"
        ],
        "placetype": [
          "aat:300008798"
        ],
        "id": 2593148,
        "name:xx": "Poplar Mountain"
      }
    },
    {
      "geometry": {
        "type": "Point",
        "coordinates": [
          -82.2833,
          35.3833
        ]
      },
      "type": "Feature",
      "properties": {
        "hierarchy": [
          "tgn:2593149",
          "tgn:1000001",
          "tgn:7012149",
          "tgn:2001504",
          "tgn:7007709",
          "tgn:7029392"
        ],
        "placetype": [
          "aat:300008798"
        ],
        "id": 2593149,
        "name:xx": "Poplar Mountain"
      }
    }
  ]
}
