{
  "geometry": {
    "type": "Point",
    "coordinates": [
      -72.7833,
      4.35
    ]
  },
  "type": "Feature",
  "properties": {
    "hierarchy": [
      "tgn:1023739",
      "tgn:1000050",
      "tgn:1000694",
      "tgn:1000002",
      "tgn:7029392"
    ],
    "placetype": [
      "aat:300008347"
    ],
    "id": 1023739,
    "name:xx": "Cabuyaro"
  }
}
