{
  "geometry": {
    "type": "Point",
    "coordinates": [
      -88.1333,
      33.8333
    ]
  },
  "type": "Feature",
  "properties": {
    "hierarchy": [
      "tgn:2775442",
      "tgn:7002659",
      "tgn:1000001",
      "tgn:7012149",
      "tgn:2000037",
      "tgn:7029392"
    ],
    "placetype": [
      "aat:300008706"
    ],
    "id": 2775442,
    "name:xx": "Wilson Creek"
  }
}
