{
  "type": "FeatureCollection",
  "features": [
    {
      "geometry": {
        "type": "Point",
        "coordinates": [
          -71.8333,
          42.5667
        ]
      },
      "type": "Feature",
      "properties": {
        "hierarchy": [
          "tgn:2049780",
          "tgn:1000001",
          "tgn:7012149",
          "tgn:1003038",
          "tgn:7013763",
          "tgn:7007517",
          "tgn:7029392"
        ],
        "placetype": [
          "aat:300000745"
        ],
        "id": 2049780,
        "name:xx": "West Fitchburg"
      }
    },
    {
      "geometry": {
        "type": "Point",
        "coordinates": [
          -71.1167,
          42.0167
        ]
      },
      "type": "Feature",
      "properties": {
        "hierarchy": [
          "tgn:2049781",
          "tgn:1002201",
          "tgn:1000001",
          "tgn:7012149",
          "tgn:7007517",
          "tgn:7029392"
        ],
        "placetype": [
          "aat:300008347"
        ],
        "id": 2049781,
        "name:xx": "Five Corners"
      }
    },
    {
      "geometry": {
        "type": "Point",
        "coordinates": [
          -73,
          42.6667
        ]
      },
      "type": "Feature",
      "properties": {
        "hierarchy": [
          "tgn:2049782",
          "tgn:7013388",
          "tgn:1000001",
          "tgn:7012149",
          "tgn:7007517",
          "tgn:7029392"
        ],
        "placetype": [
          "aat:300008347"
        ],
        "id": 2049782,
        "name:xx": "Florida"
      }
    },
    {
      "geometry": {
        "type": "Point",
        "coordinates": [
          -70.5,
          41.6833
        ]
      },
      "type": "Feature",
      "properties": {
        "hierarchy": [
          "tgn:2049783",
          "tgn:1002165",
          "tgn:1000001",
          "tgn:7012149",
          "tgn:7007517",
          "tgn:7029392"
        ],
        "placetype": [
          "aat:300008347"
        ],
        "id": 2049783,
        "name:xx": "Forestdale"
      }
    },
    {
      "geometry": {
        "type": "Point",
        "coordinates": [
          -71.4833,
          42.5667
        ]
      },
      "type": "Feature",
      "properties": {
        "hierarchy": [
          "tgn:2049786",
          "tgn:1000001",
          "tgn:1002665",
          "tgn:7012149",
          "tgn:7007517",
          "tgn:7029392"
        ],
        "placetype": [
          "aat:300008347"
        ],
        "id": 2049786,
        "name:xx": "Forge Village"
      }
    },
    {
      "geometry": {
        "type": "Point",
        "coordinates": [
          -72.7167,
          42.6667
        ]
      },
      "type": "Feature",
      "properties": {
        "hierarchy": [
          "tgn:2049789",
          "tgn:1000001",
          "tgn:7013942",
          "tgn:7012149",
          "tgn:7007517",
          "tgn:7029392"
        ],
        "placetype": [
          "aat:300008347"
        ],
        "id": 2049789,
        "name:xx": "Foundry Village"
      }
    }
  ]
}
