{
  "geometry": {
    "type": "Point",
    "coordinates": [
      -95.7333,
      33.8333
    ]
  },
  "type": "Feature",
  "properties": {
    "hierarchy": [
      "tgn:2107012",
      "tgn:1000001",
      "tgn:7012149",
      "tgn:2002024",
      "tgn:7007826",
      "tgn:7029392"
    ],
    "placetype": [
      "aat:300008347",
      "aat:300387210"
    ],
    "id": 2107012,
    "name:xx": "Ragtown"
  }
}
