{
  "geometry": {
    "type": "Point",
    "coordinates": [
      -116.6333,
      33.75
    ]
  },
  "type": "Feature",
  "properties": {
    "hierarchy": [
      "tgn:2133503",
      "tgn:1000001",
      "tgn:7012149",
      "tgn:7007157",
      "tgn:1002828",
      "tgn:7029392"
    ],
    "placetype": [
      "aat:300008761"
    ],
    "id": 2133503,
    "name:xx": "Andreas Canyon"
  }
}
