{
  "geometry": {
    "type": "Point",
    "coordinates": [
      31.314382,
      30.097587
    ]
  },
  "type": "Feature",
  "properties": {
    "hierarchy": [
      "tgn:7529646",
      "tgn:7001242",
      "tgn:7016833",
      "tgn:1001091",
      "tgn:7029392"
    ],
    "placetype": [
      "aat:300006676"
    ],
    "id": 7529646,
    "name:xx": "Mustashfá al Mayrīlānd at Takhaşşuşī"
  }
}
