{
  "type": "FeatureCollection",
  "features": [
    {
      "geometry": {
        "type": "Point",
        "coordinates": [
          -90.1333,
          46.4667
        ]
      },
      "type": "Feature",
      "properties": {
        "hierarchy": [
          "tgn:2756200",
          "tgn:1000001",
          "tgn:7012149",
          "tgn:2000960",
          "tgn:7007520",
          "tgn:7029392"
        ],
        "placetype": [
          "aat:300008706"
        ],
        "id": 2756200,
        "name:xx": "Welch Creek"
      }
    },
    {
      "geometry": {
        "type": "Point",
        "coordinates": [
          -115.4833,
          40.6167
        ]
      },
      "type": "Feature",
      "properties": {
        "hierarchy": [
          "tgn:2756201",
          "tgn:1000001",
          "tgn:2001411",
          "tgn:7012149",
          "tgn:7007526",
          "tgn:7029392"
        ],
        "placetype": [
          "aat:300008706"
        ],
        "id": 2756201,
        "name:xx": "Welch Creek"
      }
    },
    {
      "geometry": {
        "type": "Point",
        "coordinates": [
          -75.0667,
          44.25
        ]
      },
      "type": "Feature",
      "properties": {
        "hierarchy": [
          "tgn:2756202",
          "tgn:1000001",
          "tgn:7012149",
          "tgn:7016021",
          "tgn:7007568",
          "tgn:7029392"
        ],
        "placetype": [
          "aat:300008706"
        ],
        "id": 2756202,
        "name:xx": "Welch Creek"
      }
    },
    {
      "geometry": {
        "type": "Point",
        "coordinates": [
          -78.6167,
          34.4
        ]
      },
      "type": "Feature",
      "properties": {
        "hierarchy": [
          "tgn:2756203",
          "tgn:1000001",
          "tgn:2001485",
          "tgn:7012149",
          "tgn:7007709",
          "tgn:7029392"
        ],
        "placetype": [
          "aat:300008706"
        ],
        "id": 2756203,
        "name:xx": "Welch Creek"
      }
    },
    {
      "geometry": {
        "type": "Point",
        "coordinates": [
          -76.8167,
          35.7333
        ]
      },
      "type": "Feature",
      "properties": {
        "hierarchy": [
          "tgn:2756204",
          "tgn:1000001",
          "tgn:7012149",
          "tgn:7007709",
          "tgn:7029392"
        ],
        "placetype": [
          "aat:300008706"
        ],
        "id": 2756204,
        "name:xx": "Welch Creek"
      }
    },
    {
      "geometry": {
        "type": "Point",
        "coordinates": [
          -118.7333,
          44.8833
        ]
      },
      "type": "Feature",
      "properties": {
        "hierarchy": [
          "tgn:2756205",
          "tgn:1000001",
          "tgn:7012149",
          "tgn:2001708",
          "tgn:7007708",
          "tgn:7029392"
        ],
        "placetype": [
          "aat:300008706"
        ],
        "id": 2756205,
        "name:xx": "Welch Creek"
      }
    },
    {
      "geometry": {
        "type": "Point",
        "coordinates": [
          -82.4,
          34
        ]
      },
      "type": "Feature",
      "properties": {
        "hierarchy": [
          "tgn:2756206",
          "tgn:1000001",
          "tgn:7012149",
          "tgn:2001757",
          "tgn:7007712",
          "tgn:7029392"
        ],
        "placetype": [
          "aat:300008706"
        ],
        "id": 2756206,
        "name:xx": "Welch Creek"
      }
    },
    {
      "geometry": {
        "type": "Point",
        "coordinates": [
          -81.7333,
          34.2667
        ]
      },
      "type": "Feature",
      "properties": {
        "hierarchy": [
          "tgn:2756207",
          "tgn:1000001",
          "tgn:7012149",
          "tgn:2001760",
          "tgn:7007712",
          "tgn:7029392"
        ],
        "placetype": [
          "aat:300008706"
        ],
        "id": 2756207,
        "name:xx": "Welch Creek"
      }
    },
    {
      "geometry": {
        "type": "Point",
        "coordinates": [
          -100.1333,
          31.1833
        ]
      },
      "type": "Feature",
      "properties": {
        "hierarchy": [
          "tgn:2756208",
          "tgn:1000001",
          "tgn:7012149",
          "tgn:7007826",
          "tgn:7029392"
        ],
        "placetype": [
          "aat:300008706"
        ],
        "id": 2756208,
        "name:xx": "Welch Creek"
      }
    },
    {
      "geometry": {
        "type": "Point",
        "coordinates": [
          -111.1667,
          40.7
        ]
      },
      "type": "Feature",
      "properties": {
        "hierarchy": [
          "tgn:2756209",
          "tgn:1000001",
          "tgn:7012149",
          "tgn:2002122",
          "tgn:7007827",
          "tgn:7029392"
        ],
        "placetype": [
          "aat:300008706"
        ],
        "id": 2756209,
        "name:xx": "Welch Creek"
      }
    }
  ]
}
