{
  "geometry": {
    "type": "Point",
    "coordinates": [
      -86.7833,
      30.4833
    ]
  },
  "type": "Feature",
  "properties": {
    "hierarchy": [
      "tgn:2597543",
      "tgn:1000001",
      "tgn:7012149",
      "tgn:2000281",
      "tgn:7007240",
      "tgn:7029392"
    ],
    "placetype": [
      "aat:300008680"
    ],
    "id": 2597543,
    "name:xx": "Prairie Ponds"
  }
}
