{
  "geometry": {
    "type": "Point",
    "coordinates": [
      -108.5667,
      37.75
    ]
  },
  "type": "Feature",
  "properties": {
    "hierarchy": [
      "tgn:2536544",
      "tgn:1000001",
      "tgn:7012149",
      "tgn:2000208",
      "tgn:7007158",
      "tgn:7029392"
    ],
    "placetype": [
      "aat:300006191"
    ],
    "id": 2536544,
    "name:xx": "Near Draw Number Three Reservoir"
  }
}
