{
  "geometry": {
    "type": "Point",
    "coordinates": [
      -87.8667,
      38.8333
    ]
  },
  "type": "Feature",
  "properties": {
    "hierarchy": [
      "tgn:2026963",
      "tgn:1000001",
      "tgn:7012149",
      "tgn:2000517",
      "tgn:7007251",
      "tgn:7029392"
    ],
    "placetype": [
      "aat:300008347"
    ],
    "id": 2026963,
    "name:xx": "Chauncey"
  }
}
