{
  "geometry": {
    "type": "Point",
    "coordinates": [
      94.15,
      23.85
    ]
  },
  "type": "Feature",
  "properties": {
    "hierarchy": [
      "tgn:7552582",
      "tgn:1000004",
      "tgn:7000198",
      "tgn:1001997",
      "tgn:7029392"
    ],
    "placetype": [
      "aat:300008777"
    ],
    "name:en": "Nat Taung",
    "id": 7552582
  }
}
