{
  "geometry": {
    "type": "Point",
    "coordinates": [
      -80.8167,
      34.1333
    ]
  },
  "type": "Feature",
  "properties": {
    "hierarchy": [
      "tgn:2714754",
      "tgn:1000001",
      "tgn:7012149",
      "tgn:2001764",
      "tgn:7007712",
      "tgn:7029392"
    ],
    "placetype": [
      "aat:300008699"
    ],
    "id": 2714754,
    "name:xx": "Tenmile Branch"
  }
}
