{
  "geometry": {
    "type": "Point",
    "coordinates": [
      -123.3167,
      41.2167
    ]
  },
  "type": "Feature",
  "properties": {
    "hierarchy": [
      "tgn:2177899",
      "tgn:1000001",
      "tgn:7012149",
      "tgn:7007157",
      "tgn:2000189",
      "tgn:7029392"
    ],
    "placetype": [
      "aat:300008706"
    ],
    "id": 2177899,
    "name:xx": "Blackberry Creek"
  }
}
