{
  "geometry": {
    "type": "Point",
    "coordinates": [
      3.3333,
      6.55
    ]
  },
  "type": "Feature",
  "properties": {
    "hierarchy": [
      "tgn:1092238",
      "tgn:7001242",
      "tgn:1001889",
      "tgn:1000182",
      "tgn:7029392"
    ],
    "placetype": [
      "aat:300008347"
    ],
    "id": 1092238,
    "name:xx": "Oshodi"
  }
}
