{
  "geometry": {
    "type": "Point",
    "coordinates": [
      121.068056,
      24.9925
    ]
  },
  "type": "Feature",
  "properties": {
    "hierarchy": [
      "tgn:7482202",
      "tgn:1000004",
      "tgn:7001013",
      "tgn:1000141",
      "tgn:7029392"
    ],
    "placetype": [
      "aat:300008347"
    ],
    "id": 7482202,
    "name:xx": "Fengtian"
  }
}
